Workbook

Sheet Budget Summary
A1: PARTNERS OF THE AMERICAS
A2: SUMMARY BUDGET FOR MEXICO MIGRATION MESSAGING
B3: Year 1 | E3: Year 2 | H3: Total
A4: BUDGET SUMMARY CATEGORIES | B4: Grant | C4: Cost Share | D4: Total | E4: Grant | F4: Cost Share | G4: Total | H4: Grant | I4: Cost Share | J4: Total
A5: A. Personnel | B5: ='Line Item Budget'!K19 -> 80210 | C5: ='Line Item Budget'!L19 -> 0 | D5: =B5+C5 -> 80210 | E5: ='Line Item Budget'!Q19 -> 83418.4 | F5: ='Line Item Budget'!R19 -> 0 | G5: =E5+F5 -> 83418.4 | H5: =E5+B5 -> 163628.4 | I5: =F5+C5 -> 0 | J5: =I5+H5 -> 163628.4
A6: B. Fringe Benefits | B6: ='Line Item Budget'!K25 -> 27988.691 | C6: ='Line Item Budget'!L25 -> 0 | D6: =B6+C6 -> 27988.691 | E6: ='Line Item Budget'!Q25 -> 29108.239 | F6: ='Line Item Budget'!R25 -> 0 | G6: =E6+F6 -> 29108.239 | H6: =E6+B6 -> 57096.93 | I6: =F6+C6 -> 0 | J6: =I6+H6 -> 57096.93
A7: C. Travel | B7: ='Line Item Budget'!K37 -> 7135 | C7: ='Line Item Budget'!L37 -> 0 | D7: =B7+C7 -> 7135 | E7: ='Line Item Budget'!Q37 -> 7420.4 | F7: ='Line Item Budget'!R37 -> 0 | G7: =E7+F7 -> 7420.4 | H7: =E7+B7 -> 14555.4 | I7: =F7+C7 -> 0 | J7: =I7+H7 -> 14555.4
A8: D. Equipment
A9: E. Supplies | B9: ='Line Item Budget'!K42 -> 3600 | C9: ='Line Item Budget'!L42 -> 0 | D9: =B9+C9 -> 3600 | E9: ='Line Item Budget'!Q42 -> 624 | F9: ='Line Item Budget'!R42 -> 0 | G9: =E9+F9 -> 624 | H9: =E9+B9 -> 4224 | I9: =F9+C9 -> 0 | J9: =I9+H9 -> 4224
A10: F. Contractual and Subawards | B10: ='Line Item Budget'!K52 -> 115900 | C10: ='Line Item Budget'!L52 -> 0 | D10: =B10+C10 -> 115900 | E10: ='Line Item Budget'!Q52 -> 70900 | F10: ='Line Item Budget'!R52 -> 0 | G10: =E10+F10 -> 70900 | H10: =E10+B10 -> 186800 | I10: =F10+C10 -> 0 | J10: =I10+H10 -> 186800
A11: G. Construction
A12: H. Other Direct Costs | B12: ='Line Item Budget'!K74 -> 39031 | C12: ='Line Item Budget'!L74 -> 0 | D12: =B12+C12 -> 39031 | E12: ='Line Item Budget'!Q74 -> 34352.24 | F12: ='Line Item Budget'!R74 -> 0 | G12: =E12+F12 -> 34352.24 | H12: =E12+B12 -> 73383.24 | I12: =F12+C12 -> 0 | J12: =I12+H12 -> 73383.24
A13: I. Total Direct Costs | B13: ='Line Item Budget'!K75 -> 273864.69 | C13: ='Line Item Budget'!L75 -> 0 | D13: =B13+C13 -> 273864.69 | E13: ='Line Item Budget'!Q75 -> 225823.28 | F13: ='Line Item Budget'!R75 -> 0 | G13: =E13+F13 -> 225823.28 | H13: =E13+B13 -> 499687.97 | I13: =F13+C13 -> 0 | J13: =I13+H13 -> 499687.97
A14: J. Indirect Costs | B14: ='Line Item Budget'!K77 -> 77448.935 | C14: ='Line Item Budget'!L77 -> 0 | D14: =B14+C14 -> 77448.935 | E14: ='Line Item Budget'!Q77 -> 63862.823 | F14: ='Line Item Budget'!R77 -> 0 | G14: =E14+F14 -> 63862.823 | H14: =E14+B14 -> 141311.76 | I14: =F14+C14 -> 0 | J14: =I14+H14 -> 141311.76
A15: K. Total Costs | B15: =B13+B14 -> 351313.63 | C15: =C13+C14 -> 0 | D15: =D13+D14 -> 351313.63 | E15: =E13+E14 -> 289686.1 | F15: =F13+F14 -> 0 | G15: =G13+G14 -> 289686.1 | H15: =E15+B15 -> 640999.73 | I15: =F15+C15 -> 0 | J15: =I15+H15 -> 640999.73

Sheet Line Item Budget
D1: PARTNERS OF THE AMERICAS - MEXICO MIGRATION MESSAGING BUDGET
A2: Entity: | B2: P | D2: Merit and Cost of Living Increases - 4% | E2: 1.04
A3: Program/Dept.: | B3: 20200 | D3: Inflation - 4% | E3: 1.04
A4: Funder-Grant: | B4: DOS453 | D4: *Key Personnel
A5: Budget Code | B5: Account Code | C5: Country Code | D5: All costs in US$ | E5: Year 1 | M5: Year 2 | S5: Total
D6: Budget Line Items | E6: No. | F6: Unit Type | G6: Freq. | H6: % | I6: Rate | J6: Total | K6: Federal | L6: Cost Share | M6: No. | N6: Freq. | O6: Rate | P6: Total | Q6: Federal | R6: Cost Share | S6: Federal | T6: Cost Share | U6: Grand Total
D7: A. Personnel
D8: A.1 Field Staff Salaries
A9: PERSNL-CDM | B9: 70000 | C9: MEX | D9: A.1.1 Country Director Mexico (5%) | E9: 1 | F9: Month | G9: 12 | H9: 0.05 | I9: 13450 | J9: =E9*I9*G9*H9 -> 8070 | K9: =J9 -> 8070 | L9: =J9-K9 -> 0 | M9: =E9 -> 1 | N9: 12 | O9: =I9*$E$2 -> 13988 | P9: =M9*O9*N9*H9 -> 8392.8 | Q9: =P9 -> 8392.8 | R9: =P9-Q9 -> 0 | S9: =K9+Q9 -> 16462.8 | T9: =L9+R9 -> 0 | U9: =S9+T9 -> 16462.8
A10: PERSNL-PD | B10: 70000 | C10: MEX | D10: A.1.2 Program Director (10%)* | E10: 1 | F10: Month | G10: 12 | H10: 0.1 | I10: 8650 | J10: =E10*I10*G10*H10 -> 10380 | K10: =J10 -> 10380 | L10: =J10-K10 -> 0 | M10: =E10 -> 1 | N10: 12 | O10: =I10*$E$2 -> 8996 | P10: =M10*O10*N10*H10 -> 10795.2 | Q10: =P10 -> 10795.2 | R10: =P10-Q10 -> 0 | S10: =K10+Q10 -> 21175.2 | T10: =L10+R10 -> 0 | U10: =S10+T10 -> 21175.2
A11: PERSNL-SCS | B11: 70000 | C11: MEX | D11: A.1.3 Senior Communications Specialist (30%) | E11: 1 | F11: Month | G11: 12 | H11: 0.3 | I11: 4100 | J11: =E11*I11*G11*H11 -> 14760 | K11: =J11 -> 14760 | L11: =J11-K11 -> 0 | M11: =E11 -> 1 | N11: 12 | O11: =I11*$E$2 -> 4264 | P11: =M11*O11*N11*H11 -> 15350.4 | Q11: =P11 -> 15350.4 | R11: =P11-Q11 -> 0 | S11: =K11+Q11 -> 30110.4 | T11: =L11+R11 -> 0 | U11: =S11+T11 -> 30110.4
A12: PERSNL-COM | B12: 70000 | C12: MEX | D12: A.1.4 Communications Specialist (30%) | E12: 1 | F12: Month | G12: 12 | H12: 0.3 | I12: 3000 | J12: =E12*I12*G12*H12 -> 10800 | K12: =J12 -> 10800 | L12: =J12-K12 -> 0 | M12: =E12 -> 1 | N12: 12 | O12: =I12*$E$2 -> 3120 | P12: =M12*O12*N12*H12 -> 11232 | Q12: =P12 -> 11232 | R12: =P12-Q12 -> 0 | S12: =K12+Q12 -> 22032 | T12: =L12+R12 -> 0 | U12: =S12+T12 -> 22032
A13: PERSNL-SMA | B13: 70000 | C13: MEX | D13: A.1.5 Social Media Analyst (30%)* | E13: 1 | F13: Month | G13: 12 | H13: 0.3 | I13: 2100 | J13: =E13*I13*G13*H13 -> 7560 | K13: =J13 -> 7560 | L13: =J13-K13 -> 0 | M13: =E13 -> 1 | N13: 12 | O13: =I13*$E$2 -> 2184 | P13: =M13*O13*N13*H13 -> 7862.4 | Q13: =P13 -> 7862.4 | R13: =P13-Q13 -> 0 | S13: =K13+Q13 -> 15422.4 | T13: =L13+R13 -> 0 | U13: =S13+T13 -> 15422.4
A14: PERSNL-M&E | B14: 70000 | C14: MEX | D14: A.1.6 Monitoring, Evaluation, and Learning Officer (25%) | E14: 1 | F14: Month | G14: 12 | H14: 0.25 | I14: 3100 | J14: =E14*I14*G14*H14 -> 9300 | K14: =J14 -> 9300 | L14: =J14-K14 -> 0 | M14: =E14 -> 1 | N14: 12 | O14: =I14*$E$2 -> 3224 | P14: =M14*O14*N14*H14 -> 9672 | Q14: =P14 -> 9672 | R14: =P14-Q14 -> 0 | S14: =K14+Q14 -> 18972 | T14: =L14+R14 -> 0 | U14: =S14+T14 -> 18972
A15: PERSNL-F&A | B15: 70000 | C15: MEX | D15: A.1.7 Finance & Administration Director (5%) | E15: 1 | F15: Month | G15: 12 | H15: 0.05 | I15: 5500 | J15: =E15*I15*G15*H15 -> 3300 | K15: =J15 -> 3300 | L15: =J15-K15 -> 0 | M15: =E15 -> 1 | N15: 12 | O15: =I15*$E$2 -> 5720 | P15: =M15*O15*N15*H15 -> 3432 | Q15: =P15 -> 3432 | R15: =P15-Q15 -> 0 | S15: =K15+Q15 -> 6732 | T15: =L15+R15 -> 0 | U15: =S15+T15 -> 6732
A16: PERSNL-F&A | B16: 70000 | C16: MEX | D16: A.1.8 Finance & Administration Officer (20%) | E16: 1 | F16: Month | G16: 12 | H16: 0.2 | I16: 2100 | J16: =E16*I16*G16*H16 -> 5040 | K16: =J16 -> 5040 | L16: =J16-K16 -> 0 | M16: =E16 -> 1 | N16: 12 | O16: =I16*$E$2 -> 2184 | P16: =M16*O16*N16*H16 -> 5241.6 | Q16: =P16 -> 5241.6 | R16: =P16-Q16 -> 0 | S16: =K16+Q16 -> 10281.6 | T16: =L16+R16 -> 0 | U16: =S16+T16 -> 10281.6
B17: 70000 | C17: MEX | D17: A.2 HQ Staff Salaries
A18: PERSNL | B18: 50000 | C18: USA | D18: A.2.1 Program Manager (HQ) (20%) | E18: 1 | F18: Month | G18: 12 | H18: 0.2 | I18: =55000/12 -> 4583.3333 | J18: =E18*I18*G18*H18 -> 11000 | K18: =J18 -> 11000 | L18: =J18-K18 -> 0 | M18: 1 | N18: =G18 -> 12 | O18: =I18*$E$2 -> 4766.6667 | P18: =M18*O18*N18*H18 -> 11440 | Q18: =P18 -> 11440 | R18: =P18-Q18 -> 0 | S18: =K18+Q18 -> 22440 | T18: =L18+R18 -> 0 | U18: =S18+T18 -> 22440
D19: Subtotal Personnel | J19: =SUM(J9:J18) -> 80210 | K19: =SUM(K9:K18) -> 80210 | L19: =SUM(L9:L18) -> 0 | P19: =SUM(P9:P18) -> 83418.4 | Q19: =SUM(Q9:Q18) -> 83418.4 | R19: =SUM(R9:R18) -> 0 | S19: =SUM(S9:S18) -> 163628.4 | T19: =SUM(T9:T18) -> 0 | U19: =SUM(U9:U18) -> 163628.4
D20: B. Fringe Benefits
D21: B.1 HQ Fringe Benefits
A22: FRINGE | B22: 50900 | C22: USA | D22: B.1.1 U.S.-Based Personnel Fringe Benefits | F22: % | H22: 0.2347 | J22: =J18*H22 -> 2581.7 | K22: =J22 -> 2581.7 | L22: 0 | O22: =O18 -> 4766.6667 | P22: =P18*H22 -> 2684.968 | Q22: =P22 -> 2684.968 | R22: =P22-Q22 -> 0 | S22: =K22+Q22 -> 5266.668 | T22: =L22+R22 -> 0 | U22: =S22+T22 -> 5266.668
D23: B.2 Field Fringe Benefits
A24: FRINGE-MX | B24: 70015 | C24: MEX | D24: B.2.1 Mexico Field Staff Fringe Benefits | F24: % | H24: 0.3671 | J24: =(SUM(J9:J16))*$H$24 -> 25406.991 | K24: =J24 -> 25406.991 | L24: 0 | O24: =O10 -> 8996 | P24: =(SUM(P9:P16))*$H$24 -> 26423.271 | Q24: =P24 -> 26423.271 | R24: =P24-Q24 -> 0 | S24: =K24+Q24 -> 51830.262 | T24: =L24+R24 -> 0 | U24: =S24+T24 -> 51830.262
D25: Subtotal Fringe Benefits | J25: =SUM(J22:J24) -> 27988.691 | K25: =SUM(K22:K24) -> 27988.691 | L25: =SUM(L22:L24) -> 0 | P25: =SUM(P22:P24) -> 29108.239 | Q25: =SUM(Q22:Q24) -> 29108.239 | R25: =SUM(R22:R24) -> 0 | S25: =SUM(S22:S24) -> 57096.93 | T25: =SUM(T22:T24) -> 0 | U25: =SUM(U22:U24) -> 57096.93
D26: C. Travel
D27: C.1 HQ Staff International Travel
A28: STFTRAVEL | B28: 86040 | C28: USA | D28: C.1.1 International Airfare (DC-MX) | E28: 1 | F28: Flight | G28: 1 | H28: 1 | I28: 700 | J28: =E28*I28*G28 -> 700 | K28: =J28 -> 700 | L28: =J28-K28 -> 0 | M28: 1 | N28: 1 | O28: =I28*$E$3 -> 728 | P28: =M28*O28*N28*H28 -> 728 | Q28: =P28 -> 728 | R28: =P28-Q28 -> 0 | S28: =K28+Q28 -> 1428 | T28: =L28+R28 -> 0 | U28: =S28+T28 -> 1428
A29: GROUNDTRAN | B29: 86000 | C29: USA | D29: C.1.2 Ground Transportation | E29: 1 | F29: Trip | G29: 1 | H29: 1 | I29: 100 | J29: =E29*I29*G29 -> 100 | K29: =J29 -> 100 | L29: =J29-K29 -> 0 | M29: 1 | N29: 1 | O29: =I29*$E$3 -> 104 | P29: =M29*O29*N29*H29 -> 104 | Q29: =P29 -> 104 | R29: =P29-Q29 -> 0 | S29: =K29+Q29 -> 204 | T29: =L29+R29 -> 0 | U29: =S29+T29 -> 204
A30: LODGING | B30: 86030 | C30: USA | D30: C.1.3 Lodging | E30: 1 | F30: Night | G30: 4 | H30: 1 | I30: 120 | J30: =E30*I30*G30 -> 480 | K30: =J30 -> 480 | L30: =J30-K30 -> 0 | M30: 1 | N30: 4 | O30: =I30*$E$3 -> 124.8 | P30: =M30*O30*N30*H30 -> 499.2 | Q30: =P30 -> 499.2 | R30: =P30-Q30 -> 0 | S30: =K30+Q30 -> 979.2 | T30: =L30+R30 -> 0 | U30: =S30+T30 -> 979.2
A31: STFCN DIEM | B31: 86050 | C31: USA | D31: C.1.4 M&IE | E31: 1 | F31: Day | G31: 5 | H31: 1 | I31: 95 | J31: =E31*I31*G31 -> 475 | K31: =J31 -> 475 | L31: =J31-K31 -> 0 | M31: 1 | N31: 5 | O31: =I31*$E$3 -> 98.8 | P31: =M31*O31*N31*H31 -> 494 | Q31: =P31 -> 494 | R31: =P31-Q31 -> 0 | S31: =K31+Q31 -> 969 | T31: =L31+R31 -> 0 | U31: =S31+T31 -> 969
D32: C.2 Local Staff In-Country Travel to Target Geographic Regions
A33: LSLODGING | B33: 86030 | C33: MEX | D33: C.2.1 Domestic Airfare | E33: 2 | F33: Flight | G33: 1 | H33: 1 | I33: 200 | J33: =E33*I33*G33 -> 400 | K33: =J33 -> 400 | L33: =J33-K33 -> 0 | M33: 2 | N33: 1 | O33: =I33*$E$3 -> 208 | P33: =M33*O33*N33*H33 -> 416 | Q33: =P33 -> 416 | R33: =P33-Q33 -> 0 | S33: =K33+Q33 -> 816 | T33: =L33+R33 -> 0 | U33: =S33+T33 -> 816
A34: LSM&IE | B34: 86050 | C34: MEX | D34: C.2.2 Lodging | E34: 6 | F34: Night | G34: 3 | H34: 1 | I34: 100 | J34: =E34*I34*G34 -> 1800 | K34: =J34 -> 1800 | L34: =J34-K34 -> 0 | M34: 6 | N34: 3 | O34: =I34*$E$3 -> 104 | P34: =M34*O34*N34*H34 -> 1872 | Q34: =P34 -> 1872 | R34: =P34-Q34 -> 0 | S34: =K34+Q34 -> 3672 | T34: =L34+R34 -> 0 | U34: =S34+T34 -> 3672
A35: LSTRANS | B35: 86000 | C35: MEX | D35: C.2.3 M&IE | E35: 6 | F35: Day | G35: 4 | H35: 1 | I35: 70 | J35: =E35*I35*G35 -> 1680 | K35: =J35 -> 1680 | L35: =J35-K35 -> 0 | M35: 6 | N35: 4 | O35: =I35*$E$3 -> 72.8 | P35: =M35*O35*N35*H35 -> 1747.2 | Q35: =P35 -> 1747.2 | R35: =P35-Q35 -> 0 | S35: =K35+Q35 -> 3427.2 | T35: =L35+R35 -> 0 | U35: =S35+T35 -> 3427.2
A36: LSDOMAIR | B36: 86040 | C36: MEX | D36: C.2.4 Ground Transportation | E36: 1 | F36: Month | G36: 10 | H36: 1 | I36: 150 | J36: =E36*I36*G36 -> 1500 | K36: =J36 -> 1500 | L36: =J36-K36 -> 0 | M36: 1 | N36: 10 | O36: =I36*$E$3 -> 156 | P36: =M36*O36*N36*H36 -> 1560 | Q36: =P36 -> 1560 | R36: =P36-Q36 -> 0 | S36: =K36+Q36 -> 3060 | T36: =L36+R36 -> 0 | U36: =S36+T36 -> 3060
D37: Subtotal Travel | J37: =SUM(J28:J36) -> 7135 | K37: =SUM(K28:K36) -> 7135 | L37: =SUM(L28:L36) -> 0 | P37: =SUM(P28:P36) -> 7420.4 | Q37: =SUM(Q28:Q36) -> 7420.4 | R37: =SUM(R28:R36) -> 0 | S37: =SUM(S28:S36) -> 14555.4 | T37: =SUM(T28:T36) -> 0 | U37: =SUM(U28:U36) -> 14555.4
D38: D. Equipment
D39: E. Supplies
A40: SUPPLIES | B40: 82401 | C40: MEX | D40: E.1 Office Supplies | E40: 1 | F40: Month | G40: 12 | H40: 1 | I40: 50 | J40: =E40*I40*G40*H40 -> 600 | K40: =J40 -> 600 | L40: =J40-K40 -> 0 | M40: 1 | N40: 12 | O40: =I40*$E$3 -> 52 | P40: =M40*O40*N40*H40 -> 624 | Q40: =P40 -> 624 | R40: =P40-Q40 -> 0 | S40: =K40+Q40 -> 1224 | T40: =L40+R40 -> 0 | U40: =S40+T40 -> 1224
A41: LAPTOP | B41: 82401 | C41: MEX | D41: E.2 Laptop Computers & Software | E41: 1 | F41: Unit | G41: 3 | H41: 1 | I41: 1000 | J41: =E41*I41*G41*H41 -> 3000 | K41: =J41 -> 3000 | L41: =J41-K41 -> 0 | M41: 1 | N41: 0 | O41: =I41*$E$3 -> 1040 | P41: =M41*O41*N41*H41 -> 0 | Q41: =P41 -> 0 | R41: =P41-Q41 -> 0 | S41: =K41+Q41 -> 3000 | T41: =L41+R41 -> 0 | U41: =S41+T41 -> 3000
D42: Subtotal Supplies | J42: =SUM(J40:J41) -> 3600 | K42: =SUM(K40:K41) -> 3600 | L42: =SUM(L40:L41) -> 0 | P42: =SUM(P40:P41) -> 624 | Q42: =SUM(Q40:Q41) -> 624 | R42: =SUM(R40:R41) -> 0 | S42: =SUM(S40:S41) -> 4224 | T42: =SUM(T40:T41) -> 0 | U42: =SUM(U40:U41) -> 4224
D43: F. Contractual
D44: F.1 Consultants
A45: CONSULTSM | B45: 81000 | C45: MEX | D45: F.1.1 Social Media Influencer Consultants | E45: 4 | F45: Month | G45: 6 | H45: 1 | I45: 1825 | J45: =E45*G45*H45*I45 -> 43800 | K45: =J45 -> 43800 | L45: =J45-K45 -> 0 | M45: =E45 -> 4 | N45: =G45 -> 6 | O45: =I45 -> 1825 | P45: =M45*N45*O45*H45 -> 43800 | Q45: =P45 -> 43800 | R45: =P45-Q45 -> 0 | S45: =K45+Q45 -> 87600 | T45: =L45+R45 -> 0 | U45: =S45+T45 -> 87600
A46: TECHADPP | B46: 81000 | C46: MEX | D46: F.1.2 Technical Advisor on Public Policy | E46: 1 | F46: Month | G46: 5 | H46: 1 | I46: 3500 | J46: =E46*G46*H46*I46 -> 17500 | K46: =J46 -> 17500 | L46: =J46-K46 -> 0 | M46: =E46 -> 1 | N46: =G46 -> 5 | O46: =I46 -> 3500 | P46: =M46*N46*O46*H46 -> 17500 | Q46: =P46 -> 17500 | R46: =P46-Q46 -> 0 | S46: =K46+Q46 -> 35000 | T46: =L46+R46 -> 0 | U46: =S46+T46 -> 35000
A47: CONSULTDC | B47: 81000 | C47: MEX | D47: F.1.3 Consultant for Participatory Research for Data Collection | E47: 1 | F47: Month | G47: 2 | H47: 1 | I47: 3000 | J47: =E47*G47*H47*I47 -> 6000 | K47: =J47 -> 6000 | L47: =J47-K47 -> 0 | M47: =E47 -> 1 | N47: =G47 -> 2 | O47: =I47 -> 3000 | P47: =M47*N47*O47*H47 -> 6000 | Q47: =P47 -> 6000 | R47: =P47-Q47 -> 0 | S47: =K47+Q47 -> 12000 | T47: =L47+R47 -> 0 | U47: =S47+T47 -> 12000
D48: F.2 Contracts
A49: IMMERSIVE | B49: 81010 | C49: MEX | D49: F.2.1 Contract for Live Portrait and Immersive Experience | E49: 1 | F49: Contract | G49: 1 | H49: 1 | I49: 25000 | J49: =E49*G49*H49*I49 -> 25000 | K49: =J49 -> 25000 | L49: =J49-K49 -> 0 | M49: 0 | N49: 0 | O49: =I49 -> 25000 | P49: =M49*N49*O49*H49 -> 0 | Q49: =P49 -> 0 | R49: =P49-Q49 -> 0 | S49: =K49+Q49 -> 25000 | T49: =L49+R49 -> 0 | U49: =S49+T49 -> 25000
A50: FILMPROD | B50: 81010 | C50: MEX | D50: F.2.2 Contract to Film & Produce Soap Opera | E50: 1 | F50: Contract | G50: 1 | H50: 1 | I50: 20000 | J50: =E50*G50*H50*I50 -> 20000 | K50: =J50 -> 20000 | L50: =J50-K50 -> 0 | M50: 0 | N50: 0 | O50: =I50 -> 20000 | P50: =M50*N50*O50*H50 -> 0 | Q50: =P50 -> 0 | R50: =P50-Q50 -> 0 | S50: =K50+Q50 -> 20000 | T50: =L50+R50 -> 0 | U50: =S50+T50 -> 20000
A51: SECURITY | B51: 86110 | C51: MEX | D51: F.2.3 Security Advisors | E51: 1 | F51: Month | G51: 12 | H51: 1 | I51: 300 | J51: =E51*G51*H51*I51 -> 3600 | K51: =J51 -> 3600 | L51: =J51-K51 -> 0 | M51: =E51 -> 1 | N51: =G51 -> 12 | O51: =I51 -> 300 | P51: =M51*N51*O51*H51 -> 3600 | Q51: =P51 -> 3600 | R51: =P51-Q51 -> 0 | S51: =K51+Q51 -> 7200 | T51: =L51+R51 -> 0 | U51: =S51+T51 -> 7200
D52: Subtotal Contractual | J52: =SUM(J45:J51) -> 115900 | K52: =SUM(K45:K51) -> 115900 | L52: =SUM(L45:L51) -> 0 | P52: =SUM(P45:P51) -> 70900 | Q52: =SUM(Q45:Q51) -> 70900 | R52: =SUM(R45:R51) -> 0 | S52: =SUM(S45:S51) -> 186800 | T52: =SUM(T45:T51) -> 0 | U52: =SUM(U45:U51) -> 186800
D53: G. Construction
D54: H. Other Direct Costs
D55: H.1 Office Costs
A56: RENT & UT | B56: 85180 | C56: MEX | D56: H.1.1 Office Space & Utilities | E56: 1 | F56: Month | G56: 12 | H56: 1 | I56: 350 | J56: =E56*I56*G56*H56 -> 4200 | K56: =J56 -> 4200 | L56: =J56-K56 -> 0 | M56: 1 | N56: 12 | O56: =I56*$E$3 -> 364 | P56: =M56*O56*N56*H56 -> 4368 | Q56: =P56 -> 4368 | R56: =P56-Q56 -> 0 | S56: =K56+Q56 -> 8568 | T56: =L56+R56 -> 0 | U56: =S56+T56 -> 8568
A57: BANK FEES | B57: 90900 | C57: MEX | D57: H.1.2 Banking and Cash Handling Fees | E57: 1 | F57: Month | G57: 12 | H57: 1 | I57: 35 | J57: =E57*I57*G57*H57 -> 420 | K57: =J57 -> 420 | L57: =J57-K57 -> 0 | M57: 1 | N57: 12 | O57: =I57*$E$3 -> 36.4 | P57: =M57*O57*N57*H57 -> 436.8 | Q57: =P57 -> 436.8 | R57: =P57-Q57 -> 0 | S57: =K57+Q57 -> 856.8 | T57: =L57+R57 -> 0 | U57: =S57+T57 -> 856.8
A58: PAYROLL | B58: 81030 | C58: MEX | D58: H.1.3 Payroll Processing | E58: 1 | F58: Month | G58: 12 | H58: 1 | I58: 50 | J58: =E58*I58*G58*H58 -> 600 | K58: =J58 -> 600 | L58: =J58-K58 -> 0 | M58: 1 | N58: 12 | O58: =I58*$E$3 -> 52 | P58: =M58*O58*N58*H58 -> 624 | Q58: =P58 -> 624 | R58: =P58-Q58 -> 0 | S58: =K58+Q58 -> 1224 | T58: =L58+R58 -> 0 | U58: =S58+T58 -> 1224
A59: COMM | B59: 82030 | C59: MEX | D59: H.1.4 Communications Costs (Phone, Data, Internet, etc.) | E59: 1 | F59: Month | G59: 12 | H59: 1 | I59: 150 | J59: =E59*I59*G59*H59 -> 1800 | K59: =J59 -> 1800 | L59: =J59-K59 -> 0 | M59: 1 | N59: 12 | O59: =I59*$E$3 -> 156 | P59: =M59*O59*N59*H59 -> 1872 | Q59: =P59 -> 1872 | R59: =P59-Q59 -> 0 | S59: =K59+Q59 -> 3672 | T59: =L59+R59 -> 0 | U59: =S59+T59 -> 3672
A60: SUBSCRIPT | B60: 89400 | C60: MEX | D60: H.1.5 HR, Platform Subscriptions (Timekeeping and Expense Reporting) | E60: 1 | F60: Month | G60: 12 | H60: 1 | I60: =10*12 -> 120 | J60: =E60*I60*G60*H60 -> 1440 | K60: =J60 -> 1440 | L60: =J60-K60 -> 0 | M60: 1 | N60: 12 | O60: =I60*$E$3 -> 124.8 | P60: =M60*O60*N60*H60 -> 1497.6 | Q60: =P60 -> 1497.6 | R60: =P60-Q60 -> 0 | S60: =K60+Q60 -> 2937.6 | T60: =L60+R60 -> 0 | U60: =S60+T60 -> 2937.6
A61: MEETING | B61: 87010 | C61: MEX | D61: H.1.6 Meeting Expenses | E61: 1 | F61: Month | G61: 12 | H61: 1 | I61: 50 | J61: =E61*I61*G61*H61 -> 600 | K61: =J61 -> 600 | L61: =J61-K61 -> 0 | M61: 1 | N61: 12 | O61: =I61*$E$3 -> 52 | P61: =M61*O61*N61*H61 -> 624 | Q61: =P61 -> 624 | R61: =P61-Q61 -> 0 | S61: =K61+Q61 -> 1224 | T61: =L61+R61 -> 0 | U61: =S61+T61 -> 1224
A62: RECRUIT | B62: 90450 | C62: MEX | D62: H.1.7 Procurement Advertising | E62: 1 | F62: Year | G62: 1 | H62: 1 | I62: 400 | J62: =E62*I62*G62*H62 -> 400 | K62: =J62 -> 400 | L62: =J62-K62 -> 0 | M62: 1 | N62: 1 | O62: =I62*$E$3 -> 416 | P62: =M62*O62*N62*H62 -> 416 | Q62: =P62 -> 416 | R62: =P62-Q62 -> 0 | S62: =K62+Q62 -> 816 | T62: =L62+R62 -> 0 | U62: =S62+T62 -> 816
A63: LEGAL | B63: 90100 | C63: MEX | D63: H.1.8 Legal Fees | E63: 1 | F63: Year | G63: 1 | H63: 1 | I63: 250 | J63: =E63*I63*G63*H63 -> 250 | K63: =J63 -> 250 | L63: =J63-K63 -> 0 | M63: 1 | N63: 1 | O63: =I63*$E$3 -> 260 | P63: =M63*O63*N63*H63 -> 260 | Q63: =P63 -> 260 | R63: =P63-Q63 -> 0 | S63: =K63+Q63 -> 510 | T63: =L63+R63 -> 0 | U63: =S63+T63 -> 510
A64: AUDIT | B64: 82100 | C64: MEX | D64: H.1.9 Audit Fees | E64: 1 | F64: Year | G64: 1 | H64: 1 | I64: 100 | J64: =E64*I64*G64*H64 -> 100 | K64: =J64 -> 100 | L64: =J64-K64 -> 0 | M64: 1 | N64: 1 | O64: =I64*$E$3 -> 104 | P64: =M64*O64*N64*H64 -> 104 | Q64: =P64 -> 104 | R64: =P64-Q64 -> 0 | S64: =K64+Q64 -> 204 | T64: =L64+R64 -> 0 | U64: =S64+T64 -> 204
D65: H.2 Activities Costs
A66: TRANS | B66: 81021 | C66: MEX | D66: H.2.1 Translation Costs | E66: 1 | F66: Year | G66: 1 | H66: 1 | I66: 15000 | J66: =E66*G66*H66*I66 -> 15000 | K66: =J66 -> 15000 | L66: =J66-K66 -> 0 | M66: =E66 -> 1 | N66: =G66 -> 1 | O66: =I66*$E$3 -> 15600 | P66: =H66*M66*N66*O66 -> 15600 | Q66: =P66 -> 15600 | R66: =P66-Q66 -> 0 | S66: =K66+Q66 -> 30600 | T66: =L66+R66 -> 0 | U66: =S66+T66 -> 30600
A67: SOCIALADS | B67: 90450 | C67: MEX | D67: H.2.2 Social Media Ads/Boosts | E67: 1 | F67: Ad | G67: 24 | H67: 1 | I67: 250 | J67: =E67*G67*H67*I67 -> 6000 | K67: =J67 -> 6000 | L67: =J67-K67 -> 0 | M67: =E67 -> 1 | N67: =G67 -> 24 | O67: =I67*$E$3 -> 260 | P67: =H67*M67*N67*O67 -> 6240 | Q67: =P67 -> 6240 | R67: =P67-Q67 -> 0 | S67: =K67+Q67 -> 12240 | T67: =L67+R67 -> 0 | U67: =S67+T67 -> 12240
A68: WEBSITE | B68: 81035 | C68: MEX | D68: H.2.3 Website Development Fees | E68: 1 | F68: Lumpsum | G68: 1 | H68: 1 | I68: 7000 | J68: =E68*G68*H68*I68 -> 7000 | K68: =J68 -> 7000 | L68: =J68-K68 -> 0 | M68: 0 | N68: 0 | O68: =I68*$E$3 -> 7280 | P68: =H68*M68*N68*O68 -> 0 | Q68: =P68 -> 0 | R68: =P68-Q68 -> 0 | S68: =K68+Q68 -> 7000 | T68: =L68+R68 -> 0 | U68: =S68+T68 -> 7000
A69: HOSTMAINT | B69: 81035 | C69: MEX | D69: H.2.4 Website Hosting and Maintenance Fees | E69: 1 | F69: Year | G69: 1 | H69: 1 | I69: 800 | J69: =E69*G69*I69*H69 -> 800 | K69: =J69 -> 800 | L69: =J69-K69 -> 0 | M69: =E69 -> 1 | N69: =G69 -> 1 | O69: =I69*$E$3 -> 832 | P69: =M69*N69*O69*H69 -> 832 | Q69: =P69 -> 832 | R69: =P69-Q69 -> 0 | S69: =K69+Q69 -> 1632 | T69: =L69+R69 -> 0 | U69: =S69+T69 -> 1632
D70: H.3 M&E
A71: M&EMATL | B71: 82420 | C71: MEX | D71: H.3.1 M&E Materials | E71: 1 | F71: Year | G71: 1 | H71: 1 | I71: 300 | J71: =E71*G71*I71 -> 300 | K71: =J71 -> 300 | L71: =J71-K71 -> 0 | M71: 1 | N71: 1 | O71: =I71*$E$3 -> 312 | P71: =M71*N71*O71 -> 312 | Q71: =P71 -> 312 | R71: =P71-Q71 -> 0 | S71: =K71+Q71 -> 612 | T71: =L71+R71 -> 0 | U71: =S71+T71 -> 612
A72: M&ETRAIN | B72: 87010 | C72: MEX | D72: H.3.2 M&E Training and Coordination Meetings | E72: 1 | F72: Meetings | G72: 1 | H72: 1 | I72: 121 | J72: =E72*G72*I72 -> 121 | K72: =J72 -> 121 | L72: =J72-K72 -> 0 | M72: 1 | N72: 1 | O72: =I72*$E$3 -> 125.84 | P72: =M72*N72*O72 -> 125.84 | Q72: =P72 -> 125.84 | R72: =P72-Q72 -> 0 | S72: =K72+Q72 -> 246.84 | T72: =L72+R72 -> 0 | U72: =S72+T72 -> 246.84
A73: EVAL | B73: 81010 | C73: MEX | D73: H.3.3 External Project Evaluation support costs | E73: 1 | F73: Lumpsum | G73: 0 | H73: 1 | I73: 1000 | J73: =E73*G73*I73 -> 0 | K73: =J73 -> 0 | L73: =J73-K73 -> 0 | M73: 1 | N73: 1 | O73: =I73*$E$3 -> 1040 | P73: =M73*N73*O73 -> 1040 | Q73: =P73 -> 1040 | R73: =P73-Q73 -> 0 | S73: =K73+Q73 -> 1040 | T73: =L73+R73 -> 0 | U73: =S73+T73 -> 1040
D74: Subtotal Other Direct Costs | J74: =SUM(J55:J73) -> 39031 | K74: =SUM(K55:K73) -> 39031 | L74: =SUM(L55:L73) -> 0 | P74: =SUM(P55:P73) -> 34352.24 | Q74: =SUM(Q55:Q73) -> 34352.24 | R74: =SUM(R55:R73) -> 0 | S74: =SUM(S55:S73) -> 73383.24 | T74: =SUM(T55:T73) -> 0 | U74: =SUM(U55:U73) -> 73383.24
D75: I. Total Direct Costs | J75: =J19+J25+J37+J42+J52+J74 -> 273864.69 | K75: =K19+K25+K37+K42+K52+K74 -> 273864.69 | L75: =L19+L25+L37+L42+L52+L74 -> 0 | P75: =P19+P25+P37+P42+P52+P74 -> 225823.28 | Q75: =Q19+Q25+Q37+Q42+Q52+Q74 -> 225823.28 | R75: =R19+R25+R37+R42+R52+R74 -> 0 | S75: =S19+S25+S37+S42+S52+S74 -> 499687.97 | T75: =T19+T25+T37+T42+T52+T74 -> 0 | U75: =U19+U25+U37+U42+U52+U74 -> 499687.97
D76: J. Indirect Cost
A77: IDC | B77: 94050 | C77: USA | D77: J.1 Indirect Cost (28.28% NICRA rate) | F77: 0.2828 | J77: =J75*F77 -> 77448.935 | K77: =J77 -> 77448.935 | L77: =J77-K77 -> 0 | P77: =P75*F77 -> 63862.823 | Q77: =P77 -> 63862.823 | R77: =P77-Q77 -> 0 | S77: =K77+Q77 -> 141311.76 | T77: =L77+R77 -> 0 | U77: =S77+T77 -> 141311.76
D78: J.2 Total Indirect Cost | J78: =J77 -> 77448.935 | K78: =K77 -> 77448.935 | L78: =L77 -> 0 | P78: =P77 -> 63862.823 | Q78: =Q77 -> 63862.823 | R78: =R77 -> 0 | S78: =S77 -> 141311.76 | T78: =T77 -> 0 | U78: =U77 -> 141311.76
D79: K. GRAND TOTAL | J79: =J75+J78 -> 351313.63 | K79: =K75+K78 -> 351313.63 | L79: =L75+L78 -> 0 | P79: =P75+P78 -> 289686.1 | Q79: =Q75+Q78 -> 289686.1 | R79: =R75+R78 -> 0 | S79: =S75+S78 -> 640999.73 | T79: =T75+T78 -> 0 | U79: =U75+U78 -> 640999.73

Sheet Line Item Budget Monthly
D1: PARTNERS OF THE AMERICAS - MEXICO MIGRATION MESSAGING BUDGET
A2: Entity: | B2: P | D2: Merit and Cost of Living Increases - 4% | E2: 1.04
A3: Program/Dept.: | B3: 20200 | D3: Inflation - 4% | E3: 1.04
A4: Funder-Grant: | B4: DOS453 | D4: *Key Personnel
A5: Budget Code | B5: Account Code | C5: Country Code | D5: All costs in US$ | E5: Year 1 | Z5: Year 2 | AT5: Total
D6: Budget Line Items | E6: No. | F6: Unit Type | G6: Freq. | H6: % | I6: Rate | J6: Jan 24 | K6: 45323 | L6: 45352 | M6: 45383 | N6: 45413 | O6: 45444 | P6: 45474 | Q6: 45505 | R6: 45536 | S6: 45566 | T6: 45597 | U6: 45627 | V6: Total | W6: Total Original Budget | X6: Federal | Y6: Cost Share | Z6: No. | AA6: Freq. | AB6: Rate | AC6: Jan 25 | AD6: 45689 | AE6: 45717 | AF6: 45748 | AG6: 45778 | AH6: 45809 | AI6: 45839 | AJ6: 45870 | AK6: 45901 | AL6: 45931 | AM6: 45962 | AN6: 45992 | AO6: Total | AP6: Total | AQ6: Federal | AR6: Cost Share | AS6: Total Projected | AT6: Federal | AU6: Cost Share | AV6: Grand Total
D7: A. Personnel
D8: A.1 Field Staff Salaries
A9: PERSNL-CDM | B9: 70000 | C9: MEX | D9: A.1.1 Country Director Mexico (5%) | E9: 1 | F9: Month | G9: 12 | H9: 0.05 | I9: 13450 | J9: =(((3560.09/8)*31)/17.078)*1.0375 -> 838.07673 | K9: =(((3560.09/8)*31)/17.078)*1.0375 -> 838.07673 | L9: =(((3560.09/8)*31)/17.078)*1.0375 -> 838.07673 | M9: =(((3560.09/8)*35)/17.078)*1.0375 -> 946.21566 | N9: =(((3560.09/8)*31)/17.078)*1.0375 -> 838.07673 | O9: =(((3560.09/8)*31)/17.078)*1.0375 -> 838.07673 | P9: =(((3560.09/8)*31)/17.078)*1.0375 -> 838.07673 | Q9: =(((3560.09/8)*31)/17.078)*1.0375 -> 838.07673 | R9: =(((3560.09/8)*31)/17.078)*1.0375 -> 838.07673 | S9: =(((3560.09/8)*31)/17.078)*1.0375 -> 838.07673 | T9: =(((3560.09/8)*31)/17.078)*1.0375 -> 838.07673 | U9: =(((3560.09/8)*31)/17.078)*1.0375+T9*0.5 -> 1257.1151 | V9: =SUM(J9:U9) -> 10584.098 | W9: =E9*I9*G9*H9 -> 8070 | X9: =W9 -> 8070 | Y9: =W9-X9 -> 0 | Z9: =E9 -> 1 | AA9: 12 | AB9: =I9*$E$2 -> 13988 | AC9: =+T9*1.0375 -> 869.5046 | AD9: =+AC9 -> 869.5046 | AE9: =+AD9 -> 869.5046 | AF9: =+AE9+AC9/30.4*4.5 -> 998.21417 | AG9: =+AE9 -> 869.5046 | AH9: =+AG9 -> 869.5046 | AI9: =+AH9 -> 869.5046 | AJ9: =+AI9 -> 869.5046 | AK9: =+AJ9 -> 869.5046 | AL9: =+AK9 -> 869.5046 | AM9: =+AL9 -> 869.5046 | AN9: =+AM9*1.5 -> 1304.2569 | AO9: =SUM(AC9:AN9) -> 10997.517 | AP9: =Z9*AB9*AA9*H9 -> 8392.8 | AQ9: =AP9 -> 8392.8 | AR9: =AP9-AQ9 -> 0 | AS9: =+AO9+V9 -> 21581.615 | AT9: =X9+AQ9 -> 16462.8 | AU9: =Y9+AR9 -> 0 | AV9: =AT9+AU9 -> 16462.8
A10: PERSNL-PD | B10: 70000 | C10: MEX | D10: A.1.2 Program Director (10%)* | E10: 1 | F10: Month | G10: 12 | H10: 0.1 | I10: 8650 | J10: =(77351.04/17.078) -> 4529.2798 | K10: =(77351.04/17.078) -> 4529.2798 | L10: =(77351.04/17.078) -> 4529.2798 | M10: =(77351.04/17.078) -> 4529.2798 | N10: =(77351.04/17.078) -> 4529.2798 | O10: =(77351.04/17.078) -> 4529.2798 | P10: =(77351.04/17.078) -> 4529.2798 | Q10: =(77351.04/17.078) -> 4529.2798 | ... T10: =(77351.04/17.078) -> 4529.2798 | U10: =(77351.04/17.078)+T10*0.5 -> 6793.9197 | V10: =SUM(J10:U10) -> 56615.997 | W10: =E10*I10*G10*H10 -> 10380 | X10: =W10 -> 10380 | Y10: =W10-X10 -> 0 | Z10: =E10 -> 1 | AA10: 12 | AB10: =I10*$E$2 -> 8996 | AC10: =+T10*1.0375+T10/30.4*16*0.25 -> 5295.0856 | AD10: =+T10*1.0375 -> 4699.1278 | AE10: =+AD10 -> 4699.1278 | AF10: =+AE10 -> 4699.1278 | AG10: =+AF10 -> 4699.1278 | AH10: =+AG10 -> 4699.1278 | AI10: =+AH10 -> 4699.1278 | AJ10: =+AI10 -> 4699.1278 | AK10: =+AJ10 -> 4699.1278 | AL10: =+AK10 -> 4699.1278 | AM10: =+AL10 -> 4699.1278 | AN10: =+AM10*1.5 -> 7048.6917 | AO10: =SUM(AC10:AN10) -> 59335.055 | AP10: =Z10*AB10*AA10*H10 -> 10795.2 | AQ10: =AP10 -> 10795.2 | AR10: =AP10-AQ10 -> 0 | AS10: =+AO10+V10 -> 115951.05 | AT10: =X10+AQ10 -> 21175.2 | AU10: =Y10+AR10 -> 0 | AV10: =AT10+AU10 -> 21175.2
A11: PERSNL-SCS | B11: 70000 | C11: MEX | D11: A.1.3 Senior Communications Specialist (30%) | E11: 1 | F11: Month | G11: 12 | H11: 0.3 | I11: 4100 | V11: =SUM(J11:U11) -> 0 | W11: =E11*I11*G11*H11 -> 14760 | X11: =W11 -> 14760 | Y11: =W11-X11 -> 0 | Z11: =E11 -> 1 | AA11: 12 | AB11: =I11*$E$2 -> 4264 | AO11: =SUM(AC11:AN11) -> 0 | AP11: =Z11*AB11*AA11*H11 -> 15350.4 | AQ11: =AP11 -> 15350.4 | AR11: =AP11-AQ11 -> 0 | AS11: =+AO11+V11 -> 0 | AT11: =X11+AQ11 -> 30110.4 | AU11: =Y11+AR11 -> 0 | AV11: =AT11+AU11 -> 30110.4
A12: PERSNL-COM | B12: 70000 | C12: MEX | D12: A.1.4 Communications Specialist (30%) | E12: 1 | F12: Month | G12: 12 | H12: 0.3 | I12: 3000 | V12: =SUM(J12:U12) -> 0 | W12: =E12*I12*G12*H12 -> 10800 | X12: =W12 -> 10800 | Y12: =W12-X12 -> 0 | Z12: =E12 -> 1 | AA12: 12 | AB12: =I12*$E$2 -> 3120 | AO12: =SUM(AC12:AN12) -> 0 | AP12: =Z12*AB12*AA12*H12 -> 11232 | AQ12: =AP12 -> 11232 | AR12: =AP12-AQ12 -> 0 | AS12: =+AO12+V12 -> 0 | AT12: =X12+AQ12 -> 22032 | AU12: =Y12+AR12 -> 0 | AV12: =AT12+AU12 -> 22032
A13: PERSNL-SMA | B13: 70000 | C13: MEX | D13: A.1.5 Social Media Analyst (30%)* | E13: 1 | F13: Month | G13: 12 | H13: 0.3 | I13: 2100 | V13: =SUM(J13:U13) -> 0 | W13: =E13*I13*G13*H13 -> 7560 | X13: =W13 -> 7560 | Y13: =W13-X13 -> 0 | Z13: =E13 -> 1 | AA13: 12 | AB13: =I13*$E$2 -> 2184 | AO13: =SUM(AC13:AN13) -> 0 | AP13: =Z13*AB13*AA13*H13 -> 7862.4 | AQ13: =AP13 -> 7862.4 | AR13: =AP13-AQ13 -> 0 | AS13: =+AO13+V13 -> 0 | AT13: =X13+AQ13 -> 15422.4 | AU13: =Y13+AR13 -> 0 | AV13: =AT13+AU13 -> 15422.4
A14: PERSNL-M&E | B14: 70000 | C14: MEX | D14: A.1.6 Monitoring, Evaluation, and Learning Officer (25%) | E14: 1 | F14: Month | G14: 12 | H14: 0.25 | I14: 3100 | V14: =SUM(J14:U14) -> 0 | W14: =E14*I14*G14*H14 -> 9300 | X14: =W14 -> 9300 | Y14: =W14-X14 -> 0 | Z14: =E14 -> 1 | AA14: 12 | AB14: =I14*$E$2 -> 3224 | AO14: =SUM(AC14:AN14) -> 0 | AP14: =Z14*AB14*AA14*H14 -> 9672 | AQ14: =AP14 -> 9672 | AR14: =AP14-AQ14 -> 0 | AS14: =+AO14+V14 -> 0 | AT14: =X14+AQ14 -> 18972 | AU14: =Y14+AR14 -> 0 | AV14: =AT14+AU14 -> 18972
A15: PERSNL-F&A | B15: 70000 | C15: MEX | D15: A.1.7 Finance & Administration Director (5%) | E15: 1 | F15: Month | G15: 12 | H15: 0.05 | I15: 5500 | J15: =(((2722.16/8)*31)/17.078)*1.0375 -> 640.82058 | K15: =(((2722.16/8)*33)/17.078)*1.0375 -> 682.16384 | L15: =(((2722.16/8)*31)/17.078)*1.0375 -> 640.82058 | M15: =(((2722.16/8)*31)/17.078)*1.0375 -> 640.82058 | N15: =(((2722.16/8)*31)/17.078)*1.0375 -> 640.82058 | O15: =(((2722.16/8)*31)/17.078)*1.0375 -> 640.82058 | P15: =(((2722.16/8)*31)/17.078)*1.0375 -> 640.82058 | Q15: =(((2722.16/8)*31)/17.078)*1.0375 -> 640.82058 | R15: =(((2722.16/8)*31)/17.078)*1.0375 -> 640.82058 | S15: =(((2722.16/8)*31)/17.078)*1.0375 -> 640.82058 | T15: =(((2722.16/8)*31)/17.078)*1.0375+((1466.04/8*18/17.078)*1.0375)*0.25 -> 690.91847 | U15: =(((2722.16/8)*31)/17.078)*1.0375+T15*0.5 -> 986.27982 | V15: =SUM(J15:U15) -> 8126.7474 | W15: =E15*I15*G15*H15 -> 3300 | X15: =W15 -> 3300 | Y15: =W15-X15 -> 0 | Z15: =E15 -> 1 | AA15: 12 | AB15: =I15*$E$2 -> 5720 | AC15: =+T15*1.0375 -> 716.82791 | AD15: =+AC15/30.4*33 -> 778.13556 | AE15: =+AC15 -> 716.82791 | AF15: =+AE15 -> 716.82791 | AG15: =+AF15 -> 716.82791 | AH15: =+AG15 -> 716.82791 | AI15: =+AH15 -> 716.82791 | AJ15: =+AI15 -> 716.82791 | AK15: =+AJ15 -> 716.82791 | AL15: =+AK15 -> 716.82791 | AM15: =+AL15+((1466.04/8*18/17.078)*1.0375)*0.25*1.0375 -> 768.80448 | AN15: =+AM15*1.5 -> 1153.2067 | AO15: =SUM(AC15:AN15) -> 9151.598 | AP15: =Z15*AB15*AA15*H15 -> 3432 | AQ15: =AP15 -> 3432 | AR15: =AP15-AQ15 -> 0 | AS15: =+AO15+V15 -> 17278.345 | AT15: =X15+AQ15 -> 6732 | AU15: =Y15+AR15 -> 0 | AV15: =AT15+AU15 -> 6732
A16: PERSNL-FO | B16: 70000 | C16: MEX | D16: A.1.8 Finance & Administration Officer (20%) | E16: 1 | F16: Month | G16: 12 | H16: 0.2 | I16: 2100 | V16: =SUM(J16:U16) -> 0 | W16: =E16*I16*G16*H16 -> 5040 | X16: =W16 -> 5040 | Y16: =W16-X16 -> 0 | Z16: =E16 -> 1 | AA16: 12 | AB16: =I16*$E$2 -> 2184 | AO16: =SUM(AC16:AN16) -> 0 | AP16: =Z16*AB16*AA16*H16 -> 5241.6 | AQ16: =AP16 -> 5241.6 | AR16: =AP16-AQ16 -> 0 | AS16: =+AO16+V16 -> 0 | AT16: =X16+AQ16 -> 10281.6 | AU16: =Y16+AR16 -> 0 | AV16: =AT16+AU16 -> 10281.6
D17: A.2 HQ Staff Salaries | V17: =SUM(J17:U17) -> 0 | AO17: =SUM(AC17:AN17) -> 0 | AS17: =SUM(AG17:AR17) -> 0
A18: PERSNL | B18: 50000 | C18: USA | D18: A.2.1 Program Manager (HQ) (20%) | E18: 1 | F18: Month | G18: 12 | H18: 0.2 | I18: =55000/12 -> 4583.3333 | J18: =+W18/12 -> 916.66667 | K18: =+J18 -> 916.66667 | L18: =+K18 -> 916.66667 | M18: =+L18 -> 916.66667 | N18: =+M18 -> 916.66667 | O18: =+N18 -> 916.66667 | P18: =+O18 -> 916.66667 | Q18: =+P18 -> 916.66667 | R18: =+Q18 -> 916.66667 | ... U18: =+T18 -> 916.66667 | V18: =SUM(J18:U18) -> 11000 | W18: =E18*I18*G18*H18 -> 11000 | X18: =W18 -> 11000 | Y18: =W18-X18 -> 0 | Z18: 1 | AA18: =G18 -> 12 | AB18: =I18*$E$2 -> 4766.6667 | AC18: =+AP18/12 -> 953.33333 | AD18: =+AC18 -> 953.33333 | AE18: =+AD18 -> 953.33333 | AF18: =+AE18 -> 953.33333 | AG18: =+AF18 -> 953.33333 | AH18: =+AG18 -> 953.33333 | AI18: =+AH18 -> 953.33333 | AJ18: =+AI18 -> 953.33333 | AK18: =+AJ18 -> 953.33333 | ... AN18: =+AM18 -> 953.33333 | AO18: =SUM(AC18:AN18) -> 11440 | AP18: =Z18*AB18*AA18*H18 -> 11440 | AQ18: =AP18 -> 11440 | AR18: =AP18-AQ18 -> 0 | AS18: =+AO18+V18 -> 22440 | AT18: =X18+AQ18 -> 22440 | AU18: =Y18+AR18 -> 0 | AV18: =AT18+AU18 -> 22440
D19: Subtotal Personnel | J19: =SUM(J9:J18) -> 6924.8437 | K19: =SUM(K9:K18) -> 6966.187 | L19: =SUM(L9:L18) -> 6924.8437 | M19: =SUM(M9:M18) -> 7032.9827 | N19: =SUM(N9:N18) -> 6924.8437 | O19: =SUM(O9:O18) -> 6924.8437 | P19: =SUM(P9:P18) -> 6924.8437 | Q19: =SUM(Q9:Q18) -> 6924.8437 | ... Y19: =SUM(Y9:Y18) -> 0 | AC19: =SUM(AC9:AC18) -> 7834.7515 | AD19: =SUM(AD9:AD18) -> 7300.1013 | AE19: =SUM(AE9:AE18) -> 7238.7936 | AF19: =SUM(AF9:AF18) -> 7367.5032 | AG19: =SUM(AG9:AG18) -> 7238.7936 | AH19: =SUM(AH9:AH18) -> 7238.7936 | AI19: =SUM(AI9:AI18) -> 7238.7936 | AJ19: =SUM(AJ9:AJ18) -> 7238.7936 | ... AV19: =SUM(AV9:AV18) -> 163628.4
D20: B. Fringe Benefits
D21: B.1 HQ Fringe Benefits
A22: FRINGE | B22: 50900 | C22: USA | D22: B.1.1 U.S.-Based Personnel Fringe Benefits | F22: % | H22: 0.2347 | J22: =+W22/12 -> 215.14167 | K22: =+J22 -> 215.14167 | L22: =+K22 -> 215.14167 | M22: =+L22 -> 215.14167 | N22: =+M22 -> 215.14167 | O22: =+N22 -> 215.14167 | P22: =+O22 -> 215.14167 | Q22: =+P22 -> 215.14167 | R22: =+Q22 -> 215.14167 | ... U22: =+T22 -> 215.14167 | V22: =SUM(J22:U22) -> 2581.7 | W22: =W18*H22 -> 2581.7 | X22: =W22 -> 2581.7 | Y22: 0 | AB22: =AB18 -> 4766.6667 | AC22: =+AP22/12 -> 223.74733 | AD22: =+AC22 -> 223.74733 | AE22: =+AD22 -> 223.74733 | AF22: =+AE22 -> 223.74733 | AG22: =+AF22 -> 223.74733 | AH22: =+AG22 -> 223.74733 | AI22: =+AH22 -> 223.74733 | AJ22: =+AI22 -> 223.74733 | AK22: =+AJ22 -> 223.74733 | ... AN22: =+AM22 -> 223.74733 | AO22: =SUM(AC22:AN22) -> 2684.968 | AP22: =AP18*H22 -> 2684.968 | AQ22: =AP22 -> 2684.968 | AR22: =AP22-AQ22 -> 0 | AS22: =+AO22+V22 -> 5266.668 | AT22: =X22+AQ22 -> 5266.668 | AU22: =Y22+AR22 -> 0 | AV22: =AT22+AU22 -> 5266.668
D23: B.2 Field Fringe Benefits
A24: FRINGE-MX | B24: 70015 | C24: MEX | D24: B.2.1 Mexico Field Staff Fringe Benefits | F24: % | H24: 0.3671 | J24: =(+J19-J18)*0.03+((7699.09+900)/12)*1.15 -> 1004.3248 | K24: =(+K19-K18)*0.03+((7699.09+900)/12)*1.15 -> 1005.5651 | L24: =(+L19-L18)*0.03+((7699.09+900)/12)*1.15 -> 1004.3248 | M24: =(+M19-M18)*0.03+((7699.09+900)/12)*1.15 -> 1007.5689 | N24: =(+N19-N18)*0.03+((7699.09+900)/12)*1.15 -> 1004.3248 | O24: =(+O19-O18)*0.03+((7699.09+900)/12)*1.15 -> 1004.3248 | P24: =(+P19-P18)*0.03+((7699.09+900)/12)*1.15 -> 1004.3248 | Q24: =(+Q19-Q18)*0.03+((7699.09+900)/12)*1.15 -> 1004.3248 | ... U24: =(+U19-U18)*0.03+((7699.09+900)/12)*1.15 -> 1095.1989 | V24: =SUM(J24:U24) -> 12148.759 | W24: =(SUM(W9:W16))*$H$24 -> 25406.991 | X24: =W24 -> 25406.991 | Y24: 0 | AB24: =AB10 -> 8996 | AC24: =(+AC19-AC18)*0.03+((7699.09+900)/12)*1.15 -> 1030.522 | AD24: =(+AD19-AD18)*0.03+((7699.09+900)/12)*1.15 -> 1014.4825 | AE24: =(+AE19-AE18)*0.03+((7699.09+900)/12)*1.15 -> 1012.6433 | AF24: =(+AF19-AF18)*0.03+((7699.09+900)/12)*1.15 -> 1016.5046 | AG24: =(+AG19-AG18)*0.03+((7699.09+900)/12)*1.15 -> 1012.6433 | AH24: =(+AH19-AH18)*0.03+((7699.09+900)/12)*1.15 -> 1012.6433 | AI24: =(+AI19-AI18)*0.03+((7699.09+900)/12)*1.15 -> 1012.6433 | AJ24: =(+AJ19-AJ18)*0.03+((7699.09+900)/12)*1.15 -> 1012.6433 | ... AM24: =(+AM19-AM18)*0.03+((7699.09+900)/12)*1.15 -> 1014.2026 | AN24: =(+AN19-AN18)*0.03+((7699.09+900)/12)*1.15+(7291/30.4*130) -> 32287.883 | AO24: =SUM(AC24:AN24) -> 43452.097 | AP24: =(SUM(AP9:AP16))*$H$24 -> 26423.271 | AQ24: =AP24 -> 26423.271 | AR24: =AP24-AQ24 -> 0 | AS24: =+AO24+V24 -> 55600.856 | AT24: =X24+AQ24 -> 51830.262 | AU24: =Y24+AR24 -> 0 | AV24: =AT24+AU24 -> 51830.262
D25: Subtotal Fringe Benefits | J25: =SUM(J22:J24) -> 1219.4664 | K25: =SUM(K22:K24) -> 1220.7067 | L25: =SUM(L22:L24) -> 1219.4664 | M25: =SUM(M22:M24) -> 1222.7106 | N25: =SUM(N22:N24) -> 1219.4664 | O25: =SUM(O22:O24) -> 1219.4664 | P25: =SUM(P22:P24) -> 1219.4664 | Q25: =SUM(Q22:Q24) -> 1219.4664 | ... Y25: =SUM(Y22:Y24) -> 0 | AC25: =SUM(AC22:AC24) -> 1254.2693 | AD25: =SUM(AD22:AD24) -> 1238.2298 | AE25: =SUM(AE22:AE24) -> 1236.3906 | AF25: =SUM(AF22:AF24) -> 1240.2519 | AG25: =SUM(AG22:AG24) -> 1236.3906 | AH25: =SUM(AH22:AH24) -> 1236.3906 | AI25: =SUM(AI22:AI24) -> 1236.3906 | AJ25: =SUM(AJ22:AJ24) -> 1236.3906 | ... AV25: =SUM(AV22:AV24) -> 57096.93
D26: C. Travel
D27: C.1 HQ Staff International Travel
A28: STFTRAVEL | B28: 86040 | C28: USA | D28: C.1.1 International Airfare (DC-MX) | E28: 1 | F28: Flight | G28: 1 | H28: 1 | I28: 700 | V28: =SUM(J28:U28) -> 0 | W28: =E28*I28*G28 -> 700 | X28: =W28 -> 700 | Y28: =W28-X28 -> 0 | Z28: 1 | AA28: 1 | AB28: =I28*$E$3 -> 728 | AO28: =SUM(AC28:AN28) -> 0 | AP28: =Z28*AB28*AA28*H28 -> 728 | AQ28: =AP28 -> 728 | AR28: =AP28-AQ28 -> 0 | AS28: =+AO28+V28 -> 0 | AT28: =X28+AQ28 -> 1428 | AU28: =Y28+AR28 -> 0 | AV28: =AT28+AU28 -> 1428
A29: GROUNDTRAN | B29: 86000 | C29: USA | D29: C.1.2 Ground Transportation | E29: 1 | F29: Trip | G29: 1 | H29: 1 | I29: 100 | V29: =SUM(J29:U29) -> 0 | W29: =E29*I29*G29 -> 100 | X29: =W29 -> 100 | Y29: =W29-X29 -> 0 | Z29: 1 | AA29: 1 | AB29: =I29*$E$3 -> 104 | AO29: =SUM(AC29:AN29) -> 0 | AP29: =Z29*AB29*AA29*H29 -> 104 | AQ29: =AP29 -> 104 | AR29: =AP29-AQ29 -> 0 | AS29: =+AO29+V29 -> 0 | AT29: =X29+AQ29 -> 204 | AU29: =Y29+AR29 -> 0 | AV29: =AT29+AU29 -> 204
A30: LODGING | B30: 86030 | C30: USA | D30: C.1.3 Lodging | E30: 1 | F30: Night | G30: 4 | H30: 1 | I30: 120 | V30: =SUM(J30:U30) -> 0 | W30: =E30*I30*G30 -> 480 | X30: =W30 -> 480 | Y30: =W30-X30 -> 0 | Z30: 1 | AA30: 4 | AB30: =I30*$E$3 -> 124.8 | AO30: =SUM(AC30:AN30) -> 0 | AP30: =Z30*AB30*AA30*H30 -> 499.2 | AQ30: =AP30 -> 499.2 | AR30: =AP30-AQ30 -> 0 | AS30: =+AO30+V30 -> 0 | AT30: =X30+AQ30 -> 979.2 | AU30: =Y30+AR30 -> 0 | AV30: =AT30+AU30 -> 979.2
A31: STFCN DIEM | B31: 86050 | C31: USA | D31: C.1.4 M&IE | E31: 1 | F31: Day | G31: 5 | H31: 1 | I31: 95 | V31: =SUM(J31:U31) -> 0 | W31: =E31*I31*G31 -> 475 | X31: =W31 -> 475 | Y31: =W31-X31 -> 0 | Z31: 1 | AA31: 5 | AB31: =I31*$E$3 -> 98.8 | AO31: =SUM(AC31:AN31) -> 0 | AP31: =Z31*AB31*AA31*H31 -> 494 | AQ31: =AP31 -> 494 | AR31: =AP31-AQ31 -> 0 | AS31: =+AO31+V31 -> 0 | AT31: =X31+AQ31 -> 969 | AU31: =Y31+AR31 -> 0 | AV31: =AT31+AU31 -> 969
D32: C.2 Local Staff In-Country Travel to Target Geographic Regions
A33: LSLODGING | B33: 86030 | C33: MEX | D33: C.2.1 Domestic Airfare | E33: 2 | F33: Flight | G33: 1 | H33: 1 | I33: 200 | V33: =SUM(J33:U33) -> 0 | W33: =E33*I33*G33 -> 400 | X33: =W33 -> 400 | Y33: =W33-X33 -> 0 | Z33: 2 | AA33: 1 | AB33: =I33*$E$3 -> 208 | AO33: =SUM(AC33:AN33) -> 0 | AP33: =Z33*AB33*AA33*H33 -> 416 | AQ33: =AP33 -> 416 | AR33: =AP33-AQ33 -> 0 | AS33: =+AO33+V33 -> 0 | AT33: =X33+AQ33 -> 816 | AU33: =Y33+AR33 -> 0 | AV33: =AT33+AU33 -> 816
A34: LSM&IE | B34: 86050 | C34: MEX | D34: C.2.2 Lodging | E34: 6 | F34: Night | G34: 3 | H34: 1 | I34: 100 | V34: =SUM(J34:U34) -> 0 | W34: =E34*I34*G34 -> 1800 | X34: =W34 -> 1800 | Y34: =W34-X34 -> 0 | Z34: 6 | AA34: 3 | AB34: =I34*$E$3 -> 104 | AO34: =SUM(AC34:AN34) -> 0 | AP34: =Z34*AB34*AA34*H34 -> 1872 | AQ34: =AP34 -> 1872 | AR34: =AP34-AQ34 -> 0 | AS34: =+AO34+V34 -> 0 | AT34: =X34+AQ34 -> 3672 | AU34: =Y34+AR34 -> 0 | AV34: =AT34+AU34 -> 3672
A35: LSTRANS | B35: 86000 | C35: MEX | D35: C.2.3 M&IE | E35: 6 | F35: Day | G35: 4 | H35: 1 | I35: 70 | V35: =SUM(J35:U35) -> 0 | W35: =E35*I35*G35 -> 1680 | X35: =W35 -> 1680 | Y35: =W35-X35 -> 0 | Z35: 6 | AA35: 4 | AB35: =I35*$E$3 -> 72.8 | AO35: =SUM(AC35:AN35) -> 0 | AP35: =Z35*AB35*AA35*H35 -> 1747.2 | AQ35: =AP35 -> 1747.2 | AR35: =AP35-AQ35 -> 0 | AS35: =+AO35+V35 -> 0 | AT35: =X35+AQ35 -> 3427.2 | AU35: =Y35+AR35 -> 0 | AV35: =AT35+AU35 -> 3427.2
A36: LSDOMAIR | B36: 86040 | C36: MEX | D36: C.2.4 Ground Transportation | E36: 1 | F36: Month | G36: 10 | H36: 1 | I36: 150 | V36: =SUM(J36:U36) -> 0 | W36: =E36*I36*G36 -> 1500 | X36: =W36 -> 1500 | Y36: =W36-X36 -> 0 | Z36: 1 | AA36: 10 | AB36: =I36*$E$3 -> 156 | AO36: =SUM(AC36:AN36) -> 0 | AP36: =Z36*AB36*AA36*H36 -> 1560 | AQ36: =AP36 -> 1560 | AR36: =AP36-AQ36 -> 0 | AS36: =+AO36+V36 -> 0 | AT36: =X36+AQ36 -> 3060 | AU36: =Y36+AR36 -> 0 | AV36: =AT36+AU36 -> 3060
D37: Subtotal Travel | J37: =SUM(J28:J36) -> 0 | K37: =SUM(K28:K36) -> 0 | L37: =SUM(L28:L36) -> 0 | M37: =SUM(M28:M36) -> 0 | N37: =SUM(N28:N36) -> 0 | O37: =SUM(O28:O36) -> 0 | P37: =SUM(P28:P36) -> 0 | Q37: =SUM(Q28:Q36) -> 0 | ... Y37: =SUM(Y28:Y36) -> 0 | AC37: =SUM(AC28:AC36) -> 0 | AD37: =SUM(AD28:AD36) -> 0 | AE37: =SUM(AE28:AE36) -> 0 | AF37: =SUM(AF28:AF36) -> 0 | AG37: =SUM(AG28:AG36) -> 0 | AH37: =SUM(AH28:AH36) -> 0 | AI37: =SUM(AI28:AI36) -> 0 | AJ37: =SUM(AJ28:AJ36) -> 0 | ... AV37: =SUM(AV28:AV36) -> 14555.4
D38: D. Equipment
D39: E. Supplies
A40: SUPPLIES | B40: 82401 | C40: MEX | D40: E.1 Office Supplies | E40: 1 | F40: Month | G40: 12 | H40: 1 | I40: 50 | J40: =+W40/12 -> 50 | K40: =+J40 -> 50 | L40: =+K40 -> 50 | M40: =+L40 -> 50 | N40: =+M40 -> 50 | O40: =+N40 -> 50 | P40: =+O40 -> 50 | Q40: =+P40 -> 50 | R40: =+Q40 -> 50 | ... U40: =+T40 -> 50 | V40: =SUM(J40:U40) -> 600 | W40: =E40*I40*G40*H40 -> 600 | X40: =W40 -> 600 | Y40: =W40-X40 -> 0 | Z40: 1 | AA40: 12 | AB40: =I40*$E$3 -> 52 | AC40: =+AP40/12 -> 52 | AD40: =+AC40 -> 52 | AE40: =+AD40 -> 52 | AF40: =+AE40 -> 52 | AG40: =+AF40 -> 52 | AH40: =+AG40 -> 52 | AI40: =+AH40 -> 52 | AJ40: =+AI40 -> 52 | AK40: =+AJ40 -> 52 | ... AN40: =+AM40 -> 52 | AO40: =SUM(AC40:AN40) -> 624 | AP40: =Z40*AB40*AA40*H40 -> 624 | AQ40: =AP40 -> 624 | AR40: =AP40-AQ40 -> 0 | AS40: =+AO40+V40 -> 1224 | AT40: =X40+AQ40 -> 1224 | AU40: =Y40+AR40 -> 0 | AV40: =AT40+AU40 -> 1224
A41: LAPTOP | B41: 82401 | C41: MEX | D41: E.2 Laptop Computers & Software | E41: 1 | F41: Unit | G41: 3 | H41: 1 | I41: 1000 | J41: =+W41/12+1789 -> 2039 | K41: =+X41/12 -> 250 | L41: =+K41 -> 250 | M41: =+L41 -> 250 | N41: =+M41 -> 250 | O41: =+N41 -> 250 | P41: =+O41 -> 250 | Q41: =+P41 -> 250 | R41: =+Q41 -> 250 | S41: =+R41 -> 250 | ... U41: =+T41 -> 250 | V41: =SUM(J41:U41) -> 4789 | W41: =E41*I41*G41*H41 -> 3000 | X41: =W41 -> 3000 | Y41: =W41-X41 -> 0 | Z41: 1 | AA41: 0 | AB41: =I41*$E$3 -> 1040 | AO41: =SUM(AC41:AN41) -> 0 | AP41: =Z41*AB41*AA41*H41 -> 0 | AQ41: =AP41 -> 0 | AR41: =AP41-AQ41 -> 0 | AS41: =+AO41+V41 -> 4789 | AT41: =X41+AQ41 -> 3000 | AU41: =Y41+AR41 -> 0 | AV41: =AT41+AU41 -> 3000
D42: Subtotal Supplies | J42: =SUM(J40:J41) -> 2089 | K42: =SUM(K40:K41) -> 300 | L42: =SUM(L40:L41) -> 300 | M42: =SUM(M40:M41) -> 300 | N42: =SUM(N40:N41) -> 300 | O42: =SUM(O40:O41) -> 300 | P42: =SUM(P40:P41) -> 300 | Q42: =SUM(Q40:Q41) -> 300 | ... Y42: =SUM(Y40:Y41) -> 0 | AC42: =SUM(AC40:AC41) -> 52 | AD42: =SUM(AD40:AD41) -> 52 | AE42: =SUM(AE40:AE41) -> 52 | AF42: =SUM(AF40:AF41) -> 52 | AG42: =SUM(AG40:AG41) -> 52 | AH42: =SUM(AH40:AH41) -> 52 | AI42: =SUM(AI40:AI41) -> 52 | AJ42: =SUM(AJ40:AJ41) -> 52 | ... AV42: =SUM(AV40:AV41) -> 4224
D43: F. Contractual
D44: F.1 Consultants
A45: CONSULTSM | B45: 81000 | C45: MEX | D45: F.1.1 Social Media Influencer Consultants | E45: 4 | F45: Month | G45: 6 | H45: 1 | I45: 1825 | V45: =SUM(J45:U45) -> 0 | W45: =E45*G45*H45*I45 -> 43800 | X45: =W45 -> 43800 | Y45: =W45-X45 -> 0 | Z45: =E45 -> 4 | AA45: =G45 -> 6 | AB45: =I45 -> 1825 | AO45: =SUM(AC45:AN45) -> 0 | AP45: =Z45*AA45*AB45*H45 -> 43800 | AQ45: =AP45 -> 43800 | AR45: =AP45-AQ45 -> 0 | AS45: =+AO45+V45 -> 0 | AT45: =X45+AQ45 -> 87600 | AU45: =Y45+AR45 -> 0 | AV45: =AT45+AU45 -> 87600
A46: TECHADPP | B46: 81000 | C46: MEX | D46: F.1.2 Technical Advisor on Public Policy | E46: 1 | F46: Month | G46: 5 | H46: 1 | I46: 3500 | V46: =SUM(J46:U46) -> 0 | W46: =E46*G46*H46*I46 -> 17500 | X46: =W46 -> 17500 | Y46: =W46-X46 -> 0 | Z46: =E46 -> 1 | AA46: =G46 -> 5 | AB46: =I46 -> 3500 | AO46: =SUM(AC46:AN46) -> 0 | AP46: =Z46*AA46*AB46*H46 -> 17500 | AQ46: =AP46 -> 17500 | AR46: =AP46-AQ46 -> 0 | AS46: =+AO46+V46 -> 0 | AT46: =X46+AQ46 -> 35000 | AU46: =Y46+AR46 -> 0 | AV46: =AT46+AU46 -> 35000
A47: CONSULTDC | B47: 81000 | C47: MEX | D47: F.1.3 Consultant for Participatory Research for Data Collection | E47: 1 | F47: Month | G47: 2 | H47: 1 | I47: 3000 | V47: =SUM(J47:U47) -> 0 | W47: =E47*G47*H47*I47 -> 6000 | X47: =W47 -> 6000 | Y47: =W47-X47 -> 0 | Z47: =E47 -> 1 | AA47: =G47 -> 2 | AB47: =I47 -> 3000 | AO47: =SUM(AC47:AN47) -> 0 | AP47: =Z47*AA47*AB47*H47 -> 6000 | AQ47: =AP47 -> 6000 | AR47: =AP47-AQ47 -> 0 | AS47: =+AO47+V47 -> 0 | AT47: =X47+AQ47 -> 12000 | AU47: =Y47+AR47 -> 0 | AV47: =AT47+AU47 -> 12000
D48: F.2 Contracts
A49: IMMERSIVE | B49: 81010 | C49: MEX | D49: F.2.1 Contract for Live Portrait and Immersive Experience | E49: 1 | F49: Contract | G49: 1 | H49: 1 | I49: 25000 | V49: =SUM(J49:U49) -> 0 | W49: =E49*G49*H49*I49 -> 25000 | X49: =W49 -> 25000 | Y49: =W49-X49 -> 0 | Z49: 0 | AA49: 0 | AB49: =I49 -> 25000 | AO49: =SUM(AC49:AN49) -> 0 | AP49: =Z49*AA49*AB49*H49 -> 0 | AQ49: =AP49 -> 0 | AR49: =AP49-AQ49 -> 0 | AS49: =+AO49+V49 -> 0 | AT49: =X49+AQ49 -> 25000 | AU49: =Y49+AR49 -> 0 | AV49: =AT49+AU49 -> 25000
A50: FILMPROD | B50: 81010 | C50: MEX | D50: F.2.2 Contract to Film & Produce Soap Opera | E50: 1 | F50: Contract | G50: 1 | H50: 1 | I50: 20000 | V50: =SUM(J50:U50) -> 0 | W50: =E50*G50*H50*I50 -> 20000 | X50: =W50 -> 20000 | Y50: =W50-X50 -> 0 | Z50: 0 | AA50: 0 | AB50: =I50 -> 20000 | AO50: =SUM(AC50:AN50) -> 0 | AP50: =Z50*AA50*AB50*H50 -> 0 | AQ50: =AP50 -> 0 | AR50: =AP50-AQ50 -> 0 | AS50: =+AO50+V50 -> 0 | AT50: =X50+AQ50 -> 20000 | AU50: =Y50+AR50 -> 0 | AV50: =AT50+AU50 -> 20000
A51: SECURITY | B51: 86110 | C51: MEX | D51: F.2.3 Security Advisors | E51: 1 | F51: Month | G51: 12 | H51: 1 | I51: 300 | V51: =SUM(J51:U51) -> 0 | W51: =E51*G51*H51*I51 -> 3600 | X51: =W51 -> 3600 | Y51: =W51-X51 -> 0 | Z51: =E51 -> 1 | AA51: =G51 -> 12 | AB51: =I51 -> 300 | AO51: =SUM(AC51:AN51) -> 0 | AP51: =Z51*AA51*AB51*H51 -> 3600 | AQ51: =AP51 -> 3600 | AR51: =AP51-AQ51 -> 0 | AS51: =+AO51+V51 -> 0 | AT51: =X51+AQ51 -> 7200 | AU51: =Y51+AR51 -> 0 | AV51: =AT51+AU51 -> 7200
D52: Subtotal Contractual | J52: =SUM(J45:J51) -> 0 | K52: =SUM(K45:K51) -> 0 | L52: =SUM(L45:L51) -> 0 | M52: =SUM(M45:M51) -> 0 | N52: =SUM(N45:N51) -> 0 | O52: =SUM(O45:O51) -> 0 | P52: =SUM(P45:P51) -> 0 | Q52: =SUM(Q45:Q51) -> 0 | ... Y52: =SUM(Y45:Y51) -> 0 | AC52: =SUM(AC45:AC51) -> 0 | AD52: =SUM(AD45:AD51) -> 0 | AE52: =SUM(AE45:AE51) -> 0 | AF52: =SUM(AF45:AF51) -> 0 | AG52: =SUM(AG45:AG51) -> 0 | AH52: =SUM(AH45:AH51) -> 0 | AI52: =SUM(AI45:AI51) -> 0 | AJ52: =SUM(AJ45:AJ51) -> 0 | ... AV52: =SUM(AV45:AV51) -> 186800
D53: G. Construction
D54: H. Other Direct Costs
D55: H.1 Office Costs
A56: RENT & UT | B56: 85180 | C56: MEX | D56: H.1.1 Office Space & Utilities | E56: 1 | F56: Month | G56: 12 | H56: 1 | I56: 350 | V56: =SUM(J56:U56) -> 0 | W56: =E56*I56*G56*H56 -> 4200 | X56: =W56 -> 4200 | Y56: =W56-X56 -> 0 | Z56: 1 | AA56: 12 | AB56: =I56*$E$3 -> 364 | AO56: =SUM(AC56:AN56) -> 0 | AP56: =Z56*AB56*AA56*H56 -> 4368 | AQ56: =AP56 -> 4368 | AR56: =AP56-AQ56 -> 0 | AS56: =+AO56+V56 -> 0 | AT56: =X56+AQ56 -> 8568 | AU56: =Y56+AR56 -> 0 | AV56: =AT56+AU56 -> 8568
A57: BANK FEES | B57: 90900 | C57: MEX | D57: H.1.2 Banking and Cash Handling Fees | E57: 1 | F57: Month | G57: 12 | H57: 1 | I57: 35 | V57: =SUM(J57:U57) -> 0 | W57: =E57*I57*G57*H57 -> 420 | X57: =W57 -> 420 | Y57: =W57-X57 -> 0 | Z57: 1 | AA57: 12 | AB57: =I57*$E$3 -> 36.4 | AO57: =SUM(AC57:AN57) -> 0 | AP57: =Z57*AB57*AA57*H57 -> 436.8 | AQ57: =AP57 -> 436.8 | AR57: =AP57-AQ57 -> 0 | AS57: =+AO57+V57 -> 0 | AT57: =X57+AQ57 -> 856.8 | AU57: =Y57+AR57 -> 0 | AV57: =AT57+AU57 -> 856.8
A58: PAYROLL | B58: 81030 | C58: MEX | D58: H.1.3 Payroll Processing | E58: 1 | F58: Month | G58: 12 | H58: 1 | I58: 50 | V58: =SUM(J58:U58) -> 0 | W58: =E58*I58*G58*H58 -> 600 | X58: =W58 -> 600 | Y58: =W58-X58 -> 0 | Z58: 1 | AA58: 12 | AB58: =I58*$E$3 -> 52 | AO58: =SUM(AC58:AN58) -> 0 | AP58: =Z58*AB58*AA58*H58 -> 624 | AQ58: =AP58 -> 624 | AR58: =AP58-AQ58 -> 0 | AS58: =+AO58+V58 -> 0 | AT58: =X58+AQ58 -> 1224 | AU58: =Y58+AR58 -> 0 | AV58: =AT58+AU58 -> 1224
A59: COMM | B59: 82030 | C59: MEX | D59: H.1.4 Communications Costs (Phone, Data, Internet, etc.) | E59: 1 | F59: Month | G59: 12 | H59: 1 | I59: 150 | V59: =SUM(J59:U59) -> 0 | W59: =E59*I59*G59*H59 -> 1800 | X59: =W59 -> 1800 | Y59: =W59-X59 -> 0 | Z59: 1 | AA59: 12 | AB59: =I59*$E$3 -> 156 | AO59: =SUM(AC59:AN59) -> 0 | AP59: =Z59*AB59*AA59*H59 -> 1872 | AQ59: =AP59 -> 1872 | AR59: =AP59-AQ59 -> 0 | AS59: =+AO59+V59 -> 0 | AT59: =X59+AQ59 -> 3672 | AU59: =Y59+AR59 -> 0 | AV59: =AT59+AU59 -> 3672
A60: SUBSCRIPT | B60: 89400 | C60: MEX | D60: H.1.5 HR, Platform Subscriptions (Timekeeping and Expense Reporting) | E60: 1 | F60: Month | G60: 12 | H60: 1 | I60: =10*12 -> 120 | V60: =SUM(J60:U60) -> 0 | W60: =E60*I60*G60*H60 -> 1440 | X60: =W60 -> 1440 | Y60: =W60-X60 -> 0 | Z60: 1 | AA60: 12 | AB60: =I60*$E$3 -> 124.8 | AO60: =SUM(AC60:AN60) -> 0 | AP60: =Z60*AB60*AA60*H60 -> 1497.6 | AQ60: =AP60 -> 1497.6 | AR60: =AP60-AQ60 -> 0 | AS60: =+AO60+V60 -> 0 | AT60: =X60+AQ60 -> 2937.6 | AU60: =Y60+AR60 -> 0 | AV60: =AT60+AU60 -> 2937.6
A61: MEETING | B61: 87010 | C61: MEX | D61: H.1.6 Meeting Expenses | E61: 1 | F61: Month | G61: 12 | H61: 1 | I61: 50 | V61: =SUM(J61:U61) -> 0 | W61: =E61*I61*G61*H61 -> 600 | X61: =W61 -> 600 | Y61: =W61-X61 -> 0 | Z61: 1 | AA61: 12 | AB61: =I61*$E$3 -> 52 | AO61: =SUM(AC61:AN61) -> 0 | AP61: =Z61*AB61*AA61*H61 -> 624 | AQ61: =AP61 -> 624 | AR61: =AP61-AQ61 -> 0 | AS61: =+AO61+V61 -> 0 | AT61: =X61+AQ61 -> 1224 | AU61: =Y61+AR61 -> 0 | AV61: =AT61+AU61 -> 1224
A62: RECRUIT | B62: 90450 | C62: MEX | D62: H.1.7 Procurement Advertising | E62: 1 | F62: Year | G62: 1 | H62: 1 | I62: 400 | V62: =SUM(J62:U62) -> 0 | W62: =E62*I62*G62*H62 -> 400 | X62: =W62 -> 400 | Y62: =W62-X62 -> 0 | Z62: 1 | AA62: 1 | AB62: =I62*$E$3 -> 416 | AO62: =SUM(AC62:AN62) -> 0 | AP62: =Z62*AB62*AA62*H62 -> 416 | AQ62: =AP62 -> 416 | AR62: =AP62-AQ62 -> 0 | AS62: =+AO62+V62 -> 0 | AT62: =X62+AQ62 -> 816 | AU62: =Y62+AR62 -> 0 | AV62: =AT62+AU62 -> 816
A63: LEGAL | B63: 90100 | C63: MEX | D63: H.1.8 Legal Fees | E63: 1 | F63: Year | G63: 1 | H63: 1 | I63: 250 | V63: =SUM(J63:U63) -> 0 | W63: =E63*I63*G63*H63 -> 250 | X63: =W63 -> 250 | Y63: =W63-X63 -> 0 | Z63: 1 | AA63: 1 | AB63: =I63*$E$3 -> 260 | AO63: =SUM(AC63:AN63) -> 0 | AP63: =Z63*AB63*AA63*H63 -> 260 | AQ63: =AP63 -> 260 | AR63: =AP63-AQ63 -> 0 | AS63: =+AO63+V63 -> 0 | AT63: =X63+AQ63 -> 510 | AU63: =Y63+AR63 -> 0 | AV63: =AT63+AU63 -> 510
A64: AUDIT | B64: 82100 | C64: MEX | D64: H.1.9 Audit Fees | E64: 1 | F64: Year | G64: 1 | H64: 1 | I64: 100 | V64: =SUM(J64:U64) -> 0 | W64: =E64*I64*G64*H64 -> 100 | X64: =W64 -> 100 | Y64: =W64-X64 -> 0 | Z64: 1 | AA64: 1 | AB64: =I64*$E$3 -> 104 | AO64: =SUM(AC64:AN64) -> 0 | AP64: =Z64*AB64*AA64*H64 -> 104 | AQ64: =AP64 -> 104 | AR64: =AP64-AQ64 -> 0 | AS64: =+AO64+V64 -> 0 | AT64: =X64+AQ64 -> 204 | AU64: =Y64+AR64 -> 0 | AV64: =AT64+AU64 -> 204
D65: H.2 Activities Costs
A66: TRANS | B66: 81021 | C66: MEX | D66: H.2.1 Translation Costs | E66: 1 | F66: Year | G66: 1 | H66: 1 | I66: 15000 | V66: =SUM(J66:U66) -> 0 | W66: =E66*G66*H66*I66 -> 15000 | X66: =W66 -> 15000 | Y66: =W66-X66 -> 0 | Z66: =E66 -> 1 | AA66: =G66 -> 1 | AB66: =I66*$E$3 -> 15600 | AO66: =SUM(AC66:AN66) -> 0 | AP66: =H66*Z66*AA66*AB66 -> 15600 | AQ66: =AP66 -> 15600 | AR66: =AP66-AQ66 -> 0 | AS66: =+AO66+V66 -> 0 | AT66: =X66+AQ66 -> 30600 | AU66: =Y66+AR66 -> 0 | AV66: =AT66+AU66 -> 30600
A67: SOCIALADS | B67: 90450 | C67: MEX | D67: H.2.2 Social Media Ads/Boosts | E67: 1 | F67: Ad | G67: 24 | H67: 1 | I67: 250 | V67: =SUM(J67:U67) -> 0 | W67: =E67*G67*H67*I67 -> 6000 | X67: =W67 -> 6000 | Y67: =W67-X67 -> 0 | Z67: =E67 -> 1 | AA67: =G67 -> 24 | AB67: =I67*$E$3 -> 260 | AO67: =SUM(AC67:AN67) -> 0 | AP67: =H67*Z67*AA67*AB67 -> 6240 | AQ67: =AP67 -> 6240 | AR67: =AP67-AQ67 -> 0 | AS67: =+AO67+V67 -> 0 | AT67: =X67+AQ67 -> 12240 | AU67: =Y67+AR67 -> 0 | AV67: =AT67+AU67 -> 12240
A68: WEBSITE | B68: 81035 | C68: MEX | D68: H.2.3 Website Development Fees | E68: 1 | F68: Lumpsum | G68: 1 | H68: 1 | I68: 7000 | V68: =SUM(J68:U68) -> 0 | W68: =E68*G68*H68*I68 -> 7000 | X68: =W68 -> 7000 | Y68: =W68-X68 -> 0 | Z68: 0 | AA68: 0 | AB68: =I68*$E$3 -> 7280 | AO68: =SUM(AC68:AN68) -> 0 | AP68: =H68*Z68*AA68*AB68 -> 0 | AQ68: =AP68 -> 0 | AR68: =AP68-AQ68 -> 0 | AS68: =+AO68+V68 -> 0 | AT68: =X68+AQ68 -> 7000 | AU68: =Y68+AR68 -> 0 | AV68: =AT68+AU68 -> 7000
A69: HOSTMAINT | B69: 81035 | C69: MEX | D69: H.2.4 Website Hosting and Maintenance Fees | E69: 1 | F69: Year | G69: 1 | H69: 1 | I69: 800 | V69: =SUM(J69:U69) -> 0 | W69: =E69*G69*I69*H69 -> 800 | X69: =W69 -> 800 | Y69: =W69-X69 -> 0 | Z69: =E69 -> 1 | AA69: =G69 -> 1 | AB69: =I69*$E$3 -> 832 | AO69: =SUM(AC69:AN69) -> 0 | AP69: =Z69*AA69*AB69*H69 -> 832 | AQ69: =AP69 -> 832 | AR69: =AP69-AQ69 -> 0 | AS69: =+AO69+V69 -> 0 | AT69: =X69+AQ69 -> 1632 | AU69: =Y69+AR69 -> 0 | AV69: =AT69+AU69 -> 1632
D70: H.3 M&E
A71: M&EMATL | B71: 82420 | C71: MEX | D71: H.3.1 M&E Materials | E71: 1 | F71: Year | G71: 1 | H71: 1 | I71: 300 | V71: =SUM(J71:U71) -> 0 | W71: =E71*G71*I71 -> 300 | X71: =W71 -> 300 | Y71: =W71-X71 -> 0 | Z71: 1 | AA71: 1 | AB71: =I71*$E$3 -> 312 | AO71: =SUM(AC71:AN71) -> 0 | AP71: =Z71*AA71*AB71 -> 312 | AQ71: =AP71 -> 312 | AR71: =AP71-AQ71 -> 0 | AS71: =+AO71+V71 -> 0 | AT71: =X71+AQ71 -> 612 | AU71: =Y71+AR71 -> 0 | AV71: =AT71+AU71 -> 612
A72: M&ETRAIN | B72: 87010 | C72: MEX | D72: H.3.2 M&E Training and Coordination Meetings | E72: 1 | F72: Meetings | G72: 1 | H72: 1 | I72: 121 | V72: =SUM(J72:U72) -> 0 | W72: =E72*G72*I72 -> 121 | X72: =W72 -> 121 | Y72: =W72-X72 -> 0 | Z72: 1 | AA72: 1 | AB72: =I72*$E$3 -> 125.84 | AO72: =SUM(AC72:AN72) -> 0 | AP72: =Z72*AA72*AB72 -> 125.84 | AQ72: =AP72 -> 125.84 | AR72: =AP72-AQ72 -> 0 | AS72: =+AO72+V72 -> 0 | AT72: =X72+AQ72 -> 246.84 | AU72: =Y72+AR72 -> 0 | AV72: =AT72+AU72 -> 246.84
A73: EVAL | B73: 81010 | C73: MEX | D73: H.3.3 External Project Evaluation support costs | E73: 1 | F73: Lumpsum | G73: 0 | H73: 1 | I73: 1000 | V73: =SUM(J73:U73) -> 0 | W73: =E73*G73*I73 -> 0 | X73: =W73 -> 0 | Y73: =W73-X73 -> 0 | Z73: 1 | AA73: 1 | AB73: =I73*$E$3 -> 1040 | AO73: =SUM(AC73:AN73) -> 0 | AP73: =Z73*AA73*AB73 -> 1040 | AQ73: =AP73 -> 1040 | AR73: =AP73-AQ73 -> 0 | AS73: =+AO73+V73 -> 0 | AT73: =X73+AQ73 -> 1040 | AU73: =Y73+AR73 -> 0 | AV73: =AT73+AU73 -> 1040
D74: Subtotal Other Direct Costs | J74: =SUM(J55:J73) -> 0 | K74: =SUM(K55:K73) -> 0 | L74: =SUM(L55:L73) -> 0 | M74: =SUM(M55:M73) -> 0 | N74: =SUM(N55:N73) -> 0 | O74: =SUM(O55:O73) -> 0 | P74: =SUM(P55:P73) -> 0 | Q74: =SUM(Q55:Q73) -> 0 | ... Y74: =SUM(Y55:Y73) -> 0 | AC74: =SUM(AC55:AC73) -> 0 | AD74: =SUM(AD55:AD73) -> 0 | AE74: =SUM(AE55:AE73) -> 0 | AF74: =SUM(AF55:AF73) -> 0 | AG74: =SUM(AG55:AG73) -> 0 | AH74: =SUM(AH55:AH73) -> 0 | AI74: =SUM(AI55:AI73) -> 0 | AJ74: =SUM(AJ55:AJ73) -> 0 | ... AV74: =SUM(AV55:AV73) -> 73383.24
D75: I. Total Direct Costs | J75: =J19+J25+J37+J42+J52+J74 -> 10233.31 | K75: =K19+K25+K37+K42+K52+K74 -> 8486.8937 | L75: =L19+L25+L37+L42+L52+L74 -> 8444.3102 | M75: =M19+M25+M37+M42+M52+M74 -> 8555.6933 | N75: =N19+N25+N37+N42+N52+N74 -> 8444.3102 | O75: =O19+O25+O37+O42+O52+O74 -> 8444.3102 | P75: =P19+P25+P37+P42+P52+P74 -> 8444.3102 | Q75: =Q19+Q25+Q37+Q42+Q52+Q74 -> 8444.3102 | ... Y75: =Y19+Y25+Y37+Y42+Y52+Y74 -> 0 | AC75: =AC19+AC25+AC37+AC42+AC52+AC74 -> 9141.0208 | AD75: =AD19+AD25+AD37+AD42+AD52+AD74 -> 8590.3311 | AE75: =AE19+AE25+AE37+AE42+AE52+AE74 -> 8527.1842 | AF75: =AF19+AF25+AF37+AF42+AF52+AF74 -> 8659.7551 | AG75: =AG19+AG25+AG37+AG42+AG52+AG74 -> 8527.1842 | AH75: =AH19+AH25+AH37+AH42+AH52+AH74 -> 8527.1842 | AI75: =AI19+AI25+AI37+AI42+AI52+AI74 -> 8527.1842 | AJ75: =AJ19+AJ25+AJ37+AJ42+AJ52+AJ74 -> 8527.1842 | ... AV75: =AV19+AV25+AV37+AV42+AV52+AV74 -> 499687.97
D76: J. Indirect Cost
A77: IDC | B77: 94050 | C77: USA | D77: J.1 Indirect Cost (28.28% NICRA rate) | F77: 0.2828 | J77: =J75*$F$77 -> 2893.9801 | K77: =K75*$F$77 -> 2400.0936 | L77: =L75*$F$77 -> 2388.0509 | M77: =M75*$F$77 -> 2419.5501 | N77: =N75*$F$77 -> 2388.0509 | O77: =O75*$F$77 -> 2388.0509 | P77: =P75*$F$77 -> 2388.0509 | Q77: =Q75*$F$77 -> 2388.0509 | ... U77: =U75*$F$77 -> 3270.3902 | V77: =V75*E77 -> 0 | W77: =W75*F77 -> 77448.935 | X77: =W77 -> 77448.935 | Y77: =W77-X77 -> 0 | AC77: =AC75*$F$77 -> 2585.0807 | AD77: =AD75*$F$77 -> 2429.3456 | AE77: =AE75*$F$77 -> 2411.4877 | AF77: =AF75*$F$77 -> 2448.9787 | AG77: =AG75*$F$77 -> 2411.4877 | AH77: =AH75*$F$77 -> 2411.4877 | AI77: =AI75*$F$77 -> 2411.4877 | AJ77: =AJ75*$F$77 -> 2411.4877 | ... AN77: =AN75*$F$77 -> 12166.938 | AO77: =SUM(AC77:AN77) -> 38937.384 | AP77: =AP75*F77 -> 63862.823 | AQ77: =AP77 -> 63862.823 | AR77: =AP77-AQ77 -> 0 | AS77: =AS75*AB77 -> 0 | AT77: =X77+AQ77 -> 141311.76 | AU77: =Y77+AR77 -> 0 | AV77: =AT77+AU77 -> 141311.76
D78: J.2 Total Indirect Cost | J78: =J77 -> 2893.9801 | K78: =K77 -> 2400.0936 | L78: =L77 -> 2388.0509 | M78: =M77 -> 2419.5501 | N78: =N77 -> 2388.0509 | O78: =O77 -> 2388.0509 | P78: =P77 -> 2388.0509 | Q78: =Q77 -> 2388.0509 | ... Y78: =Y77 -> 0 | AC78: =AC77 -> 2585.0807 | AD78: =AD77 -> 2429.3456 | AE78: =AE77 -> 2411.4877 | AF78: =AF77 -> 2448.9787 | AG78: =AG77 -> 2411.4877 | AH78: =AH77 -> 2411.4877 | AI78: =AI77 -> 2411.4877 | AJ78: =AJ77 -> 2411.4877 | ... AV78: =AV77 -> 141311.76
D79: K. GRAND TOTAL | J79: =J75+J78 -> 13127.29 | K79: =K75+K78 -> 10886.987 | L79: =L75+L78 -> 10832.361 | M79: =M75+M78 -> 10975.243 | N79: =N75+N78 -> 10832.361 | O79: =O75+O78 -> 10832.361 | P79: =P75+P78 -> 10832.361 | Q79: =Q75+Q78 -> 10832.361 | ... Y79: =Y75+Y78 -> 0 | AC79: =AC75+AC78 -> 11726.102 | AD79: =AD75+AD78 -> 11019.677 | AE79: =AE75+AE78 -> 10938.672 | AF79: =AF75+AF78 -> 11108.734 | AG79: =AG75+AG78 -> 10938.672 | AH79: =AH75+AH78 -> 10938.672 | AI79: =AI75+AI78 -> 10938.672 | AJ79: =AJ75+AJ78 -> 10938.672 | ... AV79: =AV75+AV78 -> 640999.73
