Workbook

Sheet Budget Summary
A1: Partners of the Americas
A2: FY 2024 Traditional Public-Private Partnership Program (Education and Culture Program)
A3: Assistance Listing 19.415 / Funding Opportunity #SFOP0010173
A4: Budget Summary | B4: Educational and Cultural Affairs | C4: Cost Sharing | D4: Total
A5: Program Costs | B5: =B17+B20+B22 -> 164155 | C5: ='FY24 Budget Details'!G32+'FY24 Budget Details'!G43+'FY24 Budget Details'!G63 -> 115912.8 | D5: =B5+C5 -> 280067.8
A6: Program costs per participant | B6: =B5/30 -> 5471.8333 | C6: =C5/30 -> 3863.76 | D6: =B6+C6 -> 9335.5933
A7: Administrative Costs | B7: =B15+B16+B24 -> 184599.93 | C7: ='FY24 Budget Details'!G13+'FY24 Budget Details'!G17+'FY24 Budget Details'!G67 -> 11913.6 | D7: =B7+C7 -> 196513.53
A8: Administrative costs per participant | B8: =B7/30 -> 6153.331 | C8: =C7/30 -> 397.12 | D8: =B8+C8 -> 6550.451
A9: Total Costs | B9: =B5+B7 -> 348754.93 | C9: =C5+C7 -> 127826.4 | D9: =B9+C9 -> 476581.33
A10: Total costs per participant Number of Participants: 30 | B10: =B6+B8 -> 11625.164 | C10: =C6+C8 -> 4260.88 | D10: =B10+C10 -> 15886.044
A14: Budget Categories | B14: Amount
A15: 1. Personnel | B15: =+'FY24 Budget Details'!F13 -> 85254.8
A16: 2. Fringe Benefits | B16: =+'FY24 Budget Details'!F17 -> 22460.274
A17: 3. Travel | B17: =+'FY24 Budget Details'!F32 -> 25749
A18: 4. Equipment | B18: ='FY24 Budget Details'!F33 -> 0
A19: 5. Supplies | B19: ='FY24 Budget Details'!F34 -> 0
A20: 6. Contractual | B20: ='FY24 Budget Details'!F43 -> 128000
A21: 7. Construction | B21: ='FY24 Budget Details'!F35 -> 0
A22: 8. Other Direct Costs | B22: ='FY24 Budget Details'!F63 -> 10406
A23: 9. Total Direct Costs (lines 1-8) | B23: =SUM(B15:B22) -> 271870.07
A24: 10. Indirect Costs* | B24: ='FY24 Budget Details'!F67 -> 76884.857
A25: 11. Total Costs (lines 9-10) | B25: =B24+B23 -> 348754.93
A26: 12. Cost-Sharing | B26: ='FY24 Budget Details'!G68 -> 127826.4

Sheet FY24 Budget Details
C1: Partners of the Americas
C2: FY 2024 Traditional Public-Private Partnership Program
C3: Assistance Listing 19.415 / Funding Opportunity #SFOP0010173
C4: August 1, 2024 - December 31, 2025
C6: Budget Category | D6: Approved FY 2023 ECA Funding Level | E6: FY 2023 Actual Budget | F6: FY 2024 ECA Funds Request REVISED | G6: FY 2024 Cost Sharing | H6: FY 2024 Total Budget REVISED | I6: % Change
C7: I. Salaries
A8: PERSNL | B8: 50000 (Timesheets) | C8: 1. Senior Director - $11,000/Month Aug 2024 - Dec 2025 at 5% LOE | D8: 0 | E8: 0 | F8: =(11000*5%*5)+(11000*5%*1.05*12) -> 9680 | G8: 0 | H8: =+F8+G8 -> 9680
A9: PERSNL | B9: 50000 (Timesheets) | C9: 2. Program Director - $6,400/Month Jan 2025 - Dec 2025 at 10% LOE | D9: 12362 | E9: =((6400*0.1*12)+(11000*0.05*8)) -> 12080 | F9: =(6400*10%*0)+(6400*10%*1.05*12) -> 8064 | G9: 0 | H9: =+F9+G9 -> 8064
A10: PERSNL | B10: 50000 (Timesheets) | C10: 3. Senior Program Officer - $5,358/Month Jan 2025 - Dec 2025 at 100% LOE | D10: 35747 | E10: =5177*12 -> 62124 | F10: =(5358*20%*0)+(5358*50%*0)+(5358*1.05*12) -> 67510.8 | G10: 0 | H10: =+F10+G10 -> 67510.8
C11: 4. Program Assistant - $4,500/Month Jan 2025 - Sep 2025 at 0% LOE | D11: 40084 | E11: =(4500*20%*7) -> 6300 | F11: 0 | G11: 0 | H11: =+F11+G11 -> 0
C12: 5. Program Support | D12: 0 | E12: 0 | F12: 0 | G12: =(21.9*8)*1*68 -> 11913.6 | H12: =+F12+G12 -> 11913.6
C13: Total Salaries | D13: =SUM(D8:D12) -> 88193 | E13: =SUM(E8:E12) -> 80504 | F13: =SUM(F8:F12) -> 85254.8 | G13: =SUM(G8:G12) -> 11913.6 | H13: =+F13+G13 -> 97168.4 | I13: =+F13/D13 -> 0.96668443
C14: II. Fringe Benefits | H14: =+F14+G14 -> 0
A15: FRINGE | B15: 50900 (Timesheets) | C15: 23.47% - Fringe Benefits US-based staff | D15: 20699 | E15: =((E10+E11)*23.47%)+(E9*53.864%) -> 22565.884 | F15: =(F10+F11+F8)*23.47% -> 18116.681 | G15: 0 | H15: =+F15+G15 -> 18116.681
A16: FRINGE-CO | B16: 70015 | C16: 53.864% - Fringe Benefits Colombia based staff | D16: 0 | E16: 0 | F16: =F9*53.864% -> 4343.593 | G16: 0 | H16: =+F16+G16 -> 4343.593
C17: Total Fringe Benefits | D17: =SUM(D15:D16) -> 20699 | E17: =SUM(E15:E16) -> 22565.884 | F17: =SUM(F15:F16) -> 22460.274 | G17: =SUM(G15:G16) -> 0 | H17: =+F17+G17 -> 22460.274 | I17: =+F17/D17 -> 1.0850898
C18: III. Travel | H18: =+F18+G18 -> 0
C19: 1. Staff Travel | H19: =+F19+G19 -> 0
A20: STFTRAVEL | B20: 86040 | C20: a. Domestic Round Trip Airfare ($400 x 2 trip) | D20: 600 | E20: =400*3 -> 1200 | F20: =400*2 -> 800 | G20: 0 | H20: =+F20+G20 -> 800
A21: STFCN DIEM | B21: 86030 (Lodging) & 86050 (M&IE) | C21: b. Domestic Lodging & Per Diem Washington, DC ($258 x 12 nights x 1 trip) + ($71/day x 13 days) Other Host City ($200 x 4 nights x 1 trip) + ($71/day x 5 days) | D21: 900 | E21: =3100+720+(200*6) -> 5020 | F21: =(258*12)+(71*13)+(200*4)+(71*5) -> 5174 | G21: 0 | H21: =+F21+G21 -> 5174
A22: STFTRAVEL | B22: 86040 | C22: c. International Round Trip Airfare ($1,600 x 1 trip) | D22: 1400 | E22: 1400 | F22: =1600 -> 1600 | G22: 0 | H22: =+F22+G22 -> 1600
A23: STFCN DIEM | B23: 86030 (Lodging) & 86050 (M&IE) | C23: d. International Lodging & Per Diem ($160/day + $70/day) x 14 days | D23: 1575 | E23: =(170*7)+(50*7) -> 1540 | F23: =(160+70)*14 -> 3220 | G23: 0 | H23: =+F23+G23 -> 3220
C24: 2. Participant Travel | H24: =+F24+G24 -> 0
A25: PARTTRAVEL | B25: 86040 | C25: a. International Round Trip Airfare ($1,650 x 6 trips) | D25: 60000 | E25: =(1650*30)+(400*10)+1000 -> 54500 | F25: =1650*6 -> 9900 | G25: 0 | H25: =+F25+G25 -> 9900
A26: PARTPERDIE | B26: 86050 | C26: b. International/Domestic Per Diem ($50/day x 10 days x 6 trips) | D26: 15000 | E26: =(50*10*30)+(281.82*11*10) -> 46000.2 | F26: =50*10*6 -> 3000 | G26: 0 | H26: =+F26+G26 -> 3000
A27: PARTPERDIE | B27: 86050 | C27: c. Visa Fees ($185 x 3 participants) | D27: 1800 | E27: =180*8 -> 1440 | F27: =185*3 -> 555 | G27: 0 | H27: =+F27+G27 -> 555
A28: VISATRVEXP | B28: 86000 (Transport) 86030 (Lodging) & 86050 (M&IE) | C28: d. Visa Related Travel Fees ($250 x 6 participants) | D28: 7500 | E28: =250*30 -> 7500 | F28: =6*250 -> 1500 | G28: 0 | H28: =+F28+G28 -> 1500
C29: e. U.S. Domestic flights for LAC Group Exchange Participants ($400 x 10 participants) | D29: 0 | E29: 0 | F29: 0 | H29: =+F29+G29 -> 0
C30: f. U.S. Hotel for LAC Group Exchange Participants ($258 x 7 nights x 10 participants) Other Host City ($200 x 4 nights x 1 trip) | D30: 0 | E30: 0 | F30: 0 | H30: =+F30+G30 -> 0
C31: g. U.S. Local Travel for LAC Group Exchange | D31: 0 | E31: 0 | F31: 0 | H31: =+F31+G31 -> 0
C32: Total Travel | D32: =SUM(D20:D31) -> 88775 | E32: =SUM(E20:E31) -> 118600.2 | F32: =SUM(F20:F31) -> 25749 | G32: =SUM(G20:G28) -> 0 | H32: =+F32+G32 -> 25749 | I32: =+F32/D32 -> 0.29004787
C33: IV. Equipment | H33: =+F33+G33 -> 0
C34: V. Supplies | H34: =+F34+G34 -> 0
C35: VI. Contractual | H35: =+F35+G35 -> 0
C36: a. Large Subawards (2 subawards x $16,500) | D36: =16500*2 -> 33000 | E36: 33000 | F36: 0 | G36: 0 | H36: =+F36+G36 -> 0
C37: b. Small Subawards (3 subawards x $3,000) | D37: =3000*3 -> 9000 | E37: 9000 | F37: 0 | G37: 0 | H37: =+F37+G37 -> 0
A38: SUBCOMLED | B38: 89050 | C38: c. Subawards (6 community-led projects x $9,000) | D38: 0 | E38: 0 | F38: =6*9000 -> 54000 | G38: =9000*5 -> 45000 | H38: =+F38+G38 -> 99000
A39: SUBGROUPEX | B39: 89050 | C39: d. Subawards (group exchanges) (4 subawards x $12,500) | D39: 0 | E39: 0 | F39: =4*12500 -> 50000 | G39: =9000*4 -> 36000 | H39: =+F39+G39 -> 86000
C40: d. Logistics Consultant ($200/day x 57 days) | D40: 0 | E40: 0 | F40: 0 | G40: 0 | H40: =+F40+G40 -> 0
A41: CONSULT | B41: 81000 | C41: d. Technical/Operational Consultant Pool ($300/day x 60 days) | D41: 0 | E41: 0 | F41: =300*60 -> 18000 | G41: 0 | H41: =+F41+G41 -> 18000
A42: M&ECONSULT | B42: 81000 | C42: e. Monitoring and Evaluation Consultant ($300 x 20 days) | D42: 0 | E42: 0 | F42: =300*20 -> 6000 | G42: 0 | H42: =+F42+G42 -> 6000
C43: Total Contractual | D43: =SUM(D36:D42) -> 42000 | E43: =SUM(E36:E42) -> 42000 | F43: =SUM(F36:F42) -> 128000 | G43: =SUM(G36:G42) -> 81000 | H43: =+F43+G43 -> 209000 | I43: =+F43/D43 -> 3.047619
C44: VII. Construction | H44: =+F44+G44 -> 0
C45: VIII. Other Direct Costs | H45: =+F45+G45 -> 0
C46: 1. Honoraria | H46: =+F46+G46 -> 0
C47: a. Logistics Consultant ($200/day x 57 days) | D47: 27625 | E47: 13500 | F47: 0 | G47: 0 | H47: =+F47+G47 -> 0
C48: 2. Fees | H48: =+F48+G48 -> 0
C49: a. Monitoring and Evaluation ($300 x 14 days) | D49: 3825 | E49: 4000 | F49: 0 | G49: 0 | H49: =+F49+G49 -> 0
C50: 3. Events | H50: =+F50+G50 -> 0
C51: a. Event Costs - One-Day, In-Person Peer Learning Event | D51: 5000 | E51: =1200+1000 -> 2200 | F51: 0 | G51: 0 | H51: =+F51+G51 -> 0
C52: b. Group Meals for LAC Group Exchange ($50 x 12 people x 2 meals) | D52: 0 | F52: 0 | H52: =+F52+G52 -> 0
C53: c. Cultural Activities for Group Exchange ($90 x 11 people) | D53: 0 | F53: 0 | H53: =+F53+G53 -> 0
C54: 4. Communications | H54: =+F54+G54 -> 0
A55: COMM | B55: 82030 | C55: a. Promotion & Communications | D55: 882 | E55: 0 | F55: 7000 | G55: 0 | H55: =+F55+G55 -> 7000
A56: SUBSCRIPT | B56: 89400 | C56: b. Platform Subscriptions ($50/month x 17 months) May 2024 - June 2024 at 25% July 2024 - Sept 2024 at 50% October 2024 - Sept 2025 at 100% | D56: 1900 | E56: 510 | F56: =(50*25%*2)+(50*50%*3)+(50*100%*12) -> 700 | H56: =+F56+G56 -> 700
A57: SUBSCRIPT | B57: 89400 | C57: c. Online Platform for Subaward Management ($120/month x 17 months) | D57: 2280 | E57: 2000 | F57: =120*17 -> 2040 | G57: 0 | H57: =+F57+G57 -> 2040
C58: 5. Materials | H58: =+F58+G58 -> 0
C59: a. Translation and Interpretation Services | D59: 5000 | F59: 0 | G59: 0 | H59: =+F59+G59 -> 0
A60: SUPPLIES | B60: 82420 | C60: b. Supplies | D60: 0 | E60: 298.59 | F60: 666 | H60: =+F60+G60 -> 666
C61: 6. Volunteer Time | H61: =+F61+G61 -> 0
C62: a. U.S. and LAC Volunteer Time | D62: 0 | F62: 0 | G62: ='Volunteer Time Cost Share'!E14 -> 34912.8 | H62: =+F62+G62 -> 34912.8
C63: Total Other Direct Costs | D63: =SUM(D47:D62) -> 46512 | E63: =SUM(E47:E62) -> 22508.59 | F63: =SUM(F47:F62) -> 10406 | G63: =SUM(G47:G62) -> 34912.8 | H63: =+F63+G63 -> 45318.8 | I63: =+F63/D63 -> 0.22372721
C64: Total Direct Costs | D64: =D63+D43+D32+D17+D13 -> 286179 | E64: =E63+E43+E32+E17+E13 -> 286178.67 | F64: =F63+F43+F32+F17+F13 -> 271870.07 | G64: =G63+G43+G32+G17+G13 -> 127826.4 | H64: =+F64+G64 -> 399696.47 | I64: =+F64/D64 -> 0.95000008
C65: IX. Indirect Costs* | H65: =+F65+G65 -> 0
A66: IDC | B66: 94050 | C66: 0.2828 | D66: 80931 | E66: =E64*0.2828 -> 80931.329 | F66: =F64*C66 -> 76884.857 | G66: 0 | H66: =+F66+G66 -> 76884.857
C67: Total Indirect Costs | D67: =D66 -> 80931 | E67: =E66 -> 80931.329 | F67: =F66 -> 76884.857 | G67: =G66 -> 0 | H67: =+F67+G67 -> 76884.857 | I67: =+F67/D67 -> 0.95000503
C68: TOTAL COSTS | D68: =D67+D64 -> 367110 | E68: =E67+E64 -> 367110 | F68: =F67+F64 -> 348754.93 | G68: =G67+G64 -> 127826.4 | H68: =+F68+G68 -> 476581.33 | I68: =+F68/D68 -> 0.95000117

Sheet Volunteer Time Cost Share
A1: U.S. and LAC Volunteer Time
A2: Item | B2: # Vol-days | C2: Daily Rate | D2: Travel/project grants | E2: Total Cost Share
A4: Non-U.S. (LAC) Volunteers
A5: Participant selection/planning and preparation | B5: 2 | C5: =8.93*8 -> 71.44 | D5: 20 | E5: =B5*C5*D5 -> 2857.6
A6: Orientation | B6: 2 | C6: =8.93*8 -> 71.44 | D6: 20 | E6: =B6*C6*D6 -> 2857.6
A7: Follow-on engagement | B7: 5 | C7: =8.93*8 -> 71.44 | D7: 20 | E7: =B7*C7*D7 -> 7144
A8: Sub total | E8: =SUM(E5:E7) -> 12859.2
A9: U.S. Volunteers
A10: Participant selection/planning and preparation | B10: 2 | C10: =30.63*8 -> 245.04 | D10: 10 | E10: =B10*C10*D10 -> 4900.8
A11: Orientation | B11: 2 | C11: =30.63*8 -> 245.04 | D11: 10 | E11: =B11*C11*D11 -> 4900.8
A12: Follow-on engagement | B12: 5 | C12: =30.63*8 -> 245.04 | D12: 10 | E12: =B12*C12*D12 -> 12252
A13: Sub total | E13: =SUM(E10:E12) -> 22053.6
A14: Total volunteer time match | E14: =E13+E8 -> 34912.8
