Workbook

Sheet 2. Summary Budget
A1: Summary Cost Amendment Budget
A2: Partners of the Americas
A3: 100,000 Strong in the Americas
A4: 42 Months (April 2023 - October 2026)
D6: Current Budget (4/13/23-08/08/25) | E6: Changes (+ / -) | F6: New Budget (08/08/25-10/31/26)
A8: A | C8: Personnel | D8: ='3. Detailed Budget'!L21 -> 767085 | E8: ='3. Detailed Budget'!$M$21 -> 189464 | F8: =D8+E8 -> 956549
A9: B | C9: Fringe Benefits | D9: ='3. Detailed Budget'!L24 -> 180035 | E9: ='3. Detailed Budget'!$M$24 -> 44467 | F9: =D9+E9 -> 224502
A10: C | C10: Travel | D10: ='3. Detailed Budget'!L35 -> 35290 | E10: ='3. Detailed Budget'!M35 -> 0 | F10: =D10+E10 -> 35290
A11: D | C11: Equipment | D11: ='3. Detailed Budget'!L36 -> 0 | E11: 0 | F11: =D11+E11 -> 0
A12: E | C12: Supplies | D12: ='3. Detailed Budget'!L39 -> 550 | E12: 0 | F12: =D12+E12 -> 550
A13: F | C13: Contractual | D13: ='3. Detailed Budget'!L44 -> 5000 | E13: ='3. Detailed Budget'!$M$44 -> 26800 | F13: =D13+E13 -> 31800
A14: G | C14: Construction | D14: ='3. Detailed Budget'!L45 -> 0 | E14: 0 | F14: =D14+E14 -> 0
A15: H | C15: Other Direct Costs | D15: ='3. Detailed Budget'!L64 -> 89761 | E15: ='3. Detailed Budget'!$M$64 -> 12109.79 | F15: =D15+E15 -> 101870.79
A16: I | C16: Total Direct charges | D16: =SUM(D8:D15) -> 1077721 | E16: ='3. Detailed Budget'!M65 -> 272840.79 | F16: =D16+E16 -> 1350561.8
A17: J | C17: Total Indirect costs | D17: ='3. Detailed Budget'!L66 -> 304779 | E17: ='3. Detailed Budget'!M66 -> 77159 | F17: =D17+E17 -> 381938
A18: K | C18: Total Project Cost | D18: =SUM(D16:D17) -> 1382500 | E18: =SUM(E16:E17) -> 349999.79 | F18: =SUM(F16:F17) -> 1732499.8
A19: L | C19: Cost Share (if applicable) | D19: ='3. Detailed Budget'!P67 -> 901024 | E19: ='3. Detailed Budget'!Q67 -> 0 | F19: ='3. Detailed Budget'!R67 -> 901024
A21: * Line items amounts auto-fill from "Detailed Grant Budget Template," Tab 2. Addition and/or subtraction of example budget categories in Tab 2 may effect auto-fill function. Please make sure your line items above match those on Tab 2.
A26: * Cost-share changes should not be represented on the Summary Amendment Budget.

Sheet 3. Detailed Budget
E1: POA OVERVIEW LINE-ITEM COST AMENDMENT BUDGET (REV Dec 2025)
E2: Partners of the Americas | J2: Project Title
L3: 100,000 Strong in the Americas
E4: Cooperative Agreement Duration: 44 months (April 2023-Dec 2026) | J4: Project duration
E5: *Key personnel
H6: Unit Cost | L6: Current WHA Budget | M6: Changes (+ / -) | N6: New WHA Budget | P6: Current Cost-Share Budget | Q6: Cost-Share Changes (+ / -) | R6: New Cost-Share Budget | T6: NEW Program Total
H7: Unit | I7: Number | J7: Amount | K7: Rate
A8: DOS Grant Funds | B8: POA Cost Share Funds | C8: Activity (Budget) Code | D8: Account Code | E8: A | G8: Personnel | H8: months or years | J8: salary (monthly) | K8: % effort for Personnel ONLY
E9: A.1 | G9: US-Based personnel
A10: DOS2004 | B10: N/A | C10: PERSNL | D10: 50000 | E10: A.1.1 | G10: Senior Director | H10: months | I10: 12 | J10: 12777 | K10: 0.2 | M10: =ROUND((I10*J10)*K10,0) -> 30665 | N10: =L10+M10 -> 30665 | T10: =N10+R10 -> 30665
A11: DOS2004 | B11: N/A | C11: PERSNL | D11: 50000 | E11: A.1.2 | G11: Director of Public-Private Partnerships* | H11: months | I11: 25 | J11: 8133 | K11: 1 | L11: =ROUND((30*J11)*K11,0) -> 243990 | M11: =ROUND((I11*J11)*K11,0)-L11 -> -40665 | N11: =L11+M11 -> 203325 | T11: =N11+R11 -> 203325
A12: DOS2004 | B12: N/A | C12: PERSNL | D12: 50000 | E12: A.1.3 | G12: Program Director* | H12: months | I12: 8 | J12: 7750 | K12: 1 | L12: =ROUND((I12*J12)*K12,0) -> 62000 | N12: =L12 -> 62000
A13: DOS2004 | B13: N/A | C13: PERSNL | D13: 50000 | I13: 24 | J13: 9166 | K13: 1 | L13: =ROUND((22*J12)*K13,0) -> 170500 | M13: =ROUND((I13*J13)*K13,0)-L13 -> 49484 | N13: =L13+M13 -> 219984
A14: DOS2004 | B14: N/A | C14: PERSNL | D14: 50000 | I14: 12 | J14: 9916 | K14: 1 | M14: =ROUND((I14*J14)*K14,0) -> 118992 | N14: =M14 -> 118992 | T14: =SUM(N12,N13:N14) -> 400976
A15: DOS2004 | B15: DOS2004CS | C15: PERSNL | D15: 50000 | E15: A.1.4 | G15: Associate Director | H15: months | I15: 21 | J15: 7000 | K15: 0.8 | L15: =ROUND(((I15*J15)*K15)*(15/21),0) -> 84000 | N15: =L15+M15 -> 84000 | P15: 33600 | R15: =ROUND(((I15*J15)*K15)*(6/21),0) -> 33600 | T15: =N15+R15 -> 117600
A16: DOS2004 | B16: N/A | C16: PERSNL | D16: 50000 | E16: A.1.5 | G16: Program Officer | H16: months | I16: 21 | J16: 4460 | K16: 1 | L16: =ROUND((30*J16)*K16,0) -> 133800 | M16: =ROUND((I16*J16)*K16,0)-L16 -> -40140 | N16: =L16+M16 -> 93660 | T16: =N16+R16 -> 93660
A17: DOS2004 | B17: DOS2004CS | C17: PERSNL | D17: 50000 | E17: A.1.6 | G17: Communications Officer | H17: months | I17: 21 | J17: 4853 | K17: 0.6 | L17: =ROUND((30*J17)*0.5,0) -> 72795 | M17: =ROUND((I17*J17)*K17,0)-L17 -> -11647 | N17: =L17+M17 -> 61148 | P17: 18927 | R17: =P17 -> 18927 | T17: =N17+R17 -> 80075
A18: N/A | B18: DOS2004CS | C18: PERSNL | D18: 50000 | E18: A.1.7 | G18: Program/MEL Officer | H18: months | I18: 21 | J18: 3618 | K18: 0.3 | P18: 32562 | R18: =P18 -> 32562
A19: DOS2004 | B19: N/A | C19: PERSNL | D19: 50000 | I19: 11 | J19: 4750 | K19: 0.7 | M19: =ROUND((I19*J19)*K19,0) -> 36575 | N19: =M19 -> 36575
A20: DOS2004 | B20: N/A | C20: PERSNL | D20: 50000 | I20: 12 | J20: 5500 | K20: 0.7 | M20: =ROUND((I20*J20)*K20,0) -> 46200 | N20: =L20+M20 -> 46200 | T20: =SUM(R18,N19:N20) -> 115337
E21: Subtotal Personnel | L21: =SUM(L10:L20) -> 767085 | M21: =SUM(M10:M20) -> 189464 | N21: =SUM(N10:N20) -> 956549 | P21: =SUM(P10:P20) -> 85089 | R21: =SUM(R10:R20) -> 85089 | T21: =SUM(T10:T20) -> 1041638
E22: B | G22: Fringe Benefits
A23: DOS2004 | B23: DOS2004CS | C23: FRINGE | D23: 50900 | E23: B.1 | G23: US-Based Personnel Fringe Benefits | K23: 0.2347 | L23: =ROUND(L21*K23,0) -> 180035 | M23: =ROUND(M21*K23,0) -> 44467 | N23: =L23+M23 -> 224502 | P23: 19970 | R23: =ROUND(R21*K23,0) -> 19970 | T23: =N23+R23 -> 244472
E24: Subtotal Fringe Benefits | L24: =SUM(L23) -> 180035 | M24: =SUM(M23) -> 44467 | N24: =SUM(N23) -> 224502 | P24: =SUM(P23) -> 19970 | R24: =SUM(R23) -> 19970 | T24: =SUM(T23) -> 244472
E25: C | G25: Travel | H25: # people | I25: # trips/or days | J25: unit Cost
E26: C.1 | G26: Staff Travel
A27: DOS2004 | B27: DOS2004CS | C27: STFTRAVEL | D27: 86040 | E27: C.1.1 | G27: International Round Trip Airfare | H27: 1 | I27: 12 | J27: 1000 | L27: 7000 | N27: =L27+M27 -> 7000 | P27: 5000 | R27: =H27*5*J27 -> 5000 | T27: =N27+R27 -> 12000
A28: DOS2004 | B28: DOS2004CS | C28: STFCN DIEM | D28: 86050 | E28: C.1.2 | G28: International M&IE | H28: 1 | I28: 52 | J28: 80 | L28: 2480 | N28: =L28+M28 -> 2480 | P28: 1840 | R28: =H28*23*J28 -> 1840 | T28: =N28+R28 -> 4320
A29: DOS2004 | B29: DOS2004CS | C29: LODGING | D29: 86030 | E29: C.1.3 | G29: International Lodging | H29: 1 | I29: =I28 -> 52 | J29: 200 | L29: 6200 | N29: =L29+M29 -> 6200 | P29: 4600 | R29: =H29*23*J29 -> 4600 | T29: =N29+R29 -> 10800
A30: DOS2004 | B30: DOS2004CS | C30: LOCAL TRVL | D30: 86000 | E30: C.1.4 | G30: International Local Transportation | H30: 1 | I30: =I28 -> 52 | J30: 30 | L30: 930 | N30: =L30+M30 -> 930 | P30: 690 | R30: =H30*23*J30 -> 690 | T30: =N30+R30 -> 1620
A31: DOS2004 | B31: N/A | C31: STFTRAVEL | D31: 86040 | E31: C.1.5 | G31: Domestic Round Trip Airfare | H31: 1 | I31: 13 | J31: 500 | L31: 6500 | N31: =L31+M31 -> 6500 | T31: =N31+R31 -> 6500
A32: DOS2004 | B32: N/A | C32: STFCN DIEM | D32: 86050 | E32: C.1.6 | G32: Domestic M&IE | H32: 1 | I32: 60 | J32: 55 | L32: 3300 | N32: =L32+M32 -> 3300 | T32: =N32+R32 -> 3300
A33: DOS2004 | B33: N/A | C33: LODGING | D33: 86030 | E33: C.1.7 | G33: Domestic Lodging | H33: 1 | I33: =I32 -> 60 | J33: 98 | L33: 5880 | N33: =L33+M33 -> 5880 | T33: =N33+R33 -> 5880
A34: DOS2004 | B34: N/A | C34: LOCAL TRVL | D34: 86000 | E34: C.1.8 | G34: Domestic Local Transportation | H34: 1 | I34: =I32 -> 60 | J34: 50 | L34: 3000 | N34: =L34+M34 -> 3000 | T34: =N34+R34 -> 3000
E35: Subtotal Travel | L35: =SUM(L27:L34) -> 35290 | N35: =SUM(N27:N34) -> 35290 | P35: =SUM(P27:P34) -> 12130 | R35: =SUM(R27:R34) -> 12130 | T35: =SUM(T27:T34) -> 47420
E36: D | G36: Equipment (> $5,000 per unit ) | H36: unit | I36: # units | J36: unit cost
E37: E | G37: Supplies (< $5,000 per unit) | H37: unit | I37: # units | J37: unit cost
A38: DOS2004 | B38: N/A | C38: SUPPLIES | D38: 82420 | E38: E.1 | G38: Tablet for In-Person Innovation Network Sign-ups | H38: unit | I38: 2 | J38: 275 | L38: =I38*J38 -> 550 | N38: =L38-M38 -> 550 | T38: =N38+R38 -> 550
E39: Subtotal Supplies | L39: =SUM(L38) -> 550 | N39: =SUM(N38) -> 550 | T39: =SUM(T38) -> 550
E40: F | G40: Contractual (Subrecipients, Subcontracts, and Consultant fees)
E41: F.1 | G41: Consultants and Contracts
A42: DOS2004 | B42: N/A | C42: COMM | D42: 81010 | E42: F.1.1 | G42: Website & Digital Communications Specialist | H42: months | I42: 3 | J42: 4000 | L42: 5000 | M42: =N42-L42 -> 7000 | N42: =I42*J42 -> 12000 | T42: =N42+R42 -> 12000
A43: DOS2004 | B43: N/A | C43: CONSULT | D43: 81000 | E43: F.1.2 | G43: Applications Coordinator | H43: months | I43: 6 | J43: =N43/I43 -> 3300 | L43: 0 | M43: 19800 | N43: =L43+M43 -> 19800 | T43: =N43+R43 -> 19800
E44: Subtotal Contractual | L44: =SUM(L42:L43) -> 5000 | M44: =SUM(M42:M43) -> 26800 | N44: =SUM(N42:N43) -> 31800 | T44: =SUM(T42:T43) -> 31800
E45: G | G45: Construction | H45: unit | I45: # units | J45: unit cost
E46: H | G46: Other Direct Costs
A47: DOS2004 | B47: DOS2004CS | C47: MATL | D47: 90450 | E47: H.1 | G47: Outreach/Branded Materials | H47: bulk | I47: 344.847 | J47: 12.42 | L47: 4041 | N47: =L47+M47 -> 4041 | P47: 242 | R47: =P47+Q47 -> 242 | T47: =N47+R47 -> 4283
A48: DOS2004 | B48: N/A | C48: GRANTSMGMT | D48: 89400 | E48: H.4 | G48: Grants Management System | H48: months | I48: 44 | J48: =N48/I48 -> 589.07159 | L48: 17000 | M48: 8919.15 | N48: =L48+M48 -> 25919.15 | T48: =N48+R48 -> 25919.15
A49: N/A | B49: DOS2004CS | C49: NETWORK | D49: 89400 | E49: H.5 | G49: Network Management System | H49: months | I49: 30 | J49: 900 | P49: 27000 | R49: =P49+Q49 -> 27000 | T49: =N49+R49 -> 27000
A50: DOS2004 | B50: N/A | C50: MONEVAL | D50: 81015 | E50: H.6 | G50: Data Tracking & Collection (M&E) | H50: hours | I50: 28 | J50: 110 | L50: 3520 | N50: =L50+M50 -> 3520 | T50: =N50+R50 -> 3520
A51: DOS2004 | B51: N/A | C51: SUBSCRIPT | D51: 89400 | E51: H.7 | G51: Platform Subscriptions | H51: months | I51: 44 | J51: 152.06 | L51: 3500 | M51: =N51-L51 -> 3190.64 | N51: =I51*J51 -> 6690.64 | T51: =N51+R51 -> 6690.64
E52: H.8 | G52: 100K Capacity Building and Best Practices Workshop
A53: N/A | B53: DOS2004CS | C53: VENUE | D53: 87000 | E53: H.8.1 | G53: Space Rental | H53: venue | I53: 1 | J53: 1000 | P53: 1000 | R53: =P53+Q53 -> 1000 | T53: =N53+R53 -> 1000
A54: N/A | B54: DOS2004CS | C54: PRINT | D54: 85300 | E54: H.8.2 | G54: Printed Materials | H54: events | I54: 1 | J54: 200 | P54: 200 | R54: =P54+Q54 -> 200 | T54: =N54+R54 -> 200
A55: N/A | B55: DOS2004CS | C55: WORKMEAL | D55: 87010 | E55: H.8.3 | G55: Working Meals | H55: persons | I55: =I53*150 -> 150 | J55: 80 | P55: 3750 | R55: =P55+Q55 -> 3750 | T55: =N55+R55 -> 3750
A56: N/A | B56: DOS2004CS | C56: EQUIPRENT | D56: 87000 | E56: H.8.4 | G56: Audio-Visual Equipment Rental | H56: bulk | I56: 1 | J56: 200 | P56: 200 | R56: =P56+Q56 -> 200 | T56: =N56+R56 -> 200
E57: H.9 | G57: Conference Registrations
A58: DOS2004 | B58: N/A | C58: REGISTRN | D58: 87000 | E58: H.9.1 | G58: International Conference Registration Fees | H58: events | I58: 4 | J58: 450 | L58: 1800 | N58: =L58+M58 -> 1800 | T58: =N58+R58 -> 1800
A59: DOS2004 | B59: N/A | C59: REGISTRN | D59: 87000 | E59: H.9.2 | G59: U.S. Conference Registration Fees | H59: events | I59: 12 | J59: 825 | L59: 9900 | N59: =L59+M59 -> 9900 | T59: =N59+R59 -> 9900
E60: H.11 | G60: 100K Student Support
A61: N/A | B61: DOS2004CS | C61: PARTTRAVEL | D61: 86000 | E61: H.11.2 | G61: Participant Travel Support | H61: persons | I61: 2 | J61: 1000 | P61: 2000 | R61: =P61+Q61 -> 2000 | T61: =N61+R61 -> 2000
E62: H.12 | G62: Innovation Grants
A63: DOS2004 | B63: DOS2004CS | C63: GRANTS | D63: 89000 | E63: H.12.1 | G63: Innovation Grants | H63: grants | I63: =T63/J63 -> 31.97772 | J63: 25000 | L63: 50000 | N63: =L63+M63 -> 50000 | P63: 749443 | R63: =P63+Q63 -> 749443 | T63: =N63+R63 -> 799443
E64: Subtotal Other Direct Costs | L64: =SUM(L47:L63) -> 89761 | M64: =SUM(M47:M63) -> 12109.79 | N64: =SUM(N47:N63) -> 101870.79 | P64: =SUM(P47:P63) -> 783835 | R64: =SUM(R47:R63) -> 783835 | T64: =SUM(T47:T63) -> 885705.79
E65: I | G65: Total Direct Costs | L65: =L21+L24+L35+L44+L64+L39 -> 1077721 | M65: =M21+M24+M35+M44+M64+M39 -> 272840.79 | N65: =N21+N24+N35+N44+N64+N39 -> 1350561.8 | P65: =P21+P24+P35+P44+P64+P39 -> 901024 | R65: =R21+R24+R35+R44+R64+R39 -> 901024 | T65: =T21+T24+T35+T44+T64+T39 -> 2251585.8
A66: DOS2004 | B66: N/A | C66: IDC | D66: 94050 | E66: J | G66: Indirect Costs | H66: 0.2828 | L66: =ROUNDDOWN(L65*H66,0) -> 304779 | M66: =ROUNDDOWN(M65*H66,0) -> 77159 | N66: =ROUNDDOWN(N65*H66,0) -> 381938 | T66: =N66+R66 -> 381938
E67: K | G67: Total Project Cost | L67: =SUM(L65:L66) -> 1382500 | M67: =SUM(M65:M66) -> 349999.79 | N67: =SUM(N65:N66) -> 1732499.8 | P67: =SUM(P65:P66) -> 901024 | R67: =SUM(R65:R66) -> 901024 | T67: =N67+R67 -> 2633523.8
