Workbook

Sheet SF424
B1: Application for Federal Assistance SF-424
B2: * 1.Type of Submission: | F2: * 2. Type of Application | H2: * If Revision, select appropriate letter(s):
B3: Preapplication | F3: New | H3: Response to Issues Letter
B4: Application | F4: Continuation | H4: * Other (Specify)
B5: Changed/Corrected Application | F5: Revision
B7: * 3. Date Received: | F7: 4. Applicant Identifier:
B8: Completed by Grants.gov upon submission.
B10: 5a. Federal Entity Identifier: | F10: * 5b. Federal Award Identifier:
B13: State Use Only:
B15: 6. Date Received by State: | F15: 7. State Application Identifier:
B17: 8. APPLICANT INFORMATION:
B19: * a. Legal Name: | C19: Catholic Relief Services - United States Conference of Catholic Bishops
B21: * b. Employer/Taxpayer Identification Number (EIN/TIN): | F21: * c. Organizational DUNS:
B22: 13-5563422 | F22: 68205541
B24: d. Address:
B26: * Street 1: | C26: 228 West Lexington Street
B28: Street 2:
B30: * City: | C30: Baltimore
B32: County:
B34: * State: | C34: Maryland
B36: Province:
B38: * Country: | C38: USA
B40: * Zip / Postal Code: | C40: 21201
B42: e. Organization Unit:
B44: Department Name: | F44: Division Name:
B47: f. Name and contact information of person to be contacted on matters involving this application:
B49: Prefix: | C49: Ms. | F49: First Name: | G49: Chelsea
B51: Middle Name:
B53: Last Name: | C53: Treadwell
B55: Suffix:
B58: Title: | C58: Public Donor Liaison - Asia
B60: Organizational Affiliation:
B61: Catholic Relief Services
B64: * Telephone Number: | C64: 410-951-7468 | G64: Fax Number:
B67: * Email: | C67: chelsea.treadwell@crs.org
B70: Application for Federal Assistance SF-424
B71: 9. Type of Applicant 1: Select Applicant Type:
B72: M: Nonprofit with 501C3 IRS Status (Other than Institution of Higher Education)
B74: Type of Applicant 2: Select Applicant Type:
B77: Type of Applicant 3: Select Applicant Type:
B80: * Other (specify):
B83: * 10. Name of Federal Agency:
B84: US Department of State Bureau of Population Refugees and Migration
B86: 11. Catalog of Federal Domestic Assistance Number:
B87: 19.519
B88: CFDA Title:
B89: Overseas Refugee Assistance Program for Near East and South Asia
B91: * 12. Funding Opportunity Number:
B92: PRM-PRMOAPNE-14-006-049311 / PRM-PRMOAPNE-14-006
B93: * Title:
B96: 13. Competition Identification Number:
B98: Title:
B99: FY 2014 Funding Opportunity Announcement for NGO Programs Benefiting Sri Lankan Refugees in India
B101: 14. Areas Affected by Project (Cities, Counties, States, etc.):
B104: * 15. Descriptive Title of Applicant's Project:
B105: Combating Trafficking in Persons (TIP) though Victim-Centered Approaches in India
B107: Attach supporting documents as specified in agency instructions.
... B113: 16. Congressional Districts Of:
B114: * a. Applicant | C114: MD-7 | F114: * b. Program/Project | H114: 0
B116: Attach an additional list of Program/Project Congressional Districts if needed.
B118: 17. Proposed Project:
B119: * a. Start Date: | C119: 42277 | F119: * b. End Date: | G119: 43372
B121: 18. Estimated Funding ($):
B124: * a. Federal | C124: =SF424A!F16 -> 617282.95
B126: * b. Applicant | C126: =SF424A!G16 -> 0
B128: * c. State | C128: 0
B130: * d. Local | C130: 0
B132: * e. Other | C132: 0
B134: * f. Program Income | C134: 0
B136: * g. TOTAL | C136: =C124+C126+C128+C132 -> 617282.95
B138: * 19. Is Application Subject to Review By State Under Executive Order 12372 Process?
B139: a. This application was made available to the State under the Executive Order 12372 Process for review on:
B140: b. Program is subject to E.O. 12372 but has not been selected by the State for review.
B141: c. Program is not covered by E.O. 12372.
B143: * 20. Is the Applicant Delinquent On Any Federal Debt? (If "Yes", provide explanation.)
B144: Yes | C144: No
B146: 21. *By signing this application, I certify (1) to the statements contained in the list of certifications** and (2) that the statements herein are true, complete and accurate to the best of my knowledge. I also provide the required assurances** and agree to comply with any resulting terms if I accept an award. I am aware that any false, fictitious, or fraudulent statements or claims may subject me to criminal, civil, or administrative penalties. (U.S. Code, Title 218, Section 1001)
B148: ** I AGREE
B150: ** The list of certifications and assurances, or an internet site where you may obtain this list, is contained in the announcement or agency specific instructions.
B152: Authorized Representative:
B155: Prefix: | C155: Mr. | F155: * First Name: | G155: Tony
B157: Middle Name:
B159: * Last Name: | C159: Castleman
B161: Suffix:
B164: * Title: | C164: Country Representative, India
B167: * Telephone Number: | C167: +91-9810880281 | G167: Fax Number:
B170: * Email: | C170: tony.castleman@crs.org
B173: * Signature of Authorized Representative: | H173: * Date Signed: | I173: 42128

Sheet SF424A
B1: Standard Form 424A
B2: OMB Approval No. 0348-0044
B4: Budget Information - Non-Construction Programs
A6: SECTION A - BUDGET SUMMARY
A7: Grant Program | C7: Catalog of Federal | D7: Estimated Unobligated Funds | F7: New or Revised Budget
A8: Function | C8: Domestic Assistance
A9: or Activity | C9: Number | D9: Federal | E9: Non-Federal | F9: Federal | G9: Non-Federal | H9: Total
A10: {a} | C10: {b} | D10: {c} | E10: {d} | F10: {e} | G10: {f} | H10: {g}
A11: 1 | B11: Anti-Trafficking Program | C11: 19.019 | F11: ='Budget Summary'!L19 -> 617282.95 | G11: ='Budget Summary'!M19 -> 0 | H11: =F11+G11 -> 617282.95
A12: 2 | H12: =F12+G12 -> 0
A13: 4 | H13: =F13+G13 -> 0
A14: 3 | H14: =F14+G14 -> 0
A15: 4 | H15: =F15+G15 -> 0
A16: 5 | B16: TOTALS | D16: =SUM(D11:D14) -> 0 | E16: =SUM(E11:E14) -> 0 | F16: =SUM(F11:F15) -> 617282.95 | G16: =SUM(G11:G15) -> 0 | H16: =SUM(H11:H15) -> 617282.95
A17: SECTION B - BUDGET CATEGORIES
C18: Grant Program, Function or Activity | H18: Total
A19: 6. | B19: Object Class Categories | C19: {1} | D19: {2} | E19: {3} | F19: {4} | G19: {5} | H19: {6}
A20: a. Personnel | B20: a. Personnel | C20: ='Budget Summary'!N6 -> 141278.49 | H20: =SUM(C20:G20) -> 141278.49
A21: b. Fringe Benefits | B21: b. Fringe Benefits | C21: ='Budget Summary'!N7 -> 64661.997 | H21: =SUM(C21:G21) -> 64661.997
A22: c. Travel | B22: c. Travel | C22: ='Budget Summary'!N8 -> 23907.682 | H22: =SUM(C22:G22) -> 23907.682
A23: d. Equipment | B23: d. Equipment | C23: 0 | H23: =SUM(C23:G23) -> 0
A24: e. Supplies | B24: e. Supplies | C24: ='Budget Summary'!N10 -> 18370 | H24: =SUM(C24:G24) -> 18370
A25: f. Contractual | B25: f. Contractual | C25: ='Budget Summary'!N11 -> 199312.63 | H25: =SUM(C25:G25) -> 199312.63
A26: g. Construction | B26: g. Construction | C26: 0 | H26: =SUM(C26:G26) -> 0
A27: h. Other | B27: h. Other | C27: ='Budget Summary'!N13 -> 34721.5 | H27: =SUM(C27:G27) -> 34721.5
A28: i. Total Direct Charges (sum of 6a-6h) | B28: i. Total Direct Charges (sum of 6a-6h) | C28: =SUM(C20:C27) -> 482252.31 | H28: =SUM(C28:G28) -> 482252.31
A29: j. Indirect Charges | B29: j. Indirect Charges | C29: ='Budget Summary'!N17 -> 135030.65 | H29: =SUM(C29:G29) -> 135030.65
A30: k. TOTALS (sum of 6i and 6j) | B30: k. TOTALS (sum of 6i and 6j) | C30: =C28+C29 -> 617282.95 | D30: =D28+D29 -> 0 | E30: =E28+E29 -> 0 | F30: =F28+F29 -> 0 | G30: =G28+G29 -> 0 | H30: =SUM(C30:G30) -> 617282.95
A32: 7. | B32: Program Income | C32: 0 | D32: 0 | E32: 0 | F32: 0 | H32: 0
A34: Previous Edition Usable | D34: Authorized for Local Reproduction | G34: Standard Form 424 A (Rev. 4-92)
A37: Standard Form 424A (cont'd)
A38: SECTION C - NON-FEDERAL RESOURCES
A39: (a) Grant Program | E39: (b) Applicant | F39: (c) State | G39: (d) Other Sources | H39: (e) TOTALS
A40: 8. | B40: Anti-Trafficking Program | E40: ='Budget Summary'!M19 -> 0 | H40: =SUM(E40:G40) -> 0
A41: 9. | H41: =SUM(E41:G41) -> 0
A42: 10. | H42: =SUM(E42:G42) -> 0
A43: 11. | H43: =SUM(E43:G43) -> 0
A44: 12. | B44: TOTAL (sum of lines 8 - 11) | E44: =SUM(E40:E43) -> 0 | F44: =SUM(F40:F43) -> 0 | G44: =SUM(G40:G43) -> 0 | H44: =SUM(H40:H43) -> 0
A45: SECTION D - FORCASTED CASH NEEDS
D46: Total for 1st Year | E46: 1st Quarter | F46: 2nd Quarter | G46: 3rd Quarter | H46: 4th Quarter
A47: 13. | B47: Federal | D47: ='Budget Summary'!C19 -> 236149.22 | E47: =(SUM('Budget Summary'!C6:C10,'Budget Summary'!C13)*20%+'Budget Summary'!C11*30%)*1.1788 -> 52029.511 | F47: =(SUM('Budget Summary'!$C$6:$C$10,'Budget Summary'!$C$13)*25%+'Budget Summary'!$C$11*30%)*1.1788 -> 58636.557 | G47: =(SUM('Budget Summary'!$C$6:$C$10,'Budget Summary'!$C$13)*25%+'Budget Summary'!$C$11*30%)*1.1788 -> 58636.557 | H47: =(SUM('Budget Summary'!$C$6:$C$10,'Budget Summary'!$C$13)*30%+'Budget Summary'!$C$11*10%)*1.1788 -> 48176.049
A48: 14. | B48: Non-federal | D48: ='Budget Summary'!D19 -> 0 | E48: =(SUM('Budget Summary'!D6:D10,'Budget Summary'!D13)*20%+'Budget Summary'!D11*30%)*1.1788 -> 0 | F48: =(SUM('Budget Summary'!$D$6:$D$10,'Budget Summary'!$D$13)*25%+'Budget Summary'!$D$11*30%)*1.1788 -> 0 | G48: =(SUM('Budget Summary'!$D$6:$D$10,'Budget Summary'!$D$13)*25%+'Budget Summary'!$D$11*30%)*1.1788 -> 0 | H48: =(SUM('Budget Summary'!$D$6:$D$10,'Budget Summary'!$D$13)*30%+'Budget Summary'!$D$11*10%)*1.1788 -> 0
A49: 15. | B49: TOTAL (sum of lines 13 and 14) | D49: =SUM(D47:D48) -> 236149.22 | E49: =SUM(E47:E48) -> 52029.511 | F49: =SUM(F47:F48) -> 58636.557 | G49: =SUM(G47:G48) -> 58636.557 | H49: =SUM(H47:H48) -> 48176.049
A50: SECTION E - BUDGET ESTIMATES OF FEDERAL FUNDS NEEDED FOR BALANCE OF THE PROJECT
A51: (a) Grant Program | E51: Future Funding Periods (Years)
E52: (b) First | F52: (c) Second | G52: (d) Third | H52: (e) Fourth
A53: 16. | B53: =B40 -> Anti-Trafficking Program | E53: ='Budget Summary'!C19 -> 236149.22 | F53: ='Budget Summary'!F19 -> 289983.4 | G53: ='Budget Summary'!I19 -> 91150.333 | H53: 0
A54: 17.
A55: 18.
A56: 19.
A57: 20. | B57: TOTAL (sum of lines 16 - 19) | E57: =SUM(E53:E56) -> 236149.22 | F57: =SUM(F53:F56) -> 289983.4 | G57: =SUM(G53:G56) -> 91150.333 | H57: =SUM(H53:H56) -> 0
A58: SECTION F - OTHER BUDGET INFORMATION
A59: 21 | B59: Direct Charges (Federal only): | E59: 22. Indirect Charges (Federal only): | G59: Provisional
A60: 23 | B60: Remarks:
D62: Authorized for Local Reproduction | G62: Standard Form 424 A (Rev. 4-92) Page 2

Sheet Budget Summary
B2: PARTNERS OF THE AMERICAS
B3: SUMMARY BUDGET FOR MEXICO UNITED 2026
C4: Year 1 | F4: Year 2 | I4: Year 3 | L4: Total
B5: BUDGET SUMMARY CATEGORIES | C5: Grant | D5: Cost Share | E5: Total | F5: Grant | G5: Cost Share | H5: Total | I5: Grant | J5: Cost Share | K5: Total | L5: Grant | M5: Cost Share | N5: Total
B6: A. Personnel | C6: ='Line Item Budget'!L15 -> 54250 | D6: ='Line Item Budget'!M15 -> 0 | E6: =C6+D6 -> 54250 | F6: ='Line Item Budget'!R15 -> 59926.5 | G6: ='Line Item Budget'!S15 -> 0 | H6: =F6+G6 -> 59926.5 | I6: ='Line Item Budget'!X15 -> 27101.992 | J6: ='Line Item Budget'!Y15 -> 0 | K6: =I6+J6 -> 27101.992 | L6: ='Line Item Budget'!Z15 -> 141278.49 | M6: ='Line Item Budget'!AA15 -> 0 | N6: =L6+M6 -> 141278.49
B7: B. Fringe Benefits | C7: ='Line Item Budget'!L24 -> 24793.82 | D7: ='Line Item Budget'!M24 -> 0 | E7: =C7+D7 -> 24793.82 | F7: ='Line Item Budget'!R24 -> 27582.212 | G7: ='Line Item Budget'!S24 -> 0 | H7: =F7+G7 -> 27582.212 | I7: ='Line Item Budget'!X24 -> 12285.965 | J7: ='Line Item Budget'!Y24 -> 0 | K7: =I7+J7 -> 12285.965 | L7: ='Line Item Budget'!Z24 -> 64661.997 | M7: ='Line Item Budget'!AA24 -> 0 | N7: =L7+M7 -> 64661.997
B8: C. Travel | C8: ='Line Item Budget'!L38 -> 12429 | D8: ='Line Item Budget'!M38 -> 0 | E8: =C8+D8 -> 12429 | F8: ='Line Item Budget'!R38 -> 7883.58 | G8: ='Line Item Budget'!S38 -> 0 | H8: =F8+G8 -> 7883.58 | I8: ='Line Item Budget'!X38 -> 3595.1022 | J8: ='Line Item Budget'!Y38 -> 0 | K8: =I8+J8 -> 3595.1022 | L8: ='Line Item Budget'!Z38 -> 23907.682 | M8: ='Line Item Budget'!AA38 -> 0 | N8: =L8+M8 -> 23907.682
B9: D. Equipment
B10: E. Supplies | C10: ='Line Item Budget'!L48 -> 8550 | D10: ='Line Item Budget'!M48 -> 0 | E10: =C10+D10 -> 8550 | F10: ='Line Item Budget'!R48 -> 7440 | G10: ='Line Item Budget'!S48 -> 0 | H10: =F10+G10 -> 7440 | I10: ='Line Item Budget'!X48 -> 2380 | J10: ='Line Item Budget'!Y48 -> 0 | K10: =I10+J10 -> 2380 | L10: ='Line Item Budget'!Z48 -> 18370 | M10: ='Line Item Budget'!AA48 -> 0 | N10: =L10+M10 -> 18370
B11: F. Contractual and Subawards | C11: ='Line Item Budget'!L57 -> 72393.76 | D11: ='Line Item Budget'!M57 -> 0 | E11: =C11+D11 -> 72393.76 | F11: ='Line Item Budget'!R57 -> 103345.74 | G11: ='Line Item Budget'!S57 -> 0 | H11: =F11+G11 -> 103345.74 | I11: ='Line Item Budget'!X57 -> 23573.137 | J11: ='Line Item Budget'!Y57 -> 0 | K11: =I11+J11 -> 23573.137 | L11: ='Line Item Budget'!Z57 -> 199312.63 | M11: ='Line Item Budget'!AA57 -> 0 | N11: =L11+M11 -> 199312.63
B12: G. Construction
B13: H. Other Direct Costs | C13: ='Line Item Budget'!L89 -> 12075 | D13: ='Line Item Budget'!M89 -> 0 | E13: =C13+D13 -> 12075 | F13: ='Line Item Budget'!R89 -> 20371.5 | G13: ='Line Item Budget'!S89 -> 0 | H13: =F13+G13 -> 20371.5 | I13: ='Line Item Budget'!X89 -> 2275 | J13: ='Line Item Budget'!Y89 -> 0 | K13: =I13+J13 -> 2275 | L13: ='Line Item Budget'!Z89 -> 34721.5 | M13: ='Line Item Budget'!AA89 -> 0 | N13: =L13+M13 -> 34721.5
B15: I. Total Direct Costs | C15: ='Line Item Budget'!L90 -> 184491.58 | D15: ='Line Item Budget'!M90 -> 0 | E15: =C15+D15 -> 184491.58 | F15: ='Line Item Budget'!R90 -> 226549.53 | G15: ='Line Item Budget'!S90 -> 0 | H15: =F15+G15 -> 226549.53 | I15: ='Line Item Budget'!W90 -> 71211.197 | J15: ='Line Item Budget'!Y90 -> 0 | K15: =I15+J15 -> 71211.197 | L15: ='Line Item Budget'!Z90 -> 482252.31 | M15: =SUM(M6:M13) -> 0 | N15: =L15+M15 -> 482252.31
B17: J. Indirect Costs | C17: ='Line Item Budget'!L92 -> 51657.642 | D17: ='Line Item Budget'!M92 -> 0 | E17: =C17+D17 -> 51657.642 | F17: ='Line Item Budget'!R92 -> 63433.868 | G17: ='Line Item Budget'!S92 -> 0 | H17: =F17+G17 -> 63433.868 | I17: ='Line Item Budget'!X92 -> 19939.135 | J17: ='Line Item Budget'!Y92 -> 0 | K17: =I17+J17 -> 19939.135 | L17: ='Line Item Budget'!Z92 -> 135030.65 | M17: ='Line Item Budget'!AA92 -> 0 | N17: =L17+M17 -> 135030.65
B19: K. Total Costs | C19: =C15+C17 -> 236149.22 | D19: =D15+D17 -> 0 | E19: =E15+E17 -> 236149.22 | F19: =F15+F17 -> 289983.4 | G19: =G15+G17 -> 0 | H19: =H15+H17 -> 289983.4 | I19: =I15+I17 -> 91150.333 | J19: =J15+J17 -> 0 | ... N19: =N15+N17 -> 617282.95
B24: SAMPLE

Sheet Line Item Budget
A1: Entity: | B1: P
A2: Program/Dept.: | B2: 20200 | E2: SAMPLE
A3: Funder-Grant: | B3: DOS452 | E3: *Key Personnel
E4: PARTNERS OF THE AMERICAS - MEXICO UNITED 2026
A5: Activity Code | B5: Object Code | C5: Country Code | D5: Office Code | E5: All costs in US$ | F5: Year 1 | N5: Year 2 | T5: Year 3 | Z5: Total
E6: Budget Line Items | F6: No. | G6: Unit Type | H6: Freq. | I6: % | J6: Rate | K6: Total | L6: DRL | M6: Cost Share | N6: No. | O6: Freq. | P6: Rate | Q6: Total | R6: DRL | S6: Cost Share | T6: No. | U6: Freq. | V6: Rate | W6: Total | X6: DRL | Y6: Cost Share | Z6: DRL | AA6: Cost Share | AB6: Grand Total
E7: A. Personnel
E8: A.1 Field Staff Salaries
A9: PERSNL-CD | B9: 70000 (Personnel)/ 81000 (Consultant) | C9: MEX | D9: MEX | E9: A.1.1 Program Coordinator (100%)* | F9: 1 | G9: Month | H9: 12 | I9: 1 | M9: =K9-L9 -> 0 | N9: =F9 -> 1 | O9: =H9 -> 12 | P9: =J9*1.035 -> 0 | Q9: =N9*P9*O9*I9 -> 0 | R9: =Q9 -> 0 | S9: =Q9-R9 -> 0 | T9: =N9 -> 1 | U9: 6 | V9: =P9*1.035 -> 0 | W9: =T9*V9*U9*I9 -> 0 | X9: =W9 -> 0 | Y9: =W9-X9 -> 0 | Z9: =L9+R9+X9 -> 0 | AA9: =M9+S9+Y9 -> 0 | AB9: =Z9+AA9 -> 0
A10: PERSNL-PS | B10: 70000 (Personnel)/ 81000 (Consultant) | C10: MEX | D10: MEX | E10: A.1.2 Program Specialist (50%) | F10: 1 | G10: Month | H10: 10 | I10: 0.5 | M10: 0 | N10: =F10 -> 1 | O10: 12 | P10: =J10*1.035 -> 0 | Q10: =N10*P10*O10*I10 -> 0 | R10: =Q10 -> 0 | S10: 0 | T10: =N10 -> 1 | U10: 4 | V10: =P10*1.035 -> 0 | W10: =T10*V10*U10*I10 -> 0 | X10: =W10 -> 0 | Y10: 0 | Z10: =L10+R10+X10 -> 0 | AA10: =M10+S10+Y10 -> 0 | AB10: =Z10+AA10 -> 0
A11: PERSNL-PA | B11: 70000 (Personnel)/ 81000 (Consultant) | C11: MEX | D11: MEX | E11: A.1.3 Program Assistant (50%) | F11: 1 | G11: Month | H11: 10 | I11: 0.5 | M11: 0 | N11: =F11 -> 1 | O11: 12 | P11: =J11*1.035 -> 0 | Q11: =N11*P11*O11*I11 -> 0 | R11: =Q11 -> 0 | S11: 0 | T11: =N11 -> 1 | U11: 4 | V11: =P11*1.035 -> 0 | W11: =T11*V11*U11*I11 -> 0 | X11: =W11 -> 0 | Y11: 0 | Z11: =L11+R11+X11 -> 0 | AA11: =M11+S11+Y11 -> 0 | AB11: =Z11+AA11 -> 0
A12: PERSNL-F&A | B12: 70000 (Personnel)/ 81000 (Consultant) | C12: MEX | D12: MEX | E12: A.1.4 Administration and Finance Officer (50%) | F12: 1 | G12: Month | H12: 10 | I12: 0.5 | M12: =K12-L12 -> 0 | N12: =F12 -> 1 | O12: 12 | P12: =J12*1.035 -> 0 | Q12: =N12*P12*O12*I12 -> 0 | R12: =Q12 -> 0 | S12: =Q12-R12 -> 0 | T12: =N12 -> 1 | U12: 4 | V12: =P12*1.035 -> 0 | W12: =T12*V12*U12*I12 -> 0 | X12: =W12 -> 0 | Y12: =W12-X12 -> 0 | Z12: =L12+R12+X12 -> 0 | AA12: =M12+S12+Y12 -> 0 | AB12: =Z12+AA12 -> 0
E13: A.2 HQ Staff Salaries
A14: PERSNL | B14: Timesheets | C14: 0 | D14: 0 | E14: A.2.1 Program Manager (HQ) (20%) | F14: 1 | G14: Month | H14: 12 | I14: 0.2 | M14: =K14-L14 -> 0 | N14: 1 | O14: =H14 -> 12 | P14: =J14*1.035 -> 0 | Q14: =N14*P14*O14*I14 -> 0 | R14: =Q14 -> 0 | S14: =Q14-R14 -> 0 | T14: 1 | U14: 6 | V14: =P14*1.035 -> 0 | W14: =T14*V14*U14*I14 -> 0 | X14: =W14 -> 0 | Y14: =W14-X14 -> 0 | Z14: =L14+R14+X14 -> 0 | AA14: =M14+S14+Y14 -> 0 | AB14: =Z14+AA14 -> 0
E15: Subtotal Personnel | K15: 54250 | L15: 54250 | M15: 0 | Q15: 59926.5 | R15: 59926.5 | S15: 0 | W15: 27101.992 | X15: 27101.992 | Y15: 0 | Z15: 141278.49 | AA15: 0 | AB15: 141278.49
E16: B. Fringe Benefits
E17: B.1 HQ Fringe Benefits
A18: FRINGE | B18: Timesheets | C18: 0 | D18: 0 | E18: B.1.1 U.S.-Based Personnel Fringe Benefits | G18: %/ Month | H18: 12 | I18: 0.2181 | J18: =J14 -> 0 | K18: =K14*I18 -> 0 | L18: =K18 -> 0 | M18: 0 | O18: =H18 -> 12 | P18: =P14 -> 0 | Q18: =Q14*I18 -> 0 | R18: =Q18 -> 0 | S18: =Q18-R18 -> 0 | U18: 6 | V18: =V14 -> 0 | W18: =W14*I18 -> 0 | X18: =W18 -> 0 | Y18: =W18-X18 -> 0 | Z18: =L18+R18+X18 -> 0 | AA18: =M18+S18+Y18 -> 0 | AB18: =Z18+AA18 -> 0
E19: B.2 Field Fringe Benefits
A20: FRINGE-MX | B20: 70015 | C20: MEX | D20: MEX | E20: B.2.1 Program Coordinator (100%) | G20: %/ Month | H20: =H9 -> 12 | I20: 0.5084 | J20: =J9 -> 0 | K20: =K9*I20 -> 0 | L20: =K20 -> 0 | M20: 0 | O20: 12 | P20: =P9 -> 0 | Q20: =Q9*I20 -> 0 | R20: =Q20 -> 0 | S20: =Q20-R20 -> 0 | U20: 4 | V20: =V9 -> 0 | W20: =W9*I20 -> 0 | X20: =W20 -> 0 | Y20: =W20-X20 -> 0 | Z20: =L20+R20+X20 -> 0 | AA20: =M20+S20+Y20 -> 0 | AB20: =Z20+AA20 -> 0
A21: FRINGE-MX | B21: 70015 | C21: MEX | D21: MEX | E21: B.2.2 Program Specialist (50%) | G21: %/ Month | H21: =H10 -> 10 | I21: 0.5084 | J21: =J10 -> 0 | K21: =K10*I21 -> 0 | L21: =K21 -> 0 | M21: 0 | O21: 12 | P21: =P10 -> 0 | Q21: =Q10*I21 -> 0 | R21: =Q21 -> 0 | S21: =Q21-R21 -> 0 | U21: 4 | V21: =V10 -> 0 | W21: =W10*I21 -> 0 | X21: =W21 -> 0 | Y21: =W21-X21 -> 0 | Z21: =L21+R21+X21 -> 0 | AA21: =M21+S21+Y21 -> 0 | AB21: =Z21+AA21 -> 0
A22: FRINGE-MX | B22: 70015 | C22: MEX | D22: MEX | E22: B.2.3 Program Assistant (50%) | G22: %/ Month | H22: =H11 -> 10 | I22: 0.5084 | J22: =J11 -> 0 | K22: =K11*I22 -> 0 | L22: =K22 -> 0 | M22: 0 | O22: 12 | P22: =P11 -> 0 | Q22: =Q11*I22 -> 0 | R22: =Q22 -> 0 | S22: =Q22-R22 -> 0 | U22: 4 | V22: =V11 -> 0 | W22: =W11*I22 -> 0 | X22: =W22 -> 0 | Y22: =W22-X22 -> 0 | Z22: =L22+R22+X22 -> 0 | AA22: =M22+S22+Y22 -> 0 | AB22: =Z22+AA22 -> 0
A23: FRINGE-MX | B23: 70015 | C23: MEX | D23: MEX | E23: B.2.4 Administration and Finance Officer (50%) | G23: %/ Month | H23: =H12 -> 10 | I23: 0.5084 | J23: =J12 -> 0 | K23: =K12*I23 -> 0 | L23: =K23 -> 0 | M23: 0 | O23: 12 | P23: =P12 -> 0 | Q23: =Q12*I23 -> 0 | R23: =Q23 -> 0 | S23: =Q23-R23 -> 0 | U23: 6 | V23: =V12 -> 0 | W23: =W12*I23 -> 0 | X23: =W23 -> 0 | Y23: =W23-X23 -> 0 | Z23: =L23+R23+X23 -> 0 | AA23: =M23+S23+Y23 -> 0 | AB23: =Z23+AA23 -> 0
E24: Subtotal Fringe Benefits | K24: 24793.82 | L24: 24793.82 | M24: 0 | Q24: 27582.212 | R24: 27582.212 | S24: 0 | W24: 12285.965 | X24: 12285.965 | Y24: 0 | Z24: 64661.997 | AA24: 0 | AB24: 64661.997
E25: C. Travel
E26: C.1 HQ Staff International Travel
A27: STFTRAVEL | B27: 86040 | C27: 0 | D27: 0 | E27: C.1.1 International Airfare (DC-MX) | F27: 1 | G27: Flight | H27: 1 | I27: 1 | J27: 450 | K27: =F27*J27*H27 -> 450 | L27: =K27 -> 450 | M27: =K27-L27 -> 0 | N27: 1 | O27: 1 | P27: =J27*1.02 -> 459 | Q27: =N27*P27*O27*I27 -> 459 | R27: =Q27 -> 459 | S27: =Q27-R27 -> 0 | T27: 1 | U27: 1 | V27: =P27*1.02 -> 468.18 | W27: =T27*V27*U27*I27 -> 468.18 | X27: =W27 -> 468.18 | Y27: =W27-X27 -> 0 | Z27: =L27+R27+X27 -> 1377.18 | AA27: =M27+S27+Y27 -> 0 | AB27: =Z27+AA27 -> 1377.18
A28: GROUNDTRAN | B28: 86000 | C28: 0 | D28: 0 | E28: C.1.2 Ground Transportation | F28: 1 | G28: Trip | H28: 1 | I28: 1 | J28: 100 | K28: =F28*J28*H28 -> 100 | L28: =K28 -> 100 | M28: =K28-L28 -> 0 | N28: 1 | O28: 1 | P28: =J28*1.02 -> 102 | Q28: =N28*P28*O28*I28 -> 102 | R28: =Q28 -> 102 | S28: =Q28-R28 -> 0 | T28: 1 | U28: 1 | V28: =P28*1.02 -> 104.04 | W28: =T28*V28*U28*I28 -> 104.04 | X28: =W28 -> 104.04 | Y28: =W28-X28 -> 0 | Z28: =L28+R28+X28 -> 306.04 | AA28: =M28+S28+Y28 -> 0 | AB28: =Z28+AA28 -> 306.04
A29: LODGING | B29: 86030 | C29: 0 | D29: 0 | E29: C.1.3 Lodging | F29: 1 | G29: Night | H29: 5 | I29: 1 | J29: 150 | K29: =F29*J29*H29 -> 750 | L29: =K29 -> 750 | M29: =K29-L29 -> 0 | N29: 1 | O29: 5 | P29: =J29*1.02 -> 153 | Q29: =N29*P29*O29*I29 -> 765 | R29: =Q29 -> 765 | S29: =Q29-R29 -> 0 | T29: 1 | U29: 5 | V29: =P29*1.02 -> 156.06 | W29: =T29*V29*U29*I29 -> 780.3 | X29: =W29 -> 780.3 | Y29: =W29-X29 -> 0 | Z29: =L29+R29+X29 -> 2295.3 | AA29: =M29+S29+Y29 -> 0 | AB29: =Z29+AA29 -> 2295.3
A30: STFCN DIEM | B30: 86050 | C30: 0 | D30: 0 | E30: C.1.4 M&IE | F30: 1 | G30: Day | H30: 5 | I30: 1 | J30: 106.2 | K30: =F30*J30*H30 -> 531 | L30: =K30 -> 531 | M30: =K30-L30 -> 0 | N30: 1 | O30: 5 | P30: =J30*1.02 -> 108.324 | Q30: =N30*P30*O30*I30 -> 541.62 | R30: =Q30 -> 541.62 | S30: =Q30-R30 -> 0 | T30: 1 | U30: 5 | V30: =P30*1.02 -> 110.49048 | W30: =T30*V30*U30*I30 -> 552.4524 | X30: =W30 -> 552.4524 | Y30: =W30-X30 -> 0 | Z30: =L30+R30+X30 -> 1625.0724 | AA30: =M30+S30+Y30 -> 0 | AB30: =Z30+AA30 -> 1625.0724
E31: C.2 Local Staff In-Country Travel
A32: LSLODGING | B32: 86030 | C32: MEX | D32: MEX | E32: C.2.1 Lodging | F32: 3 | G32: Night | H32: 8 | I32: 1 | J32: 100 | K32: =F32*J32*H32 -> 2400 | L32: =K32 -> 2400 | M32: =K32-L32 -> 0 | N32: 3 | O32: 8 | P32: =J32*1.02 -> 102 | Q32: =N32*P32*O32*I32 -> 2448 | R32: =Q32 -> 2448 | S32: =Q32-R32 -> 0 | T32: 3 | U32: 2 | V32: =P32*1.02 -> 104.04 | W32: =T32*V32*U32*I32 -> 624.24 | X32: =W32 -> 624.24 | Y32: =W32-X32 -> 0 | Z32: =L32+R32+X32 -> 5472.24 | AA32: =M32+S32+Y32 -> 0 | AB32: =Z32+AA32 -> 5472.24
A33: LSM&IE | B33: 86050 | C33: MEX | D33: MEX | E33: C.2.2 M&IE | F33: 3 | G33: Day | H33: 8 | I33: 1 | J33: 45.75 | K33: =F33*J33*H33 -> 1098 | L33: =K33 -> 1098 | M33: =K33-L33 -> 0 | N33: 3 | O33: 8 | P33: =J33*1.02 -> 46.665 | Q33: =N33*P33*O33*I33 -> 1119.96 | R33: =Q33 -> 1119.96 | S33: =Q33-R33 -> 0 | T33: 3 | U33: 2 | V33: =P33*1.02 -> 47.5983 | W33: =T33*V33*U33*I33 -> 285.5898 | X33: =W33 -> 285.5898 | Y33: =W33-X33 -> 0 | Z33: =L33+R33+X33 -> 2503.5498 | AA33: =M33+S33+Y33 -> 0 | AB33: =Z33+AA33 -> 2503.5498
A34: LSTRANS | B34: 86000 | C34: MEX | D34: MEX | E34: C.2.3 Ground Transportation | F34: 1 | G34: Month | H34: 10 | I34: 1 | J34: 150 | K34: =F34*J34*H34 -> 1500 | L34: =K34 -> 1500 | M34: =K34-L34 -> 0 | N34: 1 | O34: 12 | P34: =J34*1.02 -> 153 | Q34: =N34*P34*O34*I34 -> 1836 | R34: =Q34 -> 1836 | S34: =Q34-R34 -> 0 | T34: 1 | U34: 3 | V34: =P34*1.02 -> 156.06 | W34: =T34*V34*U34*I34 -> 468.18 | X34: =W34 -> 468.18 | Y34: =W34-X34 -> 0 | Z34: =L34+R34+X34 -> 3804.18 | AA34: =M34+S34+Y34 -> 0 | AB34: =Z34+AA34 -> 3804.18
A35: LSDOMAIR | B35: 86040 | C35: MEX | D35: MEX | E35: C.2.4 Domestic Airfare | F35: 1 | G35: Year | H35: 4 | I35: 1 | J35: 150 | K35: =F35*J35*H35 -> 600 | L35: =K35 -> 600 | M35: =K35-L35 -> 0 | N35: 1 | O35: 4 | P35: =J35*1.02 -> 153 | Q35: =N35*P35*O35*I35 -> 612 | R35: =Q35 -> 612 | S35: =Q35-R35 -> 0 | T35: 1 | U35: 2 | V35: =P35*1.02 -> 156.06 | W35: =T35*V35*U35*I35 -> 312.12 | X35: =W35 -> 312.12 | Y35: =W35-X35 -> 0 | Z35: =L35+R35+X35 -> 1524.12 | AA35: =M35+S35+Y35 -> 0 | AB35: =Z35+AA35 -> 1524.12
E36: C.3 Local Staff International Travel
A37: LOCAL TRVL | B37: 86000 | C37: MEX | D37: MEX | E37: C.3.1 DRL Labor Implementer Workshop Trip | F37: 1 | G37: Trip | H37: 1 | I37: 1 | J37: 5000 | K37: =F37*J37*H37 -> 5000 | L37: =K37 -> 5000 | M37: =K37-L37 -> 0 | N37: 1 | O37: 0 | P37: =J37*1.02 -> 5100 | Q37: =N37*P37*O37*I37 -> 0 | R37: =Q37 -> 0 | S37: =Q37-R37 -> 0 | T37: 1 | U37: 0 | V37: =P37*1.02 -> 5202 | W37: =T37*V37*U37*I37 -> 0 | X37: =W37 -> 0 | Y37: =W37-X37 -> 0 | Z37: =L37+R37+X37 -> 5000 | AA37: =M37+S37+Y37 -> 0 | AB37: =Z37+AA37 -> 5000
E38: Subtotal Travel | K38: =SUM(K27:K37) -> 12429 | L38: =SUM(L27:L37) -> 12429 | M38: =SUM(M27:M37) -> 0 | Q38: =SUM(Q27:Q37) -> 7883.58 | R38: =SUM(R27:R37) -> 7883.58 | S38: =SUM(S27:S37) -> 0 | W38: =SUM(W27:W37) -> 3595.1022 | X38: =SUM(X27:X37) -> 3595.1022 | Y38: =SUM(Y27:Y37) -> 0 | Z38: =SUM(Z27:Z37) -> 23907.682 | AA38: =SUM(AA27:AA37) -> 0 | AB38: =SUM(AB27:AB37) -> 23907.682
E39: D. Equipment
E40: E. Supplies
A41: COURIER | B41: 82350 | C41: MEX | D41: MEX | E41: E.1 Courier fees/services | F41: 1 | G41: Month | H41: 10 | I41: 1 | J41: 5 | K41: =F41*J41*H41*I41 -> 50 | L41: =K41 -> 50 | M41: =K41-L41 -> 0 | N41: 1 | O41: 12 | P41: =J41 -> 5 | Q41: =N41*P41*O41*I41 -> 60 | R41: =Q41 -> 60 | S41: =Q41-R41 -> 0 | T41: 1 | U41: 3 | V41: =P41 -> 5 | W41: =T41*V41*U41*I41 -> 15 | X41: =W41 -> 15 | Y41: =W41-X41 -> 0 | Z41: =L41+R41+X41 -> 125 | AA41: =M41+S41+Y41 -> 0 | AB41: =Z41+AA41 -> 125
A42: SUPPLIES | B42: 82401 | C42: MEX | D42: MEX | E42: E.2 Office Supplies | F42: 1 | G42: Month | H42: 10 | I42: 1 | J42: 30 | K42: =F42*J42*H42*I42 -> 300 | L42: =K42 -> 300 | M42: =K42-L42 -> 0 | N42: 1 | O42: 12 | P42: =J42 -> 30 | Q42: =N42*P42*O42*I42 -> 360 | R42: =Q42 -> 360 | S42: =Q42-R42 -> 0 | T42: 1 | U42: 3 | V42: =P42 -> 30 | W42: =T42*V42*U42*I42 -> 90 | X42: =W42 -> 90 | Y42: =W42-X42 -> 0 | Z42: =L42+R42+X42 -> 750 | AA42: =M42+S42+Y42 -> 0 | AB42: =Z42+AA42 -> 750
A43: RENT & UT | B43: 85180 | C43: MEX | D43: MEX | E43: E.3 Coworking space rent | F43: 1 | G43: Month | H43: 10 | I43: 1 | J43: 500 | K43: =F43*J43*H43*I43 -> 5000 | L43: =K43 -> 5000 | M43: =K43-L43 -> 0 | N43: 1 | O43: 12 | P43: =J43 -> 500 | Q43: =N43*P43*O43*I43 -> 6000 | R43: =Q43 -> 6000 | S43: =Q43-R43 -> 0 | T43: 1 | U43: 3 | V43: =P43 -> 500 | W43: =T43*V43*U43*I43 -> 1500 | X43: =W43 -> 1500 | Y43: =W43-X43 -> 0 | Z43: =L43+R43+X43 -> 12500 | AA43: =M43+S43+Y43 -> 0 | AB43: =Z43+AA43 -> 12500
A44: BANK FEES | B44: 90900 | C44: MEX | D44: MEX | E44: E.4 Banking and Cash Handling Fees | F44: 1 | G44: Month | H44: 10 | I44: 1 | J44: 35 | K44: =F44*J44*H44*I44 -> 350 | L44: =K44 -> 350 | M44: =K44-L44 -> 0 | N44: 1 | O44: 12 | P44: =J44 -> 35 | Q44: =N44*P44*O44*I44 -> 420 | R44: =Q44 -> 420 | S44: =Q44-R44 -> 0 | T44: 1 | U44: 5 | V44: =P44 -> 35 | W44: =T44*V44*U44*I44 -> 175 | X44: =W44 -> 175 | Y44: =W44-X44 -> 0 | Z44: =L44+R44+X44 -> 945 | AA44: =M44+S44+Y44 -> 0 | AB44: =Z44+AA44 -> 945
A45: EQ.MNT REP | B45: 85105 | C45: MEX | D45: MEX | E45: E.5 Equipment Maintenance | F45: 1 | G45: Year | H45: 1 | I45: 1 | J45: 100 | K45: =F45*J45*H45*I45 -> 100 | L45: =K45 -> 100 | M45: =K45-L45 -> 0 | N45: 1 | O45: 1 | P45: =J45 -> 100 | Q45: =N45*P45*O45*I45 -> 100 | R45: =Q45 -> 100 | S45: =Q45-R45 -> 0 | T45: 1 | U45: 1 | V45: =P45 -> 100 | W45: =T45*V45*U45*I45 -> 100 | X45: =W45 -> 100 | Y45: =W45-X45 -> 0 | Z45: =L45+R45+X45 -> 300 | AA45: =M45+S45+Y45 -> 0 | AB45: =Z45+AA45 -> 300
A46: LEGAL | B46: 81010 | C46: MEX | D46: MEX | E46: E.6 Legal Fees | F46: 1 | G46: Year | H46: 1 | I46: 1 | J46: 500 | K46: =F46*J46*H46*I46 -> 500 | L46: =K46 -> 500 | M46: =K46-L46 -> 0 | N46: 1 | O46: 1 | P46: =J46 -> 500 | Q46: =N46*P46*O46*I46 -> 500 | R46: =Q46 -> 500 | S46: =Q46-R46 -> 0 | T46: 1 | U46: 1 | V46: =P46 -> 500 | W46: =T46*V46*U46*I46 -> 500 | X46: =W46 -> 500 | Y46: =W46-X46 -> 0 | Z46: =L46+R46+X46 -> 1500 | AA46: =M46+S46+Y46 -> 0 | AB46: =Z46+AA46 -> 1500
A47: LAPTOP | B47: 82401 | C47: MEX | D47: MEX | E47: E.7 Laptop Computers & Software | F47: 1 | G47: Unit | H47: 3 | I47: 1 | J47: 750 | K47: =F47*J47*H47*I47 -> 2250 | L47: =K47 -> 2250 | M47: =K47-L47 -> 0 | N47: 1 | O47: 0 | P47: =J47 -> 750 | Q47: =N47*P47*O47*I47 -> 0 | R47: =Q47 -> 0 | S47: =Q47-R47 -> 0 | T47: 1 | U47: 0 | V47: =P47 -> 750 | W47: =T47*V47*U47*I47 -> 0 | X47: =W47 -> 0 | Y47: =W47-X47 -> 0 | Z47: =L47+R47+X47 -> 2250 | AA47: =M47+S47+Y47 -> 0 | AB47: =Z47+AA47 -> 2250
E48: Subtotal Supplies | K48: =SUM(K41:K47) -> 8550 | L48: =SUM(L41:L47) -> 8550 | M48: =SUM(M41:M47) -> 0 | Q48: =SUM(Q41:Q47) -> 7440 | R48: =SUM(R41:R47) -> 7440 | S48: =SUM(S41:S47) -> 0 | W48: =SUM(W41:W47) -> 2380 | X48: =SUM(X41:X47) -> 2380 | Y48: =SUM(Y41:Y47) -> 0 | Z48: =SUM(Z41:Z47) -> 18370 | AA48: =SUM(AA41:AA47) -> 0 | AB48: =SUM(AB41:AB47) -> 18370
E49: F. Contractual
E50: F.1 Sub-awards
A51: SUBCEREAL | B51: 89050 | C51: MEX | D51: MEX | E51: F.1.1 Sub-awardee: Cereal | F51: 1 | G51: Lumpsum | H51: 1 | I51: 1 | J51: =Cereal!J42 -> 17932.32 | K51: =F51*H51*I51*J51 -> 17932.32 | L51: =K51 -> 17932.32 | M51: =Cereal!L42 -> 0 | N51: 1 | O51: 1 | P51: =Cereal!M42 -> 25716.312 | Q51: =N51*O51*P51*I51 -> 25716.312 | R51: =Cereal!N42 -> 25716.312 | S51: =Cereal!O42 -> 0 | T51: 1 | U51: =O51 -> 1 | V51: =Cereal!P42 -> 6425.7124 | W51: =T51*V51*U51*I51 -> 6425.7124 | X51: =Cereal!Q42 -> 6425.7124 | Y51: =Cereal!R42 -> 0 | Z51: =L51+R51+X51 -> 50074.344 | AA51: =M51+S51+Y51 -> 0 | AB51: =Z51+AA51 -> 50074.344
A52: SUBCDM | B52: 89050 | C52: MEX | D52: MEX | E52: F.1.2 Sub-awardee: Centro de los Derechos del Migrante (CDM) | F52: 1 | G52: Lumpsum | H52: 1 | I52: 1 | J52: =CDM!J45 -> 19444.32 | K52: =F52*H52*I52*J52 -> 19444.32 | L52: =K52 -> 19444.32 | M52: =CDM!L45 -> 0 | N52: 1 | O52: 1 | P52: =CDM!M45 -> 28038.312 | Q52: =N52*O52*P52*I52 -> 28038.312 | R52: =CDM!N45 -> 28038.312 | S52: =CDM!O45 -> 0 | T52: 1 | U52: 1 | V52: =CDM!P45 -> 7127.7124 | W52: =T52*V52*U52*I52 -> 7127.7124 | X52: =CDM!Q45 -> 7127.7124 | Y52: =CDM!R45 -> 0 | Z52: =L52+R52+X52 -> 54610.344 | AA52: =M52+S52+Y52 -> 0 | AB52: =Z52+AA52 -> 54610.344
A53: SUBRMS | B53: 89050 | C53: MEX | D53: MEX | E53: F.1.3 Sub-awardee: Red de Mujeres Sindicalistas (RMS) | F53: 1 | G53: Lumpsum | H53: 1 | I53: 1 | J53: =RMS!J43 -> 19617.12 | K53: =F53*H53*I53*J53 -> 19617.12 | L53: =K53 -> 19617.12 | M53: =RMS!L43 -> 0 | N53: 1 | O53: 1 | P53: =RMS!M43 -> 26591.112 | Q53: =N53*O53*P53*I53 -> 26591.112 | R53: =RMS!N43 -> 26591.112 | S53: =RMS!O43 -> 0 | T53: 1 | U53: 1 | V53: =RMS!P43 -> 7019.7124 | W53: =T53*V53*U53*I53 -> 7019.7124 | X53: =RMS!Q43 -> 7019.7124 | Y53: =RMS!R43 -> 0 | Z53: =L53+R53+X53 -> 53227.944 | AA53: =M53+S53+Y53 -> 0 | AB53: =Z53+AA53 -> 53227.944
A54: SUBSMALL | B54: 89050 | C54: MEX | D54: MEX | E54: F.1.4 Small sub-grants | F54: 1 | G54: Lumpsum | H54: 1 | I54: 1 | J54: 10000 | K54: =F54*H54*I54*J54 -> 10000 | L54: =K54 -> 10000 | M54: =RMS!L44 -> 0 | N54: 2 | O54: 1 | P54: =J54*H54*I54 -> 10000 | Q54: =N54*O54*P54*I54 -> 20000 | R54: =Q54 -> 20000 | S54: =RMS!O44 -> 0 | T54: 1 | U54: 0 | V54: =J54*I54*H54 -> 10000 | W54: =T54*V54*U54*I54 -> 0 | X54: =W54 -> 0 | Y54: =RMS!R44 -> 0 | Z54: =L54+R54+X54 -> 30000 | AA54: =M54+S54+Y54 -> 0 | AB54: =Z54+AA54 -> 30000
E55: F.2 Consultants
A56: CONSULT | B56: 81000 | C56: MEX/0 | D56: MEX/0 | E56: F.2.1 Consultants | F56: 1 | G56: Lumpsum | H56: 1 | I56: 1 | J56: =Consultants!H8 -> 5400 | K56: =F56*H56*I56*J56 -> 5400 | L56: =K56 -> 5400 | M56: =K56-L56 -> 0 | N56: =F56 -> 1 | O56: =H56 -> 1 | P56: =Consultants!J8 -> 3000 | Q56: =N56*O56*P56*I56 -> 3000 | R56: =Q56 -> 3000 | S56: =Q56-R56 -> 0 | T56: =N56 -> 1 | U56: =O56 -> 1 | V56: =Consultants!M8 -> 3000 | W56: =T56*V56*U56*I56 -> 3000 | X56: =W56 -> 3000 | Y56: =W56-X56 -> 0 | Z56: =L56+R56+X56 -> 11400 | AA56: =M56+S56+Y56 -> 0 | AB56: =Z56+AA56 -> 11400
E57: Subtotal Contractual | K57: =SUM(K51:K56) -> 72393.76 | L57: =SUM(L51:L56) -> 72393.76 | M57: =SUM(M51:M56) -> 0 | Q57: =SUM(Q51:Q56) -> 103345.74 | R57: =SUM(R51:R56) -> 103345.74 | S57: =SUM(S51:S56) -> 0 | W57: =SUM(W51:W56) -> 23573.137 | X57: =SUM(X51:X56) -> 23573.137 | Y57: =SUM(Y51:Y56) -> 0 | Z57: =SUM(Z51:Z56) -> 199312.63 | AA57: =SUM(AA51:AA56) -> 0 | AB57: =SUM(AB51:AB56) -> 199312.63
E58: G. Construction
E59: H. Other Direct Costs
E60: Objectives and Activities
E61: O1: Increase workers’ knowledge of labor law, and ability to understand the applicability of labor regulations and international labor standards relevant to the United 2026 games.
E62: H.1: Activity 1: Expand educational programs led by labor rights organizations in Mexico with experience in popular education methods, to train workers on protections under Mexican labor law, international labor standards, business and human rights frameworks relevant to the United 2026 games, and the risks of the games for Mexican workers.
A63: M.1.1 | B63: 87010 | C63: MEX | D63: MEX | E63: H.1.1 Labor rights organizations training coordination | F63: 1 | G63: Meeting | H63: 8 | I63: 1 | J63: 125 | K63: =F63*H63*I63*J63 -> 1000 | L63: =K63 -> 1000 | M63: =K63-L63 -> 0 | N63: 1 | O63: 8 | P63: =J63 -> 125 | Q63: =I63*N63*O63*P63 -> 1000 | R63: =Q63 -> 1000 | S63: =Q63-R63 -> 0 | T63: 1 | U63: 1 | V63: =P63 -> 125 | W63: =I63*T63*U63*V63 -> 125 | X63: =W63 -> 125 | Y63: =W63-X63 -> 0 | Z63: =L63+R63+X63 -> 2125 | AA63: =M63+S63+Y63 -> 0 | AB63: =Z63 -> 2125
A64: M.1.2 | B64: 82420 | C64: MEX | D64: MEX | E64: H.1.2 Materials for labor rights organization trainings | F64: 1 | G64: Training | H64: 8 | I64: 1 | J64: 300 | K64: =F64*H64*I64*J64 -> 2400 | L64: =K64 -> 2400 | M64: =K64-L64 -> 0 | N64: 1 | O64: 8 | P64: 150 | Q64: =I64*N64*O64*P64 -> 1200 | R64: =Q64 -> 1200 | S64: =Q64-R64 -> 0 | T64: 1 | U64: 1 | V64: =P64 -> 150 | W64: =I64*T64*U64*V64 -> 150 | X64: =W64 -> 150 | Y64: =W64-X64 -> 0 | Z64: =L64+R64+X64 -> 3750 | AA64: =M64+S64+Y64 -> 0 | AB64: =Z64 -> 3750
A65: M.1.3 | B65: 82420 | C65: MEX | D65: MEX | E65: H.1.3 Development of new modules/materials for labor rights organization trainings | F65: 1 | G65: Training | H65: 8 | I65: 1 | J65: 300 | K65: =F65*H65*I65*J65 -> 2400 | L65: =K65 -> 2400 | M65: =K65-L65 -> 0 | N65: 1 | O65: 8 | P65: 150 | Q65: =I65*N65*O65*P65 -> 1200 | R65: =Q65 -> 1200 | S65: =Q65-R65 -> 0 | T65: 1 | U65: 1 | V65: =P65 -> 150 | W65: =I65*T65*U65*V65 -> 150 | X65: =W65 -> 150 | Y65: =W65-X65 -> 0 | Z65: =L65+R65+X65 -> 3750 | AA65: =M65+S65+Y65 -> 0 | AB65: =Z65 -> 3750
E66: O2: Increase engagement and coordination between labor rights organizations, the private sector, and democratic, independent unions on the UHRS and around pre-games planning of United 2026 events, including the implementation of the human rights strategy in each host city, and ways that the Government of Mexico, FIFA and the Mexican National Soccer Federation will address and mitigate labor rights risks associated with the games.
E67: H.2: Activity 2 - Establish and facilitate a civil society labor advisory network in Mexico
A68: M.2.1 | B68: 87010 (Meeting)/ 82420 (Materials) | C68: MEX | D68: MEX | E68: H.2.1 Coordination meetings (including materials) | F68: 1 | G68: Meeting | H68: 6 | I68: 1 | J68: 125 | K68: =F68*H68*J68*I68 -> 750 | L68: =K68 -> 750 | M68: =K68-L68 -> 0 | N68: 1 | O68: 8 | P68: =J68 -> 125 | Q68: =N68*O68*P68*I68 -> 1000 | R68: =Q68 -> 1000 | S68: =Q68-R68 -> 0 | T68: 1 | U68: 2 | V68: =P68 -> 125 | W68: =T68*U68*V68*I68 -> 250 | X68: =W68 -> 250 | Y68: =W68-X68 -> 0 | Z68: =K68+Q68+W68 -> 2000 | AA68: =M68+S68+Y68 -> 0 | AB68: =Z68+AA68 -> 2000
A69: M.2.2 | B69: 87000 | C69: MEX | D69: MEX | E69: H.2.2 Working summit to establish the civil society advisory network | F69: 1 | G69: Event | H69: 1 | I69: 1 | J69: 500 | K69: =F69*H69*J69*I69 -> 500 | L69: =K69 -> 500 | M69: =K69-L69 -> 0 | N69: 1 | O69: 0 | P69: =J69 -> 500 | Q69: =N69*O69*P69*I69 -> 0 | R69: =Q69 -> 0 | S69: =Q69-R69 -> 0 | T69: 1 | U69: 0 | V69: =P69 -> 500 | W69: =T69*U69*V69*I69 -> 0 | X69: =W69 -> 0 | Y69: =W69-X69 -> 0 | Z69: =K69+Q69+W69 -> 500 | AA69: =M69+S69+Y69 -> 0 | AB69: =Z69+AA69 -> 500
A70: M.2.3 | B70: 85300 | C70: MEX | D70: MEX | E70: H.2.3 Printing of materials for summit | F70: 1 | G70: Event | H70: 1 | I70: 1 | J70: 100 | K70: =F70*H70*J70*I70 -> 100 | L70: =K70 -> 100 | M70: =K70-L70 -> 0 | N70: 1 | O70: 0 | P70: =J70 -> 100 | Q70: =N70*O70*P70*I70 -> 0 | R70: =Q70 -> 0 | S70: =Q70-R70 -> 0 | T70: 1 | U70: 0 | V70: =P70 -> 100 | W70: =T70*U70*V70*I70 -> 0 | X70: =W70 -> 0 | Y70: =W70-X70 -> 0 | Z70: =K70+Q70+W70 -> 100 | AA70: =M70+S70+Y70 -> 0 | AB70: =Z70+AA70 -> 100
A71: M.2.4 | B71: 86030 | C71: MEX | D71: MEX | E71: H.2.4 Lodging for participants | F71: 1 | G71: Night | H71: 9 | I71: 1 | J71: 150 | K71: =F71*H71*J71*I71 -> 1350 | L71: =K71 -> 1350 | M71: =K71-L71 -> 0 | N71: 1 | O71: 0 | P71: =J71 -> 150 | Q71: =N71*O71*P71*I71 -> 0 | R71: =Q71 -> 0 | S71: =Q71-R71 -> 0 | T71: 1 | U71: 0 | V71: =P71 -> 150 | W71: =T71*U71*V71*I71 -> 0 | X71: =W71 -> 0 | Y71: =W71-X71 -> 0 | Z71: =K71+Q71+W71 -> 1350 | AA71: =M71+S71+Y71 -> 0 | AB71: =Z71+AA71 -> 1350
A72: M.2.5 | B72: 86000 | C72: MEX | D72: MEX | E72: H.2.5 Transportation for participants | F72: 1 | G72: Participant | H72: 3 | I72: 1 | J72: 100 | K72: =F72*H72*J72*I72 -> 300 | L72: =K72 -> 300 | M72: =K72-L72 -> 0 | N72: 1 | O72: 0 | P72: =J72 -> 100 | Q72: =N72*O72*P72*I72 -> 0 | R72: =Q72 -> 0 | S72: =Q72-R72 -> 0 | T72: 1 | U72: 0 | V72: =P72 -> 100 | W72: =T72*U72*V72*I72 -> 0 | X72: =W72 -> 0 | Y72: =W72-X72 -> 0 | Z72: =K72+Q72+W72 -> 300 | AA72: =M72+S72+Y72 -> 0 | AB72: =Z72+AA72 -> 300
E73: O3: Strengthen the capacity of civil society actors, independent unions, and workers to monitor and report labor and human right abuses, to prepare to effectively document violations, and make strategic use of reporting and enforcement mechanisms related to the operation of the games
E74: H.3: Activity 3 - Develop trainings programs for human rights and labor rights defenders on monitoring, case development, and filing processes for existing grievance and conciliation procedures, and assist with the planning and implementation of alternative grievance procedures
A75: M.3.1 | B75: 87010 (Meeting)/ 82420 (Materials) | C75: MEX | D75: MEX | E75: H.3.1 Coordination meetings (including materials) | F75: 1 | G75: Meeting | H75: 1 | I75: 1 | J75: 125 | K75: =F75*H75*I75*J75 -> 125 | L75: =K75 -> 125 | M75: =K75-L75 -> 0 | N75: 1 | O75: 3 | P75: =J75 -> 125 | Q75: =I75*N75*O75*P75 -> 375 | R75: =Q75 -> 375 | S75: =Q75-R75 -> 0 | T75: 1 | U75: 0 | V75: =P75 -> 125 | W75: =I75*T75*U75*V75 -> 0 | X75: =W75 -> 0 | Y75: =W75-X75 -> 0 | Z75: =L75+R75+X75 -> 500 | AA75: =M75+S75+Y75 -> 0 | AB75: =Z75 -> 500
A76: M.3.2 | B76: 82420 | C76: MEX | D76: MEX | E76: H.3.2 Development of training programs | F76: 1 | G76: Document | H76: 0 | I76: 1 | J76: 2000 | K76: =F76*H76*I76*J76 -> 0 | L76: =K76 -> 0 | M76: =K76-L76 -> 0 | N76: 1 | O76: 1 | P76: =J76 -> 2000 | Q76: =I76*N76*O76*P76 -> 2000 | R76: =Q76 -> 2000 | S76: =Q76-R76 -> 0 | T76: 1 | U76: 0 | V76: =P76 -> 2000 | W76: =I76*T76*U76*V76 -> 0 | X76: =W76 -> 0 | Y76: =W76-X76 -> 0 | Z76: =L76+R76+X76 -> 2000 | AA76: =M76+S76+Y76 -> 0 | AB76: =Z76 -> 2000
E77: H.4: Activity 4 - Strengthen collaboration between civil society and journalists to monitor and report on labor rights impacts during the lifecycle of the games, including tracking violations and complaints submitted to grievance channels
A78: M.4.1 | B78: 87010 (Meeting)/ 82420 (Materials) | C78: MEX | D78: MEX | E78: H.4.1 Training for journalists (including materials) | F78: 1 | G78: Training | H78: 2 | I78: 1 | J78: 200 | K78: =F78*H78*I78*J78 -> 400 | L78: =K78 -> 400 | M78: =K78-L78 -> 0 | N78: 1 | O78: 2 | P78: =J78 -> 200 | Q78: =I78*N78*O78*P78 -> 400 | R78: =Q78 -> 400 | S78: =Q78-R78 -> 0 | T78: 1 | U78: 0 | V78: =P78 -> 200 | W78: =I78*T78*U78*V78 -> 0 | X78: =W78 -> 0 | Y78: =W78-X78 -> 0 | Z78: =L78+R78+X78 -> 800 | AA78: =M78+S78+Y78 -> 0 | AB78: =Z78 -> 800
A79: M.4.2 | B79: 86000 | C79: MEX | D79: MEX | E79: H.4.2 Ground transportation for journalists | F79: 1 | G79: Training | H79: 2 | I79: 1 | J79: 150 | K79: =F79*H79*I79*J79 -> 300 | L79: =K79 -> 300 | M79: =K79-L79 -> 0 | N79: 1 | O79: 2 | P79: =J79 -> 150 | Q79: =I79*N79*O79*P79 -> 300 | R79: =Q79 -> 300 | S79: =Q79-R79 -> 0 | T79: 1 | U79: 0 | V79: =P79 -> 150 | W79: =I79*T79*U79*V79 -> 0 | X79: =W79 -> 0 | Y79: =W79-X79 -> 0 | Z79: =L79+R79+X79 -> 600 | AA79: =M79+S79+Y79 -> 0 | AB79: =Z79 -> 600
A80: M.4.3 | B80: 86030 | C80: MEX | D80: MEX | E80: H.4.3 Lodging for journalists | F80: 1 | G80: Training | H80: 2 | I80: 1 | J80: 300 | K80: =F80*H80*I80*J80 -> 600 | L80: =K80 -> 600 | M80: =K80-L80 -> 0 | N80: 1 | O80: 2 | P80: =J80 -> 300 | Q80: =I80*N80*O80*P80 -> 600 | R80: =Q80 -> 600 | S80: =Q80-R80 -> 0 | T80: 1 | U80: 0 | V80: =P80 -> 300 | W80: =I80*T80*U80*V80 -> 0 | X80: =W80 -> 0 | Y80: =W80-X80 -> 0 | Z80: =L80+R80+X80 -> 1200 | AA80: =M80+S80+Y80 -> 0 | AB80: =Z80 -> 1200
E81: O4: Increase awareness among the general public of Mexico’s commitments to human rights in regard to the United 2026 games.
E82: H.5: Activity 5 - Provide technical assistance to civil society to develop a media campaign to socialize information of labor rights risks in preparation for the United 2026 games.
A83: M.5.1 | B83: 85300 | C83: MEX | D83: MEX | E83: H.5.1 Comic book for general public | F83: 1 | G83: Document | H83: 1 | I83: 1 | J83: 1000 | K83: =F83*0*I83*J83 -> 0 | L83: =K83 -> 0 | M83: =K83-L83 -> 0 | N83: 1 | O83: 3 | P83: =J83 -> 1000 | Q83: =I83*N83*O83*P83 -> 3000 | R83: =Q83 -> 3000 | S83: =Q83-R83 -> 0 | T83: 1 | U83: 0 | V83: =P83 -> 1000 | W83: =I83*T83*U83*V83 -> 0 | X83: =W83 -> 0 | Y83: =W83-X83 -> 0 | Z83: =L83+R83+X83 -> 3000 | AA83: =M83+S83+Y83 -> 0 | AB83: =Z83 -> 3000
A84: M.5.2 | B84: 90460 | C84: MEX | D84: MEX | E84: H.5.2 United 2026 media campaign | F84: 1 | G84: Campaign | H84: 1 | I84: 1 | J84: 300 | K84: =F84*H84*I84*J84 -> 300 | L84: =K84 -> 300 | M84: =K84-L84 -> 0 | N84: 1 | O84: 1 | P84: =J84 -> 300 | Q84: =I84*N84*O84*P84 -> 300 | R84: =Q84 -> 300 | S84: =Q84-R84 -> 0 | T84: 1 | U84: 1 | V84: =P84 -> 300 | W84: =I84*T84*U84*V84 -> 300 | X84: =W84 -> 300 | Y84: =W84-X84 -> 0 | Z84: =L84+R84+X84 -> 900 | AA84: =M84+S84+Y84 -> 0 | AB84: =Z84 -> 900
E85: H.6 M&E
A86: M.6.1 | B86: 82420 | C86: MEX | D86: MEX | E86: H.6.1 M&E Materials | F86: 1 | G86: Year | H86: 1 | I86: 1 | J86: 300 | K86: =F86*H86*J86 -> 300 | L86: =K86 -> 300 | M86: =K86-L86 -> 0 | N86: 1 | O86: 1 | P86: =J86 -> 300 | Q86: =N86*O86*P86 -> 300 | R86: =Q86 -> 300 | S86: =Q86-R86 -> 0 | T86: 1 | U86: 1 | V86: =P86 -> 300 | W86: =T86*U86*V86 -> 300 | X86: =W86 -> 300 | Y86: =W86-X86 -> 0 | Z86: =L86+R86+X86 -> 900 | AA86: =M86+S86+Y86 -> 0 | AB86: =Z86+AA86 -> 900
A87: M.6.2 | B87: 87010 | C87: MEX | D87: MEX | E87: H.6.2 M&E Training and Coordination Meetings | F87: 1 | G87: Meetings | H87: 10 | I87: 1 | J87: 125 | K87: =F87*H87*J87 -> 1250 | L87: =K87 -> 1250 | M87: =K87-L87 -> 0 | N87: 1 | O87: 12 | P87: =J87 -> 125 | Q87: =N87*O87*P87 -> 1500 | R87: =Q87 -> 1500 | S87: =Q87-R87 -> 0 | T87: 1 | U87: 8 | V87: =P87 -> 125 | W87: =T87*U87*V87 -> 1000 | X87: =W87 -> 1000 | Y87: =W87-X87 -> 0 | Z87: =L87+R87+X87 -> 3750 | AA87: =M87+S87+Y87 -> 0 | AB87: =Z87+AA87 -> 3750
A88: M.6.3 | B88: 81010 | C88: MEX | D88: MEX | E88: H.6.3 External Project Evaluation support costs | F88: 1 | G88: Lumpsum | H88: 0 | I88: 1 | J88: 7196.5 | K88: =F88*H88*J88 -> 0 | L88: =K88 -> 0 | M88: =K88-L88 -> 0 | N88: 1 | O88: 1 | P88: =J88 -> 7196.5 | Q88: =N88*O88*P88 -> 7196.5 | R88: =Q88 -> 7196.5 | S88: =Q88-R88 -> 0 | T88: 1 | U88: 0 | V88: =P88 -> 7196.5 | W88: =T88*U88*V88 -> 0 | X88: =W88 -> 0 | Y88: =W88-X88 -> 0 | Z88: =L88+R88+X88 -> 7196.5 | AA88: =M88+S88+Y88 -> 0 | AB88: =Z88+AA88 -> 7196.5
E89: Subtotal Other Direct Costs | K89: =SUM(K63:K88) -> 12075 | L89: =SUM(L63:L88) -> 12075 | M89: =SUM(M67:M88) -> 0 | Q89: =SUM(Q63:Q88) -> 20371.5 | R89: =SUM(R63:R88) -> 20371.5 | S89: =SUM(S67:S88) -> 0 | W89: =SUM(W63:W88) -> 2275 | X89: =SUM(X63:X88) -> 2275 | Y89: =SUM(Y67:Y88) -> 0 | Z89: =SUM(Z63:Z88) -> 34721.5 | AA89: =SUM(AA67:AA88) -> 0 | AB89: =SUM(AB63:AB88) -> 34721.5
E90: I. Total Direct Costs | K90: =K15+K24+K38+K48+K57+K89 -> 184491.58 | L90: =L15+L24+L38+L48+L57+L89 -> 184491.58 | M90: =M15+M24+M38+M48+M57+M89 -> 0 | Q90: =Q15+Q24+Q38+Q48+Q57+Q89 -> 226549.53 | R90: =R15+R24+R38+R48+R57+R89 -> 226549.53 | S90: =S15+S24+S38+S48+S57+S89 -> 0 | W90: =W15+W24+W38+W48+W57+W89 -> 71211.197 | X90: =X15+X24+X38+X48+X57+X89 -> 71211.197 | Y90: =Y15+Y24+Y38+Y48+Y57+Y89 -> 0 | Z90: =Z15+Z24+Z38+Z48+Z57+Z89 -> 482252.31 | AA90: =AA15+AA24+AA38+AA48+AA57+AA89 -> 0 | AB90: =AB15+AB24+AB38+AB48+AB57+AB89 -> 482252.31
E91: J. Indirect Cost
A92: IDC | B92: 94050 | C92: 0 | D92: 0 | E92: J.1 Indirect Cost (28% NICRA rate) | G92: 0.28 | I92: 1 | K92: =K90*G92 -> 51657.642 | L92: =K92 -> 51657.642 | M92: =K92-L92 -> 0 | Q92: =Q90*G92 -> 63433.868 | R92: =Q92 -> 63433.868 | S92: =Q92-R92 -> 0 | W92: =W90*G92 -> 19939.135 | X92: =W92 -> 19939.135 | Y92: =W92-X92 -> 0 | Z92: =L92+R92+X92 -> 135030.65 | AA92: =M92+S92+Y92 -> 0 | AB92: =Z92+AA92 -> 135030.65
E93: J.2 Total Indirect Cost | K93: =K92 -> 51657.642 | L93: =L92 -> 51657.642 | M93: =M92 -> 0 | Q93: =Q92 -> 63433.868 | R93: =R92 -> 63433.868 | S93: =S92 -> 0 | W93: =W92 -> 19939.135 | X93: =X92 -> 19939.135 | Y93: =Y92 -> 0 | Z93: =Z92 -> 135030.65 | AA93: =AA92 -> 0 | AB93: =AB92 -> 135030.65
E94: K. GRAND TOTAL | K94: =K90+K93 -> 236149.22 | L94: =L90+L93 -> 236149.22 | M94: =M90+M93 -> 0 | Q94: =Q90+Q93 -> 289983.4 | R94: =R90+R93 -> 289983.4 | S94: =S90+S93 -> 0 | W94: =W90+W93 -> 91150.333 | X94: =X90+X93 -> 91150.333 | Y94: =Y90+Y93 -> 0 | Z94: =Z90+Z93 -> 617282.95 | AA94: =AA90+AA93 -> 0 | AB94: =AB90+AB93 -> 617282.95

Sheet Cereal
C1: SUBGRANTEE: CEREAL
C2: Budget Line Items | D2: Description | E2: No. | F2: Rate | G2: Unit Type | H2: Frequency | I2: % | J2: YEAR 1 | M2: YEAR 2 | P2: YEAR 3 | S2: Total
J3: Total | K3: Grant | L3: Cost Share | M3: Total | N3: Grant | O3: Cost Share | P3: Total | Q3: Grant | R3: Cost Share | S3: Total | T3: Grant | U3: Cost Share
A4: Activity | B4: Object Code | C4: A. Personnel
A6: SUBCEREAL | B6: 7370 | C6: A.1 Project Coordinator (60%) | E6: 1 | F6: 1100 | G6: Month | H6: 8 | I6: 0.6 | J6: =(E6*F6*H6*I6) -> 5280 | K6: =J6 -> 5280 | L6: =J6-K6 -> 0 | M6: =(E6*F6*12*I6)*1.025 -> 8118 | N6: =M6 -> 8118 | O6: =M6-N6 -> 0 | P6: =((F6*1.025)*1.025)*I6*3 -> 2080.2375 | Q6: =P6 -> 2080.2375 | R6: =P6-Q6 -> 0 | S6: =J6+M6+P6 -> 15478.237 | T6: =K6+N6+Q6 -> 15478.237 | U6: =L6+O6+R6 -> 0
A7: SUBCEREAL | B7: 7370 | C7: A.1 Project Administrator (20%) | E7: 1 | F7: 1000 | G7: Month | H7: 8 | I7: 0.2 | J7: =(E7*F7*H7*I7) -> 1600 | K7: =J7 -> 1600 | L7: =J7-K7 -> 0 | M7: =(E7*F7*12*I7)*1.025 -> 2460 | N7: =M7 -> 2460 | O7: =M7-N7 -> 0 | P7: =((F7*1.025)*1.025)*I7*3 -> 630.375 | Q7: =P7 -> 630.375 | R7: =P7-Q7 -> 0 | S7: =J7+M7+P7 -> 4690.375 | T7: =K7+N7+Q7 -> 4690.375 | U7: =L7+O7+R7 -> 0
C8: Subtotal Personnel | J8: =SUM(J5:J7) -> 6880 | K8: =SUM(K5:K7) -> 6880 | L8: =SUM(L5:L7) -> 0 | M8: =SUM(M5:M7) -> 10578 | N8: =SUM(N5:N7) -> 10578 | O8: =SUM(O5:O7) -> 0 | P8: =SUM(P5:P7) -> 2710.6125 | Q8: =SUM(Q5:Q7) -> 2710.6125 | ... U8: =SUM(U5:U7) -> 0
C9: B. Fringe Benefits
A10: SUBCEREAL | B10: 7370 | C10: B.1 Project Coordinator (60%) | E10: 1 | F10: 1100 | G10: %/ Month | H10: 8 | I10: 0.3 | J10: =(J6*I10) -> 1584 | K10: =J10 -> 1584 | L10: =J10-K10 -> 0 | M10: =(I10*M6) -> 2435.4 | N10: =M10 -> 2435.4 | O10: =M10-N10 -> 0 | P10: =(I10*P6) -> 624.07125 | Q10: =P10 -> 624.07125 | R10: =P10-Q10 -> 0 | S10: =J10+M10+P10 -> 4643.4712 | T10: =K10+N10+Q10 -> 4643.4712 | U10: =L10+O10+R10 -> 0
A11: SUBCEREAL | B11: 7370 | C11: B.2 Project Administrator (20%) | E11: 1 | F11: 1000 | G11: %/ Month | H11: 8 | I11: 0.3 | J11: =(J7*I11) -> 480 | K11: =J11 -> 480 | L11: =J11-K11 -> 0 | M11: =(I11*M7) -> 738 | N11: =M11 -> 738 | O11: =M11-N11 -> 0 | P11: =(I11*P7) -> 189.1125 | Q11: =P11 -> 189.1125 | R11: =P11-Q11 -> 0 | S11: =J11+M11+P11 -> 1407.1125 | T11: =K11+N11+Q11 -> 1407.1125 | U11: =L11+O11+R11 -> 0
C12: Subtotal Fringe Benefits | J12: =SUM(J10:J11) -> 2064 | K12: =SUM(K10:K11) -> 2064 | L12: =SUM(L10:L11) -> 0 | M12: =SUM(M10:M11) -> 3173.4 | N12: =SUM(N10:N11) -> 3173.4 | O12: =SUM(O10:O11) -> 0 | P12: =SUM(P10:P11) -> 813.18375 | Q12: =SUM(Q10:Q11) -> 813.18375 | ... U12: =SUM(U10:U11) -> 0
C13: C. Travel
A14: SUBCEREAL | B14: 7370 | C14: C.1 Ground Transportation | E14: 1 | F14: 150 | G14: Monthly | H14: 5 | I14: 1 | J14: =(E14*F14*H14*I14) -> 750 | K14: =J14 -> 750 | L14: =J14-K14 -> 0 | M14: =(E14*F14*8*I14)*1.025 -> 1230 | N14: =M14 -> 1230 | O14: =M14-N14 -> 0 | P14: =(E14*(F14*1.025)*2*I14)*1.025 -> 315.1875 | Q14: =P14 -> 315.1875 | R14: =P14-Q14 -> 0 | S14: =J14+M14+P14 -> 2295.1875 | T14: =K14+N14+Q14 -> 2295.1875 | U14: =L14+O14+R14 -> 0
A15: SUBCEREAL | B15: 7370 | C15: C.2 Lodging | E15: =E7 -> 1 | F15: 300 | G15: Monthly | H15: 5 | I15: 1 | J15: =(E15*F15*H15*I15) -> 1500 | K15: =J15 -> 1500 | L15: =J15-K15 -> 0 | M15: =(E15*F15*8*I15)*1.025 -> 2460 | N15: =M15 -> 2460 | O15: =M15-N15 -> 0 | P15: =(E15*(F15*1.025)*2*I15)*1.025 -> 630.375 | Q15: =P15 -> 630.375 | R15: =P15-Q15 -> 0 | S15: =J15+M15+P15 -> 4590.375 | T15: =K15+N15+Q15 -> 4590.375 | U15: =L15+O15+R15 -> 0
A16: SUBCEREAL | B16: 7370 | C16: C.3 M&IE | E16: 1 | F16: 300 | G16: Monthly | H16: 5 | I16: 1 | J16: =(E16*F16*H16*I16) -> 1500 | K16: =J16 -> 1500 | L16: =J16-K16 -> 0 | M16: =(E16*F16*8*I16)*1.025 -> 2460 | N16: =M16 -> 2460 | O16: =M16-N16 -> 0 | P16: =(E16*(F16*1.025)*2*I16)*1.025 -> 630.375 | Q16: =P16 -> 630.375 | R16: =P16-Q16 -> 0 | S16: =J16+M16+P16 -> 4590.375 | T16: =K16+N16+Q16 -> 4590.375 | U16: =L16+O16+R16 -> 0
C17: Subtotal Travel | J17: =SUM(J14:J16) -> 3750 | K17: =SUM(K14:K16) -> 3750 | L17: =SUM(L14:L16) -> 0 | M17: =SUM(M14:M16) -> 6150 | N17: =SUM(N14:N16) -> 6150 | O17: =SUM(O14:O16) -> 0 | P17: =SUM(P14:P16) -> 1575.9375 | Q17: =SUM(Q14:Q16) -> 1575.9375 | ... U17: =SUM(U14:U16) -> 0
C18: D. Equipment
C19: E. Supplies
C20: F. Contractual and Subaward
C21: G. Construction
C22: H. Other Direct Costs
C23: Objectives and Activities
C24: O1: Increase workers’ knowledge of labor law, and ability to understand the applicability of labor regulations and international labor standards relevant to the United 2026 games.
C25: H.1: Activity 1: Expand educational programs led by labor rights organizations in Mexico with experience in popular education methods, to train workers on protections under Mexican labor law, international labor standards, business and human rights frameworks relevant to the United 2026 games, and the risks of the games for Mexican workers.
A26: SUBCEREAL | B26: 7370 | C26: H.1.1 Labor rights trainings for workers on labor law | E26: 1 | F26: 150 | G26: Workshop | H26: 4 | I26: 1 | J26: =E26*F26*H26*I26 -> 600 | K26: =J26 -> 600 | L26: =J26-K26 -> 0 | M26: =E26*F26*H26*I26 -> 600 | N26: =M26 -> 600 | O26: =M26-N26 -> 0 | P26: =E26*F26*0*I26 -> 0 | Q26: =P26 -> 0 | R26: =P26-Q26 -> 0 | S26: =J26+M26+P26 -> 1200 | T26: =K26+N26+Q26 -> 1200 | U26: =S26-T26 -> 0
A27: SUBCEREAL | B27: 7370 | C27: H.1.2 Printing of materials for labor rights trainings | E27: 1 | F27: 60 | G27: Workshop | H27: 4 | I27: 1 | J27: =F27*H27*I27 -> 240 | K27: =J27 -> 240 | L27: =J27-K27 -> 0 | M27: =F27*H27*I27 -> 240 | N27: =M27 -> 240 | O27: =M27-N27 -> 0 | P27: =E27*F27*0*I27 -> 0 | Q27: =P27 -> 0 | R27: =P27-Q27 -> 0 | S27: =J27+M27+P27 -> 480 | T27: =K27+N27+Q27 -> 480 | U27: =S27-T27 -> 0
A28: SUBCEREAL | B28: 7370 | C28: H.1.3 Lodging for participants | E28: 1 | F28: 300 | G28: Workshop | H28: 4 | I28: 1 | J28: =F28*H28*I28 -> 1200 | K28: =J28 -> 1200 | L28: =J28-K28 -> 0 | M28: =F28*H28*I28 -> 1200 | N28: =M28 -> 1200 | O28: =M28-N28 -> 0 | P28: =E28*F28*0*I28 -> 0 | Q28: =P28 -> 0 | R28: =P28-Q28 -> 0 | S28: =J28+M28+P28 -> 2400 | T28: =K28+N28+Q28 -> 2400 | U28: =S28-T28 -> 0
A29: SUBCEREAL | B29: 7370 | C29: H.1.4 Transportation for participants | E29: 1 | F29: 80 | G29: Workshop | H29: 4 | I29: 1 | J29: =F29*H29*I29 -> 320 | K29: =J29 -> 320 | L29: =J29-K29 -> 0 | M29: =F29*H29*I29 -> 320 | N29: =M29 -> 320 | O29: =M29-N29 -> 0 | P29: =E29*F29*0*I29 -> 0 | Q29: =P29 -> 0 | R29: =P29-Q29 -> 0 | S29: =J29+M29+P29 -> 640 | T29: =K29+N29+Q29 -> 640 | U29: =S29-T29 -> 0
A30: SUBCEREAL | B30: 7370 | C30: H.1.5 Worker outreach campaign | E30: 1 | F30: 300 | G30: Campaign | H30: 2 | I30: 1 | J30: =E30*F30*H30*I30 -> 600 | K30: =J30 -> 600 | L30: 0 | M30: =E30*F30*H30*I30 -> 600 | N30: =M30 -> 600 | O30: =M30-N30 -> 0 | P30: =E30*F30*0*I30 -> 0 | Q30: =P30 -> 0 | R30: =P30-Q30 -> 0 | S30: =J30+M30+P30 -> 1200 | T30: =K30+N30+Q30 -> 1200 | U30: =S30-T30 -> 0
C31: O2: Increase engagement and coordination between labor rights organizations, the private sector, and democratic, independent unions on the UHRS and around pre-games planning of United 2026 events, including the implementation of the human rights strategy in each host city, and ways that the Government of Mexico, FIFA and the Mexican National Soccer Federation will address and mitigate labor rights risks associated with the games.
C32: H.2 Activity 2: Establish and facilitate a civil society labor advisory network in Mexico.
A33: SUBCEREAL | B33: 7370 | C33: H.2.1 Coordination Meetings | E33: 1 | F33: 100 | G33: Meeting | H33: 3 | I33: 1 | J33: =E33*F33*H33*I33 -> 300 | K33: =J33 -> 300 | L33: =J33-K33 -> 0 | M33: =E33*F33*H33*I33 -> 300 | N33: =M33 -> 300 | O33: =M33-N33 -> 0 | P33: =E33*F33*2*I33 -> 200 | Q33: =P33 -> 200 | R33: =P33-Q33 -> 0 | S33: =J33+M33+P33 -> 800 | T33: =K33+N33+Q33 -> 800 | U33: =S33-T33 -> 0
C34: O4: Increase awareness among the general public of Mexico’s commitments to human rights in regard to the United 2026 games.
C35: H.3 Activity 5 - Provide technical assistance to civil society to develop a media campaign to socialize information of labor rights risks in preparation for the United 2026 games.
A36: SUBCEREAL | B36: 7370 | C36: H.3.1 United 2026 media campaign | E36: 1 | F36: 650 | G36: Campaign | H36: 1 | I36: 1 | J36: =E36*F36*H36*I36 -> 650 | K36: =J36 -> 650 | L36: 0 | M36: =E36*F36*H36*I36 -> 650 | N36: =M36 -> 650 | O36: =M36-N36 -> 0 | P36: =E36*F36*H36*I36 -> 650 | Q36: =P36 -> 650 | R36: =P36-Q36 -> 0 | S36: =J36+M36+P36 -> 1950 | T36: =K36+N36+Q36 -> 1950 | U36: =S36-T36 -> 0
C37: Subtotal Other Direct Costs | J37: =SUM(J26:J36) -> 3910 | K37: =SUM(K26:K36) -> 3910 | L37: =SUM(L24:L36) -> 0 | M37: =SUM(M26:M36) -> 3910 | N37: =SUM(N26:N36) -> 3910 | O37: =SUM(O24:O36) -> 0 | P37: =SUM(P26:P36) -> 850 | Q37: =SUM(Q26:Q36) -> 850 | R37: =SUM(R24:R36) -> 0 | S37: =SUM(S26:S36) -> 8670 | T37: =SUM(T26:T36) -> 8670 | U37: =SUM(U26:U36) -> 0
C38: I. Total Direct Costs | J38: =J8+J12+J17+J37 -> 16604 | K38: =J38 -> 16604 | L38: =J38-K38 -> 0 | M38: =M8+M12+M17+M37 -> 23811.4 | N38: =M38 -> 23811.4 | O38: =M38-N38 -> 0 | P38: =P8+P12+P17+P37 -> 5949.7338 | Q38: =P38 -> 5949.7338 | R38: =P38-Q38 -> 0 | S38: =S8+S12+S17+S37 -> 46365.134 | T38: =S38 -> 46365.134 | U38: =SUM(U8+U17+U37) -> 0
C39: J. Indirect Cost
A40: SUBCEREAL | B40: 7370 | C40: J.1 Administrative Cost (8%) | F40: 0.08 | I40: 1 | J40: =J38*F40*I40 -> 1328.32 | K40: =J40 -> 1328.32 | L40: =SUM(L38:L39) -> 0 | M40: =M38*F40*I40 -> 1904.912 | N40: =M40 -> 1904.912 | O40: =SUM(O38:O39) -> 0 | P40: =P38*F40*I40 -> 475.9787 | Q40: =P40 -> 475.9787 | R40: =SUM(R38:R39) -> 0 | S40: =J40+M40+P40 -> 3709.2107 | T40: =S40 -> 3709.2107 | U40: =S40-T40 -> 0
C41: J.2 Total Indirect Cost | J41: =J40 -> 1328.32 | K41: =K40 -> 1328.32 | L41: =L40 -> 0 | M41: =M40 -> 1904.912 | N41: =N40 -> 1904.912 | O41: =O40 -> 0 | P41: =P40 -> 475.9787 | Q41: =Q40 -> 475.9787 | ... U41: =U40 -> 0
C42: K. GRAND TOTAL | J42: =J38+J41 -> 17932.32 | K42: =K38+K41 -> 17932.32 | L42: =L38+L41 -> 0 | M42: =M38+M41 -> 25716.312 | N42: =N38+N41 -> 25716.312 | O42: =O38+O41 -> 0 | P42: =P38+P41 -> 6425.7124 | Q42: =Q38+Q41 -> 6425.7124 | ... U42: =U38+U41 -> 0

Sheet CDM
C1: SUBGRANTEE: CENTRO DE LOS DERECHOS DEL MIGRANTE
A2: Activity Code | B2: Object Code | C2: Budget Line Items | D2: Description | E2: No. | F2: Rate | G2: Unit Type | H2: Frequency | I2: % | J2: YEAR 1 | M2: YEAR 2 | P2: YEAR 3 | S2: Total
J3: Total | K3: Grant | L3: Cost Share | M3: Total | N3: Grant | O3: Cost Share | P3: Total | Q3: Grant | R3: Cost Share | S3: Total | T3: Grant | U3: Cost Share
C4: A. Personnel
A6: SUBCDM | B6: 7370 | C6: A.1 Project Coordinator (60%) | E6: 1 | F6: 1100 | G6: Month | H6: 8 | I6: 0.6 | J6: =(E6*F6*H6*I6) -> 5280 | K6: =J6 -> 5280 | L6: =J6-K6 -> 0 | M6: =(E6*F6*12*I6)*1.025 -> 8118 | N6: =M6 -> 8118 | O6: =M6-N6 -> 0 | P6: =((F6*1.025)*1.025)*I6*3 -> 2080.2375 | Q6: =P6 -> 2080.2375 | R6: =P6-Q6 -> 0 | S6: =J6+M6+P6 -> 15478.237 | T6: =K6+N6+Q6 -> 15478.237 | U6: =L6+O6+R6 -> 0
A7: SUBCDM | B7: 7370 | C7: A.2 Project Administrator (20%) | E7: 1 | F7: 1000 | G7: Month | H7: 8 | I7: 0.2 | J7: =(E7*F7*H7*I7) -> 1600 | K7: =J7 -> 1600 | L7: =J7-K7 -> 0 | M7: =(E7*F7*12*I7)*1.025 -> 2460 | N7: =M7 -> 2460 | O7: =M7-N7 -> 0 | P7: =((F7*1.025)*1.025)*I7*3 -> 630.375 | Q7: =P7 -> 630.375 | R7: =P7-Q7 -> 0 | S7: =J7+M7+P7 -> 4690.375 | T7: =K7+N7+Q7 -> 4690.375 | U7: =L7+O7+R7 -> 0
C8: Subtotal Personnel | J8: =SUM(J5:J7) -> 6880 | K8: =SUM(K5:K7) -> 6880 | L8: =SUM(L5:L7) -> 0 | M8: =SUM(M5:M7) -> 10578 | N8: =SUM(N5:N7) -> 10578 | O8: =SUM(O5:O7) -> 0 | P8: =SUM(P5:P7) -> 2710.6125 | Q8: =SUM(Q5:Q7) -> 2710.6125 | ... U8: =SUM(U5:U7) -> 0
C9: B. Fringe Benefits
A10: SUBCDM | B10: 7370 | C10: B.1 Project Coordinator (60%) | E10: 1 | F10: 1100 | G10: %/ Month | H10: 8 | I10: 0.3 | J10: =(J6*I10) -> 1584 | K10: =J10 -> 1584 | L10: =J10-K10 -> 0 | M10: =(I10*M6) -> 2435.4 | N10: =M10 -> 2435.4 | O10: =M10-N10 -> 0 | P10: =(I10*P6) -> 624.07125 | Q10: =P10 -> 624.07125 | R10: =P10-Q10 -> 0 | S10: =J10+M10+P10 -> 4643.4712 | T10: =K10+N10+Q10 -> 4643.4712 | U10: =L10+O10+R10 -> 0
A11: SUBCDM | B11: 7370 | C11: B.2 Project Administrator (20%) | E11: 1 | F11: 1000 | G11: %/ Month | H11: 8 | I11: 0.3 | J11: =(J7*I11) -> 480 | K11: =J11 -> 480 | L11: =J11-K11 -> 0 | M11: =(I11*M7) -> 738 | N11: =M11 -> 738 | O11: =M11-N11 -> 0 | P11: =(I11*P7) -> 189.1125 | Q11: =P11 -> 189.1125 | R11: =P11-Q11 -> 0 | S11: =J11+M11+P11 -> 1407.1125 | T11: =K11+N11+Q11 -> 1407.1125 | U11: =L11+O11+R11 -> 0
C12: Subtotal Fringe Benefits | J12: =SUM(J10:J11) -> 2064 | K12: =SUM(K10:K11) -> 2064 | L12: =SUM(L10:L11) -> 0 | M12: =SUM(M10:M11) -> 3173.4 | N12: =SUM(N10:N11) -> 3173.4 | O12: =SUM(O10:O11) -> 0 | P12: =SUM(P10:P11) -> 813.18375 | Q12: =SUM(Q10:Q11) -> 813.18375 | ... U12: =SUM(U10:U11) -> 0
C13: C. Travel
A14: SUBCDM | B14: 7370 | C14: C.1 Ground Transportation | E14: 1 | F14: 150 | G14: Monthly | H14: 6 | I14: 1 | J14: =(E14*F14*H14*I14) -> 900 | K14: =J14 -> 900 | L14: =J14-K14 -> 0 | M14: =(E14*F14*8*I14)*1.025 -> 1230 | N14: =M14 -> 1230 | O14: =M14-N14 -> 0 | P14: =(E14*(F14*1.025)*2*I14)*1.025 -> 315.1875 | Q14: =P14 -> 315.1875 | R14: =P14-Q14 -> 0 | S14: =J14+M14+P14 -> 2445.1875 | T14: =K14+N14+Q14 -> 2445.1875 | U14: =L14+O14+R14 -> 0
A15: SUBCDM | B15: 7370 | C15: C.2 Lodging | E15: =E7 -> 1 | F15: 300 | G15: Monthly | H15: 6 | I15: 1 | J15: =(E15*F15*H15*I15) -> 1800 | K15: =J15 -> 1800 | L15: =J15-K15 -> 0 | M15: =(E15*F15*8*I15)*1.025 -> 2460 | N15: =M15 -> 2460 | O15: =M15-N15 -> 0 | P15: =(E15*(F15*1.025)*2*I15)*1.025 -> 630.375 | Q15: =P15 -> 630.375 | R15: =P15-Q15 -> 0 | S15: =J15+M15+P15 -> 4890.375 | T15: =K15+N15+Q15 -> 4890.375 | U15: =L15+O15+R15 -> 0
A16: SUBCDM | B16: 7370 | C16: C.3 M&IE | E16: 1 | F16: 300 | G16: Monthly | H16: 6 | I16: 1 | J16: =(E16*F16*H16*I16) -> 1800 | K16: =J16 -> 1800 | L16: =J16-K16 -> 0 | M16: =(E16*F16*8*I16)*1.025 -> 2460 | N16: =M16 -> 2460 | O16: =M16-N16 -> 0 | P16: =(E16*(F16*1.025)*2*I16)*1.025 -> 630.375 | Q16: =P16 -> 630.375 | R16: =P16-Q16 -> 0 | S16: =J16+M16+P16 -> 4890.375 | T16: =K16+N16+Q16 -> 4890.375 | U16: =L16+O16+R16 -> 0
C17: Subtotal Travel | J17: =SUM(J14:J16) -> 4500 | K17: =SUM(K14:K16) -> 4500 | L17: =SUM(L14:L16) -> 0 | M17: =SUM(M14:M16) -> 6150 | N17: =SUM(N14:N16) -> 6150 | O17: =SUM(O14:O16) -> 0 | P17: =SUM(P14:P16) -> 1575.9375 | Q17: =SUM(Q14:Q16) -> 1575.9375 | ... U17: =SUM(U14:U16) -> 0
C18: D. Equipment
C19: E. Supplies
C20: F. Contractual and Subaward
C21: G. Construction
C22: H. Other Direct Costs
C23: Objectives and Activities
C24: O1: Increase workers’ knowledge of labor law, and ability to understand the applicability of labor regulations and international labor standards relevant to the United 2026 games.
C25: H.1: Activity 1: Expand educational programs led by labor rights organizations in Mexico with experience in popular education methods, to train workers on protections under Mexican labor law, international labor standards, business and human rights frameworks relevant to the United 2026 games, and the risks of the games for Mexican workers.
A26: SUBCDM | B26: 7370 | C26: H.1.1 Labor rights trainings for workers on labor law | E26: 1 | F26: 150 | G26: Workshop | H26: 4 | I26: 1 | J26: =E26*F26*H26*I26 -> 600 | K26: =J26 -> 600 | L26: =J26-K26 -> 0 | M26: =E26*F26*H26*I26 -> 600 | N26: =M26 -> 600 | O26: =M26-N26 -> 0 | P26: =E26*F26*0*I26 -> 0 | Q26: =P26 -> 0 | R26: =P26-Q26 -> 0 | S26: =J26+M26+P26 -> 1200 | T26: =K26+N26+Q26 -> 1200 | U26: =S26-T26 -> 0
A27: SUBCDM | B27: 7370 | C27: H.1.2 Printing of materials for labor rights trainings | E27: 1 | F27: 60 | G27: Workshop | H27: 4 | I27: 1 | J27: =F27*H27*I27 -> 240 | K27: =J27 -> 240 | L27: =J27-K27 -> 0 | M27: =F27*H27*I27 -> 240 | N27: =M27 -> 240 | O27: =M27-N27 -> 0 | P27: =E27*F27*0*I27 -> 0 | Q27: =P27 -> 0 | R27: =P27-Q27 -> 0 | S27: =J27+M27+P27 -> 480 | T27: =K27+N27+Q27 -> 480 | U27: =S27-T27 -> 0
A28: SUBCDM | B28: 7370 | C28: H.1.3 Lodging for participants | E28: 1 | F28: 300 | G28: Workshop | H28: 4 | I28: 1 | J28: =F28*H28*I28 -> 1200 | K28: =J28 -> 1200 | L28: =J28-K28 -> 0 | M28: =F28*H28*I28 -> 1200 | N28: =M28 -> 1200 | O28: =M28-N28 -> 0 | P28: =E28*F28*0*I28 -> 0 | Q28: =P28 -> 0 | R28: =P28-Q28 -> 0 | S28: =J28+M28+P28 -> 2400 | T28: =K28+N28+Q28 -> 2400 | U28: =S28-T28 -> 0
A29: SUBCDM | B29: 7370 | C29: H.1.4 Transportation for participants | E29: 1 | F29: 80 | G29: Workshop | H29: 4 | I29: 1 | J29: =F29*H29*I29 -> 320 | K29: =J29 -> 320 | L29: =J29-K29 -> 0 | M29: =F29*H29*I29 -> 320 | N29: =M29 -> 320 | O29: =M29-N29 -> 0 | P29: =E29*F29*0*I29 -> 0 | Q29: =P29 -> 0 | R29: =P29-Q29 -> 0 | S29: =J29+M29+P29 -> 640 | T29: =K29+N29+Q29 -> 640 | U29: =S29-T29 -> 0
A30: SUBCDM | B30: 7370 | C30: H.1.5 Worker outreach campaign | E30: 1 | F30: 300 | G30: Campaign | H30: 2 | I30: 1 | J30: =E30*F30*H30*I30 -> 600 | K30: =J30 -> 600 | L30: 0 | M30: =E30*F30*H30*I30 -> 600 | N30: =M30 -> 600 | O30: =M30-N30 -> 0 | P30: =E30*F30*0*I30 -> 0 | Q30: =P30 -> 0 | R30: =P30-Q30 -> 0 | S30: =J30+M30+P30 -> 1200 | T30: =K30+N30+Q30 -> 1200 | U30: =S30-T30 -> 0
C31: O2: Increase engagement and coordination between labor rights organizations, the private sector, and democratic, independent unions on the UHRS and around pre-games planning of United 2026 events, including the implementation of the human rights strategy in each host city, and ways that the Government of Mexico, FIFA and the Mexican National Soccer Federation will address and mitigate labor rights risks associated with the games.
C32: H.2 Activity 2: Establish and facilitate a civil society labor advisory network in Mexico.
A33: SUBCDM | B33: 7370 | C33: H.2.1 Coordination Meetings | E33: 1 | F33: 100 | G33: Meeting | H33: 3 | I33: 1 | J33: =E33*F33*H33*I33 -> 300 | K33: =J33 -> 300 | L33: =J33-K33 -> 0 | M33: =E33*F33*H33*I33 -> 300 | N33: =M33 -> 300 | O33: =M33-N33 -> 0 | P33: =E33*F33*2*I33 -> 200 | Q33: =P33 -> 200 | R33: =P33-Q33 -> 0 | S33: =J33+M33+P33 -> 800 | T33: =K33+N33+Q33 -> 800 | U33: =S33-T33 -> 0
C34: O4: Increase awareness among the general public of Mexico’s commitments to human rights in regard to the United 2026 games.
C35: H.3: Activity 5 - Provide technical assistance to civil society to develop a media campaign to socialize information of labor rights risks in preparation for the United 2026 games
A36: SUBCDM | B36: 7370 | C36: H.3.1 Website for labor rights violations | E36: 1 | F36: 1500 | G36: Website | H36: 1 | I36: 1 | J36: =E36*F36*0*I36 -> 0 | K36: =J36 -> 0 | L36: 0 | M36: =E36*F36*H36*I36 -> 1500 | N36: =M36 -> 1500 | O36: =M36-N36 -> 0 | P36: =E36*F36*0*I36 -> 0 | Q36: =P36 -> 0 | R36: =P36-Q36 -> 0 | S36: =J36+M36+P36 -> 1500 | T36: =K36+N36+Q36 -> 1500 | U36: =S36-T36 -> 0
A37: SUBCDM | B37: 7370 | C37: H.3.2 United 2026 media campaign | E37: 1 | F37: 500 | G37: Campaign | H37: 1 | I37: 1 | J37: =E37*F37*H37*I37 -> 500 | K37: =J37 -> 500 | L37: 0 | M37: =E37*F37*H37*I37 -> 500 | N37: =M37 -> 500 | O37: =M37-N37 -> 0 | P37: =E37*F37*H37*I37 -> 500 | Q37: =P37 -> 500 | R37: =P37-Q37 -> 0 | S37: =J37+M37+P37 -> 1500 | T37: =K37+N37+Q37 -> 1500 | U37: =S37-T37 -> 0
A38: SUBCDM | B38: 7370 | C38: H.3.2 Information sessions for the general public | E38: 1 | F38: 300 | G38: Event | H38: 2 | I38: 1 | J38: =E38*F38*H38*I38 -> 600 | K38: =J38 -> 600 | L38: 0 | M38: =E38*F38*H38*I38 -> 600 | N38: =M38 -> 600 | O38: =M38-N38 -> 0 | P38: =E38*F38*H38*I38 -> 600 | Q38: =P38 -> 600 | R38: =P38-Q38 -> 0 | S38: =J38+M38+P38 -> 1800 | T38: =K38+N38+Q38 -> 1800 | U38: =S38-T38 -> 0
A39: SUBCDM | B39: 7370 | C39: H.3.4 Development/Printing of materials for information sessions | E39: 1 | F39: 100 | G39: Event | H39: 2 | I39: 1 | J39: =E39*F39*H39*I39 -> 200 | K39: =J39 -> 200 | L39: 0 | M39: =E39*F39*H39*I39 -> 200 | N39: =M39 -> 200 | O39: =M39-N39 -> 0 | P39: =E39*F39*H39*I39 -> 200 | Q39: =P39 -> 200 | R39: =P39-Q39 -> 0 | S39: =J39+M39+P39 -> 600 | T39: =K39+N39+Q39 -> 600 | U39: =S39-T39 -> 0
C40: Subtotal Other Direct Costs | J40: =SUM(J26:J39) -> 4560 | K40: =SUM(K26:K39) -> 4560 | L40: =SUM(L26:L39) -> 0 | M40: =SUM(M26:M39) -> 6060 | N40: =SUM(N26:N39) -> 6060 | O40: =SUM(O26:O39) -> 0 | P40: =SUM(P26:P39) -> 1500 | Q40: =SUM(Q26:Q39) -> 1500 | ... U40: =SUM(U26:U39) -> 0
C41: I. Total Direct Costs | J41: =J8+J12+J17+J40 -> 18004 | K41: =J41 -> 18004 | L41: =J41-K41 -> 0 | M41: =M8+M12+M17+M40 -> 25961.4 | N41: =M41 -> 25961.4 | O41: =M41-N41 -> 0 | P41: =P8+P12+P17+P40 -> 6599.7338 | Q41: =P41 -> 6599.7338 | R41: =P41-Q41 -> 0 | S41: =S8+S12+S17+S40 -> 50565.134 | T41: =S41 -> 50565.134 | U41: =SUM(U8+U17+U40) -> 0
C42: J. Indirect Cost
A43: SUBCDM | B43: 7370 | C43: J.1 Administrative Cost (8%) | F43: 0.08 | I43: 1 | J43: =J41*F43*I43 -> 1440.32 | K43: =J43 -> 1440.32 | L43: =SUM(L41:L42) -> 0 | M43: =M41*F43*I43 -> 2076.912 | N43: =M43 -> 2076.912 | O43: =SUM(O41:O42) -> 0 | P43: =P41*F43*I43 -> 527.9787 | Q43: =P43 -> 527.9787 | R43: =SUM(R41:R42) -> 0 | S43: =J43+M43+P43 -> 4045.2107 | T43: =S43 -> 4045.2107 | U43: =S43-T43 -> 0
C44: J.2 Total Indirect Cost | J44: =J43 -> 1440.32 | K44: =K43 -> 1440.32 | L44: =L43 -> 0 | M44: =M43 -> 2076.912 | N44: =N43 -> 2076.912 | O44: =O43 -> 0 | P44: =P43 -> 527.9787 | Q44: =Q43 -> 527.9787 | ... U44: =U43 -> 0
C45: K. GRAND TOTAL | J45: =J41+J44 -> 19444.32 | K45: =K41+K44 -> 19444.32 | L45: =L41+L44 -> 0 | M45: =M41+M44 -> 28038.312 | N45: =N41+N44 -> 28038.312 | O45: =O41+O44 -> 0 | P45: =P41+P44 -> 7127.7124 | Q45: =Q41+Q44 -> 7127.7124 | ... U45: =U41+U44 -> 0

Sheet RMS
C1: SUBGRANTEE: RED DE MUJERES SINDICALISTAS
A2: Activity Code | B2: Object Code | C2: Budget Line Items | D2: Description | E2: No. | F2: Rate | G2: Unit Type | H2: Frequency | I2: % | J2: YEAR 1 | M2: YEAR 2 | P2: YEAR 3 | S2: Total
J3: Total | K3: Grant | L3: Cost Share | M3: Total | N3: Grant | O3: Cost Share | P3: Total | Q3: Grant | R3: Cost Share | S3: Total | T3: Grant | U3: Cost Share
C4: A. Personnel
A5: SUBRMS | B5: 7370 | C5: A.1 Project Coordinator (60%) | E5: 1 | F5: 1100 | G5: Month | H5: 8 | I5: 0.6 | J5: =(E5*F5*H5*I5) -> 5280 | K5: =J5 -> 5280 | L5: =J5-K5 -> 0 | M5: =(E5*F5*12*I5)*1.025 -> 8118 | N5: =M5 -> 8118 | O5: =M5-N5 -> 0 | P5: =((F5*1.025)*1.025)*I5*3 -> 2080.2375 | Q5: =P5 -> 2080.2375 | R5: =P5-Q5 -> 0 | S5: =J5+M5+P5 -> 15478.237 | T5: =K5+N5+Q5 -> 15478.237 | U5: =L5+O5+R5 -> 0
A6: SUBRMS | B6: 7370 | C6: A.2 Project Administrator (20%) | E6: 1 | F6: 1000 | G6: Month | H6: 8 | I6: 0.2 | J6: =(E6*F6*H6*I6) -> 1600 | K6: =J6 -> 1600 | L6: =J6-K6 -> 0 | M6: =(E6*F6*12*I6)*1.025 -> 2460 | N6: =M6 -> 2460 | O6: =M6-N6 -> 0 | P6: =((F6*1.025)*1.025)*I6*3 -> 630.375 | Q6: =P6 -> 630.375 | R6: =P6-Q6 -> 0 | S6: =J6+M6+P6 -> 4690.375 | T6: =K6+N6+Q6 -> 4690.375 | U6: =L6+O6+R6 -> 0
C7: Subtotal Personnel | J7: =SUM(J5:J6) -> 6880 | K7: =SUM(K5:K6) -> 6880 | L7: =SUM(L5:L6) -> 0 | M7: =SUM(M5:M6) -> 10578 | N7: =SUM(N5:N6) -> 10578 | O7: =SUM(O5:O6) -> 0 | P7: =SUM(P5:P6) -> 2710.6125 | Q7: =SUM(Q5:Q6) -> 2710.6125 | ... U7: =SUM(U5:U6) -> 0
C8: B. Fringe Benefits
A9: SUBRMS | B9: 7370 | C9: B.1 Project Coordinator (60%) | E9: 1 | F9: 1100 | G9: %/ Month | H9: 8 | I9: 0.3 | J9: =(J5*I9) -> 1584 | K9: =J9 -> 1584 | L9: =J9-K9 -> 0 | M9: =(I9*M5) -> 2435.4 | N9: =M9 -> 2435.4 | O9: =M9-N9 -> 0 | P9: =(I9*P5) -> 624.07125 | Q9: =P9 -> 624.07125 | R9: =P9-Q9 -> 0 | S9: =J9+M9+P9 -> 4643.4712 | T9: =K9+N9+Q9 -> 4643.4712 | U9: =L9+O9+R9 -> 0
A10: SUBRMS | B10: 7370 | C10: B.2 Project Administrator (20%) | E10: 1 | F10: 1000 | G10: %/ Month | H10: 8 | I10: 0.3 | J10: =(J6*I10) -> 480 | K10: =J10 -> 480 | L10: =J10-K10 -> 0 | M10: =(I10*M6) -> 738 | N10: =M10 -> 738 | O10: =M10-N10 -> 0 | P10: =(I10*P6) -> 189.1125 | Q10: =P10 -> 189.1125 | R10: =P10-Q10 -> 0 | S10: =J10+M10+P10 -> 1407.1125 | T10: =K10+N10+Q10 -> 1407.1125 | U10: =L10+O10+R10 -> 0
C11: Subtotal Fringe Benefits | J11: =SUM(J9:J10) -> 2064 | K11: =SUM(K9:K10) -> 2064 | L11: =SUM(L9:L10) -> 0 | M11: =SUM(M9:M10) -> 3173.4 | N11: =SUM(N9:N10) -> 3173.4 | O11: =SUM(O9:O10) -> 0 | P11: =SUM(P9:P10) -> 813.18375 | Q11: =SUM(Q9:Q10) -> 813.18375 | ... U11: =SUM(U9:U10) -> 0
C12: C. Travel
A13: SUBRMS | B13: 7370 | C13: C.1 Ground Transportation | E13: 1 | F13: 150 | G13: Monthly | H13: 6 | I13: 1 | J13: =(E13*F13*H13*I13) -> 900 | K13: =J13 -> 900 | L13: =J13-K13 -> 0 | M13: =(E13*F13*8*I13)*1.025 -> 1230 | N13: =M13 -> 1230 | O13: =M13-N13 -> 0 | P13: =(E13*(F13*1.025)*2*I13)*1.025 -> 315.1875 | Q13: =P13 -> 315.1875 | R13: =P13-Q13 -> 0 | S13: =J13+M13+P13 -> 2445.1875 | T13: =K13+N13+Q13 -> 2445.1875 | U13: =L13+O13+R13 -> 0
A14: SUBRMS | B14: 7370 | C14: C.2 Lodging | E14: =E6 -> 1 | F14: 300 | G14: Monthly | H14: 6 | I14: 1 | J14: =(E14*F14*H14*I14) -> 1800 | K14: =J14 -> 1800 | L14: =J14-K14 -> 0 | M14: =(E14*F14*8*I14)*1.025 -> 2460 | N14: =M14 -> 2460 | O14: =M14-N14 -> 0 | P14: =(E14*(F14*1.025)*2*I14)*1.025 -> 630.375 | Q14: =P14 -> 630.375 | R14: =P14-Q14 -> 0 | S14: =J14+M14+P14 -> 4890.375 | T14: =K14+N14+Q14 -> 4890.375 | U14: =L14+O14+R14 -> 0
A15: SUBRMS | B15: 7370 | C15: C.3 M&IE | E15: 1 | F15: 300 | G15: Monthly | H15: 6 | I15: 1 | J15: =(E15*F15*H15*I15) -> 1800 | K15: =J15 -> 1800 | L15: =J15-K15 -> 0 | M15: =(E15*F15*8*I15)*1.025 -> 2460 | N15: =M15 -> 2460 | O15: =M15-N15 -> 0 | P15: =(E15*(F15*1.025)*2*I15)*1.025 -> 630.375 | Q15: =P15 -> 630.375 | R15: =P15-Q15 -> 0 | S15: =J15+M15+P15 -> 4890.375 | T15: =K15+N15+Q15 -> 4890.375 | U15: =L15+O15+R15 -> 0
C16: Subtotal Travel | J16: =SUM(J13:J15) -> 4500 | K16: =SUM(K13:K15) -> 4500 | L16: =SUM(L13:L15) -> 0 | M16: =SUM(M13:M15) -> 6150 | N16: =SUM(N13:N15) -> 6150 | O16: =SUM(O13:O15) -> 0 | P16: =SUM(P13:P15) -> 1575.9375 | Q16: =SUM(Q13:Q15) -> 1575.9375 | ... U16: =SUM(U13:U15) -> 0
C17: D. Equipment
C18: E. Supplies
C19: F. Contractual and Subaward
C20: G. Construction
C21: H. Other Direct Costs
C22: Objectives and Activities
C23: O1: Increase workers’ knowledge of labor law, and ability to understand the applicability of labor regulations and international labor standards relevant to the United 2026 games.
C24: H.1: Activity 1: Expand educational programs led by labor rights organizations in Mexico with experience in popular education methods, to train workers on protections under Mexican labor law, international labor standards, business and human rights frameworks relevant to the United 2026 games, and the risks of the games for Mexican workers.
A25: SUBRMS | B25: 7370 | C25: H.1.1 Labor rights trainings for workers on labor law (including venue and materials) | E25: 1 | F25: 150 | G25: Workshop | H25: 4 | I25: 1 | J25: =E25*F25*H25*I25 -> 600 | K25: =J25 -> 600 | L25: =J25-K25 -> 0 | M25: =E25*F25*H25*I25 -> 600 | N25: =M25 -> 600 | O25: =M25-N25 -> 0 | P25: =E25*F25*0*I25 -> 0 | Q25: =P25 -> 0 | R25: =P25-Q25 -> 0 | S25: =J25+M25+P25 -> 1200 | T25: =K25+N25+Q25 -> 1200 | U25: =S25-T25 -> 0
A26: SUBRMS | B26: 7370 | C26: H.1.2 Printing of materials for labor rights trainings | E26: 1 | F26: 60 | G26: Workshop | H26: 4 | I26: 1 | J26: =F26*H26*I26 -> 240 | K26: =J26 -> 240 | L26: =J26-K26 -> 0 | M26: =F26*H26*I26 -> 240 | N26: =M26 -> 240 | O26: =M26-N26 -> 0 | P26: =E26*F26*0*I26 -> 0 | Q26: =P26 -> 0 | R26: =P26-Q26 -> 0 | S26: =J26+M26+P26 -> 480 | T26: =K26+N26+Q26 -> 480 | U26: =S26-T26 -> 0
A27: SUBRMS | B27: 7370 | C27: H.1.3 Lodging for participants | E27: 1 | F27: 300 | G27: Workshop | H27: 4 | I27: 1 | J27: =F27*H27*I27 -> 1200 | K27: =J27 -> 1200 | L27: =J27-K27 -> 0 | M27: =F27*H27*I27 -> 1200 | N27: =M27 -> 1200 | O27: =M27-N27 -> 0 | P27: =E27*F27*0*I27 -> 0 | Q27: =P27 -> 0 | R27: =P27-Q27 -> 0 | S27: =J27+M27+P27 -> 2400 | T27: =K27+N27+Q27 -> 2400 | U27: =S27-T27 -> 0
A28: SUBRMS | B28: 7370 | C28: H.1.4 Transportation for participants | E28: 1 | F28: 80 | G28: Workshop | H28: 4 | I28: 1 | J28: =F28*H28*I28 -> 320 | K28: =J28 -> 320 | L28: =J28-K28 -> 0 | M28: =F28*H28*I28 -> 320 | N28: =M28 -> 320 | O28: =M28-N28 -> 0 | P28: =E28*F28*0*I28 -> 0 | Q28: =P28 -> 0 | R28: =P28-Q28 -> 0 | S28: =J28+M28+P28 -> 640 | T28: =K28+N28+Q28 -> 640 | U28: =S28-T28 -> 0
A29: SUBRMS | B29: 7370 | C29: H.1.5 Worker outreach campaign | E29: 1 | F29: 300 | G29: Campaign | H29: 2 | I29: 1 | J29: =E29*F29*H29*I29 -> 600 | K29: =J29 -> 600 | L29: 0 | M29: =E29*F29*H29*I29 -> 600 | N29: =M29 -> 600 | O29: =M29-N29 -> 0 | P29: =E29*F29*0*I29 -> 0 | Q29: =P29 -> 0 | R29: =P29-Q29 -> 0 | S29: =J29+M29+P29 -> 1200 | T29: =K29+N29+Q29 -> 1200 | U29: =S29-T29 -> 0
C30: O2: Increase engagement and coordination between labor rights organizations, the private sector, and democratic, independent unions on the UHRS and around pre-games planning of United 2026 events, including the implementation of the human rights strategy in each host city, and ways that the Government of Mexico, FIFA and the Mexican National Soccer Federation will address and mitigate labor rights risks associated with the games.
C31: H.2 Activity 2- Establish and facilitate a civil society labor advisory network in Mexico
A32: SUBRMS | B32: 7370 | C32: H.2.1 Coordination meetings (including materials) | E32: 1 | F32: 120 | G32: Meeting | H32: 3 | I32: 1 | J32: =E32*H32*F32*I32 -> 360 | K32: =J32 -> 360 | L32: 0 | M32: =E32*F32*H32*I32 -> 360 | N32: =M32 -> 360 | O32: =M32-N32 -> 0 | P32: =0*F32*H32*I32 -> 0 | Q32: =P32 -> 0 | R32: =P32-Q32 -> 0 | S32: =J32+M32+P32 -> 720 | T32: =K32+N32+Q32 -> 720 | U32: =S32-T32 -> 0
C33: O4: Increase awareness among the general public of Mexico’s commitments to human rights in regard to the United 2026 games.
C34: H.3: Activity 5 - Provide technical assistance to civil society to develop a media campaign to socialize information of labor rights risks in preparation for the United 2026 games.
A35: SUBRMS | B35: 7370 | C35: H.3.1 United 2026 media campaign | E35: 1 | F35: 600 | G35: Campaign | H35: 1 | I35: 1 | J35: =E35*F35*H35*I35 -> 600 | K35: =J35 -> 600 | L35: 0 | M35: =E35*F35*H35*I35 -> 600 | N35: =M35 -> 600 | O35: =M35-N35 -> 0 | P35: =E35*F35*H35*I35 -> 600 | Q35: =P35 -> 600 | R35: =P35-Q35 -> 0 | S35: =J35+M35+P35 -> 1800 | T35: =K35+N35+Q35 -> 1800 | U35: =S35-T35 -> 0
A36: SUBRMS | B36: 7370 | C36: H.3.2 Information sessions for the general public | E36: 1 | F36: 300 | G36: Event | H36: 2 | I36: 1 | J36: =E36*F36*H36*I36 -> 600 | K36: =J36 -> 600 | L36: 0 | M36: =E36*F36*H36*I36 -> 600 | N36: =M36 -> 600 | O36: =M36-N36 -> 0 | P36: =E36*F36*H36*I36 -> 600 | Q36: =P36 -> 600 | R36: =P36-Q36 -> 0 | S36: =J36+M36+P36 -> 1800 | T36: =K36+N36+Q36 -> 1800 | U36: =S36-T36 -> 0
A37: SUBRMS | B37: 7370 | C37: H.3.3 Development/Printing of materials for information sessions | E37: 1 | F37: 100 | G37: Event | H37: 2 | I37: 1 | J37: =E37*F37*H37*I37 -> 200 | K37: =J37 -> 200 | L37: 0 | M37: =E37*F37*H37*I37 -> 200 | N37: =M37 -> 200 | O37: =M37-N37 -> 0 | P37: =E37*F37*H37*I37 -> 200 | Q37: =P37 -> 200 | R37: =P37-Q37 -> 0 | S37: =J37+M37+P37 -> 600 | T37: =K37+N37+Q37 -> 600 | U37: =S37-T37 -> 0
C38: Subtotal Other Direct Costs | J38: =SUM(J25:J37) -> 4720 | K38: =SUM(K25:K37) -> 4720 | L38: =SUM(L25:L37) -> 0 | M38: =SUM(M25:M37) -> 4720 | N38: =SUM(N25:N37) -> 4720 | O38: =SUM(O25:O35) -> 0 | P38: =SUM(P25:P37) -> 1400 | Q38: =SUM(Q25:Q37) -> 1400 | R38: =SUM(R25:R37) -> 0 | S38: =SUM(S25:S37) -> 10840 | T38: =SUM(T25:T37) -> 10840 | U38: =SUM(U25:U37) -> 0
C39: I. Total Direct Costs | J39: =J7+J11+J16+J38 -> 18164 | K39: =J39 -> 18164 | L39: =J39-K39 -> 0 | M39: =M7+M11+M16+M38 -> 24621.4 | N39: =M39 -> 24621.4 | O39: =M39-N39 -> 0 | P39: =P7+P11+P16+P38 -> 6499.7338 | Q39: =P39 -> 6499.7338 | R39: =P39-Q39 -> 0 | S39: =S7+S11+S16+S38 -> 49285.134 | T39: =S39 -> 49285.134 | U39: =SUM(U7+U16+U38) -> 0
C40: J. Indirect Cost
A41: SUBRMS | B41: 7370 | C41: J.1 Red de Mujeres Sindicalistas Administrative Cost (8%) | F41: 0.08 | I41: 1 | J41: =J39*F41*I41 -> 1453.12 | K41: =J41 -> 1453.12 | L41: =SUM(L39:L40) -> 0 | M41: =M39*F41*I41 -> 1969.712 | N41: =M41 -> 1969.712 | O41: =SUM(O39:O40) -> 0 | P41: =P39*F41*I41 -> 519.9787 | Q41: =P41 -> 519.9787 | R41: =SUM(R39:R40) -> 0 | S41: =J41+M41+P41 -> 3942.8107 | T41: =S41 -> 3942.8107 | U41: =S41-T41 -> 0
C42: J.2 Total Indirect Cost | J42: =J41 -> 1453.12 | K42: =K41 -> 1453.12 | L42: =L41 -> 0 | M42: =M41 -> 1969.712 | N42: =N41 -> 1969.712 | O42: =O41 -> 0 | P42: =P41 -> 519.9787 | Q42: =Q41 -> 519.9787 | ... U42: =U41 -> 0
C43: K. GRAND TOTAL | J43: =J39+J42 -> 19617.12 | K43: =K39+K42 -> 19617.12 | L43: =L39+L42 -> 0 | M43: =M39+M42 -> 26591.112 | N43: =N39+N42 -> 26591.112 | O43: =O39+O42 -> 0 | P43: =P39+P42 -> 7019.7124 | Q43: =Q39+Q42 -> 7019.7124 | ... U43: =U39+U42 -> 0

Sheet Consultants
A1: CONSULTANTS
A2: Budget Line Items | B2: No. | C2: Rate | D2: Unit Type | E2: Frequency | F2: % | G2: YEAR 1 | J2: YEAR 2 | M2: YEAR 3 | P2: Total
G3: Total | H3: Grant | I3: Cost Share | J3: Total | K3: Grant | L3: Cost Share | M3: Total | N3: Grant | O3: Cost Share | P3: Total | Q3: Grant | R3: Cost Share
A4: Consultants
A5: Consultant (Activity 1) | B5: 1 | C5: 120 | D5: Days | E5: 20 | F5: 1 | G5: =B5*C5*E5*F5 -> 2400 | H5: =G5 -> 2400 | I5: =G5-H5 -> 0 | J5: 0 | K5: =J5 -> 0 | L5: =J5-K5 -> 0 | M5: 0 | N5: =M5 -> 0 | O5: =M5-N5 -> 0 | P5: =G5+J5+M5 -> 2400 | Q5: =P5 -> 2400 | R5: =P5-Q5 -> 0
A6: Communications Specialist | B6: 1 | C6: 120 | D6: Days | E6: 25 | F6: 1 | G6: =B6*C6*E6*F6 -> 3000 | H6: =G6 -> 3000 | I6: =G6-H6 -> 0 | J6: =B6*C6*E6*F6 -> 3000 | K6: =J6 -> 3000 | L6: =J6-K6 -> 0 | M6: =B6*C6*E6*F6 -> 3000 | N6: =M6 -> 3000 | O6: =M6-N6 -> 0 | P6: =G6+J6+M6 -> 9000 | Q6: =P6 -> 9000 | R6: =P6-Q6 -> 0
A7: Subtotal Consultants | G7: =SUM(G5:G6) -> 5400 | H7: =SUM(H5:H6) -> 5400 | I7: =SUM(I5:I6) -> 0 | J7: =SUM(J5:J6) -> 3000 | K7: =SUM(K5:K6) -> 3000 | L7: =SUM(L5:L6) -> 0 | M7: =SUM(M5:M6) -> 3000 | N7: =SUM(N5:N6) -> 3000 | ... R7: =SUM(R5:R6) -> 0
A8: GRAND TOTAL | G8: =G7 -> 5400 | H8: =H7 -> 5400 | I8: =I7 -> 0 | J8: =J7 -> 3000 | K8: =K7 -> 3000 | L8: =L7 -> 0 | M8: =M7 -> 3000 | N8: =N7 -> 3000 | ... R8: =R7 -> 0

Sheet Detailed Budget (2)
A1: ='Budget Summary'!C4 -> Year 1 | C1: 2017 | K1: 2018 | Q1: 2019 | W1: Total
A2: Account Code | B2: All costs in US$ | C2: No. | D2: Unit Type | E2: No. of Units | F2: % | G2: Rate | H2: Total | I2: Grant | J2: CRS | K2: No. | L2: Freq. | M2: Rate | N2: Total | O2: Grant | P2: CRS | Q2: No. | R2: Freq. | S2: Rate | T2: Total | U2: Grant | V2: CRS | W2: Grant | X2: CRS | Y2: Grand Total
A3: 6052, 6069 | B3: Personnel | G3: 65 | I3: 0.85 | J3: =(100%-I3) -> 0.15 | M3: 1.36909 | O3: 1.2999 | P3: =(100%-O3) -> -0.2999 | S3: 1.36909 | U3: -0.04571 | V3: =(100%-U3) -> 1.04571
B4: Staff Salaries
B5: Head of Office | C5: 0.3 | D5: FTE | E5: 12 | F5: 1 | G5: =(1391532.0682/$G$3)/12 -> 1784.0155 | H5: =C5*G5*E5 -> 6422.4557 | I5: =H5 -> 6422.4557 | J5: =H5-I5 -> 0 | K5: =C5 -> 0.3 | L5: =E5 -> 12 | M5: =G5*1.05 -> 1873.2162 | N5: =K5*M5*L5 -> 6743.5785 | O5: =N5 -> 6743.5785 | P5: =N5-O5 -> 0 | Q5: =K5 -> 0.3 | R5: =L5 -> 12 | S5: =M5*1.05 -> 1966.8771 | T5: =Q5*S5*R5 -> 7080.7574 | U5: =T5 -> 7080.7574 | V5: =T5-U5 -> 0 | W5: =I5+O5+U5 -> 20246.792 | X5: =J5+P5+V5 -> 0 | Y5: =W5+X5 -> 20246.792 | Z5: =H5+N5+T5-Y5 -> 0 | AA5: =I5+O5+U5-W5 -> 0 | AB5: =J5+P5+V5-X5 -> 0
B6: Program Coordinator | C6: 0.8 | D6: FTE | E6: 12 | F6: 1 | G6: =(881322/$G$3)/12 -> 1129.9 | H6: =C6*G6*E6 -> 10847.04 | I6: =H6 -> 10847.04 | J6: 0 | K6: =C6 -> 0.8 | L6: =E6 -> 12 | M6: =G6*1.05 -> 1186.395 | N6: =K6*M6*L6 -> 11389.392 | O6: =N6 -> 11389.392 | P6: 0 | Q6: =K6 -> 0.8 | R6: =L6 -> 12 | S6: =M6*1.05 -> 1245.7148 | T6: =Q6*S6*R6 -> 11958.862 | U6: =T6 -> 11958.862 | V6: 0 | W6: =I6+O6+U6 -> 34195.294 | X6: =J6+P6+V6 -> 0 | Y6: =W6+X6 -> 34195.294 | Z6: =H6+N6+T6-Y6 -> 0 | AA6: =I6+O6+U6-W6 -> 0 | AB6: =J6+P6+V6-X6 -> 0
B7: Finance officer | C7: 0.2 | D7: FTE | E7: 12 | F7: 1 | G7: =(583144.65/$G$3)/12 -> 747.62135 | H7: =C7*G7*E7 -> 1794.2912 | I7: =H7 -> 1794.2912 | J7: =H7-I7 -> 0 | K7: =C7 -> 0.2 | L7: =E7 -> 12 | M7: =G7*1.05 -> 785.00241 | N7: =K7*M7*L7 -> 1884.0058 | O7: =N7 -> 1884.0058 | P7: =N7-O7 -> 0 | Q7: =K7 -> 0.2 | R7: =L7 -> 12 | S7: =M7*1.05 -> 824.25253 | T7: =Q7*S7*R7 -> 1978.2061 | U7: =T7 -> 1978.2061 | V7: =T7-U7 -> 0 | W7: =I7+O7+U7 -> 5656.5031 | X7: =J7+P7+V7 -> 0 | Y7: =W7+X7 -> 5656.5031 | Z7: =H7+N7+T7-Y7 -> 0 | AA7: =I7+O7+U7-W7 -> 0 | AB7: =J7+P7+V7-X7 -> 0
B8: Administrative Staff | C8: 0.6 | D8: FTE | E8: 12 | F8: 1 | G8: =(1126756.3725/$G$3)/4/12 -> 361.13986 | H8: =C8*G8*E8 -> 2600.207 | I8: =H8 -> 2600.207 | J8: =H8-I8 -> 0 | K8: =C8 -> 0.6 | L8: =E8 -> 12 | M8: =G8*1.05 -> 379.19686 | N8: =K8*M8*L8 -> 2730.2174 | O8: =N8 -> 2730.2174 | P8: =N8-O8 -> 0 | Q8: =K8 -> 0.6 | R8: =L8 -> 12 | S8: =M8*1.05 -> 398.1567 | T8: =Q8*S8*R8 -> 2866.7282 | U8: =T8 -> 2866.7282 | V8: =T8-U8 -> 0 | W8: =I8+O8+U8 -> 8197.1526 | X8: =J8+P8+V8 -> 0 | Y8: =W8+X8 -> 8197.1526 | Z8: =H8+N8+T8-Y8 -> 0 | AA8: =I8+O8+U8-W8 -> 0 | AB8: =J8+P8+V8-X8 -> 0
B9: MEAL Cordinator | C9: 0.4 | D9: FTE | E9: 12 | F9: 1 | G9: =(856059.4813/$G$3)/12 -> 1097.5122 | H9: =C9*G9*E9 -> 5268.0583 | I9: =H9 -> 5268.0583 | J9: =H9-I9 -> 0 | K9: =C9 -> 0.4 | L9: =E9 -> 12 | M9: =G9*1.05 -> 1152.3878 | N9: =K9*M9*L9 -> 5531.4613 | O9: =N9 -> 5531.4613 | P9: =N9-O9 -> 0 | Q9: =K9 -> 0.4 | R9: =L9 -> 12 | S9: =M9*1.05 -> 1210.0072 | T9: =Q9*S9*R9 -> 5808.0343 | U9: =T9 -> 5808.0343 | V9: =T9-U9 -> 0 | W9: =I9+O9+U9 -> 16607.554 | X9: =J9+P9+V9 -> 0 | Y9: =W9+X9 -> 16607.554 | Z9: =H9+N9+T9-Y9 -> 0 | AA9: =I9+O9+U9-W9 -> 0 | AB9: =J9+P9+V9-X9 -> 0
B10: Mang.& tech.advisors - Int’l Staff | C10: 0.04 | D10: FTE | E10: 12 | F10: 1 | G10: 2986.75 | H10: =C10*G10*E10 -> 1433.64 | I10: 1075.23 | J10: =H10-I10 -> 358.41 | K10: =C10 -> 0.04 | L10: =E10 -> 12 | M10: =G10*$M$3 -> 4089.1296 | N10: =K10*M10*L10 -> 1962.7822 | O10: =I10*$O$3 -> 1397.6915 | P10: =N10-O10 -> 565.09071 | Q10: =K10 -> 0.04 | R10: =L10 -> 12 | S10: =M10 -> 4089.1296 | T10: =Q10*S10*R10 -> 1962.7822 | U10: =O10+(O10*$U$3) -> 1333.803 | V10: =T10-U10 -> 628.97919 | W10: =I10+O10+U10 -> 3806.7245 | X10: =J10+P10+V10 -> 1552.4799 | Y10: =W10+X10 -> 5359.2044 | Z10: =H10+N10+T10-Y10 -> 0 | AA10: =I10+O10+U10-W10 -> 0 | AB10: =J10+P10+V10-X10 -> 0
B11: Mang.& tech.advisors - Nat.staff | C11: 0.65 | D11: FTE | E11: 12 | F11: 1 | G11: 1461 | H11: =C11*G11*E11 -> 11395.8 | I11: 8941.32 | J11: =H11-I11 -> 2454.48 | K11: =C11 -> 0.65 | L11: =E11 -> 12 | M11: =G11*$M$3 -> 2000.2405 | N11: =K11*M11*L11 -> 15601.876 | O11: =I11*$O$3 -> 11622.822 | P11: =N11-O11 -> 3979.054 | Q11: =K11 -> 0.65 | R11: =L11 -> 12 | S11: =M11 -> 2000.2405 | T11: =Q11*S11*R11 -> 15601.876 | U11: =O11+(O11*$U$3) -> 11091.543 | V11: =T11-U11 -> 4510.3331 | W11: =I11+O11+U11 -> 31655.685 | X11: =J11+P11+V11 -> 10943.867 | Y11: =W11+X11 -> 42599.552 | Z11: =H11+N11+T11-Y11 -> 0 | AA11: =I11+O11+U11-W11 -> 0 | AB11: =J11+P11+V11-X11 -> 0
B12: Sub Total Personnel | H12: =SUM(H5:H11) -> 39761.492 | I12: =SUM(I5:I11) -> 36948.602 | J12: =SUM(J5:J11) -> 2812.89 | N12: =SUM(N5:N11) -> 45843.313 | O12: =SUM(O5:O11) -> 41299.168 | P12: =SUM(P5:P11) -> 4544.1447 | T12: =SUM(T5:T11) -> 47257.246 | U12: =SUM(U5:U11) -> 42117.933 | V12: =SUM(V5:V11) -> 5139.3123 | W12: =SUM(W5:W11) -> 120365.7 | X12: =SUM(X5:X11) -> 12496.347 | Y12: =SUM(Y5:Y11) -> 132862.05 | Z12: =H12+N12+T12-Y12 -> 0 | AA12: =I12+O12+U12-W12 -> 0 | AB12: =J12+P12+V12-X12 -> 0
A13: 6061, 6063, 6071 | B13: Fringe Benefits | Z13: =H13+N13+T13-Y13 -> 0 | AA13: =I13+O13+U13-W13 -> 0 | AB13: =J13+P13+V13-X13 -> 0
B14: Fringe Benefits – National Staff | C14: =SUM(C5:C9) -> 2.3 | D14: Salary | E14: 12 | F14: 0.135 | G14: =SUM(H5:H9)/12 -> 2244.3377 | H14: =SUM(H5:H9)*$F$14 -> 3635.8271 | I14: =H14 -> 3635.8271 | J14: 0 | K14: =C14 -> 2.3 | L14: =E14 -> 12 | M14: =G14*1.05 -> 2356.5546 | N14: =SUM(N5:N9)*$F$14 -> 3817.6184 | O14: =N14 -> 3817.6184 | P14: =N14-O14 -> 0 | Q14: =K14 -> 2.3 | R14: =L14 -> 12 | S14: =M14*1.05001 -> 2474.4059 | T14: =SUM(T5:T9)*$F$14 -> 4008.4993 | U14: =T14 -> 4008.4993 | V14: =T14-U14 -> 0 | W14: =I14+O14+U14 -> 11461.945 | X14: =J14+P14+V14 -> 0 | Y14: =W14+X14 -> 11461.945 | Z14: =H14+N14+T14-Y14 -> 0 | AA14: =I14+O14+U14-W14 -> 0 | AB14: =J14+P14+V14-X14 -> 0
B15: Fringe Benefits – Int’l Staff | C15: =C10 -> 0.04 | D15: Salary | E15: 12 | F15: 0.29 | G15: 119.47 | H15: =G15*E15*F15 -> 415.7556 | I15: 311.8167 | J15: =H15-I15 -> 103.9389 | K15: =C15 -> 0.04 | L15: =E15 -> 12 | M15: =G15*$M$3 -> 163.56518 | N15: =M15*L15*F15 -> 569.20683 | O15: =I15*$O$3 -> 405.33053 | P15: =N15-O15 -> 163.87631 | Q15: =K15 -> 0.04 | R15: =L15 -> 12 | S15: =M15 -> 163.56518 | T15: =F15*S15*R15 -> 569.20683 | U15: =O15+(O15*$U$3) -> 386.80287 | V15: =T15-U15 -> 182.40396 | W15: =I15+O15+U15 -> 1103.9501 | X15: =J15+P15+V15 -> 450.21917 | Y15: =W15+X15 -> 1554.1693 | Z15: =H15+N15+T15-Y15 -> 0 | AA15: =I15+O15+U15-W15 -> 0 | AB15: =J15+P15+V15-X15 -> 0
B16: Overseas Allowances – Int’l Staff | C16: =C10 -> 0.04 | D16: FTE | E16: 12 | F16: 1 | G16: 2234.56 | H16: =C16*G16*E16 -> 1072.5888 | I16: 804.4416 | J16: =H16-I16 -> 268.1472 | K16: =K10 -> 0.04 | L16: =E16 -> 12 | M16: =G16*$M$3 -> 3059.3138 | N16: =K16*M16*L16 -> 1468.4706 | O16: =I16*$O$3 -> 1045.6936 | P16: =N16-O16 -> 422.77696 | Q16: =Q10 -> 0.04 | R16: =L16 -> 12 | S16: =M16 -> 3059.3138 | T16: =Q16*S16*R16 -> 1468.4706 | U16: =O16+(O16*$U$3) -> 997.89498 | V16: =T16-U16 -> 470.57562 | W16: =I16+O16+U16 -> 2848.0302 | X16: =J16+P16+V16 -> 1161.4998 | Y16: =W16+X16 -> 4009.53 | Z16: =H16+N16+T16-Y16 -> 0 | AA16: =I16+O16+U16-W16 -> 0 | AB16: =J16+P16+V16-X16 -> 0
B17: Housing and Local Benefits – Int’l Staff | C17: =C10 -> 0.04 | D17: FTE | E17: 12 | F17: 1 | G17: 1002.19 | H17: =C17*G17*E17 -> 481.0512 | I17: 360.7884 | J17: =H17-I17 -> 120.2628 | K17: =K10 -> 0.04 | L17: =E17 -> 12 | M17: =G17*$M$3 -> 1372.0883 | N17: =K17*M17*L17 -> 658.60239 | O17: =I17*$O$3 -> 468.98884 | P17: =N17-O17 -> 189.61355 | Q17: =Q10 -> 0.04 | R17: =L17 -> 12 | S17: =M17 -> 1372.0883 | T17: =Q17*S17*R17 -> 658.60239 | U17: =O17+(O17*$U$3) -> 447.55136 | V17: =T17-U17 -> 211.05103 | W17: =I17+O17+U17 -> 1277.3286 | X17: =J17+P17+V17 -> 520.92737 | Y17: =W17+X17 -> 1798.256 | Z17: =H17+N17+T17-Y17 -> 0 | AA17: =I17+O17+U17-W17 -> 0 | AB17: =J17+P17+V17-X17 -> 0
B18: Mang.& tech.advisors - Nat.staff-Fringe Benefits | C18: =C11 -> 0.65 | D18: Salary | E18: 12 | F18: 1 | G18: =1309/(C18*12) -> 167.82051 | H18: =C18*G18*E18 -> 1309 | I18: 1027.0921 | J18: =H18-I18 -> 281.90786 | K18: =C18 -> 0.65 | L18: =E18 -> 12 | M18: =G18*$M$3 -> 229.76139 | N18: =K18*M18*L18 -> 1792.1388 | O18: =I18*$O$3 -> 1335.1171 | P18: =N18-O18 -> 457.02174 | Q18: =K18 -> 0.65 | R18: =L18 -> 12 | S18: =M18 -> 229.76139 | T18: =Q18*S18*R18 -> 1792.1388 | U18: =O18+(O18*$U$3) -> 1274.0889 | V18: =T18-U18 -> 518.04994 | W18: =I18+O18+U18 -> 3636.2981 | X18: =J18+P18+V18 -> 1256.9795 | Y18: =W18+X18 -> 4893.2776 | Z18: =H18+N18+T18-Y18 -> 0 | AA18: =I18+O18+U18-W18 -> 0 | AB18: =J18+P18+V18-X18 -> 0
B19: Sub Total Fringe Benefits | H19: =SUM(H14:H18) -> 6914.2227 | I19: =SUM(I14:I18) -> 6139.9659 | J19: =SUM(J14:J18) -> 774.25676 | N19: =SUM(N14:N18) -> 8306.037 | O19: =SUM(O14:O18) -> 7072.7485 | P19: =SUM(P14:P18) -> 1233.2886 | T19: =SUM(T14:T18) -> 8496.918 | U19: =SUM(U14:U18) -> 7114.8374 | V19: =SUM(V14:V18) -> 1382.0805 | W19: =SUM(W14:W18) -> 20327.552 | X19: =SUM(X14:X18) -> 3389.6259 | Y19: =SUM(Y14:Y18) -> 23717.178 | Z19: =H19+N19+T19-Y19 -> 0 | AA19: =I19+O19+U19-W19 -> 0 | AB19: =J19+P19+V19-X19 -> 0
B20: Travel | Z20: =H20+N20+T20-Y20 -> 0 | AA20: =I20+O20+U20-W20 -> 0 | AB20: =J20+P20+V20-X20 -> 0
B21: Domestic Travel | C21: 14 | D21: flight/train | E21: 1 | F21: 1 | G21: =13000/$G$3 -> 200 | H21: =C21*G21*E21 -> 2800 | I21: =H21 -> 2800 | J21: =H21-I21 -> 0 | K21: 16 | L21: 1 | M21: =G21*1.05 -> 210 | N21: =K21*M21*L21 -> 3360 | O21: =N21 -> 3360 | P21: =N21-O21 -> 0 | Q21: 16 | R21: =L21 -> 1 | S21: =M21*1.05 -> 220.5 | T21: =Q21*S21*R21 -> 3528 | U21: =T21 -> 3528 | V21: =T21-U21 -> 0 | W21: =I21+O21+U21 -> 9688 | X21: =J21+P21+V21 -> 0 | Y21: =W21+X21 -> 9688 | Z21: =H21+N21+T21-Y21 -> 0 | AA21: =I21+O21+U21-W21 -> 0 | AB21: =J21+P21+V21-X21 -> 0
B22: Hotel | C22: =C21*3 -> 42 | D22: night | E22: 1 | F22: 1 | G22: =2700/$G$3 -> 41.538462 | H22: =C22*G22*E22 -> 1744.6154 | I22: =H22 -> 1744.6154 | J22: =H22-I22 -> 0 | K22: =K21*3 -> 48 | L22: 1 | M22: =G22*1.05 -> 43.615385 | N22: =K22*M22*L22 -> 2093.5385 | O22: =N22 -> 2093.5385 | P22: =N22-O22 -> 0 | Q22: =Q21*3 -> 48 | R22: =L22 -> 1 | S22: =M22*1.05 -> 45.796154 | T22: =Q22*S22*R22 -> 2198.2154 | U22: =T22 -> 2198.2154 | V22: =T22-U22 -> 0 | W22: =I22+O22+U22 -> 6036.3692 | X22: =J22+P22+V22 -> 0 | Y22: =W22+X22 -> 6036.3692 | Z22: =H22+N22+T22-Y22 -> 0 | AA22: =I22+O22+U22-W22 -> 0 | AB22: =J22+P22+V22-X22 -> 0
B23: Perdiem | C23: =C21*3 -> 42 | D23: day | E23: 1 | F23: 1 | G23: =1000/$G$3 -> 15.384615 | H23: =C23*G23*E23 -> 646.15385 | I23: =H23 -> 646.15385 | J23: =H23-I23 -> 0 | K23: =K21*3 -> 48 | L23: 1 | M23: =G23*1.05 -> 16.153846 | N23: =K23*M23*L23 -> 775.38462 | O23: =N23 -> 775.38462 | P23: =N23-O23 -> 0 | Q23: =Q21*3 -> 48 | R23: =L23 -> 1 | S23: =M23*1.05 -> 16.961538 | T23: =Q23*S23*R23 -> 814.15385 | U23: =T23 -> 814.15385 | V23: =T23-U23 -> 0 | W23: =I23+O23+U23 -> 2235.6923 | X23: =J23+P23+V23 -> 0 | Y23: =W23+X23 -> 2235.6923 | Z23: =H23+N23+T23-Y23 -> 0 | AA23: =I23+O23+U23-W23 -> 0 | AB23: =J23+P23+V23-X23 -> 0
B24: Mang.& tech.advisors - Nat.staff-Travel | C24: 1 | D24: Month | E24: 12 | F24: 1 | G24: 69.85 | H24: =C24*G24*E24 -> 838.2 | I24: 755.9244 | J24: =H24-I24 -> 82.2756 | K24: 12 | L24: 1 | M24: =G24*$M$3 -> 95.630936 | N24: =K24*M24*L24 -> 1147.5712 | O24: =I24*$O$3 -> 982.62613 | P24: =N24-O24 -> 164.94511 | Q24: =K24 -> 12 | R24: =L24 -> 1 | S24: =M24 -> 95.630936 | T24: =Q24*S24*R24 -> 1147.5712 | U24: =O24+(O24*$U$3) -> 937.71029 | V24: =T24-U24 -> 209.86095 | W24: =I24+O24+U24 -> 2676.2608 | X24: =J24+P24+V24 -> 457.08166 | Y24: =W24+X24 -> 3133.3425 | Z24: =H24+N24+T24-Y24 -> 0 | AA24: =I24+O24+U24-W24 -> 0 | AB24: =J24+P24+V24-X24 -> 0
B25: In-country program travel and vehicle expenses | C25: 1 | D25: Month | E25: 12 | F25: 1 | G25: =18000/$G$3 -> 276.92308 | H25: =C25*G25*E25 -> 3323.0769 | I25: 3323 | J25: =H25-I25 -> 0.076923077 | K25: 12 | L25: 1 | M25: =G25*$M$3 -> 379.13262 | N25: =K25*M25*L25 -> 4549.5914 | O25: =I25*$O$3 -> 4319.5677 | P25: =N25-O25 -> 230.02368 | Q25: =K25 -> 12 | R25: =L25 -> 1 | S25: =M25 -> 379.13262 | T25: =Q25*S25*R25 -> 4549.5914 | U25: =O25+(O25*$U$3) -> 4122.1203 | V25: =T25-U25 -> 427.47112 | W25: =I25+O25+U25 -> 11764.688 | X25: =J25+P25+V25 -> 657.57173 | Y25: =W25+X25 -> 12422.26 | Z25: =H25+N25+T25-Y25 -> 0 | AA25: =I25+O25+U25-W25 -> 0 | AB25: =J25+P25+V25-X25 -> 0
B26: Sub Total Travel & Transportation | H26: =SUM(H21:H25) -> 9352.0462 | I26: =SUM(I21:I25) -> 9269.6936 | J26: =SUM(J21:J25) -> 82.352523 | N26: =SUM(N21:N25) -> 11926.086 | O26: =SUM(O21:O25) -> 11531.117 | P26: =SUM(P21:P25) -> 394.9688 | T26: =SUM(T21:T25) -> 12237.532 | U26: =SUM(U21:U25) -> 11600.2 | V26: =SUM(V21:V25) -> 637.33207 | W26: =SUM(W21:W25) -> 32401.01 | X26: =SUM(X21:X25) -> 1114.6534 | Y26: =SUM(Y21:Y25) -> 33515.664 | Z26: =H26+N26+T26-Y26 -> 0 | AA26: =I26+O26+U26-W26 -> 0 | AB26: =J26+P26+V26-X26 -> 0
B27: Supplies | Z27: =H27+N27+T27-Y27 -> 0 | AA27: =I27+O27+U27-W27 -> 0 | AB27: =J27+P27+V27-X27 -> 0
B28: Office/Computer Supplies, Stationery and Services | C28: 1 | D28: Month | E28: 12 | F28: 1 | G28: 223.25385 | H28: =C28*G28*E28 -> 2679.0462 | I28: =C28*E28*F28*211.54 -> 2538.48 | J28: =H28-I28 -> 140.56615 | K28: =C28 -> 1 | L28: =E28 -> 12 | M28: =G28*1.05 -> 234.41654 | N28: =K28*M28*L28*F28 -> 2812.9985 | O28: =I28*1.05 -> 2665.404 | P28: =N28-O28 -> 147.59446 | Q28: =K28 -> 1 | R28: =L28 -> 12 | S28: =M28*1.05 -> 246.13737 | T28: =Q28*S28*R28*F28 -> 2953.6484 | U28: =O28*1.05 -> 2798.6742 | V28: =T28-U28 -> 154.97418 | W28: =I28+O28+U28 -> 8002.5582 | X28: =J28+P28+V28 -> 443.1348 | Y28: =W28+X28 -> 8445.693 | Z28: =H28+N28+T28-Y28 -> 0 | AA28: =I28+O28+U28-W28 -> 0 | AB28: =J28+P28+V28-X28 -> 0
B29: Printing | C29: 1 | D29: Month | E29: 12 | F29: 1 | G29: =3000/$G$3 -> 46.153846 | H29: =C29*G29*E29 -> 553.84615 | I29: =H29 -> 553.84615 | J29: =H29-I29 -> 0 | K29: =C29 -> 1 | L29: =E29 -> 12 | M29: =G29*1.05 -> 48.461538 | N29: =K29*M29*L29*F29 -> 581.53846 | O29: =N29 -> 581.53846 | P29: =N29-O29 -> 0 | Q29: =K29 -> 1 | R29: =L29 -> 12 | S29: =M29*1.05 -> 50.884615 | T29: =Q29*S29*R29*F29 -> 610.61538 | U29: =T29 -> 610.61538 | V29: =T29-U29 -> 0 | W29: =I29+O29+U29 -> 1746 | X29: =J29+P29+V29 -> 0 | Y29: =W29+X29 -> 1746 | Z29: =H29+N29+T29-Y29 -> 0 | AA29: =I29+O29+U29-W29 -> 0 | AB29: =J29+P29+V29-X29 -> 0
B30: Sub Total Supplies | H30: =SUM(H28:H29) -> 3232.8923 | I30: =SUM(I28:I29) -> 3092.3262 | J30: =SUM(J28:J29) -> 140.56615 | N30: =SUM(N28:N29) -> 3394.5369 | O30: =SUM(O28:O29) -> 3246.9425 | P30: =SUM(P28:P29) -> 147.59446 | T30: =SUM(T28:T29) -> 3564.2638 | U30: =SUM(U28:U29) -> 3409.2896 | V30: =SUM(V28:V29) -> 154.97418 | W30: =SUM(W28:W29) -> 9748.5582 | X30: =SUM(X28:X29) -> 443.1348 | Y30: =SUM(Y28:Y29) -> 10191.693 | Z30: =H30+N30+T30-Y30 -> 0 | AA30: =I30+O30+U30-W30 -> 0 | AB30: =J30+P30+V30-X30 -> 0
B31: Contractual | Z31: =H31+N31+T31-Y31 -> 0 | AA31: =I31+O31+U31-W31 -> 0 | AB31: =J31+P31+V31-X31 -> 0
B32: Prajwala | C32: 1 | D32: Lumpsum | E32: 1 | F32: 1 | G32: =Cereal!J42 -> 17932.32 | H32: =Cereal!J42 -> 17932.32 | I32: =Cereal!K42 -> 17932.32 | J32: =Cereal!L42 -> 0 | K32: 1 | L32: 1 | M32: =Cereal!M42 -> 25716.312 | N32: =Cereal!M42 -> 25716.312 | O32: =Cereal!N42 -> 25716.312 | P32: =Cereal!O42 -> 0 | Q32: 1 | R32: =L32 -> 1 | S32: =Cereal!P42 -> 6425.7124 | T32: =Q32*S32*R32*F32 -> 6425.7124 | U32: =Cereal!Q42 -> 6425.7124 | V32: =Cereal!R42 -> 0 | W32: =I32+O32+U32 -> 50074.344 | X32: =J32+P32+V32 -> 0 | Y32: =W32+X32 -> 50074.344 | Z32: =H32+N32+T32-Y32 -> 0 | AA32: =I32+O32+U32-W32 -> 0 | AB32: =J32+P32+V32-X32 -> 0
B33: Technical Advisor–Capacity Strengthening of Law enforcement Officials | C33: 10 | D33: Lumpsum | E33: 12 | F33: 1 | G33: =3000/$G$3 -> 46.153846 | H33: =C33*G33*E33 -> 5538.4615 | I33: 0 | J33: =H33-I33 -> 5538.4615 | K33: =C33 -> 10 | L33: =E33 -> 12 | M33: =G33*1.05 -> 48.461538 | N33: =6*E33*F33*G33 -> 3323.0769 | O33: 0 | P33: =N33-O33 -> 3323.0769 | Q33: =K33 -> 10 | R33: =L33 -> 12 | S33: =M33*1.05 -> 50.884615 | T33: =4*E33*F33*G33 -> 2215.3846 | U33: 0 | V33: =T33-U33 -> 2215.3846 | W33: =I33+O33+U33 -> 0 | X33: =J33+P33+V33 -> 11076.923 | Y33: =W33+X33 -> 11076.923 | Z33: =H33+N33+T33-Y33 -> 0 | AA33: =I33+O33+U33-W33 -> 0 | AB33: =J33+P33+V33-X33 -> 0
B34: Sub Total Contractual | H34: =SUM(H32:H33) -> 23470.782 | I34: =SUM(I32:I33) -> 17932.32 | J34: =SUM(J32:J33) -> 5538.4615 | M34: =SUM(M32:M33) -> 25764.774 | N34: =SUM(N32:N33) -> 29039.389 | O34: =SUM(O32:O33) -> 25716.312 | P34: =SUM(P32:P33) -> 3323.0769 | S34: =SUM(S32:S33) -> 6476.5971 | T34: =SUM(T32:T33) -> 8641.0971 | U34: =SUM(U32:U33) -> 6425.7124 | V34: =SUM(V32:V33) -> 2215.3846 | W34: =SUM(W32:W33) -> 50074.344 | X34: =SUM(X32:X33) -> 11076.923 | Y34: =SUM(Y32:Y33) -> 61151.268 | Z34: =H34+N34+T34-Y34 -> 0 | AA34: =I34+O34+U34-W34 -> 0 | AB34: =J34+P34+V34-X34 -> 0
B35: Other Direct Costs | Z35: =H35+N35+T35-Y35 -> 0 | AA35: =I35+O35+U35-W35 -> 0 | AB35: =J35+P35+V35-X35 -> 0
B36: Baseline Survey/Mid-term Review/Final Evaluation | C36: 1 | D36: Event | E36: 1 | F36: 1 | G36: =60000/$G$3 -> 923.07692 | H36: =C36*G36*E36*F36 -> 923.07692 | I36: =H36 -> 923.07692 | J36: =H36-I36 -> 0 | K36: =C36 -> 1 | L36: 1 | M36: 922.5 | N36: =K36*M36*L36*F36 -> 922.5 | O36: =N36 -> 922.5 | P36: =N36-O36 -> 0 | Q36: =K36 -> 1 | R36: =L36 -> 1 | S36: 11385 | T36: =Q36*S36*R36*F36 -> 11385 | U36: =T36 -> 11385 | V36: =T36-U36 -> 0 | W36: =I36+O36+U36 -> 13230.577 | X36: =J36+P36+V36 -> 0 | Y36: =W36+X36 -> 13230.577 | Z36: =H36+N36+T36-Y36 -> 0 | AA36: =I36+O36+U36-W36 -> 0 | AB36: =J36+P36+V36-X36 -> 0
B37: MEAL Workshop | C37: 1 | D37: Lumpsum | E37: 1 | F37: 1 | G37: =40000/$G$3 -> 615.38462 | H37: =C37*G37*E37*F37 -> 615.38462 | I37: =H37 -> 615.38462 | J37: =H37-I37 -> 0 | M37: 0 | N37: 0 | O37: =N37 -> 0 | P37: =N37-O37 -> 0 | S37: 0 | T37: 0 | U37: =T37 -> 0 | V37: 0 | W37: =I37+O37+U37 -> 615.38462 | X37: =J37+P37+V37 -> 0 | Y37: =W37+X37 -> 615.38462 | Z37: =H37+N37+T37-Y37 -> 0 | AA37: =I37+O37+U37-W37 -> 0 | AB37: =J37+P37+V37-X37 -> 0
B38: Implement. Plan Workshop | C38: 1 | D38: Workshop | E38: 1 | F38: 1 | G38: =30000/$G$3 -> 461.53846 | H38: =C38*G38*E38*F38 -> 461.53846 | I38: =H38 -> 461.53846 | J38: =H38-I38 -> 0 | M38: 0 | N38: 0 | O38: =N38 -> 0 | P38: =N38-O38 -> 0 | S38: 0 | T38: 0 | U38: =T38 -> 0 | V38: 0 | W38: =I38+O38+U38 -> 461.53846 | X38: =J38+P38+V38 -> 0 | Y38: =W38+X38 -> 461.53846 | Z38: =H38+N38+T38-Y38 -> 0 | AA38: =I38+O38+U38-W38 -> 0 | AB38: =J38+P38+V38-X38 -> 0
B39: Communication Expenses | C39: 1 | D39: Month | E39: 12 | F39: 1 | G39: =15750/$G$3 -> 242.30769 | H39: =C39*G39*E39*F39 -> 2907.6923 | I39: =H39 -> 2907.6923 | J39: =H39-I39 -> 0 | K39: =C39 -> 1 | L39: =E39 -> 12 | M39: =G39*1.05 -> 254.42308 | N39: =K39*M39*L39*F39 -> 3053.0769 | O39: =N39 -> 3053.0769 | P39: =N39-O39 -> 0 | Q39: =K39 -> 1 | R39: =L39 -> 12 | S39: =M39*1.05 -> 267.14423 | T39: =Q39*S39*R39*F39 -> 3205.7308 | U39: =T39 -> 3205.7308 | V39: =T39-U39 -> 0 | W39: =I39+O39+U39 -> 9166.5 | X39: =J39+P39+V39 -> 0 | Y39: =W39+X39 -> 9166.5 | Z39: =H39+N39+T39-Y39 -> 0 | AA39: =I39+O39+U39-W39 -> 0 | AB39: =J39+P39+V39-X39 -> 0
B40: Building rent, utilities and maintenance | C40: 1 | D40: Month | E40: 12 | F40: 1 | G40: =70026.5/$G$3 -> 1077.3308 | H40: =C40*G40*E40*F40 -> 12927.969 | I40: =H40 -> 12927.969 | J40: =H40-I40 -> 0 | K40: =C40 -> 1 | L40: =E40 -> 12 | M40: =G40*1.05 -> 1131.1973 | N40: =K40*M40*L40*F40 -> 13574.368 | O40: =N40 -> 13574.368 | P40: =N40-O40 -> 0 | Q40: =K40 -> 1 | R40: =L40 -> 12 | S40: =M40*1.05 -> 1187.7572 | T40: =Q40*S40*R40*F40 -> 14253.086 | U40: =T40 -> 14253.086 | V40: =T40-U40 -> 0 | W40: =I40+O40+U40 -> 40755.423 | X40: =J40+P40+V40 -> 0 | Y40: =W40+X40 -> 40755.423 | Z40: =H40+N40+T40-Y40 -> 0 | AA40: =I40+O40+U40-W40 -> 0 | AB40: =J40+P40+V40-X40 -> 0
B41: Contracted Audit & Legal Services | C41: 1 | D41: Month | E41: 12 | F41: 1 | G41: 90.25 | H41: =C41*G41*E41*F41 -> 1083 | I41: 851.28 | J41: =H41-I41 -> 231.72 | K41: =C41 -> 1 | L41: =E41 -> 12 | M41: =G41*$M$3 -> 123.56037 | N41: =K41*M41*L41*F41 -> 1482.7245 | O41: =I41*$O$3 -> 1106.5789 | P41: =N41-O41 -> 376.1456 | Q41: =K41 -> 1 | R41: =L41 -> 12 | S41: =M41 -> 123.56037 | T41: =Q41*S41*R41*F41 -> 1482.7245 | U41: =O41+(O41*$U$3) -> 1055.9972 | V41: =T41-U41 -> 426.72732 | W41: =I41+O41+U41 -> 3013.856 | X41: =J41+P41+V41 -> 1034.5929 | Y41: =W41+X41 -> 4048.4489 | Z41: =H41+N41+T41-Y41 -> 0 | AA41: =I41+O41+U41-W41 -> 0 | AB41: =J41+P41+V41-X41 -> 0
B42: Information Technology and Communication Expenses & Bank charges | C42: 1 | D42: Month | E42: 12 | F42: 1 | G42: 67.56 | H42: =C42*G42*E42*F42 -> 810.72 | I42: 805.32 | J42: =H42-I42 -> 5.4 | K42: =C42 -> 1 | L42: =E42 -> 12 | M42: =G42*$M$3 -> 92.49572 | N42: =K42*M42*L42*F42 -> 1109.9486 | O42: =I42*$O$3 -> 1046.8355 | P42: =N42-O42 -> 63.113177 | Q42: =K42 -> 1 | R42: =L42 -> 12 | S42: =M42 -> 92.49572 | T42: =Q42*S42*R42*F42 -> 1109.9486 | U42: =O42+(O42*$U$3) -> 998.98462 | V42: =T42-U42 -> 110.96403 | W42: =I42+O42+U42 -> 2851.1401 | X42: =J42+P42+V42 -> 179.4772 | Y42: =W42+X42 -> 3030.6173 | Z42: =H42+N42+T42-Y42 -> 0 | AA42: =I42+O42+U42-W42 -> 0 | AB42: =J42+P42+V42-X42 -> 0
B43: Facility Costs, IT Services, Communication, IT Salaries | C43: 4 | D43: Sq. Mt | E43: 12 | F43: 1 | G43: 86.29 | H43: =C43*G43*E43*F43 -> 4141.92 | I43: =H43 -> 4141.92 | J43: =H43-I43 -> 0 | K43: =C43 -> 4 | L43: =E43 -> 12 | M43: =G43*$M$3 -> 118.13878 | N43: =K43*M43*L43*F43 -> 5670.6613 | O43: =I43*$O$3 -> 5384.0818 | P43: =N43-O43 -> 286.57944 | Q43: =K43 -> 4 | R43: =L43 -> 12 | S43: =M43 -> 118.13878 | T43: =Q43*S43*R43*F43 -> 5670.6613 | U43: =O43+(O43*$U$3) -> 5137.9754 | V43: =T43-U43 -> 532.68582 | W43: =I43+O43+U43 -> 14663.977 | X43: =J43+P43+V43 -> 819.26527 | Y43: =W43+X43 -> 15483.243 | Z43: =H43+N43+T43-Y43 -> 0 | AA43: =I43+O43+U43-W43 -> 0 | AB43: =J43+P43+V43-X43 -> 0
B44: Sub Total Other Direct Costs | H44: =SUM(H36:H43) -> 23871.302 | I44: =SUM(I36:I43) -> 23634.182 | J44: =SUM(J36:J43) -> 237.12 | M44: =SUM(M36:M43) -> 2642.3153 | N44: =SUM(N36:N43) -> 25813.279 | O44: =SUM(O36:O43) -> 25087.441 | P44: =SUM(P36:P43) -> 725.83822 | S44: =SUM(S36:S43) -> 13174.096 | T44: =SUM(T36:T43) -> 37107.151 | U44: =SUM(U36:U43) -> 36036.774 | V44: =SUM(V36:V43) -> 1070.3772 | W44: =SUM(W36:W43) -> 84758.396 | X44: =SUM(X36:X43) -> 2033.3354 | Y44: =SUM(Y36:Y43) -> 86791.732 | Z44: =H44+N44+T44-Y44 -> 0 | AA44: =I44+O44+U44-W44 -> 0 | AB44: =J44+P44+V44-X44 -> 0
B45: Total Direct Costs | H45: =H12+H19+H26+H30+H34+H44 -> 106602.74 | I45: =I12+I19+I26+I30+I34+I44 -> 97017.09 | J45: =J12+J19+J26+J30+J34+J44 -> 9585.647 | N45: =N12+N19+N26+N30+N34+N44 -> 124322.64 | O45: =O12+O19+O26+O30+O34+O44 -> 113953.73 | P45: =P12+P19+P26+P30+P34+P44 -> 10368.912 | T45: =T12+T19+T26+T30+T34+T44 -> 117304.21 | U45: =U12+U19+U26+U30+U34+U44 -> 106704.75 | V45: =V12+V19+V26+V30+V34+V44 -> 10599.461 | W45: =W12+W19+W26+W30+W34+W44 -> 317675.56 | X45: =X12+X19+X26+X30+X34+X44 -> 30554.02 | Y45: =Y12+Y19+Y26+Y30+Y34+Y44 -> 348229.58 | Z45: =H45+N45+T45-Y45 -> 0 | AA45: =I45+O45+U45-W45 -> 0 | AB45: =J45+P45+V45-X45 -> 0
B46: Indirect Cost Exclusions | H46: 0 | I46: 0 | J46: 0 | N46: 0 | O46: 0 | P46: 0 | T46: 0 | U46: 0 | V46: 0 | W46: 0 | X46: 0 | Y46: 0 | Z46: =H46+N46+T46-Y46 -> 0 | AA46: =I46+O46+U46-W46 -> 0 | AB46: =J46+P46+V46-X46 -> 0
B47: Modified Total Direct Costs | H47: =H45-H46 -> 106602.74 | I47: =I45-I46 -> 97017.09 | J47: =J45-J46 -> 9585.647 | N47: =N45-N46 -> 124322.64 | O47: =O45-O46 -> 113953.73 | P47: =P45-P46 -> 10368.912 | T47: =T45-T46 -> 117304.21 | U47: =U45-U46 -> 106704.75 | V47: =V45-V46 -> 10599.461 | W47: =W45-W46 -> 317675.56 | X47: =X45-X46 -> 30554.02 | Y47: =Y45-Y46 -> 348229.58 | Z47: =H47+N47+T47-Y47 -> 0 | AA47: =I47+O47+U47-W47 -> 0 | AB47: =J47+P47+V47-X47 -> 0
A48: 6961, 6963 | B48: Indirect Cost (17.88%) | D48: 0.1788 | H48: =H47*17.88/100 -> 19060.569 | I48: =I47*17.88/100 -> 17346.656 | J48: =J47*17.88/100 -> 1713.9137 | N48: =N47*17.88/100 -> 22228.888 | O48: =O47*17.88/100 -> 20374.927 | P48: =P47*17.88/100 -> 1853.9614 | T48: =T47*17.88/100 -> 20973.992 | U48: =U47*17.88/100 -> 19078.809 | V48: =V47*17.88/100 -> 1895.1836 | W48: =I48+O48+U48 -> 56800.391 | X48: =J48+P48+V48 -> 5463.0587 | Y48: =W48+X48 -> 62263.45 | Z48: =H48+N48+T48-Y48 -> 0 | AA48: =I48+O48+U48-W48 -> 0 | AB48: =J48+P48+V48-X48 -> 0
B49: GRAND TOTAL | H49: =H48+H45 -> 125663.31 | I49: =I48+I45 -> 114363.75 | J49: =J48+J45 -> 11299.561 | N49: =N48+N45 -> 146551.53 | O49: =O48+O45 -> 134328.66 | P49: =P48+P45 -> 12222.873 | T49: =T48+T45 -> 138278.2 | U49: =U48+U45 -> 125783.56 | V49: =V48+V45 -> 12494.645 | W49: =W48+W45 -> 374475.96 | X49: =X48+X45 -> 36017.078 | Y49: =Y48+Y45 -> 410493.03 | Z49: =H49+N49+T49-Y49 -> 0 | AA49: =I49+O49+U49-W49 -> 0 | AB49: =J49+P49+V49-X49 -> 0
I70: =I47-I34 -> 79084.77

Sheet Sheet2

Sheet Detailed Budget (3)
A1: ='Budget Summary'!C4 -> Year 1 | C1: 2017 | K1: 2018 | Q1: 2019 | W1: Total
A2: Account Code | B2: All costs in US$ | C2: No. | D2: Unit Type | E2: No. of Units | F2: % | G2: Rate | H2: Total | I2: Grant | J2: CRS | K2: No. | L2: Freq. | M2: Rate | N2: Total | O2: Grant | P2: CRS | Q2: No. | R2: Freq. | S2: Rate | T2: Total | U2: Grant | V2: CRS | W2: Grant | X2: CRS | Y2: Grand Total
A3: 6052, 6069 | B3: Personnel | G3: 65 | I3: 0.85 | J3: =(100%-I3) -> 0.15 | M3: 1.36909 | O3: 1.2999 | P3: =(100%-O3) -> -0.2999 | S3: 1.36909 | U3: -0.04571 | V3: =(100%-U3) -> 1.04571
B4: Staff Salaries
B5: Head of Office | C5: 0.3 | D5: FTE | E5: 12 | F5: 1 | G5: =(1391532.0682/$G$3)/12 -> 1784.0155 | H5: =C5*G5*E5 -> 6422.4557 | I5: =H5 -> 6422.4557 | J5: =H5-I5 -> 0 | K5: =C5 -> 0.3 | L5: =E5 -> 12 | M5: =G5*1.05 -> 1873.2162 | N5: =K5*M5*L5 -> 6743.5785 | O5: =N5 -> 6743.5785 | P5: =N5-O5 -> 0 | Q5: =K5 -> 0.3 | R5: =L5 -> 12 | S5: =M5*1.05 -> 1966.8771 | T5: =Q5*S5*R5 -> 7080.7574 | U5: =T5 -> 7080.7574 | V5: =T5-U5 -> 0 | W5: =I5+O5+U5 -> 20246.792 | X5: =J5+P5+V5 -> 0 | Y5: =W5+X5 -> 20246.792 | Z5: =H5+N5+T5-Y5 -> 0 | AA5: =I5+O5+U5-W5 -> 0 | AB5: =J5+P5+V5-X5 -> 0
B6: Program Coordinator | C6: 0.8 | D6: FTE | E6: 12 | F6: 1 | G6: =(881322/$G$3)/12 -> 1129.9 | H6: =C6*G6*E6 -> 10847.04 | I6: =H6 -> 10847.04 | J6: 0 | K6: =C6 -> 0.8 | L6: =E6 -> 12 | M6: =G6*1.05 -> 1186.395 | N6: =K6*M6*L6 -> 11389.392 | O6: =N6 -> 11389.392 | P6: 0 | Q6: =K6 -> 0.8 | R6: =L6 -> 12 | S6: =M6*1.05 -> 1245.7148 | T6: =Q6*S6*R6 -> 11958.862 | U6: =T6 -> 11958.862 | V6: 0 | W6: =I6+O6+U6 -> 34195.294 | X6: =J6+P6+V6 -> 0 | Y6: =W6+X6 -> 34195.294 | Z6: =H6+N6+T6-Y6 -> 0 | AA6: =I6+O6+U6-W6 -> 0 | AB6: =J6+P6+V6-X6 -> 0
B7: Finance officer | C7: 0.2 | D7: FTE | E7: 12 | F7: 1 | G7: =(583144.65/$G$3)/12 -> 747.62135 | H7: =C7*G7*E7 -> 1794.2912 | I7: =H7 -> 1794.2912 | J7: =H7-I7 -> 0 | K7: =C7 -> 0.2 | L7: =E7 -> 12 | M7: =G7*1.05 -> 785.00241 | N7: =K7*M7*L7 -> 1884.0058 | O7: =N7 -> 1884.0058 | P7: =N7-O7 -> 0 | Q7: =K7 -> 0.2 | R7: =L7 -> 12 | S7: =M7*1.05 -> 824.25253 | T7: =Q7*S7*R7 -> 1978.2061 | U7: =T7 -> 1978.2061 | V7: =T7-U7 -> 0 | W7: =I7+O7+U7 -> 5656.5031 | X7: =J7+P7+V7 -> 0 | Y7: =W7+X7 -> 5656.5031 | Z7: =H7+N7+T7-Y7 -> 0 | AA7: =I7+O7+U7-W7 -> 0 | AB7: =J7+P7+V7-X7 -> 0
B8: Administrative Staff | C8: 0.6 | D8: FTE | E8: 12 | F8: 1 | G8: =(1126756.3725/$G$3)/4/12 -> 361.13986 | H8: =C8*G8*E8 -> 2600.207 | I8: =H8 -> 2600.207 | J8: =H8-I8 -> 0 | K8: =C8 -> 0.6 | L8: =E8 -> 12 | M8: =G8*1.05 -> 379.19686 | N8: =K8*M8*L8 -> 2730.2174 | O8: =N8 -> 2730.2174 | P8: =N8-O8 -> 0 | Q8: =K8 -> 0.6 | R8: =L8 -> 12 | S8: =M8*1.05 -> 398.1567 | T8: =Q8*S8*R8 -> 2866.7282 | U8: =T8 -> 2866.7282 | V8: =T8-U8 -> 0 | W8: =I8+O8+U8 -> 8197.1526 | X8: =J8+P8+V8 -> 0 | Y8: =W8+X8 -> 8197.1526 | Z8: =H8+N8+T8-Y8 -> 0 | AA8: =I8+O8+U8-W8 -> 0 | AB8: =J8+P8+V8-X8 -> 0
B9: MEAL Cordinator | C9: 0.4 | D9: FTE | E9: 12 | F9: 1 | G9: =(856059.4813/$G$3)/12 -> 1097.5122 | H9: =C9*G9*E9 -> 5268.0583 | I9: =H9 -> 5268.0583 | J9: =H9-I9 -> 0 | K9: =C9 -> 0.4 | L9: =E9 -> 12 | M9: =G9*1.05 -> 1152.3878 | N9: =K9*M9*L9 -> 5531.4613 | O9: =N9 -> 5531.4613 | P9: =N9-O9 -> 0 | Q9: =K9 -> 0.4 | R9: =L9 -> 12 | S9: =M9*1.05 -> 1210.0072 | T9: =Q9*S9*R9 -> 5808.0343 | U9: =T9 -> 5808.0343 | V9: =T9-U9 -> 0 | W9: =I9+O9+U9 -> 16607.554 | X9: =J9+P9+V9 -> 0 | Y9: =W9+X9 -> 16607.554 | Z9: =H9+N9+T9-Y9 -> 0 | AA9: =I9+O9+U9-W9 -> 0 | AB9: =J9+P9+V9-X9 -> 0
B10: Mang.& tech.advisors - Int’l Staff | C10: 0.04 | D10: FTE | E10: 12 | F10: 1 | G10: 2986.75 | H10: =C10*G10*E10 -> 1433.64 | I10: 1075.23 | J10: =H10-I10 -> 358.41 | K10: =C10 -> 0.04 | L10: =E10 -> 12 | M10: =G10*$M$3 -> 4089.1296 | N10: =K10*M10*L10 -> 1962.7822 | O10: =I10*$O$3 -> 1397.6915 | P10: =N10-O10 -> 565.09071 | Q10: =K10 -> 0.04 | R10: =L10 -> 12 | S10: =M10 -> 4089.1296 | T10: =Q10*S10*R10 -> 1962.7822 | U10: =O10+(O10*$U$3) -> 1333.803 | V10: =T10-U10 -> 628.97919 | W10: =I10+O10+U10 -> 3806.7245 | X10: =J10+P10+V10 -> 1552.4799 | Y10: =W10+X10 -> 5359.2044 | Z10: =H10+N10+T10-Y10 -> 0 | AA10: =I10+O10+U10-W10 -> 0 | AB10: =J10+P10+V10-X10 -> 0
B11: Mang.& tech.advisors - Nat.staff | C11: 0.65 | D11: FTE | E11: 12 | F11: 1 | G11: 1461 | H11: =C11*G11*E11 -> 11395.8 | I11: 8941.32 | J11: =H11-I11 -> 2454.48 | K11: =C11 -> 0.65 | L11: =E11 -> 12 | M11: =G11*$M$3 -> 2000.2405 | N11: =K11*M11*L11 -> 15601.876 | O11: =I11*$O$3 -> 11622.822 | P11: =N11-O11 -> 3979.054 | Q11: =K11 -> 0.65 | R11: =L11 -> 12 | S11: =M11 -> 2000.2405 | T11: =Q11*S11*R11 -> 15601.876 | U11: =O11+(O11*$U$3) -> 11091.543 | V11: =T11-U11 -> 4510.3331 | W11: =I11+O11+U11 -> 31655.685 | X11: =J11+P11+V11 -> 10943.867 | Y11: =W11+X11 -> 42599.552 | Z11: =H11+N11+T11-Y11 -> 0 | AA11: =I11+O11+U11-W11 -> 0 | AB11: =J11+P11+V11-X11 -> 0
B12: Sub Total Personnel | H12: =SUM(H5:H11) -> 39761.492 | I12: =SUM(I5:I11) -> 36948.602 | J12: =SUM(J5:J11) -> 2812.89 | N12: =SUM(N5:N11) -> 45843.313 | O12: =SUM(O5:O11) -> 41299.168 | P12: =SUM(P5:P11) -> 4544.1447 | T12: =SUM(T5:T11) -> 47257.246 | U12: =SUM(U5:U11) -> 42117.933 | V12: =SUM(V5:V11) -> 5139.3123 | W12: =SUM(W5:W11) -> 120365.7 | X12: =SUM(X5:X11) -> 12496.347 | Y12: =SUM(Y5:Y11) -> 132862.05 | Z12: =H12+N12+T12-Y12 -> 0 | AA12: =I12+O12+U12-W12 -> 0 | AB12: =J12+P12+V12-X12 -> 0
A13: 6061, 6063, 6071 | B13: Fringe Benefits | Z13: =H13+N13+T13-Y13 -> 0 | AA13: =I13+O13+U13-W13 -> 0 | AB13: =J13+P13+V13-X13 -> 0
B14: Fringe Benefits | W14: Grant | X14: CRS | Y14: Total
B15: =B5 -> Head of Office | C15: =C5 -> 0.3 | D15: Salary | E15: 12 | F15: 0.135 | G15: =G5 -> 1784.0155 | H15: =C15*G15*E15*F15 -> 867.03152 | I15: =H15 -> 867.03152 | J15: 0 | K15: =C15 -> 0.3 | L15: =E15 -> 12 | M15: =M5 -> 1873.2162 | N15: =F15*M15*K15*L15 -> 910.3831 | O15: =N15 -> 910.3831 | P15: =N15-O15 -> 0 | Q15: =K15 -> 0.3 | R15: =L15 -> 12 | S15: =S5 -> 1966.8771 | T15: =F15*S15*Q15*R15 -> 955.90225 | U15: =T15 -> 955.90225 | V15: =T15-U15 -> 0 | W15: =I15+O15+U15 -> 2733.3169 | X15: =J15+P15+V15 -> 0 | Y15: =W15+X15 -> 2733.3169 | Z15: =H15+N15+T15-Y15 -> 0 | AA15: =I15+O15+U15-W15 -> 0 | AB15: =J15+P15+V15-X15 -> 0
B16: =B6 -> Program Coordinator | C16: =C6 -> 0.8 | D16: Salary | E16: 12 | F16: 0.135 | G16: =G6 -> 1129.9 | H16: =C16*G16*E16*F16 -> 1464.3504 | I16: =H16 -> 1464.3504 | J16: 0 | K16: =C16 -> 0.8 | L16: =E16 -> 12 | M16: =M6 -> 1186.395 | N16: =F16*M16*K16*L16 -> 1537.5679 | O16: =N16 -> 1537.5679 | P16: =N16-O16 -> 0 | Q16: =K16 -> 0.8 | R16: =L16 -> 12 | S16: =S6 -> 1245.7148 | T16: =F16*S16*Q16*R16 -> 1614.4463 | U16: =T16 -> 1614.4463 | V16: =T16-U16 -> 0 | W16: =I16+O16+U16 -> 4616.3646 | X16: =J16+P16+V16 -> 0 | Y16: =W16+X16 -> 4616.3646
B17: =B7 -> Finance officer | C17: =C7 -> 0.2 | D17: Salary | E17: 12 | F17: 0.135 | G17: =G7 -> 747.62135 | H17: =C17*G17*E17*F17 -> 242.22932 | I17: =H17 -> 242.22932 | J17: 0 | K17: =C17 -> 0.2 | L17: =E17 -> 12 | M17: =M7 -> 785.00241 | N17: =F17*M17*K17*L17 -> 254.34078 | O17: =N17 -> 254.34078 | P17: =N17-O17 -> 0 | Q17: =K17 -> 0.2 | R17: =L17 -> 12 | S17: =S7 -> 824.25253 | T17: =F17*S17*Q17*R17 -> 267.05782 | U17: =T17 -> 267.05782 | V17: =T17-U17 -> 0 | W17: =I17+O17+U17 -> 763.62792 | X17: =J17+P17+V17 -> 0 | Y17: =W17+X17 -> 763.62792
B18: =B8 -> Administrative Staff | C18: =C8 -> 0.6 | D18: Salary | E18: 12 | F18: 0.135 | G18: =G8 -> 361.13986 | H18: =C18*G18*E18*F18 -> 351.02795 | I18: =H18 -> 351.02795 | J18: 0 | K18: =C18 -> 0.6 | L18: =E18 -> 12 | M18: =M8 -> 379.19686 | N18: =F18*M18*K18*L18 -> 368.57934 | O18: =N18 -> 368.57934 | P18: =N18-O18 -> 0 | Q18: =K18 -> 0.6 | R18: =L18 -> 12 | S18: =S8 -> 398.1567 | T18: =F18*S18*Q18*R18 -> 387.00831 | U18: =T18 -> 387.00831 | V18: =T18-U18 -> 0 | W18: =I18+O18+U18 -> 1106.6156 | X18: =J18+P18+V18 -> 0 | Y18: =W18+X18 -> 1106.6156
B19: =B9 -> MEAL Cordinator | C19: =C9 -> 0.4 | D19: Salary | E19: 12 | F19: 0.135 | G19: =G9 -> 1097.5122 | H19: =C19*G19*E19*F19 -> 711.18788 | I19: =H19 -> 711.18788 | J19: 0 | K19: =C19 -> 0.4 | L19: =E19 -> 12 | M19: =M9 -> 1152.3878 | N19: =F19*M19*K19*L19 -> 746.74727 | O19: =N19 -> 746.74727 | P19: =N19-O19 -> 0 | Q19: =K19 -> 0.4 | R19: =L19 -> 12 | S19: =S9 -> 1210.0072 | T19: =F19*S19*Q19*R19 -> 784.08463 | U19: =T19 -> 784.08463 | V19: =T19-U19 -> 0 | W19: =I19+O19+U19 -> 2242.0198 | X19: =J19+P19+V19 -> 0 | Y19: =W19+X19 -> 2242.0198
B20: =B25 -> Mang.& tech.advisors - Nat.staff-Fringe Benefits | W20: =W25 -> 3636.2981 | X20: =X25 -> 1256.9795 | Y20: =Y25 -> 4893.2776
W21: =SUM(W15:W20) -> 15098.243 | X21: =SUM(X15:X20) -> 1256.9795 | Y21: =SUM(Y15:Y20) -> 16355.222
B22: Fringe Benefits – Int’l Staff | C22: =C10 -> 0.04 | D22: Salary | E22: 12 | F22: 0.29 | G22: 119.47 | H22: =G22*E22*F22 -> 415.7556 | I22: 311.8167 | J22: =H22-I22 -> 103.9389 | K22: =C22 -> 0.04 | L22: =E22 -> 12 | M22: =G22*$M$3 -> 163.56518 | N22: =M22*L22*F22 -> 569.20683 | O22: =I22*$O$3 -> 405.33053 | P22: =N22-O22 -> 163.87631 | Q22: =K22 -> 0.04 | R22: =L22 -> 12 | S22: =M22 -> 163.56518 | T22: =F22*S22*R22 -> 569.20683 | U22: =O22+(O22*$U$3) -> 386.80287 | V22: =T22-U22 -> 182.40396 | W22: =I22+O22+U22 -> 1103.9501 | X22: =J22+P22+V22 -> 450.21917 | Y22: =W22+X22 -> 1554.1693 | Z22: =H22+N22+T22-Y22 -> 0 | AA22: =I22+O22+U22-W22 -> 0 | AB22: =J22+P22+V22-X22 -> 0
B23: Overseas Allowances – Int’l Staff | C23: =C10 -> 0.04 | D23: FTE | E23: 12 | F23: 1 | G23: 2234.56 | H23: =C23*G23*E23 -> 1072.5888 | I23: 804.4416 | J23: =H23-I23 -> 268.1472 | K23: =K10 -> 0.04 | L23: =E23 -> 12 | M23: =G23*$M$3 -> 3059.3138 | N23: =K23*M23*L23 -> 1468.4706 | O23: =I23*$O$3 -> 1045.6936 | P23: =N23-O23 -> 422.77696 | Q23: =Q10 -> 0.04 | R23: =L23 -> 12 | S23: =M23 -> 3059.3138 | T23: =Q23*S23*R23 -> 1468.4706 | U23: =O23+(O23*$U$3) -> 997.89498 | V23: =T23-U23 -> 470.57562 | W23: =I23+O23+U23 -> 2848.0302 | X23: =J23+P23+V23 -> 1161.4998 | Y23: =W23+X23 -> 4009.53 | Z23: =H23+N23+T23-Y23 -> 0 | AA23: =I23+O23+U23-W23 -> 0 | AB23: =J23+P23+V23-X23 -> 0
B24: Housing and Local Benefits – Int’l Staff | C24: =C10 -> 0.04 | D24: FTE | E24: 12 | F24: 1 | G24: 1002.19 | H24: =C24*G24*E24 -> 481.0512 | I24: 360.7884 | J24: =H24-I24 -> 120.2628 | K24: =K10 -> 0.04 | L24: =E24 -> 12 | M24: =G24*$M$3 -> 1372.0883 | N24: =K24*M24*L24 -> 658.60239 | O24: =I24*$O$3 -> 468.98884 | P24: =N24-O24 -> 189.61355 | Q24: =Q10 -> 0.04 | R24: =L24 -> 12 | S24: =M24 -> 1372.0883 | T24: =Q24*S24*R24 -> 658.60239 | U24: =O24+(O24*$U$3) -> 447.55136 | V24: =T24-U24 -> 211.05103 | W24: =I24+O24+U24 -> 1277.3286 | X24: =J24+P24+V24 -> 520.92737 | Y24: =W24+X24 -> 1798.256 | Z24: =H24+N24+T24-Y24 -> 0 | AA24: =I24+O24+U24-W24 -> 0 | AB24: =J24+P24+V24-X24 -> 0
B25: Mang.& tech.advisors - Nat.staff-Fringe Benefits | C25: =C11 -> 0.65 | D25: Salary | E25: 12 | F25: 1 | G25: =1309/(C25*12) -> 167.82051 | H25: =C25*G25*E25 -> 1309 | I25: 1027.0921 | J25: =H25-I25 -> 281.90786 | K25: =C25 -> 0.65 | L25: =E25 -> 12 | M25: =G25*$M$3 -> 229.76139 | N25: =K25*M25*L25 -> 1792.1388 | O25: =I25*$O$3 -> 1335.1171 | P25: =N25-O25 -> 457.02174 | Q25: =K25 -> 0.65 | R25: =L25 -> 12 | S25: =M25 -> 229.76139 | T25: =Q25*S25*R25 -> 1792.1388 | U25: =O25+(O25*$U$3) -> 1274.0889 | V25: =T25-U25 -> 518.04994 | W25: =I25+O25+U25 -> 3636.2981 | X25: =J25+P25+V25 -> 1256.9795 | Y25: =W25+X25 -> 4893.2776 | Z25: =H25+N25+T25-Y25 -> 0 | AA25: =I25+O25+U25-W25 -> 0 | AB25: =J25+P25+V25-X25 -> 0
B26: Sub Total Fringe Benefits | H26: =SUM(H15:H25) -> 6914.2227 | I26: =SUM(I15:I25) -> 6139.9659 | J26: =SUM(J15:J25) -> 774.25676 | N26: =SUM(N15:N25) -> 8306.037 | O26: =SUM(O15:O25) -> 7072.7485 | P26: =SUM(P15:P25) -> 1233.2886 | T26: =SUM(T15:T25) -> 8496.918 | U26: =SUM(U15:U25) -> 7114.8374 | V26: =SUM(V15:V25) -> 1382.0805 | W26: =SUM(W15:W25) -> 39062.093 | X26: =SUM(X15:X25) -> 5903.5849 | Y26: =SUM(Y15:Y25) -> 44965.678 | Z26: =H26+N26+T26-Y26 -> -21248.5 | AA26: =I26+O26+U26-W26 -> -18734.541 | AB26: =J26+P26+V26-X26 -> -2513.9591
B27: Travel | Z27: =H27+N27+T27-Y27 -> 0 | AA27: =I27+O27+U27-W27 -> 0 | AB27: =J27+P27+V27-X27 -> 0
B28: Domestic Travel | C28: 14 | D28: flight/train | E28: 1 | F28: 1 | G28: =13000/$G$3 -> 200 | H28: =C28*G28*E28 -> 2800 | I28: =H28 -> 2800 | J28: =H28-I28 -> 0 | K28: 16 | L28: 1 | M28: =G28*1.05 -> 210 | N28: =K28*M28*L28 -> 3360 | O28: =N28 -> 3360 | P28: =N28-O28 -> 0 | Q28: 16 | R28: =L28 -> 1 | S28: =M28*1.05 -> 220.5 | T28: =Q28*S28*R28 -> 3528 | U28: =T28 -> 3528 | V28: =T28-U28 -> 0 | W28: =I28+O28+U28 -> 9688 | X28: =J28+P28+V28 -> 0 | Y28: =W28+X28 -> 9688 | Z28: =H28+N28+T28-Y28 -> 0 | AA28: =I28+O28+U28-W28 -> 0 | AB28: =J28+P28+V28-X28 -> 0
B29: Hotel | C29: =C28*3 -> 42 | D29: night | E29: 1 | F29: 1 | G29: =2700/$G$3 -> 41.538462 | H29: =C29*G29*E29 -> 1744.6154 | I29: =H29 -> 1744.6154 | J29: =H29-I29 -> 0 | K29: =K28*3 -> 48 | L29: 1 | M29: =G29*1.05 -> 43.615385 | N29: =K29*M29*L29 -> 2093.5385 | O29: =N29 -> 2093.5385 | P29: =N29-O29 -> 0 | Q29: =Q28*3 -> 48 | R29: =L29 -> 1 | S29: =M29*1.05 -> 45.796154 | T29: =Q29*S29*R29 -> 2198.2154 | U29: =T29 -> 2198.2154 | V29: =T29-U29 -> 0 | W29: =I29+O29+U29 -> 6036.3692 | X29: =J29+P29+V29 -> 0 | Y29: =W29+X29 -> 6036.3692 | Z29: =H29+N29+T29-Y29 -> 0 | AA29: =I29+O29+U29-W29 -> 0 | AB29: =J29+P29+V29-X29 -> 0
B30: Perdiem | C30: =C28*3 -> 42 | D30: day | E30: 1 | F30: 1 | G30: =1000/$G$3 -> 15.384615 | H30: =C30*G30*E30 -> 646.15385 | I30: =H30 -> 646.15385 | J30: =H30-I30 -> 0 | K30: =K28*3 -> 48 | L30: 1 | M30: =G30*1.05 -> 16.153846 | N30: =K30*M30*L30 -> 775.38462 | O30: =N30 -> 775.38462 | P30: =N30-O30 -> 0 | Q30: =Q28*3 -> 48 | R30: =L30 -> 1 | S30: =M30*1.05 -> 16.961538 | T30: =Q30*S30*R30 -> 814.15385 | U30: =T30 -> 814.15385 | V30: =T30-U30 -> 0 | W30: =I30+O30+U30 -> 2235.6923 | X30: =J30+P30+V30 -> 0 | Y30: =W30+X30 -> 2235.6923 | Z30: =H30+N30+T30-Y30 -> 0 | AA30: =I30+O30+U30-W30 -> 0 | AB30: =J30+P30+V30-X30 -> 0
B31: Mang.& tech.advisors - Nat.staff-Travel | C31: 1 | D31: Month | E31: 12 | F31: 1 | G31: 69.85 | H31: =C31*G31*E31 -> 838.2 | I31: 755.9244 | J31: =H31-I31 -> 82.2756 | K31: 12 | L31: 1 | M31: =G31*$M$3 -> 95.630936 | N31: =K31*M31*L31 -> 1147.5712 | O31: =I31*$O$3 -> 982.62613 | P31: =N31-O31 -> 164.94511 | Q31: =K31 -> 12 | R31: =L31 -> 1 | S31: =M31 -> 95.630936 | T31: =Q31*S31*R31 -> 1147.5712 | U31: =O31+(O31*$U$3) -> 937.71029 | V31: =T31-U31 -> 209.86095 | W31: =I31+O31+U31 -> 2676.2608 | X31: =J31+P31+V31 -> 457.08166 | Y31: =W31+X31 -> 3133.3425 | Z31: =H31+N31+T31-Y31 -> 0 | AA31: =I31+O31+U31-W31 -> 0 | AB31: =J31+P31+V31-X31 -> 0
B32: In-country program travel and vehicle expenses | C32: 1 | D32: Month | E32: 12 | F32: 1 | G32: =18000/$G$3 -> 276.92308 | H32: =C32*G32*E32 -> 3323.0769 | I32: 3323 | J32: =H32-I32 -> 0.076923077 | K32: 12 | L32: 1 | M32: =G32*$M$3 -> 379.13262 | N32: =K32*M32*L32 -> 4549.5914 | O32: =I32*$O$3 -> 4319.5677 | P32: =N32-O32 -> 230.02368 | Q32: =K32 -> 12 | R32: =L32 -> 1 | S32: =M32 -> 379.13262 | T32: =Q32*S32*R32 -> 4549.5914 | U32: =O32+(O32*$U$3) -> 4122.1203 | V32: =T32-U32 -> 427.47112 | W32: =I32+O32+U32 -> 11764.688 | X32: =J32+P32+V32 -> 657.57173 | Y32: =W32+X32 -> 12422.26 | Z32: =H32+N32+T32-Y32 -> 0 | AA32: =I32+O32+U32-W32 -> 0 | AB32: =J32+P32+V32-X32 -> 0
B33: Sub Total Travel & Transportation | H33: =SUM(H28:H32) -> 9352.0462 | I33: =SUM(I28:I32) -> 9269.6936 | J33: =SUM(J28:J32) -> 82.352523 | N33: =SUM(N28:N32) -> 11926.086 | O33: =SUM(O28:O32) -> 11531.117 | P33: =SUM(P28:P32) -> 394.9688 | T33: =SUM(T28:T32) -> 12237.532 | U33: =SUM(U28:U32) -> 11600.2 | V33: =SUM(V28:V32) -> 637.33207 | W33: =SUM(W28:W32) -> 32401.01 | X33: =SUM(X28:X32) -> 1114.6534 | Y33: =SUM(Y28:Y32) -> 33515.664 | Z33: =H33+N33+T33-Y33 -> 0 | AA33: =I33+O33+U33-W33 -> 0 | AB33: =J33+P33+V33-X33 -> 0
B34: Supplies | Z34: =H34+N34+T34-Y34 -> 0 | AA34: =I34+O34+U34-W34 -> 0 | AB34: =J34+P34+V34-X34 -> 0
B35: Office/Computer Supplies, Stationery and Services | C35: 1 | D35: Month | E35: 12 | F35: 1 | G35: 223.25385 | H35: =C35*G35*E35 -> 2679.0462 | I35: =C35*E35*F35*211.54 -> 2538.48 | J35: =H35-I35 -> 140.56615 | K35: =C35 -> 1 | L35: =E35 -> 12 | M35: =G35*1.05 -> 234.41654 | N35: =K35*M35*L35*F35 -> 2812.9985 | O35: =I35*1.05 -> 2665.404 | P35: =N35-O35 -> 147.59446 | Q35: =K35 -> 1 | R35: =L35 -> 12 | S35: =M35*1.05 -> 246.13737 | T35: =Q35*S35*R35*F35 -> 2953.6484 | U35: =O35*1.05 -> 2798.6742 | V35: =T35-U35 -> 154.97418 | W35: =I35+O35+U35 -> 8002.5582 | X35: =J35+P35+V35 -> 443.1348 | Y35: =W35+X35 -> 8445.693 | Z35: =H35+N35+T35-Y35 -> 0 | AA35: =I35+O35+U35-W35 -> 0 | AB35: =J35+P35+V35-X35 -> 0
B36: Printing | C36: 1 | D36: Month | E36: 12 | F36: 1 | G36: =3000/$G$3 -> 46.153846 | H36: =C36*G36*E36 -> 553.84615 | I36: =H36 -> 553.84615 | J36: =H36-I36 -> 0 | K36: =C36 -> 1 | L36: =E36 -> 12 | M36: =G36*1.05 -> 48.461538 | N36: =K36*M36*L36*F36 -> 581.53846 | O36: =N36 -> 581.53846 | P36: =N36-O36 -> 0 | Q36: =K36 -> 1 | R36: =L36 -> 12 | S36: =M36*1.05 -> 50.884615 | T36: =Q36*S36*R36*F36 -> 610.61538 | U36: =T36 -> 610.61538 | V36: =T36-U36 -> 0 | W36: =I36+O36+U36 -> 1746 | X36: =J36+P36+V36 -> 0 | Y36: =W36+X36 -> 1746 | Z36: =H36+N36+T36-Y36 -> 0 | AA36: =I36+O36+U36-W36 -> 0 | AB36: =J36+P36+V36-X36 -> 0
B37: Sub Total Supplies | H37: =SUM(H35:H36) -> 3232.8923 | I37: =SUM(I35:I36) -> 3092.3262 | J37: =SUM(J35:J36) -> 140.56615 | N37: =SUM(N35:N36) -> 3394.5369 | O37: =SUM(O35:O36) -> 3246.9425 | P37: =SUM(P35:P36) -> 147.59446 | T37: =SUM(T35:T36) -> 3564.2638 | U37: =SUM(U35:U36) -> 3409.2896 | V37: =SUM(V35:V36) -> 154.97418 | W37: =SUM(W35:W36) -> 9748.5582 | X37: =SUM(X35:X36) -> 443.1348 | Y37: =SUM(Y35:Y36) -> 10191.693 | Z37: =H37+N37+T37-Y37 -> 0 | AA37: =I37+O37+U37-W37 -> 0 | AB37: =J37+P37+V37-X37 -> 0
B38: Contractual | Z38: =H38+N38+T38-Y38 -> 0 | AA38: =I38+O38+U38-W38 -> 0 | AB38: =J38+P38+V38-X38 -> 0
B39: Prajwala | C39: 1 | D39: Lumpsum | E39: 1 | F39: 1 | G39: =Cereal!J42 -> 17932.32 | H39: =Cereal!J42 -> 17932.32 | I39: =Cereal!K42 -> 17932.32 | J39: =Cereal!L42 -> 0 | K39: 1 | L39: 1 | M39: =Cereal!M42 -> 25716.312 | N39: =Cereal!M42 -> 25716.312 | O39: =Cereal!N42 -> 25716.312 | P39: =Cereal!O42 -> 0 | Q39: 1 | R39: =L39 -> 1 | S39: =Cereal!P42 -> 6425.7124 | T39: =Q39*S39*R39*F39 -> 6425.7124 | U39: =Cereal!Q42 -> 6425.7124 | V39: =Cereal!R42 -> 0 | W39: =I39+O39+U39 -> 50074.344 | X39: =J39+P39+V39 -> 0 | Y39: =W39+X39 -> 50074.344 | Z39: =H39+N39+T39-Y39 -> 0 | AA39: =I39+O39+U39-W39 -> 0 | AB39: =J39+P39+V39-X39 -> 0
B40: Technical Advisor–Capacity Strengthening of Law enforcement Officials | C40: 10 | D40: Lumpsum | E40: 12 | F40: 1 | G40: =3000/$G$3 -> 46.153846 | H40: =C40*G40*E40 -> 5538.4615 | I40: 0 | J40: =H40-I40 -> 5538.4615 | K40: =C40 -> 10 | L40: =E40 -> 12 | M40: =G40*1.05 -> 48.461538 | N40: =6*E40*F40*G40 -> 3323.0769 | O40: 0 | P40: =N40-O40 -> 3323.0769 | Q40: =K40 -> 10 | R40: =L40 -> 12 | S40: =M40*1.05 -> 50.884615 | T40: =4*E40*F40*G40 -> 2215.3846 | U40: 0 | V40: =T40-U40 -> 2215.3846 | W40: =I40+O40+U40 -> 0 | X40: =J40+P40+V40 -> 11076.923 | Y40: =W40+X40 -> 11076.923 | Z40: =H40+N40+T40-Y40 -> 0 | AA40: =I40+O40+U40-W40 -> 0 | AB40: =J40+P40+V40-X40 -> 0
B41: Sub Total Contractual | H41: =SUM(H39:H40) -> 23470.782 | I41: =SUM(I39:I40) -> 17932.32 | J41: =SUM(J39:J40) -> 5538.4615 | M41: =SUM(M39:M40) -> 25764.774 | N41: =SUM(N39:N40) -> 29039.389 | O41: =SUM(O39:O40) -> 25716.312 | P41: =SUM(P39:P40) -> 3323.0769 | S41: =SUM(S39:S40) -> 6476.5971 | T41: =SUM(T39:T40) -> 8641.0971 | U41: =SUM(U39:U40) -> 6425.7124 | V41: =SUM(V39:V40) -> 2215.3846 | W41: =SUM(W39:W40) -> 50074.344 | X41: =SUM(X39:X40) -> 11076.923 | Y41: =SUM(Y39:Y40) -> 61151.268 | Z41: =H41+N41+T41-Y41 -> 0 | AA41: =I41+O41+U41-W41 -> 0 | AB41: =J41+P41+V41-X41 -> 0
B42: Other Direct Costs | Z42: =H42+N42+T42-Y42 -> 0 | AA42: =I42+O42+U42-W42 -> 0 | AB42: =J42+P42+V42-X42 -> 0
B43: Baseline Survey/Mid-term Review/Final Evaluation | C43: 1 | D43: Event | E43: 1 | F43: 1 | G43: =60000/$G$3 -> 923.07692 | H43: =C43*G43*E43*F43 -> 923.07692 | I43: =H43 -> 923.07692 | J43: =H43-I43 -> 0 | K43: =C43 -> 1 | L43: 1 | M43: 922.5 | N43: =K43*M43*L43*F43 -> 922.5 | O43: =N43 -> 922.5 | P43: =N43-O43 -> 0 | Q43: =K43 -> 1 | R43: =L43 -> 1 | S43: 11385 | T43: =Q43*S43*R43*F43 -> 11385 | U43: =T43 -> 11385 | V43: =T43-U43 -> 0 | W43: =I43+O43+U43 -> 13230.577 | X43: =J43+P43+V43 -> 0 | Y43: =W43+X43 -> 13230.577 | Z43: =H43+N43+T43-Y43 -> 0 | AA43: =I43+O43+U43-W43 -> 0 | AB43: =J43+P43+V43-X43 -> 0
B44: MEAL Workshop | C44: 1 | D44: Lumpsum | E44: 1 | F44: 1 | G44: =40000/$G$3 -> 615.38462 | H44: =C44*G44*E44*F44 -> 615.38462 | I44: =H44 -> 615.38462 | J44: =H44-I44 -> 0 | M44: 0 | N44: 0 | O44: =N44 -> 0 | P44: =N44-O44 -> 0 | S44: 0 | T44: 0 | U44: =T44 -> 0 | V44: 0 | W44: =I44+O44+U44 -> 615.38462 | X44: =J44+P44+V44 -> 0 | Y44: =W44+X44 -> 615.38462 | Z44: =H44+N44+T44-Y44 -> 0 | AA44: =I44+O44+U44-W44 -> 0 | AB44: =J44+P44+V44-X44 -> 0
B45: Implement. Plan Workshop | C45: 1 | D45: Workshop | E45: 1 | F45: 1 | G45: =30000/$G$3 -> 461.53846 | H45: =C45*G45*E45*F45 -> 461.53846 | I45: =H45 -> 461.53846 | J45: =H45-I45 -> 0 | M45: 0 | N45: 0 | O45: =N45 -> 0 | P45: =N45-O45 -> 0 | S45: 0 | T45: 0 | U45: =T45 -> 0 | V45: 0 | W45: =I45+O45+U45 -> 461.53846 | X45: =J45+P45+V45 -> 0 | Y45: =W45+X45 -> 461.53846 | Z45: =H45+N45+T45-Y45 -> 0 | AA45: =I45+O45+U45-W45 -> 0 | AB45: =J45+P45+V45-X45 -> 0
B46: Communication Expenses | C46: 1 | D46: Month | E46: 12 | F46: 1 | G46: =15750/$G$3 -> 242.30769 | H46: =C46*G46*E46*F46 -> 2907.6923 | I46: =H46 -> 2907.6923 | J46: =H46-I46 -> 0 | K46: =C46 -> 1 | L46: =E46 -> 12 | M46: =G46*1.05 -> 254.42308 | N46: =K46*M46*L46*F46 -> 3053.0769 | O46: =N46 -> 3053.0769 | P46: =N46-O46 -> 0 | Q46: =K46 -> 1 | R46: =L46 -> 12 | S46: =M46*1.05 -> 267.14423 | T46: =Q46*S46*R46*F46 -> 3205.7308 | U46: =T46 -> 3205.7308 | V46: =T46-U46 -> 0 | W46: =I46+O46+U46 -> 9166.5 | X46: =J46+P46+V46 -> 0 | Y46: =W46+X46 -> 9166.5 | Z46: =H46+N46+T46-Y46 -> 0 | AA46: =I46+O46+U46-W46 -> 0 | AB46: =J46+P46+V46-X46 -> 0
B47: Building rent, utilities and maintenance | C47: 1 | D47: Month | E47: 12 | F47: 1 | G47: =70026.5/$G$3 -> 1077.3308 | H47: =C47*G47*E47*F47 -> 12927.969 | I47: =H47 -> 12927.969 | J47: =H47-I47 -> 0 | K47: =C47 -> 1 | L47: =E47 -> 12 | M47: =G47*1.05 -> 1131.1973 | N47: =K47*M47*L47*F47 -> 13574.368 | O47: =N47 -> 13574.368 | P47: =N47-O47 -> 0 | Q47: =K47 -> 1 | R47: =L47 -> 12 | S47: =M47*1.05 -> 1187.7572 | T47: =Q47*S47*R47*F47 -> 14253.086 | U47: =T47 -> 14253.086 | V47: =T47-U47 -> 0 | W47: =I47+O47+U47 -> 40755.423 | X47: =J47+P47+V47 -> 0 | Y47: =W47+X47 -> 40755.423 | Z47: =H47+N47+T47-Y47 -> 0 | AA47: =I47+O47+U47-W47 -> 0 | AB47: =J47+P47+V47-X47 -> 0
B48: Contracted Audit & Legal Services | C48: 1 | D48: Month | E48: 12 | F48: 1 | G48: 90.25 | H48: =C48*G48*E48*F48 -> 1083 | I48: 851.28 | J48: =H48-I48 -> 231.72 | K48: =C48 -> 1 | L48: =E48 -> 12 | M48: =G48*$M$3 -> 123.56037 | N48: =K48*M48*L48*F48 -> 1482.7245 | O48: =I48*$O$3 -> 1106.5789 | P48: =N48-O48 -> 376.1456 | Q48: =K48 -> 1 | R48: =L48 -> 12 | S48: =M48 -> 123.56037 | T48: =Q48*S48*R48*F48 -> 1482.7245 | U48: =O48+(O48*$U$3) -> 1055.9972 | V48: =T48-U48 -> 426.72732 | W48: =I48+O48+U48 -> 3013.856 | X48: =J48+P48+V48 -> 1034.5929 | Y48: =W48+X48 -> 4048.4489 | Z48: =H48+N48+T48-Y48 -> 0 | AA48: =I48+O48+U48-W48 -> 0 | AB48: =J48+P48+V48-X48 -> 0
B49: Information Technology and Communication Expenses & Bank charges | C49: 1 | D49: Month | E49: 12 | F49: 1 | G49: 67.56 | H49: =C49*G49*E49*F49 -> 810.72 | I49: 805.32 | J49: =H49-I49 -> 5.4 | K49: =C49 -> 1 | L49: =E49 -> 12 | M49: =G49*$M$3 -> 92.49572 | N49: =K49*M49*L49*F49 -> 1109.9486 | O49: =I49*$O$3 -> 1046.8355 | P49: =N49-O49 -> 63.113177 | Q49: =K49 -> 1 | R49: =L49 -> 12 | S49: =M49 -> 92.49572 | T49: =Q49*S49*R49*F49 -> 1109.9486 | U49: =O49+(O49*$U$3) -> 998.98462 | V49: =T49-U49 -> 110.96403 | W49: =I49+O49+U49 -> 2851.1401 | X49: =J49+P49+V49 -> 179.4772 | Y49: =W49+X49 -> 3030.6173 | Z49: =H49+N49+T49-Y49 -> 0 | AA49: =I49+O49+U49-W49 -> 0 | AB49: =J49+P49+V49-X49 -> 0
B50: Facility Costs, IT Services, Communication, IT Salaries | C50: 4 | D50: Sq. Mt | E50: 12 | F50: 1 | G50: 86.29 | H50: =C50*G50*E50*F50 -> 4141.92 | I50: =H50 -> 4141.92 | J50: =H50-I50 -> 0 | K50: =C50 -> 4 | L50: =E50 -> 12 | M50: =G50*$M$3 -> 118.13878 | N50: =K50*M50*L50*F50 -> 5670.6613 | O50: =I50*$O$3 -> 5384.0818 | P50: =N50-O50 -> 286.57944 | Q50: =K50 -> 4 | R50: =L50 -> 12 | S50: =M50 -> 118.13878 | T50: =Q50*S50*R50*F50 -> 5670.6613 | U50: =O50+(O50*$U$3) -> 5137.9754 | V50: =T50-U50 -> 532.68582 | W50: =I50+O50+U50 -> 14663.977 | X50: =J50+P50+V50 -> 819.26527 | Y50: =W50+X50 -> 15483.243 | Z50: =H50+N50+T50-Y50 -> 0 | AA50: =I50+O50+U50-W50 -> 0 | AB50: =J50+P50+V50-X50 -> 0 | AD50: =533+287 -> 820
B51: Sub Total Other Direct Costs | H51: =SUM(H43:H50) -> 23871.302 | I51: =SUM(I43:I50) -> 23634.182 | J51: =SUM(J43:J50) -> 237.12 | M51: =SUM(M43:M50) -> 2642.3153 | N51: =SUM(N43:N50) -> 25813.279 | O51: =SUM(O43:O50) -> 25087.441 | P51: =SUM(P43:P50) -> 725.83822 | S51: =SUM(S43:S50) -> 13174.096 | T51: =SUM(T43:T50) -> 37107.151 | U51: =SUM(U43:U50) -> 36036.774 | V51: =SUM(V43:V50) -> 1070.3772 | W51: =SUM(W43:W50) -> 84758.396 | X51: =SUM(X43:X50) -> 2033.3354 | Y51: =SUM(Y43:Y50) -> 86791.732 | Z51: =H51+N51+T51-Y51 -> 0 | AA51: =I51+O51+U51-W51 -> 0 | AB51: =J51+P51+V51-X51 -> 0
B52: Total Direct Costs | H52: =H12+H26+H33+H37+H41+H51 -> 106602.74 | I52: =I12+I26+I33+I37+I41+I51 -> 97017.09 | J52: =J12+J26+J33+J37+J41+J51 -> 9585.647 | N52: =N12+N26+N33+N37+N41+N51 -> 124322.64 | O52: =O12+O26+O33+O37+O41+O51 -> 113953.73 | P52: =P12+P26+P33+P37+P41+P51 -> 10368.912 | T52: =T12+T26+T33+T37+T41+T51 -> 117304.21 | U52: =U12+U26+U33+U37+U41+U51 -> 106704.75 | V52: =V12+V26+V33+V37+V41+V51 -> 10599.461 | W52: =W12+W26+W33+W37+W41+W51 -> 336410.11 | X52: =X12+X26+X33+X37+X41+X51 -> 33067.979 | Y52: =Y12+Y26+Y33+Y37+Y41+Y51 -> 369478.08 | Z52: =H52+N52+T52-Y52 -> -21248.5 | AA52: =I52+O52+U52-W52 -> -18734.541 | AB52: =J52+P52+V52-X52 -> -2513.9591
B53: Indirect Cost Exclusions | H53: 0 | I53: 0 | J53: 0 | N53: 0 | O53: 0 | P53: 0 | T53: 0 | U53: 0 | V53: 0 | W53: 0 | X53: 0 | Y53: 0 | Z53: =H53+N53+T53-Y53 -> 0 | AA53: =I53+O53+U53-W53 -> 0 | AB53: =J53+P53+V53-X53 -> 0
B54: Modified Total Direct Costs | H54: =H52-H53 -> 106602.74 | I54: =I52-I53 -> 97017.09 | J54: =J52-J53 -> 9585.647 | N54: =N52-N53 -> 124322.64 | O54: =O52-O53 -> 113953.73 | P54: =P52-P53 -> 10368.912 | T54: =T52-T53 -> 117304.21 | U54: =U52-U53 -> 106704.75 | V54: =V52-V53 -> 10599.461 | W54: =W52-W53 -> 336410.11 | X54: =X52-X53 -> 33067.979 | Y54: =Y52-Y53 -> 369478.08 | Z54: =H54+N54+T54-Y54 -> -21248.5 | AA54: =I54+O54+U54-W54 -> -18734.541 | AB54: =J54+P54+V54-X54 -> -2513.9591
A55: 6961, 6963 | B55: Indirect Cost (17.88%) | D55: 0.1788 | H55: =H54*17.88/100 -> 19060.569 | I55: =I54*17.88/100 -> 17346.656 | J55: =J54*17.88/100 -> 1713.9137 | N55: =N54*17.88/100 -> 22228.888 | O55: =O54*17.88/100 -> 20374.927 | P55: =P54*17.88/100 -> 1853.9614 | T55: =T54*17.88/100 -> 20973.992 | U55: =U54*17.88/100 -> 19078.809 | V55: =V54*17.88/100 -> 1895.1836 | W55: =I55+O55+U55 -> 56800.391 | X55: =J55+P55+V55 -> 5463.0587 | Y55: =W55+X55 -> 62263.45 | Z55: =H55+N55+T55-Y55 -> 0 | AA55: =I55+O55+U55-W55 -> 0 | AB55: =J55+P55+V55-X55 -> 0
B56: GRAND TOTAL | H56: =H55+H52 -> 125663.31 | I56: =I55+I52 -> 114363.75 | J56: =J55+J52 -> 11299.561 | N56: =N55+N52 -> 146551.53 | O56: =O55+O52 -> 134328.66 | P56: =P55+P52 -> 12222.873 | T56: =T55+T52 -> 138278.2 | U56: =U55+U52 -> 125783.56 | V56: =V55+V52 -> 12494.645 | W56: =W55+W52 -> 393210.5 | X56: =X55+X52 -> 38531.037 | Y56: =Y55+Y52 -> 431741.53 | Z56: =H56+N56+T56-Y56 -> -21248.5 | AA56: =I56+O56+U56-W56 -> -18734.541 | AB56: =J56+P56+V56-X56 -> -2513.9591

Sheet Budget Summary + 12 Add Months
A1: PARTNERS OF THE AMERICAS
A2: SUMMARY BUDGET FOR MEXICO UNITED 2026 (12 Additional Months)
B3: Year 1 | E3: Year 2 | H3: Year 3 | K3: Year 4 | N3: Total
A4: BUDGET SUMMARY CATEGORIES | B4: Grant | C4: Cost Share | D4: Total | E4: Grant | F4: Cost Share | G4: Total | H4: Grant | I4: Cost Share | J4: Total | K4: Grant | L4: Cost Share | M4: Total | N4: Grant | O4: Cost Share | P4: Total
A5: A. Personnel | B5: ='Line Item Budget'!L15 -> 54250 | C5: ='Line Item Budget'!M15 -> 0 | D5: =B5+C5 -> 54250 | E5: ='Line Item Budget'!R15 -> 59926.5 | F5: ='Line Item Budget'!S15 -> 0 | G5: =E5+F5 -> 59926.5 | H5: =E5*1.035 -> 62023.927 | I5: 0 | J5: =H5+I5 -> 62023.927 | K5: ='Line Item Budget'!X15 -> 27101.992 | L5: ='Line Item Budget'!Y15 -> 0 | M5: =K5+L5 -> 27101.992 | N5: =B5+E5+H5+K5 -> 203302.42 | O5: ='Line Item Budget'!AA15 -> 0 | P5: =N5+O5 -> 203302.42
A6: B. Fringe Benefits | B6: ='Line Item Budget'!L24 -> 24793.82 | C6: ='Line Item Budget'!M24 -> 0 | D6: =B6+C6 -> 24793.82 | E6: ='Line Item Budget'!R24 -> 27582.212 | F6: ='Line Item Budget'!S24 -> 0 | G6: =E6+F6 -> 27582.212 | H6: =E6 -> 27582.212 | I6: 0 | J6: =H6+I6 -> 27582.212 | K6: ='Line Item Budget'!X24 -> 12285.965 | L6: ='Line Item Budget'!Y24 -> 0 | M6: =K6+L6 -> 12285.965 | N6: =B6+E6+H6+K6 -> 92244.209 | O6: ='Line Item Budget'!AA24 -> 0 | P6: =N6+O6 -> 92244.209
A7: C. Travel | B7: ='Line Item Budget'!L38 -> 12429 | C7: ='Line Item Budget'!M38 -> 0 | D7: =B7+C7 -> 12429 | E7: ='Line Item Budget'!R38 -> 7883.58 | F7: ='Line Item Budget'!S38 -> 0 | G7: =E7+F7 -> 7883.58 | H7: 8672.4 | I7: 0 | J7: =H7+I7 -> 8672.4 | K7: ='Line Item Budget'!X38 -> 3595.1022 | L7: ='Line Item Budget'!Y38 -> 0 | M7: =K7+L7 -> 3595.1022 | N7: =B7+E7+H7+K7 -> 32580.082 | O7: ='Line Item Budget'!AA38 -> 0 | P7: =N7+O7 -> 32580.082
A8: D. Equipment
A9: E. Supplies | B9: ='Line Item Budget'!L48 -> 8550 | C9: ='Line Item Budget'!M48 -> 0 | D9: =B9+C9 -> 8550 | E9: ='Line Item Budget'!R48 -> 7440 | F9: ='Line Item Budget'!S48 -> 0 | G9: =E9+F9 -> 7440 | H9: =E9 -> 7440 | I9: 0 | J9: =H9+I9 -> 7440 | K9: ='Line Item Budget'!X48 -> 2380 | L9: ='Line Item Budget'!Y48 -> 0 | M9: =K9+L9 -> 2380 | N9: =B9+E9+H9+K9 -> 25810 | O9: ='Line Item Budget'!AA48 -> 0 | P9: =N9+O9 -> 25810
A10: F. Contractual and Subawards | B10: ='Line Item Budget'!L57 -> 72393.76 | C10: ='Line Item Budget'!M57 -> 0 | D10: =B10+C10 -> 72393.76 | E10: ='Line Item Budget'!R57 -> 103345.74 | F10: ='Line Item Budget'!S57 -> 0 | G10: =E10+F10 -> 103345.74 | H10: 119249 | I10: 0 | J10: =H10+I10 -> 119249 | K10: ='Line Item Budget'!X57 -> 23573.137 | L10: ='Line Item Budget'!Y57 -> 0 | M10: =K10+L10 -> 23573.137 | N10: =B10+E10+H10+K10 -> 318561.63 | O10: ='Line Item Budget'!AA57 -> 0 | P10: =N10+O10 -> 318561.63
A11: G. Construction
A12: H. Other Direct Costs | B12: ='Line Item Budget'!L89 -> 12075 | C12: ='Line Item Budget'!M89 -> 0 | D12: =B12+C12 -> 12075 | E12: ='Line Item Budget'!R89 -> 20371.5 | F12: ='Line Item Budget'!S89 -> 0 | G12: =E12+F12 -> 20371.5 | H12: 23028 | I12: 0 | J12: =H12+I12 -> 23028 | K12: ='Line Item Budget'!X89 -> 2275 | L12: ='Line Item Budget'!Y89 -> 0 | M12: =K12+L12 -> 2275 | N12: =B12+E12+H12+K12 -> 57749.5 | O12: ='Line Item Budget'!AA89 -> 0 | P12: =N12+O12 -> 57749.5
A14: I. Total Direct Costs | B14: ='Line Item Budget'!L90 -> 184491.58 | C14: ='Line Item Budget'!M90 -> 0 | D14: =B14+C14 -> 184491.58 | E14: ='Line Item Budget'!R90 -> 226549.53 | F14: ='Line Item Budget'!S90 -> 0 | G14: =E14+F14 -> 226549.53 | H14: =SUM(H12,H10,H9,H7,H6,H5) -> 247995.54 | I14: 0 | J14: =H14+I14 -> 247995.54 | K14: ='Line Item Budget'!W90 -> 71211.197 | L14: ='Line Item Budget'!Y90 -> 0 | M14: =K14+L14 -> 71211.197 | N14: =B14+E14+H14+K14 -> 730247.84 | O14: =SUM(O5:O12) -> 0 | P14: =N14+O14 -> 730247.84
A16: J. Indirect Costs | B16: ='Line Item Budget'!L92 -> 51657.642 | C16: ='Line Item Budget'!M92 -> 0 | D16: =B16+C16 -> 51657.642 | E16: ='Line Item Budget'!R92 -> 63433.868 | F16: ='Line Item Budget'!S92 -> 0 | G16: =E16+F16 -> 63433.868 | H16: =H14*28% -> 69438.751 | I16: 0 | J16: =H16+I16 -> 69438.751 | K16: ='Line Item Budget'!X92 -> 19939.135 | L16: ='Line Item Budget'!Y92 -> 0 | M16: =K16+L16 -> 19939.135 | N16: =B16+E16+H16+K16 -> 204469.4 | O16: ='Line Item Budget'!AA92 -> 0 | P16: =N16+O16 -> 204469.4
A18: K. Total Costs | B18: =B14+B16 -> 236149.22 | C18: =C14+C16 -> 0 | D18: =D14+D16 -> 236149.22 | E18: =E14+E16 -> 289983.4 | F18: =F14+F16 -> 0 | G18: =G14+G16 -> 289983.4 | H18: =H14+H16 -> 317434.29 | I18: =I14+I16 -> 0 | J18: =H18+I18 -> 317434.29 | K18: =K14+K16 -> 91150.333 | L18: =L14+L16 -> 0 | M18: =M14+M16 -> 91150.333 | N18: =N14+N16 -> 934717.24 | O18: =O14+O16 -> 0 | P18: =P14+P16 -> 934717.24
