Workbook

Sheet POA Line Item Budget
D1: PARTNERS OF THE AMERICAS
D2: Project Name: 2024 TIP Office International Programs to Combat Human Trafficking
A3: Entity: | B3: P | D3: Funding Opportunity: DFOP0016706
A4: Program/Dept.: | B4: 20200 | D4: Budget Assumptions
A5: Funder-Grant: | B5: DOS454 | D5: Inflation - Locally Purchased Goods/Services - 4% | E5: 1.04
D6: Merit Based Increases for HQ & Field Staff - 5% | E6: 1.05
D8: All costs in US$ | E8: Year 1 | K8: Year 2 | O8: Year 3 | S8: Year 4 | W8: Year 5 | AA8: Total
A9: Budget Code | B9: Account Code | C9: County Code | D9: Budget Line Items | E9: No. | F9: Unit Type | G9: No. of Units | H9: % | I9: Rate | J9: JTIP Total | K9: No. | L9: No. of Units | M9: Rate | N9: JTIP Total | O9: No. | P9: No. of Units | Q9: Rate | R9: JTIP Total | S9: No. | T9: No. of Units | U9: Rate | V9: JTIP Total | W9: No. | X9: No. of Units | Y9: Rate | Z9: JTIP Total | AA9: Total Federal Funds Requested
D10: Personnel
A11: PERSNL-PC | B11: 70000 | C11: PRY | D11: Project Coordinator (50% LOE) - Macarena Jiménez | E11: 1 | F11: FTE/month | G11: 12 | H11: 0.5 | I11: 9680 | J11: =E11*I11*G11*H11 -> 58080 | K11: =E11 -> 1 | L11: 12 | M11: =I11*$E$6 -> 10164 | N11: =K11*M11*L11*H11 -> 60984 | O11: 1 | P11: 12 | Q11: =M11*$E$6 -> 10672.2 | R11: =H11*O11*P11*Q11 -> 64033.2 | S11: 1 | T11: 12 | U11: =Q11*$E$6 -> 11205.81 | V11: =H11*S11*T11*U11 -> 67234.86 | W11: 1 | X11: 12 | Y11: =U11*$E$6 -> 11766.101 | Z11: =H11*W11*X11*Y11 -> 70596.603 | AA11: =J11+N11+R11+V11+Z11 -> 320928.66
A12: PERSNL-TS | B12: 70000 | C12: PRY | D12: Technical Specialist (50% LOE) - Aurora Figueredo | E12: 1 | F12: FTE/month | G12: 9 | H12: 0.5 | I12: 4800 | J12: =E12*I12*G12*H12 -> 21600 | K12: =E12 -> 1 | L12: 12 | M12: =I12*$E$6 -> 5040 | N12: =K12*M12*L12*H12 -> 30240 | O12: 1 | P12: 12 | Q12: =M12*$E$6 -> 5292 | R12: =H12*O12*P12*Q12 -> 31752 | S12: 1 | T12: 12 | U12: =Q12*$E$6 -> 5556.6 | V12: =H12*S12*T12*U12 -> 33339.6 | W12: 1 | X12: 6 | Y12: =U12*$E$6 -> 5834.43 | Z12: =H12*W12*X12*Y12 -> 17503.29 | AA12: =J12+N12+R12+V12+Z12 -> 134434.89
A13: PERSNL-M&E | B13: 70000 | C13: PRY | D13: M&E Coordinator (100% LOE) | E13: 1 | F13: FTE/month | G13: 9 | H13: 1 | I13: 2000 | J13: =E13*G13*H13*I13 -> 18000 | K13: 1 | L13: 12 | M13: =I13*$E$6 -> 2100 | N13: =K13*M13*L13*H13 -> 25200 | O13: 1 | P13: 12 | Q13: =M13*$E$6 -> 2205 | R13: =O13*Q13*P13*H13 -> 26460 | S13: 1 | T13: 12 | U13: =Q13*$E$6 -> 2315.25 | V13: =S13*U13*T13*H13 -> 27783 | W13: 1 | X13: 8 | Y13: =U13*$E$6*H13 -> 2431.0125 | Z13: =W13*Y13*X13*H13 -> 19448.1 | AA13: =J13+N13+R13+V13+Z13 -> 116891.1
A14: PERSNL-F&A | B14: 70000 | C14: PRY | D14: Administration and Finance Officer (50% LOE) | E14: 1 | F14: FTE/month | G14: 9 | H14: 0.5 | I14: 2200 | J14: =E14*I14*G14*H14 -> 9900 | K14: =E14 -> 1 | L14: 12 | M14: =I14*$E$6 -> 2310 | N14: =K14*M14*L14*H14 -> 13860 | O14: 1 | P14: 12 | Q14: =M14*$E$6 -> 2425.5 | R14: =H14*O14*P14*Q14 -> 14553 | S14: 1 | T14: 12 | U14: =Q14*$E$6 -> 2546.775 | V14: =H14*S14*T14*U14 -> 15280.65 | W14: 1 | X14: 8 | Y14: =U14*$E$6 -> 2674.1137 | Z14: =H14*W14*X14*Y14 -> 10696.455 | AA14: =J14+N14+R14+V14+Z14 -> 64290.105
A15: PERSNL | B15: 50000 | C15: PRY | D15: Project Manager (HQ) (30% LOE) | E15: 1 | F15: FTE/month | G15: 12 | H15: 0.3 | I15: 5567 | J15: =E15*I15*G15*H15 -> 20041.2 | K15: =E15 -> 1 | L15: 12 | M15: =I15*$E$6 -> 5845.35 | N15: =K15*M15*L15*H15 -> 21043.26 | O15: 1 | P15: 12 | Q15: =M15*$E$6 -> 6137.6175 | R15: =H15*O15*P15*Q15 -> 22095.423 | S15: 1 | T15: 12 | U15: =Q15*$E$6 -> 6444.4984 | V15: =H15*S15*T15*U15 -> 23200.194 | W15: 1 | X15: 12 | Y15: =U15*$E$6 -> 6766.7233 | Z15: =H15*W15*X15*Y15 -> 24360.204 | AA15: =J15+N15+R15+V15+Z15 -> 110740.28
D16: Subtotal Personnel | J16: =SUM(J11:J15) -> 127621.2 | N16: =SUM(N11:N15) -> 151327.26 | R16: =SUM(R11:R15) -> 158893.62 | V16: =SUM(V11:V15) -> 166838.3 | Z16: =SUM(Z11:Z15) -> 142604.65 | AA16: =SUM(AA11:AA15) -> 747285.04
D17: Fringe Benefits
A18: FRINGE-PY | B18: 70015 | C18: PRY | D18: =D11 -> Project Coordinator (50% LOE) - Macarena Jiménez | E18: =E11 -> 1 | F18: % Salary | G18: 1 | H18: 0.3527 | I18: =J11 -> 58080 | J18: =E18*I18*G18*H18 -> 20484.816 | K18: =E18 -> 1 | L18: 1 | M18: =N11 -> 60984 | N18: =H18*M18*K18*L18 -> 21509.057 | O18: 1 | P18: 1 | Q18: =R11 -> 64033.2 | R18: =H18*O18*P18*Q18 -> 22584.51 | S18: 1 | T18: 1 | U18: =V11 -> 67234.86 | V18: =H18*S18*T18*U18 -> 23713.735 | W18: 1 | X18: 1 | Y18: =Z11 -> 70596.603 | Z18: =H18*W18*X18*Y18 -> 24899.422 | AA18: =J18+N18+R18+V18+Z18 -> 113191.54
A19: FRINGE-PY | B19: 70015 | C19: PRY | D19: =D12 -> Technical Specialist (50% LOE) - Aurora Figueredo | E19: =E12 -> 1 | F19: % Salary | G19: 1 | H19: 0.3527 | I19: =J12 -> 21600 | J19: =E19*I19*G19*H19 -> 7618.32 | K19: =E19 -> 1 | L19: 1 | M19: =N12 -> 30240 | N19: =H19*M19*K19*L19 -> 10665.648 | O19: 1 | P19: 1 | Q19: =R12 -> 31752 | R19: =H19*O19*P19*Q19 -> 11198.93 | S19: 1 | T19: 1 | U19: =V12 -> 33339.6 | V19: =H19*S19*T19*U19 -> 11758.877 | W19: 1 | X19: 1 | Y19: =Z12 -> 17503.29 | Z19: =H19*W19*X19*Y19 -> 6173.4104 | AA19: =J19+N19+R19+V19+Z19 -> 47415.186
A20: FRINGE-PY | B20: 70015 | C20: PRY | D20: M&E Coordinator (100% LOE) | E20: =E13 -> 1 | F20: % Salary | G20: 1 | H20: 0.3527 | I20: =J13 -> 18000 | J20: =E20*I20*G20*H20 -> 6348.6 | K20: 1 | L20: 1 | M20: =N13 -> 25200 | N20: =H20*M20*K20*L20 -> 8888.04 | O20: 1 | P20: 1 | Q20: =R13 -> 26460 | R20: =H20*O20*P20*Q20 -> 9332.442 | S20: 1 | T20: 1 | U20: =V13 -> 27783 | V20: =H20*S20*T20*U20 -> 9799.0641 | W20: 1 | X20: 1 | Y20: =Z13 -> 19448.1 | Z20: =H20*W20*X20*Y20 -> 6859.3449 | AA20: =J20+N20+R20+V20+Z20 -> 41227.491
A21: FRINGE-PY | B21: 70015 | C21: PRY | D21: =D14 -> Administration and Finance Officer (50% LOE) | E21: =E14 -> 1 | F21: % Salary | G21: 1 | H21: 0.3527 | I21: =J14 -> 9900 | J21: =E21*I21*G21*H21 -> 3491.73 | K21: =E21 -> 1 | L21: 1 | M21: =N14 -> 13860 | N21: =H21*M21*K21*L21 -> 4888.422 | O21: 1 | P21: 1 | Q21: =R14 -> 14553 | R21: =H21*O21*P21*Q21 -> 5132.8431 | S21: 1 | T21: 1 | U21: =V14 -> 15280.65 | V21: =H21*S21*T21*U21 -> 5389.4853 | W21: 1 | X21: 1 | Y21: =Z14 -> 10696.455 | Z21: =H21*W21*X21*Y21 -> 3772.6397 | AA21: =J21+N21+R21+V21+Z21 -> 22675.12
A22: FRINGE | B22: 50900 | C22: PRY | D22: =D15 -> Project Manager (HQ) (30% LOE) | E22: =E15 -> 1 | F22: % Salary | G22: 1 | H22: 0.2347 | I22: =J15 -> 20041.2 | J22: =E22*I22*G22*H22 -> 4703.6696 | K22: =E22 -> 1 | L22: 1 | M22: =N15 -> 21043.26 | N22: =H22*M22*K22*L22 -> 4938.8531 | O22: 1 | P22: 1 | Q22: =R15 -> 22095.423 | R22: =H22*O22*P22*Q22 -> 5185.7958 | S22: 1 | T22: 1 | U22: =V15 -> 23200.194 | V22: =H22*S22*T22*U22 -> 5445.0856 | W22: 1 | X22: 1 | Y22: =Z15 -> 24360.204 | Z22: =H22*W22*X22*Y22 -> 5717.3398 | AA22: =J22+N22+R22+V22+Z22 -> 25990.744
D23: Subtotal Fringe Benefits | J23: =SUM(J18:J22) -> 42647.136 | N23: =SUM(N18:N22) -> 50890.02 | R23: =SUM(R18:R22) -> 53434.521 | V23: =SUM(V18:V22) -> 56106.247 | Z23: =SUM(Z18:Z22) -> 47422.157 | AA23: =J23+N23+R23+V23+Z23 -> 250500.08
D24: Travel
D25: HQ Staff International Travel
A26: STFTRAVEL | B26: 86040 | C26: USA | D26: International Airfare (Washington, DC- Asuncion, Paraguay) | E26: 1 | F26: Trip | G26: 1 | H26: 1 | I26: 2000 | J26: =E26*I26*G26 -> 2000 | K26: 1 | L26: 1 | M26: =I26*$E$5 -> 2080 | N26: =K26*M26*L26*H26 -> 2080 | O26: 1 | P26: 1 | Q26: =M26*$E$5 -> 2163.2 | R26: =O26*Q26*P26*L26 -> 2163.2 | S26: 1 | T26: 1 | U26: =Q26*$E$5 -> 2249.728 | V26: =S26*U26*T26*P26 -> 2249.728 | W26: 1 | X26: 1 | Y26: =U26*$E$5 -> 2339.7171 | Z26: =W26*Y26*X26*T26 -> 2339.7171 | AA26: =J26+N26+R26+V26+Z26 -> 10832.645
A27: GROUNDTRAN | B27: 86000 | C27: USA | D27: Ground Transportation | E27: 1 | F27: Day | G27: 7 | H27: 1 | I27: 50 | J27: =E27*I27*G27 -> 350 | K27: 1 | L27: 7 | M27: =I27*$E$5 -> 52 | N27: =K27*M27*L27*H27 -> 364 | O27: 1 | P27: 7 | Q27: =M27*$E$5 -> 54.08 | R27: =O27*Q27*P27 -> 378.56 | S27: 1 | T27: 7 | U27: =Q27*$E$5 -> 56.2432 | V27: =S27*U27*T27 -> 393.7024 | W27: 1 | X27: 7 | Y27: =U27*$E$5 -> 58.492928 | Z27: =W27*Y27*X27 -> 409.4505 | AA27: =J27+N27+R27+V27+Z27 -> 1895.7129
A28: LODGING | B28: 86030 | C28: USA | D28: Lodging in Asuncion | E28: 1 | F28: Night | G28: =G26*7 -> 7 | H28: 1 | I28: 95 | J28: =E28*I28*G28 -> 665 | K28: 1 | L28: =L26*7 -> 7 | M28: =I28*$E$5 -> 98.8 | N28: =K28*M28*L28*H28 -> 691.6 | O28: 1 | P28: =P26*7 -> 7 | Q28: =M28*$E$5 -> 102.752 | R28: =O28*Q28*P28 -> 719.264 | S28: 1 | T28: =T26*7 -> 7 | U28: =Q28*$E$5 -> 106.86208 | V28: =S28*U28*T28 -> 748.03456 | W28: 1 | X28: =X26*7 -> 7 | Y28: =U28*$E$5 -> 111.13656 | Z28: =W28*Y28*X28 -> 777.95594 | AA28: =J28+N28+R28+V28+Z28 -> 3601.8545
A29: STFCN DIEM | B29: 86050 | C29: USA | D29: M&IE in Asuncion | E29: 1 | F29: Day | G29: =G26*7 -> 7 | H29: 1 | I29: 81 | J29: =E29*I29*G29 -> 567 | K29: 1 | L29: =L26*7 -> 7 | M29: =I29*$E$5 -> 84.24 | N29: =K29*M29*L29*H29 -> 589.68 | O29: 1 | P29: =P26*7 -> 7 | Q29: =M29*$E$5 -> 87.6096 | R29: =O29*Q29*P29 -> 613.2672 | S29: 1 | T29: =T26*7 -> 7 | U29: =Q29*$E$5 -> 91.113984 | V29: =S29*U29*T29 -> 637.79789 | W29: 1 | X29: =X26*7 -> 7 | Y29: =U29*$E$5 -> 94.758543 | Z29: =W29*Y29*X29 -> 663.3098 | AA29: =J29+N29+R29+V29+Z29 -> 3071.0549
D30: Local Staff In-Country Travel | AA30: =J30+N30+R30+V30+Z30 -> 0
A31: LSLODGING | B31: 86030 | C31: PRY | D31: Lodging in Chaco, Ciudad del Este, Caaguazú, and Alto Paraná | E31: 3 | F31: Night | G31: 3 | H31: 1 | I31: 85 | J31: =E31*I31*G31 -> 765 | K31: 6 | L31: 3 | M31: =I31*$E$5 -> 88.4 | N31: =K31*M31*L31*H31 -> 1591.2 | O31: 6 | P31: 3 | Q31: =M31*$E$5 -> 91.936 | R31: =O31*Q31*P31 -> 1654.848 | S31: 6 | T31: 3 | U31: =Q31*$E$5 -> 95.61344 | V31: =S31*U31*T31 -> 1721.0419 | W31: 6 | X31: 3 | Y31: =U31*$E$5 -> 99.437978 | Z31: =W31*Y31*X31 -> 1789.8836 | AA31: =J31+N31+R31+V31+Z31 -> 7521.9735
A32: LSM&IE | B32: 86050 | C32: PRY | D32: M&IE in Chaco, Ciudad del Este, Caaguazú, and Alto Paraná | E32: 3 | F32: Day | G32: 3 | H32: 1 | I32: =60 * 0.9 -> 54 | J32: =E32*I32*G32 -> 486 | K32: 6 | L32: 3 | M32: =I32*$E$5 -> 56.16 | N32: =K32*M32*L32*H32 -> 1010.88 | O32: 6 | P32: 3 | Q32: =M32*$E$5 -> 58.4064 | R32: =O32*Q32*P32 -> 1051.3152 | S32: 6 | T32: 3 | U32: =Q32*$E$5 -> 60.742656 | V32: =S32*U32*T32 -> 1093.3678 | W32: 6 | X32: 3 | Y32: =U32*$E$5 -> 63.172362 | Z32: =W32*Y32*X32 -> 1137.1025 | AA32: =J32+N32+R32+V32+Z32 -> 4778.6655
A33: LSTRANS | B33: 86000 | C33: PRY | D33: Ground Transportation in Chaco, Ciudad del Este, Caaguazú, and Alto Paraná | E33: 3 | F33: Trip | G33: 1 | H33: 1 | I33: 750 | J33: =E33*I33*G33 -> 2250 | K33: 6 | L33: 1 | M33: =I33*$E$5 -> 780 | N33: =K33*M33*L33*H33 -> 4680 | O33: 6 | P33: 1 | Q33: =M33*$E$5 -> 811.2 | R33: =O33*Q33*P33 -> 4867.2 | S33: 6 | T33: 1 | U33: =Q33*$E$5 -> 843.648 | V33: =S33*U33*T33 -> 5061.888 | W33: 6 | X33: 1 | Y33: =U33*$E$5 -> 877.39392 | Z33: =W33*Y33*X33 -> 5264.3635 | AA33: =J33+N33+R33+V33+Z33 -> 22123.452
D34: International Travel - Participants Exchange of Experience on Best Practices for Managing Shelters (Activity 2.1)
A35: TRVL.2.1.A | B35: 86040 | C35: PRY | D35: International Airfare (Asuncion, Paraguay to Chile/Argentina) | E35: 0 | F35: Trip | G35: 0 | H35: 1 | I35: 350 | J35: =E35*I35*G35 -> 0 | K35: 3 | L35: 1 | M35: =I35*$E$5 -> 364 | N35: =K35*M35*L35*H35 -> 1092 | O35: 3 | P35: 1 | Q35: =M35*$E$5 -> 378.56 | R35: =O35*Q35*P35*L35 -> 1135.68 | S35: 0 | T35: 0 | U35: 0 | V35: =S35*U35*T35*P35 -> 0 | W35: 0 | X35: 0 | Y35: 0 | Z35: 0 | AA35: =J35+N35+R35+V35+Z35 -> 2227.68
A36: TRVL.2.1.B | B36: 86000 | C36: PRY | D36: Ground Transportation | E36: 0 | F36: Trip | G36: 0 | H36: 1 | I36: 50 | J36: =E36*I36*G36 -> 0 | K36: 3 | L36: 1 | M36: =I36*$E$5 -> 52 | N36: =K36*M36*L36*H36 -> 156 | O36: 3 | P36: 1 | Q36: =M36*$E$5 -> 54.08 | R36: =O36*Q36*P36*L36 -> 162.24 | S36: 0 | T36: 0 | U36: 0 | V36: =S36*U36*T36*P36 -> 0 | W36: 0 | X36: 0 | Y36: 0 | Z36: 0 | AA36: =J36+N36+R36+V36+Z36 -> 318.24
A37: TRVL.2.1.C | B37: 86030 | C37: PRY | D37: Lodging in Chile/Argentina | E37: 0 | F37: Night | G37: =G36*2 -> 0 | H37: 1 | I37: 110 | J37: =E37*I37*G37 -> 0 | K37: 3 | L37: 4 | M37: =I37*$E$5 -> 114.4 | N37: =K37*M37*L37*H37 -> 1372.8 | O37: 3 | P37: 4 | Q37: =M37*$E$5 -> 118.976 | R37: =O37*Q37*P37 -> 1427.712 | S37: 0 | T37: 0 | U37: 0 | V37: =S37*U37*T37*P37 -> 0 | W37: 0 | X37: 0 | Y37: 0 | Z37: 0 | AA37: =J37+N37+R37+V37+Z37 -> 2800.512
A38: TRVL.2.1.D | B38: 86050 | C38: PRY | D38: M&IE in Chile/Argentina | E38: 0 | F38: Day | G38: =G36*2 -> 0 | H38: 1 | I38: 100 | J38: =E38*I38*G38 -> 0 | K38: 3 | L38: 4 | M38: =I38*$E$5 -> 104 | N38: =K38*M38*L38*H38 -> 1248 | O38: 3 | P38: 4 | Q38: =M38*$E$5 -> 108.16 | R38: =O38*Q38*P38 -> 1297.92 | S38: 0 | T38: 0 | U38: 0 | V38: =S38*U38*T38*P38 -> 0 | W38: 0 | X38: 0 | Y38: 0 | Z38: 0 | AA38: =J38+N38+R38+V38+Z38 -> 2545.92
D39: Domestic Travel - Participants of Coordination Meetings to Develop a Network of Alternative Shelters (Activity 3.4)
A40: TRVL.3.4.A | B40: 86000 | C40: PRY | D40: Ground Transportation to/from Asuncion | E40: 1 | F40: Participant | G40: 10 | H40: 1 | I40: 250 | J40: =E40*I40*G40 -> 2500 | K40: 2 | L40: 10 | M40: =I40*$E$5 -> 260 | N40: =K40*M40*L40*H40 -> 5200 | O40: 2 | P40: 10 | Q40: =M40*$E$5 -> 270.4 | R40: =H40*O40*P40*Q40 -> 5408 | S40: 2 | T40: 10 | U40: =Q40*$E$5 -> 281.216 | V40: =S40*T40*U40*H40 -> 5624.32 | W40: 0 | X40: 0 | Y40: 0 | Z40: 0 | AA40: =J40+N40+R40+V40+Z40 -> 18732.32
A41: TRVL.3.4.B | B41: 86030 | C41: PRY | D41: Lodging in Asuncion | E41: 1 | F41: Night | G41: 10 | H41: 1 | I41: 95 | J41: =E41*I41*G41 -> 950 | K41: 2 | L41: =L40*1 -> 10 | M41: =I41*$E$5 -> 98.8 | N41: =K41*M41*L41*H41 -> 1976 | O41: 2 | P41: =P40*1 -> 10 | Q41: =M41*$E$5 -> 102.752 | R41: =H41*O41*P41*Q41 -> 2055.04 | S41: 2 | T41: 10 | U41: =Q41*$E$5 -> 106.86208 | V41: =H41*S41*T41*U41 -> 2137.2416 | W41: 0 | X41: 0 | Y41: 0 | Z41: 0 | AA41: =J41+N41+R41+V41+Z41 -> 7118.2816
A42: TRVL.3.4.C | B42: 86050 | C42: PRY | D42: M&IE in Asuncion | E42: 1 | F42: Day | G42: 10 | H42: 1 | I42: 81 | J42: =E42*I42*G42 -> 810 | K42: 2 | L42: =L41*1 -> 10 | M42: =I42*$E$5 -> 84.24 | N42: =K42*M42*L42*H42 -> 1684.8 | O42: 2 | P42: =P41*1 -> 10 | Q42: =M42*$E$5 -> 87.6096 | R42: =H42*O42*P42*Q42 -> 1752.192 | S42: 2 | T42: =T41*1 -> 10 | U42: =Q42*$E$5 -> 91.113984 | V42: =H42*S42*T42*U42 -> 1822.2797 | W42: 0 | X42: 0 | Y42: 0 | Z42: 0 | AA42: =J42+N42+R42+V42+Z42 -> 6069.2717
D43: Subtotal Travel | J43: =SUM(J26:J42) -> 11343 | N43: =SUM(N26:N42) -> 23736.96 | R43: =SUM(R26:R42) -> 24686.438 | V43: =SUM(V26:V42) -> 21489.402 | Z43: =SUM(Z26:Z42) -> 12381.783 | AA43: =SUM(AA26:AA42) -> 93637.583
D44: Supplies
A45: SUPPLIES | B45: 82401 | C45: PRY | D45: Office Supplies | E45: 1 | F45: Month | G45: 10 | H45: 1 | I45: 90 | J45: =E45*I45*G45*H45 -> 900 | K45: 1 | L45: 12 | M45: =I45*$E$5 -> 93.6 | N45: =K45*M45*L45*H45 -> 1123.2 | O45: 1 | P45: 12 | Q45: =M45*$E$5 -> 97.344 | R45: =O45*Q45*P45 -> 1168.128 | S45: 1 | T45: 12 | U45: =Q45*$E$5 -> 101.23776 | V45: =S45*U45*T45 -> 1214.8531 | W45: 1 | X45: 12 | Y45: =U45*$E$5 -> 105.28727 | Z45: =W45*Y45*X45 -> 1263.4472 | AA45: =J45+N45+R45+V45+Z45 -> 5669.6284
A46: LAPTOP | B46: 82401 | C46: PRY | D46: Laptop Computers & Software | E46: 1 | F46: Unit | G46: 5 | H46: 1 | I46: 1200 | J46: =E46*I46*G46*H46 -> 6000 | K46: 0 | L46: 0 | M46: 0 | N46: 0 | O46: 0 | P46: 0 | Q46: 0 | R46: 0 | S46: 0 | T46: 0 | U46: 0 | V46: =S46*U46*T46*P46 -> 0 | W46: 0 | X46: 0 | Y46: 0 | Z46: =W46*Y46*X46*T46 -> 0 | AA46: =N46+J46 -> 6000
D47: Subtotal Supplies | J47: =SUM(J45:J46) -> 6900 | N47: =SUM(N45:N46) -> 1123.2 | R47: =SUM(R45:R46) -> 1168.128 | V47: =SUM(V45:V46) -> 1214.8531 | Z47: =SUM(Z45:Z46) -> 1263.4472 | AA47: =SUM(AA45:AA46) -> 11669.628
D48: Contractual
D49: Activity 1.3: Establish Adult Male Victims of Trafficking Shelter.
A50: TIPMANAGER | B50: 81000 | C50: PRY | D50: TIP Shelter Manager | E50: 1 | F50: Month | G50: 3 | H50: 1 | I50: 1950 | J50: =E50*G50*H50*I50 -> 5850 | K50: 1 | L50: 12 | M50: =I50*$E$5 -> 2028 | N50: =K50*L50*M50 -> 24336 | O50: 1 | P50: 12 | Q50: =M50*$E$5 -> 2109.12 | R50: =O50*P50*Q50 -> 25309.44 | S50: 1 | T50: 12 | U50: =Q50*$E$5 -> 2193.4848 | V50: =S50*T50*U50 -> 26321.818 | W50: 0 | X50: 0 | Y50: 0 | Z50: 0 | AA50: =J50+N50+R50+V50+Z50 -> 81817.258
A51: PSYCHOCONS | B51: 81000 | C51: PRY | D51: Psychological Counselors for TIP Shelter | E51: 1 | F51: Month | G51: 3 | H51: 1 | I51: 925 | J51: =E51*G51*H51*I51 -> 2775 | K51: 1 | L51: 12 | M51: =I51*$E$5 -> 962 | N51: =K51*L51*M51 -> 11544 | O51: 1 | P51: 12 | Q51: =M51*$E$5 -> 1000.48 | R51: =O51*P51*Q51 -> 12005.76 | S51: 1 | T51: 12 | U51: =Q51*$E$5 -> 1040.4992 | V51: =S51*T51*U51 -> 12485.99 | W51: 0 | X51: 0 | Y51: 0 | Z51: 0 | AA51: =J51+N51+R51+V51+Z51 -> 38810.75
A52: SOCIALWORK | B52: 81000 | C52: PRY | D52: Social Workers for TIP Shelter | E52: 1 | F52: Month | G52: 3 | H52: 1 | I52: 1500 | J52: =E52*G52*H52*I52 -> 4500 | K52: 1 | L52: 12 | M52: =I52*$E$5 -> 1560 | N52: =K52*L52*M52 -> 18720 | O52: 1 | P52: 12 | Q52: =M52*$E$5 -> 1622.4 | R52: =O52*P52*Q52 -> 19468.8 | S52: 1 | T52: 12 | U52: =Q52*$E$5 -> 1687.296 | V52: =S52*T52*U52 -> 20247.552 | W52: 0 | X52: 0 | Y52: 0 | Z52: 0 | AA52: =J52+N52+R52+V52+Z52 -> 62936.352
A53: OCCPEDSUP | B53: 81000 | C53: PRY | D53: Occupational/Education Support for TIP Shelter | E53: 1 | F53: Month | G53: 3 | H53: 1 | I53: 925 | J53: =E53*G53*H53*I53 -> 2775 | K53: 1 | L53: 12 | M53: =I53*$E$5 -> 962 | N53: =K53*L53*M53 -> 11544 | O53: 1 | P53: 12 | Q53: =M53*$E$5 -> 1000.48 | R53: =O53*P53*Q53 -> 12005.76 | S53: 1 | T53: 12 | U53: =Q53*$E$5 -> 1040.4992 | V53: =S53*T53*U53 -> 12485.99 | W53: 0 | X53: 0 | Y53: 0 | Z53: 0 | AA53: =J53+N53+R53+V53+Z53 -> 38810.75
A54: LEGALCONS | B54: 81000 (Consultant)/ 81010 (Professional Fees) | C54: PRY | D54: Legal Counsel for TIP Shelter | E54: 1 | F54: Month | G54: 3 | H54: 1 | I54: 685 | J54: =E54*G54*H54*I54 -> 2055 | K54: 1 | L54: 12 | M54: =I54*$E$5 -> 712.4 | N54: =K54*L54*M54 -> 8548.8 | O54: 1 | P54: 12 | Q54: =M54*$E$5 -> 740.896 | R54: =O54*P54*Q54 -> 8890.752 | S54: 1 | T54: 12 | U54: =Q54*$E$5 -> 770.53184 | V54: =S54*T54*U54 -> 9246.3821 | W54: 0 | X54: 0 | Y54: 0 | Z54: 0 | AA54: =J54+N54+R54+V54+Z54 -> 28740.934
A55: MEDCONS | B55: 81000 (Consultant)/ 81010 (Professional Fees) | C55: PRY | D55: Medical Counsel for TIP Shelter | E55: 1 | F55: Month | G55: 3 | H55: 1 | I55: 685 | J55: =E55*G55*H55*I55 -> 2055 | K55: 1 | L55: 12 | M55: =I55*$E$5 -> 712.4 | N55: =K55*L55*M55 -> 8548.8 | O55: 1 | P55: 12 | Q55: =M55*$E$5 -> 740.896 | R55: =O55*P55*Q55 -> 8890.752 | S55: 1 | T55: 12 | U55: =Q55*$E$5 -> 770.53184 | V55: =S55*T55*U55 -> 9246.3821 | W55: 0 | X55: 0 | Y55: 0 | Z55: 0 | AA55: =J55+N55+R55+V55+Z55 -> 28740.934
D56: Activity 1.4: Develop an Adult Male Trafficking Victim Care Manual | J56: =E56*G56*H56*I56 -> 0
A57: TIPMANLCON | B57: 81000 | C57: PRY | D57: Consultant to develop Adult Male Trafficking Victim Care Manual | E57: 1 | F57: Day | G57: 25 | H57: 1 | I57: 360 | J57: =E57*G57*H57*I57 -> 9000 | K57: 0 | L57: 0 | M57: 0 | N57: 0 | O57: 0 | P57: 0 | Q57: 0 | R57: =O57*P57*Q57 -> 0 | S57: 0 | T57: 0 | U57: 0 | V57: 0 | W57: 0 | X57: 0 | Y57: 0 | Z57: 0 | AA57: =J57+N57+R57+V57+Z57 -> 9000
D58: Activity 1.5: Train Stakeholders on the Adult Male Trafficking Victim Care Manual
A59: TIPTRAINCO | B59: 81000 | C59: PRY | D59: Consultant to deliver trainings on Adult Male Trafficking Victim Care Manual | E59: 1 | F59: Day | G59: 12 | H59: 1 | I59: 360 | J59: =E59*G59*H59*I59 -> 4320 | K59: 0 | L59: 0 | M59: 0 | N59: 0 | O59: 0 | P59: 0 | Q59: 0 | R59: =O59*P59*Q59 -> 0 | S59: 0 | T59: 0 | U59: 0 | V59: 0 | W59: 0 | X59: 0 | Y59: 0 | Z59: 0 | AA59: =J59+N59+R59+V59+Z59 -> 4320
D60: Activity 2.2: Train Relevant Institution Staff on Existing SOPs for Victim Care
A61: SOPCONS | B61: 81000 | C61: PRY | D61: Consultant to deliver trainings on Existing SOPs | E61: 1 | F61: Day | G61: 10 | H61: 1 | I61: 360 | J61: =E61*G61*H61*I61 -> 3600 | K61: 1 | L61: 20 | M61: =I61*$E$5 -> 374.4 | N61: =H61*K61*L61*M61 -> 7488 | O61: 1 | P61: 20 | Q61: =M61*$E$5 -> 389.376 | R61: =E61*O61*P61*Q61 -> 7787.52 | S61: 1 | T61: 20 | U61: =Q61*$E$5 -> 404.95104 | V61: =E61*S61*T61*U61 -> 8099.0208 | W61: 2 | X61: 10 | Y61: =U61*$E$5 -> 421.14908 | Z61: =H61*W61*X61*Y61 -> 8422.9816 | AA61: =J61+N61+R61+V61+Z61 -> 35397.522
D62: M&E
A63: MIDTERM | B63: 81010 | C63: PRY | D63: M&E. Midterm Evaluation | E63: 1 | F63: Lumpsum | G63: 0 | H63: 1 | I63: 25000 | J63: =E63*G63*H63*I63 -> 0 | K63: 0 | L63: 0 | M63: =I63*$E$5 -> 26000 | N63: 0 | O63: 1 | P63: 1 | Q63: =M63*$E$5 -> 27040 | R63: =O63*P63*Q63 -> 27040 | S63: 0 | T63: 0 | U63: =Q63*$E$5 -> 28121.6 | V63: 0 | W63: 1 | X63: 0 | Y63: 0 | Z63: =H63*W63*X63*Y63 -> 0 | AA63: =J63+N63+R63+V63+Z63 -> 27040
A64: ENDLINE | B64: 81010 | C64: PRY | D64: M&E. Final Evaluation | E64: 1 | F64: Lumpsum | G64: 0 | H64: 1 | I64: 25000 | J64: =E64*G64*H64*I64 -> 0 | K64: 0 | L64: 0 | M64: =I64*$E$5 -> 26000 | N64: 0 | O64: 0 | P64: 0 | Q64: =M64*$E$5 -> 27040 | R64: =O64*P64*Q64 -> 0 | S64: 0 | T64: 0 | U64: =Q64*$E$5 -> 28121.6 | V64: 0 | W64: 1 | X64: 1 | Y64: =U64*$E$5 -> 29246.464 | Z64: =H64*W64*X64*Y64 -> 29246.464 | AA64: =J64+N64+R64+V64+Z64 -> 29246.464
D65: Subtotal Contractual | J65: =SUM(J50:J64) -> 36930 | N65: =SUM(N50:N64) -> 90729.6 | R65: =SUM(R50:R64) -> 121398.78 | V65: =SUM(V50:V64) -> 98133.135 | Z65: =SUM(Z50:Z64) -> 37669.446 | AA65: =SUM(AA50:AA64) -> 384860.96
D66: Other Direct Costs
A67: BANK FEES | B67: 90900 (Bank Fees)/ 82105 (Accounting) | C67: PRY | D67: Banking and Cash Handling & Fiscal Reviews | E67: 1 | F67: Month | G67: 9 | H67: 1 | I67: 75 | J67: =E67*I67*G67*H67 -> 675 | K67: 1 | L67: 12 | M67: =I67*$E$5 -> 78 | N67: =K67*M67*L67*H67 -> 936 | O67: 1 | P67: 12 | Q67: =M67*$E$5 -> 81.12 | R67: =O67*Q67*P67 -> 973.44 | S67: 1 | T67: 12 | U67: =Q67*$E$5 -> 84.3648 | V67: =S67*U67*T67 -> 1012.3776 | W67: 1 | X67: 12 | Y67: =U67*$E$5 -> 87.739392 | Z67: =W67*Y67*X67 -> 1052.8727 | AA67: =J67+N67+R67+V67+Z67 -> 4649.6903
A68: COURIER | B68: 82350 | C68: PRY | D68: Courier fees/services | E68: 1 | F68: Month | G68: 9 | H68: 1 | I68: 35 | J68: =E68*I68*G68*H68 -> 315 | K68: 1 | L68: 12 | M68: =I68*$E$5 -> 36.4 | N68: =K68*M68*L68*H68 -> 436.8 | O68: 1 | P68: 12 | Q68: =M68*$E$5 -> 37.856 | R68: =O68*Q68*P68 -> 454.272 | S68: 1 | T68: 12 | U68: =Q68*$E$5 -> 39.37024 | V68: =S68*U68*T68 -> 472.44288 | W68: 1 | X68: 12 | Y68: =U68*$E$5 -> 40.94505 | Z68: =W68*Y68*X68 -> 491.3406 | AA68: =J68+N68+R68+V68+Z68 -> 2169.8555
A69: COMM | B69: 82030 | C69: USA/PRY | D69: Communication Costs (Telephone (cellular and land line), email, data) | E69: 1 | F69: Month | G69: 9 | H69: 1 | I69: 120 | J69: =E69*I69*G69*H69 -> 1080 | K69: 1 | L69: 12 | M69: =I69*$E$5 -> 124.8 | N69: =K69*M69*L69*H69 -> 1497.6 | O69: 1 | P69: 12 | Q69: =M69*$E$5 -> 129.792 | R69: =O69*Q69*P69 -> 1557.504 | S69: 1 | T69: 12 | U69: =Q69*$E$5 -> 134.98368 | V69: =S69*U69*T69 -> 1619.8042 | W69: 1 | X69: 12 | Y69: =U69*$E$5 -> 140.38303 | Z69: =W69*Y69*X69 -> 1684.5963 | AA69: =J69+N69+R69+V69+Z69 -> 7439.5045
A70: LEGAL | B70: 90100 | C70: PRY | D70: Legal Fees | E70: 1 | F70: Year | G70: 1 | H70: 1 | I70: 550 | J70: =E70*I70*G70*H70 -> 550 | K70: 1 | L70: 1 | M70: =I70*$E$5 -> 572 | N70: =K70*M70*L70*H70 -> 572 | O70: 1 | P70: 1 | Q70: =M70*$E$5 -> 594.88 | R70: =O70*Q70*P70*L70 -> 594.88 | S70: 1 | T70: 1 | U70: =Q70*$E$5 -> 618.6752 | V70: =S70*U70*T70*P70 -> 618.6752 | W70: 1 | X70: 1 | Y70: =U70*$E$5 -> 643.42221 | Z70: =W70*Y70*X70*T70 -> 643.42221 | AA70: =J70+N70+R70+V70+Z70 -> 2978.9774
A71: RENT & UT | B71: 85180 | C71: PRY | D71: Office Space | E71: 1 | F71: Month | G71: 9 | H71: 1 | I71: 1250 | J71: =E71*I71*G71*H71 -> 11250 | K71: 1 | L71: 12 | M71: =I71*$E$5 -> 1300 | N71: =K71*M71*L71*H71 -> 15600 | O71: 1 | P71: 12 | Q71: =M71*$E$5 -> 1352 | R71: =O71*Q71*P71 -> 16224 | S71: 1 | T71: 12 | U71: =Q71*$E$5 -> 1406.08 | V71: =S71*U71*T71 -> 16872.96 | W71: 1 | X71: 12 | Y71: =U71*$E$5 -> 1462.3232 | Z71: =W71*Y71*X71 -> 17547.878 | AA71: =J71+N71+R71+V71+Z71 -> 77494.838
A72: SUBSCRIPT | B72: 89400 | C72: USA/PRY | D72: Subscriptions, Timekeeping and Expense Reporting Platform | E72: 1 | F72: Month | G72: 9 | H72: 1 | I72: =(20*3)+(520/12) -> 103.33333 | J72: =E72*I72*G72*H72 -> 930 | K72: 1 | L72: 12 | M72: =I72*$E$5 -> 107.46667 | N72: =K72*M72*L72*H72 -> 1289.6 | O72: 1 | P72: 12 | Q72: =M72*$E$5 -> 111.76533 | R72: =O72*Q72*P72 -> 1341.184 | S72: 1 | T72: 12 | U72: =Q72*$E$5 -> 116.23595 | V72: =S72*U72*T72 -> 1394.8314 | W72: 1 | X72: 12 | Y72: =U72*$E$5 -> 120.88538 | Z72: =W72*Y72*X72 -> 1450.6246 | AA72: =J72+N72+R72+V72+Z72 -> 6406.24
D73: Objectives and Activities
D74: O1: Increase comprehensive services for adult trafficking victims, particularly men, through the provision of shelter, trauma-informed mental health counseling, and medical and legal assistance.
D75: Activity 1.1: Identify Relevant Institution to Provide Care for Adult Male Victims of Trafficking
A76: PTIP.1.1.A | B76: 87010 | C76: PRY | D76: Meetings with the Board to assess feasibility and requirements for TIP Shelter | E76: 1 | F76: Meetings | G76: 4 | H76: 1 | I76: 135 | J76: =E76*I76*G76*H76 -> 540 | K76: 1 | L76: 2 | M76: =I76*$E$5 -> 140.4 | N76: =K76*M76*L76*H76 -> 280.8 | O76: 1 | P76: 2 | Q76: =M76*$E$5 -> 146.016 | R76: =O76*Q76*P76 -> 292.032 | S76: 1 | T76: 2 | U76: =Q76*$E$5 -> 151.85664 | V76: =S76*U76*T76 -> 303.71328 | W76: 1 | X76: 2 | Y76: =U76*$E$5 -> 157.93091 | Z76: =W76*Y76*X76 -> 315.86181 | AA76: =J76+N76+R76+V76+Z76 -> 1732.4071
D77: Activity 1.2: Sign Agreements with Governmental Institutions to Create Shelter
A78: PTIP.1.2.A | B78: 87000 | C78: PRY | D78: Venue and A/V for Signing Event | E78: 1 | F78: Event | G78: 1 | H78: 1 | I78: 900 | J78: =E78*I78*G78*H78 -> 900 | K78: 0 | L78: 0 | M78: =I78*$E$5 -> 936 | N78: =K78*M78*L78*H78 -> 0 | O78: 0 | P78: 0 | Q78: =M78*$E$5 -> 973.44 | R78: =O78*Q78*P78*L78 -> 0 | S78: 1 | T78: 1 | U78: =Q78*$E$5 -> 1012.3776 | V78: =S78*T78*U78 -> 1012.3776 | W78: 0 | X78: 0 | Y78: 0 | Z78: 0 | AA78: =J78+N78+R78+V78+Z78 -> 1912.3776
A79: PTIP.1.2.B | B79: 87000 | C79: PRY | D79: Refreshments/Coffee Break for Signing Event | E79: 1 | F79: Person | G79: 30 | H79: 1 | I79: 17 | J79: =E79*I79*G79*H79 -> 510 | K79: 0 | L79: 0 | M79: =I79*$E$5 -> 17.68 | N79: =K79*M79*L79*H79 -> 0 | O79: 0 | P79: 0 | Q79: =M79*$E$5 -> 18.3872 | R79: =O79*Q79*P79*L79 -> 0 | S79: 1 | T79: 30 | U79: =Q79*$E$5 -> 19.122688 | V79: =S79*T79*U79 -> 573.68064 | W79: 0 | X79: 0 | Y79: 0 | Z79: 0 | AA79: =J79+N79+R79+V79+Z79 -> 1083.6806
A80: PTIP.1.2.C | B80: 82420 (Programs Supplies)/ 85300 (Printing) | C80: PRY | D80: Materials and Printing for Signing Event | E80: 1 | F80: Lumpsum | G80: 1 | H80: 1 | I80: 200 | J80: =E80*I80*G80*H80 -> 200 | K80: 0 | L80: 0 | M80: =I80*$E$5 -> 208 | N80: =K80*M80*L80*H80 -> 0 | O80: 0 | P80: 0 | Q80: =M80*$E$5 -> 216.32 | R80: =O80*Q80*P80*L80 -> 0 | S80: 1 | T80: 1 | U80: =Q80*$E$5 -> 224.9728 | V80: =S80*T80*U80 -> 224.9728 | W80: 0 | X80: 0 | Y80: 0 | Z80: 0 | AA80: =J80+N80+R80+V80+Z80 -> 424.9728
D81: Activity 1.3: Establish Adult Male Victims of Trafficking Shelter
A82: PTIP.1.3.A | B82: 85180 | C82: PRY | D82: Rent and Utilities for TIP Shelter | E82: 1 | F82: Month | G82: 3 | H82: 1 | I82: 2150 | J82: =E82*I82*G82*H82 -> 6450 | K82: 1 | L82: 12 | M82: =I82*$E$5 -> 2236 | N82: =K82*M82*L82*H82 -> 26832 | O82: 1 | P82: 12 | Q82: =M82*$E$5 -> 2325.44 | R82: =O82*Q82*P82 -> 27905.28 | S82: 1 | T82: 12 | U82: =Q82*$E$5 -> 2418.4576 | V82: =S82*U82*T82 -> 29021.491 | W82: 0 | X82: 0 | Y82: 0 | Z82: 0 | AA82: =J82+N82+R82+V82+Z82 -> 90208.771
A83: PTIP.1.3.B | B83: 82420 | C83: PRY | D83: Furniture and Furnishings for TIP Shelter | E83: 1 | F83: Room | G83: 10 | H83: 1 | I83: 875 | J83: =E83*I83*G83*H83 -> 8750 | K83: 0 | L83: 0 | M83: =I83*$E$5 -> 910 | N83: =K83*M83*L83*H83 -> 0 | O83: 0 | P83: 0 | Q83: =M83*$E$5 -> 946.4 | R83: =O83*Q83*P83*L83 -> 0 | S83: 0 | T83: 0 | U83: =Q83*$E$5 -> 984.256 | V83: =S83*U83*T83*P83 -> 0 | W83: 0 | X83: 0 | Y83: 0 | Z83: 0 | AA83: =J83+N83+R83+V83+Z83 -> 8750
A84: PTIP.1.3.C | B84: 82420 | C84: PRY | D84: Personal Hygiene Products for TIP Shelter | E84: 1 | F84: Person | G84: 30 | H84: 1 | I84: 125 | J84: =E84*I84*G84*H84 -> 3750 | K84: 1 | L84: 30 | M84: =I84*$E$5 -> 130 | N84: =K84*M84*L84*H84 -> 3900 | O84: 1 | P84: 30 | Q84: =M84*$E$5 -> 135.2 | R84: =O84*Q84*P84 -> 4056 | S84: 1 | T84: 30 | U84: =Q84*$E$5 -> 140.608 | V84: =S84*U84*T84 -> 4218.24 | W84: 0 | X84: 0 | Y84: 0 | Z84: 0 | AA84: =J84+N84+R84+V84+Z84 -> 15924.24
A85: PTIP.1.3.D | B85: 82420 | C85: PRY | D85: Food and Groceries for TIP Victims | E85: 10 | F85: Month | G85: 3 | H85: 1 | I85: 165 | J85: =E85*I85*G85*H85 -> 4950 | K85: 10 | L85: 12 | M85: =I85*$E$5 -> 171.6 | N85: =K85*M85*L85*H85 -> 20592 | O85: 10 | P85: 12 | Q85: =M85*$E$5 -> 178.464 | R85: =O85*Q85*P85 -> 21415.68 | S85: 10 | T85: 12 | U85: =Q85*$E$5 -> 185.60256 | V85: =S85*U85*T85 -> 22272.307 | W85: 0 | X85: 0 | Y85: 0 | Z85: 0 | AA85: =J85+N85+R85+V85+Z85 -> 69229.987
A86: PTIP.1.3.E | B86: 82420 | C86: PRY | D86: Essential Needs (Clothing) and Medications for TIP Shelter | E86: 1 | F86: Person | G86: 30 | H86: 1 | I86: 85 | J86: =E86*I86*G86*H86 -> 2550 | K86: 1 | L86: 30 | M86: =I86*$E$5 -> 88.4 | N86: =K86*M86*L86*H86 -> 2652 | O86: 1 | P86: 30 | Q86: =M86*$E$5 -> 91.936 | R86: =O86*Q86*P86 -> 2758.08 | S86: 1 | T86: 30 | U86: =Q86*$E$5 -> 95.61344 | V86: =S86*U86*T86 -> 2868.4032 | W86: 0 | X86: 0 | Y86: 0 | Z86: 0 | AA86: =J86+N86+R86+V86+Z86 -> 10828.483
A87: PTIP.1.3.F | B87: 82401 | C87: PRY | D87: Operational Supplies for TIP Shelter | E87: 1 | F87: Month | G87: 3 | H87: 1 | I87: 175 | J87: =E87*I87*G87*H87 -> 525 | K87: 1 | L87: 12 | M87: =I87*$E$5 -> 182 | N87: =K87*M87*L87*H87 -> 2184 | O87: 1 | P87: 12 | Q87: =M87*$E$5 -> 189.28 | R87: =O87*Q87*P87 -> 2271.36 | S87: 1 | T87: 12 | U87: =Q87*$E$5 -> 196.8512 | V87: =S87*U87*T87 -> 2362.2144 | W87: 0 | X87: 0 | Y87: 0 | Z87: 0 | AA87: =J87+N87+R87+V87+Z87 -> 7342.5744
A88: PTIP.1.3.G | B88: 86110 | C88: PRY | D88: Security Contractor and Security Systems for TIP Shelter | E88: 1 | F88: Month | G88: 3 | H88: 1 | I88: 1500 | J88: =E88*I88*G88*H88 -> 4500 | K88: 1 | L88: 12 | M88: =I88*$E$5 -> 1560 | N88: =K88*M88*L88*H88 -> 18720 | O88: 1 | P88: 12 | Q88: =M88*$E$5 -> 1622.4 | R88: =O88*Q88*P88 -> 19468.8 | S88: 1 | T88: 12 | U88: =Q88*$E$5 -> 1687.296 | V88: =S88*U88*T88 -> 20247.552 | W88: 0 | X88: 0 | Y88: 0 | Z88: 0 | AA88: =J88+N88+R88+V88+Z88 -> 62936.352
A89: PTIP.1.3.H | B89: 85180 | C89: PRY | D89: Cleaning & Maintenance for TIP Shelter | E89: 1 | F89: Month | G89: 3 | H89: 1 | I89: 750 | J89: =E89*I89*G89*H89 -> 2250 | K89: 1 | L89: 12 | M89: =I89*$E$5 -> 780 | N89: =K89*M89*L89*H89 -> 9360 | O89: 1 | P89: 12 | Q89: =M89*$E$5 -> 811.2 | R89: =O89*Q89*P89 -> 9734.4 | S89: 1 | T89: 12 | U89: =Q89*$E$5 -> 843.648 | V89: =S89*U89*T89 -> 10123.776 | W89: 0 | X89: 0 | Y89: 0 | Z89: 0 | AA89: =J89+N89+R89+V89+Z89 -> 31468.176
A90: PTIP.1.3.I | B90: 82420 | C90: PRY | D90: Health, Wellness, & Rehabilitation (Vaccinations, Medications, Health Assessment, etc.) for TIP Shelter | E90: 1 | F90: Month | G90: 3 | H90: 1 | I90: 750 | J90: =E90*I90*G90*H90 -> 2250 | K90: 1 | L90: 12 | M90: =I90*$E$5 -> 780 | N90: =K90*M90*L90*H90 -> 9360 | O90: 1 | P90: 12 | Q90: =M90*$E$5 -> 811.2 | R90: =O90*Q90*P90 -> 9734.4 | S90: 1 | T90: 12 | U90: =Q90*$E$5 -> 843.648 | V90: =S90*U90*T90 -> 10123.776 | W90: 0 | X90: 0 | Y90: 0 | Z90: 0 | AA90: =J90+N90+R90+V90+Z90 -> 31468.176
A91: PTIP.1.3.J | B91: 81000 (Consultant)/ 81010 (Professional Fees) | C91: PRY | D91: Catering/Chef Services for TIP Shelter (excludes food) | E91: 1 | F91: Month | G91: 3 | H91: 1 | I91: 700 | J91: =E91*I91*G91*H91 -> 2100 | K91: 1 | L91: 12 | M91: =I91*$E$5 -> 728 | N91: =K91*M91*L91*H91 -> 8736 | O91: 1 | P91: 12 | Q91: =M91*$E$5 -> 757.12 | R91: =O91*Q91*P91 -> 9085.44 | S91: 1 | T91: 12 | U91: =Q91*$E$5 -> 787.4048 | V91: =S91*U91*T91 -> 9448.8576 | W91: 0 | X91: 0 | Y91: 0 | Z91: 0 | AA91: =J91+N91+R91+V91+Z91 -> 29370.298
A92: PTIP.1.3.K | B92: 86000 | C92: PRY | D92: Transport (fuel and transport of victims) | E92: 1 | F92: Month | G92: 3 | H92: 1 | I92: 350 | J92: =E92*I92*G92*H92 -> 1050 | K92: 1 | L92: 12 | M92: =I92*$E$5 -> 364 | N92: =K92*M92*L92*H92 -> 4368 | O92: 1 | P92: 12 | Q92: =M92*$E$5 -> 378.56 | R92: =O92*Q92*P92 -> 4542.72 | S92: 1 | T92: 12 | U92: =Q92*$E$5 -> 393.7024 | V92: =S92*U92*T92 -> 4724.4288 | W92: 0 | X92: 0 | Y92: 0 | Z92: 0 | AA92: =J92+N92+R92+V92+Z92 -> 14685.149
D93: Activity 1.4: Develop an Adult Male Trafficking Victim Care Manual | M93: =I93*$E$5 -> 0 | Q93: =M93*$E$5 -> 0 | S93: 0 | T93: 0 | U93: 0 | V93: 0 | W93: 0 | X93: 0 | Y93: 0 | Z93: 0
A94: PTIP.1.4.A | B94: 82420 (Programs Supplies)/ 85300 (Printing) | C94: PRY | D94: Develop Comprehensive Adult Male Trafficking Victim Care Manual | E94: 1 | F94: Unit | G94: 1 | H94: 1 | I94: 5000 | J94: =E94*I94*G94*H94 -> 5000 | K94: 0 | L94: 0 | M94: 0 | N94: =K94*M94*L94*H94 -> 0 | O94: 0 | P94: 0 | Q94: =M94*$E$5 -> 0 | R94: =O94*Q94*P94*L94 -> 0 | S94: 0 | T94: 0 | U94: 0 | V94: 0 | W94: 0 | X94: 0 | Y94: 0 | Z94: 0 | AA94: =J94+N94+R94+V94+Z94 -> 5000
A95: PTIP.1.4.B | B95: 81015 | C95: PRY | D95: Survivor Inclusion Compensation | E95: 1 | F95: Person | G95: 5 | H95: 1 | I95: 1000 | J95: =E95*I95*G95*H95 -> 5000 | K95: 0 | L95: 0 | M95: 0 | N95: =K95*M95*L95*H95 -> 0 | O95: 0 | P95: 0 | Q95: =M95*$E$5 -> 0 | R95: =O95*Q95*P95*L95 -> 0 | S95: 0 | T95: 0 | U95: 0 | V95: 0 | W95: 0 | X95: 0 | Y95: 0 | Z95: 0 | AA95: =J95+N95+R95+V95+Z95 -> 5000
A96: PTIP.1.4.C | B96: 85300 | C96: PRY | D96: Printing of Manual | E96: 1 | F96: Manual | G96: 250 | H96: 1 | I96: 25 | J96: =E96*I96*G96*H96 -> 6250 | K96: 1 | L96: 200 | M96: =I96*$E$5 -> 26 | N96: =K96*H96*L96*M96 -> 5200 | O96: 0 | P96: 0 | Q96: 0 | R96: 0 | S96: 0 | T96: 0 | U96: 0 | V96: 0 | W96: 0 | X96: 0 | Y96: 0 | Z96: 0 | AA96: =J96+N96+R96+V96+Z96 -> 11450
D97: Activity 1.5: Train Stakeholders on the Adult Male Trafficking Victim Care Manual | M97: =I97*$E$5 -> 0 | Q97: =M97*$E$5 -> 0 | S97: 0 | T97: 0 | U97: 0 | V97: 0 | W97: 0 | X97: 0 | Y97: 0 | Z97: 0
A98: PTIP.1.5.A | B98: 87000 | C98: PRY | D98: Venue and A/V for Training on Victim Care Manual | E98: 1 | F98: Event | G98: 1 | H98: 1 | I98: 900 | J98: =E98*I98*G98*H98 -> 900 | K98: 1 | L98: 1 | M98: =I98*$E$5 -> 936 | N98: =K98*M98*L98*H98 -> 936 | O98: 1 | P98: 1 | Q98: =M98*$E$5 -> 973.44 | R98: =O98*Q98*P98 -> 973.44 | S98: 1 | T98: 1 | U98: =Q98*$E$5 -> 1012.3776 | V98: =S98*U98*T98 -> 1012.3776 | W98: 1 | X98: 1 | Y98: =U98*$E$5 -> 1052.8727 | Z98: =W98*Y98*X98 -> 1052.8727 | AA98: =J98+N98+R98+V98+Z98 -> 4874.6903
A99: PTIP.1.5.B | B99: 87000 | C99: PRY | D99: Refreshments/Coffee Break for Training on Victim Care Manual | E99: 1 | F99: Person | G99: 50 | H99: 1 | I99: 17 | J99: =E99*I99*G99*H99 -> 850 | K99: 1 | L99: 50 | M99: =I99*$E$5 -> 17.68 | N99: =K99*M99*L99*H99 -> 884 | O99: 1 | P99: 50 | Q99: =M99*$E$5 -> 18.3872 | R99: =O99*Q99*P99 -> 919.36 | S99: 1 | T99: 50 | U99: =Q99*$E$5 -> 19.122688 | V99: =S99*U99*T99 -> 956.1344 | W99: 1 | X99: 50 | Y99: =U99*$E$5 -> 19.887596 | Z99: =W99*Y99*X99 -> 994.37978 | AA99: =J99+N99+R99+V99+Z99 -> 4603.8742
A100: PTIP.1.5.C | B100: 82420 (Programs Supplies)/ 85300 (Printing) | C100: PRY | D100: Materials and Printing for Training on Victim Care Manual | E100: 1 | F100: Lumpsum | G100: 1 | H100: 1 | I100: 600 | J100: =E100*I100*G100*H100 -> 600 | K100: 1 | L100: 1 | M100: =I100*$E$5 -> 624 | N100: =K100*M100*L100*H100 -> 624 | O100: 1 | P100: 1 | Q100: =M100*$E$5 -> 648.96 | R100: =O100*Q100*P100 -> 648.96 | S100: 1 | T100: 1 | U100: =Q100*$E$5 -> 674.9184 | V100: =S100*U100*T100 -> 674.9184 | W100: 1 | X100: 1 | Y100: =U100*$E$5 -> 701.91514 | Z100: =W100*Y100*X100 -> 701.91514 | AA100: =J100+N100+R100+V100+Z100 -> 3249.7935
D102: O2: Enhance and implement the use of existing protection SOPs to provide trauma-informed and victim-centered care to adult victims of trafficking.
...

Sheet M&E Budget
A1: M&E Budget
A2: Personnel Costs - M&E Coordinator (100% LOE) | B2: ='POA Line Item Budget'!AA13 -> 116891.1
A3: Fringe Benefits - M&E Coordinator (100% LOE) | B3: ='POA Line Item Budget'!AA20 -> 41227.491
A4: ='POA Line Item Budget'!D124 -> Customize M&E Database for Project | B4: ='POA Line Item Budget'!AA124 -> 4468.32
A5: ='POA Line Item Budget'!D125 -> M&E Materials | B5: ='POA Line Item Budget'!AA125 -> 4603.8742
A6: ='POA Line Item Budget'!D126 -> M&E Training and Coordination Meetings | B6: ='POA Line Item Budget'!AA126 -> 2708.1613
A7: Mid-term Evaluation | B7: ='POA Line Item Budget'!AA63 -> 27040
A8: Final Evaluation | B8: ='POA Line Item Budget'!AA64 -> 29246.464
A9: Total M&E Budget | B9: =SUM(B2:B8) -> 226185.41
A10: Percentage of M&E Budget | B10: =B9/2500000 -> 0.090474164

Sheet Summary by Year
A1: PARTNERS OF THE AMERICAS
A2: Project Name: 2024 TIP Office International Programs to Combat Human Trafficking
A3: Funding Opportunity: DFOP0016706 and Assistance Number: 19.019
A4: SUMMARY BUDGET
B5: Year 1 | C5: Year 2 | D5: Year 3 | E5: Year 4 | F5: Year 5 | G5: Total
A6: BUDGET SUMMARY CATEGORIES | B6: JTIP | C6: JTIP | D6: JTIP | E6: JTIP | F6: JTIP | G6: Cost Share | H6: Total Federal Funds Requested
A7: 1. Personnel | B7: ='POA Line Item Budget'!J16 -> 127621.2 | C7: ='POA Line Item Budget'!N16 -> 151327.26 | D7: ='POA Line Item Budget'!R16 -> 158893.62 | E7: ='POA Line Item Budget'!V16 -> 166838.3 | F7: ='POA Line Item Budget'!Z16 -> 142604.65 | G7: 0 | H7: =B7+C7+D7+E7+F7 -> 747285.04
A8: 2. Fringe Benefits | B8: ='POA Line Item Budget'!J23 -> 42647.136 | C8: ='POA Line Item Budget'!N23 -> 50890.02 | D8: ='POA Line Item Budget'!R23 -> 53434.521 | E8: ='POA Line Item Budget'!V23 -> 56106.247 | F8: ='POA Line Item Budget'!Z23 -> 47422.157 | G8: 0 | H8: =B8+C8+D8+E8+F8 -> 250500.08
A9: 3. Travel | B9: ='POA Line Item Budget'!J43 -> 11343 | C9: ='POA Line Item Budget'!N43 -> 23736.96 | D9: ='POA Line Item Budget'!R43 -> 24686.438 | E9: ='POA Line Item Budget'!V43 -> 21489.402 | F9: ='POA Line Item Budget'!Z43 -> 12381.783 | G9: 0 | H9: =B9+C9+D9+E9+F9 -> 93637.583
A10: 4. Equipment | H10: =B10+C10+D10+E10+F10 -> 0
A11: 5. Supplies | B11: ='POA Line Item Budget'!J47 -> 6900 | C11: ='POA Line Item Budget'!N47 -> 1123.2 | D11: ='POA Line Item Budget'!R47 -> 1168.128 | E11: ='POA Line Item Budget'!V47 -> 1214.8531 | F11: ='POA Line Item Budget'!Z47 -> 1263.4472 | G11: 0 | H11: =B11+C11+D11+E11+F11 -> 11669.628
A12: 6. Contractual | B12: ='POA Line Item Budget'!J65 -> 36930 | C12: ='POA Line Item Budget'!N65 -> 90729.6 | D12: ='POA Line Item Budget'!R65 -> 121398.78 | E12: ='POA Line Item Budget'!V65 -> 98133.135 | F12: ='POA Line Item Budget'!Z65 -> 37669.446 | G12: 0 | H12: =B12+C12+D12+E12+F12 -> 384860.96
A13: 7. Construction | H13: =B13+C13+D13+E13+F13 -> 0
A14: 8. Other Direct Costs | B14: ='POA Line Item Budget'!J127 -> 107833.32 | C14: ='POA Line Item Budget'!N127 -> 150347.6 | D14: ='POA Line Item Budget'!R127 -> 145891.62 | E14: ='POA Line Item Budget'!V127 -> 153538.31 | F14: ='POA Line Item Budget'!Z127 -> 37768.884 | G14: 0 | H14: =B14+C14+D14+E14+F14 -> 595379.73
A15: 9. Total Direct Costs | B15: =SUM(B7:B14) -> 333274.66 | C15: =SUM(C7:C14) -> 468154.64 | D15: =SUM(D7:D14) -> 505473.11 | E15: =SUM(E7:E14) -> 497320.25 | F15: =SUM(F7:F14) -> 279110.37 | G15: =SUM(G7:G14) -> 0 | H15: =B15+C15+D15+E15+F15 -> 2083333
A16: 10. Indirect Costs | B16: ='POA Line Item Budget'!J129 -> 66654.931 | C16: ='POA Line Item Budget'!N129 -> 93630.928 | D16: ='POA Line Item Budget'!R129 -> 101094.62 | E16: ='POA Line Item Budget'!V129 -> 99464.051 | F16: ='POA Line Item Budget'!Z129 -> 55822.074 | G16: 0 | H16: =B16+C16+D16+E16+F16 -> 416666.61
A17: 11. Total Costs | B17: =B15+B16 -> 399929.59 | C17: =C15+C16 -> 561785.57 | D17: =D15+D16 -> 606567.73 | E17: =E15+E16 -> 596784.3 | F17: =F15+F16 -> 334932.44 | G17: =G15+G16 -> 0 | H17: =H15+H16 -> 2499999.6
