Workbook

Sheet 1. Summary Budget
A1: SUMMARY BUDGET
A2: Partners of the Americas
A3: 100,000 Strong in the Americas
A4: 24 Months
D6: Original Budget
A8: A | C8: Personnel | D8: 0
A9: B | C9: Fringe Benefits | D9: 0
A10: C | C10: Travel | D10: ='2. Detailed Budget'!K16 -> 2389
A11: D | C11: Equipment | D11: 0
A12: E | C12: Supplies | D12: 0
A13: F | C13: Contractual | D13: ='2. Detailed Budget'!K22 -> 114000
A14: G | C14: Construction | D14: 0
A15: H | C15: Other Direct Costs | D15: ='2. Detailed Budget'!K26 -> 543
A16: I | C16: Total Direct charges | D16: ='2. Detailed Budget'!K27 -> 116932
A17: J | C17: Total Indirect costs | D17: ='2. Detailed Budget'!K28 -> 33068
A18: K | C18: Total Project Cost | D18: ='2. Detailed Budget'!K29 -> 150000
A19: L | C19: Cost Share (if applicable)
A21: * line item amounts auto-fill from "Detailed Grant Budget Template" tab

Sheet 2. Detailed Budget
D1: LINE-ITEM BUDGET
D3: Partners of the Americas,100,000 Strong in the Americas - EOY 2023 Funds PAS-Brazil | I3: Project Title
D4: Project Duration: 24 months | I4: Project duration
A5: Entity: | B5: P
A6: Program-Dept.: | B6: 40100 | G6: Unit Cost | K6: Original Budget Federal Share
A7: Funder-Grant: | B7: DOS266 | G7: Unit | H7: Number | I7: Amount | J7: Rate
A8: Budget Code | B8: Account Code | C8: Country Code | D8: A | F8: Personnel | G8: months or years | I8: salary (monthly) | J8: % effort for Personnel only
D9: B | F9: Fringe
D10: C | F10: Travel | G10: # people | H10: # units | I10: unit Cost
D11: C.1 | F11: Staff/Consultant Travel
A12: STFTRAVEL | B12: 86040 | C12: USA | D12: C.1.1 | F12: International Round Trip Airfare | G12: trips | H12: 1 | I12: 1400 | K12: =H12*I12 -> 1400
A13: STFCN DIEM | B13: 86050 | C13: USA | D13: C.1.2 | F13: International M&IE | G13: days | H13: =H12*4 -> 4 | I13: 96 | K13: =H13*I13 -> 384
A14: LODGING | B14: 86030 | C14: USA | D14: C.1.3 | F14: International Lodging | G14: nights | H14: =H13-1 -> 3 | I14: 135 | K14: =H14*I14 -> 405
A15: LOCAL TRVL | B15: 86000 | C15: USA | D15: C.1.4 | F15: International Local Transportation | G15: days | H15: =H13 -> 4 | I15: 50 | K15: =H15*I15 -> 200
D16: Subtotal Travel | K16: =SUM(K12:K15) -> 2389
D17: D | F17: Equipment (> $5,000 per unit ) | H17: # units | I17: unit cost
D18: E | F18: Supplies (< $5,000 per unit) | H18: # units | I18: unit cost
D19: F | F19: Contractual (Subrecipients, Subcontracts, and Consultant fees)
D20: F.1 | F20: Sub-grants | I20: daily rate
A21: GRANTS | B21: 89000 | C21: USA | D21: F.1.1 | F21: HEI Sub-grants | G21: grants | H21: 3 | I21: 38000 | K21: =H21*I21 -> 114000
D22: Subtotal Contractual | K22: =SUM(K21:K21) -> 114000
D23: G | F23: Construction
D24: H | F24: Other Direct Costs
A25: TRANS | B25: 81021 | C25: USA | D25: H.1 | F25: Translation Costs | G25: documents | H25: 3 | I25: 181 | K25: =H25*I25 -> 543
D26: Subtotal Other Direct Costs | K26: =SUM(K25:K25) -> 543
D27: I | F27: Total Direct Costs | K27: =K16+K22+K26 -> 116932
A28: IDC | B28: 94050 | C28: USA | D28: J | F28: Indirect Costs | G28: 0.2828 | K28: =ROUND(K27*G28,0) -> 33068
D29: K | F29: Total Project Cost | K29: =SUM(K27:K28) -> 150000
