Workbook

Sheet DOL415
C1: Partners of the Americas - #415 DOL Educafuturo
C2: Monthly Cash Disbursements Journal
E3: Month ending | F3: 41399
E4: Country | F4: Panama
A6: * Choose from drop down list
A7: Date | B7: Ref or | C7: Payee | D7: *Budget Description | E7: *Activity | F7: Amount | G7: *Object | H7: Country | I7: Office | J7: *Subcontract | O7: Session Description
B8: CK# | E8: Code | F8: (USD) | G8: Code | J8: ID
D9: Select from drop down | E9: =VLOOKUP(D9,'PN-Coding'!$A$2:$C$36,2,FALSE) -> 0 | G9: =VLOOKUP(D9,'PN-Coding'!$A$2:$C$36,3,FALSE) -> 0 | H9: PN | I9: PN | J9: 0
D10: 1.5 EpC Translation to Indigenous Languages | E10: =VLOOKUP(D10,'PN-Coding'!$A$2:$C$36,2,FALSE) -> D.1.5 | G10: =VLOOKUP(D10,'PN-Coding'!$A$2:$C$36,3,FALSE) -> 7740
D11: 1.5 Material Design and Printing | E11: =VLOOKUP(D11,'PN-Coding'!$A$2:$C$36,2,FALSE) -> D.1.5 | G11: =VLOOKUP(D11,'PN-Coding'!$A$2:$C$36,3,FALSE) -> 7710
D12: 10.7 Lodging and per diem - Program Management Trip | E12: =VLOOKUP(D12,'PN-Coding'!$A$2:$C$36,2,FALSE) -> D.10.7 | G12: =VLOOKUP(D12,'PN-Coding'!$A$2:$C$36,3,FALSE) -> 7015
D13: 10.7 Airfare - Panama-Ecuador - Program Management Trip | E13: =VLOOKUP(D13,'PN-Coding'!$A$2:$C$36,2,FALSE) -> D.10.7 | G13: =VLOOKUP(D13,'PN-Coding'!$A$2:$C$36,3,FALSE) -> 7010
D14: Select from drop down | E14: =VLOOKUP(D14,'PN-Coding'!$A$2:$C$36,2,FALSE) -> 0 | G14: =VLOOKUP(D14,'PN-Coding'!$A$2:$C$36,3,FALSE) -> 0
D15: Select from drop down | E15: =VLOOKUP(D15,'PN-Coding'!$A$2:$C$36,2,FALSE) -> 0 | G15: =VLOOKUP(D15,'PN-Coding'!$A$2:$C$36,3,FALSE) -> 0
D16: Select from drop down | E16: =VLOOKUP(D16,'PN-Coding'!$A$2:$C$36,2,FALSE) -> 0 | G16: =VLOOKUP(D16,'PN-Coding'!$A$2:$C$36,3,FALSE) -> 0
D17: Select from drop down | E17: =VLOOKUP(D17,'PN-Coding'!$A$2:$C$36,2,FALSE) -> 0 | G17: =VLOOKUP(D17,'PN-Coding'!$A$2:$C$36,3,FALSE) -> 0
D18: Select from drop down | E18: =VLOOKUP(D18,'PN-Coding'!$A$2:$C$36,2,FALSE) -> 0 | G18: =VLOOKUP(D18,'PN-Coding'!$A$2:$C$36,3,FALSE) -> 0
D19: Select from drop down | E19: =VLOOKUP(D19,'PN-Coding'!$A$2:$C$36,2,FALSE) -> 0 | G19: =VLOOKUP(D19,'PN-Coding'!$A$2:$C$36,3,FALSE) -> 0
D20: Select from drop down | E20: =VLOOKUP(D20,'PN-Coding'!$A$2:$C$36,2,FALSE) -> 0 | G20: =VLOOKUP(D20,'PN-Coding'!$A$2:$C$36,3,FALSE) -> 0
D21: Select from drop down | E21: =VLOOKUP(D21,'PN-Coding'!$A$2:$C$36,2,FALSE) -> 0 | G21: =VLOOKUP(D21,'PN-Coding'!$A$2:$C$36,3,FALSE) -> 0
... D46: Select from drop down | E46: =VLOOKUP(D46,'PN-Coding'!$A$2:$C$36,2,FALSE) -> 0 | G46: =VLOOKUP(D46,'PN-Coding'!$A$2:$C$36,3,FALSE) -> 0
E200: Total Disbursements | F200: =SUM(F30:F35) -> 0

Sheet PN-Coding
A1: BUDGET ITEM/Description | B1: Activity Code | C1: Object Codes | D1: Subcontract ID | E1: Country
A2: Select from drop down
A3: Panama Personnel | B3: Personnel | C3: 7410 | D3: Fe y Alegria | E3: PN
A4: Fringe Benefits - Panama (31%) | B4: Fringe | C4: 7420 | D4: 0
A5: Equipment | B5: Equipment | C5: 7440
A6: Audit Costs | B6: Audit | C6: 7465
A7: Bank Fees | B7: Bank fees | C7: 7460
A8: Panama & Ecuador Communications (includes courier, phones etc.) | B8: Communications | C8: 7450
A9: Equipment Repair (all) | B9: Equip. Maint & Repair | C9: 7445
A10: Insurance | B10: Insurance | C10: 8170
A11: Legal Fees | B11: Legal | C11: 7470
A12: Office & Computer Supplies | B12: Supplies | C12: 7455
A13: Rent & Utilities | B13: Rent & Utilities | C13: 7435
A14: 1.4 Lodging & Per Diem Staff | B14: D.1.4 | C14: 7015
A15: 1.5 EpC Translation to Indigenous Languages | B15: D.1.5 | C15: 7740
A16: 1.5 Material Design and Printing | B16: D.1.5 | C16: 7710
... A43: 8.7 3Subcontract: ORGANIZATION TO BE DETERMINED | B43: D.8.7 | C43: 7370

Sheet PARTNERS - ACCIDENTE
C1: Partners of the Americas
C2: Monthly Cash Disbursements Journal
F3: 42490
F4: Panama
A6: * Choose from drop down list
A7: Date | B7: Ref or | C7: Payee | D7: *Budget Description | E7: *Activity | F7: Amount | G7: *Object | H7: Description of Expense | I7: Country | J7: Office | K7: *Subcontract | P7: Session Description
B8: CK# | E8: Code | F8: (USD) | G8: Code | K8: ID
A9: 42282 | B9: 203383 | C9: Enoc Molina | F9: 300 | H9: CARGO PARTNERS: Reconocimiento por Perdidas sufridas en accidente de Nuevo Vigia (24/sept/15) | I9: PN | J9: PN | K9: Fe y Alegria | P9: Reporte Financiero - Abril 2016
A10: 42282 | B10: 203384 | C10: Eugenio Rodriguez | F10: 300 | H10: CARGO PARTNERS: Reconocimiento por Perdidas sufridas en accidente de Nuevo Vigia (24/sept/15) | I10: PN | J10: PN | K10: Fe y Alegria | P10: Reporte Financiero - Abril 2016
A11: 42282 | B11: 203385 | C11: Alida Sierra de Victoria | F11: 300 | H11: CARGO PARTNERS: Reconocimiento por Perdidas sufridas en accidente de Nuevo Vigia (24/sept/15) | I11: PN | J11: PN | K11: Fe y Alegria | P11: Reporte Financiero - Abril 2016
F13: =SUM(F9:F11) -> 900
F131: =SUM(#REF!) -> #REF!

Sheet PARTNERS - LIBROS
C1: Partners of the Americas
C2: Monthly Cash Disbursements Journal
F3: 42490
F4: Panama
A6: * Choose from drop down list
A7: Date | B7: Ref or | C7: Payee | D7: *Budget Description | E7: *Activity | F7: Amount | G7: *Object | H7: Description of Expense | I7: Country | J7: Office | K7: *Subcontract | P7: Session Description
B8: CK# | E8: Code | F8: (USD) | G8: Code | K8: ID
A9: 42426 | B9: 203635 | C9: Daphnee Ferguson | F9: 190 | H9: PARTNERS - Donacion de Libros: Honorarios Logistica Donacion de Libros (pago 1/5) | I9: PN | J9: PN | K9: Fe y Alegria | P9: Reporte Financiero - Abril 2016
A10: 42444 | B10: 203661 | C10: Daphnee Ferguson | F10: 380 | H10: PARTNERS - Donacion de Libros: Honorarios Logistica Donacion de Libros (pago 2/5) | I10: PN | J10: PN | K10: Fe y Alegria | P10: Reporte Financiero - Abril 2016
A11: 42451 | B11: 203668 | C11: Daphnee Ferguson | F11: 620 | H11: PARTNERS - Donacion de Libros: Viaticos a Darien | I11: PN | J11: PN | K11: Fe y Alegria | P11: Reporte Financiero - Abril 2016
A12: 42451 | B12: 203677 | C12: Daphnee Ferguson | F12: 700 | H12: PARTNERS - Donacion de Libros: Viaticos a C.Ngabe y Changuinola | I12: PN | J12: PN | K12: Fe y Alegria | P12: Reporte Financiero - Abril 2016
A13: 42451 | B13: 203678 | C13: Daphnee Ferguson | F13: 380 | H13: PARTNERS - Donacion de Libros: Honorarios Logistica Donacion de Libros (3/5) | I13: PN | J13: PN | K13: Fe y Alegria | P13: Reporte Financiero - Abril 2016
A14: 42464 | B14: S/R | C14: BAC Panama | F14: =22.45+35 -> 57.45 | H14: PARTNERS - Donacion de Libros: Cargos Bancarios: Comision por transferencia Internacional | I14: PN | J14: PN | K14: Fe y Alegria | P14: Reporte Financiero - Abril 2016
A15: 42464 | B15: 203695 | C15: Daphnee Ferguson | F15: 475 | H15: PARTNERS - Donacion de Libros: Honorarios Logistica Donacion de Libros (4/5) | I15: PN | J15: PN | K15: Fe y Alegria | P15: Reporte Financiero - Abril 2016
A16: 42464 | B16: 203701 | C16: Ana Lorena Jovane | F16: 1000 | H16: PARTNERS - Donacion de Libros: Entrega de donacion en comunidades (logistica) | I16: PN | J16: PN | K16: Fe y Alegria | P16: Reporte Financiero - Abril 2016
A17: 42478 | B17: 203720 | C17: Daphnee Ferguson | F17: 1505 | H17: PARTNERS - Donacion de Libros: Distribucion / Coordinacion | I17: PN | J17: PN | K17: Fe y Alegria | P17: Reporte Financiero - Abril 2016
A18: 42478 | B18: 203722 | C18: Ana Lorena Jovane | F18: 1700 | H18: PARTNERS - Donacion de Libros: Distribucion (viaticos) | I18: PN | J18: PN | K18: Fe y Alegria | P18: Reporte Financiero - Abril 2016
A19: 18 abrl 16 | C19: BAC Panama | F19: =22.45+35 -> 57.45 | H19: PARTNERS - Donacion de Libros: Cargos Bancarios: Comision por transferencia Internacional | I19: PN | J19: PN | K19: Fe y Alegria | P19: Reporte Financiero - Abril 2016
A20: 42485 | B20: 203726 | C20: Daphnee Ferguson | F20: 475 | H20: PARTNERS - Donacion de Libros: Honorarios Logistica Donacion de Libros (5/5) | I20: PN | J20: PN | K20: Fe y Alegria | P20: Reporte Financiero - Abril 2016
F22: =SUM(F9:F21) -> 7539.9
F140: =SUM(#REF!) -> #REF!

Sheet codes
A1: Activity Title | B1: Activity Code | C1: G/L Code
A2: Personnel | B2: PERSNL | C2: 7410
A3: Fringe Benefits | B3: FRINGE | C3: 7420
A4: Equipment | B4: EQUIP | C4: 7440
A5: Audit | B5: AUDIT | C5: 8230
A6: Bank Fees | B6: BANK FEES | C6: 7460
A7: Communications | B7: COMM | C7: 7450
A8: Equipment & Maint. Repair | B8: EQ.MNT REP | C8: 7445
A9: Insurance | B9: INSURANCE | C9: 8170
A10: Legal Fees | B10: LEGAL | C10: 7470
A11: Supplies | B11: SUPPLIES | C11: 7455
A12: Rent & Utilities | B12: RENT & UT | C12: 7435
A13: EPC Translations to Indigenous Languages & Matl Design Print | B13: D.1.5.A | C13: 7740
... A51: Final Evaluation | B51: D.10.10 | C51: 8221
A52: HQ Mgmt travel | B52: D.10.7.D | C52: 7510/7520
A53: Mid-term Evaluation | B53: D.10.9 | C53: 8221
A54: Subcontract: ExpoFlores - Education | B54: D.1.8.F | C54: 7370
A55: Subcontract: Comunidec - Zonal Coordinators | B55: D.10.11.D | C55: 7370
A56: Subcontract: FUDELA - Zonal Coordinators | B56: D.10.11.E | C56: 7370
A57: Subcontract: ExpoFlores - Zonal Coordinators | B57: D.10.11.F | C57: 7370
A58: Social Protection Svs. In Targated Communities | B58: D.3.1 | C58: 7120
A60: WASHINGTON
A61: Personnel | B61: PERSNL
A62: Fringe Benefits | B62: FRINGE
A63: Communications | B63: COMM
A64: Entrena Quantum Learning Teachers | B64: D.1.1
A65: Entrena Epc Facilitators Training | B65: D.1.2
A66: EpC Adaptation & Implementation | B66: D.1.3
A67: Entrena EPC Material Adaptation | B67: D.1.4
A68: Aganar Quality Control | B68: D.4.1
A69: Task Mapping Risk Assessment | B69: D.5.1
A70: CSR Technical Review | B70: D.5.2
A71: DevTech: M&E Specialist | B71: D.10.1
A72: Indirect Costs | B72: IDC
... A88: Software for Data Collection & Mgmt | B88: D.10.4
A91: PANAMA
A92: Personnel | B92: PERSNL | C92: 7410
A93: Fringe Benefits | B93: FRINGE | C93: 7420
A94: Equipment | B94: EQUIP | C94: 7440
A95: Audit | B95: AUDIT | C95: 8230
A96: Bank Fees | B96: BANK FEES | C96: 7460
A97: Communications | B97: COMM | C97: 7450
A98: Equipment & Maint. Repair | B98: EQ.MNT REP | C98: 7445
A99: Insurance | B99: INSURANCE | C99: 8170
A100: Legal Fees | B100: LEGAL | C100: 7470
A101: Supplies | B101: SUPPLIES | C101: 7455
A102: Rent & Utilities | B102: RENT & UT | C102: 7435
A103: EPC Translations to Indigenous Languages & Matl Design Print | B103: D.1.5.A | C103: 7740
... A116: CMEP Workshops | B116: D.10.6 | C116: 7120
A117: Establish M&E System- Airfare & Lodging and Per diem | B117: D.10.7.A | C117: 7010/7015
A118: Program Mgmt.- Airfare & Lodging and Per diem | B118: D.10.7.B | C118: 7510/7520
A119: Field Verification Trip Airfare & Lodging and per diem - Field Verification Visits | B119: D.10.7.C | C119: 7010/7015
A120: Field Verification Trips- Local Transportation-Airfare,Lodging,Perdiem | B120: D.10.7.C | C120: 7510/7520
A121: HQ Mgmt travel | B121: D.10.7.D | C121: 7510/7520
A122: Annual Visits DOL | B122: D.10.8 | C122: 7431
A123: Mid-term Evaluation | B123: D.10.9 | C123: 8221
A124: Stakeholders Presentation of Program Evaluation | B124: D.11.1 | C124: 8221
A125: Closing Ceremony & Presentation of Program Results | B125: D.11.2 | C125: 7391
A126: Value Chain Analysis | B126: D.2.1 | C126: 7499
A127: Linking Households to Livelihood Programs | B127: D.2.2 | C127: 7499
A128: Tech Assist.to Develop Links to Business Activities | B128: D.2.3 | C128: 7120
A129: Subcontract: Fe y Alegria | B129: D.2.5.A | C129: 7370
A130: Subcontract: APRODISO - Livelihoods | B130: D.2.5.B | C130: 7370
A131: Subcontract: APROTENGB - Livelihoods | B131: D.2.5.C | C131: 7370
A132: Social Protection Svs. In Targated Communities | B132: D.3.1 | C132: 7120
A133: Subcontract: Fe y Alegria - Social Protection | B133: D.3.2.A | C133: 7370
... A145: III Global Conference on Child Labor Brazil 2013 | B145: D.9.1 | C145: 7491
A146: Targeted Learning Exchanges | B146: D.9.2 | C146: 7010/7015
A147: Network Building | B147: D.9.3 | C147: 7120

Sheet CODES NEWS
A1: Personnel | B1: PERSNL | C1: 7410 | D1: 657695.3
A2: Fringe Benefits | B2: FRINGE | C2: 7420 | D2: 228456
A3: Equipment | B3: EQUIP | C3: 7440 | D3: 11655
A4: Audit | B4: AUDIT | C4: 8230 | D4: 20000
A5: Bank Fees | B5: BANK FEES | C5: 7460 | D5: 4800
A6: Communications | B6: COMM | C6: 7450 | D6: 6200
A7: Equipment & Maint. Repair | B7: EQ.MNT REP | C7: 7445 | D7: 7000
A8: Insurance | B8: INSURANCE | C8: 8170 | D8: 4000
A9: Legal Fees | B9: LEGAL | C9: 7470 | D9: 1000
A10: Supplies | B10: SUPPLIES | C10: 7455 | D10: 3600
A11: Rent & Utilities | B11: RENT & UT | C11: 7435 | D11: 67200
A12: EPC Translations to Indigenous Languages & Matl Design Print | B12: D.1.5.A | C12: 7740 | D12: 57971.5
... A17: Subcontract: APROTENGB - Education | B17: D.1.8.C | C17: 7370 | D17: 84000
A18: EducaFuturo Darien | B18: D.1.8.G | C18: ???? | D18: 50228
A19: Final Evaluation | B19: D.10.10 | C19: 8221 | D19: 17500
A20: Subcontract: Fe y Alegria - Zonal Coordinators | B20: D.10.11.A | C20: 7370 | D20: 29188
A21: Subcontract: APRODISO - Zonal Coordinators | B21: D.10.11.B | C21: 7370 | D21: 12485
A22: Subcontract: APROTENGB - Zonal Coordinators | B22: D.10.11.C | C22: 7370 | D22: 39296
A23: Data Base Technician Equipment | B23: D.10.12 | C23: 7440 | D23: 1000
A24: DevTech Baseline Survey | B24: D.10.2 | C24: 8221 | D24: 36743
A25: DevTech Follow-up Survey | B25: D.10.3 | C25: 8221 | D25: 34500
A26: Research Survey, Analysis and Report | B26: D.10.5 | C26: ???? | D26: 10000
A27: CMEP Workshops | B27: D.10.6 | C27: 7120 | D27: 3638.24
A28: Establish M&E System- Airfare & Lodging and Per diem | B28: D.10.7.A | C28: 7010/7015 | D28: 2200
A29: Program Mgmt.- Airfare & Lodging and Per diem | B29: D.10.7.B | C29: 7510/7520 | D29: 6600
A30: Field Verification Trip Airfare, Local Transp & Lodging and per diem - Field Verification Visits | B30: D.10.7.C | C30: 7010/7015 | D30: 22500
A31: HQ Mgmt travel | B31: D.10.7.D | C31: 7510/7520 | D31: 500
A32: Annual Visits DOL | B32: D.10.8 | C32: 7431 | D32: 3000
A33: Mid-term Evaluation | B33: D.10.9 | C33: 8221 | D33: 17500
A34: Stakeholders Presentation of Program Evaluation | B34: D.11.1 | C34: 8221 | D34: 1175
A35: Closing Ceremony & Presentation of Program Results | B35: D.11.2 | C35: 7391 | D35: 2250
A36: Value Chain Analysis | B36: D.2.1 | C36: 7499 | D36: 4000
A37: Linking Households to Livelihood Programs | B37: D.2.2 | C37: 7499 | D37: 3525
A38: Tech Assist.to Develop Links to Business Activities | B38: D.2.3 | C38: 7120 | D38: 7500
A39: Subcontract: Fe y Alegria | B39: D.2.5.A | C39: 7370 | D39: 35000
A40: Subcontract: APROTENGB - Livelihoods | B40: D.2.5.C | C40: 7370 | D40: 14000
A41: EducaFuturo Darien - Livelihoods | B41: D.2.5.G | C41: ???? | D41: 30000
A42: Social Protection Svs. In Targated Communities | B42: D.3.1 | C42: 7120 | D42: 2500
A43: Subcontract: Fe y Alegria - Social Protection | B43: D.3.2.A | C43: 7370 | D43: 4688
A44: Subcontract: APROTENGB - Social Protection | B44: D.3.2.C | C44: 7370 | D44: 1875
A45: EducaFuturo Darien - Social Protection | B45: D.3.2.G | C45: ???? | D45: 4500
A46: Aganar Quality Control | B46: D.4.1 | C46: 7495 | D46: 15000
A47: Subcontractor: CoSPAE | B47: D.4.3.A | C47: 7370 | D47: 165353
A48: EducaFuturo A Ganar Panama | B48: D.4.3.C | C48: 7391 | D48: 49500
A49: Subcontract: Aprotengb - A Ganar | B49: D.4.3.F | C49: 7370 | D49: 27000
A50: Subcontract: Fe y Alegria - A Ganar | B50: D.4.3.G | C50: 7370 | D50: 49500
A51: Local Stakeholders Event | B51: D.6.1 | C51: 7391 | D51: 2375
A52: Data Collection Training Workshops | B52: D.6.2 | C52: 7120 | D52: 240
A53: Community Based Awareness Raising Workshop[ | B53: D.8.1 | C53: 7120 | D53: 3250
A54: Community Mobilization | B54: D.8.2 | C54: 7120 | D54: 2500
A55: Mass Media Campaigns | B55: D.8.3 | C55: 7720 | D55: 4000
A56: Posters, Bulletins, Awareness Materials | B56: D.8.4 | C56: 7380 | D56: 2500
A57: III Global Conference on Child Labor Brazil 2013 | B57: D.9.1 | C57: 7491 | D57: 1000
A58: Targeted Learning Exchanges | B58: D.9.2 | C58: 7010/7015 | D58: 1080
A63: código 7010: unicamente para tiquetes aereos
A65: 7015 is Travel Related Expenses (Non-Staff)
A66: 7510- Staff Travel Airfare (POA Staff Only) | B66: carmen
A67: 7520- Staff Travel Related Expenses | B67: carmen
A68: 7010 - Travel Airfare (Non-Staff)
A71: Hi Carmen,
A72: Please see updated coding below. These object codes should be used going forward, since they are new activities with no expenditures.
A73: EducaFuturo Darien | B73: D.1.8.G | C73: 7610
A74: Research Survey, Analysis and Report | B74: D.10.5 | C74: 7390
A75: EducaFuturo Darien - Livelihoods | B75: D.2.5.G | C75: 7120
A76: EducaFuturo Darien - Social Protection | B76: D.3.2.G | C76: 7120
A77: EducaFuturo A Ganar Panama | B77: D.4.3.C | C77: 7391
A78: Thanks,
A79: Danielle
C81: *Object
C82: Code
A83: Códigos que no son del Proyecto, ejemplo: Donación de Libros | C83: 95UN 8402

Sheet Bank Recon
A2: DOL423 - Mexico
A3: Bank Reconciliation
A4: Bank Account: 22-00079459-3 Banco Santander
A5: Month and Year: | C5: 45108
A6: Exchange Rate for the Month MXN to USD | C6: 16.9203
A7: According to the Bank
A8: Balance as end of: | B8: 45108 | F8: 890791.97
A9: Plus:
A10: Deposits in Transit | F10: 0
A11: Less:
A12: Check in Transit | F12: =SUM(D14:D19) -> 0
A13: Number of Check | B13: Details of Expense | C13: Date | D13: Amount
D14: 0
D15: 0
D16: 0
D17: 0
D18: 0
D19: 0
B21: Balance According to the Bank: | C21: =C5 -> 45108 | F21: =F8+F10-F12 -> 890791.97
B22: Exchange Rate Applied MXN to USD | F22: =C6 -> 16.9203
B24: USD Balance According to the Bank end of: | C24: =C21 -> 45108 | F24: =F21/F22 -> 52646.346
A26: According to the Books
A27: Balance as Beginning of: | B27: =B8 -> 45108 | F27: 826863.71
A28: Plus:
A29: Deposits for the Month | F29: 426579.38
A30: Less:
A31: Check Written in Current Month | F31: 362651.12
B33: MXN Balance According to the Books end of: | C33: =C21 -> 45108 | F33: =F27+F29-F31 -> 890791.97
B34: Exchange Rate Applied MXN to USD | F34: =C6 -> 16.9203
B36: USD Balance According to the Books end of: | C36: =C33 -> 45108 | F36: =F33/F34 -> 52646.346
B38: Difference of Bank and Book Balance as end of: | C38: =C36 -> 45108 | F38: =F24-F36 -> 0
A40: By signing this report, I certify that the expenses contained in the present report for month of July 2023 equivalent to US dollars $13,309.59 were incurred by the entity, and are related to activities carried out by the project. I certify to the best of my knowledge and belief that the report is true, complete, and accurate, and that the expenditures and disbursements are for the purposes and objectives set forth in the terms and conditions of the Department of Labor (DOL) Award. I am aware that any false, fictitious, or fraudulent information, or the omission of any material fact, may subject me to criminal, civil or administrative penalties for fraud, false statements, false claims or otherwise. I understand that if the expenses contained herein are questioned or not approved by Partners CFO or by DOL, I will provide full cooperation to all the involved parties to complete such review, audit or investigation. | H40: Completar con el total de expensas del mes
A44: Prepared By:
B45: Finance-Administrative Director | D45: Date
A47: Approved By:
B48: Project Director | D48: Date

Sheet ACUMULADO
A1: Financial Summary | CE1: Financial Summary
B2: TOTAL BUDGET PANAMA - JULIO 2016 | C2: Budget Yr 1 | D2: First Quarter Expenditures | H2: Second Quarter Expenditures | L2: Third Quarter Expenditures | P2: Fourth Quarter Expenditures | T2: TOTAL | V2: Budget Yr1 | W2: Budget Yr 2 | X2: First Quarter Expenditures | AB2: Second Quarter Expenditures | AF2: Third Quarter Expenditures | AJ2: Fourth Quarter Expenditures | AN2: TOTAL | AP2: Budget Yr2 | AQ2: Budget Yr 3 | AR2: First Quarter Expenditures | AV2: Second Quarter Expenditures | AZ2: Third Quarter Expenditures | BD2: Fourth Quarter Expenditures | BH2: TOTAL | BJ2: Budget Yr3 | BK2: Budget Yr 4 | BL2: First Quarter Expenditures | BP2: Second Quarter Expenditures | BT2: Third Quarter Expenditures | BX2: Fourth Quarter Expenditures | CB2: TOTAL | CD2: Remaining
A3: Budget Description | D3: 41275 | E3: 41306 | F3: 41334 | G3: TOTAL | H3: 41365 | I3: 41395 | J3: 41426 | K3: TOTAL | L3: 41456 | M3: 41487 | N3: 41518 | O3: TOTAL | P3: 41548 | Q3: 41579 | R3: 41609 | S3: TOTAL | T3: EXPENDITURES 2013 | U3: % Implemetation | V3: Remaining | X3: 41640 | Y3: 41671 | Z3: 41699 | AA3: TOTAL | AB3: 41730 | AC3: 41760 | AD3: 41791 | AE3: TOTAL | AF3: 41821 | AG3: 41852 | AH3: 41883 | AI3: TOTAL | AJ3: 41913 | AK3: 41944 | AL3: 41974 | AM3: TOTAL | AN3: EXPENDITURES 2014 | AO3: % Implemetation | AP3: Remaining | AR3: 42005 | AS3: 42036 | AT3: 42064 | AU3: TOTAL | AV3: 42095 | AW3: 42125 | AX3: 42156 | AY3: TOTAL | AZ3: 42186 | BA3: 42217 | BB3: 42248 | BC3: TOTAL | BD3: 42278 | BE3: 42309 | BF3: 42339 | BG3: TOTAL | BH3: EXPENDITURES 2015 | BI3: % Implemetation | BJ3: Remaining | BL3: 42370 | BM3: 42401 | BN3: 42430 | BO3: TOTAL | BP3: 42461 | BQ3: 42491 | BR3: 42522 | BS3: TOTAL | BT3: 42552 | BU3: 42583 | BV3: 42614 | BW3: TOTAL | BX3: 42644 | BY3: 42675 | BZ3: 42705 | CA3: TOTAL | CB3: EXPENDITURES 2016 | CC3: % Implemetation | CE3: Budget Description
A4: Panama Personnel | B4: 702235.8 | C4: ='budget anual'!C6 -> #REF! | E4: 10962.24 | F4: 12340.35 | G4: =SUM(D4:F4) -> 23302.59 | H4: 15931.56 | I4: 15080.15 | J4: 15080.15 | K4: =SUM(H4:J4) -> 46091.86 | L4: 15080.15 | M4: 15080.15 | N4: 15095.39 | O4: =SUM(L4:N4) -> 45255.69 | P4: 15135.15 | Q4: 14159.89 | R4: 14080.15 | S4: =SUM(P4:R4) -> 43375.19 | T4: =G4+K4+O4+S4 -> 158025.33 | U4: =T4/C4 -> #REF! | V4: =C4-T4 -> #REF! | W4: ='budget anual'!D6 -> #REF! | X4: 14938.64 | Y4: 15030.16 | Z4: 15030.16 | AA4: =SUM(X4:Z4) -> 44998.96 | AB4: 15030.17 | AC4: 15030.15 | AD4: 15030.15 | AE4: =SUM(AB4:AD4) -> 45090.47 | AF4: 15030.15 | AG4: 15030.17 | AH4: 14934.7 | AI4: =SUM(AF4:AH4) -> 44995.02 | AJ4: =14969.3+13.12 -> 14982.42 | AK4: 15030.16 | AL4: 13180.16 | AM4: =SUM(AJ4:AL4) -> 43192.74 | AN4: =AA4+AE4+AI4+AM4 -> 178277.19 | AO4: =AN4/W4 -> #REF! | AP4: =(V4+W4)-AN4 -> #REF! | AQ4: ='budget anual'!E6 -> 131000 | AR4: 12123.73 | AS4: 14085.16 | AT4: 8056.65 | AU4: =SUM(AR4:AT4) -> 34265.54 | AV4: 7926.66 | AW4: 8843.31 | AX4: 8109.97 | AY4: =SUM(AV4:AX4) -> 24879.94 | AZ4: 8344.25 | BA4: 8859.98 | BB4: 9609.98 | BC4: =SUM(AZ4:BB4) -> 26814.21 | BD4: 10019.03 | BE4: 10359.96 | BF4: 10133.25 | BG4: =SUM(BD4:BF4) -> 30512.24 | BH4: =AU4+AY4+BC4+BG4 -> 116471.93 | BI4: =BH4/AQ4 -> 0.8890987 | BJ4: =(AP4+AQ4)-BH4 -> #REF! | BK4: =B4-T4-AN4-BH4 -> 249461.35 | BL4: 10412.99 | BM4: 9959.98 | BN4: 10309.97 | BO4: =SUM(BL4:BN4) -> 30682.94 | BP4: 10683.84 | BQ4: 10909.99 | BR4: 10809.98 | BS4: =SUM(BP4:BR4) -> 32403.81 | BT4: 10309.98 | BU4: =11059.12-500 -> 10559.12 | BV4: 10309.97 | BW4: =SUM(BT4:BV4) -> 31179.07 | BX4: 10809.97 | BY4: 8574.89 | BZ4: 6392.57 | CA4: =SUM(BX4:BZ4) -> 25777.43 | CB4: =BO4+BS4+BW4+CA4 -> 120043.25 | CC4: =CB4/BK4 -> 0.48120981 | CD4: =BK4-CB4 -> 129418.1 | CE4: Panama Personnel
A5: Fringe Benefits | B5: 228456 | C5: ='budget anual'!C8 -> #REF! | F5: 2080.88 | G5: =SUM(D5:F5) -> 2080.88 | H5: 6533.09 | I5: 2179.68 | J5: 2168.53 | K5: =SUM(H5:J5) -> 10881.3 | L5: 2168.53 | M5: 7739.87 | N5: 2188.44 | O5: =SUM(L5:N5) -> 12096.84 | P5: 4983.75 | Q5: 2130.33 | R5: 7222.66 | S5: =SUM(P5:R5) -> 14336.74 | T5: =G5+K5+O5+S5 -> 39395.76 | U5: =T5/C5 -> #REF! | V5: =C5-T5 -> #REF! | W5: ='budget anual'!D8 -> #REF! | X5: 2148.18 | Y5: 2161.33 | Z5: 2161.33 | AA5: =SUM(X5:Z5) -> 6470.84 | AB5: 7657.68 | AC5: 2161.34 | AD5: 2161.34 | AE5: =SUM(AB5:AD5) -> 11980.36 | AF5: 2161.34 | AG5: 7709.95 | AH5: 2147.61 | AI5: =SUM(AF5:AH5) -> 12018.9 | AJ5: 4037.12 | AK5: 2161.33 | AL5: 13254.69 | AM5: =SUM(AJ5:AL5) -> 19453.14 | AN5: =AA5+AE5+AI5+AM5 -> 49923.24 | AO5: =AN5/W5 -> #REF! | AP5: =(V5+W5)-AN5 -> #REF! | AQ5: ='budget anual'!E8 -> #REF! | AR5: 3006.2 | AS5: 9015.93 | AT5: 1067.96 | AU5: =SUM(AR5:AT5) -> 13090.09 | AV5: 3350.84 | AW5: 1271.67 | AX5: 1166.22 | AY5: =SUM(AV5:AX5) -> 5788.73 | AZ5: 1395.5 | BA5: 4327.25 | BB5: 1381.92 | BC5: =SUM(AZ5:BB5) -> 7104.67 | BD5: 1440.75 | BE5: 1489.77 | BF5: 5379.12 | BG5: =SUM(BD5:BF5) -> 8309.64 | BH5: =AU5+AY5+BC5+BG5 -> 34293.13 | BI5: =BH5/AQ5 -> #REF! | BJ5: =(AP5+AQ5)-BH5 -> #REF! | BK5: =B5-T5-AN5-BH5 -> 104843.87 | BL5: 1479.92 | BM5: 1432.25 | BN5: 1482.58 | BO5: =SUM(BL5:BN5) -> 4394.75 | BP5: 4917.38 | BQ5: 1518.53 | BR5: 1482.58 | BS5: =SUM(BP5:BR5) -> 7918.49 | BT5: 1482.59 | BU5: 5039.54 | BV5: 1482.58 | BW5: =SUM(BT5:BV5) -> 8004.71 | BX5: 11333.51 | BY5: 5076.61 | BZ5: 25835.2 | CA5: =SUM(BX5:BZ5) -> 42245.32 | CB5: =BO5+BS5+BW5+CA5 -> 62563.27 | CC5: =CB5/BK5 -> 0.59672797 | CD5: =BK5-CB5 -> 42280.6 | CE5: Fringe Benefits
A6: Equipment | B6: 11655 | C6: ='budget anual'!C17 -> 11655 | G6: =SUM(D6:F6) -> 0 | H6: =208.97+4862.08 -> 5071.05 | I6: 2843.77 | J6: 3431.87 | K6: =SUM(H6:J6) -> 11346.69 | L6: 74.9 | O6: =SUM(L6:N6) -> 74.9 | Q6: 475.08 | S6: =SUM(P6:R6) -> 475.08 | T6: =G6+K6+O6+S6 -> 11896.67 | U6: =T6/C6 -> 1.0207353 | V6: =C6-T6 -> -241.67 | W6: 0 | AA6: =SUM(X6:Z6) -> 0 | AD6: 93.09 | AE6: =SUM(AB6:AD6) -> 93.09 | AI6: =SUM(AF6:AH6) -> 0 | AM6: =SUM(AJ6:AL6) -> 0 | AN6: =AA6+AE6+AI6+AM6 -> 93.09 | AP6: =(V6+W6)-AN6 -> -334.76 | AQ6: 0 | AU6: =SUM(AR6:AT6) -> 0 | AV6: 972.63 | AY6: =SUM(AV6:AX6) -> 972.63 | BC6: =SUM(AZ6:BB6) -> 0 | BG6: =SUM(BD6:BF6) -> 0 | BH6: =AU6+AY6+BC6+BG6 -> 972.63 | BJ6: =(AP6+AQ6)-BH6 -> -1307.39 | BK6: =B6-T6-AN6-BH6 -> -1307.39 | BO6: =SUM(BL6:BN6) -> 0 | BS6: =SUM(BP6:BR6) -> 0 | BW6: =SUM(BT6:BV6) -> 0 | CA6: =SUM(BX6:BZ6) -> 0 | CB6: =BO6+BS6+BW6+CA6 -> 0 | CD6: =BK6-CB6 -> -1307.39 | CE6: Equipment
A7: Audit | B7: 20000 | C7: ='budget anual'!C30 -> 5000 | G7: =SUM(D7:F7) -> 0 | K7: =SUM(H7:J7) -> 0 | O7: =SUM(L7:N7) -> 0 | R7: 1350 | S7: =SUM(P7:R7) -> 1350 | T7: =G7+K7+O7+S7 -> 1350 | U7: =T7/C7 -> 0.27 | V7: =C7-T7 -> 3650 | W7: ='budget anual'!D30 -> 5000 | X7: 3150 | AA7: =SUM(X7:Z7) -> 3150 | AE7: =SUM(AB7:AD7) -> 0 | AI7: =SUM(AF7:AH7) -> 0 | AM7: =SUM(AJ7:AL7) -> 0 | AN7: =AA7+AE7+AI7+AM7 -> 3150 | AO7: =AN7/W7 -> 0.63 | AP7: =(V7+W7)-AN7 -> 5500 | AQ7: ='budget anual'!E30 -> 5000 | AR7: 2325 | AS7: 2325 | AU7: =SUM(AR7:AT7) -> 4650 | AY7: =SUM(AV7:AX7) -> 0 | BC7: =SUM(AZ7:BB7) -> 0 | BG7: =SUM(BD7:BF7) -> 0 | BH7: =AU7+AY7+BC7+BG7 -> 4650 | BI7: =BH7/AQ7 -> 0.93 | BJ7: =(AP7+AQ7)-BH7 -> 5850 | BK7: =B7-T7-AN7-BH7 -> 10850 | BL7: 1395 | BM7: 1040 | BN7: 3050.43 | BO7: =SUM(BL7:BN7) -> 5485.43 | BS7: =SUM(BP7:BR7) -> 0 | BW7: =SUM(BT7:BV7) -> 0 | CA7: =SUM(BX7:BZ7) -> 0 | CB7: =BO7+BS7+BW7+CA7 -> 5485.43 | CC7: =CB7/BK7 -> 0.50556959 | CD7: =BK7-CB7 -> 5364.57 | CE7: Audit
A8: Bank Fees | B8: 4800 | C8: ='budget anual'!C28 -> 1200 | E8: 21.4 | F8: 6.85 | G8: =SUM(D8:F8) -> 28.25 | H8: =5.35+21.4+1.5 -> 28.25 | I8: 35.4 | J8: 28.85 | K8: =SUM(H8:J8) -> 92.5 | L8: 463.6 | M8: 49.95 | N8: 7.65 | O8: =SUM(L8:N8) -> 521.2 | P8: 8.95 | Q8: 28.95 | R8: 33.9 | S8: =SUM(P8:R8) -> 71.8 | T8: =G8+K8+O8+S8 -> 713.75 | U8: =T8/C8 -> 0.59479167 | V8: =C8-T8 -> 486.25 | W8: ='budget anual'!D28 -> 1200 | X8: 40.05 | Y8: 8.95 | Z8: 50.55 | AA8: =SUM(X8:Z8) -> 99.55 | AB8: 44.5 | AC8: 7.35 | AD8: 111.04 | AE8: =SUM(AB8:AD8) -> 162.89 | AF8: 16.44 | AG8: 66.64 | AH8: 68.44 | AI8: =SUM(AF8:AH8) -> 151.52 | AJ8: 10.49 | AK8: 67.94 | AL8: 67.54 | AM8: =SUM(AJ8:AL8) -> 145.97 | AN8: =AA8+AE8+AI8+AM8 -> 559.93 | AO8: =AN8/W8 -> 0.46660833 | AP8: =(V8+W8)-AN8 -> 1126.32 | AQ8: ='budget anual'!E28 -> 1200 | AR8: 94.49 | AS8: 10.49 | AT8: 70.08 | AU8: =SUM(AR8:AT8) -> 175.06 | AV8: 70.08 | AW8: 76.71 | AX8: 77.21 | AY8: =SUM(AV8:AX8) -> 224 | AZ8: 70.38 | BA8: 68.48 | BB8: 70.18 | BC8: =SUM(AZ8:BB8) -> 209.04 | BD8: 69.48 | BE8: 78.31 | BF8: 79.01 | BG8: =SUM(BD8:BF8) -> 226.8 | BH8: =AU8+AY8+BC8+BG8 -> 834.9 | BI8: =BH8/AQ8 -> 0.69575 | BJ8: =(AP8+AQ8)-BH8 -> 1491.42 | BK8: =B8-T8-AN8-BH8 -> 2691.42 | BL8: 69.78 | BM8: 128.63 | BN8: 69.78 | BO8: =SUM(BL8:BN8) -> 268.19 | BP8: 449.33 | BQ8: 22.96 | BR8: 79.71 | BS8: =SUM(BP8:BR8) -> 552 | BT8: 72.48 | BU8: 74.28 | BV8: 41.92 | BW8: =SUM(BT8:BV8) -> 188.68 | BX8: 72.38 | BY8: 69.58 | BZ8: 19.56 | CA8: =SUM(BX8:BZ8) -> 161.52 | CB8: =BO8+BS8+BW8+CA8 -> 1170.39 | CC8: =CB8/BK8 -> 0.43485967 | CD8: =BK8-CB8 -> 1521.03 | CE8: Bank Fees
A9: Communications (courier, phones etc.) | B9: 6200 | C9: ='budget anual'!C19+'budget anual'!C20+'budget anual'!C21 -> 1550 | F9: 87.74 | G9: =SUM(D9:F9) -> 87.74 | I9: 107 | J9: 113.42 | K9: =SUM(H9:J9) -> 220.42 | O9: =SUM(L9:N9) -> 0 | P9: 163.07 | Q9: 88.25 | R9: 56.05 | S9: =SUM(P9:R9) -> 307.37 | T9: =G9+K9+O9+S9 -> 615.53 | U9: =T9/C9 -> 0.39711613 | V9: =C9-T9 -> 934.47 | W9: ='budget anual'!D19+'budget anual'!D20+'budget anual'!D21 -> 1550 | X9: 56.05 | Y9: 61.02 | Z9: 56.05 | AA9: =SUM(X9:Z9) -> 173.12 | AB9: 56.05 | AC9: 127.64 | AD9: 100.51 | AE9: =SUM(AB9:AD9) -> 284.2 | AF9: 100.21 | AG9: 100.51 | AH9: 158.01 | AI9: =SUM(AF9:AH9) -> 358.73 | AJ9: 395.83 | AK9: 100.19 | AL9: 123.96 | AM9: =SUM(AJ9:AL9) -> 619.98 | AN9: =AA9+AE9+AI9+AM9 -> 1436.03 | AO9: =AN9/W9 -> 0.92647097 | AP9: =(V9+W9)-AN9 -> 1048.44 | AQ9: ='budget anual'!E19+'budget anual'!E20+'budget anual'!E21 -> 1550 | AR9: 100.51 | AS9: 699.71 | AT9: 158.43 | AU9: =SUM(AR9:AT9) -> 958.65 | AV9: 170.51 | AW9: 143.31 | AX9: 167.51 | AY9: =SUM(AV9:AX9) -> 481.33 | AZ9: 116.61 | BA9: 164.21 | BB9: 600.69 | BC9: =SUM(AZ9:BB9) -> 881.51 | BD9: 143.31 | BE9: 153.72 | BF9: 104.93 | BG9: =SUM(BD9:BF9) -> 401.96 | BH9: =AU9+AY9+BC9+BG9 -> 2723.45 | BI9: =BH9/AQ9 -> 1.7570645 | BJ9: =(AP9+AQ9)-BH9 -> -125.01 | BK9: =B9-T9-AN9-BH9 -> 1424.99 | BL9: 146.63 | BM9: 160.64 | BN9: 121.51 | BO9: =SUM(BL9:BN9) -> 428.78 | BP9: 156.5 | BQ9: 183.58 | BR9: 114.29 | BS9: =SUM(BP9:BR9) -> 454.37 | BT9: 203.99 | BU9: 173.92 | BV9: 308.18 | BW9: =SUM(BT9:BV9) -> 686.09 | BX9: 143.31 | BY9: 159.38 | BZ9: 220.19 | CA9: =SUM(BX9:BZ9) -> 522.88 | CB9: =BO9+BS9+BW9+CA9 -> 2092.12 | CC9: =CB9/BK9 -> 1.4681647 | CD9: =BK9-CB9 -> -667.13 | CE9: Communications (courier, phones etc.)
A10: Equpment (all) maintenance & Repairs | B10: 11800 | C10: ='budget anual'!C26+'budget anual'!C27+'budget anual'!C29 -> 2950 | G10: =SUM(D10:F10) -> 0 | H10: =50+7.5 -> 57.5 | I10: 80.2 | J10: 72.87 | K10: =SUM(H10:J10) -> 210.57 | M10: 251.26 | N10: 491.13 | O10: =SUM(L10:N10) -> 742.39 | P10: 10 | Q10: 115 | S10: =SUM(P10:R10) -> 125 | T10: =G10+K10+O10+S10 -> 1077.96 | U10: =T10/C10 -> 0.36541017 | V10: =C10-T10 -> 1872.04 | W10: ='budget anual'!D26+'budget anual'!D27+'budget anual'!D29 -> 2950 | Y10: 19.73 | Z10: 115.5 | AA10: =SUM(X10:Z10) -> 135.23 | AB10: 70 | AC10: 137.8 | AD10: 80 | AE10: =SUM(AB10:AD10) -> 287.8 | AF10: 34.5 | AG10: 147.13 | AH10: 146.4 | AI10: =SUM(AF10:AH10) -> 328.03 | AJ10: 72.07 | AL10: 12.16 | AM10: =SUM(AJ10:AL10) -> 84.23 | AN10: =AA10+AE10+AI10+AM10 -> 835.29 | AO10: =AN10/W10 -> 0.28314915 | AP10: =(V10+W10)-AN10 -> 3986.75 | AQ10: ='budget anual'!E26+'budget anual'!E27+'budget anual'!E29 -> 2950 | AR10: 248.85 | AS10: 196.38 | AT10: 508.84 | AU10: =SUM(AR10:AT10) -> 954.07 | AV10: 432.97 | AW10: 292.83 | AX10: 277.96 | AY10: =SUM(AV10:AX10) -> 1003.76 | AZ10: 283.64 | BA10: 179.59 | BB10: 402.01 | BC10: =SUM(AZ10:BB10) -> 865.24 | BD10: 240.4 | BE10: 233 | BG10: =SUM(BD10:BF10) -> 473.4 | BH10: =AU10+AY10+BC10+BG10 -> 3296.47 | BI10: =BH10/AQ10 -> 1.1174475 | BJ10: =(AP10+AQ10)-BH10 -> 3640.28 | BK10: =B10-T10-AN10-BH10 -> 6590.28 | BL10: 332.95 | BM10: 159.06 | BN10: 1495.27 | BO10: =SUM(BL10:BN10) -> 1987.28 | BP10: 86 | BQ10: 579.94 | BR10: 578.88 | BS10: =SUM(BP10:BR10) -> 1244.82 | BT10: =450+44.9 -> 494.9 | BU10: =232.06-5-20 -> 207.06 | BV10: 770.7 | BW10: =SUM(BT10:BV10) -> 1472.66 | BX10: 502.69 | BY10: 68.26 | BZ10: 1044.82 | CA10: =SUM(BX10:BZ10) -> 1615.77 | CB10: =BO10+BS10+BW10+CA10 -> 6320.53 | CC10: =CB10/BK10 -> 0.95906851 | CD10: =BK10-CB10 -> 269.75 | CE10: Equpment (all) maintenance & Repairs
A11: Insurance | B11: 4000 | C11: ='budget anual'!C31 -> 1000 | G11: =SUM(D11:F11) -> 0 | K11: =SUM(H11:J11) -> 0 | O11: =SUM(L11:N11) -> 0 | S11: =SUM(P11:R11) -> 0 | T11: =G11+K11+O11+S11 -> 0 | U11: =T11/C11 -> 0 | V11: =C11-T11 -> 1000 | W11: ='budget anual'!D31 -> 1000 | AA11: =SUM(X11:Z11) -> 0 | AE11: =SUM(AB11:AD11) -> 0 | AH11: 77 | AI11: =SUM(AF11:AH11) -> 77 | AM11: =SUM(AJ11:AL11) -> 0 | AN11: =AA11+AE11+AI11+AM11 -> 77 | AO11: =AN11/W11 -> 0.077 | AP11: =(V11+W11)-AN11 -> 1923 | AQ11: ='budget anual'!E31 -> 1000 | AU11: =SUM(AR11:AT11) -> 0 | AY11: =SUM(AV11:AX11) -> 0 | BC11: =SUM(AZ11:BB11) -> 0 | BG11: =SUM(BD11:BF11) -> 0 | BH11: =AU11+AY11+BC11+BG11 -> 0 | BI11: =BH11/AQ11 -> 0 | BJ11: =(AP11+AQ11)-BH11 -> 2923 | BK11: =B11-T11-AN11-BH11 -> 3923 | BO11: =SUM(BL11:BN11) -> 0 | BS11: =SUM(BP11:BR11) -> 0 | BW11: =SUM(BT11:BV11) -> 0 | CA11: =SUM(BX11:BZ11) -> 0 | CB11: =BO11+BS11+BW11+CA11 -> 0 | CC11: =CB11/BK11 -> 0 | CD11: =BK11-CB11 -> 3923 | CE11: Insurance
A12: Legal | B12: 1000 | C12: ='budget anual'!C32 -> 0 | G12: =SUM(D12:F12) -> 0 | K12: =SUM(H12:J12) -> 0 | O12: =SUM(L12:N12) -> 0 | S12: =SUM(P12:R12) -> 0 | T12: =G12+K12+O12+S12 -> 0 | U12: =T12/C12 -> #DIV/0! | V12: =C12-T12 -> 0 | W12: ='budget anual'!D32 -> 250 | AA12: =SUM(X12:Z12) -> 0 | AE12: =SUM(AB12:AD12) -> 0 | AI12: =SUM(AF12:AH12) -> 0 | AK12: 214 | AM12: =SUM(AJ12:AL12) -> 214 | AN12: =AA12+AE12+AI12+AM12 -> 214 | AO12: =AN12/W12 -> 0.856 | AP12: =(V12+W12)-AN12 -> 36 | AQ12: ='budget anual'!E32 -> 500 | AU12: =SUM(AR12:AT12) -> 0 | AW12: 214 | AY12: =SUM(AV12:AX12) -> 214 | BA12: 1760 | BC12: =SUM(AZ12:BB12) -> 1760 | BF12: 350 | BG12: =SUM(BD12:BF12) -> 350 | BH12: =AU12+AY12+BC12+BG12 -> 2324 | BI12: =BH12/AQ12 -> 4.648 | BJ12: =(AP12+AQ12)-BH12 -> -1788 | BK12: =B12-T12-AN12-BH12 -> -1538 | BO12: =SUM(BL12:BN12) -> 0 | BQ12: 550 | BS12: =SUM(BP12:BR12) -> 550 | BW12: =SUM(BT12:BV12) -> 0 | BX12: 450 | CA12: =SUM(BX12:BZ12) -> 450 | CB12: =BO12+BS12+BW12+CA12 -> 1000 | CC12: =CB12/BK12 -> -0.65019506 | CD12: =BK12-CB12 -> -2538 | CE12: Legal
A13: Office & Computer Supplies | B13: 3600 | C13: ='budget anual'!C22+'budget anual'!C23 -> 900 | G13: =SUM(D13:F13) -> 0 | H13: =218.66+169.32+200+0.8+83.88+277.82 -> 950.48 | I13: 11.7 | J13: 211.05 | K13: =SUM(H13:J13) -> 1173.23 | L13: 72.16 | M13: 12.84 | O13: =SUM(L13:N13) -> 85 | P13: 29.62 | Q13: 53.61 | S13: =SUM(P13:R13) -> 83.23 | T13: =G13+K13+O13+S13 -> 1341.46 | U13: =T13/C13 -> 1.4905111 | V13: =C13-T13 -> -441.46 | W13: ='budget anual'!D22+'budget anual'!D23 -> 900 | X13: 199.02 | Y13: 105.93 | Z13: 88.54 | AA13: =SUM(X13:Z13) -> 393.49 | AB13: 133.72 | AC13: 125.71 | AD13: 116.14 | AE13: =SUM(AB13:AD13) -> 375.57 | AF13: 84.6 | AG13: 168.02 | AH13: 181.72 | AI13: =SUM(AF13:AH13) -> 434.34 | AJ13: 151.02 | AK13: 20.38 | AL13: 118.33 | AM13: =SUM(AJ13:AL13) -> 289.73 | AN13: =AA13+AE13+AI13+AM13 -> 1493.13 | AO13: =AN13/W13 -> 1.6590333 | AP13: =(V13+W13)-AN13 -> -1034.59 | AQ13: ='budget anual'!E22+'budget anual'!E23 -> 900 | AT13: 48.77 | AU13: =SUM(AR13:AT13) -> 48.77 | AV13: 196.81 | AW13: 217.06 | AX13: 283.4 | AY13: =SUM(AV13:AX13) -> 697.27 | AZ13: 315.98 | BA13: 176.23 | BB13: 301.41 | BC13: =SUM(AZ13:BB13) -> 793.62 | BD13: 178.2 | BE13: 191.31 | BG13: =SUM(BD13:BF13) -> 369.51 | BH13: =AU13+AY13+BC13+BG13 -> 1909.17 | BI13: =BH13/AQ13 -> 2.1213 | BJ13: =(AP13+AQ13)-BH13 -> -2043.76 | BK13: =B13-T13-AN13-BH13 -> -1143.76 | BL13: 279.73 | BM13: 307.5 | BN13: 212.28 | BO13: =SUM(BL13:BN13) -> 799.51 | BP13: 216.79 | BQ13: 262.09 | BR13: 117.34 | BS13: =SUM(BP13:BR13) -> 596.22 | BT13: 354.06 | BU13: 535.03 | BV13: 207.94 | BW13: =SUM(BT13:BV13) -> 1097.03 | BX13: 370.5 | BY13: 4.28 | BZ13: 87.44 | CA13: =SUM(BX13:BZ13) -> 462.22 | CB13: =BO13+BS13+BW13+CA13 -> 2954.98 | CC13: =CB13/BK13 -> -2.5835665 | CD13: =BK13-CB13 -> -4098.74 | CE13: Office & Computer Supplies
A14: Rent & Utilities | B14: 62400 | C14: ='budget anual'!C25 -> 15600 | G14: =SUM(D14:F14) -> 0 | H14: 3600 | I14: 1200 | J14: 11000 | K14: =SUM(H14:J14) -> 15800 | O14: =SUM(L14:N14) -> 0 | S14: =SUM(P14:R14) -> 0 | T14: =G14+K14+O14+S14 -> 15800 | U14: =T14/C14 -> 1.0128205 | V14: =C14-T14 -> -200 | W14: ='budget anual'!D25 -> 15600 | Y14: 1400 | Z14: 1400 | AA14: =SUM(X14:Z14) -> 2800 | AB14: 1400 | AC14: 1400 | AD14: 1400 | AE14: =SUM(AB14:AD14) -> 4200 | AF14: 1400 | AG14: 1400 | AH14: 1400 | AI14: =SUM(AF14:AH14) -> 4200 | AJ14: 1400 | AK14: 1400 | AL14: 1400 | AM14: =SUM(AJ14:AL14) -> 4200 | AN14: =AA14+AE14+AI14+AM14 -> 15400 | AO14: =AN14/W14 -> 0.98717949 | AP14: =(V14+W14)-AN14 -> 0 | AQ14: ='budget anual'!E25 -> 15600 | AR14: 1400 | AS14: 1400 | AT14: 1400 | AU14: =SUM(AR14:AT14) -> 4200 | AV14: =1400+2343 -> 3743 | AW14: =49.21+1400 -> 1449.21 | AX14: 1400 | AY14: =SUM(AV14:AX14) -> 6592.21 | AZ14: 1400 | BA14: 1400 | BB14: 1400 | BC14: =SUM(AZ14:BB14) -> 4200 | BD14: 1400 | BE14: 1400 | BF14: 1400 | BG14: =SUM(BD14:BF14) -> 4200 | BH14: =AU14+AY14+BC14+BG14 -> 19192.21 | BI14: =BH14/AQ14 -> 1.2302699 | BJ14: =(AP14+AQ14)-BH14 -> -3592.21 | BK14: =B14-T14-AN14-BH14 -> 12007.79 | BL14: 1400 | BM14: 1400 | BN14: 1400 | BO14: =SUM(BL14:BN14) -> 4200 | BP14: 1400 | BQ14: 1400 | BR14: 1400 | BS14: =SUM(BP14:BR14) -> 4200 | BT14: 1400 | BU14: 1400 | BV14: 1400 | BW14: =SUM(BT14:BV14) -> 4200 | BX14: 1400 | BY14: 1400 | BZ14: 1400 | CA14: =SUM(BX14:BZ14) -> 4200 | CB14: =BO14+BS14+BW14+CA14 -> 16800 | CC14: =CB14/BK14 -> 1.3990918 | CD14: =BK14-CB14 -> -4792.21 | CE14: Rent & Utilities
B15: =SUM(B4:B14) -> 1056146.8 | C15: =SUM(C4:C14) -> #REF! | D15: =SUM(D4:D14) -> 0 | E15: =SUM(E4:E14) -> 10983.64 | F15: =SUM(F4:F14) -> 14515.82 | G15: =SUM(G4:G14) -> 25499.46 | H15: =SUM(H4:H14) -> 32171.93 | I15: =SUM(I4:I14) -> 21537.9 | ... T15: =SUM(T4:T14) -> 230216.46 | U15: =T15/C15 -> #REF! | V15: =SUM(V4:V14) -> #REF! | W15: =SUM(W4:W14) -> #REF! | X15: =SUM(X4:X14) -> 20531.94 | Y15: =SUM(Y4:Y14) -> 18787.12 | Z15: =SUM(Z4:Z14) -> 18902.13 | AA15: =SUM(AA4:AA14) -> 58221.19 | AB15: =SUM(AB4:AB14) -> 24392.12 | AC15: =SUM(AC4:AC14) -> 18989.99 | ... AN15: =SUM(AN4:AN14) -> 251458.9 | AO15: =AN15/W15 -> #REF! | AP15: =SUM(AP4:AP14) -> #REF! | AQ15: =SUM(AQ4:AQ14) -> #REF! | AR15: =SUM(AR4:AR14) -> 19298.78 | AS15: =SUM(AS4:AS14) -> 27732.67 | AT15: =SUM(AT4:AT14) -> 11310.73 | AU15: =SUM(AU4:AU14) -> 58342.18 | AV15: =SUM(AV4:AV14) -> 16863.5 | AW15: =SUM(AW4:AW14) -> 12508.1 | ... BH15: =SUM(BH4:BH14) -> 186667.89 | BI15: =BH15/AQ15 -> #REF! | BJ15: =SUM(BJ4:BJ14) -> #REF! | BK15: =SUM(BK4:BK14) -> 387803.55 | BL15: =SUM(BL4:BL14) -> 15517 | BM15: =SUM(BM4:BM14) -> 14588.06 | BN15: =SUM(BN4:BN14) -> 18141.82 | BO15: =SUM(BO4:BO14) -> 48246.88 | BP15: =SUM(BP4:BP14) -> 17909.84 | BQ15: =SUM(BQ4:BQ14) -> 15427.09 | ... CB15: =SUM(CB4:CB14) -> 218429.97 | CC15: =CB15/BK15 -> 0.56324902 | CD15: =SUM(CD4:CD14) -> 169373.58
A16: Output 1: Education | CE16: Output 1: Education
A17: Translation to Indigenous Languages | B17: 0 | C17: 0 | G17: =SUM(D17:F17) -> 0 | K17: =SUM(H17:J17) -> 0 | O17: =SUM(L17:N17) -> 0 | S17: =SUM(P17:R17) -> 0 | T17: =G17+K17+O17+S17 -> 0 | U17: =T17/C17 -> #DIV/0! | V17: =C17-T17 -> 0 | W17: 0 | AA17: =SUM(X17:Z17) -> 0 | AE17: =SUM(AB17:AD17) -> 0 | AI17: =SUM(AF17:AH17) -> 0 | AM17: =SUM(AJ17:AL17) -> 0 | AN17: =AA17+AE17+AI17+AM17 -> 0 | AP17: =(V17+W17)-AN17 -> 0 | AQ17: 0 | AU17: =SUM(AR17:AT17) -> 0 | AY17: =SUM(AV17:AX17) -> 0 | BC17: =SUM(AZ17:BB17) -> 0 | BG17: =SUM(BD17:BF17) -> 0 | BH17: =AU17+AY17+BC17+BG17 -> 0 | BJ17: =(AP17+AQ17)-BH17 -> 0 | BK17: =B17-T17-AN17-BH17 -> 0 | BO17: =SUM(BL17:BN17) -> 0 | BS17: =SUM(BP17:BR17) -> 0 | BW17: =SUM(BT17:BV17) -> 0 | CA17: =SUM(BX17:BZ17) -> 0 | CB17: =BO17+BS17+BW17+CA17 -> 0 | CD17: =BK17-CB17 -> 0 | CE17: Translation to Indigenous Languages
A18: Materials, Design & Printing | B18: 57972.12 | C18: ='budget anual'!C48 -> #REF! | F18: 137.3 | G18: =SUM(D18:F18) -> 137.3 | K18: =SUM(H18:J18) -> 0 | L18: 214.72 | O18: =SUM(L18:N18) -> 214.72 | Q18: 20.33 | R18: 1000 | S18: =SUM(P18:R18) -> 1020.33 | T18: =G18+K18+O18+S18 -> 1372.35 | U18: =T18/C18 -> #REF! | V18: =C18-T18 -> #REF! | W18: ='budget anual'!D48 -> #REF! | Z18: 527.3 | AA18: =SUM(X18:Z18) -> 527.3 | AD18: 11208.25 | AE18: =SUM(AB18:AD18) -> 11208.25 | AF18: 14692.25 | AG18: 4.99 | AI18: =SUM(AF18:AH18) -> 14697.24 | AJ18: 400 | AL18: 10539.5 | AM18: =SUM(AJ18:AL18) -> 10939.5 | AN18: =AA18+AE18+AI18+AM18 -> 37372.29 | AP18: =(V18+W18)-AN18 -> #REF! | AQ18: ='budget anual'!E48 -> 19226.86 | AT18: 10539.5 | AU18: =SUM(AR18:AT18) -> 10539.5 | AW18: 489.53 | AY18: =SUM(AV18:AX18) -> 489.53 | AZ18: 3849.33 | BA18: 4338.85 | BB18: 262.15 | BC18: =SUM(AZ18:BB18) -> 8450.33 | BG18: =SUM(BD18:BF18) -> 0 | BH18: =AU18+AY18+BC18+BG18 -> 19479.36 | BJ18: =(AP18+AQ18)-BH18 -> #REF! | BK18: =B18-T18-AN18-BH18 -> -251.88 | BO18: =SUM(BL18:BN18) -> 0 | BS18: =SUM(BP18:BR18) -> 0 | BW18: =SUM(BT18:BV18) -> 0 | CA18: =SUM(BX18:BZ18) -> 0 | CB18: =BO18+BS18+BW18+CA18 -> 0 | CD18: =BK18-CB18 -> -251.88 | CE18: Materials, Design & Printing
A19: 1.6 Local Workshops venue and logistics | B19: 64000 | C19: ='budget anual'!C52 -> #REF! | G19: =SUM(D19:F19) -> 0 | K19: =SUM(H19:J19) -> 0 | N19: 1500 | O19: =SUM(L19:N19) -> 1500 | P19: 10472.89 | Q19: -287.15 | R19: 6365 | S19: =SUM(P19:R19) -> 16550.74 | T19: =G19+K19+O19+S19 -> 18050.74 | U19: =T19/C19 -> #REF! | V19: =C19-T19 -> #REF! | W19: ='budget anual'!D52 -> #REF! | X19: 12085.61 | AA19: =SUM(X19:Z19) -> 12085.61 | AE19: =SUM(AB19:AD19) -> 0 | AH19: 15896.29 | AI19: =SUM(AF19:AH19) -> 15896.29 | AJ19: -277.02 | AM19: =SUM(AJ19:AL19) -> -277.02 | AN19: =AA19+AE19+AI19+AM19 -> 27704.88 | AO19: =AN19/W19 -> #REF! | AP19: =(V19+W19)-AN19 -> #REF! | AQ19: ='budget anual'!E52 -> 18244.38 | AR19: 24098.08 | AS19: 5688.42 | AT19: 630.46 | AU19: =SUM(AR19:AT19) -> 30416.96 | AY19: =SUM(AV19:AX19) -> 0 | AZ19: 130 | BB19: 147.17 | BC19: =SUM(AZ19:BB19) -> 277.17 | BD19: 1584.65 | BG19: =SUM(BD19:BF19) -> 1584.65 | BH19: =AU19+AY19+BC19+BG19 -> 32278.78 | BJ19: =(AP19+AQ19)-BH19 -> #REF! | BK19: =B19-T19-AN19-BH19 -> -14034.4 | BL19: -482.73 | BO19: =SUM(BL19:BN19) -> -482.73 | BQ19: 1000 | BR19: 2491.98 | BS19: =SUM(BP19:BR19) -> 3491.98 | BW19: =SUM(BT19:BV19) -> 0 | CA19: =SUM(BX19:BZ19) -> 0 | CB19: =BO19+BS19+BW19+CA19 -> 3009.25 | CD19: =BK19-CB19 -> -17043.65 | CE19: 1.6 Local Workshops venue and logistics
A20: 1.7 Short Term Education Consultant Support | B20: 18200 | C20: ='budget anual'!C53 -> 0 | V20: 0 | W20: ='budget anual'!D53 -> 15500 | AF20: 3100 | AG20: 3875 | AI20: =SUM(AF20:AH20) -> 6975 | AJ20: 8525 | AM20: =SUM(AJ20:AL20) -> 8525 | AN20: =AA20+AE20+AI20+AM20 -> 15500 | AP20: =(V20+W20)-AN20 -> 0 | AQ20: ='budget anual'!E53 -> 2700 | AZ20: 600 | BA20: 800 | BB20: 900 | BC20: =SUM(AZ20:BB20) -> 2300 | BD20: 400 | BG20: =SUM(BD20:BF20) -> 400 | BH20: =AU20+AY20+BC20+BG20 -> 2700 | BJ20: =(AP20+AQ20)-BH20 -> 0 | BK20: =B20-T20-AN20-BH20 -> 0 | BO20: =SUM(BL20:BN20) -> 0 | BS20: =SUM(BP20:BR20) -> 0 | BW20: =SUM(BT20:BV20) -> 0 | CA20: =SUM(BX20:BZ20) -> 0 | CB20: =BO20+BS20+BW20+CA20 -> 0 | CD20: =BK20-CB20 -> 0 | CE20: 1.7 Short Term Education Consultant Support
A21: Implementation of EpC Activities: | AM21: =SUM(AJ21:AL21) -> 0 | AN21: =AA21+AE21+AI21+AM21 -> 0 | BG21: =SUM(BD21:BF21) -> 0 | BH21: =AU21+AY21+BC21+BG21 -> 0 | BJ21: =(AP21+AQ21)-BH21 -> 0 | BK21: =B21-T21-AN21-BH21 -> 0 | BO21: =SUM(BL21:BN21) -> 0 | BS21: =SUM(BP21:BR21) -> 0 | BW21: =SUM(BT21:BV21) -> 0 | CA21: =SUM(BX21:BZ21) -> 0 | CB21: =BO21+BS21+BW21+CA21 -> 0 | CD21: =BK21-CB21 -> 0 | CE21: Implementation of EpC Activities:
A22: Fey Alegria Direct Activities | B22: 210250 | C22: ='budget anual'!C56 -> #REF! | G22: =SUM(D22:F22) -> 0 | K22: =SUM(H22:J22) -> 0 | O22: =SUM(L22:N22) -> 0 | Q22: 97853.85 | S22: =SUM(P22:R22) -> 97853.85 | T22: =G22+K22+O22+S22 -> 97853.85 | U22: =T22/C22 -> #REF! | V22: =C22-T22 -> #REF! | W22: ='budget anual'!D56 -> #REF! | AA22: =SUM(X22:Z22) -> 0 | AE22: =SUM(AB22:AD22) -> 0 | AI22: =SUM(AF22:AH22) -> 0 | AK22: 33094.07 | AL22: 1643.02 | AM22: =SUM(AJ22:AL22) -> 34737.09 | AN22: =AA22+AE22+AI22+AM22 -> 34737.09 | AO22: =AN22/W22 -> #REF! | AP22: =(V22+W22)-AN22 -> #REF! | AQ22: ='budget anual'!E56 -> #REF! | AR22: 1995.56 | AS22: 1273.02 | AT22: 2097.46 | AU22: =SUM(AR22:AT22) -> 5366.04 | AV22: 882.67 | AW22: 932.67 | AX22: 1024.33 | AY22: =SUM(AV22:AX22) -> 2839.67 | AZ22: 951 | BA22: 24080.55 | BB22: 1176 | BC22: =SUM(AZ22:BB22) -> 26207.55 | BD22: 1223.73 | BE22: 1244.18 | BF22: =1326+15000 -> 16326 | BG22: =SUM(BD22:BF22) -> 18793.91 | BH22: =AU22+AY22+BC22+BG22 -> 53207.17 | BI22: =BH22/AQ22 -> #REF! | BJ22: =(AP22+AQ22)-BH22 -> #REF! | BK22: =B22-T22-AN22-BH22 -> 24451.89 | BL22: 1322.71 | BM22: =25300+1275.98 -> 26575.98 | BN22: 1286 | BO22: =SUM(BL22:BN22) -> 29184.69 | BP22: 1321 | BQ22: 6334.46 | BR22: =1371+16694.76 -> 18065.76 | BS22: =SUM(BP22:BR22) -> 25721.22 | BT22: 1371 | BU22: 1371 | BV22: 1372.57 | BW22: =SUM(BT22:BV22) -> 4114.57 | BX22: =1321+4400+1315.03 -> 7036.03 | BY22: 1583.52 | BZ22: 2314.85 | CA22: =SUM(BX22:BZ22) -> 10934.4 | CB22: =BO22+BS22+BW22+CA22 -> 69954.88 | CC22: =CB22/BK22 -> 2.8609191 | CD22: =BK22-CB22 -> -45502.99 | CE22: Fey Alegria Direct Activities
A23: Subcontract: APRODISO (Darién y Comarca Emberá) | B23: 21282.5 | C23: ='budget anual'!C57 -> 0 | G23: =SUM(D23:F23) -> 0 | K23: =SUM(H23:J23) -> 0 | O23: =SUM(L23:N23) -> 0 | S23: =SUM(P23:R23) -> 0 | T23: =G23+K23+O23+S23 -> 0 | U23: 0 | V23: =C23-T23 -> 0 | W23: ='budget anual'!D57 -> 21282.5 | X23: 18360 | AA23: =SUM(X23:Z23) -> 18360 | AE23: =SUM(AB23:AD23) -> 0 | AI23: =SUM(AF23:AH23) -> 0 | AK23: 2940 | AL23: -17.5 | AM23: =SUM(AJ23:AL23) -> 2922.5 | AN23: =AA23+AE23+AI23+AM23 -> 21282.5 | AO23: 0 | AP23: =(V23+W23)-AN23 -> 0 | AQ23: ='budget anual'!E57 -> 0 | AU23: =SUM(AR23:AT23) -> 0 | AY23: =SUM(AV23:AX23) -> 0 | BC23: =SUM(AZ23:BB23) -> 0 | BG23: =SUM(BD23:BF23) -> 0 | BH23: =AU23+AY23+BC23+BG23 -> 0 | BI23: 0 | BJ23: =(AP23+AQ23)-BH23 -> 0 | BK23: =B23-T23-AN23-BH23 -> 0 | BO23: =SUM(BL23:BN23) -> 0 | BS23: =SUM(BP23:BR23) -> 0 | BW23: =SUM(BT23:BV23) -> 0 | CA23: =SUM(BX23:BZ23) -> 0 | CB23: =BO23+BS23+BW23+CA23 -> 0 | CC23: 0 | CD23: =BK23-CB23 -> 0 | CE23: Subcontract: APRODISO (Darién y Comarca Emberá)
A24: Subcontract: APROTENG (Bocas del Toro) | B24: 84000 | C24: ='budget anual'!C58 -> #REF! | G24: =SUM(D24:F24) -> 0 | K24: =SUM(H24:J24) -> 0 | O24: =SUM(L24:N24) -> 0 | S24: =SUM(P24:R24) -> 0 | T24: =G24+K24+O24+S24 -> 0 | U24: 0 | V24: =C24-T24 -> #REF! | W24: ='budget anual'!D58 -> #REF! | X24: 13917 | AA24: =SUM(X24:Z24) -> 13917 | AE24: =SUM(AB24:AD24) -> 0 | AH24: 10000 | AI24: =SUM(AF24:AH24) -> 10000 | AM24: =SUM(AJ24:AL24) -> 0 | AN24: =AA24+AE24+AI24+AM24 -> 23917 | AO24: 0 | AP24: =(V24+W24)-AN24 -> #REF! | AQ24: ='budget anual'!E58 -> #REF! | AT24: 12000 | AU24: =SUM(AR24:AT24) -> 12000 | AX24: 7500 | AY24: =SUM(AV24:AX24) -> 7500 | BA24: 12000 | BC24: =SUM(AZ24:BB24) -> 12000 | BD24: 8500 | BF24: 12550 | BG24: =SUM(BD24:BF24) -> 21050 | BH24: =AU24+AY24+BC24+BG24 -> 52550 | BI24: 0 | BJ24: =(AP24+AQ24)-BH24 -> #REF! | BK24: =B24-T24-AN24-BH24 -> 7533 | BO24: =SUM(BL24:BN24) -> 0 | BP24: 1350 | BQ24: =5170.5-300 -> 4870.5 | BR24: 2488.17 | BS24: =SUM(BP24:BR24) -> 8708.67 | BT24: 6138.38 | BU24: 5071.88 | BV24: 3418.9 | BW24: =SUM(BT24:BV24) -> 14629.16 | BX24: 2480.46 | CA24: =SUM(BX24:BZ24) -> 2480.46 | CB24: =BO24+BS24+BW24+CA24 -> 25818.29 | CC24: 0 | CD24: =BK24-CB24 -> -18285.29 | CE24: Subcontract: APROTENG (Bocas del Toro)
A25: EducaFuturo - Darién y Comarca Emberá | B25: 99200 | AP25: =(V25+W25)-AN25 -> 0 | AQ25: ='budget anual'!E62 -> 28110.13 | AT25: =2699.54-86.89+1000 -> 3612.65 | AU25: =SUM(AR25:AT25) -> 3612.65 | AV25: =1461.47+2252.11 -> 3713.58 | AW25: =1972.88+4894.71 -> 6867.59 | AX25: =2319.38+1400.89 -> 3720.27 | AY25: =SUM(AV25:AX25) -> 14301.44 | AZ25: =3412.5+1959.02 -> 5371.52 | BA25: =2754.17+2545.89 -> 5300.06 | BB25: =3866.67+1970.04 -> 5836.71 | BC25: =SUM(AZ25:BB25) -> 16508.29 | BD25: =3077.08+1169.8 -> 4246.88 | BE25: =3650+2318.7 -> 5968.7 | BF25: =2983.33+2769.45 -> 5752.78 | BG25: =SUM(BD25:BF25) -> 15968.36 | BH25: =AU25+AY25+BC25+BG25 -> 50390.74 | BJ25: =(AP25+AQ25)-BH25 -> -22280.61 | BK25: =B25-T25-AN25-BH25 -> 48809.26 | BL25: 2415.7 | BM25: 2475.2 | BN25: 2314.45 | BO25: =SUM(BL25:BN25) -> 7205.35 | BP25: =1570.56+3626.69 -> 5197.25 | BQ25: =2941.67+2365.7 -> 5307.37 | BR25: 4813.63 | BS25: =SUM(BP25:BR25) -> 15318.25 | BT25: 3953.03 | BU25: =4936+500 -> 5436 | BV25: 5465.71 | BW25: =SUM(BT25:BV25) -> 14854.74 | BX25: 3704.06 | BY25: 2539.11 | BZ25: -0.01 | CA25: =SUM(BX25:BZ25) -> 6243.16 | CB25: =BO25+BS25+BW25+CA25 -> 43621.5 | CD25: =BK25-CB25 -> 5187.76 | CE25: EducaFuturo - Darién y Comarca Emberá
B26: =SUM(B16:B25) -> 554904.62 | C26: =SUM(C16:C25) -> #REF! | D26: =SUM(D16:D25) -> 0 | E26: =SUM(E16:E25) -> 0 | F26: =SUM(F16:F25) -> 137.3 | G26: =SUM(G16:G25) -> 137.3 | H26: =SUM(H16:H25) -> 0 | I26: =SUM(I16:I25) -> 0 | ... T26: =SUM(T16:T25) -> 117276.94 | U26: =T26/C26 -> #REF! | V26: =SUM(V16:V25) -> #REF! | W26: =SUM(W16:W25) -> #REF! | X26: =SUM(X16:X25) -> 44362.61 | Y26: =SUM(Y16:Y25) -> 0 | Z26: =SUM(Z16:Z25) -> 527.3 | AA26: =SUM(AA16:AA25) -> 44889.91 | AB26: =SUM(AB16:AB25) -> 0 | AC26: =SUM(AC16:AC25) -> 0 | ... AN26: =SUM(AN16:AN25) -> 160513.76 | AO26: =AN26/W26 -> #REF! | AP26: =SUM(AP16:AP25) -> #REF! | AQ26: =SUM(AQ16:AQ25) -> #REF! | AR26: =SUM(AR16:AR25) -> 26093.64 | AS26: =SUM(AS16:AS25) -> 6961.44 | AT26: =SUM(AT16:AT25) -> 28880.07 | AU26: =SUM(AU16:AU25) -> 61935.15 | AV26: =SUM(AV16:AV25) -> 4596.25 | AW26: =SUM(AW16:AW25) -> 8289.79 | ... BH26: =SUM(BH16:BH25) -> 210606.05 | BI26: =BH26/AQ26 -> #REF! | BJ26: =SUM(BJ16:BJ25) -> #REF! | BK26: =SUM(BK16:BK25) -> 66507.87 | BL26: =SUM(BL16:BL25) -> 3255.68 | BM26: =SUM(BM16:BM25) -> 29051.18 | BN26: =SUM(BN16:BN25) -> 3600.45 | BO26: =SUM(BO16:BO25) -> 35907.31 | BP26: =SUM(BP16:BP25) -> 7868.25 | BQ26: =SUM(BQ16:BQ25) -> 17512.33 | ... CB26: =SUM(CB16:CB25) -> 142403.92 | CC26: =CB26/BK26 -> 2.1411589 | CD26: =SUM(CD16:CD25) -> -75896.05
A27: Output 2: Livelihoods | CE27: Output 2: Livelihoods
A28: 2.1 Value Chain Analysis | B28: 4000 | C28: ='budget anual'!C72 -> 0 | G28: =SUM(D28:F28) -> 0 | K28: =SUM(H28:J28) -> 0 | O28: =SUM(L28:N28) -> 0 | S28: =SUM(P28:R28) -> 0 | T28: =G28+K28+O28+S28 -> 0 | U28: =T28/C28 -> #DIV/0! | V28: =C28-T28 -> 0 | W28: ='budget anual'!D72 -> 0 | AA28: =SUM(X28:Z28) -> 0 | AE28: =SUM(AB28:AD28) -> 0 | AI28: =SUM(AF28:AH28) -> 0 | AM28: =SUM(AJ28:AL28) -> 0 | AN28: =AA28+AE28+AI28+AM28 -> 0 | AP28: =(V28+W28)-AN28 -> 0 | AQ28: ='budget anual'!E72 -> 0 | AU28: =SUM(AR28:AT28) -> 0 | AY28: =SUM(AV28:AX28) -> 0 | BC28: =SUM(AZ28:BB28) -> 0 | BG28: =SUM(BD28:BF28) -> 0 | BH28: =AU28+AY28+BC28+BG28 -> 0 | BJ28: =(AP28+AQ28)-BH28 -> 0 | BK28: =B28-T28-AN28-BH28 -> 4000 | BO28: =SUM(BL28:BN28) -> 0 | BQ28: 500 | BR28: 541.06 | BS28: =SUM(BP28:BR28) -> 1041.06 | BT28: 348.11 | BW28: =SUM(BT28:BV28) -> 348.11 | BX28: -240.25 | CA28: =SUM(BX28:BZ28) -> -240.25 | CB28: =BO28+BS28+BW28+CA28 -> 1148.92 | CD28: =BK28-CB28 -> 2851.08 | CE28: 2.1 Value Chain Analysis
A29: 2.2 Linking Households to Livelihood Programs | B29: 3525 | C29: ='budget anual'!C73 -> #REF! | G29: =SUM(D29:F29) -> 0 | K29: =SUM(H29:J29) -> 0 | O29: =SUM(L29:N29) -> 0 | S29: =SUM(P29:R29) -> 0 | T29: =G29+K29+O29+S29 -> 0 | U29: =T29/C29 -> #REF! | V29: =C29-T29 -> #REF! | W29: ='budget anual'!D73 -> #REF! | AA29: =SUM(X29:Z29) -> 0 | AE29: =SUM(AB29:AD29) -> 0 | AI29: =SUM(AF29:AH29) -> 0 | AM29: =SUM(AJ29:AL29) -> 0 | AN29: =AA29+AE29+AI29+AM29 -> 0 | AO29: =AN29/W29 -> #REF! | AP29: =(V29+W29)-AN29 -> #REF! | AQ29: ='budget anual'!E73 -> #REF! | AU29: =SUM(AR29:AT29) -> 0 | AX29: 360 | AY29: =SUM(AV29:AX29) -> 360 | BA29: 213.29 | BC29: =SUM(AZ29:BB29) -> 213.29 | BG29: =SUM(BD29:BF29) -> 0 | BH29: =AU29+AY29+BC29+BG29 -> 573.29 | BI29: =BH29/AQ29 -> #REF! | BJ29: =(AP29+AQ29)-BH29 -> #REF! | BK29: =B29-T29-AN29-BH29 -> 2951.71 | BL29: -108.5 | BO29: =SUM(BL29:BN29) -> -108.5 | BS29: =SUM(BP29:BR29) -> 0 | BW29: =SUM(BT29:BV29) -> 0 | CA29: =SUM(BX29:BZ29) -> 0 | CB29: =BO29+BS29+BW29+CA29 -> -108.5 | CC29: =CB29/BK29 -> -0.036758354 | CD29: =BK29-CB29 -> 3060.21 | CE29: 2.2 Linking Households to Livelihood Programs
A30: 2.3 Technical Assistance to Develop Links to Business Activities | B30: 7500 | C30: ='budget anual'!C74 -> #REF! | T30: =G30+K30+O30+S30 -> 0 | V30: =C30-T30 -> #REF! | W30: ='budget anual'!D74 -> #REF! | AN30: =AA30+AE30+AI30+AM30 -> 0 | AP30: =(V30+W30)-AN30 -> #REF! | AQ30: ='budget anual'!E74 -> #REF! | AS30: 500 | AT30: 1400 | AU30: =SUM(AR30:AT30) -> 1900 | AY30: =SUM(AV30:AX30) -> 0 | BC30: =SUM(AZ30:BB30) -> 0 | BD30: 1000 | BF30: 1650 | BG30: =SUM(BD30:BF30) -> 2650 | BH30: =AU30+AY30+BC30+BG30 -> 4550 | BI30: =BH30/AQ30 -> #REF! | BJ30: =(AP30+AQ30)-BH30 -> #REF! | BK30: =B30-T30-AN30-BH30 -> 2950 | BL30: 2226.28 | BM30: 30 | BO30: =SUM(BL30:BN30) -> 2256.28 | BS30: =SUM(BP30:BR30) -> 0 | BW30: =SUM(BT30:BV30) -> 0 | BX30: -1171.43 | CA30: =SUM(BX30:BZ30) -> -1171.43 | CB30: =BO30+BS30+BW30+CA30 -> 1084.85 | CC30: =CB30/BK30 -> 0.36774576 | CD30: =BK30-CB30 -> 1865.15 | CE30: 2.3 Technical Assistance to Develop Links to Business Activities
A31: Literacy fund | B31: 1000 | BK31: =B31-T31-AN31-BH31 -> 1000 | BU31: 124.68 | BV31: 106.78 | BW31: =SUM(BT31:BV31) -> 231.46 | BX31: 1500 | CA31: =SUM(BX31:BZ31) -> 1500 | CB31: =BO31+BS31+BW31+CA31 -> 1731.46 | CD31: =BK31-CB31 -> -731.46 | CE31: Literacy fund
A32: Subcontract: Fe y Alegría (Comarca Ngäbe y Colón) | B32: 35000 | C32: ='budget anual'!C79 -> 0 | T32: =G32+K32+O32+S32 -> 0 | V32: =C32-T32 -> 0 | W32: ='budget anual'!D79 -> 0 | AN32: =AA32+AE32+AI32+AM32 -> 0 | AP32: =(V32+W32)-AN32 -> 0 | AQ32: ='budget anual'!E79 -> 0 | AU32: =SUM(AR32:AT32) -> 0 | AY32: =SUM(AV32:AX32) -> 0 | BC32: =SUM(AZ32:BB32) -> 0 | BG32: =SUM(BD32:BF32) -> 0 | BH32: =AU32+AY32+BC32+BG32 -> 0 | BJ32: =(AP32+AQ32)-BH32 -> 0 | BK32: =B32-T32-AN32-BH32 -> 35000 | BO32: =SUM(BL32:BN32) -> 0 | BR32: 25000 | BS32: =SUM(BP32:BR32) -> 25000 | BW32: =SUM(BT32:BV32) -> 0 | CA32: =SUM(BX32:BZ32) -> 0 | CB32: =BO32+BS32+BW32+CA32 -> 25000 | CD32: =BK32-CB32 -> 10000 | CE32: Subcontract: Fe y Alegría (Comarca Ngäbe y Colón)
A33: Subcontract: APRODISO (Darién y Comarca Emberá) | B33: 0 | C33: ='budget anual'!C80 -> 0 | T33: =G33+K33+O33+S33 -> 0 | V33: =C33-T33 -> 0 | W33: ='budget anual'!D80 -> 0 | AN33: =AA33+AE33+AI33+AM33 -> 0 | AP33: =(V33+W33)-AN33 -> 0 | AQ33: ='budget anual'!E80 -> 0 | AU33: =SUM(AR33:AT33) -> 0 | AY33: =SUM(AV33:AX33) -> 0 | BC33: =SUM(AZ33:BB33) -> 0 | BG33: =SUM(BD33:BF33) -> 0 | BH33: =AU33+AY33+BC33+BG33 -> 0 | BJ33: =(AP33+AQ33)-BH33 -> 0 | BK33: =B33-T33-AN33-BH33 -> 0 | BO33: =SUM(BL33:BN33) -> 0 | BS33: =SUM(BP33:BR33) -> 0 | BW33: =SUM(BT33:BV33) -> 0 | CA33: =SUM(BX33:BZ33) -> 0 | CB33: =BO33+BS33+BW33+CA33 -> 0 | CD33: =BK33-CB33 -> 0 | CE33: Subcontract: APRODISO (Darién y Comarca Emberá)
A34: Subcontract: APROTENG (Bocas del Toro) | B34: 12050 | C34: ='budget anual'!C81 -> 0 | G34: =SUM(D34:F34) -> 0 | K34: =SUM(H34:J34) -> 0 | O34: =SUM(L34:N34) -> 0 | S34: =SUM(P34:R34) -> 0 | T34: =G34+K34+O34+S34 -> 0 | U34: =T34/C34 -> #DIV/0! | V34: =C34-T34 -> 0 | W34: ='budget anual'!D81 -> 0 | AA34: =SUM(X34:Z34) -> 0 | AE34: =SUM(AB34:AD34) -> 0 | AI34: =SUM(AF34:AH34) -> 0 | AM34: =SUM(AJ34:AL34) -> 0 | AN34: =AA34+AE34+AI34+AM34 -> 0 | AO34: =AN34/W34 -> #DIV/0! | AP34: =(V34+W34)-AN34 -> 0 | AQ34: ='budget anual'!E81 -> 1500 | AU34: =SUM(AR34:AT34) -> 0 | AY34: =SUM(AV34:AX34) -> 0 | BC34: =SUM(AZ34:BB34) -> 0 | BD34: 1500 | BG34: =SUM(BD34:BF34) -> 1500 | BH34: =AU34+AY34+BC34+BG34 -> 1500 | BI34: =BH34/AQ34 -> 1 | BJ34: =(AP34+AQ34)-BH34 -> 0 | BK34: =B34-T34-AN34-BH34 -> 10550 | BO34: =SUM(BL34:BN34) -> 0 | BR34: 853.25 | BS34: =SUM(BP34:BR34) -> 853.25 | BT34: 1033.95 | BU34: 1873.5 | BV34: =8168.4+283 -> 8451.4 | BW34: =SUM(BT34:BV34) -> 11358.85 | BX34: 1061 | BZ34: 80 | CA34: =SUM(BX34:BZ34) -> 1141 | CB34: =BO34+BS34+BW34+CA34 -> 13353.1 | CC34: =CB34/BK34 -> 1.2656967 | CD34: =BK34-CB34 -> -2803.1 | CE34: Subcontract: APROTENG (Bocas del Toro)
A35: D.2.5.G EducaFuturo Darién & Comarca Emberá | B35: 22050 | C35: 0 | W35: 0 | AQ35: ='budget anual'!E85 -> 40 | BC35: =SUM(AZ35:BB35) -> 0 | BE35: 40 | BG35: =SUM(BD35:BF35) -> 40 | BH35: =AU35+AY35+BC35+BG35 -> 40 | BJ35: =(AP35+AQ35)-BH35 -> 0 | BK35: =B35-T35-AN35-BH35 -> 22010 | BO35: =SUM(BL35:BN35) -> 0 | BS35: =SUM(BP35:BR35) -> 0 | BV35: 18098.62 | BW35: =SUM(BT35:BV35) -> 18098.62 | BX35: -207.31 | BY35: 924.75 | CA35: =SUM(BX35:BZ35) -> 717.44 | CB35: =BO35+BS35+BW35+CA35 -> 18816.06 | CD35: =BK35-CB35 -> 3193.94 | CE35: D.2.5.G EducaFuturo Darién & Comarca Emberá
B36: =SUM(B27:B35) -> 85125 | C36: =SUM(C27:C34) -> #REF! | D36: =SUM(D27:D34) -> 0 | E36: =SUM(E27:E34) -> 0 | F36: =SUM(F27:F34) -> 0 | G36: =SUM(G27:G34) -> 0 | H36: =SUM(H27:H34) -> 0 | I36: =SUM(I27:I34) -> 0 | J36: =SUM(J27:J34) -> 0 | ... T36: =SUM(T27:T34) -> 0 | U36: =T36/C36 -> #REF! | V36: =SUM(V27:V34) -> #REF! | W36: =SUM(W27:W34) -> #REF! | X36: =SUM(X27:X34) -> 0 | Y36: =SUM(Y27:Y34) -> 0 | Z36: =SUM(Z27:Z34) -> 0 | AA36: =SUM(AA27:AA34) -> 0 | AB36: =SUM(AB27:AB34) -> 0 | AC36: =SUM(AC27:AC34) -> 0 | ... AN36: =SUM(AN27:AN34) -> 0 | AO36: =AN36/W36 -> #REF! | AP36: =SUM(AP27:AP34) -> #REF! | AQ36: =SUM(AQ27:AQ35) -> #REF! | AR36: =SUM(AR27:AR34) -> 0 | AS36: =SUM(AS27:AS34) -> 500 | AT36: =SUM(AT27:AT34) -> 1400 | AU36: =SUM(AU27:AU34) -> 1900 | AV36: =SUM(AV27:AV34) -> 0 | AW36: =SUM(AW27:AW34) -> 0 | AX36: =SUM(AX27:AX34) -> 360 | AY36: =SUM(AY27:AY34) -> 360 | ... BA36: =SUM(BA27:BA34) -> 213.29 | BB36: =SUM(BB27:BB35) -> 0 | BC36: =SUM(BC27:BC35) -> 213.29 | BD36: =SUM(BD27:BD35) -> 2500 | BE36: =SUM(BE27:BE35) -> 40 | BF36: =SUM(BF27:BF35) -> 1650 | BG36: =SUM(BG27:BG35) -> 4190 | BH36: =SUM(BH27:BH35) -> 6663.29 | BI36: =BH36/AQ36 -> #REF! | BJ36: =SUM(BJ27:BJ35) -> #REF! | BK36: =SUM(BK27:BK35) -> 78461.71 | BL36: =SUM(BL27:BL35) -> 2117.78 | BM36: =SUM(BM27:BM35) -> 30 | BN36: =SUM(BN27:BN35) -> 0 | BO36: =SUM(BO27:BO35) -> 2147.78 | BP36: =SUM(BP27:BP35) -> 0 | BQ36: =SUM(BQ27:BQ35) -> 500 | ... CB36: =SUM(CB27:CB35) -> 61025.89 | CC36: =CB36/BK36 -> 0.77777925 | CD36: =SUM(CD27:CD35) -> 17435.82
A37: Output 3: Social Protection | CE37: Output 3: Social Protection
A38: Social Protecion Services in Targeted Communities | B38: 250 | C38: ='budget anual'!C88 -> 0 | G38: =SUM(D38:F38) -> 0 | K38: =SUM(H38:J38) -> 0 | O38: =SUM(L38:N38) -> 0 | S38: =SUM(P38:R38) -> 0 | T38: =G38+K38+O38+S38 -> 0 | U38: =T38/C38 -> #DIV/0! | V38: =C38-T38 -> 0 | W38: ='budget anual'!D88 -> 0 | AA38: =SUM(X38:Z38) -> 0 | AE38: =SUM(AB38:AD38) -> 0 | AI38: =SUM(AF38:AH38) -> 0 | AM38: =SUM(AJ38:AL38) -> 0 | AN38: =AA38+AE38+AI38+AM38 -> 0 | AO38: =AN38/W38 -> #DIV/0! | AP38: =(V38+W38)-AN38 -> 0 | AQ38: ='budget anual'!E88 -> 0 | AU38: =SUM(AR38:AT38) -> 0 | AY38: =SUM(AV38:AX38) -> 0 | BC38: =SUM(AZ38:BB38) -> 0 | BG38: =SUM(BD38:BF38) -> 0 | BH38: =AU38+AY38+BC38+BG38 -> 0 | BI38: =BH38/AQ38 -> #DIV/0! | BJ38: =(AP38+AQ38)-BH38 -> 0 | BK38: =B38-T38-AN38-BH38 -> 250 | BO38: =SUM(BL38:BN38) -> 0 | BS38: =SUM(BP38:BR38) -> 0 | BW38: =SUM(BT38:BV38) -> 0 | CA38: =SUM(BX38:BZ38) -> 0 | CB38: =BO38+BS38+BW38+CA38 -> 0 | CC38: =CB38/BK38 -> 0 | CD38: =BK38-CB38 -> 250 | CE38: Social Protecion Services in Targeted Communities
A39: Subcontract: Fe y Alegría (Comarca Ngäbe y Colón) | B39: 4687.5 | C39: ='budget anual'!C89 -> 0 | T39: =G39+K39+O39+S39 -> 0 | V39: =C39-T39 -> 0 | W39: ='budget anual'!D89 -> 0 | AN39: =AA39+AE39+AI39+AM39 -> 0 | AP39: =(V39+W39)-AN39 -> 0 | AQ39: ='budget anual'!E89 -> 0 | BG39: =SUM(BD39:BF39) -> 0 | BH39: =AU39+AY39+BC39+BG39 -> 0 | BJ39: =(AP39+AQ39)-BH39 -> 0 | BK39: =B39-T39-AN39-BH39 -> 4687.5 | BO39: =SUM(BL39:BN39) -> 0 | BR39: 4687.5 | BS39: =SUM(BP39:BR39) -> 4687.5 | BW39: =SUM(BT39:BV39) -> 0 | CA39: =SUM(BX39:BZ39) -> 0 | CB39: =BO39+BS39+BW39+CA39 -> 4687.5 | CD39: =BK39-CB39 -> 0 | CE39: Subcontract: Fe y Alegría (Comarca Ngäbe y Colón)
A40: Subcontract: APRODISO (Darién y Comarca Emberá) | B40: 0 | C40: ='budget anual'!C90 -> 0 | T40: =G40+K40+O40+S40 -> 0 | V40: =C40-T40 -> 0 | W40: ='budget anual'!D90 -> 0 | AN40: =AA40+AE40+AI40+AM40 -> 0 | AP40: =(V40+W40)-AN40 -> 0 | AQ40: ='budget anual'!E90 -> 0 | BG40: =SUM(BD40:BF40) -> 0 | BH40: =AU40+AY40+BC40+BG40 -> 0 | BJ40: =(AP40+AQ40)-BH40 -> 0 | BK40: =B40-T40-AN40-BH40 -> 0 | BO40: =SUM(BL40:BN40) -> 0 | BS40: =SUM(BP40:BR40) -> 0 | BW40: =SUM(BT40:BV40) -> 0 | CA40: =SUM(BX40:BZ40) -> 0 | CB40: =BO40+BS40+BW40+CA40 -> 0 | CD40: =BK40-CB40 -> 0 | CE40: Subcontract: APRODISO (Darién y Comarca Emberá)
A41: Subcontract: APROTENG (Bocas del Toro) | B41: 1000 | C41: ='budget anual'!C91 -> 0 | T41: =G41+K41+O41+S41 -> 0 | V41: =C41-T41 -> 0 | W41: ='budget anual'!D91 -> 0 | AN41: =AA41+AE41+AI41+AM41 -> 0 | AP41: =(V41+W41)-AN41 -> 0 | AQ41: ='budget anual'!E91 -> 0 | BG41: =SUM(BD41:BF41) -> 0 | BH41: =AU41+AY41+BC41+BG41 -> 0 | BJ41: =(AP41+AQ41)-BH41 -> 0 | BK41: =B41-T41-AN41-BH41 -> 1000 | BO41: =SUM(BL41:BN41) -> 0 | BS41: =SUM(BP41:BR41) -> 0 | BW41: =SUM(BT41:BV41) -> 0 | CA41: =SUM(BX41:BZ41) -> 0 | CB41: =BO41+BS41+BW41+CA41 -> 0 | CD41: =BK41-CB41 -> 1000 | CE41: Subcontract: APROTENG (Bocas del Toro)
A42: D.3.2.G EducaFuturo Darién & Comarca Emberá | B42: 1000 | C42: 0 | W42: 0 | AQ42: 0 | BG42: =SUM(BD42:BF42) -> 0 | BH42: =AU42+AY42+BC42+BG42 -> 0 | BJ42: =(AP42+AQ42)-BH42 -> 0 | BK42: =B42-T42-AN42-BH42 -> 1000 | BO42: =SUM(BL42:BN42) -> 0 | BS42: =SUM(BP42:BR42) -> 0 | BW42: =SUM(BT42:BV42) -> 0 | CA42: =SUM(BX42:BZ42) -> 0 | CB42: =BO42+BS42+BW42+CA42 -> 0 | CD42: =BK42-CB42 -> 1000 | CE42: D.3.2.G EducaFuturo Darién & Comarca Emberá
B43: =SUM(B38:B42) -> 6937.5 | C43: =SUM(C38) -> 0 | D43: =SUM(D38) -> 0 | E43: =SUM(E38) -> 0 | F43: =SUM(F38) -> 0 | G43: =SUM(G38) -> 0 | H43: =SUM(H38) -> 0 | I43: =SUM(I38) -> 0 | J43: =SUM(J38) -> 0 | ... T43: =SUM(T38) -> 0 | U43: =T43/C43 -> #DIV/0! | V43: =SUM(V38) -> 0 | W43: =SUM(W38:W41) -> 0 | X43: =SUM(X38) -> 0 | Y43: =SUM(Y38) -> 0 | Z43: =SUM(Z38) -> 0 | AA43: =SUM(AA38) -> 0 | AB43: =SUM(AB38) -> 0 | AC43: =SUM(AC38) -> 0 | AD43: =SUM(AD38) -> 0 | AE43: =SUM(AE38) -> 0 | ... AN43: =SUM(AN38) -> 0 | AO43: =AN43/W43 -> #DIV/0! | AP43: =SUM(AP37:AP42) -> 0 | AQ43: =SUM(AQ38:AQ42) -> 0 | AR43: =SUM(AR37:AR42) -> 0 | AS43: =SUM(AS37:AS42) -> 0 | AT43: =SUM(AT37:AT42) -> 0 | AU43: =SUM(AU38:AU42) -> 0 | AV43: =SUM(AV37:AV42) -> 0 | AW43: =SUM(AW37:AW42) -> 0 | AX43: =SUM(AX37:AX42) -> 0 | AY43: =SUM(AY38:AY42) -> 0 | AZ43: =SUM(AZ37:AZ42) -> 0 | BA43: =SUM(BA37:BA42) -> 0 | BB43: =SUM(BB37:BB42) -> 0 | BC43: =SUM(BC38:BC42) -> 0 | BD43: =SUM(BD37:BD42) -> 0 | BE43: =SUM(BE37:BE42) -> 0 | BF43: =SUM(BF37:BF42) -> 0 | BG43: =SUM(BG38:BG42) -> 0 | BH43: =SUM(BH38:BH42) -> 0 | BI43: =BH43/AQ43 -> #DIV/0! | BJ43: =SUM(BJ38:BJ42) -> 0 | BK43: =SUM(BK38:BK42) -> 6937.5 | BL43: =SUM(BL37:BL42) -> 0 | BM43: =SUM(BM37:BM42) -> 0 | BN43: =SUM(BN37:BN42) -> 0 | BO43: =SUM(BO38:BO42) -> 0 | BP43: =SUM(BP37:BP42) -> 0 | BQ43: =SUM(BQ37:BQ42) -> 0 | BR43: =SUM(BR37:BR42) -> 4687.5 | BS43: =SUM(BS38:BS42) -> 4687.5 | BT43: =SUM(BT37:BT42) -> 0 | BU43: =SUM(BU37:BU42) -> 0 | BV43: =SUM(BV37:BV42) -> 0 | BW43: =SUM(BW38:BW42) -> 0 | BX43: =SUM(BX37:BX42) -> 0 | BY43: =SUM(BY37:BY42) -> 0 | BZ43: =SUM(BZ37:BZ42) -> 0 | CA43: =SUM(CA38:CA42) -> 0 | CB43: =SUM(CB38:CB42) -> 4687.5 | CC43: =CB43/BK43 -> 0.67567568 | CD43: =SUM(CD38:CD42) -> 2250
A44: Output 4: Youth Employment | CE44: Output 4: Youth Employment
A45: D.4.1 A Ganar Quality Control | B45: 15000 | C45: ='budget anual'!C98 -> #REF! | W45: ='budget anual'!D98 -> #REF! | X45: 950 | Y45: 1048.77 | Z45: 2240.01 | AA45: =SUM(X45:Z45) -> 4238.78 | AE45: =SUM(AB45:AD45) -> 0 | AI45: =SUM(AF45:AH45) -> 0 | AM45: =SUM(AJ45:AL45) -> 0 | AN45: =AA45+AE45+AI45+AM45 -> 4238.78 | AP45: =(V45+W45)-AN45 -> #REF! | AQ45: ='budget anual'!E98 -> 10761.22 | AU45: =SUM(AR45:AT45) -> 0 | AX45: 2163.75 | AY45: =SUM(AV45:AX45) -> 2163.75 | AZ45: 5197.6 | BA45: 1029.9 | BB45: 412.55 | BC45: =SUM(AZ45:BB45) -> 6640.05 | BD45: 611.84 | BF45: 2678.83 | BG45: =SUM(BD45:BF45) -> 3290.67 | BH45: =AU45+AY45+BC45+BG45 -> 12094.47 | BJ45: =(AP45+AQ45)-BH45 -> #REF! | BK45: =B45-T45-AN45-BH45 -> -1333.25 | BL45: 28.5 | BM45: -100.89 | BO45: =SUM(BL45:BN45) -> -72.39 | BS45: =SUM(BP45:BR45) -> 0 | BW45: =SUM(BT45:BV45) -> 0 | CA45: =SUM(BX45:BZ45) -> 0 | CB45: =BO45+BS45+BW45+CA45 -> -72.39 | CD45: =BK45-CB45 -> -1260.86 | CE45: D.4.1 A Ganar Quality Control
A46: D.4.3.A Subcontract: Cospae | B46: 138525 | C46: ='budget anual'!C101 -> 0 | G46: =SUM(D46:F46) -> 0 | K46: =SUM(H46:J46) -> 0 | O46: =SUM(L46:N46) -> 0 | S46: =SUM(P46:R46) -> 0 | T46: =G46+K46+O46+S46 -> 0 | U46: =T46/C46 -> #DIV/0! | V46: =C46-T46 -> 0 | W46: ='budget anual'!D101 -> 76000 | X46: 18900 | AA46: =SUM(X46:Z46) -> 18900 | AD46: 58000 | AE46: =SUM(AB46:AD46) -> 58000 | AI46: =SUM(AF46:AH46) -> 0 | AM46: =SUM(AJ46:AL46) -> 0 | AN46: =AA46+AE46+AI46+AM46 -> 76900 | AO46: =AN46/W46 -> 1.0118421 | AP46: =(V46+W46)-AN46 -> -900 | AQ46: ='budget anual'!E101 -> 2410 | AU46: =SUM(AR46:AT46) -> 0 | AY46: =SUM(AV46:AX46) -> 0 | BC46: =SUM(AZ46:BB46) -> 0 | BF46: 26140 | BG46: =SUM(BD46:BF46) -> 26140 | BH46: =AU46+AY46+BC46+BG46 -> 26140 | BI46: =BH46/AQ46 -> 10.846473 | BJ46: =(AP46+AQ46)-BH46 -> -24630 | BK46: =B46-T46-AN46-BH46 -> 35485 | BO46: =SUM(BL46:BN46) -> 0 | BP46: 31308 | BS46: =SUM(BP46:BR46) -> 31308 | BV46: 1500 | BW46: =SUM(BT46:BV46) -> 1500 | BY46: -297.18 | CA46: =SUM(BX46:BZ46) -> -297.18 | CB46: =BO46+BS46+BW46+CA46 -> 32510.82 | CC46: =CB46/BK46 -> 0.91618487 | CD46: =BK46-CB46 -> 2974.18 | CE46: D.4.3.A Subcontract: Cospae
A47: 4.3F Subcontract: Aprotengb | B47: 18500 | C47: 0 | W47: 0 | AQ47: 0 | BG47: =SUM(BD47:BF47) -> 0 | BH47: =AU47+AY47+BC47+BG47 -> 0 | BJ47: =(AP47+AQ47)-BH47 -> 0 | BK47: =B47-T47-AN47-BH47 -> 18500 | BO47: =SUM(BL47:BN47) -> 0 | BP47: 126.21 | BQ47: 300 | BR47: 416.21 | BS47: =SUM(BP47:BR47) -> 842.42 | BT47: 560 | BU47: 1269.79 | BV47: 1050 | BW47: =SUM(BT47:BV47) -> 2879.79 | BX47: -450 | CA47: =SUM(BX47:BZ47) -> -450 | CB47: =BO47+BS47+BW47+CA47 -> 3272.21 | CD47: =BK47-CB47 -> 15227.79 | CE47: 4.3F Subcontract: Aprotengb
A48: 4.3G Subcontract: Fe y Alegria | B48: 39500 | C48: 0 | W48: 0 | AQ48: 0 | BG48: =SUM(BD48:BF48) -> 0 | BH48: =AU48+AY48+BC48+BG48 -> 0 | BJ48: =(AP48+AQ48)-BH48 -> 0 | BK48: =B48-T48-AN48-BH48 -> 39500 | BL48: 1999.84 | BM48: 2582.89 | BN48: 674.15 | BO48: =SUM(BL48:BN48) -> 5256.88 | BP48: 1124.3 | BQ48: 5234.04 | BR48: 1875.7 | BS48: =SUM(BP48:BR48) -> 8234.04 | BT48: 2727.64 | BU48: 4777.7 | BV48: 3465.76 | BW48: =SUM(BT48:BV48) -> 10971.1 | CA48: =SUM(BX48:BZ48) -> 0 | CB48: =BO48+BS48+BW48+CA48 -> 24462.02 | CD48: =BK48-CB48 -> 15037.98 | CE48: 4.3G Subcontract: Fe y Alegria
A49: D.4.3.C EducaFuturo A Ganar | B49: 40300 | C49: 0 | W49: 0 | AQ49: ='budget anual'!E103 -> 5596.47 | BD49: 1193.5 | BE49: 3199.99 | BF49: 1202.98 | BG49: =SUM(BD49:BF49) -> 5596.47 | BH49: =AU49+AY49+BC49+BG49 -> 5596.47 | BJ49: =(AP49+AQ49)-BH49 -> 0 | BK49: =B49-T49-AN49-BH49 -> 34703.53 | BL49: 4128.54 | BM49: 1813.26 | BN49: 1890.29 | BO49: =SUM(BL49:BN49) -> 7832.09 | BP49: 1202.47 | BQ49: 1730 | BR49: 470.96 | BS49: =SUM(BP49:BR49) -> 3403.43 | BT49: =2927.5+557.04 -> 3484.54 | BU49: =4136.16+250+20 -> 4406.16 | BV49: 3005.92 | BW49: =SUM(BT49:BV49) -> 10896.62 | BX49: 250 | BY49: 354.92 | BZ49: -195 | CA49: =SUM(BX49:BZ49) -> 409.92 | CB49: =BO49+BS49+BW49+CA49 -> 22542.06 | CD49: =BK49-CB49 -> 12161.47 | CE49: D.4.3.C EducaFuturo A Ganar
B50: =SUM(B45:B49) -> 251825 | C50: =SUM(C45:C46) -> #REF! | D50: =SUM(D45:D46) -> 0 | E50: =SUM(E45:E46) -> 0 | F50: =SUM(F45:F46) -> 0 | G50: =SUM(G45:G46) -> 0 | H50: =SUM(H45:H46) -> 0 | I50: =SUM(I45:I46) -> 0 | J50: =SUM(J45:J46) -> 0 | ... AN50: =SUM(AN45:AN46) -> 81138.78 | AO50: =AN50/W50 -> #REF! | AP50: =SUM(AP45:AP49) -> #REF! | AQ50: =SUM(AQ44:AQ49) -> 18767.69 | AR50: =SUM(AR44:AR49) -> 0 | AS50: =SUM(AS44:AS49) -> 0 | AT50: =SUM(AT44:AT49) -> 0 | AU50: =SUM(AU44:AU49) -> 0 | AV50: =SUM(AV44:AV49) -> 0 | AW50: =SUM(AW44:AW49) -> 0 | AX50: =SUM(AX44:AX49) -> 2163.75 | ... BG50: =SUM(BG44:BG49) -> 35027.14 | BH50: =SUM(BH45:BH49) -> 43830.94 | BI50: =BH50/AQ50 -> 2.3354467 | BJ50: =SUM(BJ45:BJ49) -> #REF! | BK50: =SUM(BK44:BK49) -> 126855.28 | BL50: =SUM(BL44:BL49) -> 6156.88 | BM50: =SUM(BM44:BM49) -> 4295.26 | BN50: =SUM(BN44:BN49) -> 2564.44 | BO50: =SUM(BO44:BO49) -> 13016.58 | BP50: =SUM(BP44:BP49) -> 33760.98 | BQ50: =SUM(BQ44:BQ49) -> 7264.04 | BR50: =SUM(BR44:BR49) -> 2762.87 | ... CA50: =SUM(CA44:CA49) -> -337.26 | CB50: =SUM(CB45:CB49) -> 82714.72 | CC50: =CB50/BK50 -> 0.65204003 | CD50: =SUM(CD45:CD49) -> 44140.56
A51: Output 5: Public-Private Partnerships | CE51: Output 5: Public-Private Partnerships
A52: 5.1 Task Mapping Risk Assessment | B52: 23200 | C52: 0 | W52: 0 | AQ52: 0 | BE52: 4763.01 | BF52: 320.97 | BG52: =SUM(BD52:BF52) -> 5083.98 | BH52: =AU52+AY52+BC52+BG52 -> 5083.98 | BJ52: =(AP52+AQ52)-BH52 -> -5083.98 | BK52: =B52-T52-AN52-BH52 -> 18116.02 | BL52: 2498.13 | BM52: 975 | BN52: 381.81 | BO52: =SUM(BL52:BN52) -> 3854.94 | BQ52: 6170 | BR52: -2284.45 | BS52: =SUM(BP52:BR52) -> 3885.55 | BT52: 7769.05 | BU52: 3049.95 | BV52: -522.45 | BW52: =SUM(BT52:BV52) -> 10296.55 | CA52: =SUM(BX52:BZ52) -> 0 | CB52: =BO52+BS52+BW52+CA52 -> 18037.04 | CD52: =BK52-CB52 -> 78.98 | CE52: 5.1 Task Mapping Risk Assessment
A53: 5.2 CSR Technical Review | B53: =#REF! -> #REF! | C53: 0 | W53: 0 | AQ53: 0 | BG53: =SUM(BD53:BF53) -> 0 | BH53: =AU53+AY53+BC53+BG53 -> 0 | BJ53: =(AP53+AQ53)-BH53 -> 0 | BK53: =B53-T53-AN53-BH53 -> #REF! | BO53: =SUM(BL53:BN53) -> 0 | BS53: =SUM(BP53:BR53) -> 0 | BW53: =SUM(BT53:BV53) -> 0 | CA53: =SUM(BX53:BZ53) -> 0 | CB53: =BO53+BS53+BW53+CA53 -> 0 | CD53: =BK53-CB53 -> #REF! | CE53: 5.2 CSR Technical Review
B54: =SUM(B52:B53) -> #REF! | C54: =SUM(C52:C53) -> 0 | D54: =SUM(D52:D53) -> 0 | E54: =SUM(E52:E53) -> 0 | F54: =SUM(F52:F53) -> 0 | G54: =SUM(G52:G53) -> 0 | H54: =SUM(H52:H53) -> 0 | I54: =SUM(I52:I53) -> 0 | ... T54: =SUM(T52:T53) -> 0 | U54: =T54/C54 -> #DIV/0! | V54: =SUM(V52:V53) -> 0 | W54: =SUM(W52:W53) -> 0 | X54: =SUM(X52:X53) -> 0 | Y54: =SUM(Y52:Y53) -> 0 | Z54: =SUM(Z52:Z53) -> 0 | AA54: =SUM(AA52:AA53) -> 0 | AB54: =SUM(AB52:AB53) -> 0 | AC54: =SUM(AC52:AC53) -> 0 | ... AN54: =SUM(AN52:AN53) -> 0 | AO54: =AN54/W54 -> #DIV/0! | AP54: =SUM(AP52:AP53) -> 0 | AQ54: =SUM(AQ52:AQ53) -> 0 | AR54: =SUM(AR52:AR53) -> 0 | AS54: =SUM(AS52:AS53) -> 0 | AT54: =SUM(AT52:AT53) -> 0 | AU54: =SUM(AU52:AU53) -> 0 | AV54: =SUM(AV52:AV53) -> 0 | AW54: =SUM(AW52:AW53) -> 0 | ... BH54: =SUM(BH52:BH53) -> 5083.98 | BI54: =BH54/AQ54 -> #DIV/0! | BJ54: =SUM(BJ52:BJ53) -> -5083.98 | BK54: =SUM(BK52:BK53) -> #REF! | BL54: =SUM(BL52:BL53) -> 2498.13 | BM54: =SUM(BM52:BM53) -> 975 | BN54: =SUM(BN52:BN53) -> 381.81 | BO54: =SUM(BO52:BO53) -> 3854.94 | BP54: =SUM(BP52:BP53) -> 0 | BQ54: =SUM(BQ52:BQ53) -> 6170 | ... CB54: =SUM(CB52:CB53) -> 18037.04 | CC54: =CB54/BK54 -> #REF! | CD54: =SUM(CD52:CD53) -> #REF!
A55: Output 6: Strengthening Nexus between Education and Labor Policies | CE55: Output 6: Strengthening Nexus between Education and Labor Policies
A56: Local Stakeholders Event | B56: 3250 | C56: ='budget anual'!C118 -> 1391.39 | F56: 52 | G56: =SUM(D56:F56) -> 52 | H56: 305 | I56: =254.27+15.1 -> 269.37 | J56: 574.7 | K56: =SUM(H56:J56) -> 1149.07 | L56: 140.86 | M56: 23.49 | O56: =SUM(L56:N56) -> 164.35 | P56: 25.97 | S56: =SUM(P56:R56) -> 25.97 | T56: =G56+K56+O56+S56 -> 1391.39 | U56: =T56/C56 -> 1 | V56: =C56-T56 -> 0 | W56: ='budget anual'!D118 -> 352.07 | Y56: 212.82 | AA56: =SUM(X56:Z56) -> 212.82 | AC56: 116.25 | AE56: =SUM(AB56:AD56) -> 116.25 | AF56: 23 | AI56: =SUM(AF56:AH56) -> 23 | AM56: =SUM(AJ56:AL56) -> 0 | AN56: =AA56+AE56+AI56+AM56 -> 352.07 | AP56: =(V56+W56)-AN56 -> 0 | AQ56: ='budget anual'!E118 -> 631.54 | AU56: =SUM(AR56:AT56) -> 0 | AV56: 35.99 | AW56: 1.1 | AY56: =SUM(AV56:AX56) -> 37.09 | BB56: 704.94 | BC56: =SUM(AZ56:BB56) -> 704.94 | BG56: =SUM(BD56:BF56) -> 0 | BH56: =AU56+AY56+BC56+BG56 -> 742.03 | BJ56: =(AP56+AQ56)-BH56 -> -110.49 | BK56: =B56-T56-AN56-BH56 -> 764.51 | BL56: =29.53+367.95 -> 397.48 | BM56: 103.76 | BN56: 871 | BO56: =SUM(BL56:BN56) -> 1372.24 | BP56: 81.1 | BS56: =SUM(BP56:BR56) -> 81.1 | BT56: 98.21 | BV56: 395.15 | BW56: =SUM(BT56:BV56) -> 493.36 | BY56: 103.13 | BZ56: 4.75 | CA56: =SUM(BX56:BZ56) -> 107.88 | CB56: =BO56+BS56+BW56+CA56 -> 2054.58 | CD56: =BK56-CB56 -> -1290.07 | CE56: Local Stakeholders Event
A57: Data Collection Training Workshops | B57: 239.84 | C57: ='budget anual'!C119 -> 0 | G57: =SUM(D57:F57) -> 0 | K57: =SUM(H57:J57) -> 0 | O57: =SUM(L57:N57) -> 0 | S57: =SUM(P57:R57) -> 0 | T57: =G57+K57+O57+S57 -> 0 | U57: =T57/C57 -> #DIV/0! | V57: =C57-T57 -> 0 | W57: ='budget anual'!D119 -> 240 | AA57: =SUM(X57:Z57) -> 0 | AD57: 195.7 | AE57: =SUM(AB57:AD57) -> 195.7 | AF57: 279.14 | AG57: 5 | AI57: =SUM(AF57:AH57) -> 284.14 | AM57: =SUM(AJ57:AL57) -> 0 | AN57: =AA57+AE57+AI57+AM57 -> 479.84 | AO57: =AN57/W57 -> 1.9993333 | AP57: =(V57+W57)-AN57 -> -239.84 | AQ57: ='budget anual'!E119 -> 0 | AU57: =SUM(AR57:AT57) -> 0 | AY57: =SUM(AV57:AX57) -> 0 | BC57: =SUM(AZ57:BB57) -> 0 | BG57: =SUM(BD57:BF57) -> 0 | BH57: =AU57+AY57+BC57+BG57 -> 0 | BI57: =BH57/AQ57 -> #DIV/0! | BJ57: =(AP57+AQ57)-BH57 -> -239.84 | BK57: =B57-T57-AN57-BH57 -> -240 | BO57: =SUM(BL57:BN57) -> 0 | BS57: =SUM(BP57:BR57) -> 0 | BW57: =SUM(BT57:BV57) -> 0 | CA57: =SUM(BX57:BZ57) -> 0 | CB57: =BO57+BS57+BW57+CA57 -> 0 | CC57: =CB57/BK57 -> 0 | CD57: =BK57-CB57 -> -240 | CE57: Data Collection Training Workshops
B58: =SUM(B56:B57) -> 3489.84 | C58: =SUM(C56:C57) -> 1391.39 | D58: =SUM(D56:D57) -> 0 | E58: =SUM(E56:E57) -> 0 | F58: =SUM(F56:F57) -> 52 | G58: =SUM(G56:G57) -> 52 | H58: =SUM(H56:H57) -> 305 | I58: =SUM(I56:I57) -> 269.37 | ... T58: =SUM(T56:T57) -> 1391.39 | U58: =T58/C58 -> 1 | V58: =SUM(V56:V57) -> 0 | W58: =SUM(W56:W57) -> 592.07 | X58: =SUM(X56:X57) -> 0 | Y58: =SUM(Y56:Y57) -> 212.82 | Z58: =SUM(Z56:Z57) -> 0 | AA58: =SUM(AA56:AA57) -> 212.82 | AB58: =SUM(AB56:AB57) -> 0 | AC58: =SUM(AC56:AC57) -> 116.25 | ... AN58: =SUM(AN56:AN57) -> 831.91 | AO58: =AN58/W58 -> 1.4050872 | AP58: =SUM(AP56:AP57) -> -239.84 | AQ58: =SUM(AQ56:AQ57) -> 631.54 | AR58: =SUM(AR56:AR57) -> 0 | AS58: =SUM(AS56:AS57) -> 0 | AT58: =SUM(AT56:AT57) -> 0 | AU58: =SUM(AU56:AU57) -> 0 | AV58: =SUM(AV56:AV57) -> 35.99 | AW58: =SUM(AW56:AW57) -> 1.1 | ... BH58: =SUM(BH56:BH57) -> 742.03 | BI58: =BH58/AQ58 -> 1.1749533 | BJ58: =SUM(BJ56:BJ57) -> -350.33 | BK58: =SUM(BK56:BK57) -> 524.51 | BL58: =SUM(BL56:BL57) -> 397.48 | BM58: =SUM(BM56:BM57) -> 103.76 | BN58: =SUM(BN56:BN57) -> 871 | BO58: =SUM(BO56:BO57) -> 1372.24 | BP58: =SUM(BP56:BP57) -> 81.1 | BQ58: =SUM(BQ56:BQ57) -> 0 | ... CB58: =SUM(CB56:CB57) -> 2054.58 | CC58: =CB58/BK58 -> 3.9171417 | CD58: =SUM(CD56:CD57) -> -1530.07
A59: Output 8: Raising Awareness | CE59: Output 8: Raising Awareness
A60: Community Based Awareness Raising Workshop | B60: 3250 | C60: ='budget anual'!C134 -> 0 | G60: =SUM(D60:F60) -> 0 | K60: =SUM(H60:J60) -> 0 | O60: =SUM(L60:N60) -> 0 | S60: =SUM(P60:R60) -> 0 | T60: =G60+K60+O60+S60 -> 0 | U60: =T60/C60 -> #DIV/0! | V60: =C60-T60 -> 0 | W60: ='budget anual'!D134 -> #REF! | AA60: =SUM(X60:Z60) -> 0 | AE60: =SUM(AB60:AD60) -> 0 | AI60: =SUM(AF60:AH60) -> 0 | AK60: 3133.75 | AM60: =SUM(AJ60:AL60) -> 3133.75 | AN60: =AA60+AE60+AI60+AM60 -> 3133.75 | AO60: =AN60/W60 -> #REF! | AP60: =(V60+W60)-AN60 -> #REF! | AQ60: ='budget anual'!E134 -> #REF! | AT60: 14.81 | AU60: =SUM(AR60:AT60) -> 14.81 | AY60: =SUM(AV60:AX60) -> 0 | BC60: =SUM(AZ60:BB60) -> 0 | BG60: =SUM(BD60:BF60) -> 0 | BH60: =AU60+AY60+BC60+BG60 -> 14.81 | BI60: =BH60/AQ60 -> #REF! | BJ60: =(AP60+AQ60)-BH60 -> #REF! | BK60: =B60-T60-AN60-BH60 -> 101.44 | BO60: =SUM(BL60:BN60) -> 0 | BR60: 180 | BS60: =SUM(BP60:BR60) -> 180 | BW60: =SUM(BT60:BV60) -> 0 | CA60: =SUM(BX60:BZ60) -> 0 | CB60: =BO60+BS60+BW60+CA60 -> 180 | CC60: =CB60/BK60 -> 1.7744479 | CD60: =BK60-CB60 -> -78.56 | CE60: Community Based Awareness Raising Workshop
A61: Community Mobilization | B61: 1800 | C61: ='budget anual'!C135 -> 0 | G61: =SUM(D61:F61) -> 0 | K61: =SUM(H61:J61) -> 0 | O61: =SUM(L61:N61) -> 0 | S61: =SUM(P61:R61) -> 0 | T61: =G61+K61+O61+S61 -> 0 | U61: =T61/C61 -> #DIV/0! | V61: =C61-T61 -> 0 | W61: ='budget anual'!D135 -> #REF! | AA61: =SUM(X61:Z61) -> 0 | AE61: =SUM(AB61:AD61) -> 0 | AI61: =SUM(AF61:AH61) -> 0 | AM61: =SUM(AJ61:AL61) -> 0 | AN61: =AA61+AE61+AI61+AM61 -> 0 | AO61: =AN61/W61 -> #REF! | AP61: =(V61+W61)-AN61 -> #REF! | AQ61: ='budget anual'!E135 -> #REF! | AR61: 1008.37 | AS61: -210.4 | AU61: =SUM(AR61:AT61) -> 797.97 | AX61: 119.3 | AY61: =SUM(AV61:AX61) -> 119.3 | BA61: 192.14 | BB61: 130 | BC61: =SUM(AZ61:BB61) -> 322.14 | BG61: =SUM(BD61:BF61) -> 0 | BH61: =AU61+AY61+BC61+BG61 -> 1239.41 | BI61: =BH61/AQ61 -> #REF! | BJ61: =(AP61+AQ61)-BH61 -> #REF! | BK61: =B61-T61-AN61-BH61 -> 560.59 | BL61: -5.44 | BO61: =SUM(BL61:BN61) -> -5.44 | BR61: 272.81 | BS61: =SUM(BP61:BR61) -> 272.81 | BW61: =SUM(BT61:BV61) -> 0 | CA61: =SUM(BX61:BZ61) -> 0 | CB61: =BO61+BS61+BW61+CA61 -> 267.37 | CC61: =CB61/BK61 -> 0.47694393 | CD61: =BK61-CB61 -> 293.22 | CE61: Community Mobilization
A62: Mass Media Campaigns | B62: 2800 | C62: ='budget anual'!C136 -> 0 | G62: =SUM(D62:F62) -> 0 | K62: =SUM(H62:J62) -> 0 | O62: =SUM(L62:N62) -> 0 | S62: =SUM(P62:R62) -> 0 | T62: =G62+K62+O62+S62 -> 0 | U62: =T62/C62 -> #DIV/0! | V62: =C62-T62 -> 0 | W62: ='budget anual'!D136 -> #REF! | AA62: =SUM(X62:Z62) -> 0 | AE62: =SUM(AB62:AD62) -> 0 | AI62: =SUM(AF62:AH62) -> 0 | AM62: =SUM(AJ62:AL62) -> 0 | AN62: =AA62+AE62+AI62+AM62 -> 0 | AO62: =AN62/W62 -> #REF! | AP62: =(V62+W62)-AN62 -> #REF! | AQ62: ='budget anual'!E136 -> #REF! | AU62: =SUM(AR62:AT62) -> 0 | AX62: 2758.75 | AY62: =SUM(AV62:AX62) -> 2758.75 | BC62: =SUM(AZ62:BB62) -> 0 | BG62: =SUM(BD62:BF62) -> 0 | BH62: =AU62+AY62+BC62+BG62 -> 2758.75 | BI62: =BH62/AQ62 -> #REF! | BJ62: =(AP62+AQ62)-BH62 -> #REF! | BK62: =B62-T62-AN62-BH62 -> 41.25 | BO62: =SUM(BL62:BN62) -> 0 | BS62: =SUM(BP62:BR62) -> 0 | BW62: =SUM(BT62:BV62) -> 0 | CA62: =SUM(BX62:BZ62) -> 0 | CB62: =BO62+BS62+BW62+CA62 -> 0 | CC62: =CB62/BK62 -> 0 | CD62: =BK62-CB62 -> 41.25 | CE62: Mass Media Campaigns
A63: Posters, Bulletins, Awareness Materials | B63: 1100 | C63: ='budget anual'!C137 -> 0 | G63: =SUM(D63:F63) -> 0 | K63: =SUM(H63:J63) -> 0 | O63: =SUM(L63:N63) -> 0 | S63: =SUM(P63:R63) -> 0 | T63: =G63+K63+O63+S63 -> 0 | U63: =T63/C63 -> #DIV/0! | V63: =C63-T63 -> 0 | W63: ='budget anual'!D137 -> #REF! | AA63: =SUM(X63:Z63) -> 0 | AE63: =SUM(AB63:AD63) -> 0 | AI63: =SUM(AF63:AH63) -> 0 | AJ63: 820 | AL63: 24.82 | AM63: =SUM(AJ63:AL63) -> 844.82 | AN63: =AA63+AE63+AI63+AM63 -> 844.82 | AO63: =AN63/W63 -> #REF! | AP63: =(V63+W63)-AN63 -> #REF! | AQ63: ='budget anual'!E137 -> #REF! | AU63: =SUM(AR63:AT63) -> 0 | AY63: =SUM(AV63:AX63) -> 0 | BA63: 200 | BC63: =SUM(AZ63:BB63) -> 200 | BG63: =SUM(BD63:BF63) -> 0 | BH63: =AU63+AY63+BC63+BG63 -> 200 | BI63: =BH63/AQ63 -> #REF! | BJ63: =(AP63+AQ63)-BH63 -> #REF! | BK63: =B63-T63-AN63-BH63 -> 55.18 | BO63: =SUM(BL63:BN63) -> 0 | BS63: =SUM(BP63:BR63) -> 0 | BW63: =SUM(BT63:BV63) -> 0 | CA63: =SUM(BX63:BZ63) -> 0 | CB63: =BO63+BS63+BW63+CA63 -> 0 | CC63: =CB63/BK63 -> 0 | CD63: =BK63-CB63 -> 55.18 | CE63: Posters, Bulletins, Awareness Materials
A64: Subcontract: Fundacion Tierra Nueva | B64: =#REF! -> #REF! | C64: 0 | G64: =SUM(D64:F64) -> 0 | K64: =SUM(H64:J64) -> 0 | O64: =SUM(L64:N64) -> 0 | S64: =SUM(P64:R64) -> 0 | T64: =G64+K64+O64+S64 -> 0 | U64: =T64/C64 -> #DIV/0! | V64: =C64-T64 -> 0 | W64: 0 | AA64: =SUM(X64:Z64) -> 0 | AE64: =SUM(AB64:AD64) -> 0 | AI64: =SUM(AF64:AH64) -> 0 | AM64: =SUM(AJ64:AL64) -> 0 | AN64: =AA64+AE64+AI64+AM64 -> 0 | AO64: =AN64/W64 -> #DIV/0! | AP64: =(V64+W64)-AN64 -> 0 | AQ64: 0 | AU64: =SUM(AR64:AT64) -> 0 | AY64: =SUM(AV64:AX64) -> 0 | BC64: =SUM(AZ64:BB64) -> 0 | BG64: =SUM(BD64:BF64) -> 0 | BH64: =AU64+AY64+BC64+BG64 -> 0 | BI64: =BH64/AQ64 -> #DIV/0! | BJ64: =(AP64+AQ64)-BH64 -> 0 | BK64: =B64-T64-AN64-BH64 -> #REF! | BO64: =SUM(BL64:BN64) -> 0 | BS64: =SUM(BP64:BR64) -> 0 | BW64: =SUM(BT64:BV64) -> 0 | CA64: =SUM(BX64:BZ64) -> 0 | CB64: =BO64+BS64+BW64+CA64 -> 0 | CC64: =CB64/BK64 -> #REF! | CD64: =BK64-CB64 -> #REF! | CE64: Subcontract: Fundacion Tierra Nueva
B65: =SUM(B60:B64) -> #REF! | C65: =SUM(C60:C64) -> 0 | D65: =SUM(D60:D64) -> 0 | E65: =SUM(E60:E64) -> 0 | F65: =SUM(F60:F64) -> 0 | G65: =SUM(G60:G64) -> 0 | H65: =SUM(H60:H64) -> 0 | I65: =SUM(I60:I64) -> 0 | ... T65: =SUM(T60:T64) -> 0 | U65: =T65/C65 -> #DIV/0! | V65: =SUM(V60:V64) -> 0 | W65: =SUM(W60:W64) -> #REF! | X65: =SUM(X60:X64) -> 0 | Y65: =SUM(Y60:Y64) -> 0 | Z65: =SUM(Z60:Z64) -> 0 | AA65: =SUM(AA60:AA64) -> 0 | AB65: =SUM(AB60:AB64) -> 0 | AC65: =SUM(AC60:AC64) -> 0 | ... AN65: =SUM(AN60:AN64) -> 3978.57 | AO65: =AN65/W65 -> #REF! | AP65: =SUM(AP60:AP64) -> #REF! | AQ65: =SUM(AQ60:AQ64) -> #REF! | AR65: =SUM(AR60:AR64) -> 1008.37 | AS65: =SUM(AS60:AS64) -> -210.4 | AT65: =SUM(AT60:AT64) -> 14.81 | AU65: =SUM(AU60:AU64) -> 812.78 | AV65: =SUM(AV60:AV64) -> 0 | AW65: =SUM(AW60:AW64) -> 0 | ... BH65: =SUM(BH60:BH64) -> 4212.97 | BI65: =BH65/AQ65 -> #REF! | BJ65: =SUM(BJ60:BJ64) -> #REF! | BK65: =SUM(BK60:BK64) -> #REF! | BL65: =SUM(BL60:BL64) -> -5.44 | BM65: =SUM(BM60:BM64) -> 0 | BN65: =SUM(BN60:BN64) -> 0 | BO65: =SUM(BO60:BO64) -> -5.44 | BP65: =SUM(BP60:BP64) -> 0 | BQ65: =SUM(BQ60:BQ64) -> 0 | ... CB65: =SUM(CB60:CB64) -> 447.37 | CC65: =CB65/BK65 -> #REF! | CD65: =SUM(CD60:CD64) -> #REF!
A66: Output 9: Sharing Lessons Between and Among Countries | CE66: Output 9: Sharing Lessons Between and Among Countries
A67: III Global Conference on Child Labor Brazil 2013 - Lodging and Per Diem | B67: 1000 | C67: ='budget anual'!B144 -> 1000 | G67: =SUM(D67:F67) -> 0 | K67: =SUM(H67:J67) -> 0 | O67: =SUM(L67:N67) -> 0 | P67: 1016.33 | S67: =SUM(P67:R67) -> 1016.33 | T67: =G67+K67+O67+S67 -> 1016.33 | V67: =C67-T67 -> -16.33 | W67: 0 | AA67: =SUM(X67:Z67) -> 0 | AE67: =SUM(AB67:AD67) -> 0 | AI67: =SUM(AF67:AH67) -> 0 | AM67: =SUM(AJ67:AL67) -> 0 | AN67: =AA67+AE67+AI67+AM67 -> 0 | AP67: =(V67+W67)-AN67 -> -16.33 | AQ67: 0 | AU67: =SUM(AR67:AT67) -> 0 | AY67: =SUM(AV67:AX67) -> 0 | BC67: =SUM(AZ67:BB67) -> 0 | BG67: =SUM(BD67:BF67) -> 0 | BH67: =AU67+AY67+BC67+BG67 -> 0 | BJ67: =(AP67+AQ67)-BH67 -> -16.33 | BK67: =B67-T67-AN67-BH67 -> -16.33 | BO67: =SUM(BL67:BN67) -> 0 | BS67: =SUM(BP67:BR67) -> 0 | BW67: =SUM(BT67:BV67) -> 0 | CA67: =SUM(BX67:BZ67) -> 0 | CB67: =BO67+BS67+BW67+CA67 -> 0 | CD67: =BK67-CB67 -> -16.33 | CE67: III Global Conference on Child Labor Brazil 2013 - Lodging and Per Diem
A68: 9.2 Targeted Learning Exchanges (Lodging and Per Diem) | B68: =1080+650 -> 1730 | C68: ='budget anual'!B146 -> 1080 | G68: =SUM(D68:F68) -> 0 | K68: =SUM(H68:J68) -> 0 | O68: =SUM(L68:N68) -> 0 | Q68: 1080 | S68: =SUM(P68:R68) -> 1080 | T68: =G68+K68+O68+S68 -> 1080 | V68: =C68-T68 -> 0 | W68: 0 | AA68: =SUM(X68:Z68) -> 0 | AE68: =SUM(AB68:AD68) -> 0 | AI68: =SUM(AF68:AH68) -> 0 | AM68: =SUM(AJ68:AL68) -> 0 | AN68: =AA68+AE68+AI68+AM68 -> 0 | AP68: =(V68+W68)-AN68 -> 0 | AQ68: 0 | AU68: =SUM(AR68:AT68) -> 0 | AY68: =SUM(AV68:AX68) -> 0 | BC68: =SUM(AZ68:BB68) -> 0 | BG68: =SUM(BD68:BF68) -> 0 | BH68: =AU68+AY68+BC68+BG68 -> 0 | BJ68: =(AP68+AQ68)-BH68 -> 0 | BK68: =B68-T68-AN68-BH68 -> 650 | BO68: =SUM(BL68:BN68) -> 0 | BQ68: 456.5 | BR68: 210 | BS68: =SUM(BP68:BR68) -> 666.5 | BW68: =SUM(BT68:BV68) -> 0 | BX68: 300 | BY68: -190.23 | CA68: =SUM(BX68:BZ68) -> 109.77 | CB68: =BO68+BS68+BW68+CA68 -> 776.27 | CD68: =BK68-CB68 -> -126.27 | CE68: 9.2 Targeted Learning Exchanges (Lodging and Per Diem)
A69: 9.3 Network Building | B69: =#REF! -> #REF! | C69: 0 | G69: =SUM(D69:F69) -> 0 | K69: =SUM(H69:J69) -> 0 | O69: =SUM(L69:N69) -> 0 | S69: =SUM(P69:R69) -> 0 | T69: =G69+K69+O69+S69 -> 0 | U69: =T69/C69 -> #DIV/0! | V69: =C69-T69 -> 0 | W69: 0 | AA69: =SUM(X69:Z69) -> 0 | AE69: =SUM(AB69:AD69) -> 0 | AI69: =SUM(AF69:AH69) -> 0 | AM69: =SUM(AJ69:AL69) -> 0 | AN69: =AA69+AE69+AI69+AM69 -> 0 | AO69: =AN69/W69 -> #DIV/0! | AP69: =(V69+W69)-AN69 -> 0 | AQ69: 0 | AU69: =SUM(AR69:AT69) -> 0 | AY69: =SUM(AV69:AX69) -> 0 | BC69: =SUM(AZ69:BB69) -> 0 | BG69: =SUM(BD69:BF69) -> 0 | BH69: =AU69+AY69+BC69+BG69 -> 0 | BI69: =BH69/AQ69 -> #DIV/0! | BJ69: =(AP69+AQ69)-BH69 -> 0 | BK69: =B69-T69-AN69-BH69 -> #REF! | BO69: =SUM(BL69:BN69) -> 0 | BS69: =SUM(BP69:BR69) -> 0 | BW69: =SUM(BT69:BV69) -> 0 | CA69: =SUM(BX69:BZ69) -> 0 | CB69: =BO69+BS69+BW69+CA69 -> 0 | CC69: =CB69/BK69 -> #REF! | CD69: =BK69-CB69 -> #REF! | CE69: 9.3 Network Building
B70: =SUM(B67:B69) -> #REF! | C70: =SUM(C67:C69) -> 2080 | D70: =SUM(D67:D69) -> 0 | E70: =SUM(E67:E69) -> 0 | F70: =SUM(F67:F69) -> 0 | G70: =SUM(G67:G69) -> 0 | H70: =SUM(H67:H69) -> 0 | I70: =SUM(I67:I69) -> 0 | ... T70: =SUM(T67:T69) -> 2096.33 | U70: =T70/C70 -> 1.007851 | V70: =SUM(V67:V69) -> -16.33 | W70: =SUM(W67:W69) -> 0 | X70: =SUM(X67:X69) -> 0 | Y70: =SUM(Y67:Y69) -> 0 | Z70: =SUM(Z67:Z69) -> 0 | AA70: =SUM(AA67:AA69) -> 0 | AB70: =SUM(AB67:AB69) -> 0 | AC70: =SUM(AC67:AC69) -> 0 | ... AN70: =SUM(AN67:AN69) -> 0 | AO70: =AN70/W70 -> #DIV/0! | AP70: =SUM(AP67:AP69) -> -16.33 | AQ70: =SUM(AQ67:AQ69) -> 0 | AR70: =SUM(AR67:AR69) -> 0 | AS70: =SUM(AS67:AS69) -> 0 | AT70: =SUM(AT67:AT69) -> 0 | AU70: =SUM(AU67:AU69) -> 0 | AV70: =SUM(AV67:AV69) -> 0 | AW70: =SUM(AW67:AW69) -> 0 | ... BH70: =SUM(BH67:BH69) -> 0 | BI70: =BH70/AQ70 -> #DIV/0! | BJ70: =SUM(BJ67:BJ69) -> -16.33 | BK70: =SUM(BK67:BK69) -> #REF! | BL70: =SUM(BL67:BL69) -> 0 | BM70: =SUM(BM67:BM69) -> 0 | BN70: =SUM(BN67:BN69) -> 0 | BO70: =SUM(BO67:BO69) -> 0 | BP70: =SUM(BP67:BP69) -> 0 | BQ70: =SUM(BQ67:BQ69) -> 456.5 | ... CB70: =SUM(CB67:CB69) -> 776.27 | CC70: =CB70/BK70 -> #REF! | CD70: =SUM(CD67:CD69) -> #REF!
A71: Output 10: Monitoring and Evaluation | CE71: Output 10: Monitoring and Evaluation
A72: D.10.2 Baseline Survey | B72: 36743 | C72: ='budget anual'!C153 -> #REF! | F72: 1056 | G72: =SUM(D72:F72) -> 1056 | H72: =-231.15 -> -231.15 | I72: 1864.13 | J72: -691.75 | K72: =SUM(H72:J72) -> 941.23 | L72: 12604.4 | M72: =12709.47+147 -> 12856.47 | N72: 178.95 | O72: =SUM(L72:N72) -> 25639.82 | P72: 1060.89 | Q72: 1679.79 | R72: -54.35 | S72: =SUM(P72:R72) -> 2686.33 | T72: =G72+K72+O72+S72 -> 30323.38 | V72: =C72-T72 -> #REF! | W72: ='budget anual'!D153 -> #REF! | X72: 2116 | Y72: 1324.53 | Z72: 879.95 | AA72: =SUM(X72:Z72) -> 4320.48 | AB72: -665 | AC72: -60.22 | AE72: =SUM(AB72:AD72) -> -725.22 | AI72: =SUM(AF72:AH72) -> 0 | AK72: 2859 | AL72: -288 | AM72: =SUM(AJ72:AL72) -> 2571 | AN72: =AA72+AE72+AI72+AM72 -> 6166.26 | AO72: =AN72/(W72+V72) -> #REF! | AP72: =(V72+W72)-AN72 -> #REF! | AQ72: ='budget anual'!E153 -> 253.36 | AT72: 420 | AU72: =SUM(AR72:AT72) -> 420 | AV72: 24.8 | AY72: =SUM(AV72:AX72) -> 24.8 | BC72: =SUM(AZ72:BB72) -> 0 | BG72: =SUM(BD72:BF72) -> 0 | BH72: =AU72+AY72+BC72+BG72 -> 444.8 | BI72: =BH72/(AQ72+AP72) -> #REF! | BJ72: =(AP72+AQ72)-BH72 -> #REF! | BK72: =B72-T72-AN72-BH72 -> -191.44 | BO72: =SUM(BL72:BN72) -> 0 | BS72: =SUM(BP72:BR72) -> 0 | BW72: =SUM(BT72:BV72) -> 0 | CA72: =SUM(BX72:BZ72) -> 0 | CB72: =BO72+BS72+BW72+CA72 -> 0 | CC72: =CB72/(BK72+BJ72) -> #REF! | CD72: =BK72-CB72 -> -191.44 | CE72: D.10.2 Baseline Survey
A73: D.10.3 Follow-Up Survey | B73: 34500 | C73: ='budget anual'!C154 -> 0 | G73: =SUM(D73:F73) -> 0 | K73: =SUM(H73:J73) -> 0 | O73: =SUM(L73:N73) -> 0 | S73: =SUM(P73:R73) -> 0 | T73: =G73+K73+O73+S73 -> 0 | V73: =C73-T73 -> 0 | W73: ='budget anual'!D154 -> 0 | AA73: =SUM(X73:Z73) -> 0 | AE73: =SUM(AB73:AD73) -> 0 | AI73: =SUM(AF73:AH73) -> 0 | AM73: =SUM(AJ73:AL73) -> 0 | AN73: =AA73+AE73+AI73+AM73 -> 0 | AP73: =(V73+W73)-AN73 -> 0 | AQ73: ='budget anual'!E154 -> 0 | AU73: =SUM(AR73:AT73) -> 0 | AY73: =SUM(AV73:AX73) -> 0 | BC73: =SUM(AZ73:BB73) -> 0 | BG73: =SUM(BD73:BF73) -> 0 | BH73: =AU73+AY73+BC73+BG73 -> 0 | BJ73: =(AP73+AQ73)-BH73 -> 0 | BK73: =B73-T73-AN73-BH73 -> 34500 | BM73: 200 | BN73: 550 | BO73: =SUM(BL73:BN73) -> 750 | BP73: 550 | BR73: 675 | BS73: =SUM(BP73:BR73) -> 1225 | BT73: 1350 | BU73: =2000.03-600-500-250 -> 650.03 | BW73: =SUM(BT73:BV73) -> 2000.03 | BZ73: 1306.47 | CA73: =SUM(BX73:BZ73) -> 1306.47 | CB73: =BO73+BS73+BW73+CA73 -> 5281.5 | CD73: =BK73-CB73 -> 29218.5 | CE73: D.10.3 Follow-Up Survey
A74: 10.5 Research Survey, Analysis and Report | B74: 5000 | C74: ='budget anual'!C157 -> 0 | W74: ='budget anual'!D157 -> 0 | AQ74: 0 | BH74: =AU74+AY74+BC74+BG74 -> 0 | BJ74: =(AP74+AQ74)-BH74 -> 0 | BK74: =B74-T74-AN74-BH74 -> 5000 | BO74: =SUM(BL74:BN74) -> 0 | BV74: 2500 | BW74: =SUM(BT74:BV74) -> 2500 | BX74: 160 | BY74: 2500 | CA74: =SUM(BX74:BZ74) -> 2660 | CB74: =BO74+BS74+BW74+CA74 -> 5160 | CD74: =BK74-CB74 -> -160 | CE74: 10.5 Research Survey, Analysis and Report
A75: D.10.6 Workshop USDOL - CMEP | B75: 3638.24 | C75: ='budget anual'!C158 -> 3638.24 | H75: =1185.84+465.68+172.11-5.22 -> 1818.41 | I75: 14.83 | K75: =SUM(H75:J75) -> 1833.24 | L75: 952 | M75: -147 | O75: =SUM(L75:N75) -> 805 | R75: 1000 | S75: =SUM(P75:R75) -> 1000 | T75: =G75+K75+O75+S75 -> 3638.24 | V75: =C75-T75 -> 0 | W75: ='budget anual'!D158 -> 0 | AE75: =SUM(AB75:AD75) -> 0 | AI75: =SUM(AF75:AH75) -> 0 | AM75: =SUM(AJ75:AL75) -> 0 | AN75: =AA75+AE75+AI75+AM75 -> 0 | AP75: =(V75+W75)-AN75 -> 0 | AQ75: 0 | AY75: =SUM(AV75:AX75) -> 0 | BC75: =SUM(AZ75:BB75) -> 0 | BG75: =SUM(BD75:BF75) -> 0 | BH75: =AU75+AY75+BC75+BG75 -> 0 | BJ75: =(AP75+AQ75)-BH75 -> 0 | BK75: =B75-T75-AN75-BH75 -> 0 | BO75: =SUM(BL75:BN75) -> 0 | BS75: =SUM(BP75:BR75) -> 0 | BW75: =SUM(BT75:BV75) -> 0 | CA75: =SUM(BX75:BZ75) -> 0 | CB75: =BO75+BS75+BW75+CA75 -> 0 | CD75: =BK75-CB75 -> 0 | CE75: D.10.6 Workshop USDOL - CMEP
A76: D.10.7.A Airfare - DC-Panama-Ecuador - Establish M&E System | B76: 2200 | C76: ='budget anual'!C161 -> 490 | L76: 637 | M76: -147 | O76: =SUM(L76:N76) -> 490 | S76: =SUM(P76:R76) -> 0 | T76: =G76+K76+O76+S76 -> 490 | V76: =C76-T76 -> 0 | W76: ='budget anual'!D161 -> 0 | AI76: =SUM(AF76:AH76) -> 0 | AM76: =SUM(AJ76:AL76) -> 0 | AN76: =AA76+AE76+AI76+AM76 -> 0 | AP76: =(V76+W76)-AN76 -> 0 | AQ76: ='budget anual'!E161 -> 0 | BC76: =SUM(AZ76:BB76) -> 0 | BG76: =SUM(BD76:BF76) -> 0 | BH76: =AU76+AY76+BC76+BG76 -> 0 | BJ76: =(AP76+AQ76)-BH76 -> 0 | BK76: =B76-T76-AN76-BH76 -> 1710 | BO76: =SUM(BL76:BN76) -> 0 | BS76: =SUM(BP76:BR76) -> 0 | BW76: =SUM(BT76:BV76) -> 0 | CA76: =SUM(BX76:BZ76) -> 0 | CB76: =BO76+BS76+BW76+CA76 -> 0 | CD76: =BK76-CB76 -> 1710 | CE76: D.10.7.A Airfare - DC-Panama-Ecuador - Establish M&E System
A77: D.10.7.B. Lodging and per diem - Program Management Trip | B77: 6600 | C77: ='budget anual'!C162 -> #REF! | G77: =SUM(D77:F77) -> 0 | H77: =330.51-305 -> 25.51 | I77: 35.6 | K77: =SUM(H77:J77) -> 61.11 | L77: 420 | O77: =SUM(L77:N77) -> 420 | S77: =SUM(P77:R77) -> 0 | T77: =G77+K77+O77+S77 -> 481.11 | V77: =C77-T77 -> #REF! | W77: ='budget anual'!D162 -> 2500 | AA77: =SUM(X77:Z77) -> 0 | AB77: 2418 | AC77: -512.91 | AD77: -954.17 | AE77: =SUM(AB77:AD77) -> 950.92 | AF77: 40 | AI77: =SUM(AF77:AH77) -> 40 | AJ77: 693.11 | AK77: 266.02 | AL77: 111.84 | AM77: =SUM(AJ77:AL77) -> 1070.97 | AN77: =AA77+AE77+AI77+AM77 -> 2061.89 | AO77: =AN77/W77 -> 0.824756 | AP77: =(V77+W77)-AN77 -> #REF! | AQ77: ='budget anual'!E162 -> 2618.89 | AU77: =SUM(AR77:AT77) -> 0 | AX77: 576 | AY77: =SUM(AV77:AX77) -> 576 | AZ77: 1421.66 | BA77: -414.33 | BB77: -194.45 | BC77: =SUM(AZ77:BB77) -> 812.88 | BD77: 926.05 | BE77: 440 | BF77: -791.72 | BG77: =SUM(BD77:BF77) -> 574.33 | BH77: =AU77+AY77+BC77+BG77 -> 1963.21 | BI77: =BH77/AQ77 -> 0.74963439 | BJ77: =(AP77+AQ77)-BH77 -> #REF! | BK77: =B77-T77-AN77-BH77 -> 2093.79 | BO77: =SUM(BL77:BN77) -> 0 | BP77: 801.51 | BR77: 338.3 | BS77: =SUM(BP77:BR77) -> 1139.81 | BU77: 261.68 | BW77: =SUM(BT77:BV77) -> 261.68 | BX77: =425.07-300 -> 125.07 | CA77: =SUM(BX77:BZ77) -> 125.07 | CB77: =BO77+BS77+BW77+CA77 -> 1526.56 | CC77: =CB77/BK77 -> 0.72908935 | CD77: =BK77-CB77 -> 567.23 | CE77: D.10.7.B. Lodging and per diem - Program Management Trip
A78: D.10.7.C. Airfare - Field Verification Visits | B78: 1500 | C78: ='budget anual'!C163 -> 0 | G78: =SUM(D78:F78) -> 0 | K78: =SUM(H78:J78) -> 0 | O78: =SUM(L78:N78) -> 0 | S78: =SUM(P78:R78) -> 0 | T78: =G78+K78+O78+S78 -> 0 | V78: =C78-T78 -> 0 | W78: ='budget anual'!D163 -> #REF! | AA78: =SUM(X78:Z78) -> 0 | AE78: =SUM(AB78:AD78) -> 0 | AF78: 276.72 | AH78: 274.58 | AI78: =SUM(AF78:AH78) -> 551.3 | AL78: -249.1 | AM78: =SUM(AJ78:AL78) -> -249.1 | AN78: =AA78+AE78+AI78+AM78 -> 302.2 | AO78: =AN78/W78 -> #REF! | AP78: =(V78+W78)-AN78 -> #REF! | AQ78: ='budget anual'!E163 -> #REF! | AR78: 252.1 | AU78: =SUM(AR78:AT78) -> 252.1 | AY78: =SUM(AV78:AX78) -> 0 | BC78: =SUM(AZ78:BB78) -> 0 | BG78: =SUM(BD78:BF78) -> 0 | BH78: =AU78+AY78+BC78+BG78 -> 252.1 | BI78: =BH78/AQ78 -> #REF! | BJ78: =(AP78+AQ78)-BH78 -> #REF! | BK78: =B78-T78-AN78-BH78 -> 945.7 | BO78: =SUM(BL78:BN78) -> 0 | BS78: =SUM(BP78:BR78) -> 0 | BW78: =SUM(BT78:BV78) -> 0 | BX78: 241.4 | CA78: =SUM(BX78:BZ78) -> 241.4 | CB78: =BO78+BS78+BW78+CA78 -> 241.4 | CC78: =CB78/BK78 -> 0.25526065 | CD78: =BK78-CB78 -> 704.3 | CE78: D.10.7.C. Airfare - Field Verification Visits
A79: D.10.7.C. Lodging and per diem - Field Verification Visits | B79: 7000 | C79: ='budget anual'!C164 -> #REF! | G79: =SUM(D79:F79) -> 0 | K79: =SUM(H79:J79) -> 0 | O79: =SUM(L79:N79) -> 0 | P79: 1460.3 | S79: =SUM(P79:R79) -> 1460.3 | T79: =G79+K79+O79+S79 -> 1460.3 | V79: =C79-T79 -> #REF! | W79: ='budget anual'!D164 -> #REF! | Z79: 2184 | AA79: =SUM(X79:Z79) -> 2184 | AC79: =650-946.17 -> -296.17 | AD79: 485 | AE79: =SUM(AB79:AD79) -> 188.83 | AF79: 1290 | AG79: =-35.6+375.3 -> 339.7 | AH79: -369.34 | AI79: =SUM(AF79:AH79) -> 1260.36 | AM79: =SUM(AJ79:AL79) -> 0 | AN79: =AA79+AE79+AI79+AM79 -> 3633.19 | AO79: =AN79/W79 -> #REF! | AP79: =(V79+W79)-AN79 -> #REF! | AQ79: ='budget anual'!E164 -> #REF! | AU79: =SUM(AR79:AT79) -> 0 | AY79: =SUM(AV79:AX79) -> 0 | BC79: =SUM(AZ79:BB79) -> 0 | BD79: 800 | BG79: =SUM(BD79:BF79) -> 800 | BH79: =AU79+AY79+BC79+BG79 -> 800 | BI79: =BH79/AQ79 -> #REF! | BJ79: =(AP79+AQ79)-BH79 -> #REF! | BK79: =B79-T79-AN79-BH79 -> 1106.51 | BM79: 575 | BN79: 150 | BO79: =SUM(BL79:BN79) -> 725 | BP79: =1093.7-126.21 -> 967.49 | BQ79: 931.71 | BR79: 1379.49 | BS79: =SUM(BP79:BR79) -> 3278.69 | BW79: =SUM(BT79:BV79) -> 0 | BY79: -659.82 | CA79: =SUM(BX79:BZ79) -> -659.82 | CB79: =BO79+BS79+BW79+CA79 -> 3343.87 | CC79: =CB79/BK79 -> 3.0219971 | CD79: =BK79-CB79 -> -2237.36 | CE79: D.10.7.C. Lodging and per diem - Field Verification Visits
A80: D.10.7.C. Local Transportation Field Verification Visits | B80: 14000 | C80: ='budget anual'!C165 -> #REF! | G80: =SUM(D80:F80) -> 0 | K80: =SUM(H80:J80) -> 0 | O80: =SUM(L80:N80) -> 0 | S80: =SUM(P80:R80) -> 0 | T80: =G80+K80+O80+S80 -> 0 | V80: =C80-T80 -> #REF! | W80: ='budget anual'!D165 -> #REF! | AA80: =SUM(X80:Z80) -> 0 | AC80: 100 | AD80: 340 | AE80: =SUM(AB80:AD80) -> 440 | AF80: 641.38 | AH80: 871.12 | AI80: =SUM(AF80:AH80) -> 1512.5 | AJ80: 2313.48 | AK80: 569.16 | AL80: -656.45 | AM80: =SUM(AJ80:AL80) -> 2226.19 | AN80: =AA80+AE80+AI80+AM80 -> 4178.69 | AO80: =AN80/W80 -> #REF! | AP80: =(V80+W80)-AN80 -> #REF! | AQ80: ='budget anual'!E165 -> #REF! | AR80: 300 | AS80: 933.8 | AT80: =-71.81+86.89 -> 15.08 | AU80: =SUM(AR80:AT80) -> 1248.88 | AW80: 1950.3 | AX80: 151.26 | AY80: =SUM(AV80:AX80) -> 2101.56 | AZ80: 1885 | BA80: -148.9 | BB80: 1726.47 | BC80: =SUM(AZ80:BB80) -> 3462.57 | BD80: =1044.8-800 -> 244.8 | BE80: 1598.2 | BF80: -129.16 | BG80: =SUM(BD80:BF80) -> 1713.84 | BH80: =AU80+AY80+BC80+BG80 -> 8526.85 | BI80: =BH80/AQ80 -> #REF! | BJ80: =(AP80+AQ80)-BH80 -> #REF! | BK80: =B80-T80-AN80-BH80 -> 1294.46 | BL80: -184.7 | BM80: 575 | BN80: =469.22-150 -> 319.22 | BO80: =SUM(BL80:BN80) -> 709.52 | BS80: =SUM(BP80:BR80) -> 0 | BT80: 500 | BV80: 1487.42 | BW80: =SUM(BT80:BV80) -> 1987.42 | BX80: 145.46 | CA80: =SUM(BX80:BZ80) -> 145.46 | CB80: =BO80+BS80+BW80+CA80 -> 2842.4 | CC80: =CB80/BK80 -> 2.1958191 | CD80: =BK80-CB80 -> -1547.94 | CE80: D.10.7.C. Local Transportation Field Verification Visits
A81: D.10.7.D. Lodging and per diem - HQ Partners Management Travel | B81: 500 | C81: ='budget anual'!C166 -> #REF! | S81: =SUM(P81:R81) -> 0 | T81: =G81+K81+O81+S81 -> 0 | V81: =C81-T81 -> #REF! | W81: ='budget anual'!D166 -> #REF! | Y81: 335 | Z81: 26.75 | AA81: =SUM(X81:Z81) -> 361.75 | AE81: =SUM(AB81:AD81) -> 0 | AF81: 85 | AI81: =SUM(AF81:AH81) -> 85 | AM81: =SUM(AJ81:AL81) -> 0 | AN81: =AA81+AE81+AI81+AM81 -> 446.75 | AP81: =(V81+W81)-AN81 -> #REF! | AQ81: ='budget anual'!E166 -> 53.25 | AU81: =SUM(AR81:AT81) -> 0 | AV81: 335 | AY81: =SUM(AV81:AX81) -> 335 | BC81: =SUM(AZ81:BB81) -> 0 | BG81: =SUM(BD81:BF81) -> 0 | BH81: =AU81+AY81+BC81+BG81 -> 335 | BJ81: =(AP81+AQ81)-BH81 -> #REF! | BK81: =B81-T81-AN81-BH81 -> -281.75 | BO81: =SUM(BL81:BN81) -> 0 | BS81: =SUM(BP81:BR81) -> 0 | BW81: =SUM(BT81:BV81) -> 0 | CA81: =SUM(BX81:BZ81) -> 0 | CB81: =BO81+BS81+BW81+CA81 -> 0 | CD81: =BK81-CB81 -> -281.75 | CE81: D.10.7.D. Lodging and per diem - HQ Partners Management Travel
A82: D.10.8. Lodging and Per diem Annual Visits to USDOL | B82: 3000 | C82: ='budget anual'!C169 -> #REF! | G82: =SUM(D82:F82) -> 0 | H82: =200.67+123.36 -> 324.03 | K82: =SUM(H82:J82) -> 324.03 | L82: 962 | M82: -91.07 | O82: =SUM(L82:N82) -> 870.93 | S82: =SUM(P82:R82) -> 0 | T82: =G82+K82+O82+S82 -> 1194.96 | V82: =C82-T82 -> #REF! | W82: ='budget anual'!D169 -> #REF! | Y82: 82.6 | AA82: =SUM(X82:Z82) -> 82.6 | AE82: =SUM(AB82:AD82) -> 0 | AI82: =SUM(AF82:AH82) -> 0 | AM82: =SUM(AJ82:AL82) -> 0 | AN82: =AA82+AE82+AI82+AM82 -> 82.6 | AP82: =(V82+W82)-AN82 -> #REF! | AQ82: ='budget anual'!E169 -> 1500 | AU82: =SUM(AR82:AT82) -> 0 | AV82: 350 | AY82: =SUM(AV82:AX82) -> 350 | BC82: =SUM(AZ82:BB82) -> 0 | BG82: =SUM(BD82:BF82) -> 0 | BH82: =AU82+AY82+BC82+BG82 -> 350 | BJ82: =(AP82+AQ82)-BH82 -> #REF! | BK82: =B82-T82-AN82-BH82 -> 1372.44 | BM82: 1100 | BN82: -750.35 | BO82: =SUM(BL82:BN82) -> 349.65 | BS82: =SUM(BP82:BR82) -> 0 | BW82: =SUM(BT82:BV82) -> 0 | CA82: =SUM(BX82:BZ82) -> 0 | CB82: =BO82+BS82+BW82+CA82 -> 349.65 | CD82: =BK82-CB82 -> 1022.79 | CE82: D.10.8. Lodging and Per diem Annual Visits to USDOL
A83: D.10.9 Mid-term evaluation | B83: 17500 | C83: ='budget anual'!C171 -> #REF! | G83: =SUM(D83:F83) -> 0 | K83: =SUM(H83:J83) -> 0 | O83: =SUM(L83:N83) -> 0 | S83: =SUM(P83:R83) -> 0 | T83: =G83+K83+O83+S83 -> 0 | V83: =C83-T83 -> #REF! | W83: ='budget anual'!D171 -> #REF! | AA83: =SUM(X83:Z83) -> 0 | AE83: =SUM(AB83:AD83) -> 0 | AI83: =SUM(AF83:AH83) -> 0 | AM83: =SUM(AJ83:AL83) -> 0 | AN83: =AA83+AE83+AI83+AM83 -> 0 | AP83: =(V83+W83)-AN83 -> #REF! | AQ83: ='budget anual'!E171 -> 17500 | AT83: 790.85 | AU83: =SUM(AR83:AT83) -> 790.85 | AV83: 8954.24 | AW83: -1569.63 | AY83: =SUM(AV83:AX83) -> 7384.61 | BC83: =SUM(AZ83:BB83) -> 0 | BG83: =SUM(BD83:BF83) -> 0 | BH83: =AU83+AY83+BC83+BG83 -> 8175.46 | BJ83: =(AP83+AQ83)-BH83 -> #REF! | BK83: =B83-T83-AN83-BH83 -> 9324.54 | BO83: =SUM(BL83:BN83) -> 0 | BS83: =SUM(BP83:BR83) -> 0 | BW83: =SUM(BT83:BV83) -> 0 | CA83: =SUM(BX83:BZ83) -> 0 | CB83: =BO83+BS83+BW83+CA83 -> 0 | CD83: =BK83-CB83 -> 9324.54 | CE83: D.10.9 Mid-term evaluation
A84: D.10.10 Final Evaluation | B84: 17500 | C84: ='budget anual'!C172 -> 0 | G84: =SUM(D84:F84) -> 0 | K84: =SUM(H84:J84) -> 0 | O84: =SUM(L84:N84) -> 0 | S84: =SUM(P84:R84) -> 0 | T84: =G84+K84+O84+S84 -> 0 | V84: =C84-T84 -> 0 | W84: ='budget anual'!D172 -> 0 | AA84: =SUM(X84:Z84) -> 0 | AE84: =SUM(AB84:AD84) -> 0 | AI84: =SUM(AF84:AH84) -> 0 | AM84: =SUM(AJ84:AL84) -> 0 | AN84: =AA84+AE84+AI84+AM84 -> 0 | AP84: =(V84+W84)-AN84 -> 0 | AQ84: ='budget anual'!E172 -> 0 | AU84: =SUM(AR84:AT84) -> 0 | AY84: =SUM(AV84:AX84) -> 0 | BC84: =SUM(AZ84:BB84) -> 0 | BG84: =SUM(BD84:BF84) -> 0 | BH84: =AU84+AY84+BC84+BG84 -> 0 | BJ84: =(AP84+AQ84)-BH84 -> 0 | BK84: =B84-T84-AN84-BH84 -> 17500 | BO84: =SUM(BL84:BN84) -> 0 | BS84: =SUM(BP84:BR84) -> 0 | BT84: 2686.49 | BU84: 4103.35 | BV84: -77.78 | BW84: =SUM(BT84:BV84) -> 6712.06 | BX84: -782.44 | CA84: =SUM(BX84:BZ84) -> -782.44 | CB84: =BO84+BS84+BW84+CA84 -> 5929.62 | CD84: =BK84-CB84 -> 11570.38 | CE84: D.10.10 Final Evaluation
A85: Personnel: Zonal Coordinators & Local Transportation | CB85: =BO85+BS85+BW85+CA85 -> 0 | CD85: =BK85-CB85 -> 0 | CE85: Personnel: Zonal Coordinators & Local Transportation
A86: D.10.11.A Subcontract: Fe y Alegría | B86: 82188 | C86: ='budget anual'!C174 -> #REF! | G86: =SUM(D86:F86) -> 0 | K86: =SUM(H86:J86) -> 0 | O86: =SUM(L86:N86) -> 0 | S86: =SUM(P86:R86) -> 0 | T86: =G86+K86+O86+S86 -> 0 | V86: =C86-T86 -> #REF! | W86: ='budget anual'!D174 -> #REF! | AA86: =SUM(X86:Z86) -> 0 | AE86: =SUM(AB86:AD86) -> 0 | AI86: =SUM(AF86:AH86) -> 0 | AM86: =SUM(AJ86:AL86) -> 0 | AN86: =AA86+AE86+AI86+AM86 -> 0 | AP86: =(V86+W86)-AN86 -> #REF! | AQ86: ='budget anual'!E174 -> #REF! | AU86: =SUM(AR86:AT86) -> 0 | AY86: =SUM(AV86:AX86) -> 0 | BA86: 20000 | BC86: =SUM(AZ86:BB86) -> 20000 | BG86: =SUM(BD86:BF86) -> 0 | BH86: =AU86+AY86+BC86+BG86 -> 20000 | BJ86: =(AP86+AQ86)-BH86 -> #REF! | BK86: =B86-T86-AN86-BH86 -> 62188 | BO86: =SUM(BL86:BN86) -> 0 | BQ86: 5000 | BR86: 4188.4 | BS86: =SUM(BP86:BR86) -> 9188.4 | BW86: =SUM(BT86:BV86) -> 0 | CA86: =SUM(BX86:BZ86) -> 0 | CB86: =BO86+BS86+BW86+CA86 -> 9188.4 | CD86: =BK86-CB86 -> 52999.6 | CE86: D.10.11.A Subcontract: Fe y Alegría
A87: D.10.11.B Subcontract: APRODISO | B87: 12485 | C87: ='budget anual'!C175 -> #REF! | G87: =SUM(D87:F87) -> 0 | K87: =SUM(H87:J87) -> 0 | O87: =SUM(L87:N87) -> 0 | S87: =SUM(P87:R87) -> 0 | T87: =G87+K87+O87+S87 -> 0 | V87: =C87-T87 -> #REF! | W87: ='budget anual'!D175 -> #REF! | AA87: =SUM(X87:Z87) -> 0 | AE87: =SUM(AB87:AD87) -> 0 | AG87: 7000 | AI87: =SUM(AF87:AH87) -> 7000 | AM87: =SUM(AJ87:AL87) -> 0 | AN87: =AA87+AE87+AI87+AM87 -> 7000 | AP87: =(V87+W87)-AN87 -> #REF! | AQ87: ='budget anual'!E175 -> 5485 | AS87: 4404.23 | AU87: =SUM(AR87:AT87) -> 4404.23 | AV87: 1080.84 | AY87: =SUM(AV87:AX87) -> 1080.84 | BC87: =SUM(AZ87:BB87) -> 0 | BG87: =SUM(BD87:BF87) -> 0 | BH87: =AU87+AY87+BC87+BG87 -> 5485.07 | BJ87: =(AP87+AQ87)-BH87 -> #REF! | BK87: =B87-T87-AN87-BH87 -> -0.07 | BO87: =SUM(BL87:BN87) -> 0 | BS87: =SUM(BP87:BR87) -> 0 | BW87: =SUM(BT87:BV87) -> 0 | CA87: =SUM(BX87:BZ87) -> 0 | CB87: =BO87+BS87+BW87+CA87 -> 0 | CD87: =BK87-CB87 -> -0.07 | CE87: D.10.11.B Subcontract: APRODISO
A88: D.10.11.C Subcontract: APROTENG | B88: 39296 | C88: ='budget anual'!C176 -> #REF! | G88: =SUM(D88:F88) -> 0 | K88: =SUM(H88:J88) -> 0 | O88: =SUM(L88:N88) -> 0 | S88: =SUM(P88:R88) -> 0 | T88: =G88+K88+O88+S88 -> 0 | V88: =C88-T88 -> #REF! | W88: ='budget anual'!D176 -> #REF! | AA88: =SUM(X88:Z88) -> 0 | AE88: =SUM(AB88:AD88) -> 0 | AF88: 10000 | AI88: =SUM(AF88:AH88) -> 10000 | AM88: =SUM(AJ88:AL88) -> 0 | AN88: =AA88+AE88+AI88+AM88 -> 10000 | AP88: =(V88+W88)-AN88 -> #REF! | AQ88: ='budget anual'!E176 -> #REF! | AU88: =SUM(AR88:AT88) -> 0 | AX88: 5000 | AY88: =SUM(AV88:AX88) -> 5000 | BC88: =SUM(AZ88:BB88) -> 0 | BG88: =SUM(BD88:BF88) -> 0 | BH88: =AU88+AY88+BC88+BG88 -> 5000 | BJ88: =(AP88+AQ88)-BH88 -> #REF! | BK88: =B88-T88-AN88-BH88 -> 24296 | BM88: 12500 | BO88: =SUM(BL88:BN88) -> 12500 | BQ88: 539.8 | BR88: 771.9 | BS88: =SUM(BP88:BR88) -> 1311.7 | BT88: 1156.9 | BU88: =600+1112.68 -> 1712.68 | BV88: =917.99+125 -> 1042.99 | BW88: =SUM(BT88:BV88) -> 3912.57 | BX88: -7006.22 | CA88: =SUM(BX88:BZ88) -> -7006.22 | CB88: =BO88+BS88+BW88+CA88 -> 10718.05 | CD88: =BK88-CB88 -> 13577.95 | CE88: D.10.11.C Subcontract: APROTENG
A89: D.10.12 Data Base Technician Equipment | B89: 1000 | C89: 0 | T89: =G89+K89+O89+S89 -> 0 | V89: =C89-T89 -> 0 | W89: ='budget anual'!D181 -> #REF! | Y89: 588.93 | AA89: =SUM(X89:Z89) -> 588.93 | AE89: =SUM(AB89:AD89) -> 0 | AI89: =SUM(AF89:AH89) -> 0 | AM89: =SUM(AJ89:AL89) -> 0 | AN89: =AA89+AE89+AI89+AM89 -> 588.93 | AP89: =(V89+W89)-AN89 -> #REF! | AQ89: ='budget anual'!E181 -> 411.07 | AT89: 490.53 | AU89: =SUM(AR89:AT89) -> 490.53 | AY89: =SUM(AV89:AX89) -> 0 | BC89: =SUM(AZ89:BB89) -> 0 | BG89: =SUM(BD89:BF89) -> 0 | BH89: =AU89+AY89+BC89+BG89 -> 490.53 | BJ89: =(AP89+AQ89)-BH89 -> #REF! | BK89: =B89-T89-AN89-BH89 -> -79.46 | BO89: =SUM(BL89:BN89) -> 0 | BS89: =SUM(BP89:BR89) -> 0 | BW89: =SUM(BT89:BV89) -> 0 | CA89: =SUM(BX89:BZ89) -> 0 | CB89: =BO89+BS89+BW89+CA89 -> 0 | CD89: =BK89-CB89 -> -79.46 | CE89: D.10.12 Data Base Technician Equipment
B90: =SUM(B71:B89) -> 284650.24 | C90: =SUM(C72:C89) -> #REF! | D90: =SUM(D72:D89) -> 0 | E90: =SUM(E72:E89) -> 0 | F90: =SUM(F72:F89) -> 1056 | G90: =SUM(G72:G89) -> 1056 | H90: =SUM(H72:H89) -> 1936.8 | I90: =SUM(I72:I89) -> 1914.56 | J90: =SUM(J72:J89) -> -691.75 | ... T90: =SUM(T72:T89) -> 37587.99 | U90: =T90/C90 -> #REF! | V90: =SUM(V72:V89) -> #REF! | W90: =SUM(W72:W89) -> #REF! | X90: =SUM(X72:X89) -> 2116 | Y90: =SUM(Y72:Y89) -> 2331.06 | Z90: =SUM(Z72:Z89) -> 3090.7 | AA90: =SUM(AA72:AA89) -> 7537.76 | AB90: =SUM(AB72:AB89) -> 1753 | AC90: =SUM(AC72:AC89) -> -769.3 | ... AN90: =SUM(AN72:AN89) -> 34460.51 | AO90: =AN90/W90 -> #REF! | AP90: =SUM(AP72:AP89) -> #REF! | AQ90: =SUM(AQ72:AQ89) -> #REF! | AR90: =SUM(AR72:AR89) -> 552.1 | AS90: =SUM(AS72:AS89) -> 5338.03 | AT90: =SUM(AT72:AT89) -> 1716.46 | AU90: =SUM(AU72:AU89) -> 7606.59 | AV90: =SUM(AV72:AV89) -> 10744.88 | AW90: =SUM(AW72:AW89) -> 380.67 | ... BH90: =SUM(BH72:BH89) -> 51823.02 | BI90: =BH90/AQ90 -> #REF! | BJ90: =SUM(BJ72:BJ89) -> #REF! | BK90: =SUM(BK72:BK89) -> 160778.72 | BL90: =SUM(BL72:BL89) -> -184.7 | BM90: =SUM(BM72:BM89) -> 14950 | BN90: =SUM(BN72:BN89) -> 268.87 | BO90: =SUM(BO72:BO89) -> 15034.17 | BP90: =SUM(BP72:BP89) -> 2319 | BQ90: =SUM(BQ72:BQ89) -> 6471.51 | ... CB90: =SUM(CB72:CB89) -> 44581.45 | CC90: =CB90/BK90 -> 0.27728452 | CD90: =SUM(CD72:CD89) -> 116197.27
A91: Output 11: Transparency and Accountability | CE91: Output 11: Transparency and Accountability
A92: 11.1 Stakeholders Presentation of Program Evaluation | B92: =2350/2 -> 1175 | C92: 0 | G92: =SUM(D92:F92) -> 0 | K92: =SUM(H92:J92) -> 0 | O92: =SUM(L92:N92) -> 0 | S92: =SUM(P92:R92) -> 0 | T92: =G92+K92+O92+S92 -> 0 | V92: =C92-T92 -> 0 | W92: 0 | AA92: =SUM(X92:Z92) -> 0 | AE92: =SUM(AB92:AD92) -> 0 | AI92: =SUM(AF92:AH92) -> 0 | AM92: =SUM(AJ92:AL92) -> 0 | AN92: =AA92+AE92+AI92+AM92 -> 0 | AP92: =(V92+W92)-AN92 -> 0 | AQ92: 0 | AU92: =SUM(AR92:AT92) -> 0 | AY92: =SUM(AV92:AX92) -> 0 | BC92: =SUM(AZ92:BB92) -> 0 | BG92: =SUM(BD92:BF92) -> 0 | BH92: =AU92+AY92+BC92+BG92 -> 0 | BJ92: =(AP92+AQ92)-BH92 -> 0 | BK92: =B92-T92-AN92-BH92 -> 1175 | BO92: =SUM(BL92:BN92) -> 0 | BS92: =SUM(BP92:BR92) -> 0 | BW92: =SUM(BT92:BV92) -> 0 | CA92: =SUM(BX92:BZ92) -> 0 | CB92: =BO92+BS92+BW92+CA92 -> 0 | CD92: =BK92-CB92 -> 1175 | CE92: 11.1 Stakeholders Presentation of Program Evaluation
A93: 11.2 Closing Ceremony and Presentation of Program Results | B93: 2250 | C93: 0 | G93: =SUM(D93:F93) -> 0 | K93: =SUM(H93:J93) -> 0 | O93: =SUM(L93:N93) -> 0 | S93: =SUM(P93:R93) -> 0 | T93: =G93+K93+O93+S93 -> 0 | V93: =C93-T93 -> 0 | W93: 0 | AA93: =SUM(X93:Z93) -> 0 | AE93: =SUM(AB93:AD93) -> 0 | AI93: =SUM(AF93:AH93) -> 0 | AM93: =SUM(AJ93:AL93) -> 0 | AN93: =AA93+AE93+AI93+AM93 -> 0 | AP93: =(V93+W93)-AN93 -> 0 | AQ93: 0 | AU93: =SUM(AR93:AT93) -> 0 | AY93: =SUM(AV93:AX93) -> 0 | BC93: =SUM(AZ93:BB93) -> 0 | BG93: =SUM(BD93:BF93) -> 0 | BH93: =AU93+AY93+BC93+BG93 -> 0 | BJ93: =(AP93+AQ93)-BH93 -> 0 | BK93: =B93-T93-AN93-BH93 -> 2250 | BO93: =SUM(BL93:BN93) -> 0 | BS93: =SUM(BP93:BR93) -> 0 | BW93: =SUM(BT93:BV93) -> 0 | CA93: =SUM(BX93:BZ93) -> 0 | CB93: =BO93+BS93+BW93+CA93 -> 0 | CD93: =BK93-CB93 -> 2250 | CE93: 11.2 Closing Ceremony and Presentation of Program Results
B94: =SUM(B92:B93) -> 3425 | C94: =SUM(C92:C93) -> 0 | D94: =SUM(D92:D93) -> 0 | E94: =SUM(E92:E93) -> 0 | F94: =SUM(F92:F93) -> 0 | G94: =SUM(G92:G93) -> 0 | H94: =SUM(H92:H93) -> 0 | I94: =SUM(I92:I93) -> 0 | ... T94: =SUM(T92:T93) -> 0 | U94: 0 | V94: =SUM(V92:V93) -> 0 | W94: =SUM(W92:W93) -> 0 | X94: =SUM(X92:X93) -> 0 | Y94: =SUM(Y92:Y93) -> 0 | Z94: =SUM(Z92:Z93) -> 0 | AA94: =SUM(AA92:AA93) -> 0 | AB94: =SUM(AB92:AB93) -> 0 | AC94: =SUM(AC92:AC93) -> 0 | ... AN94: =SUM(AN92:AN93) -> 0 | AO94: 0 | AP94: =SUM(AP92:AP93) -> 0 | AQ94: =SUM(AQ92:AQ93) -> 0 | AR94: =SUM(AR92:AR93) -> 0 | AS94: =SUM(AS92:AS93) -> 0 | AT94: =SUM(AT92:AT93) -> 0 | AU94: =SUM(AU92:AU93) -> 0 | AV94: =SUM(AV92:AV93) -> 0 | AW94: =SUM(AW92:AW93) -> 0 | ... BH94: =SUM(BH92:BH93) -> 0 | BI94: 0 | BJ94: =SUM(BJ92:BJ93) -> 0 | BK94: =SUM(BK92:BK93) -> 3425 | BL94: =SUM(BL92:BL93) -> 0 | BM94: =SUM(BM92:BM93) -> 0 | BN94: =SUM(BN92:BN93) -> 0 | BO94: =SUM(BO92:BO93) -> 0 | BP94: =SUM(BP92:BP93) -> 0 | BQ94: =SUM(BQ92:BQ93) -> 0 | ... CB94: =SUM(CB92:CB93) -> 0 | CC94: 0 | CD94: =SUM(CD92:CD93) -> 3425
A96: TOTAL PANAMÁ => | B96: =B15+B26+B36+B43+B50+B54+B58+B65+B70+B90+B94 -> #REF! | C96: =C15+C26+C36+C43+C50+C58+C65+C70+C90+C94 -> #REF! | D96: =D15+D26+D36+D43+D50+D58+D65+D70+D90+D94 -> 0 | E96: =E15+E26+E36+E43+E50+E58+E65+E70+E90+E94 -> 10983.64 | F96: =F15+F26+F36+F43+F50+F58+F65+F70+F90+F94 -> 15761.12 | G96: =G15+G26+G36+G43+G50+G58+G65+G70+G90+G94 -> 26744.76 | H96: =H15+H26+H36+H43+H50+H58+H65+H70+H90+H94 -> 34413.73 | I96: =I15+I26+I36+I43+I50+I58+I65+I70+I90+I94 -> 23721.83 | J96: =J15+J26+J36+J43+J50+J58+J65+J70+J90+J94 -> 31989.69 | ... T96: =T15+T26+T36+T43+T50+T58+T65+T70+T90+T94 -> 388569.11 | U96: =T96/C96 -> #REF! | V96: =V15+V26+V36+V43+V50+V58+V65+V70+V90+V94 -> #REF! | W96: =W15+W26+W36+W43+W50+W58+W65+W70+W90+W94 -> #REF! | X96: =X15+X26+X36+X43+X50+X58+X65+X70+X90+X94 -> 86860.55 | Y96: =Y15+Y26+Y36+Y43+Y50+Y58+Y65+Y70+Y90+Y94 -> 22379.77 | Z96: =Z15+Z26+Z36+Z43+Z50+Z58+Z65+Z70+Z90+Z94 -> 24760.14 | AA96: =AA15+AA26+AA36+AA43+AA50+AA58+AA65+AA70+AA90+AA94 -> 134000.46 | AB96: =AB15+AB26+AB36+AB43+AB50+AB58+AB65+AB70+AB90+AB94 -> 26145.12 | AC96: =AC15+AC26+AC36+AC43+AC50+AC58+AC65+AC70+AC90+AC94 -> 18336.94 | ... AN96: =AN15+AN26+AN36+AN43+AN50+AN58+AN65+AN70+AN90+AN94 -> 532382.43 | AO96: =AN96/W96 -> #REF! | AP96: =AP15+AP26+AP36+AP43+AP50+AP58+AP65+AP70+AP90+AP94 -> #REF! | AQ96: =AQ15+AQ26+AQ36+AQ43+AQ50+AQ58+AQ65+AQ70+AQ90+AQ94 -> #REF! | AR96: =AR15+AR26+AR36+AR43+AR50+AR58+AR65+AR70+AR90+AR94 -> 46952.89 | AS96: =AS15+AS26+AS36+AS43+AS50+AS58+AS65+AS70+AS90+AS94 -> 40321.74 | AT96: =AT15+AT26+AT36+AT43+AT50+AT58+AT65+AT70+AT90+AT94 -> 43322.07 | AU96: =AU15+AU26+AU36+AU43+AU50+AU58+AU65+AU70+AU90+AU94 -> 130596.7 | AV96: =AV15+AV26+AV36+AV43+AV50+AV58+AV65+AV70+AV90+AV94 -> 32240.62 | AW96: =AW15+AW26+AW36+AW43+AW50+AW58+AW65+AW70+AW90+AW94 -> 21179.66 | ... BD96: =BD15+BD26+BD36+BD43+BD50+BD58+BD65+BD70+BD90+BD94 -> 35722.62 | BE96: =BE15+BE26+BE36+BE43+BE50+BE58+BE65+BE70+BE90+BE94+BE54 -> 31160.15 | BF96: =BF15+BF26+BF36+BF43+BF50+BF58+BF65+BF70+BF90+BF94+BF54 -> 83146.99 | BG96: =BG15+BG26+BG36+BG43+BG50+BG58+BG65+BG70+BG90+BG94+BG54 -> 150029.76 | BH96: =BH15+BH26+BH36+BH43+BH50+BH58+BH65+BH70+BH90+BH94+BH54 -> 509630.17 | BI96: =BH96/AQ96 -> #REF! | BJ96: =BJ15+BJ26+BJ36+BJ43+BJ50+BJ58+BJ65+BJ70+BJ90+BJ94+BJ54 -> #REF! | BK96: =BK15+BK26+BK36+BK43+BK50+BK58+BK65+BK70+BK90+BK94+BK54 -> #REF! | BL96: =BL15+BL26+BL36+BL43+BL50+BL58+BL65+BL70+BL90+BL94+BL54 -> 29752.81 | BM96: =BM15+BM26+BM36+BM43+BM50+BM58+BM65+BM70+BM90+BM94+BM54 -> 63993.26 | BN96: =BN15+BN26+BN36+BN43+BN50+BN58+BN65+BN70+BN90+BN94+BN54 -> 25828.39 | BO96: =BO15+BO26+BO36+BO43+BO50+BO58+BO65+BO70+BO90+BO94+BO54 -> 119574.46 | BP96: =BP15+BP26+BP36+BP43+BP50+BP58+BP65+BP70+BP90+BP94+BP54 -> 61939.17 | BQ96: =BQ15+BQ26+BQ36+BQ43+BQ50+BQ58+BQ65+BQ70+BQ90+BQ94+BQ54 -> 53801.47 | ... CB96: =CB15+CB26+CB36+CB43+CB50+CB58+CB65+CB70+CB90+CB94+CB54 -> 575158.71 | CC96: =CB96/BK96 -> #REF! | CD96: =CD15+CD26+CD36+CD43+CD50+CD58+CD65+CD70+CD90+CD94+CD54 -> #REF! | CE96: TOTAL PANAMÁ =>
A99: Según reporte => | D99: 0 | E99: 10983.64 | F99: 15761.12 | H99: 34413.73 | I99: 23721.83 | J99: 31989.69 | L99: 33790.32 | M99: 35628.96 | N99: 19461.56 | P99: 34366.92 | Q99: 117397.93 | R99: 31053.41 | T99: =SUM(D99:R99) -> 388569.11 | X99: 86860.549 | Y99: 22379.77 | Z99: 24760.14 | AB99: 26145.12 | AC99: 18336.94 | AD99: 88367.05 | AF99: 49254.73 | AG99: 35847.11 | AH99: 45786.53 | AJ99: 33523.52 | AK99: 61856 | AL99: 39264.97 | AN99: =SUM(X99:AL99) -> 532382.43 | AR99: 46952.89 | AS99: 40321.74 | AT99: 43322.07 | AV99: 32240.62 | AW99: 21179.66 | AX99: 34855.93 | AZ99: 31332.47 | BA99: 84527.3 | BB99: 24867.73 | BD99: 35722.62 | BE99: 31160.15 | BF99: 83146.99 | BH99: =SUM(AR99:BF99) -> 509630.17 | BL99: 29752.81 | BM99: 63993.26 | BN99: 25828.39 | BP99: 61939.17 | BQ99: 53801.47 | BR99: 82018.45 | BT99: 47495.3 | BU99: =52602.35-505 -> 52097.35 | BV99: 65282.28 | BX99: 32228.19 | BY99: 22211.2 | BZ99: 38510.84 | CB99: =SUM(BL99:BZ99) -> 575158.71
D100: =D96-D99 -> 0 | E100: =E96-E99 -> 0 | F100: =F96-F99 -> 0 | H100: =H96-H99 -> 0 | I100: =I96-I99 -> 0 | J100: =J96-J99 -> 0 | L100: =L96-L99 -> 0 | M100: =M96-M99 -> 0 | N100: =N96-N99 -> 0 | P100: =P96-P99 -> 0 | Q100: =Q96-Q99 -> 0 | R100: =R96-R99 -> 0 | X100: =X96-X99 -> 0.001 | Y100: =Y96-Y99 -> 0 | Z100: =Z96-Z99 -> 0 | AB100: =AB96-AB99 -> 0 | AC100: =AC96-AC99 -> 0 | AD100: =AD96-AD99 -> 0 | AF100: =AF96-AF99 -> 0 | AG100: =AG96-AG99 -> 0 | AH100: =AH96-AH99 -> 0 | AJ100: =AJ96-AJ99 -> 0 | AK100: =AK96-AK99 -> 0 | AL100: =AL96-AL99 -> 0 | AR100: =AR96-AR99 -> 0 | AS100: =AS96-AS99 -> 0 | AT100: =AT96-AT99 -> 0 | AV100: =AV96-AV99 -> 0 | AW100: =AW96-AW99 -> 0 | AX100: =AX96-AX99 -> 0 | AZ100: =AZ96-AZ99 -> 0 | BA100: =BA96-BA99 -> 0 | BB100: =BB96-BB99 -> 0 | BD100: =BD96-BD99 -> 0 | BE100: =BE96-BE99 -> 0 | BF100: =BF96-BF99 -> 0 | BL100: =BL96-BL99 -> 0 | BM100: =BM96-BM99 -> 0 | BN100: =BN96-BN99 -> 0 | BP100: =BP96-BP99 -> 0 | BQ100: =BQ96-BQ99 -> 0 | BR100: =BR96-BR99 -> 0 | BT100: =BT96-BT99 -> 0 | BU100: =BU96-BU99 -> 0 | BV100: =BV96-BV99 -> 0 | BX100: =BX96-BX99 -> 0 | BY100: =BY96-BY99 -> 0 | BZ100: =BZ96-BZ99 -> 0 | CB100: =CB99+BH99+AN99+T99 -> 2005740.4
A104: PARA USO INTERNO | CE104: PARA USO INTERNO

Sheet budget anual
A1: PRESUPUESTO EDUCAFUTURO - APROBADO EN DICIEMBRE 2015
A4: BUDGET ITEM | B4: PANAMA | C4: AÑO 2013 | D4: AÑO 2014 | E4: AÑO 2015 | F4: AÑO 2016 | G4: TOTAL
A6: Sub-Total Direct Labor | B6: 657695.3 | C6: =#REF! -> #REF! | D6: =#REF! -> #REF! | E6: 131000 | F6: 190392.78 | G6: =SUM(C6:F6) -> #REF!
A7: Fringe Benefits - Ecuador
A8: Fringe Benefits - Panama | B8: 228456 | C8: =#REF! -> #REF! | D8: =#REF! -> #REF! | E8: =#REF! -> #REF! | F8: 104843.87 | G8: =SUM(C8:F8) -> #REF!
A9: Fringe Benefits - Home Office (32.40%)
A11: Total Direct Labor | B11: =SUM(B6:B10) -> 886151.3 | C11: =SUM(C6:C10) -> #REF! | D11: =SUM(D6:D10) -> #REF! | E11: =SUM(E6:E10) -> #REF! | F11: =SUM(F6:F10) -> 295236.65 | G11: =SUM(G6:G10) -> #REF!
A12: Housing Allowance
A13: Living Expenses - Education Specialist | G13: =SUM(C13:F13) -> 0
A15: Total Housing | B15: =SUM(B13:B14) -> 0 | C15: =SUM(C13:C14) -> 0 | D15: =SUM(D13:D14) -> 0 | E15: =SUM(E13:E14) -> 0 | F15: =SUM(F13:F14) -> 0 | G15: =SUM(G13:G14) -> 0
A16: Equipment
A17: Total Equipment | B17: 11655 | C17: 11655 | D17: 0 | E17: 0 | F17: 0 | G17: =SUM(C17:F17) -> 11655
A18: Office Expenses
A19: Courier fees/services | B19: 1400 | C19: 350 | D19: 350 | E19: 350 | F19: 350 | G19: =SUM(C19:F19) -> 1400
A20: Email/Internet | B20: 1680 | C20: 420 | D20: 420 | E20: 420 | F20: 420 | G20: =SUM(C20:F20) -> 1680
A21: Telephone (cellular and land line) | B21: 3120 | C21: 780 | D21: 780 | E21: 780 | F21: 780 | G21: =SUM(C21:F21) -> 3120
A22: Computer Supplies | B22: 1200 | C22: 300 | D22: 300 | E22: 300 | F22: 300 | G22: =SUM(C22:F22) -> 1200
A23: Office Supplies | B23: 2400 | C23: 600 | D23: 600 | E23: 600 | F23: 600 | G23: =SUM(C23:F23) -> 2400
A24: Office rent (Ecuador @ 25%) | B24: 0 | C24: 0 | D24: 0 | E24: 0 | F24: 0 | G24: =SUM(C24:F24) -> 0
A25: Office rent (Panama @ 100%) | B25: 62400 | C25: 15600 | D25: 15600 | E25: 15600 | F25: 15600 | G25: =SUM(C25:F25) -> 62400
A26: Office Utilities | B26: 4800 | C26: 1200 | D26: 1200 | E26: 1200 | F26: 1200 | G26: =SUM(C26:F26) -> 4800
A27: Vehicle Maintenance/repairs/spare parts/gasoline | B27: 6000 | C27: 1500 | D27: 1500 | E27: 1500 | F27: 1500 | G27: =SUM(C27:F27) -> 6000
A28: Banking and Cash Handling Fees | B28: =9600/2 -> 4800 | C28: 1200 | D28: 1200 | E28: 1200 | F28: 1200 | G28: =SUM(C28:F28) -> 4800
A29: Equipment and Office Repairs and Maintenance | B29: 1000 | C29: 250 | D29: 250 | E29: 250 | F29: 250 | G29: =SUM(C29:F29) -> 1000
A30: Audit Costs (A-133) | B30: 20000 | C30: 5000 | D30: 5000 | E30: 5000 | F30: 5000 | G30: =SUM(C30:F30) -> 20000
A31: Property and Liability Insurance | B31: 4000 | C31: 1000 | D31: 1000 | E31: 1000 | F31: 1000 | G31: =SUM(C31:F31) -> 4000
A32: Legal Fees | B32: 1000 | C32: 0 | D32: 250 | E32: 500 | F32: 250 | G32: =SUM(C32:F32) -> 1000
A34: Total Office Expenses | B34: =SUM(B19:B33) -> 113800 | C34: =SUM(C19:C33) -> 28200 | D34: =SUM(D19:D33) -> 28450 | E34: =SUM(E19:E33) -> 28700 | F34: =SUM(F19:F33) -> 28450 | G34: =SUM(G19:G33) -> 113800
A35: Output 1: Education
A36: 1.1 Entrena: Quantum Learning for Teachers | G36: =SUM(C36:F36) -> 0
A37: Airfare DR-Panama-Ecuador | G37: =SUM(C37:F37) -> 0
A38: Lodging and per diem Trainer | G38: =SUM(C38:F38) -> 0
A39: 1.2 Entrena: EpC Facilitators Training | G39: =SUM(C39:F39) -> 0
A40: Lodging and per diem Trainer | G40: =SUM(C40:F40) -> 0
A41: 1.3 EpC Adaptation and Implementation - J.Helwig | G41: =SUM(C41:F41) -> 0
A42: Airfare CR-Panama-Ecuador | G42: =SUM(C42:F42) -> 0
A43: Lodging and per diem J. Helwig | G43: =SUM(C43:F43) -> 0
A44: 1.4 Entrena: EpC Material Adaptation | G44: =SUM(C44:F44) -> 0
A45: Airfare DR-Panama-Ecuador | G45: =SUM(C45:F45) -> 0
A46: Lodging and per diem Staff | G46: =SUM(C46:F46) -> 0
A47: EpC Translation to Indigenous Languages | G47: =SUM(C47:F47) -> 0
A48: Material Design and Printing | B48: 57971.5 | C48: =#REF! -> #REF! | D48: =#REF! -> #REF! | E48: 19226.86 | G48: =SUM(C48:F48) -> #REF!
A49: 1.5 Entrena: Trainer of Trainers for Quantum Learning and EpC | G49: =SUM(C49:F49) -> 0
A50: Airfare DR-Panama-Ecuador | G50: =SUM(C50:F50) -> 0
A51: Lodging and per diem Trainer | G51: =SUM(C51:F51) -> 0
A52: 1.6 Local Workshops venue and logistics | B52: 64000 | C52: =#REF! -> #REF! | D52: =#REF! -> #REF! | E52: 18244.38 | G52: =SUM(C52:F52) -> #REF!
A53: 1.7 Short Term Education Consultant Support | B53: 18200 | C53: 0 | D53: 15500 | E53: 2700 | G53: =SUM(C53:F53) -> 18200
G54: =SUM(C54:F54) -> 0
A55: Implementation of EpC Activities: | G55: =SUM(C55:F55) -> 0
A56: Fe y Alegria Direct Activities | B56: 279900 | C56: =#REF! -> #REF! | D56: =#REF! -> #REF! | E56: =#REF! -> #REF! | F56: 94101.89 | G56: =SUM(C56:F56) -> #REF!
A57: Subcontract: APRODISO | B57: 21282.5 | C57: 0 | D57: 21282.5 | E57: 0 | F57: 0 | G57: =SUM(C57:F57) -> 21282.5
A58: Subcontract: APROTENGB | B58: 84000 | C58: =#REF! -> #REF! | D58: =#REF! -> #REF! | E58: =#REF! -> #REF! | F58: 7533 | G58: =SUM(C58:F58) -> #REF!
A59: Subcontract: Comunidec | G59: =SUM(C59:F59) -> 0
A60: Subcontract: Fudela | G60: =SUM(C60:F60) -> 0
A61: Subcontract: Expoflores | G61: =SUM(C61:F61) -> 0
A62: EducaFuturo Darién | B62: 50228 | C62: 0 | D62: 0 | E62: 28110.13 | F62: 22117.87 | G62: =SUM(C62:F62) -> 50228
A63: Subcontract: J.Perez | G63: =SUM(C63:F63) -> 0
A64: Subcontract: Aurora | G64: =SUM(C64:F64) -> 0
A65: Subcontract: Mercado | G65: =SUM(C65:F65) -> 0
A66: Subcontract: Juconi | G66: =SUM(C66:F66) -> 0
A67: Subcontract: CPR | G67: =SUM(C67:F67) -> 0
A68: Subcontract: Telefonica | G68: =SUM(C68:F68) -> 0
G69: =SUM(C69:F69) -> 0
A70: Total Output 1 | B70: =SUM(B35:B69) -> 575582 | C70: =SUM(C35:C69) -> #REF! | D70: =SUM(D35:D69) -> #REF! | E70: =SUM(E35:E69) -> #REF! | F70: =SUM(F35:F69) -> 123752.76 | G70: =SUM(G35:G69) -> #REF!
A71: Output 2: Livelihoods
A72: 2.1 Value Chain Analysis | B72: 4000 | C72: 0 | D72: 0 | E72: 0 | F72: 4000 | G72: =SUM(C72:F72) -> 4000
A73: 2.2 Linking Households to Livelihood Programs | B73: 3525 | C73: =#REF! -> #REF! | D73: =#REF! -> #REF! | E73: =#REF! -> #REF! | F73: 2951.71 | G73: =SUM(C73:F73) -> #REF!
A74: 2.3 Technical Assistance to Develop Links to Business Activities | B74: 7500 | C74: =#REF! -> #REF! | D74: =#REF! -> #REF! | E74: =#REF! -> #REF! | F74: 2950 | G74: =SUM(C74:F74) -> #REF!
A75: 2.5 Literacy Fund | G75: =SUM(C75:F75) -> 0
A76: Subcontracts: | G76: =SUM(C76:F76) -> 0
A77: Subcontract: TBD | G77: =SUM(C77:F77) -> 0
A78: Subcontract: Casa Esperanza | G78: =SUM(C78:F78) -> 0
A79: Subcontract: FE Y ALEGRÍA | B79: 35000 | C79: 0 | D79: 0 | E79: 0 | F79: 35000 | G79: =SUM(C79:F79) -> 35000
A80: Subcontract: APRODISO | C80: 0 | D80: 0 | E80: 0 | F80: 0 | G80: =SUM(C80:F80) -> 0
A81: Subcontract: APROTENGB | B81: 14000 | C81: 0 | D81: 0 | E81: 1500 | F81: 12500 | G81: =SUM(C81:F81) -> 14000
A82: Subcontract: Comunidec | G82: =SUM(C82:F82) -> 0
A83: Subcontract: Fudela | G83: =SUM(C83:F83) -> 0
A84: Subcontract: Expoflores | G84: =SUM(C84:F84) -> 0
A85: EducaFuturo Darién | B85: 30000 | C85: 0 | D85: 0 | E85: 40 | F85: 29960 | G85: =SUM(C85:F85) -> 30000
A86: Total Output 2 | B86: =SUM(B72:B85) -> 94025 | C86: =SUM(C72:C85) -> #REF! | D86: =SUM(D72:D85) -> #REF! | E86: =SUM(E72:E85) -> #REF! | F86: =SUM(F72:F85) -> 87361.71 | G86: =SUM(G72:G85) -> #REF!
A87: Output 3: Social Protection
A88: 3.1 Social Protecion Services in Targeted Communities | B88: 2500 | C88: 0 | D88: 0 | E88: 0 | F88: 2500 | G88: =SUM(C88:F88) -> 2500
A89: Subcontract: FE Y ALEGRÍA | B89: 4687.5 | C89: 0 | D89: 0 | E89: 0 | F89: 4687.5 | G89: =SUM(C89:F89) -> 4687.5
A90: Subcontract: APRODISO | B90: 0 | C90: 0 | D90: 0 | E90: 0 | F90: 0 | G90: =SUM(C90:F90) -> 0
A91: Subcontract: APROTENGB | B91: 1875 | C91: 0 | D91: 0 | E91: 0 | F91: 1875 | G91: =SUM(C91:F91) -> 1875
A92: Subcontract: Comunidec | C92: 0 | D92: 0 | E92: 0 | F92: 0 | G92: =SUM(C92:F92) -> 0
A93: Subcontract: Fudela | C93: 0 | D93: 0 | E93: 0 | F93: 0 | G93: =SUM(C93:F93) -> 0
A94: Subcontract: Expoflores | C94: 0 | D94: 0 | E94: 0 | F94: 0 | G94: =SUM(C94:F94) -> 0
A95: EducaFuturo Darién | B95: 4500 | C95: 0 | D95: 0 | E95: 0 | F95: 4500 | G95: =SUM(C95:F95) -> 4500
A96: Total Output 3 | B96: =SUM(B88:B95) -> 13562.5 | C96: =SUM(C88:C95) -> 0 | D96: =SUM(D88:D95) -> 0 | E96: =SUM(E88:E95) -> 0 | F96: =SUM(F88:F95) -> 13562.5 | G96: =SUM(G88:G95) -> 13562.5
A97: Output 4: Youth Employment
A98: 4.1 A Ganar Quality Control | B98: 15000 | C98: =#REF! -> #REF! | D98: =#REF! -> #REF! | E98: 10761.22 | G98: =SUM(C98:F98) -> #REF!
A99: 4.2 A Ganar Training | C99: 0 | G99: =SUM(C99:F99) -> 0
A100: Subcontracts: | C100: 0 | G100: =SUM(C100:F100) -> 0
A101: Subcontract: Cospae | B101: 165353 | C101: 0 | D101: 76000 | E101: 2410 | F101: 86943 | G101: =SUM(C101:F101) -> 165353
A102: Subcontract: Fudela | C102: 0 | G102: =SUM(C102:F102) -> 0
A103: EducaFuturo A Ganar Panamá | B103: 49500 | C103: 0 | D103: 0 | E103: 5596.47 | F103: 43903.53 | G103: =SUM(C103:F103) -> 49500
A104: Subcontract: Expoflores | C104: 0 | G104: =SUM(C104:F104) -> 0
A105: Subcontract: Comunidec | C105: 0 | G105: =SUM(C105:F105) -> 0
A106: Subcontract: APROTENGB | B106: 27000 | C106: 0 | D106: 0 | E106: 0 | F106: 27000 | G106: =SUM(C106:F106) -> 27000
...

Sheet Hoja1
A1: Project to Combat Child Labor among Vulnerable Populations in Ecuador and Panama by Providing Direct Education and Livelihoods Services SGA-12-11
A2: Partners of the Americas - Project Revision March, 2014
A4: aprobada en mayo
A5: BUDGET ITEM | D5: PANAMA
A6: Direct Labor
A7: Key Personnel
A8: Project Director (100%), | D8: 338923.16
A9: Education Specialist (100%),
A10: Livelihoods Specialist (100%),
A11: M&E Officer (100%), | D11: 147272.52
A12: Finance/Administrative Manager (100%), | D12: 138285.34
A13: Other Proposed Staff
A14: Education Coordinator (100%) | D14: =7000 -> 7000
A15: Livelihoods Coordinator (100%) + Education Coordinator | D15: 61290.84
A16: SubProject Director / M&E Coordinator (100%)
A17: Finance/Administration Officer (50%)
A18: Data Base Technician - Ecuador
A19: Data Base Technician - Panama | D19: 9600
A20: Home Office Support
A21: Project Management Support (50%)
A23: Sub-Total Direct Labor | B23: Personnel | C23: PERSNL | D23: =SUM(D6:D22) -> 702371.86
A24: Fringe Benefits - Ecuador (25%)
A25: Fringe Benefits - Panama (27%) | B25: Fringe Benefits | C25: FRINGE | D25: =184917.88+2266.48+686.31+7000+1 -> 194871.67
A26: Fringe Benefits - Home Office (25%)
A28: Total Direct Labor | D28: =SUM(D23:D27) -> 897243.53
A29: Housing Allowance
A30: Living Expenses - Education Specialist
A31: Total Housing | D31: =SUM(D29:D30) -> 0
A32: Equipment | B32: Equipment | C32: EQUIP | D32: =12250-595 -> 11655
A34: Total Equipment | D34: =SUM(D32:D33) -> 11655
A35: Office Expenses
A36: Courier fees/services | B36: Communications | C36: COMM | D36: =1400+440 -> 1840
A37: Email/Internet | B37: Communications | C37: COMM | D37: 1680
A38: Telephone (cellular and land line) | B38: Communications | C38: COMM | D38: 3120 | E38: =SUM(D36:D38) -> 6640
A39: Computer Supplies | B39: Supplies | C39: SUPPLIES | D39: 1200
A40: Office Supplies | B40: Supplies | C40: SUPPLIES | D40: 2400
A41: Office rent (Ecuador @ 25%) | D41: 0
A42: Office rent (Panama @ 100%) | B42: Rent & Utilities | C42: RENT & UT | D42: 62400
A43: Office Utilities | B43: Rent & Utilities | C43: RENT & UT | D43: 4800
A44: Vehicle Maintenance/repairs/spare parts/gasoline | B44: Equipment & Maint. Repair | C44: EQ.MNT REP | D44: 6000
A45: Banking and Cash Handling Fees | B45: Bank Fees | C45: BANK FEES | D45: =9600/2 -> 4800
A46: Equipment and Office Repairs and Maintenance | B46: Equipment & Maint. Repair | C46: EQ.MNT REP | D46: 1000
A47: Audit Costs (A-133) | B47: Audit | C47: AUDIT | D47: 20000
A48: Property and Liability Insurance | B48: Insurance | C48: INSURANCE | D48: 4000
A49: Legal Fees | B49: Legal Fees | C49: LEGAL | D49: 1000
A51: Total Office Expenses | D51: =SUM(D35:D50) -> 114240
A52: Output 1: Education
A53: EpC Translation to Indigenous Languages | B53: EPC Translations to Indigenous Languages & Matl Design Print | C53: D.1.5.A | D53: 5000
A54: Material Design and Printing | B54: EPC Translations to Indigenous Languages & Matl Design Print | C54: D.1.5.A | D54: =14500/2 -> 7250
A55: 1.6 Local Workshops venue and logistics | B55: Local Workshops Venue and Logistics | C55: D.1.6 | D55: 46000
A56: 1.7 Short Term Education Consultant Support | B56: Short Term Education Consultant Support | C56: D.1.7 | D56: 9000
A57: Implementation of EpC Activities:
A58: Fe y Alegria Direct Activities | B58: Fey y Alegria Direct Activities | C58: D.1.8.A | D58: =207900+72000 -> 279900
A59: Subcontract: APRODISO | B59: Subcontract: APRODISO - Education | C59: D.1.8.B | D59: =52500+42000 -> 94500
A60: Subcontract: APROTENG | B60: Subcontract: APROTENGB - Education | C60: D.1.8.C | D60: 84000
A61: Total Output 1 | D61: =SUM(D52:D60) -> 525650
A62: Output 2: Livelihoods
A63: 2.1 Value Chain Analysis | B63: Value Chain Analysis | C63: D.2.1 | D63: 4000
A64: 2.2 Linking Households to Livelihood Programs | B64: Linking Households to Livelihood Programs | C64: D.2.2 | D64: 3525
A65: 2.3 Technical Assistance to Develop Links to Business Activities | B65: Tech Assist.to Develop Links to Business Activities | C65: D.2.3 | D65: 16500
A66: Subcontracts:
A67: Subcontract: Fe y Alegría | B67: Subcontract: Fe y Alegria - Livelihoods | C67: D.2.5.A | D67: =14000+21000 -> 35000
A68: Subcontract: APRODISO | B68: Subcontract: APRODISO - Livelihoods | C68: D.2.5.B | D68: =14000+21000 -> 35000
A69: Subcontract: APROTENG | B69: Subcontract: APROTENGB - Livelihoods | C69: D.2.5.C | D69: =14000 -> 14000
A71: Total Output 2 | D71: =SUM(D62:D70) -> 108025
A72: Output 3: Social Protection
A73: 3.1 Social Protecion Services in Targeted Communities | B73: Social Protection Svs. In Targated Communities | C73: D.3.1 | D73: 2500 | E73: ojo: esto hay que dividirlo con Ecuador
A74: Subcontracts:
A75: Subcontract: Fe y Alegría | B75: Subcontract: Fe y Alegria - Social Protection | C75: D.3.2.A | D75: =1875+2812.5 -> 4687.5
A76: Subcontract: APRODISO | B76: Subcontract: APRODISO - Social Protection | C76: D.3.2.B | D76: =1875+2812.5 -> 4687.5
A77: Subcontract: APROTENG | B77: Subcontract: APROTENGB - Social Protection | C77: D.3.2.C | D77: 1875
A78: Total Output 3 | D78: =SUM(D72:D77) -> 13750
A79: Output 4: Youth Employment
A80: 4.1 A Ganar Quality Control | B80: Aganar Quality Control | C80: D.4.1 | D80: 5000
A81: Subcontracts:
A82: Subcontract: Cospae | B82: Subcontractor: CoSPAE | C82: D.4.3 | D82: 189000
A83: Total Output 4 | D83: =SUM(D79:D82) -> 194000
A84: Output 5: Public-Private Partnerships
A85: 5.1 Task Mapping Risk Assessment
A86: 5.2 CSR Technical Review
A87: Travel and Per Diem
A88: Airfare DC-Panama-Ecuador - D.Mull
A89: Per Diem - D. Mull
A91: Total Output 5 | D91: =SUM(D84:D90) -> 0
A93: Output 6: Strengthening Nexus between Education and Labor Policies
A94: 6.1 Local Stakeholders Event | B94: Local Stakeholders Event | C94: D.6.1 | D94: 2375
A95: 6.2 Data Collection Training Workshops | B95: Data Collection Training Workshops | C95: D.6.2 | D95: 2750
A97: Total Output 6 | D97: =SUM(D93:D96) -> 5125
A98: Output 7: Child Labor and Disability
A99: 7.1 Adaptive Devices for Children with Disabilities
A100: 7.2 Special Transporation for Mobilizing Children/Parents with Disabilities
A101: 7.3 A Ganar Program Adaptation for Youth with Disabilities
A102: Subcontracts:
A103: Subcontract: Campopiano
A104: Subcontract: Comunidec (Esmeralda)
A105: Subcontract: Fudela (Cañar y Azuay)
A106: Subcontract: ExpoFlores (Imbabura)
A107: Total Output 7 | D107: =SUM(D98:D106) -> 0
A108: Output 8: Raising Awareness
A109: 8.1 Community Based Awareness Raising Workshop | B109: Community Based Awareness Raising Workshop[ | C109: D.8.1 | D109: 3250
...
