Workbook

Sheet Budget Summary
A1: Partners of the Americas
A2: FY 2025 Educational and Cultural Exchange Programs // Partners of the Americas' Education and Culture Program
A3: Assistance Listing 19.415 / Funding Opportunity #DFOP0017214
A4: Table A1: Estimated Unobligated Funds
A5: Grant Program Function | B5: Federal | C5: Non-Federal | D5: Total
A6: Participant Costs | B6: =SUM('FY25 Budget Details'!Q44:Q49,'FY25 Budget Details'!Q57) -> 84778.667 | C6: =SUM('FY25 Budget Details'!R44:R49,'FY25 Budget Details'!R57) -> 20000 | D6: =B6+C6 -> 104778.67
A7: Participant costs per participant | B7: =B6/B12 -> 4238.9333 | C7: =C6/B12 -> 1000 | D7: =B7+C7 -> 5238.9333
A8: Non-Participant Support Costs | B8: =B27-B6 -> 159350.33 | C8: =C27-C6 -> 53869.6 | D8: =B8+C8 -> 213219.93
A9: Non-Participant costs per participant | B9: =B8/B12 -> 7967.5167 | C9: =C8/B12 -> 2693.48 | D9: =B9+C9 -> 10660.997
A10: Total Costs | B10: =B6+B8 -> 244129 | C10: =C6+C8 -> 73869.6 | D10: =B10+C10 -> 317998.6
A11: Total costs per participant | B11: =B7+B9 -> 12206.45 | C11: =C7+C9 -> 3693.48 | D11: =B11+C11 -> 15899.93
A12: Number of participants | B12: =+'FY25 Budget Details'!N44 -> 20
A14: Section B: Budget Categories
A15: Table B1: Grant Program Function or Activity
A16: Budget Categories | B16: Federal | C16: Non-Federal | D16: Total
A17: 1. Personnel | B17: =+'FY25 Budget Details'!Q28 -> 76086.094 | C17: ='FY25 Budget Details'!R28 -> 0 | D17: =SUM(B17:C17) -> 76086.094
A18: 2. Fringe Benefits | B18: =+'FY25 Budget Details'!Q32 -> 17857.406 | C18: ='FY25 Budget Details'!R32 -> 0 | D18: =SUM(B18:C18) -> 17857.406
A19: 3. Travel | B19: =+'FY25 Budget Details'!Q50 -> 71897.695 | C19: ='FY25 Budget Details'!R50 -> 0 | D19: =SUM(B19:C19) -> 71897.695
A20: 4. Equipment | B20: =+'FY25 Budget Details'!Q51 -> 0
A21: 5. Supplies | B21: =+'FY25 Budget Details'!Q54 -> 234 | C21: ='FY25 Budget Details'!R54 -> 1998 | D21: =SUM(B21:C21) -> 2232
A22: 6. Contractual | B22: =+'FY25 Budget Details'!Q60 -> 39200 | C22: ='FY25 Budget Details'!R60 -> 35000 | D22: =SUM(B22:C22) -> 74200
A23: 7. Construction | B23: =+'FY25 Budget Details'!Q61 -> 0
A24: 8. Other Direct Costs | B24: =+'FY25 Budget Details'!Q84 -> 7010.8918 | C24: ='FY25 Budget Details'!R84 -> 36871.6 | D24: =SUM(B24:C24) -> 43882.492
A25: 9. Total Direct Costs (lines 1-8) | B25: =SUM(B17:B24) -> 212286.09 | C25: ='FY25 Budget Details'!R85 -> 73869.6 | D25: =SUM(B25:C25) -> 286155.69
A26: 10. Indirect Costs* | B26: =+'FY25 Budget Details'!Q88 -> 31842.913 | C26: ='FY25 Budget Details'!R88 -> 0 | D26: =SUM(B26:C26) -> 31842.913
A27: 11. Total Costs (lines 9-10) | B27: =B26+B25 -> 244129 | C27: ='FY25 Budget Details'!R89 -> 73869.6 | D27: =SUM(B27:C27) -> 317998.6

Sheet FY25 Budget Details
C1: Partners of the Americas
A2: Program/Dept. | B2: 40300 | C2: FY 2025 Educational and Cultural Exchange Programs (ECE) Funds
A3: Grant: | B3: DOS289 | C3: Assistance Listing 19.415 / Funding Opportunity #DFOP0017214
C4: September 1, 2025 - February 28, 2027
G6: COLUMN 1 | K6: COLUMN 2 | Q6: COLUMN 3 | R6: COLUMN 4 | S6: COLUMN 5 | T6: COLUMN 6
A7: Budget Code | B7: Account Code | C7: Budget Category FY2024 | G7: Approved FY 2024 ECA Funding Level | H7: FY 2024 Cost Sharing | I7: FY2024 Actual Budget (ACTUALS as of APRIL 30, 2025) | J7: FY2024 Projected Budget (May 2025 - Apr 2026) | K7: FY 2024 Total Budget | M7: Budget Category FY2025 | Q7: FY 2025 ECA Funds Request | R7: FY 2025 Cost Sharing | S7: FY 2025 Total Budget | T7: % Change
C8: I. Salaries | D8: MONTHS | E8: LOE | F8: UNIT COST | M8: I. Salaries | N8: MONTHS | O8: LOE | P8: UNIT COST
A9: PERSNL | B9: 50000 (Timesheets) | C9: 1. Senior Director - $12,168/Month Aug 2024 - Apr 2026 at 3-5% LOE | F9: =146016/12 -> 12168 | G9: 2500 | H9: 0 | I9: 0 | J9: =+(D9*E9*F9)+(D10*E10*F10)+(D11*E11*F11)+(D12*E12*F12)+(D13*E13*F13)+(D14*E14*F14) -> 4915.872 | K9: =+I9+J9 -> 4915.872 | L9: =+G9-K9 -> -2415.872 | M9: 1. Senior Director - $12,168/Month Sep 2025 - Feb 2027 at 5% LOE | P9: 12168 | Q9: =+(N9*O9*P9)+(N10*O10*P10)+(N11*O11*P11)+(N12*O12*P12)+(N13*O13*P13)+(N14*O14*P14) -> 8860.2509 | R9: 0 | S9: =+Q9+R9 -> 8860.2509
C10: May 2025 - August 2025 | D10: 4 | E10: 0.05 | F10: =+F9 -> 12168 | P10: 12168
C11: September 2025 - December 2025 | D11: 4 | E11: 0.025 | F11: =+F10 -> 12168 | N11: 4 | O11: 0.025 | P11: 12168
C12: January 2026 - April 2026 | D12: 4 | E12: 0.025 | F12: =+F11*1.04 -> 12654.72 | N12: 4 | O12: 0.025 | P12: 12654.72
C13: May 2026 - December 2026 | F13: =+F12 -> 12654.72 | N13: 8 | O13: 0.05 | P13: 12654.72
C14: January 2027 - February 2027 | F14: =+F13*1.04 -> 13160.909 | N14: 2 | O14: 0.05 | P14: 13160.909
C15: 2. Program Director - $7,133/Month Aug 2024 - Apr 2026 at 10% LOE | F15: 7133 | G15: 10314 | H15: 0 | I15: 3707.26 | J15: =+(D15*E15*F15)+(D16*E16*F16)+(D17*E17*F17)+(D18*E18*F18)+(D19*E19*F19)+(D20*E20*F20) -> 8673.728 | K15: =+I15+J15 -> 12380.988 | L15: =+G15-K15 -> -2066.988 | M15: REMOVED | Q15: =+(N15*O15*P15)+(N16*O16*P16)+(N17*O17*P17)+(N18*O18*P18)+(N19*O19*P19)+(N20*O20*P20) -> 0 | R15: 0 | S15: =+Q15+R15 -> 0
C16: May 2025 - August 2025 | D16: 4 | E16: 0.1 | F16: =+F15 -> 7133
C17: September 2025 - December 2025 | D17: 4 | E17: 0.1 | F17: =+F16 -> 7133
C18: January 2026 - April 2025 | D18: 4 | E18: 0.1 | F18: =+F17*1.04 -> 7418.32
C19: May 2026 - December 2026 | F19: =+F18 -> 7418.32
C20: January 2027 - February 2027 | F20: =+F19*1.04 -> 7715.0528
A21: PERSNL | B21: 50000 (Timesheets) | C21: 3. Senior Program Officer - $5,358/Month Aug 2024 - Dec 2025 at 100% LOE Jan 2026 - Apr 2026 at 50% | F21: =77075/12 -> 6422.9167 | G21: 92026 | H21: 0 | I21: 27935.62 | J21: =+(D21*E21*F21)+(D22*E22*F22)+(D23*E23*F23)+(D24*E24*F24)+(D25*E25*F25)+(D26*E26*F26) -> 64743 | K21: =+I21+J21 -> 92678.62 | L21: =+G21-K21 -> -652.62 | M21: 3. Associate Director - Program Director - $6,423/month Jan 2026 - Apr 2026 at 50% May 2026 - Feb 2027 at 80% | P21: 6422.9167 | Q21: =+(N21*O21*P21)+(N22*O22*P22)+(N23*O23*P23)+(N24*O24*P24)+(N25*O25*P25)+(N26*O26*P26) -> 67225.843 | R21: 0 | S21: =+Q21+R21 -> 67225.843
C22: May 2025 - August 2025 | D22: 4 | E22: 1 | F22: =+F21 -> 6422.9167 | P22: 6422.9167
C23: September 2025 - December 2025 | D23: 4 | E23: 1 | F23: =+F22 -> 6422.9167 | P23: 6422.9167
C24: January 2026 - April 2026 | D24: 4 | E24: 0.5 | F24: =+F23*1.04 -> 6679.8333 | N24: 4 | O24: 0.5 | P24: 6679.8333
C25: May 2026 - December 2026 | F25: =+F24 -> 6679.8333 | N25: 8 | O25: 0.8 | P25: 6679.8333
C26: January 2027 - February 2027 | F26: =+F25*1.04 -> 6947.0267 | N26: 2 | O26: 0.8 | P26: 6947.0267
C27: 4. Program Support | G27: 0 | H27: 12614 | K27: =+I27+J27 -> 0 | L27: =+G27-K27 -> 0 | M27: REMOVED | Q27: 0 | R27: 0 | S27: =+Q27+R27 -> 0
C28: Total Salaries | G28: =SUM(G9:G27) -> 104840 | H28: =SUM(H9:H27) -> 12614 | I28: =SUM(I9:I27) -> 31642.88 | J28: =SUM(J9:J27) -> 78332.6 | K28: =SUM(K9:K27) -> 109975.48 | L28: =+G28-K28 -> -5135.48 | M28: Total Salaries | Q28: =SUM(Q9:Q27) -> 76086.094 | R28: =SUM(R9:R27) -> 0 | S28: =SUM(S9:S27) -> 76086.094 | T28: =+Q28/G28 -> 0.72573534
C29: II. Fringe Benefits
A30: FRINGE | B30: 50900 (Timesheets) | C30: 23.47% - Fringe Benefits US-based staff | G30: 23901 | H30: 0 | I30: 7823.15 | J30: =J21*23.47% -> 15195.182 | K30: =+I30+J30 -> 23018.332 | L30: =+G30-K30 -> 882.6679 | M30: 23.47% - Fringe Benefits US-based staff | Q30: =(Q21+Q9)*23.47% -> 17857.406 | R30: 0 | S30: =+Q30+R30 -> 17857.406
C31: 53.864% - Fringe Benefits Colombia based staff | G31: 1500 | H31: 0 | I31: 946.3 | J31: =J15*53.864% -> 4672.0168 | K31: =+I31+J31 -> 5618.3168 | L31: =+G31-K31 -> -4118.3168 | Q31: =Q15*53.864% -> 0 | R31: 0 | S31: =+Q31+R31 -> 0
C32: Total Fringe Benefits | G32: =SUM(G30:G31) -> 25401 | H32: =SUM(H30:H31) -> 0 | I32: =SUM(I30:I31) -> 8769.45 | J32: =SUM(J30:J31) -> 19867.199 | K32: =SUM(K30:K31) -> 28636.649 | L32: =+G32-K32 -> -3235.6489 | M32: Total Fringe Benefits | Q32: =SUM(Q30:Q31) -> 17857.406 | R32: =SUM(R30:R31) -> 0 | S32: =SUM(S30:S31) -> 17857.406 | T32: =+Q32/G32 -> 0.70301981
C33: III. Travel | M33: III. Travel | N33: #PAX | P33: UNIT COST
C34: 1. Staff Travel | D34: PAX | E34: # TRIPS / # DAYS | F34: UNIT COST | M34: 1. Staff Travel
A35: STFTRAVEL | B35: 86040 | C35: a. Domestic Round Trip Airfare ($378 x 2 trip) | D35: 1 | E35: 3 | F35: 378 | G35: 1134 | H35: 0 | I35: 75.11 | J35: =+D35*E35*F35 -> 1134 | K35: =+I35+J35 -> 1209.11 | L35: =+G35-K35 -> -75.11 | M35: a. Domestic Round Trip Airfare ($500 x 4 trips) | N35: 4 | O35: 1 | P35: 500 | Q35: =+N35*O35*P35 -> 2000 | R35: 0 | S35: =+Q35+R35 -> 2000
A36: STFCN DIEM | B36: 86030 (Lodging) & 86050 (M&IE) | C36: b. Domestic Lodging & Per Diem Washington, DC ($183 x 12 nights x 1 trip + $71/day x 13 days) Other Host City ($160 x 4 nights x 1 trip + $71/day x 5 days) | D36: 2 | E36: 8 | F36: 183 | G36: 5183 | H36: 0 | I36: 0 | J36: =+(D36*E36*F36)+(D37*E37*F37)+(D38*E38*F38)+(D39*E39*F39) -> 5183 | K36: =+I36+J36+I37+J37+I38+J38+I39+J39 -> 5183 | L36: =+G36-K36 -> 0 | M36: b. Domestic Lodging & Per Diem Washington, DC ($224 x 2 nights x 1 trip + $83/day x 3 days) x 3 people Other Host City ($169 x 2 nights x 1 trip + $72/day x 3 days x 1 trip) | N36: 3 | O36: 2 | P36: 224 | Q36: =+(N36*O36*P36)+(N37*O37*P37)+(N38*O38*P38)+(N39*O39*P39) -> 2643.2 | R36: 0 | S36: =+Q36+R36 -> 2643.2
C37: Washington, DC ($71/day x 13 days) | D37: 2 | E37: 10 | F37: 71 | N37: 3 | O37: 3 | P37: 82.8
C38: Other Host City ($200 x 4 nights x 1 trip) | D38: 1 | E38: 3 | F38: 160 | N38: 1 | O38: 2 | P38: 169
C39: Other Host City ($71/day x 5 days) | D39: 1 | E39: 5 | F39: 71 | N39: 1 | O39: 3 | P39: 72
A40: STFTRAVEL | B40: 86040 | C40: c. International Round Trip Airfare ($1,467 x 2 trips) | D40: 1 | E40: 2 | F40: 1466.6667 | G40: 2933.3333 | H40: 0 | I40: 0 | J40: =+D40*E40*F40 -> 2933.3333 | K40: =+I40+J40 -> 2933.3333 | L40: =+G40-K40 -> 0 | M40: c. International Round Trip Airfare ($1,500 x 1 trips) | N40: 1 | O40: 1 | P40: 1500 | Q40: =+N40*O40*P40 -> 1500 | R40: 0 | S40: =+Q40+R40 -> 1500
A41: STFCN DIEM | B41: 86030 (Lodging) & 86050 (M&IE) | C41: d. International Lodging & Per Diem ($50/day + $86/day) x 6 days x 2 trips | D41: 2 | E41: 5 | F41: 150 | G41: 2532 | H41: 0 | I41: 0 | J41: =+(D41*E41*F41)+(D42*E42*F42) -> 2532 | K41: =+I41+J41 -> 2532 | L41: =+G41-K41 -> 0 | M41: d. International Lodging & Per Diem (1 x $114/day x 5 days) | N41: 1 | O41: 5 | P41: 113.85714 | Q41: =+(N41*O41*P41)+(N42*O42*P42) -> 975.82857 | R41: 0 | S41: =+Q41+R41 -> 975.82857
D42: 2 | E42: 6 | F42: 86 | M42: (1 x $68/day x 6 days) | N42: 1 | O42: 6 | P42: 67.757143
C43: 2. Participant Travel | M43: 2. Participant Travel
A44: PARTTRAVEL | B44: 86040 | C44: a. International Round Trip Airfare ($1,650 x 24 trips) | D44: 24 | E44: 1 | F44: 1650 | G44: 39600 | H44: 0 | I44: 0 | J44: =+D44*E44*F44 -> 39600 | K44: =+I44+J44 -> 39600 | L44: =+G44-K44 -> 0 | M44: a. International Round Trip Airfare ($1,600 x 20 trips) | N44: 20 | O44: 1 | P44: 1600 | Q44: =+N44*O44*P44 -> 32000 | R44: 0 | S44: =+Q44+R44 -> 32000
A45: PARTTRAVEL | B45: 86040 | C45: b. U.S. Domestic flights for Group Exchange Participants ($350 x 18 participants) | D45: 18 | E45: 1 | F45: 350 | G45: 6300 | H45: 0 | I45: 0 | J45: =+D45*E45*F45 -> 6300 | K45: =+I45+J45 -> 6300 | L45: =+G45-K45 -> 0 | M45: b. U.S. Domestic flights for Group Exchange Participants ($500 x 16 participants) | N45: 16 | O45: 1 | P45: 500 | Q45: =+N45*O45*P45 -> 8000 | R45: 0 | S45: =+Q45+R45 -> 8000
A46: PARTPERDIE | B46: 86050 | C46: c. International/Domestic Per Diem ($50/day x 10 days x 6 trips) | D46: 10 | E46: 6 | F46: 50 | G46: 3000 | H46: 0 | I46: 0 | J46: =+D46*E46*F46 -> 3000 | K46: =+I46+J46 -> 3000 | L46: =+G46-K46 -> 0 | M46: c. International/Domestic Per Diem ($80/day x 10 days x 20 trips) | N46: =+N44 -> 20 | O46: 10 | P46: 79.8 | Q46: =+N46*O46*P46 -> 15960 | R46: 0 | S46: =+Q46+R46 -> 15960
A47: PARTPERDIE | B47: 86050 | C47: d. Visa Fees ($185 x 3 participants) | D47: 3 | E47: 1 | F47: 185 | G47: 555 | H47: 0 | I47: 0 | J47: =+D47*E47*F47 -> 555 | K47: =+I47+J47 -> 555 | L47: =+G47-K47 -> 0 | M47: d. Visa Fees ($160 x 4 participants) | N47: 4 | O47: 1 | P47: 160 | Q47: =+N47*O47*P47 -> 640 | R47: 0 | S47: =+Q47+R47 -> 640
A48: VISATRVEXP | B48: 86000 (Transport) 86030 (Lodging) & 86050 (M&IE) | C48: e. Visa Related Travel Fees ($275 x 6 participants) | D48: 6 | E48: 1 | F48: 275 | G48: 1650 | H48: 0 | I48: 0 | J48: =+D48*E48*F48 -> 1650 | K48: =+I48+J48 -> 1650 | L48: =+G48-K48 -> 0 | M48: e. Visa Related Travel Fees ($250 x 4 participants) | N48: 4 | O48: 1 | P48: 250 | Q48: =+N48*O48*P48 -> 1000 | R48: 0 | S48: =+Q48+R48 -> 1000
A49: LODGING | B49: 86030 | C49: f. U.S. Hotel for Group Exchange Participants ($217 x 4 nights x 18 participants) | D49: 18 | E49: 4 | F49: 216.5 | G49: 15588 | H49: 785 | I49: 0 | J49: =+D49*E49*F49 -> 15588 | K49: =+I49+J49 -> 15588 | L49: =+G49-K49 -> 0 | M49: f. U.S. Hotel for Group Exchange Participants ($224 x 2 nights x 16 participants) | N49: 16 | O49: 2 | P49: 224.33333 | Q49: =+N49*O49*P49 -> 7178.6667 | R49: 0 | S49: =+Q49+R49 -> 7178.6667
C50: Total Travel | G50: =SUM(G35:G49) -> 78475.333 | H50: =SUM(H35:H49) -> 785 | I50: =SUM(I35:I49) -> 75.11 | J50: =SUM(J35:J49) -> 78475.333 | K50: =SUM(K35:K49) -> 78550.443 | L50: =+G50-K50 -> -75.11 | M50: Total Travel | Q50: =SUM(Q35:Q49) -> 71897.695 | R50: =SUM(R35:R49) -> 0 | S50: =SUM(S35:S49) -> 71897.695 | T50: =+Q50/G50 -> 0.91618209
C51: IV. Equipment | S51: =+G51+R51 -> 0
C52: V. Supplies | S52: =+G52+R52 -> 0
A53: SUPPLIES | B53: 82420 | M53: a. Supplies | N53: 18 | O53: 1 | P53: 13 | Q53: =+N53*O53*P53 -> 234 | R53: 1998 | S53: =+Q53+R53 -> 2232
C54: Total Supplies | G54: =+G53 -> 0 | H54: =+H53 -> 0 | I54: =+I53 -> 0 | J54: =+J53 -> 0 | K54: =+K53 -> 0 | L54: =+L53 -> 0 | M54: Total Supplies | Q54: =+Q53 -> 234 | R54: =+R53 -> 1998 | S54: =+S53 -> 2232 | T54: =+Q54/G80 -> 0.76595745
C55: VI. Contractual | M55: VI. Contractual | P55: UNIT COST
A56: GRANTS | B56: 89000 | C56: a. Subawards (4 community-led projects x $5,000) | D56: 1 | E56: 4 | F56: 5000 | G56: 20000 | H56: 25000 | I56: 0 | J56: =+D56*E56*F56 -> 20000 | K56: =+I56+J56 -> 20000 | L56: =+G56-K56 -> 0 | M56: a. Subawards (3 community-led projects x $5,000) | N56: 1 | O56: 3 | P56: 5000 | Q56: =+N56*O56*P56 -> 15000 | R56: 15000 | S56: =+Q56+R56 -> 30000
A57: GRANTS | B57: 89000 | C57: b. Subawards (group exchanges) (2 subawards x $10,000) | D57: 1 | E57: 2 | F57: 10000 | G57: 20000 | H57: 25000 | I57: 0 | J57: =+D57*E57*F57 -> 20000 | K57: =+I57+J57 -> 20000 | L57: =+G57-K57 -> 0 | M57: b. Subawards (group exchanges) (2 subawards x $10,000) | N57: 1 | O57: 2 | P57: 10000 | Q57: =+N57*O57*P57 -> 20000 | R57: 20000 | S57: =+Q57+R57 -> 40000
A58: CONSULT | B58: 81000 | C58: c. Technical/Operational Consultant Pool ($300/day x 40 days) | D58: 1 | E58: 10 | F58: 300 | G58: 12000 | H58: 0 | I58: 0 | J58: =+D58*E58*F58 -> 3000 | K58: =+I58+J58 -> 3000 | L58: =+G58-K58 -> 9000 | M58: c. Technical/Operational Consultant Pool ($300/day x 14 days) | N58: 1 | O58: 14 | P58: 300 | Q58: =+N58*O58*P58 -> 4200 | R58: 0 | S58: =+Q58+R58 -> 4200
C59: e. Monitoring and Evaluation Consultant ($300 x 10 days) | D59: 1 | E59: 5 | F59: 300 | G59: 3000 | H59: 0 | I59: 400 | J59: =+(D59*E59*F59)-400 -> 1100 | K59: =+I59+J59 -> 1500 | L59: =+G59-K59 -> 1500 | M59: REMOVED | Q59: =+N59*O59*P59 -> 0 | R59: 0 | S59: =+Q59+R59 -> 0
C60: Total Contractual | G60: =SUM(G56:G59) -> 55000 | H60: =SUM(H56:H59) -> 50000 | I60: =SUM(I56:I59) -> 400 | J60: =SUM(J56:J59) -> 44100 | K60: =SUM(K56:K59) -> 44500 | L60: =+G60-K60 -> 10500 | M60: Total Contractual | Q60: =SUM(Q56:Q59) -> 39200 | R60: =SUM(R56:R59) -> 35000 | S60: =+Q60+R60 -> 74200 | T60: =+Q60/G60 -> 0.71272727
C61: VII. Construction | S61: =+G61+R61 -> 0
C62: VIII. Other Direct Costs | M62: VIII. Other Direct Costs
C63: 1. Events | M63: 1. Events
A64: EVENT | B64: 87000 | C64: a. Event Costs - One-Day, In-Person Peer Learning Event | D64: 1 | E64: 1 | F64: 1898 | G64: 1898 | H64: 0 | J64: 3000 | K64: =+I64+J64 -> 3000 | L64: =+G64-K64 -> -1102 | M64: a. Event Costs - Exchange Activities | N64: 1 | O64: 1 | P64: 2000 | Q64: =+N64*O64*P64 -> 2000 | R64: 0 | S64: =+Q64+R64 -> 2000
C65: 2. Communications | M65: 2. Communications
A66: COMM | B66: 82030 | C66: a. Promotion & Communications | D66: 1 | E66: 1 | F66: 2700 | G66: =+D66*E66*F66 -> 2700 | H66: 0 | I66: 143.53 | J66: 456 | K66: =+I66+J66 -> 599.53 | L66: =+G66-K66 -> 2100.47 | M66: a. Promotion & Communications | N66: 1 | O66: 1 | P66: 154.34 | Q66: =+N66*O66*P66 -> 154.34 | R66: 0 | S66: =+Q66+R66 -> 154.34
A67: SUBSCRIPT | B67: 89400 | C67: b. Platform Subscriptions ($50/month x 17 months) May 2024 - June 2024 at 25% July 2024 - Sept 2024 at 50% October 2024 - Sept 2025 at 100% | D67: 17 | E67: 1 | F67: 56.75 | G67: 1100 | H67: 0 | J67: 1100 | K67: =+I67+J67 -> 1100 | L67: =+G67-K67 -> 0 | M67: b. Platform Subscriptions ($149/month x 18 months) September 2025 - April 2026 at 50% May 2026 - February 2027 at 100% | P67: 149.29425 | Q67: =(N67*O67*P67)+(N68*O68*P68)+(N69*O69*P69)+(N70*O70*P70)+(N71*O71*P71)+(N72*O72*P72) -> 2153.0918 | R67: 0 | S67: =+Q67+R67 -> 2153.0918
C68: May 2025 - August 2025 | D68: 4 | E68: 1 | F68: =+F67 -> 56.75 | P68: 149.29425
C69: September 2025 - December 2025 | D69: 4 | E69: 0.5 | F69: =+F68 -> 56.75 | N69: 4 | O69: 0.5 | P69: 149.29425
C70: January 2026 - April 2026 | D70: 4 | E70: 0.5 | F70: =+F69*1.04 -> 59.02 | N70: 4 | O70: 0.5 | P70: 153.77308
C71: May 2026 - December 2026 | N71: 8 | O71: 1 | P71: 153.77308
C72: January 2027 - February 2027 | N72: 2 | O72: 1 | P72: 158.38627
A73: SUBSCRIPT | B73: 89400 | C73: c. Online Platform for Subaward Management ($120/month x 17 months) | D73: 17 | E73: 1 | F73: 120 | G73: 2150 | H73: 0 | I73: 2767.2 | J73: =(D74*E74*F74)+(D75*E75*F75)+(D76*E76*F76)+(D77*E77*F77)+(D78*E78*F78) -> 2500 | K73: =+I73+J73 -> 5267.2 | L73: =+G73-K73 -> -3117.2 | M73: c. Online Platform for Subaward Management ($138/month x 18 months) | N73: 18 | O73: 1 | P73: 138.77 | Q73: =N73*O73*P73 -> 2497.86 | R73: 0 | S73: =+Q73+R73 -> 2497.86
C74: May 2025 - August 2025 | D74: 0 | E74: 1 | F74: 120
C75: September 2025 - December 2025 | D75: 1 | E75: 1 | F75: 2500
C76: January 2026 - April 2026 | D76: 0 | E76: 1 | F76: 0
C77: May 2026 - December 2026
C78: January 2027 - February 2027
C79: 3. Materials | M79: 3. Materials | S79: =+Q79+R79 -> 0
C80: a. Supplies | D80: 17 | E80: 1 | F80: 20.588235 | G80: 305.5 | H80: 2698 | I80: 8.71 | J80: 231.82 | K80: =+I80+J80 -> 240.53 | L80: =+G80-K80 -> 64.97
A81: COURIER | B81: 82350 | C81: b. Courier | G81: =+D81*E81*F81 -> 0 | K81: =+I81+J81 -> 0 | L81: =+G81-K81 -> 0 | M81: a. Courier and printing | N81: =+N44 -> 20 | O81: 1 | P81: 10.28 | Q81: =+N81*O81*P81 -> 205.6 | R81: 0 | S81: =+Q81+R81 -> 205.6
C82: 4. Volunteer Time | M82: 4. Volunteer Time
A83: IN-KIND | B83: 96000 | C83: a. U.S. and LAC Volunteer Time | G83: 0 | H83: 61729 | J83: =+D83*E83*F83 -> 0 | K83: =+I83+J83 -> 0 | L83: =+G83-K83 -> 0 | M83: a. U.S. and LAC Volunteer Time | Q83: 0 | R83: =+'Volunteer Time Cost Share'!E20 -> 36871.6 | S83: =+Q83+R83 -> 36871.6
C84: Total Other Direct Costs | G84: =SUM(G63:G83) -> 8153.5 | H84: =SUM(H63:H83) -> 64427 | I84: =SUM(I63:I83) -> 2919.44 | J84: =SUM(J63:J83) -> 7287.82 | K84: =SUM(K63:K83) -> 10207.26 | L84: =+G84-K84 -> -2053.76 | M84: Total Other Direct Costs | Q84: =SUM(Q63:Q83) -> 7010.8918 | R84: =SUM(R63:R83) -> 36871.6 | S84: =SUM(S63:S83) -> 43882.492 | T84: =+Q84/G84 -> 0.85986286
C85: Total Direct Costs | G85: =G84+G60+G50+G32+G28 -> 271869.83 | H85: =H84+H60+H50+H32+H28 -> 127826 | I85: =I84+I60+I50+I32+I28 -> 43806.88 | J85: =J84+J60+J50+J32+J28 -> 228062.95 | K85: =K84+K60+K50+K32+K28 -> 271869.83 | L85: =+G85-K85 -> 0.0010500801 | M85: Total Direct Costs | Q85: =Q84+Q60+Q50+Q54+Q32+Q28 -> 212286.09 | R85: =R84+R60+R50+R54+R32+R28 -> 73869.6 | S85: =S84+S60+S50+S54+S32+S28 -> 286155.69 | T85: =+Q85/G85 -> 0.78083723
C86: IX. Indirect Costs* | M86: IX. Indirect Costs* | S86: =+G86+R86 -> 0
A87: IDC | B87: 94050 | C87: 0.15 | G87: =G85*$C$87 -> 40780.475 | H87: 0 | I87: =I85*$C$87 -> 6571.032 | J87: =J85*$C$87 -> 34209.443 | K87: =K85*$C$87 -> 40780.475 | L87: =L85*$C$87 -> 0.00015751201 | M87: 0.15 | Q87: =Q85*$C$87 -> 31842.913 | R87: 0 | S87: =+Q87+R87 -> 31842.913 | T87: =+Q87/G87 -> 0.78083723
C88: Total Indirect Costs | G88: =G87 -> 40780.475 | H88: =H87 -> 0 | I88: =I87 -> 6571.032 | J88: =J87 -> 34209.443 | K88: =K87 -> 40780.475 | M88: Total Indirect Costs | Q88: =Q87 -> 31842.913 | R88: 0 | S88: =S87 -> 31842.913 | T88: =+Q88/G88 -> 0.78083723
C89: TOTAL COSTS | G89: =G88+G85 -> 312650.31 | H89: =H88+H85 -> 127826 | I89: =I88+I85 -> 50377.912 | J89: =J88+J85 -> 262272.4 | K89: =+I89+J89 -> 312650.31 | L89: =+G89-K89 -> 0.001207592 | M89: TOTAL COSTS | Q89: =Q88+Q85 -> 244129 | R89: =R88+R85 -> 73869.6 | S89: =S88+S85 -> 317998.6 | T89: =+Q89/G89 -> 0.78083723

Sheet Volunteer Time Cost Share
A1: U.S. and LAC Volunteer Time
A2: Item | B2: # volunteers | C2: # Vol-days | D2: Daily Rate | E2: Total Cost Share
A4: U.S. Volunteers
A5: Planning and preparation | B5: 2 | C5: 2 | D5: =31.06*8 -> 248.48 | E5: =+B5*C5*D5 -> 993.92
A6: Orientation | B6: 2 | C6: 2 | D6: =31.06*8 -> 248.48 | E6: =+B6*C6*D6 -> 993.92
A7: Participants | B7: 8 | C7: 7 | D7: =D6 -> 248.48 | E7: =+B7*C7*D7 -> 13914.88
A8: Follow-on engagement | B8: 2 | C8: 5 | D8: =31.06*8 -> 248.48 | E8: =+B8*C8*D8 -> 2484.8
A9: Communications support | B9: 1 | C9: 10 | D9: =31.06*8 -> 248.48 | E9: =+B9*C9*D9 -> 2484.8
A10: Proposal reviewers | B10: 5 | C10: 5 | D10: =31.06*8 -> 248.48 | E10: =+B10*C10*D10 -> 6212
A11: Sub total | E11: =SUM(E5:E10) -> 27084.32
A12: Non-U.S. (LAC) Volunteers
A13: Planning and preparation | B13: 2 | C13: 2 | D13: =8.93*8 -> 71.44 | E13: =+B13*C13*D13 -> 285.76
A14: Orientation | B14: 2 | C14: 2 | D14: =8.93*8 -> 71.44 | E14: =+B14*C14*D14 -> 285.76
A15: Participants | B15: 12 | C15: 7 | D15: =8.93*8 -> 71.44 | E15: =+B15*C15*D15 -> 6000.96
A16: Follow-on engagement | B16: 2 | C16: 5 | D16: =8.93*8 -> 71.44 | E16: =+B16*C16*D16 -> 714.4
A17: Communications support | B17: 1 | C17: 10 | D17: =8.93*8 -> 71.44 | E17: =+B17*C17*D17 -> 714.4
A18: Proposal reviewers | B18: 5 | C18: 5 | D18: =8.93*8 -> 71.44 | E18: =+B18*C18*D18 -> 1786
A19: Sub total | E19: =SUM(E13:E18) -> 9787.28
A20: Total volunteer time match | E20: =E11+E19 -> 36871.6
