Workbook
Name Category: #N/A
Name Category: Comparasion!#REF!
Name Category: RMS!$G$9:$G$113
Name Category: 'Project Budget'!$F$15:$F$221
Name DL_Country: #N/A
Name DL_Country: Comparasion!#REF!
Name DL_Country: RMS!#REF!
Name DL_Country: 'Project Budget'!#REF!
Name DL_TotalDOL: #N/A
Name DL_TotalDOL: Comparasion!$B$7:$B$35
Name DL_TotalDOL: RMS!$T$9:$T$27
Name DL_TotalDOL: 'Project Budget'!$S$14:$S$39
Name EQ_Country: #N/A
Name EQ_Country: Comparasion!#REF!
Name EQ_Country: RMS!#REF!
Name EQ_Country: 'Project Budget'!#REF!
Name EQ_TotalDOL: #N/A
Name EQ_TotalDOL: Comparasion!#REF!
Name EQ_TotalDOL: RMS!#REF!
Name EQ_TotalDOL: 'Project Budget'!#REF!
Name inf: #N/A
Name inf: Comparasion!#REF!
Name inf: #REF!
Name inf: #REF!
Name JEA_Country: #N/A
Name JEA_Country: Comparasion!#REF!
Name JEA_Country: #REF!
Name JEA_Country: #REF!
Name JEA_Year1: #N/A
Name JEA_Year1: Comparasion!#REF!
Name JEA_Year1: #REF!
Name JEA_Year1: #REF!
Name ME_Country: #N/A
Name ME_Country: Comparasion!#REF!
Name ME_Country: RMS!#REF!
Name ME_Country: 'Project Budget'!#REF!
Name ME_TotalDOL: #N/A
Name ME_TotalDOL: Comparasion!$B$260:$B$275
Name ME_TotalDOL: RMS!#REF!
Name ME_TotalDOL: 'Project Budget'!$S$189:$S$203
Name O1_Country: #N/A
Name O1_Country: Comparasion!#REF!
Name O1_Country: RMS!#REF!
Name O1_Country: 'Project Budget'!#REF!
Name O1_TotalDOL: #N/A
Name O1_TotalDOL: Comparasion!#REF!
Name O1_TotalDOL: RMS!$T$108:$T$109
Name O1_TotalDOL: 'Project Budget'!#REF!
Name O2_Country: #N/A
Name O2_Country: Comparasion!#REF!
Name O2_Country: RMS!#REF!
Name O2_Country: 'Project Budget'!#REF!
Name O2_TotalDOL: #N/A
Name O2_TotalDOL: Comparasion!#REF!
Name O2_TotalDOL: RMS!#REF!
Name O2_TotalDOL: 'Project Budget'!#REF!
Name SU_Country: #N/A
Name SU_Country: Comparasion!#REF!
Name SU_Country: RMS!#REF!
Name SU_Country: 'Project Budget'!#REF!

Sheet Budget Summary
A1: Improving Gender Equity in the Mexican Workplace
A2: FOA-ILAB-21-13
A3: CFDA 17.401
A4: Partners of the Americas
A6: BUDGET ITEM | B6: TOTAL DOL | C6: TOTAL COST SHARING | D6: PROJECT GRAND TOTAL | E6: ORIGINAL BUDGET | F6: DIFFERENCE
A7: Direct Labor (Personnel & Fringe) | B7: ='Project Budget'!S42 -> 3064473 | C7: ='Project Budget'!T42 -> 0 | D7: =SUM(B7:C7) -> 3064473 | E7: 2642048 | F7: =ROUND(D7-E7,0) -> 422425
A8: Travel | B8: ='Project Budget'!S62 -> 107797 | C8: ='Project Budget'!T62 -> 0 | D8: =SUM(B8:C8) -> 107797 | E8: 238355 | F8: =ROUND(D8-E8,0) -> -130558
A9: Equipment | B9: ='Project Budget'!S66 -> 0 | C9: ='Project Budget'!T66 -> 0 | D9: =SUM(B9:C9) -> 0 | E9: 45000 | F9: =ROUND(D9-E9,0) -> -45000
A10: Supplies and Office Expenses | B10: ='Project Budget'!S88 -> 474489 | C10: ='Project Budget'!T88 -> 0 | D10: =SUM(B10:C10) -> 474489 | E10: 331507 | F10: =ROUND(D10-E10,0) -> 142982
A11: Contractual (Subawards and Contracts) | B11: ='Project Budget'!S102 -> 3380737 | C11: ='Project Budget'!T102 -> 0 | D11: =SUM(B11:C11) -> 3380737 | E11: 3449920 | F11: =ROUND(D11-E11,0) -> -69183
A12: Other - Outcome 1 | B12: ='Project Budget'!S143 -> 187250 | C12: ='Project Budget'!T143 -> 0 | D12: =SUM(B12:C12) -> 187250 | E12: 318440 | F12: =ROUND(D12-E12,0) -> -131190
A13: Other - Outcome 2 | B13: ='Project Budget'!S184 -> 164740 | C13: ='Project Budget'!T184 -> 0 | D13: =SUM(B13:C13) -> 164740 | E13: 342320 | F13: =ROUND(D13-E13,0) -> -177580
A14: Monitoring, Evaluation, and Collection of Reliable Data | B14: ='Project Budget'!S217 -> 391126 | C14: ='Project Budget'!T217 -> 0 | D14: =SUM(B14:C14) -> 391126 | E14: 403022 | F14: =ROUND(D14-E14,0) -> -11896
A15: Total Direct Costs | B15: =SUM(B7:B14) -> 7770612 | C15: =SUM(C7:C14) -> 0 | D15: =SUM(D7:D14) -> 7770612 | E15: 7770611 | F15: =ROUND(D15-E15,-1) -> 0
A16: Indirect Costs (NICRA) | B16: ='Project Budget'!S221 -> 2229388 | C16: ='Project Budget'!T221 -> 0 | D16: =SUM(B16:C16) -> 2229388 | E16: 2229388 | F16: =ROUND(D16-E16,0) -> 0
A17: TOTAL COSTS | B17: =B16+B15 -> 10000000 | C17: =C16+C15 -> 0 | D17: =D16+D15 -> 10000000 | E17: 10000000 | F17: =ROUND(D17-E17,0) -> 0
A19: ADMINISTRATIVE COSTS | B19: =B16+B7 -> 5293861
A20: PROGRAM COSTS | B20: =B8+B12+B13+B14+B11+B10+B9 -> 4706139

Sheet Project Budget
E1: Equal Access to Quality Jobs for Women and Girls in Agriculture (EQUAL)
E2: FOA-ILAB-19-02
E3: Partners of the Americas
E4: Partners of the Americas
E5: NOFO: FOA-ILAB-21-13
E6: Project Name: Improving Gender Equity in the Mexican Workplace
E7: Country: Mexico
A8: Entity: | B8: P | E8: Budget Assumptions:
A9: Program-Dept.: | B9: 20200 | E9: Inflation - US Based Goods/Services | F9: 1.03
A10: Funder-Grant: | B10: DOL425 | E10: Inflation - Locally Purchased Goods/Services | F10: 1.04
E11: Merit Based Increases for HQ & Field Staff | F11: 1.035
A12: Activity Code | B12: Account Code | C12: Country Code | D12: Subcontract Code | E12: BUDGET ITEM | F12: CATEGORY | G12: UNIT | H12: # of Units | I12: RATE / UNIT | J12: YEAR 1 2022 | K12: # of Units | L12: YEAR 2 2023 | M12: # of Units | N12: YEAR 3 2024 | O12: # of Units | P12: YEAR 4 2025 | Q12: # of Units | R12: YEAR 5 2026 | S12: TOTAL DOL | T12: TOTAL COST SHARING | U12: PROJECT GRAND TOTAL
E13: Direct Labor (Personnel & Fringe Benefits)
E14: Key Personnel
A15: PERSNL-PD | B15: 70000 | C15: 0 | D15: 0 | E15: Project Director (100%) - Dr. Alma Rico | F15: Salaries | G15: Month | H15: 12 | I15: 8000 | J15: =H15*I15 -> 96000 | K15: 12 | L15: =K15*I15*$F$11 -> 99360 | M15: 12 | N15: =(M15*I15*$F$11*$F$11) -> 102838 | O15: 12 | P15: =O15*I15*$F$11*$F$11*$F$11 -> 106437 | Q15: 6 | R15: =I15*Q15*$F$11*$F$11*$F$11*$F$11 -> 55081 | S15: =SUM(J15+L15+N15+P15+R15) -> 459716 | T15: 0 | U15: =SUM(S15:T15) -> 459716
A16: PERSNL-M&E | B16: 70000 | C16: MEX | D16: 0 | E16: Monitoring and Evaluation (M&E) Officer (100%) - Ms. Ana Georgina Pulido-Carrillo / Azucena Aguirre Crespo | F16: Salaries | G16: Month | H16: 11 | I16: 4400 | J16: =I16*H16 -> 48400 | K16: 12 | L16: =K16*I16*$F$11 -> 54648 | M16: 12 | N16: =M16*I16*$F$11*$F$11 -> 56561 | O16: 12 | P16: =O16*I16*$F$11*$F$11*$F$11 -> 58540 | Q16: 6 | R16: =I16*Q16*$F$11*$F$11*$F$11*$F$11 -> 30295 | S16: =SUM(J16+L16+N16+P16+R16) -> 248444 | T16: 0 | U16: =SUM(S16:T16) -> 248444
E18: Other Professional Personnel
A19: PERSNL-GS | B19: 70000 | C19: MEX | D19: 0 | E19: Gender Specialist (100%) XIHH | F19: Salaries | G19: Month | H19: 9 | I19: 3000 | J19: =I19*H19 -> 27000 | K19: 12 | L19: =K19*I19*$F$11 -> 37260 | M19: 12 | N19: =M19*I19*$F$11*$F$11 -> 38564 | O19: 12 | P19: =O19*I19*$F$11*$F$11*$F$11 -> 39914 | Q19: 3 | R19: =I19*Q19*$F$11*$F$11*$F$11*$F$11 -> 10328 | S19: =SUM(J19+L19+N19+P19+R19) -> 153066 | T19: 0 | U19: =SUM(S19:T19) -> 153066
A20: PERSNL-WLO | B20: 70000 | C20: MEX | D20: 0 | E20: Work Labor Organizations Specialist (100%) GVG | F20: Salaries | G20: Month | H20: 6 | I20: 3500 | J20: =I20*H20 -> 21000 | K20: 12 | L20: =K20*I20*$F$11 -> 43470 | M20: 12 | N20: =M20*I20*$F$11*$F$11 -> 44991 | O20: 12 | P20: =O20*I20*$F$11*$F$11*$F$11 -> 46566 | Q20: 3 | R20: =I20*Q20*$F$11*$F$11*$F$11*$F$11 -> 12049 | S20: =SUM(J20+L20+N20+P20+R20) -> 168076 | T20: 0 | U20: =SUM(S20:T20) -> 168076
A21: PERSNL-COM | B21: 70000 | C21: MEX | D21: 0 | E21: Communication Specialist (100%) VRG | F21: Salaries | G21: Month | H21: 6 | I21: 2800 | J21: =H21*I21 -> 16800 | K21: 12 | L21: =K21*I21*$F$11 -> 34776 | M21: 12 | N21: =M21*I21*$F$11*$F$11 -> 35993 | O21: 12 | P21: =O21*I21*$F$11*$F$11*$F$11 -> 37253 | Q21: 3 | R21: =I21*Q21*$F$11*$F$11*$F$11*$F$11 -> 9639 | S21: =SUM(J21+L21+N21+P21+R21) -> 134461 | T21: 0 | U21: =SUM(S21:T21) -> 134461
A22: PERSNL-RCM | B22: 70000 | C22: MEX | D22: 0 | E22: Regional Coordinator CDMEX (100%) TBD | F22: Salaries | G22: Month | H22: 5 | I22: 2440 | J22: =H22*I22 -> 12200 | K22: 12 | L22: =K22*I22*$F$11 -> 30305 | M22: 12 | N22: =M22*I22*$F$11*$F$11 -> 31365 | O22: 12 | P22: =O22*I22*$F$11*$F$11*$F$11 -> 32463 | Q22: 3 | R22: =I22*Q22*$F$11*$F$11*$F$11*$F$11 -> 8400 | S22: =SUM(J22+L22+N22+P22+R22) -> 114733 | T22: 0 | U22: =SUM(S22:T22) -> 114733
A23: PERSNL-RCM | B23: 70000 | C23: MEX | D23: 0 | E23: Regional Coordinator Jalisco (100%) TBD | F23: Salaries | G23: Month | H23: 5 | I23: 2440 | J23: =H23*I23 -> 12200 | K23: 12 | L23: =K23*I23*$F$11 -> 30305 | M23: 12 | N23: =M23*I23*$F$11*$F$11 -> 31365 | O23: 12 | P23: =O23*I23*$F$11*$F$11*$F$11 -> 32463 | Q23: 3 | R23: =I23*Q23*$F$11*$F$11*$F$11*$F$11 -> 8400 | S23: =SUM(J23+L23+N23+P23+R23) -> 114733 | T23: 0 | U23: =SUM(S23:T23) -> 114733
A24: PERSNL-RCJ | B24: 70000 | C24: MEX | D24: 0 | E24: Regional Coordinator Chihuahua (100%) TBD | F24: Salaries | G24: Month | H24: 5 | I24: 2440 | J24: =H24*I24 -> 12200 | K24: 12 | L24: =K24*I24*$F$11 -> 30305 | M24: 12 | N24: =M24*I24*$F$11*$F$11 -> 31365 | O24: 12 | P24: =O24*I24*$F$11*$F$11*$F$11 -> 32463 | Q24: 3 | R24: =I24*Q24*$F$11*$F$11*$F$11*$F$11 -> 8400 | S24: =SUM(J24+L24+N24+P24+R24) -> 114733 | T24: 0 | U24: =SUM(S24:T24) -> 114733
A25: PERSNL-M&E | B25: 70000 | C25: MEX | D25: 0 | E25: Monitoring & Evaluation Specialist (100%) TBD | F25: Salaries | G25: Month | H25: 4 | I25: 2500 | J25: =H25*I25 -> 10000 | K25: 12 | L25: =K25*I25*$F$11 -> 31050 | M25: 12 | N25: =M25*I25*$F$11*$F$11 -> 32137 | O25: 12 | P25: =O25*I25*$F$11*$F$11*$F$11 -> 33262 | Q25: 3 | R25: =I25*Q25*$F$11*$F$11*$F$11*$F$11 -> 8606 | S25: =SUM(J25+L25+N25+P25+R25) -> 115055 | T25: 0 | U25: =SUM(S25:T25) -> 115055
A26: PERSNL-PA | B26: 70000 | C26: MEX | D26: 0 | E26: Project Assistant (100%) VILC | F26: Salaries | G26: Month | H26: 7 | I26: 2010 | J26: =H26*I26 -> 14070 | K26: 12 | L26: =K26*I26*$F$11 -> 24964 | M26: 12 | N26: =M26*I26*$F$11*$F$11 -> 25838 | O26: 12 | P26: =O26*I26*$F$11*$F$11*$F$11 -> 26742 | Q26: 6 | R26: =I26*Q26*$F$11*$F$11*$F$11*$F$11 -> 13839 | S26: =SUM(J26+L26+N26+P26+R26) -> 105453 | T26: 0 | U26: =SUM(S26:T26) -> 105453
A27: PERSNL-F&A | B27: 70000 | C27: MEX | D27: 0 | E27: Finance & Administration Director (45%) RARH | F27: Salaries | G27: Month | H27: 12 | I27: =6750*0.45 -> 3038 | J27: =H27*I27 -> 36456 | K27: 12 | L27: =K27*I27*$F$11 -> 37732 | M27: 12 | N27: =M27*I27*$F$11*$F$11 -> 39053 | O27: 12 | P27: =O27*I27*$F$11*$F$11*$F$11 -> 40419 | Q27: 6 | R27: =I27*Q27*$F$11*$F$11*$F$11*$F$11 -> 20917 | S27: =SUM(J27+L27+N27+P27+R27) -> 174577 | T27: 0 | U27: =SUM(S27:T27) -> 174577
A28: PERSNL-AST | B28: 70000 | C28: MEX | D28: 0 | E28: Administration Officer (50%) ASA | F28: Salaries | G28: Month | H28: 12 | I28: =2010*0.5 -> 1005 | J28: =H28*I28 -> 12060 | K28: 12 | L28: =K28*I28*$F$11 -> 12482 | M28: 12 | N28: =M28*I28*$F$11*$F$11 -> 12919 | O28: 12 | P28: =O28*I28*$F$11*$F$11*$F$11 -> 13371 | Q28: 6 | R28: =I28*Q28*$F$11*$F$11*$F$11*$F$11 -> 6920 | S28: =SUM(J28+L28+N28+P28+R28) -> 57752 | T28: 0 | U28: =SUM(S28:T28) -> 57752
A29: PERSNL-ACT | B29: 70000 | C29: MEX | D29: 0 | E29: Finance Officer (100%) LGA | F29: Salaries | G29: Month | H29: 8 | I29: 1900 | J29: =H29*I29 -> 15200 | K29: 12 | L29: =K29*I29*$F$11 -> 23598 | M29: 12 | N29: =M29*I29*$F$11*$F$11 -> 24424 | O29: 12 | P29: =O29*I29*$F$11*$F$11*$F$11 -> 25279 | Q29: 6 | R29: =I29*Q29*$F$11*$F$11*$F$11*$F$11 -> 13082 | S29: =SUM(J29+L29+N29+P29+R29) -> 101583 | T29: 0 | U29: =SUM(S29:T29) -> 101583
E31: Home Office Support
A32: PERSNL-PM | B32: Timesheets | C32: 0 | D32: 0 | E32: Project Manager (10%) | F32: Salaries | G32: Month | H32: 12 | I32: =13000*0.1 -> 1300 | J32: =H32*I32 -> 15600 | K32: 12 | L32: =K32*I32*$F$11 -> 16146 | M32: 12 | N32: =M32*I32*$F$11*$F$11 -> 16711 | O32: 12 | P32: =O32*I32*$F$11*$F$11*$F$11 -> 17296 | Q32: 6 | R32: =I32*Q32*$F$11*$F$11*$F$11*$F$11 -> 8951 | S32: =SUM(J32+L32+N32+P32+R32) -> 74704 | T32: 0 | U32: =SUM(S32:T32) -> 74704
A33: PERSNL-PO | B33: Timesheets | C33: 0 | D33: 0 | E33: Program Officer (40%) | F33: Salaries | G33: Month | H33: 12 | I33: =5500*0.4 -> 2200 | J33: =H33*I33 -> 26400 | K33: 12 | L33: =K33*I33*$F$11 -> 27324 | M33: 12 | N33: =M33*I33*$F$11*$F$11 -> 28280 | O33: 12 | P33: =O33*I33*$F$11*$F$11*$F$11 -> 29270 | Q33: 6 | R33: =I33*Q33*$F$11*$F$11*$F$11*$F$11 -> 15147 | S33: =SUM(J33+L33+N33+P33+R33) -> 126421 | T33: 0 | U33: =SUM(S33:T33) -> 126421
E35: Subtotal Personnel | J35: =SUM(J15:J33) -> 375586 | L35: =SUM(L15:L33) -> 533725 | N35: =SUM(N15:N33) -> 552404 | P35: =SUM(P15:P33) -> 571738 | R35: =SUM(R15:R33) -> 230054 | S35: =SUM(J35+L35+N35+P35+R35) -> 2263507 | T35: 0 | U35: =SUM(S35:T35) -> 2263507
E37: Fringe Benefits
A38: FRINGE-MX | B38: 70015 | C38: MEX | D38: 0 | E38: Fringe benefits - Mexico | F38: Fringe Benefits | G38: Month | I38: 0.3671 | J38: =SUM(J15:J29)*$I38 -> 122459 | L38: =SUM(L15:L29)*$I38 -> 179973 | N38: =SUM(N15:N29)*$I38 -> 186271 | P38: =SUM(P15:P29)*$I38 -> 192791 | R38: =SUM(R15:R29)*$I38 -> 75606 | S38: =SUM(J38+L38+N38+P38+R38) -> 757100 | T38: 0 | U38: =SUM(S38:T38) -> 757100
A39: FRINGE | B39: Timesheets | C39: 0 | D39: 0 | E39: Fringe benefits - Home Office Support | F39: Fringe Benefits | G39: Month | I39: 0.2181 | J39: =SUM(J32:J33)*$I$39 -> 9160 | L39: =SUM(L32:L33)*$I$39 -> 9481 | N39: =SUM(N32:N33)*$I$39 -> 9813 | P39: =SUM(P32:P33)*$I$39 -> 10156 | R39: =SUM(R32:R33)*$I$39 -> 5256 | S39: =SUM(J39+L39+N39+P39+R39) -> 43866 | T39: 0 | U39: =SUM(S39:T39) -> 43866
E41: Subtotal Fringe Benefits | J41: =SUM(J38:J40) -> 131619 | L41: =SUM(L38:L40) -> 189454 | N41: =SUM(N38:N40) -> 196084 | P41: =SUM(P38:P40) -> 202947 | R41: =SUM(R38:R40) -> 80862 | S41: =SUM(S38:S40) -> 800966 | T41: =SUM(T39:T39) -> 0 | U41: =SUM(U38:U40) -> 800966
E42: Subtotal Direct Labor (Personnel & Fringe Benefits) | J42: =J41+J35 -> 507205 | L42: =L41+L35 -> 723179 | N42: =N41+N35 -> 748488 | P42: =P41+P35 -> 774685 | R42: =R41+R35 -> 310916 | S42: =S41+S35 -> 3064473 | T42: =T41+T35 -> 0 | U42: =U41+U35 -> 3064473
E43: Travel
E44: T1: Post-award Meeting with ILAB
A45: GE.T1.A | B45: 86040 | C45: 0/MEX | D45: 0 | E45: Airfare - Mexico-DC | F45: Travel | G45: Trip | I45: 650 | J45: =H45*I45 -> 0 | K45: 2 | L45: =K45*I45*$F$10 -> 1352 | N45: =M45*I45*$F$10*$F$10 -> 0 | O45: 0 | P45: =O45*I45*$F$10*$F$10*$F$10 -> 0 | Q45: 0 | R45: =Q45*I45*$F$10*$F$10*$F$10*$F$10 -> 0 | S45: =J45+L45+N45+P45+R45 -> 1352 | T45: - | U45: =SUM(S45:T45) -> 1352
A46: GE.T1.B | B46: 86030 (Lodging)/ 86050 (M&IE) | C46: 0/MEX | D46: 0 | E46: Lodging and M&IE in DC | F46: Travel | G46: Day | I46: 218 | J46: =H46*I46 -> 0 | K46: 10 | L46: =K46*I46*$F$10 -> 2267 | N46: =M46*I46*$F$10*$F$10 -> 0 | O46: 0 | P46: =O46*I46*$F$10*$F$10*$F$10 -> 0 | Q46: 0 | R46: =Q46*I46*$F$10*$F$10*$F$10*$F$10 -> 0 | S46: =J46+L46+N46+P46+R46 -> 2267 | T46: - | U46: =SUM(S46:T46) -> 2267
A47: GE.T1.C | B47: 86000 | C47: 0/MEX | D47: 0 | E47: Local transportation in DC | F47: Travel | G47: Day | I47: 60 | J47: =H47*I47 -> 0 | K47: 10 | L47: =K47*I47*$F$10 -> 624 | N47: =M47*I47*$F$10*$F$10 -> 0 | O47: 0 | P47: =O47*I47*$F$10*$F$10*$F$10 -> 0 | Q47: 0 | R47: =Q47*I47*$F$10*$F$10*$F$10*$F$10 -> 0 | S47: =J47+L47+N47+P47+R47 -> 624 | T47: - | U47: =SUM(S47:T47) -> 624
A48: GE.T1.D | B48: 86050 | C48: 0/MEX | D48: 0 | E48: U.S. Visa Fees | F48: Travel | G48: Trip | I48: 160 | J48: =H48*I48 -> 0 | K48: 2 | L48: =K48*I48*$F$10 -> 333 | N48: =M48*I48*$F$10*$F$10 -> 0 | O48: 0 | P48: =O48*I48*$F$10*$F$10*$F$10 -> 0 | Q48: 0 | R48: =Q48*I48*$F$10*$F$10*$F$10*$F$10 -> 0 | S48: =J48+L48+N48+P48+R48 -> 333 | T48: - | U48: =SUM(S48:T48) -> 333
E49: T2: Field Personnel Annual Visits with ILAB
A50: GE.T2.A | B50: 86040 | C50: 0/MEX | D50: 0 | E50: Airfare - Mexico-DC | F50: Travel | G50: Trip | H50: 2 | I50: 650 | J50: =H50*I50 -> 1300 | K50: 2 | L50: =K50*I50*$F$10 -> 1352 | M50: 2 | N50: =M50*I50*$F$10*$F$10 -> 1406 | O50: 2 | P50: =O50*I50*$F$10*$F$10*$F$10 -> 1462 | Q50: 2 | R50: =Q50*I50*$F$10*$F$10*$F$10*$F$10 -> 1521 | S50: =J50+L50+N50+P50+R50 -> 7041 | T50: - | U50: =SUM(S50:T50) -> 7041
A51: GE.T2.B | B51: 86030 (Lodging)/ 86050 (M&IE) | C51: 0/MEX | D51: 0 | E51: Lodging and M&IE in DC | F51: Travel | G51: Day | H51: 5 | I51: 218 | J51: =H51*I51 -> 1090 | K51: 10 | L51: =K51*I51*$F$10 -> 2267 | M51: 10 | N51: =M51*I51*$F$10*$F$10 -> 2358 | O51: 10 | P51: =O51*I51*$F$10*$F$10*$F$10 -> 2452 | Q51: 10 | R51: =Q51*I51*$F$10*$F$10*$F$10*$F$10 -> 2550 | S51: =J51+L51+N51+P51+R51 -> 10717 | T51: - | U51: =SUM(S51:T51) -> 10717
A52: GE.T2.C | B52: 86000 | C52: 0/MEX | D52: 0 | E52: Local transportation in DC | F52: Travel | G52: Day | H52: 5 | I52: 60 | J52: =H52*I52 -> 300 | K52: 10 | L52: =K52*I52*$F$10 -> 624 | M52: 10 | N52: =M52*I52*$F$10*$F$10 -> 649 | O52: 10 | P52: =O52*I52*$F$10*$F$10*$F$10 -> 675 | Q52: 10 | R52: =Q52*I52*$F$10*$F$10*$F$10*$F$10 -> 702 | S52: =J52+L52+N52+P52+R52 -> 2950 | T52: - | U52: =SUM(S52:T52) -> 2950
E53: T3: Project Management Travel to Field
A54: GE.T3.A | B54: 86040 | C54: MEX | D54: 0 | E54: Airfare - DC-Mexico | F54: Travel | G54: Trip | H54: 10 | I54: 650 | J54: =I54*H54 -> 6500 | K54: 4 | L54: =K54*I54*$F$10 -> 2704 | M54: 4 | N54: =M54*I54*$F$10*$F$10 -> 2812 | O54: 4 | P54: =O54*I54*$F$10*$F$10*$F$10 -> 2925 | Q54: 2 | R54: =Q54*I54*$F$10*$F$10*$F$10*$F$10 -> 1521 | S54: =J54+L54+N54+P54+R54 -> 16462 | T54: - | U54: =SUM(S54:T54) -> 16462
A55: GE.T3.B | B55: 86030 (Lodging)/ 86050 (M&IE) | C55: MEX | D55: 0 | E55: Lodging and M&IE in Mexico | F55: Travel | G55: Day | H55: =H54*5 -> 50 | I55: 216 | J55: =I55*H55 -> 10800 | K55: =K54*5 -> 20 | L55: =K55*I55*$F$10 -> 4493 | M55: =M54*5 -> 20 | N55: =M55*I55*$F$10*$F$10 -> 4673 | O55: =O54*5 -> 20 | P55: =O55*I55*$F$10*$F$10*$F$10 -> 4859 | Q55: =Q54*5 -> 10 | R55: =Q55*I55*$F$10*$F$10*$F$10*$F$10 -> 2527 | S55: =J55+L55+N55+P55+R55 -> 27352 | T55: - | U55: =SUM(S55:T55) -> 27352
A56: GE.T3.C | B56: 86000 | C56: MEX | D56: 0 | E56: Local transportation in Mexico | F56: Travel | G56: Day | H56: =H54*5 -> 50 | I56: 60 | J56: =I56*H56 -> 3000 | K56: =K54*5 -> 20 | L56: =K56*I56*$F$10 -> 1248 | M56: =M54*5 -> 20 | N56: =M56*I56*$F$10*$F$10 -> 1298 | O56: =O54*5 -> 20 | P56: =O56*I56*$F$10*$F$10*$F$10 -> 1350 | Q56: =Q54*5 -> 10 | R56: =Q56*I56*$F$10*$F$10*$F$10*$F$10 -> 702 | S56: =J56+L56+N56+P56+R56 -> 7598 | T56: - | U56: =SUM(S56:T56) -> 7598
E57: T.4 Field-based Travel for Non-M&E Activities
A58: GE.T4.A | B58: 86030 (Lodging)/ 86050 (M&IE) | C58: MEX | D58: 0 | E58: Lodging and M&IE | F58: Travel | G58: Day | H58: 10 | I58: 110 | J58: =(H58*I58) -> 1100 | K58: 10 | L58: =K58*I58*$F$10 -> 1144 | M58: 10 | N58: =M58*I58*$F$10*$F$10 -> 1190 | O58: 10 | P58: =O58*I58*$F$10*$F$10*$F$10 -> 1237 | Q58: 2 | R58: =Q58*I58*$F$10*$F$10*$F$10*$F$10 -> 257 | S58: =J58+L58+N58+P58+R58 -> 4928 | T58: 0 | U58: =SUM(S58:T58) -> 4928
A59: GE.T4.B | B59: 86000 | C59: MEX | D59: 0 | E59: Local transportation (ground transportation) | F59: Travel | G59: Day | H59: 10 | I59: 60 | J59: =H59*I59 -> 600 | K59: 10 | L59: =K59*I59*$F$10 -> 624 | M59: 10 | N59: =M59*I59*$F$10*$F$10 -> 649 | O59: 10 | P59: =O59*I59*$F$10*$F$10*$F$10 -> 675 | Q59: 2 | R59: =Q59*I59*$F$10*$F$10*$F$10*$F$10 -> 140 | S59: =J59+L59+N59+P59+R59 -> 2688 | T59: 0 | U59: =SUM(S59:T59) -> 2688
A60: GE.T4.C | B60: 86040 | C60: MEX | D60: 0 | E60: Local transportation (airfare) | F60: Travel | G60: Trip | H60: 12 | I60: 600 | J60: =(I60*H60) -> 7200 | K60: 8 | L60: =K60*I60*$F$10 -> 4992 | M60: 8 | N60: =M60*I60*$F$10*$F$10 -> 5192 | O60: 8 | P60: =O60*I60*$F$10*$F$10*$F$10 -> 5399 | Q60: 1 | R60: =Q60*I60*$F$10*$F$10*$F$10*$F$10 -> 702 | S60: =J60+L60+N60+P60+R60 -> 23485 | T60: 0 | U60: =SUM(S60:T60) -> 23485
E62: Subtotal Travel | J62: =SUM(J45:J60) -> 31890 | L62: =SUM(L45:L60) -> 24024 | N62: =SUM(N45:N60) -> 20227 | P62: =SUM(P45:P60) -> 21034 | R62: =SUM(R45:R60) -> 10622 | S62: =SUM(S45:S60) -> 107797 | T62: =SUM(T45:T60) -> 0 | U62: =SUM(S62:T62) -> 107797
E63: Equipment
A64: VEHICLE | B64: 85200 | C64: MEX | D64: 0 | E64: Project Vehicle | F64: Equipment | G64: Unit | J64: =H64*I64 -> 0 | K64: 0 | L64: =K64*I64*$F$10 -> 0 | M64: 0 | N64: =M64*I64*$F$10*$F$10 -> 0 | O64: 0 | P64: =O64*I64*$F$10*$F$10*$F$10 -> 0 | Q64: 0 | R64: =Q64*I64*$F$10*$F$10*$F$10*$F$10 -> 0 | S64: =J64+L64+N64+P64+R64 -> 0 | T64: 0 | U64: =SUM(S64:T64) -> 0
E66: Subtotal Equipment | J66: =SUM(J64) -> 0 | L66: =SUM(L64) -> 0 | N66: =SUM(N64) -> 0 | P66: =SUM(P64) -> 0 | R66: =SUM(R64) -> 0 | S66: =J66+L66+N66+P66+R66 -> 0 | T66: =SUM(T64) -> 0 | U66: =SUM(S66:T66) -> 0
E67: Supplies and Office Expenses
E68: Project Office
A69: LAPTOP | B69: 82401 | C69: MEX | D69: 0 | E69: Laptop computers & software | F69: Supplies | G69: Unit | H69: 12 | I69: 1200 | J69: =H69*I69 -> 14400 | L69: =K69*I69*$F$10 -> 0 | M69: 0 | N69: =M69*I69*$F$10*$F$10 -> 0 | O69: 0 | P69: =O69*I69*$F$10*$F$10*$F$10 -> 0 | Q69: 0 | R69: =Q69*I69*$F$10*$F$10*$F$10*$F$10 -> 0 | S69: =J69+L69+N69+P69+R69 -> 14400 | T69: 0 | U69: =SUM(S69:T69) -> 14400
A70: BANK FEES | B70: 90900 | C70: MEX | D70: 0 | E70: Banking and cash handling fees | F70: Office Expenses | G70: Month | H70: 12 | I70: 50 | J70: =H70*I70 -> 600 | K70: 12 | L70: =K70*I70*$F$10 -> 624 | M70: 12 | N70: =M70*I70*$F$10*$F$10 -> 649 | O70: 12 | P70: =O70*I70*$F$10*$F$10*$F$10 -> 675 | Q70: 6 | R70: =Q70*I70*$F$10*$F$10*$F$10*$F$10 -> 351 | S70: =J70+L70+N70+P70+R70 -> 2899 | T70: 0 | U70: =SUM(S70:T70) -> 2899
A71: COURIER | B71: 82350 | C71: MEX | D71: 0 | E71: Courier fees/services | F71: Office Expenses | G71: Year | H71: 1 | I71: 70 | J71: =H71*I71 -> 70 | K71: 1 | L71: =K71*I71*$F$10 -> 73 | M71: 1 | N71: =M71*I71*$F$10*$F$10 -> 76 | O71: 1 | P71: =O71*I71*$F$10*$F$10*$F$10 -> 79 | Q71: 0.5 | R71: =Q71*I71*$F$10*$F$10*$F$10*$F$10 -> 41 | S71: =J71+L71+N71+P71+R71 -> 339 | T71: 0 | U71: =SUM(S71:T71) -> 339
A72: RECRUIT | B72: 90450 | C72: MEX | D72: 0 | E72: Recruitment/Procurement Advertising | F72: Office Expenses | G72: Per position | H72: 9 | I72: 650 | J72: =H72*I72 -> 5850 | K72: 1 | L72: =K72*I72*$F$10 -> 676 | M72: 1 | N72: =M72*I72*$F$10*$F$10 -> 703 | O72: 1 | P72: =O72*I72*$F$10*$F$10*$F$10 -> 731 | Q72: 0 | R72: =Q72*I72*$F$10*$F$10*$F$10*$F$10 -> 0 | S72: =J72+L72+N72+P72+R72 -> 7960 | T72: 0 | U72: =SUM(S72:T72) -> 7960
A73: SUPPLIES | B73: 82401 | C73: MEX | D73: 0 | E73: Office supplies | F73: Supplies | G73: Month | H73: 6 | I73: 375 | J73: =I73*H73 -> 2250 | K73: 12 | L73: =K73*I73*$F$10 -> 4680 | M73: 12 | N73: =M73*I73*$F$10*$F$10 -> 4867 | O73: 12 | P73: =O73*I73*$F$10*$F$10*$F$10 -> 5062 | Q73: 3 | R73: =Q73*I73*$F$10*$F$10*$F$10*$F$10 -> 1316 | S73: =J73+L73+N73+P73+R73 -> 18175 | T73: 0 | U73: =SUM(S73:T73) -> 18175
A74: COMM | B74: 82030 | C74: MEX | D74: 0 | E74: Communications Costs (Internet, Phone, Data) | F74: Office Expenses | G74: Month | H74: 3 | I74: 1200 | J74: =H74*I74 -> 3600 | K74: 12 | L74: =K74*I74*$F$10 -> 14976 | M74: 12 | N74: =M74*I74*$F$10*$F$10 -> 15575 | O74: 12 | P74: =O74*I74*$F$10*$F$10*$F$10 -> 16198 | Q74: 4 | R74: =Q74*I74*$F$10*$F$10*$F$10*$F$10 -> 5615 | S74: =J74+L74+N74+P74+R74 -> 55964 | T74: 0 | U74: =SUM(S74:T74) -> 55964
A75: RENT & UT | B75: 85180 | C75: MEX | D75: 0 | E75: Coworking office space in CDMEX | F75: Office Expenses | G75: Month | H75: 12 | I75: 3350 | J75: =H75*I75 -> 40200 | K75: 12 | L75: =K75*I75*$F$10 -> 41808 | M75: 12 | N75: =M75*I75*$F$10*$F$10 -> 43480 | O75: 12 | P75: =O75*I75*$F$10*$F$10*$F$10 -> 45220 | Q75: 3 | R75: =Q75*I75*$F$10*$F$10*$F$10*$F$10 -> 11757 | S75: =J75+L75+N75+P75+R75 -> 182465 | T75: 0 | U75: =SUM(S75:T75) -> 182465
A76: RENT & UT | B76: 85180 | C76: MEX | D76: 0 | E76: Coworking office space in Jalisco | F76: Office Expenses | G76: Month | H76: 4 | I76: 420 | J76: =H76*I76 -> 1680 | K76: 12 | L76: =K76*I76*$F$10 -> 5242 | M76: 12 | N76: =M76*I76*$F$10*$F$10 -> 5451 | O76: 12 | P76: =O76*I76*$F$10*$F$10*$F$10 -> 5669 | Q76: 3 | R76: =Q76*I76*$F$10*$F$10*$F$10*$F$10 -> 1474 | S76: =J76+L76+N76+P76+R76 -> 19516 | T76: 0 | U76: =SUM(S76:T76) -> 19516
A77: RENT & UT | B77: 85180 | C77: MEX | D77: 0 | E77: Coworking office space in Chihuahua | F77: Office Expenses | G77: Month | H77: 4 | I77: 420 | J77: =H77*I77 -> 1680 | K77: 12 | L77: =K77*I77*$F$10 -> 5242 | M77: 12 | N77: =M77*I77*$F$10*$F$10 -> 5451 | O77: 12 | P77: =O77*I77*$F$10*$F$10*$F$10 -> 5669 | Q77: 3 | R77: =Q77*I77*$F$10*$F$10*$F$10*$F$10 -> 1474 | S77: =J77+L77+N77+P77+R77 -> 19516 | T77: 0 | U77: =SUM(S77:T77) -> 19516
A78: PROP&LIAB | B78: 89500 | C78: MEX | D78: 0 | E78: Property and liability insurance | F78: Office Expenses | G78: Year | H78: 1 | I78: 300 | J78: =H78*I78 -> 300 | K78: 1 | L78: =K78*I78*$F$10 -> 312 | M78: 1 | N78: =M78*I78*$F$10*$F$10 -> 324 | O78: 1 | P78: =O78*I78*$F$10*$F$10*$F$10 -> 337 | Q78: 0.5 | R78: =Q78*I78*$F$10*$F$10*$F$10*$F$10 -> 175 | S78: =J78+L78+N78+P78+R78 -> 1448 | T78: 0 | U78: =SUM(S78:T78) -> 1448
A79: LEGAL | B79: 90100 | C79: MEX | D79: 0 | E79: Legal fees | F79: Office Expenses | G79: Year | H79: 1 | I79: 2400 | J79: =I79*H79 -> 2400 | K79: 1 | L79: =K79*I79*$F$10 -> 2496 | M79: 1 | N79: =M79*I79*$F$10*$F$10 -> 2596 | O79: 1 | P79: =O79*I79*$F$10*$F$10*$F$10 -> 2700 | Q79: 0.5 | R79: =Q79*I79*$F$10*$F$10*$F$10*$F$10 -> 1404 | S79: =J79+L79+N79+P79+R79 -> 11596 | T79: 0 | U79: =SUM(S79:T79) -> 11596
A80: PAYROLL | B80: 81030 | C80: MEX | D80: 0 | E80: Payroll Processing | F80: Office Expenses | G80: Month | H80: 5 | I80: 350 | J80: =H80*I80 -> 1750 | K80: 12 | L80: =K80*I80*$F$10 -> 4368 | M80: 12 | N80: =M80*I80*$F$10*$F$10 -> 4543 | O80: 12 | P80: =O80*I80*$F$10*$F$10*$F$10 -> 4724 | Q80: 6 | R80: =Q80*I80*$F$10*$F$10*$F$10*$F$10 -> 2457 | S80: =J80+L80+N80+P80+R80 -> 17842 | T80: - | U80: =SUM(S80:T80) -> 17842
E81: Audits and Attestation Engagements
A82: AUDIT | B82: 82100 | C82: MEX | D82: 0 | E82: Audit costs (A-133) | F82: Supplies | G82: Year | I82: 4000 | J82: =H82*I82 -> 0 | K82: 1 | L82: =K82*I82*$F$9 -> 4120 | M82: 1 | N82: =M82*I82*$F$10*$F$10 -> 4326 | O82: 1 | P82: =O82*I82*$F$10*$F$10*$F$10 -> 4499 | Q82: 0 | R82: =Q82*I82*$F$10*$F$10*$F$10*$F$10 -> 0 | S82: =J82+L82+N82+P82+R82 -> 12945 | T82: 0 | U82: =SUM(S82:T82) -> 12945
A83: ATTESTENG | B83: 81010 | C83: MEX | D83: 0 | E83: Attestation Engagement | F83: Supplies | G83: Year | H83: 0 | I83: 100000 | J83: =H83*I83 -> 0 | K83: 0 | L83: =K83*I83*$F$9 -> 0 | M83: 1 | N83: =M83*I83 -> 100000 | O83: 0 | P83: =O83*I83*$F$9*$F$9*$F$9 -> 0 | Q83: 0 | R83: =Q83*I83*$F$9*$F$9*$F$9*$F$9 -> 0 | S83: =J83+L83+N83+P83+R83 -> 100000 | T83: 0 | U83: =SUM(S83:T83) -> 100000
E84: Project-wide Web Fees
A85: SUBSCRIPT | B85: 89400 | C85: MEX/0 | D85: 0 | E85: Timekeeping and expense reporting platform | F85: Supplies | G85: Month | H85: 12 | I85: 150 | J85: =H85*I85 -> 1800 | K85: 12 | L85: =K85*I85*$F$10 -> 1872 | M85: 12 | N85: =M85*I85*$F$9*$F$9 -> 1910 | O85: 12 | P85: =O85*I85*$F$9*$F$9*$F$9 -> 1967 | Q85: 6 | R85: =Q85*I85*$F$9*$F$9*$F$9*$F$9 -> 1013 | S85: =J85+L85+N85+P85+R85 -> 8562 | T85: 0 | U85: =SUM(S85:T85) -> 8562
A86: SUBSCRIPT | B86: 89400 | C86: MEX/0 | D86: 0 | E86: Zoom license and platform subscriptions | F86: Supplies | G86: Year | I86: 200 | J86: =H86*I86 -> 0 | K86: 1 | L86: =K86*I86*$F$9 -> 206 | M86: 1 | N86: =M86*I86*$F$9*$F$9 -> 212 | O86: 1 | P86: =O86*I86*$F$9*$F$9*$F$9 -> 219 | Q86: 1 | R86: =Q86*I86*$F$9*$F$9*$F$9*$F$9 -> 225 | S86: =J86+L86+N86+P86+R86 -> 862 | T86: 0 | U86: =SUM(S86:T86) -> 862
E88: Subtotal Supplies and Office Expenses | J88: =SUM(J69:J86) -> 76580 | L88: =SUM(L69:L86) -> 86695 | N88: =SUM(N69:N86) -> 190163 | P88: =SUM(P69:P86) -> 93749 | R88: =SUM(R69:R86) -> 27302 | S88: =J88+L88+N88+P88+R88 -> 474489 | T88: =SUM(T71:T86) -> 0 | U88: =SUM(S88:T88) -> 474489
E89: Contractual (Subawards and Contracts)
A90: SUBRMS | B90: 89050 | C90: MEX | D90: RMS | E90: Subaward to RMS | F90: Contractual | G90: Subaward | H90: 1 | I90: =RMS!K115 -> 90926 | J90: =RMS!K115 -> 90926 | K90: 1 | L90: =RMS!M115 -> 579752 | M90: 1 | N90: =RMS!O115 -> 521443 | O90: 1 | P90: =RMS!Q115 -> 443815 | Q90: 1 | R90: =RMS!S115 -> 94562 | S90: =SUM(J90,L90,N90,P90,R90) -> 1730498 | T90: 0 | U90: =SUM(S90:T90) -> 1730498
A91: SUBCEREAL | B91: 89050 | C91: MEX | D91: CEREAL | E91: Subaward to CEREAL | F91: Contractual | G91: Subaward | I91: 0 | J91: =CEREAL!K99 -> 50929 | K91: 1 | L91: =CEREAL!M99 -> 248448 | M91: 1 | N91: =CEREAL!O99 -> 210006 | O91: 1 | P91: =CEREAL!Q99 -> 213864 | Q91: 1 | R91: =CEREAL!S99 -> 44377 | S91: =J91+L91+N91+P91+R91 -> 767624 | T91: 0 | U91: =SUM(S91:T91) -> 767624
A92: SUBTRANMYM | B92: 89050 | C92: MEX | D92: TRANMYM | E92: Fixed Price Subaward to Transforma MyM | F92: Contractual | G92: Subaward | I92: 0 | J92: 11830 | K92: 1 | L92: 48053 | M92: 1 | N92: 62551 | O92: 1 | P92: 36604 | Q92: 1 | R92: 8278 | S92: =J92+L92+N92+P92+R92 -> 167316 | T92: 0 | U92: =SUM(S92:T92) -> 167316
A93: CONMASPRO | B93: 89000 | C93: MEX | D93: MASPRO | E93: Contract to Mas Proyectos | F93: Contractual | G93: Contract | I93: 0 | J93: 37772 | K93: 1 | L93: 124385 | M93: 1 | N93: 122586 | O93: 1 | P93: 120528 | Q93: 1 | R93: 10028 | S93: =J93+L93+N93+P93+R93 -> 415299 | T93: 0 | U93: =SUM(S93:T93) -> 415299
A94: RPFAT | B94: 89000 | C94: MEX | D94: FAT | E94: Resource Partner: FAT | F94: Contractual | G94: Contract | H94: 1 | I94: 5000 | J94: =I94*H94 -> 5000 | K94: 2.5 | L94: =K94*I94 -> 12500 | M94: 2.5 | N94: =M94*I94 -> 12500 | O94: 2 | P94: =O94*I94 -> 10000 | Q94: 0 | R94: =Q94*I94 -> 0 | S94: =SUM(J94,L94,N94,P94,R94) -> 40000 | T94: 0 | U94: =SUM(S94:T94) -> 40000
A95: RPIBERO | B95: 89000 | C95: MEX | D95: IBERO | E95: Resource Partner: Ibero | F95: Contractual | G95: Contract | H95: 0.5 | I95: 7500 | J95: =$I95*H95 -> 3750 | K95: 1.25 | L95: =$I95*K95 -> 9375 | M95: 1.25 | N95: =$I95*M95 -> 9375 | O95: 1 | P95: =$I95*O95 -> 7500 | Q95: 0 | R95: =Q95*I95 -> 0 | S95: =SUM(J95,L95,N95,P95,R95) -> 30000 | T95: 0 | U95: =SUM(S95:T95) -> 30000
A96: RPCFO | B96: 89000 | C96: MEX | D96: CFO | E96: Resource Partner: CFO | F96: Contractual | G96: Contract | H96: 0.5 | I96: =12500*2 -> 25000 | J96: =I96*H96 -> 12500 | K96: 0.8 | L96: =K96*I96 -> 20000 | M96: 0.8 | N96: =M96*I96 -> 20000 | O96: 0.5 | P96: =O96*I96 -> 12500 | Q96: 0 | R96: =Q96*I96 -> 0 | S96: =SUM(J96,L96,N96,P96,R96) -> 65000 | T96: 0 | U96: =SUM(S96:T96) -> 65000
A97: RPCOPIJAL | B97: 89000 | C97: MEX | D97: COPIJAL | E97: Resource Partner: COPIJAL | F97: Contractual | G97: Contract | H97: 0.5 | I97: 12500 | J97: =$I97*H97 -> 6250 | K97: 0.5 | L97: =$I97*K97 -> 6250 | M97: 0.5 | N97: =$I97*M97 -> 6250 | O97: 0.5 | P97: =$I97*O97 -> 6250 | Q97: 0 | R97: =Q97*I97 -> 0 | S97: =SUM(J97,L97,N97,P97,R97) -> 25000 | T97: 0 | U97: =SUM(S97:T97) -> 25000
A98: RPFOTESO | B98: 89000 | C98: MEX | D98: FOTESO | E98: Resource Partner: FOTESO | F98: Contractual | G98: Contract | H98: 1 | I98: 5000 | J98: 5000 | K98: 2.5 | L98: =K98*I98 -> 12500 | M98: 2.5 | N98: =M98*I98 -> 12500 | O98: 2 | P98: =O98*I98 -> 10000 | Q98: 0 | R98: =Q98*I98 -> 0 | S98: =SUM(J98,L98,N98,P98,R98) -> 40000 | T98: 0 | U98: =SUM(S98:T98) -> 40000
A99: RPINCIDIR | B99: 89000 | C99: MEX | D99: INCIDIR | E99: Resource Partner: Incidir | F99: Contractual | G99: Contract | H99: 0.5 | I99: 12500 | J99: =$I99*H99 -> 6250 | K99: 1.25 | L99: =$I99*K99 -> 15625 | M99: 1.25 | N99: =$I99*M99 -> 15625 | O99: 1 | P99: =$I99*O99 -> 12500 | Q99: 0 | R99: =Q99*I99 -> 0 | S99: =SUM(J99,L99,N99,P99,R99) -> 50000 | T99: 0 | U99: =SUM(S99:T99) -> 50000
A100: RPCIPCO | B100: 89000 | C100: MEX | D100: CIPCO | E100: Resource Partner: CIPCO | F100: Contractual | G100: Contract | H100: 0.5 | I100: 12500 | J100: =$I100*H100 -> 6250 | K100: 1.25 | L100: =$I100*K100 -> 15625 | M100: 1.25 | N100: =$I100*M100 -> 15625 | O100: 1 | P100: =$I100*O100 -> 12500 | Q100: 0 | R100: =Q100*I100 -> 0 | S100: =SUM(J100,L100,N100,P100,R100) -> 50000 | T100: 0 | U100: =SUM(S100:T100) -> 50000
E102: Subtotal Contractual (Subawards and Contracts) | J102: =SUM(J90:J100) -> 236457 | L102: =SUM(L90:L100) -> 1092513 | N102: =SUM(N90:N100) -> 1008461 | P102: =SUM(P90:P100) -> 886061 | R102: =SUM(R90:R100) -> 157245 | S102: =SUM(S90:S100) -> 3380737 | T102: =SUM(T90:T100) -> 0 | U102: =SUM(U90:U100) -> 3380737
E103: Outcome 1: WO advance issues surrounding substantive equality, including gender proportionality in leadership and participation in key activities, within their institutions
E104: Activities/Costs
E105: 1. Conduct a diagnostic and report on gender equality and representation issues within worker organizations
A106: GE.1.1.A | B106: 87010 | C106: MEX | D106: 0 | E106: Participatory diagnosis on gender equality and gender representation issues within WO | F106: Outcome1 | G106: Meeting | I106: 200 | J106: =I106*H106 -> 0 | K106: 20 | L106: =K106*I106 -> 4000 | N106: =M106*I106 -> 0 | P106: =O106*I106 -> 0 | R106: =Q106*I106 -> 0 | S106: =SUM(J106,L106,N106,P106,R106) -> 4000 | U106: =SUM(S106:T106) -> 4000
A107: GE.1.1.B | B107: 86030 (Lodging)/ 86050 (M&IE) | C107: MEX | D107: 0 | E107: Lodging and M&IE for diagnostic development | F107: Travel | G107: Day | H107: 5 | I107: 110 | J107: =I107*H107 -> 550 | K107: 15 | L107: =K107*I107 -> 1650 | M107: 0 | N107: =M107*I107 -> 0 | O107: 0 | P107: =O107*I107 -> 0 | Q107: 0 | R107: =Q107*I107 -> 0 | S107: =SUM(J107,L107,N107,P107,R107) -> 2200 | T107: 0 | U107: =SUM(S107:T107) -> 2200
A108: GE.1.1.C | B108: 86000 | C108: MEX | D108: 0 | E108: Local transportation for diagnostic development | F108: Travel | G108: Day | H108: 5 | I108: 60 | J108: =I108*H108 -> 300 | K108: 15 | L108: =K108*I108 -> 900 | M108: 0 | N108: =M108*I108 -> 0 | O108: 0 | P108: =O108*I108 -> 0 | Q108: 0 | R108: =Q108*I108 -> 0 | S108: =SUM(J108,L108,N108,P108,R108) -> 1200 | T108: 0 | U108: =SUM(S108:T108) -> 1200
A109: GE.1.1.D | B109: 81000 | C109: MEX | D109: 0 | E109: Consultant: Lead for the diagnostic and report on gender equality and representation issues within worker organizations | F109: Contractual | G109: Day | H109: 10 | I109: 350 | J109: =I109*H109 -> 3500 | K109: 40 | L109: =K109*I109 -> 14000 | N109: =M109*I109 -> 0 | P109: =O109*I109 -> 0 | R109: =Q109*I109 -> 0 | S109: =SUM(J109,L109,N109,P109,R109) -> 17500 | U109: =SUM(S109:T109) -> 17500
...

Sheet Comparasion
A1: Equal Access to Quality Jobs for Women and Girls in Agriculture (EQUAL)
A2: FOA-ILAB-19-02
A3: Partners of the Americas
A4: Project Name: Improving Gender Equity in the Mexican Workplace
A5: BUDGET ITEM | B5: Current approved allocation | C5: New proposed allocation | D5: New proposed allocation
A6: Direct Labor (Personnel & Fringe Benefits)
A7: Key Personnel
A8: Project Director (100%) - Dr. Alma Rico | B8: 453777 | C8: ='Project Budget'!S15 -> 459716 | D8: ='Project Budget'!U15 -> 459716
A9: Monitoring and Evaluation (M&E) Officer (100%) - Ms. Ana Georgina Pulido-Carrillo | B9: 253722 | C9: ='Project Budget'!S16 -> 248444 | D9: ='Project Budget'!U16 -> 248444
A11: Other Professional Personnel
A12: Gender Specialist (100%) | B12: 200619 | C12: ='Project Budget'!U19 -> 153066 | D12: =B12-C12 -> 47553
A13: Work Labor Organizations Specialist (100%) GVG | B13: 0 | C13: ='Project Budget'!U20 -> 168076 | D13: =B13-C13 -> -168076
A14: Communication Specialist (100%) VRG | B14: 0 | C14: ='Project Budget'!U21 -> 134461 | D14: =B14-C14 -> -134461
A15: Regional Coordinator CDMX (100%) | B15: 112871 | C15: ='Project Budget'!U22 -> 114733 | D15: =B15-C15 -> -1862
A16: Regional Coordinator Jalisco (100%) | B16: 112871 | C16: ='Project Budget'!U23 -> 114733 | D16: =B16-C16 -> -1862
A17: Regional Coordinator Chihuahua (100%) | B17: 112871 | C17: ='Project Budget'!U24 -> 114733 | D17: =B17-C17 -> -1862
A18: Communication Officer (100%) | B18: 146220 | C18: 0 | D18: =B18-C18 -> 146220
A19: Monitoring & Evaluation Specialist (100%) TBD | B19: 0 | C19: ='Project Budget'!S25 -> 115055 | D19: =B19-C19 -> -115055
A20: Project Assistant (100%) VILC | B20: 0 | C20: ='Project Budget'!S26 -> 105453 | D20: =B20-C20 -> -105453
A21: Finance & Administration Director (45%) RARH | B21: 169992 | C21: ='Project Budget'!S27 -> 174577 | D21: =B21-C21 -> -4585
A22: Administrative Assistant (100%) | B22: 94264 | C22: 0 | D22: =B22-C22 -> 94264
A23: Accountant (100%) | B23: 98130 | C23: 0 | D23: =B23-C23 -> 98130
A24: Administration Officer (50%) ASA | B24: 0 | C24: ='Project Budget'!U28 -> 57752 | D24: =B24-C24 -> -57752
A25: Finance Officer (100%) LGA | B25: 0 | C25: ='Project Budget'!U29 -> 101583 | D25: =B25-C25 -> -101583
A27: Home Office Support
A28: Project Manager (10%) | B28: 72078 | C28: ='Project Budget'!S32 -> 74704 | D28: =B28-C28 -> -2626
A29: Program Officer (40%) | B29: 126860 | C29: ='Project Budget'!S33 -> 126421 | D29: =B29-C29 -> 439
A31: Subtotal Personnel | B31: =SUM(B8:B29) -> 1954275 | C31: =SUM(C8:C29) -> 2263507 | D31: =B31-C31 -> -309232
A33: Fringe Benefits
A34: Fringe benefits - Mexico Staff | B34: 644385 | C34: ='Project Budget'!S38 -> 757100 | D34: =B34-C34 -> -112715
A35: Fringe benefits - Home Office Support | B35: 43388 | C35: ='Project Budget'!S39 -> 43866 | D35: =B35-C35 -> -478
A37: Subtotal Fringe Benefits | B37: =SUM(B33:B35) -> 687773 | C37: =SUM(C33:C35) -> 800966 | D37: =B37-C37 -> -113193
A38: Subtotal Direct Labor (Personnel & Fringe Benefits) | B38: =B37+B31 -> 2642048 | C38: =C37+C31 -> 3064473 | D38: =B38-C38 -> -422425
A39: Travel
A40: T1: Post-award Meeting with ILAB
A41: Airfare - Mexico-DC | B41: 1300 | C41: ='Project Budget'!U45 -> 1352 | D41: =B41-C41 -> -52
A42: Lodging and M&IE in DC | B42: 2184 | C42: ='Project Budget'!U46 -> 2267 | D42: =B42-C42 -> -83
A43: Local transportation in DC | B43: 600 | C43: ='Project Budget'!U47 -> 624 | D43: =B43-C43 -> -24
A44: U.S. Visa Fees | B44: 320 | C44: ='Project Budget'!U48 -> 333 | D44: =B44-C44 -> -13
A45: T2: Field Personnel Annual Visits with ILAB
A46: Airfare - Mexico-DC | B46: 3575 | C46: ='Project Budget'!U50 -> 7041 | D46: =B46-C46 -> -3466
A47: Lodging and M&IE in DC | B47: 9606 | C47: ='Project Budget'!U51 -> 10717 | D47: =B47-C47 -> -1111
A48: Local transportation in DC | B48: 2639 | C48: ='Project Budget'!U52 -> 2950 | D48: =B48-C48 -> -311
A49: T3: Project Management Travel to Field
A50: Airfare - DC-Mexico | B50: 5631 | C50: ='Project Budget'!U54 -> 16462 | D50: =B50-C50 -> -10831
A51: Lodging and M&IE in Mexico | B51: 9364 | C51: ='Project Budget'!U55 -> 27352 | D51: =B51-C51 -> -17988
A52: Local transportation in Mexico | B52: 4331 | C52: ='Project Budget'!U56 -> 7598 | D52: =B52-C52 -> -3267
A53: T.4 Field-based Travel for Non-M&E Activities
A54: Lodging and M&IE | B54: 82662 | C54: ='Project Budget'!U58 -> 4928 | D54: =B54-C54 -> 77734
A55: Local transportation (ground transportation) | B55: 21991 | C55: ='Project Budget'!U59 -> 2688 | D55: =B55-C55 -> 19303
A56: Local transportation (airfare) | B56: 65972 | C56: ='Project Budget'!U60 -> 23485 | D56: =B56-C56 -> 42487
A57: T.5 Local Field Travel
A58: Fuel for Vehicle | B58: 28180 | C58: 0 | D58: =B58-C58 -> 28180
A60: Subtotal Travel | B60: =SUM(B41:B58) -> 238355 | C60: =SUM(C41:C58) -> 107797 | D60: =B60-C60 -> 130558
A61: Equipment
A62: Project Vehicle | B62: 45000 | C62: 0 | D62: =B62-C62 -> 45000
A64: Subtotal Equipment | B64: =SUM(B62) -> 45000 | C64: =SUM(C62) -> 0 | D64: =B64-C64 -> 45000
A65: Supplies and Office Expenses
A66: Project Office
A67: Laptop computers & software | B67: 11400 | C67: ='Project Budget'!S69 -> 14400 | D67: =B67-C67 -> -3000
A68: Banking and cash handling fees | B68: 3479 | C68: ='Project Budget'!S70 -> 2899 | D68: =B68-C68 -> 580
A69: Courier fees/services | B69: 542 | C69: ='Project Budget'!S71 -> 339 | D69: =B69-C69 -> 203
A70: Recruitment/Procurement Advertising | B70: 2123 | C70: ='Project Budget'!S72 -> 7960 | D70: =B70-C70 -> -5837
A71: Office supplies | B71: 8371 | C71: ='Project Budget'!S73 -> 18175 | D71: =B71-C71 -> -9804
A72: Communications Costs (Internet, Phone, Data) | B72: 14202 | C72: ='Project Budget'!S74 -> 55964 | D72: =B72-C72 -> -41762
A73: Coworking office space in CDMX | B73: 68296 | C73: ='Project Budget'!S75 -> 182465 | D73: =B73-C73 -> -114169
A74: Coworking office space in Jalisco | B74: 24587 | C74: ='Project Budget'!S76 -> 19516 | D74: =B74-C74 -> 5071
A75: Coworking office space in Chihuahua | B75: 24587 | C75: ='Project Budget'!S77 -> 19516 | D75: =B75-C75 -> 5071
A76: Property and liability insurance | B76: 1625 | C76: ='Project Budget'!S78 -> 1448 | D76: =B76-C76 -> 177
A77: Vehicle Maintenance and Insurance | B77: 8124 | C77: 0 | D77: =B77-C77 -> 8124
A78: Legal fees | B78: 6500 | C78: ='Project Budget'!S79 -> 11596 | D78: =B78-C78 -> -5096
A79: Payroll Processing | B79: 21059 | C79: ='Project Budget'!S80 -> 17842 | D79: =B79-C79 -> 3217
A80: Audits and Attestation Engagements
A81: Audit costs (A-133) | B81: 20917 | C81: ='Project Budget'!S82 -> 12945 | D81: =B81-C81 -> 7972
A82: Attestation Engagement | B82: 106090 | C82: ='Project Budget'!S83 -> 100000 | D82: =B82-C82 -> 6090
A83: Project-wide Web Fees
A84: Timekeeping and expense reporting platform | B84: 8543 | C84: ='Project Budget'!S85 -> 8562 | D84: =B84-C84 -> -19
A85: Zoom license and platform subscriptions | B85: 1062 | C85: ='Project Budget'!S86 -> 862 | D85: =B85-C85 -> 200
A87: Subtotal Supplies and Office Expenses | B87: =SUM(B67:B85) -> 331507 | C87: =SUM(C67:C85) -> 474489 | D87: =B87-C87 -> -142982
A88: Contractual (Subawards and Contracts)
A89: Subaward to RMS | B89: 0 | C89: ='Project Budget'!S90 -> 1730498 | D89: =B89-C89 -> -1730498
A90: Subaward to CEREAL | B90: 1650433 | C90: ='Project Budget'!S91 -> 767624 | D90: =B90-C90 -> 882809
A91: Fixed Price Subaward to Transforma MyM | B91: 532300 | C91: ='Project Budget'!S92 -> 167316 | D91: =B91-C91 -> 364984
A92: Contract to Mas Proyectos | B92: 517187 | C92: ='Project Budget'!S93 -> 415299 | D92: =B92-C92 -> 101888
A93: Resource Partner: FAT | B93: 50000 | C93: ='Project Budget'!S94 -> 40000 | D93: =B93-C93 -> 10000
A94: Resource Partner: Ibero | B94: 200000 | C94: ='Project Budget'!S95 -> 30000 | D94: =B94-C94 -> 170000
A95: Resource Partner: CFO | B95: 250000 | C95: ='Project Budget'!S96 -> 65000 | D95: =B95-C95 -> 185000
A96: Resource Partner: Fondo Unido | B96: 100000 | C96: 0 | D96: =B96-C96 -> 100000
A97: Resource Partner: COPIJAL | B97: 50000 | C97: ='Project Budget'!S97 -> 25000 | D97: =B97-C97 -> 25000
A98: Resource Partner: FOTESO | B98: 0 | C98: ='Project Budget'!S98 -> 40000 | D98: =B98-C98 -> -40000
A99: Resource Partner: Incidir | B99: 50000 | C99: ='Project Budget'!S99 -> 50000 | D99: =B99-C99 -> 0
A100: Resource Partner: CIPCO | B100: 50000 | C100: ='Project Budget'!S100 -> 50000 | D100: =B100-C100 -> 0
A102: Subtotal Contractual (Subawards and Contracts) | B102: =SUM(B89:B100) -> 3449920 | C102: =SUM(C89:C100) -> 3380737 | D102: =B102-C102 -> 69183
A103: Outcome 1: Worker organizations advance issues surrounding gender equity, including gender proportionality in leadership and participation in key activities, within their institutions
A104: Activities/Costs
A105: 1.1. Conduct a diagnostic and report on gender equality and representation issues within worker organizations
A106: Meeting expenses for the development of the diagnostic | B106: 4200 | C106: 0 | D106: =B106-C106 -> 4200
A107: Participatory diagnosis on gender equality and gender representation issues within WO | B107: 0 | C107: ='Project Budget'!S106 -> 4000 | D107: =B107-C107 -> -4000
A108: Lodging and M&IE for diagnostic development | B108: 14190 | C108: ='Project Budget'!S107 -> 2200 | D108: =B108-C108 -> 11990
A109: Local transportation for diagnostic development | B109: 12900 | C109: ='Project Budget'!S108 -> 1200 | D109: =B109-C109 -> 11700
...

Sheet RMS
F1: Name of Project: DOL425 Improving Gender Equity in the Mexican Workplace
F2: Name of Subawardee: Red de Mujeres Sindicalistas (RMS)
F3: Subaward Budget
A4: Entity: | B4: P | F4: Budget Assumptions:
A5: Program-Dept.: | B5: 20200 | F5: Inflation - Locally Purchased Goods/Services | G5: 1.04
A6: Funder-Grant: | B6: DOL425 | F6: Merit Based Increases for Staff | G6: 1.035
A7: Activity Code | B7: Account Code | C7: Country Code | D7: Subcontract Code | E7: Sub-budget Code | F7: BUDGET ITEM | G7: CATEGORY | H7: UNIT | I7: # of Units | J7: RATE/ UNIT | K7: YEAR 1 2022 | L7: # of Units | M7: YEAR 2 2023 | N7: # of Units | O7: YEAR 3 2024 | P7: # of Units | Q7: YEAR 4 2025 | R7: # of Units | S7: YEAR 5 2026 | T7: TOTAL PARTNERS OF THE AMERICAS | U7: TOTAL COST SHARING | V7: PROJECT GRAND TOTAL
F8: Direct Labor
A9: SUBRMS | B9: 89050 | C9: MEX | D9: RMS | E9: RMSPERPC | F9: General Project Coordinator (50%) | G9: Salaries | H9: Month | I9: 3 | J9: =4500*0.5 -> 2250 | K9: =I9*J9 -> 6750 | L9: 12 | M9: =L9*J9*$G$6 -> 27945 | N9: 12 | O9: =N9*J9*$G$6*$G$6 -> 28923 | P9: 12 | Q9: =P9*J9*$G$6*$G$6*$G$6 -> 29935 | R9: 2 | S9: =R9*J9*$G$6*$G$6*$G$6*$G$6 -> 5164 | T9: =SUM(K9+M9+O9+Q9+S9) -> 98717 | U9: 0 | V9: =SUM(T9:U9) -> 98717
A10: SUBRMS | B10: 89050 | C10: MEX | D10: RMS | E10: RMSPERTC | F10: Training Coordinator (50%) | G10: Salaries | H10: Month | I10: 3 | J10: =4500*0.5 -> 2250 | K10: =I10*J10 -> 6750 | L10: 12 | M10: =L10*J10*$G$6 -> 27945 | N10: 12 | O10: =N10*J10*$G$6*$G$6 -> 28923 | P10: 12 | Q10: =P10*J10*$G$6*$G$6*$G$6 -> 29935 | R10: 2 | S10: =R10*J10*$G$6*$G$6*$G$6*$G$6 -> 5164 | T10: =SUM(K10+M10+O10+Q10+S10) -> 98717 | U10: 0 | V10: =SUM(T10:U10) -> 98717
A11: SUBRMS | B11: 89050 | C11: MEX | D11: RMS | E11: RMSPERAC | F11: Administration Coordinator (50%) | G11: Salaries | H11: Month | I11: 3 | J11: =4500*0.5 -> 2250 | K11: =I11*J11 -> 6750 | L11: 12 | M11: =L11*J11*$G$6 -> 27945 | N11: 12 | O11: =N11*J11*$G$6*$G$6 -> 28923 | P11: 12 | Q11: =P11*J11*$G$6*$G$6*$G$6 -> 29935 | R11: 2 | S11: =R11*J11*$G$6*$G$6*$G$6*$G$6 -> 5164 | T11: =SUM(K11+M11+O11+Q11+S11) -> 98717 | U11: 0 | V11: =SUM(T11:U11) -> 98717
A12: SUBRMS | B12: 89050 | C12: MEX | D12: RMS | E12: RMSPERCOM | F12: Communication Coordinator (50%) | G12: Salaries | H12: Month | I12: 3 | J12: =2500*0.5 -> 1250 | K12: =I12*J12 -> 3750 | L12: 12 | M12: =L12*J12*$G$6 -> 15525 | N12: 12 | O12: =N12*J12*$G$6*$G$6 -> 16068 | P12: 12 | Q12: =P12*J12*$G$6*$G$6*$G$6 -> 16631 | R12: 2 | S12: =R12*J12*$G$6*$G$6*$G$6*$G$6 -> 2869 | T12: =SUM(K12+M12+O12+Q12+S12) -> 54843 | U12: 0 | V12: =SUM(T12:U12) -> 54843
A13: SUBRMS | B13: 89050 | C13: MEX | D13: RMS | E13: RMSPERM&E | F13: Monitoring & Evaluation Coordinator (100%) | G13: Salaries | H13: Month | I13: 2 | J13: 1752 | K13: =I13*J13 -> 3504 | L13: 12 | M13: =L13*J13*$G$6 -> 21760 | N13: 12 | O13: =N13*J13*$G$6*$G$6 -> 22521 | P13: 12 | Q13: =P13*J13*$G$6*$G$6*$G$6 -> 23310 | R13: 2 | S13: =R13*J13*$G$6*$G$6*$G$6*$G$6 -> 4021 | T13: =SUM(K13+M13+O13+Q13+S13) -> 75116 | U13: 0 | V13: =SUM(T13:U13) -> 75116
A14: SUBRMS | B14: 89050 | C14: MEX | D14: RMS | E14: RMSPERIMPC | F14: Follow-up and Implementation Coordinator (100%) | G14: Salaries | H14: Month | I14: 2 | J14: 1502 | K14: =I14*J14 -> 3004 | L14: 12 | M14: =L14*J14*$G$6 -> 18655 | N14: 12 | O14: =N14*J14*$G$6*$G$6 -> 19308 | P14: 12 | Q14: =P14*J14*$G$6*$G$6*$G$6 -> 19984 | R14: 2 | S14: =R14*J14*$G$6*$G$6*$G$6*$G$6 -> 3447 | T14: =SUM(K14+M14+O14+Q14+S14) -> 64398 | U14: 0 | V14: =SUM(T14:U14) -> 64398
A15: SUBRMS | B15: 89050 | C15: MEX | D15: RMS | E15: RMSPERADM | F15: Administration Assistant (50%) | G15: Salaries | H15: Month | I15: 2 | J15: =1001*0.5 -> 501 | K15: =I15*J15 -> 1002 | L15: 12 | M15: =L15*J15*$G$6 -> 6222 | N15: 12 | O15: =N15*J15*$G$6*$G$6 -> 6440 | P15: 12 | Q15: =P15*J15*$G$6*$G$6*$G$6 -> 6666 | R15: 2 | S15: =R15*J15*$G$6*$G$6*$G$6*$G$6 -> 1150 | T15: =SUM(K15+M15+O15+Q15+S15) -> 21480 | U15: 0 | V15: =SUM(T15:U15) -> 21480
A16: SUBRMS | B16: 89050 | C16: MEX | D16: RMS | E16: RMSPERORG | F16: Organization and Logistics Lead (100%) | G16: Salaries | H16: Month | I16: 2 | J16: 1001 | K16: =I16*J16 -> 2002 | L16: 12 | M16: =L16*J16*$G$6 -> 12432 | N16: 12 | O16: =N16*J16*$G$6*$G$6 -> 12868 | P16: 12 | Q16: =P16*J16*$G$6*$G$6*$G$6 -> 13318 | R16: 2 | S16: =R16*J16*$G$6*$G$6*$G$6*$G$6 -> 2297 | T16: =SUM(K16+M16+O16+Q16+S16) -> 42917 | U16: 0 | V16: =SUM(T16:U16) -> 42917
A17: SUBRMS | B17: 89050 | C17: MEX | D17: RMS | E17: RMSPEREVN | F17: Events Assistant (100%) | G17: Salaries | H17: Month | I17: 2 | J17: 1001 | K17: =I17*J17 -> 2002 | L17: 12 | M17: =L17*J17*$G$6 -> 12432 | N17: 12 | O17: =N17*J17*$G$6*$G$6 -> 12868 | P17: 12 | Q17: =P17*J17*$G$6*$G$6*$G$6 -> 13318 | R17: 2 | S17: =R17*J17*$G$6*$G$6*$G$6*$G$6 -> 2297 | T17: =SUM(K17+M17+O17+Q17+S17) -> 42917 | U17: 0 | V17: =SUM(T17:U17) -> 42917
A18: SUBRMS | B18: 89050 | C18: MEX | D18: RMS | E18: RMSPERACCT | F18: Accountant (100%) | G18: Salaries | H18: Month | I18: 3 | J18: 1001 | K18: =I18*J18 -> 3003 | L18: 12 | M18: =L18*J18*$G$6 -> 12432 | N18: 12 | O18: =N18*J18*$G$6*$G$6 -> 12868 | P18: 12 | Q18: =P18*J18*$G$6*$G$6*$G$6 -> 13318 | R18: 2 | S18: =R18*J18*$G$6*$G$6*$G$6*$G$6 -> 2297 | T18: =SUM(K18+M18+O18+Q18+S18) -> 43918 | U18: 0 | V18: =SUM(T18:U18) -> 43918
A19: SUBRMS | B19: 89050 | C19: MEX | D19: RMS | E19: RMSPERDES | F19: Designer (50%) | G19: Salaries | H19: Month | I19: 2 | J19: =1001*0.5 -> 501 | K19: =I19*J19 -> 1002 | L19: 12 | M19: =L19*J19*$G$6 -> 6222 | N19: 12 | O19: =N19*J19*$G$6*$G$6 -> 6440 | P19: 12 | Q19: =P19*J19*$G$6*$G$6*$G$6 -> 6666 | R19: 2 | S19: =R19*J19*$G$6*$G$6*$G$6*$G$6 -> 1150 | T19: =SUM(K19+M19+O19+Q19+S19) -> 21480 | U19: 0 | V19: =SUM(T19:U19) -> 21480
A20: SUBRMS | B20: 89050 | C20: MEX | D20: RMS | E20: RMSPERSOC | F20: Social Media and Campaigns Lead (50%) | G20: Salaries | H20: Month | I20: 2 | J20: =1001*0.5 -> 501 | K20: =I20*J20 -> 1002 | L20: 12 | M20: =L20*J20*$G$6 -> 6222 | N20: 12 | O20: =N20*J20*$G$6*$G$6 -> 6440 | P20: 12 | Q20: =P20*J20*$G$6*$G$6*$G$6 -> 6666 | R20: 2 | S20: =R20*J20*$G$6*$G$6*$G$6*$G$6 -> 1150 | T20: =SUM(K20+M20+O20+Q20+S20) -> 21480 | U20: 0 | V20: =SUM(T20:U20) -> 21480
A21: SUBRMS | B21: 89050 | C21: MEX | D21: RMS | E21: RMSPERCDJ | F21: Cd. Juarez Organizer (100%) | G21: Salaries | H21: Month | I21: 2 | J21: 1001 | K21: =I21*J21 -> 2002 | L21: 12 | M21: =L21*J21*$G$6 -> 12432 | N21: 12 | O21: =N21*J21*$G$6*$G$6 -> 12868 | P21: 12 | Q21: =P21*J21*$G$6*$G$6*$G$6 -> 13318 | R21: 2 | S21: =R21*J21*$G$6*$G$6*$G$6*$G$6 -> 2297 | T21: =SUM(K21+M21+O21+Q21+S21) -> 42917 | U21: 0 | V21: =SUM(T21:U21) -> 42917
A22: SUBRMS | B22: 89050 | C22: MEX | D22: RMS | E22: RMSPERGUAD | F22: Guadalajara Organizer (100%) | G22: Salaries | H22: Month | I22: 2 | J22: 851 | K22: =I22*J22 -> 1702 | L22: 12 | M22: =L22*J22*$G$6 -> 10569 | N22: 12 | O22: =N22*J22*$G$6*$G$6 -> 10939 | P22: 12 | Q22: =P22*J22*$G$6*$G$6*$G$6 -> 11322 | R22: 2 | S22: =R22*J22*$G$6*$G$6*$G$6*$G$6 -> 1953 | T22: =SUM(K22+M22+O22+Q22+S22) -> 36485 | U22: 0 | V22: =SUM(T22:U22) -> 36485
A23: SUBRMS | B23: 89050 | C23: MEX | D23: RMS | E23: RMSPERCDMX | F23: CDMX Organizer (100%) | G23: Salaries | H23: Month | I23: 2 | J23: 851 | K23: =I23*J23 -> 1702 | L23: 12 | M23: =L23*J23*$G$6 -> 10569 | N23: 12 | O23: =N23*J23*$G$6*$G$6 -> 10939 | P23: 12 | Q23: =P23*J23*$G$6*$G$6*$G$6 -> 11322 | R23: 2 | S23: =R23*J23*$G$6*$G$6*$G$6*$G$6 -> 1953 | T23: =SUM(K23+M23+O23+Q23+S23) -> 36485 | U23: 0 | V23: =SUM(T23:U23) -> 36485
F24: Subtotal | K24: =SUM(K9:K23) -> 45927 | M24: =SUM(M9:M23) -> 229307 | O24: =SUM(O9:O23) -> 237336 | Q24: =SUM(Q9:Q23) -> 245644 | S24: =SUM(S9:S23) -> 42373 | T24: =SUM(T9:T23) -> 800587 | U24: =SUM(U9:U23) -> 0 | V24: =SUM(V9:V23) -> 800587
F26: Fringe Benefits
A27: SUBRMS | B27: 89050 | C27: MEX | D27: RMS | E27: RMSFRINGE | F27: Fringe benefits - Field Office | G27: Fringe Benefits | J27: 0.2 | K27: =K24*$J$27 -> 9185 | M27: =M24*$J$27 -> 45861 | O27: =O24*$J$27 -> 47467 | Q27: =Q24*$J$27 -> 49129 | S27: =S24*$J$27 -> 8475 | T27: =SUM(K27+M27+O27+Q27+S27) -> 160117 | U27: 0 | V27: =SUM(T27:U27) -> 160117
F29: Subtotal Direct Labor | K29: =SUM(K24:K27) -> 55112 | M29: =SUM(M24:M27) -> 275168 | O29: =SUM(O24:O27) -> 284803 | Q29: =SUM(Q24:Q27) -> 294773 | S29: =SUM(S24:S27) -> 50848 | T29: =K29+M29+O29+Q29+S29 -> 960704 | U29: =SUM(U9:U27) -> 0 | V29: =SUM(T29:U29) -> 960704
F31: Travel
F32: T1: Cd. Juarez Chihuahua / Guadalajara/ CDMX
A33: SUBRMS | B33: 89050 | C33: MEX | D33: RMS | E33: RMSAIRFARE | F33: Airfare | G33: Travel | H33: Trip | I33: 9 | J33: 300 | K33: =I33*J33 -> 2700 | L33: 32 | M33: =L33*J33 -> 9600 | N33: 60 | O33: =N33*J33 -> 18000 | P33: 36 | Q33: =P33*J33 -> 10800 | R33: 4 | S33: =R33*J33 -> 1200 | T33: =K33+M33+O33+Q33+S33 -> 42300 | U33: 0 | V33: =SUM(T33:U33) -> 42300
A34: SUBRMS | B34: 89050 | C34: MEX | D34: RMS | E34: RMSLODGING | F34: Lodging | G34: Travel | H34: Day | I34: =9+9+6+3 -> 27 | J34: 75 | K34: =I34*J34 -> 2025 | L34: =20+18+14+12 -> 64 | M34: =L34*J34 -> 4800 | N34: =36+36+36+12 -> 120 | O34: =N34*J34 -> 9000 | P34: =28+22+22 -> 72 | Q34: =P34*J34 -> 5400 | R34: 16 | S34: =R34*J34 -> 1200 | T34: =K34+M34+O34+Q34+S34 -> 22425 | U34: 0 | V34: =SUM(T34:U34) -> 22425
A35: SUBRMS | B35: 89050 | C35: MEX | D35: RMS | E35: RMSM&IE | F35: M&IE | G35: Travel | H35: Day | I35: =9+9+6+1 -> 25 | J35: 40 | K35: =I35*J35 -> 1000 | L35: =20+18+14+6 -> 58 | M35: =L35*J35 -> 2320 | N35: =36+36+36+36+6 -> 150 | O35: =N35*J35 -> 6000 | P35: =28+22+22 -> 72 | Q35: =P35*J35 -> 2880 | R35: 16 | S35: =R35*J35 -> 640 | T35: =K35+M35+O35+Q35+S35 -> 12840 | U35: 0 | V35: =SUM(T35:U35) -> 12840
A36: SUBRMS | B36: 89050 | C36: MEX | D36: RMS | E36: RMSTRANS | F36: Ground Transportation | G36: Travel | H36: Day | I36: =9+9+6+3 -> 27 | J36: 35 | K36: =I36*J36 -> 945 | L36: =20+18+14+12 -> 64 | M36: =L36*J36 -> 2240 | N36: =36+36+36+12 -> 120 | O36: =N36*J36 -> 4200 | P36: =28+22+22 -> 72 | Q36: =P36*J36 -> 2520 | R36: 16 | S36: =R36*J36 -> 560 | T36: =K36+M36+O36+Q36+S36 -> 10465 | U36: 0 | V36: =SUM(T36:U36) -> 10465
A37: SUBRMS | B37: 89050 | C37: MEX | D37: RMS | E37: RMSMSTRE | F37: Misc. Staff Travel Related Expenses | G37: Travel | H37: Day | I37: =3+9 -> 12 | J37: 25 | K37: =I37*J37 -> 300 | L37: =10+18+14 -> 42 | M37: =L37*J37 -> 1050 | N37: =18+36 -> 54 | O37: =N37*J37 -> 1350 | P37: =14+22 -> 36 | Q37: =P37*J37 -> 900 | R37: 5 | S37: =R37*J37 -> 125 | T37: =K37+M37+O37+Q37+S37 -> 3725 | U37: 0 | V37: =SUM(T37:U37) -> 3725
F39: Subtotal Travel | K39: =SUM(K33:K37) -> 6970 | M39: =SUM(M33:M37) -> 20010 | O39: =SUM(O33:O37) -> 38550 | Q39: =SUM(Q33:Q37) -> 22500 | S39: =SUM(S33:S37) -> 3725 | T39: =K39+M39+O39+Q39+S39 -> 91755 | U39: =SUM(U33:U37) -> 0 | V39: =SUM(T39:U39) -> 91755
F40: Supplies - Under $5,000 USD
A41: SUBRMS | B41: 89050 | C41: MEX | D41: RMS | E41: RMSDESKTOP | F41: Desktop computers, laptops and software | G41: Supplies | H41: Unit | I41: 5 | J41: 751 | K41: =I41*J41 -> 3755 | L41: 5 | M41: =L41*J41 -> 3755 | N41: 0 | O41: =N41*J41 -> 0 | P41: 0 | Q41: =P41*J41 -> 0 | R41: 0 | S41: =R41*J41 -> 0 | T41: =K41+M41+O41+Q41+S41 -> 7510 | U41: 0 | V41: =SUM(T41:U41) -> 7510
A42: SUBRMS | B42: 89050 | C42: MEX | D42: RMS | E42: RMSMEET | F42: Meeting Expenses | G42: Supplies | H42: Unit | I42: 1 | J42: 100 | K42: =I42*J42 -> 100 | L42: 12 | M42: =L42*J42 -> 1200 | N42: 12 | O42: =N42*J42 -> 1200 | P42: 12 | Q42: =P42*J42 -> 1200 | R42: 3 | S42: =R42*J42 -> 300 | T42: =K42+M42+O42+Q42+S42 -> 4000 | U42: 0 | V42: =SUM(T42:U42) -> 4000
A43: SUBRMS | B43: 89050 | C43: MEX | D43: RMS | E43: RMSPHONE | F43: Phones | G43: Supplies | H43: Unit | I43: 7 | J43: 300 | K43: =I43*J43 -> 2100 | L43: 0 | M43: =L43*J43 -> 0 | N43: 2 | O43: =N43*J43 -> 600 | P43: 0 | Q43: =P43*J43 -> 0 | R43: 0 | S43: =R43*J43 -> 0 | T43: =K43+M43+O43+Q43+S43 -> 2700 | U43: 0 | V43: =SUM(T43:U43) -> 2700
A44: SUBRMS | B44: 89050 | C44: MEX | D44: RMS | E44: RMSSUPPLY | F44: Office Supplies | G44: Supplies | H44: Month | I44: 1 | J44: 75 | K44: =I44*J44 -> 75 | L44: 12 | M44: =L44*J44 -> 900 | N44: 12 | O44: =N44*J44 -> 900 | P44: 12 | Q44: =P44*J44 -> 900 | R44: 1 | S44: =R44*J44 -> 75 | T44: =K44+M44+O44+Q44+S44 -> 2850 | U44: 0 | V44: =SUM(T44:U44) -> 2850
A45: SUBRMS | B45: 89050 | C45: MEX | D45: RMS | E45: RMSMATLS | F45: Stationary/Printing Materials | G45: Supplies | H45: Unit | I45: 1 | J45: 100 | K45: =I45*J45 -> 100 | L45: 4 | M45: =L45*J45 -> 400 | N45: 4 | O45: =N45*J45 -> 400 | P45: 4 | Q45: =P45*J45 -> 400 | R45: 1 | S45: =R45*J45 -> 100 | T45: =K45+M45+O45+Q45+S45 -> 1400 | U45: 0 | V45: =SUM(T45:U45) -> 1400
A46: SUBRMS | B46: 89050 | C46: MEX | D46: RMS | E46: RMSCAMAE | F46: Camera and audio equipment | G46: Supplies | H46: Unit | I46: 1 | J46: 1252 | K46: =I46*J46 -> 1252 | L46: 1 | M46: =L46*J46 -> 1252 | N46: 0 | O46: =N46*J46 -> 0 | P46: 0 | Q46: =P46*J46 -> 0 | R46: 0 | S46: =R46*J46 -> 0 | T46: =K46+M46+O46+Q46+S46 -> 2504 | U46: 0 | V46: =SUM(T46:U46) -> 2504
F48: Subtotal Supplies | K48: =SUM(K41:K46) -> 7382 | M48: =SUM(M41:M46) -> 7507 | O48: =SUM(O41:O46) -> 3100 | Q48: =SUM(Q41:Q46) -> 2500 | S48: =SUM(S41:S46) -> 475 | T48: =K48+M48+O48+Q48+S48 -> 20964 | U48: =SUM(U41:U46) -> 0 | V48: =SUM(T48:U48) -> 20964
F49: Office Expenses
A50: SUBRMS | B50: 89050 | C50: MEX | D50: RMS | E50: RMSBANK | F50: Banking and cash handling fees | G50: Office Expenses | H50: Month | I50: 3 | J50: 50 | K50: =I50*J50 -> 150 | L50: 12 | M50: =L50*J50 -> 600 | N50: 12 | O50: =N50*J50 -> 600 | P50: 12 | Q50: =P50*J50 -> 600 | R50: 2 | S50: =R50*J50 -> 100 | T50: =K50+M50+O50+Q50+S50 -> 2050 | U50: 0 | V50: =SUM(T50:U50) -> 2050
A51: SUBRMS | B51: 89050 | C51: MEX | D51: RMS | E51: RMSPOSTAGE | F51: Courier fees/services/postage | G51: Office Expenses | H51: Month | I51: 1 | J51: 35 | K51: =I51*J51 -> 35 | L51: 5 | M51: =L51*J51 -> 175 | N51: 5 | O51: =N51*J51 -> 175 | P51: 5 | Q51: =P51*J51 -> 175 | R51: 2 | S51: =R51*J51 -> 70 | T51: =K51+M51+O51+Q51+S51 -> 630 | U51: 0 | V51: =SUM(T51:U51) -> 630
A52: SUBRMS | B52: 89050 | C52: MEX | D52: RMS | E52: RMSINTEMA | F52: Email/Internet | G52: Office Expenses | H52: Month | I52: 3 | J52: 50 | K52: =I52*J52 -> 150 | L52: 12 | M52: =L52*J52 -> 600 | N52: 12 | O52: =N52*J52 -> 600 | P52: 12 | Q52: =P52*J52 -> 600 | R52: 2 | S52: =R52*J52 -> 100 | T52: =K52+M52+O52+Q52+S52 -> 2050 | U52: 0 | V52: =SUM(T52:U52) -> 2050
A53: SUBRMS | B53: 89050 | C53: MEX | D53: RMS | E53: RMSPHONE | F53: Phones line rent | G53: Office Expenses | H53: Month | I53: 2 | J53: =30*7 -> 210 | K53: =I53*J53 -> 420 | L53: 12 | M53: =L53*J53 -> 2520 | N53: 12 | O53: =N53*J53 -> 2520 | P53: 12 | Q53: =P53*J53 -> 2520 | R53: 2 | S53: =R53*J53 -> 420 | T53: =K53+M53+O53+Q53+S53 -> 8400 | U53: 0 | V53: =SUM(T53:U53) -> 8400
A54: SUBRMS | B54: 89050 | C54: MEX | D54: RMS | E54: RMSRENT | F54: Office Rent | G54: Office Expenses | H54: Month | I54: 2 | J54: 1250 | K54: =I54*J54 -> 2500 | L54: 12 | M54: =L54*J54 -> 15000 | N54: 12 | O54: =N54*J54 -> 15000 | P54: 12 | Q54: =P54*J54 -> 15000 | R54: 2 | S54: =R54*J54 -> 2500 | T54: =K54+M54+O54+Q54+S54 -> 50000 | U54: 0 | V54: =SUM(T54:U54) -> 50000
A55: SUBRMS | B55: 89050 | C55: MEX | D55: RMS | E55: RMSEQUMAN | F55: Equipment and office repairs and maintenance | G55: Office Expenses | H55: Month | I55: 0 | J55: 100 | K55: =I55*J55 -> 0 | L55: 4 | M55: =L55*J55 -> 400 | N55: 4 | O55: =N55*J55 -> 400 | P55: 4 | Q55: =P55*J55 -> 400 | R55: 1 | S55: =R55*J55 -> 100 | T55: =K55+M55+O55+Q55+S55 -> 1300 | U55: 0 | V55: =SUM(T55:U55) -> 1300
F57: Subtotal Office Expenses | K57: =SUM(K50:K55) -> 3255 | M57: =SUM(M50:M55) -> 19295 | O57: =SUM(O50:O55) -> 19295 | Q57: =SUM(Q50:Q55) -> 19295 | S57: =SUM(S50:S55) -> 3290 | T57: =K57+M57+O57+Q57+S57 -> 64430 | U57: =SUM(U50:U55) -> 0 | V57: =SUM(T57:U57) -> 64430
F58: The above is only for percentage calculations for the below outcomes
F60: Outcome 1: WO advance issues surrounding substantive equality, including gender proportionality in leadership and participation in key activities, within their institutions
F61: Activities/Costs
F62: Personnel & Fringe (60% of Direct Labor line item) | G62: Outcome1 | H62: Unit | I62: =$K$29 -> 55112 | J62: 0.6 | K62: =I62*J62 -> 33067 | L62: =$M$29 -> 275168 | M62: =L62*J62 -> 165101 | N62: =$O$29 -> 284803 | O62: =N62*J62 -> 170882 | P62: =$Q$29 -> 294773 | Q62: =P62*J62 -> 176864 | R62: =$S$29 -> 50848 | S62: =R62*J62 -> 30509 | T62: =K62+M62+O62+Q62+S62 -> 576423 | U62: 0 | V62: =SUM(T62:U62) -> 576423
F63: Travel (60%) | G63: Outcome1 | H63: Unit | I63: =$K$39 -> 6970 | J63: 0.6 | K63: =I63*J63 -> 4182 | L63: =$M$39 -> 20010 | M63: =L63*J63 -> 12006 | N63: =$O$39 -> 38550 | O63: =N63*J63 -> 23130 | P63: =$Q$39 -> 22500 | Q63: =P63*J63 -> 13500 | R63: =$S$39 -> 3725 | S63: =R63*J63 -> 2235 | T63: =K63+M63+O63+Q63+S63 -> 55053 | U63: 0 | V63: =SUM(T63:U63) -> 55053
F64: Supplies (60%) | G64: Outcome1 | H64: Unit | I64: =$K$48 -> 7382 | J64: 0.6 | K64: =I64*J64 -> 4429 | L64: =$M$48 -> 7507 | M64: =L64*J64 -> 4504 | N64: =$O$48 -> 3100 | O64: =N64*J64 -> 1860 | P64: =$Q$48 -> 2500 | Q64: =P64*J64 -> 1500 | R64: =$S$48 -> 475 | S64: =R64*J64 -> 285 | T64: =K64+M64+O64+Q64+S64 -> 12578 | U64: 0 | V64: =SUM(T64:U64) -> 12578
F65: Office Expenses (60%) | G65: Outcome1 | H65: Unit | I65: =$K$57 -> 3255 | J65: 0.6 | K65: =I65*J65 -> 1953 | L65: =$M$57 -> 19295 | M65: =L65*J65 -> 11577 | N65: =$O$57 -> 19295 | O65: =N65*J65 -> 11577 | P65: =$Q$57 -> 19295 | Q65: =P65*J65 -> 11577 | R65: =$S$57 -> 3290 | S65: =R65*J65 -> 1974 | T65: =K65+M65+O65+Q65+S65 -> 38658 | U65: 0 | V65: =SUM(T65:U65) -> 38658
F66: 1: Conduct a participatory diagnosis on gender equality and representation issues within WO | G66: Outcome1 | H66: Unit
A67: SUBRMS | B67: 89050 | C67: MEX | D67: RMS | E67: RMSOUT1-1 | F67: Participatory diagnosis on gender equality and gender representation issues within WO | G67: Outcome1 | H67: Unit | I67: 0 | J67: 23337 | K67: =I67*J67 -> 0 | L67: 1 | M67: =L67*J67 -> 23337 | N67: 0 | O67: =J67*N67 -> 0 | P67: 0 | Q67: =J67*P67 -> 0 | R67: 0 | S67: =J67*R67 -> 0 | T67: =K67+M67+O67+Q67+S67 -> 23337 | U67: 0 | V67: =SUM(T67:U67) -> 23337
F68: 2: Identify and train young women workers in leadership, negotiation, and conflict resolution
A69: SUBRMS | B69: 89050 | C69: MEX | D69: RMS | E69: RMSOUT1-2 | F69: Training of young women workers in leadership, negotiation and conflict resolution. | G69: Outcome1 | H69: Unit | I69: 0 | J69: 36354 | K69: =I69*J69 -> 0 | L69: 0 | M69: =L69*J69 -> 0 | N69: 1 | O69: =J69*N69 -> 36354 | P69: 1 | Q69: =J69*P69 -> 36354 | R69: 0 | S69: =J69*R69 -> 0 | T69: =K69+M69+O69+Q69+S69 -> 72708 | U69: 0 | V69: =SUM(T69:U69) -> 72708
F70: Activity 3. Train female leaders in WO on collective negotiation and issues of substantive equality.
A71: SUBRMS | B71: 89050 | C71: MEX | D71: RMS | E71: RMSOUT1-3 | F71: Training for OPT leaders for collective bargaining on issues of substantive equality. | G71: Outcome1 | H71: Unit | I71: 0 | J71: =80058/3 -> 26686 | K71: =I71*J71 -> 0 | L71: 0 | M71: =L71*J71 -> 0 | N71: 1 | O71: =J71*N71 -> 26686 | P71: 1 | Q71: =J71*P71 -> 26686 | R71: 1 | S71: =J71*R71 -> 26686 | T71: =K71+M71+O71+Q71+S71 -> 80058 | V71: =SUM(T71:U71) -> 80058
F72: 6: Develop protocols focused on eliminating violence and harassment within WO membership
A73: SUBRMS | B73: 89050 | C73: MEX | D73: RMS | E73: RMSOUT1-6 | F73: Protocols focused on eliminating violence and harassment among WO members | G73: Outcome1 | H73: Unit | I73: 0 | J73: 43614 | K73: =I73*J73 -> 0 | L73: 1 | M73: =L73*J73 -> 43614 | N73: 0 | O73: =J73*N73 -> 0 | P73: 0 | Q73: =J73*P73 -> 0 | R73: 0 | S73: =J73*R73 -> 0 | T73: =K73+M73+O73+Q73+S73 -> 43614 | U73: 0 | V73: =SUM(T73:U73) -> 43614
F74: 7: Develop a toolkit for WO to support the integration of the gender perspective and the increase of women members
A75: SUBRMS | B75: 89050 | C75: MEX | D75: RMS | E75: RMSOUT1-7 | F75: Toolkit for substantive equality and the unionization of women | G75: Outcome1 | H75: Unit | I75: 0 | J75: 25170 | K75: =I75*J75 -> 0 | L75: 1 | M75: =L75*J75 -> 25170 | N75: 0 | O75: =J75*N75 -> 0 | P75: 0 | Q75: =J75*P75 -> 0 | R75: 0 | S75: =J75*R75 -> 0 | T75: =K75+M75+O75+Q75+S75 -> 25170 | U75: 0 | V75: =SUM(T75:U75) -> 25170
F77: Direct Costs Total for Outcome 1 | K77: =SUM(K62:K75) -> 43631 | M77: =SUM(M62:M75) -> 285309 | O77: =SUM(O62:O75) -> 270489 | Q77: =SUM(Q62:Q75) -> 266481 | S77: =SUM(S62:S75) -> 61689 | T77: =K77+M77+O77+Q77+S77 -> 927599 | U77: =SUM(U62:U69) -> 0 | V77: =SUM(T77:U77) -> 927599
A79: SUBRMS | B79: 89050 | C79: MEX | D79: RMS | E79: RMSIDCCOST | F79: Total Indirect Costs (NICRA or De Minimis) for Outcome 1 | G79: Indirect Charges | J79: 0.1 | K79: =(K77)*J79 -> 4363 | M79: =(M77)*J79 -> 28531 | O79: =(O77)*J79 -> 27049 | Q79: =(Q77)*J79 -> 26648 | S79: =(S77)*J79 -> 6169 | T79: =SUM(K79+M79+O79+Q79+S79) -> 92760 | U79: 0 | V79: =SUM(T79:U79) -> 92760
F81: Subtotal Outcome 1 | K81: =SUM(K77:K79) -> 47994 | M81: =SUM(M77:M79) -> 313840 | O81: =SUM(O77:O79) -> 297538 | Q81: =SUM(Q77:Q79) -> 293129 | S81: =SUM(S77:S79) -> 67858 | T81: =K81+M81+O81+Q81+S81 -> 1020359 | U81: =SUM(U77:U80) -> 0 | V81: =SUM(T81:U81) -> 1020359
F82: Outcome 2: Worker organizations undertake sustained action to promote gender equity in the workplace.
F83: Activities/Costs
F84: Personnel & Fringe (45% of Direct Labor line item) | G84: Outcome2 | H84: Unit | I84: =$K$29 -> 55112 | J84: 0.35 | K84: =I84*J84 -> 19289 | L84: =$M$29 -> 275168 | M84: =L84*J84 -> 96309 | N84: =$O$29 -> 284803 | O84: =N84*J84 -> 99681 | P84: =$Q$29 -> 294773 | Q84: =P84*J84 -> 103171 | R84: =$S$29 -> 50848 | S84: =R84*J84 -> 17797 | T84: =K84+M84+O84+Q84+S84 -> 336247 | U84: 0 | V84: =SUM(T84:U84) -> 336247
F85: Travel (45%) | G85: Outcome2 | H85: Unit | I85: =$K$39 -> 6970 | J85: 0.35 | K85: =I85*J85 -> 2440 | L85: =$M$39 -> 20010 | M85: =L85*J85 -> 7004 | N85: =$O$39 -> 38550 | O85: =N85*J85 -> 13493 | P85: =$Q$39 -> 22500 | Q85: =P85*J85 -> 7875 | R85: =$S$39 -> 3725 | S85: =R85*J85 -> 1304 | T85: =K85+M85+O85+Q85+S85 -> 32116 | U85: 0 | V85: =SUM(T85:U85) -> 32116
F86: Supplies (45%) | G86: Outcome2 | H86: Unit | I86: =$K$48 -> 7382 | J86: 0.35 | K86: =I86*J86 -> 2584 | L86: =$M$48 -> 7507 | M86: =L86*J86 -> 2627 | N86: =$O$48 -> 3100 | O86: =N86*J86 -> 1085 | P86: =$Q$48 -> 2500 | Q86: =P86*J86 -> 875 | R86: =$S$48 -> 475 | S86: =R86*J86 -> 166 | T86: =K86+M86+O86+Q86+S86 -> 7337 | U86: 0 | V86: =SUM(T86:U86) -> 7337
F87: Office Expenses (45%) | G87: Outcome2 | H87: Unit | I87: =$K$57 -> 3255 | J87: 0.35 | K87: =I87*J87 -> 1139 | L87: =$M$57 -> 19295 | M87: =L87*J87 -> 6753 | N87: =$O$57 -> 19295 | O87: =N87*J87 -> 6753 | P87: =$Q$57 -> 19295 | Q87: =P87*J87 -> 6753 | R87: =$S$57 -> 3290 | S87: =R87*J87 -> 1152 | T87: =K87+M87+O87+Q87+S87 -> 22550 | U87: 0 | V87: =SUM(T87:U87) -> 22550
F88: 15: Train workers and WO on effective methods for gathering evidence and reporting discrimination and GBVH in the workplace
A89: SUBRMS | B89: 89050 | C89: MEX | D89: RMS | E89: RMSOUT2-15 | F89: Specialized training for the presentation of cases of discrimination and GBVH aimed at workers and WO | G89: Outcome2 | H89: Unit | I89: 0 | J89: 62890 | K89: =I89*J89 -> 0 | L89: 0 | M89: =L89*J89 -> 0 | N89: 1 | O89: =N89*J89 -> 62890 | P89: 0 | Q89: =P89*J89 -> 0 | R89: 0 | S89: =R89*J89 -> 0 | T89: =K89+M89+O89+Q89+S89 -> 62890 | U89: 0 | V89: =SUM(T89:U89) -> 62890
F90: 16: Provide legal support to workers in cases related to gender discrimination, wage violations, failure to pay social protection systems, harassment or violence, and other relevant labor violations
A91: SUBRMS | B91: 89050 | C91: MEX | D91: RMS | E91: RMSOUT2116 | F91: Network of Lawyers for the Defense of Workers | G91: Outcome2 | H91: Unit | I91: 1 | J91: 1000 | K91: =I91*J91 -> 1000 | L91: 1 | M91: =L91*J91 -> 1000 | N91: 1 | O91: =N91*J91 -> 1000 | P91: 0 | Q91: =P91*J91 -> 0 | R91: 0 | S91: =R91*J91 -> 0 | T91: =K91+M91+O91+Q91+S91 -> 3000 | U91: 0 | V91: =SUM(T91:U91) -> 3000
A92: SUBRMS | B92: 89050 | C92: MEX | D92: RMS | E92: RMSOUT2216 | F92: Consultants for training workers to gathering evidence | G92: Outcome2 | H92: Month | I92: 4 | J92: 2000 | K92: =I92*J92 -> 8000 | L92: 24 | M92: =L92*J92 -> 48000 | N92: 0 | O92: =N92*J92 -> 0 | P92: 0 | Q92: =P92*J92 -> 0 | R92: 0 | S92: =R92*J92 -> 0 | T92: =K92+M92+O92+Q92+S92 -> 56000 | U92: 0 | V92: =SUM(T92:U92) -> 56000
A93: SUBRMS | B93: 89050 | C93: MEX | D93: RMS | E93: RMSOUT2316 | F93: Legal Advice delivered to workers in cases of gender discrimination in the workplace and associated labor violations. | G93: Outcome2 | H93: Workshop | J93: 20862 | K93: =I93*J93 -> 0 | L93: 3 | M93: =L93*J93 -> 62586 | N93: 0 | O93: =N93*J93 -> 0 | P93: 0 | Q93: =P93*J93 -> 0 | R93: 0 | S93: =R93*J93 -> 0 | T93: =K93+M93+O93+Q93+S93 -> 62586 | U93: 0 | V93: =SUM(T93:U93) -> 62586
F94: Direct Costs Total for Outcome 2 | K94: =SUM(K84:K93) -> 34452 | M94: =SUM(M84:M93) -> 224279 | O94: =SUM(O84:O93) -> 184902 | Q94: =SUM(Q84:Q93) -> 118674 | S94: =SUM(S84:S93) -> 20419 | T94: =SUM(T84:T93) -> 582726 | U94: =SUM(U84:U93) -> 0 | V94: =SUM(T94:U94) -> 582726
A96: SUBRMS | B96: 89050 | C96: MEX | D96: RMS | E96: RMSIDCCOST | F96: Total Indirect Costs (NICRA or De Minimis) for Outcome 2 | G96: Indirect Charges | J96: 0.1 | K96: =(K94)*J96 -> 3445 | M96: =(M94)*J96 -> 22428 | O96: =(O94)*J96 -> 18490 | Q96: =(Q94)*J96 -> 11867 | S96: =(S94)*J96 -> 2042 | T96: =SUM(K96+M96+O96+Q96+S96) -> 58272 | U96: 0 | V96: =SUM(T96:U96) -> 58272
F98: Subtotal Outcome 2 | K98: =SUM(K94:K96) -> 37897 | M98: =SUM(M94:M96) -> 246707 | O98: =SUM(O94:O96) -> 203392 | Q98: =SUM(Q94:Q96) -> 130541 | S98: =SUM(S94:S96) -> 22461 | T98: =K98+M98+O98+Q98+S98 -> 640998 | U98: =SUM(U89:U93) -> 0 | V98: =SUM(T98:U98) -> 640998
F99: Monitoring, Evaluation, and Collection of Reliable Data
F100: Activities/Costs
F101: Personnel & Fringe (5% of Direct Labor line item) | G101: M&E | H101: Unit | I101: =K29 -> 55112 | J101: 0.05 | K101: =I101*J101 -> 2756 | L101: =$M$29 -> 275168 | M101: =L101*J101 -> 13758 | N101: =$O$29 -> 284803 | O101: =N101*J101 -> 14240 | P101: =$Q$29 -> 294773 | Q101: =P101*J101 -> 14739 | R101: =$S$29 -> 50848 | S101: =R101*J101 -> 2542 | T101: =K101+M101+O101+Q101+S101 -> 48035 | U101: 0 | V101: =SUM(T101:U101) -> 48035
F102: Travel (5%) | G102: M&E | H102: Unit | I102: =$K$39 -> 6970 | J102: 0.05 | K102: =I102*J102 -> 349 | L102: =$M$39 -> 20010 | M102: =L102*J102 -> 1001 | N102: =$O$39 -> 38550 | O102: =N102*J102 -> 1928 | P102: =$Q$39 -> 22500 | Q102: =P102*J102 -> 1125 | R102: =$S$39 -> 3725 | S102: =R102*J102 -> 186 | T102: =K102+M102+O102+Q102+S102 -> 4589 | U102: 0 | V102: =SUM(T102:U102) -> 4589
F103: Supplies (5%) | G103: M&E | H103: Unit | I103: =$K$48 -> 7382 | J103: 0.05 | K103: =I103*J103 -> 369 | L103: =$M$48 -> 7507 | M103: =L103*J103 -> 375 | N103: =$O$48 -> 3100 | O103: =N103*J103 -> 155 | P103: =$Q$48 -> 2500 | Q103: =P103*J103 -> 125 | R103: =$S$48 -> 475 | S103: =R103*J103 -> 24 | T103: =K103+M103+O103+Q103+S103 -> 1048 | U103: 0 | V103: =SUM(T103:U103) -> 1048
F104: Office Expenses (5%) | G104: M&E | H104: Unit | I104: =$K$57 -> 3255 | J104: 0.05 | K104: =I104*J104 -> 163 | L104: =$M$57 -> 19295 | M104: =L104*J104 -> 965 | N104: =$O$57 -> 19295 | O104: =N104*J104 -> 965 | P104: =$Q$57 -> 19295 | Q104: =P104*J104 -> 965 | R104: =$S$57 -> 3290 | S104: =R104*J104 -> 165 | T104: =K104+M104+O104+Q104+S104 -> 3223 | U104: 0 | V104: =SUM(T104:U104) -> 3223
A105: SUBRMS | B105: 89050 | C105: MEX | D105: RMS | E105: RMSLDPRM&E | F105: Lodging and M&IE - Field verification and data collection visits | G105: M&E | H105: Days | I105: 4 | J105: 110 | K105: =I105*J105 -> 440 | L105: 6 | M105: =L105*J105 -> 660 | N105: 6 | O105: =N105*J105 -> 660 | P105: 6 | Q105: =P105*J105 -> 660 | R105: 4 | S105: =R105*J105 -> 440 | T105: =K105+M105+O105+Q105+S105 -> 2860 | U105: 0 | V105: =SUM(T105:U105) -> 2860
A106: SUBRMS | B106: 89050 | C106: MEX | D106: RMS | E106: RMSTRANM&E | F106: Local transportation - Field verification and data collection visits | G106: M&E | H106: Days | I106: 4 | J106: 100 | K106: =I106*J106 -> 400 | L106: 6 | M106: =L106*J106 -> 600 | N106: 6 | O106: =N106*J106 -> 600 | P106: 6 | Q106: =P106*J106 -> 600 | R106: 4 | S106: =R106*J106 -> 400 | T106: =K106+M106+O106+Q106+S106 -> 2600 | U106: 0 | V106: =SUM(T106:U106) -> 2600
A107: SUBRMS | B107: 89050 | C107: MEX | D107: RMS | E107: RMSDATAM&E | F107: Data collection materials and printing | G107: M&E | H107: Unit | I107: 1 | J107: 100 | K107: =I107*J107 -> 100 | L107: 1 | M107: =L107*J107 -> 100 | N107: 1 | O107: =N107*J107 -> 100 | P107: 1 | Q107: =P107*J107 -> 100 | R107: 1 | S107: =R107*J107 -> 100 | T107: =K107+M107+O107+Q107+S107 -> 500 | U107: 0 | V107: =SUM(T107:U107) -> 500
F109: Direct Costs Total for Monitoring, Evaluation, and Collection of Reliable Data | K109: =SUM(K101:K107) -> 4577 | M109: =SUM(M101:M107) -> 17459 | O109: =SUM(O101:O107) -> 18648 | Q109: =SUM(Q101:Q107) -> 18314 | S109: =SUM(S101:S107) -> 3857 | T109: =K109+M109+O109+Q109+S109 -> 62855 | U109: =SUM(U101:U107) -> 0 | V109: =SUM(T109:U109) -> 62855
A111: SUBRMS | B111: 89050 | C111: MEX | D111: RMS | E111: RMSIDCCOST | F111: Total Indirect Costs (NICRA or De Minimis) for M&E and Collection of Reliable Data | G111: Indirect Charges | J111: 0.1 | K111: =(K109)*J111 -> 458 | M111: =(M109)*J111 -> 1746 | O111: =(O109)*J111 -> 1865 | Q111: =(Q109)*J111 -> 1831 | S111: =(S109)*J111 -> 386 | T111: =SUM(K111+M111+O111+Q111+S111) -> 6286 | U111: 0 | V111: =SUM(T111:U111) -> 6286
F113: Subtotal Monitoring, Evaluation, and Collection of Reliable Data | K113: =SUM(K109:K111) -> 5035 | M113: =SUM(M109:M111) -> 19205 | O113: =SUM(O109:O111) -> 20513 | Q113: =SUM(Q109:Q111) -> 20145 | S113: =SUM(S109:S111) -> 4243 | T113: =K113+M113+O113+Q113+S113 -> 69141 | U113: =SUM(U109:U111) -> 0 | V113: =SUM(T113:U113) -> 69141
F115: TOTAL COSTS | K115: =K113+K98+K81 -> 90926 | M115: =M113+M98+M81 -> 579752 | O115: =O113+O98+O81 -> 521443 | Q115: =Q113+Q98+Q81 -> 443815 | S115: =S113+S98+S81 -> 94562 | T115: =S115+Q115+O115+M115+K115 -> 1730498 | U115: =U113+U98+U81 -> 0 | V115: =SUM(T115:U115) -> 1730498

Sheet CEREAL
F1: Name of Project: Improving Gender Equity in the Mexican Workplace
F2: Name of Subawardee: Center for Reflection and Action on Labor Rights (CEREAL)
F3: Subaward Budget
A4: Entity: | B4: P | F4: Budget Assumptions:
A5: Program-Dept.: | B5: 20200 | F5: Inflation - Locally Purchased Goods/Services | G5: 1.04
A6: Funder-Grant: | B6: DOL425 | F6: Merit Based Increases for Staff | G6: 1.035
A7: Activity Code | B7: Account Code | C7: Country Code | D7: Subcontract Code | E7: Sub-budget Code | F7: BUDGET ITEM | G7: CATEGORY | H7: UNIT | I7: # of Units | J7: RATE/ UNIT | K7: YEAR 1 2022 | L7: # of Units | M7: YEAR 2 2023 | N7: # of Units | O7: YEAR 3 2024 | P7: # of Units | Q7: YEAR 4 2025 | R7: # of Units | S7: YEAR 5 2026 | T7: TOTAL CEREAL | U7: TOTAL COST SHARING | V7: PROJECT GRAND TOTAL
F8: Direct Labor
A9: SUBCEREAL | B9: 89050 | C9: MEX | D9: CEREAL | E9: CERPERPC | F9: Project Coordinator 50% | G9: Salaries | H9: Month | I9: 3 | J9: 1586 | K9: =I9*J9 -> 4758 | L9: 12 | M9: =L9*J9*$G$6 -> 19698 | N9: 12 | O9: =N9*J9*$G$6*$G$6 -> 20388 | P9: 12 | Q9: =P9*J9*$G$6*$G$6*$G$6 -> 21101 | R9: 2 | S9: =R9*J9*$G$6*$G$6*$G$6*$G$6 -> 3640 | T9: =SUM(K9+M9+O9+Q9+S9) -> 69585 | U9: 0 | V9: =SUM(T9:U9) -> 69585
A10: SUBCEREAL | B10: 89050 | C10: MEX | D10: CEREAL | E10: CERPERADM | F10: Administration 50% | G10: Salaries | H10: Month | I10: 3 | J10: 1458 | K10: =I10*J10 -> 4374 | L10: 12 | M10: =L10*J10*$G$6 -> 18108 | N10: 12 | O10: =N10*J10*$G$6*$G$6 -> 18742 | P10: 12 | Q10: =P10*J10*$G$6*$G$6*$G$6 -> 19398 | R10: 2 | S10: =R10*J10*$G$6*$G$6*$G$6*$G$6 -> 3346 | T10: =SUM(K10+M10+O10+Q10+S10) -> 63968 | U10: 0 | V10: =SUM(T10:U10) -> 63968
A11: SUBCEREAL | B11: 89050 | C11: MEX | D11: CEREAL | E11: CERPERIDV | F11: Institutional Development 50% | G11: Salaries | H11: Month | I11: 3 | J11: 1458 | K11: =I11*J11 -> 4374 | L11: 12 | M11: =L11*J11*$G$6 -> 18108 | N11: 12 | O11: =N11*J11*$G$6*$G$6 -> 18742 | P11: 12 | Q11: =P11*J11*$G$6*$G$6*$G$6 -> 19398 | R11: 2 | S11: =R11*J11*$G$6*$G$6*$G$6*$G$6 -> 3346 | T11: =SUM(K11+M11+O11+Q11+S11) -> 63968 | U11: 0 | V11: =SUM(T11:U11) -> 63968
A12: SUBCEREAL | B12: 89050 | C12: MEX | D12: CEREAL | E12: CERPERLEG | F12: Legal Coordinator 50% | G12: Salaries | H12: Month | I12: 3 | J12: 1458 | K12: =I12*J12 -> 4374 | L12: 12 | M12: =L12*J12*$G$6 -> 18108 | N12: 12 | O12: =N12*J12*$G$6*$G$6 -> 18742 | P12: 12 | Q12: =P12*J12*$G$6*$G$6*$G$6 -> 19398 | R12: 2 | S12: =R12*J12*$G$6*$G$6*$G$6*$G$6 -> 3346 | T12: =SUM(K12+M12+O12+Q12+S12) -> 63968 | U12: 0 | V12: =SUM(T12:U12) -> 63968
A13: SUBCEREAL | B13: 89050 | C13: MEX | D13: CEREAL | E13: CERPEROPC | F13: Organizational Processes Coordinator 50% | G13: Salaries | H13: Month | I13: 3 | J13: 1458 | K13: =I13*J13 -> 4374 | L13: 12 | M13: =L13*J13*$G$6 -> 18108 | N13: 12 | O13: =N13*J13*$G$6*$G$6 -> 18742 | P13: 12 | Q13: =P13*J13*$G$6*$G$6*$G$6 -> 19398 | R13: 2 | S13: =R13*J13*$G$6*$G$6*$G$6*$G$6 -> 3346 | T13: =SUM(K13+M13+O13+Q13+S13) -> 63968 | U13: 0 | V13: =SUM(T13:U13) -> 63968
A14: SUBCEREAL | B14: 89050 | C14: MEX | D14: CEREAL | E14: CERPEREDU | F14: Education Coordinator 50% | G14: Salaries | H14: Month | I14: 3 | J14: 1458 | K14: =I14*J14 -> 4374 | L14: 12 | M14: =L14*J14*$G$6 -> 18108 | N14: 12 | O14: =N14*J14*$G$6*$G$6 -> 18742 | P14: 12 | Q14: =P14*J14*$G$6*$G$6*$G$6 -> 19398 | S14: =R14*J14*$G$6*$G$6*$G$6*$G$6 -> 0 | T14: =SUM(K14+M14+O14+Q14+S14) -> 60622 | U14: 0 | V14: =SUM(T14:U14) -> 60622
A15: SUBCEREAL | B15: 89050 | C15: MEX | D15: CEREAL | E15: CERPERPRO | F15: Promotor 1 50% | G15: Salaries | H15: Month | I15: 2 | J15: 125 | K15: =I15*J15 -> 250 | L15: 12 | M15: =L15*J15*$G$6 -> 1553 | N15: 12 | O15: =N15*J15*$G$6*$G$6 -> 1607 | P15: 12 | Q15: =P15*J15*$G$6*$G$6*$G$6 -> 1663 | S15: =R15*J15*$G$6*$G$6*$G$6*$G$6 -> 0 | T15: =SUM(K15+M15+O15+Q15+S15) -> 5073 | U15: 0 | V15: =SUM(T15:U15) -> 5073
A16: SUBCEREAL | B16: 89050 | C16: MEX | D16: CEREAL | E16: CERPERPRO | F16: Promotor 2 50% | G16: Salaries | H16: Month | I16: 2 | J16: 125 | K16: =I16*J16 -> 250 | L16: 12 | M16: =L16*J16*$G$6 -> 1553 | N16: 12 | O16: =N16*J16*$G$6*$G$6 -> 1607 | P16: 12 | Q16: =P16*J16*$G$6*$G$6*$G$6 -> 1663 | S16: =R16*J16*$G$6*$G$6*$G$6*$G$6 -> 0 | T16: =SUM(K16+M16+O16+Q16+S16) -> 5073 | U16: 0 | V16: =SUM(T16:U16) -> 5073
A17: SUBCEREAL | B17: 89050 | C17: MEX | D17: CEREAL | E17: CERPERPRO | F17: Promotor 3 50% | G17: Salaries | H17: Month | I17: 2 | J17: 125 | K17: =I17*J17 -> 250 | L17: 12 | M17: =L17*J17*$G$6 -> 1553 | N17: 12 | O17: =N17*J17*$G$6*$G$6 -> 1607 | P17: 12 | Q17: =P17*J17*$G$6*$G$6*$G$6 -> 1663 | S17: =R17*J17*$G$6*$G$6*$G$6*$G$6 -> 0 | T17: =SUM(K17+M17+O17+Q17+S17) -> 5073 | U17: 0 | V17: =SUM(T17:U17) -> 5073
A18: SUBCEREAL | B18: 89050 | C18: MEX | D18: CEREAL | E18: CERPERPRO | F18: Promotor 4 50% | G18: Salaries | H18: Month | I18: 2 | J18: 125 | K18: =I18*J18 -> 250 | L18: 12 | M18: =L18*J18*$G$6 -> 1553 | N18: 12 | O18: =N18*J18*$G$6*$G$6 -> 1607 | P18: 12 | Q18: =P18*J18*$G$6*$G$6*$G$6 -> 1663 | S18: =R18*J18*$G$6*$G$6*$G$6*$G$6 -> 0 | T18: =SUM(K18+M18+O18+Q18+S18) -> 5073 | U18: 0 | V18: =SUM(T18:U18) -> 5073
F20: Subtotal Direct Labor | K20: =SUM(K9:K19) -> 27628 | M20: =SUM(M9:M19) -> 116450 | O20: =SUM(O9:O19) -> 120526 | Q20: =SUM(Q9:Q19) -> 124743 | S20: =SUM(S9:S19) -> 17024 | T20: =SUM(T9:T19) -> 406371 | U20: =SUM(U9:U19) -> 0 | V20: =SUM(V9:V19) -> 406371
F22: Subtotal Travel | K22: =SUM(K21:K21) -> 0 | M22: =SUM(M21:M21) -> 0 | O22: =SUM(O21:O21) -> 0 | Q22: =SUM(Q21:Q21) -> 0 | S22: =SUM(S21:S21) -> 0 | T22: =SUM(T21:T21) -> 0 | U22: =SUM(U21:U21) -> 0 | V22: =SUM(V21:V21) -> 0
F23: Supplies & Office Expenses
A24: SUBCEREAL | B24: 89050 | C24: MEX | D24: CEREAL | E24: CERDESK | F24: Desktop computers, laptops and software | G24: Supplies | H24: Unit | I24: 4 | J24: 1000 | K24: =I24*J24 -> 4000 | L24: 0 | M24: =L24*J24*$G$5 -> 0 | N24: 0 | O24: =N24*J24*$G$5*$G$5 -> 0 | P24: 0 | Q24: =P24*J24*$G$5*$G$5*$G$5 -> 0 | R24: 0 | S24: =R24*J24*$G$5*$G$5*$G$5*$G$5 -> 0 | T24: =K24+M24+O24+Q24+S24 -> 4000 | U24: 0 | V24: =SUM(T24:U24) -> 4000
A25: SUBCEREAL | B25: 89050 | C25: MEX | D25: CEREAL | E25: CERMEET | F25: Meeting Expenses | G25: Supplies | H25: Year | I25: 1 | J25: 1000 | K25: =I25*J25 -> 1000 | L25: 1 | M25: =L25*J25*$G$5 -> 1040 | N25: 1 | O25: =N25*J25*$G$5*$G$5 -> 1082 | P25: 1 | Q25: =P25*J25*$G$5*$G$5*$G$5 -> 1125 | R25: 0.25 | S25: =R25*J25*$G$5*$G$5*$G$5*$G$5 -> 292 | T25: =K25+M25+O25+Q25+S25 -> 4539 | U25: 0 | V25: =SUM(T25:U25) -> 4539
A26: SUBCEREAL | B26: 89050 | C26: MEX | D26: CEREAL | E26: CERPHONE | F26: Phones | G26: Supplies | H26: Unit | I26: 4 | J26: 300 | K26: =I26*J26 -> 1200 | L26: 0 | M26: =L26*J26*$G$5 -> 0 | N26: 0 | O26: =N26*J26*$G$5*$G$5 -> 0 | P26: 0 | Q26: =P26*J26*$G$5*$G$5*$G$5 -> 0 | R26: 0 | S26: =R26*J26*$G$5*$G$5*$G$5*$G$5 -> 0 | T26: =K26+M26+O26+Q26+S26 -> 1200 | U26: 0 | V26: =SUM(T26:U26) -> 1200
A27: SUBCEREAL | B27: 89050 | C27: MEX | D27: CEREAL | E27: CERMATLS | F27: Stationary / Printing Materials | G27: Supplies | H27: Year | I27: 1 | J27: 900 | K27: =I27*J27 -> 900 | L27: 1 | M27: =L27*J27*$G$5 -> 936 | N27: 1 | O27: =N27*J27*$G$5*$G$5 -> 973 | P27: 1 | Q27: =P27*J27*$G$5*$G$5*$G$5 -> 1012 | R27: 0.25 | S27: =R27*J27*$G$5*$G$5*$G$5*$G$5 -> 263 | T27: =K27+M27+O27+Q27+S27 -> 4084 | U27: 0 | V27: =SUM(T27:U27) -> 4084
A28: SUBCEREAL | B28: 89050 | C28: MEX | D28: CEREAL | E28: CERCAMARA | F28: Camara Canon | G28: Supplies | H28: Set | I28: 1 | J28: 1000 | K28: =I28*J28 -> 1000 | L28: 0 | M28: =L28*J28*$G$5 -> 0 | N28: 0 | O28: =N28*J28*$G$5*$G$5 -> 0 | P28: 0 | Q28: =P28*J28*$G$5*$G$5*$G$5 -> 0 | R28: 0 | S28: =R28*J28*$G$5*$G$5*$G$5*$G$5 -> 0 | T28: =K28+M28+O28+Q28+S28 -> 1000 | U28: 0 | V28: =SUM(T28:U28) -> 1000
A29: SUBCEREAL | B29: 89050 | C29: MEX | D29: CEREAL | E29: CERPRINT | F29: Printer | G29: Supplies | H29: Set | I29: 1 | J29: 550 | K29: =I29*J29 -> 550 | L29: 0 | M29: =L29*J29*$G$5 -> 0 | N29: 0 | O29: =N29*J29*$G$5*$G$5 -> 0 | P29: 0 | Q29: =P29*J29*$G$5*$G$5*$G$5 -> 0 | R29: 0 | S29: =R29*J29*$G$5*$G$5*$G$5*$G$5 -> 0 | T29: =K29+M29+O29+Q29+S29 -> 550 | U29: 0 | V29: =SUM(T29:U29) -> 550
A30: SUBCEREAL | B30: 89050 | C30: MEX | D30: CEREAL | E30: CERSPEAKER | F30: Speaker System | G30: Supplies | H30: Set | I30: 1 | J30: 250 | K30: =I30*J30 -> 250 | L30: 0 | M30: =L30*J30*$G$5 -> 0 | N30: 0 | O30: =N30*J30*$G$5*$G$5 -> 0 | P30: 0 | Q30: =P30*J30*$G$5*$G$5*$G$5 -> 0 | R30: 0 | S30: =R30*J30*$G$5*$G$5*$G$5*$G$5 -> 0 | T30: =K30+M30+O30+Q30+S30 -> 250 | U30: 0 | V30: =SUM(T30:U30) -> 250
A31: SUBCEREAL | B31: 89050 | C31: MEX | D31: CEREAL | E31: CERBANK | F31: Banking and cash handling fees | G31: Office Expenses | H31: Month | I31: 3 | J31: 40 | K31: =I31*J31 -> 120 | L31: 12 | M31: =L31*J31*$G$5 -> 499 | N31: 12 | O31: =N31*J31*$G$5*$G$5 -> 519 | P31: 12 | Q31: =P31*J31*$G$5*$G$5*$G$5 -> 540 | R31: 2 | S31: =R31*J31*$G$5*$G$5*$G$5*$G$5 -> 94 | T31: =K31+M31+O31+Q31+S31 -> 1772 | U31: 0 | V31: =SUM(T31:U31) -> 1772
A32: SUBCEREAL | B32: 89050 | C32: MEX | D32: CEREAL | E32: CEREMAIL | F32: Email/Internet | G32: Office Expenses | H32: Month | I32: 3 | J32: 100 | K32: =I32*J32 -> 300 | L32: 12 | M32: =L32*J32*$G$5 -> 1248 | N32: 12 | O32: =N32*J32*$G$5*$G$5 -> 1298 | P32: 12 | Q32: =P32*J32*$G$5*$G$5*$G$5 -> 1350 | R32: 2 | S32: =R32*J32*$G$5*$G$5*$G$5*$G$5 -> 234 | T32: =K32+M32+O32+Q32+S32 -> 4430 | U32: 0 | V32: =SUM(T32:U32) -> 4430
A33: SUBCEREAL | B33: 89050 | C33: MEX | D33: CEREAL | E33: CERCOMMS | F33: Phones and Communication Costs | G33: Office Expenses | H33: Month | I33: 3 | J33: =(30*4) -> 120 | K33: =I33*J33 -> 360 | L33: 12 | M33: =L33*J33*$G$5 -> 1498 | N33: 12 | O33: =N33*J33*$G$5*$G$5 -> 1558 | P33: 12 | Q33: =P33*J33*$G$5*$G$5*$G$5 -> 1620 | R33: 2 | S33: =R33*J33*$G$5*$G$5*$G$5*$G$5 -> 281 | T33: =K33+M33+O33+Q33+S33 -> 5317 | U33: 0 | V33: =SUM(T33:U33) -> 5317
A34: SUBCEREAL | B34: 89050 | C34: MEX | D34: CEREAL | E34: CERRENT | F34: Office Rent | G34: Office Expenses | H34: Month | I34: 2 | J34: 1000 | K34: =I34*J34 -> 2000 | L34: 12 | M34: =L34*J34*$G$5 -> 12480 | N34: 12 | O34: =N34*J34*$G$5*$G$5 -> 12979 | P34: 12 | Q34: =P34*J34*$G$5*$G$5*$G$5 -> 13498 | R34: 2 | S34: =R34*J34*$G$5*$G$5*$G$5*$G$5 -> 2340 | T34: =K34+M34+O34+Q34+S34 -> 43297 | U34: 0 | V34: =SUM(T34:U34) -> 43297
A35: SUBCEREAL | B35: 89050 | C35: MEX | D35: CEREAL | E35: CEREQUIP | F35: Equipment and office repairs and maintenance | G35: Office Expenses | H35: Month | I35: 0 | J35: 250 | K35: =I35*J35 -> 0 | L35: 3 | M35: =L35*J35*$G$5 -> 780 | N35: 3 | O35: =N35*J35*$G$5*$G$5 -> 811 | P35: 3 | Q35: =P35*J35*$G$5*$G$5*$G$5 -> 844 | R35: 1 | S35: =R35*J35*$G$5*$G$5*$G$5*$G$5 -> 292 | T35: =K35+M35+O35+Q35+S35 -> 2727 | U35: 0 | V35: =SUM(T35:U35) -> 2727
A36: SUBCEREAL | B36: 89050 | C36: MEX | D36: CEREAL | E36: CERINSUR | F36: Insurance | G36: Office Expenses | H36: Year | I36: 1 | J36: 250 | K36: =I36*J36 -> 250 | L36: 1 | M36: =L36*J36*$G$5 -> 260 | N36: 1 | O36: =N36*J36*$G$5*$G$5 -> 270 | P36: 1 | Q36: =P36*J36*$G$5*$G$5*$G$5 -> 281 | R36: 0.25 | S36: =R36*J36*$G$5*$G$5*$G$5*$G$5 -> 73 | T36: =K36+M36+O36+Q36+S36 -> 1134 | U36: 0 | V36: =SUM(T36:U36) -> 1134
A37: SUBCEREAL | B37: 89050 | C37: MEX | D37: CEREAL | E37: CERSUPPLY | F37: Offices supplies | G37: Office Expenses | H37: Year | I37: 1 | J37: 250 | K37: =I37*J37 -> 250 | L37: 1 | M37: =L37*J37*$G$5 -> 260 | N37: 1 | O37: =N37*J37*$G$5*$G$5 -> 270 | P37: 1 | Q37: =P37*J37*$G$5*$G$5*$G$5 -> 281 | R37: 1 | S37: =R37*J37*$G$5*$G$5*$G$5*$G$5 -> 292 | T37: =K37+M37+O37+Q37+S37 -> 1353 | U37: 0 | V37: =SUM(T37:U37) -> 1353
F39: Subtotal Supplies & Office Expenses | K39: =SUM(K24:K37) -> 12180 | M39: =SUM(M24:M37) -> 19001 | O39: =SUM(O24:O37) -> 19760 | Q39: =SUM(Q24:Q37) -> 20551 | S39: =SUM(S24:S37) -> 4161 | T39: =SUM(T24:T37) -> 75653 | U39: =SUM(U24:U37) -> 0 | V39: =SUM(V24:V37) -> 75653
F40: The above is only for percentage calculations for the below outcomes
F41: Outcome 1: WO advance issues surrounding substantive equality, including gender proportionality in leadership and participation in key activities, within their institutions
F42: Activities/Costs
F43: Personnel & Fringe (40% of Direct Labor line item) | G43: Outcome1 | H43: Unit | I43: =$K$20 -> 27628 | J43: 0.4 | K43: =I43*J43 -> 11051 | L43: =$M$20 -> 116450 | M43: =L43*J43 -> 46580 | N43: =$O$20 -> 120526 | O43: =N43*J43 -> 48210 | P43: =$Q$20 -> 124743 | Q43: =P43*J43 -> 49897 | R43: =$S$20 -> 17024 | S43: =R43*J43 -> 6810 | T43: =K43+M43+O43+Q43+S43 -> 162548 | U43: 0 | V43: =SUM(T43:U43) -> 162548
F44: Supplies & Office Expenses (40%) | G44: Outcome1 | H44: Unit | I44: =$K$39 -> 12180 | J44: 0.4 | K44: =I44*J44 -> 4872 | L44: =$M$39 -> 19001 | M44: =L44*J44 -> 7600 | N44: =$O$39 -> 19760 | O44: =N44*J44 -> 7904 | P44: =$Q$39 -> 20551 | Q44: =P44*J44 -> 8220 | R44: =$S$39 -> 4161 | S44: =R44*J44 -> 1664 | T44: =K44+M44+O44+Q44+S44 -> 30260 | U44: 0 | V44: =SUM(T44:U44) -> 30260
F45: 1: Conduct a participatory diagnosis on gender equality and representation issues within WO
A46: SUBCEREAL | B46: 89050 | C46: MEX | D46: CEREAL | E46: CEROUT1-1 | F46: Participatory diagnosis on gender equality and gender representation issues within WO | G46: Outcome1 | H46: Unit | I46: 0 | J46: 20000 | K46: =I46*J46 -> 0 | L46: 1 | M46: =J46*L46 -> 20000 | S46: =R46*J46 -> 0 | T46: =K46+M46+O46+Q46+S46 -> 20000 | U46: 0 | V46: =SUM(T46:U46) -> 20000
F47: 2: Identify and train young women workers in leadership, negotiation, and conflict resolution
A48: SUBCEREAL | B48: 89050 | C48: MEX | D48: CEREAL | E48: CEROUT1-2 | F48: Training of young women workers in leadership, negotiation and conflict resolution. | G48: Outcome1 | H48: Unit | I48: 1 | J48: =17116-9000-6000 -> 2116 | K48: =$J48*I48 -> 2116 | L48: 6 | M48: =$J48*L48 -> 12696 | N48: 6 | O48: =$J48*N48 -> 12696 | P48: 6 | Q48: =$J48*P48 -> 12696 | R48: 2 | S48: =$J48*R48 -> 4232 | T48: =K48+M48+O48+Q48+S48 -> 44436 | U48: 0 | V48: =SUM(T48:U48) -> 44436
F49: 4: Develop strategic plans for WO to comply with the gender provisions of the Mexican labor reform
A50: SUBCEREAL | B50: 89050 | C50: MEX | D50: CEREAL | E50: CEROUT1-4 | F50: Strategic plans for WO to comply with the gender provisions of the Mexican labor reform | G50: Outcome1 | H50: Unit | J50: 5583 | K50: =I50*J50 -> 0 | L50: 1 | M50: =L50*J50 -> 5583 | O50: =N50*J50 -> 0 | Q50: =P50*J50 -> 0 | S50: =R50*J50 -> 0 | T50: =K50+M50+O50+Q50+S50 -> 5583 | U50: 0 | V50: =SUM(T50:U50) -> 5583
F51: 6: Develop protocols focused on eliminating violence and harassment within WO membership
A52: SUBCEREAL | B52: 89050 | C52: MEX | D52: CEREAL | E52: CEROUT1-6 | F52: Protocols focused on eliminating violence and harassment among WO members | G52: Outcome1 | H52: Unit | J52: 5250 | K52: =I52*J52 -> 0 | L52: 1 | M52: =L52*J52 -> 5250 | O52: =N52*J52 -> 0 | Q52: =P52*J52 -> 0 | S52: =R52*J52 -> 0 | T52: =K52+M52+O52+Q52+S52 -> 5250 | U52: 0 | V52: =SUM(T52:U52) -> 5250
F53: 7: Develop a toolkit for WO to support the integration of the gender perspective and the increase of women members
A54: SUBCEREAL | B54: 89050 | C54: MEX | D54: CEREAL | E54: CEROUT1-7 | F54: Toolkit for substantive equality and the unionization of women | G54: Outcome1 | H54: Unit | I54: 1 | J54: =8856-6000 -> 2856 | K54: =$J54*I54 -> 2856 | L54: 2 | M54: =$J54*L54 -> 5712 | N54: 2 | O54: =$J54*N54 -> 5712 | P54: 2 | Q54: =$J54*P54 -> 5712 | R54: 1 | S54: =$J54*R54 -> 2856 | T54: =K54+M54+O54+Q54+S54 -> 22848 | U54: 0 | V54: =SUM(T54:U54) -> 22848
F55: 8: Identify, systematize, and disseminate good practices on gender, democracy, and WO administration
A56: SUBCEREAL | B56: 89050 | C56: MEX | D56: CEREAL | E56: CEROUT1-8 | F56: Compendium of good practices on democracy and WO administration | G56: Outcome1 | H56: Unit | J56: 1500 | K56: =$J56*I56 -> 0 | L56: 1 | M56: =$J56*L56 -> 1500 | N56: 2 | O56: =$J56*N56 -> 3000 | P56: 1 | Q56: 1500 | R56: 1 | S56: =$J56*R56 -> 1500 | T56: =K56+M56+O56+Q56+S56 -> 7500 | U56: 0 | V56: =SUM(T56:U56) -> 7500
F58: Direct Costs Total for Outcome 1 | K58: =SUM(K43:K56) -> 20895 | M58: =SUM(M43:M56) -> 104921 | O58: =SUM(O43:O56) -> 77522 | Q58: =SUM(Q43:Q56) -> 78025 | S58: =SUM(S43:S56) -> 17062 | T58: =K58+M58+O58+Q58+S58 -> 298425 | U58: =SUM(U43:U56) -> 0 | V58: =SUM(T58:U58) -> 298425
A60: SUBCEREAL | B60: 89050 | C60: MEX | D60: CEREAL | E60: CERIDCCOST | F60: Total Indirect Costs (De Minimis 10%) for Outcome 1 | G60: Indirect Charges | J60: 0.1 | K60: =(K58)*J60 -> 2090 | M60: =(M58)*J60 -> 10492 | O60: =(O58)*J60 -> 7752 | Q60: =(Q58)*$J60 -> 7803 | S60: =(S58)*$J60 -> 1706 | T60: =SUM(K60+M60+O60+Q60+S60) -> 29843 | U60: 0 | V60: =SUM(T60:U60) -> 29843
F62: Subtotal Outcome 1 | K62: =SUM(K58:K60) -> 22985 | M62: =SUM(M58:M60) -> 115413 | O62: =SUM(O58:O60) -> 85274 | Q62: =SUM(Q58:Q60) -> 85828 | S62: =SUM(S58:S60) -> 18768 | T62: =K62+M62+O62+Q62+S62 -> 328268 | U62: =U60 -> 0 | V62: =SUM(T62:U62) -> 328268
F63: Outcome 2: Worker organizations undertake sustained action to promote gender equity in the workplace
F64: Activities/Costs
F65: Personnel & Fringe (30% of Direct Labor line item) | G65: Outcome2 | H65: Unit | I65: =$K$20 -> 27628 | J65: 0.3 | K65: =I65*J65 -> 8288 | L65: =$M$20 -> 116450 | M65: =L65*J65 -> 34935 | N65: =$O$20 -> 120526 | O65: =N65*J65 -> 36158 | P65: =$Q$20 -> 124743 | Q65: =P65*J65 -> 37423 | R65: =$S$20 -> 17024 | S65: =R65*J65 -> 5107 | T65: =K65+M65+O65+Q65+S65 -> 121911 | U65: 0 | V65: =SUM(T65:U65) -> 121911
F66: Supplies & Office Expenses (30%) | G66: Outcome2 | H66: Unit | I66: =$K$39 -> 12180 | J66: 0.3 | K66: =I66*J66 -> 3654 | L66: =$M$39 -> 19001 | M66: =L66*J66 -> 5700 | N66: =$O$39 -> 19760 | O66: =N66*J66 -> 5928 | P66: =$Q$39 -> 20551 | Q66: =P66*J66 -> 6165 | R66: =$S$39 -> 4161 | S66: =R66*J66 -> 1248 | T66: =K66+M66+O66+Q66+S66 -> 22695 | U66: 0 | V66: =SUM(T66:U66) -> 22695
F67: 9: Conduct a participatory diagnosis on substantive equality and representation in the prioritized sectors and workplaces
A68: SUBCEREAL | B68: 89050 | C68: MEX | D68: CEREAL | E68: CEROUT2-9 | F68: Participatory diagnosis on gender equality and representation in prioritized sectors and workplaces | G68: Outcome2 | H68: Unit | I68: 1 | J68: 11650 | L68: 1 | M68: =L68*$J68 -> 11650 | O68: =N68*J68 -> 0 | Q68: =P68*J68 -> 0 | S68: =R68*J68 -> 0 | T68: =K68+M68+O68+Q68+S68 -> 11650 | U68: 0 | V68: =SUM(T68:U68) -> 11650
F69: 12: Establish roundtables within WO to disseminate best practices for substantive equality in the workplace
A70: SUBCEREAL | B70: 89050 | C70: MEX | D70: CEREAL | E70: CEROUT2-12 | F70: Permanent roundtables within WO | G70: Outcome2 | H70: Workshops | J70: 500 | K70: =I70*J70 -> 0 | L70: 12 | M70: =L70*$J70 -> 6000 | N70: 12 | O70: =N70*$J70 -> 6000 | P70: 12 | Q70: =P70*$J70 -> 6000 | R70: 6 | S70: =R70*$J70 -> 3000 | T70: =K70+M70+O70+Q70+S70 -> 21000 | U70: 0 | V70: =SUM(T70:U70) -> 21000
F71: 13: Develop technical roundtables on social protection systems led by WO
A72: SUBCEREAL | B72: 89050 | C72: MEX | D72: CEREAL | E72: CEROUT2-13 | F72: Quarterly reports of problems addressed by the roundtables | G72: Outcome2 | H72: Unit | I72: 1 | J72: 1500 | L72: 4 | M72: =L72*$J72 -> 6000 | N72: 4 | O72: =N72*$J72 -> 6000 | P72: 4 | Q72: =P72*$J72 -> 6000 | R72: 2 | S72: =R72*$J72 -> 3000 | T72: =K72+M72+O72+Q72+S72 -> 21000 | U72: 0 | V72: =SUM(T72:U72) -> 21000
F73: 15: Train workers and WO on effective methods for gathering evidence and reporting discrimination and GBVH in the workplace
A74: SUBCEREAL | B74: 89050 | C74: MEX | D74: CEREAL | E74: CEROUT2-15 | F74: Specialized training for the presentation of cases of discrimination and GBVH aimed at workers and WO | G74: Outcome2 | H74: Unit | I74: 1 | J74: 1200 | L74: 5 | M74: =L74*$J74 -> 6000 | N74: 6 | O74: =N74*$J74 -> 7200 | P74: 6 | Q74: =P74*$J74 -> 7200 | T74: =K74+M74+O74+Q74+S74 -> 20400 | U74: 0 | V74: =SUM(T74:U74) -> 20400
F75: 16: Provide legal support to workers in cases related to gender discrimination, wage violations, failure to pay social protection systems, harassment or violence, and other relevant labor violations
A76: SUBCEREAL | B76: 89050 | C76: MEX | D76: CEREAL | E76: CEROUT2-16 | F76: Network of Lawyers for the Defense of Workers | G76: Outcome2 | H76: Unit | I76: 1 | J76: 1000 | K76: =I76*J76 -> 1000 | L76: 1 | M76: =L76*J76 -> 1000 | N76: 1 | O76: =N76*J76 -> 1000 | P76: 1 | Q76: =P76*$J76 -> 1000 | R76: 1 | S76: =R76*$J76 -> 1000 | T76: =K76+M76+O76+Q76+S76 -> 5000 | U76: 0 | V76: =SUM(T76:U76) -> 5000
A77: SUBCEREAL | B77: 89050 | C77: MEX | D77: CEREAL | E77: CEROUT2-16 | F77: Legal Advice delivered to workers in cases of gender discrimination in the workplace and associated labor violations. | G77: Outcome2 | H77: Unit | I77: 0 | J77: 6100 | K77: =I77*J77 -> 0 | L77: 1 | M77: =L77*J77 -> 6100 | N77: 1 | O77: =N77*J77 -> 6100 | P77: 1 | Q77: =P77*$J77 -> 6100 | R77: 0.5 | S77: =R77*$J77 -> 3050 | T77: =K77+M77+O77+Q77+S77 -> 21350 | U77: 0 | V77: =SUM(T77:U77) -> 21350
K78: =I78*J78 -> 0
F79: Direct Costs Total for Outcome 2 | K79: =SUM(K65:K77) -> 12942 | M79: =SUM(M65:M77) -> 77385 | O79: =SUM(O65:O77) -> 68386 | Q79: =SUM(Q65:Q77) -> 69888 | S79: =SUM(S65:S77) -> 16405 | T79: =SUM(T65:T77) -> 245006 | U79: =SUM(U65:U77) -> 0 | V79: =SUM(V65:V77) -> 245006
A81: SUBCEREAL | B81: 89050 | C81: MEX | D81: CEREAL | E81: CERIDCCOST | F81: Total Indirect Costs (De Minimis 10%) for Outcome 2 | G81: Indirect Charges | J81: 0.1 | K81: =(K79)*J81 -> 1294 | M81: =(M79)*J81 -> 7739 | O81: =(O79)*J81 -> 6839 | Q81: =(Q79)*$J81 -> 6989 | S81: =(S79)*$J81 -> 1641 | T81: =SUM(K81+M81+O81+Q81+S81) -> 24502 | U81: 0 | V81: =SUM(T81:U81) -> 24502
F83: Subtotal Outcome 2 | K83: =SUM(K79:K81) -> 14236 | M83: =SUM(M79:M81) -> 85124 | O83: =SUM(O79:O81) -> 75225 | Q83: =SUM(Q79:Q81) -> 76877 | S83: =SUM(S79:S81) -> 18046 | T83: =K83+M83+O83+Q83+S83 -> 269508 | U83: =U81 -> 0 | V83: =SUM(T83:U83) -> 269508
F84: 3: Monitoring, Evaluation, and Collection of Reliable Data
F85: Activities/Costs
F86: Personnel & Fringe (30% of Direct Labor line item) | G86: M&E | H86: Unit | I86: =$K$20 -> 27628 | J86: 0.3 | K86: =I86*J86 -> 8288 | L86: =$M$20 -> 116450 | M86: =L86*J86 -> 34935 | N86: =$O$20 -> 120526 | O86: =N86*J86 -> 36158 | P86: =$Q$20 -> 124743 | Q86: =P86*J86 -> 37423 | R86: =$S$20 -> 17024 | S86: =R86*J86 -> 5107 | T86: =K86+M86+O86+Q86+S86 -> 121911 | U86: 0 | V86: =SUM(T86:U86) -> 121911
F87: Supplies & Office Expenses 30% | G87: M&E | H87: Unit | I87: =$K$39 -> 12180 | J87: 0.3 | K87: =I87*J87 -> 3654 | L87: =$M$39 -> 19001 | M87: =L87*J87 -> 5700 | N87: =$O$39 -> 19760 | O87: =N87*J87 -> 5928 | P87: =$Q$39 -> 20551 | Q87: =P87*J87 -> 6165 | R87: =$S$39 -> 4161 | S87: =R87*J87 -> 1248 | T87: =K87+M87+O87+Q87+S87 -> 22695 | U87: 0 | V87: =SUM(T87:U87) -> 22695
F88: 3.7.1.1 Collection of Reliable Data and Processing of Monitoring Data
A89: SUBCEREAL | B89: 89050 | C89: MEX | D89: CEREAL | E89: CERLODGPER | F89: Lodging and M&IE - Field verification and data collection visits | G89: M&E | H89: Unit | I89: 2 | J89: 110 | K89: =I89*J89 -> 220 | L89: 12 | M89: =L89*J89 -> 1320 | N89: 12 | O89: =N89*J89 -> 1320 | P89: 12 | Q89: =P89*J89 -> 1320 | R89: 2 | S89: =R89*J89 -> 220 | T89: =K89+M89+O89+Q89+S89 -> 4400 | U89: 0 | V89: =SUM(T89:U89) -> 4400
A90: SUBCEREAL | B90: 89050 | C90: MEX | D90: CEREAL | E90: CERTRANS | F90: Local transportation - Field verification and data collection visits | G90: M&E | H90: Unit | I90: 2 | J90: 100 | K90: =I90*J90 -> 200 | L90: 12 | M90: =L90*J90 -> 1200 | N90: 12 | O90: =N90*J90 -> 1200 | P90: 12 | Q90: =P90*J90 -> 1200 | R90: 2 | S90: =R90*J90 -> 200 | T90: =K90+M90+O90+Q90+S90 -> 4000 | U90: 0 | V90: =SUM(T90:U90) -> 4000
A91: SUBCEREAL | B91: 89050 | C91: MEX | D91: CEREAL | E91: CERDATA | F91: Data collection materials and printing | G91: M&E | H91: Unit | I91: 1 | J91: 100 | K91: =I91*J91 -> 100 | L91: 4 | M91: =L91*J91 -> 400 | N91: 4 | O91: =N91*J91 -> 400 | P91: 4 | Q91: =P91*J91 -> 400 | R91: 1 | S91: =R91*J91 -> 100 | T91: =K91+M91+O91+Q91+S91 -> 1400 | U91: 0 | V91: =SUM(T91:U91) -> 1400
F93: Direct Costs Total for Monitoring, Evaluation, and Collection of Reliable Data | K93: =SUM(K86:K91) -> 12462 | M93: =SUM(M86:M91) -> 43555 | O93: =SUM(O86:O91) -> 45006 | Q93: =SUM(Q86:Q91) -> 46508 | S93: =SUM(S86:S91) -> 6875 | T93: =K93+M93+O93+Q93+S93 -> 154406 | U93: =SUM(U86:U91) -> 0 | V93: =SUM(T93:U93) -> 154406
A95: SUBCEREAL | B95: 89050 | C95: MEX | D95: CEREAL | E95: CERIDCCOST | F95: Total Indirect Costs (De Minimis 10%) for M&E | G95: Indirect Charges | J95: 0.1 | K95: =(K93)*J95 -> 1246 | M95: =(M93)*J95 -> 4356 | O95: =(O93)*J95 -> 4501 | Q95: =(Q93)*J95 -> 4651 | S95: =(S93)*J95 -> 688 | T95: =SUM(K95+M95+O95+Q95+S95) -> 15442 | U95: 0 | V95: =SUM(T95:U95) -> 15442
F97: Subtotal M&E | K97: =SUM(K93:K95) -> 13708 | M97: =SUM(M93:M95) -> 47911 | O97: =SUM(O93:O95) -> 49507 | Q97: =SUM(Q93:Q95) -> 51159 | S97: =SUM(S93:S95) -> 7563 | T97: =K97+M97+O97+Q97+S97 -> 169848 | U97: =U95 -> 0 | V97: =SUM(T97:U97) -> 169848
F99: TOTAL COSTS | K99: =K97+K62+K83 -> 50929 | M99: =M97+M62+M83 -> 248448 | O99: =O97+O62+O83 -> 210006 | Q99: =Q97+Q62+Q83 -> 213864 | S99: =S97+S62+S83 -> 44377 | T99: =T97+T62+T83 -> 767624 | U99: =U97+U62+U83 -> 0 | V99: =V97+V62+V83 -> 767624
