Workbook
Name \A: #REF!
Name \A: #REF!
Name \A: #REF!
Name \P: #REF!
Name \P: #REF!
Name \P: #REF!
Name \S: #REF!
Name \S: #REF!
Name \S: #REF!
Name _______sho1: '[3]Detailed Budget-SAVE'!#REF!
Name _______sho1: '[3]Detailed Budget-SAVE'!#REF!
Name _______sho1: '[3]Detailed Budget-SAVE'!#REF!
Name __2DAI_1: #N/A
Name __3FEE: #N/A
Name __AFP1: #N/A
Name __AFP2: #N/A
Name __AFP3: #N/A
Name __AFP4: #N/A
Name __AMP1: #N/A
Name __AMP2: #N/A
Name __AMP3: #N/A
Name __AMP4: #N/A
Name __DAI4: #N/A
Name __EES1: #N/A
Name __EES2: #N/A
Name __EES3: #N/A
Name __EES4: #N/A
Name __EXT1: #N/A
Name __EXT2: #N/A
Name __EXT3: #N/A
Name __EXT4: #N/A
Name __FCP1: #N/A
Name __FCP2: #N/A
Name __FCP3: #N/A
Name __FCP4: #N/A
Name __FRI1: #N/A
Name __FRI4: #N/A
Name __HRA1: #N/A
Name __HRA2: #N/A
Name __HRA3: #N/A
Name __HRA4: #N/A
Name __inf1: #REF!
Name __LT4: [4]Parameters!$B$40
Name __ODC1: #N/A
Name __ODC2: #N/A
Name __POL1: #N/A
Name __POL2: #N/A
Name __POL3: #N/A
Name __POL4: #N/A
Name __TOT1: #N/A
Name __TOT2: #N/A
Name __TRV1: #N/A
Name __TRV2: #N/A
Name _060: #REF!
Name _1_1: #REF!
Name _13th_and_14th_month: [5]Parameters!$D$62
Name _2_1034: #REF!
Name _2DAI_1: #N/A
Name _3_1440: #REF!
Name _3FEE: #N/A

Sheet USDA Budget Summary
A1: C-1
A2: Proposed Budget Summary
A4: Program (FFPr or MGD): | B4: FFPr
A5: Country of Operation: | B5: Nigeria (Non-priority country)
A6: Implementing Organization: | B6: Partners of the Americas Inc.
A7: Fiscal Year: | B7: 2025
A8: Agreement Number: | B8: USDA-FAS-10.606-0700-25(000)
A10: Total Amount of Federal Funds Requested
A11: Funding Source (FAS for MGD) (CCC for FFPr) | B11: Funding Year | C11: Commodity Cost | D11: Freight Cost | E11: Administrative Costs (cash portion) | F11: Total Federal Funding Obligated
B12: 2025 | C12: 20610000 | D12: 4750000 | E12: 1000000 | F12: =E12+D12+C12 -> 26360000
A14: Project Operating Budget
A15: Expense Type | B15: Monetization Proceeds (FFPr Only) | C15: FAS or CCC Funds (CCC is Admin Only) | D15: Cost Share | E15: Total w/out Cost Share | F15: Total w/Cost Share
A16: Administration
A17: Salaries/Personnel | B17: ='Program Budget'!V32-C17 -> 98891.649 | C17: 264655 | D17: ='Program Budget'!W32 -> 0 | E17: =B17+C17 -> 363546.65 | F17: =B17+C17+D17 -> 363546.65
A18: Benefits | B18: ='Program Budget'!V38-C18 -> 26906.721 | C18: 68781 | D18: ='Program Budget'!W38 -> 0 | E18: =B18+C18 -> 95687.721 | F18: =B18+C18+D18 -> 95687.721
A19: Travel | B19: ='Program Budget'!V58-C19 -> 180726.56 | C19: 60136 | D19: ='Program Budget'!W58 -> 0 | E19: =B19+C19 -> 240862.56 | F19: =B19+C19+D19 -> 240862.56
A20: Professional Services/Contractual | B20: ='Program Budget'!V84-C20 -> 641325.78 | C20: 351567.22 | D20: ='Program Budget'!W84 -> 0 | E20: =B20+C20 -> 992893 | F20: =B20+C20+D20 -> 992893
A21: Equipment | B21: ='Program Budget'!V89-C21 -> 0 | C21: 60000 | D21: ='Program Budget'!W89 -> 0 | E21: =B21+C21 -> 60000 | F21: =B21+C21+D21 -> 60000
A22: Office | B22: ='Program Budget'!V105-C22 -> 229220.93 | C22: 47105 | D22: ='Program Budget'!W105 -> 0 | E22: =B22+C22 -> 276325.93 | F22: =B22+C22+D22 -> 276325.93
A23: Supplies | B23: ='Program Budget'!V114-C23 -> 5323.0325 | C23: 10346 | D23: ='Program Budget'!W114 -> 0 | E23: =B23+C23 -> 15669.032 | F23: =B23+C23+D23 -> 15669.032
A24: Other | B24: ='Program Budget'!V126-C24 -> 64793.809 | C24: 6975 | D24: 0 | E24: =B24+C24 -> 71768.809 | F24: =B24+C24+D24 -> 71768.809
A25: Total Administration | B25: =SUM(B17:B24) -> 1247188.5 | C25: =SUM(C17:C24) -> 869565.22 | D25: =SUM(D17:D24) -> 0 | E25: =SUM(E17:E24) -> 2116753.7 | F25: =SUM(F17:F24) -> 2116753.7
A27: Activities
A28: Activity 1: Increase Agricultural Productivity & Trade through Livestock Production | B28: ='Program Budget'!V183 -> 3439474 | C28: 0 | D28: ='Program Budget'!W183 -> 40000 | E28: =B28+C28 -> 3439474 | F28: =B28+C28+D28 -> 3479474
A29: Activity 2: Improve Trade Finance Capacity to Increase US Exports to Nigeria | B29: ='Program Budget'!V263 -> 4282400.9 | C29: 0 | D29: ='Program Budget'!W263 -> 307715.54 | E29: =B29+C29 -> 4282400.9 | F29: =B29+C29+D29 -> 4590116.5
A30: Activity 3: Expand Trade by Reducing Non-Tariff Trade Barriers | B30: ='Program Budget'!V315 -> 1095119.7 | C30: 0 | D30: =ROUND('Program Budget'!W315,0) -> 0 | E30: =B30+C30 -> 1095119.7 | F30: =B30+C30+D30 -> 1095119.7
A31: Total Activities | B31: =SUM(B28:B30) -> 8816994.6 | C31: =SUM(C28:C30) -> 0 | D31: =SUM(D28:D30) -> 347715.54 | E31: =SUM(E28:E30) -> 8816994.6 | F31: =SUM(F28:F30) -> 9164710.1
A33: Commodity and Food Purchases (N/A to FFPr)
A34: Commodity Procurement | B34: 0 | C34: 0 | D34: 0 | E34: =B34+C34 -> 0 | F34: =B34+C34+D34 -> 0
A35: Food Vouchers (N/A to MGD)
A36: Cash Transfers (N/A to MGD)
A37: Total Commodity Procurement | B37: =SUM(B34:B36) -> 0 | C37: =SUM(C34:C36) -> 0 | D37: =SUM(D34:D36) -> 0 | E37: =SUM(E34:E36) -> 0 | F37: =SUM(F34:F36) -> 0
A39: ITSH (N/A to FFPr)
A40: Salaries | B40: 0 | C40: 0 | D40: 0 | E40: =B40+C40 -> 0 | F40: =B40+C40+D40 -> 0
A41: Benefits | B41: 0 | C41: 0 | D41: 0 | E41: =B41+C41 -> 0 | F41: =B41+C41+D41 -> 0
A42: Transportation | B42: 0 | C42: 0 | D42: 0 | E42: =B42+C42 -> 0 | F42: =B42+C42+D42 -> 0
A43: Professional Services | B43: 0 | C43: 0 | D43: =0 -> 0 | E43: =B43+C43 -> 0 | F43: =B43+C43+D43 -> 0
A44: Warehouse | B44: 0 | C44: 0 | D44: 0 | E44: =B44+C44 -> 0 | F44: =B44+C44+D44 -> 0
A45: Supplies | B45: 0 | C45: 0 | D45: 0 | E45: =B45+C45 -> 0 | F45: =B45+C45+D45 -> 0
A46: Other | B46: 0 | C46: 0 | D46: 0 | E46: =B46+C46 -> 0 | F46: =B46+C46+D46 -> 0
A47: Total ITSH | B47: =SUM(B40:B46) -> 0 | C47: 0 | D47: =SUM(D40:D46) -> 0 | E47: =SUM(E40:E46) -> 0 | F47: =SUM(F40:F46) -> 0
A49: Total Direct Costs | B49: =B25+B31+B47+B37 -> 10064183 | C49: =C25+C31+C47+C37 -> 869565.22 | D49: =D25+D31+D47+D37 -> 347715.54 | E49: =E37+E31+E25+E47 -> 10933748 | F49: =F37+F31+F25+F47 -> 11281464
A51: Indirect Costs
A52: ICR on Administration | B52: =((B25*0.15)) -> 187078.27 | C52: =((C25*0.15)) -> 130434.78 | E52: =B52+C52 -> 317513.05
A53: ICR on Activities | B53: ='Indirect Calculations'!I61 -> 1117577.7 | C53: =C31*0.15 -> 0 | E53: =B53+C53 -> 1117577.7
A54: ICR on Commodity and Food Purchases (N/A to FFPr) | B54: =B37*0.15 -> 0 | C54: =C37*0.15 -> 0 | E54: =B54+C54 -> 0
A55: ICR on ITSH (N/A to FFPr) | B55: =B47*0.15 -> 0 | C55: =C47*0.15 -> 0 | E55: =B55+C55 -> 0
A56: Total Indirect Costs | B56: =(SUM(B52:B55)) -> 1304655.9 | C56: =(SUM(C52:C55)) -> 130434.78 | E56: =(SUM(E52:E55)) -> 1435090.7
A58: Anticipated Program Income | F58: 578839
A60: Grand Total Costs | B60: =(B56+B49) -> 11368839 | C60: =(C56+C49) -> 1000000 | D60: =(D56+D49) -> 347715.54 | E60: =(E56+E49) -> 12368839 | F60: =(F49+E56) -> 12716555
A62: Total Amount of Federal Award (Total Federal Funds Requested Plus Cost Share): | F62: =F12+D60 -> 26707716
B64: =F58+'Program Budget'!G61 -> 11368839

Sheet Detailed Budget
A2: Item | B2: Type of Unit | C2: Year 1 | G2: Year 2 | K2: Year 3 | O2: Year 4 | S2: Year 5 | W2: Total
C3: Cost | D3: Quantity | E3: Percent Allocated | F3: Total | G3: Cost | H3: Quantity | I3: Percent Allocated | J3: Total | K3: Cost | L3: Quantity | M3: Percent Allocated | N3: Total | O3: Cost | P3: Quantity | Q3: Percent Allocated | R3: Total | S3: Cost | T3: Quantity | U3: Percent Allocated | V3: Total
A4: Direct Costs
A5: Salaries
A6: USN/TCN Staff
A7: None | F7: =C7*D7*E7 -> 0 | J7: =G7*H7*I7 -> 0 | N7: =K7*L7*M7 -> 0 | R7: =O7*P7*Q7 -> 0 | V7: =S7*T7*U7 -> 0 | W7: =F7+J7+N7+R7+V7 -> 0
A8: Total: Expatriate Salaries & Wages | F8: =SUM(F7:F7) -> 0 | J8: =SUM(J7:J7) -> 0 | N8: =SUM(N7:N7) -> 0 | R8: =SUM(R7:R7) -> 0 | V8: =SUM(V7:V7) -> 0 | W8: =+F8+J8+N8+R8+V8 -> 0
A9: CNN Staff
A10: ='Program Budget'!D12 -> Key Personnel: Chief of Party | B10: ='Program Budget'!F12 -> Month | C10: ='Program Budget'!H12 -> 9583.3333 | D10: ='Program Budget'!G12 -> 11 | E10: ='Program Budget'!E12+'Activity 1'!E10+'Activity 2'!E10+'Activity 3'!E10 -> 1 | F10: =C10*D10*E10 -> 105416.67 | G10: =C10*1.05 -> 10062.5 | H10: ='Program Budget'!K12 -> 12 | I10: =Admin!I10+'Activity 1'!I10+'Activity 2'!I10+'Activity 3'!I10 -> 1 | J10: =G10*H10*I10 -> 120750 | K10: =G10*1.05 -> 10565.625 | L10: ='Program Budget'!N12 -> 12 | M10: =Admin!M10+'Activity 1'!M10+'Activity 2'!M10+'Activity 3'!M10 -> 1 | N10: =K10*L10*M10 -> 126787.5 | O10: =K10*1.05 -> 11093.906 | P10: ='Program Budget'!Q12 -> 12 | Q10: =Admin!Q10+'Activity 1'!Q10+'Activity 2'!Q10+'Activity 3'!Q10 -> 1 | R10: =O10*P10*Q10 -> 133126.88 | S10: =O10*1.05 -> 11648.602 | T10: ='Program Budget'!T12 -> 0 | U10: =Admin!U10+'Activity 1'!U10+'Activity 2'!U10+'Activity 3'!U10 -> 0 | V10: =S10*T10*U10 -> 0 | W10: =F10+J10+N10+R10+V10 -> 486081.04
A11: ='Program Budget'!D13 -> Technical Director | B11: ='Program Budget'!F13 -> Month | C11: ='Program Budget'!H13 -> 3500 | D11: ='Program Budget'!G13 -> 9 | E11: ='Program Budget'!E13+'Activity 1'!E11+'Activity 2'!E11+'Activity 3'!E11 -> 1 | F11: =C11*D11*E11 -> 31500 | G11: =C11*1.05 -> 3675 | H11: ='Program Budget'!K13 -> 12 | I11: =Admin!I11+'Activity 1'!I11+'Activity 2'!I11+'Activity 3'!I11 -> 1 | J11: =G11*H11*I11 -> 44100 | K11: =G11*1.05 -> 3858.75 | L11: ='Program Budget'!N13 -> 12 | M11: =Admin!M11+'Activity 1'!M11+'Activity 2'!M11+'Activity 3'!M11 -> 1 | N11: =K11*L11*M11 -> 46305 | O11: =K11*1.05 -> 4051.6875 | P11: ='Program Budget'!Q13 -> 12 | Q11: =Admin!Q11+'Activity 1'!Q11+'Activity 2'!Q11+'Activity 3'!Q11 -> 1 | R11: =O11*P11*Q11 -> 48620.25 | S11: =O11*1.05 -> 4254.2719 | T11: ='Program Budget'!T13 -> 0 | U11: =Admin!U11+'Activity 1'!U11+'Activity 2'!U11+'Activity 3'!U11 -> 0 | V11: =S11*T11*U11 -> 0 | W11: =F11+J11+N11+R11+V11 -> 170525.25
A12: ='Program Budget'!D14 -> Technical Lead - Activity 2 US Exports | B12: ='Program Budget'!F14 -> Month | C12: ='Program Budget'!H14 -> 2833.3333 | D12: ='Program Budget'!G14 -> 8 | E12: ='Program Budget'!E14+'Activity 1'!E12+'Activity 2'!E12+'Activity 3'!E12 -> 1 | F12: =C12*D12*E12 -> 22666.667 | G12: =C12*1.05 -> 2975 | H12: ='Program Budget'!K14 -> 12 | I12: =Admin!I12+'Activity 1'!I12+'Activity 2'!I12+'Activity 3'!I12 -> 1 | J12: =G12*H12*I12 -> 35700 | K12: =G12*1.05 -> 3123.75 | L12: ='Program Budget'!N14 -> 12 | M12: =Admin!M12+'Activity 1'!M12+'Activity 2'!M12+'Activity 3'!M12 -> 1 | N12: =K12*L12*M12 -> 37485 | O12: =K12*1.05 -> 3279.9375 | P12: ='Program Budget'!Q14 -> 12 | Q12: =Admin!Q12+'Activity 1'!Q12+'Activity 2'!Q12+'Activity 3'!Q12 -> 1 | R12: =O12*P12*Q12 -> 39359.25 | S12: =O12*1.05 -> 3443.9344 | T12: ='Program Budget'!T14 -> 0 | U12: =Admin!U12+'Activity 1'!U12+'Activity 2'!U12+'Activity 3'!U12 -> 0 | V12: =S12*T12*U12 -> 0 | W12: =F12+J12+N12+R12+V12 -> 135210.92
A13: ='Program Budget'!D15 -> Technical Lead - Activity 2 Access to Finance Specialist | B13: ='Program Budget'!F15 -> Month | C13: ='Program Budget'!H15 -> 2833.3333 | D13: ='Program Budget'!G15 -> 8 | E13: ='Program Budget'!E15+'Activity 1'!E13+'Activity 2'!E13+'Activity 3'!E13 -> 1 | F13: =C13*D13*E13 -> 22666.667 | G13: =C13*1.05 -> 2975 | H13: ='Program Budget'!K15 -> 12 | I13: =Admin!I13+'Activity 1'!I13+'Activity 2'!I13+'Activity 3'!I13 -> 1 | J13: =G13*H13*I13 -> 35700 | K13: =G13*1.05 -> 3123.75 | L13: ='Program Budget'!N15 -> 12 | M13: =Admin!M13+'Activity 1'!M13+'Activity 2'!M13+'Activity 3'!M13 -> 1 | N13: =K13*L13*M13 -> 37485 | O13: =K13*1.05 -> 3279.9375 | P13: ='Program Budget'!Q15 -> 12 | Q13: =Admin!Q13+'Activity 1'!Q13+'Activity 2'!Q13+'Activity 3'!Q13 -> 1 | R13: =O13*P13*Q13 -> 39359.25 | S13: =O13*1.05 -> 3443.9344 | T13: ='Program Budget'!T15 -> 0 | U13: =Admin!U13+'Activity 1'!U13+'Activity 2'!U13+'Activity 3'!U13 -> 0 | V13: =S13*T13*U13 -> 0 | W13: =F13+J13+N13+R13+V13 -> 135210.92
A14: ='Program Budget'!D16 -> Communications/Strategic Partnerships Manager | B14: ='Program Budget'!F16 -> Month | C14: ='Program Budget'!H16 -> 2666.6667 | D14: ='Program Budget'!G16 -> 8 | E14: ='Program Budget'!E16+'Activity 1'!E14+'Activity 2'!E14+'Activity 3'!E14 -> 1 | F14: =C14*D14*E14 -> 21333.333 | G14: =C14*1.05 -> 2800 | H14: ='Program Budget'!K16 -> 12 | I14: =Admin!I14+'Activity 1'!I14+'Activity 2'!I14+'Activity 3'!I14 -> 1 | J14: =G14*H14*I14 -> 33600 | K14: =G14*1.05 -> 2940 | L14: ='Program Budget'!N16 -> 12 | M14: =Admin!M14+'Activity 1'!M14+'Activity 2'!M14+'Activity 3'!M14 -> 1 | N14: =K14*L14*M14 -> 35280 | O14: =K14*1.05 -> 3087 | P14: ='Program Budget'!Q16 -> 12 | Q14: =Admin!Q14+'Activity 1'!Q14+'Activity 2'!Q14+'Activity 3'!Q14 -> 1 | R14: =O14*P14*Q14 -> 37044 | S14: =O14*1.05 -> 3241.35 | T14: ='Program Budget'!T16 -> 0 | U14: =Admin!U14+'Activity 1'!U14+'Activity 2'!U14+'Activity 3'!U14 -> 0 | V14: =S14*T14*U14 -> 0 | W14: =F14+J14+N14+R14+V14 -> 127257.33
A15: ='Program Budget'!D17 -> M&E Director | B15: ='Program Budget'!F17 -> Month | C15: ='Program Budget'!H17 -> 3500 | D15: ='Program Budget'!G17 -> 10 | E15: ='Program Budget'!E17+'Activity 1'!E15+'Activity 2'!E15+'Activity 3'!E15 -> 1 | F15: =C15*D15*E15 -> 35000 | G15: =C15*1.05 -> 3675 | H15: ='Program Budget'!K17 -> 12 | I15: =Admin!I15+'Activity 1'!I15+'Activity 2'!I15+'Activity 3'!I15 -> 1 | J15: =G15*H15*I15 -> 44100 | K15: =G15*1.05 -> 3858.75 | L15: ='Program Budget'!N17 -> 12 | M15: =Admin!M15+'Activity 1'!M15+'Activity 2'!M15+'Activity 3'!M15 -> 1 | N15: =K15*L15*M15 -> 46305 | O15: =K15*1.05 -> 4051.6875 | P15: ='Program Budget'!Q17 -> 12 | Q15: =Admin!Q15+'Activity 1'!Q15+'Activity 2'!Q15+'Activity 3'!Q15 -> 1 | R15: =O15*P15*Q15 -> 48620.25 | S15: =O15*1.05 -> 4254.2719 | T15: ='Program Budget'!T17 -> 0 | U15: =Admin!U15+'Activity 1'!U15+'Activity 2'!U15+'Activity 3'!U15 -> 0 | V15: =S15*T15*U15 -> 0 | W15: =F15+J15+N15+R15+V15 -> 174025.25
A16: ='Program Budget'!D18 -> M&E Specialist | B16: ='Program Budget'!F18 -> Month | C16: ='Program Budget'!H18 -> 2000 | D16: ='Program Budget'!G18 -> 8 | E16: ='Program Budget'!E18+'Activity 1'!E16+'Activity 2'!E16+'Activity 3'!E16 -> 1 | F16: =C16*D16*E16 -> 16000 | G16: =C16*1.05 -> 2100 | H16: ='Program Budget'!K18 -> 12 | I16: =Admin!I16+'Activity 1'!I16+'Activity 2'!I16+'Activity 3'!I16 -> 1 | J16: =G16*H16*I16 -> 25200 | K16: =G16*1.05 -> 2205 | L16: ='Program Budget'!N18 -> 12 | M16: =Admin!M16+'Activity 1'!M16+'Activity 2'!M16+'Activity 3'!M16 -> 1 | N16: =K16*L16*M16 -> 26460 | O16: =K16*1.05 -> 2315.25 | P16: ='Program Budget'!Q18 -> 12 | Q16: =Admin!Q16+'Activity 1'!Q16+'Activity 2'!Q16+'Activity 3'!Q16 -> 1 | R16: =O16*P16*Q16 -> 27783 | S16: =O16*1.05 -> 2431.0125 | T16: ='Program Budget'!T18 -> 0 | U16: =Admin!U16+'Activity 1'!U16+'Activity 2'!U16+'Activity 3'!U16 -> 0 | V16: =S16*T16*U16 -> 0 | W16: =F16+J16+N16+R16+V16 -> 95443
A17: ='Program Budget'!D19 -> Key Personnel: Finance & Administration (F&A) Director | B17: ='Program Budget'!F19 -> Month | C17: ='Program Budget'!H19 -> 3500 | D17: ='Program Budget'!G19 -> 10 | E17: ='Program Budget'!E19+'Activity 1'!E17+'Activity 2'!E17+'Activity 3'!E17 -> 1 | F17: =C17*D17*E17 -> 35000 | G17: =C17*1.05 -> 3675 | H17: ='Program Budget'!K19 -> 12 | I17: =Admin!I17+'Activity 1'!I17+'Activity 2'!I17+'Activity 3'!I17 -> 1 | J17: =G17*H17*I17 -> 44100 | K17: =G17*1.05 -> 3858.75 | L17: ='Program Budget'!N19 -> 12 | M17: =Admin!M17+'Activity 1'!M17+'Activity 2'!M17+'Activity 3'!M17 -> 1 | N17: =K17*L17*M17 -> 46305 | O17: =K17*1.05 -> 4051.6875 | P17: ='Program Budget'!Q19 -> 12 | Q17: =Admin!Q17+'Activity 1'!Q17+'Activity 2'!Q17+'Activity 3'!Q17 -> 1 | R17: =O17*P17*Q17 -> 48620.25 | S17: =O17*1.05 -> 4254.2719 | T17: ='Program Budget'!T19 -> 0 | U17: =Admin!U17+'Activity 1'!U17+'Activity 2'!U17+'Activity 3'!U17 -> 0 | V17: =S17*T17*U17 -> 0 | W17: =F17+J17+N17+R17+V17 -> 174025.25
A18: ='Program Budget'!D20 -> Accountant | B18: ='Program Budget'!F20 -> Month | C18: ='Program Budget'!H20 -> 2000 | D18: ='Program Budget'!G20 -> 8 | E18: ='Program Budget'!E20+'Activity 1'!E18+'Activity 2'!E18+'Activity 3'!E18 -> 1 | F18: =C18*D18*E18 -> 16000 | G18: =C18*1.05 -> 2100 | H18: ='Program Budget'!K20 -> 12 | I18: =Admin!I18+'Activity 1'!I18+'Activity 2'!I18+'Activity 3'!I18 -> 1 | J18: =G18*H18*I18 -> 25200 | K18: =G18*1.05 -> 2205 | L18: ='Program Budget'!N20 -> 12 | M18: =Admin!M18+'Activity 1'!M18+'Activity 2'!M18+'Activity 3'!M18 -> 1 | N18: =K18*L18*M18 -> 26460 | O18: =K18*1.05 -> 2315.25 | P18: ='Program Budget'!Q20 -> 12 | Q18: =Admin!Q18+'Activity 1'!Q18+'Activity 2'!Q18+'Activity 3'!Q18 -> 1 | R18: =O18*P18*Q18 -> 27783 | S18: =O18*1.05 -> 2431.0125 | T18: ='Program Budget'!T20 -> 0 | U18: =Admin!U18+'Activity 1'!U18+'Activity 2'!U18+'Activity 3'!U18 -> 0 | V18: =S18*T18*U18 -> 0 | W18: =F18+J18+N18+R18+V18 -> 95443
A19: ='Program Budget'!D21 -> Administration/ HR Manager | B19: ='Program Budget'!F21 -> Month | C19: ='Program Budget'!H21 -> 2666.6667 | D19: ='Program Budget'!G21 -> 10 | E19: ='Program Budget'!E21+'Activity 1'!E19+'Activity 2'!E19+'Activity 3'!E19 -> 1 | F19: =C19*D19*E19 -> 26666.667 | G19: =C19*1.05 -> 2800 | H19: ='Program Budget'!K21 -> 12 | I19: =Admin!I19+'Activity 1'!I19+'Activity 2'!I19+'Activity 3'!I19 -> 1 | J19: =G19*H19*I19 -> 33600 | K19: =G19*1.05 -> 2940 | L19: ='Program Budget'!N21 -> 12 | M19: =Admin!M19+'Activity 1'!M19+'Activity 2'!M19+'Activity 3'!M19 -> 1 | N19: =K19*L19*M19 -> 35280 | O19: =K19*1.05 -> 3087 | P19: ='Program Budget'!Q21 -> 12 | Q19: =Admin!Q19+'Activity 1'!Q19+'Activity 2'!Q19+'Activity 3'!Q19 -> 1 | R19: =O19*P19*Q19 -> 37044 | S19: =O19*1.05 -> 3241.35 | T19: ='Program Budget'!T21 -> 0 | U19: =Admin!U19+'Activity 1'!U19+'Activity 2'!U19+'Activity 3'!U19 -> 0 | V19: =S19*T19*U19 -> 0 | W19: =F19+J19+N19+R19+V19 -> 132590.67
A20: ='Program Budget'!D22 -> Grants & Contracts Manager | B20: ='Program Budget'!F22 -> Month | C20: ='Program Budget'!H22 -> 2666.6667 | D20: ='Program Budget'!G22 -> 9 | E20: ='Program Budget'!E22+'Activity 1'!E20+'Activity 2'!E20+'Activity 3'!E20 -> 1 | F20: =C20*D20*E20 -> 24000 | G20: =C20*1.05 -> 2800 | H20: ='Program Budget'!K22 -> 12 | I20: =Admin!I20+'Activity 1'!I20+'Activity 2'!I20+'Activity 3'!I20 -> 1 | J20: =G20*H20*I20 -> 33600 | K20: =G20*1.05 -> 2940 | L20: ='Program Budget'!N22 -> 12 | M20: =Admin!M20+'Activity 1'!M20+'Activity 2'!M20+'Activity 3'!M20 -> 1 | N20: =K20*L20*M20 -> 35280 | O20: =K20*1.05 -> 3087 | P20: ='Program Budget'!Q22 -> 12 | Q20: =Admin!Q20+'Activity 1'!Q20+'Activity 2'!Q20+'Activity 3'!Q20 -> 1 | R20: =O20*P20*Q20 -> 37044 | S20: =O20*1.05 -> 3241.35 | T20: ='Program Budget'!T22 -> 0 | U20: =Admin!U20+'Activity 1'!U20+'Activity 2'!U20+'Activity 3'!U20 -> 0 | V20: =S20*T20*U20 -> 0 | W20: =F20+J20+N20+R20+V20 -> 129924
A21: ='Program Budget'!D23 -> Compliance & Procurement Specialist | B21: ='Program Budget'!F23 -> Month | C21: ='Program Budget'!H23 -> 2000 | D21: ='Program Budget'!G23 -> 9 | E21: ='Program Budget'!E23+'Activity 1'!E21+'Activity 2'!E21+'Activity 3'!E21 -> 1 | F21: =C21*D21*E21 -> 18000 | G21: =C21*1.05 -> 2100 | H21: ='Program Budget'!K23 -> 12 | I21: =Admin!I21+'Activity 1'!I21+'Activity 2'!I21+'Activity 3'!I21 -> 1 | J21: =G21*H21*I21 -> 25200 | K21: =G21*1.05 -> 2205 | L21: ='Program Budget'!N23 -> 12 | M21: =Admin!M21+'Activity 1'!M21+'Activity 2'!M21+'Activity 3'!M21 -> 1 | N21: =K21*L21*M21 -> 26460 | O21: =K21*1.05 -> 2315.25 | P21: ='Program Budget'!Q23 -> 12 | Q21: =Admin!Q21+'Activity 1'!Q21+'Activity 2'!Q21+'Activity 3'!Q21 -> 1 | R21: =O21*P21*Q21 -> 27783 | S21: =O21*1.05 -> 2431.0125 | T21: ='Program Budget'!T23 -> 0 | U21: =Admin!U21+'Activity 1'!U21+'Activity 2'!U21+'Activity 3'!U21 -> 0 | V21: =S21*T21*U21 -> 0 | W21: =F21+J21+N21+R21+V21 -> 97443
A22: ='Program Budget'!D24 -> Driver | B22: ='Program Budget'!F24 -> Month | C22: ='Program Budget'!H24 -> 500 | D22: ='Program Budget'!G24 -> 7 | E22: ='Program Budget'!E24+'Activity 1'!E22+'Activity 2'!E22+'Activity 3'!E22 -> 1 | F22: =C22*D22*E22 -> 3500 | G22: =C22*1.05 -> 525 | H22: ='Program Budget'!K24 -> 12 | I22: =Admin!I22+'Activity 1'!I22+'Activity 2'!I22+'Activity 3'!I22 -> 1 | J22: =G22*H22*I22 -> 6300 | K22: =G22*1.05 -> 551.25 | L22: ='Program Budget'!N24 -> 12 | M22: =Admin!M22+'Activity 1'!M22+'Activity 2'!M22+'Activity 3'!M22 -> 1 | N22: =K22*L22*M22 -> 6615 | O22: =K22*1.05 -> 578.8125 | P22: ='Program Budget'!Q24 -> 12 | Q22: =Admin!Q22+'Activity 1'!Q22+'Activity 2'!Q22+'Activity 3'!Q22 -> 1 | R22: =O22*P22*Q22 -> 6945.75 | S22: =O22*1.05 -> 607.75313 | T22: ='Program Budget'!T24 -> 0 | U22: =Admin!U22+'Activity 1'!U22+'Activity 2'!U22+'Activity 3'!U22 -> 0 | V22: =S22*T22*U22 -> 0 | W22: =F22+J22+N22+R22+V22 -> 23360.75
A23: Total Local Salary Cost | F23: =SUM(F10:F22) -> 377750 | J23: =SUM(J10:J22) -> 507150 | N23: =SUM(N10:N22) -> 532507.5 | R23: =SUM(R10:R22) -> 559132.88 | V23: =SUM(V10:V22) -> 0 | W23: =SUM(W10:W22) -> 1976540.4 | Y23: =Admin!W23+'Activity 1'!W23+'Activity 2'!W23+'Activity 3'!W23 -> 1976540.4
A24: HQ Staff
A25: ='Program Budget'!D26 -> Senior Vice President of Programs | B25: ='Program Budget'!F26 -> Month | C25: ='Program Budget'!H26 -> 13500 | D25: ='Program Budget'!G26 -> 12 | E25: =Admin!E25+'Activity 1'!E25+'Activity 2'!E25+'Activity 3'!E25 -> 0.05 | F25: =C25*D25*E25 -> 8100 | G25: =C25*1.05 -> 14175 | H25: ='Program Budget'!K26 -> 12 | I25: =Admin!I25+'Activity 1'!I25+'Activity 2'!I25+'Activity 3'!I25 -> 0.05 | J25: =G25*H25*I25 -> 8505 | K25: =G25*1.05 -> 14883.75 | L25: ='Program Budget'!N26 -> 12 | M25: =Admin!M25+'Activity 1'!M25+'Activity 2'!M25+'Activity 3'!M25 -> 0.05 | N25: =K25*L25*M25 -> 8930.25 | O25: =K25*1.05 -> 15627.938 | P25: ='Program Budget'!Q26 -> 12 | Q25: =Admin!Q25+'Activity 1'!Q25+'Activity 2'!Q25+'Activity 3'!Q25 -> 0.05 | R25: =O25*P25*Q25 -> 9376.7625 | S25: =O25*1.05 -> 16409.334 | T25: ='Program Budget'!T26 -> 0 | U25: =Admin!U25+'Activity 1'!U25+'Activity 2'!U25+'Activity 3'!U25 -> 0 | V25: =S25*T25*U25 -> 0 | W25: =F25+J25+N25+R25+V25 -> 34912.012
A26: ='Program Budget'!D27 -> Senior Program Director | B26: ='Program Budget'!F27 -> Month | C26: ='Program Budget'!H27 -> 12500 | D26: ='Program Budget'!G27 -> 12 | E26: =Admin!E26+'Activity 1'!E26+'Activity 2'!E26+'Activity 3'!E26 -> 0.25 | F26: =C26*D26*E26 -> 37500 | G26: =C26*1.05 -> 13125 | H26: ='Program Budget'!K27 -> 12 | I26: =Admin!I26+'Activity 1'!I26+'Activity 2'!I26+'Activity 3'!I26 -> 0.25 | J26: =G26*H26*I26 -> 39375 | K26: =G26*1.05 -> 13781.25 | L26: ='Program Budget'!N27 -> 12 | M26: =Admin!M26+'Activity 1'!M26+'Activity 2'!M26+'Activity 3'!M26 -> 0.25 | N26: =K26*L26*M26 -> 41343.75 | O26: =K26*1.05 -> 14470.312 | P26: ='Program Budget'!Q27 -> 12 | Q26: =Admin!Q26+'Activity 1'!Q26+'Activity 2'!Q26+'Activity 3'!Q26 -> 0.25 | R26: =O26*P26*Q26 -> 43410.938 | S26: =O26*1.05 -> 15193.828 | T26: ='Program Budget'!T27 -> 0 | U26: =Admin!U26+'Activity 1'!U26+'Activity 2'!U26+'Activity 3'!U26 -> 0 | V26: =S26*T26*U26 -> 0 | W26: =F26+J26+N26+R26+V26 -> 161629.69
A27: ='Program Budget'!D28 -> Associate Director | B27: ='Program Budget'!F28 -> Month | C27: ='Program Budget'!H28 -> 7500 | D27: ='Program Budget'!G28 -> 12 | E27: =Admin!E27+'Activity 1'!E27+'Activity 2'!E27+'Activity 3'!E27 -> 1 | F27: =C27*D27*E27 -> 90000 | G27: =C27*1.05 -> 7875 | H27: ='Program Budget'!K28 -> 12 | I27: =Admin!I27+'Activity 1'!I27+'Activity 2'!I27+'Activity 3'!I27 -> 1 | J27: =G27*H27*I27 -> 94500 | K27: =G27*1.05 -> 8268.75 | L27: ='Program Budget'!N28 -> 12 | M27: =Admin!M27+'Activity 1'!M27+'Activity 2'!M27+'Activity 3'!M27 -> 1 | N27: =K27*L27*M27 -> 99225 | O27: =K27*1.05 -> 8682.1875 | P27: ='Program Budget'!Q28 -> 12 | Q27: =Admin!Q27+'Activity 1'!Q27+'Activity 2'!Q27+'Activity 3'!Q27 -> 1 | R27: =O27*P27*Q27 -> 104186.25 | S27: =O27*1.05 -> 9116.2969 | T27: ='Program Budget'!T28 -> 0 | U27: =Admin!U27+'Activity 1'!U27+'Activity 2'!U27+'Activity 3'!U27 -> 0 | V27: =S27*T27*U27 -> 0 | W27: =F27+J27+N27+R27+V27 -> 387911.25
A28: ='Program Budget'!D29 -> Compliance & Contracts Director | B28: ='Program Budget'!F29 -> Month | C28: ='Program Budget'!H29 -> 9166.6667 | D28: ='Program Budget'!G29 -> 12 | E28: =Admin!E28+'Activity 1'!E28+'Activity 2'!E28+'Activity 3'!E28 -> 0.25 | F28: =C28*D28*E28 -> 27500 | G28: =C28*1.05 -> 9625 | H28: ='Program Budget'!K29 -> 12 | I28: =Admin!I28+'Activity 1'!I28+'Activity 2'!I28+'Activity 3'!I28 -> 0.25 | J28: =G28*H28*I28 -> 28875 | K28: =G28*1.05 -> 10106.25 | L28: ='Program Budget'!N29 -> 12 | M28: =Admin!M28+'Activity 1'!M28+'Activity 2'!M28+'Activity 3'!M28 -> 0.25 | N28: =K28*L28*M28 -> 30318.75 | O28: =K28*1.05 -> 10611.562 | P28: ='Program Budget'!Q29 -> 12 | Q28: =Admin!Q28+'Activity 1'!Q28+'Activity 2'!Q28+'Activity 3'!Q28 -> 0.25 | R28: =O28*P28*Q28 -> 31834.688 | S28: =O28*1.05 -> 11142.141 | T28: ='Program Budget'!T29 -> 0 | U28: =Admin!U28+'Activity 1'!U28+'Activity 2'!U28+'Activity 3'!U28 -> 0 | V28: =S28*T28*U28 -> 0 | W28: =F28+J28+N28+R28+V28 -> 118528.44 | Y28: =W28+W29 -> 390066.31
A29: ='Program Budget'!D30 -> Finance, HR, & Administration Home Office Support | B29: ='Program Budget'!F30 -> Month | C29: ='Program Budget'!H30 -> 7500 | D29: ='Program Budget'!G30 -> 12 | E29: =Admin!E29+'Activity 1'!E29+'Activity 2'!E29+'Activity 3'!E29 -> 0.7 | F29: =C29*D29*E29 -> 63000 | G29: =C29*1.05 -> 7875 | H29: ='Program Budget'!K30 -> 12 | I29: =Admin!I29+'Activity 1'!I29+'Activity 2'!I29+'Activity 3'!I29 -> 0.7 | J29: =G29*H29*I29 -> 66150 | K29: =G29*1.05 -> 8268.75 | L29: ='Program Budget'!N30 -> 12 | M29: =Admin!M29+'Activity 1'!M29+'Activity 2'!M29+'Activity 3'!M29 -> 0.7 | N29: =K29*L29*M29 -> 69457.5 | O29: =K29*1.05 -> 8682.1875 | P29: ='Program Budget'!Q30 -> 12 | Q29: =Admin!Q29+'Activity 1'!Q29+'Activity 2'!Q29+'Activity 3'!Q29 -> 0.7 | R29: =O29*P29*Q29 -> 72930.375 | S29: =O29*1.05 -> 9116.2969 | T29: ='Program Budget'!T30 -> 0 | U29: =Admin!U29+'Activity 1'!U29+'Activity 2'!U29+'Activity 3'!U29 -> 0 | V29: =S29*T29*U29 -> 0 | W29: =F29+J29+N29+R29+V29 -> 271537.88
A30: Total HQ Staff | F30: =SUM(F24:F29) -> 226100 | J30: =SUM(J24:J29) -> 237405 | N30: =SUM(N24:N29) -> 249275.25 | R30: =SUM(R24:R29) -> 261739.01 | V30: =SUM(V24:V29) -> 0 | W30: =SUM(W24:W29) -> 974519.26 | Y30: =Admin!W30+'Activity 1'!W30+'Activity 2'!W30+'Activity 3'!W30 -> 974519.26
A32: Subtotal: Salaries & Wages | F32: =F30+F23+F8 -> 603850 | J32: =J30+J23+J8 -> 744555 | N32: =N30+N23+N8 -> 781782.75 | R32: =R30+R23+R8 -> 820871.89 | V32: =V30+V23+V8 -> 0 | W32: =+F32+J32+N32+R32+V32 -> 2951059.6
A33: Fringe
A34: USN/TCN Staff | B34: ='Program Budget'!F36 -> % | C34: =F8 -> 0 | D34: 1 | E34: 0 | F34: =C34*D34*E34 -> 0 | G34: =J8 -> 0 | H34: 1 | I34: =E34 -> 0 | J34: =G34*H34*I34 -> 0 | K34: =N8 -> 0 | L34: 1 | M34: =I34 -> 0 | N34: =K34*L34*M34 -> 0 | O34: =R8 -> 0 | P34: 1 | Q34: =M34 -> 0 | R34: =O34*P34*Q34 -> 0 | S34: =V8 -> 0 | T34: 1 | U34: 0 | V34: =S34*T34*U34 -> 0 | W34: =F34+J34+N34+R34+V34 -> 0
A35: ='Program Budget'!D35 -> Fringe Benefits CCN - Nigeria | B35: ='Program Budget'!F35 -> % | C35: =F23 -> 377750 | D35: 1 | E35: ='Program Budget'!H35 -> 0.296 | F35: =C35*D35*E35 -> 111814 | G35: =J23 -> 507150 | H35: 1 | I35: =E35 -> 0.296 | J35: =G35*H35*I35 -> 150116.4 | K35: =N23 -> 532507.5 | L35: 1 | M35: =E35 -> 0.296 | N35: =K35*L35*M35 -> 157622.22 | O35: =R23 -> 559132.88 | P35: 1 | Q35: =E35 -> 0.296 | R35: =O35*P35*Q35 -> 165503.33 | S35: =V23 -> 0 | T35: 1 | U35: 0 | V35: =S35*T35*U35 -> 0 | W35: =F35+J35+N35+R35+V35 -> 585055.95
A36: HQ Staff | B36: ='Program Budget'!F36 -> % | C36: =F30 -> 226100 | D36: 1 | E36: ='Program Budget'!H36 -> 0.2347 | F36: =C36*D36*E36 -> 53065.67 | G36: =J30 -> 237405 | H36: 1 | I36: =E36 -> 0.2347 | J36: =G36*H36*I36 -> 55718.953 | K36: =N30 -> 249275.25 | L36: 1 | M36: =I36 -> 0.2347 | N36: =K36*L36*M36 -> 58504.901 | O36: =R30 -> 261739.01 | P36: 1 | Q36: =M36 -> 0.2347 | R36: =O36*P36*Q36 -> 61430.146 | S36: =V30 -> 0 | T36: 1 | U36: 0 | V36: =S36*T36*U36 -> 0 | W36: =F36+J36+N36+R36+V36 -> 228719.67
A37: Total: Fringe Benefits | F37: =+SUM(F34:F36) -> 164879.67 | J37: =+SUM(J34:J36) -> 205835.35 | N37: =+SUM(N34:N36) -> 216127.12 | R37: =+SUM(R34:R36) -> 226933.48 | V37: =+SUM(V34:V36) -> 0 | W37: =+F37+J37+N37+R37+V37 -> 813775.62
A38: Allowances
A39: None | F39: =C39*D39*E39 -> 0 | J39: =G39*H39*I39 -> 0 | N39: =K39*L39*M39 -> 0 | R39: =O39*P39*Q39 -> 0 | V39: =S39*T39*U39 -> 0 | W39: =F39+J39+N39+R39+V39 -> 0
A40: Total: Allowances | F40: =SUM(F39:F39) -> 0 | J40: =SUM(J39:J39) -> 0 | N40: =SUM(N39:N39) -> 0 | R40: =SUM(R39:R39) -> 0 | V40: =SUM(V39:V39) -> 0 | W40: =SUM(W39:W39) -> 0
A42: Subtotal: Benefits | F42: =F40+F37 -> 164879.67 | J42: =J40+J37 -> 205835.35 | N42: =N40+N37 -> 216127.12 | R42: =R40+R37 -> 226933.48 | V42: =V40+V37 -> 0 | W42: =+F42+J42+N42+R42+V42 -> 813775.62
A43: International Travel
A44: ='Program Budget'!D42 -> Airfare - DC-Nigeria - HO Project Management Trip | B44: ='Program Budget'!F42 -> Trip | C44: ='Program Budget'!H42 -> 1800 | D44: ='Program Budget'!G42 -> 3 | E44: 1 | F44: =C44*D44*E44 -> 5400 | G44: =C44*1.05 -> 1890 | H44: ='Program Budget'!K42 -> 2 | I44: 1 | J44: =G44*H44*I44 -> 3780 | K44: =G44*1.05 -> 1984.5 | L44: ='Program Budget'!N42 -> 2 | M44: 1 | N44: =K44*L44*M44 -> 3969 | O44: =K44*1.05 -> 2083.725 | P44: ='Program Budget'!Q42 -> 2 | Q44: 1 | R44: =O44*P44*Q44 -> 4167.45 | S44: =O44*1.05 -> 2187.9113 | T44: ='Program Budget'!T42 -> 0 | U44: 0 | V44: =S44*T44*U44 -> 0 | W44: =F44+J44+N44+R44+V44 -> 17316.45
A45: ='Program Budget'!D48 -> Airfare - Roundtrip - Nigeria to USA | B45: ='Program Budget'!F48 -> Trip | C45: ='Program Budget'!H48 -> 1800 | D45: ='Program Budget'!G48 -> 3 | E45: 1 | F45: =C45*D45*E45 -> 5400 | G45: =C45*1.05 -> 1890 | H45: ='Program Budget'!K48 -> 3 | I45: 1 | J45: =G45*H45*I45 -> 5670 | K45: =G45*1.05 -> 1984.5 | L45: ='Program Budget'!N48 -> 3 | M45: 1 | N45: =K45*L45*M45 -> 5953.5 | O45: =K45*1.05 -> 2083.725 | P45: ='Program Budget'!Q48 -> 3 | Q45: 1 | R45: =O45*P45*Q45 -> 6251.175 | S45: =O45*1.05 -> 2187.9113 | T45: ='Program Budget'!T48 -> 0 | U45: 0 | V45: =S45*T45*U45 -> 0 | W45: =F45+J45+N45+R45+V45 -> 23274.675
A46: ='Program Budget'!D230 -> Airfare - Roundtrip - USA to Nigeria - Buyer Conferences for American Farmers, Ranchers and Agricultural Professionals - 50% of Cost | B46: ='Program Budget'!F230 -> Trip | C46: ='Program Budget'!H230 -> 900 | D46: ='Program Budget'!G230 -> 0 | E46: 1 | F46: =C46*D46*E46 -> 0 | G46: =C46*1.05 -> 945 | H46: ='Program Budget'!K230 -> 10 | I46: 1 | J46: =G46*H46*I46 -> 9450 | K46: =G46*1.05 -> 992.25 | L46: ='Program Budget'!N230 -> 10 | M46: 1 | N46: =K46*L46*M46 -> 9922.5 | O46: =K46*1.05 -> 1041.8625 | P46: ='Program Budget'!Q230 -> 0 | Q46: 1 | R46: =O46*P46*Q46 -> 0 | S46: =O46*1.05 -> 1093.9556 | T46: ='Program Budget'!T230 -> 0 | U46: 0 | V46: =S46*T46*U46 -> 0 | W46: =F46+J46+N46+R46+V46 -> 19372.5
A47: ='Program Budget'!D232 -> Airfare - Roundtrip - USA to Nigeria - Trade Finance & Export Consultant | B47: ='Program Budget'!F232 -> Trip | C47: ='Program Budget'!H232 -> 1800 | D47: ='Program Budget'!G232 -> 1 | E47: 1 | F47: =C47*D47*E47 -> 1800 | G47: =C47*1.05 -> 1890 | H47: ='Program Budget'!K232 -> 2 | I47: 1 | J47: =G47*H47*I47 -> 3780 | K47: =G47*1.05 -> 1984.5 | L47: ='Program Budget'!N232 -> 2 | M47: 1 | N47: =K47*L47*M47 -> 3969 | O47: =K47*1.05 -> 2083.725 | P47: ='Program Budget'!Q232 -> 1 | Q47: 1 | R47: =O47*P47*Q47 -> 2083.725 | S47: =O47*1.05 -> 2187.9113 | T47: ='Program Budget'!T232 -> 0 | U47: 0 | V47: =S47*T47*U47 -> 0 | W47: =F47+J47+N47+R47+V47 -> 11632.725
A48: Local Travel
A49: ='Program Budget'!D44 -> Ground Transportation – HO Project Management Trip | B49: ='Program Budget'!F44 -> Trip | C49: ='Program Budget'!H44 -> 150 | D49: ='Program Budget'!G44 -> 3 | E49: 1 | F49: =C49*D49*E49 -> 450 | G49: =C49*1.05 -> 157.5 | H49: ='Program Budget'!K44 -> 2 | I49: 1 | J49: =G49*H49*I49 -> 315 | K49: =G49*1.05 -> 165.375 | L49: ='Program Budget'!N44 -> 2 | M49: 1 | N49: =K49*L49*M49 -> 330.75 | O49: =K49*1.05 -> 173.64375 | P49: ='Program Budget'!Q44 -> 2 | Q49: 1 | R49: =O49*P49*Q49 -> 347.2875 | S49: =O49*1.05 -> 182.32594 | T49: ='Program Budget'!T44 -> 0 | U49: 0 | V49: =S49*T49*U49 -> 0 | W49: =F49+J49+N49+R49+V49 -> 1443.0375
A50: ='Program Budget'!D50 -> Ground Transportation for Nigeria Staff Travel | B50: ='Program Budget'!F50 -> Trip | C50: ='Program Budget'!H50 -> 250 | D50: ='Program Budget'!G50 -> 3 | E50: 1 | F50: =C50*D50*E50 -> 750 | G50: =C50*1.05 -> 262.5 | H50: ='Program Budget'!K50 -> 3 | I50: 1 | J50: =G50*H50*I50 -> 787.5 | K50: =G50*1.05 -> 275.625 | L50: ='Program Budget'!N50 -> 3 | M50: 1 | N50: =K50*L50*M50 -> 826.875 | O50: =K50*1.05 -> 289.40625 | P50: ='Program Budget'!Q50 -> 3 | Q50: 1 | R50: =O50*P50*Q50 -> 868.21875 | S50: =O50*1.05 -> 303.87656 | T50: ='Program Budget'!T50 -> 0 | U50: 0 | V50: =S50*T50*U50 -> 0 | W50: =F50+J50+N50+R50+V50 -> 3232.5938
A51: ='Program Budget'!D55 -> Roundtrip Domestic Airfare - Lagos to Implementing Regions – Training, M&E, & Data Collection | B51: ='Program Budget'!F55 -> Trip | C51: ='Program Budget'!H55 -> 250 | D51: ='Program Budget'!G55 -> 36 | E51: 1 | F51: =C51*D51*E51 -> 9000 | G51: =C51*1.05 -> 262.5 | H51: ='Program Budget'!K55 -> 36 | I51: 1 | J51: =G51*H51*I51 -> 9450 | K51: =G51*1.05 -> 275.625 | L51: ='Program Budget'!N55 -> 36 | M51: 1 | N51: =K51*L51*M51 -> 9922.5 | O51: =K51*1.05 -> 289.40625 | P51: ='Program Budget'!Q55 -> 36 | Q51: 1 | R51: =O51*P51*Q51 -> 10418.625 | S51: =O51*1.05 -> 303.87656 | T51: ='Program Budget'!T55 -> 0 | U51: 0 | V51: =S51*T51*U51 -> 0 | W51: =F51+J51+N51+R51+V51 -> 38791.125
A52: ='Program Budget'!D56 -> Local Transportation (Car Rental, Taxis) – Training, M&E, & Data Collection | B52: ='Program Budget'!F56 -> Trip | C52: ='Program Budget'!H56 -> 30 | D52: ='Program Budget'!G56 -> 36 | E52: 1 | F52: =C52*D52*E52 -> 1080 | G52: =C52*1.05 -> 31.5 | H52: ='Program Budget'!K56 -> 36 | I52: 1 | J52: =G52*H52*I52 -> 1134 | K52: =G52*1.05 -> 33.075 | L52: ='Program Budget'!N56 -> 36 | M52: 1 | N52: =K52*L52*M52 -> 1190.7 | O52: =K52*1.05 -> 34.72875 | P52: ='Program Budget'!Q56 -> 36 | Q52: 1 | R52: =O52*P52*Q52 -> 1250.235 | S52: =O52*1.05 -> 36.465188 | T52: ='Program Budget'!T56 -> 0 | U52: 0 | V52: =S52*T52*U52 -> 0 | W52: =F52+J52+N52+R52+V52 -> 4654.935
A53: ='Program Budget'!D168 -> Local Transportation (Taxis/Ubers) for Project Implementation | B53: ='Program Budget'!F168 -> Month | C53: ='Activity 1'!C46+'Activity 2'!C46+'Activity 3'!C44 -> 900 | D53: ='Program Budget'!G168 -> 6 | E53: 1 | F53: =C53*D53*E53 -> 5400 | G53: =C53*1.05 -> 945 | H53: ='Program Budget'!K168 -> 12 | I53: 1 | J53: =G53*H53*I53 -> 11340 | K53: =G53*1.05 -> 992.25 | L53: ='Program Budget'!N168 -> 12 | M53: 1 | N53: =K53*L53*M53 -> 11907 | O53: =K53*1.05 -> 1041.8625 | P53: ='Program Budget'!Q168 -> 12 | Q53: 1 | R53: =O53*P53*Q53 -> 12502.35 | S53: =O53*1.05 -> 1093.9556 | T53: ='Program Budget'!T168 -> 0 | U53: 0 | V53: =S53*T53*U53 -> 0 | W53: =F53+J53+N53+R53+V53 -> 41149.35
A54: ='Program Budget'!D169 -> Roundtrip Domestic Airfare - Lagos to Implementing Regions for Trainings on Activity 1 | B54: ='Program Budget'!F169 -> Trip | C54: ='Program Budget'!H169 -> 250 | D54: ='Program Budget'!G169 -> 12 | E54: 1 | F54: =C54*D54*E54 -> 3000 | G54: =C54*1.05 -> 262.5 | H54: ='Program Budget'!K169 -> 24 | I54: 1 | J54: =G54*H54*I54 -> 6300 | K54: =G54*1.05 -> 275.625 | L54: ='Program Budget'!N169 -> 24 | M54: 1 | N54: =K54*L54*M54 -> 6615 | O54: =K54*1.05 -> 289.40625 | P54: ='Program Budget'!Q169 -> 24 | Q54: 1 | R54: =O54*P54*Q54 -> 6945.75 | S54: =O54*1.05 -> 303.87656 | T54: ='Program Budget'!T169 -> 0 | U54: 0 | V54: =S54*T54*U54 -> 0 | W54: =F54+J54+N54+R54+V54 -> 22860.75
A55: ='Program Budget'!D170 -> Local Transportation (Car Rental, Taxis) for Trainings on Activity 1 | B55: ='Program Budget'!F170 -> Trip | C55: ='Program Budget'!H170 -> 30 | D55: ='Program Budget'!G170 -> 12 | E55: 1 | F55: =C55*D55*E55 -> 360 | G55: =C55*1.05 -> 31.5 | H55: ='Program Budget'!K170 -> 24 | I55: 1 | J55: =G55*H55*I55 -> 756 | K55: =G55*1.05 -> 33.075 | L55: ='Program Budget'!N170 -> 24 | M55: 1 | N55: =K55*L55*M55 -> 793.8 | O55: =K55*1.05 -> 34.72875 | P55: ='Program Budget'!Q170 -> 24 | Q55: 1 | R55: =O55*P55*Q55 -> 833.49 | S55: =O55*1.05 -> 36.465188 | T55: ='Program Budget'!T170 -> 0 | U55: 0 | V55: =S55*T55*U55 -> 0 | W55: =F55+J55+N55+R55+V55 -> 2743.29
A56: ='Program Budget'!D227 -> Roundtrip Domestic Airfare - Lagos to Implementing Regions for Trainings on Activity 2 | B56: ='Program Budget'!F227 -> Trip | C56: ='Program Budget'!H227 -> 250 | D56: ='Program Budget'!G227 -> 12 | E56: 1 | F56: =C56*D56*E56 -> 3000 | G56: =C56*1.05 -> 262.5 | H56: ='Program Budget'!K227 -> 24 | I56: 1 | J56: =G56*H56*I56 -> 6300 | K56: =G56*1.05 -> 275.625 | L56: ='Program Budget'!N227 -> 24 | M56: 1 | N56: =K56*L56*M56 -> 6615 | O56: =K56*1.05 -> 289.40625 | P56: ='Program Budget'!Q227 -> 24 | Q56: 1 | R56: =O56*P56*Q56 -> 6945.75 | S56: =O56*1.05 -> 303.87656 | T56: ='Program Budget'!T227 -> 0 | U56: 0 | V56: =S56*T56*U56 -> 0 | W56: =F56+J56+N56+R56+V56 -> 22860.75
A57: ='Program Budget'!D228 -> Local Transportation (Car Rental, Taxis) for Trainings on Activity 2 | B57: ='Program Budget'!F228 -> Trip | C57: ='Program Budget'!H228 -> 30 | D57: ='Program Budget'!G228 -> 12 | E57: 1 | F57: =C57*D57*E57 -> 360 | G57: =C57*1.05 -> 31.5 | H57: ='Program Budget'!K228 -> 24 | I57: 1 | J57: =G57*H57*I57 -> 756 | K57: =G57*1.05 -> 33.075 | L57: ='Program Budget'!N228 -> 24 | M57: 1 | N57: =K57*L57*M57 -> 793.8 | O57: =K57*1.05 -> 34.72875 | P57: ='Program Budget'!Q228 -> 24 | Q57: 1 | R57: =O57*P57*Q57 -> 833.49 | S57: =O57*1.05 -> 36.465188 | T57: ='Program Budget'!T228 -> 0 | U57: 0 | V57: =S57*T57*U57 -> 0 | W57: =F57+J57+N57+R57+V57 -> 2743.29
A58: ='Program Budget'!D234 -> Ground Transportation – Trade Finance & Export Consultant | B58: ='Program Budget'!F234 -> Trip | C58: ='Program Budget'!H234 -> 150 | D58: ='Program Budget'!G234 -> 1 | E58: 1 | F58: =C58*D58*E58 -> 150 | G58: =C58*1.05 -> 157.5 | H58: ='Program Budget'!K234 -> 2 | I58: 1 | J58: =G58*H58*I58 -> 315 | K58: =G58*1.05 -> 165.375 | L58: ='Program Budget'!N234 -> 2 | M58: 1 | N58: =K58*L58*M58 -> 330.75 | O58: =K58*1.05 -> 173.64375 | P58: ='Program Budget'!Q234 -> 1 | Q58: 1 | R58: =O58*P58*Q58 -> 173.64375 | S58: =O58*1.05 -> 182.32594 | T58: ='Program Budget'!T234 -> 0 | U58: 0 | V58: =S58*T58*U58 -> 0 | W58: =F58+J58+N58+R58+V58 -> 969.39375
A59: ='Program Budget'!D305 -> Roundtrip Domestic Airfare - Lagos to Implementing Regions for Trainings on Activity 3 | B59: ='Program Budget'!F305 -> Trip | C59: ='Program Budget'!H305 -> 250 | D59: ='Program Budget'!G305 -> 6 | E59: 1 | F59: =C59*D59*E59 -> 1500 | G59: =C59*1.05 -> 262.5 | H59: ='Program Budget'!K305 -> 12 | I59: 1 | J59: =G59*H59*I59 -> 3150 | K59: =G59*1.05 -> 275.625 | L59: ='Program Budget'!N305 -> 12 | M59: 1 | N59: =K59*L59*M59 -> 3307.5 | O59: =K59*1.05 -> 289.40625 | P59: ='Program Budget'!Q305 -> 12 | Q59: 1 | R59: =O59*P59*Q59 -> 3472.875 | S59: =O59*1.05 -> 303.87656 | T59: ='Program Budget'!T305 -> 0 | U59: 0 | V59: =S59*T59*U59 -> 0 | W59: =F59+J59+N59+R59+V59 -> 11430.375
A60: ='Program Budget'!D306 -> Local Transportation (Car Rental, Taxis) for Trainings on Activity 3 | B60: ='Program Budget'!F306 -> Trip | C60: ='Program Budget'!H306 -> 30 | D60: ='Program Budget'!G306 -> 6 | E60: 1 | F60: =C60*D60*E60 -> 180 | G60: =C60*1.05 -> 31.5 | H60: ='Program Budget'!K306 -> 12 | I60: 1 | J60: =G60*H60*I60 -> 378 | K60: =G60*1.05 -> 33.075 | L60: ='Program Budget'!N306 -> 12 | M60: 1 | N60: =K60*L60*M60 -> 396.9 | O60: =K60*1.05 -> 34.72875 | P60: ='Program Budget'!Q306 -> 12 | Q60: 1 | R60: =O60*P60*Q60 -> 416.745 | S60: =O60*1.05 -> 36.465188 | T60: ='Program Budget'!T306 -> 0 | U60: 0 | V60: =S60*T60*U60 -> 0 | W60: =F60+J60+N60+R60+V60 -> 1371.645
A61: Vehicle Fuel
A62: ='Program Budget'!D54 -> Vehicle Fuel Expense (for Field Office Vehicles) | B62: ='Program Budget'!F54 -> Month | C62: ='Program Budget'!H54+'Program Budget'!H167+'Program Budget'!H225+'Program Budget'!H303 -> 230 | D62: ='Program Budget'!G54 -> 3 | E62: 1 | F62: =C62*D62*E62 -> 690 | G62: =C62*1.05 -> 241.5 | H62: ='Program Budget'!K54 -> 12 | I62: 1 | J62: =G62*H62*I62 -> 2898 | K62: =G62*1.05 -> 253.575 | L62: ='Program Budget'!N54 -> 12 | M62: 1 | N62: =K62*L62*M62 -> 3042.9 | O62: =K62*1.05 -> 266.25375 | P62: ='Program Budget'!Q54 -> 12 | Q62: 1 | R62: =O62*P62*Q62 -> 3195.045 | S62: =O62*1.05 -> 279.56644 | T62: ='Program Budget'!T54 -> 0 | U62: 0 | V62: =S62*T62*U62 -> 0 | W62: =F62+J62+N62+R62+V62 -> 9825.945
A63: Per Diem & Lodging
A64: ='Program Budget'!D43 -> Lodging and M&IE - HO Project Management Trip | B64: ='Program Budget'!F43 -> Day | C64: ='Program Budget'!H43 -> 310.5 | D64: ='Program Budget'!G43 -> 30 | E64: 1 | F64: =C64*D64*E64 -> 9315 | G64: =C64*1.05 -> 326.025 | H64: ='Program Budget'!K43 -> 20 | I64: 1 | J64: =G64*H64*I64 -> 6520.5 | K64: =G64*1.05 -> 342.32625 | L64: ='Program Budget'!N43 -> 20 | M64: 1 | N64: =K64*L64*M64 -> 6846.525 | O64: =K64*1.05 -> 359.44256 | P64: ='Program Budget'!Q43 -> 20 | Q64: 1 | R64: =O64*P64*Q64 -> 7188.8513 | S64: =O64*1.05 -> 377.41469 | T64: ='Program Budget'!T43 -> 0 | U64: 0 | V64: =S64*T64*U64 -> 0 | W64: =F64+J64+N64+R64+V64 -> 29870.876
A65: ='Program Budget'!D45 -> Other Travel Related Expenses – HO Project Management Trip | B65: ='Program Budget'!F45 -> Trip | C65: ='Program Budget'!H45 -> 150 | D65: ='Program Budget'!G45 -> 3 | E65: 1 | F65: =C65*D65*E65 -> 450 | G65: =C65*1.05 -> 157.5 | H65: ='Program Budget'!K45 -> 2 | I65: 1 | J65: =G65*H65*I65 -> 315 | K65: =G65*1.05 -> 165.375 | L65: ='Program Budget'!N45 -> 2 | M65: 1 | N65: =K65*L65*M65 -> 330.75 | O65: =K65*1.05 -> 173.64375 | P65: ='Program Budget'!Q45 -> 2 | Q65: 1 | R65: =O65*P65*Q65 -> 347.2875 | S65: =O65*1.05 -> 182.32594 | T65: ='Program Budget'!T45 -> 0 | U65: 0 | V65: =S65*T65*U65 -> 0 | W65: =F65+J65+N65+R65+V65 -> 1443.0375
A66: ='Program Budget'!D46 -> Visa Cost for US Staff Travel | B66: ='Program Budget'!F46 -> Trip | C66: ='Program Budget'!H46 -> 160 | D66: ='Program Budget'!G46 -> 3 | E66: 1 | F66: =C66*D66*E66 -> 480 | G66: =C66*1.05 -> 168 | H66: ='Program Budget'!K46 -> 2 | I66: 1 | J66: =G66*H66*I66 -> 336 | K66: =G66*1.05 -> 176.4 | L66: ='Program Budget'!N46 -> 2 | M66: 1 | N66: =K66*L66*M66 -> 352.8 | O66: =K66*1.05 -> 185.22 | P66: ='Program Budget'!Q46 -> 2 | Q66: 1 | R66: =O66*P66*Q66 -> 370.44 | S66: =O66*1.05 -> 194.481 | T66: ='Program Budget'!T46 -> 0 | U66: 0 | V66: =S66*T66*U66 -> 0 | W66: =F66+J66+N66+R66+V66 -> 1539.24
A67: ='Program Budget'!D49 -> Lodging and M&IE for Nigeria Staff Travel | B67: ='Program Budget'!F49 -> Day | C67: ='Program Budget'!H49 -> 262.8 | D67: ='Program Budget'!G49 -> 21 | E67: 1 | F67: =C67*D67*E67 -> 5518.8 | G67: =C67*1.05 -> 275.94 | H67: ='Program Budget'!K49 -> 21 | I67: 1 | J67: =G67*H67*I67 -> 5794.74 | K67: =G67*1.05 -> 289.737 | L67: ='Program Budget'!N49 -> 21 | M67: 1 | N67: =K67*L67*M67 -> 6084.477 | O67: =K67*1.05 -> 304.22385 | P67: ='Program Budget'!Q49 -> 21 | Q67: 1 | R67: =O67*P67*Q67 -> 6388.7009 | S67: =O67*1.05 -> 319.43504 | T67: ='Program Budget'!T49 -> 0 | U67: 0 | V67: =S67*T67*U67 -> 0 | W67: =F67+J67+N67+R67+V67 -> 23786.718
A68: ='Program Budget'!D51 -> Other Travel Related Expenses for Nigeria Staff Travel | B68: ='Program Budget'!F51 -> Trip | C68: ='Program Budget'!H51 -> 150 | D68: ='Program Budget'!G51 -> 3 | E68: 1 | F68: =C68*D68*E68 -> 450 | G68: =C68*1.05 -> 157.5 | H68: ='Program Budget'!K51 -> 3 | I68: 1 | J68: =G68*H68*I68 -> 472.5 | K68: =G68*1.05 -> 165.375 | L68: ='Program Budget'!N51 -> 3 | M68: 1 | N68: =K68*L68*M68 -> 496.125 | O68: =K68*1.05 -> 173.64375 | P68: ='Program Budget'!Q51 -> 3 | Q68: 1 | R68: =O68*P68*Q68 -> 520.93125 | S68: =O68*1.05 -> 182.32594 | T68: ='Program Budget'!T51 -> 0 | U68: 0 | V68: =S68*T68*U68 -> 0 | W68: =F68+J68+N68+R68+V68 -> 1939.5563
A69: ='Program Budget'!D52 -> Visa Cost for Nigerian Staff Travel | B69: ='Program Budget'!F52 -> Trip | C69: ='Program Budget'!H52 -> 185 | D69: ='Program Budget'!G52 -> 4 | E69: 1 | F69: =C69*D69*E69 -> 740 | G69: =C69*1.05 -> 194.25 | H69: ='Program Budget'!K52 -> 2 | I69: 1 | J69: =G69*H69*I69 -> 388.5 | K69: =G69*1.05 -> 203.9625 | L69: ='Program Budget'!N52 -> 0 | M69: 1 | N69: =K69*L69*M69 -> 0 | O69: =K69*1.05 -> 214.16063 | P69: ='Program Budget'!Q52 -> 0 | Q69: 1 | R69: =O69*P69*Q69 -> 0 | S69: =O69*1.05 -> 224.86866 | T69: ='Program Budget'!T52 -> 0 | U69: 0 | V69: =S69*T69*U69 -> 0 | W69: =F69+J69+N69+R69+V69 -> 1128.5
A70: ='Program Budget'!D57 -> Lodging and M&IE - Training, M&E, & Data Collection | B70: ='Program Budget'!F57 -> Day | C70: ='Program Budget'!H57 -> 145.5 | D70: ='Program Budget'!G57 -> 144 | E70: 1 | F70: =C70*D70*E70 -> 20952 | G70: =C70*1.05 -> 152.775 | H70: ='Program Budget'!K57 -> 144 | I70: 1 | J70: =G70*H70*I70 -> 21999.6 | K70: =G70*1.05 -> 160.41375 | L70: ='Program Budget'!N57 -> 144 | M70: 1 | N70: =K70*L70*M70 -> 23099.58 | O70: =K70*1.05 -> 168.43444 | P70: ='Program Budget'!Q57 -> 144 | Q70: 1 | R70: =O70*P70*Q70 -> 24254.559 | S70: =O70*1.05 -> 176.85616 | T70: ='Program Budget'!T57 -> 0 | U70: 0 | V70: =S70*T70*U70 -> 0 | W70: =F70+J70+N70+R70+V70 -> 90305.739
A71: ='Program Budget'!D171 -> Lodging and M&IE for Trainings on Activity 1 | B71: ='Program Budget'!F171 -> Day | C71: ='Program Budget'!H171 -> 145.5 | D71: ='Program Budget'!G171 -> 36 | E71: 1 | F71: =C71*D71*E71 -> 5238 | G71: =C71*1.05 -> 152.775 | H71: ='Program Budget'!K171 -> 72 | I71: 1 | J71: =G71*H71*I71 -> 10999.8 | K71: =G71*1.05 -> 160.41375 | L71: ='Program Budget'!N171 -> 72 | M71: 1 | N71: =K71*L71*M71 -> 11549.79 | O71: =K71*1.05 -> 168.43444 | P71: ='Program Budget'!Q171 -> 72 | Q71: 1 | R71: =O71*P71*Q71 -> 12127.28 | S71: =O71*1.05 -> 176.85616 | T71: ='Program Budget'!T171 -> 0 | U71: 0 | V71: =S71*T71*U71 -> 0 | W71: =F71+J71+N71+R71+V71 -> 39914.87
A72: ='Program Budget'!D229 -> Lodging and M&IE for Trainings on Activity 2 | B72: ='Program Budget'!F229 -> Day | C72: ='Program Budget'!H229 -> 145.5 | D72: ='Program Budget'!G229 -> 36 | E72: 1 | F72: =C72*D72*E72 -> 5238 | G72: =C72*1.05 -> 152.775 | H72: ='Program Budget'!K229 -> 72 | I72: 1 | J72: =G72*H72*I72 -> 10999.8 | K72: =G72*1.05 -> 160.41375 | L72: ='Program Budget'!N229 -> 72 | M72: 1 | N72: =K72*L72*M72 -> 11549.79 | O72: =K72*1.05 -> 168.43444 | P72: ='Program Budget'!Q229 -> 72 | Q72: 1 | R72: =O72*P72*Q72 -> 12127.28 | S72: =O72*1.05 -> 176.85616 | T72: ='Program Budget'!T229 -> 0 | U72: 0 | V72: =S72*T72*U72 -> 0 | W72: =F72+J72+N72+R72+V72 -> 39914.87
A73: ='Program Budget'!D231 -> Lodging and M&IE - Buyer Conferences for American Farmers, Ranchers and Agricultural Professionals - 50% of Cost | B73: ='Program Budget'!F231 -> Day | C73: ='Program Budget'!H231 -> 155.25 | D73: ='Program Budget'!G231 -> 0 | E73: 1 | F73: =C73*D73*E73 -> 0 | G73: =C73*1.05 -> 163.0125 | H73: ='Program Budget'!K231 -> 70 | I73: 1 | J73: =G73*H73*I73 -> 11410.875 | K73: =G73*1.05 -> 171.16313 | L73: ='Program Budget'!N231 -> 70 | M73: 1 | N73: =K73*L73*M73 -> 11981.419 | O73: =K73*1.05 -> 179.72128 | P73: ='Program Budget'!Q231 -> 0 | Q73: 1 | R73: =O73*P73*Q73 -> 0 | S73: =O73*1.05 -> 188.70735 | T73: ='Program Budget'!T231 -> 0 | U73: 0 | V73: =S73*T73*U73 -> 0 | W73: =F73+J73+N73+R73+V73 -> 23392.294
A74: ='Program Budget'!D233 -> Lodging and M&IE - Trade Finance & Export Consultant | B74: ='Program Budget'!F233 -> Day | C74: ='Program Budget'!H233 -> 310.5 | D74: ='Program Budget'!G233 -> 7 | E74: 1 | F74: =C74*D74*E74 -> 2173.5 | G74: =C74*1.05 -> 326.025 | H74: ='Program Budget'!K233 -> 14 | I74: 1 | J74: =G74*H74*I74 -> 4564.35 | K74: =G74*1.05 -> 342.32625 | L74: ='Program Budget'!N233 -> 14 | M74: 1 | N74: =K74*L74*M74 -> 4792.5675 | O74: =K74*1.05 -> 359.44256 | P74: ='Program Budget'!Q233 -> 7 | Q74: 1 | R74: =O74*P74*Q74 -> 2516.0979 | S74: =O74*1.05 -> 377.41469 | T74: ='Program Budget'!T233 -> 0 | U74: 0 | V74: =S74*T74*U74 -> 0 | W74: =F74+J74+N74+R74+V74 -> 14046.515
A75: ='Program Budget'!D234 -> Ground Transportation – Trade Finance & Export Consultant | B75: ='Program Budget'!F234 -> Trip | C75: ='Program Budget'!H234 -> 150 | D75: ='Program Budget'!G234 -> 1 | E75: 1 | F75: =C75*D75*E75 -> 150 | G75: =C75*1.05 -> 157.5 | H75: ='Program Budget'!K234 -> 2 | I75: 1 | J75: =G75*H75*I75 -> 315 | K75: =G75*1.05 -> 165.375 | L75: ='Program Budget'!N234 -> 2 | M75: 1 | N75: =K75*L75*M75 -> 330.75 | O75: =K75*1.05 -> 173.64375 | P75: ='Program Budget'!Q234 -> 1 | Q75: 1 | R75: =O75*P75*Q75 -> 173.64375 | S75: =O75*1.05 -> 182.32594 | T75: ='Program Budget'!T234 -> 0 | U75: 0 | V75: =S75*T75*U75 -> 0 | W75: =F75+J75+N75+R75+V75 -> 969.39375
A76: ='Program Budget'!D236 -> Visa Cost - Trade Finance & Expert Consultant | B76: ='Program Budget'!F236 -> Trip | C76: ='Program Budget'!H236 -> 160 | D76: ='Program Budget'!G236 -> 1 | E76: 1 | F76: =C76*D76*E76 -> 160 | G76: =C76*1.05 -> 168 | H76: ='Program Budget'!K236 -> 2 | I76: 1 | J76: =G76*H76*I76 -> 336 | K76: =G76*1.05 -> 176.4 | L76: ='Program Budget'!N236 -> 2 | M76: 1 | N76: =K76*L76*M76 -> 352.8 | O76: =K76*1.05 -> 185.22 | P76: ='Program Budget'!Q236 -> 1 | Q76: 1 | R76: =O76*P76*Q76 -> 185.22 | S76: =O76*1.05 -> 194.481 | T76: ='Program Budget'!T236 -> 0 | U76: 0 | V76: =S76*T76*U76 -> 0 | W76: =F76+J76+N76+R76+V76 -> 1034.02
A77: ='Program Budget'!D307 -> Lodging and M&IE for Trainings on Activity 3 | B77: ='Program Budget'!F307 -> Day | C77: ='Program Budget'!H307 -> 145.5 | D77: ='Program Budget'!G307 -> 18 | E77: 1 | F77: =C77*D77*E77 -> 2619 | G77: =C77*1.05 -> 152.775 | H77: ='Program Budget'!K307 -> 36 | I77: 1 | J77: =G77*H77*I77 -> 5499.9 | K77: =G77*1.05 -> 160.41375 | L77: ='Program Budget'!N307 -> 36 | M77: 1 | N77: =K77*L77*M77 -> 5774.895 | O77: =K77*1.05 -> 168.43444 | P77: ='Program Budget'!Q307 -> 36 | Q77: 1 | R77: =O77*P77*Q77 -> 6063.6398 | S77: =O77*1.05 -> 176.85616 | T77: ='Program Budget'!T307 -> 0 | U77: 0 | V77: =S77*T77*U77 -> 0 | W77: =F77+J77+N77+R77+V77 -> 19957.435
A79: Subtotal: Travel | F79: =SUM(F44:F78) -> 92004.3 | J79: =SUM(J44:J78) -> 146512.07 | N79: =SUM(N44:N78) -> 153429.74 | R79: =SUM(R44:R78) -> 132969.79 | V79: =SUM(V44:V78) -> 0 | W79: =SUM(W44:W78) -> 524915.89
A80: Professional Services
A81: ='Program Budget'!D61 -> Monetization Agent Fee | B81: ='Program Budget'!F61 -> % | C81: 10790000 | D81: 1 | E81: 0.0167 | F81: =C81*D81*E81 -> 180193 | G81: 0 | H81: 0 | I81: 0 | J81: =G81*H81*I81 -> 0 | K81: =G81 -> 0 | L81: ='Program Budget'!N61 -> 0 | M81: 0 | N81: =K81*L81*M81 -> 0 | O81: =K81 -> 0 | P81: ='Program Budget'!Q611 -> 0 | Q81: 0 | R81: =O81*P81*Q81 -> 0 | S81: =O81 -> 0 | T81: ='Program Budget'!T61 -> 0 | U81: 0 | V81: =S81*T81*U81 -> 0 | W81: =F81+J81+N81+R81+V81 -> 180193
A82: ='Program Budget'!D62 -> Monetization Impact Assessment | B82: ='Program Budget'!F62 -> Unit | C82: ='Program Budget'!H62 -> 60000 | D82: ='Program Budget'!G62 -> 0 | E82: 0 | F82: =C82*D82*E82 -> 0 | G82: =C82 -> 60000 | H82: ='Program Budget'!K62 -> 1 | I82: 1 | J82: =G82*H82*I82 -> 60000 | K82: =G82 -> 60000 | L82: ='Program Budget'!N62 -> 0 | M82: 0 | N82: =K82*L82*M82 -> 0 | O82: =K82 -> 60000 | P82: ='Program Budget'!Q62 -> 0 | Q82: 0 | R82: =O82*P82*Q82 -> 0 | S82: =O82 -> 60000 | T82: ='Program Budget'!T62 -> 0 | U82: 0 | V82: =S82*T82*U82 -> 0 | W82: =F82+J82+N82+R82+V82 -> 60000
A83: ='Program Budget'!D63 -> Single Audit | B83: ='Program Budget'!F63 -> Year | C83: ='Program Budget'!H63 -> 13000 | D83: ='Program Budget'!G63 -> 1 | E83: 1 | F83: =C83*D83*E83 -> 13000 | G83: =C83 -> 13000 | H83: ='Program Budget'!K63 -> 1 | I83: 1 | J83: =G83*H83*I83 -> 13000 | K83: =G83 -> 13000 | L83: ='Program Budget'!N63 -> 1 | M83: 1 | N83: =K83*L83*M83 -> 13000 | O83: =K83 -> 13000 | P83: ='Program Budget'!Q63 -> 1 | Q83: 1 | R83: =O83*P83*Q83 -> 13000 | S83: =O83 -> 13000 | T83: ='Program Budget'!T63 -> 0 | U83: 0 | V83: =S83*T83*U83 -> 0 | W83: =F83+J83+N83+R83+V83 -> 52000
A84: ='Program Budget'!D64 -> Payroll Processing and Local Accounting Books Preparation | B84: ='Program Budget'!F64 -> Month | C84: ='Program Budget'!H64 -> 2000 | D84: ='Program Budget'!G64 -> 12 | E84: 1 | F84: =C84*D84*E84 -> 24000 | G84: =C84 -> 2000 | H84: ='Program Budget'!K64 -> 12 | I84: 1 | J84: =G84*H84*I84 -> 24000 | K84: =G84 -> 2000 | L84: ='Program Budget'!N64 -> 12 | M84: 1 | N84: =K84*L84*M84 -> 24000 | O84: =K84 -> 2000 | P84: ='Program Budget'!Q64 -> 12 | Q84: 1 | R84: =O84*P84*Q84 -> 24000 | S84: =O84 -> 2000 | T84: ='Program Budget'!T64 -> 0 | U84: 0 | V84: =S84*T84*U84 -> 0 | W84: =F84+J84+N84+R84+V84 -> 96000
A85: ='Program Budget'!D65 -> Legal & Registration Fees | B85: ='Program Budget'!F65 -> Year | C85: ='Program Budget'!H65 -> 3000 | D85: ='Program Budget'!G65 -> 1 | E85: 1 | F85: =C85*D85*E85 -> 3000 | G85: =C85 -> 3000 | H85: ='Program Budget'!K65 -> 1 | I85: 1 | J85: =G85*H85*I85 -> 3000 | K85: =G85 -> 3000 | L85: ='Program Budget'!N65 -> 1 | M85: 1 | N85: =K85*L85*M85 -> 3000 | O85: =K85 -> 3000 | P85: ='Program Budget'!Q65 -> 1 | Q85: 1 | R85: =O85*P85*Q85 -> 3000 | S85: =O85 -> 3000 | T85: ='Program Budget'!T65 -> 0 | U85: 0 | V85: =S85*T85*U85 -> 0 | W85: =F85+J85+N85+R85+V85 -> 12000
A86: ='Program Budget'!D66 -> IT Services & Management | B86: ='Program Budget'!F66 -> Month | C86: ='Program Budget'!H66 -> 500 | D86: ='Program Budget'!G66 -> 12 | E86: 1 | F86: =C86*D86*E86 -> 6000 | G86: =C86 -> 500 | H86: ='Program Budget'!K66 -> 12 | I86: 1 | J86: =G86*H86*I86 -> 6000 | K86: =G86 -> 500 | L86: ='Program Budget'!N66 -> 12 | M86: 1 | N86: =K86*L86*M86 -> 6000 | O86: =K86 -> 500 | P86: ='Program Budget'!Q66 -> 12 | Q86: 1 | R86: =O86*P86*Q86 -> 6000 | S86: =O86 -> 500 | T86: ='Program Budget'!T66 -> 0 | U86: 0 | V86: =S86*T86*U86 -> 0 | W86: =F86+J86+N86+R86+V86 -> 24000
A87: ='Program Budget'!D67 -> Security Services, Risk Assessments, & Security Assessment | B87: ='Program Budget'!F67 -> Year | C87: =Admin!C70+'Activity 1'!C57+'Activity 2'!C63+'Activity 3'!C54 -> 7000 | D87: ='Program Budget'!G67 -> 1 | E87: 1 | F87: =C87*D87*E87 -> 7000 | G87: =C87 -> 7000 | H87: ='Program Budget'!K67 -> 1 | I87: 1 | J87: =G87*H87*I87 -> 7000 | K87: =G87 -> 7000 | L87: ='Program Budget'!N67 -> 1 | M87: 1 | N87: =K87*L87*M87 -> 7000 | O87: =K87 -> 7000 | P87: ='Program Budget'!Q67 -> 1 | Q87: 1 | R87: =O87*P87*Q87 -> 7000 | S87: =O87 -> 7000 | T87: ='Program Budget'!T67 -> 0 | U87: 0 | V87: =S87*T87*U87 -> 0 | W87: =F87+J87+N87+R87+V87 -> 28000
A88: ='Program Budget'!D68 -> Short-Term Administrative Support Consultants | B88: ='Program Budget'!F68 -> Day | C88: ='Program Budget'!H68 -> 520 | D88: ='Program Budget'!G68 -> 15 | E88: 1 | F88: =C88*D88*E88 -> 7800 | G88: =C88 -> 520 | H88: ='Program Budget'!K68 -> 15 | I88: 1 | J88: =G88*H88*I88 -> 7800 | K88: =G88 -> 520 | L88: ='Program Budget'!N68 -> 15 | M88: 1 | N88: =K88*L88*M88 -> 7800 | O88: =K88 -> 520 | P88: ='Program Budget'!Q68 -> 15 | Q88: 1 | R88: =O88*P88*Q88 -> 7800 | S88: =O88 -> 520 | T88: ='Program Budget'!T68 -> 0 | U88: 0 | V88: =S88*T88*U88 -> 0 | W88: =F88+J88+N88+R88+V88 -> 31200
A89: ='Program Budget'!D158 -> Contract for Nation-wide Poultry Consumption Campaign | B89: ='Program Budget'!F158 -> Year | C89: ='Program Budget'!H158 -> 160000 | D89: ='Program Budget'!G158 -> 0 | E89: 1 | F89: =C89*D89*E89 -> 0 | G89: =C89 -> 160000 | H89: ='Program Budget'!K158 -> 0.5 | I89: 1 | J89: =G89*H89*I89 -> 80000 | K89: =G89 -> 160000 | L89: ='Program Budget'!N158 -> 1 | M89: 1 | N89: =K89*L89*M89 -> 160000 | O89: =K89 -> 160000 | P89: ='Program Budget'!Q158 -> 1 | Q89: 1 | R89: =O89*P89*Q89 -> 160000 | S89: =O89 -> 160000 | T89: ='Program Budget'!T158 -> 0 | U89: 0 | V89: =S89*T89*U89 -> 0 | W89: =F89+J89+N89+R89+V89 -> 400000
A90: ='Program Budget'!D215 -> Contracts for Trade Finance Capacity Building for American Producers and Cooperators (Nigerian) | B90: ='Program Budget'!F215 -> Lumpsum | C90: ='Program Budget'!H215 -> 67000 | D90: ='Program Budget'!G215 -> 0.5 | E90: 1 | F90: =C90*D90*E90 -> 33500 | G90: =C90 -> 67000 | H90: ='Program Budget'!K215 -> 1 | I90: 1 | J90: =G90*H90*I90 -> 67000 | K90: =G90 -> 67000 | L90: ='Program Budget'!N215 -> 1 | M90: 1 | N90: =K90*L90*M90 -> 67000 | O90: =K90 -> 67000 | P90: ='Program Budget'!Q215 -> 0.5 | Q90: 1 | R90: =O90*P90*Q90 -> 33500 | S90: =O90 -> 67000 | T90: ='Program Budget'!T215 -> 0 | U90: 0 | V90: =S90*T90*U90 -> 0 | W90: =F90+J90+N90+R90+V90 -> 201000
A91: ='Program Budget'!D216 -> Expert Consultant on Trade Finance & Exports (US based) | B91: ='Program Budget'!F216 -> Day | C91: ='Program Budget'!H216 -> 620 | D91: ='Program Budget'!G216 -> 40 | E91: 1 | F91: =C91*D91*E91 -> 24800 | G91: =C91 -> 620 | H91: ='Program Budget'!K216 -> 45 | I91: 1 | J91: =G91*H91*I91 -> 27900 | K91: =G91 -> 620 | L91: ='Program Budget'!N216 -> 45 | M91: 1 | N91: =K91*L91*M91 -> 27900 | O91: =K91 -> 620 | P91: ='Program Budget'!Q216 -> 37 | Q91: 1 | R91: =O91*P91*Q91 -> 22940 | S91: =O91 -> 620 | T91: ='Program Budget'!T216 -> 0 | U91: 0 | V91: =S91*T91*U91 -> 0 | W91: =F91+J91+N91+R91+V91 -> 103540
A92: ='Program Budget'!D69 -> Monitoring, Evaluation, and Collection of Reliable Data
A93: ='Program Budget'!D70 -> Evaluations
A94: ='Program Budget'!D71 -> Baseline Evaluation | B94: ='Program Budget'!F71 -> Unit | C94: ='Program Budget'!H71 -> 150000 | D94: ='Program Budget'!G71 -> 1 | E94: 1 | F94: =C94*D94*E94 -> 150000 | G94: =C94 -> 150000 | H94: ='Program Budget'!K71 -> 0 | I94: 1 | J94: =G94*H94*I94 -> 0 | K94: =G94 -> 150000 | L94: ='Program Budget'!N71 -> 0 | M94: 1 | N94: =K94*L94*M94 -> 0 | O94: =K94 -> 150000 | P94: ='Program Budget'!Q71 -> 0 | Q94: 1 | R94: =O94*P94*Q94 -> 0 | S94: =O94 -> 150000 | T94: ='Program Budget'!T71 -> 0 | U94: 0 | V94: =S94*T94*U94 -> 0 | W94: =F94+J94+N94+R94+V94 -> 150000
A95: ='Program Budget'!D72 -> Midterm Evaluation | B95: ='Program Budget'!F72 -> Unit | C95: ='Program Budget'!H72 -> 160000 | D95: ='Program Budget'!G72 -> 0 | E95: 1 | F95: =C95*D95*E95 -> 0 | G95: =C95 -> 160000 | H95: ='Program Budget'!K72 -> 0 | I95: 1 | J95: =G95*H95*I95 -> 0 | K95: =G95 -> 160000 | L95: ='Program Budget'!N72 -> 1 | M95: 1 | N95: =K95*L95*M95 -> 160000 | O95: =K95 -> 160000 | P95: ='Program Budget'!Q72 -> 0 | Q95: 1 | R95: =O95*P95*Q95 -> 0 | S95: =O95 -> 160000 | T95: ='Program Budget'!T72 -> 0 | U95: 0 | V95: =S95*T95*U95 -> 0 | W95: =F95+J95+N95+R95+V95 -> 160000
A96: ='Program Budget'!D73 -> Final Evaluation | B96: ='Program Budget'!F73 -> Unit | C96: ='Program Budget'!H73 -> 175000 | D96: ='Program Budget'!G73 -> 0 | E96: 1 | F96: =C96*D96*E96 -> 0 | G96: =C96 -> 175000 | H96: ='Program Budget'!K73 -> 0 | I96: 1 | J96: =G96*H96*I96 -> 0 | K96: =G96 -> 175000 | L96: ='Program Budget'!N73 -> 0 | M96: 1 | N96: =K96*L96*M96 -> 0 | O96: =K96 -> 175000 | P96: ='Program Budget'!Q73 -> 1 | Q96: 1 | R96: =O96*P96*Q96 -> 175000 | S96: =O96 -> 175000 | T96: ='Program Budget'!T73 -> 0 | U96: 0 | V96: =S96*T96*U96 -> 0 | W96: =F96+J96+N96+R96+V96 -> 175000
A97: ='Program Budget'!D74 -> Monitoring Guidelines Development
A98: ='Program Budget'!D75 -> Monitoring Guidelines Creation & Printing | B98: ='Program Budget'!F75 -> Document | C98: ='Program Budget'!H75 -> 2000 | D98: ='Program Budget'!G75 -> 1 | E98: 1 | F98: =C98*D98*E98 -> 2000 | G98: =C98 -> 2000 | H98: ='Program Budget'!K75 -> 0 | I98: 1 | J98: =G98*H98*I98 -> 0 | K98: =G98 -> 2000 | L98: ='Program Budget'!N75 -> 0 | M98: 1 | N98: =K98*L98*M98 -> 0 | O98: =K98 -> 2000 | P98: ='Program Budget'!Q75 -> 0 | Q98: 1 | R98: =O98*P98*Q98 -> 0 | S98: =O98 -> 2000 | T98: ='Program Budget'!T75 -> 0 | U98: 0 | V98: =S98*T98*U98 -> 0 | W98: =F98+J98+N98+R98+V98 -> 2000
A99: ='Program Budget'!D76 -> Monitoring Guidelines Revision & Printing | B99: ='Program Budget'!F76 -> Year | C99: ='Program Budget'!H76 -> 1000 | D99: ='Program Budget'!G76 -> 0 | E99: 1 | F99: =C99*D99*E99 -> 0 | G99: =C99 -> 1000 | H99: ='Program Budget'!K76 -> 1 | I99: 1 | J99: =G99*H99*I99 -> 1000 | K99: =G99 -> 1000 | L99: ='Program Budget'!N76 -> 1 | M99: 1 | N99: =K99*L99*M99 -> 1000 | O99: =K99 -> 1000 | P99: ='Program Budget'!Q76 -> 1 | Q99: 1 | R99: =O99*P99*Q99 -> 1000 | S99: =O99 -> 1000 | T99: ='Program Budget'!T76 -> 0 | U99: 0 | V99: =S99*T99*U99 -> 0 | W99: =F99+J99+N99+R99+V99 -> 3000
A100: ='Program Budget'!D77 -> Monitoring Guidelines Staff Training on Indicators and Data Collection/Analysis | B100: ='Program Budget'!F77 -> Workshop | C100: ='Program Budget'!H77 -> 2500 | D100: ='Program Budget'!G77 -> 1 | E100: 1 | F100: =C100*D100*E100 -> 2500 | G100: =C100 -> 2500 | H100: ='Program Budget'!K77 -> 1 | I100: 1 | J100: =G100*H100*I100 -> 2500 | K100: =G100 -> 2500 | L100: ='Program Budget'!N77 -> 1 | M100: 1 | N100: =K100*L100*M100 -> 2500 | O100: =K100 -> 2500 | P100: ='Program Budget'!Q77 -> 1 | Q100: 1 | R100: =O100*P100*Q100 -> 2500 | S100: =O100 -> 2500 | T100: ='Program Budget'!T77 -> 0 | U100: 0 | V100: =S100*T100*U100 -> 0 | W100: =F100+J100+N100+R100+V100 -> 10000
A101: ='Program Budget'!D78 -> M&E Database
A102: ='Program Budget'!D79 -> M&E Database Trainings | B102: ='Program Budget'!F79 -> Year | C102: ='Program Budget'!H79 -> 500 | D102: ='Program Budget'!G79 -> 1 | E102: 1 | F102: =C102*D102*E102 -> 500 | G102: =C102 -> 500 | H102: ='Program Budget'!K79 -> 1 | I102: 1 | J102: =G102*H102*I102 -> 500 | K102: =G102 -> 500 | L102: ='Program Budget'!N79 -> 1 | M102: 1 | N102: =K102*L102*M102 -> 500 | O102: =K102 -> 500 | P102: ='Program Budget'!Q79 -> 1 | Q102: 1 | R102: =O102*P102*Q102 -> 500 | S102: =O102 -> 500 | T102: ='Program Budget'!T79 -> 0 | U102: 0 | V102: =S102*T102*U102 -> 0 | W102: =F102+J102+N102+R102+V102 -> 2000
A103: ='Program Budget'!D80 -> M&E Database Platform Startup | B103: ='Program Budget'!F80 -> Year | C103: ='Program Budget'!H80 -> 5500 | D103: ='Program Budget'!G80 -> 1 | E103: 1 | F103: =C103*D103*E103 -> 5500 | G103: =C103 -> 5500 | H103: ='Program Budget'!K80 -> 0 | I103: 1 | J103: =G103*H103*I103 -> 0 | K103: =G103 -> 5500 | L103: ='Program Budget'!N80 -> 0 | M103: 1 | N103: =K103*L103*M103 -> 0 | O103: =K103 -> 5500 | P103: ='Program Budget'!Q80 -> 0 | Q103: 1 | R103: =O103*P103*Q103 -> 0 | S103: =O103 -> 5500 | T103: ='Program Budget'!T80 -> 0 | U103: 0 | V103: =S103*T103*U103 -> 0 | W103: =F103+J103+N103+R103+V103 -> 5500
A104: ='Program Budget'!D81 -> M&E Database Platform Subscription Fee (Annual) | B104: ='Program Budget'!F81 -> Year | C104: ='Program Budget'!H81 -> 6500 | D104: ='Program Budget'!G81 -> 1 | E104: 1 | F104: =C104*D104*E104 -> 6500 | G104: =C104 -> 6500 | H104: ='Program Budget'!K81 -> 1 | I104: 1 | J104: =G104*H104*I104 -> 6500 | K104: =G104 -> 6500 | L104: ='Program Budget'!N81 -> 1 | M104: 1 | N104: =K104*L104*M104 -> 6500 | O104: =K104 -> 6500 | P104: ='Program Budget'!Q81 -> 1 | Q104: 1 | R104: =O104*P104*Q104 -> 6500 | S104: =O104 -> 6500 | T104: ='Program Budget'!T81 -> 0 | U104: 0 | V104: =S104*T104*U104 -> 0 | W104: =F104+J104+N104+R104+V104 -> 26000 | Y104: =SUM(W94:W104)/W168 -> 0.043132585
...

Sheet Admin
A2: Item | C2: Year 1 | G2: Year 2 | K2: Year 3 | O2: Year 4 | S2: Year 5 | W2: Total
C3: Cost | D3: Quantity | E3: Percent Allocated | F3: Total | G3: Cost | H3: Quantity | I3: Percent Allocated | J3: Total | K3: Cost | L3: Quantity | M3: Percent Allocated | N3: Total | O3: Cost | P3: Quantity | Q3: Percent Allocated | R3: Total | S3: Cost | T3: Quantity | U3: Percent Allocated | V3: Total
A4: Direct Costs
A5: Salaries
A6: USN/TCN Staff
A7: None | F7: =C7*D7*E7 -> 0 | J7: =G7*H7*I7 -> 0 | N7: =K7*L7*M7 -> 0 | R7: =O7*P7*Q7 -> 0 | V7: =S7*T7*U7 -> 0 | W7: =F7+J7+N7+R7+V7 -> 0
A8: Total: Expatriate Salaries & Wages | F8: =SUM(F7:F7) -> 0 | J8: =SUM(J7:J7) -> 0 | N8: =SUM(N7:N7) -> 0 | R8: =SUM(R7:R7) -> 0 | V8: =SUM(V7:V7) -> 0 | W8: =+F8+J8+N8+R8+V8 -> 0
A9: CNN Staff
A10: ='Program Budget'!D12 -> Key Personnel: Chief of Party | B10: ='Program Budget'!F12 -> Month | C10: ='Program Budget'!H12 -> 9583.3333 | D10: ='Program Budget'!G12 -> 11 | E10: ='Program Budget'!E12 -> 0.5 | F10: =C10*D10*E10 -> 52708.333 | G10: =C10*1.05 -> 10062.5 | H10: ='Program Budget'!K12 -> 12 | I10: ='Program Budget'!J12 -> 0.05 | J10: =G10*H10*I10 -> 6037.5 | K10: =G10*1.05 -> 10565.625 | L10: ='Program Budget'!N12 -> 12 | M10: ='Program Budget'!M12 -> 0.05 | N10: =K10*L10*M10 -> 6339.375 | O10: =K10*1.05 -> 11093.906 | P10: ='Program Budget'!Q12 -> 12 | Q10: ='Program Budget'!P12 -> 0.05 | R10: =O10*P10*Q10 -> 6656.3438 | S10: =O10*1.05 -> 11648.602 | T10: ='Program Budget'!T12 -> 0 | U10: ='Program Budget'!S12 -> 0 | V10: =S10*T10*U10 -> 0 | W10: =F10+J10+N10+R10+V10 -> 71741.552
A11: ='Program Budget'!D13 -> Technical Director | B11: ='Program Budget'!F13 -> Month | C11: ='Program Budget'!H13 -> 3500 | D11: ='Program Budget'!G13 -> 9 | E11: ='Program Budget'!E13 -> 0.28 | F11: =C11*D11*E11 -> 8820 | G11: =C11*1.05 -> 3675 | H11: ='Program Budget'!K13 -> 12 | I11: ='Program Budget'!J13 -> 0 | J11: =G11*H11*I11 -> 0 | K11: =G11*1.05 -> 3858.75 | L11: ='Program Budget'!N13 -> 12 | M11: ='Program Budget'!M13 -> 0 | N11: =K11*L11*M11 -> 0 | O11: =K11*1.05 -> 4051.6875 | P11: ='Program Budget'!Q13 -> 12 | Q11: ='Program Budget'!P13 -> 0 | R11: =O11*P11*Q11 -> 0 | S11: =O11*1.05 -> 4254.2719 | T11: ='Program Budget'!T13 -> 0 | U11: ='Program Budget'!S13 -> 0 | V11: =S11*T11*U11 -> 0 | W11: =F11+J11+N11+R11+V11 -> 8820
A12: ='Program Budget'!D14 -> Technical Lead - Activity 2 US Exports | B12: ='Program Budget'!F14 -> Month | C12: ='Program Budget'!H14 -> 2833.3333 | D12: ='Program Budget'!G14 -> 8 | E12: ='Program Budget'!E14 -> 0.2 | F12: =C12*D12*E12 -> 4533.3333 | G12: =C12*1.05 -> 2975 | H12: ='Program Budget'!K14 -> 12 | I12: ='Program Budget'!J14 -> 0 | J12: =G12*H12*I12 -> 0 | K12: =G12*1.05 -> 3123.75 | L12: ='Program Budget'!N14 -> 12 | M12: ='Program Budget'!M14 -> 0 | N12: =K12*L12*M12 -> 0 | O12: =K12*1.05 -> 3279.9375 | P12: ='Program Budget'!Q14 -> 12 | Q12: ='Program Budget'!P14 -> 0 | R12: =O12*P12*Q12 -> 0 | S12: =O12*1.05 -> 3443.9344 | T12: ='Program Budget'!T14 -> 0 | U12: ='Program Budget'!S14 -> 0 | V12: =S12*T12*U12 -> 0 | W12: =F12+J12+N12+R12+V12 -> 4533.3333
A13: ='Program Budget'!D15 -> Technical Lead - Activity 2 Access to Finance Specialist | B13: ='Program Budget'!F15 -> Month | C13: ='Program Budget'!H15 -> 2833.3333 | D13: ='Program Budget'!G15 -> 8 | E13: ='Program Budget'!E15 -> 0.2 | F13: =C13*D13*E13 -> 4533.3333 | G13: =C13*1.05 -> 2975 | H13: ='Program Budget'!K15 -> 12 | I13: ='Program Budget'!J15 -> 0 | J13: =G13*H13*I13 -> 0 | K13: =G13*1.05 -> 3123.75 | L13: ='Program Budget'!N15 -> 12 | M13: ='Program Budget'!M15 -> 0 | N13: =K13*L13*M13 -> 0 | O13: =K13*1.05 -> 3279.9375 | P13: ='Program Budget'!Q15 -> 12 | Q13: ='Program Budget'!P15 -> 0 | R13: =O13*P13*Q13 -> 0 | S13: =O13*1.05 -> 3443.9344 | T13: ='Program Budget'!T15 -> 0 | U13: ='Program Budget'!S15 -> 0 | V13: =S13*T13*U13 -> 0 | W13: =F13+J13+N13+R13+V13 -> 4533.3333
A14: ='Program Budget'!D16 -> Communications/Strategic Partnerships Manager | B14: ='Program Budget'!F16 -> Month | C14: ='Program Budget'!H16 -> 2666.6667 | D14: ='Program Budget'!G16 -> 8 | E14: ='Program Budget'!E16 -> 0.2 | F14: =C14*D14*E14 -> 4266.6667 | G14: =C14*1.05 -> 2800 | H14: ='Program Budget'!K16 -> 12 | I14: ='Program Budget'!J16 -> 0 | J14: =G14*H14*I14 -> 0 | K14: =G14*1.05 -> 2940 | L14: ='Program Budget'!N16 -> 12 | M14: ='Program Budget'!M16 -> 0 | N14: =K14*L14*M14 -> 0 | O14: =K14*1.05 -> 3087 | P14: ='Program Budget'!Q16 -> 12 | Q14: ='Program Budget'!P16 -> 0 | R14: =O14*P14*Q14 -> 0 | S14: =O14*1.05 -> 3241.35 | T14: ='Program Budget'!T16 -> 0 | U14: ='Program Budget'!S16 -> 0 | V14: =S14*T14*U14 -> 0 | W14: =F14+J14+N14+R14+V14 -> 4266.6667
A15: ='Program Budget'!D17 -> M&E Director | B15: ='Program Budget'!F17 -> Month | C15: ='Program Budget'!H17 -> 3500 | D15: ='Program Budget'!G17 -> 10 | E15: ='Program Budget'!E17 -> 0.35 | F15: =C15*D15*E15 -> 12250 | G15: =C15*1.05 -> 3675 | H15: ='Program Budget'!K17 -> 12 | I15: ='Program Budget'!J17 -> 0.05 | J15: =G15*H15*I15 -> 2205 | K15: =G15*1.05 -> 3858.75 | L15: ='Program Budget'!N17 -> 12 | M15: ='Program Budget'!M17 -> 0.05 | N15: =K15*L15*M15 -> 2315.25 | O15: =K15*1.05 -> 4051.6875 | P15: ='Program Budget'!Q17 -> 12 | Q15: ='Program Budget'!P17 -> 0.05 | R15: =O15*P15*Q15 -> 2431.0125 | S15: =O15*1.05 -> 4254.2719 | T15: ='Program Budget'!T17 -> 0 | U15: ='Program Budget'!S17 -> 0 | V15: =S15*T15*U15 -> 0 | W15: =F15+J15+N15+R15+V15 -> 19201.263
A16: ='Program Budget'!D18 -> M&E Specialist | B16: ='Program Budget'!F18 -> Month | C16: ='Program Budget'!H18 -> 2000 | D16: ='Program Budget'!G18 -> 8 | E16: ='Program Budget'!E18 -> 0.2 | F16: =C16*D16*E16 -> 3200 | G16: =C16*1.05 -> 2100 | H16: ='Program Budget'!K18 -> 12 | I16: ='Program Budget'!J18 -> 0.05 | J16: =G16*H16*I16 -> 1260 | K16: =G16*1.05 -> 2205 | L16: ='Program Budget'!N18 -> 12 | M16: ='Program Budget'!M18 -> 0.05 | N16: =K16*L16*M16 -> 1323 | O16: =K16*1.05 -> 2315.25 | P16: ='Program Budget'!Q18 -> 12 | Q16: ='Program Budget'!P18 -> 0.05 | R16: =O16*P16*Q16 -> 1389.15 | S16: =O16*1.05 -> 2431.0125 | T16: ='Program Budget'!T18 -> 0 | U16: ='Program Budget'!S18 -> 0 | V16: =S16*T16*U16 -> 0 | W16: =F16+J16+N16+R16+V16 -> 7172.15
A17: ='Program Budget'!D19 -> Key Personnel: Finance & Administration (F&A) Director | B17: ='Program Budget'!F19 -> Month | C17: ='Program Budget'!H19 -> 3500 | D17: ='Program Budget'!G19 -> 10 | E17: ='Program Budget'!E19 -> 0.35 | F17: =C17*D17*E17 -> 12250 | G17: =C17*1.05 -> 3675 | H17: ='Program Budget'!K19 -> 12 | I17: ='Program Budget'!J19 -> 0.05 | J17: =G17*H17*I17 -> 2205 | K17: =G17*1.05 -> 3858.75 | L17: ='Program Budget'!N19 -> 12 | M17: ='Program Budget'!M19 -> 0.05 | N17: =K17*L17*M17 -> 2315.25 | O17: =K17*1.05 -> 4051.6875 | P17: ='Program Budget'!Q19 -> 12 | Q17: ='Program Budget'!P19 -> 0.05 | R17: =O17*P17*Q17 -> 2431.0125 | S17: =O17*1.05 -> 4254.2719 | T17: ='Program Budget'!T19 -> 0 | U17: ='Program Budget'!S19 -> 0 | V17: =S17*T17*U17 -> 0 | W17: =F17+J17+N17+R17+V17 -> 19201.263
A18: ='Program Budget'!D20 -> Accountant | B18: ='Program Budget'!F20 -> Month | C18: ='Program Budget'!H20 -> 2000 | D18: ='Program Budget'!G20 -> 8 | E18: ='Program Budget'!E20 -> 0.2 | F18: =C18*D18*E18 -> 3200 | G18: =C18*1.05 -> 2100 | H18: ='Program Budget'!K20 -> 12 | I18: ='Program Budget'!J20 -> 0 | J18: =G18*H18*I18 -> 0 | K18: =G18*1.05 -> 2205 | L18: ='Program Budget'!N20 -> 12 | M18: ='Program Budget'!M20 -> 0 | N18: =K18*L18*M18 -> 0 | O18: =K18*1.05 -> 2315.25 | P18: ='Program Budget'!Q20 -> 12 | Q18: ='Program Budget'!P20 -> 0 | R18: =O18*P18*Q18 -> 0 | S18: =O18*1.05 -> 2431.0125 | T18: ='Program Budget'!T20 -> 0 | U18: ='Program Budget'!S20 -> 0 | V18: =S18*T18*U18 -> 0 | W18: =F18+J18+N18+R18+V18 -> 3200
A19: ='Program Budget'!D21 -> Administration/ HR Manager | B19: ='Program Budget'!F21 -> Month | C19: ='Program Budget'!H21 -> 2666.6667 | D19: ='Program Budget'!G21 -> 10 | E19: ='Program Budget'!E21 -> 0.35 | F19: =C19*D19*E19 -> 9333.3333 | G19: =C19*1.05 -> 2800 | H19: ='Program Budget'!K21 -> 12 | I19: ='Program Budget'!J21 -> 0.05 | J19: =G19*H19*I19 -> 1680 | K19: =G19*1.05 -> 2940 | L19: ='Program Budget'!N21 -> 12 | M19: ='Program Budget'!M21 -> 0.05 | N19: =K19*L19*M19 -> 1764 | O19: =K19*1.05 -> 3087 | P19: ='Program Budget'!Q21 -> 12 | Q19: ='Program Budget'!P21 -> 0.05 | R19: =O19*P19*Q19 -> 1852.2 | S19: =O19*1.05 -> 3241.35 | T19: ='Program Budget'!T21 -> 0 | U19: ='Program Budget'!S21 -> 0 | V19: =S19*T19*U19 -> 0 | W19: =F19+J19+N19+R19+V19 -> 14629.533
A20: ='Program Budget'!D22 -> Grants & Contracts Manager | B20: ='Program Budget'!F22 -> Month | C20: ='Program Budget'!H22 -> 2666.6667 | D20: ='Program Budget'!G22 -> 9 | E20: ='Program Budget'!E22 -> 0.28 | F20: =C20*D20*E20 -> 6720 | G20: =C20*1.05 -> 2800 | H20: ='Program Budget'!K22 -> 12 | I20: ='Program Budget'!J22 -> 0 | J20: =G20*H20*I20 -> 0 | K20: =G20*1.05 -> 2940 | L20: ='Program Budget'!N22 -> 12 | M20: ='Program Budget'!M22 -> 0 | N20: =K20*L20*M20 -> 0 | O20: =K20*1.05 -> 3087 | P20: ='Program Budget'!Q22 -> 12 | Q20: ='Program Budget'!P22 -> 0 | R20: =O20*P20*Q20 -> 0 | S20: =O20*1.05 -> 3241.35 | T20: ='Program Budget'!T22 -> 0 | U20: ='Program Budget'!S22 -> 0 | V20: =S20*T20*U20 -> 0 | W20: =F20+J20+N20+R20+V20 -> 6720
A21: ='Program Budget'!D23 -> Compliance & Procurement Specialist | B21: ='Program Budget'!F23 -> Month | C21: ='Program Budget'!H23 -> 2000 | D21: ='Program Budget'!G23 -> 9 | E21: ='Program Budget'!E23 -> 0.28 | F21: =C21*D21*E21 -> 5040 | G21: =C21*1.05 -> 2100 | H21: ='Program Budget'!K23 -> 12 | I21: ='Program Budget'!J23 -> 0 | J21: =G21*H21*I21 -> 0 | K21: =G21*1.05 -> 2205 | L21: ='Program Budget'!N23 -> 12 | M21: ='Program Budget'!M23 -> 0 | N21: =K21*L21*M21 -> 0 | O21: =K21*1.05 -> 2315.25 | P21: ='Program Budget'!Q23 -> 12 | Q21: ='Program Budget'!P23 -> 0 | R21: =O21*P21*Q21 -> 0 | S21: =O21*1.05 -> 2431.0125 | T21: ='Program Budget'!T23 -> 0 | U21: ='Program Budget'!S23 -> 0 | V21: =S21*T21*U21 -> 0 | W21: =F21+J21+N21+R21+V21 -> 5040
A22: ='Program Budget'!D24 -> Driver | B22: ='Program Budget'!F24 -> Month | C22: ='Program Budget'!H24 -> 500 | D22: ='Program Budget'!G24 -> 7 | E22: ='Program Budget'!E24 -> 0 | F22: =C22*D22*E22 -> 0 | G22: =C22*1.05 -> 525 | H22: ='Program Budget'!K24 -> 12 | I22: ='Program Budget'!J24 -> 0 | J22: =G22*H22*I22 -> 0 | K22: =G22*1.05 -> 551.25 | L22: ='Program Budget'!N24 -> 12 | M22: ='Program Budget'!M24 -> 0 | N22: =K22*L22*M22 -> 0 | O22: =K22*1.05 -> 578.8125 | P22: ='Program Budget'!Q24 -> 12 | Q22: ='Program Budget'!P24 -> 0 | R22: =O22*P22*Q22 -> 0 | S22: =O22*1.05 -> 607.75313 | T22: ='Program Budget'!T24 -> 0 | U22: ='Program Budget'!S24 -> 0 | V22: =S22*T22*U22 -> 0 | W22: =F22+J22+N22+R22+V22 -> 0
A23: Total Local Salary Cost | F23: =SUM(F9:F22) -> 126855 | J23: =SUM(J9:J22) -> 13387.5 | N23: =SUM(N9:N22) -> 14056.875 | R23: =SUM(R9:R22) -> 14759.719 | V23: =SUM(V9:V22) -> 0 | W23: =SUM(W9:W22) -> 169059.09
A24: HQ Staff
A25: ='Program Budget'!D26 -> Senior Vice President of Programs | B25: ='Program Budget'!F26 -> Month | C25: ='Program Budget'!H26 -> 13500 | D25: ='Program Budget'!G26 -> 12 | E25: ='Program Budget'!E26 -> 0.02 | F25: =C25*D25*E25 -> 3240 | G25: =C25*1.05 -> 14175 | H25: ='Program Budget'!K26 -> 12 | I25: ='Program Budget'!J26 -> 0.02 | J25: =G25*H25*I25 -> 3402 | K25: =G25*1.05 -> 14883.75 | L25: ='Program Budget'!N26 -> 12 | M25: ='Program Budget'!M26 -> 0.02 | N25: =K25*L25*M25 -> 3572.1 | O25: =K25*1.05 -> 15627.938 | P25: ='Program Budget'!Q26 -> 12 | Q25: ='Program Budget'!P26 -> 0.02 | R25: =O25*P25*Q25 -> 3750.705 | S25: =O25*1.05 -> 16409.334 | T25: ='Program Budget'!T26 -> 0 | U25: ='Program Budget'!S26 -> 0 | V25: =S25*T25*U25 -> 0 | W25: =F25+J25+N25+R25+V25 -> 13964.805
A26: ='Program Budget'!D27 -> Senior Program Director | B26: ='Program Budget'!F27 -> Month | C26: ='Program Budget'!H27 -> 12500 | D26: ='Program Budget'!G27 -> 12 | E26: ='Program Budget'!E27 -> 0.12 | F26: =C26*D26*E26 -> 18000 | G26: =C26*1.05 -> 13125 | H26: ='Program Budget'!K27 -> 12 | I26: ='Program Budget'!J27 -> 0.05 | J26: =G26*H26*I26 -> 7875 | K26: =G26*1.05 -> 13781.25 | L26: ='Program Budget'!N27 -> 12 | M26: ='Program Budget'!M27 -> 0.05 | N26: =K26*L26*M26 -> 8268.75 | O26: =K26*1.05 -> 14470.312 | P26: ='Program Budget'!Q27 -> 12 | Q26: ='Program Budget'!P27 -> 0.05 | R26: =O26*P26*Q26 -> 8682.1875 | S26: =O26*1.05 -> 15193.828 | T26: ='Program Budget'!T27 -> 0 | U26: ='Program Budget'!S27 -> 0 | V26: =S26*T26*U26 -> 0 | W26: =F26+J26+N26+R26+V26 -> 42825.938
A27: ='Program Budget'!D28 -> Associate Director | B27: ='Program Budget'!F28 -> Month | C27: ='Program Budget'!H28 -> 7500 | D27: ='Program Budget'!G28 -> 12 | E27: ='Program Budget'!E28 -> 0.5 | F27: =C27*D27*E27 -> 45000 | G27: =C27*1.05 -> 7875 | H27: ='Program Budget'!K28 -> 12 | I27: ='Program Budget'!J28 -> 0.05 | J27: =G27*H27*I27 -> 4725 | K27: =G27*1.05 -> 8268.75 | L27: ='Program Budget'!N28 -> 12 | M27: ='Program Budget'!M28 -> 0.05 | N27: =K27*L27*M27 -> 4961.25 | O27: =K27*1.05 -> 8682.1875 | P27: ='Program Budget'!Q28 -> 12 | Q27: ='Program Budget'!P28 -> 0.05 | R27: =O27*P27*Q27 -> 5209.3125 | S27: =O27*1.05 -> 9116.2969 | T27: ='Program Budget'!T28 -> 0 | U27: ='Program Budget'!S28 -> 0 | V27: =S27*T27*U27 -> 0 | W27: =F27+J27+N27+R27+V27 -> 59895.562
A28: ='Program Budget'!D29 -> Compliance & Contracts Director | B28: ='Program Budget'!F29 -> Month | C28: ='Program Budget'!H29 -> 9166.6667 | D28: ='Program Budget'!G29 -> 12 | E28: ='Program Budget'!E29 -> 0.12 | F28: =C28*D28*E28 -> 13200 | G28: =C28*1.05 -> 9625 | H28: ='Program Budget'!K29 -> 12 | I28: ='Program Budget'!J29 -> 0.05 | J28: =G28*H28*I28 -> 5775 | K28: =G28*1.05 -> 10106.25 | L28: ='Program Budget'!N29 -> 12 | M28: ='Program Budget'!M29 -> 0.05 | N28: =K28*L28*M28 -> 6063.75 | O28: =K28*1.05 -> 10611.562 | P28: ='Program Budget'!Q29 -> 12 | Q28: ='Program Budget'!P29 -> 0.05 | R28: =O28*P28*Q28 -> 6366.9375 | S28: =O28*1.05 -> 11142.141 | T28: ='Program Budget'!T29 -> 0 | U28: ='Program Budget'!S29 -> 0 | V28: =S28*T28*U28 -> 0 | W28: =F28+J28+N28+R28+V28 -> 31405.688
A29: ='Program Budget'!D30 -> Finance, HR, & Administration Home Office Support | B29: ='Program Budget'!F30 -> Month | C29: ='Program Budget'!H30 -> 7500 | D29: ='Program Budget'!G30 -> 12 | E29: ='Program Budget'!E30 -> 0.35 | F29: =C29*D29*E29 -> 31500 | G29: =C29*1.05 -> 7875 | H29: ='Program Budget'!K30 -> 12 | I29: ='Program Budget'!J30 -> 0.05 | J29: =G29*H29*I29 -> 4725 | K29: =G29*1.05 -> 8268.75 | L29: ='Program Budget'!N30 -> 12 | M29: ='Program Budget'!M30 -> 0.05 | N29: =K29*L29*M29 -> 4961.25 | O29: =K29*1.05 -> 8682.1875 | P29: ='Program Budget'!Q30 -> 12 | Q29: ='Program Budget'!P30 -> 0.05 | R29: =O29*P29*Q29 -> 5209.3125 | S29: =O29*1.05 -> 9116.2969 | T29: ='Program Budget'!T30 -> 0 | U29: ='Program Budget'!S30 -> 0 | V29: =S29*T29*U29 -> 0 | W29: =F29+J29+N29+R29+V29 -> 46395.562
A30: Total HQ Staff | F30: =SUM(F24:F29) -> 110940 | J30: =SUM(J24:J29) -> 26502 | N30: =SUM(N24:N29) -> 27827.1 | R30: =SUM(R24:R29) -> 29218.455 | V30: =SUM(V24:V29) -> 0 | W30: =SUM(W24:W29) -> 194487.55
A32: Subtotal: Salaries & Wages | F32: =F30+F23+F8 -> 237795 | J32: =J30+J23+J8 -> 39889.5 | N32: =N30+N23+N8 -> 41883.975 | R32: =R30+R23+R8 -> 43978.174 | V32: =V30+V23+V8 -> 0 | W32: =+F32+J32+N32+R32+V32 -> 363546.65
A33: Fringe
A34: USN/TCN Staff | B34: ='Program Budget'!F35 -> % | C34: =F8 -> 0 | D34: 1 | E34: 0 | F34: =C34*D34*E34 -> 0 | G34: =J8 -> 0 | H34: 1 | I34: =E34 -> 0 | J34: =G34*H34*I34 -> 0 | K34: =N8 -> 0 | L34: 1 | M34: =E34 -> 0 | N34: =K34*L34*M34 -> 0 | O34: =R8 -> 0 | P34: 1 | Q34: =E34 -> 0 | R34: =O34*P34*Q34 -> 0 | S34: =V8 -> 0 | T34: 1 | U34: =E34 -> 0 | V34: =S34*T34*U34 -> 0 | W34: =F34+J34+N34+R34+V34 -> 0
A35: ='Program Budget'!D35 -> Fringe Benefits CCN - Nigeria | B35: ='Program Budget'!F36 -> % | C35: =F23 -> 126855 | D35: 1 | E35: ='Program Budget'!H35 -> 0.296 | F35: =C35*D35*E35 -> 37549.08 | G35: =J23 -> 13387.5 | H35: 1 | I35: =E35 -> 0.296 | J35: =G35*H35*I35 -> 3962.7 | K35: =N23 -> 14056.875 | L35: 1 | M35: =E35 -> 0.296 | N35: =K35*L35*M35 -> 4160.835 | O35: =R23 -> 14759.719 | P35: 1 | Q35: =E35 -> 0.296 | R35: =O35*P35*Q35 -> 4368.8768 | S35: =V23 -> 0 | T35: 1 | U35: 0 | V35: =S35*T35*U35 -> 0 | W35: =F35+J35+N35+R35+V35 -> 50041.492
A36: HQ Staff | B36: ='Program Budget'!F36 -> % | C36: =F30 -> 110940 | D36: 1 | E36: ='Program Budget'!H36 -> 0.2347 | F36: =C36*D36*E36 -> 26037.618 | G36: =J30 -> 26502 | H36: 1 | I36: =E36 -> 0.2347 | J36: =G36*H36*I36 -> 6220.0194 | K36: =N30 -> 27827.1 | L36: 1 | M36: =E36 -> 0.2347 | N36: =K36*L36*M36 -> 6531.0204 | O36: =R30 -> 29218.455 | P36: 1 | Q36: =E36 -> 0.2347 | R36: =O36*P36*Q36 -> 6857.5714 | S36: =V30 -> 0 | T36: 1 | U36: 0 | V36: =S36*T36*U36 -> 0 | W36: =F36+J36+N36+R36+V36 -> 45646.229
A37: Total: Fringe Benefits | F37: =+SUM(F34:F36) -> 63586.698 | J37: =+SUM(J34:J36) -> 10182.719 | N37: =+SUM(N34:N36) -> 10691.855 | R37: =+SUM(R34:R36) -> 11226.448 | V37: =+SUM(V34:V36) -> 0 | W37: =+F37+J37+N37+R37+V37 -> 95687.721
A38: Allowances
A39: None | F39: =C39*D39*E39 -> 0 | J39: =G39*H39*I39 -> 0 | N39: =K39*L39*M39 -> 0 | R39: =O39*P39*Q39 -> 0 | V39: =S39*T39*U39 -> 0 | W39: =F39+J39+N39+R39+V39 -> 0
A40: Total: Allowances | F40: =SUM(F39:F39) -> 0 | J40: =SUM(J39:J39) -> 0 | N40: =SUM(N39:N39) -> 0 | R40: =SUM(R39:R39) -> 0 | V40: =SUM(V39:V39) -> 0 | W40: =SUM(W39:W39) -> 0
A42: Subtotal: Benefits | F42: =F40+F37 -> 63586.698 | J42: =J40+J37 -> 10182.719 | N42: =N40+N37 -> 10691.855 | R42: =R40+R37 -> 11226.448 | V42: =V40+V37 -> 0 | W42: =+F42+J42+N42+R42+V42 -> 95687.721
A43: International Travel
A44: ='Program Budget'!D42 -> Airfare - DC-Nigeria - HO Project Management Trip | B44: ='Program Budget'!F42 -> Trip | C44: ='Program Budget'!H42 -> 1800 | D44: ='Program Budget'!G42 -> 3 | E44: 1 | F44: =C44*D44*E44 -> 5400 | G44: =C44*1.05 -> 1890 | H44: ='Program Budget'!K42 -> 2 | I44: 1 | J44: =G44*H44*I44 -> 3780 | K44: =G44*1.05 -> 1984.5 | L44: ='Program Budget'!N42 -> 2 | M44: 1 | N44: =K44*L44*M44 -> 3969 | O44: =K44*1.05 -> 2083.725 | P44: ='Program Budget'!Q42 -> 2 | Q44: 1 | R44: =O44*P44*Q44 -> 4167.45 | S44: =O44*1.05 -> 2187.9113 | T44: ='Program Budget'!T42 -> 0 | U44: 0 | V44: =S44*T44*U44 -> 0 | W44: =F44+J44+N44+R44+V44 -> 17316.45
A45: ='Program Budget'!D48 -> Airfare - Roundtrip - Nigeria to USA | B45: ='Program Budget'!F48 -> Trip | C45: ='Program Budget'!H48 -> 1800 | D45: ='Program Budget'!G48 -> 3 | E45: 1 | F45: =C45*D45*E45 -> 5400 | G45: =C45*1.05 -> 1890 | H45: ='Program Budget'!K48 -> 3 | I45: 1 | J45: =G45*H45*I45 -> 5670 | K45: =G45*1.05 -> 1984.5 | L45: ='Program Budget'!N48 -> 3 | M45: 1 | N45: =K45*L45*M45 -> 5953.5 | O45: =K45*1.05 -> 2083.725 | P45: ='Program Budget'!Q48 -> 3 | Q45: 1 | R45: =O45*P45*Q45 -> 6251.175 | S45: =O45*1.05 -> 2187.9113 | T45: ='Program Budget'!T48 -> 0 | U45: 0 | V45: =S45*T45*U45 -> 0 | W45: =F45+J45+N45+R45+V45 -> 23274.675
A46: Local Travel
A47: ='Program Budget'!D44 -> Ground Transportation – HO Project Management Trip | B47: ='Program Budget'!F44 -> Trip | C47: ='Program Budget'!H44 -> 150 | D47: ='Program Budget'!G44 -> 3 | E47: 1 | F47: =C47*D47*E47 -> 450 | G47: =C47*1.05 -> 157.5 | H47: ='Program Budget'!K44 -> 2 | I47: 1 | J47: =G47*H47*I47 -> 315 | K47: =G47*1.05 -> 165.375 | L47: ='Program Budget'!N44 -> 2 | M47: 1 | N47: =K47*L47*M47 -> 330.75 | O47: =K47*1.05 -> 173.64375 | P47: ='Program Budget'!Q44 -> 2 | Q47: 1 | R47: =O47*P47*Q47 -> 347.2875 | S47: =O47*1.05 -> 182.32594 | T47: ='Program Budget'!T44 -> 0 | U47: 0 | V47: =S47*T47*U47 -> 0 | W47: =F47+J47+N47+R47+V47 -> 1443.0375
A48: ='Program Budget'!D50 -> Ground Transportation for Nigeria Staff Travel | B48: ='Program Budget'!F50 -> Trip | C48: ='Program Budget'!H50 -> 250 | D48: ='Program Budget'!G50 -> 3 | E48: 1 | F48: =C48*D48*E48 -> 750 | G48: =C48*1.05 -> 262.5 | H48: ='Program Budget'!K50 -> 3 | I48: 1 | J48: =G48*H48*I48 -> 787.5 | K48: =G48*1.05 -> 275.625 | L48: ='Program Budget'!N50 -> 3 | M48: 1 | N48: =K48*L48*M48 -> 826.875 | O48: =K48*1.05 -> 289.40625 | P48: ='Program Budget'!Q50 -> 3 | Q48: 1 | R48: =O48*P48*Q48 -> 868.21875 | S48: =O48*1.05 -> 303.87656 | T48: ='Program Budget'!T50 -> 0 | U48: 0 | V48: =S48*T48*U48 -> 0 | W48: =F48+J48+N48+R48+V48 -> 3232.5938
A49: ='Program Budget'!D55 -> Roundtrip Domestic Airfare - Lagos to Implementing Regions – Training, M&E, & Data Collection | B49: ='Program Budget'!F55 -> Trip | C49: ='Program Budget'!H55 -> 250 | D49: ='Program Budget'!G55 -> 36 | E49: 1 | F49: =C49*D49*E49 -> 9000 | G49: =C49*1.05 -> 262.5 | H49: ='Program Budget'!K55 -> 36 | I49: 1 | J49: =G49*H49*I49 -> 9450 | K49: =G49*1.05 -> 275.625 | L49: ='Program Budget'!N55 -> 36 | M49: 1 | N49: =K49*L49*M49 -> 9922.5 | O49: =K49*1.05 -> 289.40625 | P49: ='Program Budget'!Q55 -> 36 | Q49: 1 | R49: =O49*P49*Q49 -> 10418.625 | S49: =O49*1.05 -> 303.87656 | T49: ='Program Budget'!T55 -> 0 | U49: 0 | V49: =S49*T49*U49 -> 0 | W49: =F49+J49+N49+R49+V49 -> 38791.125
A50: ='Program Budget'!D56 -> Local Transportation (Car Rental, Taxis) – Training, M&E, & Data Collection | B50: ='Program Budget'!F56 -> Trip | C50: ='Program Budget'!H56 -> 30 | D50: ='Program Budget'!G56 -> 36 | E50: 1 | F50: =C50*D50*E50 -> 1080 | G50: =C50*1.05 -> 31.5 | H50: ='Program Budget'!K56 -> 36 | I50: 1 | J50: =G50*H50*I50 -> 1134 | K50: =G50*1.05 -> 33.075 | L50: ='Program Budget'!N56 -> 36 | M50: 1 | N50: =K50*L50*M50 -> 1190.7 | O50: =K50*1.05 -> 34.72875 | P50: ='Program Budget'!Q56 -> 36 | Q50: 1 | R50: =O50*P50*Q50 -> 1250.235 | S50: =O50*1.05 -> 36.465188 | T50: ='Program Budget'!T56 -> 0 | U50: 0 | V50: =S50*T50*U50 -> 0 | W50: =F50+J50+N50+R50+V50 -> 4654.935
A51: Vehicle Fuel
A52: ='Program Budget'!D54 -> Vehicle Fuel Expense (for Field Office Vehicles) | B52: ='Program Budget'!F54 -> Month | C52: ='Program Budget'!H54 -> 50 | D52: ='Program Budget'!G54 -> 3 | E52: 1 | F52: =C52*D52*E52 -> 150 | G52: =C52*1.05 -> 52.5 | H52: ='Program Budget'!K54 -> 12 | I52: 1 | J52: =G52*H52*I52 -> 630 | K52: =G52*1.05 -> 55.125 | L52: ='Program Budget'!N54 -> 12 | M52: 1 | N52: =K52*L52*M52 -> 661.5 | O52: =K52*1.05 -> 57.88125 | P52: ='Program Budget'!Q54 -> 12 | Q52: 1 | R52: =O52*P52*Q52 -> 694.575 | S52: =O52*1.05 -> 60.775313 | T52: ='Program Budget'!T54 -> 0 | U52: 0 | V52: =S52*T52*U52 -> 0 | W52: =F52+J52+N52+R52+V52 -> 2136.075
A53: Per Diem & Lodging
A54: ='Program Budget'!D43 -> Lodging and M&IE - HO Project Management Trip | B54: ='Program Budget'!F43 -> Day | C54: ='Program Budget'!H43 -> 310.5 | D54: ='Program Budget'!G43 -> 30 | E54: 1 | F54: =C54*D54*E54 -> 9315 | G54: =C54*1.05 -> 326.025 | H54: ='Program Budget'!K43 -> 20 | I54: 1 | J54: =G54*H54*I54 -> 6520.5 | K54: =G54*1.05 -> 342.32625 | L54: ='Program Budget'!N43 -> 20 | M54: 1 | N54: =K54*L54*M54 -> 6846.525 | O54: =K54*1.05 -> 359.44256 | P54: ='Program Budget'!Q43 -> 20 | Q54: 1 | R54: =O54*P54*Q54 -> 7188.8513 | S54: =O54*1.05 -> 377.41469 | T54: ='Program Budget'!T43 -> 0 | U54: 0 | V54: =S54*T54*U54 -> 0 | W54: =F54+J54+N54+R54+V54 -> 29870.876
A55: ='Program Budget'!D45 -> Other Travel Related Expenses – HO Project Management Trip | B55: ='Program Budget'!F45 -> Trip | C55: ='Program Budget'!H45 -> 150 | D55: ='Program Budget'!G45 -> 3 | E55: 1 | F55: =C55*D55*E55 -> 450 | G55: =C55*1.05 -> 157.5 | H55: ='Program Budget'!K45 -> 2 | I55: 1 | J55: =G55*H55*I55 -> 315 | K55: =G55*1.05 -> 165.375 | L55: ='Program Budget'!N45 -> 2 | M55: 1 | N55: =K55*L55*M55 -> 330.75 | O55: =K55*1.05 -> 173.64375 | P55: ='Program Budget'!Q45 -> 2 | Q55: 1 | R55: =O55*P55*Q55 -> 347.2875 | S55: =O55*1.05 -> 182.32594 | T55: ='Program Budget'!T45 -> 0 | U55: 0 | V55: =S55*T55*U55 -> 0 | W55: =F55+J55+N55+R55+V55 -> 1443.0375
A56: ='Program Budget'!D46 -> Visa Cost for US Staff Travel | B56: ='Program Budget'!F46 -> Trip | C56: ='Program Budget'!H46 -> 160 | D56: ='Program Budget'!G46 -> 3 | E56: 1 | F56: =C56*D56*E56 -> 480 | G56: =C56*1.05 -> 168 | H56: ='Program Budget'!K46 -> 2 | I56: 1 | J56: =G56*H56*I56 -> 336 | K56: =G56*1.05 -> 176.4 | L56: ='Program Budget'!N46 -> 2 | M56: 1 | N56: =K56*L56*M56 -> 352.8 | O56: =K56*1.05 -> 185.22 | P56: ='Program Budget'!Q46 -> 2 | Q56: 1 | R56: =O56*P56*Q56 -> 370.44 | S56: =O56*1.05 -> 194.481 | T56: ='Program Budget'!T46 -> 0 | U56: 0 | V56: =S56*T56*U56 -> 0 | W56: =F56+J56+N56+R56+V56 -> 1539.24
A57: ='Program Budget'!D49 -> Lodging and M&IE for Nigeria Staff Travel | B57: ='Program Budget'!F49 -> Day | C57: ='Program Budget'!H49 -> 262.8 | D57: ='Program Budget'!G49 -> 21 | E57: 1 | F57: =C57*D57*E57 -> 5518.8 | G57: =C57*1.05 -> 275.94 | H57: ='Program Budget'!K49 -> 21 | I57: 1 | J57: =G57*H57*I57 -> 5794.74 | K57: =G57*1.05 -> 289.737 | L57: ='Program Budget'!N49 -> 21 | M57: 1 | N57: =K57*L57*M57 -> 6084.477 | O57: =K57*1.05 -> 304.22385 | P57: ='Program Budget'!Q49 -> 21 | Q57: 1 | R57: =O57*P57*Q57 -> 6388.7009 | S57: =O57*1.05 -> 319.43504 | T57: ='Program Budget'!T49 -> 0 | U57: 0 | V57: =S57*T57*U57 -> 0 | W57: =F57+J57+N57+R57+V57 -> 23786.718
A58: ='Program Budget'!D51 -> Other Travel Related Expenses for Nigeria Staff Travel | B58: ='Program Budget'!F51 -> Trip | C58: ='Program Budget'!H51 -> 150 | D58: ='Program Budget'!G51 -> 3 | E58: 1 | F58: =C58*D58*E58 -> 450 | G58: =C58*1.05 -> 157.5 | H58: ='Program Budget'!K51 -> 3 | I58: 1 | J58: =G58*H58*I58 -> 472.5 | K58: =G58*1.05 -> 165.375 | L58: ='Program Budget'!N51 -> 3 | M58: 1 | N58: =K58*L58*M58 -> 496.125 | O58: =K58*1.05 -> 173.64375 | P58: ='Program Budget'!Q51 -> 3 | Q58: 1 | R58: =O58*P58*Q58 -> 520.93125 | S58: =O58*1.05 -> 182.32594 | T58: ='Program Budget'!T51 -> 0 | U58: 0 | V58: =S58*T58*U58 -> 0 | W58: =F58+J58+N58+R58+V58 -> 1939.5563
A59: ='Program Budget'!D52 -> Visa Cost for Nigerian Staff Travel | B59: ='Program Budget'!F52 -> Trip | C59: ='Program Budget'!H52 -> 185 | D59: ='Program Budget'!G52 -> 4 | E59: 1 | F59: =C59*D59*E59 -> 740 | G59: =C59*1.05 -> 194.25 | H59: ='Program Budget'!K52 -> 2 | I59: 1 | J59: =G59*H59*I59 -> 388.5 | K59: =G59*1.05 -> 203.9625 | L59: ='Program Budget'!N52 -> 0 | M59: 1 | N59: =K59*L59*M59 -> 0 | O59: =K59*1.05 -> 214.16063 | P59: ='Program Budget'!Q52 -> 0 | Q59: 1 | R59: =O59*P59*Q59 -> 0 | S59: =O59*1.05 -> 224.86866 | T59: ='Program Budget'!T52 -> 0 | U59: 0 | V59: =S59*T59*U59 -> 0 | W59: =F59+J59+N59+R59+V59 -> 1128.5
A60: ='Program Budget'!D57 -> Lodging and M&IE - Training, M&E, & Data Collection | B60: ='Program Budget'!F57 -> Day | C60: ='Program Budget'!H57 -> 145.5 | D60: ='Program Budget'!G57 -> 144 | E60: 1 | F60: =C60*D60*E60 -> 20952 | G60: =C60*1.05 -> 152.775 | H60: ='Program Budget'!K57 -> 144 | I60: 1 | J60: =G60*H60*I60 -> 21999.6 | K60: =G60*1.05 -> 160.41375 | L60: ='Program Budget'!N57 -> 144 | M60: 1 | N60: =K60*L60*M60 -> 23099.58 | O60: =K60*1.05 -> 168.43444 | P60: ='Program Budget'!Q57 -> 144 | Q60: 1 | R60: =O60*P60*Q60 -> 24254.559 | S60: =O60*1.05 -> 176.85616 | T60: ='Program Budget'!T57 -> 0 | U60: 0 | V60: =S60*T60*U60 -> 0 | W60: =F60+J60+N60+R60+V60 -> 90305.739
A62: Subtotal: Travel | F62: =SUM(F43:F61) -> 60135.8 | J62: =SUM(J43:J61) -> 57593.34 | N62: =SUM(N43:N61) -> 60065.082 | R62: =SUM(R43:R61) -> 63068.336 | V62: =SUM(V43:V61) -> 0 | W62: =+F62+J62+N62+R62+V62 -> 240862.56
A63: Professional Services/Contractual
A64: ='Program Budget'!D61 -> Monetization Agent Fee | B64: ='Program Budget'!F61 -> % | C64: ='Program Budget'!G61 -> 10790000 | D64: 1 | E64: ='Program Budget'!H61 -> 0.0167 | F64: =C64*D64*E64 -> 180193 | G64: 0 | H64: 0 | I64: 0 | J64: =G64*H64*I64 -> 0 | K64: =G64 -> 0 | L64: ='Program Budget'!N61 -> 0 | M64: 0 | N64: =K64*L64*M64 -> 0 | O64: =K64 -> 0 | P64: ='Program Budget'!Q61 -> 0 | Q64: 0 | R64: =O64*P64*Q64 -> 0 | S64: =O64 -> 0 | T64: ='Program Budget'!T61 -> 0 | U64: 0 | V64: =S64*T64*U64 -> 0 | W64: =F64+J64+N64+R64+V64 -> 180193
A65: ='Program Budget'!D62 -> Monetization Impact Assessment | B65: ='Program Budget'!F62 -> Unit | C65: ='Program Budget'!H62 -> 60000 | D65: ='Program Budget'!G62 -> 0 | E65: 0 | F65: =C65*D65*E65 -> 0 | G65: =C65 -> 60000 | H65: ='Program Budget'!K62 -> 1 | I65: 1 | J65: =G65*H65*I65 -> 60000 | K65: =G65 -> 60000 | L65: ='Program Budget'!N62 -> 0 | M65: 0 | N65: =K65*L65*M65 -> 0 | O65: =K65 -> 60000 | P65: ='Program Budget'!Q62 -> 0 | Q65: 0 | R65: =O65*P65*Q65 -> 0 | S65: =O65 -> 60000 | T65: ='Program Budget'!T62 -> 0 | U65: 0 | V65: =S65*T65*U65 -> 0 | W65: =F65+J65+N65+R65+V65 -> 60000
A66: ='Program Budget'!D63 -> Single Audit | B66: ='Program Budget'!F63 -> Year | C66: ='Program Budget'!H63 -> 13000 | D66: ='Program Budget'!G63 -> 1 | E66: 1 | F66: =C66*D66*E66 -> 13000 | G66: =C66 -> 13000 | H66: ='Program Budget'!K63 -> 1 | I66: 1 | J66: =G66*H66*I66 -> 13000 | K66: =G66 -> 13000 | L66: ='Program Budget'!N63 -> 1 | M66: 1 | N66: =K66*L66*M66 -> 13000 | O66: =K66 -> 13000 | P66: ='Program Budget'!Q63 -> 1 | Q66: 1 | R66: =O66*P66*Q66 -> 13000 | S66: =O66 -> 13000 | T66: ='Program Budget'!T63 -> 0 | U66: 0 | V66: =S66*T66*U66 -> 0 | W66: =F66+J66+N66+R66+V66 -> 52000
A67: ='Program Budget'!D64 -> Payroll Processing and Local Accounting Books Preparation | B67: ='Program Budget'!F64 -> Month | C67: ='Program Budget'!H64 -> 2000 | D67: ='Program Budget'!G64 -> 12 | E67: 1 | F67: =C67*D67*E67 -> 24000 | G67: =C67 -> 2000 | H67: ='Program Budget'!K64 -> 12 | I67: 1 | J67: =G67*H67*I67 -> 24000 | K67: =G67 -> 2000 | L67: ='Program Budget'!N64 -> 12 | M67: 1 | N67: =K67*L67*M67 -> 24000 | O67: =K67 -> 2000 | P67: ='Program Budget'!Q64 -> 12 | Q67: 1 | R67: =O67*P67*Q67 -> 24000 | S67: =O67 -> 2000 | T67: ='Program Budget'!T64 -> 0 | U67: 0 | V67: =S67*T67*U67 -> 0 | W67: =F67+J67+N67+R67+V67 -> 96000
A68: ='Program Budget'!D65 -> Legal & Registration Fees | B68: ='Program Budget'!F65 -> Year | C68: ='Program Budget'!H65 -> 3000 | D68: ='Program Budget'!G65 -> 1 | E68: 1 | F68: =C68*D68*E68 -> 3000 | G68: =C68 -> 3000 | H68: ='Program Budget'!K65 -> 1 | I68: 1 | J68: =G68*H68*I68 -> 3000 | K68: =G68 -> 3000 | L68: ='Program Budget'!N65 -> 1 | M68: 1 | N68: =K68*L68*M68 -> 3000 | O68: =K68 -> 3000 | P68: ='Program Budget'!Q65 -> 1 | Q68: 1 | R68: =O68*P68*Q68 -> 3000 | S68: =O68 -> 3000 | T68: ='Program Budget'!T65 -> 0 | U68: 0 | V68: =S68*T68*U68 -> 0 | W68: =F68+J68+N68+R68+V68 -> 12000
A69: ='Program Budget'!D66 -> IT Services & Management | B69: ='Program Budget'!F66 -> Month | C69: ='Program Budget'!H66 -> 500 | D69: ='Program Budget'!G66 -> 12 | E69: 1 | F69: =C69*D69*E69 -> 6000 | G69: =C69 -> 500 | H69: ='Program Budget'!K66 -> 12 | I69: 1 | J69: =G69*H69*I69 -> 6000 | K69: =G69 -> 500 | L69: ='Program Budget'!N66 -> 12 | M69: 1 | N69: =K69*L69*M69 -> 6000 | O69: =K69 -> 500 | P69: ='Program Budget'!Q66 -> 12 | Q69: 1 | R69: =O69*P69*Q69 -> 6000 | S69: =O69 -> 500 | T69: ='Program Budget'!T66 -> 0 | U69: 0 | V69: =S69*T69*U69 -> 0 | W69: =F69+J69+N69+R69+V69 -> 24000
A70: ='Program Budget'!D67 -> Security Services, Risk Assessments, & Security Assessment | B70: ='Program Budget'!F67 -> Year | C70: ='Program Budget'!H67 -> 1000 | D70: ='Program Budget'!G67 -> 1 | E70: 1 | F70: =C70*D70*E70 -> 1000 | G70: =C70 -> 1000 | H70: ='Program Budget'!K67 -> 1 | I70: 1 | J70: =G70*H70*I70 -> 1000 | K70: =G70 -> 1000 | L70: ='Program Budget'!N67 -> 1 | M70: 1 | N70: =K70*L70*M70 -> 1000 | O70: =K70 -> 1000 | P70: ='Program Budget'!Q67 -> 1 | Q70: 1 | R70: =O70*P70*Q70 -> 1000 | S70: =O70 -> 1000 | T70: ='Program Budget'!T67 -> 0 | U70: 0 | V70: =S70*T70*U70 -> 0 | W70: =F70+J70+N70+R70+V70 -> 4000
A71: ='Program Budget'!D68 -> Short-Term Administrative Support Consultants | B71: ='Program Budget'!F68 -> Day | C71: ='Program Budget'!H68 -> 520 | D71: ='Program Budget'!G68 -> 15 | E71: 1 | F71: =C71*D71*E71 -> 7800 | G71: =C71 -> 520 | H71: ='Program Budget'!K68 -> 15 | I71: 1 | J71: =G71*H71*I71 -> 7800 | K71: =G71 -> 520 | L71: ='Program Budget'!N68 -> 15 | M71: 1 | N71: =K71*L71*M71 -> 7800 | O71: =K71 -> 520 | P71: ='Program Budget'!Q68 -> 15 | Q71: 1 | R71: =O71*P71*Q71 -> 7800 | S71: =O71 -> 520 | T71: ='Program Budget'!T68 -> 0 | U71: 0 | V71: =S71*T71*U71 -> 0 | W71: =F71+J71+N71+R71+V71 -> 31200
A72: ='Program Budget'!D70 -> Evaluations
A73: ='Program Budget'!D71 -> Baseline Evaluation | B73: ='Program Budget'!F71 -> Unit | C73: ='Program Budget'!H71 -> 150000 | D73: ='Program Budget'!G71 -> 1 | E73: 1 | F73: =C73*D73*E73 -> 150000 | G73: =C73 -> 150000 | H73: ='Program Budget'!K71 -> 0 | I73: 0 | J73: =G73*H73*I73 -> 0 | K73: =G73 -> 150000 | L73: ='Program Budget'!N71 -> 0 | M73: 0 | N73: =K73*L73*M73 -> 0 | O73: =K73 -> 150000 | P73: ='Program Budget'!Q71 -> 0 | Q73: 0 | R73: =O73*P73*Q73 -> 0 | S73: =O73 -> 150000 | T73: ='Program Budget'!T71 -> 0 | U73: 0 | V73: =S73*T73*U73 -> 0 | W73: =F73+J73+N73+R73+V73 -> 150000
A74: ='Program Budget'!D72 -> Midterm Evaluation | B74: ='Program Budget'!F72 -> Unit | C74: ='Program Budget'!H72 -> 160000 | D74: ='Program Budget'!G72 -> 0 | E74: 0 | F74: =C74*D74*E74 -> 0 | G74: =C74 -> 160000 | H74: ='Program Budget'!K72 -> 0 | I74: 0 | J74: =G74*H74*I74 -> 0 | K74: =G74 -> 160000 | L74: ='Program Budget'!N72 -> 1 | M74: 1 | N74: =K74*L74*M74 -> 160000 | O74: =K74 -> 160000 | P74: ='Program Budget'!Q72 -> 0 | Q74: 0 | R74: =O74*P74*Q74 -> 0 | S74: =O74 -> 160000 | T74: ='Program Budget'!T72 -> 0 | U74: 0 | V74: =S74*T74*U74 -> 0 | W74: =F74+J74+N74+R74+V74 -> 160000
A75: ='Program Budget'!D73 -> Final Evaluation | B75: ='Program Budget'!F73 -> Unit | C75: ='Program Budget'!H73 -> 175000 | D75: ='Program Budget'!G73 -> 0 | E75: 0 | F75: =C75*D75*E75 -> 0 | G75: =C75 -> 175000 | H75: ='Program Budget'!K73 -> 0 | I75: 0 | J75: =G75*H75*I75 -> 0 | K75: =G75 -> 175000 | L75: ='Program Budget'!N73 -> 0 | M75: 0 | N75: =K75*L75*M75 -> 0 | O75: =K75 -> 175000 | P75: ='Program Budget'!Q73 -> 1 | Q75: 1 | R75: =O75*P75*Q75 -> 175000 | S75: =O75 -> 175000 | T75: ='Program Budget'!T73 -> 0 | U75: 0 | V75: =S75*T75*U75 -> 0 | W75: =F75+J75+N75+R75+V75 -> 175000
A76: ='Program Budget'!D74 -> Monitoring Guidelines Development
A77: ='Program Budget'!D75 -> Monitoring Guidelines Creation & Printing | B77: ='Program Budget'!F75 -> Document | C77: ='Program Budget'!H75 -> 2000 | D77: ='Program Budget'!G75 -> 1 | E77: 1 | F77: =C77*D77*E77 -> 2000 | G77: =C77 -> 2000 | H77: ='Program Budget'!K75 -> 0 | I77: 0 | J77: =G77*H77*I77 -> 0 | K77: =G77 -> 2000 | L77: ='Program Budget'!N75 -> 0 | M77: 0 | N77: =K77*L77*M77 -> 0 | O77: =K77 -> 2000 | P77: ='Program Budget'!Q75 -> 0 | Q77: 0 | R77: =O77*P77*Q77 -> 0 | S77: =O77 -> 2000 | T77: ='Program Budget'!T75 -> 0 | U77: 0 | V77: =S77*T77*U77 -> 0 | W77: =F77+J77+N77+R77+V77 -> 2000
A78: ='Program Budget'!D76 -> Monitoring Guidelines Revision & Printing | B78: ='Program Budget'!F76 -> Year | C78: ='Program Budget'!H76 -> 1000 | D78: ='Program Budget'!G76 -> 0 | E78: 0 | F78: =C78*D78*E78 -> 0 | G78: =C78 -> 1000 | H78: ='Program Budget'!K76 -> 1 | I78: 1 | J78: =G78*H78*I78 -> 1000 | K78: =G78 -> 1000 | L78: ='Program Budget'!N76 -> 1 | M78: 1 | N78: =K78*L78*M78 -> 1000 | O78: =K78 -> 1000 | P78: ='Program Budget'!Q76 -> 1 | Q78: 1 | R78: =O78*P78*Q78 -> 1000 | S78: =O78 -> 1000 | T78: ='Program Budget'!T76 -> 0 | U78: 0 | V78: =S78*T78*U78 -> 0 | W78: =F78+J78+N78+R78+V78 -> 3000
A79: ='Program Budget'!D77 -> Monitoring Guidelines Staff Training on Indicators and Data Collection/Analysis | B79: ='Program Budget'!F77 -> Workshop | C79: ='Program Budget'!H77 -> 2500 | D79: ='Program Budget'!G77 -> 1 | E79: 1 | F79: =C79*D79*E79 -> 2500 | G79: =C79 -> 2500 | H79: ='Program Budget'!K77 -> 1 | I79: 1 | J79: =G79*H79*I79 -> 2500 | K79: =G79 -> 2500 | L79: ='Program Budget'!N77 -> 1 | M79: 1 | N79: =K79*L79*M79 -> 2500 | O79: =K79 -> 2500 | P79: ='Program Budget'!Q77 -> 1 | Q79: 1 | R79: =O79*P79*Q79 -> 2500 | S79: =O79 -> 2500 | T79: ='Program Budget'!T77 -> 0 | U79: 0 | V79: =S79*T79*U79 -> 0 | W79: =F79+J79+N79+R79+V79 -> 10000
A80: ='Program Budget'!D78 -> M&E Database
A81: ='Program Budget'!D79 -> M&E Database Trainings | B81: ='Program Budget'!F79 -> Year | C81: ='Program Budget'!H79 -> 500 | D81: ='Program Budget'!G79 -> 1 | E81: 1 | F81: =C81*D81*E81 -> 500 | G81: =C81 -> 500 | H81: ='Program Budget'!K79 -> 1 | I81: 1 | J81: =G81*H81*I81 -> 500 | K81: =G81 -> 500 | L81: ='Program Budget'!N79 -> 1 | M81: 1 | N81: =K81*L81*M81 -> 500 | O81: =K81 -> 500 | P81: ='Program Budget'!Q79 -> 1 | Q81: 1 | R81: =O81*P81*Q81 -> 500 | S81: =O81 -> 500 | T81: ='Program Budget'!T79 -> 0 | U81: 0 | V81: =S81*T81*U81 -> 0 | W81: =F81+J81+N81+R81+V81 -> 2000
A82: ='Program Budget'!D80 -> M&E Database Platform Startup | B82: ='Program Budget'!F80 -> Year | C82: ='Program Budget'!H80 -> 5500 | D82: ='Program Budget'!G80 -> 1 | E82: 1 | F82: =C82*D82*E82 -> 5500 | G82: =C82 -> 5500 | H82: ='Program Budget'!K80 -> 0 | I82: 1 | J82: =G82*H82*I82 -> 0 | K82: =G82 -> 5500 | L82: ='Program Budget'!N80 -> 0 | M82: 1 | N82: =K82*L82*M82 -> 0 | O82: =K82 -> 5500 | P82: ='Program Budget'!Q80 -> 0 | Q82: 1 | R82: =O82*P82*Q82 -> 0 | S82: =O82 -> 5500 | T82: ='Program Budget'!T80 -> 0 | U82: 0 | V82: =S82*T82*U82 -> 0 | W82: =F82+J82+N82+R82+V82 -> 5500
A83: ='Program Budget'!D81 -> M&E Database Platform Subscription Fee (Annual) | B83: ='Program Budget'!F81 -> Year | C83: ='Program Budget'!H81 -> 6500 | D83: ='Program Budget'!G81 -> 1 | E83: 1 | F83: =C83*D83*E83 -> 6500 | G83: =C83 -> 6500 | H83: ='Program Budget'!K81 -> 1 | I83: 1 | J83: =G83*H83*I83 -> 6500 | K83: =G83 -> 6500 | L83: ='Program Budget'!N81 -> 1 | M83: 1 | N83: =K83*L83*M83 -> 6500 | O83: =K83 -> 6500 | P83: ='Program Budget'!Q81 -> 1 | Q83: 1 | R83: =O83*P83*Q83 -> 6500 | S83: =O83 -> 6500 | T83: ='Program Budget'!T81 -> 0 | U83: 0 | V83: =S83*T83*U83 -> 0 | W83: =F83+J83+N83+R83+V83 -> 26000
A85: Subtotal: Professional Services/Contractual | F85: =SUM(F64:F84) -> 401993 | J85: =SUM(J64:J84) -> 125300 | N85: =SUM(N64:N84) -> 225300 | R85: =SUM(R64:R84) -> 240300 | V85: =SUM(V64:V84) -> 0 | W85: =+F85+J85+N85+R85+V85 -> 992893
A86: Equipment (>$5000/unit)
A87: ='Program Budget'!D87 -> Vehicles for Field Office | B87: ='Program Budget'!F87 -> Unit | C87: ='Program Budget'!H87 -> 60000 | D87: ='Program Budget'!G87 -> 1 | E87: 1 | F87: =C87*D87*E87 -> 60000 | G87: =C87 -> 60000 | H87: ='Program Budget'!K87 -> 0 | I87: 0 | J87: =G87*H87*I87 -> 0 | K87: =G87 -> 60000 | L87: ='Program Budget'!N87 -> 0 | M87: 0 | N87: =K87*L87*M87 -> 0 | O87: =K87 -> 60000 | P87: ='Program Budget'!Q87 -> 0 | Q87: 0 | R87: =O87*P87*Q87 -> 0 | S87: =O87 -> 60000 | T87: ='Program Budget'!T87 -> 0 | U87: 0 | V87: =S87*T87*U87 -> 0 | W87: =F87+J87+N87+R87+V87 -> 60000
A89: Subtotal: Equipment | F89: =SUM(F87:F88) -> 60000 | J89: =SUM(J87:J88) -> 0 | N89: =SUM(N87:N88) -> 0 | R89: =SUM(R87:R88) -> 0 | V89: =SUM(V87:V88) -> 0 | W89: =+F89+J89+N89+R89+V89 -> 60000
A90: Home Office
A91: ='Program Budget'!D93 -> Banking and Cash Handling Fees (HO) | B91: ='Program Budget'!F93 -> Month | C91: ='Program Budget'!H93 -> 250 | D91: ='Program Budget'!G93 -> 12 | E91: 1 | F91: =C91*D91*E91 -> 3000 | G91: =C91*1.05 -> 262.5 | H91: ='Program Budget'!K93 -> 12 | I91: 1 | J91: =G91*H91*I91 -> 3150 | K91: =G91*1.05 -> 275.625 | L91: ='Program Budget'!N93 -> 12 | M91: 1 | N91: =K91*L91*M91 -> 3307.5 | O91: =K91*1.05 -> 289.40625 | P91: ='Program Budget'!Q93 -> 12 | Q91: 1 | R91: =O91*P91*Q91 -> 3472.875 | S91: =O91*1.05 -> 303.87656 | T91: ='Program Budget'!T93 -> 0 | U91: 0 | V91: =S91*T91*U91 -> 0 | W91: =F91+J91+N91+R91+V91 -> 12930.375
A92: ='Program Budget'!D94 -> IT & Communications Stipend for HO Staff | B92: ='Program Budget'!F94 -> Month | C92: ='Program Budget'!H94 -> 112.5 | D92: ='Program Budget'!G94 -> 12 | E92: 1 | F92: =C92*D92*E92 -> 1350 | G92: =C92*1.05 -> 118.125 | H92: ='Program Budget'!K94 -> 12 | I92: 1 | J92: =G92*H92*I92 -> 1417.5 | K92: =G92*1.05 -> 124.03125 | L92: ='Program Budget'!N94 -> 12 | M92: 1 | N92: =K92*L92*M92 -> 1488.375 | O92: =K92*1.05 -> 130.23281 | P92: ='Program Budget'!Q94 -> 12 | Q92: 1 | R92: =O92*P92*Q92 -> 1562.7937 | S92: =O92*1.05 -> 136.74445 | T92: ='Program Budget'!T94 -> 0 | U92: 0 | V92: =S92*T92*U92 -> 0 | W92: =F92+J92+N92+R92+V92 -> 5818.6687
A93: Field Office
A94: ='Program Budget'!D96 -> Banking and Cash Handling Fees (Nigeria) | B94: ='Program Budget'!F96 -> Month | C94: ='Program Budget'!H96 -> 50 | D94: ='Program Budget'!G96 -> 6 | E94: 1 | F94: =C94*D94*E94 -> 300 | G94: =C94*1.05 -> 52.5 | H94: ='Program Budget'!K96 -> 12 | I94: 1 | J94: =G94*H94*I94 -> 630 | K94: =G94*1.05 -> 55.125 | L94: ='Program Budget'!N96 -> 12 | M94: 1 | N94: =K94*L94*M94 -> 661.5 | O94: =K94*1.05 -> 57.88125 | P94: ='Program Budget'!Q96 -> 9 | Q94: 1 | R94: =O94*P94*Q94 -> 520.93125 | S94: =O94*1.05 -> 60.775313 | T94: ='Program Budget'!T96 -> 0 | U94: 0 | V94: =S94*T94*U94 -> 0 | W94: =F94+J94+N94+R94+V94 -> 2112.4313
A95: ='Program Budget'!D97 -> Communications Costs (Internet, Phone, Data) (Lagos) | B95: ='Program Budget'!F97 -> Month | C95: ='Program Budget'!H97 -> 375 | D95: ='Program Budget'!G97 -> 3 | E95: 1 | F95: =C95*D95*E95 -> 1125 | G95: =C95*1.05 -> 393.75 | H95: ='Program Budget'!K97 -> 12 | I95: 1 | J95: =G95*H95*I95 -> 4725 | K95: =G95*1.05 -> 413.4375 | L95: ='Program Budget'!N97 -> 12 | M95: 1 | N95: =K95*L95*M95 -> 4961.25 | O95: =K95*1.05 -> 434.10938 | P95: ='Program Budget'!Q97 -> 9 | Q95: 1 | R95: =O95*P95*Q95 -> 3906.9844 | S95: =O95*1.05 -> 455.81484 | T95: ='Program Budget'!T97 -> 0 | U95: 0 | V95: =S95*T95*U95 -> 0 | W95: =F95+J95+N95+R95+V95 -> 14718.234
A96: ='Program Budget'!D98 -> Office Rent, Utilities & Cleaning (Lagos) (Coworking Space, rental price includes all costs) | B96: ='Program Budget'!F98 -> Month | C96: ='Program Budget'!H98 -> 2150 | D96: ='Program Budget'!G98 -> 3 | E96: 1 | F96: =C96*D96*E96 -> 6450 | G96: =C96*1.05 -> 2257.5 | H96: ='Program Budget'!K98 -> 12 | I96: 1 | J96: =G96*H96*I96 -> 27090 | K96: =G96*1.05 -> 2370.375 | L96: ='Program Budget'!N98 -> 12 | M96: 1 | N96: =K96*L96*M96 -> 28444.5 | O96: =K96*1.05 -> 2488.8938 | P96: ='Program Budget'!Q98 -> 9 | Q96: 1 | R96: =O96*P96*Q96 -> 22400.044 | S96: =O96*1.05 -> 2613.3384 | T96: ='Program Budget'!T98 -> 0 | U96: 0 | V96: =S96*T96*U96 -> 0 | W96: =F96+J96+N96+R96+V96 -> 84384.544
A97: ='Program Budget'!D99 -> Courier fees/Services/Postage | B97: ='Program Budget'!F99 -> Month | C97: ='Program Budget'!H99 -> 20 | D97: ='Program Budget'!G99 -> 3 | E97: 1 | F97: =C97*D97*E97 -> 60 | G97: =C97*1.05 -> 21 | H97: ='Program Budget'!K99 -> 12 | I97: 1 | J97: =G97*H97*I97 -> 252 | K97: =G97*1.05 -> 22.05 | L97: ='Program Budget'!N99 -> 12 | M97: 1 | N97: =K97*L97*M97 -> 264.6 | O97: =K97*1.05 -> 23.1525 | P97: ='Program Budget'!Q99 -> 9 | Q97: 1 | R97: =O97*P97*Q97 -> 208.3725 | S97: =O97*1.05 -> 24.310125 | T97: ='Program Budget'!T99 -> 0 | U97: 0 | V97: =S97*T97*U97 -> 0 | W97: =F97+J97+N97+R97+V97 -> 784.9725
A98: ='Program Budget'!D100 -> Recruitment/Procurement Advertising | B98: ='Program Budget'!F100 -> Year | C98: ='Program Budget'!H100 -> 300 | D98: ='Program Budget'!G100 -> 1 | E98: 1 | F98: =C98*D98*E98 -> 300 | G98: =C98*1.05 -> 315 | H98: ='Program Budget'!K100 -> 1 | I98: 1 | J98: =G98*H98*I98 -> 315 | K98: =G98*1.05 -> 330.75 | L98: ='Program Budget'!N100 -> 1 | M98: 1 | N98: =K98*L98*M98 -> 330.75 | O98: =K98*1.05 -> 347.2875 | P98: ='Program Budget'!Q100 -> 1 | Q98: 1 | R98: =O98*P98*Q98 -> 347.2875 | S98: =O98*1.05 -> 364.65188 | T98: ='Program Budget'!T100 -> 0 | U98: 0 | V98: =S98*T98*U98 -> 0 | W98: =F98+J98+N98+R98+V98 -> 1293.0375
A99: ='Program Budget'!D101 -> Meeting Expenses - Room Rental and A/V Equipment (for Small Meeting, Rooms Space Rented per Hour) | B99: ='Program Budget'!F101 -> Hours | C99: ='Program Budget'!H101 -> 20 | D99: ='Program Budget'!G101 -> 120 | E99: 1 | F99: =C99*D99*E99 -> 2400 | G99: =C99*1.05 -> 21 | H99: ='Program Budget'!K101 -> 160 | I99: 1 | J99: =G99*H99*I99 -> 3360 | K99: =G99*1.05 -> 22.05 | L99: ='Program Budget'!N101 -> 160 | M99: 1 | N99: =K99*L99*M99 -> 3528 | O99: =K99*1.05 -> 23.1525 | P99: ='Program Budget'!Q101 -> 160 | Q99: 1 | R99: =O99*P99*Q99 -> 3704.4 | S99: =O99*1.05 -> 24.310125 | T99: ='Program Budget'!T101 -> 0 | U99: 0 | V99: =S99*T99*U99 -> 0 | W99: =F99+J99+N99+R99+V99 -> 12992.4
A100: ='Program Budget'!D102 -> Accounting Platform (Sage Intacct & QuickBooks) | B100: ='Program Budget'!F102 -> Month | C100: ='Program Budget'!H102 -> 1500 | D100: ='Program Budget'!G102 -> 9 | E100: 1 | F100: =C100*D100*E100 -> 13500 | G100: =C100*1.05 -> 1575 | H100: ='Program Budget'!K102 -> 12 | I100: 1 | J100: =G100*H100*I100 -> 18900 | K100: =G100*1.05 -> 1653.75 | L100: ='Program Budget'!N102 -> 12 | M100: 1 | N100: =K100*L100*M100 -> 19845 | O100: =K100*1.05 -> 1736.4375 | P100: ='Program Budget'!Q102 -> 9 | Q100: 1 | R100: =O100*P100*Q100 -> 15627.938 | S100: =O100*1.05 -> 1823.2594 | T100: ='Program Budget'!T102 -> 0 | U100: 0 | V100: =S100*T100*U100 -> 0 | W100: =F100+J100+N100+R100+V100 -> 67872.938
A101: ='Program Budget'!D103 -> Licenses & Subscriptions (Microsoft 365, Replicon, PandaDoc, TripLog, Adobe, DeepL & Visual Compliance) | B101: ='Program Budget'!F103 -> Month | C101: ='Program Budget'!H103 -> 1521.6667 | D101: ='Program Budget'!G103 -> 12 | E101: 1 | F101: =C101*D101*E101 -> 18260 | G101: =C101*1.05 -> 1597.75 | H101: ='Program Budget'!K103 -> 12 | I101: 1 | J101: =G101*H101*I101 -> 19173 | K101: =G101*1.05 -> 1677.6375 | L101: ='Program Budget'!N103 -> 12 | M101: 1 | N101: =K101*L101*M101 -> 20131.65 | O101: =K101*1.05 -> 1761.5194 | P101: ='Program Budget'!Q103 -> 9 | Q101: 1 | R101: =O101*P101*Q101 -> 15853.674 | S101: =O101*1.05 -> 1849.5953 | T101: ='Program Budget'!T103 -> 0 | U101: 0 | V101: =S101*T101*U101 -> 0 | W101: =F101+J101+N101+R101+V101 -> 73418.324
A103: Subtotal: Office | F103: =SUM(F90:F101) -> 46745 | J103: =SUM(J90:J101) -> 79012.5 | N103: =SUM(N90:N101) -> 82963.125 | R103: =SUM(R90:R101) -> 67605.3 | V103: =SUM(V90:V101) -> 0 | W103: =SUM(W90:W101) -> 276325.93
A104: Supplies
A105: ='Program Budget'!D108 -> Desktop/Laptop Computers | B105: ='Program Budget'!F108 -> Unit | C105: ='Program Budget'!H108 -> 600 | D105: ='Program Budget'!G108 -> 12 | E105: 1 | F105: =C105*D105*E105 -> 7200 | G105: =C105*1.05 -> 630 | H105: ='Program Budget'!K108 -> 0 | I105: 0 | J105: =G105*H105*I105 -> 0 | K105: =G105*1.05 -> 661.5 | L105: ='Program Budget'!N108 -> 0 | M105: 0 | N105: =K105*L105*M105 -> 0 | O105: =K105*1.05 -> 694.575 | P105: ='Program Budget'!Q108 -> 0 | Q105: 0 | R105: =O105*P105*Q105 -> 0 | S105: =O105*1.05 -> 729.30375 | T105: ='Program Budget'!T108 -> 0 | U105: 0 | V105: =S105*T105*U105 -> 0 | W105: =F105+J105+N105+R105+V105 -> 7200
A106: ='Program Budget'!D109 -> All in One: Printer, Photocopier & Scanner | B106: ='Program Budget'!F109 -> Unit | C106: ='Program Budget'!H109 -> 335 | D106: ='Program Budget'!G109 -> 2 | E106: 1 | F106: =C106*D106*E106 -> 670 | G106: =C106*1.05 -> 351.75 | H106: ='Program Budget'!K109 -> 0 | I106: 0 | J106: =G106*H106*I106 -> 0 | K106: =G106*1.05 -> 369.3375 | L106: ='Program Budget'!N109 -> 0 | M106: 0 | N106: =K106*L106*M106 -> 0 | O106: =K106*1.05 -> 387.80438 | P106: ='Program Budget'!Q109 -> 0 | Q106: 0 | R106: =O106*P106*Q106 -> 0 | S106: =O106*1.05 -> 407.19459 | T106: ='Program Budget'!T109 -> 0 | U106: 0 | V106: =S106*T106*U106 -> 0 | W106: =F106+J106+N106+R106+V106 -> 670
A107: ='Program Budget'!D110 -> Projector and Video Conferencing Equipment | B107: ='Program Budget'!F110 -> Unit | C107: ='Program Budget'!H110 -> 416.63 | D107: ='Program Budget'!G110 -> 1 | E107: 1 | F107: =C107*D107*E107 -> 416.63 | G107: =C107*1.05 -> 437.4615 | H107: ='Program Budget'!K110 -> 0 | I107: 0 | J107: =G107*H107*I107 -> 0 | K107: =G107*1.05 -> 459.33458 | L107: ='Program Budget'!N110 -> 0 | M107: 0 | N107: =K107*L107*M107 -> 0 | O107: =K107*1.05 -> 482.3013 | P107: ='Program Budget'!Q110 -> 0 | Q107: 0 | R107: =O107*P107*Q107 -> 0 | S107: =O107*1.05 -> 506.41637 | T107: ='Program Budget'!T110 -> 0 | U107: 0 | V107: =S107*T107*U107 -> 0 | W107: =F107+J107+N107+R107+V107 -> 416.63
...

Sheet Activity 1
A2: Item | B2: Type of Unit | C2: Year 1 | G2: Year 2 | K2: Year 3 | O2: Year 4 | S2: Year 5 | W2: Total
C3: Cost | D3: Quantity | E3: Percent Allocated | F3: Total | G3: Cost | H3: Quantity | I3: Percent Allocated | J3: Total | K3: Cost | L3: Quantity | M3: Percent Allocated | N3: Total | O3: Cost | P3: Quantity | Q3: Percent Allocated | R3: Total | S3: Cost | T3: Quantity | U3: Percent Allocated | V3: Total
A4: Direct Costs
A5: Salaries/Personnel
A6: USN/TCN Staff
A7: None | F7: =C7*D7*E7 -> 0 | J7: =G7*H7*I7 -> 0 | N7: =K7*L7*M7 -> 0 | R7: =O7*P7*Q7 -> 0 | V7: =S7*T7*U7 -> 0 | W7: =F7+J7+N7+R7+V7 -> 0
A8: Total: Expatriate Salaries & Wages | F8: =SUM(F7:F7) -> 0 | J8: =SUM(J7:J7) -> 0 | N8: =SUM(N7:N7) -> 0 | R8: =SUM(R7:R7) -> 0 | V8: =SUM(V7:V7) -> 0 | W8: =+F8+J8+N8+R8+V8 -> 0
A9: CCN Staff
A10: ='Program Budget'!D12 -> Key Personnel: Chief of Party | B10: ='Program Budget'!F131 -> Month | C10: ='Program Budget'!H131 -> 9583.3333 | D10: ='Program Budget'!G131 -> 11 | E10: ='Program Budget'!E131 -> 0.2 | F10: =C10*D10*E10 -> 21083.333 | G10: =C10*1.05 -> 10062.5 | H10: ='Program Budget'!K131 -> 12 | I10: ='Program Budget'!J131 -> 0.2 | J10: =G10*H10*I10 -> 24150 | K10: =G10*1.05 -> 10565.625 | L10: ='Program Budget'!N131 -> 12 | M10: ='Program Budget'!M131 -> 0.2 | N10: =K10*L10*M10 -> 25357.5 | O10: =K10*1.05 -> 11093.906 | P10: ='Program Budget'!Q131 -> 12 | Q10: ='Program Budget'!P131 -> 0.3 | R10: =O10*P10*Q10 -> 39938.063 | S10: =O10*1.05 -> 11648.602 | T10: ='Program Budget'!T131 -> 0 | U10: ='Program Budget'!S131 -> 0 | V10: =S10*T10*U10 -> 0 | W10: =F10+J10+N10+R10+V10 -> 110528.9
A11: ='Program Budget'!D13 -> Technical Director | B11: ='Program Budget'!F132 -> Month | C11: ='Program Budget'!H132 -> 3500 | D11: ='Program Budget'!G132 -> 9 | E11: ='Program Budget'!E132 -> 0.22 | F11: =C11*D11*E11 -> 6930 | G11: =C11*1.05 -> 3675 | H11: ='Program Budget'!K132 -> 12 | I11: ='Program Budget'!J132 -> 0.2 | J11: =G11*H11*I11 -> 8820 | K11: =G11*1.05 -> 3858.75 | L11: ='Program Budget'!N132 -> 12 | M11: ='Program Budget'!M132 -> 0.2 | N11: =K11*L11*M11 -> 9261 | O11: =K11*1.05 -> 4051.6875 | P11: ='Program Budget'!Q132 -> 12 | Q11: ='Program Budget'!P132 -> 0.3 | R11: =O11*P11*Q11 -> 14586.075 | S11: =O11*1.05 -> 4254.2719 | T11: ='Program Budget'!T132 -> 0 | U11: ='Program Budget'!S132 -> 0 | V11: =S11*T11*U11 -> 0 | W11: =F11+J11+N11+R11+V11 -> 39597.075
A12: ='Program Budget'!D14 -> Technical Lead - Activity 2 US Exports | B12: ='Program Budget'!F133 -> Month | C12: ='Program Budget'!H133 -> 2833.3333 | D12: ='Program Budget'!G133 -> 8 | E12: ='Program Budget'!E133 -> 0 | F12: =C12*D12*E12 -> 0 | G12: =C12*1.05 -> 2975 | H12: ='Program Budget'!K133 -> 12 | I12: ='Program Budget'!J133 -> 0 | J12: =G12*H12*I12 -> 0 | K12: =G12*1.05 -> 3123.75 | L12: ='Program Budget'!N133 -> 12 | M12: ='Program Budget'!M133 -> 0 | N12: =K12*L12*M12 -> 0 | O12: =K12*1.05 -> 3279.9375 | P12: ='Program Budget'!Q133 -> 12 | Q12: ='Program Budget'!P133 -> 0 | R12: =O12*P12*Q12 -> 0 | S12: =O12*1.05 -> 3443.9344 | T12: ='Program Budget'!T133 -> 0 | U12: ='Program Budget'!S133 -> 0 | V12: =S12*T12*U12 -> 0 | W12: =F12+J12+N12+R12+V12 -> 0
A13: ='Program Budget'!D15 -> Technical Lead - Activity 2 Access to Finance Specialist | B13: ='Program Budget'!F134 -> Month | C13: ='Program Budget'!H134 -> 2833.3333 | D13: ='Program Budget'!G134 -> 8 | E13: ='Program Budget'!E134 -> 0 | F13: =C13*D13*E13 -> 0 | G13: =C13*1.05 -> 2975 | H13: ='Program Budget'!K134 -> 12 | I13: ='Program Budget'!J134 -> 0 | J13: =G13*H13*I13 -> 0 | K13: =G13*1.05 -> 3123.75 | L13: ='Program Budget'!N134 -> 12 | M13: ='Program Budget'!M134 -> 0 | N13: =K13*L13*M13 -> 0 | O13: =K13*1.05 -> 3279.9375 | P13: ='Program Budget'!Q134 -> 12 | Q13: ='Program Budget'!P134 -> 0 | R13: =O13*P13*Q13 -> 0 | S13: =O13*1.05 -> 3443.9344 | T13: ='Program Budget'!T134 -> 0 | U13: ='Program Budget'!S134 -> 0 | V13: =S13*T13*U13 -> 0 | W13: =F13+J13+N13+R13+V13 -> 0
A14: ='Program Budget'!D16 -> Communications/Strategic Partnerships Manager | B14: ='Program Budget'!F135 -> Month | C14: ='Program Budget'!H135 -> 2666.6667 | D14: ='Program Budget'!G135 -> 8 | E14: ='Program Budget'!E135 -> 0.3 | F14: =C14*D14*E14 -> 6400 | G14: =C14*1.05 -> 2800 | H14: ='Program Budget'!K135 -> 12 | I14: ='Program Budget'!J135 -> 0.4 | J14: =G14*H14*I14 -> 13440 | K14: =G14*1.05 -> 2940 | L14: ='Program Budget'!N135 -> 12 | M14: ='Program Budget'!M135 -> 0.4 | N14: =K14*L14*M14 -> 14112 | O14: =K14*1.05 -> 3087 | P14: ='Program Budget'!Q135 -> 12 | Q14: ='Program Budget'!P135 -> 0.5 | R14: =O14*P14*Q14 -> 18522 | S14: =O14*1.05 -> 3241.35 | T14: ='Program Budget'!T135 -> 0 | U14: ='Program Budget'!S135 -> 0 | V14: =S14*T14*U14 -> 0 | W14: =F14+J14+N14+R14+V14 -> 52474
A15: ='Program Budget'!D17 -> M&E Director | B15: ='Program Budget'!F136 -> Month | C15: ='Program Budget'!H136 -> 3500 | D15: ='Program Budget'!G136 -> 10 | E15: ='Program Budget'!E136 -> 0.2 | F15: =C15*D15*E15 -> 7000 | G15: =C15*1.05 -> 3675 | H15: ='Program Budget'!K136 -> 12 | I15: ='Program Budget'!J136 -> 0.25 | J15: =G15*H15*I15 -> 11025 | K15: =G15*1.05 -> 3858.75 | L15: ='Program Budget'!N136 -> 12 | M15: ='Program Budget'!M136 -> 0.25 | N15: =K15*L15*M15 -> 11576.25 | O15: =K15*1.05 -> 4051.6875 | P15: ='Program Budget'!Q136 -> 12 | Q15: ='Program Budget'!P136 -> 0.35 | R15: =O15*P15*Q15 -> 17017.087 | S15: =O15*1.05 -> 4254.2719 | T15: ='Program Budget'!T136 -> 0 | U15: ='Program Budget'!S136 -> 0 | V15: =S15*T15*U15 -> 0 | W15: =F15+J15+N15+R15+V15 -> 46618.337
A16: ='Program Budget'!D18 -> M&E Specialist | B16: ='Program Budget'!F137 -> Month | C16: ='Program Budget'!H137 -> 2000 | D16: ='Program Budget'!G137 -> 8 | E16: ='Program Budget'!E137 -> 0.25 | F16: =C16*D16*E16 -> 4000 | G16: =C16*1.05 -> 2100 | H16: ='Program Budget'!K137 -> 12 | I16: ='Program Budget'!J137 -> 0.25 | J16: =G16*H16*I16 -> 6300 | K16: =G16*1.05 -> 2205 | L16: ='Program Budget'!N137 -> 12 | M16: ='Program Budget'!M137 -> 0.25 | N16: =K16*L16*M16 -> 6615 | O16: =K16*1.05 -> 2315.25 | P16: ='Program Budget'!Q137 -> 12 | Q16: ='Program Budget'!P137 -> 0.35 | R16: =O16*P16*Q16 -> 9724.05 | S16: =O16*1.05 -> 2431.0125 | T16: ='Program Budget'!T137 -> 0 | U16: ='Program Budget'!S137 -> 0 | V16: =S16*T16*U16 -> 0 | W16: =F16+J16+N16+R16+V16 -> 26639.05
A17: ='Program Budget'!D19 -> Key Personnel: Finance & Administration (F&A) Director | B17: ='Program Budget'!F138 -> Month | C17: ='Program Budget'!H138 -> 3500 | D17: ='Program Budget'!G138 -> 10 | E17: ='Program Budget'!E138 -> 0.2 | F17: =C17*D17*E17 -> 7000 | G17: =C17*1.05 -> 3675 | H17: ='Program Budget'!K138 -> 12 | I17: ='Program Budget'!J138 -> 0.3 | J17: =G17*H17*I17 -> 13230 | K17: =G17*1.05 -> 3858.75 | L17: ='Program Budget'!N138 -> 12 | M17: ='Program Budget'!M138 -> 0.3 | N17: =K17*L17*M17 -> 13891.5 | O17: =K17*1.05 -> 4051.6875 | P17: ='Program Budget'!Q138 -> 12 | Q17: ='Program Budget'!P138 -> 0.4 | R17: =O17*P17*Q17 -> 19448.1 | S17: =O17*1.05 -> 4254.2719 | T17: ='Program Budget'!T138 -> 0 | U17: ='Program Budget'!S138 -> 0 | V17: =S17*T17*U17 -> 0 | W17: =F17+J17+N17+R17+V17 -> 53569.6
A18: ='Program Budget'!D20 -> Accountant | B18: ='Program Budget'!F139 -> Month | C18: ='Program Budget'!H139 -> 2000 | D18: ='Program Budget'!G139 -> 8 | E18: ='Program Budget'!E139 -> 0.25 | F18: =C18*D18*E18 -> 4000 | G18: =C18*1.05 -> 2100 | H18: ='Program Budget'!K139 -> 12 | I18: ='Program Budget'!J139 -> 0.25 | J18: =G18*H18*I18 -> 6300 | K18: =G18*1.05 -> 2205 | L18: ='Program Budget'!N139 -> 12 | M18: ='Program Budget'!M139 -> 0.25 | N18: =K18*L18*M18 -> 6615 | O18: =K18*1.05 -> 2315.25 | P18: ='Program Budget'!Q139 -> 12 | Q18: ='Program Budget'!P139 -> 0.4 | R18: =O18*P18*Q18 -> 11113.2 | S18: =O18*1.05 -> 2431.0125 | T18: ='Program Budget'!T139 -> 0 | U18: ='Program Budget'!S139 -> 0 | V18: =S18*T18*U18 -> 0 | W18: =F18+J18+N18+R18+V18 -> 28028.2
A19: ='Program Budget'!D21 -> Administration/ HR Manager | B19: ='Program Budget'!F140 -> Month | C19: ='Program Budget'!H140 -> 2666.6667 | D19: ='Program Budget'!G140 -> 10 | E19: ='Program Budget'!E140 -> 0.15 | F19: =C19*D19*E19 -> 4000 | G19: =C19*1.05 -> 2800 | H19: ='Program Budget'!K140 -> 12 | I19: ='Program Budget'!J140 -> 0.25 | J19: =G19*H19*I19 -> 8400 | K19: =G19*1.05 -> 2940 | L19: ='Program Budget'!N140 -> 12 | M19: ='Program Budget'!M140 -> 0.25 | N19: =K19*L19*M19 -> 8820 | O19: =K19*1.05 -> 3087 | P19: ='Program Budget'!Q140 -> 12 | Q19: ='Program Budget'!P140 -> 0.35 | R19: =O19*P19*Q19 -> 12965.4 | S19: =O19*1.05 -> 3241.35 | T19: ='Program Budget'!T140 -> 0 | U19: ='Program Budget'!S140 -> 0 | V19: =S19*T19*U19 -> 0 | W19: =F19+J19+N19+R19+V19 -> 34185.4
A20: ='Program Budget'!D22 -> Grants & Contracts Manager | B20: ='Program Budget'!F141 -> Month | C20: ='Program Budget'!H141 -> 2666.6667 | D20: ='Program Budget'!G141 -> 9 | E20: ='Program Budget'!E141 -> 0.21 | F20: =C20*D20*E20 -> 5040 | G20: =C20*1.05 -> 2800 | H20: ='Program Budget'!K141 -> 12 | I20: ='Program Budget'!J141 -> 0.3 | J20: =G20*H20*I20 -> 10080 | K20: =G20*1.05 -> 2940 | L20: ='Program Budget'!N141 -> 12 | M20: ='Program Budget'!M141 -> 0.3 | N20: =K20*L20*M20 -> 10584 | O20: =K20*1.05 -> 3087 | P20: ='Program Budget'!Q141 -> 12 | Q20: ='Program Budget'!P141 -> 0.4 | R20: =O20*P20*Q20 -> 14817.6 | S20: =O20*1.05 -> 3241.35 | T20: ='Program Budget'!T141 -> 0 | U20: ='Program Budget'!S141 -> 0 | V20: =S20*T20*U20 -> 0 | W20: =F20+J20+N20+R20+V20 -> 40521.6
A21: ='Program Budget'!D23 -> Compliance & Procurement Specialist | B21: ='Program Budget'!F142 -> Month | C21: ='Program Budget'!H142 -> 2000 | D21: ='Program Budget'!G142 -> 9 | E21: ='Program Budget'!E142 -> 0.21 | F21: =C21*D21*E21 -> 3780 | G21: =C21*1.05 -> 2100 | H21: ='Program Budget'!K142 -> 12 | I21: ='Program Budget'!J142 -> 0.3 | J21: =G21*H21*I21 -> 7560 | K21: =G21*1.05 -> 2205 | L21: ='Program Budget'!N142 -> 12 | M21: ='Program Budget'!M142 -> 0.3 | N21: =K21*L21*M21 -> 7938 | O21: =K21*1.05 -> 2315.25 | P21: ='Program Budget'!Q142 -> 12 | Q21: ='Program Budget'!P142 -> 0.4 | R21: =O21*P21*Q21 -> 11113.2 | S21: =O21*1.05 -> 2431.0125 | T21: ='Program Budget'!T142 -> 0 | U21: ='Program Budget'!S142 -> 0 | V21: =S21*T21*U21 -> 0 | W21: =F21+J21+N21+R21+V21 -> 30391.2
A22: ='Program Budget'!D24 -> Driver | B22: ='Program Budget'!F143 -> Month | C22: ='Program Budget'!H143 -> 500 | D22: ='Program Budget'!G143 -> 7 | E22: ='Program Budget'!E143 -> 0.25 | F22: =C22*D22*E22 -> 875 | G22: =C22*1.05 -> 525 | H22: ='Program Budget'!K143 -> 12 | I22: ='Program Budget'!J143 -> 0.25 | J22: =G22*H22*I22 -> 1575 | K22: =G22*1.05 -> 551.25 | L22: ='Program Budget'!N143 -> 12 | M22: ='Program Budget'!M143 -> 0.25 | N22: =K22*L22*M22 -> 1653.75 | O22: =K22*1.05 -> 578.8125 | P22: ='Program Budget'!Q143 -> 12 | Q22: ='Program Budget'!P143 -> 0.35 | R22: =O22*P22*Q22 -> 2431.0125 | S22: =O22*1.05 -> 607.75313 | T22: ='Program Budget'!T143 -> 0 | U22: ='Program Budget'!S143 -> 0 | V22: =S22*T22*U22 -> 0 | W22: =F22+J22+N22+R22+V22 -> 6534.7625
A23: Total Local Salary Cost | F23: =SUM(F10:F22) -> 70108.333 | J23: =SUM(J10:J22) -> 110880 | N23: =SUM(N10:N22) -> 116424 | R23: =SUM(R10:R22) -> 171675.79 | V23: =SUM(V10:V22) -> 0 | W23: =SUM(W10:W22) -> 469088.12
A24: HQ Staff
A25: ='Program Budget'!D26 -> Senior Vice President of Programs | B25: ='Program Budget'!F145 -> Month | C25: ='Program Budget'!H145 -> 13500 | D25: ='Program Budget'!G145 -> 12 | E25: ='Program Budget'!E145 -> 0.01 | F25: =C25*D25*E25 -> 1620 | G25: =C25*1.05 -> 14175 | H25: ='Program Budget'!K145 -> 12 | I25: ='Program Budget'!J145 -> 0.01 | J25: =G25*H25*I25 -> 1701 | K25: =G25*1.05 -> 14883.75 | L25: ='Program Budget'!N145 -> 12 | M25: ='Program Budget'!M145 -> 0.01 | N25: =K25*L25*M25 -> 1786.05 | O25: =K25*1.05 -> 15627.938 | P25: ='Program Budget'!Q145 -> 12 | Q25: ='Program Budget'!P145 -> 0.01 | R25: =O25*P25*Q25 -> 1875.3525 | S25: =O25*1.05 -> 16409.334 | T25: ='Program Budget'!T145 -> 0 | U25: ='Program Budget'!S145 -> 0 | V25: =S25*T25*U25 -> 0 | W25: =F25+J25+N25+R25+V25 -> 6982.4025
A26: ='Program Budget'!D27 -> Senior Program Director | B26: ='Program Budget'!F146 -> Month | C26: ='Program Budget'!H146 -> 12500 | D26: ='Program Budget'!G146 -> 12 | E26: ='Program Budget'!E146 -> 0.04 | F26: =C26*D26*E26 -> 6000 | G26: =C26*1.05 -> 13125 | H26: ='Program Budget'!K146 -> 12 | I26: ='Program Budget'!J146 -> 0.05 | J26: =G26*H26*I26 -> 7875 | K26: =G26*1.05 -> 13781.25 | L26: ='Program Budget'!N146 -> 12 | M26: ='Program Budget'!M146 -> 0.05 | N26: =K26*L26*M26 -> 8268.75 | O26: =K26*1.05 -> 14470.312 | P26: ='Program Budget'!Q146 -> 12 | Q26: ='Program Budget'!P146 -> 0.05 | R26: =O26*P26*Q26 -> 8682.1875 | S26: =O26*1.05 -> 15193.828 | T26: ='Program Budget'!T146 -> 0 | U26: ='Program Budget'!S146 -> 0 | V26: =S26*T26*U26 -> 0 | W26: =F26+J26+N26+R26+V26 -> 30825.938
A27: ='Program Budget'!D28 -> Associate Director | B27: ='Program Budget'!F147 -> Month | C27: ='Program Budget'!H147 -> 7500 | D27: ='Program Budget'!G147 -> 12 | E27: ='Program Budget'!E147 -> 0.05 | F27: =C27*D27*E27 -> 4500 | G27: =C27*1.05 -> 7875 | H27: ='Program Budget'!K147 -> 12 | I27: ='Program Budget'!J147 -> 0.2 | J27: =G27*H27*I27 -> 18900 | K27: =G27*1.05 -> 8268.75 | L27: ='Program Budget'!N147 -> 12 | M27: ='Program Budget'!M147 -> 0.2 | N27: =K27*L27*M27 -> 19845 | O27: =K27*1.05 -> 8682.1875 | P27: ='Program Budget'!Q147 -> 12 | Q27: ='Program Budget'!P147 -> 0.2 | R27: =O27*P27*Q27 -> 20837.25 | S27: =O27*1.05 -> 9116.2969 | T27: ='Program Budget'!T147 -> 0 | U27: ='Program Budget'!S147 -> 0 | V27: =S27*T27*U27 -> 0 | W27: =F27+J27+N27+R27+V27 -> 64082.25
A28: ='Program Budget'!D29 -> Compliance & Contracts Director | B28: ='Program Budget'!F148 -> Month | C28: ='Program Budget'!H148 -> 9166.6667 | D28: ='Program Budget'!G148 -> 12 | E28: ='Program Budget'!E148 -> 0.04 | F28: =C28*D28*E28 -> 4400 | G28: =C28*1.05 -> 9625 | H28: ='Program Budget'!K148 -> 12 | I28: ='Program Budget'!J148 -> 0.05 | J28: =G28*H28*I28 -> 5775 | K28: =G28*1.05 -> 10106.25 | L28: ='Program Budget'!N148 -> 12 | M28: ='Program Budget'!M148 -> 0.05 | N28: =K28*L28*M28 -> 6063.75 | O28: =K28*1.05 -> 10611.562 | P28: ='Program Budget'!Q148 -> 12 | Q28: ='Program Budget'!P148 -> 0.05 | R28: =O28*P28*Q28 -> 6366.9375 | S28: =O28*1.05 -> 11142.141 | T28: ='Program Budget'!T148 -> 0 | U28: ='Program Budget'!S148 -> 0 | V28: =S28*T28*U28 -> 0 | W28: =F28+J28+N28+R28+V28 -> 22605.688
A29: ='Program Budget'!D30 -> Finance, HR, & Administration Home Office Support | B29: ='Program Budget'!F149 -> Month | C29: ='Program Budget'!H149 -> 7500 | D29: ='Program Budget'!G149 -> 12 | E29: ='Program Budget'!E149 -> 0.08 | F29: =C29*D29*E29 -> 7200 | G29: =C29*1.05 -> 7875 | H29: ='Program Budget'!K149 -> 12 | I29: ='Program Budget'!J149 -> 0.15 | J29: =G29*H29*I29 -> 14175 | K29: =G29*1.05 -> 8268.75 | L29: ='Program Budget'!N149 -> 12 | M29: ='Program Budget'!M149 -> 0.15 | N29: =K29*L29*M29 -> 14883.75 | O29: =K29*1.05 -> 8682.1875 | P29: ='Program Budget'!Q149 -> 12 | Q29: ='Program Budget'!P149 -> 0.15 | R29: =O29*P29*Q29 -> 15627.938 | S29: =O29*1.05 -> 9116.2969 | T29: ='Program Budget'!T149 -> 0 | U29: ='Program Budget'!S149 -> 0 | V29: =S29*T29*U29 -> 0 | W29: =F29+J29+N29+R29+V29 -> 51886.688
A30: Total HQ Staff | F30: =SUM(F24:F29) -> 23720 | J30: =SUM(J24:J29) -> 48426 | N30: =SUM(N24:N29) -> 50847.3 | R30: =SUM(R24:R29) -> 53389.665 | V30: =SUM(V24:V29) -> 0 | W30: =SUM(W24:W29) -> 176382.96
A32: Subtotal: Salaries & Wages | F32: =F23+F8+F30 -> 93828.333 | J32: =J23+J8+J30 -> 159306 | N32: =N23+N8+N30 -> 167271.3 | R32: =R23+R8+R30 -> 225065.45 | V32: =V23+V8+V30 -> 0 | W32: =W23+W8+W30 -> 645471.09
A33: Fringe Benefits
A34: USN/TCN Staff | B34: ='Program Budget'!F153 -> % | C34: =F8 -> 0 | D34: 1 | E34: 0 | F34: =C34*D34*E34 -> 0 | G34: =J8 -> 0 | H34: 1 | I34: =E34 -> 0 | J34: =G34*H34*I34 -> 0 | K34: =N8 -> 0 | L34: 1 | M34: =E34 -> 0 | N34: =K34*L34*M34 -> 0 | O34: =R8 -> 0 | P34: 1 | Q34: =E34 -> 0 | R34: =O34*P34*Q34 -> 0 | S34: =V8 -> 0 | T34: 1 | U34: =E34 -> 0 | V34: =S34*T34*U34 -> 0 | W34: =F34+J34+N34+R34+V34 -> 0
A35: CCN - Nigeria (above $3,500 monthly) | B35: ='Program Budget'!F153 -> % | C35: =F23 -> 70108.333 | D35: 1 | E35: ='Program Budget'!H153 -> 0.296 | F35: =C35*D35*E35 -> 20752.067 | G35: =J23 -> 110880 | H35: 1 | I35: =E35 -> 0.296 | J35: =G35*H35*I35 -> 32820.48 | K35: =N23 -> 116424 | L35: 1 | M35: =E35 -> 0.296 | N35: =K35*L35*M35 -> 34461.504 | O35: =R23 -> 171675.79 | P35: 1 | Q35: =E35 -> 0.296 | R35: =O35*P35*Q35 -> 50816.033 | S35: =V23 -> 0 | T35: 1 | U35: 0 | V35: =S35*T35*U35 -> 0 | W35: =F35+J35+N35+R35+V35 -> 138850.08
A36: HQ Staff | B36: ='Program Budget'!F154 -> % | C36: =F30 -> 23720 | D36: 1 | E36: ='Program Budget'!H154 -> 0.2347 | F36: =C36*D36*E36 -> 5567.084 | G36: =J30 -> 48426 | H36: 1 | I36: =E36 -> 0.2347 | J36: =G36*H36*I36 -> 11365.582 | K36: =N30 -> 50847.3 | L36: 1 | M36: =E36 -> 0.2347 | N36: =K36*L36*M36 -> 11933.861 | O36: =R30 -> 53389.665 | P36: 1 | Q36: =E36 -> 0.2347 | R36: =O36*P36*Q36 -> 12530.554 | S36: =V30 -> 0 | T36: 1 | U36: 0 | V36: =S36*T36*U36 -> 0 | W36: =F36+J36+N36+R36+V36 -> 41397.082
A37: Total: Fringe Benefits | F37: =SUM(F34:F36) -> 26319.151 | J37: =+SUM(J34:J36) -> 44186.062 | N37: =+SUM(N34:N36) -> 46395.365 | R37: =+SUM(R34:R36) -> 63346.587 | V37: =+SUM(V34:V36) -> 0 | W37: =+F37+J37+N37+R37+V37 -> 180247.17
A38: Allowances | W38: =+F38+J38+N38+R38+V38 -> 0
A39: None | F39: =C39*D39*E39 -> 0 | J39: =G39*H39*I39 -> 0 | N39: =K39*L39*M39 -> 0 | R39: =O39*P39*Q39 -> 0 | V39: =S39*T39*U39 -> 0 | W39: =F39+J39+N39+R39+V39 -> 0
A40: Total: Allowances | F40: =SUM(F39:F39) -> 0 | J40: =SUM(J39:J39) -> 0 | N40: =SUM(N39:N39) -> 0 | R40: =SUM(R39:R39) -> 0 | V40: =SUM(V39:V39) -> 0 | W40: =F40+J40+N40+R40+V40 -> 0
A42: Subtotal: Benefits | F42: =F40+F37 -> 26319.151 | J42: =J40+J37 -> 44186.062 | N42: =N40+N37 -> 46395.365 | R42: =R40+R37 -> 63346.587 | V42: =V40+V37 -> 0 | W42: =+F42+J42+N42+R42+V42 -> 180247.17
A43: International Travel
A44: None | F44: =C44*D44*E44 -> 0 | J44: =G44*H44*I44 -> 0 | N44: =K44*L44*M44 -> 0 | R44: =O44*P44*Q44 -> 0 | V44: =S44*T44*U44 -> 0 | W44: =F44+J44+N44+R44+V44 -> 0
A45: Local Travel
A46: ='Program Budget'!D168 -> Local Transportation (Taxis/Ubers) for Project Implementation | B46: ='Program Budget'!F168 -> Month | C46: ='Program Budget'!H168 -> 300 | D46: ='Program Budget'!G168 -> 6 | E46: 1 | F46: =C46*D46*E46 -> 1800 | G46: =C46*1.05 -> 315 | H46: ='Program Budget'!K168 -> 12 | I46: 1 | J46: =G46*H46*I46 -> 3780 | K46: =G46*1.05 -> 330.75 | L46: ='Program Budget'!N168 -> 12 | M46: 1 | N46: =K46*L46*M46 -> 3969 | O46: =K46*1.05 -> 347.2875 | P46: ='Program Budget'!Q168 -> 12 | Q46: 1 | R46: =O46*P46*Q46 -> 4167.45 | S46: =O46*1.05 -> 364.65188 | T46: ='Program Budget'!T168 -> 0 | U46: 0 | V46: =S46*T46*U46 -> 0 | W46: =F46+J46+N46+R46+V46 -> 13716.45
A47: ='Program Budget'!D169 -> Roundtrip Domestic Airfare - Lagos to Implementing Regions for Trainings on Activity 1 | B47: ='Program Budget'!F169 -> Trip | C47: ='Program Budget'!H169 -> 250 | D47: ='Program Budget'!G169 -> 12 | E47: 1 | F47: =C47*D47*E47 -> 3000 | G47: =C47*1.05 -> 262.5 | H47: ='Program Budget'!K169 -> 24 | I47: 1 | J47: =G47*H47*I47 -> 6300 | K47: =G47*1.05 -> 275.625 | L47: ='Program Budget'!N169 -> 24 | M47: 1 | N47: =K47*L47*M47 -> 6615 | O47: =K47*1.05 -> 289.40625 | P47: ='Program Budget'!Q169 -> 24 | Q47: 1 | R47: =O47*P47*Q47 -> 6945.75 | S47: =O47*1.05 -> 303.87656 | T47: ='Program Budget'!T169 -> 0 | U47: 0 | V47: =S47*T47*U47 -> 0 | W47: =F47+J47+N47+R47+V47 -> 22860.75
A48: ='Program Budget'!D170 -> Local Transportation (Car Rental, Taxis) for Trainings on Activity 1 | B48: ='Program Budget'!F170 -> Trip | C48: ='Program Budget'!H170 -> 30 | D48: ='Program Budget'!G170 -> 12 | E48: 1 | F48: =C48*D48*E48 -> 360 | G48: =C48*1.05 -> 31.5 | H48: ='Program Budget'!K170 -> 24 | I48: 1 | J48: =G48*H48*I48 -> 756 | K48: =G48*1.05 -> 33.075 | L48: ='Program Budget'!N170 -> 24 | M48: 1 | N48: =K48*L48*M48 -> 793.8 | O48: =K48*1.05 -> 34.72875 | P48: ='Program Budget'!Q170 -> 24 | Q48: 1 | R48: =O48*P48*Q48 -> 833.49 | S48: =O48*1.05 -> 36.465188 | T48: ='Program Budget'!T170 -> 0 | U48: 0 | V48: =S48*T48*U48 -> 0 | W48: =F48+J48+N48+R48+V48 -> 2743.29
A49: Vehicle Fuel
A50: ='Program Budget'!D167 -> Vehicle Fuel Expense (for Field Office Vehicle) | B50: ='Program Budget'!F167 -> Month | C50: ='Program Budget'!H167 -> 60 | D50: ='Program Budget'!G167 -> 3 | E50: 1 | F50: =C50*D50*E50 -> 180 | G50: =C50*1.05 -> 63 | H50: ='Program Budget'!K167 -> 12 | I50: 1 | J50: =G50*H50*I50 -> 756 | K50: =G50*1.05 -> 66.15 | L50: ='Program Budget'!N167 -> 12 | M50: 1 | N50: =K50*L50*M50 -> 793.8 | O50: =K50*1.05 -> 69.4575 | P50: ='Program Budget'!Q167 -> 12 | Q50: 1 | R50: =O50*P50*Q50 -> 833.49 | S50: =O50*1.05 -> 72.930375 | T50: ='Program Budget'!T167 -> 0 | U50: 0 | V50: =S50*T50*U50 -> 0 | W50: =F50+J50+N50+R50+V50 -> 2563.29
A51: Per Diem & Lodging
A52: ='Program Budget'!D171 -> Lodging and M&IE for Trainings on Activity 1 | B52: ='Program Budget'!F171 -> Day | C52: ='Program Budget'!H171 -> 145.5 | D52: ='Program Budget'!G171 -> 36 | E52: 1 | F52: =C52*D52*E52 -> 5238 | G52: =C52*1.05 -> 152.775 | H52: ='Program Budget'!K171 -> 72 | I52: 1 | J52: =G52*H52*I52 -> 10999.8 | K52: =G52*1.05 -> 160.41375 | L52: ='Program Budget'!N171 -> 72 | M52: 1 | N52: =K52*L52*M52 -> 11549.79 | O52: =K52*1.05 -> 168.43444 | P52: ='Program Budget'!Q171 -> 72 | Q52: 1 | R52: =O52*P52*Q52 -> 12127.28 | S52: =O52*1.05 -> 176.85616 | T52: ='Program Budget'!T171 -> 0 | U52: 0 | V52: =S52*T52*U52 -> 0 | W52: =F52+J52+N52+R52+V52 -> 39914.87
A54: Subtotal: Travel | F54: =SUM(F43:F53) -> 10578 | J54: =SUM(J43:J53) -> 22591.8 | N54: =SUM(N43:N53) -> 23721.39 | R54: =SUM(R43:R53) -> 24907.46 | V54: =SUM(V43:V53) -> 0 | W54: =SUM(W43:W53) -> 81798.649
A55: Professional Services/Contractual
A56: ='Program Budget'!D158 -> Contract for Nation-wide Poultry Consumption Campaign | B56: ='Program Budget'!F158 -> Year | C56: ='Program Budget'!H158 -> 160000 | D56: ='Program Budget'!G158 -> 0 | E56: 1 | F56: =C56*D56*E56 -> 0 | G56: =C56 -> 160000 | H56: ='Program Budget'!K158 -> 0.5 | I56: 1 | J56: =G56*H56*I56 -> 80000 | K56: =G56 -> 160000 | L56: ='Program Budget'!N158 -> 1 | M56: 1 | N56: =K56*L56*M56 -> 160000 | O56: =K56 -> 160000 | P56: ='Program Budget'!Q158 -> 1 | Q56: 1 | R56: =O56*P56*Q56 -> 160000 | S56: =O56 -> 160000 | T56: ='Program Budget'!T158 -> 0 | U56: 0 | V56: =S56*T56*U56 -> 0 | W56: =F56+J56+N56+R56+V56 -> 400000
A57: ='Program Budget'!D159 -> Security Services, Risk Assessments, & Security Assessment | B57: ='Program Budget'!F159 -> Year | C57: ='Program Budget'!H159 -> 2000 | D57: ='Program Budget'!G159 -> 1 | E57: 1 | F57: =C57*D57*E57 -> 2000 | G57: =C57 -> 2000 | H57: ='Program Budget'!K159 -> 1 | I57: 1 | J57: =G57*H57*I57 -> 2000 | K57: =G57 -> 2000 | L57: ='Program Budget'!N159 -> 1 | M57: 1 | N57: =K57*L57*M57 -> 2000 | O57: =K57 -> 2000 | P57: ='Program Budget'!Q159 -> 1 | Q57: 1 | R57: =O57*P57*Q57 -> 2000 | S57: =O57 -> 2000 | T57: ='Program Budget'!T159 -> 0 | U57: 0 | V57: =S57*T57*U57 -> 0 | W57: =F57+J57+N57+R57+V57 -> 8000
A58: Subtotal: Professional Services/Contractual | F58: =SUM(F56:F57) -> 2000 | J58: =SUM(J56:J57) -> 82000 | N58: =SUM(N56:N57) -> 162000 | R58: =SUM(R56:R57) -> 162000 | V58: =SUM(V56:V57) -> 0 | W58: =+F58+J58+N58+R58+V58 -> 408000
A59: Equipment (>$5000/unit)
A60: None | F60: =C60*D60*E60 -> 0 | J60: =G60*H60*I60 -> 0 | N60: =K60*L60*M60 -> 0 | R60: =O60*P60*Q60 -> 0 | V60: =S60*T60*U60 -> 0 | W60: =F60+J60+N60+R60+V60 -> 0
A61: Subtotal: Equipment | F61: =SUM(F60:F60) -> 0 | J61: =SUM(J60:J60) -> 0 | N61: =SUM(N60:N60) -> 0 | R61: =SUM(R60:R60) -> 0 | V61: =SUM(V60:V60) -> 0 | W61: =+F61+J61+N61+R61+V61 -> 0
A62: Office
A63: None | F63: =C63*D63*E63 -> 0 | J63: =G63*H63*I63 -> 0 | N63: =K63*L63*M63 -> 0 | R63: =O63*P63*Q63 -> 0 | V63: =S63*T63*U63 -> 0 | W63: =F63+J63+N63+R63+V63 -> 0
A64: Subtotal: Office | F64: =SUM(F60:F60) -> 0 | J64: =SUM(J60:J60) -> 0 | N64: =SUM(N60:N60) -> 0 | R64: =SUM(R60:R60) -> 0 | V64: =SUM(V60:V60) -> 0 | W64: =+F64+J64+N64+R64+V64 -> 0
A65: Supplies
A66: None | F66: =C66*D66*E66 -> 0 | J66: =G66*H66*I66 -> 0 | N66: =K66*L66*M66 -> 0 | R66: =O66*P66*Q66 -> 0 | V66: =S66*T66*U66 -> 0 | W66: =F66+J66+N66+R66+V66 -> 0
A68: Subtotal: Supplies | F68: =SUM(F66:F67) -> 0 | J68: =SUM(J66:J67) -> 0 | N68: =SUM(N66:N67) -> 0 | R68: =SUM(R66:R67) -> 0 | V68: =SUM(V66:V67) -> 0 | W68: =+F68+J68+N68+R68+V68 -> 0
A69: Other Direct Cost
A70: Subaward
A71: ='Program Budget'!D176 -> Subrecipient: U.S. Soybean Export Council (USSEC) | B71: ='Program Budget'!F176 -> Subaward | C71: ='Program Budget'!I176 -> 296003.1 | D71: ='Program Budget'!G176 -> 1 | E71: 1 | F71: =C71*D71*E71 -> 296003.1 | G71: ='Program Budget'!L176 -> 694790.9 | H71: ='Program Budget'!K176 -> 1 | I71: 1 | J71: =G71*H71*I71 -> 694790.9 | K71: ='Program Budget'!O176 -> 714164.03 | L71: ='Program Budget'!N176 -> 1 | M71: 1 | N71: =K71*L71*M71 -> 714164.03 | O71: ='Program Budget'!R176 -> 418999.05 | P71: 1 | Q71: 1 | R71: =O71*P71*Q71 -> 418999.05 | S71: ='Program Budget'!U176 -> 0 | T71: ='Program Budget'!T176 -> 0 | U71: 0 | V71: =S71*T71*U71 -> 0 | W71: =F71+J71+N71+R71+V71 -> 2123957.1
A72: Subtotal: Other Direct Cost | F72: =SUM(F69:F71) -> 296003.1 | J72: =SUM(J69:J71) -> 694790.9 | N72: =SUM(N69:N71) -> 714164.03 | R72: =SUM(R69:R71) -> 418999.05 | V72: =SUM(V69:V71) -> 0 | W72: =+F72+J72+N72+R72+V72 -> 2123957.1
A74: Total Direct Cost | F74: =F32+F42+F54+F64+F68+F58+F72+F61 -> 428728.58 | J74: =J32+J42+J54+J64+J68+J58+J72+J61 -> 1002874.8 | N74: =N32+N42+N54+N64+N68+N58+N72+N61 -> 1113552.1 | R74: =R32+R42+R54+R64+R68+R58+R72+R61 -> 894318.55 | V74: =V32+V42+V54+V64+V68+V58+V72+V61 -> 0 | W74: =W32+W42+W54+W64+W68+W58+W72 -> 3439474
A76: Indirect Costs
A77: ICR on Administration | B77: % | C77: 0 | D77: 0 | E77: 0.15 | F77: =C77*D77*E77 -> 0 | G77: 0 | H77: 0 | I77: =E77 -> 0.15 | J77: =G77*H77*I77 -> 0 | K77: 0 | L77: 0 | M77: =I77 -> 0.15 | N77: =K77*L77*M77 -> 0 | O77: 0 | P77: 0 | Q77: =M77 -> 0.15 | R77: =O77*P77*Q77 -> 0 | S77: 0 | T77: 0 | U77: 0 | V77: =S77*T77*U77 -> 0 | W77: =F77+J77+N77+R77+V77 -> 0
A78: ICR on Activities (Total Direct Activities Costs Less Subawards) | B78: % | C78: =F74-F71 -> 132725.48 | D78: 1 | E78: 0.15 | F78: =C78*D78*E78 -> 19908.823 | G78: =J74-J71 -> 308083.86 | H78: 1 | I78: =E78 -> 0.15 | J78: =G78*H78*I78 -> 46212.579 | K78: =N74-N71 -> 399388.06 | L78: 1 | M78: =I78 -> 0.15 | N78: =K78*L78*M78 -> 59908.208 | O78: =R74-R71 -> 475319.5 | P78: 1 | Q78: =M78 -> 0.15 | R78: =O78*P78*Q78 -> 71297.925 | S78: =V74-V71 -> 0 | T78: 1 | U78: 0 | V78: =S78*T78*U78 -> 0 | W78: =F78+J78+N78+R78+V78 -> 197327.54
A79: ICR on Activities (Subawards) | B79: % | C79: =F71 -> 296003.1 | D79: 1 | E79: 0.07 | F79: =C79*D79*E79 -> 20720.217 | G79: =J71 -> 694790.9 | H79: 1 | I79: =E79 -> 0.07 | J79: =G79*H79*I79 -> 48635.363 | K79: =N71 -> 714164.03 | L79: 1 | M79: =I79 -> 0.07 | N79: =K79*L79*M79 -> 49991.482 | O79: =R71 -> 418999.05 | P79: 1 | Q79: =M79 -> 0.07 | R79: =O79*P79*Q79 -> 29329.933 | S79: =V71 -> 0 | T79: 1 | U79: 0 | V79: =S79*T79*U79 -> 0 | W79: =F79+J79+N79+R79+V79 -> 148677
A81: Subtotal Indirect Cost | F81: =SUM(F77:F80) -> 40629.04 | J81: =SUM(J77:J80) -> 94847.942 | N81: =SUM(N77:N80) -> 109899.69 | R81: =SUM(R77:R80) -> 100627.86 | V81: =SUM(V77:V80) -> 0 | W81: =SUM(W77:W80) -> 346004.53
A83: Total Estimated Cost (Direct Cost + Indirect Cost) | F83: =F74+F81 -> 469357.62 | J83: =J74+J81 -> 1097722.7 | N83: =N74+N81 -> 1223451.8 | R83: =R74+R81 -> 994946.41 | V83: =V74+V81 -> 0 | W83: =F83+J83+N83+R83+V83 -> 3785478.5
A84: ='Program Budget'!D180 -> Public & Private Sector Support for Nation-wide Poultry Consumption Campaign | B84: ='Program Budget'!F180 -> Year | C84: ='Program Budget'!H180 -> 16000 | D84: ='Program Budget'!G180 -> 0 | E84: 1 | F84: =C84*D84*E84 -> 0 | G84: =C84 -> 16000 | H84: ='Program Budget'!K180 -> 0.5 | I84: 1 | J84: =G84*H84*I84 -> 8000 | K84: =G84 -> 16000 | L84: ='Program Budget'!N180 -> 1 | M84: 1 | N84: =K84*L84*M84 -> 16000 | O84: =K84 -> 16000 | P84: ='Program Budget'!N176 -> 1 | Q84: 1 | R84: =O84*P84*Q84 -> 16000 | S84: =O84 -> 16000 | T84: ='Program Budget'!T180 -> 0 | U84: 0 | V84: =S84*T84*U84 -> 0 | W84: =F84+J84+N84+R84+V84 -> 40000
A85: Total Estimated Cost (Direct Cost + Indirect Cost+ Cost Share) | F85: =SUM(F83:F84) -> 469357.62 | J85: =SUM(J83:J84) -> 1105722.7 | N85: =SUM(N83:N84) -> 1239451.8 | R85: =SUM(R83:R84) -> 1010946.4 | V85: =SUM(V83:V84) -> 0 | W85: =F85+J85+N85+R85+V85 -> 3825478.5
A87: Anticipated Program Income (baked in costs and this is for reference)

Sheet Activity 2
A2: Item | B2: Type of Unit | C2: Year 1 | G2: Year 2 | K2: Year 3 | O2: Year 4 | S2: Year 5 | W2: Total
C3: Cost | D3: Quantity | E3: Percent Allocated | F3: Total | G3: Cost | H3: Quantity | I3: Percent Allocated | J3: Total | K3: Cost | L3: Quantity | M3: Percent Allocated | N3: Total | O3: Cost | P3: Quantity | Q3: Percent Allocated | R3: Total | S3: Cost | T3: Quantity | U3: Percent Allocated | V3: Total
A4: Direct Costs
A5: Salaries
A6: USN/TCN Staff
A7: None | F7: =C7*D7*E7 -> 0 | J7: =G7*H7*I7 -> 0 | N7: =K7*L7*M7 -> 0 | R7: =O7*P7*Q7 -> 0 | V7: =S7*T7*U7 -> 0 | W7: =F7+J7+N7+R7+V7 -> 0
A8: Total: Expatriate Salaries & Wages | F8: =SUM(F7:F7) -> 0 | J8: =SUM(J7:J7) -> 0 | N8: =SUM(N7:N7) -> 0 | R8: =SUM(R7:R7) -> 0 | V8: =SUM(V7:V7) -> 0 | W8: =+F8+J8+N8+R8+V8 -> 0
A9: CCN Staff
A10: ='Program Budget'!D12 -> Key Personnel: Chief of Party | B10: ='Program Budget'!F188 -> Month | C10: ='Program Budget'!H12 -> 9583.3333 | D10: ='Program Budget'!G12 -> 11 | E10: ='Program Budget'!E188 -> 0.2 | F10: =C10*D10*E10 -> 21083.333 | G10: =C10*1.05 -> 10062.5 | H10: ='Program Budget'!K12 -> 12 | I10: ='Program Budget'!J188 -> 0.55 | J10: =G10*H10*I10 -> 66412.5 | K10: =G10*1.05 -> 10565.625 | L10: ='Program Budget'!N12 -> 12 | M10: ='Program Budget'!M188 -> 0.55 | N10: =K10*L10*M10 -> 69733.125 | O10: =K10*1.05 -> 11093.906 | P10: ='Program Budget'!Q12 -> 12 | Q10: ='Program Budget'!P188 -> 0.6 | R10: =O10*P10*Q10 -> 79876.125 | S10: =O10*1.05 -> 11648.602 | T10: ='Program Budget'!T12 -> 0 | U10: ='Program Budget'!S188 -> 0 | V10: =S10*T10*U10 -> 0 | W10: =F10+J10+N10+R10+V10 -> 237105.08
A11: ='Program Budget'!D13 -> Technical Director | B11: ='Program Budget'!F189 -> Month | C11: ='Program Budget'!H13 -> 3500 | D11: ='Program Budget'!G13 -> 9 | E11: ='Program Budget'!E189 -> 0.35 | F11: =C11*D11*E11 -> 11025 | G11: =C11*1.05 -> 3675 | H11: ='Program Budget'!K13 -> 12 | I11: ='Program Budget'!J189 -> 0.6 | J11: =G11*H11*I11 -> 26460 | K11: =G11*1.05 -> 3858.75 | L11: ='Program Budget'!N13 -> 12 | M11: ='Program Budget'!M189 -> 0.6 | N11: =K11*L11*M11 -> 27783 | O11: =K11*1.05 -> 4051.6875 | P11: ='Program Budget'!Q13 -> 12 | Q11: ='Program Budget'!P189 -> 0.6 | R11: =O11*P11*Q11 -> 29172.15 | S11: =O11*1.05 -> 4254.2719 | T11: ='Program Budget'!T13 -> 0 | U11: ='Program Budget'!S189 -> 0 | V11: =S11*T11*U11 -> 0 | W11: =F11+J11+N11+R11+V11 -> 94440.15
A12: ='Program Budget'!D14 -> Technical Lead - Activity 2 US Exports | B12: ='Program Budget'!F190 -> Month | C12: ='Program Budget'!H14 -> 2833.3333 | D12: ='Program Budget'!G14 -> 8 | E12: ='Program Budget'!E190 -> 0.8 | F12: =C12*D12*E12 -> 18133.333 | G12: =C12*1.05 -> 2975 | H12: ='Program Budget'!K14 -> 12 | I12: ='Program Budget'!J190 -> 1 | J12: =G12*H12*I12 -> 35700 | K12: =G12*1.05 -> 3123.75 | L12: ='Program Budget'!N14 -> 12 | M12: ='Program Budget'!M190 -> 1 | N12: =K12*L12*M12 -> 37485 | O12: =K12*1.05 -> 3279.9375 | P12: ='Program Budget'!Q14 -> 12 | Q12: ='Program Budget'!P190 -> 1 | R12: =O12*P12*Q12 -> 39359.25 | S12: =O12*1.05 -> 3443.9344 | T12: ='Program Budget'!T14 -> 0 | U12: ='Program Budget'!S190 -> 0 | V12: =S12*T12*U12 -> 0 | W12: =F12+J12+N12+R12+V12 -> 130677.58
A13: ='Program Budget'!D15 -> Technical Lead - Activity 2 Access to Finance Specialist | B13: ='Program Budget'!F191 -> Month | C13: ='Program Budget'!H15 -> 2833.3333 | D13: ='Program Budget'!G15 -> 8 | E13: ='Program Budget'!E191 -> 0.8 | F13: =C13*D13*E13 -> 18133.333 | G13: =C13*1.05 -> 2975 | H13: ='Program Budget'!K15 -> 12 | I13: ='Program Budget'!J191 -> 1 | J13: =G13*H13*I13 -> 35700 | K13: =G13*1.05 -> 3123.75 | L13: ='Program Budget'!N15 -> 12 | M13: ='Program Budget'!M191 -> 1 | N13: =K13*L13*M13 -> 37485 | O13: =K13*1.05 -> 3279.9375 | P13: ='Program Budget'!Q15 -> 12 | Q13: ='Program Budget'!P191 -> 1 | R13: =O13*P13*Q13 -> 39359.25 | S13: =O13*1.05 -> 3443.9344 | T13: ='Program Budget'!T15 -> 0 | U13: ='Program Budget'!S191 -> 0 | V13: =S13*T13*U13 -> 0 | W13: =F13+J13+N13+R13+V13 -> 130677.58
A14: ='Program Budget'!D16 -> Communications/Strategic Partnerships Manager | B14: ='Program Budget'!F192 -> Month | C14: ='Program Budget'!H16 -> 2666.6667 | D14: ='Program Budget'!G16 -> 8 | E14: ='Program Budget'!E192 -> 0.3 | F14: =C14*D14*E14 -> 6400 | G14: =C14*1.05 -> 2800 | H14: ='Program Budget'!K16 -> 12 | I14: ='Program Budget'!J192 -> 0.35 | J14: =G14*H14*I14 -> 11760 | K14: =G14*1.05 -> 2940 | L14: ='Program Budget'!N16 -> 12 | M14: ='Program Budget'!M192 -> 0.35 | N14: =K14*L14*M14 -> 12348 | O14: =K14*1.05 -> 3087 | P14: ='Program Budget'!Q16 -> 12 | Q14: ='Program Budget'!P192 -> 0.5 | R14: =O14*P14*Q14 -> 18522 | S14: =O14*1.05 -> 3241.35 | T14: ='Program Budget'!T16 -> 0 | U14: ='Program Budget'!S192 -> 0 | V14: =S14*T14*U14 -> 0 | W14: =F14+J14+N14+R14+V14 -> 49030
A15: ='Program Budget'!D17 -> M&E Director | B15: ='Program Budget'!F193 -> Month | C15: ='Program Budget'!H17 -> 3500 | D15: ='Program Budget'!G17 -> 10 | E15: ='Program Budget'!E193 -> 0.25 | F15: =C15*D15*E15 -> 8750 | G15: =C15*1.05 -> 3675 | H15: ='Program Budget'!K17 -> 12 | I15: ='Program Budget'!J193 -> 0.45 | J15: =G15*H15*I15 -> 19845 | K15: =G15*1.05 -> 3858.75 | L15: ='Program Budget'!N17 -> 12 | M15: ='Program Budget'!M193 -> 0.45 | N15: =K15*L15*M15 -> 20837.25 | O15: =K15*1.05 -> 4051.6875 | P15: ='Program Budget'!Q17 -> 12 | Q15: ='Program Budget'!P193 -> 0.5 | R15: =O15*P15*Q15 -> 24310.125 | S15: =O15*1.05 -> 4254.2719 | T15: ='Program Budget'!T17 -> 0 | U15: ='Program Budget'!S193 -> 0 | V15: =S15*T15*U15 -> 0 | W15: =F15+J15+N15+R15+V15 -> 73742.375
A16: ='Program Budget'!D18 -> M&E Specialist | B16: ='Program Budget'!F194 -> Month | C16: ='Program Budget'!H18 -> 2000 | D16: ='Program Budget'!G18 -> 8 | E16: ='Program Budget'!E194 -> 0.3 | F16: =C16*D16*E16 -> 4800 | G16: =C16*1.05 -> 2100 | H16: ='Program Budget'!K18 -> 12 | I16: ='Program Budget'!J194 -> 0.45 | J16: =G16*H16*I16 -> 11340 | K16: =G16*1.05 -> 2205 | L16: ='Program Budget'!N18 -> 12 | M16: ='Program Budget'!M194 -> 0.45 | N16: =K16*L16*M16 -> 11907 | O16: =K16*1.05 -> 2315.25 | P16: ='Program Budget'!Q18 -> 12 | Q16: ='Program Budget'!P194 -> 0.5 | R16: =O16*P16*Q16 -> 13891.5 | S16: =O16*1.05 -> 2431.0125 | T16: ='Program Budget'!T18 -> 0 | U16: ='Program Budget'!S194 -> 0 | V16: =S16*T16*U16 -> 0 | W16: =F16+J16+N16+R16+V16 -> 41938.5
A17: ='Program Budget'!D19 -> Key Personnel: Finance & Administration (F&A) Director | B17: ='Program Budget'!F195 -> Month | C17: ='Program Budget'!H19 -> 3500 | D17: ='Program Budget'!G19 -> 10 | E17: ='Program Budget'!E195 -> 0.25 | F17: =C17*D17*E17 -> 8750 | G17: =C17*1.05 -> 3675 | H17: ='Program Budget'!K19 -> 12 | I17: ='Program Budget'!J195 -> 0.35 | J17: =G17*H17*I17 -> 15435 | K17: =G17*1.05 -> 3858.75 | L17: ='Program Budget'!N19 -> 12 | M17: ='Program Budget'!M195 -> 0.35 | N17: =K17*L17*M17 -> 16206.75 | O17: =K17*1.05 -> 4051.6875 | P17: ='Program Budget'!Q19 -> 12 | Q17: ='Program Budget'!P195 -> 0.5 | R17: =O17*P17*Q17 -> 24310.125 | S17: =O17*1.05 -> 4254.2719 | T17: ='Program Budget'!T19 -> 0 | U17: ='Program Budget'!S195 -> 0 | V17: =S17*T17*U17 -> 0 | W17: =F17+J17+N17+R17+V17 -> 64701.875
A18: ='Program Budget'!D20 -> Accountant | B18: ='Program Budget'!F196 -> Month | C18: ='Program Budget'!H20 -> 2000 | D18: ='Program Budget'!G20 -> 8 | E18: ='Program Budget'!E196 -> 0.3 | F18: =C18*D18*E18 -> 4800 | G18: =C18*1.05 -> 2100 | H18: ='Program Budget'!K20 -> 12 | I18: ='Program Budget'!J196 -> 0.5 | J18: =G18*H18*I18 -> 12600 | K18: =G18*1.05 -> 2205 | L18: ='Program Budget'!N20 -> 12 | M18: ='Program Budget'!M196 -> 0.5 | N18: =K18*L18*M18 -> 13230 | O18: =K18*1.05 -> 2315.25 | P18: ='Program Budget'!Q20 -> 12 | Q18: ='Program Budget'!P196 -> 0.55 | R18: =O18*P18*Q18 -> 15280.65 | S18: =O18*1.05 -> 2431.0125 | T18: ='Program Budget'!T20 -> 0 | U18: ='Program Budget'!S196 -> 0 | V18: =S18*T18*U18 -> 0 | W18: =F18+J18+N18+R18+V18 -> 45910.65
A19: ='Program Budget'!D21 -> Administration/ HR Manager | B19: ='Program Budget'!F197 -> Month | C19: ='Program Budget'!H21 -> 2666.6667 | D19: ='Program Budget'!G21 -> 10 | E19: ='Program Budget'!E197 -> 0.4 | F19: =C19*D19*E19 -> 10666.667 | G19: =C19*1.05 -> 2800 | H19: ='Program Budget'!K21 -> 12 | I19: ='Program Budget'!J197 -> 0.45 | J19: =G19*H19*I19 -> 15120 | K19: =G19*1.05 -> 2940 | L19: ='Program Budget'!N21 -> 12 | M19: ='Program Budget'!M197 -> 0.45 | N19: =K19*L19*M19 -> 15876 | O19: =K19*1.05 -> 3087 | P19: ='Program Budget'!Q21 -> 12 | Q19: ='Program Budget'!P197 -> 0.55 | R19: =O19*P19*Q19 -> 20374.2 | S19: =O19*1.05 -> 3241.35 | T19: ='Program Budget'!T21 -> 0 | U19: ='Program Budget'!S197 -> 0 | V19: =S19*T19*U19 -> 0 | W19: =F19+J19+N19+R19+V19 -> 62036.867
A20: ='Program Budget'!D22 -> Grants & Contracts Manager | B20: ='Program Budget'!F198 -> Month | C20: ='Program Budget'!H22 -> 2666.6667 | D20: ='Program Budget'!G22 -> 9 | E20: ='Program Budget'!E198 -> 0.3 | F20: =C20*D20*E20 -> 7200 | G20: =C20*1.05 -> 2800 | H20: ='Program Budget'!K22 -> 12 | I20: ='Program Budget'!J198 -> 0.4 | J20: =G20*H20*I20 -> 13440 | K20: =G20*1.05 -> 2940 | L20: ='Program Budget'!N22 -> 12 | M20: ='Program Budget'!M198 -> 0.4 | N20: =K20*L20*M20 -> 14112 | O20: =K20*1.05 -> 3087 | P20: ='Program Budget'!Q22 -> 12 | Q20: ='Program Budget'!P198 -> 0.6 | R20: =O20*P20*Q20 -> 22226.4 | S20: =O20*1.05 -> 3241.35 | T20: ='Program Budget'!T22 -> 0 | U20: ='Program Budget'!S198 -> 0 | V20: =S20*T20*U20 -> 0 | W20: =F20+J20+N20+R20+V20 -> 56978.4
A21: ='Program Budget'!D23 -> Compliance & Procurement Specialist | B21: ='Program Budget'!F199 -> Month | C21: ='Program Budget'!H23 -> 2000 | D21: ='Program Budget'!G23 -> 9 | E21: ='Program Budget'!E199 -> 0.3 | F21: =C21*D21*E21 -> 5400 | G21: =C21*1.05 -> 2100 | H21: ='Program Budget'!K23 -> 12 | I21: ='Program Budget'!J199 -> 0.4 | J21: =G21*H21*I21 -> 10080 | K21: =G21*1.05 -> 2205 | L21: ='Program Budget'!N23 -> 12 | M21: ='Program Budget'!M199 -> 0.4 | N21: =K21*L21*M21 -> 10584 | O21: =K21*1.05 -> 2315.25 | P21: ='Program Budget'!Q23 -> 12 | Q21: ='Program Budget'!P199 -> 0.6 | R21: =O21*P21*Q21 -> 16669.8 | S21: =O21*1.05 -> 2431.0125 | T21: ='Program Budget'!T23 -> 0 | U21: ='Program Budget'!S199 -> 0 | V21: =S21*T21*U21 -> 0 | W21: =F21+J21+N21+R21+V21 -> 42733.8
A22: ='Program Budget'!D24 -> Driver | B22: ='Program Budget'!F200 -> Month | C22: ='Program Budget'!H24 -> 500 | D22: ='Program Budget'!G24 -> 7 | E22: ='Program Budget'!E200 -> 0.5 | F22: =C22*D22*E22 -> 1750 | G22: =C22*1.05 -> 525 | H22: ='Program Budget'!K24 -> 12 | I22: ='Program Budget'!J200 -> 0.5 | J22: =G22*H22*I22 -> 3150 | K22: =G22*1.05 -> 551.25 | L22: ='Program Budget'!N24 -> 12 | M22: ='Program Budget'!M200 -> 0.5 | N22: =K22*L22*M22 -> 3307.5 | O22: =K22*1.05 -> 578.8125 | P22: ='Program Budget'!Q24 -> 12 | Q22: ='Program Budget'!P200 -> 0.65 | R22: =O22*P22*Q22 -> 4514.7375 | S22: =O22*1.05 -> 607.75313 | T22: ='Program Budget'!T24 -> 0 | U22: ='Program Budget'!S200 -> 0 | V22: =S22*T22*U22 -> 0 | W22: =F22+J22+N22+R22+V22 -> 12722.237
A23: Total Local Salary Cost | F23: =SUM(F10:F22) -> 126891.67 | J23: =SUM(J10:J22) -> 277042.5 | N23: =SUM(N10:N22) -> 290894.62 | R23: =SUM(R10:R22) -> 347866.31 | V23: =SUM(V11:V22) -> 0 | W23: =SUM(W10:W22) -> 1042695.1
A24: HQ Staff
A25: ='Program Budget'!D26 -> Senior Vice President of Programs | B25: ='Program Budget'!F202 -> Month | C25: ='Program Budget'!H202 -> 13500 | D25: ='Program Budget'!G202 -> 12 | E25: ='Program Budget'!E202 -> 0.01 | F25: =C25*D25*E25 -> 1620 | G25: =C25*1.05 -> 14175 | H25: ='Program Budget'!K202 -> 12 | I25: ='Program Budget'!J202 -> 0.01 | J25: =G25*H25*I25 -> 1701 | K25: =G25*1.05 -> 14883.75 | L25: ='Program Budget'!N202 -> 12 | M25: ='Program Budget'!M202 -> 0.01 | N25: =K25*L25*M25 -> 1786.05 | O25: =K25*1.05 -> 15627.938 | P25: ='Program Budget'!Q202 -> 12 | Q25: ='Program Budget'!P202 -> 0.01 | R25: =O25*P25*Q25 -> 1875.3525 | S25: =O25*1.05 -> 16409.334 | T25: ='Program Budget'!T202 -> 0 | U25: ='Program Budget'!S202 -> 0 | V25: =S25*T25*U25 -> 0 | W25: =F25+J25+N25+R25+V25 -> 6982.4025
A26: ='Program Budget'!D27 -> Senior Program Director | B26: ='Program Budget'!F203 -> Month | C26: ='Program Budget'!H203 -> 12500 | D26: ='Program Budget'!G203 -> 12 | E26: ='Program Budget'!E203 -> 0.05 | F26: =C26*D26*E26 -> 7500 | G26: =C26*1.05 -> 13125 | H26: ='Program Budget'!K203 -> 12 | I26: ='Program Budget'!J203 -> 0.1 | J26: =G26*H26*I26 -> 15750 | K26: =G26*1.05 -> 13781.25 | L26: ='Program Budget'!N203 -> 12 | M26: ='Program Budget'!M203 -> 0.1 | N26: =K26*L26*M26 -> 16537.5 | O26: =K26*1.05 -> 14470.312 | P26: ='Program Budget'!Q203 -> 12 | Q26: ='Program Budget'!P203 -> 0.1 | R26: =O26*P26*Q26 -> 17364.375 | S26: =O26*1.05 -> 15193.828 | T26: ='Program Budget'!T203 -> 0 | U26: ='Program Budget'!S203 -> 0 | V26: =S26*T26*U26 -> 0 | W26: =F26+J26+N26+R26+V26 -> 57151.875
A27: ='Program Budget'!D28 -> Associate Director | B27: ='Program Budget'!F204 -> Month | C27: ='Program Budget'!H204 -> 7500 | D27: ='Program Budget'!G204 -> 12 | E27: ='Program Budget'!E204 -> 0.4 | F27: =C27*D27*E27 -> 36000 | G27: =C27*1.05 -> 7875 | H27: ='Program Budget'!K204 -> 12 | I27: ='Program Budget'!J204 -> 0.55 | J27: =G27*H27*I27 -> 51975 | K27: =G27*1.05 -> 8268.75 | L27: ='Program Budget'!N204 -> 12 | M27: ='Program Budget'!M204 -> 0.55 | N27: =K27*L27*M27 -> 54573.75 | O27: =K27*1.05 -> 8682.1875 | P27: ='Program Budget'!Q204 -> 12 | Q27: ='Program Budget'!P204 -> 0.55 | R27: =O27*P27*Q27 -> 57302.438 | S27: =O27*1.05 -> 9116.2969 | T27: ='Program Budget'!T204 -> 0 | U27: ='Program Budget'!S204 -> 0 | V27: =S27*T27*U27 -> 0 | W27: =F27+J27+N27+R27+V27 -> 199851.19
A28: ='Program Budget'!D29 -> Compliance & Contracts Director | B28: ='Program Budget'!F205 -> Month | C28: ='Program Budget'!H205 -> 9166.6667 | D28: ='Program Budget'!G205 -> 12 | E28: ='Program Budget'!E205 -> 0.05 | F28: =C28*D28*E28 -> 5500 | G28: =C28*1.05 -> 9625 | H28: ='Program Budget'!K205 -> 12 | I28: ='Program Budget'!J205 -> 0.1 | J28: =G28*H28*I28 -> 11550 | K28: =G28*1.05 -> 10106.25 | L28: ='Program Budget'!N205 -> 12 | M28: ='Program Budget'!M205 -> 0.1 | N28: =K28*L28*M28 -> 12127.5 | O28: =K28*1.05 -> 10611.562 | P28: ='Program Budget'!Q205 -> 12 | Q28: ='Program Budget'!P205 -> 0.1 | R28: =O28*P28*Q28 -> 12733.875 | S28: =O28*1.05 -> 11142.141 | T28: ='Program Budget'!T205 -> 0 | U28: ='Program Budget'!S205 -> 0 | V28: =S28*T28*U28 -> 0 | W28: =F28+J28+N28+R28+V28 -> 41911.375
A29: ='Program Budget'!D30 -> Finance, HR, & Administration Home Office Support | B29: ='Program Budget'!F206 -> Month | C29: ='Program Budget'!H206 -> 7500 | D29: ='Program Budget'!G206 -> 12 | E29: ='Program Budget'!E206 -> 0.2 | F29: =C29*D29*E29 -> 18000 | G29: =C29*1.05 -> 7875 | H29: ='Program Budget'!K206 -> 12 | I29: ='Program Budget'!J206 -> 0.35 | J29: =G29*H29*I29 -> 33075 | K29: =G29*1.05 -> 8268.75 | L29: ='Program Budget'!N206 -> 12 | M29: ='Program Budget'!M206 -> 0.35 | N29: =K29*L29*M29 -> 34728.75 | O29: =K29*1.05 -> 8682.1875 | P29: ='Program Budget'!Q206 -> 12 | Q29: ='Program Budget'!P206 -> 0.35 | R29: =O29*P29*Q29 -> 36465.188 | S29: =O29*1.05 -> 9116.2969 | T29: ='Program Budget'!T206 -> 0 | U29: ='Program Budget'!S206 -> 0 | V29: =S29*T29*U29 -> 0 | W29: =F29+J29+N29+R29+V29 -> 122268.94
A30: Total HQ Staff | F30: =SUM(F24:F29) -> 68620 | J30: =SUM(J24:J29) -> 114051 | N30: =SUM(N24:N29) -> 119753.55 | R30: =SUM(R24:R29) -> 125741.23 | V30: =SUM(V24:V29) -> 0 | W30: =SUM(W24:W29) -> 428165.78
A32: Subtotal: Salaries & Wages | F32: =F23+F8+F30 -> 195511.67 | J32: =J23+J8+J30 -> 391093.5 | N32: =N23+N8+N30 -> 410648.17 | R32: =R23+R8+R30 -> 473607.54 | V32: =V23+V8+V30 -> 0 | W32: =W23+W8+W30 -> 1470860.9
A33: Fringe Benefits
A34: USN/TCN Staff | B34: ='Program Budget'!F210 -> % | C34: =F8 -> 0 | D34: 1 | E34: 0 | F34: =C34*D34*E34 -> 0 | G34: =J8 -> 0 | H34: 1 | I34: =E34 -> 0 | J34: =G34*H34*I34 -> 0 | K34: =N8 -> 0 | L34: 1 | M34: =E34 -> 0 | N34: =K34*L34*M34 -> 0 | O34: =R8 -> 0 | P34: 1 | Q34: =E34 -> 0 | R34: =O34*P34*Q34 -> 0 | S34: =V8 -> 0 | T34: 1 | U34: =E34 -> 0 | V34: =S34*T34*U34 -> 0 | W34: =F34+J34+N34+R34+V34 -> 0
A35: CCN - Nigeria (above $3,500 monthly) | B35: ='Program Budget'!F210 -> % | C35: =F23 -> 126891.67 | D35: 1 | E35: ='Program Budget'!H210 -> 0.296 | F35: =C35*D35*E35 -> 37559.933 | G35: =J23 -> 277042.5 | H35: 1 | I35: =E35 -> 0.296 | J35: =G35*H35*I35 -> 82004.58 | K35: =N23 -> 290894.62 | L35: 1 | M35: =E35 -> 0.296 | N35: =K35*L35*M35 -> 86104.809 | O35: =R23 -> 347866.31 | P35: 1 | Q35: =E35 -> 0.296 | R35: =O35*P35*Q35 -> 102968.43 | S35: =V23 -> 0 | T35: 1 | U35: 0 | V35: =S35*T35*U35 -> 0 | W35: =F35+J35+N35+R35+V35 -> 308637.75
A36: HQ Staff | B36: ='Program Budget'!F211 -> % | C36: =F30 -> 68620 | D36: 1 | E36: ='Program Budget'!H211 -> 0.2347 | F36: =C36*D36*E36 -> 16105.114 | G36: =J30 -> 114051 | H36: 1 | I36: =E36 -> 0.2347 | J36: =G36*H36*I36 -> 26767.77 | K36: =N30 -> 119753.55 | L36: 1 | M36: =E36 -> 0.2347 | N36: =K36*L36*M36 -> 28106.158 | O36: =R30 -> 125741.23 | P36: 1 | Q36: =E36 -> 0.2347 | R36: =O36*P36*Q36 -> 29511.466 | S36: =V30 -> 0 | T36: 1 | U36: 0 | V36: =S36*T36*U36 -> 0 | W36: =F36+J36+N36+R36+V36 -> 100490.51
A37: Total: Fringe Benefits | F37: =+SUM(F34:F36) -> 53665.047 | J37: =+SUM(J34:J36) -> 108772.35 | N37: =+SUM(N34:N36) -> 114210.97 | R37: =+SUM(R34:R36) -> 132479.89 | V37: =+SUM(V34:V36) -> 0 | W37: =+F37+J37+N37+R37+V37 -> 409128.26
A38: Allowances | W38: =+F38+J38+N38+R38+V38 -> 0
A39: None | F39: =C39*D39*E39 -> 0 | J39: =G39*H39*I39 -> 0 | N39: =K39*L39*M39 -> 0 | R39: =O39*P39*Q39 -> 0 | V39: =S39*T39*U39 -> 0 | W39: =F39+J39+N39+R39+V39 -> 0
A40: Total: Allowances | F40: =SUM(F39:F39) -> 0 | J40: =SUM(J39:J39) -> 0 | N40: =SUM(N39:N39) -> 0 | R40: =SUM(R39:R39) -> 0 | V40: =SUM(V39:V39) -> 0 | W40: =F40+J40+N40+R40+V40 -> 0
A41: Subtotal: Benefits | F41: =F40+F37 -> 53665.047 | J41: =J40+J37 -> 108772.35 | N41: =N40+N37 -> 114210.97 | R41: =R40+R37 -> 132479.89 | V41: =V40+V37 -> 0 | W41: =+F41+J41+N41+R41+V41 -> 409128.26
A42: International Travel
A43: ='Program Budget'!D230 -> Airfare - Roundtrip - USA to Nigeria - Buyer Conferences for American Farmers, Ranchers and Agricultural Professionals - 50% of Cost | B43: ='Program Budget'!F227 -> Trip | C43: ='Program Budget'!H230 -> 900 | D43: ='Program Budget'!G230 -> 0 | E43: 1 | F43: =C43*D43*E43 -> 0 | G43: =C43*1.05 -> 945 | H43: ='Program Budget'!K230 -> 10 | I43: 1 | J43: =G43*H43*I43 -> 9450 | K43: =G43*1.05 -> 992.25 | L43: ='Program Budget'!N230 -> 10 | M43: 1 | N43: =K43*L43*M43 -> 9922.5 | O43: =K43*1.05 -> 1041.8625 | P43: ='Program Budget'!Q230 -> 0 | Q43: 1 | R43: =O43*P43*Q43 -> 0 | S43: =O43*1.05 -> 1093.9556 | T43: ='Program Budget'!T230 -> 0 | U43: 0 | V43: =S43*T43*U43 -> 0 | W43: =F43+J43+N43+R43+V43 -> 19372.5
A44: ='Program Budget'!D232 -> Airfare - Roundtrip - USA to Nigeria - Trade Finance & Export Consultant | B44: ='Program Budget'!F232 -> Trip | C44: ='Program Budget'!H232 -> 1800 | D44: ='Program Budget'!G232 -> 1 | E44: 1 | F44: =C44*D44*E44 -> 1800 | G44: =C44*1.05 -> 1890 | H44: ='Program Budget'!K232 -> 2 | I44: 1 | J44: =G44*H44*I44 -> 3780 | K44: =G44*1.05 -> 1984.5 | L44: ='Program Budget'!N232 -> 2 | M44: 1 | N44: =K44*L44*M44 -> 3969 | O44: =K44*1.05 -> 2083.725 | P44: ='Program Budget'!Q232 -> 1 | Q44: 1 | R44: =O44*P44*Q44 -> 2083.725 | S44: =O44*1.05 -> 2187.9113 | T44: ='Program Budget'!T232 -> 0 | U44: 0 | V44: =S44*T44*U44 -> 0 | W44: =F44+J44+N44+R44+V44 -> 11632.725
A45: Local Travel
A46: ='Program Budget'!D226 -> Local Transportation (Taxis/Ubers) for Project Implementation | B46: ='Program Budget'!F226 -> Month | C46: ='Program Budget'!H226 -> 300 | D46: ='Program Budget'!G226 -> 6 | E46: 1 | F46: =C46*D46*E46 -> 1800 | G46: =C46*1.05 -> 315 | H46: ='Program Budget'!K226 -> 12 | I46: 1 | J46: =G46*H46*I46 -> 3780 | K46: =G46*1.05 -> 330.75 | L46: ='Program Budget'!N226 -> 12 | M46: 1 | N46: =K46*L46*M46 -> 3969 | O46: =K46*1.05 -> 347.2875 | P46: ='Program Budget'!Q226 -> 12 | Q46: 1 | R46: =O46*P46*Q46 -> 4167.45 | S46: =O46*1.05 -> 364.65188 | T46: ='Program Budget'!T226 -> 0 | U46: 0 | V46: =S46*T46*U46 -> 0 | W46: =F46+J46+N46+R46+V46 -> 13716.45
A47: ='Program Budget'!D227 -> Roundtrip Domestic Airfare - Lagos to Implementing Regions for Trainings on Activity 2 | B47: ='Program Budget'!F227 -> Trip | C47: ='Program Budget'!H227 -> 250 | D47: ='Program Budget'!G227 -> 12 | E47: 1 | F47: =C47*D47*E47 -> 3000 | G47: =C47*1.05 -> 262.5 | H47: ='Program Budget'!K227 -> 24 | I47: 1 | J47: =G47*H47*I47 -> 6300 | K47: =G47*1.05 -> 275.625 | L47: ='Program Budget'!N227 -> 24 | M47: 1 | N47: =K47*L47*M47 -> 6615 | O47: =K47*1.05 -> 289.40625 | P47: ='Program Budget'!Q227 -> 24 | Q47: 1 | R47: =O47*P47*Q47 -> 6945.75 | S47: =O47*1.05 -> 303.87656 | T47: ='Program Budget'!T227 -> 0 | U47: 0 | V47: =S47*T47*U47 -> 0 | W47: =F47+J47+N47+R47+V47 -> 22860.75
A48: ='Program Budget'!D228 -> Local Transportation (Car Rental, Taxis) for Trainings on Activity 2 | B48: ='Program Budget'!F228 -> Trip | C48: ='Program Budget'!H228 -> 30 | D48: ='Program Budget'!G228 -> 12 | E48: 1 | F48: =C48*D48*E48 -> 360 | G48: =C48*1.05 -> 31.5 | H48: ='Program Budget'!K228 -> 24 | I48: 1 | J48: =G48*H48*I48 -> 756 | K48: =G48*1.05 -> 33.075 | L48: ='Program Budget'!N228 -> 24 | M48: 1 | N48: =K48*L48*M48 -> 793.8 | O48: =K48*1.05 -> 34.72875 | P48: ='Program Budget'!Q228 -> 24 | Q48: 1 | R48: =O48*P48*Q48 -> 833.49 | S48: =O48*1.05 -> 36.465188 | T48: ='Program Budget'!T228 -> 0 | U48: 0 | V48: =S48*T48*U48 -> 0 | W48: =F48+J48+N48+R48+V48 -> 2743.29
A49: ='Program Budget'!D234 -> Ground Transportation – Trade Finance & Export Consultant | B49: ='Program Budget'!F234 -> Trip | C49: ='Program Budget'!H234 -> 150 | D49: ='Program Budget'!G234 -> 1 | E49: 1 | F49: =C49*D49*E49 -> 150 | G49: =C49*1.05 -> 157.5 | H49: ='Program Budget'!K234 -> 2 | I49: 1 | J49: =G49*H49*I49 -> 315 | K49: =G49*1.05 -> 165.375 | L49: ='Program Budget'!N234 -> 2 | M49: 1 | N49: =K49*L49*M49 -> 330.75 | O49: =K49*1.05 -> 173.64375 | P49: ='Program Budget'!Q234 -> 1 | Q49: 1 | R49: =O49*P49*Q49 -> 173.64375 | S49: =O49*1.05 -> 182.32594 | T49: ='Program Budget'!T234 -> 0 | U49: 0 | V49: =S49*T49*U49 -> 0 | W49: =F49+J49+N49+R49+V49 -> 969.39375
A50: Vehicle Fuel
A51: ='Program Budget'!D225 -> Vehicle Fuel Expense (for Field Office Vehicle) | B51: ='Program Budget'!F225 -> Month | C51: ='Program Budget'!H225 -> 60 | D51: ='Program Budget'!G225 -> 3 | E51: 1 | F51: =C51*D51*E51 -> 180 | G51: =C51*1.05 -> 63 | H51: ='Program Budget'!K225 -> 12 | I51: 1 | J51: =G51*H51*I51 -> 756 | K51: =G51*1.05 -> 66.15 | L51: ='Program Budget'!N225 -> 12 | M51: 1 | N51: =K51*L51*M51 -> 793.8 | O51: =K51*1.05 -> 69.4575 | P51: ='Program Budget'!Q225 -> 12 | Q51: 1 | R51: =O51*P51*Q51 -> 833.49 | S51: =O51*1.05 -> 72.930375 | T51: ='Program Budget'!T225 -> 0 | U51: 0 | V51: =S51*T51*U51 -> 0 | W51: =F51+J51+N51+R51+V51 -> 2563.29
A52: Per Diem & Lodging | F52: =C52*D52*E52 -> 0 | J52: =G52*H52*I52 -> 0 | N52: =K52*L52*M52 -> 0 | R52: =O52*P52*Q52 -> 0
A53: ='Program Budget'!D229 -> Lodging and M&IE for Trainings on Activity 2 | B53: ='Program Budget'!F229 -> Day | C53: ='Program Budget'!H229 -> 145.5 | D53: ='Program Budget'!G229 -> 36 | E53: 1 | F53: =C53*D53*E53 -> 5238 | G53: =C53*1.05 -> 152.775 | H53: ='Program Budget'!K229 -> 72 | I53: 1 | J53: =G53*H53*I53 -> 10999.8 | K53: =G53*1.05 -> 160.41375 | L53: ='Program Budget'!N229 -> 72 | M53: 1 | N53: =K53*L53*M53 -> 11549.79 | O53: =K53*1.05 -> 168.43444 | P53: ='Program Budget'!Q229 -> 72 | Q53: 1 | R53: =O53*P53*Q53 -> 12127.28 | S53: =O53*1.05 -> 176.85616 | T53: ='Program Budget'!T229 -> 0 | U53: 0 | V53: =S53*T53*U53 -> 0 | W53: =F53+J53+N53+R53+V53 -> 39914.87
A54: ='Program Budget'!D231 -> Lodging and M&IE - Buyer Conferences for American Farmers, Ranchers and Agricultural Professionals - 50% of Cost | B54: ='Program Budget'!F231 -> Day | C54: ='Program Budget'!H231 -> 155.25 | D54: ='Program Budget'!G231 -> 0 | E54: 1 | F54: =C54*D54*E54 -> 0 | G54: =C54*1.05 -> 163.0125 | H54: ='Program Budget'!K231 -> 70 | I54: 1 | J54: =G54*H54*I54 -> 11410.875 | K54: =G54*1.05 -> 171.16313 | L54: ='Program Budget'!N231 -> 70 | M54: 1 | N54: =K54*L54*M54 -> 11981.419 | O54: =K54*1.05 -> 179.72128 | P54: ='Program Budget'!Q231 -> 0 | Q54: 1 | R54: =O54*P54*Q54 -> 0 | S54: =O54*1.05 -> 188.70735 | T54: ='Program Budget'!T231 -> 0 | U54: 0 | V54: =S54*T54*U54 -> 0 | W54: =F54+J54+N54+R54+V54 -> 23392.294
A55: ='Program Budget'!D233 -> Lodging and M&IE - Trade Finance & Export Consultant | B55: ='Program Budget'!F233 -> Day | C55: ='Program Budget'!H233 -> 310.5 | D55: ='Program Budget'!G233 -> 7 | E55: 1 | F55: =C55*D55*E55 -> 2173.5 | G55: =C55*1.05 -> 326.025 | H55: ='Program Budget'!K233 -> 14 | I55: 1 | J55: =G55*H55*I55 -> 4564.35 | K55: =G55*1.05 -> 342.32625 | L55: ='Program Budget'!N233 -> 14 | M55: 1 | N55: =K55*L55*M55 -> 4792.5675 | O55: =K55*1.05 -> 359.44256 | P55: ='Program Budget'!Q233 -> 7 | Q55: 1 | R55: =O55*P55*Q55 -> 2516.0979 | S55: =O55*1.05 -> 377.41469 | T55: ='Program Budget'!T233 -> 0 | U55: 0 | V55: =S55*T55*U55 -> 0 | W55: =F55+J55+N55+R55+V55 -> 14046.515
A56: ='Program Budget'!D235 -> Other Travel Related Expenses & Visa – Trade Finance & Export Consultant | B56: ='Program Budget'!F235 -> Trip | C56: ='Program Budget'!H235 -> 150 | D56: ='Program Budget'!G235 -> 1 | E56: 1 | F56: =C56*D56*E56 -> 150 | G56: =C56*1.05 -> 157.5 | H56: ='Program Budget'!K235 -> 2 | I56: 1 | J56: =G56*H56*I56 -> 315 | K56: =G56*1.05 -> 165.375 | L56: ='Program Budget'!N235 -> 2 | M56: 1 | N56: =K56*L56*M56 -> 330.75 | O56: =K56*1.05 -> 173.64375 | P56: ='Program Budget'!Q235 -> 1 | Q56: 1 | R56: =O56*P56*Q56 -> 173.64375 | S56: =O56*1.05 -> 182.32594 | T56: ='Program Budget'!T235 -> 0 | U56: 0 | V56: =S56*T56*U56 -> 0 | W56: =F56+J56+N56+R56+V56 -> 969.39375
A57: ='Program Budget'!D236 -> Visa Cost - Trade Finance & Expert Consultant | B57: ='Program Budget'!F236 -> Trip | C57: ='Program Budget'!H236 -> 160 | D57: ='Program Budget'!G236 -> 1 | E57: 1 | F57: =C57*D57*E57 -> 160 | G57: =C57*1.05 -> 168 | H57: ='Program Budget'!K236 -> 2 | I57: 1 | J57: =G57*H57*I57 -> 336 | K57: =G57*1.05 -> 176.4 | L57: ='Program Budget'!N236 -> 2 | M57: 1 | N57: =K57*L57*M57 -> 352.8 | O57: =K57*1.05 -> 185.22 | P57: ='Program Budget'!Q236 -> 1 | Q57: 1 | R57: =O57*P57*Q57 -> 185.22 | S57: =O57*1.05 -> 194.481 | T57: ='Program Budget'!T236 -> 0 | U57: 0 | V57: =S57*T57*U57 -> 0 | W57: =F57+J57+N57+R57+V57 -> 1034.02
A59: Subtotal: Travel | F59: =SUM(F42:F58) -> 15011.5 | J59: =SUM(J42:J58) -> 52763.025 | N59: =SUM(N42:N58) -> 55401.176 | R59: =SUM(R42:R58) -> 30039.79 | V59: =SUM(V42:V58) -> 0 | W59: =SUM(W42:W58) -> 153215.49
A60: Professional Services/Contractual
A61: ='Program Budget'!D215 -> Contracts for Trade Finance Capacity Building for American Producers and Cooperators (Nigerian) | B61: ='Program Budget'!F215 -> Lumpsum | C61: ='Program Budget'!H215 -> 67000 | D61: ='Program Budget'!G215 -> 0.5 | E61: 1 | F61: =C61*D61*E61 -> 33500 | G61: =C61 -> 67000 | H61: ='Program Budget'!K215 -> 1 | I61: 1 | J61: =G61*H61*I61 -> 67000 | K61: =G61 -> 67000 | L61: ='Program Budget'!N215 -> 1 | M61: 1 | N61: =K61*L61*M61 -> 67000 | O61: =K61 -> 67000 | P61: ='Program Budget'!Q215 -> 0.5 | Q61: 1 | R61: =O61*P61*Q61 -> 33500 | S61: =O61 -> 67000 | T61: ='Program Budget'!T215 -> 0 | U61: 0 | V61: =S61*T61*U61 -> 0 | W61: =F61+J61+N61+R61+V61 -> 201000
A62: ='Program Budget'!D216 -> Expert Consultant on Trade Finance & Exports (US based) | B62: ='Program Budget'!F216 -> Day | C62: ='Program Budget'!H216 -> 620 | D62: ='Program Budget'!G216 -> 40 | E62: 1 | F62: =C62*D62*E62 -> 24800 | G62: =C62 -> 620 | H62: ='Program Budget'!K216 -> 45 | I62: 1 | J62: =G62*H62*I62 -> 27900 | K62: =G62 -> 620 | L62: ='Program Budget'!N216 -> 45 | M62: 1 | N62: =K62*L62*M62 -> 27900 | O62: =K62 -> 620 | P62: ='Program Budget'!Q216 -> 37 | Q62: 1 | R62: =O62*P62*Q62 -> 22940 | S62: =O62 -> 620 | T62: ='Program Budget'!T216 -> 0 | U62: 0 | V62: =S62*T62*U62 -> 0 | W62: =F62+J62+N62+R62+V62 -> 103540
A63: ='Program Budget'!D217 -> Security Services, Risk Assessments, & Security Assessment | B63: ='Program Budget'!F217 -> Year | C63: ='Program Budget'!H217 -> 2000 | D63: ='Program Budget'!G217 -> 1 | E63: 1 | F63: =C63*D63*E63 -> 2000 | G63: =C63 -> 2000 | H63: ='Program Budget'!K217 -> 1 | I63: 1 | J63: =G63*H63*I63 -> 2000 | K63: =G63 -> 2000 | L63: ='Program Budget'!N217 -> 1 | M63: 1 | N63: =K63*L63*M63 -> 2000 | O63: =K63 -> 2000 | P63: ='Program Budget'!Q217 -> 1 | Q63: 1 | R63: =O63*P63*Q63 -> 2000 | S63: =O63 -> 2000 | T63: ='Program Budget'!T217 -> 0 | U63: 0 | V63: =S63*T63*U63 -> 0 | W63: =F63+J63+N63+R63+V63 -> 8000
A65: Subtotal: Professional Services/Contractual | F65: =SUM(F61:F64) -> 60300 | J65: =SUM(J61:J64) -> 96900 | N65: =SUM(N61:N64) -> 96900 | R65: =SUM(R61:R64) -> 58440 | V65: =SUM(V61:V64) -> 0 | W65: =SUM(W61:W64) -> 312540
A66: Equipment (>$5000/unit)
A67: None | F67: =C67*D67*E67 -> 0 | J67: =G67*H67*I67 -> 0 | N67: =K67*L67*M67 -> 0 | R67: =O67*P67*Q67 -> 0 | V67: =S67*T67*U67 -> 0 | W67: =F67+J67+N67+R67+V67 -> 0
A68: Subtotal: Equipment | F68: =SUM(F67:F67) -> 0 | J68: =SUM(J67:J67) -> 0 | N68: =SUM(N67:N67) -> 0 | R68: =SUM(R67:R67) -> 0 | V68: =SUM(V67:V67) -> 0 | W68: =+F68+J68+N68+R68+V68 -> 0
A69: Office
A70: None | F70: =C70*D70*E70 -> 0 | J70: =G70*H70*I70 -> 0 | N70: =K70*L70*M70 -> 0 | R70: =O70*P70*Q70 -> 0 | V70: =S70*T70*U70 -> 0 | W70: =F70+J70+N70+R70+V70 -> 0
A71: Subtotal: Office | F71: =SUM(F67:F67) -> 0 | J71: =SUM(J67:J67) -> 0 | N71: =SUM(N67:N67) -> 0 | R71: =SUM(R67:R67) -> 0 | V71: =SUM(V67:V67) -> 0 | W71: =+F71+J71+N71+R71+V71 -> 0
A72: Supplies
A73: ='Program Budget'!D221 -> Webinar Platform (Zoom) for Trainings | B73: ='Program Budget'!F221 -> Month | C73: ='Program Budget'!H221 -> 340 | D73: ='Program Budget'!G221 -> 6 | E73: 1 | F73: =C73*D73*E73 -> 2040 | G73: =C73*1.05 -> 357 | H73: ='Program Budget'!K221 -> 12 | I73: 1 | J73: =G73*H73*I73 -> 4284 | K73: =G73*1.05 -> 374.85 | L73: ='Program Budget'!N221 -> 12 | M73: 1 | N73: =K73*L73*M73 -> 4498.2 | O73: =K73*1.05 -> 393.5925 | P73: ='Program Budget'!Q221 -> 12 | Q73: 1 | R73: =O73*P73*Q73 -> 4723.11 | S73: =O73*1.05 -> 413.27213 | T73: ='Program Budget'!T221 -> 0 | U73: 0 | V73: =S73*T73*U73 -> 0 | W73: =F73+J73+N73+R73+V73 -> 15545.31
A75: Subtotal: Supplies | F75: =SUM(F73:F74) -> 2040 | J75: =SUM(J73:J74) -> 4284 | N75: =SUM(N73:N74) -> 4498.2 | R75: =SUM(R73:R74) -> 4723.11 | V75: =SUM(V73:V74) -> 0 | W75: =SUM(W73:W74) -> 15545.31
A76: Other Direct Cost
A77: Trainings & Meetings
A78: ='Program Budget'!D241 -> Subrecipient: None | B78: ='Program Budget'!F241 -> Subaward | C78: ='Program Budget'!I241 -> 0 | D78: ='Program Budget'!G241 -> 0 | E78: 1 | F78: =C78*D78*E78 -> 0 | G78: ='Program Budget'!L241 -> 0 | H78: ='Program Budget'!K241 -> 0 | I78: 1 | J78: =G78*H78*I78 -> 0 | K78: ='Program Budget'!O241 -> 0 | L78: ='Program Budget'!N241 -> 0 | M78: 1 | N78: =K78*L78*M78 -> 0 | O78: ='Program Budget'!R241 -> 0 | P78: ='Program Budget'!Q241 -> 0 | Q78: 1 | R78: =O78*P78*Q78 -> 0 | S78: ='Program Budget'!U241 -> 0 | T78: ='Program Budget'!T241 -> 0 | U78: 0 | V78: =S78*T78*U78 -> 0 | W78: =F78+J78+N78+R78+V78 -> 0
A79: ='Program Budget'!D242 -> Trainings & Meetings
A80: ='Program Budget'!D243 -> One-Day Workshops for Nigerian Banks and Importers on FAS Programs | B80: ='Program Budget'!F243 -> Workshop | C80: ='Program Budget'!H243 -> 1719 | D80: ='Program Budget'!G243 -> 2 | E80: 1 | F80: =C80*D80*E80 -> 3438 | G80: =C80 -> 1719 | H80: ='Program Budget'!K243 -> 0 | I80: 1 | J80: =G80*H80*I80 -> 0 | K80: =G80 -> 1719 | L80: ='Program Budget'!N243 -> 0 | M80: 1 | N80: =K80*L80*M80 -> 0 | O80: =K80 -> 1719 | P80: ='Program Budget'!Q243 -> 0 | Q80: 1 | R80: =O80*P80*Q80 -> 0 | S80: =O80 -> 1719 | T80: ='Program Budget'!T243 -> 0 | U80: 0 | V80: =S80*T80*U80 -> 0 | W80: =F80+J80+N80+R80+V80 -> 3438
A81: ='Program Budget'!D244 -> One-Day Workshops for Nigerian Banks and Importers on Foreign Currency Risk | B81: ='Program Budget'!F244 -> Workshop | C81: ='Program Budget'!H244 -> 1719 | D81: ='Program Budget'!G244 -> 0 | E81: 1 | F81: =C81*D81*E81 -> 0 | G81: =C81 -> 1719 | H81: ='Program Budget'!K244 -> 1 | I81: 1 | J81: =G81*H81*I81 -> 1719 | K81: =G81 -> 1719 | L81: ='Program Budget'!N244 -> 1 | M81: 1 | N81: =K81*L81*M81 -> 1719 | O81: =K81 -> 1719 | P81: ='Program Budget'!Q244 -> 0 | Q81: 1 | R81: =O81*P81*Q81 -> 0 | S81: =O81 -> 1719 | T81: ='Program Budget'!T244 -> 0 | U81: 0 | V81: =S81*T81*U81 -> 0 | W81: =F81+J81+N81+R81+V81 -> 3438
A82: ='Program Budget'!D245 -> Three-Day Buyers Conferences | B82: ='Program Budget'!F245 -> Conference | C82: ='Program Budget'!H245 -> 75000 | D82: ='Program Budget'!G245 -> 0 | E82: 1 | F82: =C82*D82*E82 -> 0 | G82: =C82 -> 75000 | H82: ='Program Budget'!K245 -> 1 | I82: 1 | J82: =G82*H82*I82 -> 75000 | K82: =G82 -> 75000 | L82: ='Program Budget'!N245 -> 1 | M82: 1 | N82: =K82*L82*M82 -> 75000 | O82: =K82 -> 75000 | P82: ='Program Budget'!Q245 -> 0 | Q82: 1 | R82: =O82*P82*Q82 -> 0 | S82: =O82 -> 75000 | T82: ='Program Budget'!T245 -> 0 | U82: 0 | V82: =S82*T82*U82 -> 0 | W82: =F82+J82+N82+R82+V82 -> 150000
A83: ='Program Budget'!D246 -> One-Day Workshop for Institutions, Ministries and Private Sector - Identify & Prioritize Financing Solutions | B83: ='Program Budget'!F246 -> Workshop | C83: ='Program Budget'!H246 -> 1824 | D83: ='Program Budget'!G246 -> 1 | E83: 1 | F83: =C83*D83*E83 -> 1824 | G83: =C83 -> 1824 | H83: ='Program Budget'!K246 -> 0 | I83: 1 | J83: =G83*H83*I83 -> 0 | K83: =G83 -> 1824 | L83: ='Program Budget'!N246 -> 0 | M83: 1 | N83: =K83*L83*M83 -> 0 | O83: =K83 -> 1824 | P83: ='Program Budget'!Q246 -> 0 | Q83: 1 | R83: =O83*P83*Q83 -> 0 | S83: =O83 -> 1824 | T83: ='Program Budget'!T246 -> 0 | U83: 0 | V83: =S83*T83*U83 -> 0 | W83: =F83+J83+N83+R83+V83 -> 1824
A84: ='Program Budget'!D247 -> Ongoing Technical Assistance for Access to Local Trade Finance | B84: ='Program Budget'!F247 -> Training | C84: ='Program Budget'!H247 -> 757 | D84: ='Program Budget'!G247 -> 0 | E84: 1 | F84: =C84*D84*E84 -> 0 | G84: =C84 -> 757 | H84: ='Program Budget'!K247 -> 11 | I84: 1 | J84: =G84*H84*I84 -> 8327 | K84: =G84 -> 757 | L84: ='Program Budget'!N247 -> 12 | M84: 1 | N84: =K84*L84*M84 -> 9084 | O84: =K84 -> 757 | P84: ='Program Budget'!Q247 -> 0 | Q84: 1 | R84: =O84*P84*Q84 -> 0 | S84: =O84 -> 757 | T84: ='Program Budget'!T247 -> 0 | U84: 0 | V84: =S84*T84*U84 -> 0 | W84: =F84+J84+N84+R84+V84 -> 17411
A85: ='Program Budget'!D248 -> Grants
A86: ='Program Budget'!D249 -> Co-Investment Agribusiness Grants | B86: ='Program Budget'!F249 -> Lumpsum | C86: ='Program Budget'!H249 -> 1300000 | D86: ='Program Budget'!G249 -> 0 | E86: 1 | F86: =C86*D86*E86 -> 0 | G86: =C86 -> 1300000 | H86: ='Program Budget'!K249 -> 0.25 | I86: 1 | J86: =G86*H86*I86 -> 325000 | K86: =G86 -> 1300000 | L86: ='Program Budget'!N249 -> 0.5 | M86: 1 | N86: =K86*L86*M86 -> 650000 | O86: =K86 -> 1300000 | P86: ='Program Budget'!Q249 -> 0.25 | Q86: 1 | R86: =O86*P86*Q86 -> 325000 | S86: =O86 -> 1300000 | T86: ='Program Budget'!T249 -> 0 | U86: 0 | V86: =S86*T86*U86 -> 0 | W86: =F86+J86+N86+R86+V86 -> 1300000
A87: ='Program Budget'!D250 -> Small Grants to Producers & Processors | B87: ='Program Budget'!F250 -> Grants | C87: ='Program Budget'!H250 -> 13000 | D87: ='Program Budget'!G250 -> 0 | E87: 1 | F87: =C87*D87*E87 -> 0 | G87: =C87 -> 13000 | H87: ='Program Budget'!K250 -> 17 | I87: 1 | J87: =G87*H87*I87 -> 221000 | K87: =G87 -> 13000 | L87: ='Program Budget'!N250 -> 17 | M87: 1 | N87: =K87*L87*M87 -> 221000 | O87: =K87 -> 13000 | P87: ='Program Budget'!Q250 -> 0 | Q87: 1 | R87: =O87*P87*Q87 -> 0 | S87: =O87 -> 13000 | T87: ='Program Budget'!T250 -> 0 | U87: 0 | V87: =S87*T87*U87 -> 0 | W87: =F87+J87+N87+R87+V87 -> 442000
A88: ='Program Budget'!D251 -> Communications
A89: ='Program Budget'!D252 -> Communications Cost to Release RFP on Co-Investment Agribusiness Grants | B89: ='Program Budget'!F252 -> Year | C89: ='Program Budget'!H252 -> 1000 | D89: ='Program Budget'!G252 -> 0 | E89: 1 | F89: =C89*D89*E89 -> 0 | G89: =C89 -> 1000 | H89: ='Program Budget'!K252 -> 1 | I89: 1 | J89: =G89*H89*I89 -> 1000 | K89: =G89 -> 1000 | L89: ='Program Budget'!N252 -> 1 | M89: 1 | N89: =K89*L89*M89 -> 1000 | O89: =K89 -> 1000 | P89: ='Program Budget'!Q252 -> 1 | Q89: 1 | R89: =O89*P89*Q89 -> 1000 | S89: =O89 -> 1000 | T89: ='Program Budget'!T252 -> 0 | U89: 0 | V89: =S89*T89*U89 -> 0 | W89: =F89+J89+N89+R89+V89 -> 3000
A91: Subtotal: Other Direct Cost | F91: =SUM(F77:F90) -> 5262 | J91: =SUM(J77:J90) -> 632046 | N91: =SUM(N77:N90) -> 957803 | R91: =SUM(R77:R90) -> 326000 | V91: =SUM(V77:V90) -> 0 | W91: =+F91+J91+N91+R91+V91 -> 1921111
A93: Total Direct Cost | F93: =F32+F41+F59+F71+F75+F65+F91 -> 331790.21 | J93: =J32+J41+J59+J71+J75+J65+J91 -> 1285858.9 | N93: =N32+N41+N59+N71+N75+N65+N91 -> 1639461.5 | R93: =R32+R41+R59+R71+R75+R65+R91 -> 1025290.3 | V93: =V32+V41+V59+V71+V75+V65+V91 -> 0 | W93: =W32+W41+W59+W71+W75+W65+W91 -> 4282400.9
A95: Indirect Costs
A96: ICR on Administration | B96: % | C96: 0 | D96: 0 | E96: 0.15 | F96: =C96*D96*E96 -> 0 | G96: 0 | H96: 0 | I96: =E96 -> 0.15 | J96: =G96*H96*I96 -> 0 | K96: 0 | L96: 0 | M96: =I96 -> 0.15 | N96: =K96*L96*M96 -> 0 | O96: 0 | P96: 0 | Q96: =M96 -> 0.15 | R96: =O96*P96*Q96 -> 0 | S96: 0 | T96: 0 | U96: 0 | V96: =S96*T96*U96 -> 0 | W96: =F96+J96+N96+R96+V96 -> 0
A97: ICR on Activities (Total Direct Activities Costs Less Subawards) | B97: % | C97: =F93-F78 -> 331790.21 | D97: 1 | E97: 0.15 | F97: =C97*D97*E97 -> 49768.532 | G97: =J93-J78 -> 1285858.9 | H97: 1 | I97: =E97 -> 0.15 | J97: =G97*H97*I97 -> 192878.83 | K97: =N93-N78 -> 1639461.5 | L97: 1 | M97: =I97 -> 0.15 | N97: =K97*L97*M97 -> 245919.23 | O97: =R93-R78 -> 1025290.3 | P97: 1 | Q97: =M97 -> 0.15 | R97: =O97*P97*Q97 -> 153793.55 | S97: =V93-V78 -> 0 | T97: 1 | U97: 0 | V97: =S97*T97*U97 -> 0 | W97: =F97+J97+N97+R97+V97 -> 642360.14
A98: ICR on Activities (Subawards) | B98: % | C98: =F78 -> 0 | D98: 1 | E98: 0.07 | F98: =C98*D98*E98 -> 0 | G98: =J78 -> 0 | H98: 1 | I98: =E98 -> 0.07 | J98: =G98*H98*I98 -> 0 | K98: =N78 -> 0 | L98: 1 | M98: =I98 -> 0.07 | N98: =K98*L98*M98 -> 0 | O98: =R78 -> 0 | P98: 1 | Q98: =M98 -> 0.07 | R98: =O98*P98*Q98 -> 0 | S98: =V78 -> 0 | T98: 1 | U98: 0 | V98: =S98*T98*U98 -> 0 | W98: =F98+J98+N98+R98+V98 -> 0
A100: Subtotal Indirect Cost | F100: =SUM(F96:F98) -> 49768.532 | J100: =SUM(J96:J98) -> 192878.83 | N100: =SUM(N96:N98) -> 245919.23 | R100: =SUM(R96:R98) -> 153793.55 | V100: =SUM(V96:V98) -> 0 | W100: =SUM(W96:W98) -> 642360.14
A102: Total Estimated Cost (Direct Cost + Indirect Cost) | F102: =F93+F100 -> 381558.75 | J102: =J93+J100 -> 1478737.7 | N102: =N93+N100 -> 1885380.7 | R102: =R93+R100 -> 1179083.9 | V102: =V93+V100 -> 0 | W102: =F102+J102+N102+R102+V102 -> 4924761.1
A103: ='Program Budget'!D256 -> Co-Investment Agribusiness Grants (Matching) | B103: ='Program Budget'!F256 -> Lumpsum | C103: ='Program Budget'!H256 -> 260000 | D103: ='Program Budget'!G256 -> 0 | E103: 1 | F103: =C103*D103*E103 -> 0 | G103: =C103 -> 260000 | H103: ='Program Budget'!K256 -> 0.25 | I103: 1 | J103: =G103*H103*I103 -> 65000 | K103: =G103 -> 260000 | L103: ='Program Budget'!N256 -> 0.5 | M103: 1 | N103: =K103*L103*M103 -> 130000 | O103: =K103 -> 260000 | P103: ='Program Budget'!Q256 -> 0.25 | Q103: 1 | R103: =O103*P103*Q103 -> 65000 | S103: =O103 -> 260000 | T103: ='Program Budget'!T256 -> 0 | U103: 1 | V103: =S103*T103*U103 -> 0 | W103: =F103+J103+N103+R103+V103 -> 260000
A104: ='Program Budget'!D257 -> Airfare - Roundtrip - USA to Nigeria - Buyer Conferences for American Farmers, Ranchers and Agricultural Professionals - 50% of Cost | B104: ='Program Budget'!F257 -> Trip | C104: ='Program Budget'!H257 -> 900 | D104: ='Program Budget'!G257 -> 0 | E104: 1 | F104: =C104*D104*E104 -> 0 | G104: =C104*1.05 -> 945 | H104: ='Program Budget'!K257 -> 10 | I104: 1 | J104: =G104*H104*I104 -> 9450 | K104: =G104*1.05 -> 992.25 | L104: ='Program Budget'!N257 -> 10 | M104: 1 | N104: =K104*L104*M104 -> 9922.5 | O104: =K104*1.05 -> 1041.8625 | P104: ='Program Budget'!Q257 -> 0 | Q104: 1 | R104: =O104*P104*Q104 -> 0 | S104: =O104*1.05 -> 1093.9556 | T104: ='Program Budget'!T257 -> 0 | U104: 1 | V104: =S104*T104*U104 -> 0 | W104: =F104+J104+N104+R104+V104 -> 19372.5
A105: ='Program Budget'!D258 -> Lodging and M&IE - Buyer Conferences for American Farmers, Ranchers and Agricultural Professionals - 50% of Cost | B105: ='Program Budget'!F258 -> Day | C105: ='Program Budget'!H258 -> 155.25 | D105: ='Program Budget'!G258 -> 0 | E105: 1 | F105: =C105*D105*E105 -> 0 | G105: =C105*1.05 -> 163.0125 | H105: ='Program Budget'!K258 -> 70 | I105: 1 | J105: =G105*H105*I105 -> 11410.875 | K105: =G105*1.05 -> 171.16313 | L105: ='Program Budget'!N258 -> 70 | M105: 1 | N105: =K105*L105*M105 -> 11981.419 | O105: =K105*1.05 -> 179.72128 | P105: ='Program Budget'!Q258 -> 0 | Q105: 1 | R105: =O105*P105*Q105 -> 0 | S105: =O105*1.05 -> 188.70735 | T105: ='Program Budget'!T258 -> 0 | U105: 1 | V105: =S105*T105*U105 -> 0 | W105: =F105+J105+N105+R105+V105 -> 23392.294
A106: ='Program Budget'!D259 -> Ground Transportation – Buyer Conferences for Nigerian Producers and Agricultural Professionals | B106: ='Program Budget'!F259 -> Day | C106: ='Program Budget'!H259 -> 75 | D106: ='Program Budget'!G259 -> 0 | E106: 1 | F106: =C106*D106*E106 -> 0 | G106: =C106*1.05 -> 78.75 | H106: ='Program Budget'!K259 -> 10 | I106: 1 | J106: =G106*H106*I106 -> 787.5 | K106: =G106*1.05 -> 82.6875 | L106: ='Program Budget'!N259 -> 10 | M106: 1 | N106: =K106*L106*M106 -> 826.875 | O106: =K106*1.05 -> 86.821875 | P106: ='Program Budget'!Q259 -> 0 | Q106: 1 | R106: =O106*P106*Q106 -> 0 | S106: =O106*1.05 -> 91.162969 | T106: ='Program Budget'!T259 -> 0 | U106: 1 | V106: =S106*T106*U106 -> 0 | W106: =F106+J106+N106+R106+V106 -> 1614.375
A107: ='Program Budget'!D260 -> Visa Cost for Buyer Conferences for Nigerian Producers and Agricultural Professionals | B107: ='Program Budget'!F260 -> Trip | C107: ='Program Budget'!H260 -> 155 | D107: ='Program Budget'!G260 -> 0 | E107: 1 | F107: =C107*D107*E107 -> 0 | G107: =C107*1.05 -> 162.75 | H107: ='Program Budget'!K260 -> 10 | I107: 1 | J107: =G107*H107*I107 -> 1627.5 | K107: =G107*1.05 -> 170.8875 | L107: ='Program Budget'!N260 -> 10 | M107: 1 | N107: =K107*L107*M107 -> 1708.875 | O107: =K107*1.05 -> 179.43188 | P107: ='Program Budget'!Q260 -> 0 | Q107: 1 | R107: =O107*P107*Q107 -> 0 | S107: =O107*1.05 -> 188.40347 | T107: ='Program Budget'!T260 -> 0 | U107: 1 | V107: =S107*T107*U107 -> 0 | W107: =F107+J107+N107+R107+V107 -> 3336.375
A108: Total Estimated Cost (Direct Cost + Indirect Cost+ Cost Share) | F108: =SUM(F102:F107) -> 381558.75 | J108: =SUM(J102:J107) -> 1567013.6 | N108: =SUM(N102:N107) -> 2039820.4 | R108: =SUM(R102:R107) -> 1244083.9 | V108: =SUM(V102:V107) -> 0 | W108: =SUM(W102:W107) -> 5232476.6
A110: Anticipated Program Income (baked in costs and this is for reference)

Sheet Activity 3
A2: Item | B2: Type of Unit | C2: Year 1 | G2: Year 2 | K2: Year 3 | O2: Year 4 | S2: Year 5 | W2: Total
C3: Cost | D3: Quantity | E3: Percent Allocated | F3: Total | G3: Cost | H3: Quantity | I3: Percent Allocated | J3: Total | K3: Cost | L3: Quantity | M3: Percent Allocated | N3: Total | O3: Cost | P3: Quantity | Q3: Percent Allocated | R3: Total | S3: Cost | T3: Quantity | U3: Percent Allocated | V3: Total
A4: Direct Costs
A5: Salaries/Personnel
A6: USN/TCN Staff
A7: None | F7: =C7*D7*E7 -> 0 | J7: =G7*H7*I7 -> 0 | N7: =K7*L7*M7 -> 0 | R7: =O7*P7*Q7 -> 0 | V7: =S7*T7*U7 -> 0 | W7: =F7+J7+N7+R7+V7 -> 0
A8: Total: Expatriate Salaries & Wages | F8: =SUM(F7:F7) -> 0 | J8: =SUM(J7:J7) -> 0 | N8: =SUM(N7:N7) -> 0 | R8: =SUM(R7:R7) -> 0 | V8: =SUM(V7:V7) -> 0 | W8: =+F8+J8+N8+R8+V8 -> 0
A9: CCN Staff
A10: ='Program Budget'!D12 -> Key Personnel: Chief of Party | B10: ='Program Budget'!F268 -> Month | C10: ='Program Budget'!H12 -> 9583.3333 | D10: ='Program Budget'!G12 -> 11 | E10: ='Program Budget'!E268 -> 0.1 | F10: =C10*D10*E10 -> 10541.667 | G10: =C10*1.05 -> 10062.5 | H10: ='Program Budget'!K12 -> 12 | I10: ='Program Budget'!J268 -> 0.2 | J10: =G10*H10*I10 -> 24150 | K10: =G10*1.05 -> 10565.625 | L10: ='Program Budget'!N12 -> 12 | M10: ='Program Budget'!M268 -> 0.2 | N10: =K10*L10*M10 -> 25357.5 | O10: =K10*1.05 -> 11093.906 | P10: ='Program Budget'!Q12 -> 12 | Q10: ='Program Budget'!P268 -> 0.05 | R10: =O10*P10*Q10 -> 6656.3438 | S10: =O10*1.05 -> 11648.602 | T10: ='Program Budget'!T12 -> 0 | U10: ='Program Budget'!S268 -> 0 | V10: =S10*T10*U10 -> 0 | W10: =F10+J10+N10+R10+V10 -> 66705.51
A11: ='Program Budget'!D13 -> Technical Director | B11: ='Program Budget'!F269 -> Month | C11: ='Program Budget'!H13 -> 3500 | D11: ='Program Budget'!G13 -> 9 | E11: ='Program Budget'!E269 -> 0.15 | F11: =C11*D11*E11 -> 4725 | G11: =C11*1.05 -> 3675 | H11: ='Program Budget'!K13 -> 12 | I11: ='Program Budget'!J269 -> 0.2 | J11: =G11*H11*I11 -> 8820 | K11: =G11*1.05 -> 3858.75 | L11: ='Program Budget'!N13 -> 12 | M11: ='Program Budget'!M269 -> 0.2 | N11: =K11*L11*M11 -> 9261 | O11: =K11*1.05 -> 4051.6875 | P11: ='Program Budget'!Q13 -> 12 | Q11: ='Program Budget'!P269 -> 0.1 | R11: =O11*P11*Q11 -> 4862.025 | S11: =O11*1.05 -> 4254.2719 | T11: ='Program Budget'!T13 -> 0 | U11: ='Program Budget'!S269 -> 0 | V11: =S11*T11*U11 -> 0 | W11: =F11+J11+N11+R11+V11 -> 27668.025
A12: ='Program Budget'!D14 -> Technical Lead - Activity 2 US Exports | B12: ='Program Budget'!F270 -> Month | C12: ='Program Budget'!H14 -> 2833.3333 | D12: ='Program Budget'!G14 -> 8 | E12: ='Program Budget'!E270 -> 0 | F12: =C12*D12*E12 -> 0 | G12: =C12*1.05 -> 2975 | H12: ='Program Budget'!K14 -> 12 | I12: ='Program Budget'!J270 -> 0 | J12: =G12*H12*I12 -> 0 | K12: =G12*1.05 -> 3123.75 | L12: ='Program Budget'!N14 -> 12 | M12: ='Program Budget'!M270 -> 0 | N12: =K12*L12*M12 -> 0 | O12: =K12*1.05 -> 3279.9375 | P12: ='Program Budget'!Q14 -> 12 | Q12: ='Program Budget'!P270 -> 0 | R12: =O12*P12*Q12 -> 0 | S12: =O12*1.05 -> 3443.9344 | T12: ='Program Budget'!T14 -> 0 | U12: ='Program Budget'!S270 -> 0 | V12: =S12*T12*U12 -> 0 | W12: =F12+J12+N12+R12+V12 -> 0
A13: ='Program Budget'!D15 -> Technical Lead - Activity 2 Access to Finance Specialist | B13: ='Program Budget'!F271 -> Month | C13: ='Program Budget'!H15 -> 2833.3333 | D13: ='Program Budget'!G15 -> 8 | E13: ='Program Budget'!E271 -> 0 | F13: =C13*D13*E13 -> 0 | G13: =C13*1.05 -> 2975 | H13: ='Program Budget'!K15 -> 12 | I13: ='Program Budget'!J271 -> 0 | J13: =G13*H13*I13 -> 0 | K13: =G13*1.05 -> 3123.75 | L13: ='Program Budget'!N15 -> 12 | M13: ='Program Budget'!M271 -> 0 | N13: =K13*L13*M13 -> 0 | O13: =K13*1.05 -> 3279.9375 | P13: ='Program Budget'!Q15 -> 12 | Q13: ='Program Budget'!P271 -> 0 | R13: =O13*P13*Q13 -> 0 | S13: =O13*1.05 -> 3443.9344 | T13: ='Program Budget'!T15 -> 0 | U13: ='Program Budget'!S271 -> 0 | V13: =S13*T13*U13 -> 0 | W13: =F13+J13+N13+R13+V13 -> 0
A14: ='Program Budget'!D16 -> Communications/Strategic Partnerships Manager | B14: ='Program Budget'!F272 -> Month | C14: ='Program Budget'!H16 -> 2666.6667 | D14: ='Program Budget'!G16 -> 8 | E14: ='Program Budget'!E272 -> 0.2 | F14: =C14*D14*E14 -> 4266.6667 | G14: =C14*1.05 -> 2800 | H14: ='Program Budget'!K16 -> 12 | I14: ='Program Budget'!J272 -> 0.25 | J14: =G14*H14*I14 -> 8400 | K14: =G14*1.05 -> 2940 | L14: ='Program Budget'!N16 -> 12 | M14: ='Program Budget'!M272 -> 0.25 | N14: =K14*L14*M14 -> 8820 | O14: =K14*1.05 -> 3087 | P14: ='Program Budget'!Q16 -> 12 | Q14: ='Program Budget'!P272 -> 0 | R14: =O14*P14*Q14 -> 0 | S14: =O14*1.05 -> 3241.35 | T14: ='Program Budget'!T16 -> 0 | U14: ='Program Budget'!S272 -> 0 | V14: =S14*T14*U14 -> 0 | W14: =F14+J14+N14+R14+V14 -> 21486.667
A15: ='Program Budget'!D17 -> M&E Director | B15: ='Program Budget'!F273 -> Month | C15: ='Program Budget'!H17 -> 3500 | D15: ='Program Budget'!G17 -> 10 | E15: ='Program Budget'!E273 -> 0.2 | F15: =C15*D15*E15 -> 7000 | G15: =C15*1.05 -> 3675 | H15: ='Program Budget'!K17 -> 12 | I15: ='Program Budget'!J273 -> 0.25 | J15: =G15*H15*I15 -> 11025 | K15: =G15*1.05 -> 3858.75 | L15: ='Program Budget'!N17 -> 12 | M15: ='Program Budget'!M273 -> 0.25 | N15: =K15*L15*M15 -> 11576.25 | O15: =K15*1.05 -> 4051.6875 | P15: ='Program Budget'!Q17 -> 12 | Q15: ='Program Budget'!P273 -> 0.1 | R15: =O15*P15*Q15 -> 4862.025 | S15: =O15*1.05 -> 4254.2719 | T15: ='Program Budget'!T17 -> 0 | U15: ='Program Budget'!S273 -> 0 | V15: =S15*T15*U15 -> 0 | W15: =F15+J15+N15+R15+V15 -> 34463.275
A16: ='Program Budget'!D18 -> M&E Specialist | B16: ='Program Budget'!F274 -> Month | C16: ='Program Budget'!H18 -> 2000 | D16: ='Program Budget'!G18 -> 8 | E16: ='Program Budget'!E274 -> 0.25 | F16: =C16*D16*E16 -> 4000 | G16: =C16*1.05 -> 2100 | H16: ='Program Budget'!K18 -> 12 | I16: ='Program Budget'!J274 -> 0.25 | J16: =G16*H16*I16 -> 6300 | K16: =G16*1.05 -> 2205 | L16: ='Program Budget'!N18 -> 12 | M16: ='Program Budget'!M274 -> 0.25 | N16: =K16*L16*M16 -> 6615 | O16: =K16*1.05 -> 2315.25 | P16: ='Program Budget'!Q18 -> 12 | Q16: ='Program Budget'!P274 -> 0.1 | R16: =O16*P16*Q16 -> 2778.3 | S16: =O16*1.05 -> 2431.0125 | T16: ='Program Budget'!T18 -> 0 | U16: ='Program Budget'!S274 -> 0 | V16: =S16*T16*U16 -> 0 | W16: =F16+J16+N16+R16+V16 -> 19693.3
A17: ='Program Budget'!D19 -> Key Personnel: Finance & Administration (F&A) Director | B17: ='Program Budget'!F275 -> Month | C17: ='Program Budget'!H19 -> 3500 | D17: ='Program Budget'!G19 -> 10 | E17: ='Program Budget'!E275 -> 0.2 | F17: =C17*D17*E17 -> 7000 | G17: =C17*1.05 -> 3675 | H17: ='Program Budget'!K19 -> 12 | I17: ='Program Budget'!J275 -> 0.3 | J17: =G17*H17*I17 -> 13230 | K17: =G17*1.05 -> 3858.75 | L17: ='Program Budget'!N19 -> 12 | M17: ='Program Budget'!M275 -> 0.3 | N17: =K17*L17*M17 -> 13891.5 | O17: =K17*1.05 -> 4051.6875 | P17: ='Program Budget'!Q19 -> 12 | Q17: ='Program Budget'!P275 -> 0.05 | R17: =O17*P17*Q17 -> 2431.0125 | S17: =O17*1.05 -> 4254.2719 | T17: ='Program Budget'!T19 -> 0 | U17: ='Program Budget'!S275 -> 0 | V17: =S17*T17*U17 -> 0 | W17: =F17+J17+N17+R17+V17 -> 36552.512
A18: ='Program Budget'!D20 -> Accountant | B18: ='Program Budget'!F276 -> Month | C18: ='Program Budget'!H20 -> 2000 | D18: ='Program Budget'!G20 -> 8 | E18: ='Program Budget'!E276 -> 0.25 | F18: =C18*D18*E18 -> 4000 | G18: =C18*1.05 -> 2100 | H18: ='Program Budget'!K20 -> 12 | I18: ='Program Budget'!J276 -> 0.25 | J18: =G18*H18*I18 -> 6300 | K18: =G18*1.05 -> 2205 | L18: ='Program Budget'!N20 -> 12 | M18: ='Program Budget'!M276 -> 0.25 | N18: =K18*L18*M18 -> 6615 | O18: =K18*1.05 -> 2315.25 | P18: ='Program Budget'!Q20 -> 12 | Q18: ='Program Budget'!P276 -> 0.05 | R18: =O18*P18*Q18 -> 1389.15 | S18: =O18*1.05 -> 2431.0125 | T18: ='Program Budget'!T20 -> 0 | U18: ='Program Budget'!S276 -> 0 | V18: =S18*T18*U18 -> 0 | W18: =F18+J18+N18+R18+V18 -> 18304.15
A19: ='Program Budget'!D21 -> Administration/ HR Manager | B19: ='Program Budget'!F277 -> Month | C19: ='Program Budget'!H21 -> 2666.6667 | D19: ='Program Budget'!G21 -> 10 | E19: ='Program Budget'!E277 -> 0.1 | F19: =C19*D19*E19 -> 2666.6667 | G19: =C19*1.05 -> 2800 | H19: ='Program Budget'!K21 -> 12 | I19: ='Program Budget'!J277 -> 0.25 | J19: =G19*H19*I19 -> 8400 | K19: =G19*1.05 -> 2940 | L19: ='Program Budget'!N21 -> 12 | M19: ='Program Budget'!M277 -> 0.25 | N19: =K19*L19*M19 -> 8820 | O19: =K19*1.05 -> 3087 | P19: ='Program Budget'!Q21 -> 12 | Q19: ='Program Budget'!P277 -> 0.05 | R19: =O19*P19*Q19 -> 1852.2 | S19: =O19*1.05 -> 3241.35 | T19: ='Program Budget'!T21 -> 0 | U19: ='Program Budget'!S277 -> 0 | V19: =S19*T19*U19 -> 0 | W19: =F19+J19+N19+R19+V19 -> 21738.867
A20: ='Program Budget'!D22 -> Grants & Contracts Manager | B20: ='Program Budget'!F278 -> Month | C20: ='Program Budget'!H22 -> 2666.6667 | D20: ='Program Budget'!G22 -> 9 | E20: ='Program Budget'!E278 -> 0.21 | F20: =C20*D20*E20 -> 5040 | G20: =C20*1.05 -> 2800 | H20: ='Program Budget'!K22 -> 12 | I20: ='Program Budget'!J278 -> 0.3 | J20: =G20*H20*I20 -> 10080 | K20: =G20*1.05 -> 2940 | L20: ='Program Budget'!N22 -> 12 | M20: ='Program Budget'!M278 -> 0.3 | N20: =K20*L20*M20 -> 10584 | O20: =K20*1.05 -> 3087 | P20: ='Program Budget'!Q22 -> 12 | Q20: ='Program Budget'!P278 -> 0 | R20: =O20*P20*Q20 -> 0 | S20: =O20*1.05 -> 3241.35 | T20: ='Program Budget'!T22 -> 0 | U20: ='Program Budget'!S278 -> 0 | V20: =S20*T20*U20 -> 0 | W20: =F20+J20+N20+R20+V20 -> 25704
A21: ='Program Budget'!D23 -> Compliance & Procurement Specialist | B21: ='Program Budget'!F279 -> Month | C21: ='Program Budget'!H23 -> 2000 | D21: ='Program Budget'!G23 -> 9 | E21: ='Program Budget'!E279 -> 0.21 | F21: =C21*D21*E21 -> 3780 | G21: =C21*1.05 -> 2100 | H21: ='Program Budget'!K23 -> 12 | I21: ='Program Budget'!J279 -> 0.3 | J21: =G21*H21*I21 -> 7560 | K21: =G21*1.05 -> 2205 | L21: ='Program Budget'!N23 -> 12 | M21: ='Program Budget'!M279 -> 0.3 | N21: =K21*L21*M21 -> 7938 | O21: =K21*1.05 -> 2315.25 | P21: ='Program Budget'!Q23 -> 12 | Q21: ='Program Budget'!P279 -> 0 | R21: =O21*P21*Q21 -> 0 | S21: =O21*1.05 -> 2431.0125 | T21: ='Program Budget'!T23 -> 0 | U21: ='Program Budget'!S279 -> 0 | V21: =S21*T21*U21 -> 0 | W21: =F21+J21+N21+R21+V21 -> 19278
A22: ='Program Budget'!D24 -> Driver | B22: ='Program Budget'!F280 -> Month | C22: ='Program Budget'!H24 -> 500 | D22: ='Program Budget'!G24 -> 7 | E22: ='Program Budget'!E280 -> 0.25 | F22: =C22*D22*E22 -> 875 | G22: =C22*1.05 -> 525 | H22: ='Program Budget'!K24 -> 12 | I22: ='Program Budget'!J280 -> 0.25 | J22: =G22*H22*I22 -> 1575 | K22: =G22*1.05 -> 551.25 | L22: ='Program Budget'!N24 -> 12 | M22: ='Program Budget'!M280 -> 0.25 | N22: =K22*L22*M22 -> 1653.75 | O22: =K22*1.05 -> 578.8125 | P22: ='Program Budget'!Q24 -> 12 | Q22: ='Program Budget'!P280 -> 0 | R22: =O22*P22*Q22 -> 0 | S22: =O22*1.05 -> 607.75313 | T22: ='Program Budget'!T24 -> 0 | U22: ='Program Budget'!S280 -> 0 | V22: =S22*T22*U22 -> 0 | W22: =F22+J22+N22+R22+V22 -> 4103.75
A23: Total Local Salary Cost | F23: =SUM(F10:F22) -> 53895 | J23: =SUM(J10:J22) -> 105840 | N23: =SUM(N10:N22) -> 111132 | R23: =SUM(R10:R22) -> 24831.056 | V23: =SUM(V10:V22) -> 0 | W23: =SUM(W10:W22) -> 295698.06
A24: HQ Staff
A25: ='Program Budget'!D26 -> Senior Vice President of Programs | B25: ='Program Budget'!F202 -> Month | C25: ='Program Budget'!H282 -> 13500 | D25: ='Program Budget'!G282 -> 12 | E25: ='Program Budget'!E282 -> 0.01 | F25: =C25*D25*E25 -> 1620 | G25: =C25*1.05 -> 14175 | H25: ='Program Budget'!K282 -> 12 | I25: ='Program Budget'!J282 -> 0.01 | J25: =G25*H25*I25 -> 1701 | K25: =G25*1.05 -> 14883.75 | L25: ='Program Budget'!N282 -> 12 | M25: ='Program Budget'!M282 -> 0.01 | N25: =K25*L25*M25 -> 1786.05 | O25: =K25*1.05 -> 15627.938 | P25: ='Program Budget'!Q282 -> 12 | Q25: ='Program Budget'!P282 -> 0.01 | R25: =O25*P25*Q25 -> 1875.3525 | S25: =O25*1.05 -> 16409.334 | T25: ='Program Budget'!T282 -> 0 | U25: ='Program Budget'!S282 -> 0 | V25: =S25*T25*U25 -> 0 | W25: =F25+J25+N25+R25+V25 -> 6982.4025
A26: ='Program Budget'!D27 -> Senior Program Director | B26: ='Program Budget'!F203 -> Month | C26: ='Program Budget'!H283 -> 12500 | D26: ='Program Budget'!G283 -> 12 | E26: ='Program Budget'!E283 -> 0.04 | F26: =C26*D26*E26 -> 6000 | G26: =C26*1.05 -> 13125 | H26: ='Program Budget'!K283 -> 12 | I26: ='Program Budget'!J283 -> 0.05 | J26: =G26*H26*I26 -> 7875 | K26: =G26*1.05 -> 13781.25 | L26: ='Program Budget'!N283 -> 12 | M26: ='Program Budget'!M283 -> 0.05 | N26: =K26*L26*M26 -> 8268.75 | O26: =K26*1.05 -> 14470.312 | P26: ='Program Budget'!Q283 -> 12 | Q26: ='Program Budget'!P283 -> 0.05 | R26: =O26*P26*Q26 -> 8682.1875 | S26: =O26*1.05 -> 15193.828 | T26: ='Program Budget'!T283 -> 0 | U26: ='Program Budget'!S283 -> 0 | V26: =S26*T26*U26 -> 0 | W26: =F26+J26+N26+R26+V26 -> 30825.938
A27: ='Program Budget'!D28 -> Associate Director | B27: ='Program Budget'!F204 -> Month | C27: ='Program Budget'!H284 -> 7500 | D27: ='Program Budget'!G284 -> 12 | E27: ='Program Budget'!E284 -> 0.05 | F27: =C27*D27*E27 -> 4500 | G27: =C27*1.05 -> 7875 | H27: ='Program Budget'!K284 -> 12 | I27: ='Program Budget'!J284 -> 0.2 | J27: =G27*H27*I27 -> 18900 | K27: =G27*1.05 -> 8268.75 | L27: ='Program Budget'!N284 -> 12 | M27: ='Program Budget'!M284 -> 0.2 | N27: =K27*L27*M27 -> 19845 | O27: =K27*1.05 -> 8682.1875 | P27: ='Program Budget'!Q284 -> 12 | Q27: ='Program Budget'!P284 -> 0.2 | R27: =O27*P27*Q27 -> 20837.25 | S27: =O27*1.05 -> 9116.2969 | T27: ='Program Budget'!T284 -> 0 | U27: ='Program Budget'!S284 -> 0 | V27: =S27*T27*U27 -> 0 | W27: =F27+J27+N27+R27+V27 -> 64082.25
A28: ='Program Budget'!D29 -> Compliance & Contracts Director | B28: ='Program Budget'!F205 -> Month | C28: ='Program Budget'!H285 -> 9166.6667 | D28: ='Program Budget'!G285 -> 12 | E28: ='Program Budget'!E285 -> 0.04 | F28: =C28*D28*E28 -> 4400 | G28: =C28*1.05 -> 9625 | H28: ='Program Budget'!K285 -> 12 | I28: ='Program Budget'!J285 -> 0.05 | J28: =G28*H28*I28 -> 5775 | K28: =G28*1.05 -> 10106.25 | L28: ='Program Budget'!N285 -> 12 | M28: ='Program Budget'!M285 -> 0.05 | N28: =K28*L28*M28 -> 6063.75 | O28: =K28*1.05 -> 10611.562 | P28: ='Program Budget'!Q285 -> 12 | Q28: ='Program Budget'!P285 -> 0.05 | R28: =O28*P28*Q28 -> 6366.9375 | S28: =O28*1.05 -> 11142.141 | T28: ='Program Budget'!T285 -> 0 | U28: ='Program Budget'!S285 -> 0 | V28: =S28*T28*U28 -> 0 | W28: =F28+J28+N28+R28+V28 -> 22605.688
A29: ='Program Budget'!D30 -> Finance, HR, & Administration Home Office Support | B29: ='Program Budget'!F206 -> Month | C29: ='Program Budget'!H286 -> 7500 | D29: ='Program Budget'!G286 -> 12 | E29: ='Program Budget'!E286 -> 0.07 | F29: =C29*D29*E29 -> 6300 | G29: =C29*1.05 -> 7875 | H29: ='Program Budget'!K286 -> 12 | I29: ='Program Budget'!J286 -> 0.15 | J29: =G29*H29*I29 -> 14175 | K29: =G29*1.05 -> 8268.75 | L29: ='Program Budget'!N286 -> 12 | M29: ='Program Budget'!M286 -> 0.15 | N29: =K29*L29*M29 -> 14883.75 | O29: =K29*1.05 -> 8682.1875 | P29: ='Program Budget'!Q286 -> 12 | Q29: ='Program Budget'!P286 -> 0.15 | R29: =O29*P29*Q29 -> 15627.938 | S29: =O29*1.05 -> 9116.2969 | T29: ='Program Budget'!T286 -> 0 | U29: ='Program Budget'!S286 -> 0 | V29: =S29*T29*U29 -> 0 | W29: =F29+J29+N29+R29+V29 -> 50986.688
A30: Total HQ Staff | F30: =SUM(F24:F29) -> 22820 | J30: =SUM(J24:J29) -> 48426 | N30: =SUM(N24:N29) -> 50847.3 | R30: =SUM(R24:R29) -> 53389.665 | V30: =SUM(V24:V29) -> 0 | W30: =SUM(W24:W29) -> 175482.96
A32: Subtotal: Salaries & Wages | F32: =F23+F8+F30 -> 76715 | J32: =J23+J8+J30 -> 154266 | N32: =N23+N8+N30 -> 161979.3 | R32: =R23+R8+R30 -> 78220.721 | V32: =V23+V8+V30 -> 0 | W32: =W23+W8+W30 -> 471181.02
A33: Fringe Benefits
A34: USN/TCN Staff | B34: ='Program Budget'!F290 -> % | C34: =F8 -> 0 | D34: 1 | E34: 0 | F34: =C34*D34*E34 -> 0 | G34: =J8 -> 0 | H34: 1 | I34: =E34 -> 0 | J34: =G34*H34*I34 -> 0 | K34: =N8 -> 0 | L34: 1 | M34: =E34 -> 0 | N34: =K34*L34*M34 -> 0 | O34: =R8 -> 0 | P34: 1 | Q34: =E34 -> 0 | R34: =O34*P34*Q34 -> 0 | S34: =V8 -> 0 | T34: 1 | U34: =E34 -> 0 | V34: =S34*T34*U34 -> 0 | W34: =F34+J34+N34+R34+V34 -> 0
A35: ='Program Budget'!D290 -> Fringe Benefits CCN - Nigeria | B35: ='Program Budget'!F291 -> % | C35: =F23 -> 53895 | D35: 1 | E35: ='Program Budget'!H290 -> 0.296 | F35: =C35*D35*E35 -> 15952.92 | G35: =J23 -> 105840 | H35: 1 | I35: =E35 -> 0.296 | J35: =G35*H35*I35 -> 31328.64 | K35: =N23 -> 111132 | L35: 1 | M35: =E35 -> 0.296 | N35: =K35*L35*M35 -> 32895.072 | O35: =R23 -> 24831.056 | P35: 1 | Q35: =E35 -> 0.296 | R35: =O35*P35*Q35 -> 7349.9927 | S35: =V23 -> 0 | T35: 1 | U35: 0 | V35: =S35*T35*U35 -> 0 | W35: =F35+J35+N35+R35+V35 -> 87526.625
