Workbook
Name Category: #N/A
Name Category: #N/A
Name Category: #N/A
Name Category: 'Project Budget'!$G$16:$G$208
Name DL_Country: #N/A
Name DL_Country: #N/A
Name DL_Country: #N/A
Name DL_Country: 'Project Budget'!#REF!
Name DL_TotalDOL: #N/A
Name DL_TotalDOL: #N/A
Name DL_TotalDOL: #N/A
Name DL_TotalDOL: 'Project Budget'!$R$15:$R$35
Name EQ_Country: #N/A
Name EQ_Country: #N/A
Name EQ_Country: #N/A
Name EQ_Country: 'Project Budget'!#REF!
Name EQ_TotalDOL: #N/A
Name EQ_TotalDOL: #N/A
Name EQ_TotalDOL: #N/A
Name EQ_TotalDOL: 'Project Budget'!#REF!
Name inf: #N/A
Name inf: #N/A
Name inf: #N/A
Name inf: #REF!
Name JEA_Country: #N/A
Name JEA_Country: #N/A
Name JEA_Country: #N/A
Name JEA_Country: #REF!
Name JEA_Year1: #N/A
Name JEA_Year1: #N/A
Name JEA_Year1: #N/A
Name JEA_Year1: #REF!
Name ME_Country: #N/A
Name ME_Country: #N/A
Name ME_Country: #N/A
Name ME_Country: 'Project Budget'!#REF!
Name ME_TotalDOL: #N/A
Name ME_TotalDOL: #N/A
Name ME_TotalDOL: #N/A
Name ME_TotalDOL: 'Project Budget'!$R$179:$R$192
Name O1_Country: #N/A
Name O1_Country: #N/A
Name O1_Country: #N/A
Name O1_Country: 'Project Budget'!#REF!
Name O1_TotalDOL: #N/A
Name O1_TotalDOL: #N/A
Name O1_TotalDOL: #N/A
Name O1_TotalDOL: 'Project Budget'!$R$85:$R$85
Name O2_Country: #N/A
Name O2_Country: #N/A
Name O2_Country: #N/A
Name O2_Country: 'Project Budget'!#REF!
Name O2_TotalDOL: #N/A
Name O2_TotalDOL: #N/A
Name O2_TotalDOL: #N/A
Name O2_TotalDOL: 'Project Budget'!#REF!
Name SU_Country: #N/A
Name SU_Country: #N/A
Name SU_Country: #N/A
Name SU_Country: 'Project Budget'!#REF!

Sheet Budget Summary
B1: Advancing Labor Compliance in Colombia’s Port Sector
B2: FOA-ILAB-20-09
B3: Partners of the Americas
B4: BUDGET ITEM | C4: TOTAL DOL | D4: TOTAL COST SHARING | E4: PROJECT GRAND TOTAL
B5: Direct Labor | C5: ='Project Budget'!R37 -> 1688340.4 | D5: ='Project Budget'!S37 -> 0 | E5: =SUM(C5:D5) -> 1688340.4
B6: Travel | C6: ='Project Budget'!R59 -> 71509.611 | D6: ='Project Budget'!S59 -> 0 | E6: =SUM(C6:D6) -> 71509.611
B7: Equipment | C7: ='Project Budget'!R62 -> 0 | D7: ='Project Budget'!S62 -> 0 | E7: =SUM(C7:D7) -> 0
B8: Supplies and Office Expenses | C8: ='Project Budget'!R81 -> 278250.22 | D8: ='Project Budget'!S81 -> 0 | E8: =SUM(C8:D8) -> 278250.22
B9: Outcome 1 | C9: ='Project Budget'!R98 -> 545426.32 | D9: ='Project Budget'!S98 -> 0 | E9: =SUM(C9:D9) -> 545426.32
B10: Outcome 2 | C10: ='Project Budget'!R123 -> 312200.36 | D10: ='Project Budget'!S142 -> 0 | E10: =SUM(C10:D10) -> 312200.36
B11: Outcome 3 | C11: ='Project Budget'!R142 -> 663288.23 | D11: ='Project Budget'!S142 -> 0 | E11: ='Project Budget'!T142 -> 663288.23
B12: Outcome 4 | C12: ='Project Budget'!R175 -> 131152.04 | D12: ='Project Budget'!S175 -> 0 | E12: ='Project Budget'!T175 -> 131152.04
B13: Monitoring, Evaluation, and Collection of Reliable Data | C13: ='Project Budget'!R204 -> 195138.32 | D13: ='Project Budget'!S204 -> 0 | E13: =SUM(C13:D13) -> 195138.32
B14: Total Direct Costs | C14: =SUM(C5:C13) -> 3885305.5 | D14: =SUM(D5:D13) -> 0 | E14: =SUM(E5:E13) -> 3885305.5
B15: Indirect Costs (NICRA) | C15: ='Project Budget'!R208 -> 1114694.1 | D15: ='Project Budget'!S208 -> 0 | E15: =SUM(C15:D15) -> 1114694.1
B16: TOTAL COSTS | C16: =C15+C14 -> 4999999.6 | D16: =D15+D14 -> 0 | E16: =E15+E14 -> 4999999.6
B18: ADMINISTRATIVE COSTS (Direct Labor, Equipment, Supplies, Indirect Costs) | C18: =C5+C7+C8+C15 -> 3081284.7
B19: PROGRAM COSTS (Travel, Contractual, Other Direct Costs) | C19: =C6+C9+C10+C11+C12+C13 -> 1918714.9

Sheet Project Budget
F1: Equal Access to Quality Jobs for Women and Girls in Agriculture (EQUAL)
F2: FOA-ILAB-19-02
G3: Advancing Labor Compliance in Colombia’s Port Sector
A4: Entity: | B4: P | F4: Partners of the Americas
A5: Program-Dept.: | B5: 20200 | F5: NOFO: FOA-ILAB-20-09
A6: Funder-Grant: | B6: DOL422 | F6: Duration: 4 Years
F7: Country: Colombia
F8: Budget Assumptions:
F9: Inflation - US Based Goods/Services | G9: 1.03
F10: Inflation - Locally Purchased Goods/Services | G10: 1.05
F11: Merit Based Increases for HQ & Field Staff | G11: 1.035
A13: Sage Activity | B13: Sage Object Code/ Line Item | C13: Country Code (DC=0 or CO) | D13: Office Code (DC=0 or CO) | E13: Subcontract Code | F13: BUDGET ITEM | G13: CATEGORY | H13: UNIT | I13: # of Units | J13: RATE / UNIT | K13: YEAR 1 | L13: # of Units | M13: YEAR 2 | N13: # of Units | O13: YEAR 3 | P13: # of Units | Q13: YEAR 4 | R13: TOTAL DOL | S13: TOTAL COST SHARING | T13: PROJECT GRAND TOTAL
F14: Direct Labor
F15: Key Personnel
A16: PERSNL-PD | B16: Timesheets | C16: USA | D16: USA | E16: 0 | F16: Project Director (90%) | G16: Salaries | H16: Month | I16: 12 | J16: =5630*0.9 -> 5067 | K16: =I16*J16 -> 60804 | L16: 12 | M16: =L16*J16*$G$11 -> 62932.14 | N16: 12 | O16: =N16*J16*$G$11*$G$11 -> 65134.765 | P16: 12 | Q16: =P16*J16*$G$11*$G$11*$G$11 -> 67414.482 | R16: =SUM(K16+M16+O16+Q16) -> 256285.39 | S16: 0 | T16: =SUM(R16:S16) -> 256285.39
A17: PERSNL-M&E | B17: 70000 | C17: COL2 | D17: COL2 | E17: 0 | F17: Monitoring and Evaluation (M&E) Officer (100%) | G17: Salaries | H17: Month | I17: 11 | J17: 3300 | K17: =I17*J17 -> 36300 | L17: 12 | M17: =L17*J17*$G$11 -> 40986 | N17: 12 | O17: =N17*J17*$G$11*$G$11 -> 42420.51 | P17: 12 | Q17: =P17*J17*$G$11*$G$11*$G$11 -> 43905.228 | R17: =SUM(K17+M17+O17+Q17) -> 163611.74 | S17: 0 | T17: =SUM(R17:S17) -> 163611.74
F19: Other Professional Personnel
A20: PERSNL-DPD | B20: 70000 | C20: COL2 | D20: COL2 | E20: 0 | F20: Deputy Project Director (100%) | G20: Salaries | H20: Month | I20: 10 | J20: 3500 | K20: =I20*J20 -> 35000 | L20: 12 | M20: =L20*J20*$G$11 -> 43470 | N20: 12 | O20: =N20*J20*$G$11*$G$11 -> 44991.45 | P20: 10 | Q20: =P20*J20*$G$11*$G$11*$G$11 -> 38805.126 | R20: =SUM(K20+M20+O20+Q20) -> 162266.58 | S20: 0 | T20: =SUM(R20:S20) -> 162266.58
A21: PERSNL-COM | B21: 70000 | C21: COL2 | D21: COL2 | E21: 0 | F21: Communications Officer (50%) | G21: Salaries | H21: Month | I21: 10 | J21: =2600*0.5 -> 1300 | K21: =I21*J21 -> 13000 | L21: 12 | M21: =L21*J21*$G$11 -> 16146 | N21: 12 | O21: =N21*J21*$G$11*$G$11 -> 16711.11 | P21: 9 | Q21: =P21*J21*$G$11*$G$11*$G$11 -> 12971.999 | R21: =SUM(K21+M21+O21+Q21) -> 58829.109 | S21: 0 | T21: =SUM(R21:S21) -> 58829.109
A22: PERSNL-POB | B22: 70000 | C22: COL2 | D22: COL2 | E22: 0 | F22: Stakeholder Engagement and Partnership Officer in Buenaventura/Cali (100%) | G22: Salaries | H22: Month | I22: 10 | J22: 3400 | K22: =I22*J22 -> 34000 | L22: 12 | M22: =L22*J22*$G$11 -> 42228 | N22: 12 | O22: =N22*J22*$G$11*$G$11 -> 43705.98 | P22: 9 | Q22: =P22*J22*$G$11*$G$11*$G$11 -> 33926.767 | R22: =SUM(K22+M22+O22+Q22) -> 153860.75 | S22: 0 | T22: =SUM(R22:S22) -> 153860.75
A23: PERSNL-POC | B23: 70000 | C23: COL2 | D23: COL2 | E23: 0 | F23: Stakeholder Engagement and Partnership Officer in Cartagena (100%) | G23: Salaries | H23: Month | I23: 0 | J23: 3000 | K23: =I23*J23 -> 0 | L23: 12 | M23: =L23*J23*$G$11 -> 37260 | N23: 12 | O23: =N23*J23*$G$11*$G$11 -> 38564.1 | P23: 9 | Q23: =P23*J23*$G$11*$G$11*$G$11 -> 29935.383 | R23: =SUM(K23+M23+O23+Q23) -> 105759.48 | S23: 0 | T23: =SUM(R23:S23) -> 105759.48
A24: PERSNL-F&A | B24: 70000 | C24: COL2 | D24: COL2 | E24: 0 | F24: Finance and Administration Manager (100%) | G24: Salaries | H24: Month | I24: 11 | J24: 2000 | K24: =I24*J24 -> 22000 | L24: 12 | M24: =L24*J24*$G$11 -> 24840 | N24: 12 | O24: =N24*J24*$G$11*$G$11 -> 25709.4 | P24: 12 | Q24: =P24*J24*$G$11*$G$11*$G$11 -> 26609.229 | R24: =SUM(K24+M24+O24+Q24) -> 99158.629 | S24: 0 | T24: =SUM(R24:S24) -> 99158.629
F26: Home Office Support
A27: PERSNL-PM | B27: Timesheets | C27: USA | D27: USA | E27: 0 | F27: Project Manager (10%) | G27: Salaries | H27: Month | I27: 12 | J27: =9334*0.1 -> 933.4 | K27: =I27*J27 -> 11200.8 | L27: 12 | M27: =L27*J27*$G$11 -> 11592.828 | N27: 12 | O27: =N27*J27*$G$11*$G$11 -> 11998.577 | P27: 12 | Q27: =P27*J27*$G$11*$G$11*$G$11 -> 12418.527 | R27: =SUM(K27+M27+O27+Q27) -> 47210.732 | S27: 0 | T27: =SUM(R27:S27) -> 47210.732
A28: PERSNL-PO | B28: Timesheets | C28: USA | D28: USA | E28: 0 | F28: Program Officer (40%) | G28: Salaries | H28: Month | I28: 12 | J28: =5200*0.4 -> 2080 | K28: =I28*J28 -> 24960 | L28: 12 | M28: =L28*J28*$G$11 -> 25833.6 | N28: 12 | O28: =N28*J28*$G$11*$G$11 -> 26737.776 | P28: 12 | Q28: =P28*J28*$G$11*$G$11*$G$11 -> 27673.598 | R28: =SUM(K28+M28+O28+Q28) -> 105204.97 | S28: 0 | T28: =SUM(R28:S28) -> 105204.97
F30: Subtotal | K30: =SUM(K16:K28) -> 237264.8 | M30: =SUM(M16:M28) -> 305288.57 | O30: =SUM(O16:O28) -> 315973.67 | Q30: =SUM(Q16:Q28) -> 293660.34 | R30: =SUM(K30+M30+O30+Q30) -> 1152187.4 | S30: 0 | T30: =SUM(R30:S30) -> 1152187.4
F32: Fringe Benefits
A33: FRINGE-CO | B33: 70015 | C33: COL2 | D33: COL2 | E33: 0 | F33: Fringe Benefits CCN - Colombia (above $3,204 monthly) | G33: Fringe Benefits | J33: 0.53864 | K33: =SUM(K16+K17+K20+K22)*$J$33 -> 89470.259 | M33: =SUM(M16+M17+M20+M22)*$J$33 -> 102134.84 | O33: =SUM(O16+O17+O20+O22)*$J$33 -> 105709.56 | Q33: =SUM(Q16+Q17+Q20+Q22)*$J$33 -> 99137.555 | R33: =SUM(K33+M33+O33+Q33) -> 396452.21 | S33: 0 | T33: =SUM(R33:S33) -> 396452.21
A34: FRINGE-CO | B34: 70015 | C34: COL2 | D34: COL2 | E34: 0 | F34: Fringe Benefits CCN - Colombia (below $3,204 monthly) | G34: Fringe Benefits | J34: 0.40364 | K34: =SUM(K21,K23,K24)*$J$34 -> 14127.4 | M34: =SUM(M21,M23,M24)*$J$34 -> 31583.215 | O34: =SUM(O21,O23,O24)*$J$34 -> 32688.628 | Q34: =SUM(Q21,Q23,Q24)*$J$34 -> 28059.685 | R34: =SUM(K34+M34+O34+Q34) -> 106458.93 | S34: 0 | T34: =SUM(R34:S34) -> 106458.93
A35: FRINGE | B35: 50900 | C35: USA | D35: USA | E35: 0 | F35: Fringe benefits - Home Office Support | G35: Fringe Benefits | J35: 0.2181 | K35: =SUM(K27:K28)*$J$35 -> 7886.6705 | M35: =SUM(M27:M28)*$J$35 -> 8162.7039 | O35: =SUM(O27:O28)*$J$35 -> 8448.3986 | Q35: =SUM(Q27:Q28)*$J$35 -> 8744.0925 | R35: =SUM(K35+M35+O35+Q35) -> 33241.866 | S35: 0 | T35: =SUM(R35:S35) -> 33241.866
F37: Subtotal Direct Labor | K37: =SUM(K30:K35) -> 348749.13 | M37: =SUM(M30:M35) -> 447169.33 | O37: =SUM(O30:O35) -> 462820.25 | Q37: =SUM(Q30:Q35) -> 429601.67 | R37: =K37+M37+O37+Q37 -> 1688340.4 | S37: =SUM(S30:S35) -> 0 | T37: =SUM(R37:S37) -> 1688340.4
F38: Travel
F39: T1: Post-award Meeting with ILAB
A40: CP.T1.A | B40: 86040 | C40: COL2 | D40: COL2 | E40: 0 | F40: Airfare - Colombia-DC | G40: Travel | H40: Trip | I40: 2 | J40: 750 | K40: =I40*J40 -> 1500 | L40: 0 | M40: =L40*J40*$G$9 -> 0 | N40: 0 | O40: =N40*J40*$G$9*$G$9 -> 0 | P40: 0 | Q40: =P40*J40*$G$9*$G$9*$G$9 -> 0 | R40: =K40+M40+O40+Q40 -> 1500 | S40: - | T40: =SUM(R40:S40) -> 1500
A41: CP.T1.B | B41: 86030 (Lodging)/ 86050 (M&IE) | C41: COL2 | D41: COL2 | E41: 0 | F41: Lodging and M&IE in DC | G41: Travel | H41: Day | I41: =5*2 -> 10 | J41: =68.4+210 -> 278.4 | K41: =I41*J41 -> 2784 | L41: 0 | M41: =L41*J41*$G$9 -> 0 | N41: 0 | O41: =N41*J41*$G$9*$G$9 -> 0 | P41: 0 | Q41: =P41*J41*$G$9*$G$9*$G$9 -> 0 | R41: =K41+M41+O41+Q41 -> 2784 | S41: - | T41: =SUM(R41:S41) -> 2784
A42: CP.T1.C | B42: 86000 | C42: COL2 | D42: COL2 | E42: 0 | F42: Local transportation in DC | G42: Travel | H42: Day | I42: 5 | J42: 25 | K42: =I42*J42 -> 125 | L42: 0 | M42: =L42*J42*$G$9 -> 0 | N42: 0 | O42: =N42*J42*$G$9*$G$9 -> 0 | P42: 0 | Q42: =P42*J42*$G$9*$G$9*$G$9 -> 0 | R42: =K42+M42+O42+Q42 -> 125 | S42: - | T42: =SUM(R42:S42) -> 125
A43: CP.T1.D | B43: 86050 | C43: COL2 | D43: COL2 | E43: 0 | F43: U.S. Visa Fees | G43: Travel | H43: Trip | I43: 2 | J43: 160 | K43: =I43*J43 -> 320 | L43: 0 | M43: =L43*J43*$G$9 -> 0 | N43: 0 | O43: =N43*J43*$G$9*$G$9 -> 0 | P43: 0 | Q43: =P43*J43*$G$9*$G$9*$G$9 -> 0 | R43: =K43+M43+O43+Q43 -> 320 | S43: - | T43: =SUM(R43:S43) -> 320
F44: T2: Field Personnel Annual Visits with ILAB
A45: CP.T2.A | B45: 86040 | C45: COL2 | D45: COL2 | E45: 0 | F45: Airfare - Colombia-DC | G45: Travel | H45: Trip | I45: 0 | J45: 750 | K45: =I45*J45 -> 0 | L45: 1 | M45: =L45*J45*$G$9 -> 772.5 | N45: 2 | O45: =N45*J45*$G$9*$G$9 -> 1591.35 | P45: 1 | Q45: =P45*J45*$G$9*$G$9*$G$9 -> 819.54525 | R45: =K45+M45+O45+Q45 -> 3183.3953 | S45: - | T45: =SUM(R45:S45) -> 3183.3953
A46: CP.T2.B | B46: 86030 (Lodging)/ 86050 (M&IE) | C46: COL2 | D46: COL2 | E46: 0 | F46: Lodging and M&IE in DC | G46: Travel | H46: Day | I46: 0 | J46: =68.4+210 -> 278.4 | K46: =I46*J46 -> 0 | L46: 7 | M46: =L46*J46*$G$9 -> 2007.264 | N46: 14 | O46: =N46*J46*$G$9*$G$9 -> 4134.9638 | P46: 7 | Q46: =P46*J46*$G$9*$G$9*$G$9 -> 2129.5064 | R46: =K46+M46+O46+Q46 -> 8271.7342 | S46: - | T46: =SUM(R46:S46) -> 8271.7342
A47: CP.T2.C | B47: 86000 | C47: COL2 | D47: COL2 | E47: 0 | F47: Local transportation in DC | G47: Travel | H47: Day | I47: 0 | J47: 25 | K47: =I47*J47 -> 0 | L47: 7 | M47: =L47*J47*$G$9 -> 180.25 | N47: 7 | O47: =N47*J47*$G$9*$G$9 -> 185.6575 | P47: 7 | Q47: =P47*J47*$G$9*$G$9*$G$9 -> 191.22723 | R47: =K47+M47+O47+Q47 -> 557.13473 | S47: - | T47: =SUM(R47:S47) -> 557.13473
F48: T3: Project Management Travel to Field
A49: CP.T3.A | B49: 86040 | C49: USA | D49: USA | E49: 0 | F49: Airfare - DC-Colombia | G49: Travel | H49: Trip | I49: 1 | J49: 750 | K49: =I49*J49 -> 750 | L49: 1 | M49: =L49*J49*$G$9 -> 772.5 | N49: 1 | O49: =N49*J49*$G$9*$G$9 -> 795.675 | P49: 1 | Q49: =P49*J49*$G$9*$G$9*$G$9 -> 819.54525 | R49: =K49+M49+O49+Q49 -> 3137.7203 | S49: - | T49: =SUM(R49:S49) -> 3137.7203
A50: CP.T3.B | B50: 86030 (Lodging)/ 86050 (M&IE) | C50: USA | D50: USA | E50: 0 | F50: Lodging and M&IE | G50: Travel | H50: Day | I50: 5 | J50: =89+210 -> 299 | K50: =I50*J50 -> 1495 | L50: =5*1 -> 5 | M50: =L50*J50*$G$10 -> 1569.75 | N50: =5*1 -> 5 | O50: =N50*J50*$G$10*$G$10 -> 1648.2375 | P50: 5 | Q50: =P50*J50*$G$10*$G$10*$G$10 -> 1730.6494 | R50: =K50+M50+O50+Q50 -> 6443.6369 | S50: - | T50: =SUM(R50:S50) -> 6443.6369
A51: CP.T3.C | B51: 86000 | C51: USA | D51: USA | E51: 0 | F51: Local transportation | G51: Travel | H51: Day | I51: 5 | J51: 25 | K51: =I51*J51 -> 125 | L51: =5*1 -> 5 | M51: =L51*J51*$G$10 -> 131.25 | N51: =5*1 -> 5 | O51: =N51*J51*$G$10*$G$10 -> 137.8125 | P51: 5 | Q51: =P51*J51*$G$10*$G$10*$G$10 -> 144.70312 | R51: =K51+M51+O51+Q51 -> 538.76562 | S51: - | T51: =SUM(R51:S51) -> 538.76562
F52: T.4 Field-based Travel for Non-M&E Activities
A53: CP.T4.A | B53: 86030 (Lodging)/ 86050 (M&IE) | C53: COL2 | D53: COL2 | E53: 0 | F53: Lodging and M&IE Buenaventura | G53: Travel | H53: Month | I53: 5 | J53: =(96+30.5)*3 -> 379.5 | K53: =I53*J53 -> 1897.5 | L53: 7 | M53: =L53*J53*$G$10 -> 2789.325 | N53: 7 | O53: =N53*J53*$G$10*$G$10 -> 2928.7913 | P53: 5 | Q53: =P53*J53*$G$10*$G$10*$G$10 -> 2196.5934 | R53: =K53+M53+O53+Q53 -> 9812.2097 | S53: 0 | T53: =SUM(R53:S53) -> 9812.2097
A54: CP.T4.B | B54: 86030 (Lodging)/ 86050 (M&IE) | C54: COL2 | D54: COL2 | E54: 0 | F54: Lodging and M&IE Cartagena | G54: Travel | H54: Month | I54: 5 | J54: =(180+55)*3 -> 705 | K54: =I54*J54 -> 3525 | L54: 7 | M54: =L54*J54*$G$10 -> 5181.75 | N54: 7 | O54: =N54*J54*$G$10*$G$10 -> 5440.8375 | P54: 5 | Q54: =P54*J54*$G$10*$G$10*$G$10 -> 4080.6281 | R54: =K54+M54+O54+Q54 -> 18228.216 | S54: 0 | T54: =SUM(R54:S54) -> 18228.216
A55: CP.T4.C | B55: 86030 (Lodging)/ 86050 (M&IE) | C55: COL2 | D55: COL2 | E55: 0 | F55: Lodging and M&IE Santa Marta | G55: Travel | H55: Month | I55: 4 | J55: =(100+35.5)*3 -> 406.5 | K55: =I55*J55 -> 1626 | L55: 5 | M55: =L55*J55*$G$10 -> 2134.125 | N55: 5 | O55: =N55*J55*$G$10*$G$10 -> 2240.8313 | P55: 4 | Q55: =P55*J55*$G$10*$G$10*$G$10 -> 1882.2983 | R55: =K55+M55+O55+Q55 -> 7883.2545 | S55: 0 | T55: =SUM(R55:S55) -> 7883.2545
A56: CP.T4.D | B56: 86000 | C56: COL2 | D56: COL2 | E56: 0 | F56: Local transportation (ground transportation) | G56: Travel | H56: Month | I56: 6 | J56: =25*3 -> 75 | K56: =I56*J56 -> 450 | L56: 12 | M56: =L56*J56*$G$10 -> 945 | N56: 12 | O56: =N56*J56*$G$10*$G$10 -> 992.25 | P56: 6 | Q56: =P56*J56*$G$10*$G$10*$G$10 -> 520.93125 | R56: =K56+M56+O56+Q56 -> 2908.1813 | S56: 0 | T56: =SUM(R56:S56) -> 2908.1813
A57: CP.T4.E | B57: 86040 | C57: COL2 | D57: COL2 | E57: 0 | F57: Local transportation (airfare) | G57: Travel | H57: Month | I57: 6 | J57: =150 -> 150 | K57: =I57*J57 -> 900 | L57: 12 | M57: =L57*J57*$G$10 -> 1890 | N57: 12 | O57: =N57*J57*$G$10*$G$10 -> 1984.5 | P57: 6 | Q57: =P57*J57*$G$10*$G$10*$G$10 -> 1041.8625 | R57: =K57+M57+O57+Q57 -> 5816.3625 | S57: 0 | T57: =SUM(R57:S57) -> 5816.3625
F59: Subtotal Travel | K59: =SUM(K40:K57) -> 15497.5 | M59: =SUM(M40:M57) -> 18373.714 | O59: =SUM(O40:O57) -> 22080.906 | Q59: =SUM(Q40:Q57) -> 15557.49 | R59: =K59+M59+O59+Q59 -> 71509.611 | S59: =SUM(S40:S56) -> 0 | T59: =SUM(R59:S59) -> 71509.611
F60: Equipment
F62: Subtotal Equipment | K62: =K61 -> 0 | M62: =M61 -> 0 | O62: =O61 -> 0 | Q62: =Q61 -> 0 | R62: =K62+M62+O62+Q62 -> 0 | S62: =S61 -> 0 | T62: =SUM(R62:S62) -> 0
F63: Supplies and Office Expenses
F64: Project Office
A65: LAPTOP | B65: 82401 | C65: COL2/USA | D65: COL2/USA | E65: 0 | F65: Laptop computers & software | G65: Supplies | H65: Unit | I65: 7 | J65: 750 | K65: =I65*J65 -> 5250 | L65: 0 | M65: =L65*J65 -> 0 | N65: 0 | O65: =N65*J65 -> 0 | P65: 0 | Q65: =P65*J65 -> 0 | R65: =K65+M65+O65+Q65 -> 5250 | S65: 0 | T65: =SUM(R65:S65) -> 5250
A66: BANK FEES | B66: 90900 | C66: COL2 | D66: COL2 | E66: 0 | F66: Banking and cash handling fees | G66: Supplies | H66: Month | I66: 11 | J66: 35.7 | K66: =I66*J66 -> 392.7 | L66: 12 | M66: =L66*J66*$G$10 -> 449.82 | N66: 12 | O66: =N66*J66*$G$10*$G$10 -> 472.311 | P66: 11 | Q66: =P66*J66*$G$10*$G$10*$G$10 -> 454.59934 | R66: =K66+M66+O66+Q66 -> 1769.4303 | S66: 0 | T66: =SUM(R66:S66) -> 1769.4303
A67: COURIER | B67: 82350 | C67: COL2 | D67: COL2 | E67: 0 | F67: Courier fees/services | G67: Supplies | H67: Year | I67: 1 | J67: 60 | K67: =I67*J67 -> 60 | L67: 1 | M67: =L67*J67*$G$10 -> 63 | N67: 1 | O67: =N67*J67*$G$10*$G$10 -> 66.15 | P67: 1 | Q67: =P67*J67*$G$10*$G$10*$G$10 -> 69.4575 | R67: =K67+M67+O67+Q67 -> 258.6075 | S67: 0 | T67: =SUM(R67:S67) -> 258.6075
A68: RECRUIT | B68: 90450 | C68: COL2 | D68: COL2 | E68: 0 | F68: Recruitment/Procurement Advertising | G68: Supplies | H68: Year | I68: 1 | J68: 300 | K68: =I68*J68 -> 300 | L68: 1 | M68: =L68*J68*$G$10 -> 315 | N68: 1 | O68: =N68*J68*$G$10*$G$10 -> 330.75 | P68: 1 | Q68: =P68*J68*$G$10*$G$10*$G$10 -> 347.2875 | R68: =K68+M68+O68+Q68 -> 1293.0375 | S68: 0 | T68: =SUM(R68:S68) -> 1293.0375
A69: SUPPLIES | B69: 82401 | C69: COL2 | D69: COL2 | E69: 0 | F69: Office supplies | G69: Supplies | H69: Month | I69: 11 | J69: 105 | K69: =I69*J69 -> 1155 | L69: 12 | M69: =L69*J69*$G$10 -> 1323 | N69: 12 | O69: =N69*J69*$G$10*$G$10 -> 1389.15 | P69: 10 | Q69: =P69*J69*$G$10*$G$10*$G$10 -> 1215.5063 | R69: =K69+M69+O69+Q69 -> 5082.6562 | S69: 0 | T69: =SUM(R69:S69) -> 5082.6562
A70: RENT & UT | B70: 85180 | C70: COL2 | D70: COL2 | E70: 0 | F70: Office space | G70: Supplies | H70: Month | I70: 11 | J70: 700 | K70: =I70*J70 -> 7700 | L70: 12 | M70: =L70*J70*$G$10 -> 8820 | N70: 12 | O70: =N70*J70*$G$10*$G$10 -> 9261 | P70: 11 | Q70: =P70*J70*$G$10*$G$10*$G$10 -> 8913.7125 | R70: =K70+M70+O70+Q70 -> 34694.713 | S70: 0 | T70: =SUM(R70:S70) -> 34694.713
A71: PROP&LIAB | B71: 89500 | C71: COL2 | D71: COL2 | E71: 0 | F71: Property and liability insurance | G71: Supplies | H71: Year | I71: 1 | J71: 400 | K71: =I71*J71 -> 400 | L71: 1 | M71: =L71*J71*$G$10 -> 420 | N71: 1 | O71: =N71*J71*$G$10*$G$10 -> 441 | P71: 1 | Q71: =P71*J71*$G$10*$G$10*$G$10 -> 463.05 | R71: =K71+M71+O71+Q71 -> 1724.05 | S71: 0 | T71: =SUM(R71:S71) -> 1724.05
A72: LEGAL | B72: 81010 | C72: COL2 | D72: COL2 | E72: 0 | F72: Legal fees | G72: Supplies | H72: Year | I72: 1 | J72: 1000 | K72: =I72*J72 -> 1000 | L72: 1 | M72: =L72*J72*$G$10 -> 1050 | N72: 1 | O72: =N72*J72*$G$10*$G$10 -> 1102.5 | P72: 1 | Q72: =P72*J72*$G$10*$G$10*$G$10 -> 1157.625 | R72: =K72+M72+O72+Q72 -> 4310.125 | S72: 0 | T72: =SUM(R72:S72) -> 4310.125
A73: SECURITY | B73: 86110 | C73: COL2/USA | D73: COL2/USA | E73: 0 | F73: Security Plan expenses | G73: Supplies | H73: Month | I73: 11 | J73: 2000 | K73: =I73*J73 -> 22000 | L73: 12 | M73: =L73*J73*$G$10 -> 25200 | N73: 12 | O73: =N73*J73*$G$10*$G$10 -> 26460 | P73: 11 | Q73: =P73*J73*$G$10*$G$10*$G$10 -> 25467.75 | R73: =K73+M73+O73+Q73 -> 99127.75 | S73: 0 | T73: =SUM(R73:S73) -> 99127.75
A74: BIOKITS | B74: 82420 | C74: COL2 | D74: COL2 | E74: 0 | F74: Biosecurity kits for staff | G74: Supplies | H74: Month | I74: 11 | J74: 40 | K74: =I74*J74 -> 440 | L74: 12 | M74: =L74*J74*$G$10 -> 504 | N74: 12 | O74: =N74*J74*$G$10*$G$10 -> 529.2 | P74: 12 | Q74: =P74*J74*$G$10*$G$10*$G$10 -> 555.66 | R74: =K74+M74+O74+Q74 -> 2028.86 | S74: 0 | T74: =SUM(R74:S74) -> 2028.86
F75: Audits and Attestation Engagements
A76: AUDIT | B76: 82100 | C76: COL2 | D76: COL2 | E76: 0 | F76: Audit costs (A-133) | G76: Supplies | H76: Year | I76: 1 | J76: 5000 | K76: =I76*J76 -> 5000 | L76: 1 | M76: =L76*J76 -> 5000 | N76: 1 | O76: =N76*J76 -> 5000 | P76: 1 | Q76: =P76*J76 -> 5000 | R76: =K76+M76+O76+Q76 -> 20000 | S76: 0 | T76: =SUM(R76:S76) -> 20000
A77: ATTESTENG | B77: 81010 | C77: COL2 | D77: COL2 | E77: 0 | F77: Attestation Engagement | G77: Supplies | H77: Year | I77: 0 | J77: 100000 | K77: =I77*J77 -> 0 | L77: 0 | M77: =L77*J77 -> 0 | N77: 1 | O77: =N77*J77 -> 100000 | P77: 0 | Q77: =P77*J77 -> 0 | R77: =K77+M77+O77+Q77 -> 100000 | S77: 0 | T77: =SUM(R77:S77) -> 100000
F78: Project-wide Web Fees
A79: SUBSCRIPT | B79: 89400 | C79: COL2/USA | D79: COL2/USA | E79: 0 | F79: Timekeeping and expense reporting platform | G79: Supplies | H79: Month | I79: 12 | J79: =6*9 -> 54 | K79: =I79*J79 -> 648 | L79: 12 | M79: =L79*J79*$G$9 -> 667.44 | N79: 12 | O79: =N79*J79*G9*G9 -> 687.4632 | P79: 12 | Q79: =P79*J79*G9*G9*G9 -> 708.0871 | R79: =K79+M79+O79+Q79 -> 2710.9903 | S79: 0 | T79: =SUM(R79:S79) -> 2710.9903
F81: Subtotal Office Expenses | K81: =SUM(K65:K79) -> 44345.7 | M81: =SUM(M65:M79) -> 43812.26 | O81: =SUM(O65:O79) -> 145739.52 | Q81: =SUM(Q65:Q79) -> 44352.735 | R81: =K81+M81+O81+Q81 -> 278250.22 | S81: =SUM(S65:S80) -> 0 | T81: =SUM(R81:S81) -> 278250.22
F82: Outcome 1: Increased understanding of barriers to compliance with national laws related to internationally recognized labor rights in Colombia’s port sector
F83: Activities/Costs
F84: 1.1 Sub Awards
A85: CP.1.1.A | B85: 89050 | C85: COL2 | D85: COL2 | E85: UNIJAVERIA | F85: 1.1.1 Contractual: Sub-award to Universidad Javeriana | G85: Contractual | H85: Unit | K85: ='Universidad Javeriana'!G64 -> 127188.05 | M85: ='Universidad Javeriana'!I64 -> 12293.009 | O85: ='Universidad Javeriana'!K64 -> 12127.988 | Q85: ='Universidad Javeriana'!M64 -> 8357.4761 | R85: =K85+M85+O85+Q85 -> 159966.52 | S85: 0 | T85: =R85+S85 -> 159966.52
A86: CP.1.1.B | B86: 89050 | C86: USA | D86: USA | E86: SAI | F86: 1.1.2 Contractual: Sub-award to Social Accountability International | G86: Contractual | H86: Unit | K86: =SAI!G78 -> 86429.168 | M86: =SAI!I78 -> 110275.66 | O86: =SAI!K78 -> 89786.52 | Q86: =SAI!M78 -> 87336.156 | R86: =K86+M86+O86+Q86 -> 373827.5 | S86: 0 | T86: =R86+S86 -> 373827.5
F87: 1.2 Develop Initial Findings and Conclusions of Assessment Findings
A88: CP.1.2.A | B88: 87000 | C88: COL2 | D88: COL2 | E88: 0 | F88: Work seminars with key stakeholders to validate conclusions | G88: Other | H88: Seminars | I88: 4 | J88: 300 | K88: =J88*I88 -> 1200 | L88: 0 | M88: =(L88*J88)*$G$10 -> 0 | N88: 0 | O88: =N88*J88 -> 0 | P88: 0 | Q88: =P88*J88 -> 0 | R88: =K88+M88+O88+Q88 -> 1200 | S88: 0 | T88: =SUM(R88:S88) -> 1200
A89: CP.1.2.B | B89: 81999 | C89: COL2 | D89: COL2 | E89: 0 | F89: Consultancy to develop final document of assessment | G89: Contractual | H89: Month | I89: 1 | J89: 1500 | K89: =J89*I89 -> 1500 | L89: 0 | M89: =(L89*J89)*$G$10 -> 0 | O89: =N89*J89 -> 0 | P89: 0 | Q89: =P89*J89 -> 0 | R89: =K89+M89+O89+Q89 -> 1500 | S89: 0 | T89: =SUM(R89:S89) -> 1500
A90: CP.1.2.C | B90: 81021 | C90: COL2 | D90: COL2 | E90: 0 | F90: Document translation | G90: Other | H90: Document | I90: 1 | J90: 1200 | K90: =J90*I90 -> 1200 | L90: 0 | M90: =(L90*J90)*$G$10 -> 0 | N90: 0 | O90: =N90*K90 -> 0 | P90: 0 | Q90: =P90*J90 -> 0 | R90: =K90+M90+O90+Q90 -> 1200 | S90: 0 | T90: =SUM(R90:S90) -> 1200
F91: 1.3 Present Assessment Findings to Relevant Stakeholders
A92: CP.1.3.A | B92: 87010 | C92: COL2 | D92: COL2 | E92: 0 | F92: Individual meetings to present assessment findings | G92: Other | H92: Meeting | I92: 2 | J92: 75 | K92: =J92*I92 -> 150 | L92: 8 | M92: =(L92*J92)*$G$10 -> 630 | N92: 0 | O92: =N92*J92 -> 0 | P92: 0 | Q92: =P92*J92 -> 0 | R92: =K92+M92+O92+Q92 -> 780 | S92: 0 | T92: =SUM(R92:S92) -> 780
A93: CP.1.3.B | B93: 86030 | C93: COL2 | D93: COL2 | E93: 0 | F93: Tailored stakeholder presentations of assessment findings | G93: Other | H93: Meeting | I93: 2 | J93: 125 | K93: =J93*I93 -> 250 | L93: 6 | M93: =(L93*J93)*$G$10 -> 787.5 | N93: 0 | O93: =N93*K93 -> 0 | P93: 0 | Q93: =P93*J93 -> 0 | R93: =K93+M93+O93+Q93 -> 1037.5 | S93: 0 | T93: =SUM(R93:S93) -> 1037.5
A94: CP.1.3.C | B94: 86030 (Lodging)/ 86050 (M&IE) | C94: COL2 | D94: COL2 | E94: 0 | F94: Lodging and M&IE for field staff to present assessment findings | G94: Travel | H94: Day | I94: 6 | J94: =150+43 -> 193 | K94: =J94*I94 -> 1158 | L94: 12 | M94: =(L94*J94)*$G$10 -> 2431.8 | N94: 0 | O94: =N94*K94 -> 0 | P94: 0 | Q94: =P94*J94 -> 0 | R94: =K94+M94+O94+Q94 -> 3589.8 | S94: 0 | T94: =SUM(R94:S94) -> 3589.8
A95: CP.1.3.D | B95: 86000 | C95: COL2 | D95: COL2 | E95: 0 | F95: Local transportation for field staff to present assessment findings | G95: Travel | H95: Trip | I95: 3 | J95: 150 | K95: =J95*I95 -> 450 | L95: 6 | M95: =(L95*J95)*$G$10 -> 945 | N95: 0 | O95: =N95*K95 -> 0 | P95: 0 | Q95: =P95*J95 -> 0 | R95: =K95+M95+O95+Q95 -> 1395 | S95: 0 | T95: =SUM(R95:S95) -> 1395
A96: CP.1.3.E | B96: 82420 | C96: COL2 | D96: COL2 | E96: 0 | F96: Development of materials for social media | G96: Other | H96: Campaign | I96: 1 | J96: 300 | K96: =J96*I96 -> 300 | L96: 2 | M96: =(L96*J96)*$G$10 -> 630 | N96: 0 | O96: =N96*K96 -> 0 | P96: 0 | Q96: =P96*J96 -> 0 | R96: =K96+M96+O96+Q96 -> 930 | S96: 0 | T96: =SUM(R96:S96) -> 930
F98: Subtotal Outcome 1 | K98: =SUM(K85:K96) -> 219825.22 | M98: =SUM(M85:M96) -> 127992.97 | O98: =SUM(O85:O96) -> 101914.51 | Q98: =SUM(Q85:Q96) -> 95693.632 | R98: =K98+M98+O98+Q98 -> 545426.32 | S98: =SUM(S85:S96) -> 0 | T98: =SUM(R98:S98) -> 545426.32
F99: Outcome 2: Development of approaches to support compliance with internationally recognized labor standards in Colombia’s port sector
F100: Activities/Costs
F101: 2.1 Sub Awards
A102: CP.2.1.A | B102: 89050 | C102: USA | D102: USA | E102: SAI | F102: 2.1.1 Contractual: Sub-award to SAI | G102: Contractual | H102: Unit | K102: =SAI!G94 -> 32071.584 | M102: =SAI!I94 -> 50708.403 | O102: =SAI!K94 -> 47415.78 | Q102: =SAI!M94 -> 43668.078 | R102: =K102+M102+O102+Q102 -> 173863.85 | S102: 0 | T102: =R102+S102 -> 173863.85
A103: CP.2.1.B | B103: 89050 | C103: COL2 | D103: COL2 | E103: UNIJAVERIA | F103: 2.1.2 Contractual: Sub-award to Universidad Javeriana | G103: Contractual | H103: Unit | K103: ='Universidad Javeriana'!G85 -> 22541.53 | M103: ='Universidad Javeriana'!I85 -> 16236.509 | O103: ='Universidad Javeriana'!K85 -> 24783.488 | Q103: ='Universidad Javeriana'!M85 -> 14231.476 | R103: =K103+M103+O103+Q103 -> 77793.003 | S103: 0 | T103: =R103+S103 -> 77793.003
A104: CP.2.1.C | B104: 89050 | C104: COL2 | D104: COL2 | E104: CARVAJAL | F104: 2.1.3 Contractual: Sub-award to Fundación Carvajal | G104: Contractual | H104: Unit | K104: ='Fundación Carvajal'!F62 -> 0 | M104: ='Fundación Carvajal'!H62 -> 26216.814 | O104: ='Fundación Carvajal'!J62 -> 18708.577 | Q104: ='Fundación Carvajal'!L62 -> 0 | R104: =K104+M104+O104+Q104 -> 44925.391 | S104: 0 | T104: =R104+S104 -> 44925.391
F105: 2.2 Refinement of Proposed Activities to the Local Context
A106: CP.2.2.A | B106: 81010 | C106: COL2 | D106: COL2 | E106: 0 | F106: "Do No Harm" Analysis | G106: Other | H106: Document | I106: 0 | J106: 3000 | K106: =J106*I106 -> 0 | L106: 1 | M106: =(L106*J106)*$G$10 -> 3150 | N106: 0 | O106: =(N106*J106)*$G$10*$G$10 -> 0 | P106: 0 | Q106: =P106*J106 -> 0 | R106: =K106+M106+O106+Q106 -> 3150 | S106: 0 | T106: =SUM(R106:S106) -> 3150
A107: CP.2.2.B | B107: 81010 | C107: COL2 | D107: COL2 | E107: 0 | F107: Security/Risk Plan Analysis | G107: Other | H107: Document | I107: 1 | J107: 5000 | K107: =J107*I107 -> 5000 | L107: 0 | M107: =(L107*J107)*$G$10 -> 0 | N107: 0 | O107: =(N107*J107)*$G$10*$G$10 -> 0 | P107: 0 | Q107: =P107*J107 -> 0 | R107: =K107+M107+O107+Q107 -> 5000 | S107: 0 | T107: =SUM(R107:S107) -> 5000
F108: 2.3 Adapt and Prioritize Proposed Interventions with Stakeholders
A109: CP.2.3.A | B109: 87000 | C109: COL2 | D109: COL2 | E109: 0 | F109: Workshop to adapt and prioritize interventions with stakeholders | G109: Other | H109: Workshop | I109: 0 | J109: 300 | K109: =J109*I109 -> 0 | L109: 2 | M109: =(L109*J109)*$G$10 -> 630 | N109: 0 | O109: =(N109*J109)*$G$10*$G$10 -> 0 | P109: 0 | Q109: =P109*J109 -> 0 | R109: =K109+M109+O109+Q109 -> 630 | S109: 0 | T109: =SUM(R109:S109) -> 630
A110: CP.2.3.B | B110: 82420 (Matl)/ 85300 (Print.) | C110: COL2 | D110: COL2 | E110: 0 | F110: Material development/printing for workshop | G110: Other | H110: Year | I110: 0 | J110: 200 | K110: =J110*I110 -> 0 | L110: 1 | M110: =(L110*J110)*$G$10 -> 210 | N110: 0 | O110: =(N110*J110)*$G$10*$G$10 -> 0 | P110: 0 | Q110: =P110*J110 -> 0 | R110: =K110+M110+O110+Q110 -> 210 | S110: 0 | T110: =SUM(R110:S110) -> 210
...

Sheet SAI
A1: Name of Project: Advancing Labor Compliance in Colombia’s Port Sector
A2: Name of Subawardee: Social Accountability International (SAI)
A3: Subaward Budget
A4: Budget Assumptions:
A5: Inflation - US Based Goods/Services | B5: 1.03
A6: Inflation - Locally Purchased Goods/Services | B6: 1.05
A7: Merit Based Increases for HQ Staff | B7: 1.03
A8: Merit Based Increases for Field Staff | B8: 1.035
A10: BUDGET ITEM | B10: COUNTRY | C10: CATEGORY | D10: UNIT | E10: # of Units | F10: RATE/ UNIT | G10: YEAR 1 | H10: # of Units | I10: YEAR 2 | J10: # of Units | K10: YEAR 3 | L10: # of Units | M10: YEAR 4 | N10: TOTAL SAI | O10: TOTAL COST SHARING | P10: PROJECT GRAND TOTAL
A12: Direct Labor
A13: Field Personnel (include Level of Effort (LOE))
A14: Trainer & Facilitator 1 | B14: Colombia | C14: Salaries | D14: Day | E14: =5*6 -> 30 | F14: 300 | G14: =E14*F14 -> 9000 | H14: =10*12 -> 120 | I14: =H14*F14*$B$8 -> 37260 | J14: 120 | K14: =J14*F14*$B$8*$B$8 -> 38564.1 | L14: =11.5*12 -> 138 | M14: =L14*F14*$B$8*$B$8*$B$8 -> 45900.92 | N14: =SUM(G14+I14+K14+M14) -> 130725.02 | O14: 0 | P14: =SUM(N14:O14) -> 130725.02
A15: Trainer & Facilitator 2 | B15: Colombia | C15: Salaries | D15: Day | E15: =5*6 -> 30 | F15: 300 | G15: =E15*F15 -> 9000 | H15: =10*12 -> 120 | I15: =H15*F15*$B$8 -> 37260 | J15: 120 | K15: =J15*F15*$B$8*$B$8 -> 38564.1 | L15: =11.5*12 -> 138 | M15: =L15*F15*$B$8*$B$8*$B$8 -> 45900.92 | N15: =SUM(G15+I15+K15+M15) -> 130725.02 | O15: 0 | P15: =SUM(N15:O15) -> 130725.02
A16: Trainer & Facilitator 3 | B16: Costa Rica | C16: Salaries | D16: Day | E16: =5*3 -> 15 | F16: 350 | G16: =E16*F16 -> 5250 | H16: =5*3 -> 15 | I16: =H16*F16*$B$8 -> 5433.75 | J16: =5*3 -> 15 | K16: =J16*F16*$B$8*$B$8 -> 5623.9312 | L16: 0 | M16: =L16*F16*$B$8*$B$8*$B$8 -> 0 | N16: =SUM(G16+I16+K16+M16) -> 16307.681 | O16: 0 | P16: =SUM(N16:O16) -> 16307.681
A17: Trainer & Facilitator 4 | B17: Costa Rica | C17: Salaries | D17: Day | E17: =5*3 -> 15 | F17: 550 | G17: =E17*F17 -> 8250 | H17: =5*3 -> 15 | I17: =H17*F17*$B$8 -> 8538.75 | J17: =5*3 -> 15 | K17: =J17*F17*$B$8*$B$8 -> 8837.6062 | L17: 0 | M17: =L17*F17*$B$8*$B$8*$B$8 -> 0 | N17: =SUM(G17+I17+K17+M17) -> 25626.356 | O17: 0 | P17: =SUM(N17:O17) -> 25626.356
A18: HQ Personnel (include Level of Effort (LOE))
A19: Senior Director, Innovations and Capacity Building | B19: USA | C19: Salaries | D19: Day | E19: =2*12 -> 24 | F19: =125000/222 -> 563.06306 | G19: =E19*F19 -> 13513.514 | H19: =2*12 -> 24 | I19: =H19*F19*$B$7 -> 13918.919 | J19: =2*12 -> 24 | K19: =J19*F19*$B$7*$B$7 -> 14336.486 | L19: =2*12 -> 24 | M19: =L19*F19*$B$7*$B$7*$B$7 -> 14766.581 | N19: =SUM(G19+I19+K19+M19) -> 56535.5 | O19: 0 | P19: =SUM(N19:O19) -> 56535.5
A20: Associate Director, Innovations and Partnerships | B20: USA | C20: Salaries | D20: Day | E20: =4*10 -> 40 | F20: =100000/218 -> 458.7156 | G20: =E20*F20 -> 18348.624 | H20: =3*12 -> 36 | I20: =H20*F20*$B$7 -> 17009.174 | J20: =2*12 -> 24 | K20: =J20*F20*$B$7*$B$7 -> 11679.633 | L20: =2*12 -> 24 | M20: =L20*F20*$B$7*$B$7*$B$7 -> 12030.022 | N20: =SUM(G20+I20+K20+M20) -> 59067.453 | O20: 0 | P20: =SUM(N20:O20) -> 59067.453
A21: Manager, Innovations & Corporate Programs | B21: USA | C21: Salaries | D21: Day | E21: =1*12 -> 12 | F21: =70000/222 -> 315.31532 | G21: =E21*F21 -> 3783.7838 | H21: =1*12 -> 12 | I21: =H21*F21*$B$7 -> 3897.2973 | J21: =1*12 -> 12 | K21: =J21*F21*$B$7*$B$7 -> 4014.2162 | L21: =1*12 -> 12 | M21: =L21*F21*$B$7*$B$7*$B$7 -> 4134.6427 | N21: =SUM(G21+I21+K21+M21) -> 15829.94 | O21: 0 | P21: =SUM(N21:O21) -> 15829.94
A22: Manager, Stakeholder Relations | B22: USA | C22: Salaries | D22: Day | E22: =1*10 -> 10 | F22: =70000/222 -> 315.31532 | G22: =E22*F22 -> 3153.1532 | H22: =2*12 -> 24 | I22: =H22*F22*$B$7 -> 7794.5946 | J22: =1*12 -> 12 | K22: =J22*F22*$B$7*$B$7 -> 4014.2162 | L22: 10 | M22: =L22*F22*$B$7*$B$7*$B$7 -> 3445.5356 | N22: =SUM(G22+I22+K22+M22) -> 18407.5 | O22: 0 | P22: =SUM(N22:O22) -> 18407.5
A23: Manager, Operations | B23: USA | C23: Salaries | D23: Day | E23: =2*10 -> 20 | F23: =70000/222 -> 315.31532 | G23: =E23*F23 -> 6306.3063 | H23: =1*12 -> 12 | I23: =H23*F23*$B$7 -> 3897.2973 | J23: =1*12 -> 12 | K23: =J23*F23*$B$7*$B$7 -> 4014.2162 | L23: =1*12 -> 12 | M23: =L23*F23*$B$7*$B$7*$B$7 -> 4134.6427 | N23: =SUM(G23+I23+K23+M23) -> 18352.463 | O23: 0 | P23: =SUM(N23:O23) -> 18352.463
A25: Subtotal | G25: =SUM(G14:G23) -> 76605.381 | I25: =SUM(I14:I23) -> 135009.78 | K25: =SUM(K14:K23) -> 129648.51 | M25: =SUM(M14:M23) -> 130313.26 | N25: =SUM(G25+I25+K25+M25) -> 471576.93 | O25: 0 | P25: =SUM(N25:O25) -> 471576.93
A27: Fringe Benefits
A28: Fringe benefits HQ Support | C28: Fringe Benefits | F28: 0.29 | G28: =F28*SUM(G19:G23) -> 13080.56 | I28: =F28*SUM(I19:I23) -> 13490.012 | K28: =F28*SUM(K19:K23) -> 11037.043 | M28: =F28*SUM(M19:M23) -> 11168.313 | N28: =SUM(G28+I28+K28+M28) -> 48775.928 | O28: 0 | P28: =SUM(N28:O28) -> 48775.928
E29: 5
A30: Subtotal Direct Labor | G30: =SUM(G25:G28) -> 89685.941 | I30: =SUM(I25:I28) -> 148499.79 | K30: =SUM(K25:K28) -> 140685.55 | M30: =SUM(M25:M28) -> 141481.58 | N30: =G30+I30+K30+M30 -> 520352.86 | O30: =SUM(O13:O28) -> 0 | P30: =SUM(N30:O30) -> 520352.86
A32: Travel
A33: HQ Trips to Colombia
A34: Airfare NYC-Colombia (Bogota/Buenaventura/Cartagena) | C34: Travel | D34: Trip | E34: 1 | F34: 400 | G34: =E34*F34 -> 400 | H34: 1 | I34: =H34*F34*$B$6 -> 420 | J34: 1 | K34: =J34*F34*$B$6*$B$6 -> 441 | L34: 1 | M34: =L34*F34*$B$6*$B$6*$B$6 -> 463.05 | N34: =G34+I34+K34+M34 -> 1724.05 | O34: - | P34: =SUM(N34:O34) -> 1724.05
A35: Airfare Cartagena-Buenaventura | C35: Travel | D35: Trip | E35: 1 | F35: 60 | G35: =E35*F35 -> 60 | H35: 1 | I35: =H35*F35*$B$6 -> 63 | J35: 1 | K35: =J35*F35*$B$6*$B$6 -> 66.15 | L35: 1 | M35: =L35*F35*$B$6*$B$6*$B$6 -> 69.4575 | N35: =G35+I35+K35+M35 -> 258.6075 | O35: - | P35: =SUM(N35:O35) -> 258.6075
A36: Lodging and M&IE - Colombia (Bogota/Buenaventura/Cartagena) | C36: Travel | D36: Day | E36: 7 | F36: =200+99 -> 299 | G36: =E36*F36 -> 2093 | H36: 7 | I36: =H36*F36*$B$6 -> 2197.65 | J36: 7 | K36: =J36*F36*$B$6*$B$6 -> 2307.5325 | L36: 7 | M36: =L36*F36*$B$6*$B$6*$B$6 -> 2422.9091 | N36: =G36+I36+K36+M36 -> 9021.0916 | O36: - | P36: =SUM(N36:O36) -> 9021.0916
A37: Ground Transportation | C37: Travel | D37: Day | E37: 7 | F37: 25 | G37: =E37*F37 -> 175 | H37: 7 | I37: =H37*F37*$B$6 -> 183.75 | J37: 7 | K37: =J37*F37*$B$6*$B$6 -> 192.9375 | L37: 7 | M37: =L37*F37*$B$6*$B$6*$B$6 -> 202.58438 | N37: =G37+I37+K37+M37 -> 754.27188 | O37: - | P37: =SUM(N37:O37) -> 754.27188
A38: Field Personnel Trips in Colombia (field personnel based in Bogota)
A39: Airfare Bogota-Buenaventura | C39: Travel | D39: Trip | E39: 5 | F39: 70 | G39: =E39*F39 -> 350 | H39: 6 | I39: =H39*F39*$B$6 -> 441 | J39: 4 | K39: =J39*F39*$B$6*$B$6 -> 308.7 | L39: 2 | M39: =L39*F39*$B$6*$B$6*$B$6 -> 162.0675 | N39: =G39+I39+K39+M39 -> 1261.7675 | O39: - | P39: =SUM(N39:O39) -> 1261.7675
A40: Airfare Bogota-Cartagena | C40: Travel | D40: Trip | E40: 5 | F40: 60 | G40: =E40*F40 -> 300 | H40: 6 | I40: =H40*F40*$B$6 -> 378 | J40: 4 | K40: =J40*F40*$B$6*$B$6 -> 264.6 | L40: 2 | M40: =L40*F40*$B$6*$B$6*$B$6 -> 138.915 | N40: =G40+I40+K40+M40 -> 1081.515 | O40: - | P40: =SUM(N40:O40) -> 1081.515
A41: Lodging and M&IE - Buenaventura | C41: Travel | D41: Day | E41: =5*5 -> 25 | F41: =96+55 -> 151 | G41: =E41*F41 -> 3775 | H41: =6*5 -> 30 | I41: =H41*F41*$B$6 -> 4756.5 | J41: =4*5 -> 20 | K41: =J41*F41*$B$6*$B$6 -> 3329.55 | L41: =2*5 -> 10 | M41: =L41*F41*$B$6*$B$6*$B$6 -> 1748.0138 | N41: =G41+I41+K41+M41 -> 13609.064 | O41: - | P41: =SUM(N41:O41) -> 13609.064
A42: Lodging and M&IE - Cartagena | C42: Travel | D42: Day | E42: =5*5 -> 25 | F42: =200+99 -> 299 | G42: =E42*F42 -> 7475 | H42: =6*5 -> 30 | I42: =H42*F42*$B$6 -> 9418.5 | J42: =4*5 -> 20 | K42: =J42*F42*$B$6*$B$6 -> 6592.95 | L42: =2*5 -> 10 | M42: =L42*F42*$B$6*$B$6*$B$6 -> 3461.2988 | N42: =G42+I42+K42+M42 -> 26947.749 | O42: - | P42: =SUM(N42:O42) -> 26947.749
A43: Ground Transportation | C43: Travel | D43: Day | E43: 50 | F43: 25 | G43: =E43*F43 -> 1250 | H43: 60 | I43: =H43*F43*$B$6 -> 1575 | J43: 40 | K43: =J43*F43*$B$6*$B$6 -> 1102.5 | L43: 20 | M43: =L43*F43*$B$6*$B$6*$B$6 -> 578.8125 | N43: =G43+I43+K43+M43 -> 4506.3125 | O43: - | P43: =SUM(N43:O43) -> 4506.3125
A45: Subtotal Travel | G45: =SUM(G33:G43) -> 15878 | I45: =SUM(I33:I43) -> 19433.4 | K45: =SUM(K33:K43) -> 14605.92 | M45: =SUM(M33:M43) -> 9247.1085 | N45: =G45+I45+K45+M45 -> 59164.429 | O45: =SUM(O33:O43) -> 0 | P45: =SUM(N45:O45) -> 59164.429
A46: Supplies - Under $5,000 USD
A47: Desktop computers, laptops and software | C47: Supplies | D47: Unit | E47: 3 | F47: 200 | G47: =E47*F47 -> 600 | H47: 0 | I47: =H47*F47*$B$5 -> 0 | J47: 0 | K47: =J47*F47*$B$5*$B$5 -> 0 | L47: 0 | M47: =L47*F47*$B$5*$B$5*$B$5 -> 0 | N47: =G47+I47+K47+M47 -> 600 | O47: 0 | P47: =SUM(N47:O47) -> 600
A48: Stationary/printing materials | C48: Supplies | D48: Unit | E48: 12 | F48: 25 | G48: =E48*F48 -> 300 | H48: 12 | I48: =H48*F48*$B$5 -> 309 | J48: 12 | K48: =J48*F48*$B$5*$B$5 -> 318.27 | L48: 12 | M48: =L48*F48*$B$5*$B$5*$B$5 -> 327.8181 | N48: =G48+I48+K48+M48 -> 1255.0881 | O48: 0 | P48: =SUM(N48:O48) -> 1255.0881
A50: Subtotal Supplies | G50: =SUM(G47:G48) -> 900 | I50: =SUM(I47:I48) -> 309 | K50: =SUM(K47:K48) -> 318.27 | M50: =SUM(M47:M48) -> 327.8181 | N50: =G50+I50+K50+M50 -> 1855.0881 | O50: =SUM(O47:O48) -> 0 | P50: =SUM(N50:O50) -> 1855.0881
A51: Office Expenses
A52: Banking and cash handling fees | C52: Office Expenses | D52: Month | E52: 10 | F52: 30 | G52: =E52*F52 -> 300 | H52: 12 | I52: =H52*F52*$B$5 -> 370.8 | J52: 12 | K52: =J52*F52*$B$5*$B$5 -> 381.924 | L52: 10 | M52: =L52*F52*$B$5*$B$5*$B$5 -> 327.8181 | N52: =G52+I52+K52 -> 1052.724 | O52: 0 | P52: =SUM(N52:O52) -> 1052.724
A53: Courier fees/services/postage | C53: Office Expenses | D53: Month | E53: 10 | F53: 5 | G53: =E53*F53 -> 50 | H53: 12 | I53: =H53*F53*$B$5 -> 61.8 | J53: 12 | K53: =J53*F53*$B$5*$B$5 -> 63.654 | L53: 10 | M53: =L53*F53*$B$5*$B$5*$B$5 -> 54.63635 | N53: =G53+I53+K53+M53 -> 230.09035 | O53: 0 | P53: =SUM(N53:O53) -> 230.09035
A54: Teleconferencing/videoconferencing | C54: Office Expenses | D54: Month | E54: 10 | F54: 25 | G54: =E54*F54 -> 250 | H54: 12 | I54: =H54*F54*$B$5 -> 309 | J54: 12 | K54: =J54*F54*$B$5*$B$5 -> 318.27 | L54: 10 | M54: =L54*F54*$B$5*$B$5*$B$5 -> 273.18175 | N54: =G54+I54+K54+M54 -> 1150.4517 | O54: 0 | P54: =SUM(N54:O54) -> 1150.4517
A55: Security Plan expenses | C55: Office Expenses | D55: Month | E55: 10 | F55: 500 | G55: =E55*F55 -> 5000 | H55: 12 | I55: =H55*F55*$B$5 -> 6180 | J55: 12 | K55: =J55*F55*$B$5*$B$5 -> 6365.4 | L55: 12 | M55: =L55*F55*$B$5*$B$5*$B$5 -> 6556.362 | N55: =G55+I55+K55+M55 -> 24101.762 | O55: 0 | P55: =SUM(N55:O55) -> 24101.762
A56: Biosecurity kits for staff | C56: Office Expenses | D56: Month | E56: 10 | F56: 40 | G56: =E56*F56 -> 400 | H56: 12 | I56: =H56*F56*$B$5 -> 494.4 | J56: 12 | K56: =J56*F56*$B$5*$B$5 -> 509.232 | L56: 12 | M56: =L56*F56*$B$5*$B$5*$B$5 -> 524.50896 | N56: =G56+I56+K56+M56 -> 1928.141 | O56: 0 | P56: =SUM(N56:O56) -> 1928.141
A58: Subtotal Office Expenses | G58: =SUM(G52:G56) -> 6000 | I58: =SUM(I52:I56) -> 7416 | K58: =SUM(K52:K56) -> 7638.48 | M58: =SUM(M52:M56) -> 7736.5072 | N58: =G58+I58+K58+M58 -> 28790.987 | O58: =SUM(O52:O56) -> 0 | P58: =SUM(N58:O58) -> 28790.987
A59: The above is only for percentage calculations for the below outcomes
A60: Outcome 1: Increased understanding of barriers to compliance with national laws related to internationally recognized labor rights in Colombia’s port sector
A61: Activities/Costs
A62: Personnel & Fringe (50% of Direct Labor line item) | C62: Outcome1 | D62: Unit | E62: =$G$30 -> 89685.941 | F62: 0.5 | G62: =E62*F62 -> 44842.97 | H62: =$I$30 -> 148499.79 | I62: =H62*F62 -> 74249.897 | J62: =$K$30 -> 140685.55 | K62: =J62*F62 -> 70342.774 | L62: =$M$30 -> 141481.58 | M62: =L62*F62 -> 70740.789 | N62: =G62+I62+K62+M62 -> 260176.43 | O62: 0 | P62: =SUM(N62:O62) -> 260176.43
A63: Travel 50% | C63: Outcome1 | D63: Unit | E63: =$G$45 -> 15878 | F63: 0.5 | G63: =E63*F63 -> 7939 | H63: =$I$45 -> 19433.4 | I63: =H63*F63 -> 9716.7 | J63: =$K$45 -> 14605.92 | K63: =J63*F63 -> 7302.96 | L63: =$M$45 -> 9247.1085 | M63: =L63*F63 -> 4623.5543 | N63: =G63+I63+K63+M63 -> 29582.214 | O63: 0 | P63: =SUM(N63:O63) -> 29582.214
A64: Supplies 50% | C64: Outcome1 | D64: Unit | E64: =$G$50 -> 900 | F64: 0.5 | G64: =E64*F64 -> 450 | H64: =$I$50 -> 309 | I64: =H64*F64 -> 154.5 | J64: =$K$50 -> 318.27 | K64: =J64*F64 -> 159.135 | L64: =$M$50 -> 327.8181 | M64: =L64*F64 -> 163.90905 | N64: =G64+I64+K64+M64 -> 927.54405 | O64: 0 | P64: =SUM(N64:O64) -> 927.54405
A65: Office Expenses 50% | C65: Outcome1 | D65: Unit | E65: =$G$58 -> 6000 | F65: 0.5 | G65: =E65*F65 -> 3000 | H65: =$I$58 -> 7416 | I65: =H65*F65 -> 3708 | J65: =$K$58 -> 7638.48 | K65: =J65*F65 -> 3819.24 | L65: =$M$58 -> 7736.5072 | M65: =L65*F65 -> 3868.2536 | N65: =G65+I65+K65+M65 -> 14395.494 | O65: 0 | P65: =SUM(N65:O65) -> 14395.494
A66: 1.1.2.1 Stakeholder engagement for assessment of port sector
A67: Stakeholder workshops in Buenaventura | C67: Outcome1 | D67: Unit | E67: 2 | F67: 230 | G67: =E67*F67 -> 460 | H67: 3 | I67: =H67*F67*$B$6 -> 724.5 | J67: 0 | K67: =J67*F67*$B$6*$B$6 -> 0 | L67: 0 | M67: =L67*F67*$B$6*$B$6*$B$6 -> 0 | N67: =G67+I67+K67+M67 -> 1184.5 | O67: 0 | P67: =SUM(N67:O67) -> 1184.5
A68: Stakeholder workshops in Cartagena | C68: Outcome1 | D68: Unit | E68: 3 | F68: 285 | G68: =E68*F68 -> 855 | H68: 4 | I68: =H68*F68*$B$6 -> 1197 | J68: 0 | K68: =J68*F68*$B$6*$B$6 -> 0 | L68: 0 | M68: =L68*F68*$B$6*$B$6*$B$6 -> 0 | N68: =G68+I68+K68+M68 -> 2052 | O68: 0 | P68: =SUM(N68:O68) -> 2052
A69: Port operator and subcontractor labor assessments in Buenaventura | C69: Outcome1 | D69: Unit | E69: 50 | F69: 100 | G69: =E69*F69 -> 5000 | H69: 50 | I69: =H69*F69*$B$6 -> 5250 | J69: 0 | K69: =J69*F69*$B$6*$B$6 -> 0 | L69: 0 | M69: =L69*F69*$B$6*$B$6*$B$6 -> 0 | N69: =G69+I69+K69+M69 -> 10250 | O69: 0 | P69: =SUM(N69:O69) -> 10250
A70: Port operator and subcontractor labor assessments in Cartagena | C70: Outcome1 | D70: Unit | E70: 50 | F70: 100 | G70: =E70*F70 -> 5000 | H70: 50 | I70: =H70*F70*$B$6 -> 5250 | J70: 0 | K70: =J70*F70*$B$6*$B$6 -> 0 | L70: 0 | M70: =L70*F70*$B$6*$B$6*$B$6 -> 0 | N70: =G70+I70+K70+M70 -> 10250 | O70: 0 | P70: =SUM(N70:O70) -> 10250
A71: Printing and materials for workshops | C71: Outcome1 | D71: Unit | E71: 5 | F71: 205 | G71: =E71*F71 -> 1025 | H71: 0 | I71: =H71*F71*$B$6 -> 0 | J71: 0 | K71: =J71*F71*$B$6*$B$6 -> 0 | L71: 0 | M71: =L71*F71*$B$6*$B$6*$B$6 -> 0 | N71: =G71+I71+K71+M71 -> 1025 | O71: 0 | P71: =SUM(N71:O71) -> 1025
A72: Worker surveys (mobile) | C72: Outcome1 | D72: Unit | E72: 2000 | F72: 5 | G72: =E72*F72 -> 10000 | H72: 0 | I72: =H72*F72*$B$6 -> 0 | J72: 0 | K72: =J72*F72*$B$6*$B$6 -> 0 | L72: 0 | M72: =L72*F72*$B$6*$B$6*$B$6 -> 0 | N72: =G72+I72+K72+M72 -> 10000 | O72: 0 | P72: =SUM(N72:O72) -> 10000
A74: Direct Costs Total for Outcome 1 | G74: =SUM(G62:G72) -> 78571.97 | I74: =SUM(I62:I72) -> 100250.6 | K74: =SUM(K62:K72) -> 81624.109 | M74: =SUM(M62:M72) -> 79396.505 | N74: =G74+I74+K74+M74 -> 339843.18 | O74: =SUM(O62:O72) -> 0 | P74: =SUM(N74:O74) -> 339843.18
A76: Total Indirect Costs (De Minimis 10%) for Outcome 1 | C76: Indirect Charges | F76: 0.1 | G76: =(G74)*F76 -> 7857.197 | I76: =(I74)*F76 -> 10025.06 | K76: =(K74)*F76 -> 8162.4109 | M76: =(M74)*F76 -> 7939.6505 | N76: =SUM(G76+I76+K76+M76) -> 33984.318 | O76: 0 | P76: =SUM(N76:O76) -> 33984.318
A78: Subtotal Outcome 1 | G78: =SUM(G74:G76) -> 86429.168 | I78: =SUM(I74:I76) -> 110275.66 | K78: =SUM(K74:K76) -> 89786.52 | M78: =SUM(M74:M76) -> 87336.156 | N78: =G78+I78+K78+M78 -> 373827.5 | O78: =SUM(O74:O76) -> 0 | P78: =SUM(N78:O78) -> 373827.5
A79: Outcome 2: Development of approaches to support compliance with internationally recognized labor standards in Colombia’s port sector
A80: Activities/Costs
A81: Personnel & Fringe (25% of Direct Labor line item) | C81: Outcome2 | D81: Unit | E81: =$G$30 -> 89685.941 | F81: 0.25 | G81: =E81*F81 -> 22421.485 | H81: =$I$30 -> 148499.79 | I81: =H81*F81 -> 37124.949 | J81: =$K$30 -> 140685.55 | K81: =J81*F81 -> 35171.387 | L81: =$M$30 -> 141481.58 | M81: =L81*F81 -> 35370.394 | N81: =G81+I81+K81+M81 -> 130088.22 | O81: 0 | P81: =SUM(N81:O81) -> 130088.22
A82: Travel 25% | C82: Outcome2 | D82: Unit | E82: =$G$45 -> 15878 | F82: 0.25 | G82: =E82*F82 -> 3969.5 | H82: =$I$45 -> 19433.4 | I82: =H82*F82 -> 4858.35 | J82: =$K$45 -> 14605.92 | K82: =J82*F82 -> 3651.48 | L82: =$M$45 -> 9247.1085 | M82: =L82*F82 -> 2311.7771 | N82: =G82+I82+K82+M82 -> 14791.107 | O82: 0 | P82: =SUM(N82:O82) -> 14791.107
A83: Supplies 25% | C83: Outcome2 | D83: Unit | E83: =$G$50 -> 900 | F83: 0.25 | G83: =E83*F83 -> 225 | H83: =$I$50 -> 309 | I83: =H83*F83 -> 77.25 | J83: =$K$50 -> 318.27 | K83: =J83*F83 -> 79.5675 | L83: =$M$50 -> 327.8181 | M83: =L83*F83 -> 81.954525 | N83: =G83+I83+K83+M83 -> 463.77202 | O83: 0 | P83: =SUM(N83:O83) -> 463.77202
A84: Office Expenses 25% | C84: Outcome2 | D84: Unit | E84: =$G$58 -> 6000 | F84: 0.25 | G84: =E84*F84 -> 1500 | H84: =$I$58 -> 7416 | I84: =H84*F84 -> 1854 | J84: =$K$58 -> 7638.48 | K84: =J84*F84 -> 1909.62 | L84: =$M$58 -> 7736.5072 | M84: =L84*F84 -> 1934.1268 | N84: =G84+I84+K84+M84 -> 7197.7468 | O84: 0 | P84: =SUM(N84:O84) -> 7197.7468
A85: 2.1.1.1 Codesign workshops with stakeholders
A86: Participatory design workshops in Buenaventura | C86: Outcome2 | D86: Unit | E86: 2 | F86: 100 | G86: =E86*F86 -> 200 | H86: 4 | I86: =H86*F86*$B$6 -> 420 | J86: 4 | K86: =J86*F86*$B$6*$B$6 -> 441 | L86: 0 | M86: =L86*F86*$B$6*$B$6*$B$6 -> 0 | N86: =G86+I86+K86+M86 -> 1061 | O86: 0 | P86: =SUM(N86:O86) -> 1061
A87: Participatory design workshops in Cartagena | C87: Outcome2 | D87: Unit | E87: 2 | F87: 220 | G87: =E87*F87 -> 440 | H87: 4 | I87: =H87*F87*$B$6 -> 924 | J87: 4 | K87: =J87*F87*$B$6*$B$6 -> 970.2 | L87: 0 | M87: =L87*F87*$B$6*$B$6*$B$6 -> 0 | N87: =G87+I87+K87+M87 -> 2334.2 | O87: 0 | P87: =SUM(N87:O87) -> 2334.2
A88: Printing and materials for workshops | C88: Outcome1 | D88: Unit | E88: 4 | F88: 100 | G88: =E88*F88 -> 400 | H88: 8 | I88: =H88*F88*$B$6 -> 840 | J88: 8 | K88: =J88*F88*$B$6*$B$6 -> 882 | L88: 0 | M88: =L88*F88*$B$6*$B$6*$B$6 -> 0 | N88: =G88+I88+K88+M88 -> 2122 | O88: 0 | P88: =SUM(N88:O88) -> 2122
A90: Direct Costs Total for Outcome 2 | G90: =SUM(G81:G88) -> 29155.985 | I90: =SUM(I81:I88) -> 46098.549 | K90: =SUM(K81:K88) -> 43105.255 | M90: =SUM(M81:M88) -> 39698.253 | N90: =G90+I90+K90+M90 -> 158058.04 | O90: =SUM(O81:O88) -> 0 | P90: =SUM(N90:O90) -> 158058.04
A92: Total Indirect Costs (De Minimis 10%) for Outcome 2 | C92: Indirect Charges | F92: 0.1 | G92: =(G90)*F92 -> 2915.5985 | I92: =(I90)*F92 -> 4609.8549 | K92: =(K90)*F92 -> 4310.5255 | M92: =(M90)*F92 -> 3969.8253 | N92: =SUM(G92+I92+K92+M92) -> 15805.804 | O92: 0 | P92: =SUM(N92:O92) -> 15805.804
A94: Subtotal Outcome 2 | G94: =SUM(G90:G92) -> 32071.584 | I94: =SUM(I90:I92) -> 50708.403 | K94: =SUM(K90:K92) -> 47415.78 | M94: =SUM(M90:M92) -> 43668.078 | N94: =G94+I94+K94+M94 -> 173863.85 | O94: =SUM(O90:O92) -> 0 | P94: =SUM(N94:O94) -> 173863.85
A95: Outcome 3: Demonstrated effectiveness of approaches to support compliance with national laws related to internationally recognized labor rights in the Colombia’s port sector
A96: Activities/Costs
A97: Personnel & Fringe (20% of Direct Labor line item) | C97: Outcome3 | D97: Unit | E97: =$G$30 -> 89685.941 | F97: 0.2 | G97: =E97*F97 -> 17937.188 | H97: =$I$30 -> 148499.79 | I97: =H97*F97 -> 29699.959 | J97: =$K$30 -> 140685.55 | K97: =J97*F97 -> 28137.11 | L97: =$M$30 -> 141481.58 | M97: =L97*F97 -> 28296.315 | N97: =G97+I97+K97+M97 -> 104070.57 | O97: 0 | P97: =SUM(N97:O97) -> 104070.57
A98: Travel 20% | C98: Outcome3 | D98: Unit | E98: =$G$45 -> 15878 | F98: 0.2 | G98: =E98*F98 -> 3175.6 | H98: =$I$45 -> 19433.4 | I98: =H98*F98 -> 3886.68 | J98: =$K$45 -> 14605.92 | K98: =J98*F98 -> 2921.184 | L98: =$M$45 -> 9247.1085 | M98: =L98*F98 -> 1849.4217 | N98: =G98+I98+K98+M98 -> 11832.886 | O98: 0 | P98: =SUM(N98:O98) -> 11832.886
A99: Supplies 20% | C99: Outcome3 | D99: Unit | E99: =$G$50 -> 900 | F99: 0.2 | G99: =E99*F99 -> 180 | H99: =$I$50 -> 309 | I99: =H99*F99 -> 61.8 | J99: =$K$50 -> 318.27 | K99: =J99*F99 -> 63.654 | L99: =$M$50 -> 327.8181 | M99: =L99*F99 -> 65.56362 | N99: =G99+I99+K99+M99 -> 371.01762 | O99: 0 | P99: =SUM(N99:O99) -> 371.01762
A100: Office Expenses 20% | C100: Outcome3 | D100: Unit | E100: =$G$58 -> 6000 | F100: 0.2 | G100: =E100*F100 -> 1200 | H100: =$I$58 -> 7416 | I100: =H100*F100 -> 1483.2 | J100: =$K$58 -> 7638.48 | K100: =J100*F100 -> 1527.696 | L100: =$M$58 -> 7736.5072 | M100: =L100*F100 -> 1547.3014 | N100: =G100+I100+K100+M100 -> 5758.1974 | O100: 0 | P100: =SUM(N100:O100) -> 5758.1974
A101: 3.1.1.1 Engage multi-sector advisory committee to evaluate and select pilot programs
A102: Multi-sector advisory committee workshops in Buenaventura | C102: Outcome1 | D102: Unit | E102: 2 | F102: 100 | G102: =E102*F102 -> 200 | H102: 3 | I102: =H102*F102*$B$6 -> 315 | J102: 3 | K102: =J102*F102*$B$6*$B$6 -> 330.75 | L102: 2 | M102: =L102*F102*$B$6*$B$6*$B$6 -> 231.525 | N102: =G102+I102+K102+M102 -> 1077.275 | O102: 0 | P102: =SUM(N102:O102) -> 1077.275
A103: Multi-sector advisory committee workshops in Cartagena | C103: Outcome1 | D103: Unit | E103: 2 | F103: 245 | G103: =E103*F103 -> 490 | H103: 3 | I103: =H103*F103*$B$6 -> 771.75 | J103: 3 | K103: =J103*F103*$B$6*$B$6 -> 810.3375 | L103: 2 | M103: =L103*F103*$B$6*$B$6*$B$6 -> 567.23625 | N103: =G103+I103+K103+M103 -> 2639.3238 | O103: 0 | P103: =SUM(N103:O103) -> 2639.3238
A104: Worker surveys (mobile) | C104: Outcome1 | D104: Unit | E104: 0 | F104: 5 | G104: =E104*F104 -> 0 | H104: 100 | I104: =H104*F104*$B$6 -> 525 | J104: 1000 | K104: =J104*F104*$B$6*$B$6 -> 5512.5 | L104: 1000 | M104: =L104*F104*$B$6*$B$6*$B$6 -> 5788.125 | N104: =G104+I104+K104+M104 -> 11825.625 | O104: 0 | P104: =SUM(N104:O104) -> 11825.625
A105: Online Training System | C105: Outcome3 | D105: Unit | E105: 0 | F105: 15 | G105: =E105*F105 -> 0 | H105: 100 | I105: =H105*F105*$B$5 -> 1545 | J105: 500 | K105: =J105*F105*B5*B5 -> 7956.75 | L105: 500 | M105: =L105*F105*B5*B5*B5 -> 8195.4525 | N105: =G105+I105+K105+M105 -> 17697.202 | O105: 0 | P105: =SUM(N105:O105) -> 17697.202
A106: 3.1.1.2 Training workshops for relevant stakeholders in ports
A107: Training workshops in Buenaventura | C107: Outcome3 | D107: Unit | E107: 0 | F107: 255 | G107: =E107*F107 -> 0 | H107: 2 | I107: =H107*F107*$B$6 -> 535.5 | J107: 6 | K107: =J107*F107*$B$6*$B$6 -> 1686.825 | L107: 6 | M107: =L107*F107*$B$6*$B$6*$B$6 -> 1771.1663 | N107: =G107+I107+K107+M107 -> 3993.4913 | O107: 0 | P107: =SUM(N107:O107) -> 3993.4913
A108: Training workshops in Cartagena | C108: Outcome3 | D108: Unit | E108: 0 | F108: 500 | G108: =E108*F108 -> 0 | H108: 2 | I108: =H108*F108*$B$6 -> 1050 | J108: 6 | K108: =J108*F108*$B$6*$B$6 -> 3307.5 | L108: 6 | M108: =L108*F108*$B$6*$B$6*$B$6 -> 3472.875 | N108: =G108+I108+K108+M108 -> 7830.375 | O108: 0 | P108: =SUM(N108:O108) -> 7830.375
A110: Direct Costs Total for Outcome 3 | G110: =SUM(G97:G108) -> 23182.788 | I110: =SUM(I97:I108) -> 39873.889 | K110: =SUM(K97:K108) -> 52254.306 | M110: =SUM(M97:M108) -> 51784.982 | N110: =G110+I110+K110+M110 -> 167095.97 | O110: =SUM(O97:O105) -> 0 | P110: =SUM(N110:O110) -> 167095.97
A112: Total Indirect Costs (De Minimis 10%) for Outcome 3 | C112: Indirect Charges | F112: 0.1 | G112: =(G110)*F112 -> 2318.2788 | I112: =(I110)*F112 -> 3987.3889 | K112: =(K110)*F112 -> 5225.4306 | M112: =(M110)*F112 -> 5178.4982 | N112: =SUM(G112+I112+K112+M112) -> 16709.597 | O112: 0 | P112: =SUM(N112:O112) -> 16709.597
A114: Subtotal Outcome 3 | G114: =SUM(G110:G112) -> 25501.067 | I114: =SUM(I110:I112) -> 43861.278 | K114: =SUM(K110:K112) -> 57479.737 | M114: =SUM(M110:M112) -> 56963.48 | N114: =G114+I114+K114+M114 -> 183805.56 | O114: =SUM(O110:O112) -> 0 | P114: =SUM(N114:O114) -> 183805.56
A115: 5: Monitoring, Evaluation, and Collection of Reliable Data
A116: Activities/Costs
A117: Personnel & Fringe (5% of Direct Labor line item) | C117: M&E | D117: Unit | E117: =$G$30 -> 89685.941 | F117: 0.05 | G117: =E117*F117 -> 4484.297 | H117: =$I$30 -> 148499.79 | I117: =H117*F117 -> 7424.9897 | J117: =$K$30 -> 140685.55 | K117: =J117*F117 -> 7034.2774 | L117: =$M$30 -> 141481.58 | M117: =L117*F117 -> 7074.0789 | N117: =G117+I117+K117+M117 -> 26017.643 | O117: 0 | P117: =SUM(N117:O117) -> 26017.643
...

Sheet Fundación Carvajal
A1: Name of Project: Advancing Labor Compliance in Colombia’s Port Sector
A2: Name of Subawardee: Fundación Carvajal
A3: Budget Assumptions:
A5: Inflation - Locally Purchased Goods/Services | B5: 1.05
A7: Merit Based Increases for Field Staff | B7: 1.035
A9: BUDGET ITEM | B9: CATEGORY | C9: UNIT | D9: # of Units | E9: RATE/ UNIT | F9: YEAR 1 | G9: # of Units | H9: YEAR 2 | I9: # of Units | J9: YEAR 3 | K9: # of Units | L9: YEAR 4 | M9: TOTAL FUNDACIÓN CARVAJAL | N9: TOTAL COST SHARING | O9: PROJECT GRAND TOTAL
A11: Direct Labor
A12: Field Personnel
A13: Civil Society Engagement Coordinator (30%) | B13: Salaries | C13: Month | D13: 0 | E13: 615 | F13: =D13*E13 -> 0 | G13: 12 | H13: =G13*E13*$B$7 -> 7638.3 | I13: 12 | J13: =I13*E13 -> 7380 | K13: 0 | L13: =K13*E13 -> 0 | M13: =SUM(F13+H13+J13+L13) -> 15018.3 | N13: 0 | O13: =SUM(M13:N13) -> 15018.3
A14: Social Adviser (100%) | B14: Salaries | C14: Month | D14: 0 | E14: 762 | F14: =D14*E14 -> 0 | G14: 12 | H14: =G14*E14*$B$7 -> 9464.04 | I14: 12 | J14: =I14*E14 -> 9144 | K14: 0 | L14: =K14*E14 -> 0 | M14: =SUM(F14+H14+J14+L14) -> 18608.04 | N14: 0 | O14: =SUM(M14:N14) -> 18608.04
A15: HQ Personnel
A16: Methodological Leader (10%) | B16: Salaries | C16: Month | D16: 0 | E16: 307 | F16: =D16*E16 -> 0 | G16: 10 | H16: =G16*E16*$B$7 -> 3177.45 | I16: 12 | J16: =I16*E16 -> 3684 | K16: 0 | L16: =K16*E16 -> 0 | M16: =SUM(F16+H16+J16+L16) -> 6861.45 | N16: 0 | O16: =SUM(M16:N16) -> 6861.45
A17: Civil Society Mapping Leader (10%) | B17: Salaries | C17: Month | D17: 0 | E17: 108 | F17: =D17*E17 -> 0 | G17: 10 | H17: =G17*E17*$B$7 -> 1117.8 | I17: 12 | J17: =I17*E17 -> 1296 | K17: 0 | L17: =K17*E17 -> 0 | M17: =SUM(F17+H17+J17+L17) -> 2413.8 | N17: 0 | O17: =SUM(M17:N17) -> 2413.8
A19: Subtotal | F19: =SUM(F13:F17) -> 0 | H19: =SUM(H13:H17) -> 21397.59 | J19: =SUM(J13:J17) -> 21504 | L19: =SUM(L13:L17) -> 0 | M19: =SUM(F19+H19+J19+L19) -> 42901.59 | N19: 0 | O19: =SUM(M19:N19) -> 42901.59
A21: Fringe Benefits
A22: Fringe benefits | B22: Fringe Benefits | C22: Month | D22: 0 | E22: 0.53766 | F22: =F19*E22 -> 0 | H22: =H19*E22 -> 11504.628 | J22: =E22*J19 -> 11561.841 | L22: =L19*E22 -> 0 | M22: =SUM(F22+H22+J22+L22) -> 23066.469 | N22: 0 | O22: =SUM(M22:N22) -> 23066.469
A24: Subtotal Direct Labor | F24: =SUM(F19:F22) -> 0 | H24: =SUM(H19:H22) -> 32902.218 | J24: =SUM(J19:J22) -> 33065.841 | L24: =SUM(L19:L22) -> 0 | M24: =F24+H24+J24+L24 -> 65968.059 | N24: =SUM(N12:N22) -> 0 | O24: =SUM(M24:N24) -> 65968.059
A26: Travel
A28: Subtotal Travel | F28: =F2 -> 0 | H28: =H27 -> 0 | J28: =J27 -> 0 | L28: =L27 -> 0 | M28: =F28+H28+J28+L28 -> 0 | N28: =N27 -> 0 | O28: =SUM(M28:N28) -> 0
A29: Supplies and Office Expenses
A30: Laptop computers | B30: Supplies | C30: Unit | D30: 0 | E30: 750 | F30: =D30*E30 -> 0 | G30: 3 | H30: =G30*E30*$B$5 -> 2362.5 | I30: 0 | J30: =(I30*E30)*$B$5*$B$5 -> 0 | K30: 0 | L30: =(K30*E30)*$B$5*$B$5*$B$5 -> 0 | M30: =F30+H30+J30+L30 -> 2362.5 | N30: 0 | O30: =SUM(M30:N30) -> 2362.5
A31: Zoom License | B31: Supplies | C31: Month | D31: 0 | E31: 19 | F31: =D31*E31 -> 0 | G31: 12 | H31: =G31*E31*$B$5 -> 239.4 | I31: 12 | J31: =(I31*E31)*$B$5*$B$5 -> 251.37 | K31: 0 | L31: =(K31*E31)*$B$5*$B$5*$B$5 -> 0 | M31: =F31+H31+J31+L31 -> 490.77 | N31: 0 | O31: =SUM(M31:N31) -> 490.77
A32: Project cellphone | B32: Supplies | C32: Unit | D32: 0 | E32: 500 | F32: =D32*E32 -> 0 | G32: 1 | H32: =G32*E32*$B$5 -> 525 | I32: 0 | J32: =(I32*E32)*$B$5*$B$5 -> 0 | L32: =(K32*E32)*$B$5*$B$5*$B$5 -> 0 | M32: =F32+H32+J32+L32 -> 525 | N32: 0 | O32: =SUM(M32:N32) -> 525
A33: Project cellphone plan | B33: Supplies | C33: Month | D33: 0 | E33: 25 | F33: =D33*E33 -> 0 | G33: 12 | H33: =G33*E33*$B$5 -> 315 | I33: 12 | J33: =(I33*E33)*$B$5*$B$5 -> 330.75 | K33: 0 | L33: =(K33*E33)*$B$5*$B$5*$B$5 -> 0 | M33: =F33+H33+J33+L33 -> 645.75 | N33: 0 | O33: =SUM(M33:N33) -> 645.75
A34: Banking and cash handling fees | B34: Supplies | C34: Month | D34: 0 | E34: 30 | F34: =D34*E34 -> 0 | G34: 12 | H34: =G34*E34*$B$5 -> 378 | I34: 12 | J34: =(I34*E34)*$B$5*$B$5 -> 396.9 | K34: 0 | L34: =(K34*E34)*$B$5*$B$5*$B$5 -> 0 | M34: =F34+H34+J34+L34 -> 774.9 | N34: 0 | O34: =SUM(M34:N34) -> 774.9
A35: Courier fees/services/postage | B35: Supplies | C35: Year | D35: 0 | E35: 100 | F35: =D35*E35 -> 0 | G35: 1 | H35: =G35*E35*$B$5 -> 105 | I35: 1 | J35: =(I35*E35)*$B$5*$B$5 -> 110.25 | K35: 0 | L35: =(K35*E35)*$B$5*$B$5*$B$5 -> 0 | M35: =F35+H35+J35+L35 -> 215.25 | N35: 0 | O35: =SUM(M35:N35) -> 215.25
A36: Recruitment/Procurement Advertising | B36: Supplies | C36: Year | D36: 0 | E36: 81 | F36: =D36*E36 -> 0 | G36: 3 | H36: =G36*E36*$B$5 -> 255.15 | I36: 0 | J36: =(I36*E36)*$B$5*$B$5 -> 0 | K36: 0 | L36: =(K36*E36)*$B$5*$B$5*$B$5 -> 0 | M36: =F36+H36+J36+L36 -> 255.15 | N36: 0 | O36: =SUM(M36:N36) -> 255.15
A37: Project emails and internet | B37: Supplies | C37: Month | D37: 0 | E37: 43 | F37: =D37*E37 -> 0 | G37: 12 | H37: =G37*E37*$B$5 -> 541.8 | I37: 12 | J37: =(I37*E37)*$B$5*$B$5 -> 568.89 | K37: 0 | L37: =(K37*E37)*$B$5*$B$5*$B$5 -> 0 | M37: =F37+H37+J37+L37 -> 1110.69 | N37: 0 | O37: =SUM(M37:N37) -> 1110.69
A38: Project office rent | B38: Supplies | C38: Month | D38: 0 | E38: 111 | F38: =D38*E38 -> 0 | G38: 12 | H38: =G38*E38*$B$5 -> 1398.6 | I38: 12 | J38: =(I38*E38)*$B$5*$B$5 -> 1468.53 | K38: 0 | L38: =(K38*E38)*$B$5*$B$5*$B$5 -> 0 | M38: =F38+H38+J38+L38 -> 2867.13 | N38: 0 | O38: =SUM(M38:N38) -> 2867.13
A39: Security Plan expenses | B39: Supplies | C39: Month | D39: 0 | E39: 1000 | F39: =D39*E39 -> 0 | G39: 12 | H39: =G39*E39*$B$5 -> 12600 | I39: 12 | J39: =(I39*E39)*$B$5*$B$5 -> 13230 | K39: 0 | L39: =(K39*E39)*$B$5*$B$5*$B$5 -> 0 | M39: =F39+H39+J39+L39 -> 25830 | N39: 0 | O39: =SUM(M39:N39) -> 25830
A40: Biosecurity kits for project staff | B40: Supplies | C40: Month | D40: 0 | E40: 42 | F40: =D40*E40 -> 0 | G40: 12 | H40: =G40*E40*$B$5 -> 529.2 | I40: 12 | J40: =(I40*E40)*$B$5*$B$5 -> 555.66 | K40: 0 | L40: =(K40*E40)*$B$5*$B$5*$B$5 -> 0 | M40: =F40+H40+J40+L40 -> 1084.86 | N40: 0 | O40: =SUM(M40:N40) -> 1084.86
A42: Subtotal Supplies and Office Expenses | F42: =SUM(F30:F40) -> 0 | H42: =SUM(H30:H40) -> 19249.65 | J42: =SUM(J30:J40) -> 16912.35 | L42: =SUM(L30:L40) -> 0 | M42: =F42+H42+J42+L42 -> 36162 | N42: =SUM(N30:N40) -> 0 | O42: =SUM(M42:N42) -> 36162
A43: The above is only for percentage calculations for the below outcomes
A44: Outcome 2: Development of approaches to support compliance with internationally recognized labor standards in Colombia’s port sector
A45: Activities/Costs
A46: Personnel & Fringe (20% of Direct Labor line item) | B46: Personnel | C46: Unit | D46: =$F$24 -> 0 | E46: 0.25 | F46: =D46*E46 -> 0 | G46: =H24 -> 32902.218 | H46: =G46*E46 -> 8225.5546 | I46: =$J$24 -> 33065.841 | J46: =I46*E46 -> 8266.4602 | K46: =$L$24 -> 0 | L46: =K46*E46 -> 0 | M46: =F46+H46+J46+L46 -> 16492.015 | N46: 0 | O46: =SUM(M46:N46) -> 16492.015
A47: Supplies and Office Expenses 20% | B47: Supplies | C47: Unit | D47: =$F$42 -> 0 | E47: 0.25 | F47: =D47*E47 -> 0 | G47: =H42 -> 19249.65 | H47: =G47*E47 -> 4812.4125 | I47: =$J$42 -> 16912.35 | J47: =I47*E47 -> 4228.0875 | K47: =$L$42 -> 0 | L47: =K47*E47 -> 0 | M47: =F47+H47+J47+L47 -> 9040.5 | N47: 0 | O47: =SUM(M47:N47) -> 9040.5
A48: 2.1.3.1 Socialization of scope of the project with civil society organizations
A49: Initial engagement meetings with civil society organizations | B49: Other | C49: Meeting | D49: 0 | E49: 125 | F49: =D49*E49 -> 0 | G49: 8 | H49: =(G49*E49)*$B$5 -> 1050 | I49: 4 | J49: =(I49*E49)*$B$5*$B$5 -> 551.25 | K49: 0 | L49: =(K49*E49)*$B$5*$B$5*$B$5 -> 0 | M49: =F49+H49+J49+L49 -> 1601.25 | N49: 0 | O49: =SUM(M49:N49) -> 1601.25
A50: 2.1.3.2 Strengthen civil society and worker organizations
A51: Consultant: CSO mapping support | B51: Contractual | C51: Day | D51: 0 | E51: 35 | F51: =D51*E51 -> 0 | G51: 60 | H51: =G51*E51*$B$7 -> 2173.5 | I51: 60 | J51: =I51*E51 -> 2100 | K51: 0 | L51: =K51*E51 -> 0 | M51: =F51+H51+J51+L51 -> 4273.5 | N51: 0 | O51: =SUM(M51:N51) -> 4273.5
A52: Training CSOs and worker organizations on social dialogue skills | B52: Other | C52: Training | D52: 0 | E52: 300 | F52: =E52*D52 -> 0 | G52: 6 | H52: =G52*E52 -> 1800 | I52: 2 | J52: =I52*E52 -> 600 | K52: 0 | L52: =K52*E52 -> 0 | M52: =F52+H52+J52+L52 -> 2400 | N52: 0 | O52: =SUM(M52:N52) -> 2400
A53: Training CSOs and worker organizations on ethnic issues | B53: Other | C53: Training | D53: 0 | E53: 300 | F53: =E53*D53 -> 0 | G53: 6 | H53: =G53*E53 -> 1800 | I53: 2 | J53: =I53*E53 -> 600 | K53: 0 | L53: =K53*E53 -> 0 | M53: =F53+H53+J53+L53 -> 2400 | N53: 0 | O53: =SUM(M53:N53) -> 2400
A54: Lodging and M&IE for project staff | B54: Travel | C54: Day | D54: 0 | E54: 108 | F54: =D54*E54 -> 0 | G54: 12 | H54: =G54*E54 -> 1296 | I54: 2 | J54: =I54*E54 -> 216 | K54: 0 | L54: =K54*E54 -> 0 | M54: =F54+H54+J54+L54 -> 1512 | N54: 0 | O54: =SUM(M54:N54) -> 1512
A55: Local transportation for project staff | B55: Travel | C55: Trip | D55: 0 | E55: 46 | F55: =D55*E55 -> 0 | G55: 6 | H55: =G55*E55 -> 276 | I55: 1 | J55: =I55*E55 -> 46 | K55: 0 | L55: =K55*E55 -> 0 | M55: =F55+H55+J55+L55 -> 322 | N55: 0 | O55: =SUM(M55:N55) -> 322
A56: Material design and printing for CSO and worker organization trainings | B56: Other | C56: Training | D56: 0 | E56: 200 | F56: =D56*E56 -> 0 | G56: 12 | H56: =G56*E56 -> 2400 | I56: 2 | J56: =I56*E56 -> 400 | K56: 0 | L56: =K56*E56 -> 0 | M56: =F56+H56+J56+L56 -> 2800 | N56: 0 | O56: =SUM(M56:N56) -> 2800
A58: Direct Costs Total for Outcome 2 | F58: =SUM(F46:F56) -> 0 | H58: =SUM(H46:H56) -> 23833.467 | J58: =SUM(J46:J56) -> 17007.798 | L58: =SUM(L46:L56) -> 0 | M58: =F58+H58+J58+L58 -> 40841.265 | N58: =SUM(N46:N49) -> 0 | O58: =SUM(M58:N58) -> 40841.265
A60: Total Indirect Costs (De Minimis 10%) for Outcome 2 | B60: Indirect Charges | E60: 0.1 | F60: =(F58)*E60 -> 0 | H60: =(H58)*E60 -> 2383.3467 | J60: =(J58)*E60 -> 1700.7798 | L60: =(L58)*E60 -> 0 | M60: =SUM(F60+H60+J60+L60) -> 4084.1265 | N60: 0 | O60: =SUM(M60:N60) -> 4084.1265
A62: Subtotal Outcome 2 | F62: =SUM(F58:F60) -> 0 | H62: =SUM(H58:H60) -> 26216.814 | J62: =SUM(J58:J60) -> 18708.577 | L62: =SUM(L58:L60) -> 0 | M62: =F62+H62+J62+L62 -> 44925.391 | N62: =SUM(N49:N49) -> 0 | O62: =SUM(M62:N62) -> 44925.391
A63: Outcome 3: Demonstrated effectiveness of approaches to support compliance with national laws related to internationally recognized labor rights in the Colombia’s port sector
A64: Activities/Costs
A65: Personnel & Fringe (50% of Direct Labor line item) | B65: Personnel | C65: Unit | D65: =$F$24 -> 0 | E65: 0.5 | F65: =D65*E65 -> 0 | G65: =H24 -> 32902.218 | H65: =G65*E65 -> 16451.109 | I65: =$J$24 -> 33065.841 | J65: =I65*E65 -> 16532.92 | K65: =$L$24 -> 0 | L65: =K65*E65 -> 0 | M65: =F65+H65+J65+L65 -> 32984.029 | N65: 0 | O65: =SUM(M65:N65) -> 32984.029
A66: Supplies and Office Expenses 50% | B66: Supplies | C66: Unit | D66: =$F$42 -> 0 | E66: 0.5 | F66: =D66*E66 -> 0 | G66: =H60 -> 2383.3467 | H66: =G66*E66 -> 1191.6734 | I66: =$J$42 -> 16912.35 | J66: =I66*E66 -> 8456.175 | K66: =$L$42 -> 0 | L66: =K66*E66 -> 0 | M66: =F66+H66+J66+L66 -> 9647.8484 | N66: 0 | O66: =SUM(M66:N66) -> 9647.8484
A67: 3.1.2.1 Workshops to develop approaches with CSOs
A68: Workshops with CSOs to develop action plans for adoptability of approaches | B68: Other | C68: Workshop | D68: 0 | E68: 300 | F68: =D68*E68 -> 0 | G68: 1 | H68: =(G68*E68)*$B$5 -> 315 | I68: 4 | J68: =(I68*E68)*$B$5*$B$5 -> 1323 | K68: 0 | L68: =(K68*F68)*$B$5*$B$5*$B$5 -> 0 | M68: =F68+H68+J68+L68 -> 1638 | N68: 0 | O68: =SUM(M68:N68) -> 1638
A69: Workshops with CSOs to develop action plans for adaptability of approaches | B69: Other | C69: Workshop | D69: 0 | E69: 300 | F69: =D69*E69 -> 0 | G69: 1 | H69: =(G69*E69)*$B$5 -> 315 | I69: 4 | J69: =(I69*E69)*$B$5*$B$5 -> 1323 | K69: 0 | L69: =(K69*F69)*$B$5*$B$5*$B$5 -> 0 | M69: =F69+H69+J69+L69 -> 1638 | N69: 0 | O69: =SUM(M69:N69) -> 1638
A70: Lodging and M&IE for project staff | B70: Travel | C70: Day | D70: 0 | E70: 108 | F70: =D70*E70 -> 0 | G70: 0 | H70: =G70*E70 -> 0 | I70: 6 | J70: =I70*E70 -> 648 | K70: 0 | L70: =K70*E70 -> 0 | M70: =F70+H70+J70+L70 -> 648 | N70: 0 | O70: =SUM(M70:N70) -> 648
A71: Local transportation for project staff | B71: Travel | C71: Trip | D71: 0 | E71: 46 | F71: =D71*E71 -> 0 | G71: 0 | H71: =G71*E71 -> 0 | I71: 3 | J71: =I71*E71 -> 138 | K71: 0 | L71: =K71*E71 -> 0 | M71: =F71+H71+J71+L71 -> 138 | N71: 0 | O71: =SUM(M71:N71) -> 138
A72: Material design and printing for workshops with CSOs | B72: Other | C72: Workshop | D72: 0 | E72: 200 | F72: =D72*E72 -> 0 | G72: 1 | H72: =G72*E72 -> 200 | I72: 6 | J72: =I72*E72 -> 1200 | K72: 0 | L72: =K72*E72 -> 0 | M72: =F72+H72+J72+L72 -> 1400 | N72: 0 | O72: =SUM(M72:N72) -> 1400
A73: 3.1.2.2 Exchanges between CSOs from Buenaventura and Cartagena
A74: Workshops for collaboration between CSOs for adaptability/adoptability of approaches | B74: Other | C74: Workshop | D74: 0 | E74: 300 | F74: =SUM(D74*E74) -> 0 | G74: 0 | H74: =G74*E74 -> 0 | I74: 2 | J74: =I74*E74 -> 600 | K74: 0 | L74: =K74*E74 -> 0 | M74: =F74+H74+J74+L74 -> 600 | N74: 0 | O74: =SUM(M74:N74) -> 600
A75: Material design and printing for exchange workshops with CSOs | B75: Other | C75: Workshop | D75: 0 | E75: 150 | F75: =SUM(D75*E75) -> 0 | G75: 0 | H75: =G75*E75 -> 0 | I75: 2 | J75: =I75*E75 -> 300 | K75: 0 | L75: =K75*E75 -> 0 | M75: =F75+H75+J75+L75 -> 300 | N75: 0 | O75: =SUM(M75:N75) -> 300
A76: Participant lodging and M&IE | B76: Travel | C76: Day | D76: 0 | E76: 108 | F76: =SUM(D76*E76) -> 0 | G76: 0 | H76: =G76*E76 -> 0 | I76: 16 | J76: =I76*E76 -> 1728 | K76: 0 | L76: =K76*E76 -> 0 | M76: =F76+H76+J76+L76 -> 1728 | N76: 0 | O76: =SUM(M76:N76) -> 1728
A77: Participant local transportation | B77: Travel | C77: Trip | D77: 0 | E77: 46 | F77: =SUM(D77*E77) -> 0 | G77: 0 | H77: =G77*E77 -> 0 | I77: 8 | J77: =I77*E77 -> 368 | K77: 0 | L77: =K77*E77 -> 0 | M77: =F77+H77+J77+L77 -> 368 | N77: 0 | O77: =SUM(M77:N77) -> 368
A78: Lodging and M&IE for project staff | B78: Travel | C78: Day | D78: 0 | E78: 108 | F78: =SUM(D78*E78) -> 0 | G78: 0 | H78: =G78*E78 -> 0 | I78: 8 | J78: =I78*E78 -> 864 | K78: 0 | L78: =K78*E78 -> 0 | M78: =F78+H78+J78+L78 -> 864 | N78: 0 | O78: =SUM(M78:N78) -> 864
A79: Local transportation for project staff | B79: Travel | C79: Trip | D79: 0 | E79: 46 | F79: =SUM(D79*E79) -> 0 | G79: 0 | H79: =G79*E79 -> 0 | I79: 4 | J79: =I79*E79 -> 184 | K79: 0 | L79: =K79*E79 -> 0 | M79: =F79+H79+J79+L79 -> 184 | N79: 0 | O79: =SUM(M79:N79) -> 184
A81: Direct Costs Total for Outcome 3 | F81: =SUM(F65:F79) -> 0 | H81: =SUM(H65:H79) -> 18472.782 | J81: =SUM(J65:J79) -> 33665.095 | L81: =SUM(L65:L79) -> 0 | M81: =F81+H81+J81+L81 -> 52137.878 | N81: =SUM(N65:N79) -> 0 | O81: =SUM(M81:N81) -> 52137.878
A83: Total Indirect Costs (De Minimis 10%) for Outcome 3 | B83: Indirect Charges | E83: 0.1 | F83: =(F81)*E83 -> 0 | H83: =(H81)*E83 -> 1847.2782 | J83: =(J81)*E83 -> 3366.5095 | L83: =(L81)*E83 -> 0 | M83: =SUM(F83+H83+J83+L83) -> 5213.7878 | N83: 0 | O83: =SUM(M83:N83) -> 5213.7878
A85: Subtotal Outcome 3 | F85: =SUM(F81:F83) -> 0 | H85: =SUM(H81:H83) -> 20320.061 | J85: =SUM(J81:J83) -> 37031.605 | L85: =SUM(L81:L83) -> 0 | M85: =F85+H85+J85+L85 -> 57351.666 | N85: =SUM(N81:N83) -> 0 | O85: =SUM(M85:N85) -> 57351.666
A86: Outcome 4: Increased awareness and adoption of approaches to support compliance with national laws related to internationally recognized labor rights in Colombia’s port sector
A87: Activities/Costs
A88: Personnel & Fringe (20% of Direct Labor line item) | B88: Personnel | C88: Unit | D88: =$F$24 -> 0 | E88: 0.2 | F88: =D88*E88 -> 0 | G88: =H24 -> 32902.218 | H88: =G88*E88 -> 6580.4436 | I88: =$J$24 -> 33065.841 | J88: =I88*E88 -> 6613.1681 | K88: =$L$24 -> 0 | L88: =K88*E88 -> 0 | M88: =F88+H88+J88+L88 -> 13193.612 | N88: 0 | O88: =SUM(M88:N88) -> 13193.612
A89: Supplies and Office Expenses 20% | B89: Supplies | C89: Unit | D89: =$F$42 -> 0 | E89: 0.2 | F89: =D89*E89 -> 0 | G89: =H83 -> 1847.2782 | H89: =G89*E89 -> 369.45565 | I89: =$J$42 -> 16912.35 | J89: =I89*E89 -> 3382.47 | K89: =$L$42 -> 0 | L89: =K89*E89 -> 0 | M89: =F89+H89+J89+L89 -> 3751.9256 | N89: 0 | O89: =SUM(M89:N89) -> 3751.9256
A90: 4.1.2.1 Awareness raising strategy with CSOs
A91: Media campaigns with civil society organizations | B91: Other | C91: Campaign | D91: 0 | E91: 500 | F91: =D91*E91 -> 0 | G91: 1 | H91: =(G91*E91)*$B$5 -> 525 | I91: 4 | J91: =(I91*E91)*$B$5*$B$5 -> 2205 | K91: 0 | L91: =(K91*E91)*$B$5*$B$5*$B$5 -> 0 | M91: =F91+H91+J91+L91 -> 2730 | N91: 0 | O91: =SUM(M91:N91) -> 2730
A92: Graphic design development for social media | B92: Contractual | C92: Day | D92: 0 | E92: 100 | F92: =D92*E92 -> 0 | G92: 5 | H92: =(G92*E92)*$B$5 -> 525 | I92: 15 | J92: =(I92*E92)*$B$5*$B$5 -> 1653.75 | K92: 0 | L92: =(K92*E92)*$B$5*$B$5*$B$5 -> 0 | M92: =F92+H92+J92+L92 -> 2178.75 | N92: 0 | O92: =SUM(M92:N92) -> 2178.75
A94: Direct Costs Total for Outcome 4 | F94: =SUM(F88:F92) -> 0 | H94: =SUM(H88:H92) -> 7999.8993 | J94: =SUM(J88:J92) -> 13854.388 | L94: =SUM(L88:L92) -> 0 | M94: =F94+H94+J94+L94 -> 21854.287 | N94: =SUM(N88:N92) -> 0 | O94: =SUM(M94:N94) -> 21854.287
A96: Total Indirect Costs (De Minimis 10%) for Outcome 4 | B96: Indirect Charges | E96: 0.1 | F96: =(F94)*E96 -> 0 | H96: =(H94)*E96 -> 799.98993 | J96: =(J94)*E96 -> 1385.4388 | L96: =(L94)*E96 -> 0 | M96: =SUM(F96+H96+J96+L96) -> 2185.4287 | N96: 0 | O96: =SUM(M96:N96) -> 2185.4287
A98: Subtotal Outcome 4 | F98: =SUM(F94:F96) -> 0 | H98: =SUM(H94:H96) -> 8799.8892 | J98: =SUM(J94:J96) -> 15239.827 | L98: =SUM(L94:L96) -> 0 | M98: =F98+H98+J98+L98 -> 24039.716 | N98: =SUM(N91:N92) -> 0 | O98: =SUM(M98:N98) -> 24039.716
A99: 5: Monitoring, Evaluation, and Collection of Reliable Data
A100: Activities/Costs
A101: Personnel & Fringe (5% of Direct Labor line item) | B101: M&E | C101: Unit | D101: =$F$24 -> 0 | E101: 0.05 | F101: =D101*E101 -> 0 | G101: =H24 -> 32902.218 | H101: =G101*E101 -> 1645.1109 | I101: =$J$24 -> 33065.841 | J101: =I101*E101 -> 1653.292 | K101: =$L$24 -> 0 | L101: =K101*E101 -> 0 | M101: =F101+H101+J101+L101 -> 3298.4029 | N101: 0 | O101: =SUM(M101:N101) -> 3298.4029
A102: Supplies and Office Expenses 5% | B102: M&E | C102: Unit | D102: =$F$42 -> 0 | E102: 0.05 | F102: =D102*E102 -> 0 | G102: =H42 -> 19249.65 | H102: =G102*E102 -> 962.4825 | I102: =$J$42 -> 16912.35 | J102: =I102*E102 -> 845.6175 | K102: =$L$42 -> 0 | L102: =K102*E102 -> 0 | M102: =F102+H102+J102+L102 -> 1808.1 | N102: 0 | O102: =SUM(M102:N102) -> 1808.1
A103: 5.7.2.1 Collection of Reliable Data and Processing of Monitoring Data | M103: =F103+H103+J103+L103 -> 0
A104: Lodging and M&IE Field verification and data collection visits | B104: M&E | C104: Day | E104: 108 | F104: =D104*E104 -> 0 | G104: 12 | H104: =(G104*E104)*$B$5 -> 1360.8 | I104: 15 | J104: =(I104*E104)*$B$5*$B$5 -> 1786.05 | K104: 0 | L104: =K104*E104 -> 0 | M104: =F104+H104+J104+L104 -> 3146.85 | N104: 0 | O104: =SUM(M104:N104) -> 3146.85
A105: Local transportation - Field verification and data collection visits | B105: M&E | C105: Trip | E105: 46 | F105: =D105*E105 -> 0 | G105: 8 | H105: =(G105*E105)*$B$5 -> 386.4 | I105: 10 | J105: =(I105*E105)*$B$5*$B$5 -> 507.15 | K105: 0 | L105: =K105*E105 -> 0 | M105: =F105+H105+J105+L105 -> 893.55 | N105: 0 | O105: =SUM(M105:N105) -> 893.55
A106: Data collection materials and printing | B106: M&E | C106: Month | E106: 150 | F106: =D106*E106 -> 0 | G106: 6 | H106: =(G106*E106)*$B$5 -> 945 | I106: 6 | J106: =(I106*E106)*$B$5*$B$5 -> 992.25 | K106: 0 | L106: =K106*E106 -> 0 | M106: =F106+H106+J106+L106 -> 1937.25 | N106: 0 | O106: =SUM(M106:N106) -> 1937.25
A108: Direct Costs Total for Monitoring, Evaluation, and Collection of Reliable Data | F108: =SUM(F101:F106) -> 0 | H108: =SUM(H101:H106) -> 5299.7934 | J108: =SUM(J101:J106) -> 5784.3595 | L108: =SUM(L101:L106) -> 0 | M108: =F108+H108+J108+L108 -> 11084.153 | N108: =SUM(N101:N106) -> 0 | O108: =SUM(M108:N108) -> 11084.153
A110: Total Indirect Costs (NICRA or De Minimis) for M&E and Collection of Reliable Data | B110: Indirect Charges | E110: 0.1 | F110: =(F108)*E110 -> 0 | H110: =(H108)*E110 -> 529.97934 | J110: =(J108)*E110 -> 578.43595 | L110: =(L108)*E110 -> 0 | M110: =SUM(F110+H110+J110+L110) -> 1108.4153 | N110: 0 | O110: =SUM(M110:N110) -> 1108.4153
A112: Subtotal Monitoring, Evaluation, and Collection of Reliable Data | F112: =SUM(F108:F110) -> 0 | H112: =SUM(H108:H110) -> 5829.7728 | J112: =SUM(J108:J110) -> 6362.7955 | L112: =SUM(L108:L110) -> 0 | M112: =F112+H112+J112+L112 -> 12192.568 | N112: =SUM(N108:N110) -> 0 | O112: =SUM(M112:N112) -> 12192.568
A114: TOTAL COSTS | F114: =F112+F98+F85+F62 -> 0 | H114: =H112+H98+H85+H62 -> 61166.536 | J114: =J112+J98+J85+J62 -> 77342.805 | L114: =L112+L62+L98+L85 -> 0 | M114: =L114+J114+H114+F114 -> 138509.34 | N114: =N112+N62 -> 0 | O114: =SUM(M114:N114) -> 138509.34

Sheet Universidad Javeriana
A1: Name of Project: Advancing Labor Compliance in Colombia’s Port Sector
A2: Name of Subawardee: Universidad Javeriana
A3: Subaward Budget
A4: Budget Assumptions:
A5: Inflation - US Based Goods/Services | B5: 1.03
A6: Inflation - Locally Purchased Goods/Services | B6: 1.05
A7: Merit Based Increases for HQ Staff | B7: 1.03
A10: BUDGET ITEM | B10: COUNTRY | C10: CATEGORY | D10: UNIT | E10: # of Units | F10: RATE/ UNIT | G10: YEAR 1 | H10: # of Units | I10: YEAR 2 | J10: # of Units | K10: YEAR 3 | L10: # of Units | M10: YEAR 4 | N10: TOTAL UNIVERSIDAD JAVERIANA | O10: TOTAL COST SHARING | P10: PROJECT GRAND TOTAL
A12: Direct Labor
A13: HQ Personnel (include Level of Effort (LOE))
A14: Project Manager (100%) | C14: Salaries | D14: Month | E14: 10 | F14: 2500 | G14: =E14*F14 -> 25000 | H14: 12 | I14: =((H14*F14)*50%)*$B$7 -> 15450 | J14: 12 | K14: =((J14*F14)*50%)*$B$7*$B$7 -> 15913.5 | L14: 10 | M14: =((L14*F14)*40%)*$B$7*$B$7*$B$7 -> 10927.27 | N14: =SUM(G14+I14+K14+M14) -> 67290.77 | O14: 0 | P14: =SUM(N14:O14) -> 67290.77
A15: Project Academic Coordinator (100%) | C15: Salaries | D15: Month | E15: 10 | F15: 1800 | G15: =E15*F15 -> 18000 | H15: 12 | I15: =((H15*F15)*50%)*$B$7 -> 11124 | J15: 12 | K15: =((J15*F15)*50%)*$B$7*$B$7 -> 11457.72 | L15: 10 | M15: =((L15*F15)*40%)*$B$7*$B$7*$B$7 -> 7867.6344 | N15: =SUM(G15+I15+K15+M15) -> 48449.354 | O15: 0 | P15: =SUM(N15:O15) -> 48449.354
A16: Research Logistic Coordinator (100%) | C16: Salaries | D16: Month | E16: 10 | F16: 1000 | G16: =E16*F16 -> 10000 | H16: 3 | I16: =((H16*F16)*50%)*$B$7 -> 1545 | J16: 0 | K16: =((J16*F16)*50%)*$B$7*$B$7 -> 0 | L16: 0 | M16: =((L16*F16)*40%)*$B$7*$B$7*$B$7 -> 0 | N16: =SUM(G16+I16+K16+M16) -> 11545 | O16: 0 | P16: =SUM(N16:O16) -> 11545
A18: Subtotal | G18: =SUM(G13:G16) -> 53000 | I18: =SUM(I13:I16) -> 28119 | K18: =SUM(K13:K16) -> 27371.22 | M18: =SUM(M13:M16) -> 18794.904 | N18: =SUM(G18+I18+K18+M18) -> 127285.12 | O18: 0 | P18: =SUM(N18:O18) -> 127285.12
A20: Fringe Benefits
A21: Fringe benefits | C21: Fringe Benefits | F21: 0.3164 | G21: =G18*F21 -> 16769.2 | I21: =I18*F21 -> 8896.8516 | K21: =K18*F21 -> 8660.254 | M21: =M18*F21 -> 5946.7078 | N21: =SUM(G21+I21+K21+M21) -> 40273.013 | O21: 0 | P21: =SUM(N21:O21) -> 40273.013
A23: Subtotal Direct Labor | G23: =SUM(G18:G21) -> 69769.2 | I23: =SUM(I18:I21) -> 37015.852 | K23: =SUM(K18:K21) -> 36031.474 | M23: =SUM(M18:M21) -> 24741.612 | N23: =G23+I23+K23+M23 -> 167558.14 | O23: =SUM(O13:O21) -> 0 | P23: =SUM(N23:O23) -> 167558.14
A25: Travel
A27: Subtotal Travel | G27: =G26 -> 0 | I27: =I26 -> 0 | K27: =K26 -> 0 | M27: =M26 -> 0 | N27: =G27+I27+K27+M27 -> 0 | O27: =O26 -> 0 | P27: =SUM(N27:O27) -> 0
A28: Supplies - Under $5,000 USD
A30: Subtotal Supplies | G30: =G29 -> 0 | I30: =I29 -> 0 | K30: =K29 -> 0 | M30: =M29 -> 0 | N30: =G30+I30+K30+M30 -> 0 | O30: =O29 -> 0 | P30: =SUM(N30:O30) -> 0
A31: Office Expenses
A32: Banking and cash handling fees | C32: Office Expenses | D32: Month | E32: 10 | F32: 30 | G32: =E32*F32 -> 300 | H32: 12 | I32: =((H32*F32)*50%)*$B$6 -> 189 | J32: 12 | K32: =((J32*F32)*50%)*$B$6*$B$6 -> 198.45 | L32: 10 | M32: =((L32*F32)*40%)*$B$6*$B$6*$B$6 -> 138.915 | N32: =G32+I32+K32+M32 -> 826.365 | O32: 0 | P32: =SUM(N32:O32) -> 826.365
A33: Office supplies | C33: Office Expenses | D33: Month | E33: 10 | F33: 150 | G33: =E33*F33 -> 1500 | H33: 12 | I33: =((H33*F33)*50%)*$B$6 -> 945 | J33: 12 | K33: =((J33*F33)*50%)*$B$6*$B$6 -> 992.25 | L33: 10 | M33: =((L33*F33)*40%)*$B$6*$B$6*$B$6 -> 694.575 | N33: =G33+I33+K33+M33 -> 4131.825 | O33: 0 | P33: =SUM(N33:O33) -> 4131.825
A34: Security Plan expenses | C34: Office Expenses | D34: Month | E34: 10 | F34: 1000 | G34: =E34*F34 -> 10000 | H34: 12 | I34: =((H34*F34)*50%)*$B$6 -> 6300 | J34: 12 | K34: =((J34*F34)*50%)*$B$6*$B$6 -> 6615 | L34: 10 | M34: =((L34*F34)*40%)*$B$6*$B$6*$B$6 -> 4630.5 | N34: =G34+I34+K34+M34 -> 27545.5 | O34: 0 | P34: =SUM(N34:O34) -> 27545.5
A35: Biosecurity skits for staff | C35: Office Expenses | D35: Month | E35: 10 | F35: 40 | G35: =E35*F35 -> 400 | H35: 12 | I35: =((H35*F35)*50%)*$B$6 -> 252 | J35: 12 | K35: =((J35*F35)*50%)*$B$6*$B$6 -> 264.6 | L35: 10 | M35: =((L35*F35)*40%)*$B$6*$B$6*$B$6 -> 185.22 | N35: =G35+I35+K35+M35 -> 1101.82 | O35: 0 | P35: =SUM(N35:O35) -> 1101.82
A37: Subtotal Office Expenses | G37: =SUM(G32:G35) -> 12200 | I37: =SUM(I32:I35) -> 7686 | K37: =SUM(K32:K35) -> 8070.3 | M37: =SUM(M32:M35) -> 5649.21 | N37: =G37+I37+K37+M37 -> 33605.51 | O37: =SUM(O32:O35) -> 0 | P37: =SUM(N37:O37) -> 33605.51
A38: The above is only for percentage calculations for the below outcomes
A39: Outcome 1: Increased understanding of barriers to compliance with national laws related to internationally recognized labor rights in Colombia’s port sector
A40: Activities/Costs
A41: Personnel and Fringe (25% of Direct Labor line item) | C41: Salaries | D41: Month | E41: =G23 -> 69769.2 | F41: 0.25 | G41: =E41*F41 -> 17442.3 | H41: =I23 -> 37015.852 | I41: =H41*F41 -> 9253.9629 | J41: =K23 -> 36031.474 | K41: =J41*F41 -> 9007.8685 | L41: =M23 -> 24741.612 | M41: =L41*F41 -> 6185.403 | N41: =G41+I41+K41+M41 -> 41889.534 | O41: - | P41: =SUM(N41:O41) -> 41889.534
A42: Office Expenses 25% | C42: Supplies | D42: Month | E42: =G37 -> 12200 | F42: 0.25 | G42: =E42*F42 -> 3050 | H42: =I37 -> 7686 | I42: =H42*F42 -> 1921.5 | J42: =K37 -> 8070.3 | K42: =J42*F42 -> 2017.575 | L42: =M37 -> 5649.21 | M42: =L42*F42 -> 1412.3025 | N42: =G42+I42+K42+M42 -> 8401.3775 | O42: - | P42: =SUM(N42:O42) -> 8401.3775
A43: Labor Research Coordinator | C43: Salaries | D43: Month | E43: 10 | F43: 1800 | G43: =E43*F43 -> 18000 | H43: 0 | I43: =((H43*F43)*50%)*$B$8 -> 0 | J43: 0 | K43: =((J43*F43)*50%)*$B$8*$B$8 -> 0 | L43: 0 | M43: =((L43*F43)*40%)*$B$8*$B$8*$B$8 -> 0 | N43: =G43+I43+K43+M43 -> 18000 | O43: 0 | P43: =SUM(N43:O43) -> 18000
A44: Quantitative Investigator | C44: Salaries | D44: Month | E44: 10 | F44: 1500 | G44: =E44*F44 -> 15000 | H44: 0 | I44: =((H44*F44)*50%)*$B$8 -> 0 | J44: 0 | K44: =((J44*F44)*50%)*$B$8*$B$8 -> 0 | L44: 0 | M44: =((L44*F44)*40%)*$B$8*$B$8*$B$8 -> 0 | N44: =G44+I44+K44+M44 -> 15000 | O44: 0 | P44: =SUM(N44:O44) -> 15000
A45: Field Investigator 1 | C45: Salaries | D45: Month | E45: 10 | F45: 1000 | G45: =E45*F45 -> 10000 | H45: 0 | I45: =((H45*F45)*50%)*$B$8 -> 0 | J45: 0 | K45: =((J45*F45)*50%)*$B$8*$B$8 -> 0 | L45: 0 | M45: =((L45*F45)*40%)*$B$8*$B$8*$B$8 -> 0 | N45: =G45+I45+K45+M45 -> 10000 | O45: 0 | P45: =SUM(N45:O45) -> 10000
A46: Field Investigator 2 | C46: Salaries | D46: Month | E46: 10 | F46: 1000 | G46: =E46*F46 -> 10000 | H46: 0 | I46: =((H46*F46)*50%)*$B$8 -> 0 | J46: 0 | K46: =((J46*F46)*50%)*$B$8*$B$8 -> 0 | L46: 0 | M46: =((L46*F46)*40%)*$B$8*$B$8*$B$8 -> 0 | N46: =G46+I46+K46+M46 -> 10000 | O46: 0 | P46: =SUM(N46:O46) -> 10000
A47: Field Investigator 3 | C47: Salaries | D47: Month | E47: 10 | F47: 1000 | G47: =E47*F47 -> 10000 | H47: 0 | I47: =((H47*F47)*50%)*$B$8 -> 0 | J47: 0 | K47: =((J47*F47)*50%)*$B$8*$B$8 -> 0 | L47: 0 | M47: =((L47*F47)*40%)*$B$8*$B$8*$B$8 -> 0 | N47: =G47+I47+K47+M47 -> 10000 | O47: 0 | P47: =SUM(N47:O47) -> 10000
A48: Fringe benefits - Outcome 1 | C48: Fringe Benefits | F48: 0.3164 | G48: =SUM(G43:G47)*F48 -> 19933.2 | I48: =SUM(I43:I47)*F48 -> 0 | K48: =((J48*F48)*50%)*$B$8*$B$8 -> 0 | M48: =((L48*F48)*40%)*$B$8*$B$8*$B$8 -> 0 | N48: =G48+I48+K48+M48 -> 19933.2 | O48: 0 | P48: =SUM(N48:O48) -> 19933.2
A49: 1.1.1.1 Interviews with port stakeholders for the development of port assessment | P49: =SUM(N49:O49) -> 0
A50: Field personnel - Airfare | C50: Travel | D50: Trip | E50: 6 | F50: 100 | G50: =E50*F50 -> 600 | H50: 0 | I50: =(H50*F50)*$B$6 -> 0 | J50: 0 | K50: =(J50*F50)*$B$6*$B$6 -> 0 | L50: 0 | M50: =(L50*F50)*$B$6*$B$6*$B$6 -> 0 | N50: =G50+I50+K50+M50 -> 600 | O50: - | P50: =SUM(N50:O50) -> 600
A51: Field personnel - Lodging | C51: Travel | D51: Day | E51: 24 | F51: 150 | G51: =E51*F51 -> 3600 | H51: 0 | I51: =(H51*F51)*$B$6 -> 0 | J51: 0 | K51: =(J51*F51)*$B$6*$B$6 -> 0 | L51: 0 | M51: =(L51*F51)*$B$6*$B$6*$B$6 -> 0 | N51: =G51+I51+K51+M51 -> 3600 | O51: - | P51: =SUM(N51:O51) -> 3600
A52: Field personnel - Ground Transportation | C52: Travel | D52: Day | E52: 24 | F52: 25 | G52: =E52*F52 -> 600 | H52: 0 | I52: =(H52*F52)*$B$6 -> 0 | J52: 0 | K52: =(J52*F52)*$B$6*$B$6 -> 0 | L52: 0 | M52: =(L52*F52)*$B$6*$B$6*$B$6 -> 0 | N52: =G52+I52+K52+M52 -> 600 | O52: - | P52: =SUM(N52:O52) -> 600
A53: Field personnel - M&IE | C53: Travel | D53: Day | E53: 24 | F53: 50 | G53: =E53*F53 -> 1200 | H53: 0 | I53: =(H53*F53)*$B$6 -> 0 | J53: 0 | K53: =(J53*F53)*$B$6*$B$6 -> 0 | L53: 0 | M53: =(L53*F53)*$B$6*$B$6*$B$6 -> 0 | N53: =G53+I53+K53+M53 -> 1200 | O53: - | P53: =SUM(N53:O53) -> 1200
A54: 1.1.1.2 Focus groups with port stakeholders for the development of port assessment
A55: Workshop venue and related expenses | C55: Travel | D55: Day | E55: 4 | F55: 200 | G55: =E55*F55 -> 800 | H55: 0 | I55: =(H55*F55)*$B$6 -> 0 | J55: 0 | K55: =(J55*F55)*$B$6*$B$6 -> 0 | L55: 0 | M55: =(L55*F55)*$B$6*$B$6*$B$6 -> 0 | N55: =G55+I55+K55+M55 -> 800 | O55: - | P55: =SUM(N55:O55) -> 800
A56: Field personnel - Airfare | C56: Travel | D56: Trip | E56: 6 | F56: 100 | G56: =E56*F56 -> 600 | H56: 0 | I56: =(H56*F56)*$B$6 -> 0 | J56: 0 | K56: =(J56*F56)*$B$6*$B$6 -> 0 | L56: 0 | M56: =(L56*F56)*$B$6*$B$6*$B$6 -> 0 | N56: =G56+I56+K56+M56 -> 600 | O56: - | P56: =SUM(N56:O56) -> 600
A57: Field personnel - Lodging | C57: Travel | D57: Day | E57: 24 | F57: 150 | G57: =E57*F57 -> 3600 | H57: 0 | I57: =(H57*F57)*$B$6 -> 0 | J57: 0 | K57: =(J57*F57)*$B$6*$B$6 -> 0 | L57: 0 | M57: =(L57*F57)*$B$6*$B$6*$B$6 -> 0 | N57: =G57+I57+K57+M57 -> 3600 | O57: - | P57: =SUM(N57:O57) -> 3600
A58: Field personnel - M&IE | C58: Travel | D58: Day | E58: 24 | F58: 50 | G58: =E58*F58 -> 1200 | H58: 0 | I58: =(H58*F58)*$B$6 -> 0 | J58: 0 | K58: =(J58*F58)*$B$6*$B$6 -> 0 | L58: 0 | M58: =(L58*F58)*$B$6*$B$6*$B$6 -> 0 | N58: =G58+I58+K58+M58 -> 1200 | O58: - | P58: =SUM(N58:O58) -> 1200
A60: Direct Costs Total for Outcome 1 | G60: =SUM(G41:G58) -> 115625.5 | I60: =SUM(I41:I58) -> 11175.463 | K60: =SUM(K41:K58) -> 11025.444 | M60: =SUM(M41:M58) -> 7597.7055 | N60: =G60+I60+K60+M60 -> 145424.11 | O60: =SUM(O50:O58) -> 0 | P60: =SUM(N60:O60) -> 145424.11
A62: Total Indirect Costs (De Minimis 10%) for Outcome 1 | C62: Indirect Charges | F62: 0.1 | G62: =G60*F62 -> 11562.55 | I62: =I60*F62 -> 1117.5463 | K62: =K60*F62 -> 1102.5444 | M62: =M60*F62 -> 759.77055 | N62: =G62+I62+K62+M62 -> 14542.411 | O62: 0 | P62: =SUM(N62:O62) -> 14542.411
A64: Subtotal Outcome 1 | G64: =SUM(G60:G62) -> 127188.05 | I64: =SUM(I60:I62) -> 12293.009 | K64: =SUM(K60:K62) -> 12127.988 | M64: =SUM(M60:M62) -> 8357.4761 | N64: =G64+I64+K64+M64 -> 159966.52 | O64: =SUM(O60:O62) -> 0 | P64: =SUM(N64:O64) -> 159966.52
A65: Outcome 2: Development of approaches to support compliance with national laws related to internationally recognized labor rights in Colombia’s port sector.
A66: Activities/Costs
A67: Personnel and Fringe (25% of Direct Labor line item) | C67: Salaries | D67: Month | E67: =G23 -> 69769.2 | F67: 0.25 | G67: =E67*F67 -> 17442.3 | H67: =I23 -> 37015.852 | I67: =H67*F67 -> 9253.9629 | J67: =K23 -> 36031.474 | K67: =J67*F67 -> 9007.8685 | L67: =M23 -> 24741.612 | M67: =L67*F67 -> 6185.403 | N67: =G67+I67+K67+M67 -> 41889.534 | O67: - | P67: =SUM(N67:O67) -> 41889.534
A68: Office Expenses 25% | C68: Supplies | D68: Month | E68: =G37 -> 12200 | F68: 0.25 | G68: =E68*F68 -> 3050 | H68: =I37 -> 7686 | I68: =H68*F68 -> 1921.5 | J68: =K37 -> 8070.3 | K68: =J68*F68 -> 2017.575 | L68: =M37 -> 5649.21 | M68: =L68*F68 -> 1412.3025 | N68: =G68+I68+K68+M68 -> 8401.3775 | O68: - | P68: =SUM(N68:O68) -> 8401.3775
A69: 2.1.2.1 Development of Social and Cultural Based approaches
A70: Engagement/Coordination meetings with stakeholders | C70: Other | D70: Meeting | E70: 0 | F70: 75 | G70: =F70*E70 -> 0 | H70: 3 | I70: =H70*F70 -> 225 | J70: 6 | K70: =J70*F70 -> 450 | L70: 2 | M70: =L70*F70 -> 150 | N70: =G70+I70+K70+M70 -> 825 | O70: 0 | P70: =SUM(N70:O70) -> 825
A71: Trainings for sustained social dialogue and a tripartite approach | C71: Other | D71: Training | E71: 0 | F71: 150 | G71: =F71*E71 -> 0 | H71: 2 | I71: =H71*F71 -> 300 | J71: 4 | K71: =J71*F71 -> 600 | L71: 2 | M71: =L71*F71 -> 300 | N71: =G71+I71+K71+M71 -> 1200 | O71: 0 | P71: =SUM(N71:O71) -> 1200
A72: Consultant: Training Lead | C72: Contractual | D72: Day | E72: 0 | F72: 120 | G72: =F72*E72 -> 0 | H72: 5 | I72: =H72*F72 -> 600 | J72: 10 | K72: =J72*F72 -> 1200 | L72: 5 | M72: =L72*F72 -> 600 | N72: =G72+I72+K72+M72 -> 2400 | O72: 0 | P72: =SUM(N72:O72) -> 2400
A73: Workshops for employer-employee teams | C73: Other | D73: Workshop | E73: 0 | F73: 300 | G73: =F73*E73 -> 0 | H73: 1 | I73: =H73*F73 -> 300 | J73: 5 | K73: =J73*F73 -> 1500 | L73: 2 | M73: =L73*F73 -> 600 | N73: =G73+I73+K73+M73 -> 2400 | O73: 0 | P73: =SUM(N73:O73) -> 2400
A74: Consultant: Workshop Lead | C74: Contractual | D74: Day | E74: 0 | F74: 120 | G74: =F74*E74 -> 0 | H74: 3 | I74: =H74*F74 -> 360 | J74: 14 | K74: =J74*F74 -> 1680 | L74: 7 | M74: =L74*F74 -> 840 | N74: =G74+I74+K74+M74 -> 2880 | O74: 0 | P74: =SUM(N74:O74) -> 2880
A75: "Sustainable unions" workshops | C75: Other | D75: Workshop | E75: 0 | F75: 300 | G75: =F75*E75 -> 0 | H75: 1 | I75: =H75*F75 -> 300 | J75: 4 | K75: =J75*F75 -> 1200 | L75: 2 | M75: =L75*F75 -> 600 | N75: =G75+I75+K75+M75 -> 2100 | O75: 0 | P75: =SUM(N75:O75) -> 2100
A76: Material design and printing for Social and Cultural Activities | C76: Other | D76: Event | E76: 0 | F76: 150 | G76: =F76*E76 -> 0 | H76: 4 | I76: =H76*F76 -> 600 | J76: 13 | K76: =J76*F76 -> 1950 | L76: 6 | M76: =L76*F76 -> 900 | N76: =G76+I76+K76+M76 -> 3450 | O76: 0 | P76: =SUM(N76:O76) -> 3450
A77: Lodging for project staff to support Social and Cultural Activities | C77: Travel | D77: Day | E77: 0 | F77: 150 | G77: =F77*E77 -> 0 | H77: 4 | I77: =H77*F77 -> 600 | J77: 13 | K77: =J77*F77 -> 1950 | L77: 6 | M77: =L77*F77 -> 900 | N77: =G77+I77+K77+M77 -> 3450 | O77: 0 | P77: =SUM(N77:O77) -> 3450
A78: M&IE for project staff to support Social and Cultural Activities | C78: Travel | D78: Day | E78: 0 | F78: 50 | G78: =F78*E78 -> 0 | H78: 4 | I78: =H78*F78 -> 200 | J78: 13 | K78: =J78*F78 -> 650 | L78: 6 | M78: =L78*F78 -> 300 | N78: =G78+I78+K78+M78 -> 1150 | O78: 0 | P78: =SUM(N78:O78) -> 1150
A79: Ground transportation for project staff to support Social and Cultural Activities | C79: Travel | D79: Day | E79: 0 | F79: 25 | G79: =F79*E79 -> 0 | H79: 4 | I79: =H79*F79 -> 100 | J79: 13 | K79: =J79*F79 -> 325 | L79: 6 | M79: =L79*F79 -> 150 | N79: =G79+I79+K79+M79 -> 575 | O79: 0 | P79: =SUM(N79:O79) -> 575
A81: Direct Costs Total for Outcome 2 | G81: =SUM(G67:G79) -> 20492.3 | I81: =SUM(I67:I79) -> 14760.463 | K81: =SUM(K67:K79) -> 22530.444 | M81: =SUM(M67:M79) -> 12937.706 | N81: =G81+I81+K81+M81 -> 70720.912 | O81: =SUM(O67:O79) -> 0 | P81: =SUM(N81:O81) -> 70720.912
A83: Total Indirect Costs (De Minimis 10%) for Outcome 2 | C83: Indirect Charges | F83: 0.1 | G83: =G81*F83 -> 2049.23 | I83: =I81*F83 -> 1476.0463 | K83: =K81*F83 -> 2253.0444 | M83: =M81*F83 -> 1293.7706 | N83: =G83+I83+K83+M83 -> 7072.0912 | O83: 0 | P83: =SUM(N83:O83) -> 7072.0912
A85: Subtotal Outcome 2 | G85: =SUM(G81:G83) -> 22541.53 | I85: =SUM(I81:I83) -> 16236.509 | K85: =SUM(K81:K83) -> 24783.488 | M85: =SUM(M81:M83) -> 14231.476 | N85: =G85+I85+K85+M85 -> 77793.003 | O85: =SUM(O81:O83) -> 0 | P85: =SUM(N85:O85) -> 77793.003
A86: Outcome 3: Demonstrated effectiveness of approaches to support compliance with national laws related to internationally recognized labor rights in the Colombia’s port sector
A87: Activities/Costs
A88: Personnel & Fringe (25% of Direct Labor line item) | C88: Outcome3 | D88: Unit | E88: =G23 -> 69769.2 | F88: 0.25 | G88: =E88*F88 -> 17442.3 | H88: =I23 -> 37015.852 | I88: =H88*F88 -> 9253.9629 | J88: =K23 -> 36031.474 | K88: =J88*F88 -> 9007.8685 | L88: =M23 -> 24741.612 | M88: =L88*F88 -> 6185.403 | N88: =G88+I88+K88+M88 -> 41889.534 | O88: 0 | P88: =SUM(N88:O88) -> 41889.534
A89: Office Expenses 25% | C89: Outcome3 | D89: Unit | E89: =G37 -> 12200 | F89: 0.25 | G89: =E89*F89 -> 3050 | H89: =I37 -> 7686 | I89: =H89*F89 -> 1921.5 | J89: =K37 -> 8070.3 | K89: =J89*F89 -> 2017.575 | L89: =M37 -> 5649.21 | M89: =L89*F89 -> 1412.3025 | N89: =G89+I89+K89+M89 -> 8401.3775 | O89: 0 | P89: =SUM(N89:O89) -> 8401.3775
A90: 3.1.3.1 Development of Adoptability and Adaptability of Approaches
A91: Workshops with private sector and workers unions to develop action plans for adoptability of approaches | C91: Other | D91: Workshop | E91: 0 | F91: 300 | G91: =SUM(E91*F91) -> 0 | H91: 1 | I91: =H91*F91 -> 300 | J91: 3 | K91: =J91*F91 -> 900 | L91: 0 | M91: =L91*F91 -> 0 | N91: =G91+I91+K91+M91 -> 1200 | O91: 0 | P91: =SUM(N91:O91) -> 1200
A92: Workshops with private sector and workers unions to develop action plans for adaptability of approaches | C92: Other | D92: Workshop | E92: 0 | F92: 150 | G92: =SUM(E92*F92) -> 0 | H92: 1 | I92: =H92*F92 -> 150 | J92: 3 | K92: =J92*F92 -> 450 | L92: 0 | M92: =L92*F92 -> 0 | N92: =G92+I92+K92+M92 -> 600 | O92: 0 | P92: =SUM(N92:O92) -> 600
A93: Lodging and M&IE for project staff | C93: Travel | D93: Day | E93: 0 | F93: 108 | G93: =SUM(E93*F93) -> 0 | H93: 0 | I93: =H93*F93 -> 0 | J93: 16 | K93: =J93*F93 -> 1728 | L93: 0 | M93: =L93*F93 -> 0 | N93: =G93+I93+K93+M93 -> 1728 | O93: 0 | P93: =SUM(N93:O93) -> 1728
A94: Local transportation for project staff | C94: Travel | D94: Day | E94: 0 | F94: 46 | G94: =SUM(E94*F94) -> 0 | H94: 0 | I94: =H94*F94 -> 0 | J94: 8 | K94: =J94*F94 -> 368 | L94: 0 | M94: =L94*F94 -> 0 | N94: =G94+I94+K94+M94 -> 368 | O94: 0 | P94: =SUM(N94:O94) -> 368
A95: Material design and printing for workshops with private sector and workers unions | C95: Materials | D95: Day | E95: 0 | F95: 108 | G95: =SUM(E95*F95) -> 0 | H95: 0 | I95: =H95*F95 -> 0 | J95: 8 | K95: =J95*F95 -> 864 | L95: 0 | M95: =L95*F95 -> 0 | N95: =G95+I95+K95+M95 -> 864 | O95: 0 | P95: =SUM(N95:O95) -> 864
A97: Direct Costs Total for Outcome 3 | G97: =SUM(G88:G95) -> 20492.3 | I97: =SUM(I88:I95) -> 11625.463 | K97: =SUM(K88:K95) -> 15335.444 | M97: =SUM(M88:M95) -> 7597.7055 | N97: =G97+I97+K97+M97 -> 55050.912 | O97: =SUM(O88:O90) -> 0 | P97: =SUM(N97:O97) -> 55050.912
A99: Total Indirect Costs (De Minimis 10%) for Outcome 3 | C99: Indirect Charges | F99: 0.1 | G99: =(G97)*F99 -> 2049.23 | I99: =(I97)*F99 -> 1162.5463 | K99: =(K97)*F99 -> 1533.5444 | M99: =(M97)*F99 -> 759.77055 | N99: =SUM(G99+I99+K99+M99) -> 5505.0912 | O99: 0 | P99: =SUM(N99:O99) -> 5505.0912
A101: Subtotal Outcome 3 | G101: =SUM(G97:G99) -> 22541.53 | I101: =SUM(I97:I99) -> 12788.009 | K101: =SUM(K97:K99) -> 16868.988 | M101: =SUM(M97:M99) -> 8357.4761 | N101: =G101+I101+K101+M101 -> 60556.003 | O101: =SUM(O90:O90) -> 0 | P101: =SUM(N101:O101) -> 60556.003
A102: Outcome 4: Increased awareness and adoption of approaches to support compliance with national laws related to internationally recognized labor rights in Colombia’s port sector
A103: Activities/Costs
A104: Personnel & Fringe (20% of Direct Labor line item) | C104: Outcome3 | D104: Unit | E104: =G23 -> 69769.2 | F104: 0.2 | G104: =E104*F104 -> 13953.84 | H104: =I23 -> 37015.852 | I104: =H104*F104 -> 7403.1703 | J104: =K23 -> 36031.474 | K104: =J104*F104 -> 7206.2948 | L104: =M23 -> 24741.612 | M104: =L104*F104 -> 4948.3224 | N104: =G104+I104+K104+M104 -> 33511.628 | O104: 0 | P104: =SUM(N104:O104) -> 33511.628
A105: Office Expenses 20% | C105: Outcome3 | D105: Unit | E105: =G37 -> 12200 | F105: 0.2 | G105: =E105*F105 -> 2440 | H105: =I37 -> 7686 | I105: =H105*F105 -> 1537.2 | J105: =K37 -> 8070.3 | K105: =J105*F105 -> 1614.06 | L105: =M37 -> 5649.21 | M105: =L105*F105 -> 1129.842 | N105: =G105+I105+K105+M105 -> 6721.102 | O105: 0 | P105: =SUM(N105:O105) -> 6721.102
A106: 4.1.1.1 Awareness raising with private sector and workers organizations
A107: Media campaigns with private sector and workers unions | C107: Outcome3 | D107: Campaign | E107: 0 | F107: 500 | G107: =E107*F107 -> 0 | H107: 1 | I107: =(H107*F107)*$B$5 -> 515 | J107: 4 | K107: =(J107*F107)*$B$5*$B$5 -> 2121.8 | L107: 4 | M107: =(L107*F107)*$B$5*$B$5*$B$5 -> 2185.454 | N107: =G107+I107+K107+M107 -> 4822.254 | O107: 0 | P107: =SUM(N107:O107) -> 4822.254
A108: Graphic design development for social media | C108: Contractual | D108: Day | E108: 0 | F108: 100 | G108: =E108*F108 -> 0 | H108: 5 | I108: =(H108*F108)*$B$5 -> 515 | J108: 15 | K108: =(J108*F108)*$B$5*$B$5 -> 1591.35 | L108: 15 | M108: =(L108*F108)*$B$5*$B$5*$B$5 -> 1639.0905 | N108: =G108+I108+K108+M108 -> 3745.4405 | O108: 0 | P108: =SUM(N108:O108) -> 3745.4405
A110: Direct Costs Total for Outcome 4 | G110: =SUM(G104:G108) -> 16393.84 | I110: =SUM(I104:I108) -> 9970.3703 | K110: =SUM(K104:K108) -> 12533.505 | M110: =SUM(M104:M108) -> 9902.7089 | N110: =G110+I110+K110+M110 -> 48800.424 | O110: =SUM(O104:O108) -> 0 | P110: =SUM(N110:O110) -> 48800.424
A112: Total Indirect Costs (De Minimis 10%) for Outcome 4 | C112: Indirect Charges | F112: 0.1 | G112: =(G110)*F112 -> 1639.384 | I112: =(I110)*F112 -> 997.03703 | K112: =(K110)*F112 -> 1253.3505 | M112: =(M110)*F112 -> 990.27089 | N112: =SUM(G112+I112+K112+M112) -> 4880.0424 | O112: 0 | P112: =SUM(N112:O112) -> 4880.0424
A114: Subtotal Outcome 4 | G114: =SUM(G110:G112) -> 18033.224 | I114: =SUM(I110:I112) -> 10967.407 | K114: =SUM(K110:K112) -> 13786.855 | M114: =SUM(M110:M112) -> 10892.98 | N114: =G114+I114+K114+M114 -> 53680.466 | O114: =SUM(O110:O112) -> 0 | P114: =SUM(N114:O114) -> 53680.466
A115: 5: Monitoring, Evaluation, and Collection of Reliable Data
A116: Activities/Costs
A117: Personnel & Fringe (5% of Direct Labor line item) | C117: M&E | D117: Unit | E117: =G23 -> 69769.2 | F117: 0.05 | G117: =E117*F117 -> 3488.46 | H117: =I23 -> 37015.852 | I117: =H117*F117 -> 1850.7926 | J117: =K23 -> 36031.474 | K117: =J117*F117 -> 1801.5737 | L117: =M23 -> 24741.612 | M117: =L117*F117 -> 1237.0806 | N117: =G117+I117+K117+M117 -> 8377.9069 | O117: 0 | P117: =SUM(N117:O117) -> 8377.9069
A118: Office Expenses 5% | C118: M&E | D118: Unit | E118: =G37 -> 12200 | F118: 0.05 | G118: =E118*F118 -> 610 | H118: =I37 -> 7686 | I118: =H118*F118 -> 384.3 | J118: =K37 -> 8070.3 | K118: =J118*F118 -> 403.515 | L118: =M37 -> 5649.21 | M118: =L118*F118 -> 282.4605 | N118: =G118+I118+K118+M118 -> 1680.2755 | O118: 0 | P118: =SUM(N118:O118) -> 1680.2755
A119: 5.7.3.1 Collection of Reliable Data and Processing of Monitoring Data
A120: Lodging and M&IE Field verification and data collection visits | C120: M&E | D120: Day | E120: 0 | F120: 108 | G120: =F120*E120 -> 0 | H120: 12 | I120: =(H120*F120)*$B$6 -> 1360.8 | J120: 15 | K120: =J120*F120*$B$6*$B$6 -> 1786.05 | L120: 15 | M120: =L120*F120*$B$6*$B$6*$B$6 -> 1875.3525 | N120: =G120+I120+K120+M120 -> 5022.2025 | O120: 0 | P120: =SUM(N120:O120) -> 5022.2025
A121: Local transportation - Field verification and data collection visits | C121: M&E | D121: Trip | E121: 0 | F121: 46 | G121: =F121*E121 -> 0 | H121: 8 | I121: =(H121*F121)*$B$6 -> 386.4 | J121: 10 | K121: =J121*F121*$B$6*$B$6 -> 507.15 | L121: 10 | M121: =L121*F121*$B$6*$B$6*$B$6 -> 532.5075 | N121: =G121+I121+K121+M121 -> 1426.0575 | O121: 0 | P121: =SUM(N121:O121) -> 1426.0575
A122: Data collection materials and printing | C122: M&E | D122: Month | E122: 0 | F122: 150 | G122: =F122*E122 -> 0 | H122: 6 | I122: =(H122*F122)*$B$6 -> 945 | J122: 6 | K122: =J122*F122*$B$6*$B$6 -> 992.25 | L122: 6 | M122: =L122*F122*$B$6*$B$6*$B$6 -> 1041.8625 | N122: =G122+I122+K122+M122 -> 2979.1125 | O122: 0 | P122: =SUM(N122:O122) -> 2979.1125
...

Sheet SF-424 Cost Categories
B2: Category | C2: TOTAL USDOL
B3: Salaries | C3: =SUMIF(Category,B3,TotalDOL) -> 1152187.4
B4: Fringe Benefits | C4: =SUMIF(Category,"Fringe Benefits",TotalDOL) -> 536153
B5: Travel | C5: =SUMIF(Category,"Travel",TotalDOL) -> 105008.56
B6: Equipment | C6: =SUMIF(Category,"Equipment",TotalDOL) -> 0
B7: Supplies | C7: =SUMIF(Category,"Supplies",TotalDOL) -> 278250.22
B8: Contractual | C8: =SUMIF(Category,"Contractual",TotalDOL) -> 1472575.7
B9: Other Direct Charges | C9: =SUMIF(Category,"Other",TotalDOL) -> 315985.65
B10: Indirect Charges | C10: =SUMIF(Category,"Indirect Charges",TotalDOL) -> 1114694.1
B12: TOTAL | C12: =SUM(C3:C10) -> 4974854.7
