Workbook
Name agentfee: #REF!
Name agentfee: Assumptions!$D$55
Name avrent: [1]Assumptions!$D$111
Name avrent: #REF!
Name avrent: Assumptions!$D$98
Name Category: #REF!
Name Check25: 'SF424'!$A$5
Name Check26: 'SF424'!$A$6
Name Check27: 'SF424'!$A$7
Name Check28: 'SF424'!$D$5
Name Check29: 'SF424'!$D$6
Name Check30: 'SF424'!$D$7
Name Check32: 'SF424'!$A$126
Name Check33: 'SF424'!$A$127
Name Check35: 'SF424'!$A$129
Name Check36: 'SF424'!$A$131
Name coffee: [1]Assumptions!$D$108
Name coffee: #REF!
Name coffee: Assumptions!$D$95
Name consairfare: #REF!
Name consairfare: Assumptions!$D$80
Name consground: #REF!
Name consground: Assumptions!$D$81
Name conslodg: #REF!
Name conslodg: Assumptions!$D$82
Name consmeals: #REF!
Name consmeals: Assumptions!$D$83
Name consmisc: #REF!
Name consmisc: Assumptions!$D$84
Name DL_Country: '[2]Line-Item Budget'!#REF!
Name DL_Country: #REF!
Name DL_TotalDOL: #REF!
Name Dropdown1: 'SF424'!$G$5
Name Dropdown2: 'SF424'!#REF!
Name EQ_Country: '[2]Line-Item Budget'!#REF!
Name EQ_Country: #REF!
Name EQ_TotalDOL: '[2]Line-Item Budget'!#REF!
Name EQ_TotalDOL: #REF!
Name er: #REF!
Name er: Assumptions!$B$17
Name ground: #REF!
Name ground: Assumptions!$D$59
Name guideprint: Assumptions!$D$103
Name inmuniz: #REF!
Name inmuniz: Assumptions!$D$57
Name intairfare: #REF!
Name intairfare: Assumptions!$D$52
Name intcalls: #REF!
Name intcalls: Assumptions!#REF!
Name intcons: #REF!
Name intcons: Assumptions!$D$77
Name intmisc: #REF!
Name intmisc: Assumptions!$D$60
Name livingq: #REF!
Name livingq: Assumptions!#REF!
Name Local_transport_part: [2]Assumptions!$B$10:$D$10
Name localairfare: #REF!
Name localairfare: Assumptions!$D$73
Name localcons: #REF!
Name localcons: Assumptions!$D$79

Sheet AgroJusto Budget
C1: Project Line-Item Budget
C2: Partners of the Americas
C3: Project to Improve Adherence to International Labor Standards in the Agricultural Sector in Ecuador Improve Adherence to International Labor Standards in the Agricultural Sector in Ecuador
C4: 48 Months
C5: Cost Assumptions
C6: Inflation - US Based Goods/Services | D6: 1.03
C7: Inflation - Locally Purchased Goods/Services | D7: 1.04
C8: Merit Based Increases for HO & Field Staff | D8: 1.05
A10: Activity Code | B10: Account Code | C10: BUDGET ITEM | D10: CATEGORY | E10: LOE | F10: UNIT | G10: # of Units | H10: RATE / UNIT | I10: Year 1 | J10: # of Units | K10: Year 2 | L10: # of Units | M10: Year 3 | N10: # of Units | O10: Year 4 | P10: TOTAL DOL | Q10: TOTAL COST SHARING | R10: PROJECT GRAND TOTAL
C11: Personnel
C12: Key Personnel
A13: PERSNL-PD | B13: 70000 | C13: Project Director (100%) - Alexis Naranjo | D13: Salaries | E13: 1 | F13: Month | G13: 11 | H13: 6000 | I13: =G13*H13*E13 -> 66000 | J13: 12 | K13: =J13*H13*$D$8 -> 75600 | L13: 12 | M13: =(L13*H13*$D$8*$D$8) -> 79380 | N13: 12 | O13: =N13*H13*$D$8*$D$8*$D$8 -> 83349 | P13: =SUM(I13+K13+M13+O13) -> 304329 | Q13: 0 | R13: =SUM(P13:Q13) -> 304329
A14: PERSNL-M&E | B14: 70000 | C14: Monitoring and Evaluation (M&E) Officer (100%) - Mónica Rentería | D14: Salaries | E14: 1 | F14: Month | G14: 11 | H14: =40000/12 -> 3333.3333 | I14: =G14*H14*E14 -> 36666.667 | J14: 12 | K14: =J14*H14*$D$8 -> 42000 | L14: 12 | M14: =(L14*H14*$D$8*$D$8) -> 44100 | N14: 12 | O14: =N14*H14*$D$8*$D$8*$D$8 -> 46305 | P14: =SUM(I14+K14+M14+O14) -> 169071.67 | Q14: 0 | R14: =SUM(P14:Q14) -> 169071.67
C15: Other Professional Personnel
A16: PERSNL-PSL | B16: 70000 | C16: Public Sector Liaison (100%)- Luis Almagor | D16: Salaries | E16: 1 | F16: Month | G16: 11 | H16: 2400 | I16: =G16*H16*E16 -> 26400 | J16: 12 | K16: =J16*H16*$D$8 -> 30240 | L16: 12 | M16: =(L16*H16*$D$8*$D$8) -> 31752 | N16: 8 | O16: =N16*H16*$D$8*$D$8*$D$8 -> 22226.4 | P16: =SUM(I16+K16+M16+O16) -> 110618.4 | Q16: 0 | R16: =SUM(P16:Q16) -> 110618.4
A17: PERSNL-COM | B17: 70000 | C17: Communications Specialist (100%) - Emilia Bayas | D17: Salaries | E17: 1 | F17: Month | G17: 11 | H17: 1800 | I17: =G17*H17*E17 -> 19800 | J17: 12 | K17: =J17*H17*$D$8 -> 22680 | L17: 12 | M17: =(L17*H17*$D$8*$D$8) -> 23814 | N17: 8 | O17: =N17*H17*$D$8*$D$8*$D$8 -> 16669.8 | P17: =SUM(I17+K17+M17+O17) -> 82963.8 | Q17: 0 | R17: =SUM(P17:Q17) -> 82963.8
A18: PERSNL-SAF | B18: 70000 | C18: Occupational Safety and Health Specialist (100%) - César Ávila | D18: Salaries | E18: 1 | F18: Month | G18: 11 | H18: 2400 | I18: =G18*H18*E18 -> 26400 | J18: 12 | K18: =J18*H18*$D$8 -> 30240 | L18: 12 | M18: =(L18*H18*$D$8*$D$8) -> 31752 | N18: 8 | O18: =N18*H18*$D$8*$D$8*$D$8 -> 22226.4 | P18: =SUM(I18+K18+M18+O18) -> 110618.4 | Q18: 0 | R18: =SUM(P18:Q18) -> 110618.4
A19: PERSNL-F&A | B19: 70000 | C19: Finance & Administration Director (100%) | D19: Salaries | E19: 1 | F19: Month | G19: 5 | H19: 3400 | I19: =G19*H19*E19 -> 17000 | J19: 12 | K19: =J19*H19*$D$8 -> 42840 | L19: 12 | M19: =(L19*H19*$D$8*$D$8) -> 44982 | N19: 12 | O19: =N19*H19*$D$8*$D$8*$D$8 -> 47231.1 | P19: =SUM(I19+K19+M19+O19) -> 152053.1 | Q19: 0 | R19: =SUM(P19:Q19) -> 152053.1
A20: PERSNL-OPS | B20: 70000 | C20: Operations Coordinator (100%) | D20: Salaries | E20: 1 | F20: Month | G20: 3 | H20: 2000 | I20: =G20*H20*E20 -> 6000 | J20: 12 | K20: =J20*H20*$D$8 -> 25200 | L20: 12 | M20: =(L20*H20*$D$8*$D$8) -> 26460 | N20: 8 | O20: =N20*H20*$D$8*$D$8*$D$8 -> 18522 | P20: =SUM(I20+K20+M20+O20) -> 76182 | Q20: 0 | R20: =SUM(P20:Q20) -> 76182
A21: PERSNL-RCC | B21: 70000 | C21: Regional Coordinator 1, Cotopaxi (100%) | D21: Salaries | E21: 1 | F21: Month | G21: 3 | H21: =15000/12-62 -> 1188 | I21: =G21*H21*E21 -> 3564 | J21: 12 | K21: =J21*H21*$D$8 -> 14968.8 | L21: 12 | M21: =(L21*H21*$D$8*$D$8) -> 15717.24 | N21: 8 | O21: =N21*H21*$D$8*$D$8*$D$8 -> 11002.068 | P21: =SUM(I21+K21+M21+O21) -> 45252.108 | Q21: 0 | R21: =SUM(P21:Q21) -> 45252.108
A22: PERSNL-RCO | B22: 70000 | C22: Regional Coordinator 2, El Oro (100%) | D22: Salaries | E22: 1 | F22: Month | G22: 3 | H22: =15000/12-62 -> 1188 | I22: =G22*H22*E22 -> 3564 | J22: 12 | K22: =J22*H22*$D$8 -> 14968.8 | L22: 12 | M22: =(L22*H22*$D$8*$D$8) -> 15717.24 | N22: 8 | O22: =N22*H22*$D$8*$D$8*$D$8 -> 11002.068 | P22: =SUM(I22+K22+M22+O22) -> 45252.108 | Q22: 0 | R22: =SUM(P22:Q22) -> 45252.108
C23: Home Office Support | M23: =(L23*H23*$D$6*$D$7) -> 0 | O23: =N23*H23*$D$6*$D$7*$D$8 -> 0
A24: PERSNL-PM | B24: 50000 | C24: Project Manager (30%) | D24: Salaries | E24: 0.3 | F24: Month | G24: 11 | H24: 10729 | I24: =G24*H24*E24 -> 35405.7 | J24: 12 | K24: =J24*H24*$D$8*E24 -> 40555.62 | L24: 12 | M24: =(L24*H24*$D$8*$D$8)*E24 -> 42583.401 | N24: 12 | O24: =(N24*H24*$D$8*$D$8*$D$8)*E24 -> 44712.571 | P24: =SUM(I24+K24+M24+O24) -> 163257.29 | Q24: 0 | R24: =SUM(P24:Q24) -> 163257.29
A25: PERSNL-PO | B25: 50000 | C25: 2 Program Officers (20%) | D25: Salaries | E25: 0.2 | F25: Month | G25: 11 | H25: 10105 | I25: =G25*H25*E25 -> 22231 | J25: 12 | K25: =J25*H25*$D$8*E25 -> 25464.6 | L25: 12 | M25: =(L25*H25*$D$8*$D$8)*E25 -> 26737.83 | N25: 12 | O25: =(N25*H25*$D$8*$D$8*$D$8)*E25 -> 28074.722 | P25: =SUM(I25+K25+M25+O25) -> 102508.15 | Q25: 0 | R25: =SUM(P25:Q25) -> 102508.15
C26: Total Personnel | I26: =SUM(I13:I25) -> 263031.37 | K26: =SUM(K13:K25) -> 364757.82 | M26: =SUM(M13:M25) -> 382995.71 | O26: =SUM(O13:O25) -> 351321.13 | P26: =SUM(P13:P25) -> 1362106 | Q26: =SUM(Q13:Q25) -> 0 | R26: =SUM(P26:Q26) -> 1362106
C27: Fringe Benefits
C29: Fringe Benefits
A30: FRINGE-EC | B30: 70015 | C30: Fringe benefits - Ecuador | D30: Fringe Benefits | F30: Month | H30: 0.4333 | I30: =SUM(I13:I22)*$H30 -> 88997.509 | K30: =SUM(K13:K22)*$H30 -> 129443 | M30: =SUM(M13:M22)*$H30 -> 135915.15 | O30: =SUM(O13:O22)*$H30 -> 120688.71 | P30: =SUM(I30+K30+M30+O30) -> 475044.37 | Q30: 0 | R30: =SUM(P30:Q30) -> 475044.37
A31: FRINGE | B31: 50900 | C31: Fringe benefits - Home Office Support | D31: Fringe Benefits | F31: Month | H31: 0.2347 | I31: =SUM(I24:I25)*$H$31 -> 13527.333 | K31: =SUM(K24:K25)*$H$31 -> 15494.946 | M31: =SUM(M24:M25)*$H$31 -> 16269.693 | O31: =SUM(O24:O25)*$H$31 -> 17083.178 | P31: =SUM(I31+K31+M31+O31) -> 62375.15 | Q31: 0 | R31: =SUM(P31:Q31) -> 62375.15
C33: Total Fringe Benefits | I33: =SUM(I30:I32) -> 102524.84 | K33: =SUM(K30:K32) -> 144937.95 | M33: =SUM(M30:M32) -> 152184.85 | O33: =SUM(O30:O32) -> 137771.89 | P33: =SUM(P30:P32) -> 537419.52 | Q33: =SUM(Q31:Q31) -> 0 | R33: =SUM(R30:R32) -> 537419.52
C34: Travel
C35: T1: Post-award Meeting with ILAB
A36: EC.T1.A | B36: 86040 | C36: Airfare - Ecuador-DC | D36: Travel | F36: Trip | H36: 650 | I36: =G36*H36 -> 0 | J36: 2 | K36: =J36*H36*$D$7 -> 1352 | L36: 0 | M36: =L36*H36*$D$7*$D$7 -> 0 | N36: 0 | O36: =N36*H36*$D$7*$D$7*$D$7 -> 0 | P36: =SUM(I36+K36+M36+O36) -> 1352 | Q36: - | R36: =SUM(P36:Q36) -> 1352
A37: EC.T1.B | B37: 86030 (Lodging)/ 86050 (M&IE) | C37: Lodging and M&IE in DC | D37: Travel | F37: Day | H37: =(258+79)*90% -> 303.3 | I37: =G37*H37 -> 0 | J37: 10 | K37: =J37*H37*$D$7 -> 3154.32 | L37: 0 | M37: =L37*H37*$D$7*$D$7 -> 0 | N37: 0 | O37: =N37*H37*$D$7*$D$7*$D$7 -> 0 | P37: =SUM(I37+K37+M37+O37) -> 3154.32 | Q37: - | R37: =SUM(P37:Q37) -> 3154.32
A38: EC.T1.C | B38: 86000 | C38: Local transportation in DC | D38: Travel | F38: Day | H38: 60 | I38: =G38*H38 -> 0 | J38: 10 | K38: =J38*H38*$D$7 -> 624 | L38: 0 | M38: =L38*H38*$D$7*$D$7 -> 0 | N38: 0 | O38: =N38*H38*$D$7*$D$7*$D$7 -> 0 | P38: =SUM(I38+K38+M38+O38) -> 624 | Q38: - | R38: =SUM(P38:Q38) -> 624
A39: EC.T1.D | B39: 86050 | C39: U.S. Visa Fees | D39: Travel | F39: Trip | H39: 160 | I39: =G39*H39 -> 0 | J39: 2 | K39: =J39*H39*$D$7 -> 332.8 | L39: 0 | M39: =L39*H39*$D$7*$D$7 -> 0 | N39: 0 | O39: =N39*H39*$D$7*$D$7*$D$7 -> 0 | P39: =SUM(I39+K39+M39+O39) -> 332.8 | Q39: - | R39: =SUM(P39:Q39) -> 332.8
C40: T2: Field Personnel Annual Visits with ILAB
A41: EC.T2.A | B41: 86040 | C41: Airfare - Ecuador-DC | D41: Travel | F41: Trip | G41: 2 | H41: 650 | I41: =G41*H41 -> 1300 | J41: 2 | K41: =J41*H41*$D$7 -> 1352 | L41: 2 | M41: =L41*H41*$D$7*$D$7 -> 1406.08 | N41: 2 | O41: =N41*H41*$D$7*$D$7*$D$7 -> 1462.3232 | P41: =SUM(I41+K41+M41+O41) -> 5520.4032 | Q41: - | R41: =SUM(P41:Q41) -> 5520.4032
A42: EC.T2.B | B42: 86030 (Lodging)/ 86050 (M&IE) | C42: Lodging and M&IE in DC | D42: Travel | F42: Day | G42: 5 | H42: =(258+79)*90% -> 303.3 | I42: =G42*H42 -> 1516.5 | J42: 10 | K42: =J42*H42*$D$7 -> 3154.32 | L42: 10 | M42: =L42*H42*$D$7*$D$7 -> 3280.4928 | N42: 10 | O42: =N42*H42*$D$7*$D$7*$D$7 -> 3411.7125 | P42: =SUM(I42+K42+M42+O42) -> 11363.025 | Q42: - | R42: =SUM(P42:Q42) -> 11363.025
A43: EC.T2.C | B43: 86000 | C43: Local transportation in DC | D43: Travel | F43: Day | G43: 5 | H43: 60 | I43: =G43*H43 -> 300 | J43: 10 | K43: =J43*H43*$D$7 -> 624 | L43: 10 | M43: =L43*H43*$D$7*$D$7 -> 648.96 | N43: 10 | O43: =N43*H43*$D$7*$D$7*$D$7 -> 674.9184 | P43: =SUM(I43+K43+M43+O43) -> 2247.8784 | Q43: - | R43: =SUM(P43:Q43) -> 2247.8784
C44: T3: Home Support Annual Visits to Field
A45: EC.T3.A | B45: 86040 | C45: Airfare - DC - Ecuador | D45: Travel | F45: Trip | G45: 4 | H45: 650 | I45: =G45*H45 -> 2600 | J45: 1 | K45: =J45*H45*$D$7 -> 676 | L45: 1 | M45: =L45*H45*$D$7*$D$7 -> 703.04 | N45: 1 | O45: =N45*H45*$D$7*$D$7*$D$7 -> 731.1616 | P45: =SUM(I45+K45+M45+O45) -> 4710.2016 | Q45: - | R45: =SUM(P45:Q45) -> 4710.2016
A46: EC.T3.B | B46: 86030 (Lodging)/ 86050 (M&IE) | C46: Lodging and M&IE in Quito | D46: Travel | F46: Day | G46: 20 | H46: =(295)*90% -> 265.5 | I46: =G46*H46 -> 5310 | J46: 7 | K46: =J46*H46*$D$7 -> 1932.84 | L46: 7 | M46: =L46*H46*$D$7*$D$7 -> 2010.1536 | N46: 7 | O46: =N46*H46*$D$7*$D$7*$D$7 -> 2090.5597 | P46: =SUM(I46+K46+M46+O46) -> 11343.553 | Q46: - | R46: =SUM(P46:Q46) -> 11343.553
A47: EC.T3.C | B47: 86000 | C47: Local transportation in Quito | D47: Travel | F47: Day | G47: 20 | H47: 60 | I47: =G47*H47 -> 1200 | J47: 7 | K47: =J47*H47*$D$7 -> 436.8 | L47: 7 | M47: =L47*H47*$D$7*$D$7 -> 454.272 | N47: 7 | O47: =N47*H47*$D$7*$D$7*$D$7 -> 472.44288 | P47: =SUM(I47+K47+M47+O47) -> 2563.5149 | Q47: - | R47: =SUM(P47:Q47) -> 2563.5149
A48: EC.T3.D | B48: 86050 | C48: Ecuador Visa Fees | D48: Travel | F48: Trip | G48: 1 | H48: 160 | I48: =G48*H48 -> 160 | J48: 1 | K48: =J48*H48*$D$7 -> 166.4 | L48: 1 | M48: =L48*H48*$D$7*$D$7 -> 173.056 | N48: 1 | O48: =N48*H48*$D$7*$D$7*$D$7 -> 179.97824 | P48: =SUM(I48+K48+M48+O48) -> 679.43424 | Q48: - | R48: =SUM(P48:Q48) -> 679.43424
A49: EC.T4.A | B49: 86000 (Transport)/ 86030 (Lodging)/ 86050 (M&IE) | C49: T4: Domestic Travel to Field (See Travel Detail Tab) | I49: =+' Activities Detail'!L280 -> 0 | K49: =+' Activities Detail'!O280 -> 51812.8 | M49: =+' Activities Detail'!R280 -> 35524.07 | O49: =+' Activities Detail'!U280 -> 55310.688 | P49: =SUM(I49+K49+M49+O49) -> 142647.56 | R49: =SUM(P49:Q49) -> 142647.56
C51: Total Travel | I51: =SUM(I36:I49) -> 12386.5 | K51: =SUM(K36:K49) -> 65618.28 | M51: =SUM(M36:M49) -> 44200.125 | O51: =SUM(O36:O49) -> 64333.784 | P51: =SUM(P36:P49) -> 186538.69 | Q51: =SUM(Q36:Q49) -> 0 | R51: =SUM(P51:Q51) -> 186538.69
C52: Equipment
C53: None | D53: Equipment | F53: Unit | J53: 0 | K53: =J53*H53*Assumptions!$C$19 -> 0 | L53: 0 | M53: =L53*H53*Assumptions!$C$19*Assumptions!$C$19 -> 0 | N53: 0 | O53: =N53*H53*Assumptions!$C$19*Assumptions!$C$19*Assumptions!$C$19 -> 0 | P53: =SUM(I53+K53+M53+O53) -> 0 | Q53: 0 | R53: =SUM(P53:Q53) -> 0
C55: Total Equipment | I55: =SUM(I53) -> 0 | K55: =SUM(K53) -> 0 | M55: =SUM(M53) -> 0 | O55: =SUM(O53) -> 0 | P55: =SUM(P53) -> 0 | Q55: =SUM(Q53) -> 0 | R55: =SUM(P55:Q55) -> 0
C56: Supplies
A57: LAPTOP | B57: 82401 | C57: Laptop computers & software | D57: Supplies | F57: Unit | G57: 7 | H57: =1254.6 -> 1254.6 | I57: =G57*H57 -> 8782.2 | K57: =J57*H57*$D$7 -> 0 | L57: 0 | M57: =L57*H57*$D$7*$D$7 -> 0 | N57: 0 | O57: =N57*H57*$D$7*$D$7*$D$7 -> 0 | P57: =SUM(I57+K57+M57+O57) -> 8782.2 | Q57: 0 | R57: =SUM(P57:Q57) -> 8782.2
A58: SUPPLIES | B58: 82401 | C58: Office supplies | D58: Supplies | F58: Month | G58: 9 | H58: 125 | I58: =H58*G58 -> 1125 | J58: 12 | K58: =J58*H58*$D$7 -> 1560 | L58: 12 | M58: =L58*H58*$D$7*$D$7 -> 1622.4 | N58: 12 | O58: =N58*H58*$D$7*$D$7*$D$7 -> 1687.296 | P58: =SUM(I58+K58+M58+O58) -> 5994.696 | Q58: 0 | R58: =SUM(P58:Q58) -> 5994.696
C60: Total Supplies | I60: =SUM(I57:I58) -> 9907.2 | K60: =SUM(K57:K58) -> 1560 | M60: =SUM(M57:M58) -> 1622.4 | O60: =SUM(O57:O58) -> 1687.296 | P60: =SUM(P57:P58) -> 14776.896 | Q60: =SUM(Q57:Q58) -> 0 | R60: =SUM(P60:Q60) -> 14776.896
C61: Contractual
A63: EXPOFLOR | B63: 89050 | C63: Expoflores | D63: Contractual | F63: Contract | G63: 1 | I63: 10000 | J63: 1 | K63: 20000 | L63: 1 | M63: 20000 | N63: 1 | O63: 10000 | P63: =SUM(I63+K63+M63+O63) -> 60000 | R63: =SUM(P63:Q63) -> 60000
A64: CLAC | B64: 89050 | C64: CLAC | D64: Contractual | F64: Contract | G64: 1 | J64: 1 | K64: 7500 | L64: 1 | M64: 7500 | N64: 1 | O64: 5000 | P64: =SUM(I64+K64+M64+O64) -> 20000 | R64: =SUM(P64:Q64) -> 20000
A65: ASTAC | B65: 89050 | C65: ASTAC | D65: Contractual | F65: Contract | G65: 1 | J65: 1 | K65: 10000 | L65: 1 | M65: 20000 | N65: 1 | O65: 25000 | P65: =SUM(I65+K65+M65+O65) -> 55000 | R65: 55000
A66: ASOPRO | B66: 89050 | C66: ASOPROTRABAN | D66: Contractual | F66: Contract | G66: 1 | J66: 1 | K66: 7500 | L66: 1 | M66: 10000 | N66: 1 | O66: 17500 | P66: =SUM(I66+K66+M66+O66) -> 35000 | R66: =SUM(P66:Q66) -> 35000
A67: BANABIO | B67: 89050 | C67: BANABIO | D67: Contractual | F67: Contract | G67: 1 | K67: 15000 | M67: 15000 | N67: 1 | O67: 10000 | P67: =SUM(I67+K67+M67+O67) -> 40000 | R67: =SUM(P67:Q67) -> 40000
A68: SUBINDES | B68: 89050 | C68: INDES | D68: Contractual | F68: Contract | G68: 1 | I68: 97651 | J68: 1 | K68: 245097 | L68: 1 | M68: 244066 | N68: 1 | O68: 140436 | P68: =+I68+K68+M68+O68 -> 727250 | R68: =P68 -> 727250
C69: INDES - Field Verification & Data Collection Expenses (M&E) | D69: Contractual | F69: Contract | G69: 1 | I69: 905 | J69: 1 | K69: 18715 | L69: 1 | M69: 20681 | N69: 1 | O69: 16199 | P69: =I69+K69+M69+O69 -> 56500 | R69: =P69 -> 56500
C70: Total Contractual | I70: =SUM(I62:I69) -> 108556 | K70: =SUM(K62:K69) -> 323812 | M70: =SUM(M62:M69) -> 337247 | O70: =SUM(O62:O69) -> 224135 | P70: =SUM(P62:P69) -> 993750 | Q70: =SUM(Q62:Q68) -> 0 | R70: =SUM(R62:R69) -> 993750
C71: Other Direct Costs
C72: Project Office
A73: BANK FEES | B73: 90900 | C73: Banking and cash handling fees | D73: Office Expenses | F73: Month | G73: 5 | H73: 50 | I73: =G73*H73 -> 250 | J73: 12 | K73: =J73*H73*$D$7 -> 624 | L73: 12 | M73: =L73*H73*$D$7*$D$7 -> 648.96 | N73: 12 | O73: =N73*H73*$D$7*$D$7*$D$7 -> 674.9184 | P73: =SUM(I73+K73+M73+O73) -> 2197.8784 | Q73: 0 | R73: =SUM(P73:Q73) -> 2197.8784
A74: COURIER | B74: 82350 | C74: Courier fees/services | D74: Office Expenses | F74: Year | G74: 1 | H74: 70 | I74: =G74*H74 -> 70 | J74: 1 | K74: =J74*H74*$D$7 -> 72.8 | L74: 1 | M74: =L74*H74*$D$7*$D$7 -> 75.712 | N74: 1 | O74: =N74*H74*$D$7*$D$7*$D$7 -> 78.74048 | P74: =SUM(I74+K74+M74+O74) -> 297.25248 | Q74: 0 | R74: =SUM(P74:Q74) -> 297.25248
A75: RECRUIT | B75: 90450 | C75: Recruitment/Procurement Advertising | D75: Office Expenses | F75: Per position | G75: 4 | I75: =G75*H75 -> 0 | K75: =J75*H75*$D$7 -> 0 | M75: =L75*H75*$D$7*$D$7 -> 0 | O75: =N75*H75*$D$7*$D$7*$D$7 -> 0 | P75: =SUM(I75+K75+M75+O75) -> 0 | Q75: 0 | R75: =SUM(P75:Q75) -> 0
A76: COMM | B76: 82030 | C76: Communications Costs (Data) | D76: Office Expenses | F76: Month | G76: 9 | H76: 150 | I76: =G76*H76 -> 1350 | J76: 12 | K76: =J76*H76*$D$7 -> 1872 | L76: 12 | M76: =L76*H76*$D$7*$D$7 -> 1946.88 | N76: 12 | O76: =N76*H76*$D$7*$D$7*$D$7 -> 2024.7552 | P76: =SUM(I76+K76+M76+O76) -> 7193.6352 | Q76: 0 | R76: =SUM(P76:Q76) -> 7193.6352
A77: RENT & UT | B77: 85180 | C77: Coworking office space (includes utilities, Wi-Fi, coffee) | D77: Office Expenses | F77: Month | G77: 6 | H77: 1140 | I77: =G77*H77 -> 6840 | J77: 12 | K77: =J77*H77*$D$7 -> 14227.2 | L77: 12 | M77: =L77*H77*$D$7*$D$7 -> 14796.288 | N77: 12 | O77: =N77*H77*$D$7*$D$7*$D$7 -> 15388.14 | P77: =SUM(I77+K77+M77+O77) -> 51251.628 | Q77: 0 | R77: =SUM(P77:Q77) -> 51251.628
A78: PROP&LIAB | B78: 89500 | C78: Property and liability insurance | D78: Office Expenses | F78: Year | G78: 1 | H78: 250 | I78: =G78*H78 -> 250 | J78: 1 | K78: =J78*H78*$D$7 -> 260 | L78: 1 | M78: =L78*H78*$D$7*$D$7 -> 270.4 | N78: 1 | O78: =N78*H78*$D$7*$D$7*$D$7 -> 281.216 | P78: =SUM(I78+K78+M78+O78) -> 1061.616 | Q78: 0 | R78: =SUM(P78:Q78) -> 1061.616
A79: LEGAL | B79: 90100 | C79: Legal fees | D79: Office Expenses | F79: Year | G79: 0 | H79: 1200 | I79: 5936 | J79: 1 | K79: =J79*H79*$D$7 -> 1248 | L79: 1 | M79: =L79*H79*$D$7*$D$7 -> 1297.92 | N79: 1 | O79: =N79*H79*$D$7*$D$7*$D$7 -> 1349.8368 | P79: =SUM(I79+K79+M79+O79) -> 9831.7568 | Q79: 0 | R79: =SUM(P79:Q79) -> 9831.7568
A80: PAYROLL | B80: 81030 | C80: Payroll Processing | D80: Office Expenses | F80: Month | G80: 3 | H80: 350 | I80: =G80*H80 -> 1050 | J80: 12 | K80: =J80*H80*$D$7 -> 4368 | L80: 12 | M80: =L80*H80*$D$7*$D$7 -> 4542.72 | N80: 12 | O80: =N80*H80*$D$7*$D$7*$D$7 -> 4724.4288 | P80: =SUM(I80+K80+M80+O80) -> 14685.149 | Q80: - | R80: =SUM(P80:Q80) -> 14685.149
A81: SUBSCRIPT | B81: 89400 | C81: HR platform for timekeeping and expense reporting | D81: Office Expenses | F81: Month | G81: 9 | H81: 108 | I81: =G81*H81 -> 972 | J81: 12 | K81: =J81*H81*$D$7 -> 1347.84 | L81: 12 | M81: =L81*H81*$D$7*$D$7 -> 1401.7536 | N81: 9 | O81: =N81*H81*$D$7*$D$7*$D$7 -> 1093.3678 | P81: =SUM(I81+K81+M81+O81) -> 4814.9614 | Q81: 0 | R81: =SUM(P81:Q81) -> 4814.9614
A82: SUBSCRIPT | B82: 89400 | C82: Zoom license and platform subscriptions | D82: Office Expenses | F82: Year | G82: 1 | H82: 1650 | I82: =G82*H82 -> 1650 | J82: 1 | K82: =J82*H82*$D$7 -> 1716 | L82: 1 | M82: =L82*H82*$D$7*$D$7 -> 1784.64 | N82: 1 | O82: =N82*H82*$D$7*$D$7*$D$7 -> 1856.0256 | P82: =SUM(I82+K82+M82+O82) -> 7006.6656 | Q82: 0 | R82: =SUM(P82:Q82) -> 7006.6656
A83: SECURITY | B83: 86110 | C83: Security Provider | D83: Office Expenses | F83: Month | G83: 1 | H83: 37758 | I83: =G83*H83 -> 37758 | K83: =J83*H83*$D$7 -> 0 | M83: =L83*H83*$D$7*$D$7 -> 0 | O83: =N83*H83*$D$7*$D$7*$D$7 -> 0 | P83: =SUM(I83+K83+M83+O83) -> 37758 | Q83: 0 | R83: =SUM(P83:Q83) -> 37758
A84: VISUALCOM | B84: 89400 | C84: Visual Asset Communications | D84: Office Expenses | F84: Year | G84: 1 | H84: 5000 | I84: =G84*H84 -> 5000 | J84: 1 | K84: 15000 | L84: 1 | M84: 10000 | N84: 1 | O84: 10000 | P84: =SUM(I84+K84+M84+O84) -> 40000 | Q84: 0 | R84: =SUM(P84:Q84) -> 40000
C85: Subtotal Project Office, Audit, Communications | I85: =SUM(I73:I84) -> 61126 | K85: =SUM(K73:K84) -> 40735.84 | M85: =SUM(M73:M84) -> 36765.274 | O85: =SUM(O73:O84) -> 37471.429 | P85: =SUM(P73:P84) -> 176098.54 | R85: =SUM(R73:R84) -> 176098.54
C86: Outcome 1
C87: Activity 1.1. Assess labor law enforcement institutions, processes, and services: challenges and opportunities for action to address child labor and forced labor | D87: Outcome1
C88: Activity 1.2. Strengthen intersectoral coordination by re-invigorating referral mechanisms and strengthening Consejos and Juntas: | D88: Outcome1 | I88: =+' Activities Detail'!L20 -> 0 | K88: =+' Activities Detail'!O20 -> 1435.2 | M88: =+' Activities Detail'!R20 -> 0 | O88: =+' Activities Detail'!U20 -> 0 | P88: =SUM(I88+K88+M88+O88) -> 1435.2 | R88: =SUM(P88:Q88) -> 1435.2
C89: Activity 1.3. Develop government capacity building strategy applying assessment results | D89: Outcome1 | I89: =+' Activities Detail'!L49 -> 0 | K89: =+' Activities Detail'!O49 -> 10400 | M89: =+' Activities Detail'!R49 -> 0 | O89: =+' Activities Detail'!U49 -> 0 | P89: =SUM(I89+K89+M89+O89) -> 10400 | R89: =SUM(P89:Q89) -> 10400
C90: Activity 1.4. Develop, deliver, and institutionalize tailored capacity building for government officials: | D90: Outcome1 | I90: =+' Activities Detail'!L81 -> 0 | K90: =+' Activities Detail'!O64 -> 7280 | M90: =+' Activities Detail'!R64 -> 9085.44 | O90: =+' Activities Detail'!U64 -> 7874.048 | P90: =SUM(I90+K90+M90+O90) -> 24239.488 | R90: =SUM(P90:Q90) -> 24239.488
C91: Activity 1.5. Strengthen digital child labor tracking and public reporting/accountability: | D91: Outcome1 | I91: =+' Activities Detail'!L81 -> 0 | K91: =+' Activities Detail'!O81 -> 52000 | M91: =+' Activities Detail'!R81 -> 0 | O91: =+' Activities Detail'!U81 -> 0 | P91: =SUM(I91+K91+M91+O91) -> 52000 | R91: =SUM(P91:Q91) -> 52000
C92: Activity 1.6. Partner with GADs to integrate enforcement processes and capacity building into local community development plans and budgets: | D92: Outcome1 | I92: =+' Activities Detail'!L96 -> 0 | K92: =+' Activities Detail'!O96 -> 0 | M92: =+' Activities Detail'!R96 -> 0 | O92: =+' Activities Detail'!U96 -> 2125.993 | P92: =SUM(I92+K92+M92+O92) -> 2125.993 | R92: =SUM(P92:Q92) -> 2125.993
C93: Activity 1.7 Disseminate successes: | D93: Outcome1 | I93: =+' Activities Detail'!L113 -> 0 | K93: =+' Activities Detail'!O113 -> 0 | M93: =+' Activities Detail'!R113 -> 9085.44 | O93: =+' Activities Detail'!U113 -> 9448.8576 | P93: =SUM(I93+K93+M93+O93) -> 18534.298 | R93: =SUM(P93:Q93) -> 18534.298
C94: Subtotal Outcome 1 | I94: =SUM(I87:I93) -> 0 | K94: =SUM(K87:K93) -> 71115.2 | M94: =SUM(M87:M93) -> 18170.88 | O94: =SUM(O87:O93) -> 19448.899 | P94: =SUM(P87:P93) -> 108734.98 | R94: =SUM(P94:Q94) -> 108734.98
C95: Outcome 2
C96: Activity 2.1. Assess rural workers’ information needs, work experiences, and trusted organizations | D96: Outcome2
C97: Activity 2.2. Build capacity of worker organizations, producer associations, and other actors to reach workers to understand their rights | D97: Outcome2 | I97: =+' Activities Detail'!L124 -> 0 | K97: =+' Activities Detail'!O124 -> 0 | M97: =+' Activities Detail'!R124 -> 0 | O97: =+' Activities Detail'!U124 -> 0 | P97: =SUM(I97+K97+M97+O97) -> 0 | R97: =SUM(P97:Q97) -> 0
C98: Activity 2.3. Institutionalize worker and community training and awareness-raising | D98: Outcome2 | I98: =+' Activities Detail'!L132 -> 0 | K98: =+' Activities Detail'!O132 -> 3536 | M98: =+' Activities Detail'!R132 -> 3677.44 | O98: =+' Activities Detail'!U132 -> 1912.2688 | P98: =SUM(I98+K98+M98+O98) -> 9125.7088 | R98: =SUM(P98:Q98) -> 9125.7088
C99: Activity 2.4. Establish and convene neutral spaces for bipartite and tripartite social dialogue | D99: Outcome2 | I99: =+' Activities Detail'!L141 -> 0 | K99: =+' Activities Detail'!O141 -> 2371.2 | M99: =+' Activities Detail'!R141 -> 2466.048 | N99: =+' Activities Detail'!Q141 -> 0 | O99: =+' Activities Detail'!U141 -> 2564.6899 | P99: =SUM(I99+K99+M99+O99) -> 7401.9379 | R99: =SUM(P99:Q99) -> 7401.9379
C100: Activity 2.5. Train small, medium, and large employers to engage workers, understand workers’ rights, and monitor rights compliance in their supply chains | D100: Outcome2 | I100: =+' Activities Detail'!L150 -> 0 | K100: =+' Activities Detail'!O150 -> 14352 | M100: =+' Activities Detail'!R150 -> 14926.08 | O100: =+' Activities Detail'!U150 -> 0 | P100: =SUM(I100+K100+M100+O100) -> 29278.08 | R100: =SUM(P100:Q100) -> 29278.08
C101: Activity 2.6 Partner with GADs to integrate the above training, awareness-raising, and social dialogue activities into community development plans | D101: Outcome2 | I101: =+' Activities Detail'!L163 -> 0 | K101: =+' Activities Detail'!O163 -> 0 | L101: =+' Activities Detail'!O163 -> 0 | M101: =+' Activities Detail'!R163 -> 886.912 | N101: =+' Activities Detail'!Q163 -> 0 | O101: =+' Activities Detail'!U163 -> 922.38848 | P101: =SUM(I101+K101+M101+O101) -> 1809.3005 | R101: =SUM(P101:Q101) -> 1809.3005
C102: Activity 2.7. Generate new opportunities for learning among civil society, workers, government, private sector, and others. | D102: Outcome2 | I102: =+' Activities Detail'!L179 -> 0 | K102: =+' Activities Detail'!O179 -> 0 | L102: =+' Activities Detail'!O179 -> 0 | M102: =+' Activities Detail'!R179 -> 17089.28 | N102: =+' Activities Detail'!Q179 -> 0 | O102: =+' Activities Detail'!U179 -> 17772.851 | P102: =SUM(I102+K102+M102+O102) -> 34862.131 | R102: =SUM(P102:Q102) -> 34862.131
C103: Activity 2.8. Assess changes in rural workers’, business, Community-Based Organizations, and government officials’ knowledge, skills, and practices. | D103: Outcome2 | I103: =+' Activities Detail'!L196 -> 0 | K103: =+' Activities Detail'!O196 -> 0 | L103: =+' Activities Detail'!O196 -> 0 | M103: =+' Activities Detail'!R196 -> 0 | N103: =+' Activities Detail'!Q196 -> 0 | O103: =+' Activities Detail'!U196 -> 12823.45 | P103: =SUM(I103+K103+M103+O103) -> 12823.45 | R103: =SUM(P103:Q103) -> 12823.45
C104: Subtotal Outcome 2 | I104: =SUM(I96:I103) -> 0 | K104: =SUM(K96:K103) -> 20259.2 | M104: =SUM(M96:M103) -> 39045.76 | O104: =SUM(O96:O103) -> 35995.648 | P104: =SUM(P96:P103) -> 95300.608 | R104: =SUM(P104:Q104) -> 95300.608
C105: Outcome 3 | R105: =SUM(P105:Q105) -> 0
C106: Activity 3.1- Undertake Remediation Constraints and Opportunities Analysis | D106: Outcome3
C107: Activity 3.2 Validate analysis and select pilot remediation mechanism designs | D107: Outcome3 | I107: =+' Activities Detail'!L216 -> 0 | K107: =+' Activities Detail'!O216 -> 2808 | M107: =+' Activities Detail'!R216 -> 0 | O107: =+' Activities Detail'!U216 -> 0 | P107: =SUM(I107+K107+M107+O107) -> 2808 | R107: =SUM(P107:Q107) -> 2808
...

Sheet  Activities Detail
C5: Partners of the Americas
C6: DONOR: | D6: =Assumptions!C9 -> USDOL
C7: Country: | D7: =Assumptions!C10 -> Ecuador
C8: Program Name: | D8: =Assumptions!C11 -> Project to Improve Adherence to International Labor Standards in the Agricultural Sector in Ecuador
C9: Grant Number: | D9: =Assumptions!C12 -> FOA-ILAB-23-28
C10: Period of Performance: | D10: =Assumptions!C13 -> 48 months
C14: ACTIVITY DESCRIPTION | D14: Units | F14: Cost | G14: Base | H14: # of days | J14: ='AgroJusto Budget'!I10 -> Year 1 | M14: ='AgroJusto Budget'!K10 -> Year 2 | P14: ='AgroJusto Budget'!M10 -> Year 3 | S14: ='AgroJusto Budget'!O10 -> Year 4 | V14: Total
J15: # Activities | L15: Amount | M15: # Activities | O15: Amount | P15: # Activities | R15: Amount | S15: # Activities | U15: Amount
C16: ODC Escalation Factor | D16: 0.04 | L16: 1 | O16: =$L$16*SUM(1+$D$16) -> 1.04 | R16: =$O$16*SUM(1+$D$16) -> 1.0816 | U16: =$R$16*SUM(1+$D$16) -> 1.124864
C17: MEETINGS
C20: Activity 1.2. Strengthen intersectoral coordination by re-invigorating referral mechanisms and strengthening Consejos and Juntas: | H20: 1 | J20: 0 | L20: =SUM(K22:K46) -> 0 | M20: 4 | O20: =SUM(N22:N26) -> 1435.2 | P20: 0 | R20: =SUM(Q22:Q26) -> 0 | S20: 0 | U20: =SUM(T22:T26) -> 0 | V20: =SUM(L20,O20,R20,U20,) -> 1435.2
C21: Workshop activities costs
A22: EC.1.4.A | B22: 86000 | C22: Local transportation (training site) | D22: 15 | E22: Individual | F22: =parttransp -> 4 | G22: /day | H22: =IF(D22=0,0,H20) -> 1 | I22: =D22*F22*H22 -> 60 | K22: =$I22*J20*L$16 -> 0 | N22: =$I22*M20*O$16 -> 249.6 | Q22: =$I22*P20*R$16 -> 0 | T22: =$I22*S20*U$16 -> 0 | V22: =T22+Q22+N22+K22 -> 249.6
A23: EC.1.4.B | B23: 87000 | C23: Lunch/coffee breaks | D23: 15 | E23: Individual | F23: =coffee+lunch -> 16 | G23: /day | H23: =IF(D23=0,0,H20) -> 1 | I23: =D23*F23*H23 -> 240 | K23: =$I23*J20*L$16 -> 0 | N23: =$I23*M20*O$16 -> 998.4 | Q23: =$I23*P20*R$16 -> 0 | T23: =$I23*S20*U$16 -> 0 | V23: =T23+Q23+N23+K23 -> 998.4
A24: EC.1.7.C | B24: 82420 | C24: Materials & Supplies | D24: 15 | E24: workshop | F24: =mats -> 3 | G24: =E24 -> workshop | H24: =IF(D24=0,0,1) -> 1 | I24: =D24*F24*H24 -> 45 | K24: =$I24*J20*L$16 -> 0 | N24: =$I24*M20*O$16 -> 187.2 | Q24: =$I24*P20*R$16 -> 0 | T24: =$I24*S20*U$16 -> 0 | V24: =T24+Q24+N24+K24 -> 187.2
A25: EC.1.2.A | B25: 85300 | C25: Printing (Guide) | D25: 0 | E25: canton | F25: =guideprint -> 200 | G25: =E25 -> canton | H25: =IF(D25=0,0,1) -> 0 | I25: =D25*F25*H25 -> 0 | K25: =$I25*L$16 -> 0 | Q25: =$I25*P20*R$16 -> 0 | T25: =$I25*S20*U$16 -> 0 | V25: =T25+Q25+N25+K25 -> 0
A26: EC.1.1.A | B26: 81000 | C26: Local Consultant (Guide Development) | D26: 0 | E26: Individual | F26: =localcons -> 300 | G26: /day | H26: 1 | I26: =D26*F26*H26 -> 0 | K26: =$I26*J20*L$16 -> 0 | N26: =$I26*M20*O$16 -> 0 | Q26: =$I26*P20*R$16 -> 0 | T26: =$I26*S20*U$16 -> 0 | V26: =T26+Q26+N26+K26 -> 0
C27: Staff from outside training site | V27: =T27+Q27+N27+K27 -> 0
C28: Transportation (El Oro) | D28: 3 | E28: Individual | F28: =Assumptions!D73 -> 195 | G28: /trip | H28: 1 | I28: =D28*F28*H28 -> 585 | K28: =$I28*K$20*L$16 -> 0 | N28: =$I28*M20*O$16 -> 2433.6 | V28: 0
C29: Ground transportation (El Oro) | D29: 3 | E29: Individual | F29: =partground -> 9 | G29: /day | H29: 4 | I29: =D29*F29*H29 -> 108 | K29: =$I29*K$20*L$16 -> 0 | N29: =$I29*M20*O$16 -> 449.28 | V29: 0
C30: Lodging | D30: 3 | E30: Individual | F30: =Assumptions!D70 -> 122 | G30: /day | H30: 4 | I30: =D30*F30*H30 -> 1464 | K30: =$I30*K$20*L$16 -> 0 | N30: =$I30*M20*O$16 -> 6090.24 | V30: 0
C31: M&IE | D31: 3 | E31: Individual | F31: =partmeals -> 47 | G31: /day | H31: 4 | I31: =D31*F31*H31 -> 564 | K31: =$I31*K$20*L$16 -> 0 | N31: =$I31*M20*O$16 -> 2346.24 | V31: 0
C32: Staff from outside training site | V32: =T32+Q32+N32+K32 -> 0
C33: Transportation (Cotopaxi) | D33: 3 | E33: Individual | F33: =partground -> 9 | G33: /trip | H33: 2 | I33: =D33*F33*H33 -> 54 | K33: =$I33*J$20*L$16 -> 0 | N33: =$I33*M20*O$16 -> 224.64 | V33: 0
C34: Ground transportation (Cotopaxi) | D34: 3 | E34: Individual | F34: =partground -> 9 | G34: /day | H34: 4 | I34: =D34*F34*H34 -> 108 | K34: =$I34*J$20*L$16 -> 0 | N34: =$I34*M20*O$16 -> 449.28 | V34: 0
C35: M&IE | D35: 3 | E35: Individual | F35: =partmeals -> 47 | G35: /day | H35: 4 | I35: =D35*F35*H35 -> 564 | K35: =$I35*J$20*L$16 -> 0 | N35: =$I35*M20*O$16 -> 2346.24 | V35: 0
C37: Staff from outside training site - Asistencia Técnica (coordinar mesas)
C38: Transportation (El Oro) | D38: 2 | E38: Individual | F38: =Assumptions!D73 -> 195 | G38: /trip | H38: 1 | I38: =D38*F38*H38 -> 390 | K38: =$I38*K$20*L$16 -> 0 | N38: =$I38*M20*O$16 -> 1622.4
C39: Ground transportation (El Oro) | D39: 2 | E39: Individual | F39: =partground -> 9 | G39: /day | H39: 4 | I39: =D39*F39*H39 -> 72 | K39: =$I39*K$20*L$16 -> 0 | N39: =$I39*M20*O$16 -> 299.52
C40: Lodging | D40: 2 | E40: Individual | F40: =Assumptions!D70 -> 122 | G40: /day | H40: 4 | I40: =D40*F40*H40 -> 976 | K40: =$I40*K$20*L$16 -> 0 | N40: =$I40*M20*O$16 -> 4060.16
C41: M&IE | D41: 2 | E41: Individual | F41: =partmeals -> 47 | G41: /day | H41: 4 | I41: =D41*F41*H41 -> 376 | K41: =$I41*K$20*L$16 -> 0 | N41: =$I41*M20*O$16 -> 1564.16
C42: Staff from outside training site
C43: Transportation (Cotopaxi) | D43: 2 | E43: Individual | F43: =partground -> 9 | G43: /trip | H43: 2 | I43: =D43*F43*H43 -> 36 | K43: =$I43*J$20*L$16 -> 0 | N43: =$I43*M20*O$16 -> 149.76
C44: Ground transportation (Cotopaxi) | D44: 2 | E44: Individual | F44: =partground -> 9 | G44: /day | H44: 4 | I44: =D44*F44*H44 -> 72 | K44: =$I44*J$20*L$16 -> 0 | N44: =$I44*M20*O$16 -> 299.52
C45: M&IE | D45: 2 | E45: Individual | F45: =partmeals -> 47 | G45: /day | H45: 4 | I45: =D45*F45*H45 -> 376 | K45: =$I45*J$20*L$16 -> 0 | N45: =$I45*M20*O$16 -> 1564.16
V46: =T46+Q46+N46+K46 -> 0
C47: ACTIVITY TOTAL | G47: =SUM(N21:N46) -> 25334.4
C49: Activity 1.3. Develop government capacity building strategy applying assessment results | H49: 1 | L49: =SUM(K51:K61) -> 0 | M49: 1 | O49: =SUM(N51:N51) -> 10400 | P49: 0 | R49: =SUM(Q51:Q61) -> 0 | S49: 0 | U49: =SUM(T51:T61) -> 0 | V49: =SUM(L49,O49,R49,U49,) -> 10400
C50: Project activities costs
C51: Application of MIRTI | D51: 1 | E51: each | F51: 10000 | G51: MIRTI | H51: 1 | I51: =D51*F51*H51 -> 10000 | N51: =$I51*M49*O$16 -> 10400 | V51: =T51+Q51+N51+K51 -> 10400
C52: Staff from outside training site
C53: Transportation (El Oro) | D53: 2 | E53: Individual | F53: =Assumptions!D73 -> 195 | G53: /trip | H53: 1 | I53: =D53*F53*H53 -> 390 | K53: =$I53*K$20*L$16 -> 0 | N53: =$I53*M49*O$16 -> 405.6
C54: Ground transportation (El Oro) | D54: 2 | E54: Individual | F54: =partground -> 9 | G54: /day | H54: 2 | I54: =D54*F54*H54 -> 36 | K54: =$I54*K$20*L$16 -> 0 | N54: =$I54*M49*O$16 -> 37.44
C55: Lodging | D55: 2 | E55: Individual | F55: =Assumptions!D70 -> 122 | G55: /day | H55: 2 | I55: =D55*F55*H55 -> 488 | K55: =$I55*K$20*L$16 -> 0 | N55: =$I55*M49*O$16 -> 507.52
C56: M&IE | D56: 2 | E56: Individual | F56: =partmeals -> 47 | G56: /day | H56: 2 | I56: =D56*F56*H56 -> 188 | K56: =$I56*K$20*L$16 -> 0 | N56: =$I56*M49*O$16 -> 195.52
C57: Staff from outside training site
C58: Transportation (Cotopaxi) | D58: 2 | E58: Individual | F58: =partground -> 9 | G58: /trip | H58: 2 | I58: =D58*F58*H58 -> 36 | K58: =$I58*J$20*L$16 -> 0 | N58: =$I58*M49*O$16 -> 37.44
C59: Ground transportation (Cotopaxi) | D59: 2 | E59: Individual | F59: =partground -> 9 | G59: /day | H59: 2 | I59: =D59*F59*H59 -> 36 | K59: =$I59*J$20*L$16 -> 0 | N59: =$I59*M49*O$16 -> 37.44
C60: M&IE | D60: 2 | E60: Individual | F60: =partmeals -> 47 | G60: /day | H60: 2 | I60: =D60*F60*H60 -> 188 | K60: =$I60*J$20*L$16 -> 0 | N60: =$I60*M49*O$16 -> 195.52
V61: =T61+Q61+N61+K61 -> 0
C62: ACTIVITY TOTAL | G62: =SUM(N50:N61) -> 11816.48
C64: Activity 1.4. Develop, deliver, and institutionalize tailored capacity building for government officials: | H64: 1 | L64: =SUM(K66:K68) -> 0 | M64: 10 | O64: =SUM(N66:N68) -> 7280 | P64: 12 | R64: =SUM(Q66:Q68) -> 9085.44 | S64: 10 | U64: =SUM(T66:T68) -> 7874.048 | V64: =SUM(L64,O64,R64,U64,) -> 24239.488
C65: Project activities costs
A66: EC.1.4.A | B66: 86000 | C66: Local transportation (El Oro and Cotopaxi) | D66: 15 | E66: Individual | F66: =parttransp -> 4 | G66: /day | H66: 2 | I66: =D66*F66*H66 -> 120 | K66: =$I66*J64*L$16 -> 0 | N66: =$I66*M64*O$16 -> 1248 | Q66: =$I66*P64*R$16 -> 1557.504 | T66: =$I66*S64*U$16 -> 1349.8368 | V66: =T66+Q66+N66+K66 -> 4155.3408
A67: EC.1.4.B | B67: 87000 | C67: Lunch/coffee breaks | D67: 15 | E67: Individual | F67: =coffee+lunch -> 16 | G67: /day | H67: 2 | I67: =D67*F67*H67 -> 480 | K67: =$I67*J64*L$16 -> 0 | N67: =$I67*M64*O$16 -> 4992 | Q67: =$I67*P64*R$16 -> 6230.016 | T67: =$I67*S64*U$16 -> 5399.3472 | V67: =T67+Q67+N67+K67 -> 16621.363
A68: EC.1.4.C | B68: 85300 | C68: Printing (Photocopies) | D68: 1 | E68: activity | F68: =print -> 50 | G68: =E68 -> activity | H68: 2 | I68: =D68*F68*H68 -> 100 | K68: =$I68*J64*L$16 -> 0 | N68: =$I68*M64*O$16 -> 1040 | Q68: =$I68*P64*R$16 -> 1297.92 | T68: =$I68*S64*U$16 -> 1124.864 | V68: =T68+Q68+N68+K68 -> 3462.784
C69: Staff from outside training site | V69: =T69+Q69+N69+K69 -> 0
C70: Transportation (El Oro) | D70: 2 | E70: Individual | F70: =Assumptions!D73 -> 195 | G70: /trip | H70: =IF(D70=0,0,1) -> 1 | I70: =D70*F70*H70 -> 390 | K70: =$I70*J$64*L$16 -> 0 | N70: =$I70*M$64*O$16 -> 4056 | Q70: =$I70*P$64*R$16 -> 5061.888 | T70: =$I70*S$64*U$16 -> 4386.9696 | V70: 0
C71: Ground transportation (El Oro) | D71: 2 | E71: Individual | F71: =partground -> 9 | G71: /day | H71: =IF(D71=0,0,1) -> 1 | I71: =D71*F71*H71 -> 18 | K71: =$I71*J$64*L$16 -> 0 | N71: =$I71*M$64*O$16 -> 187.2 | Q71: =$I71*P$64*R$16 -> 233.6256 | T71: =$I71*S$64*U$16 -> 202.47552 | V71: 0
C72: Lodging | D72: 2 | E72: Individual | F72: =Assumptions!D70 -> 122 | G72: /day | H72: 2 | I72: =D72*F72*H72 -> 488 | K72: =$I72*J$64*L$16 -> 0 | N72: =$I72*M$64*O$16 -> 5075.2 | Q72: =$I72*P$64*R$16 -> 6333.8496 | T72: =$I72*S$64*U$16 -> 5489.3363 | V72: 0
C73: M&IE | D73: 2 | E73: Individual | F73: =partmeals -> 47 | G73: /day | H73: 2 | I73: =D73*F73*H73 -> 188 | K73: =$I73*J$64*L$16 -> 0 | N73: =$I73*M$64*O$16 -> 1955.2 | Q73: =$I73*P$64*R$16 -> 2440.0896 | T73: =$I73*S$64*U$16 -> 2114.7443 | V73: 0
C74: Staff from outside training site | V74: =T74+Q74+N74+K74 -> 0
C75: Transportation (Cotopaxi) | D75: 1 | E75: Individual | F75: =partground -> 9 | G75: /trip | H75: 2 | I75: =D75*F75*H75 -> 18 | K75: =$I75*J$64*L$16 -> 0 | N75: =$I75*M$64*O$16 -> 187.2 | Q75: =$I75*P$64*R$16 -> 233.6256 | T75: =$I75*S$64*U$16 -> 202.47552 | V75: 0
C76: Ground transportation (Cotopaxi) | D76: 1 | E76: Individual | F76: =partground -> 9 | G76: /day | H76: 1 | I76: =D76*F76*H76 -> 9 | K76: =$I76*J$64*L$16 -> 0 | N76: =$I76*M$64*O$16 -> 93.6 | Q76: =$I76*P$64*R$16 -> 116.8128 | T76: =$I76*S$64*U$16 -> 101.23776 | V76: 0
C77: M&IE | D77: 1 | E77: Individual | F77: =partmeals -> 47 | G77: /day | H77: 2 | I77: =D77*F77*H77 -> 94 | K77: =$I77*J$64*L$16 -> 0 | N77: =$I77*M$64*O$16 -> 977.6 | Q77: =$I77*P$64*R$16 -> 1220.0448 | T77: =$I77*S$64*U$16 -> 1057.3722 | V77: 0
C79: ACTIVITY TOTAL | G79: =SUM(N65:T78) -> 65966.035
C81: Activity 1.5. Strengthen digital child labor tracking and public reporting/accountability: | H81: 1 | L81: =SUM(K83) -> 0 | M81: 1 | O81: =SUM(N83) -> 52000 | P81: 1 | R81: =SUM(Q83) -> 0 | S81: 1 | U81: =SUM(T83) -> 0 | V81: =SUM(L81,O81,R81,U81,) -> 52000
C82: Project activities costs
A83: EC.1.5.A | B83: 81010 | C83: Software Development | D83: 1 | E83: each | F83: 50000 | G83: /software | H83: 0 | I83: =D83*F83*H83 -> 0 | K83: 0 | N83: =$F83*M81*O$16 -> 52000 | Q83: =$I83*P81*R$16 -> 0 | T83: =$I83*S81*U$16 -> 0 | V83: =T83+Q83+N83+K83 -> 52000
C84: Staff from outside site | V84: =T84+Q84+N84+K84 -> 0
C85: Transportation (El Oro) | D85: 2 | E85: Individual | F85: =Assumptions!D73 -> 195 | G85: /trip | H85: =IF(D85=0,0,1) -> 1 | I85: =D85*F85*H85 -> 390 | K85: =$I85*$J$81*L$16 -> 0 | N85: =$I85*$M$81*O$16 -> 405.6 | Q85: =$I85*$P$81*R$16 -> 421.824 | T85: =$I85*$S$81*U$16 -> 438.69696 | V85: 0
C86: Ground transportation (El Oro) | D86: 2 | E86: Individual | F86: =partground -> 9 | G86: /day | H86: =IF(D86=0,0,1) -> 1 | I86: =D86*F86*H86 -> 18 | K86: =$I86*$J$81*L$16 -> 0 | N86: =$I86*$M$81*O$16 -> 18.72 | Q86: =$I86*$P$81*R$16 -> 19.4688 | T86: =$I86*$S$81*U$16 -> 20.247552 | V86: 0
C87: Lodging | D87: 2 | E87: Individual | F87: =Assumptions!D70 -> 122 | G87: /day | H87: 2 | I87: =D87*F87*H87 -> 488 | K87: =$I87*$J$81*L$16 -> 0 | N87: =$I87*$M$81*O$16 -> 507.52 | Q87: =$I87*$P$81*R$16 -> 527.8208 | T87: =$I87*$S$81*U$16 -> 548.93363 | V87: 0
C88: M&IE | D88: 2 | E88: Individual | F88: =partmeals -> 47 | G88: /day | H88: 2 | I88: =D88*F88*H88 -> 188 | K88: =$I88*$J$81*L$16 -> 0 | N88: =$I88*$M$81*O$16 -> 195.52 | Q88: =$I88*$P$81*R$16 -> 203.3408 | T88: =$I88*$S$81*U$16 -> 211.47443 | V88: 0
C89: =C84 -> Staff from outside site
C90: Transportation (Cotopaxi) | D90: 2 | E90: Individual | F90: =partground -> 9 | G90: /trip | H90: 2 | I90: =D90*F90*H90 -> 36 | K90: =$I90*J$81*L$16 -> 0 | N90: =$I90*M$81*O$16 -> 37.44 | Q90: =$I90*P$81*R$16 -> 38.9376 | T90: =$I90*S$81*U$16 -> 40.495104 | V90: 0
C91: Ground transportation (Cotopaxi) | D91: 2 | E91: Individual | F91: =partground -> 9 | G91: /day | H91: 2 | I91: =D91*F91*H91 -> 36 | K91: =$I91*J$81*L$16 -> 0 | N91: =$I91*M$81*O$16 -> 37.44 | Q91: =$I91*P$81*R$16 -> 38.9376 | T91: =$I91*S$81*U$16 -> 40.495104 | V91: 0
C92: M&IE | D92: 2 | E92: Individual | F92: =partmeals -> 47 | G92: /day | H92: 2 | I92: =D92*F92*H92 -> 188 | K92: =$I92*J$81*L$16 -> 0 | N92: =$I92*M$81*O$16 -> 195.52 | Q92: =$I92*P$81*R$16 -> 203.3408 | T92: =$I92*S$81*U$16 -> 211.47443 | V92: 0
K93: =$I93*$J$81*L$16 -> 0 | N93: =$I93*$M$81*O$16 -> 0 | Q93: =$I93*$P$81*R$16 -> 0
C94: ACTIVITY TOTAL | G94: =SUM(I82:I93) -> 1344
C96: Activity 1.6. Partner with GADs to integrate enforcement processes and capacity building into local community development plans and budgets: | H96: 1 | L96: =SUM(K98:K100) -> 0 | M96: 0 | O96: =SUM(N98:N100) -> 0 | P96: 0 | R96: =SUM(Q98:Q100) -> 0 | S96: 6 | U96: =SUM(T98:T100) -> 2125.993 | V96: =SUM(L96,O96,R96,U96,) -> 2125.993
C97: Training/workshop/project activities costs
A98: EC.1.4.A | B98: 86000 | C98: Local transportation (training site) | D98: 15 | E98: Individual | F98: =parttransp -> 4 | G98: /day | H98: =IF(D98=0,0,H96) -> 1 | I98: =D98*F98*H98 -> 60 | K98: =$I98*J96*L$16 -> 0 | N98: =$I98*M96*O$16 -> 0 | Q98: =$I98*P96*R$16 -> 0 | T98: =$I98*S96*U$16 -> 404.95104 | V98: =T98+Q98+N98+K98 -> 404.95104
A99: EC.1.4.B | B99: 87000 | C99: Lunch/coffee breaks | D99: 15 | E99: Individual | F99: =coffee+lunch -> 16 | G99: /day | H99: =IF(D99=0,0,H96) -> 1 | I99: =D99*F99*H99 -> 240 | K99: =$I99*J96*L$16 -> 0 | N99: =$I99*M96*O$16 -> 0 | Q99: =$I99*P96*R$16 -> 0 | T99: =$I99*S96*U$16 -> 1619.8042 | V99: =T99+Q99+N99+K99 -> 1619.8042
A100: EC.1.4.C | B100: 85300 | C100: Printing (Photocopies) | D100: 1 | E100: activity | F100: 15 | G100: =E100 -> activity | H100: =IF(D100=0,0,1) -> 1 | I100: =D100*F100*H100 -> 15 | K100: =$I100*J96*L$16 -> 0 | N100: =$I100*M96*O$16 -> 0 | Q100: =$I100*P96*R$16 -> 0 | T100: =$I100*S96*U$16 -> 101.23776 | V100: =T100+Q100+N100+K100 -> 101.23776
C101: Staff from outside site | V101: =T101+Q101+N101+K101 -> 0
C102: Transportation (El Oro) | D102: 2 | E102: Individual | F102: =Assumptions!D73 -> 195 | G102: /trip | H102: 3 | I102: =D102*F102*H102 -> 1170 | N102: 0 | Q102: 0 | T102: =$I102*1*U$16 -> 1316.0909 | V102: 0
C103: Ground transportation (El Oro) | D103: 2 | E103: Individual | F103: =partground -> 9 | G103: /day | H103: 3 | I103: =D103*F103*H103 -> 54 | N103: 0 | Q103: 0 | T103: =$I103*U$16 -> 60.742656 | V103: 0
C104: Lodging | D104: 4 | E104: Individual | F104: =Assumptions!D70 -> 122 | G104: /day | H104: 6 | I104: =D104*F104*H104 -> 2928 | N104: 0 | Q104: 0 | T104: =$I104*U$16 -> 3293.6018 | V104: 0
C105: M&IE | D105: 4 | E105: Individual | F105: =partmeals -> 47 | G105: /day | H105: 2 | I105: =D105*F105*H105 -> 376 | N105: 0 | Q105: 0 | T105: =$I105*U$16 -> 422.94886 | V105: 0
C106: Staff from outside training site
C107: Transportation (Cotopaxi) | D107: 2 | E107: Individual | F107: =partground -> 9 | G107: /trip | H107: 3 | I107: =D107*F107*H107 -> 54 | N107: 0 | Q107: 0 | T107: =$I107*U$16 -> 60.742656 | V107: 0
C108: Ground transportation (Cotopaxi) | D108: 2 | E108: Individual | F108: =partground -> 9 | G108: /day | H108: 3 | I108: =D108*F108*H108 -> 54 | N108: 0 | Q108: 0 | T108: =$I108*U$16 -> 60.742656 | V108: 0
C109: Lodging | D109: 4 | E109: Individual | F109: =Assumptions!D70 -> 122 | G109: /day | H109: 3 | I109: =D109*F109*H109 -> 1464 | N109: 0 | Q109: 0 | T109: =$I109*U$16 -> 1646.8009 | V109: 0
C110: M&IE | D110: 4 | E110: Individual | F110: =partmeals -> 47 | G110: /day | H110: 2 | I110: =D110*F110*H110 -> 376 | N110: 0 | Q110: 0 | T110: =$I110*U$16 -> 422.94886 | V110: 0
C111: ACTIVITY TOTAL | G111: =SUM(I97:I110) -> 6791
C113: Activity 1.7 Disseminate successes: | H113: 1 | L113: =SUM(K115:K120) -> 0 | M113: 0 | O113: =SUM(N115:N120) -> 0 | P113: 2 | R113: =SUM(Q115:Q120) -> 9085.44 | S113: 2 | U113: =SUM(T115:T120) -> 9448.8576 | V113: =SUM(L113,O113,R113,U113,) -> 18534.298
C114: Meetings/Forums/Seminars
A115: EC.1.4.A | B115: 86000 | C115: Local transportation (training site) | D115: 80 | E115: Individual | F115: =parttransp -> 4 | G115: /day | H115: =IF(D115=0,0,H113) -> 1 | I115: =D115*F115*H115 -> 320 | K115: =$I115*J113*L$16 -> 0 | N115: =$I115*M113*O$16 -> 0 | Q115: =$I115*P113*R$16 -> 692.224 | T115: =$I115*S113*U$16 -> 719.91296 | V115: =T115+Q115+N115+K115 -> 1412.137
A116: EC.1.4.B | B116: 87000 | C116: Lunch/coffee breaks | D116: 80 | E116: Individual | F116: =coffee+lunch -> 16 | G116: /day | H116: =IF(D116=0,0,H113) -> 1 | I116: =D116*F116*H116 -> 1280 | K116: =$I116*J113*L$16 -> 0 | N116: =$I116*M113*O$16 -> 0 | Q116: =$I116*P113*R$16 -> 2768.896 | T116: =$I116*S113*U$16 -> 2879.6518 | V116: =T116+Q116+N116+K116 -> 5648.5478
...

Sheet US & Local Summaries
A1: =Assumptions!B8 -> Partners of America
A2: =Assumptions!B9 -> DONOR: | F2: =Assumptions!C9 -> USDOL
A3: =Assumptions!B10 -> Country: | F3: =Assumptions!C10 -> Ecuador
A4: =Assumptions!B11 -> Program Name: | F4: =Assumptions!C11 -> Project to Improve Adherence to International Labor Standards in the Agricultural Sector in Ecuador
A5: =Assumptions!B12 -> Grant Number: | F5: =Assumptions!C12 -> FOA-ILAB-23-28
A6: =Assumptions!B13 -> Period of Performance: | F6: =Assumptions!C13 -> 48 months | I6: =Assumptions!G13 -> 0
A8: US COSTS
A10: Line Item | F10: =#REF! -> #REF! | I10: =#REF! -> #REF! | L10: =#REF! -> #REF! | O10: =#REF! -> #REF! | R10: =#REF! -> #REF! | U10: Total
A12: Salaries | F12: =#REF! -> #REF! | I12: =#REF! -> #REF! | L12: =#REF! -> #REF! | O12: =#REF! -> #REF! | R12: =#REF! -> #REF! | U12: =SUM(F12,I12,L12,O12,R12) -> #REF!
A13: Fringe Benefits | F13: =#REF! -> #REF! | I13: =#REF! -> #REF! | L13: =#REF! -> #REF! | O13: =#REF! -> #REF! | R13: =#REF! -> #REF! | U13: =SUM(F13,I13,L13,O13,R13) -> #REF!
A14: Travel | F14: =#REF! -> #REF! | I14: =#REF! -> #REF! | L14: =#REF! -> #REF! | O14: =#REF! -> #REF! | R14: =#REF! -> #REF! | U14: =SUM(F14,I14,L14,O14,R14) -> #REF!
A15: Equipment | F15: =#REF! -> #REF! | I15: =#REF! -> #REF! | L15: =#REF! -> #REF! | O15: =#REF! -> #REF! | R15: =#REF! -> #REF! | U15: =SUM(F15,I15,L15,O15,R15) -> #REF!
A16: Materials and Supplies | F16: =#REF! -> #REF! | I16: =#REF! -> #REF! | L16: =#REF! -> #REF! | O16: =#REF! -> #REF! | R16: =#REF! -> #REF! | U16: =SUM(F16,I16,L16,O16,R16) -> #REF!
A17: Consultants | F17: =#REF! -> #REF! | I17: =#REF! -> #REF! | L17: =#REF! -> #REF! | O17: =#REF! -> #REF! | R17: =#REF! -> #REF! | U17: =SUM(F17,I17,L17,O17,R17) -> #REF!
A18: Contractual | F18: =#REF! -> #REF! | I18: =#REF! -> #REF! | L18: =#REF! -> #REF! | O18: =#REF! -> #REF! | R18: =#REF! -> #REF! | U18: =SUM(F18,I18,L18,O18,R18) -> #REF!
A19: Other Direct Costs | F19: =#REF! -> #REF! | I19: =#REF! -> #REF! | L19: =#REF! -> #REF! | O19: =#REF! -> #REF! | R19: =#REF! -> #REF! | U19: =SUM(F19,I19,L19,O19,R19) -> #REF!
A20: Subtotal | F20: =#REF! -> #REF! | I20: =#REF! -> #REF! | L20: =#REF! -> #REF! | O20: =#REF! -> #REF! | R20: =#REF! -> #REF! | U20: =SUM(F20,I20,L20,O20,R20) -> #REF!
A22: Service Center (excluding subcontractors) | F22: =#REF! -> #REF! | I22: =#REF! -> #REF! | L22: =#REF! -> #REF! | O22: =#REF! -> #REF! | R22: =#REF! -> #REF! | U22: =SUM(F22,I22,L22,O22,R22) -> #REF!
A23: Service Center on Subcontractors | F23: =#REF! -> #REF! | I23: =#REF! -> #REF! | L23: =#REF! -> #REF! | O23: =#REF! -> #REF! | R23: =#REF! -> #REF! | U23: =SUM(F23,I23,L23,O23,R23) -> #REF!
A25: F&A Costs | F25: =#REF! -> #REF! | I25: =#REF! -> #REF! | L25: =#REF! -> #REF! | O25: =#REF! -> #REF! | R25: =#REF! -> #REF! | U25: =SUM(F25,I25,L25,O25,R25) -> #REF!
A26: F&A Costs (Applied to Subcontracts) | F26: =#REF! -> #REF! | I26: =#REF! -> #REF! | L26: =#REF! -> #REF! | O26: =#REF! -> #REF! | R26: =#REF! -> #REF! | U26: =SUM(F26,I26,L26,O26,R26) -> #REF!
A28: Total per year | F28: =SUM(F20:F27) -> #REF! | I28: =SUM(I20:I27) -> #REF! | L28: =SUM(L20:L27) -> #REF! | O28: =SUM(O20:O27) -> #REF! | R28: =SUM(R20:R27) -> #REF! | U28: =SUM(E28:T28) -> #REF!
A30: IN-COUNTRY COSTS
A32: Line Item | F32: =F10 -> #REF! | I32: =I10 -> #REF! | L32: =L10 -> #REF! | O32: =O10 -> #REF! | R32: =R10 -> #REF! | U32: =U10 -> Total
A34: Salaries | F34: =#REF! -> #REF! | I34: =#REF! -> #REF! | L34: =#REF! -> #REF! | O34: =#REF! -> #REF! | R34: =#REF! -> #REF! | U34: =SUM(F34,I34,L34,O34,R34) -> #REF!
A35: Fringe Benefits | F35: =#REF! -> #REF! | I35: =#REF! -> #REF! | L35: =#REF! -> #REF! | O35: =#REF! -> #REF! | R35: =#REF! -> #REF! | U35: =SUM(F35,I35,L35,O35,R35) -> #REF!
A36: Travel | F36: =#REF! -> #REF! | I36: =#REF! -> #REF! | L36: =#REF! -> #REF! | O36: =#REF! -> #REF! | R36: =#REF! -> #REF! | U36: =SUM(F36,I36,L36,O36,R36) -> #REF!
A37: Equipment | F37: =#REF! -> #REF! | I37: =#REF! -> #REF! | L37: =#REF! -> #REF! | O37: =#REF! -> #REF! | R37: =#REF! -> #REF! | U37: =SUM(F37,I37,L37,O37,R37) -> #REF!
A38: Materials and Supplies | F38: =#REF! -> #REF! | I38: =#REF! -> #REF! | L38: =#REF! -> #REF! | O38: =#REF! -> #REF! | R38: =#REF! -> #REF! | U38: =SUM(F38,I38,L38,O38,R38) -> #REF!
A39: Consultants | F39: =#REF! -> #REF! | I39: =#REF! -> #REF! | L39: =#REF! -> #REF! | O39: =#REF! -> #REF! | R39: =#REF! -> #REF! | U39: =SUM(F39,I39,L39,O39,R39) -> #REF!
A40: Contractual | F40: =#REF! -> #REF! | I40: =#REF! -> #REF! | L40: =#REF! -> #REF! | O40: =#REF! -> #REF! | R40: =#REF! -> #REF! | U40: =SUM(F40,I40,L40,O40,R40) -> #REF!
A41: Other Direct Costs | F41: =#REF! -> #REF! | I41: =#REF! -> #REF! | L41: =#REF! -> #REF! | O41: =#REF! -> #REF! | R41: =#REF! -> #REF! | U41: =SUM(F41,I41,L41,O41,R41) -> #REF!
A42: Subtotal | F42: =#REF! -> #REF! | I42: =#REF! -> #REF! | L42: =#REF! -> #REF! | O42: =#REF! -> #REF! | R42: =#REF! -> #REF! | U42: =SUM(F42,I42,L42,O42,R42) -> #REF!
A44: Service Center (excluding subcontractors) | F44: =#REF! -> #REF! | I44: =#REF! -> #REF! | L44: =#REF! -> #REF! | O44: =#REF! -> #REF! | R44: =#REF! -> #REF! | U44: =SUM(F44,I44,L44,O44,R44) -> #REF!
A45: Service Center on Subcontractors | F45: =#REF! -> #REF! | I45: =#REF! -> #REF! | L45: =#REF! -> #REF! | O45: =#REF! -> #REF! | R45: =#REF! -> #REF! | U45: =SUM(F45,I45,L45,O45,R45) -> #REF!
A47: F&A Costs | F47: =#REF! -> #REF! | I47: =#REF! -> #REF! | L47: =#REF! -> #REF! | O47: =#REF! -> #REF! | R47: =#REF! -> #REF! | U47: =SUM(F47,I47,L47,O47,R47) -> #REF!
A48: F&A Costs (Applied to Subcontracts) | F48: =#REF! -> #REF! | I48: =#REF! -> #REF! | L48: =#REF! -> #REF! | O48: =#REF! -> #REF! | R48: =#REF! -> #REF! | U48: =SUM(F48,I48,L48,O48,R48) -> #REF!
A50: Total per year | F50: =SUM(F42:F49) -> #REF! | I50: =SUM(I42:I49) -> #REF! | L50: =SUM(L42:L49) -> #REF! | O50: =SUM(O42:O49) -> #REF! | R50: =SUM(R42:R49) -> #REF! | U50: =SUM(F50,I50,L50,O50,R50) -> #REF!
A52: Grand Total | F52: =SUM(F50,F28) -> #REF! | I52: =SUM(I50,I28) -> #REF! | L52: =SUM(L50,L28) -> #REF! | O52: =SUM(O50,O28) -> #REF! | R52: =SUM(R50,R28) -> #REF! | U52: =SUM(F52,I52,L52,O52,R52) -> #REF!

Sheet TA Summary
B1: =Assumptions!$B$8 -> Partners of America
B2: =CONCATENATE(Assumptions!$B9," ",Assumptions!$C9) -> DONOR: USDOL
B3: =CONCATENATE(Assumptions!$B10," ",Assumptions!$C10) -> Country: Ecuador
B4: =CONCATENATE(Assumptions!$B11," ",Assumptions!$C11) -> Program Name: Project to Improve Adherence to International Labor Standards in the Agricultural Sector in Ecuador
B5: =CONCATENATE(Assumptions!$B12," ",Assumptions!$C12) -> Grant Number: FOA-ILAB-23-28
B7: TOTAL FUNDING FOR EXPATRIATE AND IN-COUNTRY TECHNICAL ASSISTANCE
B9: Line Item | C9: =#REF! -> #REF! | F9: =#REF! -> #REF! | I9: =#REF! -> #REF! | L9: =#REF! -> #REF! | O9: =#REF! -> #REF! | S9: Total
A11: 6.a | B11: Expatriate Technical Assistance
B12: Program and Technical Staff - US Hires | C12: =SUM(#REF!,#REF!) -> #REF! | F12: =SUM(#REF!,#REF!) -> #REF! | I12: =SUM(#REF!,#REF!) -> #REF! | L12: =SUM(#REF!,#REF!) -> #REF! | O12: =SUM(#REF!,#REF!) -> #REF! | S12: =SUM(C12:O12) -> #REF!
B13: STA US Hires | C13: =SUM(#REF!) -> #REF! | F13: =SUM(#REF!) -> #REF! | I13: =SUM(#REF!) -> #REF! | L13: =SUM(#REF!) -> #REF! | O13: =SUM(#REF!) -> #REF! | S13: =SUM(C13:O13) -> #REF!
B14: Regional Hires | C14: =SUM(#REF!,#REF!) -> #REF! | F14: =SUM(#REF!,#REF!) -> #REF! | I14: =SUM(#REF!,#REF!) -> #REF! | L14: =SUM(#REF!,#REF!) -> #REF! | O14: =SUM(#REF!,#REF!) -> #REF! | S14: =SUM(C14:O14) -> #REF!
B15: International Consultants | C15: =SUM(#REF!) -> #REF! | F15: =SUM(#REF!) -> #REF! | I15: =SUM(#REF!) -> #REF! | L15: =SUM(#REF!) -> #REF! | O15: =SUM(#REF!) -> #REF! | S15: =SUM(C15:O15) -> #REF!
B16: Fringe Benefits US Hires | C16: =SUM(#REF!,#REF!,#REF!) -> #REF! | F16: =SUM(#REF!,#REF!,#REF!) -> #REF! | I16: =SUM(#REF!,#REF!,#REF!) -> #REF! | L16: =SUM(#REF!,#REF!,#REF!) -> #REF! | O16: =SUM(#REF!,#REF!,#REF!) -> #REF! | S16: =SUM(C16:O16) -> #REF!
B17: Fringe Benefits Regional Hires | C17: =SUM(#REF!) -> #REF! | F17: =SUM(#REF!) -> #REF! | I17: =SUM(#REF!) -> #REF! | L17: =SUM(#REF!) -> #REF! | O17: =SUM(#REF!) -> #REF! | S17: =SUM(C17:O17) -> #REF!
B18: Allowances | C18: =SUM(#REF!) -> #REF! | F18: =SUM(#REF!) -> #REF! | I18: =SUM(#REF!) -> #REF! | L18: =SUM(#REF!) -> #REF! | O18: =SUM(#REF!) -> #REF! | S18: =SUM(C18:O18) -> #REF!
B19: International Travel | C19: =#REF! -> #REF! | F19: =#REF! -> #REF! | I19: =#REF! -> #REF! | L19: =#REF! -> #REF! | O19: =#REF! -> #REF! | S19: =SUM(C19:O19) -> #REF!
B20: International Consultants Travel | C20: =SUM(#REF!) -> #REF! | F20: =SUM(#REF!) -> #REF! | I20: =SUM(#REF!) -> #REF! | L20: =SUM(#REF!) -> #REF! | O20: =SUM(#REF!) -> #REF! | S20: =SUM(C20:O20) -> #REF!
B21: Total Expatriate TA | C21: =SUM(C12:C20) -> #REF! | F21: =SUM(F12:F20) -> #REF! | I21: =SUM(I12:I20) -> #REF! | L21: =SUM(L12:L20) -> #REF! | O21: =SUM(O12:O20) -> #REF! | S21: =SUM(C21:O21) -> #REF!
B23: Country Offices
B24: Program and Technical Staff - Local Hires | C24: =#REF! -> #REF! | F24: =#REF! -> #REF! | I24: =#REF! -> #REF! | L24: =#REF! -> #REF! | O24: =#REF! -> #REF! | S24: =SUM(O24,C24,F24,I24,L24) -> #REF!
B25: Support Staff - Local Hires | C25: =#REF! -> #REF! | F25: =#REF! -> #REF! | I25: =#REF! -> #REF! | L25: =#REF! -> #REF! | O25: =#REF! -> #REF! | S25: =SUM(O25,C25,F25,I25,L25) -> #REF!
B26: Local Consultants Labor | C26: =SUM(#REF!) -> #REF! | F26: =SUM(#REF!) -> #REF! | I26: =SUM(#REF!) -> #REF! | L26: =SUM(#REF!) -> #REF! | O26: =SUM(#REF!) -> #REF! | S26: =SUM(O26,C26,F26,I26,L26) -> #REF!
B27: Fringe Benefits - Local Hires | C27: =#REF! -> #REF! | F27: =#REF! -> #REF! | I27: =#REF! -> #REF! | L27: =#REF! -> #REF! | O27: =#REF! -> #REF! | S27: =SUM(O27,C27,F27,I27,L27) -> #REF!
B28: Domestic Travel | C28: =#REF! -> #REF! | F28: =#REF! -> #REF! | I28: =#REF! -> #REF! | L28: =#REF! -> #REF! | O28: =#REF! -> #REF! | S28: =SUM(O28,C28,F28,I28,L28) -> #REF!
B29: Local Consultants Travel | C29: =SUM(#REF!) -> #REF! | F29: =SUM(#REF!) -> #REF! | I29: =SUM(#REF!) -> #REF! | L29: =SUM(#REF!) -> #REF! | O29: =SUM(#REF!) -> #REF! | S29: =SUM(O29,C29,F29,I29,L29) -> #REF!
B30: Total Cooperating Country Nationals TA | C30: =SUM(C23:C29) -> #REF! | F30: =SUM(F23:F29) -> #REF! | I30: =SUM(I23:I29) -> #REF! | L30: =SUM(L23:L29) -> #REF! | O30: =SUM(O23:O29) -> #REF! | S30: =SUM(C30:O30) -> #REF!
B32: Total Technical Assistance Costs | C32: =SUM(C30,C21) -> #REF! | F32: =SUM(F30,F21) -> #REF! | I32: =SUM(I30,I21) -> #REF! | L32: =SUM(L30,L21) -> #REF! | O32: =SUM(O30,O21) -> #REF! | S32: =SUM(C32:O32) -> #REF!

Sheet Funding By Partner
A1: =Assumptions!$B$8 -> Partners of America
A2: =CONCATENATE(Assumptions!$B9," ",Assumptions!$C9) -> DONOR: USDOL
A3: =CONCATENATE(Assumptions!$B10," ",Assumptions!$C10) -> Country: Ecuador
A4: =CONCATENATE(Assumptions!$B11," ",Assumptions!$C11) -> Program Name: Project to Improve Adherence to International Labor Standards in the Agricultural Sector in Ecuador
A5: =CONCATENATE(Assumptions!$B12," ",Assumptions!$C12) -> Grant Number: FOA-ILAB-23-28
A7: TOTAL FUNDING BY PARTNER
A9: Partner | B9: =Assumptions!G24 -> Year 1 | E9: =Assumptions!J24 -> Year 2 | H9: =Assumptions!M24 -> Year 3 | K9: =Assumptions!P24 -> Year 4 | N9: =Assumptions!S24 -> Year 5 | Q9: Total
B10: Federal Funding | C10: Non-Federal Funding | E10: Federal Funding | F10: Non-Federal Funding | H10: Federal Funding | I10: Non-Federal Funding | K10: Federal Funding | L10: Non-Federal Funding | N10: Federal Funding | O10: Non-Federal Funding | Q10: Federal Funding | R10: Non-Federal Funding | T10: If RFA requests for Cost Share - Unhide columns "C", "F", "I", "L", "O" and "Q"
T11: Double-checks
A12: Jhpiego Corporation | B12: =B35-SUM(B13:B33) -> #REF! | E12: =E35-SUM(E13:E33) -> #REF! | H12: =H35-SUM(H13:H33) -> #REF! | K12: =K35-SUM(K13:K33) -> #REF! | N12: =N35-SUM(N13:N33) -> #REF! | Q12: =SUM(B12,E12,H12,K12,N12) -> #REF! | R12: =SUM(C12,F12,I12,L12,O12,#REF!,#REF!,#REF!,#REF!,#REF!) -> #REF! | T12: =SUM(B12:P12) -> #REF!
A14: =#REF! -> #REF! | B14: =#REF! -> #REF! | E14: =#REF! -> #REF! | H14: =#REF! -> #REF! | K14: =#REF! -> #REF! | N14: =#REF! -> #REF! | Q14: =SUM(B14,E14,H14,K14,N14) -> #REF! | R14: =SUM(O14,L14,I14,F14,C14) -> 0 | T14: =SUM(B14:P14) -> #REF!
A16: =#REF! -> #REF! | B16: =#REF! -> #REF! | E16: =#REF! -> #REF! | H16: =#REF! -> #REF! | K16: =#REF! -> #REF! | N16: =#REF! -> #REF! | Q16: =SUM(B16,E16,H16,K16,N16) -> #REF! | R16: =SUM(O16,L16,I16,F16,C16) -> 0 | T16: =SUM(B16:P16) -> #REF!
A18: =#REF! -> #REF! | B18: =#REF! -> #REF! | E18: =#REF! -> #REF! | H18: =#REF! -> #REF! | K18: =#REF! -> #REF! | N18: =#REF! -> #REF! | Q18: =SUM(B18,E18,H18,K18,N18) -> #REF! | R18: =SUM(O18,L18,I18,F18,C18) -> 0 | T18: =SUM(B18:P18) -> #REF!
A20: =#REF! -> #REF! | B20: =#REF! -> #REF! | E20: =#REF! -> #REF! | H20: =#REF! -> #REF! | K20: =#REF! -> #REF! | N20: =#REF! -> #REF! | Q20: =SUM(B20,E20,H20,K20,N20) -> #REF! | R20: =SUM(O20,L20,I20,F20,C20) -> 0 | T20: =SUM(B20:P20) -> #REF!
A22: =#REF! -> #REF! | B22: =#REF! -> #REF! | E22: =#REF! -> #REF! | H22: =#REF! -> #REF! | K22: =#REF! -> #REF! | N22: =#REF! -> #REF! | Q22: =SUM(B22,E22,H22,K22,N22) -> #REF! | R22: =SUM(O22,L22,I22,F22,C22) -> 0 | T22: =SUM(B22:P22) -> #REF!
A24: =#REF! -> #REF! | B24: =#REF! -> #REF! | E24: =#REF! -> #REF! | H24: =#REF! -> #REF! | K24: =#REF! -> #REF! | N24: =#REF! -> #REF! | Q24: =SUM(B24,E24,H24,K24,N24) -> #REF! | R24: =SUM(O24,L24,I24,F24,C24) -> 0 | T24: =SUM(B24:P24) -> #REF!
A26: =#REF! -> #REF! | B26: =#REF! -> #REF! | E26: =#REF! -> #REF! | H26: =#REF! -> #REF! | K26: =#REF! -> #REF! | N26: =#REF! -> #REF! | Q26: =SUM(B26,E26,H26,K26,N26) -> #REF! | R26: =SUM(O26,L26,I26,F26,C26) -> 0 | T26: =SUM(B26:P26) -> #REF!
A28: =#REF! -> #REF! | B28: =#REF! -> #REF! | E28: =#REF! -> #REF! | H28: =#REF! -> #REF! | K28: =#REF! -> #REF! | N28: =#REF! -> #REF! | Q28: =SUM(B28,E28,H28,K28,N28) -> #REF! | R28: =SUM(O28,L28,I28,F28,C28) -> 0 | T28: =SUM(B28:P28) -> #REF!
A30: =#REF! -> #REF! | B30: =#REF! -> #REF! | E30: =#REF! -> #REF! | H30: =#REF! -> #REF! | K30: =#REF! -> #REF! | N30: =#REF! -> #REF! | Q30: =SUM(B30,E30,H30,K30,N30) -> #REF! | R30: =SUM(O30,L30,I30,F30,C30) -> 0 | T30: =SUM(B30:P30) -> #REF!
Q32: =SUM(N32,K32,H32,E32,B32) -> 0 | R32: =SUM(O32,L32,I32,F32,C32) -> 0 | T32: =SUM(B32:P32) -> 0
A35: TOTAL COSTS | B35: =#REF! -> #REF! | C35: =SUM(C11:C34) -> 0 | E35: =#REF! -> #REF! | F35: =SUM(F11:F34) -> 0 | H35: =#REF! -> #REF! | I35: =SUM(I11:I34) -> 0 | K35: =#REF! -> #REF! | L35: =SUM(L11:L34) -> 0 | N35: =#REF! -> #REF! | O35: =SUM(O11:O34) -> 0 | Q35: =SUM(B35,E35,H35,K35,N35) -> #REF! | R35: =SUM(O35,L35,I35,F35,C35) -> 0 | T35: =SUM(B35:P35) -> #REF!

Sheet LOE Table
A1: =Assumptions!$B$8 -> Partners of America
A2: =CONCATENATE(Assumptions!$B9," ",Assumptions!$C9) -> DONOR: USDOL | Q2: Escalation Factor:
A3: =CONCATENATE(Assumptions!$B10," ",Assumptions!$C10) -> Country: Ecuador | Q3: Inflation Rate:
A4: =CONCATENATE(Assumptions!$B11," ",Assumptions!$C11) -> Program Name: Project to Improve Adherence to International Labor Standards in the Agricultural Sector in Ecuador
A5: =CONCATENATE(Assumptions!$B12," ",Assumptions!$C12) -> Grant Number: FOA-ILAB-23-28
A7: LEVEL OF EFFORT TABLE
A9: PERSONNEL | C9: =#REF! -> #REF! | F9: =#REF! -> #REF! | I9: =Assumptions!M24 -> Year 3 | L9: =#REF! -> #REF! | O9: =#REF! -> #REF! | R9: Total | T9: Calculation
A10: Position Description | B10: Unit | C10: Units | F10: Units | I10: Units | L10: Units | O10: Units | R10: % | S10: US$ | T10: Check: | V10: show
V11: =IF(SUM(S12:S190)=0,"hide","show") -> #REF!
A12: =#REF! -> #REF! | V12: =IF(SUM(S20:S190)=0,"hide","show") -> #REF!
A13: =#REF! -> #REF! | V13: =IF(SUM(S14:S18)=0,"hide","show") -> #REF!
A14: =#REF! -> #REF! | B14: % | C14: =#REF! -> #REF! | F14: =#REF! -> #REF! | I14: =#REF! -> #REF! | L14: =#REF! -> #REF! | O14: =#REF! -> #REF! | R14: =C14+F14+I14+L14+O14 -> #REF! | S14: =#REF! -> #REF! | V14: =IF(S14=0,"hide","show") -> #REF!
A15: =#REF! -> #REF! | B15: % | C15: =#REF! -> #REF! | F15: =#REF! -> #REF! | I15: =#REF! -> #REF! | L15: =#REF! -> #REF! | O15: =#REF! -> #REF! | R15: =C15+F15+I15+L15+O15 -> #REF! | S15: =#REF! -> #REF! | V15: =IF(S15=0,"hide","show") -> #REF!
A16: =#REF! -> #REF! | B16: % | C16: =#REF! -> #REF! | F16: =#REF! -> #REF! | I16: =#REF! -> #REF! | L16: =#REF! -> #REF! | O16: =#REF! -> #REF! | R16: =C16+F16+I16+L16+O16 -> #REF! | S16: =#REF! -> #REF! | V16: =IF(S16=0,"hide","show") -> #REF!
A17: =#REF! -> #REF! | B17: % | C17: =#REF! -> #REF! | F17: =#REF! -> #REF! | I17: =#REF! -> #REF! | L17: =#REF! -> #REF! | O17: =#REF! -> #REF! | R17: =C17+F17+I17+L17+O17 -> #REF! | S17: =#REF! -> #REF! | V17: =IF(S17=0,"hide","show") -> #REF!
A18: =#REF! -> #REF! | B18: % | C18: =#REF! -> #REF! | F18: =#REF! -> #REF! | I18: =#REF! -> #REF! | L18: =#REF! -> #REF! | O18: =#REF! -> #REF! | R18: =C18+F18+I18+L18+O18 -> #REF! | S18: =#REF! -> #REF! | V18: =IF(S18=0,"hide","show") -> #REF!
V19: =IF(SUM(S20:S110)=0,"hide","show") -> #REF!
A20: =#REF! -> #REF! | V20: =IF(SUM(S21:S25)=0,"hide","show") -> #REF!
A21: =#REF! -> #REF! | B21: % | C21: =#REF! -> #REF! | F21: =#REF! -> #REF! | I21: =#REF! -> #REF! | L21: =#REF! -> #REF! | O21: =#REF! -> #REF! | R21: =C21+F21+I21+L21+O21 -> #REF! | S21: =#REF! -> #REF! | V21: =IF(S21=0,"hide","show") -> #REF!
A22: =#REF! -> #REF! | B22: % | C22: =#REF! -> #REF! | F22: =#REF! -> #REF! | I22: =#REF! -> #REF! | L22: =#REF! -> #REF! | O22: =#REF! -> #REF! | R22: =C22+F22+I22+L22+O22 -> #REF! | S22: =#REF! -> #REF! | V22: =IF(S22=0,"hide","show") -> #REF!
A23: =#REF! -> #REF! | B23: % | C23: =#REF! -> #REF! | F23: =#REF! -> #REF! | I23: =#REF! -> #REF! | L23: =#REF! -> #REF! | O23: =#REF! -> #REF! | R23: =C23+F23+I23+L23+O23 -> #REF! | S23: =#REF! -> #REF! | V23: =IF(S23=0,"hide","show") -> #REF!
A24: =#REF! -> #REF! | B24: % | C24: =#REF! -> #REF! | F24: =#REF! -> #REF! | I24: =#REF! -> #REF! | L24: =#REF! -> #REF! | O24: =#REF! -> #REF! | R24: =C24+F24+I24+L24+O24 -> #REF! | S24: =#REF! -> #REF! | V24: =IF(S24=0,"hide","show") -> #REF!
A25: =#REF! -> #REF! | B25: % | C25: =#REF! -> #REF! | F25: =#REF! -> #REF! | I25: =#REF! -> #REF! | L25: =#REF! -> #REF! | O25: =#REF! -> #REF! | R25: =C25+F25+I25+L25+O25 -> #REF! | S25: =#REF! -> #REF! | V25: =IF(S25=0,"hide","show") -> #REF!
V26: =IF(SUM(S27:S190)=0,"hide","show") -> #REF!
A27: =#REF! -> #REF! | V27: =IF(SUM(S28:S190)=0,"hide","show") -> #REF!
A28: =#REF! -> #REF! | V28: =IF(SUM(S29:S110)=0,"hide","show") -> #REF!
A29: =#REF! -> #REF! | B29: % | C29: =#REF! -> #REF! | F29: =#REF! -> #REF! | I29: =#REF! -> #REF! | L29: =#REF! -> #REF! | O29: =#REF! -> #REF! | R29: =C29+F29+I29+L29+O29 -> #REF! | S29: =#REF! -> #REF! | V29: =IF(S29=0,"hide","show") -> #REF!
A30: =#REF! -> #REF! | B30: % | C30: =#REF! -> #REF! | F30: =#REF! -> #REF! | I30: =#REF! -> #REF! | L30: =#REF! -> #REF! | O30: =#REF! -> #REF! | R30: =C30+F30+I30+L30+O30 -> #REF! | S30: =#REF! -> #REF! | V30: =IF(S30=0,"hide","show") -> #REF!
A31: =#REF! -> #REF! | B31: % | C31: =#REF! -> #REF! | F31: =#REF! -> #REF! | I31: =#REF! -> #REF! | L31: =#REF! -> #REF! | O31: =#REF! -> #REF! | R31: =C31+F31+I31+L31+O31 -> #REF! | S31: =#REF! -> #REF! | V31: =IF(S31=0,"hide","show") -> #REF!
A32: =#REF! -> #REF! | B32: % | C32: =#REF! -> #REF! | F32: =#REF! -> #REF! | I32: =#REF! -> #REF! | L32: =#REF! -> #REF! | O32: =#REF! -> #REF! | R32: =C32+F32+I32+L32+O32 -> #REF! | S32: =#REF! -> #REF! | V32: =IF(S32=0,"hide","show") -> #REF!
A33: =#REF! -> #REF! | B33: % | C33: =#REF! -> #REF! | F33: =#REF! -> #REF! | I33: =#REF! -> #REF! | L33: =#REF! -> #REF! | O33: =#REF! -> #REF! | R33: =C33+F33+I33+L33+O33 -> #REF! | S33: =#REF! -> #REF! | V33: =IF(S33=0,"hide","show") -> #REF!
A34: =#REF! -> #REF! | B34: % | C34: =#REF! -> #REF! | F34: =#REF! -> #REF! | I34: =#REF! -> #REF! | L34: =#REF! -> #REF! | O34: =#REF! -> #REF! | R34: =C34+F34+I34+L34+O34 -> #REF! | S34: =#REF! -> #REF! | V34: =IF(S34=0,"hide","show") -> #REF!
A35: =#REF! -> #REF! | B35: % | C35: =#REF! -> #REF! | F35: =#REF! -> #REF! | I35: =#REF! -> #REF! | L35: =#REF! -> #REF! | O35: =#REF! -> #REF! | R35: =C35+F35+I35+L35+O35 -> #REF! | S35: =#REF! -> #REF! | V35: =IF(S35=0,"hide","show") -> #REF!
A36: =#REF! -> #REF! | B36: % | C36: =#REF! -> #REF! | F36: =#REF! -> #REF! | I36: =#REF! -> #REF! | L36: =#REF! -> #REF! | O36: =#REF! -> #REF! | R36: =C36+F36+I36+L36+O36 -> #REF! | S36: =#REF! -> #REF! | V36: =IF(S36=0,"hide","show") -> #REF!
A37: =#REF! -> #REF! | B37: % | C37: =#REF! -> #REF! | F37: =#REF! -> #REF! | I37: =#REF! -> #REF! | L37: =#REF! -> #REF! | O37: =#REF! -> #REF! | R37: =C37+F37+I37+L37+O37 -> #REF! | S37: =#REF! -> #REF! | V37: =IF(S37=0,"hide","show") -> #REF!
A38: =#REF! -> #REF! | B38: % | C38: =#REF! -> #REF! | F38: =#REF! -> #REF! | I38: =#REF! -> #REF! | L38: =#REF! -> #REF! | O38: =#REF! -> #REF! | R38: =C38+F38+I38+L38+O38 -> #REF! | S38: =#REF! -> #REF! | V38: =IF(S38=0,"hide","show") -> #REF!
A39: =#REF! -> #REF! | B39: % | C39: =#REF! -> #REF! | F39: =#REF! -> #REF! | I39: =#REF! -> #REF! | L39: =#REF! -> #REF! | O39: =#REF! -> #REF! | R39: =C39+F39+I39+L39+O39 -> #REF! | S39: =#REF! -> #REF! | V39: =IF(S39=0,"hide","show") -> #REF!
A40: =#REF! -> #REF! | B40: % | C40: =#REF! -> #REF! | F40: =#REF! -> #REF! | I40: =#REF! -> #REF! | L40: =#REF! -> #REF! | O40: =#REF! -> #REF! | R40: =C40+F40+I40+L40+O40 -> #REF! | S40: =#REF! -> #REF! | V40: =IF(S40=0,"hide","show") -> #REF!
... A114: =#REF! -> #REF! | B114: % | C114: =#REF! -> #REF! | F114: =#REF! -> #REF! | I114: =#REF! -> #REF! | L114: =#REF! -> #REF! | O114: =#REF! -> #REF! | R114: =C114+F114+I114+L114+O114 -> #REF! | S114: =#REF! -> #REF! | V114: =IF(S114=0,"hide","show") -> #REF!
V115: =IF(SUM(S117:S190)=0,"hide","show") -> #REF!
A116: =#REF! -> #REF! | V116: =IF(SUM(S117:S190)=0,"hide","show") -> #REF!
A117: =#REF! -> #REF! | B117: % | C117: =#REF! -> #REF! | F117: =#REF! -> #REF! | I117: =#REF! -> #REF! | L117: =#REF! -> #REF! | O117: =#REF! -> #REF! | R117: =C117+F117+I117+L117+O117 -> #REF! | S117: =#REF! -> #REF! | V117: =IF(S117=0,"hide","show") -> #REF!
A118: =#REF! -> #REF! | B118: % | C118: =#REF! -> #REF! | F118: =#REF! -> #REF! | I118: =#REF! -> #REF! | L118: =#REF! -> #REF! | O118: =#REF! -> #REF! | R118: =C118+F118+I118+L118+O118 -> #REF! | S118: =#REF! -> #REF! | V118: =IF(S118=0,"hide","show") -> #REF!
A119: =#REF! -> #REF! | B119: % | C119: =#REF! -> #REF! | F119: =#REF! -> #REF! | I119: =#REF! -> #REF! | L119: =#REF! -> #REF! | O119: =#REF! -> #REF! | R119: =C119+F119+I119+L119+O119 -> #REF! | S119: =#REF! -> #REF! | V119: =IF(S119=0,"hide","show") -> #REF!
A120: =#REF! -> #REF! | B120: % | C120: =#REF! -> #REF! | F120: =#REF! -> #REF! | I120: =#REF! -> #REF! | L120: =#REF! -> #REF! | O120: =#REF! -> #REF! | R120: =C120+F120+I120+L120+O120 -> #REF! | S120: =#REF! -> #REF! | V120: =IF(S120=0,"hide","show") -> #REF!
A121: =#REF! -> #REF! | B121: % | C121: =#REF! -> #REF! | F121: =#REF! -> #REF! | I121: =#REF! -> #REF! | L121: =#REF! -> #REF! | O121: =#REF! -> #REF! | R121: =C121+F121+I121+L121+O121 -> #REF! | S121: =#REF! -> #REF! | V121: =IF(S121=0,"hide","show") -> #REF!
A122: =#REF! -> #REF! | B122: % | C122: =#REF! -> #REF! | F122: =#REF! -> #REF! | I122: =#REF! -> #REF! | L122: =#REF! -> #REF! | O122: =#REF! -> #REF! | R122: =C122+F122+I122+L122+O122 -> #REF! | S122: =#REF! -> #REF! | V122: =IF(S122=0,"hide","show") -> #REF!
A123: =#REF! -> #REF! | B123: % | C123: =#REF! -> #REF! | F123: =#REF! -> #REF! | I123: =#REF! -> #REF! | L123: =#REF! -> #REF! | O123: =#REF! -> #REF! | R123: =C123+F123+I123+L123+O123 -> #REF! | S123: =#REF! -> #REF! | V123: =IF(S123=0,"hide","show") -> #REF!
A124: =#REF! -> #REF! | B124: % | C124: =#REF! -> #REF! | F124: =#REF! -> #REF! | I124: =#REF! -> #REF! | L124: =#REF! -> #REF! | O124: =#REF! -> #REF! | R124: =C124+F124+I124+L124+O124 -> #REF! | S124: =#REF! -> #REF! | V124: =IF(S124=0,"hide","show") -> #REF!
A125: =#REF! -> #REF! | B125: % | C125: =#REF! -> #REF! | F125: =#REF! -> #REF! | I125: =#REF! -> #REF! | L125: =#REF! -> #REF! | O125: =#REF! -> #REF! | R125: =C125+F125+I125+L125+O125 -> #REF! | S125: =#REF! -> #REF! | V125: =IF(S125=0,"hide","show") -> #REF!
A126: =#REF! -> #REF! | B126: % | C126: =#REF! -> #REF! | F126: =#REF! -> #REF! | I126: =#REF! -> #REF! | L126: =#REF! -> #REF! | O126: =#REF! -> #REF! | R126: =C126+F126+I126+L126+O126 -> #REF! | S126: =#REF! -> #REF! | V126: =IF(S126=0,"hide","show") -> #REF!
A127: =#REF! -> #REF! | B127: % | C127: =#REF! -> #REF! | F127: =#REF! -> #REF! | I127: =#REF! -> #REF! | L127: =#REF! -> #REF! | O127: =#REF! -> #REF! | R127: =C127+F127+I127+L127+O127 -> #REF! | S127: =#REF! -> #REF! | V127: =IF(S127=0,"hide","show") -> #REF!
A128: =#REF! -> #REF! | B128: % | C128: =#REF! -> #REF! | F128: =#REF! -> #REF! | I128: =#REF! -> #REF! | L128: =#REF! -> #REF! | O128: =#REF! -> #REF! | R128: =C128+F128+I128+L128+O128 -> #REF! | S128: =#REF! -> #REF! | V128: =IF(S128=0,"hide","show") -> #REF!
... A190: =#REF! -> #REF! | B190: % | C190: =#REF! -> #REF! | F190: =#REF! -> #REF! | I190: =#REF! -> #REF! | L190: =#REF! -> #REF! | O190: =#REF! -> #REF! | R190: =C190+F190+I190+L190+O190 -> #REF! | S190: =#REF! -> #REF! | V190: =IF(S190=0,"hide","show") -> #REF!
V191: =IF(SUM(S193:S212)=0,"hide","show") -> #REF!
A192: =#REF! -> #REF! | V192: =IF(SUM(S194:S212)=0,"hide","show") -> #REF!
A193: =#REF! -> #REF! | V193: =IF(SUM(S194:S198)=0,"hide","show") -> #REF!
A194: =#REF! -> #REF! | B194: % | C194: =#REF! -> #REF! | F194: =#REF! -> #REF! | I194: =#REF! -> #REF! | L194: =#REF! -> #REF! | O194: =#REF! -> #REF! | R194: =C194+F194+I194+L194+O194 -> #REF! | S194: =#REF! -> #REF! | V194: =IF(S194=0,"hide","show") -> #REF!
A195: =#REF! -> #REF! | B195: % | C195: =#REF! -> #REF! | F195: =#REF! -> #REF! | I195: =#REF! -> #REF! | L195: =#REF! -> #REF! | O195: =#REF! -> #REF! | R195: =C195+F195+I195+L195+O195 -> #REF! | S195: =#REF! -> #REF! | V195: =IF(S195=0,"hide","show") -> #REF!
A196: =#REF! -> #REF! | B196: % | C196: =#REF! -> #REF! | F196: =#REF! -> #REF! | I196: =#REF! -> #REF! | L196: =#REF! -> #REF! | O196: =#REF! -> #REF! | R196: =C196+F196+I196+L196+O196 -> #REF! | S196: =#REF! -> #REF! | V196: =IF(S196=0,"hide","show") -> #REF!
A197: =#REF! -> #REF! | B197: % | C197: =#REF! -> #REF! | F197: =#REF! -> #REF! | I197: =#REF! -> #REF! | L197: =#REF! -> #REF! | O197: =#REF! -> #REF! | R197: =C197+F197+I197+L197+O197 -> #REF! | S197: =#REF! -> #REF! | V197: =IF(S197=0,"hide","show") -> #REF!
A198: =#REF! -> #REF! | B198: % | C198: =#REF! -> #REF! | F198: =#REF! -> #REF! | I198: =#REF! -> #REF! | L198: =#REF! -> #REF! | O198: =#REF! -> #REF! | R198: =C198+F198+I198+L198+O198 -> #REF! | S198: =#REF! -> #REF! | V198: =IF(S198=0,"hide","show") -> #REF!
V199: =IF(SUM(S201:S205)=0,"hide","show") -> #REF!
A200: =#REF! -> #REF! | V200: =IF(SUM(S201:S205)=0,"hide","show") -> #REF!
A201: =#REF! -> #REF! | B201: % | C201: =#REF! -> #REF! | F201: =#REF! -> #REF! | I201: =#REF! -> #REF! | L201: =#REF! -> #REF! | O201: =#REF! -> #REF! | R201: =C201+F201+I201+L201+O201 -> #REF! | S201: =#REF! -> #REF! | V201: =IF(S201=0,"hide","show") -> #REF!
A202: =#REF! -> #REF! | B202: % | C202: =#REF! -> #REF! | F202: =#REF! -> #REF! | I202: =#REF! -> #REF! | L202: =#REF! -> #REF! | O202: =#REF! -> #REF! | R202: =C202+F202+I202+L202+O202 -> #REF! | S202: =#REF! -> #REF! | V202: =IF(S202=0,"hide","show") -> #REF!
A203: =#REF! -> #REF! | B203: % | C203: =#REF! -> #REF! | F203: =#REF! -> #REF! | I203: =#REF! -> #REF! | L203: =#REF! -> #REF! | O203: =#REF! -> #REF! | R203: =C203+F203+I203+L203+O203 -> #REF! | S203: =#REF! -> #REF! | V203: =IF(S203=0,"hide","show") -> #REF!
A204: =#REF! -> #REF! | B204: % | C204: =#REF! -> #REF! | F204: =#REF! -> #REF! | I204: =#REF! -> #REF! | L204: =#REF! -> #REF! | O204: =#REF! -> #REF! | R204: =C204+F204+I204+L204+O204 -> #REF! | S204: =#REF! -> #REF! | V204: =IF(S204=0,"hide","show") -> #REF!
A205: =#REF! -> #REF! | B205: % | C205: =#REF! -> #REF! | F205: =#REF! -> #REF! | I205: =#REF! -> #REF! | L205: =#REF! -> #REF! | O205: =#REF! -> #REF! | R205: =C205+F205+I205+L205+O205 -> #REF! | S205: =#REF! -> #REF! | V205: =IF(S205=0,"hide","show") -> #REF!
V206: =IF(SUM(S208:S212)=0,"hide","show") -> #REF!
A207: =#REF! -> #REF! | V207: =IF(SUM(S208:S212)=0,"hide","show") -> #REF!
A208: =#REF! -> #REF! | B208: % | C208: =#REF! -> #REF! | F208: =#REF! -> #REF! | I208: =#REF! -> #REF! | L208: =#REF! -> #REF! | O208: =#REF! -> #REF! | R208: =C208+F208+I208+L208+O208 -> #REF! | S208: =#REF! -> #REF! | V208: =IF(S208=0,"hide","show") -> #REF!
A209: =#REF! -> #REF! | B209: % | C209: =#REF! -> #REF! | F209: =#REF! -> #REF! | I209: =#REF! -> #REF! | L209: =#REF! -> #REF! | O209: =#REF! -> #REF! | R209: =C209+F209+I209+L209+O209 -> #REF! | S209: =#REF! -> #REF! | V209: =IF(S209=0,"hide","show") -> #REF!
A210: =#REF! -> #REF! | B210: % | C210: =#REF! -> #REF! | F210: =#REF! -> #REF! | I210: =#REF! -> #REF! | L210: =#REF! -> #REF! | O210: =#REF! -> #REF! | R210: =C210+F210+I210+L210+O210 -> #REF! | S210: =#REF! -> #REF! | V210: =IF(S210=0,"hide","show") -> #REF!
A211: =#REF! -> #REF! | B211: % | C211: =#REF! -> #REF! | F211: =#REF! -> #REF! | I211: =#REF! -> #REF! | L211: =#REF! -> #REF! | O211: =#REF! -> #REF! | R211: =C211+F211+I211+L211+O211 -> #REF! | S211: =#REF! -> #REF! | V211: =IF(S211=0,"hide","show") -> #REF!
A212: =#REF! -> #REF! | B212: % | C212: =#REF! -> #REF! | F212: =#REF! -> #REF! | I212: =#REF! -> #REF! | L212: =#REF! -> #REF! | O212: =#REF! -> #REF! | R212: =C212+F212+I212+L212+O212 -> #REF! | S212: =#REF! -> #REF! | V212: =IF(S212=0,"hide","show") -> #REF!
V213: =IF(SUM(S215:S219)=0,"hide","show") -> #REF!
A214: =#REF! -> #REF! | V214: =IF(SUM(S215:S219)=0,"hide","show") -> #REF!
A215: =#REF! -> #REF! | B215: % | C215: =#REF! -> #REF! | F215: =#REF! -> #REF! | I215: =#REF! -> #REF! | L215: =#REF! -> #REF! | O215: =#REF! -> #REF! | R215: =C215+F215+I215+L215+O215 -> #REF! | S215: =#REF! -> #REF! | V215: =IF(S215=0,"hide","show") -> #REF!
A216: =#REF! -> #REF! | B216: % | C216: =#REF! -> #REF! | F216: =#REF! -> #REF! | I216: =#REF! -> #REF! | L216: =#REF! -> #REF! | O216: =#REF! -> #REF! | R216: =C216+F216+I216+L216+O216 -> #REF! | S216: =#REF! -> #REF! | V216: =IF(S216=0,"hide","show") -> #REF!
A217: =#REF! -> #REF! | B217: % | C217: =#REF! -> #REF! | F217: =#REF! -> #REF! | I217: =#REF! -> #REF! | L217: =#REF! -> #REF! | O217: =#REF! -> #REF! | R217: =C217+F217+I217+L217+O217 -> #REF! | S217: =#REF! -> #REF! | V217: =IF(S217=0,"hide","show") -> #REF!
A218: =#REF! -> #REF! | B218: % | C218: =#REF! -> #REF! | F218: =#REF! -> #REF! | I218: =#REF! -> #REF! | L218: =#REF! -> #REF! | O218: =#REF! -> #REF! | R218: =C218+F218+I218+L218+O218 -> #REF! | S218: =#REF! -> #REF! | V218: =IF(S218=0,"hide","show") -> #REF!
A219: =#REF! -> #REF! | B219: % | C219: =#REF! -> #REF! | F219: =#REF! -> #REF! | I219: =#REF! -> #REF! | L219: =#REF! -> #REF! | O219: =#REF! -> #REF! | R219: =C219+F219+I219+L219+O219 -> #REF! | S219: =#REF! -> #REF! | V219: =IF(S219=0,"hide","show") -> #REF!
V220: =IF(SUM(S222:S228)=0,"hide","show") -> #REF!
A221: =#REF! -> #REF! | C221: =SUM(C13:C19) -> #REF! | F221: =SUM(F13:F19) -> #REF! | I221: =SUM(I13:I19) -> #REF! | L221: =SUM(L13:L19) -> #REF! | O221: =SUM(O13:O19) -> #REF! | R221: =C221+F221+I221+L221+O221 -> #REF! | S221: =#REF! -> #REF! | V221: =IF(S221=0,"hide","show") -> #REF!
A222: =#REF! -> #REF! | C222: =SUM(C20:C26) -> #REF! | F222: =SUM(F20:F26) -> #REF! | I222: =SUM(I20:I26) -> #REF! | L222: =SUM(L20:L26) -> #REF! | O222: =SUM(O20:O26) -> #REF! | R222: =C222+F222+I222+L222+O222 -> #REF! | S222: =#REF! -> #REF! | V222: =IF(S222=0,"hide","show") -> #REF!
A223: =#REF! -> #REF! | C223: =SUM(C28:C115) -> #REF! | F223: =SUM(F28:F115) -> #REF! | I223: =SUM(I28:I115) -> #REF! | L223: =SUM(L28:L115) -> #REF! | O223: =SUM(O28:O115) -> #REF! | R223: =C223+F223+I223+L223+O223 -> #REF! | S223: =#REF! -> #REF! | V223: =IF(S223=0,"hide","show") -> #REF!
A224: =#REF! -> #REF! | C224: =SUM(C116:C191) -> #REF! | F224: =SUM(F116:F191) -> #REF! | I224: =SUM(I116:I191) -> #REF! | L224: =SUM(L116:L191) -> #REF! | O224: =SUM(O116:O191) -> #REF! | R224: =C224+F224+I224+L224+O224 -> #REF! | S224: =#REF! -> #REF! | V224: =IF(S224=0,"hide","show") -> #REF!
A225: =#REF! -> #REF! | C225: =SUM(C193:C199) -> #REF! | F225: =SUM(F193:F199) -> #REF! | I225: =SUM(I193:I199) -> #REF! | L225: =SUM(L193:L199) -> #REF! | O225: =SUM(O193:O199) -> #REF! | R225: =C225+F225+I225+L225+O225 -> #REF! | S225: =#REF! -> #REF! | V225: =IF(S225=0,"hide","show") -> #REF!
A226: =#REF! -> #REF! | C226: =SUM(C200:C206) -> #REF! | F226: =SUM(F200:F206) -> #REF! | I226: =SUM(I200:I206) -> #REF! | L226: =SUM(L200:L206) -> #REF! | O226: =SUM(O200:O206) -> #REF! | R226: =C226+F226+I226+L226+O226 -> #REF! | S226: =#REF! -> #REF! | V226: =IF(S226=0,"hide","show") -> #REF!
A227: =#REF! -> #REF! | C227: =SUM(C207:C213) -> #REF! | F227: =SUM(F207:F213) -> #REF! | I227: =SUM(I207:I213) -> #REF! | L227: =SUM(L207:L213) -> #REF! | O227: =SUM(O207:O213) -> #REF! | R227: =C227+F227+I227+L227+O227 -> #REF! | S227: =#REF! -> #REF! | V227: =IF(S227=0,"hide","show") -> #REF!
A228: =#REF! -> #REF! | C228: =SUM(C214:C219) -> #REF! | F228: =SUM(F214:F219) -> #REF! | I228: =SUM(I214:I219) -> #REF! | L228: =SUM(L214:L219) -> #REF! | O228: =SUM(O214:O219) -> #REF! | R228: =C228+F228+I228+L228+O228 -> #REF! | S228: =#REF! -> #REF! | V228: =IF(S228=0,"hide","show") -> #REF!
V229: =IF(S230=0,"hide","show") -> #REF!
A230: Total Labor | C230: =SUM(C12:C219)/100% -> #REF! | F230: =SUM(F12:F219)/100% -> #REF! | I230: =SUM(I12:I219)/100% -> #REF! | L230: =SUM(L12:L219)/100% -> #REF! | O230: =SUM(O12:O219)/100% -> #REF! | R230: =SUM(R20:R219)/100% -> #REF! | S230: =SUM(S13:S219)/100% -> #REF! | T230: =SUM(S12:S219) -> #REF! | V230: =IF(S230=0,"hide","show") -> #REF!

Sheet Total Budget by Sponsored Class
B1: =Assumptions!B8 -> Partners of America
B2: =Assumptions!B9 -> DONOR: | C2: =Assumptions!C9 -> USDOL
B3: =Assumptions!B10 -> Country: | C3: =Assumptions!C10 -> Ecuador
B4: =Assumptions!B11 -> Program Name: | C4: =Assumptions!C11 -> Project to Improve Adherence to International Labor Standards in the Agricultural Sector in Ecuador
B5: =Assumptions!B12 -> Grant Number: | C5: =Assumptions!C12 -> FOA-ILAB-23-28
B6: =Assumptions!B13 -> Period of Performance: | C6: =Assumptions!C13 -> 48 months | H6: =Assumptions!G13 -> 0
B8: TOTAL BUDGET SUMMARY BY SPONSORED CLASS
H10: US COSTS for ION | I10: 78 - 12345678
A12: SF424a | B12: Sponsored Class | C12: Description | D12: G/L | E12: Description | H12: Total | I12: =#REF! -> #REF! | L12: =#REF! -> #REF! | O12: =#REF! -> #REF! | R12: =#REF! -> #REF! | U12: =#REF! -> #REF!
A14: Personnel | B14: 610000 | C14: Salaries & Wages: Faculty and Senior Staff | H14: =SUM(I14,L14,O14,R14,U14) -> #REF! | I14: =SUM('US Costs by Sponsored Class'!I14,'Incountry Costs by GL USD'!I15) -> #REF! | L14: =SUM('US Costs by Sponsored Class'!L14,'Incountry Costs by GL USD'!L15) -> #REF! | O14: =SUM('US Costs by Sponsored Class'!O14,'Incountry Costs by GL USD'!O15) -> #REF! | R14: =SUM('US Costs by Sponsored Class'!R14,'Incountry Costs by GL USD'!R15) -> #REF! | U14: =SUM('US Costs by Sponsored Class'!U14,'Incountry Costs by GL USD'!U15) -> #REF!
B15: 612000 | C15: Salaries & Wages: Administrative Staff | H15: =SUM(I15,L15,O15,R15,U15) -> #REF! | I15: ='US Costs by Sponsored Class'!I15 -> #REF! | L15: ='US Costs by Sponsored Class'!L15 -> #REF! | O15: ='US Costs by Sponsored Class'!O15 -> #REF! | R15: ='US Costs by Sponsored Class'!R15 -> #REF! | U15: ='US Costs by Sponsored Class'!U15 -> #REF!
A17: Fringe Benefits | B17: 620000 | C17: Fringe Benefits | H17: =SUM(I17,L17,O17,R17,U17) -> #REF! | I17: =SUM('US Costs by Sponsored Class'!I16,'Incountry Costs by GL USD'!I16) -> #REF! | L17: =SUM('US Costs by Sponsored Class'!L16,'Incountry Costs by GL USD'!L16) -> #REF! | O17: =SUM('US Costs by Sponsored Class'!O16,'Incountry Costs by GL USD'!O16) -> #REF! | R17: =SUM('US Costs by Sponsored Class'!R16,'Incountry Costs by GL USD'!R16) -> #REF! | U17: =SUM('US Costs by Sponsored Class'!U16,'Incountry Costs by GL USD'!U16) -> #REF!
A19: Travel | B19: 652000 | C19: Travel Domestic | H19: =SUM(I19,L19,O19,R19,U19) -> #REF! | I19: =SUM('US Costs by Sponsored Class'!I18,'Incountry Costs by GL USD'!I17) -> #REF! | L19: =SUM('US Costs by Sponsored Class'!L18,'Incountry Costs by GL USD'!L17) -> #REF! | O19: =SUM('US Costs by Sponsored Class'!O18,'Incountry Costs by GL USD'!O17) -> #REF! | R19: =SUM('US Costs by Sponsored Class'!R18,'Incountry Costs by GL USD'!R17) -> #REF! | U19: =SUM('US Costs by Sponsored Class'!U18,'Incountry Costs by GL USD'!U17) -> #REF!
B20: 652100 | C20: Travel Foreign | H20: =SUM(I20,L20,O20,R20,U20) -> #REF! | I20: =SUM('US Costs by Sponsored Class'!H19,'Incountry Costs by GL USD'!I18:I19) -> #REF! | L20: =SUM('US Costs by Sponsored Class'!K19,'Incountry Costs by GL USD'!L18:L19) -> #REF! | O20: =SUM('US Costs by Sponsored Class'!N19,'Incountry Costs by GL USD'!O18:O19) -> #REF! | R20: =SUM('US Costs by Sponsored Class'!Q19,'Incountry Costs by GL USD'!R18:R19) -> #REF! | U20: =SUM('US Costs by Sponsored Class'!T19,'Incountry Costs by GL USD'!U18:U19) -> #REF!
A22: Supplies | B22: 630000 | C22: Supplies & Materials | H22: =SUM(I22,L22,O22,R22,U22) -> #REF! | I22: =SUM('US Costs by Sponsored Class'!I21:I22,'Incountry Costs by GL USD'!I20:I29) -> #REF! | L22: =SUM('US Costs by Sponsored Class'!L21:L22,'Incountry Costs by GL USD'!L20:L29) -> #REF! | O22: =SUM('US Costs by Sponsored Class'!O21:O22,'Incountry Costs by GL USD'!O20:O29) -> #REF! | R22: =SUM('US Costs by Sponsored Class'!R21:R22,'Incountry Costs by GL USD'!R20:R29) -> #REF! | U22: =SUM('US Costs by Sponsored Class'!U21:U22,'Incountry Costs by GL USD'!U20:U29) -> #REF!
D24: 633032 | E24: Office Supplies
D25: 633037 | E25: Publications/Journals/Subscriptions
D26: 635001 | E26: Electricity
D27: 635010 | E27: Utilities: Water
D28: 640282 | E28: Delivery/Courier Service
A30: Equipment | B30: 653400 | C30: Equipment | H30: =SUM(I30,L30,O30,R30,U30) -> #REF! | I30: =SUM('US Costs by Sponsored Class'!I29,'Incountry Costs by GL USD'!I30) -> #REF! | L30: =SUM('US Costs by Sponsored Class'!L29,'Incountry Costs by GL USD'!L30) -> #REF! | O30: =SUM('US Costs by Sponsored Class'!O29,'Incountry Costs by GL USD'!O30) -> #REF! | R30: =SUM('US Costs by Sponsored Class'!R29,'Incountry Costs by GL USD'!R30) -> #REF! | U30: =SUM('US Costs by Sponsored Class'!U29,'Incountry Costs by GL USD'!U30) -> #REF!
A32: Contractual | B32: 640300 | C32: Contractual Services | H32: =SUM(I32,L32,O32,R32,U32) -> #REF! | I32: =SUM('US Costs by Sponsored Class'!I31,'Incountry Costs by GL USD'!I32:I44) -> #REF! | L32: =SUM('US Costs by Sponsored Class'!L31,'Incountry Costs by GL USD'!L32:L44) -> #REF! | O32: =SUM('US Costs by Sponsored Class'!O31,'Incountry Costs by GL USD'!O32:O44) -> #REF! | R32: =SUM('US Costs by Sponsored Class'!R31,'Incountry Costs by GL USD'!R32:R44) -> #REF! | U32: =SUM('US Costs by Sponsored Class'!U31,'Incountry Costs by GL USD'!U32:U44) -> #REF!
B33: 640500 | C33: Consultant | H33: =SUM(I33,L33,O33,R33,U33) -> #REF! | I33: =SUM('US Costs by Sponsored Class'!I32,'Incountry Costs by GL USD'!I45) -> #REF! | L33: =SUM('US Costs by Sponsored Class'!L32,'Incountry Costs by GL USD'!L45) -> #REF! | O33: =SUM('US Costs by Sponsored Class'!O32,'Incountry Costs by GL USD'!O45) -> #REF! | R33: =SUM('US Costs by Sponsored Class'!R32,'Incountry Costs by GL USD'!R45) -> #REF! | U33: =SUM('US Costs by Sponsored Class'!U32,'Incountry Costs by GL USD'!U45) -> #REF!
B34: 642400 | C34: Subaward | H34: =SUM(I34,L34,O34,R34,U34) -> #REF! | I34: =SUM('US Costs by Sponsored Class'!I33,'Incountry Costs by GL USD'!I46) -> #REF! | L34: =SUM('US Costs by Sponsored Class'!L33,'Incountry Costs by GL USD'!L46) -> #REF! | O34: =SUM('US Costs by Sponsored Class'!O33,'Incountry Costs by GL USD'!O46) -> #REF! | R34: =SUM('US Costs by Sponsored Class'!R33,'Incountry Costs by GL USD'!R46) -> #REF! | U34: =SUM('US Costs by Sponsored Class'!U33,'Incountry Costs by GL USD'!U46) -> #REF!
B35: 637000 | C35: Repairs & Maintenance | H35: =SUM(I35,L35,O35,R35,U35) -> #REF! | I35: =SUM('US Costs by Sponsored Class'!I34,'Incountry Costs by GL USD'!I31) -> #REF! | L35: =SUM('US Costs by Sponsored Class'!L34,'Incountry Costs by GL USD'!L31) -> #REF! | O35: =SUM('US Costs by Sponsored Class'!O34,'Incountry Costs by GL USD'!O31) -> #REF! | R35: =SUM('US Costs by Sponsored Class'!R34,'Incountry Costs by GL USD'!R31) -> #REF! | U35: =SUM('US Costs by Sponsored Class'!U34,'Incountry Costs by GL USD'!U31) -> #REF!
A37: Other | B37: 640102 | C37: Leased Facilities External | H37: =SUM(I37,L37,O37,R37,U37) -> #REF! | I37: =SUM('US Costs by Sponsored Class'!I36,'Incountry Costs by GL USD'!I47) -> #REF! | L37: =SUM('US Costs by Sponsored Class'!L36,'Incountry Costs by GL USD'!L47) -> #REF! | O37: =SUM('US Costs by Sponsored Class'!O36,'Incountry Costs by GL USD'!O47) -> #REF! | R37: =SUM('US Costs by Sponsored Class'!R36,'Incountry Costs by GL USD'!R47) -> #REF! | U37: =SUM('US Costs by Sponsored Class'!U36,'Incountry Costs by GL USD'!U47) -> #REF!
B38: 641400 | C38: Telecommunications | H38: =SUM(I38,L38,O38,R38,U38) -> #REF! | I38: =SUM('US Costs by Sponsored Class'!I37,'Incountry Costs by GL USD'!I48) -> #REF! | L38: =SUM('US Costs by Sponsored Class'!L37,'Incountry Costs by GL USD'!L48) -> #REF! | O38: =SUM('US Costs by Sponsored Class'!O37,'Incountry Costs by GL USD'!O48) -> #REF! | R38: =SUM('US Costs by Sponsored Class'!R37,'Incountry Costs by GL USD'!R48) -> #REF! | U38: =SUM('US Costs by Sponsored Class'!U37,'Incountry Costs by GL USD'!U48) -> #REF!
B39: 642500 | C39: Other Expenses | H39: =SUM(I39,L39,O39,R39,U39) -> #REF! | I39: =SUM('US Costs by Sponsored Class'!I38,'Incountry Costs by GL USD'!I49:I54) -> #REF! | L39: =SUM('US Costs by Sponsored Class'!L38,'Incountry Costs by GL USD'!L49:L54) -> #REF! | O39: =SUM('US Costs by Sponsored Class'!O38,'Incountry Costs by GL USD'!O49:O54) -> #REF! | R39: =SUM('US Costs by Sponsored Class'!R38,'Incountry Costs by GL USD'!R49:R54) -> #REF! | U39: =SUM('US Costs by Sponsored Class'!U38,'Incountry Costs by GL USD'!U49:U54) -> #REF!
B40: 643000 | C40: Other Expenses (Excluded from F&A) | H40: =SUM(I40,L40,O40,R40,U40) -> #REF! | I40: =SUM('US Costs by Sponsored Class'!I39,'Incountry Costs by GL USD'!I55:I56) -> #REF! | L40: =SUM('US Costs by Sponsored Class'!L39,'Incountry Costs by GL USD'!L55:L56) -> #REF! | O40: =SUM('US Costs by Sponsored Class'!O39,'Incountry Costs by GL USD'!O55:O56) -> #REF! | R40: =SUM('US Costs by Sponsored Class'!R39,'Incountry Costs by GL USD'!R55:R56) -> #REF! | U40: =SUM('US Costs by Sponsored Class'!U39,'Incountry Costs by GL USD'!U55:U56) -> #REF!
B42: Subtotal | H42: =SUM(I42,L42,O42,R42,U42) -> #REF! | I42: =SUM(I13:I41) -> #REF! | L42: =SUM(L13:L41) -> #REF! | O42: =SUM(O13:O41) -> #REF! | R42: =SUM(R13:R41) -> #REF! | U42: =SUM(U13:U41) -> #REF!
B44: 690007 | C44: Service Center | H44: =SUM(I44,L44,O44,R44,U44) -> #REF! | I44: ='US Costs by Sponsored Class'!I43 -> #REF! | L44: ='US Costs by Sponsored Class'!L43 -> #REF! | O44: ='US Costs by Sponsored Class'!O43 -> #REF! | R44: ='US Costs by Sponsored Class'!R43 -> #REF! | U44: ='US Costs by Sponsored Class'!U43 -> #REF!
B46: 699999 | C46: F&A | H46: =SUM(I46,L46,O46,R46,U46) -> #REF! | I46: ='US Costs by Sponsored Class'!I45 -> #REF! | L46: ='US Costs by Sponsored Class'!L45 -> #REF! | O46: ='US Costs by Sponsored Class'!O45 -> #REF! | R46: ='US Costs by Sponsored Class'!R45 -> #REF! | U46: ='US Costs by Sponsored Class'!U45 -> #REF!
B48: Total per year | H48: =SUM(I48,L48,O48,R48,U48) -> #REF! | I48: =SUM(I42:I47) -> #REF! | L48: =SUM(L42:L47) -> #REF! | O48: =SUM(O42:O47) -> #REF! | R48: =SUM(R42:R47) -> #REF! | U48: =SUM(U42:U47) -> #REF!
B50: Calculation check

Sheet US Costs by Sponsored Class
B1: =Assumptions!B8 -> Partners of America
B2: =Assumptions!B9 -> DONOR: | C2: =Assumptions!C9 -> USDOL
B3: =Assumptions!B10 -> Country: | C3: =Assumptions!C10 -> Ecuador
B4: =Assumptions!B11 -> Program Name: | C4: =Assumptions!C11 -> Project to Improve Adherence to International Labor Standards in the Agricultural Sector in Ecuador
B5: =Assumptions!B12 -> Grant Number: | C5: =Assumptions!C12 -> FOA-ILAB-23-28
B6: =Assumptions!B13 -> Period of Performance: | C6: =Assumptions!C13 -> 48 months | E6: =Assumptions!G13 -> 0
B8: BUDGET SUMMARY BY G/L
D10: US COSTS for ION | E10: 78 - 12345678
A12: SF424a | B12: Sponsored Class | C12: Description | D12: G/L | E12: Description | H12: Workplan Year Budget | I12: =#REF! -> #REF! | L12: =#REF! -> #REF! | O12: =#REF! -> #REF! | R12: =#REF! -> #REF! | U12: =#REF! -> #REF!
A14: Personnel | B14: 610000 | C14: Salaries & Wages: Faculty and Senior Staff | D14: 613001 | E14: Salary: Non-Administrative Staff | H14: =SUM(I14,L14,O14,R14,U14) -> #REF! | I14: =SUMIF(#REF!,$B$14,#REF!) -> #REF! | L14: =SUMIF(#REF!,$B$14,#REF!) -> #REF! | O14: =SUMIF(#REF!,$B$14,#REF!) -> #REF! | R14: =SUMIF(#REF!,$B$14,#REF!) -> #REF! | U14: =SUMIF(#REF!,$B$14,#REF!) -> #REF!
B15: 612000 | C15: Salaries & Wages: Administrative Staff | D15: 612001 | E15: Salary: Administrative Staff | H15: =SUM(I15,L15,O15,R15,U15) -> #REF! | I15: =SUMIF(#REF!,$B$15,#REF!) -> #REF! | L15: =SUMIF(#REF!,$B$15,#REF!) -> #REF! | O15: =SUMIF(#REF!,$B$15,#REF!) -> #REF! | R15: =SUMIF(#REF!,$B$15,#REF!) -> #REF! | U15: =SUMIF(#REF!,$B$15,#REF!) -> #REF!
A16: Fringe Benefits | B16: 620000 | C16: Fringe Benefits | D16: 620001 | E16: Fringe Benefits: Staff | H16: =SUM(I16,L16,O16,R16,U16) -> #REF! | I16: =SUMIF(#REF!,$B$16,#REF!) -> #REF! | L16: =SUMIF(#REF!,$B$16,#REF!) -> #REF! | O16: =SUMIF(#REF!,$B$16,#REF!) -> #REF! | R16: =SUMIF(#REF!,$B$16,#REF!) -> #REF! | U16: =SUMIF(#REF!,$B$16,#REF!) -> #REF!
D17: 620002 | E17: Fringe Benefits: Allowances
A18: Travel | B18: 652000 | C18: Travel Domestic | H18: =SUM(I18,L18,O18,R18,U18) -> #REF! | I18: =SUMIF(#REF!,$B$18,#REF!) -> #REF! | L18: =SUMIF(#REF!,$B$18,#REF!) -> #REF! | O18: =SUMIF(#REF!,$B$18,#REF!) -> #REF! | R18: =SUMIF(#REF!,$B$18,#REF!) -> #REF! | U18: =SUMIF(#REF!,$B$18,#REF!) -> #REF!
B19: 652100 | C19: Travel Foreign | H19: =SUM(I19,L19,O19,R19,U19) -> #REF! | I19: =SUMIF(#REF!,$B$19,#REF!) -> #REF! | L19: =SUMIF(#REF!,$B$19,#REF!) -> #REF! | O19: =SUMIF(#REF!,$B$19,#REF!) -> #REF! | R19: =SUMIF(#REF!,$B$19,#REF!) -> #REF! | U19: =SUMIF(#REF!,$B$19,#REF!) -> #REF!
A21: Supplies | B21: 630000 | C21: Supplies & Materials | D21: 631001 | E21: Furniture | H21: =SUM(I21,L21,O21,R21,U21) -> #REF! | I21: =SUMIF(#REF!,$B$21,#REF!) -> #REF! | L21: =SUMIF(#REF!,$B$21,#REF!) -> #REF! | O21: =SUMIF(#REF!,$B$21,#REF!) -> #REF! | R21: =SUMIF(#REF!,$B$21,#REF!) -> #REF! | U21: =SUMIF(#REF!,$B$21,#REF!) -> #REF!
D22: 631003 | E22: Non-capital PC purchases | H22: =SUM(I22,L22,O22,R22,U22) -> #REF! | I22: =SUMIF(#REF!,$B$21,#REF!) -> #REF! | L22: =SUMIF(#REF!,$B$21,#REF!) -> #REF! | O22: =SUMIF(#REF!,$B$21,#REF!) -> #REF! | R22: =SUMIF(#REF!,$B$21,#REF!) -> #REF! | U22: =SUMIF(#REF!,$B$21,#REF!) -> #REF!
D23: 633032 | E23: Office Supplies | H23: =SUM(I23,L23,O23,R23,U23,#REF!,#REF!,#REF!,#REF!,#REF!) -> #REF!
D24: 633037 | E24: Publications/Journals/Subscriptions | H24: =SUM(I24,L24,O24,R24,U24,#REF!,#REF!,#REF!,#REF!,#REF!) -> #REF!
D25: 635001 | E25: Electricity | H25: =SUM(I25,L25,O25,R25,U25,#REF!,#REF!,#REF!,#REF!,#REF!) -> #REF!
D26: 635010 | E26: Utilities: Water | H26: =SUM(I26,L26,O26,R26,U26,#REF!,#REF!,#REF!,#REF!,#REF!) -> #REF!
D27: 640282 | E27: Delivery/Courier Service | H27: =SUM(I27,L27,O27,R27,U27,#REF!,#REF!,#REF!,#REF!,#REF!) -> #REF!
A29: Equipment | B29: 653400 | C29: Equipment | H29: =SUM(I29,L29,O29,R29,U29) -> #REF! | I29: =SUMIF(#REF!,$B$29,#REF!) -> #REF! | L29: =SUMIF(#REF!,$B$29,#REF!) -> #REF! | O29: =SUMIF(#REF!,$B$29,#REF!) -> #REF! | R29: =SUMIF(#REF!,$B$29,#REF!) -> #REF! | U29: =SUMIF(#REF!,$B$29,#REF!) -> #REF!
A31: Contractual | B31: 640300 | C31: Contractual Services | H31: =SUM(I31,L31,O31,R31,U31) -> #REF! | I31: =SUMIF(#REF!,$B$31,#REF!) -> #REF! | L31: =SUMIF(#REF!,$B$31,#REF!) -> #REF! | O31: =SUMIF(#REF!,$B$31,#REF!) -> #REF! | R31: =SUMIF(#REF!,$B$31,#REF!) -> #REF! | U31: =SUMIF(#REF!,$B$31,#REF!) -> #REF!
B32: 640500 | C32: Consultant | H32: =SUM(I32,L32,O32,R32,U32) -> #REF! | I32: =SUMIF(#REF!,$B$32,#REF!) -> #REF! | L32: =SUMIF(#REF!,$B$32,#REF!) -> #REF! | O32: =SUMIF(#REF!,$B$32,#REF!) -> #REF! | R32: =SUMIF(#REF!,$B$32,#REF!) -> #REF! | U32: =SUMIF(#REF!,$B$32,#REF!) -> #REF!
B33: 642400 | C33: Subaward | H33: =SUM(I33,L33,O33,R33,U33) -> #REF! | I33: =SUMIF(#REF!,$B$33,#REF!) -> #REF! | L33: =SUMIF(#REF!,$B$33,#REF!) -> #REF! | O33: =SUMIF(#REF!,$B$33,#REF!) -> #REF! | R33: =SUMIF(#REF!,$B$33,#REF!) -> #REF! | U33: =SUMIF(#REF!,$B$33,#REF!) -> #REF!
B34: 637000 | C34: Repairs & Maintenance | H34: =SUM(I34,L34,O34,R34,U34) -> #REF! | I34: =SUMIF(#REF!,$B$34,#REF!) -> #REF! | L34: =SUMIF(#REF!,$B$34,#REF!) -> #REF! | O34: =SUMIF(#REF!,$B$34,#REF!) -> #REF! | R34: =SUMIF(#REF!,$B$34,#REF!) -> #REF! | U34: =SUMIF(#REF!,$B$34,#REF!) -> #REF!
A36: Other | B36: 640102 | C36: Leased Facilities External | H36: =SUM(I36,L36,O36,R36,U36) -> #REF! | I36: =SUMIF(#REF!,$B$36,#REF!) -> #REF! | L36: =SUMIF(#REF!,$B$36,#REF!) -> #REF! | O36: =SUMIF(#REF!,$B$36,#REF!) -> #REF! | R36: =SUMIF(#REF!,$B$36,#REF!) -> #REF! | U36: =SUMIF(#REF!,$B$36,#REF!) -> #REF!
B37: 641400 | C37: Telecommunications | H37: =SUM(I37,L37,O37,R37,U37) -> #REF! | I37: =SUMIF(#REF!,$B$37,#REF!) -> #REF! | L37: =SUMIF(#REF!,$B$37,#REF!) -> #REF! | O37: =SUMIF(#REF!,$B$37,#REF!) -> #REF! | R37: =SUMIF(#REF!,$B$37,#REF!) -> #REF! | U37: =SUMIF(#REF!,$B$37,#REF!) -> #REF!
B38: 642500 | C38: Other Expenses | H38: =SUM(I38,L38,O38,R38,U38) -> #REF! | I38: =SUMIF(#REF!,$B$38,#REF!) -> #REF! | L38: =SUMIF(#REF!,$B$38,#REF!) -> #REF! | O38: =SUMIF(#REF!,$B$38,#REF!) -> #REF! | R38: =SUMIF(#REF!,$B$38,#REF!) -> #REF! | U38: =SUMIF(#REF!,$B$38,#REF!) -> #REF!
B39: 643000 | C39: Other Expenses (Excluded from F&A) | H39: =SUM(I39,L39,O39,R39,U39) -> #REF! | I39: =SUMIF(#REF!,$B$39,#REF!) -> #REF! | L39: =SUMIF(#REF!,$B$39,#REF!) -> #REF! | O39: =SUMIF(#REF!,$B$39,#REF!) -> #REF! | R39: =SUMIF(#REF!,$B$39,#REF!) -> #REF! | U39: =SUMIF(#REF!,$B$39,#REF!) -> #REF!
B41: Subtotal | H41: =SUM(I41,L41,O41,R41,U41) -> #REF! | I41: =SUM(L13:L40) -> #REF! | L41: =SUM(O13:O40) -> #REF! | O41: =SUM(R13:R40) -> #REF! | R41: =SUM(U13:U40) -> #REF! | U41: =SUM(X13:X40) -> 0
B43: 690007 | C43: Service Center | H43: =SUM(I43,L43,O43,R43,U43) -> #REF! | I43: =SUMIF(#REF!,$B$43,#REF!) -> #REF! | L43: =SUMIF(#REF!,$B$43,#REF!) -> #REF! | O43: =SUMIF(#REF!,$B$43,#REF!) -> #REF! | R43: =SUMIF(#REF!,$B$43,#REF!) -> #REF! | U43: =SUMIF(#REF!,$B$43,#REF!) -> #REF!
B45: 699999 | C45: F&A | H45: =SUM(I45,L45,O45,R45,U45) -> #REF! | I45: =SUMIF(#REF!,$B$45,#REF!) -> #REF! | L45: =SUMIF(#REF!,$B$45,#REF!) -> #REF! | O45: =SUMIF(#REF!,$B$45,#REF!) -> #REF! | R45: =SUMIF(#REF!,$B$45,#REF!) -> #REF! | U45: =SUMIF(#REF!,$B$45,#REF!) -> #REF!
B47: Total per year | H47: =SUM(H41:H46) -> #REF! | I47: =SUM(I41:I46) -> #REF! | L47: =SUM(L41:L46) -> #REF! | O47: =SUM(O41:O46) -> #REF! | R47: =SUM(R41:R46) -> #REF! | U47: =SUM(U41:U46) -> #REF!
B49: Calculation check | I49: =SUM(#REF!,#REF!,#REF!) -> #REF! | L49: =SUM(#REF!,#REF!,#REF!) -> #REF! | O49: =SUM(#REF!,#REF!,#REF!) -> #REF! | R49: =SUM(#REF!,#REF!,#REF!) -> #REF! | U49: =SUM(#REF!,#REF!,#REF!) -> #REF!

Sheet Incountry Costs by GL USD
D1: Jhpiego Corporation
D2: =Assumptions!B9 -> DONOR: | E2: =Assumptions!C9 -> USDOL
D3: =Assumptions!B10 -> Country: | E3: =Assumptions!C10 -> Ecuador
D4: =Assumptions!B11 -> Program Name: | E4: =Assumptions!C11 -> Project to Improve Adherence to International Labor Standards in the Agricultural Sector in Ecuador
D5: =Assumptions!B12 -> Grant Number: | E5: =Assumptions!C12 -> FOA-ILAB-23-28
D6: =Assumptions!B13 -> Period of Performance: | E6: =Assumptions!C13 -> 48 months | H6: =Assumptions!G13 -> 0
D8: BUDGET SUMMARY BY G/L in USD
D10: IN-COUNTRY COSTS by Jhpiego FISCAL YEAR
E11: IN-COUNTRY ION: | I11: 21 - 987654321 | L11: 22 - 987654322 | O11: 23 - 987654323 | R11: 24 - 987654324 | U11: 25 - 987654325
A13: SF424a | B13: Sponsored Class | C13: Description | D13: G/L | E13: Description | H13: Workplan Year Budget | I13: =#REF! -> #REF! | L13: =#REF! -> #REF! | O13: =#REF! -> #REF! | R13: =#REF! -> #REF! | U13: =#REF! -> #REF!
A15: Personnel | B15: 610000 | C15: Salaries & Wages | D15: 616112 | E15: In-country Salaries | H15: =SUM(I15,L15,O15,R15,U15) -> #REF! | I15: =SUMIF(#REF!,$D$15,#REF!) -> #REF! | L15: =SUMIF(#REF!,$D$15,#REF!) -> #REF! | O15: =SUMIF(#REF!,$D$15,#REF!) -> #REF! | R15: =SUMIF(#REF!,$D$15,#REF!) -> #REF! | U15: =SUMIF(#REF!,$D$15,#REF!) -> #REF!
A16: Fringe Benefits | B16: 620000 | C16: Fringe Benefits | D16: 620112 | E16: In-country Fringe | H16: =SUM(I16,L16,O16,R16,U16) -> #REF! | I16: =SUMIF(#REF!,$D$16,#REF!) -> #REF! | L16: =SUMIF(#REF!,$D$16,#REF!) -> #REF! | O16: =SUMIF(#REF!,$D$16,#REF!) -> #REF! | R16: =SUMIF(#REF!,$D$16,#REF!) -> #REF! | U16: =SUMIF(#REF!,$D$16,#REF!) -> #REF!
A17: Travel | B17: 652000 | C17: Travel Domestic | D17: 652201 | E17: Trainee Travel | H17: =SUM(I17,L17,O17,R17,U17) -> #REF! | I17: =SUMIF(#REF!,$D$17,#REF!) -> #REF! | L17: =SUMIF(#REF!,$D$17,#REF!) -> #REF! | O17: =SUMIF(#REF!,$D$17,#REF!) -> #REF! | R17: =SUMIF(#REF!,$D$17,#REF!) -> #REF! | U17: =SUMIF(#REF!,$D$17,#REF!) -> #REF!
B18: 652100 | C18: Travel Foreign | D18: 652101 | E18: Travel Foreign | H18: =SUM(I18,L18,O18,R18,U18) -> #REF! | I18: =SUMIF(#REF!,$D$18,#REF!) -> #REF! | L18: =SUMIF(#REF!,$D$18,#REF!) -> #REF! | O18: =SUMIF(#REF!,$D$18,#REF!) -> #REF! | R18: =SUMIF(#REF!,$D$18,#REF!) -> #REF! | U18: =SUMIF(#REF!,$D$18,#REF!) -> #REF!
D19: 652102 | E19: Travel Overseas Local | H19: =SUM(I19,L19,O19,R19,U19) -> #REF! | I19: =SUMIF(#REF!,$D$19,#REF!) -> #REF! | L19: =SUMIF(#REF!,$D$19,#REF!) -> #REF! | O19: =SUMIF(#REF!,$D$19,#REF!) -> #REF! | R19: =SUMIF(#REF!,$D$19,#REF!) -> #REF! | U19: =SUMIF(#REF!,$D$19,#REF!) -> #REF!
A20: Supplies | B20: 630000 | C20: Supplies & Materials | D20: 631001 | E20: Furniture | H20: =SUM(I20,L20,O20,R20,U20) -> #REF! | I20: =SUMIF(#REF!,$D$20,#REF!) -> #REF! | L20: =SUMIF(#REF!,$D$20,#REF!) -> #REF! | O20: =SUMIF(#REF!,$D$20,#REF!) -> #REF! | R20: =SUMIF(#REF!,$D$20,#REF!) -> #REF! | U20: =SUMIF(#REF!,$D$20,#REF!) -> #REF!
B21: 630000 | C21: Supplies & Materials | D21: 631003 | E21: Non-capital PC purchases | H21: =SUM(I21,L21,O21,R21,U21) -> #REF! | I21: =SUMIF(#REF!,$D$21,#REF!) -> #REF! | L21: =SUMIF(#REF!,$D$21,#REF!) -> #REF! | O21: =SUMIF(#REF!,$D$21,#REF!) -> #REF! | R21: =SUMIF(#REF!,$D$21,#REF!) -> #REF! | U21: =SUMIF(#REF!,$D$21,#REF!) -> #REF!
B22: 630000 | C22: Supplies & Materials | D22: 633027 | E22: Supplies & Other PSC | H22: =SUM(I22,L22,O22,R22,U22) -> #REF! | I22: =SUMIF(#REF!,$D$22,#REF!) -> #REF! | J22: =SUMIF(#REF!,$D$22,#REF!) -> #REF! | K22: =SUMIF(#REF!,$D$22,#REF!) -> #REF! | L22: =SUMIF(#REF!,$D$22,#REF!) -> #REF! | M22: =SUMIF(#REF!,$D$22,#REF!) -> #REF! | N22: =SUMIF(#REF!,$D$22,#REF!) -> #REF! | O22: =SUMIF(#REF!,$D$22,#REF!) -> #REF! | P22: =SUMIF(#REF!,$D$22,#REF!) -> #REF! | ... W22: =SUMIF(#REF!,$D$22,#REF!) -> #REF!
B23: 630000 | C23: Supplies & Materials | D23: 633032 | E23: Office Supplies | H23: =SUM(I23,L23,O23,R23,U23) -> #REF! | I23: =SUMIF(#REF!,$D$23,#REF!) -> #REF! | L23: =SUMIF(#REF!,$D$23,#REF!) -> #REF! | O23: =SUMIF(#REF!,$D$23,#REF!) -> #REF! | R23: =SUMIF(#REF!,$D$23,#REF!) -> #REF! | U23: =SUMIF(#REF!,$D$23,#REF!) -> #REF!
B24: 630000 | C24: Supplies & Materials | D24: 630064 | E24: Medical Supplies | H24: =SUM(I24,L24,O24,R24,U24) -> #REF! | I24: 0 | L24: =SUMIF(#REF!,$D$23,#REF!) -> #REF! | O24: =SUMIF(#REF!,$D$23,#REF!) -> #REF! | R24: =SUMIF(#REF!,$D$23,#REF!) -> #REF! | U24: =SUMIF(#REF!,$D$23,#REF!) -> #REF!
B25: 630000 | C25: Supplies & Materials | D25: 633002 | E25: Expendable Supplies | H25: =SUM(I25,L25,O25,R25,U25) -> #REF! | I25: 0 | L25: =SUMIF(#REF!,$D$23,#REF!) -> #REF! | O25: =SUMIF(#REF!,$D$23,#REF!) -> #REF! | R25: =SUMIF(#REF!,$D$23,#REF!) -> #REF! | U25: =SUMIF(#REF!,$D$23,#REF!) -> #REF!
B26: 630000 | C26: Supplies & Materials | D26: 633037 | E26: Publications/Journals/Subscriptions | H26: =SUM(I26,L26,O26,R26,U26) -> #REF! | I26: =SUMIF(#REF!,$D$26,#REF!) -> #REF! | L26: =SUMIF(#REF!,$D$26,#REF!) -> #REF! | O26: =SUMIF(#REF!,$D$26,#REF!) -> #REF! | R26: =SUMIF(#REF!,$D$26,#REF!) -> #REF! | U26: =SUMIF(#REF!,$D$26,#REF!) -> #REF!
B27: 630000 | C27: Supplies & Materials | D27: 635001 | E27: Electricity | H27: =SUM(I27,L27,O27,R27,U27) -> #REF! | I27: =SUMIF(#REF!,$D$27,#REF!) -> #REF! | L27: =SUMIF(#REF!,$D$27,#REF!) -> #REF! | O27: =SUMIF(#REF!,$D$27,#REF!) -> #REF! | R27: =SUMIF(#REF!,$D$27,#REF!) -> #REF! | U27: =SUMIF(#REF!,$D$27,#REF!) -> #REF!
B28: 630000 | C28: Supplies & Materials | D28: 635010 | E28: Utilities: Water | H28: =SUM(I28,L28,O28,R28,U28) -> #REF! | I28: =SUMIF(#REF!,$D$28,#REF!) -> #REF! | L28: =SUMIF(#REF!,$D$28,#REF!) -> #REF! | O28: =SUMIF(#REF!,$D$28,#REF!) -> #REF! | R28: =SUMIF(#REF!,$D$28,#REF!) -> #REF! | U28: =SUMIF(#REF!,$D$28,#REF!) -> #REF!
B29: 630000 | C29: Supplies & Materials | D29: 640282 | E29: Delivery/Courier Service | H29: =SUM(I29,L29,O29,R29,U29) -> #REF! | I29: =SUMIF(#REF!,$D$29,#REF!) -> #REF! | L29: =SUMIF(#REF!,$D$29,#REF!) -> #REF! | O29: =SUMIF(#REF!,$D$29,#REF!) -> #REF! | R29: =SUMIF(#REF!,$D$29,#REF!) -> #REF! | U29: =SUMIF(#REF!,$D$29,#REF!) -> #REF!
A30: Equipment | B30: 653400 | C30: Equipment | D30: 631099 | E30: Equipment Purchases - SRM only | H30: =SUM(I30,L30,O30,R30,U30) -> #REF! | I30: =SUMIF(#REF!,$D$30,#REF!) -> #REF! | L30: =SUMIF(#REF!,$D$30,#REF!) -> #REF! | O30: =SUMIF(#REF!,$D$30,#REF!) -> #REF! | R30: =SUMIF(#REF!,$D$30,#REF!) -> #REF! | U30: =SUMIF(#REF!,$D$30,#REF!) -> #REF!
A31: Contractual | B31: 637000 | C31: Repairs & Maintenance | D31: 637001 | E31: Equipment Maintenance Agreements | H31: =SUM(I31,L31,O31,R31,U31) -> #REF! | I31: =SUMIF(#REF!,$D$31,#REF!) -> #REF! | L31: =SUMIF(#REF!,$D$31,#REF!) -> #REF! | O31: =SUMIF(#REF!,$D$31,#REF!) -> #REF! | R31: =SUMIF(#REF!,$D$31,#REF!) -> #REF! | U31: =SUMIF(#REF!,$D$31,#REF!) -> #REF!
B32: 640300 | C32: Contractual Services | D32: 640101 | E32: Rental Short-Term | H32: =SUM(I32,L32,O32,R32,U32) -> #REF! | I32: =SUMIF(#REF!,$D$32,#REF!) -> #REF! | L32: =SUMIF(#REF!,$D$32,#REF!) -> #REF! | O32: =SUMIF(#REF!,$D$32,#REF!) -> #REF! | R32: =SUMIF(#REF!,$D$32,#REF!) -> #REF! | U32: =SUMIF(#REF!,$D$32,#REF!) -> #REF!
B33: 640300 | C33: Contractual Services | D33: 640202 | E33: Equipment Lease Payment | H33: =SUM(I33,L33,O33,R33,U33) -> #REF! | I33: =SUMIF(#REF!,$D$33,#REF!) -> #REF! | L33: =SUMIF(#REF!,$D$33,#REF!) -> #REF! | O33: =SUMIF(#REF!,$D$33,#REF!) -> #REF! | R33: =SUMIF(#REF!,$D$33,#REF!) -> #REF! | U33: =SUMIF(#REF!,$D$33,#REF!) -> #REF!
B34: 640300 | C34: Contractual Services | D34: 640205 | E34: Motor Vehicle Leasing | H34: =SUM(I34,L34,O34,R34,U34) -> #REF! | I34: =SUMIF(#REF!,$D$34,#REF!) -> #REF! | L34: =SUMIF(#REF!,$D$34,#REF!) -> #REF! | O34: =SUMIF(#REF!,$D$34,#REF!) -> #REF! | R34: =SUMIF(#REF!,$D$34,#REF!) -> #REF! | U34: =SUMIF(#REF!,$D$34,#REF!) -> #REF!
B35: 640300 | C35: Contractual Services | D35: 640301 | E35: Contractual Services - General | H35: =SUM(I35,L35,O35,R35,U35) -> #REF! | I35: =SUMIF(#REF!,$D$35,#REF!) -> #REF! | L35: =SUMIF(#REF!,$D$35,#REF!) -> #REF! | O35: =SUMIF(#REF!,$D$35,#REF!) -> #REF! | R35: =SUMIF(#REF!,$D$35,#REF!) -> #REF! | U35: =SUMIF(#REF!,$D$35,#REF!) -> #REF!
B36: 640300 | C36: Contractual Services | D36: 640317 | E36: Contractual Services - Ground Maintenance | H36: =SUM(I36,L36,O36,R36,U36) -> #REF! | I36: =SUMIF(#REF!,$D$36,#REF!) -> #REF! | L36: =SUMIF(#REF!,$D$36,#REF!) -> #REF! | O36: =SUMIF(#REF!,$D$36,#REF!) -> #REF! | R36: =SUMIF(#REF!,$D$36,#REF!) -> #REF! | U36: =SUMIF(#REF!,$D$36,#REF!) -> #REF!
B37: 640300 | C37: Contractual Services | D37: 640318 | E37: Contractual Services - Cleaning | H37: =SUM(I37,L37,O37,R37,U37) -> #REF! | I37: =SUMIF(#REF!,$D$37,#REF!) -> #REF! | L37: =SUMIF(#REF!,$D$37,#REF!) -> #REF! | O37: =SUMIF(#REF!,$D$37,#REF!) -> #REF! | R37: =SUMIF(#REF!,$D$37,#REF!) -> #REF! | U37: =SUMIF(#REF!,$D$37,#REF!) -> #REF!
B38: 640300 | C38: Contractual Services | D38: 640321 | E38: Contractual Services - Off-Site Storage | H38: =SUM(I38,L38,O38,R38,U38) -> #REF! | I38: =SUMIF(#REF!,$D$38,#REF!) -> #REF! | L38: =SUMIF(#REF!,$D$38,#REF!) -> #REF! | O38: =SUMIF(#REF!,$D$38,#REF!) -> #REF! | R38: =SUMIF(#REF!,$D$38,#REF!) -> #REF! | U38: =SUMIF(#REF!,$D$38,#REF!) -> #REF!
B39: 640300 | C39: Contractual Services | D39: 640341 | E39: Contractual Services - Security Services | H39: =SUM(I39,L39,O39,R39,U39) -> #REF! | I39: =SUMIF(#REF!,$D$39,#REF!) -> #REF! | L39: =SUMIF(#REF!,$D$39,#REF!) -> #REF! | O39: =SUMIF(#REF!,$D$39,#REF!) -> #REF! | R39: =SUMIF(#REF!,$D$39,#REF!) -> #REF! | U39: =SUMIF(#REF!,$D$39,#REF!) -> #REF!
B40: 640300 | C40: Contractual Services | D40: 640351 | E40: Legal Fees | H40: =SUM(I40,L40,O40,R40,U40) -> #REF! | I40: =SUMIF(#REF!,$D$40,#REF!) -> #REF! | L40: =SUMIF(#REF!,$D$40,#REF!) -> #REF! | O40: =SUMIF(#REF!,$D$40,#REF!) -> #REF! | R40: =SUMIF(#REF!,$D$40,#REF!) -> #REF! | U40: =SUMIF(#REF!,$D$40,#REF!) -> #REF!
B41: 640300 | C41: Contractual Services | D41: 640361 | E41: Accounting/Auditing Expense | H41: =SUM(I41,L41,O41,R41,U41) -> #REF! | I41: =SUMIF(#REF!,$D$41,#REF!) -> #REF! | L41: =SUMIF(#REF!,$D$41,#REF!) -> #REF! | O41: =SUMIF(#REF!,$D$41,#REF!) -> #REF! | R41: =SUMIF(#REF!,$D$41,#REF!) -> #REF! | U41: =SUMIF(#REF!,$D$41,#REF!) -> #REF!
B42: 640300 | C42: Contractual Services | D42: 640381 | E42: Professional Services - External | H42: =SUM(I42,L42,O42,R42,U42) -> #REF! | I42: =SUMIF(#REF!,$D$42,#REF!) -> #REF! | L42: =SUMIF(#REF!,$D$42,#REF!) -> #REF! | O42: =SUMIF(#REF!,$D$42,#REF!) -> #REF! | R42: =SUMIF(#REF!,$D$42,#REF!) -> #REF! | U42: =SUMIF(#REF!,$D$42,#REF!) -> #REF!
B43: 640300 | C43: Contractual Services | D43: 640455 | E43: Software Maintenance Agreeement | H43: =SUM(I43,L43,O43,R43,U43) -> #REF! | I43: =SUMIF(#REF!,$D$43,#REF!) -> #REF! | L43: =SUMIF(#REF!,$D$43,#REF!) -> #REF! | O43: =SUMIF(#REF!,$D$43,#REF!) -> #REF! | R43: =SUMIF(#REF!,$D$43,#REF!) -> #REF! | U43: =SUMIF(#REF!,$D$43,#REF!) -> #REF!
B44: 640300 | C44: Contractual Services | D44: 642501 | E44: Printing | H44: =SUM(I44,L44,O44,R44,U44) -> #REF! | I44: =SUMIF(#REF!,$D$44,#REF!) -> #REF! | L44: =SUMIF(#REF!,$D$44,#REF!) -> #REF! | O44: =SUMIF(#REF!,$D$44,#REF!) -> #REF! | R44: =SUMIF(#REF!,$D$44,#REF!) -> #REF! | U44: =SUMIF(#REF!,$D$44,#REF!) -> #REF!
B45: 640500 | C45: Contractual Services | D45: 640501 | E45: Consultant Fees | H45: =SUM(I45,L45,O45,R45,U45) -> #REF! | I45: =SUMIF(#REF!,$D$45,#REF!) -> #REF! | L45: =SUMIF(#REF!,$D$45,#REF!) -> #REF! | O45: =SUMIF(#REF!,$D$45,#REF!) -> #REF! | R45: =SUMIF(#REF!,$D$45,#REF!) -> #REF! | U45: =SUMIF(#REF!,$D$45,#REF!) -> #REF!
B46: 642400 | C46: Subaward | D46: 642405 | E46: Subaward General | H46: =SUM(I46,L46,O46,R46,U46) -> #REF! | I46: =SUMIF(#REF!,$D$46,#REF!) -> #REF! | L46: =SUMIF(#REF!,$D$46,#REF!) -> #REF! | O46: =SUMIF(#REF!,$D$46,#REF!) -> #REF! | R46: =SUMIF(#REF!,$D$46,#REF!) -> #REF! | U46: =SUMIF(#REF!,$D$46,#REF!) -> #REF!
A47: Other | B47: 640102 | C47: Leased Facilities External | D47: 640102 | E47: Leased Facilities External | H47: =SUM(I47,L47,O47,R47,U47) -> #REF! | I47: =SUMIF(#REF!,$D$47,#REF!) -> #REF! | L47: =SUMIF(#REF!,$D$47,#REF!) -> #REF! | O47: =SUMIF(#REF!,$D$47,#REF!) -> #REF! | R47: =SUMIF(#REF!,$D$47,#REF!) -> #REF! | U47: =SUMIF(#REF!,$D$47,#REF!) -> #REF!
B48: 641400 | C48: Telecommunications | D48: 641402 | E48: Telephone Long Distance | H48: =SUM(I48,L48,O48,R48,U48) -> #REF! | I48: =SUMIF(#REF!,$D$48,#REF!) -> #REF! | L48: =SUMIF(#REF!,$D$48,#REF!) -> #REF! | O48: =SUMIF(#REF!,$D$48,#REF!) -> #REF! | R48: =SUMIF(#REF!,$D$48,#REF!) -> #REF! | U48: =SUMIF(#REF!,$D$48,#REF!) -> #REF!
B49: 642500 | C49: Other Expenses | D49: 640403 | E49: Memberships/Dues | H49: =SUM(I49,L49,O49,R49,U49) -> #REF! | I49: =SUMIF(#REF!,$D$49,#REF!) -> #REF! | L49: =SUMIF(#REF!,$D$49,#REF!) -> #REF! | O49: =SUMIF(#REF!,$D$49,#REF!) -> #REF! | R49: =SUMIF(#REF!,$D$49,#REF!) -> #REF! | U49: =SUMIF(#REF!,$D$49,#REF!) -> #REF!
B50: 642500 | C50: Other Expenses | D50: 642002 | E50: Meals Non-Travel & Entertainment | H50: =SUM(I50,L50,O50,R50,U50) -> #REF! | I50: =SUMIF(#REF!,$D$50,#REF!) -> #REF! | L50: =SUMIF(#REF!,$D$50,#REF!) -> #REF! | O50: =SUMIF(#REF!,$D$50,#REF!) -> #REF! | R50: =SUMIF(#REF!,$D$50,#REF!) -> #REF! | U50: =SUMIF(#REF!,$D$50,#REF!) -> #REF!
B51: 642500 | C51: Other Expenses | D51: 642211 | E51: Insurance - General | H51: =SUM(I51,L51,O51,R51,U51) -> #REF! | I51: =SUMIF(#REF!,$D$51,#REF!) -> #REF! | L51: =SUMIF(#REF!,$D$51,#REF!) -> #REF! | O51: =SUMIF(#REF!,$D$51,#REF!) -> #REF! | R51: =SUMIF(#REF!,$D$51,#REF!) -> #REF! | U51: =SUMIF(#REF!,$D$51,#REF!) -> #REF!
B52: 642500 | C52: Other Expenses | D52: 643012 | E52: VAT Tax Paid | H52: =SUM(I52,L52,O52,R52,U52) -> #REF! | I52: =SUMIF(#REF!,$D$52,#REF!) -> #REF! | L52: =SUMIF(#REF!,$D$52,#REF!) -> #REF! | O52: =SUMIF(#REF!,$D$52,#REF!) -> #REF! | R52: =SUMIF(#REF!,$D$52,#REF!) -> #REF! | U52: =SUMIF(#REF!,$D$52,#REF!) -> #REF!
B53: 642500 | C53: Other Expenses | D53: 647001 | E53: Training | H53: =SUM(I53,L53,O53,R53,U53) -> #REF! | I53: =SUMIF(#REF!,$D$53,#REF!) -> #REF! | L53: =SUMIF(#REF!,$D$53,#REF!) -> #REF! | O53: =SUMIF(#REF!,$D$53,#REF!) -> #REF! | R53: =SUMIF(#REF!,$D$53,#REF!) -> #REF! | U53: =SUMIF(#REF!,$D$53,#REF!) -> #REF!
B54: 642500 | C54: Other Expenses | D54: 651851 | E54: Bank Service Charges | H54: =SUM(I54,L54,O54,R54,U54) -> #REF! | I54: =SUMIF(#REF!,$D$54,#REF!) -> #REF! | L54: =SUMIF(#REF!,$D$54,#REF!) -> #REF! | O54: =SUMIF(#REF!,$D$54,#REF!) -> #REF! | R54: =SUMIF(#REF!,$D$54,#REF!) -> #REF! | U54: =SUMIF(#REF!,$D$54,#REF!) -> #REF!
B55: 643000 | C55: Other Expenses Excluded | D55: 622502 | E55: Travel Insurance | H55: =SUM(I55,L55,O55,R55,U55) -> #REF! | I55: =SUMIF(#REF!,$D$55,#REF!) -> #REF! | L55: =SUMIF(#REF!,$D$55,#REF!) -> #REF! | O55: =SUMIF(#REF!,$D$55,#REF!) -> #REF! | R55: =SUMIF(#REF!,$D$55,#REF!) -> #REF! | U55: =SUMIF(#REF!,$D$55,#REF!) -> #REF!
B56: 643000 | C56: Other Expenses Excluded | D56: 651901 | E56: Foreign Currency Exchange Gain/Loss | H56: =SUM(I56,L56,O56,R56,U56) -> #REF! | I56: =SUMIF(#REF!,$D$56,#REF!) -> #REF! | L56: =SUMIF(#REF!,$D$56,#REF!) -> #REF! | O56: =SUMIF(#REF!,$D$56,#REF!) -> #REF! | R56: =SUMIF(#REF!,$D$56,#REF!) -> #REF! | U56: =SUMIF(#REF!,$D$56,#REF!) -> #REF!
B58: Total per year | D58: Total per year | H58: =SUM(I58,L58,O58,R58,U58) -> #REF! | I58: =SUM(I14:I57) -> #REF! | L58: =SUM(L14:L57) -> #REF! | O58: =SUM(O14:O57) -> #REF! | R58: =SUM(R14:R57) -> #REF! | U58: =SUM(U14:U57) -> #REF!
B60: Calculation check

Sheet IC by GL in LC
D1: Jhpiego Corporation
D2: =Assumptions!B9 -> DONOR: | E2: ='Incountry Costs by GL USD'!E2 -> USDOL
D3: =Assumptions!B10 -> Country: | E3: ='Incountry Costs by GL USD'!E3 -> Ecuador
D4: =Assumptions!B11 -> Program Name: | E4: ='Incountry Costs by GL USD'!E4 -> Project to Improve Adherence to International Labor Standards in the Agricultural Sector in Ecuador
D5: =Assumptions!B12 -> Grant Number: | E5: ='Incountry Costs by GL USD'!E5 -> FOA-ILAB-23-28
D6: =Assumptions!B13 -> Period of Performance: | E6: ='Incountry Costs by GL USD'!E6 -> 48 months | H6: ='Incountry Costs by GL USD'!H6 -> 0
D8: BUDGET SUMMARY BY G/L in USD
D10: IN-COUNTRY COSTS in LOCAL CURRENCY | I10: US$1= | L10: =er -> 0 | O10: local currency | V10: US$1=
E11: IN-COUNTRY ION: | I11: ='Incountry Costs by GL USD'!I11 -> 21 - 987654321 | L11: ='Incountry Costs by GL USD'!L11 -> 22 - 987654322 | O11: ='Incountry Costs by GL USD'!O11 -> 23 - 987654323 | R11: ='Incountry Costs by GL USD'!R11 -> 24 - 987654324 | U11: ='Incountry Costs by GL USD'!U11 -> 25 - 987654325
A13: SF424a | B13: Sponsored Class | C13: Description | D13: G/L | E13: Description | H13: Workplan Year Budget | I13: =#REF! -> #REF! | L13: =#REF! -> #REF! | O13: =#REF! -> #REF! | R13: =#REF! -> #REF! | U13: =#REF! -> #REF!
A15: Personnel | B15: 610000 | C15: Salaries & Wages | D15: 616112 | E15: In-country Salaries | H15: ='Incountry Costs by GL USD'!H15*$L$10 -> #REF! | I15: ='Incountry Costs by GL USD'!I15*$L$10 -> #REF! | L15: ='Incountry Costs by GL USD'!L15*$L$10 -> #REF! | O15: ='Incountry Costs by GL USD'!O15*$L$10 -> #REF! | R15: ='Incountry Costs by GL USD'!R15*$L$10 -> #REF! | U15: ='Incountry Costs by GL USD'!U15*$L$10 -> #REF!
A16: Fringe Benefits | B16: 620000 | C16: Fringe Benefits | D16: 620112 | E16: In-country Fringe | H16: ='Incountry Costs by GL USD'!H16*$L$10 -> #REF! | I16: ='Incountry Costs by GL USD'!I16*$L$10 -> #REF! | L16: ='Incountry Costs by GL USD'!L16*$L$10 -> #REF! | O16: ='Incountry Costs by GL USD'!O16*$L$10 -> #REF! | R16: ='Incountry Costs by GL USD'!R16*$L$10 -> #REF! | U16: ='Incountry Costs by GL USD'!U16*$L$10 -> #REF!
A17: Travel | B17: 652000 | C17: Travel Domestic | D17: 652201 | E17: Trainee Travel | H17: ='Incountry Costs by GL USD'!H17*$L$10 -> #REF! | I17: ='Incountry Costs by GL USD'!I17*$L$10 -> #REF! | L17: ='Incountry Costs by GL USD'!L17*$L$10 -> #REF! | O17: ='Incountry Costs by GL USD'!O17*$L$10 -> #REF! | R17: ='Incountry Costs by GL USD'!R17*$L$10 -> #REF! | U17: ='Incountry Costs by GL USD'!U17*$L$10 -> #REF!
B18: 652100 | C18: Travel Foreign | D18: 652101 | E18: Travel Foreign | H18: ='Incountry Costs by GL USD'!H18*$L$10 -> #REF! | I18: ='Incountry Costs by GL USD'!I18*$L$10 -> #REF! | L18: ='Incountry Costs by GL USD'!L18*$L$10 -> #REF! | O18: ='Incountry Costs by GL USD'!O18*$L$10 -> #REF! | R18: ='Incountry Costs by GL USD'!R18*$L$10 -> #REF! | U18: ='Incountry Costs by GL USD'!U18*$L$10 -> #REF!
D19: 652102 | E19: Travel Overseas Local | H19: ='Incountry Costs by GL USD'!H19*$L$10 -> #REF! | I19: ='Incountry Costs by GL USD'!I19*$L$10 -> #REF! | L19: ='Incountry Costs by GL USD'!L19*$L$10 -> #REF! | O19: ='Incountry Costs by GL USD'!O19*$L$10 -> #REF! | R19: ='Incountry Costs by GL USD'!R19*$L$10 -> #REF! | U19: ='Incountry Costs by GL USD'!U19*$L$10 -> #REF!
A20: Supplies | B20: 630000 | C20: Supplies & Materials | D20: 631001 | E20: Furniture | H20: ='Incountry Costs by GL USD'!H20*$L$10 -> #REF! | I20: ='Incountry Costs by GL USD'!I20*$L$10 -> #REF! | L20: ='Incountry Costs by GL USD'!L20*$L$10 -> #REF! | O20: ='Incountry Costs by GL USD'!O20*$L$10 -> #REF! | R20: ='Incountry Costs by GL USD'!R20*$L$10 -> #REF! | U20: ='Incountry Costs by GL USD'!U20*$L$10 -> #REF!
B21: 630000 | C21: Supplies & Materials | D21: 631003 | E21: Non-capital PC purchases | H21: ='Incountry Costs by GL USD'!H21*$L$10 -> #REF! | I21: ='Incountry Costs by GL USD'!I21*$L$10 -> #REF! | L21: ='Incountry Costs by GL USD'!L21*$L$10 -> #REF! | O21: ='Incountry Costs by GL USD'!O21*$L$10 -> #REF! | R21: ='Incountry Costs by GL USD'!R21*$L$10 -> #REF! | U21: ='Incountry Costs by GL USD'!U21*$L$10 -> #REF!
B22: 630000 | C22: Supplies & Materials | D22: 633032 | E22: Office Supplies | H22: ='Incountry Costs by GL USD'!H23*$L$10 -> #REF! | I22: ='Incountry Costs by GL USD'!I23*$L$10 -> #REF! | L22: ='Incountry Costs by GL USD'!L23*$L$10 -> #REF! | O22: ='Incountry Costs by GL USD'!O23*$L$10 -> #REF! | R22: ='Incountry Costs by GL USD'!R23*$L$10 -> #REF! | U22: ='Incountry Costs by GL USD'!U23*$L$10 -> #REF!
B23: 630000 | C23: Supplies & Materials | D23: 633037 | E23: Publications/Journals/Subscriptions | H23: ='Incountry Costs by GL USD'!H26*$L$10 -> #REF! | I23: ='Incountry Costs by GL USD'!I26*$L$10 -> #REF! | L23: ='Incountry Costs by GL USD'!L26*$L$10 -> #REF! | O23: ='Incountry Costs by GL USD'!O26*$L$10 -> #REF! | R23: ='Incountry Costs by GL USD'!R26*$L$10 -> #REF! | U23: ='Incountry Costs by GL USD'!U26*$L$10 -> #REF!
B24: 630000 | C24: Supplies & Materials | D24: 635001 | E24: Electricity | H24: ='Incountry Costs by GL USD'!H27*$L$10 -> #REF! | I24: ='Incountry Costs by GL USD'!I27*$L$10 -> #REF! | L24: ='Incountry Costs by GL USD'!L27*$L$10 -> #REF! | O24: ='Incountry Costs by GL USD'!O27*$L$10 -> #REF! | R24: ='Incountry Costs by GL USD'!R27*$L$10 -> #REF! | U24: ='Incountry Costs by GL USD'!U27*$L$10 -> #REF!
B25: 630000 | C25: Supplies & Materials | D25: 635010 | E25: Utilities: Water | H25: ='Incountry Costs by GL USD'!H28*$L$10 -> #REF! | I25: ='Incountry Costs by GL USD'!I28*$L$10 -> #REF! | L25: ='Incountry Costs by GL USD'!L28*$L$10 -> #REF! | O25: ='Incountry Costs by GL USD'!O28*$L$10 -> #REF! | R25: ='Incountry Costs by GL USD'!R28*$L$10 -> #REF! | U25: ='Incountry Costs by GL USD'!U28*$L$10 -> #REF!
B26: 630000 | C26: Supplies & Materials | D26: 640282 | E26: Delivery/Courier Service | H26: ='Incountry Costs by GL USD'!H29*$L$10 -> #REF! | I26: ='Incountry Costs by GL USD'!I29*$L$10 -> #REF! | L26: ='Incountry Costs by GL USD'!L29*$L$10 -> #REF! | O26: ='Incountry Costs by GL USD'!O29*$L$10 -> #REF! | R26: ='Incountry Costs by GL USD'!R29*$L$10 -> #REF! | U26: ='Incountry Costs by GL USD'!U29*$L$10 -> #REF!
A27: Equipment | B27: 653400 | C27: Equipment | D27: 631099 | E27: Equipment Purchases - SRM only | H27: ='Incountry Costs by GL USD'!H30*$L$10 -> #REF! | I27: ='Incountry Costs by GL USD'!I30*$L$10 -> #REF! | L27: ='Incountry Costs by GL USD'!L30*$L$10 -> #REF! | O27: ='Incountry Costs by GL USD'!O30*$L$10 -> #REF! | R27: ='Incountry Costs by GL USD'!R30*$L$10 -> #REF! | U27: ='Incountry Costs by GL USD'!U30*$L$10 -> #REF!
A28: Contractual | B28: 637000 | C28: Repairs & Maintenance | D28: 637001 | E28: Equipment Maintenance Agreements | H28: ='Incountry Costs by GL USD'!H31*$L$10 -> #REF! | I28: ='Incountry Costs by GL USD'!I31*$L$10 -> #REF! | L28: ='Incountry Costs by GL USD'!L31*$L$10 -> #REF! | O28: ='Incountry Costs by GL USD'!O31*$L$10 -> #REF! | R28: ='Incountry Costs by GL USD'!R31*$L$10 -> #REF! | U28: ='Incountry Costs by GL USD'!U31*$L$10 -> #REF!
B29: 640300 | C29: Contractual Services | D29: 640101 | E29: Rental Short-Term | H29: ='Incountry Costs by GL USD'!H32*$L$10 -> #REF! | I29: ='Incountry Costs by GL USD'!I32*$L$10 -> #REF! | L29: ='Incountry Costs by GL USD'!L32*$L$10 -> #REF! | O29: ='Incountry Costs by GL USD'!O32*$L$10 -> #REF! | R29: ='Incountry Costs by GL USD'!R32*$L$10 -> #REF! | U29: ='Incountry Costs by GL USD'!U32*$L$10 -> #REF!
B30: 640300 | C30: Contractual Services | D30: 640202 | E30: Equipment Lease Payment | H30: ='Incountry Costs by GL USD'!H33*$L$10 -> #REF! | I30: ='Incountry Costs by GL USD'!I33*$L$10 -> #REF! | L30: ='Incountry Costs by GL USD'!L33*$L$10 -> #REF! | O30: ='Incountry Costs by GL USD'!O33*$L$10 -> #REF! | R30: ='Incountry Costs by GL USD'!R33*$L$10 -> #REF! | U30: ='Incountry Costs by GL USD'!U33*$L$10 -> #REF!
B31: 640300 | C31: Contractual Services | D31: 640205 | E31: Motor Vehicle Leasing | H31: ='Incountry Costs by GL USD'!H34*$L$10 -> #REF! | I31: ='Incountry Costs by GL USD'!I34*$L$10 -> #REF! | L31: ='Incountry Costs by GL USD'!L34*$L$10 -> #REF! | O31: ='Incountry Costs by GL USD'!O34*$L$10 -> #REF! | R31: ='Incountry Costs by GL USD'!R34*$L$10 -> #REF! | U31: ='Incountry Costs by GL USD'!U34*$L$10 -> #REF!
B32: 640300 | C32: Contractual Services | D32: 640301 | E32: Contractual Services - General | H32: ='Incountry Costs by GL USD'!H35*$L$10 -> #REF! | I32: ='Incountry Costs by GL USD'!I35*$L$10 -> #REF! | L32: ='Incountry Costs by GL USD'!L35*$L$10 -> #REF! | O32: ='Incountry Costs by GL USD'!O35*$L$10 -> #REF! | R32: ='Incountry Costs by GL USD'!R35*$L$10 -> #REF! | U32: ='Incountry Costs by GL USD'!U35*$L$10 -> #REF!
B33: 640300 | C33: Contractual Services | D33: 640317 | E33: Contractual Services - Ground Maintenance | H33: ='Incountry Costs by GL USD'!H36*$L$10 -> #REF! | I33: ='Incountry Costs by GL USD'!I36*$L$10 -> #REF! | L33: ='Incountry Costs by GL USD'!L36*$L$10 -> #REF! | O33: ='Incountry Costs by GL USD'!O36*$L$10 -> #REF! | R33: ='Incountry Costs by GL USD'!R36*$L$10 -> #REF! | U33: ='Incountry Costs by GL USD'!U36*$L$10 -> #REF!
B34: 640300 | C34: Contractual Services | D34: 640318 | E34: Contractual Services - Cleaning | H34: ='Incountry Costs by GL USD'!H37*$L$10 -> #REF! | I34: ='Incountry Costs by GL USD'!I37*$L$10 -> #REF! | L34: ='Incountry Costs by GL USD'!L37*$L$10 -> #REF! | O34: ='Incountry Costs by GL USD'!O37*$L$10 -> #REF! | R34: ='Incountry Costs by GL USD'!R37*$L$10 -> #REF! | U34: ='Incountry Costs by GL USD'!U37*$L$10 -> #REF!
B35: 640300 | C35: Contractual Services | D35: 640321 | E35: Contractual Services - Off-Site Storage | H35: ='Incountry Costs by GL USD'!H38*$L$10 -> #REF! | I35: ='Incountry Costs by GL USD'!I38*$L$10 -> #REF! | L35: ='Incountry Costs by GL USD'!L38*$L$10 -> #REF! | O35: ='Incountry Costs by GL USD'!O38*$L$10 -> #REF! | R35: ='Incountry Costs by GL USD'!R38*$L$10 -> #REF! | U35: ='Incountry Costs by GL USD'!U38*$L$10 -> #REF!
B36: 640300 | C36: Contractual Services | D36: 640341 | E36: Contractual Services - Security Services | H36: ='Incountry Costs by GL USD'!H39*$L$10 -> #REF! | I36: ='Incountry Costs by GL USD'!I39*$L$10 -> #REF! | L36: ='Incountry Costs by GL USD'!L39*$L$10 -> #REF! | O36: ='Incountry Costs by GL USD'!O39*$L$10 -> #REF! | R36: ='Incountry Costs by GL USD'!R39*$L$10 -> #REF! | U36: ='Incountry Costs by GL USD'!U39*$L$10 -> #REF!
B37: 640300 | C37: Contractual Services | D37: 640351 | E37: Legal Fees | H37: ='Incountry Costs by GL USD'!H40*$L$10 -> #REF! | I37: ='Incountry Costs by GL USD'!I40*$L$10 -> #REF! | L37: ='Incountry Costs by GL USD'!L40*$L$10 -> #REF! | O37: ='Incountry Costs by GL USD'!O40*$L$10 -> #REF! | R37: ='Incountry Costs by GL USD'!R40*$L$10 -> #REF! | U37: ='Incountry Costs by GL USD'!U40*$L$10 -> #REF!
B38: 640300 | C38: Contractual Services | D38: 640361 | E38: Accounting/Auditing Expense | H38: ='Incountry Costs by GL USD'!H41*$L$10 -> #REF! | I38: ='Incountry Costs by GL USD'!I41*$L$10 -> #REF! | L38: ='Incountry Costs by GL USD'!L41*$L$10 -> #REF! | O38: ='Incountry Costs by GL USD'!O41*$L$10 -> #REF! | R38: ='Incountry Costs by GL USD'!R41*$L$10 -> #REF! | U38: ='Incountry Costs by GL USD'!U41*$L$10 -> #REF!
B39: 640300 | C39: Contractual Services | D39: 640381 | E39: Professional Services - External | H39: ='Incountry Costs by GL USD'!H42*$L$10 -> #REF! | I39: ='Incountry Costs by GL USD'!I42*$L$10 -> #REF! | L39: ='Incountry Costs by GL USD'!L42*$L$10 -> #REF! | O39: ='Incountry Costs by GL USD'!O42*$L$10 -> #REF! | R39: ='Incountry Costs by GL USD'!R42*$L$10 -> #REF! | U39: ='Incountry Costs by GL USD'!U42*$L$10 -> #REF!
B40: 640300 | C40: Contractual Services | D40: 640455 | E40: Software Maintenance Agreeement | H40: ='Incountry Costs by GL USD'!H43*$L$10 -> #REF! | I40: ='Incountry Costs by GL USD'!I43*$L$10 -> #REF! | L40: ='Incountry Costs by GL USD'!L43*$L$10 -> #REF! | O40: ='Incountry Costs by GL USD'!O43*$L$10 -> #REF! | R40: ='Incountry Costs by GL USD'!R43*$L$10 -> #REF! | U40: ='Incountry Costs by GL USD'!U43*$L$10 -> #REF!
B41: 640300 | C41: Contractual Services | D41: 640501 | E41: Consultant Fees | H41: ='Incountry Costs by GL USD'!H45*$L$10 -> #REF! | I41: ='Incountry Costs by GL USD'!I45*$L$10 -> #REF! | L41: ='Incountry Costs by GL USD'!L45*$L$10 -> #REF! | O41: ='Incountry Costs by GL USD'!O45*$L$10 -> #REF! | R41: ='Incountry Costs by GL USD'!R45*$L$10 -> #REF! | U41: ='Incountry Costs by GL USD'!U45*$L$10 -> #REF!
B42: 640300 | C42: Contractual Services | D42: 642501 | E42: Printing | H42: ='Incountry Costs by GL USD'!H44*$L$10 -> #REF! | I42: ='Incountry Costs by GL USD'!I44*$L$10 -> #REF! | L42: ='Incountry Costs by GL USD'!L44*$L$10 -> #REF! | O42: ='Incountry Costs by GL USD'!O44*$L$10 -> #REF! | R42: ='Incountry Costs by GL USD'!R44*$L$10 -> #REF! | U42: ='Incountry Costs by GL USD'!U44*$L$10 -> #REF!
B43: 642400 | C43: Subaward | D43: 642405 | E43: Subaward General | H43: ='Incountry Costs by GL USD'!H46*$L$10 -> #REF! | I43: ='Incountry Costs by GL USD'!I46*$L$10 -> #REF! | L43: ='Incountry Costs by GL USD'!L46*$L$10 -> #REF! | O43: ='Incountry Costs by GL USD'!O46*$L$10 -> #REF! | R43: ='Incountry Costs by GL USD'!R46*$L$10 -> #REF! | U43: ='Incountry Costs by GL USD'!U46*$L$10 -> #REF!
A44: Other | B44: 640102 | C44: Leased Facilities External | D44: 640102 | E44: Leased Facilities External | H44: ='Incountry Costs by GL USD'!H47*$L$10 -> #REF! | I44: ='Incountry Costs by GL USD'!I47*$L$10 -> #REF! | L44: ='Incountry Costs by GL USD'!L47*$L$10 -> #REF! | O44: ='Incountry Costs by GL USD'!O47*$L$10 -> #REF! | R44: ='Incountry Costs by GL USD'!R47*$L$10 -> #REF! | U44: ='Incountry Costs by GL USD'!U47*$L$10 -> #REF!
B45: 641400 | C45: Telecommunications | D45: 641402 | E45: Telephone Long Distance | H45: ='Incountry Costs by GL USD'!H48*$L$10 -> #REF! | I45: ='Incountry Costs by GL USD'!I48*$L$10 -> #REF! | L45: ='Incountry Costs by GL USD'!L48*$L$10 -> #REF! | O45: ='Incountry Costs by GL USD'!O48*$L$10 -> #REF! | R45: ='Incountry Costs by GL USD'!R48*$L$10 -> #REF! | U45: ='Incountry Costs by GL USD'!U48*$L$10 -> #REF!
B46: 642500 | C46: Other Expenses | D46: 640403 | E46: Memberships/Dues | H46: ='Incountry Costs by GL USD'!H49*$L$10 -> #REF! | I46: ='Incountry Costs by GL USD'!I49*$L$10 -> #REF! | L46: ='Incountry Costs by GL USD'!L49*$L$10 -> #REF! | O46: ='Incountry Costs by GL USD'!O49*$L$10 -> #REF! | R46: ='Incountry Costs by GL USD'!R49*$L$10 -> #REF! | U46: ='Incountry Costs by GL USD'!U49*$L$10 -> #REF!
B47: 642500 | C47: Other Expenses | D47: 642002 | E47: Meals Non-Travel & Entertainment | H47: ='Incountry Costs by GL USD'!H50*$L$10 -> #REF! | I47: ='Incountry Costs by GL USD'!I50*$L$10 -> #REF! | L47: ='Incountry Costs by GL USD'!L50*$L$10 -> #REF! | O47: ='Incountry Costs by GL USD'!O50*$L$10 -> #REF! | R47: ='Incountry Costs by GL USD'!R50*$L$10 -> #REF! | U47: ='Incountry Costs by GL USD'!U50*$L$10 -> #REF!
B48: 642500 | C48: Other Expenses | D48: 642211 | E48: Insurance - General | H48: ='Incountry Costs by GL USD'!H51*$L$10 -> #REF! | I48: ='Incountry Costs by GL USD'!I51*$L$10 -> #REF! | L48: ='Incountry Costs by GL USD'!L51*$L$10 -> #REF! | O48: ='Incountry Costs by GL USD'!O51*$L$10 -> #REF! | R48: ='Incountry Costs by GL USD'!R51*$L$10 -> #REF! | U48: ='Incountry Costs by GL USD'!U51*$L$10 -> #REF!
B49: 642500 | C49: Other Expenses | D49: 643012 | E49: VAT Tax Paid | H49: ='Incountry Costs by GL USD'!H52*$L$10 -> #REF! | I49: ='Incountry Costs by GL USD'!I52*$L$10 -> #REF! | L49: ='Incountry Costs by GL USD'!L52*$L$10 -> #REF! | O49: ='Incountry Costs by GL USD'!O52*$L$10 -> #REF! | R49: ='Incountry Costs by GL USD'!R52*$L$10 -> #REF! | U49: ='Incountry Costs by GL USD'!U52*$L$10 -> #REF!
B50: 642500 | C50: Other Expenses | D50: 647001 | E50: Training | H50: ='Incountry Costs by GL USD'!H53*$L$10 -> #REF! | I50: ='Incountry Costs by GL USD'!I53*$L$10 -> #REF! | L50: ='Incountry Costs by GL USD'!L53*$L$10 -> #REF! | O50: ='Incountry Costs by GL USD'!O53*$L$10 -> #REF! | R50: ='Incountry Costs by GL USD'!R53*$L$10 -> #REF! | U50: ='Incountry Costs by GL USD'!U53*$L$10 -> #REF!
B51: 642500 | C51: Other Expenses | D51: 651851 | E51: Bank Service Charges | H51: ='Incountry Costs by GL USD'!H54*$L$10 -> #REF! | I51: ='Incountry Costs by GL USD'!I54*$L$10 -> #REF! | L51: ='Incountry Costs by GL USD'!L54*$L$10 -> #REF! | O51: ='Incountry Costs by GL USD'!O54*$L$10 -> #REF! | R51: ='Incountry Costs by GL USD'!R54*$L$10 -> #REF! | U51: ='Incountry Costs by GL USD'!U54*$L$10 -> #REF!
B52: 643000 | C52: Other Expenses Excluded | D52: 622502 | E52: Travel Insurance | H52: ='Incountry Costs by GL USD'!H55*$L$10 -> #REF! | I52: ='Incountry Costs by GL USD'!I55*$L$10 -> #REF! | L52: ='Incountry Costs by GL USD'!L55*$L$10 -> #REF! | O52: ='Incountry Costs by GL USD'!O55*$L$10 -> #REF! | R52: ='Incountry Costs by GL USD'!R55*$L$10 -> #REF! | U52: ='Incountry Costs by GL USD'!U55*$L$10 -> #REF!
B53: 643000 | C53: Other Expenses Excluded | D53: 651901 | E53: Foreign Currency Exchange Gain/Loss | H53: ='Incountry Costs by GL USD'!H56*$L$10 -> #REF! | I53: ='Incountry Costs by GL USD'!I56*$L$10 -> #REF! | L53: ='Incountry Costs by GL USD'!L56*$L$10 -> #REF! | O53: ='Incountry Costs by GL USD'!O56*$L$10 -> #REF! | R53: ='Incountry Costs by GL USD'!R56*$L$10 -> #REF! | U53: ='Incountry Costs by GL USD'!U56*$L$10 -> #REF!
B55: Total per year | D55: Total per year | H55: =SUM(I55,L55,O55,R55,U55,#REF!,#REF!,#REF!,#REF!,#REF!) -> #REF! | I55: =SUM(I14:I54) -> #REF! | L55: =SUM(L14:L54) -> #REF! | O55: =SUM(O14:O54) -> #REF! | R55: =SUM(R14:R54) -> #REF! | U55: =SUM(U14:U54) -> #REF!
B57: Calculation check | I57: =#REF! -> #REF! | L57: =#REF! -> #REF! | O57: =#REF! -> #REF! | R57: =#REF! -> #REF! | U57: =#REF! -> #REF!

Sheet Office Budget
A1: =Assumptions!$B$8 -> Partners of America
A2: =CONCATENATE(Assumptions!$B9," ",Assumptions!$C9) -> DONOR: USDOL
A3: =CONCATENATE(Assumptions!$B10," ",Assumptions!$C10) -> Country: Ecuador
A4: =CONCATENATE(Assumptions!$B11," ",Assumptions!$C11) -> Program Name: Project to Improve Adherence to International Labor Standards in the Agricultural Sector in Ecuador | G4: QUESTION: should annual cost be included in detailed budget and percent applied there?
A5: =CONCATENATE(Assumptions!$B12," ",Assumptions!$C12) -> Grant Number: FOA-ILAB-23-28 | G5: OR should allocation be shown at 100%?
G6: PORTFOLIO? OR DIRECT LABOR?
A7: COUNTRY OFFICE BUDGET
A10: SF424a | B10: Sponsored Class | C10: GL | D10: Description | E10: Annual Cost | G10: Annual Cost | I10: Office Costs Allocated to this Program | K10: Monthly Cost
A11: Categories | E11: Local Currency | G11: USD | I11: % | K11: USD
E13: Exchange rate | F13: US$1= | G13: 1 | I13: Percent: | J13: 1 | K13: # of months | L13: 12
A16: Personnel | B16: Salaries & Wages | C16: 616112 | D16: In-Country Salaries | F16: /year | G16: =E16/$G$13 -> 0 | H16: /year | K16: =G16/$L$13 -> 0 | L16: /month
A17: Fringe Benefits | B17: Fringe Benefits | C17: 620112 | D17: In-Country Fringe | F17: /year | G17: =E17/$G$13 -> 0 | H17: /year | K17: =G17/$L$13 -> 0 | L17: /month
A18: Travel | B18: Travel Foreign (Overseas Local) | C18: 652102 | D18: Taxi Services | F18: /year | G18: =E18/$G$13 -> 0 | H18: /year | K18: =G18/$L$13 -> 0 | L18: /month
A19: Supplies | B19: Supplies & Materials | C19: 635001 | D19: Utilities: Electricity | F19: /year | G19: =E19/$G$13 -> 0 | H19: /year | K19: =G19/$L$13 -> 0 | L19: /month
B20: Supplies & Materials | C20: 635010 | D20: Utilities: Water | F20: /year | G20: =E20/$G$13 -> 0 | H20: /year | K20: =G20/$L$13 -> 0 | L20: /month
B21: Supplies & Materials | C21: 633032 | D21: Kitchen Supplies | F21: /year | G21: =E21/$G$13 -> 0 | H21: /year | K21: =G21/$L$13 -> 0 | L21: /month
B22: Supplies & Materials | C22: 640282 | D22: Courier Services | F22: /year | G22: =E22/$G$13 -> 0 | H22: /year | K22: =G22/$L$13 -> 0 | L22: /month
A23: Equipment | B23: Equipment | C23: 653400 | D23: Equipment Purchases - SRM only | F23: /year | G23: =E23/$G$13 -> 0 | H23: /year | K23: =G23/$L$13 -> 0 | L23: /month
A24: Contractual | B24: Contractual Services | C24: 640341 | D24: Contracts: Security | F24: /year | G24: =E24/$G$13 -> 0 | H24: /year | K24: =G24/$L$13 -> 0 | L24: /month
B25: Contractual Services | C25: 640318 | D25: Contracts: Office Cleaning | F25: /year | G25: =E25/$G$13 -> 0 | H25: /year | K25: =G25/$L$13 -> 0 | L25: /month
B26: Contractual Services | C26: 640361 | D26: Contracts: Annual Audit fees | F26: /year | G26: =E26/$G$13 -> 0 | H26: /year | K26: =G26/$L$13 -> 0 | L26: /month
B27: Contractual Services | C27: 640351 | D27: Contracts: Legal Services | F27: /year | G27: =E27/$G$13 -> 0 | H27: /year | K27: =G27/$L$13 -> 0 | L27: /month
B28: Contractual Services | C28: 640205 | D28: Contracts: Vehicle Rental | F28: /year | G28: =E28/$G$13 -> 0 | H28: /year | K28: =G28/$L$13 -> 0 | L28: /month
B29: Contractual Services | C29: 642501 | D29: Office stationery (printing) | F29: /year | G29: =E29/$G$13 -> 0 | H29: /year | K29: =G29/$L$13 -> 0 | L29: /month
B30: Contractual Services | C30: 642501 | D30: Advertising | F30: /year | G30: =E30/$G$13 -> 0 | H30: /year | K30: =G30/$L$13 -> 0 | L30: /month
B31: Contractual Services | C31: 640318 | D31: Office waste removal | F31: /year | G31: =E31/$G$13 -> 0 | H31: /year | K31: =G31/$L$13 -> 0 | L31: /month
B32: Contractual Services | C32: 640301 | D32: ISTS services | F32: /year | G32: =E32/$G$13 -> 0 | H32: /year | K32: =G32/$L$13 -> 0 | L32: /month
B33: Contractual Services | C33: 640301 | D33: Vehicle maintenance | F33: /year | G33: =E33/$G$13 -> 0 | H33: /year | K33: =G33/$L$13 -> 0 | L33: /month
B34: Contractual Services | C34: 640321 | D34: Warehousing/Storage Services | F34: /year | G34: =E34/$G$13 -> 0 | H34: /year | K34: =G34/$L$13 -> 0 | L34: /month
B35: Contractual Services | C35: 642501 | D35: Advertising for recruitment | F35: /year | G35: =E35/$G$13 -> 0 | H35: /year | K35: =G35/$L$13 -> 0 | L35: /month
B36: Contractual Services | C36: 640301 | D36: Vehicle Tracking System (office pool vehicle) | F36: /year | G36: =E36/$G$13 -> 0 | H36: /year | K36: =G36/$L$13 -> 0 | L36: /month
B37: Contractual Services | C37: 640455 | D37: Lisences and renewals | F37: /year | G37: =E37/$G$13 -> 0 | H37: /year | K37: =G37/$L$13 -> 0 | L37: /month
A38: Other | B38: Leased Facilities External | C38: 640102 | D38: Office rent | F38: /year | G38: =E38/$G$13 -> 0 | H38: /year | K38: =G38/$L$13 -> 0 | L38: /month
B39: Leased Facilities External | C39: 640102 | D39: Office Leasehold improvements | F39: /year | G39: =E39/$G$13 -> 0 | H39: /year | K39: =G39/$L$13 -> 0 | L39: /month
B40: Other Expenses | C40: 651851 | D40: Bank charges | F40: /year | G40: =E40/$G$13 -> 0 | H40: /year | K40: =G40/$L$13 -> 0 | L40: /month
B41: Other Expenses | C41: 642211 | D41: Vehicle insurance | F41: /year | G41: =E41/$G$13 -> 0 | H41: /year | K41: =G41/$L$13 -> 0 | L41: /month
B42: Other Expenses | C42: 642002 | D42: Refreshments for office business meetings | F42: /year | G42: =E42/$G$13 -> 0 | H42: /year | K42: =G42/$L$13 -> 0 | L42: /month
B43: Other Expenses | C43: 640403 | D43: NGO Annual fees | F43: /year | G43: =E43/$G$13 -> 0 | H43: /year | K43: =G43/$L$13 -> 0 | L43: /month
B44: Other Expenses | C44: 642002 | D44: staff Development events | F44: /year | G44: =E44/$G$13 -> 0 | H44: /year | K44: =G44/$L$13 -> 0 | L44: /month
B45: Telecommunications | C45: 641402 | D45: Office Internet | F45: /year | G45: =E45/$G$13 -> 0 | H45: /year | K45: =G45/$L$13 -> 0 | L45: /month
B46: Telecommunications | C46: 641402 | D46: Communications | F46: /year | G46: =E46/$G$13 -> 0 | H46: /year | K46: =G46/$L$13 -> 0 | L46: /month
B47: Telecommunications | C47: 641402 | D47: Staff Airtime | F47: /year | G47: =E47/$G$13 -> 0 | H47: /year | K47: =G47/$L$13 -> 0 | L47: /month
D48: add other costs as necessary | F48: /year | G48: =E48/$G$13 -> 0 | H48: /year | K48: =G48/$L$13 -> 0 | L48: /month
D49: add other costs as necessary | F49: /year | G49: =E49/$G$13 -> 0 | H49: /year | K49: =G49/$L$13 -> 0 | L49: /month
D50: Total | E50: =SUM(E16:E49) -> 0 | F50: /year | G50: =SUM(G16:G49) -> 0 | H50: /year | K50: =SUM(K16:K49) -> 0 | L50: month

Sheet Assumptions
A5: GENERAL ASSUMPTIONS
A7: Header Information:
B8: Partners of America
B9: DONOR: | C9: USDOL
B10: Country: | C10: Ecuador
B11: Program Name: | C11: Project to Improve Adherence to International Labor Standards in the Agricultural Sector in Ecuador
B12: Grant Number: | C12: FOA-ILAB-23-28
B13: Period of Performance: | C13: 48 months | F13: to
A15: Rates:
B16: 0.2828 | C16: NICRA - POA
B17: 0 | C17: Exchange Rate
B18: Inflation - US Based Goods/Services | C18: 1.03
B19: Inflation - Locally Purchased Goods/Services | C19: 1.04
B20: Merit Based Increases for HO & Field Staff | C20: 1.05
A23: ODC Escalation
B24: Escalation Percentage: | D24: 0.03 | G24: Year 1 | H24: Year 2 | I24: Year 3 | J24: Year 2 | M24: Year 3 | N24: Year 2 | O24: Year 2 | P24: Year 4 | Q24: Year 2 | R24: Year 2 | S24: Year 5 | T24: Year 2 | U24: Year 2 | V24: Year 6 | W24: Year 2 | X24: Year 2 | Y24: Year 7 | Z24: Year 2 | AA24: Year 2 | AB24: Year 8 | AC24: Year 2 | AD24: Year 2 | AE24: Year 9 | AF24: Year 2 | AG24: Year 2 | AH24: Year 10
G25: 45292
G26: 45657
G27: 1 | J27: =G27*SUM(1+$D$24) -> 1.03 | M27: =J27*SUM(1+$D$24) -> 1.0609 | P27: =M27*SUM(1+$D$24) -> 1.092727 | S27: =P27*SUM(1+$D$24) -> 1.1255088 | V27: =S27*SUM(1+$D$24) -> 1.1592741 | Y27: =V27*SUM(1+$D$24) -> 1.1940523 | AB27: =Y27*SUM(1+$D$24) -> 1.2298739 | AE27: =AB27*SUM(1+$D$24) -> 1.2667701 | AH27: =AE27*SUM(1+$D$24) -> 1.3047732
A30: Annual Salary Increases for International Staff
A32: Standard Increase Percentage: | D32: 0.04
A33: Annual Salary Escalation Date: | D33: 45566
M34: Percent | S34: Increase Factor | AB34: Percent | AH34: Increase Factor
B36: Year 1 | C36: =G25 -> 45292 | D36: =D33 -> 45566 | E36: =ROUND((D36-C36)/30,0) -> 9 | F36: / | G36: 12 | J36: @ | M36: 0 | P36: =E36/G36*M36 -> 0 | V36: 12 | Y36: @ | AB36: 0 | AE36: =T36/V36*AB36 -> 0
E37: =12-E36 -> 3 | F37: / | G37: 12 | J37: @ | M37: =IF(M36=0,D32,SUM(M36+1)*SUM(1+D32)-1) -> 0.04 | P37: =E37/G37*M37 -> 0.01 | S37: =SUM(1+SUM(P36:P37)) -> 1.01 | V37: 12 | Y37: @ | AB37: =IF(AB36=0,S32,SUM(AB36+1)*SUM(1+S32)-1) -> 0 | AE37: =T37/V37*AB37 -> 0 | AH37: =SUM(1+SUM(AE36:AE37)) -> 1
A39: Annual Salary Increases for Local Staff
A41: Standard Increase Percentage: | D41: 0.05
A42: Annual Salary Escalation Date: | D42: 45474
M43: Percent | S43: Increase Factor | AB43: Percent | AH43: Increase Factor
B45: Year 1 | C45: =G25 -> 45292 | D45: =D42 -> 45474 | E45: =ROUND((D45-C45)/30,0) -> 6 | F45: / | G45: 12 | J45: @ | M45: 0 | P45: =E45/G45*M45 -> 0 | V45: 12 | Y45: @ | AB45: 0 | AE45: =T45/V45*AB45 -> 0
E46: =12-E45 -> 6 | F46: / | G46: 12 | J46: @ | M46: =IF(M45=0,D41,SUM(M45+1)*SUM(1+D42)-1) -> 0.05 | P46: =E46/G46*M46 -> 0.025 | S46: =SUM(1+SUM(P45:P46)) -> 1.025 | V46: 12 | Y46: @ | AB46: =IF(AB45=0,S41,SUM(AB45+1)*SUM(1+S42)-1) -> 0 | AE46: =T46/V46*AB46 -> 0 | AH46: =SUM(1+SUM(AE45:AE46)) -> 1
B50: International Travel | C50: Cell Name | D50: Unit Cost | E50: Base
B51: Quito
B52: Airfare | C52: intairfare | E52: round trip coach
B53: Lodging | C53: usaidlodg | D53: 200 | E53: per night
B54: Meals and Incidentals | C54: usaidmeals | D54: 119 | E54: per day
B55: Agent fee | C55: agentfee | E55: per ticket
B56: Visa | C56: visa | D56: 150
B57: Inmunizations | C57: inmuniz | D57: 150
B58: Medex | C58: medex
B59: Freedom Services | C59: ground | E59: round trip to/from airport
B60: Other Misc costs | C60: intmisc
B63: Incountry Operating Costs - Local Costs
B65: Domestic Travel | D65: Lodging | E65: M&IE | F65: Total
B66: Quito | D66: =190*50% -> 95 | E66: =105*50% -> 52.5 | F66: =SUM(D66:E66) -> 147.5
B67: Cotopaxi | D67: =122*50% -> 61 | E67: =94*50% -> 47 | F67: =SUM(D67:E67) -> 108
B68: El Oro | D68: 122 | E68: =94*50% -> 47 | F68: =SUM(D68:E68) -> 169 | Q68: 39114 | AF68: 39114
B69: Average Rates | D69: =AVERAGE(D66:D68) -> 92.666667 | E69: =AVERAGE(E66:E68) -> 48.833333 | F69: =SUM(D69:E69) -> 141.5 | Q69: 39114 | AF69: 39114
B70: Lodging - Local Staff | C70: locallodg | D70: 122 | E70: per day | Q70: 39114 | AF70: 39114
B71: Meals - Local Staff | C71: localmeals | D71: 47 | E71: per day | Q71: 39114 | AF71: 39114
B72: Miscellaneous - Local Staff | C72: localmisc | D72: 0 | E72: per trip | Q72: 39114 | AF72: 39114
B73: Airfare | C73: localairfare | D73: 195 | E73: round trip coach
B75: Training | C75: Cell Name | D75: Unit Cost | E75: Base
B76: Consultant costs
B77: International Consultant | C77: intcons | D77: 0 | E77: honorarium per day
B78: Regional Consultant | C78: regcons | D78: 0 | E78: honorarium per day
B79: Local Consultant | C79: localcons | D79: 300 | E79: honorarium per day
B80: Travel - airfare | C80: consairfare | D80: 0 | E80: per trip
B81: Travel - ground transp | C81: consground | D81: 0 | E81: per trip
B82: Lodging | C82: conslodg | D82: 0 | E82: per night
B83: Meals and Incidentals | C83: consmeals | D83: 0 | E83: per day
B84: Miscellaneous | C84: consmisc | D84: 0 | E84: per trip
B85: Surveyor fees | C85: surveyor | D85: 9 | E85: survey
B86: Participant costs
B87: Local transport part | C87: parttransp | D87: 4 | E87: per part
B88: Airfare | C88: partairfare | D88: 195 | E88: per trip
B89: Ground Transportation | C89: partground | D89: 9 | E89: per trip
B90: Lodging | C90: partlodg | D90: 60 | E90: per night
B91: Meals and Incidentals | C91: partmeals | D91: =E68 -> 47 | E91: per day
B92: Travel Day Lunch | C92: tdlunch | D92: 12 | E92: per day
B93: Miscellaneous | C93: partmisc | D93: 0 | E93: per trip
B94: Meeting Costs
B95: Coffee Break | C95: coffee | D95: 4 | E95: per person per day
B96: Lunch | C96: lunch | D96: 12 | E96: per person per day
B97: Room Rental | C97: roomrent | D97: 0 | E97: per day
B98: AV Rental | C98: avrent | D98: 0 | E98: per day
B99: Materials & Supplies | C99: mats | D99: 3 | E99: per workshop
B100: Materials & Supplies | C100: partmats | D100: 1 | E100: per workshop
B101: Printing costs | C101: print | D101: 50 | E101: per workshop
B102: Printing costs | C102: partprint | D102: 3 | E102: per workshop
B103: Gude Printing | C103: guideprint | D103: 200 | E103: per canton
B104: Workshops | C104: workshop | D104: 600 | E104: per workshop

Sheet Budget Summary
A3: Project Budget Summary
A4: Partners of the Americas
A5: ='AgroJusto Budget'!C3 -> Project to Improve Adherence to International Labor Standards in the Agricultural Sector in Ecuador Improve Adherence to International Labor Standards in the Agricultural Sector in Ecuador
A6: 48 Months
A8: BUDGET SUMMARY CATEGORIES | B8: YEAR 1 | C8: YEAR 2 | D8: YEAR 3 | E8: YEAR 4 | F8: TOTAL FEDERAL FUNDS REQUESTED
A10: 1. PERSONNEL | B10: ='AgroJusto Budget'!I26 -> 263031.37 | C10: ='AgroJusto Budget'!K26 -> 364757.82 | D10: ='AgroJusto Budget'!M26 -> 382995.71 | E10: ='AgroJusto Budget'!O26 -> 351321.13 | F10: =SUM(B10:E10) -> 1362106
A11: 2. FRINGE BENEFITS | B11: ='AgroJusto Budget'!I33 -> 102524.84 | C11: ='AgroJusto Budget'!K33 -> 144937.95 | D11: ='AgroJusto Budget'!M33 -> 152184.85 | E11: ='AgroJusto Budget'!O33 -> 137771.89 | F11: =SUM(B11:E11) -> 537419.52
A12: 3. TRAVEL | B12: ='AgroJusto Budget'!I51 -> 12386.5 | C12: ='AgroJusto Budget'!K51 -> 65618.28 | D12: ='AgroJusto Budget'!M51 -> 44200.125 | E12: ='AgroJusto Budget'!O51 -> 64333.784 | F12: =SUM(B12:E12) -> 186538.69
A13: 4. EQUIPMENT | B13: ='AgroJusto Budget'!I55 -> 0 | C13: ='AgroJusto Budget'!K55 -> 0 | D13: ='AgroJusto Budget'!M55 -> 0 | E13: ='AgroJusto Budget'!O55 -> 0 | F13: =SUM(B13:E13) -> 0
A14: 5. SUPPLIES | B14: ='AgroJusto Budget'!I60 -> 9907.2 | C14: ='AgroJusto Budget'!K60 -> 1560 | D14: ='AgroJusto Budget'!M60 -> 1622.4 | E14: ='AgroJusto Budget'!O60 -> 1687.296 | F14: =SUM(B14:E14) -> 14776.896
A15: 6. CONTRACTUAL | B15: ='AgroJusto Budget'!I70 -> 108556 | C15: ='AgroJusto Budget'!K70 -> 323812 | D15: ='AgroJusto Budget'!M70 -> 337247 | E15: ='AgroJusto Budget'!O70 -> 224135 | F15: =SUM(B15:E15) -> 993750
A16: 7. CONSTRUCTION | B16: 0 | C16: 0 | D16: 0 | E16: 0 | F16: =SUM(B16:E16) -> 0
A17: 8. OTHER DIRECT COSTS | B17: ='AgroJusto Budget'!I140 -> 109804.36 | C17: ='AgroJusto Budget'!K140 -> 212305.48 | D17: ='AgroJusto Budget'!M140 -> 120960.8 | E17: ='AgroJusto Budget'!O140 -> 157380 | F17: =SUM(B17:E17) -> 600450.64
A19: 9. TOTAL DIRECT COSTS (Lines 1-8) | B19: =SUM(B10:B17) -> 606210.27 | C19: =SUM(C10:C17) -> 1112991.5 | D19: =SUM(D10:D17) -> 1039210.9 | E19: =SUM(E10:E17) -> 936629.1 | F19: =SUM(F10:F17) -> 3695041.8
A20: 10. INDIRECT COSTS | B20: ='AgroJusto Budget'!I144 -> 171436.26 | C20: ='AgroJusto Budget'!K144 -> 314754 | D20: ='AgroJusto Budget'!M144 -> 293888.84 | E20: ='AgroJusto Budget'!O144 -> 264878.71 | F20: =SUM(B20:E20) -> 1044957.8
A21: 11. TOTAL COSTS (Lines 9-10) | B21: =SUM(B19:B20) -> 777646.53 | C21: =SUM(C19:C20) -> 1427745.5 | D21: =SUM(D19:D20) -> 1333099.7 | E21: =SUM(E19:E20) -> 1201507.8 | F21: =SUM(F19:F20) -> 4739999.6

Sheet INDES Sub Budget Summary 
A5: Sub-Award Budget Summary
A6: INDES Sub-Recipient
A7: 48 Months
A9: BUDGET SUMMARY CATEGORIES | B9: YEAR 1 | C9: YEAR 2 | D9: YEAR 3 | E9: YEAR 4 | F9: TOTAL FEDERAL FUNDS REQUESTED
A11: 1. PERSONNEL | B11: ='[1]INDES Sub Line-Item Budget'!G23 -> 47950 | C11: ='[1]INDES Sub Line-Item Budget'!I23 -> 85200 | D11: ='[1]INDES Sub Line-Item Budget'!K23 -> 85200 | E11: ='[1]INDES Sub Line-Item Budget'!M23 -> 43000 | F11: =SUM(B11:E11) -> 261350
A12: 2. FRINGE BENEFITS | B12: =+'[1]INDES Sub Line-Item Budget'!G30 -> 23700.32 | C12: =+'[1]INDES Sub Line-Item Budget'!I30 -> 41723.509 | D12: =+'[1]INDES Sub Line-Item Budget'!K30 -> 41723.509 | E12: =+'[1]INDES Sub Line-Item Budget'!M30 -> 20805.292 | F12: =SUM(B12:E12) -> 127952.63
A13: 3. TRAVEL | B13: ='[1]INDES Sub Line-Item Budget'!G34 -> 1948 | C13: ='[1]INDES Sub Line-Item Budget'!I34 -> 34625.4 | D13: ='[1]INDES Sub Line-Item Budget'!K34 -> 37775.962 | E13: ='[1]INDES Sub Line-Item Budget'!M34 -> 23734.63 | F13: =SUM(B13:E13) -> 98083.992
A14: 4. EQUIPMENT | B14: ='[1]INDES Sub Line-Item Budget'!G36 -> 0 | C14: 0 | D14: 0 | E14: 0 | F14: =SUM(B14:E14) -> 0
A15: 5. SUPPLIES | B15: =+'[1]INDES Sub Line-Item Budget'!G51 -> 10389.882 | C15: =+'[1]INDES Sub Line-Item Budget'!I51 -> 5669.6471 | D15: =+'[1]INDES Sub Line-Item Budget'!K51 -> 5669.6471 | E15: =+'[1]INDES Sub Line-Item Budget'!M51 -> 2789.8235 | F15: =SUM(B15:E15) -> 24519
A16: 6. CONTRACTUAL | B16: 0 | C16: 0 | D16: 0 | E16: 0 | F16: =SUM(B16:E16) -> 0
A17: 7. CONSTRUCTION | B17: 0 | C17: 0 | D17: 0 | E17: 0 | F17: =SUM(B17:E17) -> 0
A18: 8. OTHER DIRECT COSTS | B18: ='[1]INDES Sub Line-Item Budget'!G86 -> 5608 | C18: ='[1]INDES Sub Line-Item Budget'!I86 -> 72147.976 | D18: ='[1]INDES Sub Line-Item Budget'!K86 -> 70385.456 | E18: ='[1]INDES Sub Line-Item Budget'!M86 -> 52453.144 | F18: =SUM(B18:E18) -> 200594.58
A20: 9. TOTAL DIRECT COSTS (Lines 1-8) | B20: =SUM(B11:B18) -> 89596.202 | C20: =SUM(C11:C18) -> 239366.53 | D20: =SUM(D11:D18) -> 240754.57 | E20: =SUM(E11:E18) -> 142782.89 | F20: =SUM(F11:F18) -> 712500.2
A21: 10. INDIRECT COSTS | B21: =+B20*0.1 -> 8959.6202 | C21: =+C20*0.1 -> 23936.653 | D21: =+D20*0.1 -> 24075.457 | E21: =+E20*0.1 -> 14278.289 | F21: =SUM(B21:E21) -> 71250.02
A22: 11. TOTAL COSTS (Lines 9-10) | B22: =SUM(B20:B21) -> 98555.822 | C22: =SUM(C20:C21) -> 263303.19 | D22: =SUM(D20:D21) -> 264830.03 | E22: =SUM(E20:E21) -> 157061.18 | F22: =SUM(F20:F21) -> 783750.22

Sheet INDES Sub Budget
E1: Project Line-Item Budget
E2: INDES
E3: 48 Months
E4: Cost Assumptions
A5: Entity: | B5: P | E5: Inflation - US Based Goods/Services | F5: 1.03
A6: Program-Dept.: | B6: 20200 | E6: Inflation - Locally Purchased Goods/Services | F6: 1.04
A7: Funder-Grant: | B7: DOL427 | E7: Merit Based Increases for HO & Field Staff | F7: 1.05
A9: Activity Code | B9: Account Code | C9: Country Code | D9: Country Code | E9: BUDGET ITEM | F9: CATEGORY | G9: LOE | H9: UNIT | I9: # of Units | J9: RATE / UNIT | K9: Year 1 | L9: # of Units | M9: Year 2 | N9: # of Units | O9: Year 3 | P9: # of Units | Q9: Year 4 | R9: TOTAL US$ | S9: TOTAL COST SHARING | T9: PROJECT GRAND TOTAL
E10: Personnel
E12: Professional Personnel
A13: SUBINDES | B13: 89050 | C13: ECU | D13: INDPERDIR | E13: Director | F13: Salaries | G13: 0.5 | H13: Month | I13: 11 | J13: 2000 | K13: =I13*J13 -> 22000 | L13: 12 | M13: =(2000)*L13 -> 24000 | N13: 12 | O13: =(2000)*N13 -> 24000 | P13: 7 | Q13: =(2000)*P13 -> 14000 | R13: =SUM(K13+M13+O13+Q13) -> 84000 | S13: 0 | T13: =SUM(R13:S13) -> 84000
A14: SUBINDES | B14: 89050 | C14: ECU | D14: INDPERPC | E14: Project Coordinator | F14: Salaries | G14: 0.5 | H14: Month | I14: 11 | J14: 1100 | K14: =I14*J14 -> 12100 | L14: 12 | M14: =(1100)*L14 -> 13200 | N14: 12 | O14: =(1100)*N14 -> 13200 | P14: 5 | Q14: =(1100)*P14 -> 5500 | R14: =SUM(K14+M14+O14+Q14) -> 44000 | S14: 0 | T14: =SUM(R14:S14) -> 44000
A15: SUBINDES | B15: 89050 | C15: ECU | D15: INDPERF&AO | E15: Finance & Administration Officer | F15: Salaries | G15: 0.5 | H15: Month | I15: 11 | J15: 750 | K15: =I15*J15 -> 8250 | L15: 12 | M15: =L15*J15 -> 9000 | N15: 12 | O15: =(N15*J15) -> 9000 | P15: 7 | Q15: =P15*J15 -> 5250 | R15: =SUM(K15+M15+O15+Q15) -> 31500 | S15: 0 | T15: =SUM(R15:S15) -> 31500
A16: SUBINDES | B16: 89050 | C16: ECU | D16: INDPERF&AA | E16: Finance & Administration Assistant | F16: Salaries | G16: 0.5 | H16: Month | I16: 4 | J16: 800 | K16: =I16*J16 -> 3200 | L16: 12 | M16: =L16*J16 -> 9600 | N16: 12 | O16: =(N16*J16) -> 9600 | P16: 5 | Q16: =P16*J16 -> 4000 | R16: =SUM(K16+M16+O16+Q16) -> 26400 | S16: 0 | T16: =SUM(R16:S16) -> 26400
A17: SUBINDES | B17: 89050 | C17: ECU | D17: INDPERLC | E17: Local Coordinator | F17: Salaries | G17: 0.5 | H17: Month | I17: 4 | J17: 600 | K17: =I17*J17 -> 2400 | L17: 12 | M17: =(600)*L17 -> 7200 | N17: 12 | O17: =(600)*N17 -> 7200 | P17: 5 | Q17: =(600)*P17 -> 3000 | R17: =SUM(K17+M17+O17+Q17) -> 19800 | S17: 0 | T17: =SUM(R17:S17) -> 19800
A18: SUBINDES | B18: 89050 | C18: ECU | D18: INDPERM&E | E18: M&E Officer | F18: Salaries | G18: 1 | H18: Month | I18: 0 | J18: 1000 | K18: =I18*J18 -> 0 | L18: 12 | M18: =(1000)*L18 -> 12000 | N18: 12 | O18: =(1000)*N18 -> 12000 | P18: 7 | Q18: =(1000)*P18 -> 7000 | R18: =SUM(K18+M18+O18+Q18) -> 31000 | S18: 0 | T18: =SUM(R18:S18) -> 31000
A19: SUBINDES | B19: 89050 | C19: ECU | D19: INDPERTECH | E19: Technical Officer x 1 | F19: Salaries | G19: 1 | H19: Month | I19: 0 | J19: 850 | K19: =I19*J19*G19 -> 0 | L19: 12 | M19: =(850)*L19 -> 10200 | N19: 12 | O19: =(850)*N19 -> 10200 | P19: 5 | Q19: =(850)*P19 -> 4250 | R19: =SUM(K19+M19+O19+Q19) -> 24650 | S19: 0 | T19: =SUM(R19:S19) -> 24650
E22: Total Personnel | K22: =SUM(K11:K20) -> 47950 | M22: =SUM(M11:M20) -> 85200 | O22: =SUM(O11:O20) -> 85200 | Q22: =SUM(Q11:Q20) -> 43000 | R22: =SUM(R11:R20) -> 261350 | S22: =SUM(S11:S19) -> 0 | T22: =SUM(R22:S22) -> 261350
E23: Fringe Benefits
E25: Fringe Benefits
A26: SUBINDES | B26: 89050 | C26: ECU | D26: INDFRINGEC | E26: Fringe benefits - Ecuador | F26: Fringe Benefits | H26: Month | J26: 0.483844 | K26: =K22*J26 -> 23200.32 | M26: =M22*J26 -> 41223.509 | O26: =O22*J26 -> 41223.509 | Q26: =J26*Q22 -> 20805.292 | R26: =SUM(K26+M26+O26+Q26) -> 126452.63 | S26: 0 | T26: =SUM(R26:S26) -> 126452.63
A27: SUBINDES | B27: 89050 | C27: ECU | D27: INDLIFEIN | E27: Fringe benefits - Ecuador - Life Insurance | F27: Fringe Benefits | H27: Annual | K27: 500 | M27: 500 | O27: 500 | R27: =SUM(K27+M27+O27+Q27) -> 1500 | T27: =SUM(R27:S27) -> 1500
E29: Total Fringe Benefits | K29: =SUM(K26:K28) -> 23700.32 | M29: =SUM(M26:M28) -> 41723.509 | O29: =SUM(O26:O28) -> 41723.509 | Q29: =SUM(Q26:Q28) -> 20805.292 | R29: =SUM(R26:R28) -> 127952.63 | S29: =SUM(S26:S28) -> 0 | T29: =SUM(T26:T28) -> 127952.63
E30: Travel
A31: SUBINDES | B31: 89050 | C31: ECU | D31: INDTRLCOPX | E31: T3: Domestic Travel to Field (See Travel Detail Tab) / | F31: Cotopaxi | K31: =+'[1]INDES Sub Activities Detail'!J728 -> 1308 | M31: =+'[1]INDES Sub Activities Detail'!M728 -> 16055.52 | O31: =+'[1]INDES Sub Activities Detail'!P728 -> 18276.877 | Q31: =+'[1]INDES Sub Activities Detail'!S728 -> 9734.5731 | R31: =SUM(K31+M31+O31+Q31) -> 45374.97 | T31: =SUM(R31:S31) -> 45374.97
A32: SUBINDES | B32: 89050 | C32: ECU | D32: INDTRLORO | E32: T3: Domestic Travel to Field (See Travel Detail Tab) | F32: El Oro | K32: =+'[1]INDES Sub Activities Detail'!J729 -> 640 | M32: =+'[1]INDES Sub Activities Detail'!M729 -> 18569.88 | O32: =+'[1]INDES Sub Activities Detail'!P729 -> 19499.085 | Q32: =+'[1]INDES Sub Activities Detail'!S729 -> 14000.057 | R32: =SUM(K32+M32+O32+Q32) -> 52709.022 | T32: =SUM(R32:S32) -> 52709.022
E33: Total Travel | K33: =SUM(K31:K32) -> 1948 | M33: =SUM(M31:M32) -> 34625.4 | O33: =SUM(O31:O32) -> 37775.962 | Q33: =SUM(Q31:Q32) -> 23734.63 | R33: =SUM(R31:R32) -> 98083.992 | S33: =SUM(S31:S31) -> 0 | T33: =SUM(R33:S33) -> 98083.992
E34: Equipment
E35: Equipment | F35: Equipment | H35: Unit | I35: 0 | J35: 0 | K35: =I35*J35 -> 0 | L35: 0 | M35: =L35*J35*[1]Assumptions!$C$19 -> 0 | N35: 0 | O35: =N35*J35*[1]Assumptions!$C$19*[1]Assumptions!$C$19 -> 0 | P35: 0 | Q35: =P35*J35*[1]Assumptions!$C$19*[1]Assumptions!$C$19*[1]Assumptions!$C$19 -> 0 | R35: =SUM(K35+M35+O35+Q35) -> 0 | S35: 0 | T35: =SUM(R35:S35) -> 0
E37: Total Equipment | K37: =SUM(K35) -> 0 | M37: =SUM(M35) -> 0 | O37: =SUM(O35) -> 0 | Q37: =SUM(Q35) -> 0 | R37: =SUM(R35) -> 0 | S37: =SUM(S35) -> 0 | T37: =SUM(R37:S37) -> 0
E38: Supplies
A39: SUBINDES | B39: 89050 | C39: ECU | D39: INDOFFSUP | E39: Office supplies | F39: Supplies | H39: Month | I39: 4 | J39: 130 | K39: =J39*I39 -> 520 | L39: 12 | M39: =L39*J39 -> 1560 | N39: 12 | O39: =N39*J39 -> 1560 | P39: 8 | Q39: =P39*J39 -> 1040 | R39: =SUM(K39+M39+O39+Q39) -> 4680 | S39: 0 | T39: =SUM(R39:S39) -> 4680
A40: SUBINDES | B40: 89050 | C40: ECU | D40: INDCOMPUT | E40: Computers | F40: Supplies | H40: Month | I40: 5 | J40: 1000 | K40: =J40*I40 -> 5000 | L40: 0 | M40: =L40*J40 -> 0 | N40: 0 | O40: =N40*J40 -> 0 | P40: 0 | Q40: =P40*J40 -> 0 | R40: =SUM(K40+M40+O40+Q40) -> 5000 | T40: =SUM(R40:S40) -> 5000
A41: SUBINDES | B41: 89050 | C41: ECU | D41: INDLICENC | E41: Licences | F41: Supplies | H41: Month | I41: 5 | J41: 150 | K41: =J41*I41 -> 750 | L41: 5 | M41: =L41*J41 -> 750 | N41: 5 | O41: =N41*J41 -> 750 | P41: 0 | Q41: =P41*J41 -> 0 | R41: =SUM(K41+M41+O41+Q41) -> 2250 | T41: =SUM(R41:S41) -> 2250
A42: SUBINDES | B42: 89050 | C42: ECU | D42: INDEQUIPIN | E42: Equipment insurance | F42: Supplies | H42: Month | I42: 5 | J42: 80 | K42: =J42*I42 -> 400 | L42: 5 | M42: =L42*J42 -> 400 | N42: 5 | O42: =N42*J42 -> 400 | P42: 0 | Q42: =P42*J42 -> 0 | R42: =SUM(K42+M42+O42+Q42) -> 1200 | T42: =SUM(R42:S42) -> 1200
A43: SUBINDES | B43: 89050 | C43: ECU | D43: INDFURNT | E43: Office furniture | F43: Supplies | H43: Month | I43: 1 | J43: 1800 | K43: =J43*I43 -> 1800 | M43: =L43*J43 -> 0 | O43: =N43*J43 -> 0 | Q43: =P43*J43 -> 0 | R43: =SUM(K43+M43+O43+Q43) -> 1800 | T43: =SUM(R43:S43) -> 1800
A44: SUBINDES | B44: 89050 | C44: ECU | D44: INDEQUIPMA | E44: Equipment maintenance | F44: Supplies | H44: Month | I44: 0 | J44: 40 | K44: =J44*I44 -> 0 | L44: 5 | M44: =L44*J44 -> 200 | N44: 5 | O44: =N44*J44 -> 200 | Q44: =P44*J44 -> 0 | R44: =SUM(K44+M44+O44+Q44) -> 400 | T44: =SUM(R44:S44) -> 400
A45: SUBINDES | B45: 89050 | C45: ECU | D45: INDACCTSYM | E45: Accounting system | F45: Supplies | H45: Month | I45: 4 | J45: 25 | K45: =J45*I45 -> 100 | L45: 12 | M45: =L45*J45 -> 300 | N45: 12 | O45: =N45*J45 -> 300 | P45: 8 | Q45: =P45*J45 -> 200 | R45: =SUM(K45+M45+O45+Q45) -> 900 | T45: =SUM(R45:S45) -> 900
A46: SUBINDES | B46: 89050 | C46: ECU | D46: INDCOMMATL | E46: Coomunicationa material | F46: Supplies | H46: Month | I46: 4 | J46: 100 | K46: =J46*I46 -> 400 | L46: 12 | M46: =L46*J46 -> 1200 | N46: 12 | O46: =N46*J46 -> 1200 | P46: 8 | Q46: =P46*J46 -> 800 | R46: =SUM(K46+M46+O46+Q46) -> 3600 | T46: =SUM(R46:S46) -> 3600
A47: SUBINDES | B47: 89050 | C47: ECU | D47: INDCOMFEES | E47: Communication fees | F47: Supplies | H47: Month | I47: 4 | J47: 44.970588 | K47: =J47*I47 -> 179.88235 | L47: 12 | M47: =L47*J47 -> 539.64706 | N47: 12 | O47: =N47*J47 -> 539.64706 | P47: 6 | Q47: =P47*J47 -> 269.82353 | R47: =SUM(K47+M47+O47+Q47) -> 1529 | T47: =SUM(R47:S47) -> 1529
A48: SUBINDES | B48: 89050 | C48: ECU | D48: INDLEGAL | E48: Legal fees | F48: Supplies | H48: Month | I48: 1 | J48: 1000 | K48: =J48*I48 -> 1000 | M48: =L48*J48 -> 0 | O48: =N48*J48 -> 0 | Q48: =P48*J48 -> 0 | R48: =SUM(K48+M48+O48+Q48) -> 1000 | T48: =SUM(R48:S48) -> 1000
A49: SUBINDES | B49: 89050 | C49: ECU | D49: INDBANKFEE | E49: Bank fees | F49: Supplies | H49: Month | I49: 4 | J49: 60 | K49: =J49*I49 -> 240 | L49: 12 | M49: =L49*J49 -> 720 | N49: 12 | O49: =N49*J49 -> 720 | P49: 8 | Q49: =P49*J49 -> 480 | R49: =SUM(K49+M49+O49+Q49) -> 2160 | T49: =SUM(R49:S49) -> 2160
E50: Total Supplies | K50: =SUM(K39:K49) -> 10389.882 | M50: =SUM(M39:M49) -> 5669.6471 | O50: =SUM(O39:O49) -> 5669.6471 | Q50: =SUM(Q39:Q49) -> 2789.8235 | R50: =SUM(R39:R49) -> 24519 | S50: =SUM(S39:S39) -> 0 | T50: =SUM(T39:T49) -> 24519
E51: Contractual
E53: Total Contractual | K53: =SUM(K52:K52) -> 0 | M53: =SUM(M52:M52) -> 0 | O53: =SUM(O52:O52) -> 0 | Q53: =SUM(Q52:Q52) -> 0 | R53: =SUM(R52:R52) -> 0 | S53: =SUM(S52:S52) -> 0 | T53: =SUM(T52:T52) -> 0
E54: Other Direct Costs
E55: Project Office
A56: SUBINDES | B56: 89050 | C56: ECU | D56: INDOFFICE | E56: INDES Project Office | F56: Office Expenses | H56: Month | I56: 4 | J56: 600 | K56: =I56*J56 -> 2400 | L56: 12 | M56: =+J56*L56 -> 7200 | N56: 12 | O56: =+J56*N56 -> 7200 | P56: 8 | Q56: =+J56*P56 -> 4800 | R56: =SUM(K56+M56+O56+Q56) -> 21600 | S56: 0 | T56: =SUM(R56:S56) -> 21600
E57: Outcome 1
E58: Activity 1.1. Assess labor law enforcement institutions, processes, and services: challenges and opportunities for action to address child labor and forced labor | F58: Outcome 1 | K58: ='[1]INDES Sub Activities Detail'!J20+'[1]INDES Sub Activities Detail'!J34 -> 0 | M58: ='[1]INDES Sub Activities Detail'!M20+'[1]INDES Sub Activities Detail'!M34 -> 0 | O58: ='[1]INDES Sub Activities Detail'!P20+'[1]INDES Sub Activities Detail'!P34 -> 0 | Q58: =+'[1]INDES Sub Activities Detail'!S20+'[1]INDES Sub Activities Detail'!S34 -> 0 | R58: =SUM(K58+M58+O58+Q58) -> 0
E59: Activity 1.2. Strengthen intersectoral coordination by re-invigorating referral mechanisms and strengthening Consejos and Juntas: | F59: Outcome 1 | K59: ='[1]INDES Sub Activities Detail'!J50+'[1]INDES Sub Activities Detail'!J64 -> 0 | M59: =+'[1]INDES Sub Activities Detail'!M50+'[1]INDES Sub Activities Detail'!M64 -> 0 | O59: ='[1]INDES Sub Activities Detail'!P50+'[1]INDES Sub Activities Detail'!P64 -> 0 | Q59: ='[1]INDES Sub Activities Detail'!S50+'[1]INDES Sub Activities Detail'!S64 -> 0 | R59: =SUM(K59+M59+O59+Q59) -> 0
A60: SUBINDES | B60: 89050 | C60: ECU | D60: INDES1.3 | E60: Activity 1.3. Develop government capacity building strategy applying assessment results | F60: Outcome 1 | K60: =+'[1]INDES Sub Activities Detail'!J79+'[1]INDES Sub Activities Detail'!J104 -> 0 | M60: =+'[1]INDES Sub Activities Detail'!M79+'[1]INDES Sub Activities Detail'!M104 -> 4944.576 | O60: ='[1]INDES Sub Activities Detail'!P79+'[1]INDES Sub Activities Detail'!P104 -> 0 | Q60: ='[1]INDES Sub Activities Detail'!S79+'[1]INDES Sub Activities Detail'!S104 -> 0 | R60: =SUM(K60+M60+O60+Q60) -> 4944.576 | T60: =SUM(R60:S60) -> 4944.576
A61: SUBINDES | B61: 89050 | C61: ECU | D61: INDES1.4 | E61: Activity 1.4. Develop, deliver, and institutionalize tailored capacity building for government officials: | F61: Outcome1 | K61: ='[1]INDES Sub Activities Detail'!J118+'[1]INDES Sub Activities Detail'!J133 -> 450 | M61: ='[1]INDES Sub Activities Detail'!M118+'[1]INDES Sub Activities Detail'!M133 -> 2808 | O61: ='[1]INDES Sub Activities Detail'!P118+'[1]INDES Sub Activities Detail'!P133 -> 2920.32 | Q61: ='[1]INDES Sub Activities Detail'!S118+'[1]INDES Sub Activities Detail'!S133 -> 1518.5664 | R61: =SUM(K61+M61+O61+Q61) -> 7696.8864 | T61: =SUM(R61:S61) -> 7696.8864
E62: Activity 1.5. Strengthen digital child labor tracking and public reporting/accountability: | F62: Outcome 1 | K62: ='[1]INDES Sub Activities Detail'!J148+'[1]INDES Sub Activities Detail'!J164 -> 0 | M62: ='[1]INDES Sub Activities Detail'!M148+'[1]INDES Sub Activities Detail'!M164 -> 0 | O62: ='[1]INDES Sub Activities Detail'!P148+'[1]INDES Sub Activities Detail'!P164 -> 0 | Q62: ='[1]INDES Sub Activities Detail'!S148+'[1]INDES Sub Activities Detail'!S164 -> 0 | R62: =SUM(K62+M62+O62+Q62) -> 0
A63: SUBINDES | B63: 89050 | C63: ECU | D63: INDES1.6 | E63: Activity 1.6. Partner with GADs to integrate enforcement processes and capacity building into local community development plans and budgets: | F63: Outcome1 | K63: ='[1]INDES Sub Activities Detail'!J178+'[1]INDES Sub Activities Detail'!J194 -> 315 | M63: =+'[1]INDES Sub Activities Detail'!M178+'[1]INDES Sub Activities Detail'!M194 -> 2948.4 | O63: ='[1]INDES Sub Activities Detail'!P178+'[1]INDES Sub Activities Detail'!P194 -> 3066.336 | Q63: ='[1]INDES Sub Activities Detail'!S178+'[1]INDES Sub Activities Detail'!S194 -> 1771.6608 | R63: =SUM(K63+M63+O63+Q63) -> 8101.3968 | T63: =SUM(R63:S63) -> 8101.3968
E64: Activity 1.7 Disseminate successes: | F64: Outcome1 | K64: ='[1]INDES Sub Activities Detail'!J208+'[1]INDES Sub Activities Detail'!J222 -> 0 | M64: ='[1]INDES Sub Activities Detail'!M208+'[1]INDES Sub Activities Detail'!M222 -> 0 | O64: ='[1]INDES Sub Activities Detail'!P208+'[1]INDES Sub Activities Detail'!P222 -> 0 | Q64: ='[1]INDES Sub Activities Detail'!S208+'[1]INDES Sub Activities Detail'!S222 -> 0 | R64: =SUM(K64+M64+O64+Q64) -> 0 | T64: =SUM(R64:S64) -> 0
E66: Outcome 2
E67: Activity 2.1. Assess rural workers’ information needs, work experiences, and trusted organizations | F67: Outcome2 | K67: =+'[1]INDES Sub Activities Detail'!J233+'[1]INDES Sub Activities Detail'!J248 -> 0 | M67: =+'[1]INDES Sub Activities Detail'!M233+'[1]INDES Sub Activities Detail'!M248 -> 0 | O67: =+'[1]INDES Sub Activities Detail'!P233+'[1]INDES Sub Activities Detail'!P248 -> 0 | Q67: =+'[1]INDES Sub Activities Detail'!S233+'[1]INDES Sub Activities Detail'!S248 -> 0 | R67: =SUM(K67+M67+O67+Q67) -> 0 | T67: =SUM(R67:S67) -> 0
A68: SUBINDES | B68: 89050 | C68: ECU | D68: INDES2.2 | E68: Activity 2.2. Build capacity of worker organizations, producer associations, and other actors to reach workers to understand their rights | F68: Outcome2 | K68: =+'[1]INDES Sub Activities Detail'!J262+'[1]INDES Sub Activities Detail'!J277 -> 1620 | M68: =+'[1]INDES Sub Activities Detail'!M262+'[1]INDES Sub Activities Detail'!M277 -> 9620 | O68: =+'[1]INDES Sub Activities Detail'!P262+'[1]INDES Sub Activities Detail'!P277 -> 11032.32 | Q68: =+'[1]INDES Sub Activities Detail'!S262+'[1]INDES Sub Activities Detail'!S277 -> 7835.8026 | R68: =SUM(K68+M68+O68+Q68) -> 30108.123 | T68: =SUM(R68:S68) -> 30108.123
A69: SUBINDES | B69: 89050 | C69: ECU | D69: INDES2.3 | E69: Activity 2.3. Institutionalize worker and community training and awareness-raising | F69: Outcome2 | K69: =+'[1]INDES Sub Activities Detail'!J292+'[1]INDES Sub Activities Detail'!J306 -> 0 | M69: =+'[1]INDES Sub Activities Detail'!M292+'[1]INDES Sub Activities Detail'!M306 -> 5460 | O69: =+'[1]INDES Sub Activities Detail'!P292+'[1]INDES Sub Activities Detail'!P306 -> 5678.4 | Q69: =+'[1]INDES Sub Activities Detail'!S292+'[1]INDES Sub Activities Detail'!S306 -> 5061.888 | R69: =SUM(K69+M69+O69+Q69) -> 16200.288 | T69: =SUM(R69:S69) -> 16200.288
A70: SUBINDES | B70: 89050 | C70: ECU | D70: INDES2.4 | E70: Activity 2.4. Establish and convene neutral spaces for bipartite and tripartite social dialogue | F70: Outcome2 | K70: =+'[1]INDES Sub Activities Detail'!J319+'[1]INDES Sub Activities Detail'!J333 -> 0 | M70: =+'[1]INDES Sub Activities Detail'!M319+'[1]INDES Sub Activities Detail'!M333 -> 4680 | O70: =+'[1]INDES Sub Activities Detail'!P319+'[1]INDES Sub Activities Detail'!P333 -> 4867.2 | Q70: =+'[1]INDES Sub Activities Detail'!S319+'[1]INDES Sub Activities Detail'!S333 -> 3374.592 | R70: =SUM(K70+M70+O70+Q70) -> 12921.792 | T70: =SUM(R70:S70) -> 12921.792
A71: SUBINDES | B71: 89050 | C71: ECU | D71: INDES2.5 | E71: Activity 2.5. Train small, medium, and large employers to engage workers, understand workers’ rights, and monitor rights compliance in their supply chains | F71: Outcome2 | K71: =+'[1]INDES Sub Activities Detail'!J345+'[1]INDES Sub Activities Detail'!J359 -> 0 | M71: =+'[1]INDES Sub Activities Detail'!M345+'[1]INDES Sub Activities Detail'!M359 -> 5616 | O71: =+'[1]INDES Sub Activities Detail'!P345+'[1]INDES Sub Activities Detail'!P359 -> 5840.64 | Q71: =+'[1]INDES Sub Activities Detail'!S345+'[1]INDES Sub Activities Detail'!S359 -> 4049.5104 | R71: =SUM(K71+M71+O71+Q71) -> 15506.15 | T71: =SUM(R71:S71) -> 15506.15
A72: SUBINDES | B72: 89050 | C72: ECU | D72: INDES2.6 | E72: Activity 2.6 Partner with GADs to integrate the above training, awareness-raising, and social dialogue activities into community development plans | F72: Outcome 2 | M72: =+'[1]INDES Sub Activities Detail'!M372+'[1]INDES Sub Activities Detail'!M386 -> 1872 | O72: =+'[1]INDES Sub Activities Detail'!P372+'[1]INDES Sub Activities Detail'!P386 -> 1946.88 | Q72: =+'[1]INDES Sub Activities Detail'!S372 -> 2335.2177 | R72: =K72+M72+O72+Q72 -> 6154.0977 | T72: =SUM(R72:S72) -> 6154.0977
A73: SUBINDES | B73: 89050 | C73: ECU | D73: INDES2.7 | E73: Activity 2.7. Generate new opportunities for learning among civil society, workers, government, private sector, and others. | F73: Outcome2 | K73: =+'[1]INDES Sub Activities Detail'!J399+'[1]INDES Sub Activities Detail'!J414 -> 0 | M73: =+'[1]INDES Sub Activities Detail'!M399+'[1]INDES Sub Activities Detail'!M414 -> 936 | O73: =+'[1]INDES Sub Activities Detail'!P399+'[1]INDES Sub Activities Detail'!P414 -> 973.44 | Q73: =+'[1]INDES Sub Activities Detail'!S399+'[1]INDES Sub Activities Detail'!S414 -> 506.1888 | R73: =SUM(K73+M73+O73+Q73) -> 2415.6288 | T73: =SUM(R73:S73) -> 2415.6288
E74: Activity 2.8. Assess changes in rural workers’, business, Community-Based Organizations, and government officials’ knowledge, skills, and practices. | F74: Outcome2 | K74: =+'[1]INDES Sub Activities Detail'!J428+'[1]INDES Sub Activities Detail'!J442 -> 0 | M74: =+'[1]INDES Sub Activities Detail'!M428+'[1]INDES Sub Activities Detail'!M442 -> 0 | O74: =+'[1]INDES Sub Activities Detail'!P428+'[1]INDES Sub Activities Detail'!P442 -> 0 | Q74: =+'[1]INDES Sub Activities Detail'!S428+'[1]INDES Sub Activities Detail'!S442 -> 0 | R74: =SUM(K74+M74+O74+Q74) -> 0 | T74: =SUM(R74:S74) -> 0
E75: Outcome 3 | T75: =SUM(R75:S75) -> 0
E76: Activity 3.1 Undertake an analysis of remediation constraints and opportunities[ | F76: Outcome3 | K76: =+'[1]INDES Sub Activities Detail'!J456+'[1]INDES Sub Activities Detail'!J468 -> 0 | M76: =+'[1]INDES Sub Activities Detail'!M456+'[1]INDES Sub Activities Detail'!M468 -> 0 | O76: =+'[1]INDES Sub Activities Detail'!P456+'[1]INDES Sub Activities Detail'!P468 -> 0 | Q76: =+'[1]INDES Sub Activities Detail'!S456+'[1]INDES Sub Activities Detail'!S468 -> 0 | R76: =SUM(K76+M76+O76+Q76) -> 0 | T76: =SUM(R76:S76) -> 0
E77: Activity 3.2 Validate analysis and select pilot remediation mechanism designs | F77: Outcome3 | K77: =+'[1]INDES Sub Activities Detail'!J482+'[1]INDES Sub Activities Detail'!J497 -> 0 | M77: =+'[1]INDES Sub Activities Detail'!M482+'[1]INDES Sub Activities Detail'!M497 -> 0 | O77: =+'[1]INDES Sub Activities Detail'!P482+'[1]INDES Sub Activities Detail'!P497 -> 0 | Q77: =+'[1]INDES Sub Activities Detail'!S482+'[1]INDES Sub Activities Detail'!S497 -> 0 | R77: =SUM(K77+M77+O77+Q77) -> 0 | T77: =SUM(R77:S77) -> 0
A78: SUBINDES | B78: 89050 | C78: ECU | D78: INDES3.3 | E78: Activity 3.3. Engage partners to design, implement, and monitor pilot remediation solutions | F78: Outcome3 | K78: =+'[1]INDES Sub Activities Detail'!J512+'[1]INDES Sub Activities Detail'!J525 -> 0 | M78: =+'[1]INDES Sub Activities Detail'!M512+'[1]INDES Sub Activities Detail'!M525 -> 1248 | O78: =+'[1]INDES Sub Activities Detail'!P512+'[1]INDES Sub Activities Detail'!P525 -> 1297.92 | Q78: =+'[1]INDES Sub Activities Detail'!S512+'[1]INDES Sub Activities Detail'!S525 -> 0 | R78: =SUM(K78+M78+O78+Q78) -> 2545.92 | T78: =SUM(R78:S78) -> 2545.92
E79: .Activity 3.4. Finalize and institutionalize proven grievance and restitution mechanisms | F79: Outcome3 | K79: =+'[1]INDES Sub Activities Detail'!J539+'[1]INDES Sub Activities Detail'!J553 -> 0 | M79: =+'[1]INDES Sub Activities Detail'!M539+'[1]INDES Sub Activities Detail'!M553 -> 0 | O79: =+'[1]INDES Sub Activities Detail'!P539+'[1]INDES Sub Activities Detail'!P553 -> 0 | Q79: =+'[1]INDES Sub Activities Detail'!S539+'[1]INDES Sub Activities Detail'!S553 -> 0 | R79: =SUM(K79+M79+O79+Q79) -> 0 | T79: =SUM(R79:S79) -> 0
E80: Activity 3.5. Develop and integrate an anonymous reporting mechanism | F80: Outcome3 | K80: =+'[1]INDES Sub Activities Detail'!J567+'[1]INDES Sub Activities Detail'!J581 -> 0 | M80: ='[1]INDES Sub Activities Detail'!M567+'[1]INDES Sub Activities Detail'!M581 -> 0 | O80: =+'[1]INDES Sub Activities Detail'!P567+'[1]INDES Sub Activities Detail'!P581 -> 0 | Q80: =+'[1]INDES Sub Activities Detail'!S567+'[1]INDES Sub Activities Detail'!S581 -> 0 | R80: =SUM(K80+M80+O80+Q80) -> 0 | T80: =SUM(R80:S80) -> 0
A81: SUBINDES | B81: 89050 | C81: ECU | D81: INDES3.6 | E81: Activity 3.6. Engage medium and large producers to strengthen grievance and restitution mechanisms in their workplaces and supply chains. | F81: Outcome 3 | K81: =+'[1]INDES Sub Activities Detail'!J689+'[1]INDES Sub Activities Detail'!J703 -> 0 | M81: =+'[1]INDES Sub Activities Detail'!M689+'[1]INDES Sub Activities Detail'!M703 -> 7800 | O81: =+'[1]INDES Sub Activities Detail'!P689+'[1]INDES Sub Activities Detail'!P703 -> 6760 | Q81: =+'[1]INDES Sub Activities Detail'!S689+'[1]INDES Sub Activities Detail'!S703 -> 6474.7172 | R81: =SUM(K81+M81+O81+Q81) -> 21034.717 | T81: =SUM(R81:S81) -> 21034.717
E82: Monitoring, Evaluation, and Collection of Reliable Data
A83: SUBINDES | B83: 89050 | C83: ECU | D83: INDM&ETRAN | E83: Transportation - Field Verification & Data Collection Expenses | K83: 338 | M83: 7012 | O83: 7697 | Q83: 6281 | R83: =SUM(K83+M83+O83+Q83) -> 21328 | T83: =SUM(R83:S83) -> 21328
A84: SUBINDES | B84: 89050 | C84: ECU | D84: INDM&ELODG | E84: Lodging and M&IE - Field Verification & Data Collection Expenses | K84: 485 | M84: 10003 | O84: 11105 | Q84: 8444 | R84: =SUM(K84+M84+O84+Q84) -> 30037 | T84: =SUM(R84:S84) -> 30037
E85: Total Other Direct Costs | K85: =SUM(K56:K84) -> 5608 | M85: =SUM(M56:M84) -> 72147.976 | O85: =SUM(O56:O84) -> 70385.456 | Q85: =SUM(Q56:Q84) -> 52453.144 | R85: =SUM(R56:R84) -> 200594.58 | S85: =SUM(S63:S67) -> 0 | T85: =SUM(T56:T84) -> 200594.58
E87: Total Direct Costs | K87: =SUM(K22+K29+K33+K50++K85+K53+K37) -> 89596.202 | M87: =SUM(M22+M29+M33+M50++M85+M53+M37) -> 239366.53 | O87: =SUM(O22+O29+O33+O50++O85+O53+O37) -> 240754.57 | Q87: =SUM(Q22+Q29+Q33+Q50++Q85+Q53+Q37) -> 142782.89 | R87: =SUM(R22+R29+R33+R50++R85+R53+R37) -> 712500.2 | S87: =SUM(S22+S29+S33+S50++S85+S53+S37) -> 0 | T87: =SUM(T22+T29+T33+T50++T85+T53+T37) -> 712500.2
A89: SUBINDES | B89: 89050 | C89: ECU | D89: INDESIDC | E89: De minimis rate | F89: Indirect Charges | J89: 0.1 | K89: =(K87)*J89 -> 8959.6202 | M89: =(M87)*J89 -> 23936.653 | O89: =(O87)*J89 -> 24075.457 | Q89: =(Q87)*J89 -> 14278.289 | R89: =SUM(K89+M89+O89+Q89) -> 71250.02 | S89: 0 | T89: =SUM(R89:S89) -> 71250.02
E91: TOTAL PROGRAM COSTS | K91: =K87+K89 -> 98555.822 | M91: =M87+M89 -> 263303.19 | O91: =O87+O89 -> 264830.03 | Q91: =Q87+Q89 -> 157061.18 | R91: =R87+R89 -> 783750.22 | S91: =S87+S89 -> 0 | T91: =SUM(R91:S91) -> 783750.22

Sheet INDES Sub Activities Detail
A5: ='[1]INDES Sub Line-Item Budget'!A2:P2 -> INDES Sub-Recipient / Sub-receptor INDES
A6: DONOR | B6: =[1]Assumptions!C9 -> USDOL
A7: Country | B7: =[1]Assumptions!C10 -> Ecuador
A8: Program Name | B8: =[1]Assumptions!C11 -> Project to Improve Adherence to International Labor Standards in the Agricultural Sector in Ecuador
A9: Grant Number | B9: =[1]Assumptions!C12 -> FOA-ILAB-23-28
A10: Period of Performance | B10: =[1]Assumptions!C13 -> 48 months
A14: ACTIVITY DESCRIPTION | B14: Units | D14: Cost | E14: Base | F14: # of days | H14: ='[1]INDES Sub Line-Item Budget'!G10 -> Year 1 / Año 1 | K14: ='[1]INDES Sub Line-Item Budget'!I10 -> Year 2 / Año 2 | N14: ='[1]INDES Sub Line-Item Budget'!K10 -> Year 3 / Año 3 | Q14: ='[1]INDES Sub Line-Item Budget'!M10 -> Year 4 / Año 4 | T14: Total
H15: # Activities | J15: Amount | K15: # Activities | M15: Amount | N15: # Activities | P15: Amount | Q15: # Activities | S15: Amount
A16: ODC Escalation Factor | B16: 0.04 | J16: 1 | M16: =$J$16*SUM(1+$B$16) -> 1.04 | P16: =$M$16*SUM(1+$B$16) -> 1.0816 | S16: =$P$16*SUM(1+$B$16) -> 1.124864
A17: MEETINGS
A20: Activity 1.1. Evaluar las instituciones, procesos y servicios de cumplimiento de la ley laboral. INDES ACOMPAÑA | J20: =SUM(I23:I25) -> 0 | M20: =SUM(L23:L25) -> 0 | P20: =SUM(O23:O25) -> 0 | S20: =SUM(R23:R25) -> 0 | T20: =SUM(J20,M20,P20,S20,) -> 0
A21: COTOPAXI
A22: Training/workshop/project activities costs
A23: Local transportation (Cotopaxi) | B23: 0 | C23: Individual | D23: =parttransp -> 4 | E23: /day | F23: =IF(B23=0,0,F20) -> 0 | G23: =B23*D23*F23 -> 0 | I23: =$G23*H20*J$16 -> 0 | L23: =$G23*K20*M$16 -> 0 | O23: =$G23*N20*P$16 -> 0 | R23: =$G23*Q20*S$16 -> 0
A24: Lunch/coffee breaks | B24: 0 | C24: Individual | D24: =coffee+lunch -> 16 | E24: /day | F24: =IF(B24=0,0,F20) -> 0 | G24: =B24*D24*F24 -> 0 | I24: =$G24*H20*J$16 -> 0 | L24: =$G24*K20*M$16 -> 0 | O24: =$G24*N20*P$16 -> 0 | R24: =$G24*Q20*S$16 -> 0
A25: Printing (Photocopies) | B25: 0 | C25: activity | D25: =print -> 50 | E25: =C25 -> activity | F25: =IF(B25=0,0,1) -> 0 | G25: =B25*D25*F25 -> 0 | I25: =$G25*H20*J$16 -> 0 | L25: =$G25*K20*M$16 -> 0 | O25: =$G25*N20*P$16 -> 0 | R25: =$G25*Q20*S$16 -> 0
A27: Staff from outside training site | G27: =B27*D27*F27 -> 0
A28: Transportation (Cotopaxi) | C28: Individual | D28: =partground -> 9 | E28: /trip | F28: 3 | G28: =B28*D28*F28 -> 0 | I28: =$G28*$H$20*J$16 -> 0 | L28: =$G28*$K$20*M$16 -> 0 | O28: =$G28*$N$20*P$16 -> 0 | R28: =$G28*$Q$20*S$16 -> 0
A29: Ground transportation (Cotopaxi) | C29: Individual | D29: =partground -> 9 | E29: /day | F29: 3 | G29: =B29*D29*F29 -> 0 | I29: =$G29*$H$20*J$16 -> 0 | L29: =$G29*$K$20*M$16 -> 0 | O29: =$G29*$N$20*P$16 -> 0 | R29: =$G29*$Q$20*S$16 -> 0
A30: Lodging | C30: Individual | D30: =partlodg -> 35 | E30: /day | F30: 3 | G30: =B30*D30*F30 -> 0 | I30: =$G30*$H$20*J$16 -> 0 | L30: =$G30*$K$20*M$16 -> 0 | O30: =$G30*$N$20*P$16 -> 0 | R30: =$G30*$Q$20*S$16 -> 0
A31: M&IE (excluding lunch) | C31: Individual | D31: =partmeals -> 47 | E31: /day | F31: 3 | G31: =B31*D31*F31 -> 0 | I31: =$G31*$H$20*J$16 -> 0 | L31: =$G31*$K$20*M$16 -> 0 | O31: =$G31*$N$20*P$16 -> 0 | R31: =$G31*$Q$20*S$16 -> 0
A32: Travel Day Lunch | C32: Individual | D32: =parttransp -> 4 | E32: /trip | F32: 3 | G32: =B32*D32*F32 -> 0 | I32: =$G32*$H$20*J$16 -> 0 | L32: =$G32*$K$20*M$16 -> 0 | O32: =$G32*$N$20*P$16 -> 0 | R32: =$G32*$Q$20*S$16 -> 0
A33: ACTIVITY TOTAL | E33: =SUM(G28:G32) -> 0
A34: EL ORO | J34: =SUM(I37:I39) -> 0 | M34: =SUM(L37:L39) -> 0 | P34: =SUM(O37:O39) -> 0 | S34: =SUM(R37:R39) -> 0 | T34: =SUM(J34,M34,P34,S34,) -> 0
A35: Training/workshop/project activities costs
A36: Local transportation (El Oro) | C36: Individual | D36: =parttransp -> 4 | E36: /day | F36: =IF(B36=0,0,F32) -> 0 | G36: =B36*D36*F36 -> 0 | I36: =$G36*H32*J$16 -> 0 | L36: =$G36*K32*M$16 -> 0 | O36: =$G36*N32*P$16 -> 0 | R36: =$G36*Q32*S$16 -> 0
A37: Lunch/coffee breaks | C37: Individual | D37: =coffee+lunch -> 16 | E37: /day | F37: =IF(B37=0,0,F32) -> 0 | G37: =B37*D37*F37 -> 0 | I37: =$G37*H32*J$16 -> 0 | L37: =$G37*K32*M$16 -> 0 | O37: =$G37*N32*P$16 -> 0 | R37: =$G37*Q32*S$16 -> 0
A38: Printing (Photocopies) | C38: activity | D38: =print -> 50 | E38: =C38 -> activity | F38: =IF(B38=0,0,1) -> 0 | G38: =B38*D38*F38 -> 0 | I38: =$G38*H32*J$16 -> 0 | L38: =$G38*K32*M$16 -> 0 | O38: =$G38*N32*P$16 -> 0 | R38: =$G38*Q32*S$16 -> 0
A40: Staff from outside training site | G40: =B40*D40*F40 -> 0
A41: Transportation (El Oro) | B41: 1 | C41: Individual | D41: =partground -> 9 | E41: /trip | F41: 3 | G41: =B41*D41*F41 -> 27 | I41: =$G41*J$16*$H$34 -> 0 | L41: =$G41*$K$34*M$16 -> 0 | O41: =$G41*$N$34*P$16 -> 0 | R41: =$G41*$Q$34*S$16 -> 0
A42: Ground transportation (El Oro) | B42: 1 | C42: Individual | D42: =+[1]Assumptions!D101 -> 25 | E42: /day | F42: 3 | G42: =B42*D42*F42 -> 75 | I42: =$G42*J$16*$H$34 -> 0 | L42: =$G42*$K$34*M$16 -> 0 | O42: =$G42*$N$34*P$16 -> 0 | R42: =$G42*$Q$34*S$16 -> 0
A43: Lodging | B43: 1 | C43: Individual | D43: =+[1]Assumptions!D103 -> 90 | E43: /day | F43: 3 | G43: =B43*D43*F43 -> 270 | I43: =$G43*J$16*$H$34 -> 0 | L43: =$G43*$K$34*M$16 -> 0 | O43: =$G43*$N$34*P$16 -> 0 | R43: =$G43*$Q$34*S$16 -> 0
A44: M&IE (excluding lunch) | B44: 1 | C44: Individual | D44: =partmeals -> 47 | E44: /day | F44: 3 | G44: =B44*D44*F44 -> 141 | I44: =$G44*J$16*$H$34 -> 0 | L44: =$G44*$K$34*M$16 -> 0 | O44: =$G44*$N$34*P$16 -> 0 | R44: =$G44*$Q$34*S$16 -> 0
A45: Airfare | B45: 1 | C45: Individual | D45: =partairfare -> 200 | E45: /trip | F45: 1 | G45: =B45*D45*F45 -> 200 | I45: =$G45*J$16*$H$34 -> 0 | L45: =$G45*$K$34*M$16 -> 0 | O45: =$G45*$N$34*P$16 -> 0 | R45: =$G45*$Q$34*S$16 -> 0
A46: ACTIVITY TOTAL
A50: Activity 1.2. Strengthen intersectoral coordination by re-invigorating referral mechanisms and strengthening Consejos and Juntas | J50: =SUM(I53:I55) -> 0 | M50: =SUM(L53:L55) -> 0 | P50: =SUM(O53:O55) -> 0 | S50: =SUM(R53:R55) -> 0 | T50: =SUM(J50,M50,P50,S50,) -> 0
A51: COTOPAXI
A52: Training/workshop/project activities costs
A53: Local transportation (Cotopaxi) | B53: 0 | C53: Individual | D53: =parttransp -> 4 | E53: /day | F53: =IF(B53=0,0,F50) -> 0 | G53: =B53*D53*F53 -> 0 | I53: =$G53*H50*J$16 -> 0 | L53: =$G53*K50*M$16 -> 0 | O53: =$G53*N50*P$16 -> 0 | R53: =$G53*Q50*S$16 -> 0
A54: Lunch/coffee breaks | B54: 0 | C54: Individual | D54: =coffee+lunch -> 16 | E54: /day | F54: =IF(B54=0,0,F50) -> 0 | G54: =B54*D54*F54 -> 0 | I54: =$G54*H50*J$16 -> 0 | L54: =$G54*K50*M$16 -> 0 | O54: =$G54*N50*P$16 -> 0 | R54: =$G54*Q50*S$16 -> 0
A55: Printing (Photocopies) | B55: 0 | C55: activity | D55: =print -> 50 | E55: =C55 -> activity | F55: =IF(B55=0,0,1) -> 0 | G55: =B55*D55*F55 -> 0 | I55: =$G55*H50*J$16 -> 0 | L55: =$G55*K50*M$16 -> 0 | O55: =$G55*N50*P$16 -> 0 | R55: =$G55*Q50*S$16 -> 0
A57: Staff from outside training site | G57: =B57*D57*F57 -> 0
A58: Transportation (Cotopaxi) | C58: Individual | D58: =partground -> 9 | E58: /trip | F58: 1 | G58: =B58*D58*F58 -> 0 | I58: =$G58*$H$50*J$16 -> 0 | L58: =$G58*$K$50*M$16 -> 0 | O58: =$G58*$N$20*P$16 -> 0 | R58: =$G58*$Q$20*S$16 -> 0
A59: Ground transportation (Cotopaxi) | C59: Individual | D59: =partground -> 9 | E59: /day | F59: 1 | G59: =B59*D59*F59 -> 0 | I59: =$G59*$H$50*J$16 -> 0 | L59: =$G59*$K$50*M$16 -> 0 | O59: =$G59*$N$20*P$16 -> 0 | R59: =$G59*$Q$20*S$16 -> 0
A60: Lodging | C60: Individual | D60: =partlodg -> 35 | E60: /day | F60: 1 | G60: =B60*D60*F60 -> 0 | I60: =$G60*$H$50*J$16 -> 0 | L60: =$G60*$K$50*M$16 -> 0 | O60: =$G60*$N$20*P$16 -> 0 | R60: =$G60*$Q$20*S$16 -> 0
A61: M&IE (excluding lunch) | C61: Individual | D61: =partmeals -> 47 | E61: /day | F61: 1 | G61: =B61*D61*F61 -> 0 | I61: =$G61*$H$50*J$16 -> 0 | L61: =$G61*$K$50*M$16 -> 0 | O61: =$G61*$N$20*P$16 -> 0 | R61: =$G61*$Q$20*S$16 -> 0
A62: Travel Day Lunch | C62: Individual | D62: =parttransp -> 4 | E62: /trip | F62: 1 | G62: =B62*D62*F62 -> 0 | I62: =$G62*$H$50*J$16 -> 0 | L62: =$G62*$K$20*M$16 -> 0 | O62: =$G62*$N$20*P$16 -> 0 | R62: =$G62*$Q$20*S$16 -> 0
A63: ACTIVITY TOTAL | E63: =SUM(G58:G62) -> 0
A64: EL ORO | J64: =SUM(I67:I69) -> 0 | M64: =SUM(L67:L69) -> 0 | P64: =SUM(O67:O69) -> 0 | S64: =SUM(R67:R69) -> 0 | T64: =SUM(J64,M64,P64,S64,) -> 0
A65: Training/workshop/project activities costs
A66: Local transportation (El Oro) | C66: Individual | D66: =parttransp -> 4 | E66: /day | F66: =IF(B66=0,0,F62) -> 0 | G66: =B66*D66*F66 -> 0 | I66: =$G66*H62*J$16 -> 0 | L66: =$G66*K62*M$16 -> 0 | O66: =$G66*N62*P$16 -> 0 | R66: =$G66*Q62*S$16 -> 0
A67: Lunch/coffee breaks | C67: Individual | D67: =coffee+lunch -> 16 | E67: /day | F67: =IF(B67=0,0,F62) -> 0 | G67: =B67*D67*F67 -> 0 | I67: =$G67*H62*J$16 -> 0 | L67: =$G67*K62*M$16 -> 0 | O67: =$G67*N62*P$16 -> 0 | R67: =$G67*Q62*S$16 -> 0
A68: Printing (Photocopies) | C68: activity | D68: =print -> 50 | E68: =C68 -> activity | F68: =IF(B68=0,0,1) -> 0 | G68: =B68*D68*F68 -> 0 | I68: =$G68*H62*J$16 -> 0 | L68: =$G68*K62*M$16 -> 0 | O68: =$G68*N62*P$16 -> 0 | R68: =$G68*Q62*S$16 -> 0
A70: Staff from outside training site | G70: =B70*D70*F70 -> 0
A71: Transportation (El Oro) | B71: 1 | C71: Individual | D71: =partground -> 9 | E71: /trip | F71: 2 | G71: =B71*D71*F71 -> 18 | I71: =$G71*J$16*$H$64 -> 0 | L71: =$G71*$K$64*M$16 -> 0 | O71: =$G71*$N$34*P$16 -> 0 | R71: =$G71*$Q$34*S$16 -> 0
A72: Ground transportation (El Oro) | B72: 1 | C72: Individual | D72: =+[1]Assumptions!D101 -> 25 | E72: /day | F72: 2 | G72: =B72*D72*F72 -> 50 | I72: =$G72*J$16*$H$64 -> 0 | L72: =$G72*$K$64*M$16 -> 0 | O72: =$G72*$N$34*P$16 -> 0 | R72: =$G72*$Q$34*S$16 -> 0
A73: Lodging | B73: 1 | C73: Individual | D73: =+[1]Assumptions!D103 -> 90 | E73: /day | F73: 2 | G73: =B73*D73*F73 -> 180 | I73: =$G73*J$16*$H$64 -> 0 | L73: =$G73*$K$64*M$16 -> 0 | O73: =$G73*$N$34*P$16 -> 0 | R73: =$G73*$Q$34*S$16 -> 0
A74: M&IE (excluding lunch) | B74: 1 | C74: Individual | D74: =partmeals -> 47 | E74: /day | F74: 2 | G74: =B74*D74*F74 -> 94 | I74: =$G74*J$16*$H$64 -> 0 | L74: =$G74*$K$64*M$16 -> 0 | O74: =$G74*$N$34*P$16 -> 0 | R74: =$G74*$Q$34*S$16 -> 0
A75: Airfare | B75: 1 | C75: Individual | D75: =partairfare -> 200 | E75: /trip | F75: 1 | G75: =B75*D75*F75 -> 200 | I75: =$G75*J$16*$H$64 -> 0 | L75: =$G75*$K$64*M$16 -> 0 | O75: =$G75*$N$34*P$16 -> 0 | R75: =$G75*$Q$34*S$16 -> 0
A76: ACTIVITY TOTAL | E76: =SUM(G71:G75) -> 542
A79: Activity 1.3. Develop a government capacity-building strategy by applying assessment results. POA & INDES | J79: =SUM(I82:I84) -> 0 | K79: 1 | M79: =SUM(L94:L96) -> 4944.576 | P79: =SUM(O82:O84) -> 0 | S79: =SUM(R82:R84) -> 0 | T79: =SUM(J79,M79,P79,S79,) -> 4944.576
A80: COTOPAXI
A81: Training/workshop
A82: Local transportation (Cotopaxi) | B82: 0 | C82: Individual | D82: =parttransp -> 4 | E82: /day | F82: =IF(B82=0,0,F79) -> 0 | G82: =B82*D82*F82 -> 0 | I82: =$G82*H79*J$16 -> 0 | L82: =$G82*K79*M$16 -> 0 | O82: =$G82*N79*P$16 -> 0 | R82: =$G82*Q79*S$16 -> 0
A83: Lunch/coffee breaks | B83: 0 | C83: Individual | D83: =coffee+lunch -> 16 | E83: /day | F83: =IF(B83=0,0,F79) -> 0 | G83: =B83*D83*F83 -> 0 | I83: =$G83*H79*J$16 -> 0 | L83: =$G83*K79*M$16 -> 0 | O83: =$G83*N79*P$16 -> 0 | R83: =$G83*Q79*S$16 -> 0
A84: Printing (Photocopies) | B84: 0 | C84: activity | D84: =print -> 50 | E84: =C84 -> activity | F84: =IF(B84=0,0,1) -> 0 | G84: =B84*D84*F84 -> 0 | I84: =$G84*H79*J$16 -> 0 | L84: =$G84*K79*M$16 -> 0 | O84: =$G84*N79*P$16 -> 0 | R84: =$G84*Q79*S$16 -> 0
A86: Staff from outside training site / | G86: =B86*D86*F86 -> 0
A87: Transportation (Cotopaxi) | C87: Individual | D87: =partground -> 9 | E87: /trip | F87: 3 | G87: =B87*D87*F87 -> 0 | I87: =$G87*$H$79*$J$16 -> 0 | L87: =$G87*$K$79*M$16 -> 0 | O87: =$G87*$N$79*P$16 -> 0 | R87: =$G87*$Q$79*S$16 -> 0
A88: Ground transportation (Cotopaxi) | C88: Individual | D88: =partground -> 9 | E88: /day | F88: 3 | G88: =B88*D88*F88 -> 0 | I88: =$G88*$H$79*$J$16 -> 0 | L88: =$G88*$K$79*M$16 -> 0 | O88: =$G88*$N$79*P$16 -> 0 | R88: =$G88*$Q$79*S$16 -> 0
A89: Lodging | C89: Individual | D89: =partlodg -> 35 | E89: /day | F89: 1 | G89: =B89*D89*F89 -> 0 | I89: =$G89*$H$79*$J$16 -> 0 | L89: =$G89*$K$79*M$16 -> 0 | O89: =$G89*$N$79*P$16 -> 0 | R89: =$G89*$Q$79*S$16 -> 0
A90: M&IE (excluding lunch) | C90: Individual | D90: =partmeals -> 47 | E90: /day | F90: 1 | G90: =B90*D90*F90 -> 0 | I90: =$G90*$H$79*$J$16 -> 0 | L90: =$G90*$K$79*M$16 -> 0 | O90: =$G90*$N$79*P$16 -> 0 | R90: =$G90*$Q$79*S$16 -> 0
A91: Travel Day Lunch | C91: Individual | D91: =parttransp -> 4 | E91: /trip | F91: 1 | G91: =B91*D91*F91 -> 0 | I91: =$G91*$H$79*$J$16 -> 0 | L91: =$G91*$K$79*M$16 -> 0 | O91: =$G91*$N$79*P$16 -> 0 | R91: =$G91*$Q$79*S$16 -> 0
A92: ACTIVITY TOTAL | E92: =SUM(G81:G91) -> 0
A93: Project activities costs
A94: Local transportation (training site) | C94: Individual | D94: 4 | E94: /day
A95: Printing (Guide SST flowers) | C95: each | D95: 20 | E95: each | F95: 1 | G95: =B95*D95*F95 -> 0 | L95: =$G95*$K$79*M$16 -> 0
A96: Local Consultant (Guide SST) | B96: 1 | C96: Individual | D96: 339.6 | E96: /day | F96: 14 | G96: =B96*D96*F96 -> 4754.4 | L96: =$G96*$K$79*M$16 -> 4944.576
A97: Staff from outside training site
A98: Transportation (Cotopaxi) | B98: 1 | C98: Individual | D98: =partground -> 9 | E98: /trip | F98: 11 | G98: =B98*D98*F98 -> 99 | L98: =$G98*$K$79*M$16 -> 102.96
A99: Ground transportation (Cotopaxi) | B99: 1 | C99: Individual | D99: 6 | E99: /day | F99: 10 | G99: =B99*D99*F99 -> 60 | L99: =$G99*$K$79*M$16-1.4 -> 61
A100: Lodging | C100: Individual | D100: =partlodg -> 35 | E100: /day | F100: 6 | G100: =B100*D100*F100 -> 0 | L100: =$G100*$K$79*M$16 -> 0
A101: M&IE | C101: Individual | D101: =partmeals -> 47 | E101: /day | F101: 6 | G101: =B101*D101*F101 -> 0 | L101: =$G101*$K$79*M$16 -> 0
A102: ACTIVITY TOTAL
A104: EL ORO | J104: =SUM(I107:I109) -> 0 | M104: =SUM(L107:L109) -> 0 | P104: =SUM(O107:O109) -> 0 | S104: =SUM(R107:R109) -> 0 | T104: =SUM(J104,M104,P104,S104,) -> 0
A105: Training/workshop/project activities costs
A106: Local transportation (El Oro) | C106: Individual | D106: =parttransp -> 4 | E106: /day | F106: =IF(B106=0,0,F92) -> 0 | G106: =B106*D106*F106 -> 0 | I106: =$G106*H92*J$16 -> 0 | L106: =$G106*K92*M$16 -> 0 | O106: =$G106*N92*P$16 -> 0 | R106: =$G106*Q92*S$16 -> 0
A107: Lunch/coffee breaks | C107: Individual | D107: =coffee+lunch -> 16 | E107: /day | F107: =IF(B107=0,0,F92) -> 0 | G107: =B107*D107*F107 -> 0 | I107: =$G107*H92*J$16 -> 0 | L107: =$G107*K92*M$16 -> 0 | O107: =$G107*N92*P$16 -> 0 | R107: =$G107*Q92*S$16 -> 0
A108: Printing (Photocopies) | C108: activity | D108: =print -> 50 | E108: =C108 -> activity | F108: =IF(B108=0,0,1) -> 0 | G108: =B108*D108*F108 -> 0 | I108: =$G108*H92*J$16 -> 0 | L108: =$G108*K92*M$16 -> 0 | O108: =$G108*N92*P$16 -> 0 | R108: =$G108*Q92*S$16 -> 0
A110: Staff from outside training site | G110: =B110*D110*F110 -> 0
A111: Transportation (El Oro) | B111: 0 | C111: Individual | D111: =partground -> 9 | E111: /trip | F111: 1 | G111: =B111*D111*F111 -> 0 | I111: =$G111*J$16*$H$64 -> 0 | L111: =$G111*$K$64*M$16 -> 0 | O111: =$G111*$N$34*P$16 -> 0 | R111: =$G111*$Q$34*S$16 -> 0
A112: Ground transportation (El Oro) | B112: 0 | C112: Individual | D112: =+[1]Assumptions!D101 -> 25 | E112: /day | F112: 1 | G112: =B112*D112*F112 -> 0 | I112: =$G112*J$16*$H$64 -> 0 | L112: =$G112*$K$64*M$16 -> 0 | O112: =$G112*$N$34*P$16 -> 0 | R112: =$G112*$Q$34*S$16 -> 0
A113: Lodging | B113: 0 | C113: Individual | D113: =+[1]Assumptions!D103 -> 90 | E113: /day | F113: 1 | G113: =B113*D113*F113 -> 0 | I113: =$G113*J$16*$H$64 -> 0 | L113: =$G113*$K$64*M$16 -> 0 | O113: =$G113*$N$34*P$16 -> 0 | R113: =$G113*$Q$34*S$16 -> 0
A114: M&IE (excluding lunch) | B114: 0 | C114: Individual | D114: =partmeals -> 47 | E114: /day | F114: 1 | G114: =B114*D114*F114 -> 0 | I114: =$G114*J$16*$H$64 -> 0 | L114: =$G114*$K$64*M$16 -> 0 | O114: =$G114*$N$34*P$16 -> 0 | R114: =$G114*$Q$34*S$16 -> 0
A115: Airfare | B115: 0 | C115: Individual | D115: =partairfare -> 200 | E115: /trip | F115: 1 | G115: =B115*D115*F115 -> 0 | I115: =$G115*J$16*$H$64 -> 0 | L115: =$G115*$K$64*M$16 -> 0 | O115: =$G115*$N$34*P$16 -> 0 | R115: =$G115*$Q$34*S$16 -> 0
A116: ACTIVITY TOTAL | E116: =SUM(G111:G115) -> 0
A118: Activity 1.4. Develop, deliver, and institutionalize tailored CB for government officials | F118: 1 | H118: 1 | J118: =SUM(I121:I123) -> 450 | K118: 6 | M118: =SUM(L121:L123) -> 2808 | N118: 6 | P118: =SUM(O121:O123) -> 2920.32 | Q118: 3 | S118: =SUM(R121:R123) -> 1518.5664 | T118: =SUM(J118,M118,P118,S118,) -> 7696.8864
A119: COTOPAXI
A120: Training/workshop/project activities costs
A121: Local transportation (Cotopaxi) | B121: 20 | C121: Individual | D121: =parttransp -> 4 | E121: /day | F121: =IF(B121=0,0,F118) -> 1 | G121: =B121*D121*F121 -> 80 | I121: =$G121*H118*J$16 -> 80 | L121: =$G121*K118*M$16 -> 499.2 | O121: =$G121*N118*P$16 -> 519.168 | R121: =$G121*Q118*S$16 -> 269.96736
A122: Lunch/coffee breaks | B122: 20 | C122: Individual | D122: =coffee+lunch -> 16 | E122: /day | F122: =IF(B122=0,0,F118) -> 1 | G122: =B122*D122*F122 -> 320 | I122: =$G122*H118*J$16 -> 320 | L122: =$G122*K118*M$16 -> 1996.8 | O122: =$G122*N118*P$16 -> 2076.672 | R122: =$G122*Q118*S$16 -> 1079.8694
...

Sheet Travel
A1: Travel Budget
A2: YEAR 1
A3: Position Traveling | B3: From-To | C3: Activity/ Purpose | D3: # of Trips/YR | E3: Transport (Int'l/trip) | F3: Total Transport | G3: # of Days/Trip | H3: M&IE Rate | I3: Total M&IE | J3: Lodging Rate (Int'l) | K3: Total Lodging | L3: Ground Transfers | M3: Travel Other | N3: Total
A4: International Travel
A5: M&E Officer | B5: ex. Washington, DC to San Jose, Costa Rica | C5: ex. Monitoring & Evaluation | D5: 1 | E5: 1200 | F5: =D5*E5 -> 1200 | G5: 5 | H5: 126 | I5: =G5*H5 -> 630 | J5: 147 | K5: =G5*J5 -> 735 | L5: 50 | M5: 30 | N5: =SUM(F5,I5,K5,L5,M5) -> 2645
F6: =D6*E6 -> 0 | I6: =G6*H6 -> 0 | K6: =G6*J6 -> 0 | N6: =SUM(F6,I6,K6,L6,M6) -> 0
A7: Domestic Travel
A8: M&E Officer | B8: Quito to El Oro | F8: =D8*E8 -> 0 | I8: =G8*H8 -> 0 | K8: =G8*J8 -> 0 | N8: =SUM(F8,I8,K8,L8,M8) -> 0
A9: Project Director | B9: Quito to El Oro | F9: =D9*E9 -> 0 | I9: =G9*H9 -> 0 | K9: =G9*J9 -> 0 | N9: =SUM(F9,I9,K9,L9,M9) -> 0
A10: M&E Officer | B10: Quito to Cotopaxi | F10: =D10*E10 -> 0 | I10: =G10*H10 -> 0 | K10: =G10*J10 -> 0 | N10: =SUM(F10,I10,K10,L10,M10) -> 0
A11: Project Director | B11: Quito to Cotopaxi | F11: =D11*E11 -> 0 | I11: =G11*H11 -> 0 | K11: =G11*J11 -> 0 | N11: =SUM(F11,I11,K11,L11,M11) -> 0
A12: Total Year 1 | F12: =SUM(F5:F6,F8) -> 1200 | I12: =SUM(I5:I6,I8) -> 630 | K12: =SUM(K5:K6,K8) -> 735 | N12: =SUM(N5:N6,N8) -> 2645
A13: YEAR 2
A14: Position Traveling | B14: To-From | C14: Activity/ Purpose | D14: # of Trips/YR | E14: Transport (Int'l/trip) | F14: Total Transport $ | G14: # of Days/Trip | H14: M&IE Rate | I14: Total M&IE | J14: Lodging Rate (Int'l) | K14: Total Lodging | L14: Ground Transfers | M14: Travel Other | N14: Total
A15: International Travel
F16: =D16*E16 -> 0 | I16: =G16*H16 -> 0 | K16: =G16*J16 -> 0 | N16: =SUM(F16,I16,K16,L16,M16) -> 0
F17: =D17*E17 -> 0 | I17: =G17*H17 -> 0 | K17: =G17*J17 -> 0 | N17: =SUM(F17,I17,K17,L17,M17) -> 0
A18: Domestic Travel
F19: =D19*E19 -> 0 | I19: =G19*H19 -> 0 | K19: =G19*J19 -> 0 | N19: =SUM(F19,I19,K19,L19,M19) -> 0
A20: Total Year 2 | F20: =SUM(F16:F17,F19) -> 0 | I20: =SUM(I16:I17,I19) -> 0 | K20: =SUM(K16:K17,K19) -> 0 | N20: =SUM(N16:N17,N19) -> 0
A21: YEAR 3
A22: Position Traveling | B22: To-From | C22: Activity/ Purpose | D22: # of Trips/YR | E22: Transport (Int'l/trip) | F22: Total Transport $ | G22: # of Days/Trip | H22: M&IE Rate | I22: Total M&IE | J22: Lodging Rate (Int'l) | K22: Total Lodging | L22: Ground Transfers | M22: Travel Other | N22: Total
A23: International Travel
F24: =D24*E24 -> 0 | I24: =G24*H24 -> 0 | K24: =G24*J24 -> 0 | N24: =SUM(F24,I24,K24,L24,M24) -> 0
F25: =D25*E25 -> 0 | I25: =G25*H25 -> 0 | K25: =G25*J25 -> 0 | N25: =SUM(F25,I25,K25,L25,M25) -> 0
A26: Domestic Travel
F27: =D27*E27 -> 0 | I27: =G27*H27 -> 0 | K27: =G27*J27 -> 0 | N27: =SUM(F27,I27,K27,L27,M27) -> 0
A28: Total Year 3 | F28: =SUM(F24:F25,F27) -> 0 | I28: =SUM(I24:I25,I27) -> 0 | K28: =SUM(K24:K25,K27) -> 0 | N28: =SUM(N24:N25,N27) -> 0
A29: YEAR 4
A30: Position Traveling | B30: To-From | C30: Activity/ Purpose | D30: # of Trips/YR | E30: Transport (Int'l/trip) | F30: Total Transport $ | G30: # of Days/Trip | H30: M&IE Rate | I30: Total M&IE | J30: Lodging Rate (Int'l) | K30: Total Lodging | L30: Ground Transfers | M30: Travel Other | N30: Total
A31: International Travel
F32: =D32*E32 -> 0 | I32: =G32*H32 -> 0 | K32: =G32*J32 -> 0 | N32: =SUM(F32,I32,K32,L32,M32) -> 0
F33: =D33*E33 -> 0 | I33: =G33*H33 -> 0 | K33: =G33*J33 -> 0 | N33: =SUM(F33,I33,K33,L33,M33) -> 0
F34: =D34*E34 -> 0 | I34: =G34*H34 -> 0 | K34: =G34*J34 -> 0 | N34: =SUM(F34,I34,K34,L34,M34) -> 0
A35: Domestic Travel
F36: =D36*E36 -> 0 | I36: =G36*H36 -> 0 | K36: =G36*J36 -> 0 | N36: =SUM(F36,I36,K36,L36,M36) -> 0
A37: Total Year 4 | F37: =SUM(F32:F34,F36) -> 0 | I37: =SUM(I32:I34,I36) -> 0 | K37: =SUM(K32:K34,K36) -> 0 | N37: =SUM(N32:N34,N36) -> 0
A38: TOTAL ALL YEARS | F38: =SUM(F12,F20,F28,F37) -> 1200 | I38: =SUM(I12,I20,I28,I37) -> 630 | K38: =SUM(K12,K20,K28,K37) -> 735 | N38: =SUM(N12,N20,N28,N37) -> 2645

Sheet HO LOE
A1: =Assumptions!$B$8 -> Partners of America
A2: =CONCATENATE(Assumptions!$B9," ",Assumptions!$C9) -> DONOR: USDOL
A3: =CONCATENATE(Assumptions!$B10," ",Assumptions!$C10) -> Country: Ecuador
A4: =CONCATENATE(Assumptions!$B11," ",Assumptions!$C11) -> Program Name: Project to Improve Adherence to International Labor Standards in the Agricultural Sector in Ecuador
A5: =CONCATENATE(Assumptions!$B12," ",Assumptions!$C12) -> Grant Number: FOA-ILAB-23-28
A7: HOME OFFICE SUPPORT
A9: Position | B9: Name | C9: Current Annual Salary | D9: Projected Annual Salary | E9: =#REF! -> #REF! | H9: =#REF! -> #REF! | K9: =#REF! -> #REF! | N9: =#REF! -> #REF! | Q9: =#REF! -> #REF! | T9: =#REF! -> #REF! | W9: =#REF! -> #REF! | Z9: =#REF! -> #REF! | AC9: =#REF! -> #REF! | AF9: =#REF! -> #REF! | AI9: Total
E10: LOE % | F10: Amount | G10: Number of Days | H10: LOE % | I10: Amount | J10: Number of Days | K10: LOE % | L10: Amount | M10: Number of Days | N10: LOE % | O10: Amount | P10: Number of Days | Q10: LOE % | R10: Amount | S10: Number of Days | T10: LOE % | U10: Amount | V10: Number of Days | W10: LOE % | X10: Amount | Y10: Number of Days | Z10: LOE % | AA10: Amount | AB10: Number of Days | AC10: LOE % | AD10: Amount | AE10: Number of Days | AF10: LOE % | AG10: Amount | AH10: Number of Days | AI10: LOE % | AJ10: Amount | AK10: Number of Days
B11: Escalation Rate | D11: 1.04 | F11: =Assumptions!S37 -> 1.01 | I11: =F11*(1+#REF!) -> #REF! | L11: =I11*(1+#REF!) -> #REF! | O11: =L11*(1+#REF!) -> #REF! | R11: =O11*(1+#REF!) -> #REF! | U11: =R11*(1+#REF!) -> #REF! | X11: =U11*(1+#REF!) -> #REF! | AA11: =X11*(1+#REF!) -> #REF! | AD11: =AA11*(1+#REF!) -> #REF! | AG11: =AD11*(1+#REF!) -> #REF!
A12: Program Management
A14: Position | B14: Name | C14: Current Monthly Salary | D14: Projected Monthly Salary | E14: LOE % | F14: Total | G14: Number of Days | T14: LOE % | U14: Total | V14: Number of Days
A16: GPO Director | D16: 100000 | E16: 0.1 | F16: =E16*D16*F$11 -> 10100 | G16: =E16*260 -> 26 | H16: 0 | I16: =H16*$D16*I$11 -> #REF! | J16: =H16*260 -> 0 | K16: 0 | L16: =K16*$D16*L$11 -> #REF! | M16: =K16*260 -> 0 | N16: 0 | O16: =N16*$D16*O$11 -> #REF! | P16: =N16*260 -> 0 | Q16: 0 | R16: =Q16*$D16*R$11 -> #REF! | S16: =Q16*260 -> 0 | T16: 0 | U16: =T16*S16*U$11 -> #REF! | V16: =T16*260 -> 0 | W16: 0 | X16: =W16*$D16*X$11 -> #REF! | Y16: =W16*260 -> 0 | Z16: 0 | AA16: =Z16*$D16*AA$11 -> #REF! | AB16: =Z16*260 -> 0 | AC16: 0.05 | AD16: =AC16*$D16*AD$11 -> #REF! | AE16: =AC16*260 -> 13 | AF16: 0 | AG16: =AF16*$D16*AG$11 -> #REF! | AH16: =AF16*260 -> 0 | AI16: =SUM(E16,H16,K16,N16,Q16,T16,W16,Z16,AC16,AF16) -> 0.15 | AJ16: =SUM(F16,I16,L16,O16,R16,U16,X16,AA16,AD16,AG16) -> #REF! | AK16: =SUM(G16,J16,M16,P16,S16,V16,Y16,AB16,AE16,AH16) -> 39
A17: Associate GPO Director | D17: 100000 | E17: 0.1 | F17: =E17*D17*F$11 -> 10100 | G17: =E17*260 -> 26 | H17: 0 | I17: =H17*$D17*I$11 -> #REF! | J17: =H17*260 -> 0 | K17: 0 | L17: =K17*$D17*L$11 -> #REF! | M17: =K17*260 -> 0 | N17: 0 | O17: =N17*$D17*O$11 -> #REF! | P17: =N17*260 -> 0 | Q17: 0 | R17: =Q17*$D17*R$11 -> #REF! | S17: =Q17*260 -> 0 | T17: 0 | U17: =T17*S17*U$11 -> #REF! | V17: =T17*260 -> 0 | W17: 0 | X17: =W17*$D17*X$11 -> #REF! | Y17: =W17*260 -> 0 | Z17: 0 | AA17: =Z17*$D17*AA$11 -> #REF! | AB17: =Z17*260 -> 0 | AC17: 0 | AD17: =AC17*$D17*AD$11 -> #REF! | AE17: =AC17*260 -> 0 | AF17: 0 | AG17: =AF17*$D17*AG$11 -> #REF! | AH17: =AF17*260 -> 0 | AI17: =SUM(E17,H17,K17,N17,Q17,T17,W17,Z17,AC17,AF17) -> 0.1 | AJ17: =SUM(F17,I17,L17,O17,R17,U17,X17,AA17,AD17,AG17) -> #REF! | AK17: =SUM(G17,J17,M17,P17,S17,V17,Y17,AB17,AE17,AH17) -> 26
A18: Regional Team Leader | D18: 100000 | E18: 0.1 | F18: =E18*D18*F$11 -> 10100 | G18: =E18*260 -> 26 | H18: 0 | I18: =H18*$D18*I$11 -> #REF! | J18: =H18*260 -> 0 | K18: 0 | L18: =K18*$D18*L$11 -> #REF! | M18: =K18*260 -> 0 | N18: 0 | O18: =N18*$D18*O$11 -> #REF! | P18: =N18*260 -> 0 | Q18: 0 | R18: =Q18*$D18*R$11 -> #REF! | S18: =Q18*260 -> 0 | T18: 0 | U18: =T18*S18*U$11 -> #REF! | V18: =T18*260 -> 0 | W18: 0 | X18: =W18*$D18*X$11 -> #REF! | Y18: =W18*260 -> 0 | Z18: 0.05 | AA18: =Z18*$D18*AA$11 -> #REF! | AB18: =Z18*260 -> 13 | AC18: 0 | AD18: =AC18*$D18*AD$11 -> #REF! | AE18: =AC18*260 -> 0 | AF18: 0.05 | AG18: =AF18*$D18*AG$11 -> #REF! | AH18: =AF18*260 -> 13 | AI18: =SUM(E18,H18,K18,N18,Q18,T18,W18,Z18,AC18,AF18) -> 0.2 | AJ18: =SUM(F18,I18,L18,O18,R18,U18,X18,AA18,AD18,AG18) -> #REF! | AK18: =SUM(G18,J18,M18,P18,S18,V18,Y18,AB18,AE18,AH18) -> 52
A19: Program Officer | D19: 100000 | E19: 0.1 | F19: =E19*D19*F$11 -> 10100 | G19: =E19*260 -> 26 | H19: 0 | I19: =H19*$D19*I$11 -> #REF! | J19: =H19*260 -> 0 | K19: 0 | L19: =K19*$D19*L$11 -> #REF! | M19: =K19*260 -> 0 | N19: 0 | O19: =N19*$D19*O$11 -> #REF! | P19: =N19*260 -> 0 | Q19: 0 | R19: =Q19*$D19*R$11 -> #REF! | S19: =Q19*260 -> 0 | T19: 0 | U19: =T19*S19*U$11 -> #REF! | V19: =T19*260 -> 0 | W19: 0 | X19: =W19*$D19*X$11 -> #REF! | Y19: =W19*260 -> 0 | Z19: 0 | AA19: =Z19*$D19*AA$11 -> #REF! | AB19: =Z19*260 -> 0 | AC19: 0 | AD19: =AC19*$D19*AD$11 -> #REF! | AE19: =AC19*260 -> 0 | AF19: 0 | AG19: =AF19*$D19*AG$11 -> #REF! | AH19: =AF19*260 -> 0 | AI19: =SUM(E19,H19,K19,N19,Q19,T19,W19,Z19,AC19,AF19) -> 0.1 | AJ19: =SUM(F19,I19,L19,O19,R19,U19,X19,AA19,AD19,AG19) -> #REF! | AK19: =SUM(G19,J19,M19,P19,S19,V19,Y19,AB19,AE19,AH19) -> 26
A20: Program Coordinator | D20: 100000 | E20: 0.1 | F20: =E20*D20*F$11 -> 10100 | G20: =E20*260 -> 26 | H20: 0 | I20: =H20*$D20*I$11 -> #REF! | J20: =H20*260 -> 0 | K20: 0 | L20: =K20*$D20*L$11 -> #REF! | M20: =K20*260 -> 0 | N20: 0 | O20: =N20*$D20*O$11 -> #REF! | P20: =N20*260 -> 0 | Q20: 0 | R20: =Q20*$D20*R$11 -> #REF! | S20: =Q20*260 -> 0 | T20: 0 | U20: =T20*S20*U$11 -> #REF! | V20: =T20*260 -> 0 | W20: 0 | X20: =W20*$D20*X$11 -> #REF! | Y20: =W20*260 -> 0 | Z20: 0 | AA20: =Z20*$D20*AA$11 -> #REF! | AB20: =Z20*260 -> 0 | AC20: 0 | AD20: =AC20*$D20*AD$11 -> #REF! | AE20: =AC20*260 -> 0 | AF20: 0 | AG20: =AF20*$D20*AG$11 -> #REF! | AH20: =AF20*260 -> 0 | AI20: =SUM(E20,H20,K20,N20,Q20,T20,W20,Z20,AC20,AF20) -> 0.1 | AJ20: =SUM(F20,I20,L20,O20,R20,U20,X20,AA20,AD20,AG20) -> #REF! | AK20: =SUM(G20,J20,M20,P20,S20,V20,Y20,AB20,AE20,AH20) -> 26
