Workbook
Name \a: '[1]CUADRO No 4'!#REF!
Name \c: #REF!
Name \i: #REF!
Name \P: #REF!
Name \r: #REF!
Name __pd1: [2]Rates!$J$24
Name __pd6: [2]Rates!$J$30
Name __tix1: [2]Rates!$J$40
Name __tix2: [2]Rates!$J$41
Name __tix6: [2]Rates!$J$47
Name _1: #REF!
Name _1998: #REF!
Name _1999: #REF!
Name _2: #REF!
Name _2000: #REF!
Name _2001: #REF!
Name _2002: #REF!
Name _3: #REF!
Name _4: #REF!
Name _5: #REF!
Name _6: #REF!
Name _7: #REF!
Name _8: #REF!
Name _fmi1: [3]PAGOFMI!$A$1:$L$51
Name _fmi2: [3]PAGOFMI!$P$1:$AA$51
Name _fmi3: [3]PAGORES!$AC$1:$AN$43
Name _fmi4: [3]PAGORES!$AP$1:$BA$44
Name _PIB01: [4]SUPUESTOS!#REF!
Name _PIB02: [5]SUPUESTOS!#REF!
Name _PIB95: [4]SUPUESTOS!$J$47
Name _PIB96: [4]SUPUESTOS!$K$47
Name _PIB97: [6]SUPUESTOS!$L$47
Name _PIB98: [6]SUPUESTOS!$M$47
Name _PIB99: [6]SUPUESTOS!$N$47
Name _RES9397: #REF!
Name _rez2: '[3]PAGOS VIGENCIA t'!$A$57:$AH$108
Name _rez3: [3]PAGORES!$A$1:$M$37
Name _rez4: [3]PAGORES!$O$1:$AN$43
Name a: #REF!
Name A_2002: #REF!
Name A_CAPITAL: [9]Hoja4!$B$3:$O$34
Name A_DEPTOS: [9]Hoja4!$B$76:$N$108
Name A_impresión_IM: #REF!
Name A_MUNPIOS: [9]Hoja4!$B$39:$N$71
Name AAA: [10]proyecINGRESOS99!$L$1:$T$97
Name AEFormar: [11]Variables!$C$5
Name Ajustado: #REF!
Name almuerzo: [11]Variables!$C$18
Name alquilertableta: [11]Variables!$C$21
Name ANEXO_No.: #REF!
Name ANEXO_No._5: #REF!
Name ANPDH: '[12]Salary & PR Tax'!#REF!
Name aprnac: [13]GASTOS!#REF!
Name APROPIACIONES_PAC_Y_REZAGO_1999___2000: #REF!
Name aprprp: [13]GASTOS!#REF!
Name asigbas: #REF!
Name asigbasempu: #REF!
Name asigbasisten: #REF!
Name asigmen: #REF!
Name auxalm: #REF!

Sheet Budget Summary Partners
B1: Partners of the Americas Juntos Aprendemos Budget 2020
B2: USAID RFA No. 7200AA21RFA00001
A4: Line Items | B4: Year 1 | E4: Year 2 | H4: Year 3 | K4: Year 4 | N4: Year 5 | Q4: Total | R4: Total | S4: Grand
B5: USAID | C5: Leverage | D5: Total | E5: USAID | F5: Leverage | G5: Total | H5: USAID | I5: Leverage | J5: Total | K5: USAID | L5: Leverage | M5: Total | N5: USAID | O5: Leverage | P5: Total | Q5: USAID | R5: Leverage | S5: Total
A7: Personnel | B7: ='Budget Partners'!K39 -> 757570.27 | C7: ='Budget Partners'!L39 -> 0 | D7: =SUM(B7:C7) -> 757570.27 | E7: ='Budget Partners'!Q39 -> 869469.74 | F7: ='Budget Partners'!R39 -> 0 | G7: =SUM(E7:F7) -> 869469.74 | H7: ='Budget Partners'!W39 -> 904248.53 | I7: ='Budget Partners'!X39 -> 0 | J7: =SUM(H7:I7) -> 904248.53 | K7: ='Budget Partners'!AC39 -> 940418.48 | L7: ='Budget Partners'!AD39 -> 0 | M7: =SUM(K7:L7) -> 940418.48 | N7: ='Budget Partners'!AI39 -> 919932.24 | O7: ='Budget Partners'!AJ39 -> 0 | P7: =SUM(N7:O7) -> 919932.24 | Q7: ='Budget Partners'!AL39 -> 4391639.3 | R7: ='Budget Partners'!AM39 -> 0 | S7: ='Budget Partners'!AN39 -> 4391639.3
A9: Fringe Benefits | B9: ='Budget Partners'!K57 -> 387758.33 | C9: ='Budget Partners'!L57 -> 0 | D9: ='Budget Partners'!M57 -> 387758.33 | E9: ='Budget Partners'!Q57 -> 421082.64 | F9: ='Budget Partners'!R57 -> 0 | G9: ='Budget Partners'!S57 -> 421082.64 | H9: ='Budget Partners'!W57 -> 435904.26 | I9: ='Budget Partners'!X57 -> 0 | J9: ='Budget Partners'!Y57 -> 435904.26 | K9: ='Budget Partners'!AC57 -> 454244.23 | L9: ='Budget Partners'!AD57 -> 0 | M9: ='Budget Partners'!AE57 -> 454244.23 | N9: ='Budget Partners'!AI57 -> 463361.04 | O9: ='Budget Partners'!AJ57 -> 0 | P9: ='Budget Partners'!AK57 -> 463361.04 | Q9: ='Budget Partners'!AL57 -> 2162350.5 | R9: ='Budget Partners'!AM57 -> 0 | S9: ='Budget Partners'!AN57 -> 2162350.5
A11: Travel | B11: ='Budget Partners'!K106 -> 55845 | C11: ='Budget Partners'!L106 -> 0 | D11: ='Budget Partners'!M106 -> 55845 | E11: ='Budget Partners'!Q106 -> 110986.5 | F11: ='Budget Partners'!R106 -> 0 | G11: ='Budget Partners'!S106 -> 110986.5 | H11: ='Budget Partners'!W106 -> 116653.85 | I11: ='Budget Partners'!X106 -> 0 | J11: ='Budget Partners'!Y106 -> 116653.85 | K11: ='Budget Partners'!AC106 -> 118091.68 | L11: ='Budget Partners'!AD106 -> 0 | M11: ='Budget Partners'!AE106 -> 118091.68 | N11: ='Budget Partners'!AI106 -> 70200.655 | O11: ='Budget Partners'!AJ106 -> 0 | P11: ='Budget Partners'!AK106 -> 70200.655 | Q11: ='Budget Partners'!AL106 -> 471777.68 | R11: ='Budget Partners'!AM106 -> 0 | S11: ='Budget Partners'!AN106 -> 471777.68
A13: Equipment | B13: ='Budget Partners'!K112 -> 150000 | C13: ='Budget Partners'!L112 -> 0 | D13: ='Budget Partners'!M112 -> 150000 | E13: ='Budget Partners'!Q112 -> 0 | F13: ='Budget Partners'!R112 -> 0 | G13: ='Budget Partners'!S112 -> 0 | H13: ='Budget Partners'!W112 -> 0 | I13: ='Budget Partners'!X112 -> 0 | J13: ='Budget Partners'!Y112 -> 0 | K13: ='Budget Partners'!AC112 -> 0 | L13: ='Budget Partners'!AD112 -> 0 | M13: ='Budget Partners'!AE112 -> 0 | N13: ='Budget Partners'!AI112 -> 0 | O13: ='Budget Partners'!AJ112 -> 0 | P13: ='Budget Partners'!AK112 -> 0 | Q13: ='Budget Partners'!AL112 -> 150000 | R13: ='Budget Partners'!AM112 -> 0 | S13: ='Budget Partners'!AN112 -> 150000
A15: Supplies | B15: ='Budget Partners'!K137 -> 86398.18 | C15: ='Budget Partners'!L137 -> 0 | D15: ='Budget Partners'!M137 -> 86398.18 | E15: ='Budget Partners'!Q137 -> 40125 | F15: ='Budget Partners'!R137 -> 0 | G15: ='Budget Partners'!S137 -> 40125 | H15: ='Budget Partners'!W137 -> 41283.075 | I15: ='Budget Partners'!X137 -> 0 | J15: ='Budget Partners'!Y137 -> 41283.075 | K15: ='Budget Partners'!AC137 -> 27723.393 | L15: ='Budget Partners'!AD137 -> 0 | M15: ='Budget Partners'!AE137 -> 27723.393 | N15: ='Budget Partners'!AI137 -> 22177.052 | O15: ='Budget Partners'!AJ137 -> 0 | P15: ='Budget Partners'!AK137 -> 22177.052 | Q15: ='Budget Partners'!AL137 -> 217706.7 | R15: ='Budget Partners'!AM137 -> 0 | S15: ='Budget Partners'!AN137 -> 217706.7
A17: Contractual | B17: ='Budget Partners'!K168 -> 3318069.5 | C17: ='Budget Partners'!L168 -> 245351.82 | D17: ='Budget Partners'!M168 -> 3563421.3 | E17: ='Budget Partners'!Q168 -> 3997677.1 | F17: ='Budget Partners'!R168 -> 200067.84 | G17: ='Budget Partners'!S168 -> 4197744.9 | H17: ='Budget Partners'!W168 -> 4340006.7 | I17: ='Budget Partners'!X168 -> 198207.17 | J17: ='Budget Partners'!Y168 -> 4538213.9 | K17: ='Budget Partners'!AC168 -> 4317470.6 | L17: ='Budget Partners'!AD168 -> 205687.48 | M17: ='Budget Partners'!AE168 -> 4523158 | N17: ='Budget Partners'!AI168 -> 2761408.6 | O17: ='Budget Partners'!AJ168 -> 209691.71 | P17: ='Budget Partners'!AK168 -> 2971100.3 | Q17: ='Budget Partners'!AL168 -> 18734632 | R17: ='Budget Partners'!AM168 -> 1059006 | S17: ='Budget Partners'!AN168 -> 19793638
A19: Other Direct Costs | B19: ='Budget Partners'!K220 -> 316251 | C19: ='Budget Partners'!L220 -> 0 | D19: ='Budget Partners'!M220 -> 316251 | E19: ='Budget Partners'!Q220 -> 192761.42 | F19: ='Budget Partners'!R220 -> 0 | G19: ='Budget Partners'!S220 -> 192761.42 | H19: ='Budget Partners'!W220 -> 197225 | I19: ='Budget Partners'!X220 -> 0 | J19: ='Budget Partners'!Y220 -> 197225 | K19: ='Budget Partners'!AC220 -> 199315.36 | L19: ='Budget Partners'!AD220 -> 0 | M19: ='Budget Partners'!AE220 -> 199315.36 | N19: ='Budget Partners'!AI220 -> 163481.31 | O19: ='Budget Partners'!AJ220 -> 0 | P19: ='Budget Partners'!AK220 -> 163481.31 | Q19: ='Budget Partners'!AL220 -> 1069034.1 | R19: ='Budget Partners'!AM220 -> 0 | S19: ='Budget Partners'!AN220 -> 1069034.1
A21: Total Direct Costs | B21: ='Budget Partners'!K222 -> 5071892.3 | C21: ='Budget Partners'!L222 -> 245351.82 | D21: ='Budget Partners'!M222 -> 5317244.1 | E21: ='Budget Partners'!Q222 -> 5632102.4 | F21: ='Budget Partners'!R222 -> 200067.84 | G21: ='Budget Partners'!S222 -> 5832170.2 | H21: ='Budget Partners'!W222 -> 6035321.4 | I21: ='Budget Partners'!X222 -> 198207.17 | J21: ='Budget Partners'!Y222 -> 6233528.6 | K21: ='Budget Partners'!AC222 -> 6057263.7 | L21: ='Budget Partners'!AD222 -> 205687.48 | M21: ='Budget Partners'!AE222 -> 6262951.2 | N21: ='Budget Partners'!AI222 -> 4400560.9 | O21: ='Budget Partners'!AJ222 -> 209691.71 | P21: ='Budget Partners'!AK222 -> 4610252.6 | Q21: ='Budget Partners'!AL222 -> 27197141 | R21: ='Budget Partners'!AM222 -> 1059006 | S21: ='Budget Partners'!AN222 -> 28256147
A22: Indirect Costs | B22: ='Budget Partners'!K223 -> 1455125.9 | C22: ='Budget Partners'!L223 -> 0 | D22: ='Budget Partners'!M223 -> 1455125.9 | E22: ='Budget Partners'!Q223 -> 1615850.2 | F22: ='Budget Partners'!R223 -> 0 | G22: ='Budget Partners'!S223 -> 1615850.2 | H22: ='Budget Partners'!W223 -> 1731533.7 | I22: ='Budget Partners'!X223 -> 0 | J22: ='Budget Partners'!Y223 -> 1731533.7 | K22: ='Budget Partners'!AC223 -> 1737829 | L22: ='Budget Partners'!AD223 -> 0 | M22: ='Budget Partners'!AE223 -> 1737829 | N22: ='Budget Partners'!AI223 -> 1262520.9 | O22: ='Budget Partners'!AJ223 -> 0 | P22: ='Budget Partners'!AK223 -> 1262520.9 | Q22: ='Budget Partners'!AL223 -> 7802859.7 | R22: ='Budget Partners'!AM223 -> 0 | S22: ='Budget Partners'!AN223 -> 7802859.7
A23: Total | B23: ='Budget Partners'!K224 -> 6527018.2 | C23: ='Budget Partners'!L224 -> 245351.82 | D23: ='Budget Partners'!M224 -> 6772370 | E23: ='Budget Partners'!Q224 -> 7247952.6 | F23: ='Budget Partners'!R224 -> 200067.84 | G23: ='Budget Partners'!S224 -> 7448020.4 | H23: ='Budget Partners'!W224 -> 7766855.1 | I23: ='Budget Partners'!X224 -> 198207.17 | J23: ='Budget Partners'!Y224 -> 7965062.3 | K23: ='Budget Partners'!AC224 -> 7795092.7 | L23: ='Budget Partners'!AD224 -> 205687.48 | M23: ='Budget Partners'!AE224 -> 8000780.1 | N23: ='Budget Partners'!AI224 -> 5663081.8 | O23: ='Budget Partners'!AJ224 -> 209691.71 | P23: ='Budget Partners'!AK224 -> 5872773.5 | Q23: ='Budget Partners'!AL224 -> 35000000 | R23: ='Budget Partners'!AM224 -> 1059006 | S23: ='Budget Partners'!AN224 -> 36059006
B25: New Partnership Initiative Eligibility
B26: Sub-awards to new or underutilized partners via prime awardees that serve in a limited mentorship role
B28: Modality 3a: Local Entity Sub-Awardees That Move to Direct Awards: Prime awardees must pass a minimum of 50 percent of the total funding of their awards to local sub-awardees, with a goal of moving them to qualify for direct awards. In appropriate cases, USAID might pursue prime / mentor awards with a provision for transition awards to some local entities during the life of the award.
B29: Total Award: | E29: =Q23 -> 35000000
B30: 50% of Total Award: | E30: =E29*0.5 -> 17500000
B31: Subaward Parque Explora: | E31: ='Budget Summary Parque Explora'!Q23 -> 6818381.4
B32: Subaward ProAntioquia: | E32: ='Budget Summary ProAntioquia'!Q23 -> 2133978.7
B33: Subaward Fundación Carvajal: | E33: ='Budget Summary Fund. Carvajal'!Q23 -> 8686266.3
B34: Total Subawards: | E34: =SUM(E31:E33) -> 17638626

Sheet Budget Partners
G1: Partners of the Americas Juntos Aprendemos Budget 2020
G2: USAID RFA No. 7200AA21RFA00001
G3: Duration: 5 Years
G4: Country: Colombia
A5: Entity: | B5: P | F5: Budget Assumptions
A6: Program-Dept.: | B6: 20300 | F6: Inflation - US Based Goods/Services - 1.5% | G6: 1.015
A7: Funder-Grant: | B7: USAID800 | F7: Inflation - Locally Purchased Goods/Services - 3%** | G7: 1.03
F8: Merit Based Increases for HQ & Field Staff - 4% | G8: 1.04
F9: **Based on Banco de la Republica Colombia Expected Inflation Rate
F11: *Key Personnel
A12: Sage Activity | B12: Sage Object Code/ Line Item | C12: Country Code (DC=0 or CO) | D12: Office Code (DC=0 or CO) | E12: Subcontract Code | F12: Line Items | K12: Year 1 | Q12: Year 2 | T12: Year 3 | AC12: Year 4 | AI12: Year 5 | AL12: Total | AM12: Total | AN12: Grand
G13: Unit | H13: Cost | I13: Duration | J13: Type | K13: USAID | L13: Leverage | M13: Total | N13: Unit | O13: Cost | P13: Duration | Q13: USAID | R13: Leverage | S13: Total | T13: Unit | U13: Cost | V13: Duration | W13: USAID | X13: Leverage | Y13: Total | Z13: Unit | AA13: Cost | AB13: Duration | AC13: USAID | AD13: Leverage | AE13: Total | AF13: Unit | AG13: Cost | AH13: Duration | AI13: USAID | AJ13: Leverage | AK13: Total | AL13: USAID | AM13: Leverage | AN13: Total
F15: Personnel
F16: Headquarters Personnel | G16: LOE
A17: PERSNL | B17: Timesheets | C17: USA | D17: USA | E17: 0 | F17: Program Director | G17: 0.3 | H17: =116762/12 -> 9730.1667 | I17: 12 | J17: /months | K17: =I17*H17*G17 -> 35028.6 | L17: 0 | M17: =SUM(K17:L17) -> 35028.6 | N17: =G17 -> 0.3 | O17: =H17*$G$8 -> 10119.373 | P17: 12 | Q17: =N17*O17*P17 -> 36429.744 | R17: 0 | S17: =SUM(Q17:R17) -> 36429.744 | T17: =G17 -> 0.3 | U17: =H17*$G$8*$G$8 -> 10524.148 | V17: 12 | W17: =T17*U17*V17 -> 37886.934 | X17: 0 | Y17: =SUM(W17:X17) -> 37886.934 | Z17: =T17 -> 0.3 | AA17: =H17*$G$8*$G$8*$G$8 -> 10945.114 | AB17: 12 | AC17: =Z17*AA17*AB17 -> 39402.411 | AD17: 0 | AE17: =SUM(AC17:AD17) -> 39402.411 | AF17: =Z17 -> 0.3 | AG17: =H17*$G$8*$G$8*$G$8*$G$8 -> 11382.919 | AH17: 12 | AI17: =AF17*AG17*AH17 -> 40978.508 | AJ17: 0 | AK17: =SUM(AI17:AJ17) -> 40978.508 | AL17: =K17+Q17+W17+AC17+AI17 -> 189726.2 | AM17: =L17+R17+X17+AD17+AJ17 -> 0 | AN17: =SUM(AL17:AM17) -> 189726.2
A18: PERSNL | B18: Timesheets | C18: USA | D18: USA | E18: 0 | F18: Associate Director | G18: 1 | H18: =85000/12 -> 7083.3333 | I18: 12 | J18: /months | K18: =I18*H18*G18 -> 85000 | L18: 0 | M18: =SUM(K18:L18) -> 85000 | N18: =G18 -> 1 | O18: =H18*$G$8 -> 7366.6667 | P18: 12 | Q18: =N18*O18*P18 -> 88400 | R18: 0 | S18: =SUM(Q18:R18) -> 88400 | T18: =N18 -> 1 | U18: =H18*$G$8*$G$8 -> 7661.3333 | V18: 12 | W18: =T18*U18*V18 -> 91936 | X18: 0 | Y18: =SUM(W18:X18) -> 91936 | Z18: =T18 -> 1 | AA18: =H18*$G$8*$G$8*$G$8 -> 7967.7867 | AB18: 12 | AC18: =Z18*AA18*AB18 -> 95613.44 | AD18: 0 | AE18: =SUM(AC18:AD18) -> 95613.44 | AF18: =Z18 -> 1 | AG18: =H18*$G$8*$G$8*$G$8*$G$8 -> 8286.4981 | AH18: 12 | AI18: =AF18*AG18*AH18 -> 99437.978 | AJ18: 0 | AK18: =SUM(AI18:AJ18) -> 99437.978 | AL18: =K18+Q18+W18+AC18+AI18 -> 460387.42 | AM18: =L18+R18+X18+AD18+AJ18 -> 0 | AN18: =SUM(AL18:AM18) -> 460387.42
A19: PERSNL | B19: Timesheets | C19: USA | D19: USA | E19: 0 | F19: Senior Program Officer | G19: 1 | H19: =52000/12 -> 4333.3333 | I19: 12 | J19: /months | K19: =I19*H19*G19 -> 52000 | L19: 0 | M19: =SUM(K19:L19) -> 52000 | N19: =G19 -> 1 | O19: =H19*$G$8 -> 4506.6667 | P19: 12 | Q19: =N19*O19*P19 -> 54080 | R19: 0 | S19: =SUM(Q19:R19) -> 54080 | T19: =N19 -> 1 | U19: =H19*$G$8*$G$8 -> 4686.9333 | V19: 12 | W19: =T19*U19*V19 -> 56243.2 | X19: 0 | Y19: =SUM(W19:X19) -> 56243.2 | Z19: =T19 -> 1 | AA19: =H19*$G$8*$G$8*$G$8 -> 4874.4107 | AB19: 12 | AC19: =Z19*AA19*AB19 -> 58492.928 | AD19: 0 | AE19: =SUM(AC19:AD19) -> 58492.928 | AF19: =Z19 -> 1 | AG19: =H19*$G$8*$G$8*$G$8*$G$8 -> 5069.3871 | AH19: 12 | AI19: =AF19*AG19*AH19 -> 60832.645 | AJ19: 0 | AK19: =SUM(AI19:AJ19) -> 60832.645 | AL19: =K19+Q19+W19+AC19+AI19 -> 281648.77 | AM19: =L19+R19+X19+AD19+AJ19 -> 0 | AN19: =SUM(AL19:AM19) -> 281648.77
F20: Subtotal HQ Personnel | K20: =SUM(K17:K19) -> 172028.6 | L20: =SUM(L17:L19) -> 0 | M20: =SUM(M17:M19) -> 172028.6 | Q20: =SUM(Q17:Q19) -> 178909.74 | R20: =SUM(R17:R19) -> 0 | S20: =SUM(S17:S19) -> 178909.74 | W20: =SUM(W17:W19) -> 186066.13 | X20: =SUM(X17:X19) -> 0 | Y20: =SUM(Y17:Y19) -> 186066.13 | AC20: =SUM(AC17:AC19) -> 193508.78 | AD20: =SUM(AD17:AD19) -> 0 | AE20: =SUM(AE17:AE19) -> 193508.78 | AI20: =SUM(AI17:AI19) -> 201249.13 | AJ20: =SUM(AJ17:AJ19) -> 0 | AK20: =SUM(AK17:AK19) -> 201249.13 | AL20: =SUM(AL17:AL19) -> 931762.39 | AM20: =SUM(AM17:AM19) -> 0 | AN20: =SUM(AN17:AN19) -> 931762.39
F22: Field Personnel | G22: LOE
A23: PERSNL-COP | B23: Timesheets | C23: COL2 | D23: COL2 | E23: 0 | F23: Chief of Party* | G23: 1 | H23: =135000/12 -> 11250 | I23: 12 | J23: /months | K23: =I23*H23*G23 -> 135000 | L23: 0 | M23: =SUM(K23:L23) -> 135000 | N23: 1 | O23: =H23*$G$8 -> 11700 | P23: 12 | Q23: =O23*P23*N23 -> 140400 | R23: 0 | S23: =SUM(Q23:R23) -> 140400 | T23: 1 | U23: =(H23*$G$8*$G$8) -> 12168 | V23: 12 | W23: =V23*U23*T23 -> 146016 | X23: 0 | Y23: =SUM(W23:X23) -> 146016 | Z23: 1 | AA23: =H23*$G$8*$G$8*$G$8 -> 12654.72 | AB23: 12 | AC23: =AB23*AA23*Z23 -> 151856.64 | AD23: 0 | AE23: =SUM(AC23:AD23) -> 151856.64 | AF23: 1 | AG23: =H23*$G$8*$G$8*$G$8*$G$8 -> 13160.909 | AH23: 12 | AI23: =AH23*AG23*AF23 -> 157930.91 | AJ23: 0 | AK23: =SUM(AI23:AJ23) -> 157930.91 | AL23: =K23+Q23+W23+AC23+AI23 -> 731203.55 | AM23: =L23+R23+X23+AD23+AJ23 -> 0 | AN23: =SUM(AL23:AM23) -> 731203.55
A24: PERSNL-DCP | B24: 70000 | C24: COL2 | D24: COL2 | E24: 0 | F24: Deputy Chief of Party* | G24: 1 | H24: =100000/12 -> 8333.3333 | I24: 12 | J24: /months | K24: =I24*H24*G24 -> 100000 | L24: 0 | M24: =SUM(K24:L24) -> 100000 | N24: 1 | O24: =H24*$G$8 -> 8666.6667 | P24: 12 | Q24: =O24*P24*N24 -> 104000 | R24: 0 | S24: =SUM(Q24:R24) -> 104000 | T24: 1 | U24: =H24*$G$8*$G$8 -> 9013.3333 | V24: 12 | W24: =V24*U24*T24 -> 108160 | X24: 0 | Y24: =SUM(W24:X24) -> 108160 | Z24: 1 | AA24: =H24*$G$8*$G$8*$G$8 -> 9373.8667 | AB24: 12 | AC24: =AB24*AA24*Z24 -> 112486.4 | AD24: 0 | AE24: =SUM(AC24:AD24) -> 112486.4 | AF24: 1 | AG24: =H24*$G$8*$G$8*$G$8*$G$8 -> 9748.8213 | AH24: 12 | AI24: =AH24*AG24*AF24 -> 116985.86 | AJ24: 0 | AK24: =SUM(AI24:AJ24) -> 116985.86 | AL24: =K24+Q24+W24+AC24+AI24 -> 541632.26 | AM24: =L24+R24+X24+AD24+AJ24 -> 0 | AN24: =SUM(AL24:AM24) -> 541632.26
A25: PERSNL-F&A | B25: 70000 | C25: COL2 | D25: COL2 | E25: 0 | F25: Finance & Admin Director | G25: 1 | H25: =52500/12 -> 4375 | I25: 12 | J25: /months | K25: =I25*H25*G25 -> 52500 | L25: 0 | M25: =SUM(K25:L25) -> 52500 | N25: 1 | O25: =H25*$G$8 -> 4550 | P25: 12 | Q25: =O25*P25*N25 -> 54600 | R25: 0 | S25: =SUM(Q25:R25) -> 54600 | T25: 1 | U25: =H25*$G$8*$G$8 -> 4732 | V25: 12 | W25: =V25*U25*T25 -> 56784 | X25: 0 | Y25: =SUM(W25:X25) -> 56784 | Z25: 1 | AA25: =H25*$G$8*$G$8*$G$8 -> 4921.28 | AB25: 12 | AC25: =AB25*AA25*Z25 -> 59055.36 | AD25: 0 | AE25: =SUM(AC25:AD25) -> 59055.36 | AF25: 1 | AG25: =H25*$G$8*$G$8*$G$8*$G$8 -> 5118.1312 | AH25: 12 | AI25: =AH25*AG25*AF25 -> 61417.574 | AJ25: 0 | AK25: =SUM(AI25:AJ25) -> 61417.574 | AL25: =K25+Q25+W25+AC25+AI25 -> 284356.93 | AM25: =L25+R25+X25+AD25+AJ25 -> 0 | AN25: =SUM(AL25:AM25) -> 284356.93
A26: PERSNL-GD | B26: 70000 | C26: COL2 | D26: COL2 | E26: 0 | F26: Grants Director | G26: 1 | H26: =52500/12 -> 4375 | I26: 10 | J26: /months | K26: =I26*H26*G26 -> 43750 | L26: 0 | M26: =SUM(K26:L26) -> 43750 | N26: 1 | O26: =H26*$G$8 -> 4550 | P26: 12 | Q26: =O26*P26*N26 -> 54600 | R26: 0 | S26: =SUM(Q26:R26) -> 54600 | T26: 1 | U26: =H26*$G$8*$G$8 -> 4732 | V26: 12 | W26: =V26*U26*T26 -> 56784 | X26: 0 | Y26: =SUM(W26:X26) -> 56784 | Z26: 1 | AA26: =H26*$G$8*$G$8*$G$8 -> 4921.28 | AB26: 12 | AC26: =AB26*AA26*Z26 -> 59055.36 | AD26: 0 | AE26: =SUM(AC26:AD26) -> 59055.36 | AF26: 1 | AG26: =H26*$G$8*$G$8*$G$8*$G$8 -> 5118.1312 | AH26: 12 | AI26: =AH26*AG26*AF26 -> 61417.574 | AJ26: 0 | AK26: =SUM(AI26:AJ26) -> 61417.574 | AL26: =K26+Q26+W26+AC26+AI26 -> 275606.93 | AM26: =L26+R26+X26+AD26+AJ26 -> 0 | AN26: =SUM(AL26:AM26) -> 275606.93
A27: PERSNL-HRM | B27: 70000 | C27: COL2 | D27: COL2 | E27: 0 | F27: Human Resource Manager | G27: 1 | H27: =38000/12 -> 3166.6667 | I27: 10 | J27: /months | K27: =I27*H27*G27 -> 31666.667 | L27: 0 | M27: =SUM(K27:L27) -> 31666.667 | N27: 1 | O27: =H27*$G$8 -> 3293.3333 | P27: 12 | Q27: =O27*P27*N27 -> 39520 | R27: 0 | S27: =SUM(Q27:R27) -> 39520 | T27: 1 | U27: =H27*$G$8*$G$8 -> 3425.0667 | V27: 12 | W27: =V27*U27*T27 -> 41100.8 | X27: 0 | Y27: =SUM(W27:X27) -> 41100.8 | Z27: 1 | AA27: =H27*$G$8*$G$8*$G$8 -> 3562.0693 | AB27: 12 | AC27: =AB27*AA27*Z27 -> 42744.832 | AD27: 0 | AE27: =SUM(AC27:AD27) -> 42744.832 | AF27: 1 | AG27: =H27*$G$8*$G$8*$G$8*$G$8 -> 3704.5521 | AH27: 11 | AI27: =AH27*AG27*AF27 -> 40750.073 | AJ27: 0 | AK27: =SUM(AI27:AJ27) -> 40750.073 | AL27: =K27+Q27+W27+AC27+AI27 -> 195782.37 | AM27: =L27+R27+X27+AD27+AJ27 -> 0 | AN27: =SUM(AL27:AM27) -> 195782.37
A28: PERSNL-ACT | B28: 70000 | C28: COL2 | D28: COL2 | E28: 0 | F28: Accountant | G28: 1 | H28: =22500/12 -> 1875 | I28: 9 | J28: /months | K28: =I28*H28*G28 -> 16875 | L28: 0 | M28: =SUM(K28:L28) -> 16875 | N28: 1 | O28: =H28*$G$8 -> 1950 | P28: 12 | Q28: =O28*P28*N28 -> 23400 | R28: 0 | S28: =SUM(Q28:R28) -> 23400 | T28: 1 | U28: =H28*$G$8*$G$8 -> 2028 | V28: 12 | W28: =V28*U28*T28 -> 24336 | X28: 0 | Y28: =SUM(W28:X28) -> 24336 | Z28: 1 | AA28: =H28*$G$8*$G$8*$G$8 -> 2109.12 | AB28: 12 | AC28: =AB28*AA28*Z28 -> 25309.44 | AD28: 0 | AE28: =SUM(AC28:AD28) -> 25309.44 | AF28: 1 | AG28: =H28*$G$8*$G$8*$G$8*$G$8 -> 2193.4848 | AH28: 9 | AI28: =AH28*AG28*AF28 -> 19741.363 | AJ28: 0 | AK28: =SUM(AI28:AJ28) -> 19741.363 | AL28: =K28+Q28+W28+AC28+AI28 -> 109661.8 | AM28: =L28+R28+X28+AD28+AJ28 -> 0 | AN28: =SUM(AL28:AM28) -> 109661.8
A29: PERSNL-ADM | B29: 70000 | C29: COL2 | D29: COL2 | E29: 0 | F29: Administrative Assistant | G29: 1 | H29: =15000/12 -> 1250 | I29: 8 | J29: /months | K29: =I29*H29*G29 -> 10000 | L29: 0 | M29: =SUM(K29:L29) -> 10000 | N29: 1 | O29: =H29*$G$8 -> 1300 | P29: 12 | Q29: =O29*P29*N29 -> 15600 | R29: 0 | S29: =SUM(Q29:R29) -> 15600 | T29: 1 | U29: =H29*$G$8*$G$8 -> 1352 | V29: 12 | W29: =V29*U29*T29 -> 16224 | X29: 0 | Y29: =SUM(W29:X29) -> 16224 | Z29: 1 | AA29: =H29*$G$8*$G$8*$G$8 -> 1406.08 | AB29: 12 | AC29: =AB29*AA29*Z29 -> 16872.96 | AD29: 0 | AE29: =SUM(AC29:AD29) -> 16872.96 | AF29: 1 | AG29: =H29*$G$8*$G$8*$G$8*$G$8 -> 1462.3232 | AH29: 8 | AI29: =AH29*AG29*AF29 -> 11698.586 | AJ29: 0 | AK29: =SUM(AI29:AJ29) -> 11698.586 | AL29: =K29+Q29+W29+AC29+AI29 -> 70395.546 | AM29: =L29+R29+X29+AD29+AJ29 -> 0 | AN29: =SUM(AL29:AM29) -> 70395.546
A30: PERSNL-MED | B30: 70000 | C30: COL2 | D30: COL2 | E30: 0 | F30: M&E Director | G30: 1 | H30: =52500/12 -> 4375 | I30: 12 | J30: /months | K30: =I30*H30*G30 -> 52500 | L30: 0 | M30: =SUM(K30:L30) -> 52500 | N30: 1 | O30: =H30*$G$8 -> 4550 | P30: 12 | Q30: =O30*P30*N30 -> 54600 | R30: 0 | S30: =SUM(Q30:R30) -> 54600 | T30: 1 | U30: =H30*$G$8*$G$8 -> 4732 | V30: 12 | W30: =V30*U30*T30 -> 56784 | X30: 0 | Y30: =SUM(W30:X30) -> 56784 | Z30: 1 | AA30: =H30*$G$8*$G$8*$G$8 -> 4921.28 | AB30: 12 | AC30: =AB30*AA30*Z30 -> 59055.36 | AD30: 0 | AE30: =SUM(AC30:AD30) -> 59055.36 | AF30: 1 | AG30: =H30*$G$8*$G$8*$G$8*$G$8 -> 5118.1312 | AH30: 12 | AI30: =AH30*AG30*AF30 -> 61417.574 | AJ30: 0 | AK30: =SUM(AI30:AJ30) -> 61417.574 | AL30: =K30+Q30+W30+AC30+AI30 -> 284356.93 | AM30: =L30+R30+X30+AD30+AJ30 -> 0 | AN30: =SUM(AL30:AM30) -> 284356.93
A31: PERSNL-M&E | B31: 70000 | C31: COL2 | D31: COL2 | E31: 0 | F31: M&E Manager | G31: 1 | H31: =38000/12 -> 3166.6667 | I31: 9 | J31: /months | K31: =I31*H31*G31 -> 28500 | L31: 0 | M31: =SUM(K31:L31) -> 28500 | N31: 1 | O31: =H31*$G$8 -> 3293.3333 | P31: 12 | Q31: =O31*P31*N31 -> 39520 | R31: 0 | S31: =SUM(Q31:R31) -> 39520 | T31: 1 | U31: =H31*$G$8*$G$8 -> 3425.0667 | V31: 12 | W31: =V31*U31*T31 -> 41100.8 | X31: 0 | Y31: =SUM(W31:X31) -> 41100.8 | Z31: 1 | AA31: =H31*$G$8*$G$8*$G$8 -> 3562.0693 | AB31: 12 | AC31: =AB31*AA31*Z31 -> 42744.832 | AD31: 0 | AE31: =SUM(AC31:AD31) -> 42744.832 | AF31: 1 | AG31: =H31*$G$8*$G$8*$G$8*$G$8 -> 3704.5521 | AH31: 9 | AI31: =AH31*AG31*AF31 -> 33340.969 | AJ31: 0 | AK31: =SUM(AI31:AJ31) -> 33340.969 | AL31: =K31+Q31+W31+AC31+AI31 -> 185206.6 | AM31: =L31+R31+X31+AD31+AJ31 -> 0 | AN31: =SUM(AL31:AM31) -> 185206.6
A32: PERSNL-CDD | B32: 70000 | C32: COL2 | D32: COL2 | E32: 0 | F32: Capacity Development Director* | G32: 1 | H32: =52500/12 -> 4375 | I32: 12 | J32: /months | K32: =I32*H32*G32 -> 52500 | L32: 0 | M32: =SUM(K32:L32) -> 52500 | N32: 1 | O32: =H32*$G$8 -> 4550 | P32: 12 | Q32: =O32*P32*N32 -> 54600 | R32: 0 | S32: =SUM(Q32:R32) -> 54600 | T32: 1 | U32: =H32*$G$8*$G$8 -> 4732 | V32: 12 | W32: =V32*U32*T32 -> 56784 | X32: 0 | Y32: =SUM(W32:X32) -> 56784 | Z32: 1 | AA32: =H32*$G$8*$G$8*$G$8 -> 4921.28 | AB32: 12 | AC32: =AB32*AA32*Z32 -> 59055.36 | AD32: 0 | AE32: =SUM(AC32:AD32) -> 59055.36 | AF32: 1 | AG32: =H32*$G$8*$G$8*$G$8*$G$8 -> 5118.1312 | AH32: 12 | AI32: =AH32*AG32*AF32 -> 61417.574 | AJ32: 0 | AK32: =SUM(AI32:AJ32) -> 61417.574 | AL32: =K32+Q32+W32+AC32+AI32 -> 284356.93 | AM32: =L32+R32+X32+AD32+AJ32 -> 0 | AN32: =SUM(AL32:AM32) -> 284356.93
A33: PERSNL-CDM | B33: 70000 | C33: COL2 | D33: COL2 | E33: 0 | F33: Capacity Development Manager | G33: 1 | H33: =38000/12 -> 3166.6667 | I33: 9 | J33: /months | K33: =I33*H33*G33 -> 28500 | L33: 0 | M33: =SUM(K33:L33) -> 28500 | N33: 1 | O33: =H33*$G$8 -> 3293.3333 | P33: 12 | Q33: =O33*P33*N33 -> 39520 | R33: 0 | S33: =SUM(Q33:R33) -> 39520 | T33: 1 | U33: =H33*$G$8*$G$8 -> 3425.0667 | V33: 12 | W33: =V33*U33*T33 -> 41100.8 | X33: 0 | Y33: =SUM(W33:X33) -> 41100.8 | Z33: 1 | AA33: =H33*$G$8*$G$8*$G$8 -> 3562.0693 | AB33: 12 | AC33: =AB33*AA33*Z33 -> 42744.832 | AD33: 0 | AE33: =SUM(AC33:AD33) -> 42744.832 | AF33: 1 | AG33: =H33*$G$8*$G$8*$G$8*$G$8 -> 3704.5521 | AH33: 9 | AI33: =AH33*AG33*AF33 -> 33340.969 | AJ33: 0 | AK33: =SUM(AI33:AJ33) -> 33340.969 | AL33: =K33+Q33+W33+AC33+AI33 -> 185206.6 | AM33: =L33+R33+X33+AD33+AJ33 -> 0 | AN33: =SUM(AL33:AM33) -> 185206.6
A34: PERSNL-RCN | B34: 70000 | C34: COL2 | D34: COL2 | E34: 0 | F34: Regional Coordinator Northern Coast | G34: 1 | H34: =22500/12 -> 1875 | I34: 6 | J34: /months | K34: =I34*H34*G34 -> 11250 | L34: 0 | M34: =SUM(K34:L34) -> 11250 | N34: 1 | O34: =H34*$G$8 -> 1950 | P34: 12 | Q34: =O34*P34*N34 -> 23400 | R34: 0 | S34: =SUM(Q34:R34) -> 23400 | T34: 1 | U34: =H34*$G$8*$G$8 -> 2028 | V34: 12 | W34: =V34*U34*T34 -> 24336 | X34: 0 | Y34: =SUM(W34:X34) -> 24336 | Z34: 1 | AA34: =H34*$G$8*$G$8*$G$8 -> 2109.12 | AB34: 12 | AC34: =AB34*AA34*Z34 -> 25309.44 | AD34: 0 | AE34: =SUM(AC34:AD34) -> 25309.44 | AF34: 1 | AG34: =H34*$G$8*$G$8*$G$8*$G$8 -> 2193.4848 | AH34: 9 | AI34: =AH34*AG34*AF34 -> 19741.363 | AJ34: 0 | AK34: =SUM(AI34:AJ34) -> 19741.363 | AL34: =K34+Q34+W34+AC34+AI34 -> 104036.8 | AM34: =L34+R34+X34+AD34+AJ34 -> 0 | AN34: =SUM(AL34:AM34) -> 104036.8
A35: PERSNL-RCC | B35: 70000 | C35: COL2 | D35: COL2 | E35: 0 | F35: Regional Coordinator Central Region | G35: 1 | H35: =22500/12 -> 1875 | I35: 6 | J35: /months | K35: =I35*H35*G35 -> 11250 | L35: 0 | M35: =SUM(K35:L35) -> 11250 | N35: 1 | O35: =H35*$G$8 -> 1950 | P35: 12 | Q35: =O35*P35*N35 -> 23400 | R35: 0 | S35: =SUM(Q35:R35) -> 23400 | T35: 1 | U35: =H35*$G$8*$G$8 -> 2028 | V35: 12 | W35: =V35*U35*T35 -> 24336 | X35: 0 | Y35: =SUM(W35:X35) -> 24336 | Z35: 1 | AA35: =H35*$G$8*$G$8*$G$8 -> 2109.12 | AB35: 12 | AC35: =AB35*AA35*Z35 -> 25309.44 | AD35: 0 | AE35: =SUM(AC35:AD35) -> 25309.44 | AF35: 1 | AG35: =H35*$G$8*$G$8*$G$8*$G$8 -> 2193.4848 | AH35: 9 | AI35: =AH35*AG35*AF35 -> 19741.363 | AJ35: 0 | AK35: =SUM(AI35:AJ35) -> 19741.363 | AL35: =K35+Q35+W35+AC35+AI35 -> 104036.8 | AM35: =L35+R35+X35+AD35+AJ35 -> 0 | AN35: =SUM(AL35:AM35) -> 104036.8
A36: PERSNL-RCW | B36: 70000 | C36: COL2 | D36: COL2 | E36: 0 | F36: Regional Coordinator Northwestern Region | G36: 1 | H36: =22500/12 -> 1875 | I36: 6 | J36: /months | K36: =I36*H36*G36 -> 11250 | L36: 0 | M36: =SUM(K36:L36) -> 11250 | N36: 1 | O36: =H36*$G$8 -> 1950 | P36: 12 | Q36: =O36*P36*N36 -> 23400 | R36: 0 | S36: =SUM(Q36:R36) -> 23400 | T36: 1 | U36: =H36*$G$8*$G$8 -> 2028 | V36: 12 | W36: =V36*U36*T36 -> 24336 | X36: 0 | Y36: =SUM(W36:X36) -> 24336 | Z36: 1 | AA36: =H36*$G$8*$G$8*$G$8 -> 2109.12 | AB36: 12 | AC36: =AB36*AA36*Z36 -> 25309.44 | AD36: 0 | AE36: =SUM(AC36:AD36) -> 25309.44 | AF36: 1 | AG36: =H36*$G$8*$G$8*$G$8*$G$8 -> 2193.4848 | AH36: 9 | AI36: =AH36*AG36*AF36 -> 19741.363 | AJ36: 0 | AK36: =SUM(AI36:AJ36) -> 19741.363 | AL36: =K36+Q36+W36+AC36+AI36 -> 104036.8 | AM36: =L36+R36+X36+AD36+AJ36 -> 0 | AN36: =SUM(AL36:AM36) -> 104036.8
F37: Subtotal Field Personnel | K37: =SUM(K23:K36) -> 585541.67 | L37: =SUM(L23:L36) -> 0 | M37: =SUM(M23:M36) -> 585541.67 | Q37: =SUM(Q23:Q36) -> 690560 | R37: =SUM(R23:R36) -> 0 | S37: =SUM(S23:S36) -> 690560 | W37: =SUM(W23:W36) -> 718182.4 | X37: =SUM(X23:X36) -> 0 | Y37: =SUM(Y23:Y36) -> 718182.4 | AC37: =SUM(AC23:AC36) -> 746909.7 | AD37: =SUM(AD23:AD36) -> 0 | AE37: =SUM(AE23:AE36) -> 746909.7 | AI37: =SUM(AI23:AI36) -> 718683.11 | AJ37: =SUM(AJ23:AJ36) -> 0 | AK37: =SUM(AK23:AK36) -> 718683.11 | AL37: =K37+Q37+W37+AC37+AI37 -> 3459876.9 | AM37: =L37+R37+X37+AD37+AJ37 -> 0 | AN37: =SUM(AL37:AM37) -> 3459876.9
F39: Personnel Total | K39: =K37+K20 -> 757570.27 | L39: =L37+L20 -> 0 | M39: =M37+M20 -> 757570.27 | Q39: =Q37+Q20 -> 869469.74 | R39: =R37+R20 -> 0 | S39: =S37+S20 -> 869469.74 | W39: =W37+W20 -> 904248.53 | X39: =X37+X20 -> 0 | Y39: =Y37+Y20 -> 904248.53 | AC39: =AC37+AC20 -> 940418.48 | AD39: =AD37+AD20 -> 0 | AE39: =AE37+AE20 -> 940418.48 | AI39: =AI37+AI20 -> 919932.24 | AJ39: =AJ37+AJ20 -> 0 | AK39: =AK37+AK20 -> 919932.24 | AL39: =AL37+AL20 -> 4391639.3 | AM39: =AM37+AM20 -> 0 | AN39: =AN37+AN20 -> 4391639.3
F41: Fringe Benefits
F42: HQ Fringe Benefits | G42: LOE
A43: FRINGE | B43: 50900 | C43: USA | D43: USA | E43: 0 | F43: Fringe Benefits - Headquarters | G43: 0.2181 | K43: =(K20+K23)*$G$43 -> 66962.938 | L43: 0 | M43: =SUM(K43:L43) -> 66962.938 | Q43: =(Q20+Q23)*$G$43 -> 69641.455 | R43: 0 | S43: =SUM(Q43:R43) -> 69641.455 | W43: =(W20+W23)*$G$43 -> 72427.113 | X43: 0 | Y43: =SUM(W43:X43) -> 72427.113 | AC43: =(AC20+AC23)*$G$43 -> 75324.198 | AD43: 0 | AE43: =SUM(AC43:AD43) -> 75324.198 | AI43: =(AI20+AI23)*$G$43 -> 78337.166 | AJ43: 0 | AK43: =SUM(AI43:AJ43) -> 78337.166 | AL43: =K43+Q43+W43+AC43+AI43 -> 362692.87 | AM43: =L43+R43+X43+AD43+AJ43 -> 0 | AN43: =SUM(AL43:AM43) -> 362692.87
F44: Subtotal HQ Fringe Benefits | K44: =SUM(K43) -> 66962.938 | L44: =SUM(L43) -> 0 | M44: =SUM(M43) -> 66962.938 | Q44: =SUM(Q43) -> 69641.455 | R44: =SUM(R43) -> 0 | S44: =SUM(S43) -> 69641.455 | W44: =SUM(W43) -> 72427.113 | X44: =SUM(X43) -> 0 | Y44: =SUM(Y43) -> 72427.113 | AC44: =SUM(AC43) -> 75324.198 | AD44: =SUM(AD43) -> 0 | AE44: =SUM(AE43) -> 75324.198 | AI44: =SUM(AI43) -> 78337.166 | AJ44: =SUM(AJ43) -> 0 | AK44: =SUM(AK43) -> 78337.166 | AL44: =SUM(AL43) -> 362692.87 | AM44: =SUM(AM43) -> 0 | AN44: =SUM(AN43) -> 362692.87
F46: Field Fringe Benefits
A47: FRINGE-CO | B47: 70015 | C47: USA | D47: USA | E47: 0 | F47: Fringe Benefits CCN - Colombia (above $2,600 monthly) | G47: 0.53864 | K47: =(K24+K25+K26+K27+K30+K31+K32+K33)*$G$47 -> 210024.71 | L47: 0 | M47: =SUM(K47:L47) -> 210024.71 | Q47: =(Q24+Q25+Q26+Q27+Q30+Q31+Q32+Q33)*$G$47 -> 237518.69 | R47: 0 | S47: =SUM(Q47:R47) -> 237518.69 | W47: =(W24+W25+W26+W27+W30+W31+W32+W33)*$G$47 -> 247019.44 | X47: 0 | Y47: =SUM(W47:X47) -> 247019.44 | AC47: =(AC24+AC25+AC26+AC27+AC30+AC31+AC32+AC33)*$G$47 -> 256900.22 | AD47: 0 | AE47: =SUM(AC47:AD47) -> 256900.22 | AI47: =(AI24+AI25+AI26+AI27+AI30+AI31+AI32+AI33)*$G$47 -> 253208.29 | AJ47: 0 | AK47: =SUM(AI47:AJ47) -> 253208.29 | AL47: =K47+Q47+W47+AC47+AI47 -> 1204671.4 | AM47: =L47+R47+X47+AD47+AJ47 -> 0 | AN47: =SUM(AL47:AM47) -> 1204671.4
A48: FRINGE-CO | B48: 70015 | C48: USA | D48: USA | E48: 0 | F48: Fringe Benefits CCN - Colombia (below $2,600 monthly) | G48: 0.40364 | K48: =(K28+K29+K34+K35+K36)*$G$48 -> 24470.675 | L48: 0 | M48: =SUM(K48:L48) -> 24470.675 | Q48: =(Q28+Q29+Q34+Q35+Q36)*$G$48 -> 44077.488 | R48: 0 | S48: =SUM(Q48:R48) -> 44077.488 | W48: =(W28+W29+W34+W35+W36)*$G$48 -> 45840.588 | X48: 0 | Y48: =SUM(W48:X48) -> 45840.588 | AC48: =(AC28+AC29+AC34+AC35+AC36)*$G$48 -> 47674.211 | AD48: 0 | AE48: =SUM(AC48:AD48) -> 47674.211 | AI48: =(AI28+AI29+AI34+AI35+AI36)*$G$48 -> 36595.632 | AJ48: 0 | AK48: =SUM(AI48:AJ48) -> 36595.632 | AL48: =K48+Q48+W48+AC48+AI48 -> 198658.59 | AM48: =L48+R48+X48+AD48+AJ48 -> 0 | AN48: =SUM(AL48:AM48) -> 198658.59
A49: POST DIFF | B49: 50202 | C49: COL2 | D49: COL2 | E49: 0 | F49: Post (Hardship) Differential for Expatriate Chief of Party | G49: 0.1 | K49: =$G$49*K23 -> 13500 | L49: 0 | M49: =SUM(K49:L49) -> 13500 | Q49: =$G$49*Q23 -> 14040 | R49: 0 | S49: =SUM(Q49:R49) -> 14040 | W49: =$G$49*W23 -> 14601.6 | X49: 0 | Y49: =SUM(W49:X49) -> 14601.6 | AC49: =$G$49*AC23 -> 15185.664 | AD49: 0 | AE49: =SUM(AC49:AD49) -> 15185.664 | AI49: =$G$49*AI23 -> 15793.091 | AJ49: 0 | AK49: =SUM(AI49:AJ49) -> 15793.091 | AL49: =K49+Q49+W49+AC49+AI49 -> 73120.355 | AM49: =L49+R49+X49+AD49+AJ49 -> 0 | AN49: =SUM(AL49:AM49) -> 73120.355
A50: HOUSE. ALL | B50: 50203 | C50: COL2 | D50: COL2 | E50: 0 | F50: Housing Allowance for Expatriate Chief of Party | G50: 1 | H50: 2800 | I50: 12 | J50: /month | K50: =I50*H50*G50 -> 33600 | L50: 0 | M50: =SUM(K50:L50) -> 33600 | N50: 1 | O50: =H50*$G$7 -> 2884 | P50: =P23 -> 12 | Q50: =P50*O50*N50 -> 34608 | R50: 0 | S50: =SUM(Q50:R50) -> 34608 | T50: 1 | U50: =H50*$G$7*$G$7 -> 2970.52 | V50: 12 | W50: =V50*U50*T50 -> 35646.24 | X50: 0 | Y50: =SUM(W50:X50) -> 35646.24 | Z50: 1 | AA50: =H50*$G$7*$G$7*$G$7 -> 3059.6356 | AB50: 12 | AC50: =AB50*AA50*Z50 -> 36715.627 | AD50: 0 | AE50: =SUM(AC50:AD50) -> 36715.627 | AF50: 1 | AG50: =H50*$G$7*$G$7*$G$7*$G$7 -> 3151.4247 | AH50: 12 | AI50: =AH50*AG50*AF50 -> 37817.096 | AJ50: 0 | AK50: =SUM(AI50:AJ50) -> 37817.096 | AL50: =K50+Q50+W50+AC50+AI50 -> 178386.96 | AM50: =L50+R50+X50+AD50+AJ50 -> 0 | AN50: =SUM(AL50:AM50) -> 178386.96
A51: REALLOC | B51: 50205 | C51: COL2 | D51: COL2 | E51: 0 | F51: Reallocation Allowance for Expatriate Chief of Party | G51: 1 | H51: 20000 | I51: 1 | J51: /yearly | K51: =I51*H51*G51 -> 20000 | L51: 0 | M51: =SUM(K51:L51) -> 20000 | N51: 0 | O51: =H51 -> 20000 | P51: 1 | Q51: =P51*O51*N51 -> 0 | R51: 0 | S51: =SUM(Q51:R51) -> 0 | T51: 0 | U51: =H51 -> 20000 | V51: 1 | W51: =V51*U51*T51 -> 0 | X51: 0 | Y51: =SUM(W51:X51) -> 0 | Z51: 0 | AA51: =H51 -> 20000 | AB51: 0 | AC51: =AB51*AA51*Z51 -> 0 | AD51: 0 | AE51: =SUM(AC51:AD51) -> 0 | AF51: 0 | AG51: =H51 -> 20000 | AH51: 0 | AI51: =AH51*AG51*AF51 -> 0 | AJ51: 0 | AK51: =SUM(AI51:AJ51) -> 0 | AL51: =K51+Q51+W51+AC51+AI51 -> 20000 | AM51: =L51+R51+X51+AD51+AJ51 -> 0 | AN51: =SUM(AL51:AM51) -> 20000
A52: DEMOBILE | B52: 50205 | C52: COL2 | D52: COL2 | E52: 0 | F52: Demobilization Allowance for Expatriate Chief of Party | G52: 0 | H52: 20000 | I52: 0 | J52: /yearly | K52: =I52*H52*G52 -> 0 | L52: 0 | M52: =SUM(K52:L52) -> 0 | N52: 0 | O52: =H52 -> 20000 | P52: 0 | Q52: =P52*O52*N52 -> 0 | R52: 0 | S52: =SUM(Q52:R52) -> 0 | T52: 0 | U52: =H52 -> 20000 | V52: 0 | W52: =V52*U52*T52 -> 0 | X52: 0 | Y52: =SUM(W52:X52) -> 0 | Z52: 0 | AA52: =H52 -> 20000 | AB52: 0 | AC52: =AB52*AA52*Z52 -> 0 | AD52: 0 | AE52: =SUM(AC52:AD52) -> 0 | AF52: 1 | AG52: =H52 -> 20000 | AH52: 1 | AI52: =AH52*AG52*AF52 -> 20000 | AJ52: 0 | AK52: =SUM(AI52:AJ52) -> 20000 | AL52: =K52+Q52+W52+AC52+AI52 -> 20000 | AM52: =L52+R52+X52+AD52+AJ52 -> 0 | AN52: =SUM(AL52:AM52) -> 20000
A53: EDUALLOW | B53: 50204 | C53: COL2 | D53: COL2 | E53: 0 | F53: Educational Allowance for Expatriate Chief of Party's Dependents | G53: 2 | H53: 800 | I53: 12 | J53: /month | K53: =I53*H53*G53 -> 19200 | L53: 0 | M53: =SUM(K53:L53) -> 19200 | N53: 2 | O53: =H53*$G$7 -> 824 | P53: =P25 -> 12 | Q53: =P53*O53*N53 -> 19776 | R53: 0 | S53: =SUM(Q53:R53) -> 19776 | T53: 2 | U53: =H53*$G$7*$G$7 -> 848.72 | V53: 12 | W53: =V53*U53*T53 -> 20369.28 | X53: 0 | Y53: =SUM(W53:X53) -> 20369.28 | Z53: 2 | AA53: =H53*$G$7*$G$7*$G$7 -> 874.1816 | AB53: 12 | AC53: =AB53*AA53*Z53 -> 20980.358 | AD53: 0 | AE53: =SUM(AC53:AD53) -> 20980.358 | AF53: 2 | AG53: =H53*$G$7*$G$7*$G$7*$G$7 -> 900.40705 | AH53: 12 | AI53: =AH53*AG53*AF53 -> 21609.769 | AJ53: 0 | AK53: =SUM(AI53:AJ53) -> 21609.769 | AL53: =K53+Q53+W53+AC53+AI53 -> 101935.41 | AM53: =L53+R53+X53+AD53+AJ53 -> 0 | AN53: =SUM(AL53:AM53) -> 101935.41
A54: R&RTRIP | B54: 50206 | C54: COL2 | D54: COL2 | E54: 0 | F54: R&R for Expatriate Chief of Party | G54: 0 | H54: 350 | I54: 1 | J54: /yearly | K54: =I54*H54*G54 -> 0 | L54: 0 | M54: =SUM(K54:L54) -> 0 | N54: 4 | O54: =H54*$G$6 -> 355.25 | P54: 1 | Q54: =P54*O54*N54 -> 1421 | R54: 0 | S54: =SUM(Q54:R54) -> 1421 | T54: 0 | U54: =H54*$G$6*$G$6 -> 360.57875 | V54: 1 | W54: =V54*U54*T54 -> 0 | X54: 0 | Y54: =SUM(W54:X54) -> 0 | Z54: 4 | AA54: =H54*$G$6*$G$6*$G$6 -> 365.98743 | AB54: 1 | AC54: =AB54*AA54*Z54 -> 1463.9497 | AD54: 0 | AE54: =SUM(AC54:AD54) -> 1463.9497 | AF54: 0 | AG54: =H54*$G$6*$G$6*$G$6*$G$6 -> 371.47724 | AH54: 1 | AI54: =AH54*AG54*AF54 -> 0 | AJ54: 0 | AK54: =SUM(AI54:AJ54) -> 0 | AL54: =K54+Q54+W54+AC54+AI54 -> 2884.9497 | AM54: =L54+R54+X54+AD54+AJ54 -> 0 | AN54: =SUM(AL54:AM54) -> 2884.9497
F55: Subtotal Field Fringe Benefits | K55: =SUM(K47:K54) -> 320795.39 | L55: =SUM(L47:L54) -> 0 | M55: =SUM(M47:M54) -> 320795.39 | Q55: =SUM(Q47:Q54) -> 351441.18 | R55: =SUM(R47:R54) -> 0 | S55: =SUM(S47:S54) -> 351441.18 | W55: =SUM(W47:W54) -> 363477.15 | X55: =SUM(X47:X54) -> 0 | Y55: =SUM(Y47:Y54) -> 363477.15 | AC55: =SUM(AC47:AC54) -> 378920.03 | AD55: =SUM(AD47:AD54) -> 0 | AE55: =SUM(AE47:AE54) -> 378920.03 | AI55: =SUM(AI47:AI54) -> 385023.88 | AJ55: =SUM(AJ47:AJ54) -> 0 | AK55: =SUM(AK47:AK54) -> 385023.88 | AL55: =SUM(AL47:AL54) -> 1799657.6 | AM55: =SUM(AM47:AM54) -> 0 | AN55: =SUM(AN47:AN54) -> 1799657.6
F57: Fringe Benefits Total | K57: =K55+K44 -> 387758.33 | L57: =L55+L44 -> 0 | M57: =M55+M44 -> 387758.33 | Q57: =Q55+Q44 -> 421082.64 | R57: =R55+R44 -> 0 | S57: =S55+S44 -> 421082.64 | W57: =W55+W44 -> 435904.26 | X57: =X55+X44 -> 0 | Y57: =Y55+Y44 -> 435904.26 | AC57: =AC55+AC44 -> 454244.23 | AD57: =AD55+AD44 -> 0 | AE57: =AE55+AE44 -> 454244.23 | AI57: =AI55+AI44 -> 463361.04 | AJ57: =AJ55+AJ44 -> 0 | AK57: =AK55+AK44 -> 463361.04 | AL57: =AL55+AL44 -> 2162350.5 | AM57: =AM55+AM44 -> 0 | AN57: =AN55+AN44 -> 2162350.5
F59: Travel
F61: HQ Travel
F62: T.1 Project Management Travel to Field
A63: T1AIRFARE | B63: 86040 | C63: USA | D63: USA | E63: 0 | F63: International Airfare to Colombia | G63: 3 | H63: 750 | I63: 1 | J63: /trip | K63: =I63*H63*G63 -> 2250 | L63: 0 | M63: =SUM(K63:L63) -> 2250 | N63: 7 | O63: =H63*$G$6 -> 761.25 | P63: 1 | Q63: =N63*O63*P63 -> 5328.75 | R63: 0 | S63: =SUM(Q63:R63) -> 5328.75 | T63: 7 | U63: =H63*$G$6*$G$6 -> 772.66875 | V63: 1 | W63: =T63*U63*V63 -> 5408.6812 | X63: 0 | Y63: =SUM(W63:X63) -> 5408.6812 | Z63: 7 | AA63: =H63*$G$6*$G$6*$G$6 -> 784.25878 | AB63: 1 | AC63: =Z63*AA63*AB63 -> 5489.8115 | AD63: 0 | AE63: =SUM(AC63:AD63) -> 5489.8115 | AF63: 5 | AG63: =H63*$G$6*$G$6*$G$6*$G$6 -> 796.02266 | AH63: 1 | AI63: =AF63*AG63*AH63 -> 3980.1133 | AJ63: 0 | AK63: =SUM(AI63:AJ63) -> 3980.1133 | AL63: =K63+Q63+W63+AC63+AI63 -> 22457.356 | AM63: =L63+R63+X63+AD63+AJ63 -> 0 | AN63: =SUM(AL63:AM63) -> 22457.356
A64: T1M&E | B64: 86050 | C64: USA | D64: USA | E64: 0 | F64: Meals and Incidentals | G64: =$G$63 -> 3 | H64: 90 | I64: 10 | J64: /day | K64: =I64*H64*G64 -> 2700 | L64: 0 | M64: =SUM(K64:L64) -> 2700 | N64: =$N$63 -> 7 | O64: =H64*$G$6 -> 91.35 | P64: 10 | Q64: =N64*O64*P64 -> 6394.5 | R64: 0 | S64: =SUM(Q64:R64) -> 6394.5 | T64: =$T$63 -> 7 | U64: =H64*$G$6*$G$6 -> 92.72025 | V64: 10 | W64: =T64*U64*V64 -> 6490.4175 | X64: 0 | Y64: =SUM(W64:X64) -> 6490.4175 | Z64: =$Z$63 -> 7 | AA64: =H64*$G$6*$G$6*$G$6 -> 94.111054 | AB64: 10 | AC64: =Z64*AA64*AB64 -> 6587.7738 | AD64: 0 | AE64: =SUM(AC64:AD64) -> 6587.7738 | AF64: =$AF$63 -> 5 | AG64: =H64*$G$6*$G$6*$G$6*$G$6 -> 95.52272 | AH64: 10 | AI64: =AF64*AG64*AH64 -> 4776.136 | AJ64: 0 | AK64: =SUM(AI64:AJ64) -> 4776.136 | AL64: =K64+Q64+W64+AC64+AI64 -> 26948.827 | AM64: =L64+R64+X64+AD64+AJ64 -> 0 | AN64: =SUM(AL64:AM64) -> 26948.827
A65: T1LODGING | B65: 86030 | C65: USA | D65: USA | E65: 0 | F65: Lodging | G65: =$G$63 -> 3 | H65: 120 | I65: 10 | J65: /day | K65: =I65*H65*G65 -> 3600 | L65: 0 | M65: =SUM(K65:L65) -> 3600 | N65: =$N$63 -> 7 | O65: =H65*$G$6 -> 121.8 | P65: 10 | Q65: =N65*O65*P65 -> 8526 | R65: 0 | S65: =SUM(Q65:R65) -> 8526 | T65: =$T$63 -> 7 | U65: =H65*$G$6*$G$6 -> 123.627 | V65: 10 | W65: =T65*U65*V65 -> 8653.89 | X65: 0 | Y65: =SUM(W65:X65) -> 8653.89 | Z65: =$Z$63 -> 7 | AA65: =H65*$G$6*$G$6*$G$6 -> 125.4814 | AB65: 10 | AC65: =Z65*AA65*AB65 -> 8783.6983 | AD65: 0 | AE65: =SUM(AC65:AD65) -> 8783.6983 | AF65: =$AF$63 -> 5 | AG65: =H65*$G$6*$G$6*$G$6*$G$6 -> 127.36363 | AH65: 10 | AI65: =AF65*AG65*AH65 -> 6368.1813 | AJ65: 0 | AK65: =SUM(AI65:AJ65) -> 6368.1813 | AL65: =K65+Q65+W65+AC65+AI65 -> 35931.77 | AM65: =L65+R65+X65+AD65+AJ65 -> 0 | AN65: =SUM(AL65:AM65) -> 35931.77
A66: T1LOCALTRA | B66: 86000 | C66: USA | D66: USA | E66: 0 | F66: Local Transportation | G66: =$G$63 -> 3 | H66: 25 | I66: 10 | J66: /day | K66: =I66*H66*G66 -> 750 | L66: 0 | M66: =SUM(K66:L66) -> 750 | N66: =$N$63 -> 7 | O66: =H66*$G$6 -> 25.375 | P66: 10 | Q66: =N66*O66*P66 -> 1776.25 | R66: 0 | S66: =SUM(Q66:R66) -> 1776.25 | T66: =$T$63 -> 7 | U66: =H66*$G$6*$G$6 -> 25.755625 | V66: 10 | W66: =T66*U66*V66 -> 1802.8937 | X66: 0 | Y66: =SUM(W66:X66) -> 1802.8937 | Z66: =$Z$63 -> 7 | AA66: =H66*$G$6*$G$6*$G$6 -> 26.141959 | AB66: 10 | AC66: =Z66*AA66*AB66 -> 1829.9372 | AD66: 0 | AE66: =SUM(AC66:AD66) -> 1829.9372 | AF66: =$AF$63 -> 5 | AG66: =H66*$G$6*$G$6*$G$6*$G$6 -> 26.534089 | AH66: 10 | AI66: =AF66*AG66*AH66 -> 1326.7044 | AJ66: 0 | AK66: =SUM(AI66:AJ66) -> 1326.7044 | AL66: =K66+Q66+W66+AC66+AI66 -> 7485.7853 | AM66: =L66+R66+X66+AD66+AJ66 -> 0 | AN66: =SUM(AL66:AM66) -> 7485.7853
A67: T1OTHEREX | B67: 86050 | C67: USA | D67: USA | E67: 0 | F67: Other Travel Related Expenses | G67: =$G$63 -> 3 | H67: 50 | I67: 1 | J67: /trip | K67: =I67*H67*G67 -> 150 | L67: 0 | M67: =SUM(K67:L67) -> 150 | N67: =$N$63 -> 7 | O67: =H67*$G$6 -> 50.75 | P67: 1 | Q67: =N67*O67*P67 -> 355.25 | R67: 0 | S67: =SUM(Q67:R67) -> 355.25 | T67: =$T$63 -> 7 | U67: =H67*$G$6*$G$6 -> 51.51125 | V67: 1 | W67: =T67*U67*V67 -> 360.57875 | X67: 0 | Y67: =SUM(W67:X67) -> 360.57875 | Z67: =$Z$63 -> 7 | AA67: =H67*$G$6*$G$6*$G$6 -> 52.283919 | AB67: 1 | AC67: =Z67*AA67*AB67 -> 365.98743 | AD67: 0 | AE67: =SUM(AC67:AD67) -> 365.98743 | AF67: =$AF$63 -> 5 | AG67: =H67*$G$6*$G$6*$G$6*$G$6 -> 53.068178 | AH67: 1 | AI67: =AF67*AG67*AH67 -> 265.34089 | AJ67: 0 | AK67: =SUM(AI67:AJ67) -> 265.34089 | AL67: =K67+Q67+W67+AC67+AI67 -> 1497.1571 | AM67: =L67+R67+X67+AD67+AJ67 -> 0 | AN67: =SUM(AL67:AM67) -> 1497.1571
F68: Subtotal HQ Travel | K68: =SUM(K63:K67) -> 9450 | L68: =SUM(L63:L67) -> 0 | M68: =SUM(M63:M67) -> 9450 | Q68: =SUM(Q63:Q67) -> 22380.75 | R68: =SUM(R63:R67) -> 0 | S68: =SUM(S63:S67) -> 22380.75 | W68: =SUM(W63:W67) -> 22716.461 | X68: =SUM(X63:X67) -> 0 | Y68: =SUM(Y63:Y67) -> 22716.461 | AC68: =SUM(AC63:AC67) -> 23057.208 | AD68: =SUM(AD63:AD67) -> 0 | AE68: =SUM(AE63:AE67) -> 23057.208 | AI68: =SUM(AI63:AI67) -> 16716.476 | AJ68: =SUM(AJ63:AJ67) -> 0 | AK68: =SUM(AK63:AK67) -> 16716.476 | AL68: =SUM(AL63:AL67) -> 94320.895 | AM68: =SUM(AM63:AM67) -> 0 | AN68: =SUM(AN63:AN67) -> 94320.895
F70: Field Travel
F71: T.2 Colombia Staff Local Travel for M&E, Training, Mentoring, and Capacity Building
A72: T2LOCALTRA | B72: 86000 (Ground Transport)/ 86040 (Airfare) | C72: COL2 | D72: COL2 | E72: 0 | F72: Local Transportation (Airfare, Taxis, & Rental Car/Driver) | G72: =(2*9)*2 -> 36 | H72: 250 | I72: 1 | J72: /trip | K72: =I72*H72*G72 -> 9000 | L72: 0 | M72: =SUM(K72:L72) -> 9000 | N72: =(9*4)*2 -> 72 | O72: =H72*$G$7 -> 257.5 | P72: 1 | Q72: =N72*O72*P72 -> 18540 | R72: 0 | S72: =SUM(Q72:R72) -> 18540 | T72: =(9*4)*2 -> 72 | U72: =H72*$G$7*$G$7 -> 265.225 | V72: 1 | W72: =T72*U72*V72 -> 19096.2 | X72: 0 | Y72: =SUM(W72:X72) -> 19096.2 | Z72: =(9*4)*2 -> 72 | AA72: =H72*$G$7*$G$7*$G$7 -> 273.18175 | AB72: 1 | AC72: =Z72*AA72*AB72 -> 19669.086 | AD72: 0 | AE72: =SUM(AC72:AD72) -> 19669.086 | AF72: =(2*9)*2 -> 36 | AG72: =H72*$G$7*$G$7*$G$7*$G$7 -> 281.3772 | AH72: 1 | AI72: =AF72*AG72*AH72 -> 10129.579 | AJ72: 0 | AK72: =SUM(AI72:AJ72) -> 10129.579 | AL72: =K72+Q72+W72+AC72+AI72 -> 76434.865 | AM72: =L72+R72+X72+AD72+AJ72 -> 0 | AN72: =SUM(AL72:AM72) -> 76434.865
A73: T2M&E | B73: 86050 | C73: COL2 | D73: COL2 | E73: 0 | F73: Meals and Incidentals | G73: =$G$72 -> 36 | H73: 40 | I73: 5 | J73: /day | K73: =I73*H73*G73 -> 7200 | L73: 0 | M73: =SUM(K73:L73) -> 7200 | N73: =$N$72 -> 72 | O73: =H73*$G$7 -> 41.2 | P73: 5 | Q73: =N73*O73*P73 -> 14832 | R73: 0 | S73: =SUM(Q73:R73) -> 14832 | T73: =$T$72 -> 72 | U73: =H73*$G$7*$G$7 -> 42.436 | V73: 5 | W73: =T73*U73*V73 -> 15276.96 | X73: 0 | Y73: =SUM(W73:X73) -> 15276.96 | Z73: =$Z$72 -> 72 | AA73: =H73*$G$7*$G$7*$G$7 -> 43.70908 | AB73: 5 | AC73: =Z73*AA73*AB73 -> 15735.269 | AD73: 0 | AE73: =SUM(AC73:AD73) -> 15735.269 | AF73: =$AF$72 -> 36 | AG73: =H73*$G$7*$G$7*$G$7*$G$7 -> 45.020352 | AH73: 5 | AI73: =AF73*AG73*AH73 -> 8103.6634 | AJ73: 0 | AK73: =SUM(AI73:AJ73) -> 8103.6634 | AL73: =K73+Q73+W73+AC73+AI73 -> 61147.892 | AM73: =L73+R73+X73+AD73+AJ73 -> 0 | AN73: =SUM(AL73:AM73) -> 61147.892
A74: T2LODGING | B74: 86000 | C74: COL2 | D74: COL2 | E74: 0 | F74: Lodging | G74: =$G$72 -> 36 | H74: 80 | I74: 5 | J74: /day | K74: =I74*H74*G74 -> 14400 | L74: 0 | M74: =SUM(K74:L74) -> 14400 | N74: =$N$72 -> 72 | O74: =H74*$G$7 -> 82.4 | P74: 5 | Q74: =N74*O74*P74 -> 29664 | R74: 0 | S74: =SUM(Q74:R74) -> 29664 | T74: =$T$72 -> 72 | U74: =H74*$G$7*$G$7 -> 84.872 | V74: 5 | W74: =T74*U74*V74 -> 30553.92 | X74: 0 | Y74: =SUM(W74:X74) -> 30553.92 | Z74: =$Z$72 -> 72 | AA74: =H74*$G$7*$G$7*$G$7 -> 87.41816 | AB74: 5 | AC74: =Z74*AA74*AB74 -> 31470.538 | AD74: 0 | AE74: =SUM(AC74:AD74) -> 31470.538 | AF74: =$AF$72 -> 36 | AG74: =H74*$G$7*$G$7*$G$7*$G$7 -> 90.040705 | AH74: 5 | AI74: =AF74*AG74*AH74 -> 16207.327 | AJ74: 0 | AK74: =SUM(AI74:AJ74) -> 16207.327 | AL74: =K74+Q74+W74+AC74+AI74 -> 122295.78 | AM74: =L74+R74+X74+AD74+AJ74 -> 0 | AN74: =SUM(AL74:AM74) -> 122295.78
A75: T2OTHEREX | B75: 86050 | C75: COL2 | D75: COL2 | E75: 0 | F75: Other Travel Related Expenses | G75: =$G$72 -> 36 | H75: 25 | I75: 1 | J75: /trip | K75: =I75*H75*G75 -> 900 | L75: 0 | M75: =SUM(K75:L75) -> 900 | N75: =$N$72 -> 72 | O75: =H75*$G$7 -> 25.75 | P75: 1 | Q75: =N75*O75*P75 -> 1854 | R75: 0 | S75: =SUM(Q75:R75) -> 1854 | T75: =$T$72 -> 72 | U75: =H75*$G$7*$G$7 -> 26.5225 | V75: 1 | W75: =T75*U75*V75 -> 1909.62 | X75: 0 | Y75: =SUM(W75:X75) -> 1909.62 | Z75: =$Z$72 -> 72 | AA75: =H75*$G$7*$G$7*$G$7 -> 27.318175 | AB75: 1 | AC75: =Z75*AA75*AB75 -> 1966.9086 | AD75: 0 | AE75: =SUM(AC75:AD75) -> 1966.9086 | AF75: =$AF$72 -> 36 | AG75: =H75*$G$7*$G$7*$G$7*$G$7 -> 28.13772 | AH75: 1 | AI75: =AF75*AG75*AH75 -> 1012.9579 | AJ75: 0 | AK75: =SUM(AI75:AJ75) -> 1012.9579 | AL75: =K75+Q75+W75+AC75+AI75 -> 7643.4865 | AM75: =L75+R75+X75+AD75+AJ75 -> 0 | AN75: =SUM(AL75:AM75) -> 7643.4865
F77: T.3 Colombia Staff Local Travel for Compliance & Finance Training
A78: T3LOCALTRA | B78: 86000 (Ground Transport)/ 86040 (Airfare) | C78: COL2 | D78: COL2 | E78: 0 | F78: Local Transportation (Airfare, Taxis, & Rental Car/Driver) | G78: =2*3 -> 6 | H78: 250 | I78: 1 | J78: /trip | K78: =I78*H78*G78 -> 1500 | L78: 0 | M78: =SUM(K78:L78) -> 1500 | N78: =2*(3*2) -> 12 | O78: =H78*$G$7 -> 257.5 | P78: 1 | Q78: =N78*O78*P78 -> 3090 | R78: 0 | S78: =SUM(Q78:R78) -> 3090 | T78: =2*(3*2) -> 12 | U78: =H78*$G$7*$G$7 -> 265.225 | V78: 1 | W78: =T78*U78*V78 -> 3182.7 | X78: 0 | Y78: =SUM(W78:X78) -> 3182.7 | Z78: =2*(3*2) -> 12 | AA78: =H78*$G$7*$G$7*$G$7 -> 273.18175 | AB78: 1 | AC78: =Z78*AA78*AB78 -> 3278.181 | AD78: 0 | AE78: =SUM(AC78:AD78) -> 3278.181 | AF78: =2*3 -> 6 | AG78: =H78*$G$7*$G$7*$G$7*$G$7 -> 281.3772 | AH78: 1 | AI78: =AF78*AG78*AH78 -> 1688.2632 | AJ78: 0 | AK78: =SUM(AI78:AJ78) -> 1688.2632 | AL78: =K78+Q78+W78+AC78+AI78 -> 12739.144 | AM78: =L78+R78+X78+AD78+AJ78 -> 0 | AN78: =SUM(AL78:AM78) -> 12739.144
A79: T3M&E | B79: 86050 | C79: COL2 | D79: COL2 | E79: 0 | F79: Meals and Incidentals | G79: =$G$78 -> 6 | H79: 40 | I79: 5 | J79: /day | K79: =I79*H79*G79 -> 1200 | L79: 0 | M79: =SUM(K79:L79) -> 1200 | N79: =$N$78 -> 12 | O79: =H79*$G$7 -> 41.2 | P79: 5 | Q79: =N79*O79*P79 -> 2472 | R79: 0 | S79: =SUM(Q79:R79) -> 2472 | T79: =$T$78 -> 12 | U79: =H79*$G$7*$G$7 -> 42.436 | V79: 5 | W79: =T79*U79*V79 -> 2546.16 | X79: 0 | Y79: =SUM(W79:X79) -> 2546.16 | Z79: =$Z$78 -> 12 | AA79: =H79*$G$7*$G$7*$G$7 -> 43.70908 | AB79: 5 | AC79: =Z79*AA79*AB79 -> 2622.5448 | AD79: 0 | AE79: =SUM(AC79:AD79) -> 2622.5448 | AF79: =$AF$78 -> 6 | AG79: =H79*$G$7*$G$7*$G$7*$G$7 -> 45.020352 | AH79: 5 | AI79: =AF79*AG79*AH79 -> 1350.6106 | AJ79: 0 | AK79: =SUM(AI79:AJ79) -> 1350.6106 | AL79: =K79+Q79+W79+AC79+AI79 -> 10191.315 | AM79: =L79+R79+X79+AD79+AJ79 -> 0 | AN79: =SUM(AL79:AM79) -> 10191.315
A80: T3LODGING | B80: 86000 | C80: COL2 | D80: COL2 | E80: 0 | F80: Lodging | G80: =$G$78 -> 6 | H80: 80 | I80: 5 | J80: /day | K80: =I80*H80*G80 -> 2400 | L80: 0 | M80: =SUM(K80:L80) -> 2400 | N80: =$N$78 -> 12 | O80: =H80*$G$7 -> 82.4 | P80: 5 | Q80: =N80*O80*P80 -> 4944 | R80: 0 | S80: =SUM(Q80:R80) -> 4944 | T80: =$T$78 -> 12 | U80: =H80*$G$7*$G$7 -> 84.872 | V80: 5 | W80: =T80*U80*V80 -> 5092.32 | X80: 0 | Y80: =SUM(W80:X80) -> 5092.32 | Z80: =$Z$78 -> 12 | AA80: =H80*$G$7*$G$7*$G$7 -> 87.41816 | AB80: 5 | AC80: =Z80*AA80*AB80 -> 5245.0896 | AD80: 0 | AE80: =SUM(AC80:AD80) -> 5245.0896 | AF80: =$AF$78 -> 6 | AG80: =H80*$G$7*$G$7*$G$7*$G$7 -> 90.040705 | AH80: 5 | AI80: =AF80*AG80*AH80 -> 2701.2211 | AJ80: 0 | AK80: =SUM(AI80:AJ80) -> 2701.2211 | AL80: =K80+Q80+W80+AC80+AI80 -> 20382.631 | AM80: =L80+R80+X80+AD80+AJ80 -> 0 | AN80: =SUM(AL80:AM80) -> 20382.631
A81: T3OTHEREX | B81: 86050 | C81: COL2 | D81: COL2 | E81: 0 | F81: Other Travel Related Expenses | G81: =$G$78 -> 6 | H81: 25 | I81: 1 | J81: /trip | K81: =I81*H81*G81 -> 150 | L81: 0 | M81: =SUM(K81:L81) -> 150 | N81: =$N$78 -> 12 | O81: =H81*$G$7 -> 25.75 | P81: 1 | Q81: =N81*O81*P81 -> 309 | R81: 0 | S81: =SUM(Q81:R81) -> 309 | T81: =$T$78 -> 12 | U81: =H81*$G$7*$G$7 -> 26.5225 | V81: 1 | W81: =T81*U81*V81 -> 318.27 | X81: 0 | Y81: =SUM(W81:X81) -> 318.27 | Z81: =$Z$78 -> 12 | AA81: =H81*$G$7*$G$7*$G$7 -> 27.318175 | AB81: 1 | AC81: =Z81*AA81*AB81 -> 327.8181 | AD81: 0 | AE81: =SUM(AC81:AD81) -> 327.8181 | AF81: =$AF$78 -> 6 | AG81: =H81*$G$7*$G$7*$G$7*$G$7 -> 28.13772 | AH81: 1 | AI81: =AF81*AG81*AH81 -> 168.82632 | AJ81: 0 | AK81: =SUM(AI81:AJ81) -> 168.82632 | AL81: =K81+Q81+W81+AC81+AI81 -> 1273.9144 | AM81: =L81+R81+X81+AD81+AJ81 -> 0 | AN81: =SUM(AL81:AM81) -> 1273.9144
F83: T.4 Local Travel in Bogota for Field Staff
A84: T4VEHICLE | B84: 86000 | C84: COL2 | D84: COL2 | E84: 0 | F84: Vehicle Fuel Expense - 3 Vehicles | G84: 3 | H84: 300 | I84: 6 | J84: /month | K84: =I84*H84*G84 -> 5400 | L84: 0 | M84: =SUM(K84:L84) -> 5400 | N84: 3 | O84: =H84*$G$7 -> 309 | P84: 12 | Q84: =N84*O84*P84 -> 11124 | R84: 0 | S84: =SUM(Q84:R84) -> 11124 | T84: 3 | U84: =H84*$G$7*$G$7 -> 318.27 | V84: 12 | W84: =T84*U84*V84 -> 11457.72 | X84: 0 | Y84: =SUM(W84:X84) -> 11457.72 | Z84: 3 | AA84: =H84*$G$7*$G$7*$G$7 -> 327.8181 | AB84: 12 | AC84: =Z84*AA84*AB84 -> 11801.452 | AD84: 0 | AE84: =SUM(AC84:AD84) -> 11801.452 | AF84: 3 | AG84: =H84*$G$7*$G$7*$G$7*$G$7 -> 337.65264 | AH84: 9 | AI84: =AF84*AG84*AH84 -> 9116.6214 | AJ84: 0 | AK84: =SUM(AI84:AJ84) -> 9116.6214 | AL84: =K84+Q84+W84+AC84+AI84 -> 48899.793 | AM84: =L84+R84+X84+AD84+AJ84 -> 0 | AN84: =SUM(AL84:AM84) -> 48899.793
F86: T.5 Travel for Advisory Board Meetings - 2 Annually
A87: T5LOCALTRA | B87: 86000 (Ground Transport)/ 86040 (Airfare) | C87: COL2 | D87: COL2 | E87: 0 | F87: Local Transportation for Field Staff | G87: 5 | H87: 80 | I87: 1 | J87: /trip | K87: =I87*H87*G87 -> 400 | L87: 0 | M87: =SUM(K87:L87) -> 400 | N87: 5 | O87: =H87*$G$7 -> 82.4 | P87: 1 | Q87: =N87*O87*P87 -> 412 | R87: 0 | S87: =SUM(Q87:R87) -> 412 | T87: 5 | U87: =H87*$G$7*$G$7 -> 84.872 | V87: 1 | W87: =T87*U87*V87 -> 424.36 | X87: 0 | Y87: =SUM(W87:X87) -> 424.36 | Z87: 5 | AA87: =H87*$G$7*$G$7*$G$7 -> 87.41816 | AB87: 1 | AC87: =Z87*AA87*AB87 -> 437.0908 | AD87: 0 | AE87: =SUM(AC87:AD87) -> 437.0908 | AF87: 5 | AG87: =H87*$G$7*$G$7*$G$7*$G$7 -> 90.040705 | AH87: 1 | AI87: =AF87*AG87*AH87 -> 450.20352 | AJ87: 0 | AK87: =SUM(AI87:AJ87) -> 450.20352 | AL87: =K87+Q87+W87+AC87+AI87 -> 2123.6543 | AM87: =L87+R87+X87+AD87+AJ87 -> 0 | AN87: =SUM(AL87:AM87) -> 2123.6543
A88: T5M&E | B88: 86050 | C88: COL2 | D88: COL2 | E88: 0 | F88: Meals and Incidentals for Field Staff | G88: =$G$87 -> 5 | H88: 40 | I88: 2 | J88: /day | K88: =I88*H88*G88 -> 400 | L88: 0 | M88: =SUM(K88:L88) -> 400 | N88: =$N$87 -> 5 | O88: =H88*$G$7 -> 41.2 | P88: 2 | Q88: =N88*O88*P88 -> 412 | R88: 0 | S88: =SUM(Q88:R88) -> 412 | T88: =$T$87 -> 5 | U88: =H88*$G$7*$G$7 -> 42.436 | V88: 2 | W88: =T88*U88*V88 -> 424.36 | X88: 0 | Y88: =SUM(W88:X88) -> 424.36 | Z88: =$Z$87 -> 5 | AA88: =H88*$G$7*$G$7*$G$7 -> 43.70908 | AB88: 2 | AC88: =Z88*AA88*AB88 -> 437.0908 | AD88: 0 | AE88: =SUM(AC88:AD88) -> 437.0908 | AF88: =$AF$87 -> 5 | AG88: =H88*$G$7*$G$7*$G$7*$G$7 -> 45.020352 | AH88: 2 | AI88: =AF88*AG88*AH88 -> 450.20352 | AJ88: 0 | AK88: =SUM(AI88:AJ88) -> 450.20352 | AL88: =K88+Q88+W88+AC88+AI88 -> 2123.6543 | AM88: =L88+R88+X88+AD88+AJ88 -> 0 | AN88: =SUM(AL88:AM88) -> 2123.6543
A89: T5LODGING | B89: 86000 | C89: COL2 | D89: COL2 | E89: 0 | F89: Lodging for Field Staff | G89: =$G$87 -> 5 | H89: 80 | I89: 2 | J89: /day | K89: =I89*H89*G89 -> 800 | L89: 0 | M89: =SUM(K89:L89) -> 800 | N89: =$N$87 -> 5 | O89: =H89*$G$7 -> 82.4 | P89: 2 | Q89: =N89*O89*P89 -> 824 | R89: 0 | S89: =SUM(Q89:R89) -> 824 | T89: =$T$87 -> 5 | U89: =H89*$G$7*$G$7 -> 84.872 | V89: 2 | W89: =T89*U89*V89 -> 848.72 | X89: 0 | Y89: =SUM(W89:X89) -> 848.72 | Z89: =$Z$87 -> 5 | AA89: =H89*$G$7*$G$7*$G$7 -> 87.41816 | AB89: 2 | AC89: =Z89*AA89*AB89 -> 874.1816 | AD89: 0 | AE89: =SUM(AC89:AD89) -> 874.1816 | AF89: =$AF$87 -> 5 | AG89: =H89*$G$7*$G$7*$G$7*$G$7 -> 90.040705 | AH89: 2 | AI89: =AF89*AG89*AH89 -> 900.40705 | AJ89: 0 | AK89: =SUM(AI89:AJ89) -> 900.40705 | AL89: =K89+Q89+W89+AC89+AI89 -> 4247.3086 | AM89: =L89+R89+X89+AD89+AJ89 -> 0 | AN89: =SUM(AL89:AM89) -> 4247.3086
A90: T5OTHEREX | B90: 86050 | C90: COL2 | D90: COL2 | E90: 0 | F90: Other Travel Related Expenses for Field Staff | G90: =$G$87 -> 5 | H90: 25 | I90: 1 | J90: /trip | K90: =I90*H90*G90 -> 125 | L90: 0 | M90: =SUM(K90:L90) -> 125 | N90: =$N$87 -> 5 | O90: =H90*$G$7 -> 25.75 | P90: 1 | Q90: =N90*O90*P90 -> 128.75 | R90: 0 | S90: =SUM(Q90:R90) -> 128.75 | T90: =$T$87 -> 5 | U90: =H90*$G$7*$G$7 -> 26.5225 | V90: 1 | W90: =T90*U90*V90 -> 132.6125 | X90: 0 | Y90: =SUM(W90:X90) -> 132.6125 | Z90: =$Z$87 -> 5 | AA90: =H90*$G$7*$G$7*$G$7 -> 27.318175 | AB90: 1 | AC90: =Z90*AA90*AB90 -> 136.59088 | AD90: 0 | AE90: =SUM(AC90:AD90) -> 136.59088 | AF90: =$AF$87 -> 5 | AG90: =H90*$G$7*$G$7*$G$7*$G$7 -> 28.13772 | AH90: 1 | AI90: =AF90*AG90*AH90 -> 140.6886 | AJ90: 0 | AK90: =SUM(AI90:AJ90) -> 140.6886 | AL90: =K90+Q90+W90+AC90+AI90 -> 663.64198 | AM90: =L90+R90+X90+AD90+AJ90 -> 0 | AN90: =SUM(AL90:AM90) -> 663.64198
F92: T.6 Travel for Annual Forums for Education Observatories
A93: T6LOCALTRA | B93: 86000 (Ground Transport)/ 86040 (Airfare) | C93: COL2 | D93: COL2 | E93: 0 | F93: Local Transportation for Field Staff | G93: 5 | H93: 50 | I93: 1 | J93: /trip | K93: =I93*H93*G93 -> 250 | L93: 0 | M93: =SUM(K93:L93) -> 250 | N93: 0 | O93: =H93*$G$7 -> 51.5 | P93: 1 | Q93: =N93*O93*P93 -> 0 | R93: 0 | S93: =SUM(Q93:R93) -> 0 | T93: 5 | U93: =H93*$G$7*$G$7 -> 53.045 | V93: 1 | W93: =T93*U93*V93 -> 265.225 | X93: 0 | Y93: =SUM(W93:X93) -> 265.225 | Z93: 0 | AA93: =H93*$G$7*$G$7*$G$7 -> 54.63635 | AB93: 1 | AC93: =Z93*AA93*AB93 -> 0 | AD93: 0 | AE93: =SUM(AC93:AD93) -> 0 | AF93: 0 | AG93: =H93*$G$7*$G$7*$G$7*$G$7 -> 56.275441 | AH93: 1 | AI93: =AF93*AG93*AH93 -> 0 | AJ93: 0 | AK93: =SUM(AI93:AJ93) -> 0 | AL93: =K93+Q93+W93+AC93+AI93 -> 515.225 | AM93: =L93+R93+X93+AD93+AJ93 -> 0 | AN93: =SUM(AL93:AM93) -> 515.225
A94: T6M&E | B94: 86050 | C94: COL2 | D94: COL2 | E94: 0 | F94: Meals and Incidentals for Field Staff | G94: =$G$87 -> 5 | H94: 40 | I94: 2 | J94: /day | K94: =I94*H94*G94 -> 400 | L94: 0 | M94: =SUM(K94:L94) -> 400 | N94: 0 | O94: =H94*$G$7 -> 41.2 | P94: 2 | Q94: =N94*O94*P94 -> 0 | R94: 0 | S94: =SUM(Q94:R94) -> 0 | T94: =$T$87 -> 5 | U94: =H94*$G$7*$G$7 -> 42.436 | V94: 2 | W94: =T94*U94*V94 -> 424.36 | X94: 0 | Y94: =SUM(W94:X94) -> 424.36 | Z94: 0 | AA94: =H94*$G$7*$G$7*$G$7 -> 43.70908 | AB94: 2 | AC94: =Z94*AA94*AB94 -> 0 | AD94: 0 | AE94: =SUM(AC94:AD94) -> 0 | AF94: 0 | AG94: =H94*$G$7*$G$7*$G$7*$G$7 -> 45.020352 | AH94: 2 | AI94: =AF94*AG94*AH94 -> 0 | AJ94: 0 | AK94: =SUM(AI94:AJ94) -> 0 | AL94: =K94+Q94+W94+AC94+AI94 -> 824.36 | AM94: =L94+R94+X94+AD94+AJ94 -> 0 | AN94: =SUM(AL94:AM94) -> 824.36
A95: T6LODGING | B95: 86000 | C95: COL2 | D95: COL2 | E95: 0 | F95: Lodging for Field Staff | G95: =$G$87 -> 5 | H95: 80 | I95: 2 | J95: /day | K95: =I95*H95*G95 -> 800 | L95: 0 | M95: =SUM(K95:L95) -> 800 | N95: 0 | O95: =H95*$G$7 -> 82.4 | P95: 2 | Q95: =N95*O95*P95 -> 0 | R95: 0 | S95: =SUM(Q95:R95) -> 0 | T95: =$T$87 -> 5 | U95: =H95*$G$7*$G$7 -> 84.872 | V95: 2 | W95: =T95*U95*V95 -> 848.72 | X95: 0 | Y95: =SUM(W95:X95) -> 848.72 | Z95: 0 | AA95: =H95*$G$7*$G$7*$G$7 -> 87.41816 | AB95: 2 | AC95: =Z95*AA95*AB95 -> 0 | AD95: 0 | AE95: =SUM(AC95:AD95) -> 0 | AF95: 0 | AG95: =H95*$G$7*$G$7*$G$7*$G$7 -> 90.040705 | AH95: 2 | AI95: =AF95*AG95*AH95 -> 0 | AJ95: 0 | AK95: =SUM(AI95:AJ95) -> 0 | AL95: =K95+Q95+W95+AC95+AI95 -> 1648.72 | AM95: =L95+R95+X95+AD95+AJ95 -> 0 | AN95: =SUM(AL95:AM95) -> 1648.72
A96: T6OTHEREX | B96: 86050 | C96: COL2 | D96: COL2 | E96: 0 | F96: Other Travel Related Expenses for Field Staff | G96: =$G$87 -> 5 | H96: 25 | I96: 1 | J96: /trip | K96: =I96*H96*G96 -> 125 | L96: 0 | M96: =SUM(K96:L96) -> 125 | N96: 0 | O96: =H96*$G$7 -> 25.75 | P96: 1 | Q96: =N96*O96*P96 -> 0 | R96: 0 | S96: =SUM(Q96:R96) -> 0 | T96: =$T$87 -> 5 | U96: =H96*$G$7*$G$7 -> 26.5225 | V96: 1 | W96: =T96*U96*V96 -> 132.6125 | X96: 0 | Y96: =SUM(W96:X96) -> 132.6125 | Z96: 0 | AA96: =H96*$G$7*$G$7*$G$7 -> 27.318175 | AB96: 1 | AC96: =Z96*AA96*AB96 -> 0 | AD96: 0 | AE96: =SUM(AC96:AD96) -> 0 | AF96: 0 | AG96: =H96*$G$7*$G$7*$G$7*$G$7 -> 28.13772 | AH96: 1 | AI96: =AF96*AG96*AH96 -> 0 | AJ96: 0 | AK96: =SUM(AI96:AJ96) -> 0 | AL96: =K96+Q96+W96+AC96+AI96 -> 257.6125 | AM96: =L96+R96+X96+AD96+AJ96 -> 0 | AN96: =SUM(AL96:AM96) -> 257.6125
F98: T.7 Travel for Annual Community of Practice
A99: T7LOCALTRA | B99: 86000 (Ground Transport)/ 86040 (Airfare) | C99: COL2 | D99: COL2 | E99: 0 | F99: Local Transportation for Field Staff | G99: 3 | H99: 50 | I99: 1 | J99: /trip | K99: =I99*H99*G99 -> 150 | L99: 0 | M99: =SUM(K99:L99) -> 150 | N99: 0 | O99: =H99*$G$7 -> 51.5 | P99: 1 | Q99: =N99*O99*P99 -> 0 | R99: 0 | S99: =SUM(Q99:R99) -> 0 | T99: 3 | U99: =H99*$G$7*$G$7 -> 53.045 | V99: 1 | W99: =T99*U99*V99 -> 159.135 | X99: 0 | Y99: =SUM(W99:X99) -> 159.135 | Z99: 3 | AA99: =H99*$G$7*$G$7*$G$7 -> 54.63635 | AB99: 1 | AC99: =Z99*AA99*AB99 -> 163.90905 | AD99: 0 | AE99: =SUM(AC99:AD99) -> 163.90905 | AF99: 3 | AG99: =H99*$G$7*$G$7*$G$7*$G$7 -> 56.275441 | AH99: 1 | AI99: =AF99*AG99*AH99 -> 168.82632 | AJ99: 0 | AK99: =SUM(AI99:AJ99) -> 168.82632 | AL99: =K99+Q99+W99+AC99+AI99 -> 641.87037 | AM99: =L99+R99+X99+AD99+AJ99 -> 0 | AN99: =SUM(AL99:AM99) -> 641.87037
A100: T7M&E | B100: 86050 | C100: COL2 | D100: COL2 | E100: 0 | F100: Meals and Incidentals for Field Staff | G100: 3 | H100: 40 | I100: 2 | J100: /day | K100: =I100*H100*G100 -> 240 | L100: 0 | M100: =SUM(K100:L100) -> 240 | N100: 0 | O100: =H100*$G$7 -> 41.2 | P100: 2 | Q100: =N100*O100*P100 -> 0 | R100: 0 | S100: =SUM(Q100:R100) -> 0 | T100: 3 | U100: =H100*$G$7*$G$7 -> 42.436 | V100: 2 | W100: =T100*U100*V100 -> 254.616 | X100: 0 | Y100: =SUM(W100:X100) -> 254.616 | Z100: 3 | AA100: =H100*$G$7*$G$7*$G$7 -> 43.70908 | AB100: 2 | AC100: =Z100*AA100*AB100 -> 262.25448 | AD100: 0 | AE100: =SUM(AC100:AD100) -> 262.25448 | AF100: 3 | AG100: =H100*$G$7*$G$7*$G$7*$G$7 -> 45.020352 | AH100: 2 | AI100: =AF100*AG100*AH100 -> 270.12211 | AJ100: 0 | AK100: =SUM(AI100:AJ100) -> 270.12211 | AL100: =K100+Q100+W100+AC100+AI100 -> 1026.9926 | AM100: =L100+R100+X100+AD100+AJ100 -> 0 | AN100: =SUM(AL100:AM100) -> 1026.9926
A101: T7LODGING | B101: 86000 | C101: COL2 | D101: COL2 | E101: 0 | F101: Lodging for Field Staff | G101: 3 | H101: 80 | I101: 2 | J101: /day | K101: =I101*H101*G101 -> 480 | L101: 0 | M101: =SUM(K101:L101) -> 480 | N101: 0 | O101: =H101*$G$7 -> 82.4 | P101: 2 | Q101: =N101*O101*P101 -> 0 | R101: 0 | S101: =SUM(Q101:R101) -> 0 | T101: 3 | U101: =H101*$G$7*$G$7 -> 84.872 | V101: 2 | W101: =T101*U101*V101 -> 509.232 | X101: 0 | Y101: =SUM(W101:X101) -> 509.232 | Z101: 3 | AA101: =H101*$G$7*$G$7*$G$7 -> 87.41816 | AB101: 2 | AC101: =Z101*AA101*AB101 -> 524.50896 | AD101: 0 | AE101: =SUM(AC101:AD101) -> 524.50896 | AF101: 3 | AG101: =H101*$G$7*$G$7*$G$7*$G$7 -> 90.040705 | AH101: 2 | AI101: =AF101*AG101*AH101 -> 540.24423 | AJ101: 0 | AK101: =SUM(AI101:AJ101) -> 540.24423 | AL101: =K101+Q101+W101+AC101+AI101 -> 2053.9852 | AM101: =L101+R101+X101+AD101+AJ101 -> 0 | AN101: =SUM(AL101:AM101) -> 2053.9852
A102: T7OTHEREX | B102: 86050 | C102: COL2 | D102: COL2 | E102: 0 | F102: Other Travel Related Expenses for Field Staff | G102: 3 | H102: 25 | I102: 1 | J102: /trip | K102: =I102*H102*G102 -> 75 | L102: 0 | M102: =SUM(K102:L102) -> 75 | N102: 0 | O102: =H102*$G$7 -> 25.75 | P102: 1 | Q102: =N102*O102*P102 -> 0 | R102: 0 | S102: =SUM(Q102:R102) -> 0 | T102: 3 | U102: =H102*$G$7*$G$7 -> 26.5225 | V102: 1 | W102: =T102*U102*V102 -> 79.5675 | X102: 0 | Y102: =SUM(W102:X102) -> 79.5675 | Z102: 3 | AA102: =H102*$G$7*$G$7*$G$7 -> 27.318175 | AB102: 1 | AC102: =Z102*AA102*AB102 -> 81.954525 | AD102: 0 | AE102: =SUM(AC102:AD102) -> 81.954525 | AF102: 3 | AG102: =H102*$G$7*$G$7*$G$7*$G$7 -> 28.13772 | AH102: 1 | AI102: =AF102*AG102*AH102 -> 84.413161 | AJ102: 0 | AK102: =SUM(AI102:AJ102) -> 84.413161 | AL102: =K102+Q102+W102+AC102+AI102 -> 320.93519 | AM102: =L102+R102+X102+AD102+AJ102 -> 0 | AN102: =SUM(AL102:AM102) -> 320.93519
F104: Subtotal Field Travel | K104: =SUM(K71:K103) -> 46395 | L104: =SUM(L71:L103) -> 0 | M104: =SUM(M71:M103) -> 46395 | Q104: =SUM(Q71:Q103) -> 88605.75 | R104: =SUM(R71:R103) -> 0 | S104: =SUM(S71:S103) -> 88605.75 | W104: =SUM(W71:W103) -> 93937.391 | X104: =SUM(X71:X103) -> 0 | Y104: =SUM(Y71:Y103) -> 93937.391 | AC104: =SUM(AC71:AC103) -> 95034.467 | AD104: =SUM(AD71:AD103) -> 0 | AE104: =SUM(AE71:AE103) -> 95034.467 | AI104: =SUM(AI71:AI103) -> 53484.179 | AJ104: =SUM(AJ71:AJ103) -> 0 | AK104: =SUM(AK71:AK103) -> 53484.179 | AL104: =SUM(AL71:AL103) -> 377456.79 | AM104: =SUM(AM71:AM103) -> 0 | AN104: =SUM(AN71:AN103) -> 377456.79
F106: Travel Total | K106: =K104+K68 -> 55845 | L106: =L104+L68 -> 0 | M106: =M104+M68 -> 55845 | Q106: =Q104+Q68 -> 110986.5 | R106: =R104+R68 -> 0 | S106: =S104+S68 -> 110986.5 | W106: =W104+W68 -> 116653.85 | X106: =X104+X68 -> 0 | Y106: =Y104+Y68 -> 116653.85 | AC106: =AC104+AC68 -> 118091.68 | AD106: =AD104+AD68 -> 0 | AE106: =AE104+AE68 -> 118091.68 | AI106: =AI104+AI68 -> 70200.655 | AJ106: =AJ104+AJ68 -> 0 | AK106: =AK104+AK68 -> 70200.655 | AL106: =AL104+AL68 -> 471777.68 | AM106: =AM104+AM68 -> 0 | AN106: =AN104+AN68 -> 471777.68
F108: Equipment
A110: VEHICLE | B110: 85200 | C110: COL2 | D110: COL2 | E110: 0 | F110: Vehicle for Field Offices | G110: 3 | H110: 50000 | J110: /vehicle | K110: =H110*G110 -> 150000 | L110: 0 | M110: =SUM(K110:L110) -> 150000 | N110: 0 | O110: =H110 -> 50000 | Q110: =N110*O110 -> 0 | R110: 0 | S110: =SUM(Q110:R110) -> 0 | T110: 0 | U110: =H110 -> 50000 | W110: =U110*T110 -> 0 | X110: 0 | Y110: =SUM(W110:X110) -> 0 | Z110: 0 | AA110: =H110 -> 50000 | AC110: =Z110*AA110 -> 0 | AD110: 0 | AE110: =SUM(AC110:AD110) -> 0 | AF110: 0 | AG110: =H110 -> 50000 | AI110: =AG110*AF110 -> 0 | AJ110: 0 | AK110: =SUM(AI110:AJ110) -> 0 | AL110: =K110+Q110+W110+AC110+AI110 -> 150000 | AM110: =L110+R110+X110+AD110+AJ110 -> 0 | AN110: =SUM(AL110:AM110) -> 150000
F112: Equipment Total | K112: =SUM(K110:K111) -> 150000 | L112: =SUM(L110:L111) -> 0 | M112: =SUM(M110:M111) -> 150000 | Q112: =SUM(Q110:Q111) -> 0 | R112: =SUM(R110:R111) -> 0 | S112: =SUM(S110:S111) -> 0 | W112: =SUM(W110:W111) -> 0 | X112: =SUM(X110:X111) -> 0 | Y112: =SUM(Y110:Y111) -> 0 | AC112: =SUM(AC110:AC111) -> 0 | AD112: =SUM(AD110:AD111) -> 0 | AE112: =SUM(AE110:AE111) -> 0 | AI112: =SUM(AI110:AI111) -> 0 | AJ112: =SUM(AJ110:AJ111) -> 0 | AK112: =SUM(AK110:AK111) -> 0 | AL112: =SUM(AL110:AL111) -> 150000 | AM112: =SUM(AM110:AM111) -> 0 | AN112: =SUM(AL112:AM112) -> 150000
F114: Supplies
F116: HQ Office Supplies
A117: LAPTOP | B117: 82401 | C117: USA | D117: USA | E117: 0 | F117: Laptop, Bag, Accessories | G117: 3 | H117: =Supplies!B31 -> 1204.99 | J117: /unit | K117: =H117*G117 -> 3614.97 | L117: 0 | M117: =SUM(K117:L117) -> 3614.97 | N117: 0 | O117: =H117*$G$6 -> 1223.0648 | Q117: =N117*O117 -> 0 | R117: 0 | S117: =SUM(Q117:R117) -> 0 | T117: =Q117*R117*S117 -> 0 | U117: =H117*$G$6*$G$6 -> 1241.4108 | W117: =U117*T117 -> 0 | X117: 0 | Y117: =SUM(W117:X117) -> 0 | Z117: =W117*X117*Y117 -> 0 | AA117: =H117*$G$6*$G$6*$G$6 -> 1260.032 | AC117: =AA117*Z117 -> 0 | AD117: 0 | AE117: =SUM(AC117:AD117) -> 0 | AF117: =AC117*AD117*AE117 -> 0 | AG117: =H117*$G$6*$G$6*$G$6*$G$6 -> 1278.9325 | AH117: 0 | AI117: =AG117*AF117 -> 0 | AJ117: 0 | AK117: =SUM(AI117:AJ117) -> 0 | AL117: =K117+Q117+W117+AC117+AI117 -> 3614.97 | AM117: =L117+R117+X117+AD117+AJ117 -> 0 | AN117: =SUM(AL117:AM117) -> 3614.97
A118: CAMERA | B118: 82401 | C118: USA | D118: USA | E118: 0 | F118: Camera, Accessories, Memory Card, S&H | G118: 1 | H118: =Supplies!B39 -> 469.95 | J118: /unit | K118: =H118*G118 -> 469.95 | L118: 0 | M118: =SUM(K118:L118) -> 469.95 | N118: 0 | O118: =H118*$G$6 -> 476.99925 | Q118: =N118*O118 -> 0 | R118: 0 | S118: =SUM(Q118:R118) -> 0 | T118: =Q118*R118*S118 -> 0 | U118: =H118*$G$6*$G$6 -> 484.15424 | W118: =U118*T118 -> 0 | X118: 0 | Y118: =SUM(W118:X118) -> 0 | Z118: =W118*X118*Y118 -> 0 | AA118: =H118*$G$6*$G$6*$G$6 -> 491.41655 | AC118: =AA118*Z118 -> 0 | AD118: 0 | AE118: =SUM(AC118:AD118) -> 0 | AF118: =AC118*AD118*AE118 -> 0 | AG118: =H118*$G$6*$G$6*$G$6*$G$6 -> 498.7878 | AI118: =AG118*AF118 -> 0 | AJ118: 0 | AK118: =SUM(AI118:AJ118) -> 0 | AL118: =K118+Q118+W118+AC118+AI118 -> 469.95 | AM118: =L118+R118+X118+AD118+AJ118 -> 0 | AN118: =SUM(AL118:AM118) -> 469.95
A119: PROJECTOR | B119: 82401 | C119: USA | D119: USA | E119: 0 | F119: LCD Projector | G119: 1 | H119: =Supplies!B45 -> 854 | J119: /unit | K119: =H119*G119 -> 854 | L119: 0 | M119: =SUM(K119:L119) -> 854 | N119: 0 | O119: =H119*$G$6 -> 866.81 | Q119: =N119*O119 -> 0 | R119: 0 | S119: =SUM(Q119:R119) -> 0 | T119: =Q119*R119*S119 -> 0 | U119: =H119*$G$6*$G$6 -> 879.81215 | W119: =U119*T119 -> 0 | X119: 0 | Y119: =SUM(W119:X119) -> 0 | Z119: =W119*X119*Y119 -> 0 | AA119: =H119*$G$6*$G$6*$G$6 -> 893.00933 | AC119: =AA119*Z119 -> 0 | AD119: 0 | AE119: =SUM(AC119:AD119) -> 0 | AF119: =AC119*AD119*AE119 -> 0 | AG119: =H119*$G$6*$G$6*$G$6*$G$6 -> 906.40447 | AI119: =AG119*AF119 -> 0 | AJ119: 0 | AK119: =SUM(AI119:AJ119) -> 0 | AL119: =K119+Q119+W119+AC119+AI119 -> 854 | AM119: =L119+R119+X119+AD119+AJ119 -> 0 | AN119: =SUM(AL119:AM119) -> 854
A120: FURNITURE | B120: 82401 | C120: USA | D120: USA | E120: 0 | F120: Office Furniture (Includes Desk, Chairs, Table, Shelves, & Filing Cabinet) | G120: 3 | H120: =Supplies!B69 -> 2790 | J120: /unit | K120: =H120*G120 -> 8370 | L120: 0 | M120: =SUM(K120:L120) -> 8370 | N120: 0 | O120: =H120*$G$6 -> 2831.85 | Q120: =N120*O120 -> 0 | R120: 0 | S120: =SUM(Q120:R120) -> 0 | T120: =Q120*R120*S120 -> 0 | U120: =H120*$G$6*$G$6 -> 2874.3277 | W120: =U120*T120 -> 0 | X120: 0 | Y120: =SUM(W120:X120) -> 0 | Z120: =W120*X120*Y120 -> 0 | AA120: =H120*$G$6*$G$6*$G$6 -> 2917.4427 | AC120: =AA120*Z120 -> 0 | AD120: 0 | AE120: =SUM(AC120:AD120) -> 0 | AF120: =AC120*AD120*AE120 -> 0 | AG120: =H120*$G$6*$G$6*$G$6*$G$6 -> 2961.2043 | AI120: =AG120*AF120 -> 0 | AJ120: 0 | AK120: =SUM(AI120:AJ120) -> 0 | AL120: =K120+Q120+W120+AC120+AI120 -> 8370 | AM120: =L120+R120+X120+AD120+AJ120 -> 0 | AN120: =SUM(AL120:AM120) -> 8370
A121: SUPPLIES | B121: 82401 | C121: USA | D121: USA | E121: 0 | F121: Program Specific Office Supplies and Stationary for HQ | G121: 1 | H121: 250 | I121: 12 | J121: /month | K121: =H121*G121*I121 -> 3000 | L121: 0 | M121: =SUM(K121:L121) -> 3000 | N121: 1 | O121: =H121*$G$6 -> 253.75 | P121: 12 | Q121: =N121*O121*P121 -> 3045 | R121: 0 | S121: =SUM(Q121:R121) -> 3045 | T121: 1 | U121: =H121*$G$6*$G$6 -> 257.55625 | V121: 12 | W121: =U121*T121*V121 -> 3090.675 | X121: 0 | Y121: =SUM(W121:X121) -> 3090.675 | Z121: 1 | AA121: =H121*$G$6*$G$6*$G$6 -> 261.41959 | AB121: 12 | AC121: =AA121*Z121*AB121 -> 3137.0351 | AD121: 0 | AE121: =SUM(AC121:AD121) -> 3137.0351 | AF121: 1 | AG121: =H121*$G$6*$G$6*$G$6*$G$6 -> 265.34089 | AH121: 12 | AI121: =AG121*AF121*AH121 -> 3184.0907 | AJ121: 0 | AK121: =SUM(AI121:AJ121) -> 3184.0907 | AL121: =K121+Q121+W121+AC121+AI121 -> 15456.801 | AM121: =L121+R121+X121+AD121+AJ121 -> 0 | AN121: =SUM(AL121:AM121) -> 15456.801
F122: Subtotal HQ Office Supplies | K122: =SUM(K117:K121) -> 16308.92 | L122: =SUM(L117:L121) -> 0 | M122: =SUM(M117:M121) -> 16308.92 | Q122: =SUM(Q117:Q121) -> 3045 | R122: =SUM(R117:R121) -> 0 | S122: =SUM(S117:S121) -> 3045 | W122: =SUM(W117:W121) -> 3090.675 | X122: =SUM(X117:X121) -> 0 | Y122: =SUM(Y117:Y121) -> 3090.675 | AC122: =SUM(AC117:AC121) -> 3137.0351 | AD122: =SUM(AD117:AD121) -> 0 | AE122: =SUM(AE117:AE121) -> 3137.0351 | AI122: =SUM(AI117:AI121) -> 3184.0907 | AJ122: =SUM(AJ117:AJ121) -> 0 | AK122: =SUM(AK117:AK121) -> 3184.0907 | AL122: =K122+Q122+W122+AC122+AI122 -> 28765.721 | AM122: =L122+R122+X122+AD122+AJ122 -> 0 | AN122: =SUM(AL122:AM122) -> 28765.721
...

Sheet Budget Summary Parque Explora
B1: Name of Subawardee: Parque Explora
B2: USAID RFA No. 7200AA21RFA00001
B4: Year 1 | E4: Year 2 | H4: Year 3 | K4: Year 4 | N4: Year 5 | Q4: Total | R4: Total | S4: Grand
B5: USAID | C5: Leverage | D5: Total | E5: USAID | F5: Leverage | G5: Total | H5: USAID | I5: Leverage | J5: Total | K5: USAID | L5: Leverage | M5: Total | N5: USAID | O5: Leverage | P5: Total | Q5: USAID | R5: Leverage | S5: Total
A7: Personnel | B7: ='Budget Parque Explora'!L51 -> 290716.67 | C7: ='Budget Parque Explora'!M51 -> 67092.083 | D7: ='Budget Parque Explora'!N51 -> 357808.75 | E7: ='Budget Parque Explora'!R51 -> 560248 | F7: ='Budget Parque Explora'!S51 -> 48302.8 | G7: ='Budget Parque Explora'!T51 -> 608550.8 | H7: ='Budget Parque Explora'!X51 -> 582657.92 | I7: ='Budget Parque Explora'!Y51 -> 50234.912 | J7: ='Budget Parque Explora'!Z51 -> 632892.83 | K7: ='Budget Parque Explora'!AD51 -> 605964.24 | L7: ='Budget Parque Explora'!AE51 -> 52244.308 | M7: ='Budget Parque Explora'!AF51 -> 658208.55 | N7: ='Budget Parque Explora'!AJ51 -> 325522.89 | O7: ='Budget Parque Explora'!AK51 -> 54457.403 | P7: ='Budget Parque Explora'!AL51 -> 379980.3 | Q7: ='Budget Parque Explora'!AM51 -> 2365109.7 | R7: ='Budget Parque Explora'!AN51 -> 272331.51 | S7: ='Budget Parque Explora'!AO51 -> 2637441.2
A9: Fringe Benefits | B9: ='Budget Parque Explora'!L56 -> 130924.75 | C9: ='Budget Parque Explora'!M56 -> 32796.049 | D9: ='Budget Parque Explora'!N56 -> 163720.8 | E9: ='Budget Parque Explora'!R56 -> 243225.18 | F9: ='Budget Parque Explora'!S56 -> 22641.902 | G9: ='Budget Parque Explora'!T56 -> 265867.08 | H9: ='Budget Parque Explora'!X56 -> 252954.19 | I9: ='Budget Parque Explora'!Y56 -> 23547.578 | J9: ='Budget Parque Explora'!Z56 -> 276501.77 | K9: ='Budget Parque Explora'!AD56 -> 263072.36 | L9: ='Budget Parque Explora'!AE56 -> 24489.481 | M9: ='Budget Parque Explora'!AF56 -> 287561.84 | N9: ='Budget Parque Explora'!AJ56 -> 146280.36 | O9: ='Budget Parque Explora'!AK56 -> 26224.263 | P9: ='Budget Parque Explora'!AL56 -> 172504.63 | Q9: ='Budget Parque Explora'!AM56 -> 1036456.8 | R9: ='Budget Parque Explora'!AN56 -> 129699.27 | S9: ='Budget Parque Explora'!AO56 -> 1166156.1
A11: Travel | B11: ='Budget Parque Explora'!L121 -> 61740 | C11: ='Budget Parque Explora'!M121 -> 0 | D11: ='Budget Parque Explora'!N121 -> 61740 | E11: ='Budget Parque Explora'!R121 -> 122765.4 | F11: ='Budget Parque Explora'!S121 -> 0 | G11: ='Budget Parque Explora'!T121 -> 122765.4 | H11: ='Budget Parque Explora'!X121 -> 216148.93 | I11: ='Budget Parque Explora'!Y121 -> 0 | J11: ='Budget Parque Explora'!Z121 -> 216148.93 | K11: ='Budget Parque Explora'!AD121 -> 190494.37 | L11: ='Budget Parque Explora'!AE121 -> 0 | M11: ='Budget Parque Explora'!AF121 -> 190494.37 | N11: ='Budget Parque Explora'!AJ121 -> 68821.057 | O11: ='Budget Parque Explora'!AK121 -> 0 | P11: ='Budget Parque Explora'!AL121 -> 68821.057 | Q11: ='Budget Parque Explora'!AM121 -> 659969.76 | R11: ='Budget Parque Explora'!AN121 -> 0 | S11: ='Budget Parque Explora'!AO121 -> 659969.76
A13: Equipment | B13: ='Budget Parque Explora'!L127 -> 50000 | C13: ='Budget Parque Explora'!M127 -> 0 | D13: ='Budget Parque Explora'!N127 -> 50000 | E13: ='Budget Parque Explora'!R127 -> 0 | F13: ='Budget Parque Explora'!S127 -> 0 | G13: ='Budget Parque Explora'!T127 -> 0 | H13: ='Budget Parque Explora'!X127 -> 0 | I13: ='Budget Parque Explora'!Y127 -> 0 | J13: ='Budget Parque Explora'!Z127 -> 0 | K13: ='Budget Parque Explora'!AD127 -> 0 | L13: ='Budget Parque Explora'!AE127 -> 0 | M13: ='Budget Parque Explora'!AF127 -> 0 | N13: ='Budget Parque Explora'!AJ127 -> 0 | O13: ='Budget Parque Explora'!AK127 -> 0 | P13: ='Budget Parque Explora'!AL127 -> 0 | Q13: ='Budget Parque Explora'!AM127 -> 50000 | R13: ='Budget Parque Explora'!AN127 -> 0 | S13: ='Budget Parque Explora'!AO127 -> 50000
A15: Supplies | B15: ='Budget Parque Explora'!L142 -> 18439.9 | C15: ='Budget Parque Explora'!M142 -> 0 | D15: ='Budget Parque Explora'!N142 -> 18439.9 | E15: ='Budget Parque Explora'!R142 -> 21423.918 | F15: ='Budget Parque Explora'!S142 -> 0 | G15: ='Budget Parque Explora'!T142 -> 21423.918 | H15: ='Budget Parque Explora'!X142 -> 9548.1 | I15: ='Budget Parque Explora'!Y142 -> 0 | J15: ='Budget Parque Explora'!Z142 -> 9548.1 | K15: ='Budget Parque Explora'!AD142 -> 4917.2715 | L15: ='Budget Parque Explora'!AE142 -> 0 | M15: ='Budget Parque Explora'!AF142 -> 4917.2715 | N15: ='Budget Parque Explora'!AJ142 -> 3798.5922 | O15: ='Budget Parque Explora'!AK142 -> 0 | P15: ='Budget Parque Explora'!AL142 -> 3798.5922 | Q15: ='Budget Parque Explora'!AM142 -> 58127.781 | R15: ='Budget Parque Explora'!AN142 -> 0 | S15: ='Budget Parque Explora'!AO142 -> 58127.781
A17: Contractual | B17: ='Budget Parque Explora'!L154 -> 204200 | C17: ='Budget Parque Explora'!M154 -> 0 | D17: ='Budget Parque Explora'!N154 -> 204200 | E17: ='Budget Parque Explora'!R154 -> 208400 | F17: ='Budget Parque Explora'!S154 -> 0 | G17: ='Budget Parque Explora'!T154 -> 208400 | H17: ='Budget Parque Explora'!X154 -> 208400 | I17: ='Budget Parque Explora'!Y154 -> 0 | J17: ='Budget Parque Explora'!Z154 -> 208400 | K17: ='Budget Parque Explora'!AD154 -> 208400 | L17: ='Budget Parque Explora'!AE154 -> 0 | M17: ='Budget Parque Explora'!AF154 -> 208400 | N17: ='Budget Parque Explora'!AJ154 -> 206300 | O17: ='Budget Parque Explora'!AK154 -> 0 | P17: ='Budget Parque Explora'!AL154 -> 206300 | Q17: ='Budget Parque Explora'!AM154 -> 1035700 | R17: ='Budget Parque Explora'!AN154 -> 0 | S17: ='Budget Parque Explora'!AO154 -> 1035700
A19: Other Direct Costs | B19: ='Budget Parque Explora'!L203 -> 122135.9 | C19: ='Budget Parque Explora'!M203 -> 0 | D19: ='Budget Parque Explora'!N203 -> 122135.9 | E19: ='Budget Parque Explora'!R203 -> 76503.2 | F19: ='Budget Parque Explora'!S203 -> 0 | G19: ='Budget Parque Explora'!T203 -> 76503.2 | H19: ='Budget Parque Explora'!X203 -> 406653.84 | I19: ='Budget Parque Explora'!Y203 -> 0 | J19: ='Budget Parque Explora'!Z203 -> 406653.84 | K19: ='Budget Parque Explora'!AD203 -> 419001.66 | L19: ='Budget Parque Explora'!AE203 -> 0 | M19: ='Budget Parque Explora'!AF203 -> 419001.66 | N19: ='Budget Parque Explora'!AJ203 -> 64324.394 | O19: ='Budget Parque Explora'!AK203 -> 0 | P19: ='Budget Parque Explora'!AL203 -> 64324.394 | Q19: ='Budget Parque Explora'!AM203 -> 1088619 | R19: ='Budget Parque Explora'!AN203 -> 0 | S19: ='Budget Parque Explora'!AO203 -> 1088619
A21: Total Direct Costs | B21: =SUM(B7:B20) -> 878157.22 | C21: =SUM(C7:C20) -> 99888.132 | D21: =SUM(D7:D20) -> 978045.35 | E21: =SUM(E7:E20) -> 1232565.7 | F21: =SUM(F7:F20) -> 70944.702 | G21: =SUM(G7:G20) -> 1303510.4 | H21: =SUM(H7:H20) -> 1676363 | I21: =SUM(I7:I20) -> 73782.49 | ... S21: =SUM(S7:S20) -> 6696013.9
A22: Indirect Costs | B22: ='Budget Parque Explora'!L206 -> 62815.722 | C22: ='Budget Parque Explora'!M206 -> 9988.8132 | D22: ='Budget Parque Explora'!N206 -> 72804.535 | E22: ='Budget Parque Explora'!R206 -> 103256.57 | F22: ='Budget Parque Explora'!S206 -> 7094.4702 | G22: ='Budget Parque Explora'!T206 -> 110351.04 | H22: ='Budget Parque Explora'!X206 -> 147636.3 | I22: ='Budget Parque Explora'!Y206 -> 7378.249 | J22: ='Budget Parque Explora'!Z206 -> 155014.55 | K22: ='Budget Parque Explora'!AD206 -> 149184.99 | L22: ='Budget Parque Explora'!AE206 -> 7673.379 | M22: ='Budget Parque Explora'!AF206 -> 156858.37 | N22: ='Budget Parque Explora'!AJ206 -> 61504.73 | O22: ='Budget Parque Explora'!AK206 -> 8068.1667 | P22: ='Budget Parque Explora'!AL206 -> 69572.897 | Q22: ='Budget Parque Explora'!AM206 -> 524398.31 | R22: ='Budget Parque Explora'!AN206 -> 40203.078 | S22: ='Budget Parque Explora'!AO206 -> 564601.39
A23: Total | B23: =B22+B21 -> 940972.94 | C23: =C22+C21 -> 109876.95 | D23: =D22+D21 -> 1050849.9 | E23: =E22+E21 -> 1335822.3 | F23: =F22+F21 -> 78039.172 | G23: =G22+G21 -> 1413861.4 | H23: =H22+H21 -> 1823999.3 | I23: =I22+I21 -> 81160.739 | ... S23: =S22+S21 -> 7260615.3

Sheet Budget Parque Explora
H1: USAID Juntos Aprendemos
H2: Parque Explora
H3: Subaward Budget
A4: Entity: | B4: P | H4: Country: Colombia
A5: Program-Dept.: | B5: 20300 | G5: Budget Assumptions
A6: Funder-Grant: | B6: USAID800 | G6: Inflation - Locally Purchased Goods/Services - 3% | H6: 1.03
G7: Merit Based Increases for HQ & Field Staff - 4% | H7: 1.04
G9: *Key Personnel
A10: Sage Activity | B10: Sage Object Code/ Line Item | C10: Country Code (DC=0 or CO) | D10: Office Code (DC=0 or CO) | E10: Subcontract Code | F10: Open 1 Code | L10: Year 1 | R10: Year 2 | U10: Year 3 | AD10: Year 4 | AJ10: Year 5 | AM10: Total | AN10: Total | AO10: Grand
H11: Unit | I11: Cost | J11: Duration | K11: Type | L11: USAID | M11: Leverage | N11: Total | O11: Unit | P11: Cost | Q11: Duration | R11: USAID | S11: Leverage | T11: Total | U11: Unit | V11: Cost | W11: Duration | X11: USAID | Y11: Leverage | Z11: Total | AA11: Unit | AB11: Cost | AC11: Duration | AD11: USAID | AE11: Leverage | AF11: Total | AG11: Unit | AH11: Cost | AI11: Duration | AJ11: USAID | AK11: Leverage | AL11: Total | AM11: USAID | AN11: Leverage | AO11: Total
G13: Personnel
G14: Headquarters Personnel | H14: LOE
G15: Project Office (Bogota)
A16: SUBEXPLORA | B16: 89050 | C16: COL2 | D16: COL2 | E16: EXPLORA | F16: EXPPERSNL | G16: Community Engagement and Outreach Director* | H16: 1 | I16: =52500/12 -> 4375 | J16: 11 | K16: /months | L16: =J16*I16*H16 -> 48125 | M16: 0 | N16: =SUM(L16:M16) -> 48125 | O16: =H16 -> 1 | P16: =I16*$H$7 -> 4550 | Q16: 12 | R16: =O16*P16*Q16 -> 54600 | S16: 0 | T16: =SUM(R16:S16) -> 54600 | U16: =H16 -> 1 | V16: =I16*$H$7*$H$7 -> 4732 | W16: 12 | X16: =U16*V16*W16 -> 56784 | Y16: 0 | Z16: =SUM(X16:Y16) -> 56784 | AA16: =U16 -> 1 | AB16: =I16*$H$7*$H$7*$H$7 -> 4921.28 | AC16: 12 | AD16: =AA16*AB16*AC16 -> 59055.36 | AE16: 0 | AF16: =SUM(AD16:AE16) -> 59055.36 | AG16: =AA16 -> 1 | AH16: =I16*$H$7*$H$7*$H$7*$H$7 -> 5118.1312 | AI16: 11 | AJ16: =AG16*AH16*AI16 -> 56299.443 | AK16: 0 | AL16: =SUM(AJ16:AK16) -> 56299.443 | AM16: =L16+R16+X16+AD16+AJ16 -> 274863.8 | AN16: =M16+S16+Y16+AE16+AK16 -> 0 | AO16: =SUM(AM16:AN16) -> 274863.8
A17: SUBEXPLORA | B17: 89050 | C17: COL2 | D17: COL2 | E17: EXPLORA | F17: EXPPERSNL | G17: Community Engagement and Outreach Manager | H17: 1 | I17: =38000/12 -> 3166.6667 | J17: 10 | K17: /months | L17: =J17*I17*H17 -> 31666.667 | M17: 0 | N17: =SUM(L17:M17) -> 31666.667 | O17: 1 | P17: =I17*$H$7 -> 3293.3333 | Q17: 12 | R17: =P17*Q17*O17 -> 39520 | S17: 0 | T17: =SUM(R17:S17) -> 39520 | U17: 1 | V17: =I17*$H$7*$H$7 -> 3425.0667 | W17: 12 | X17: =W17*V17*U17 -> 41100.8 | Y17: 0 | Z17: =SUM(X17:Y17) -> 41100.8 | AA17: 1 | AB17: =I17*$H$7*$H$7*$H$7 -> 3562.0693 | AC17: 12 | AD17: =AC17*AB17*AA17 -> 42744.832 | AE17: 0 | AF17: =SUM(AD17:AE17) -> 42744.832 | AG17: 1 | AH17: =I17*$H$7*$H$7*$H$7*$H$7 -> 3704.5521 | AI17: 8 | AJ17: =AI17*AH17*AG17 -> 29636.417 | AK17: 0 | AL17: =SUM(AJ17:AK17) -> 29636.417 | AM17: =L17+R17+X17+AD17+AJ17 -> 184668.72 | AN17: =M17+S17+Y17+AE17+AK17 -> 0 | AO17: =SUM(AM17:AN17) -> 184668.72
G18: Parque Explora Office (Medellin)
A19: SUBEXPLORA | B19: 89050 | C19: COL2 | D19: COL2 | E19: EXPLORA | F19: EXPPERSNL | G19: School Research Coordinator | H19: 1 | I19: =22500/12 -> 1875 | J19: 10 | K19: /months | L19: =J19*I19*H19 -> 18750 | M19: 0 | N19: =SUM(L19:M19) -> 18750 | O19: 1 | P19: =I19*$H$7 -> 1950 | Q19: 12 | R19: =P19*Q19*O19 -> 23400 | S19: 0 | T19: =SUM(R19:S19) -> 23400 | U19: 1 | V19: =I19*$H$7*$H$7 -> 2028 | W19: 12 | X19: =W19*V19*U19 -> 24336 | Y19: 0 | Z19: =SUM(X19:Y19) -> 24336 | AA19: 1 | AB19: =I19*$H$7*$H$7*$H$7 -> 2109.12 | AC19: 12 | AD19: =AC19*AB19*AA19 -> 25309.44 | AE19: 0 | AF19: =SUM(AD19:AE19) -> 25309.44 | AG19: 1 | AH19: =I19*$H$7*$H$7*$H$7*$H$7 -> 2193.4848 | AI19: 8 | AJ19: =AI19*AH19*AG19 -> 17547.878 | AK19: 0 | AL19: =SUM(AJ19:AK19) -> 17547.878 | AM19: =L19+R19+X19+AD19+AJ19 -> 109343.32 | AN19: =M19+S19+Y19+AE19+AK19 -> 0 | AO19: =SUM(AM19:AN19) -> 109343.32
A20: SUBEXPLORA | B20: 89050 | C20: COL2 | D20: COL2 | E20: EXPLORA | F20: EXPPERSNL | G20: Pedagogical Coordinator | H20: 1 | I20: =22500/12 -> 1875 | J20: 10 | K20: /months | L20: =J20*I20*H20 -> 18750 | M20: 0 | N20: =SUM(L20:M20) -> 18750 | O20: 1 | P20: =I20*$H$7 -> 1950 | Q20: 12 | R20: =P20*Q20*O20 -> 23400 | S20: 0 | T20: =SUM(R20:S20) -> 23400 | U20: 1 | V20: =I20*$H$7*$H$7 -> 2028 | W20: 12 | X20: =W20*V20*U20 -> 24336 | Y20: 0 | Z20: =SUM(X20:Y20) -> 24336 | AA20: 1 | AB20: =I20*$H$7*$H$7*$H$7 -> 2109.12 | AC20: 12 | AD20: =AC20*AB20*AA20 -> 25309.44 | AE20: 0 | AF20: =SUM(AD20:AE20) -> 25309.44 | AG20: 1 | AH20: =I20*$H$7*$H$7*$H$7*$H$7 -> 2193.4848 | AI20: 8 | AJ20: =AI20*AH20*AG20 -> 17547.878 | AK20: 0 | AL20: =SUM(AJ20:AK20) -> 17547.878 | AM20: =L20+R20+X20+AD20+AJ20 -> 109343.32 | AN20: =M20+S20+Y20+AE20+AK20 -> 0 | AO20: =SUM(AM20:AN20) -> 109343.32
A21: SUBEXPLORA | B21: 89050 | C21: COL2 | D21: COL2 | E21: EXPLORA | F21: EXPPERSNL | G21: Clubes Explora Coordinator | H21: 1 | I21: =22500/12 -> 1875 | J21: 10 | K21: /months | L21: =J21*I21*H21 -> 18750 | M21: 0 | N21: =SUM(L21:M21) -> 18750 | O21: 1 | P21: =I21*$H$7 -> 1950 | Q21: 12 | R21: =P21*Q21*O21 -> 23400 | S21: 0 | T21: =SUM(R21:S21) -> 23400 | U21: 1 | V21: =I21*$H$7*$H$7 -> 2028 | W21: 12 | X21: =W21*V21*U21 -> 24336 | Y21: 0 | Z21: =SUM(X21:Y21) -> 24336 | AA21: 1 | AB21: =I21*$H$7*$H$7*$H$7 -> 2109.12 | AC21: 12 | AD21: =AC21*AB21*AA21 -> 25309.44 | AE21: 0 | AF21: =SUM(AD21:AE21) -> 25309.44 | AG21: 1 | AH21: =I21*$H$7*$H$7*$H$7*$H$7 -> 2193.4848 | AI21: 8 | AJ21: =AI21*AH21*AG21 -> 17547.878 | AK21: 0 | AL21: =SUM(AJ21:AK21) -> 17547.878 | AM21: =L21+R21+X21+AD21+AJ21 -> 109343.32 | AN21: =M21+S21+Y21+AE21+AK21 -> 0 | AO21: =SUM(AM21:AN21) -> 109343.32
A22: SUBEXPLORA | B22: 89050 | C22: COL2 | D22: COL2 | E22: EXPLORA | F22: EXPPERSNL | G22: Clubes Explora Content Professional | H22: 1 | I22: =15000/12 -> 1250 | J22: 10 | K22: /months | L22: =J22*I22*H22 -> 12500 | M22: 0 | N22: =SUM(L22:M22) -> 12500 | O22: 1 | P22: =I22*$H$7 -> 1300 | Q22: 12 | R22: =P22*Q22*O22 -> 15600 | S22: 0 | T22: =SUM(R22:S22) -> 15600 | U22: 1 | V22: =I22*$H$7*$H$7 -> 1352 | W22: 12 | X22: =W22*V22*U22 -> 16224 | Y22: 0 | Z22: =SUM(X22:Y22) -> 16224 | AA22: 1 | AB22: =I22*$H$7*$H$7*$H$7 -> 1406.08 | AC22: 12 | AD22: =AC22*AB22*AA22 -> 16872.96 | AE22: 0 | AF22: =SUM(AD22:AE22) -> 16872.96 | AG22: 1 | AH22: =I22*$H$7*$H$7*$H$7*$H$7 -> 1462.3232 | AI22: 8 | AJ22: =AI22*AH22*AG22 -> 11698.586 | AK22: 0 | AL22: =SUM(AJ22:AK22) -> 11698.586 | AM22: =L22+R22+X22+AD22+AJ22 -> 72895.546 | AN22: =M22+S22+Y22+AE22+AK22 -> 0 | AO22: =SUM(AM22:AN22) -> 72895.546
A23: SUBEXPLORA | B23: 89050 | C23: COL2 | D23: COL2 | E23: EXPLORA | F23: EXPPERSNL | G23: School Research Professional | H23: 1 | I23: =15000/12 -> 1250 | J23: 10 | K23: /months | L23: =J23*I23*H23 -> 12500 | M23: 0 | N23: =SUM(L23:M23) -> 12500 | O23: 1 | P23: =I23*$H$7 -> 1300 | Q23: 12 | R23: =P23*Q23*O23 -> 15600 | S23: 0 | T23: =SUM(R23:S23) -> 15600 | U23: 1 | V23: =I23*$H$7*$H$7 -> 1352 | W23: 12 | X23: =W23*V23*U23 -> 16224 | Y23: 0 | Z23: =SUM(X23:Y23) -> 16224 | AA23: 1 | AB23: =I23*$H$7*$H$7*$H$7 -> 1406.08 | AC23: 12 | AD23: =AC23*AB23*AA23 -> 16872.96 | AE23: 0 | AF23: =SUM(AD23:AE23) -> 16872.96 | AG23: 1 | AH23: =I23*$H$7*$H$7*$H$7*$H$7 -> 1462.3232 | AI23: 8 | AJ23: =AI23*AH23*AG23 -> 11698.586 | AK23: 0 | AL23: =SUM(AJ23:AK23) -> 11698.586 | AM23: =L23+R23+X23+AD23+AJ23 -> 72895.546 | AN23: =M23+S23+Y23+AE23+AK23 -> 0 | AO23: =SUM(AM23:AN23) -> 72895.546
A24: SUBEXPLORA | B24: 89050 | C24: COL2 | D24: COL2 | E24: EXPLORA | F24: EXPPERSNL | G24: Monitoring and Evaluation Specialist | H24: 1 | I24: =31200/12 -> 2600 | J24: 8 | K24: /months | L24: =J24*I24*H24 -> 20800 | M24: 0 | N24: =SUM(L24:M24) -> 20800 | O24: 1 | P24: =I24*$H$7 -> 2704 | Q24: 12 | R24: =P24*Q24*O24 -> 32448 | S24: 0 | T24: =SUM(R24:S24) -> 32448 | U24: 1 | V24: =I24*$H$7*$H$7 -> 2812.16 | W24: 12 | X24: =W24*V24*U24 -> 33745.92 | Y24: 0 | Z24: =SUM(X24:Y24) -> 33745.92 | AA24: 1 | AB24: =I24*$H$7*$H$7*$H$7 -> 2924.6464 | AC24: 12 | AD24: =AC24*AB24*AA24 -> 35095.757 | AE24: 0 | AF24: =SUM(AD24:AE24) -> 35095.757 | AG24: 1 | AH24: =I24*$H$7*$H$7*$H$7*$H$7 -> 3041.6323 | AI24: 8 | AJ24: =AI24*AH24*AG24 -> 24333.058 | AK24: 0 | AL24: =SUM(AJ24:AK24) -> 24333.058 | AM24: =L24+R24+X24+AD24+AJ24 -> 146422.73 | AN24: =M24+S24+Y24+AE24+AK24 -> 0 | AO24: =SUM(AM24:AN24) -> 146422.73
A25: SUBEXPLORA | B25: 89050 | C25: COL2 | D25: COL2 | E25: EXPLORA | F25: EXPPERSNL | G25: Communication and Graphic Design Professional | H25: 1 | I25: =15000/12 -> 1250 | J25: 6 | K25: /months | L25: =J25*I25*H25 -> 7500 | M25: 0 | N25: =SUM(L25:M25) -> 7500 | O25: 1 | P25: =I25*$H$7 -> 1300 | Q25: 12 | R25: =P25*Q25*O25 -> 15600 | S25: 0 | T25: =SUM(R25:S25) -> 15600 | U25: 1 | V25: =I25*$H$7*$H$7 -> 1352 | W25: 12 | X25: =W25*V25*U25 -> 16224 | Y25: 0 | Z25: =SUM(X25:Y25) -> 16224 | AA25: 1 | AB25: =I25*$H$7*$H$7*$H$7 -> 1406.08 | AC25: 12 | AD25: =AC25*AB25*AA25 -> 16872.96 | AE25: 0 | AF25: =SUM(AD25:AE25) -> 16872.96 | AG25: 1 | AH25: =I25*$H$7*$H$7*$H$7*$H$7 -> 1462.3232 | AI25: 8 | AJ25: =AI25*AH25*AG25 -> 11698.586 | AK25: 0 | AL25: =SUM(AJ25:AK25) -> 11698.586 | AM25: =L25+R25+X25+AD25+AJ25 -> 67895.546 | AN25: =M25+S25+Y25+AE25+AK25 -> 0 | AO25: =SUM(AM25:AN25) -> 67895.546
A26: SUBEXPLORA | B26: 89050 | C26: COL2 | D26: COL2 | E26: EXPLORA | F26: EXPPERSNL | G26: Grants & Compliance Coordinator | H26: 1 | I26: =22500/12 -> 1875 | J26: 3 | K26: /months | L26: =J26*I26*H26 -> 5625 | M26: 0 | N26: =SUM(L26:M26) -> 5625 | O26: 1 | P26: =I26*$H$7 -> 1950 | Q26: 12 | R26: =P26*Q26*O26 -> 23400 | S26: 0 | T26: =SUM(R26:S26) -> 23400 | U26: 1 | V26: =I26*$H$7*$H$7 -> 2028 | W26: 12 | X26: =W26*V26*U26 -> 24336 | Y26: 0 | Z26: =SUM(X26:Y26) -> 24336 | AA26: 1 | AB26: =I26*$H$7*$H$7*$H$7 -> 2109.12 | AC26: 12 | AD26: =AC26*AB26*AA26 -> 25309.44 | AE26: 0 | AF26: =SUM(AD26:AE26) -> 25309.44 | AG26: 1 | AH26: =I26*$H$7*$H$7*$H$7*$H$7 -> 2193.4848 | AI26: 8 | AJ26: =AI26*AH26*AG26 -> 17547.878 | AK26: 0 | AL26: =SUM(AJ26:AK26) -> 17547.878 | AM26: =L26+R26+X26+AD26+AJ26 -> 96218.318 | AN26: =M26+S26+Y26+AE26+AK26 -> 0 | AO26: =SUM(AM26:AN26) -> 96218.318
A27: SUBEXPLORA | B27: 89050 | C27: COL2 | D27: COL2 | E27: EXPLORA | F27: EXPPERSNL | G27: Finance & Admin Coordinator (2) | H27: 1 | I27: =(22500/12)*2 -> 3750 | J27: 9 | K27: /months | L27: =J27*I27*H27 -> 33750 | M27: 0 | N27: =SUM(L27:M27) -> 33750 | O27: 1 | P27: =I27*$H$7 -> 3900 | Q27: 12 | R27: =P27*Q27*O27 -> 46800 | S27: 0 | T27: =SUM(R27:S27) -> 46800 | U27: 1 | V27: =I27*$H$7*$H$7 -> 4056 | W27: 12 | X27: =W27*V27*U27 -> 48672 | Y27: 0 | Z27: =SUM(X27:Y27) -> 48672 | AA27: 1 | AB27: =I27*$H$7*$H$7*$H$7 -> 4218.24 | AC27: 12 | AD27: =AC27*AB27*AA27 -> 50618.88 | AE27: 0 | AF27: =SUM(AD27:AE27) -> 50618.88 | AG27: 1 | AH27: =I27*$H$7*$H$7*$H$7*$H$7 -> 4386.9696 | AI27: 8 | AJ27: =AI27*AH27*AG27 -> 35095.757 | AK27: 0 | AL27: =SUM(AJ27:AK27) -> 35095.757 | AM27: =L27+R27+X27+AD27+AJ27 -> 214936.64 | AN27: =M27+S27+Y27+AE27+AK27 -> 0 | AO27: =SUM(AM27:AN27) -> 214936.64
A28: SUBEXPLORA | B28: 89050 | C28: COL2 | D28: COL2 | E28: EXPLORA | F28: EXPERSNLEV | G28: Executive Director | H28: 0.05 | I28: =64000/12 -> 5333.3333 | J28: 11 | K28: /months | L28: 0 | M28: =J28*I28*H28 -> 2933.3333 | N28: =SUM(L28:M28) -> 2933.3333 | O28: 0.05 | P28: =I28*$H$7 -> 5546.6667 | Q28: 12 | R28: 0 | S28: =P28*O28*Q28 -> 3328 | T28: =SUM(R28:S28) -> 3328 | U28: 0.05 | V28: =I28*$H$7*$H$7 -> 5768.5333 | W28: 12 | X28: 0 | Y28: =V28*U28*W28 -> 3461.12 | Z28: =SUM(X28:Y28) -> 3461.12 | AA28: 0.05 | AB28: =I28*$H$7*$H$7*$H$7 -> 5999.2747 | AC28: 12 | AD28: 0 | AE28: =AB28*AA28*AC28 -> 3599.5648 | AF28: =SUM(AD28:AE28) -> 3599.5648 | AG28: 0.05 | AH28: =I28*$H$7*$H$7*$H$7*$H$7 -> 6239.2457 | AI28: 10 | AJ28: 0 | AK28: =AH28*AG28*AI28 -> 3119.6228 | AL28: =SUM(AJ28:AK28) -> 3119.6228 | AM28: =L28+R28+X28+AD28+AJ28 -> 0 | AN28: =M28+S28+Y28+AE28+AK28 -> 16441.641 | AO28: =SUM(AM28:AN28) -> 16441.641
A29: SUBEXPLORA | B29: 89050 | C29: COL2 | D29: COL2 | E29: EXPLORA | F29: EXPERSNLEV | G29: Financial Director | H29: 0.2 | I29: =48000/12 -> 4000 | J29: 11 | K29: /months | L29: 0 | M29: =J29*I29*H29 -> 8800 | N29: =SUM(L29:M29) -> 8800 | O29: 0.1 | P29: =I29*$H$7 -> 4160 | Q29: 12 | R29: 0 | S29: =P29*O29*Q29 -> 4992 | T29: =SUM(R29:S29) -> 4992 | U29: 0.1 | V29: =I29*$H$7*$H$7 -> 4326.4 | W29: 12 | X29: 0 | Y29: =V29*U29*W29 -> 5191.68 | Z29: =SUM(X29:Y29) -> 5191.68 | AA29: 0.1 | AB29: =I29*$H$7*$H$7*$H$7 -> 4499.456 | AC29: 12 | AD29: 0 | AE29: =AB29*AA29*AC29 -> 5399.3472 | AF29: =SUM(AD29:AE29) -> 5399.3472 | AG29: 0.2 | AH29: =I29*$H$7*$H$7*$H$7*$H$7 -> 4679.4342 | AI29: 12 | AJ29: 0 | AK29: =AH29*AG29*AI29 -> 11230.642 | AL29: =SUM(AJ29:AK29) -> 11230.642 | AM29: =L29+R29+X29+AD29+AJ29 -> 0 | AN29: =M29+S29+Y29+AE29+AK29 -> 35613.669 | AO29: =SUM(AM29:AN29) -> 35613.669
A30: SUBEXPLORA | B30: 89050 | C30: COL2 | D30: COL2 | E30: EXPLORA | F30: EXPERSNLEV | G30: Content Director | H30: 0.2 | I30: =48000/12 -> 4000 | J30: 9 | K30: /months | L30: 0 | M30: =J30*I30*H30 -> 7200 | N30: =SUM(L30:M30) -> 7200 | O30: 0.05 | P30: =I30*$H$7 -> 4160 | Q30: 12 | R30: 0 | S30: =P30*O30*Q30 -> 2496 | T30: =SUM(R30:S30) -> 2496 | U30: 0.05 | V30: =I30*$H$7*$H$7 -> 4326.4 | W30: 12 | X30: 0 | Y30: =V30*U30*W30 -> 2595.84 | Z30: =SUM(X30:Y30) -> 2595.84 | AA30: 0.05 | AB30: =I30*$H$7*$H$7*$H$7 -> 4499.456 | AC30: 12 | AD30: 0 | AE30: =AB30*AA30*AC30 -> 2699.6736 | AF30: =SUM(AD30:AE30) -> 2699.6736 | AG30: 0.1 | AH30: =I30*$H$7*$H$7*$H$7*$H$7 -> 4679.4342 | AI30: 8 | AJ30: 0 | AK30: =AH30*AG30*AI30 -> 3743.5474 | AL30: =SUM(AJ30:AK30) -> 3743.5474 | AM30: =L30+R30+X30+AD30+AJ30 -> 0 | AN30: =M30+S30+Y30+AE30+AK30 -> 18735.061 | AO30: =SUM(AM30:AN30) -> 18735.061
A31: SUBEXPLORA | B31: 89050 | C31: COL2 | D31: COL2 | E31: EXPLORA | F31: EXPERSNLEV | G31: Head of Content | H31: 0.2 | I31: 2000 | J31: 9 | K31: /months | L31: 0 | M31: =J31*I31*H31 -> 3600 | N31: =SUM(L31:M31) -> 3600 | O31: 0.05 | P31: =I31*$H$7 -> 2080 | Q31: 12 | R31: 0 | S31: =P31*O31*Q31 -> 1248 | T31: =SUM(R31:S31) -> 1248 | U31: 0.05 | V31: =I31*$H$7*$H$7 -> 2163.2 | W31: 12 | X31: 0 | Y31: =V31*U31*W31 -> 1297.92 | Z31: =SUM(X31:Y31) -> 1297.92 | AA31: 0.05 | AB31: =I31*$H$7*$H$7*$H$7 -> 2249.728 | AC31: 12 | AD31: 0 | AE31: =AB31*AA31*AC31 -> 1349.8368 | AF31: =SUM(AD31:AE31) -> 1349.8368 | AG31: 0.1 | AH31: =I31*$H$7*$H$7*$H$7*$H$7 -> 2339.7171 | AI31: 8 | AJ31: 0 | AK31: =AH31*AG31*AI31 -> 1871.7737 | AL31: =SUM(AJ31:AK31) -> 1871.7737 | AM31: =L31+R31+X31+AD31+AJ31 -> 0 | AN31: =M31+S31+Y31+AE31+AK31 -> 9367.5305 | AO31: =SUM(AM31:AN31) -> 9367.5305
A32: SUBEXPLORA | B32: 89050 | C32: COL2 | D32: COL2 | E32: EXPLORA | F32: EXPERSNLEV | G32: Director of Communications | H32: 0.2 | I32: =48000/12 -> 4000 | J32: 9 | K32: /months | L32: 0 | M32: =J32*I32*H32 -> 7200 | N32: =SUM(L32:M32) -> 7200 | O32: 0.05 | P32: =I32*$H$7 -> 4160 | Q32: 12 | R32: 0 | S32: =P32*O32*Q32 -> 2496 | T32: =SUM(R32:S32) -> 2496 | U32: 0.05 | V32: =I32*$H$7*$H$7 -> 4326.4 | W32: 12 | X32: 0 | Y32: =V32*U32*W32 -> 2595.84 | Z32: =SUM(X32:Y32) -> 2595.84 | AA32: 0.05 | AB32: =I32*$H$7*$H$7*$H$7 -> 4499.456 | AC32: 12 | AD32: 0 | AE32: =AB32*AA32*AC32 -> 2699.6736 | AF32: =SUM(AD32:AE32) -> 2699.6736 | AG32: 0.05 | AH32: =I32*$H$7*$H$7*$H$7*$H$7 -> 4679.4342 | AI32: 8 | AJ32: 0 | AK32: =AH32*AG32*AI32 -> 1871.7737 | AL32: =SUM(AJ32:AK32) -> 1871.7737 | AM32: =L32+R32+X32+AD32+AJ32 -> 0 | AN32: =M32+S32+Y32+AE32+AK32 -> 16863.287 | AO32: =SUM(AM32:AN32) -> 16863.287
A33: SUBEXPLORA | B33: 89050 | C33: COL2 | D33: COL2 | E33: EXPLORA | F33: EXPERSNLEV | G33: Director of Education | H33: 0.2 | I33: =48000/12 -> 4000 | J33: 10 | K33: /months | L33: 0 | M33: =J33*I33*H33 -> 8000 | N33: =SUM(L33:M33) -> 8000 | O33: 0.1 | P33: =I33*$H$7 -> 4160 | Q33: 12 | R33: 0 | S33: =P33*O33*Q33 -> 4992 | T33: =SUM(R33:S33) -> 4992 | U33: 0.1 | V33: =I33*$H$7*$H$7 -> 4326.4 | W33: 12 | X33: 0 | Y33: =V33*U33*W33 -> 5191.68 | Z33: =SUM(X33:Y33) -> 5191.68 | AA33: 0.1 | AB33: =I33*$H$7*$H$7*$H$7 -> 4499.456 | AC33: 12 | AD33: 0 | AE33: =AB33*AA33*AC33 -> 5399.3472 | AF33: =SUM(AD33:AE33) -> 5399.3472 | AG33: 0.2 | AH33: =I33*$H$7*$H$7*$H$7*$H$7 -> 4679.4342 | AI33: 8 | AJ33: 0 | AK33: =AH33*AG33*AI33 -> 7487.0948 | AL33: =SUM(AJ33:AK33) -> 7487.0948 | AM33: =L33+R33+X33+AD33+AJ33 -> 0 | AN33: =M33+S33+Y33+AE33+AK33 -> 31070.122 | AO33: =SUM(AM33:AN33) -> 31070.122
A34: SUBEXPLORA | B34: 89050 | C34: COL2 | D34: COL2 | E34: EXPLORA | F34: EXPERSNLEV | G34: Head of Education | H34: 0.3 | I34: 2000 | J34: 10 | K34: /months | L34: 0 | M34: =J34*I34*H34 -> 6000 | N34: =SUM(L34:M34) -> 6000 | O34: 0.15 | P34: =I34*$H$7 -> 2080 | Q34: 12 | R34: 0 | S34: =P34*O34*Q34 -> 3744 | T34: =SUM(R34:S34) -> 3744 | U34: 0.15 | V34: =I34*$H$7*$H$7 -> 2163.2 | W34: 12 | X34: 0 | Y34: =V34*U34*W34 -> 3893.76 | Z34: =SUM(X34:Y34) -> 3893.76 | AA34: 0.15 | AB34: =I34*$H$7*$H$7*$H$7 -> 2249.728 | AC34: 12 | AD34: 0 | AE34: =AB34*AA34*AC34 -> 4049.5104 | AF34: =SUM(AD34:AE34) -> 4049.5104 | AG34: 0.2 | AH34: =I34*$H$7*$H$7*$H$7*$H$7 -> 2339.7171 | AI34: 9 | AJ34: 0 | AK34: =AH34*AG34*AI34 -> 4211.4908 | AL34: =SUM(AJ34:AK34) -> 4211.4908 | AM34: =L34+R34+X34+AD34+AJ34 -> 0 | AN34: =M34+S34+Y34+AE34+AK34 -> 21898.761 | AO34: =SUM(AM34:AN34) -> 21898.761
A35: SUBEXPLORA | B35: 89050 | C35: COL2 | D35: COL2 | E35: EXPLORA | F35: EXPERSNLEV | G35: Director of Design | H35: 0.2 | I35: =48000/12 -> 4000 | J35: 8 | K35: /months | L35: 0 | M35: =J35*I35*H35 -> 6400 | N35: =SUM(L35:M35) -> 6400 | O35: 0.05 | P35: =I35*$H$7 -> 4160 | Q35: 12 | R35: 0 | S35: =P35*O35*Q35 -> 2496 | T35: =SUM(R35:S35) -> 2496 | U35: 0.05 | V35: =I35*$H$7*$H$7 -> 4326.4 | W35: 12 | X35: 0 | Y35: =V35*U35*W35 -> 2595.84 | Z35: =SUM(X35:Y35) -> 2595.84 | AA35: 0.05 | AB35: =I35*$H$7*$H$7*$H$7 -> 4499.456 | AC35: 12 | AD35: 0 | AE35: =AB35*AA35*AC35 -> 2699.6736 | AF35: =SUM(AD35:AE35) -> 2699.6736 | AG35: 0.05 | AH35: =I35*$H$7*$H$7*$H$7*$H$7 -> 4679.4342 | AI35: 8 | AJ35: 0 | AK35: =AH35*AG35*AI35 -> 1871.7737 | AL35: =SUM(AJ35:AK35) -> 1871.7737 | AM35: =L35+R35+X35+AD35+AJ35 -> 0 | AN35: =M35+S35+Y35+AE35+AK35 -> 16063.287 | AO35: =SUM(AM35:AN35) -> 16063.287
A36: SUBEXPLORA | B36: 89050 | C36: COL2 | D36: COL2 | E36: EXPLORA | F36: EXPERSNLEV | G36: Head of Design | H36: 0.2 | I36: 2000 | J36: 8 | K36: /months | L36: 0 | M36: =J36*I36*H36 -> 3200 | N36: =SUM(L36:M36) -> 3200 | O36: 0.1 | P36: =I36*$H$7 -> 2080 | Q36: 12 | R36: 0 | S36: =P36*O36*Q36 -> 2496 | T36: =SUM(R36:S36) -> 2496 | U36: 0.1 | V36: =I36*$H$7*$H$7 -> 2163.2 | W36: 12 | X36: 0 | Y36: =V36*U36*W36 -> 2595.84 | Z36: =SUM(X36:Y36) -> 2595.84 | AA36: 0.1 | AB36: =I36*$H$7*$H$7*$H$7 -> 2249.728 | AC36: 12 | AD36: 0 | AE36: =AB36*AA36*AC36 -> 2699.6736 | AF36: =SUM(AD36:AE36) -> 2699.6736 | AG36: 0.1 | AH36: =I36*$H$7*$H$7*$H$7*$H$7 -> 2339.7171 | AI36: 8 | AJ36: 0 | AK36: =AH36*AG36*AI36 -> 1871.7737 | AL36: =SUM(AJ36:AK36) -> 1871.7737 | AM36: =L36+R36+X36+AD36+AJ36 -> 0 | AN36: =M36+S36+Y36+AE36+AK36 -> 12863.287 | AO36: =SUM(AM36:AN36) -> 12863.287
A37: SUBEXPLORA | B37: 89050 | C37: COL2 | D37: COL2 | E37: EXPLORA | F37: EXPERSNLEV | G37: Purchasing Coordinator | H37: 0.1 | I37: 2000 | J37: 9 | K37: /months | L37: 0 | M37: =J37*I37*H37 -> 1800 | N37: =SUM(L37:M37) -> 1800 | O37: 0.1 | P37: =I37*$H$7 -> 2080 | Q37: 12 | R37: 0 | S37: =P37*O37*Q37 -> 2496 | T37: =SUM(R37:S37) -> 2496 | U37: 0.1 | V37: =I37*$H$7*$H$7 -> 2163.2 | W37: 12 | X37: 0 | Y37: =V37*U37*W37 -> 2595.84 | Z37: =SUM(X37:Y37) -> 2595.84 | AA37: 0.1 | AB37: =I37*$H$7*$H$7*$H$7 -> 2249.728 | AC37: 12 | AD37: 0 | AE37: =AB37*AA37*AC37 -> 2699.6736 | AF37: =SUM(AD37:AE37) -> 2699.6736 | AG37: 0.1 | AH37: =I37*$H$7*$H$7*$H$7*$H$7 -> 2339.7171 | AI37: 8 | AJ37: 0 | AK37: =AH37*AG37*AI37 -> 1871.7737 | AL37: =SUM(AJ37:AK37) -> 1871.7737 | AM37: =L37+R37+X37+AD37+AJ37 -> 0 | AN37: =M37+S37+Y37+AE37+AK37 -> 11463.287 | AO37: =SUM(AM37:AN37) -> 11463.287
A38: SUBEXPLORA | B38: 89050 | C38: COL2 | D38: COL2 | E38: EXPLORA | F38: EXPERSNLEV | G38: Accounting Coordinator | H38: 0.3 | I38: 1250 | J38: 8 | K38: /months | L38: 0 | M38: =J38*I38*H38 -> 3000 | N38: =SUM(L38:M38) -> 3000 | O38: 0.3 | P38: =I38*$H$7 -> 1300 | Q38: 12 | R38: 0 | S38: =P38*O38*Q38 -> 4680 | T38: =SUM(R38:S38) -> 4680 | U38: 0.3 | V38: =I38*$H$7*$H$7 -> 1352 | W38: 12 | X38: 0 | Y38: =V38*U38*W38 -> 4867.2 | Z38: =SUM(X38:Y38) -> 4867.2 | AA38: 0.3 | AB38: =I38*$H$7*$H$7*$H$7 -> 1406.08 | AC38: 12 | AD38: 0 | AE38: =AB38*AA38*AC38 -> 5061.888 | AF38: =SUM(AD38:AE38) -> 5061.888 | AG38: 0.3 | AH38: =I38*$H$7*$H$7*$H$7*$H$7 -> 1462.3232 | AI38: 10 | AJ38: 0 | AK38: =AH38*AG38*AI38 -> 4386.9696 | AL38: =SUM(AJ38:AK38) -> 4386.9696 | AM38: =L38+R38+X38+AD38+AJ38 -> 0 | AN38: =M38+S38+Y38+AE38+AK38 -> 21996.058 | AO38: =SUM(AM38:AN38) -> 21996.058
A39: SUBEXPLORA | B39: 89050 | C39: COL2 | D39: COL2 | E39: EXPLORA | F39: EXPERSNLEV | G39: Accounting Analyst | H39: 0.3 | I39: 1000 | J39: 8 | K39: /months | L39: 0 | M39: =J39*I39*H39 -> 2400 | N39: =SUM(L39:M39) -> 2400 | O39: 0.3 | P39: =I39*$H$7 -> 1040 | Q39: 12 | R39: 0 | S39: =P39*O39*Q39 -> 3744 | T39: =SUM(R39:S39) -> 3744 | U39: 0.3 | V39: =I39*$H$7*$H$7 -> 1081.6 | W39: 12 | X39: 0 | Y39: =V39*U39*W39 -> 3893.76 | Z39: =SUM(X39:Y39) -> 3893.76 | AA39: 0.3 | AB39: =I39*$H$7*$H$7*$H$7 -> 1124.864 | AC39: 12 | AD39: 0 | AE39: =AB39*AA39*AC39 -> 4049.5104 | AF39: =SUM(AD39:AE39) -> 4049.5104 | AG39: 0.3 | AH39: =I39*$H$7*$H$7*$H$7*$H$7 -> 1169.8586 | AI39: 8 | AJ39: 0 | AK39: =AH39*AG39*AI39 -> 2807.6605 | AL39: =SUM(AJ39:AK39) -> 2807.6605 | AM39: =L39+R39+X39+AD39+AJ39 -> 0 | AN39: =M39+S39+Y39+AE39+AK39 -> 16894.931 | AO39: =SUM(AM39:AN39) -> 16894.931
A40: SUBEXPLORA | B40: 89050 | C40: COL2 | D40: COL2 | E40: EXPLORA | F40: EXPERSNLEV | G40: Finance Coordinator | H40: 0.1 | I40: 1250 | J40: 9 | K40: /months | L40: 0 | M40: =J40*I40*H40 -> 1125 | N40: =SUM(L40:M40) -> 1125 | O40: 0.1 | P40: =I40*$H$7 -> 1300 | Q40: 12 | R40: 0 | S40: =P40*O40*Q40 -> 1560 | T40: =SUM(R40:S40) -> 1560 | U40: 0.1 | V40: =I40*$H$7*$H$7 -> 1352 | W40: 12 | X40: 0 | Y40: =V40*U40*W40 -> 1622.4 | Z40: =SUM(X40:Y40) -> 1622.4 | AA40: 0.1 | AB40: =I40*$H$7*$H$7*$H$7 -> 1406.08 | AC40: 12 | AD40: 0 | AE40: =AB40*AA40*AC40 -> 1687.296 | AF40: =SUM(AD40:AE40) -> 1687.296 | AG40: 0.1 | AH40: =I40*$H$7*$H$7*$H$7*$H$7 -> 1462.3232 | AI40: 12 | AJ40: 0 | AK40: =AH40*AG40*AI40 -> 1754.7878 | AL40: =SUM(AJ40:AK40) -> 1754.7878 | AM40: =L40+R40+X40+AD40+AJ40 -> 0 | AN40: =M40+S40+Y40+AE40+AK40 -> 7749.4838 | AO40: =SUM(AM40:AN40) -> 7749.4838
A41: SUBEXPLORA | B41: 89050 | C41: COL2 | D41: COL2 | E41: EXPLORA | F41: EXPERSNLEV | G41: Finance Analyst | H41: 0.1 | I41: 1000 | J41: 9 | K41: /months | L41: 0 | M41: =J41*I41*H41 -> 900 | N41: =SUM(L41:M41) -> 900 | O41: 0.1 | P41: =I41*$H$7 -> 1040 | Q41: 12 | R41: 0 | S41: =P41*O41*Q41 -> 1248 | T41: =SUM(R41:S41) -> 1248 | U41: 0.1 | V41: =I41*$H$7*$H$7 -> 1081.6 | W41: 12 | X41: 0 | Y41: =V41*U41*W41 -> 1297.92 | Z41: =SUM(X41:Y41) -> 1297.92 | AA41: 0.1 | AB41: =I41*$H$7*$H$7*$H$7 -> 1124.864 | AC41: 12 | AD41: 0 | AE41: =AB41*AA41*AC41 -> 1349.8368 | AF41: =SUM(AD41:AE41) -> 1349.8368 | AG41: 0.1 | AH41: =I41*$H$7*$H$7*$H$7*$H$7 -> 1169.8586 | AI41: 9 | AJ41: 0 | AK41: =AH41*AG41*AI41 -> 1052.8727 | AL41: =SUM(AJ41:AK41) -> 1052.8727 | AM41: =L41+R41+X41+AD41+AJ41 -> 0 | AN41: =M41+S41+Y41+AE41+AK41 -> 5848.6295 | AO41: =SUM(AM41:AN41) -> 5848.6295
A42: SUBEXPLORA | B42: 89050 | C42: COL2 | D42: COL2 | E42: EXPLORA | F42: EXPERSNLEV | G42: Legal Director | H42: 0.05 | I42: =48000/12 -> 4000 | J42: 9 | K42: /months | L42: 0 | M42: =J42*I42*H42 -> 1800 | N42: =SUM(L42:M42) -> 1800 | O42: 0.05 | P42: =I42*$H$7 -> 4160 | Q42: 12 | R42: 0 | S42: =P42*O42*Q42 -> 2496 | T42: =SUM(R42:S42) -> 2496 | U42: 0.05 | V42: =I42*$H$7*$H$7 -> 4326.4 | W42: 12 | X42: 0 | Y42: =V42*U42*W42 -> 2595.84 | Z42: =SUM(X42:Y42) -> 2595.84 | AA42: 0.05 | AB42: =I42*$H$7*$H$7*$H$7 -> 4499.456 | AC42: 12 | AD42: 0 | AE42: =AB42*AA42*AC42 -> 2699.6736 | AF42: =SUM(AD42:AE42) -> 2699.6736 | AG42: 0.05 | AH42: =I42*$H$7*$H$7*$H$7*$H$7 -> 4679.4342 | AI42: 9 | AJ42: 0 | AK42: =AH42*AG42*AI42 -> 2105.7454 | AL42: =SUM(AJ42:AK42) -> 2105.7454 | AM42: =L42+R42+X42+AD42+AJ42 -> 0 | AN42: =M42+S42+Y42+AE42+AK42 -> 11697.259 | AO42: =SUM(AM42:AN42) -> 11697.259
A43: SUBEXPLORA | B43: 89050 | C43: COL2 | D43: COL2 | E43: EXPLORA | F43: EXPERSNLEV | G43: Legal Professional | H43: 0.3 | I43: =12150/12 -> 1012.5 | J43: 9 | K43: /months | L43: 0 | M43: =J43*I43*H43 -> 2733.75 | N43: =SUM(L43:M43) -> 2733.75 | O43: 0.3 | P43: =I43*$H$7 -> 1053 | Q43: 12 | R43: 0 | S43: =P43*O43*Q43 -> 3790.8 | T43: =SUM(R43:S43) -> 3790.8 | U43: 0.3 | V43: =I43*$H$7*$H$7 -> 1095.12 | W43: 12 | X43: 0 | Y43: =V43*U43*W43 -> 3942.432 | Z43: =SUM(X43:Y43) -> 3942.432 | AA43: 0.3 | AB43: =I43*$H$7*$H$7*$H$7 -> 1138.9248 | AC43: 12 | AD43: 0 | AE43: =AB43*AA43*AC43 -> 4100.1293 | AF43: =SUM(AD43:AE43) -> 4100.1293 | AG43: 0.3 | AH43: =I43*$H$7*$H$7*$H$7*$H$7 -> 1184.4818 | AI43: 9 | AJ43: 0 | AK43: =AH43*AG43*AI43 -> 3198.1008 | AL43: =SUM(AJ43:AK43) -> 3198.1008 | AM43: =L43+R43+X43+AD43+AJ43 -> 0 | AN43: =M43+S43+Y43+AE43+AK43 -> 17765.212 | AO43: =SUM(AM43:AN43) -> 17765.212
G44: Subtotal HQ Personnel | L44: =SUM(L16:L43) -> 228716.67 | M44: =SUM(M16:M43) -> 67092.083 | N44: =SUM(N16:N43) -> 295808.75 | R44: =SUM(R16:R43) -> 313768 | S44: =SUM(S16:S43) -> 48302.8 | T44: =SUM(T16:T43) -> 362070.8 | X44: =SUM(X16:X43) -> 326318.72 | Y44: =SUM(Y16:Y43) -> 50234.912 | Z44: =SUM(Z16:Z43) -> 376553.63 | AD44: =SUM(AD16:AD43) -> 339371.47 | AE44: =SUM(AE16:AE43) -> 52244.308 | AF44: =SUM(AF16:AF43) -> 391615.78 | AJ44: =SUM(AJ16:AJ43) -> 250651.95 | AK44: =SUM(AK16:AK43) -> 54457.403 | AL44: =SUM(AL16:AL43) -> 305109.35 | AM44: =SUM(AM16:AM43) -> 1458826.8 | AN44: =SUM(AN16:AN43) -> 272331.51 | AO44: =SUM(AO16:AO43) -> 1731158.3
G46: Field Personnel | H46: LOE
A47: SUBEXPLORA | B47: 89050 | C47: COL2 | D47: COL2 | E47: EXPLORA | F47: EXPPERSNL | G47: School Research Leaders (16 People) | H47: 1 | I47: =(12000/12)*16 -> 16000 | J47: 2 | K47: /months | L47: =J47*I47*H47 -> 32000 | M47: 0 | N47: =SUM(L47:M47) -> 32000 | O47: 1 | P47: =I47*$H$7 -> 16640 | Q47: 12 | R47: =O47*P47*Q47 -> 199680 | S47: 0 | T47: =SUM(R47:S47) -> 199680 | U47: =+O47 -> 1 | V47: =I47*$H$7*$H$7 -> 17305.6 | W47: 12 | X47: =U47*V47*W47 -> 207667.2 | Y47: 0 | Z47: =SUM(X47:Y47) -> 207667.2 | AA47: =U47 -> 1 | AB47: =I47*$H$7*$H$7*$H$7 -> 17997.824 | AC47: 12 | AD47: =AA47*AB47*AC47 -> 215973.89 | AE47: 0 | AF47: =SUM(AD47:AE47) -> 215973.89 | AG47: 1 | AH47: =I47*$H$7*$H$7*$H$7*$H$7 -> 18717.737 | AI47: 4 | AJ47: =AG47*AH47*AI47 -> 74870.948 | AK47: 0 | AL47: =SUM(AJ47:AK47) -> 74870.948 | AM47: =L47+R47+X47+AD47+AJ47 -> 730192.04 | AN47: =M47+S47+Y47+AE47+AK47 -> 0 | AO47: =SUM(AM47:AN47) -> 730192.04
A48: SUBEXPLORA | B48: 89050 | C48: COL2 | D48: COL2 | E48: EXPLORA | F48: EXPPERSNL | G48: Training Professionals (3 People) | H48: 1 | I48: =(15000/12)*3 -> 3750 | J48: 8 | K48: /months | L48: =J48*I48*H48 -> 30000 | M48: 0 | N48: =SUM(L48:M48) -> 30000 | O48: =H48 -> 1 | P48: =I48*$H$7 -> 3900 | Q48: 12 | R48: =O48*P48*Q48 -> 46800 | S48: 0 | T48: =SUM(R48:S48) -> 46800 | U48: =H48 -> 1 | V48: =I48*$H$7*$H$7 -> 4056 | W48: 12 | X48: =U48*V48*W48 -> 48672 | Y48: 0 | Z48: =SUM(X48:Y48) -> 48672 | AA48: =U48 -> 1 | AB48: =I48*$H$7*$H$7*$H$7 -> 4218.24 | AC48: 12 | AD48: =AA48*AB48*AC48 -> 50618.88 | AE48: 0 | AF48: =SUM(AD48:AE48) -> 50618.88 | AG48: =AA48 -> 1 | AH48: =I48*$H$7*$H$7*$H$7*$H$7 -> 4386.9696 | AI48: 0 | AJ48: =AG48*AH48*AI48 -> 0 | AK48: 0 | AL48: =SUM(AJ48:AK48) -> 0 | AM48: =L48+R48+X48+AD48+AJ48 -> 176090.88 | AN48: =M48+S48+Y48+AE48+AK48 -> 0 | AO48: =SUM(AM48:AN48) -> 176090.88
G49: Subtotal Field Personnel | L49: =SUM(L47:L48) -> 62000 | M49: =SUM(M47:M48) -> 0 | N49: =SUM(N47:N48) -> 62000 | R49: =SUM(R47:R48) -> 246480 | S49: =SUM(S47:S48) -> 0 | T49: =SUM(T47:T48) -> 246480 | X49: =SUM(X47:X48) -> 256339.2 | Y49: =SUM(Y47:Y48) -> 0 | Z49: =SUM(Z47:Z48) -> 256339.2 | AD49: =SUM(AD47:AD48) -> 266592.77 | AE49: =SUM(AE47:AE48) -> 0 | AF49: =SUM(AF47:AF48) -> 266592.77 | AJ49: =SUM(AJ47:AJ48) -> 74870.948 | AK49: =SUM(AK47:AK48) -> 0 | AL49: =SUM(AL47:AL48) -> 74870.948 | AM49: =SUM(AM47:AM48) -> 906282.92 | AN49: =SUM(AN47:AN48) -> 0 | AO49: =SUM(AO47:AO48) -> 906282.92
G51: Personnel Total | L51: =L49+L44 -> 290716.67 | M51: =M49+M44 -> 67092.083 | N51: =N49+N44 -> 357808.75 | R51: =R49+R44 -> 560248 | S51: =S49+S44 -> 48302.8 | T51: =T49+T44 -> 608550.8 | X51: =X49+X44 -> 582657.92 | Y51: =Y49+Y44 -> 50234.912 | Z51: =Z49+Z44 -> 632892.83 | AD51: =AD49+AD44 -> 605964.24 | AE51: =AE49+AE44 -> 52244.308 | AF51: =AF49+AF44 -> 658208.55 | AJ51: =AJ49+AJ44 -> 325522.89 | AK51: =AK49+AK44 -> 54457.403 | AL51: =AL49+AL44 -> 379980.3 | AM51: =AM49+AM44 -> 2365109.7 | AN51: =AN49+AN44 -> 272331.51 | AO51: =AO49+AO44 -> 2637441.2
G53: Fringe Benefits
A54: SUBEXPLORA | B54: 89050 | C54: COL2 | D54: COL2 | E54: EXPLORA | F54: EXPRFRINGE/ EXFRINGEL | G54: Fringe Benefits – Colombia HQ and Field Staff (above $2,600 monthly) | H54: 0.53864 | L54: =$H$54*(L16+L17+L24+L28+L29+L30+L32+L33+L35+L42) -> 54182.695 | M54: =$H$54*(M16+M17+M24+M28+M29+M30+M32+M33+M35+M42) -> 22802.427 | N54: =M54+L54 -> 76985.122 | O54: =H54 -> 0.53864 | R54: =$H$54*(R16+R17+R24+R28+R29+R30+R32+R33+R35+R42) -> 68174.588 | S54: =$H$54*(S16+S17+S24+S28+S29+S30+S32+S33+S35+S42) -> 12548.157 | T54: =S54+R54 -> 80722.745 | U54: =H54 -> 0.53864 | X54: =$H$54*(X16+X17+X24+X28+X29+X30+X32+X33+X35+X42) -> 70901.571 | Y54: =$H$54*(Y16+Y17+Y24+Y28+Y29+Y30+Y32+Y33+Y35+Y42) -> 13050.084 | Z54: =Y54+X54 -> 83951.655 | AA54: =H54 -> 0.53864 | AD54: =$H$54*(AD16+AD17+AD24+AD28+AD29+AD30+AD32+AD33+AD35+AD42) -> 73737.634 | AE54: =$H$54*(AE16+AE17+AE24+AE28+AE29+AE30+AE32+AE33+AE35+AE42) -> 13572.087 | AF54: =AE54+AD54 -> 87309.721 | AG54: =H54 -> 0.53864 | AJ54: =$H$54*(AJ16+AJ17+AJ24+AJ28+AJ29+AJ30+AJ32+AJ33+AJ35+AJ42) -> 59395.25 | AK54: =$H$54*(AK16+AK17+AK24+AK28+AK29+AK30+AK32+AK33+AK35+AK42) -> 16929.563 | AL54: =AK54+AJ54 -> 76324.813 | AM54: =L54+R54+X54+AD54+AJ54 -> 326391.74 | AN54: =M54+S54+Y54+AE54+AK54 -> 78902.318 | AO54: =SUM(AM54:AN54) -> 405294.06
A55: SUBEXPLORA | B55: 89050 | C55: COL2 | D55: COL2 | E55: EXPLORA | F55: EXPRFRINGE/ EXFRINGEL | G55: Fringe Benefits - Colombia HQ and Field Staff (below $2,600 monthly) | H55: 0.40364 | L55: =$H$55*(L47+L48+L19+L20+L21+L22+L23+L25+L26+L27+L31+L34+L36+L37+L38+L39+L40+L41+L43) -> 76742.055 | M55: =$H$55*(M47+M48+M19+M20+M21+M22+M23+M25+M26+M27+M31+M34+M36+M37+M38+M39+M40+M41+M43) -> 9993.6218 | N55: =M55+L55 -> 86735.677 | O55: =H55 -> 0.40364 | R55: =$H$55*(R47+R48+R19+R20+R21+R22+R23+R25+R26+R27+R31+R34+R36+R37+R38+R39+R40+R41+R43) -> 175050.6 | S55: =$H$55*(S47+S48+S19+S20+S21+S22+S23+S25+S26+S27+S31+S34+S36+S37+S38+S39+S40+S41+S43) -> 10093.745 | T55: =S55+R55 -> 185144.34 | U55: =H55 -> 0.40364 | X55: =$H$55*(X47+X48+X19+X20+X21+X22+X23+X25+X26+X27+X31+X34+X36+X37+X38+X39+X40+X41+X43) -> 182052.62 | Y55: =$H$55*(Y47+Y48+Y19+Y20+Y21+Y22+Y23+Y25+Y26+Y27+Y31+Y34+Y36+Y37+Y38+Y39+Y40+Y41+Y43) -> 10497.495 | Z55: =Y55+X55 -> 192550.11 | AA55: =H55 -> 0.40364 | AD55: =$H$55*(AD47+AD48+AD19+AD20+AD21+AD22+AD23+AD25+AD26+AD27+AD31+AD34+AD36+AD37+AD38+AD39+AD40+AD41+AD43) -> 189334.72 | AE55: =$H$55*(AE47+AE48+AE19+AE20+AE21+AE22+AE23+AE25+AE26+AE27+AE31+AE34+AE36+AE37+AE38+AE39+AE40+AE41+AE43) -> 10917.394 | AF55: =AE55+AD55 -> 200252.12 | AG55: =H55 -> 0.40364 | AJ55: =$H$55*(AJ47+AJ48+AJ19+AJ20+AJ21+AJ22+AJ23+AJ25+AJ26+AJ27+AJ31+AJ34+AJ36+AJ37+AJ38+AJ39+AJ40+AJ41+AJ43) -> 86885.114 | AK55: =$H$55*(AK47+AK48+AK19+AK20+AK21+AK22+AK23+AK25+AK26+AK27+AK31+AK34+AK36+AK37+AK38+AK39+AK40+AK41+AK43) -> 9294.7004 | AL55: =AK55+AJ55 -> 96179.815 | AM55: =L55+R55+X55+AD55+AJ55 -> 710065.11 | AN55: =M55+S55+Y55+AE55+AK55 -> 50796.956 | AO55: =SUM(AM55:AN55) -> 760862.06
G56: Fringe Benefits Total | L56: =SUM(L54:L55) -> 130924.75 | M56: =SUM(M54:M55) -> 32796.049 | N56: =SUM(N54:N55) -> 163720.8 | R56: =SUM(R54:R55) -> 243225.18 | S56: =SUM(S54:S55) -> 22641.902 | T56: =SUM(T54:T55) -> 265867.08 | X56: =SUM(X54:X55) -> 252954.19 | Y56: =SUM(Y54:Y55) -> 23547.578 | Z56: =SUM(Z54:Z55) -> 276501.77 | AD56: =SUM(AD54:AD55) -> 263072.36 | AE56: =SUM(AE54:AE55) -> 24489.481 | AF56: =SUM(AF54:AF55) -> 287561.84 | AJ56: =SUM(AJ54:AJ55) -> 146280.36 | AK56: =SUM(AK54:AK55) -> 26224.263 | AL56: =SUM(AL54:AL55) -> 172504.63 | AM56: =SUM(AM54:AM55) -> 1036456.8 | AN56: =SUM(AN54:AN55) -> 129699.27 | AO56: =SUM(AO54:AO55) -> 1166156.1
G58: Travel
G60: HQ Staff Travel for School Research
A61: SUBEXPLORA | B61: 89050 | C61: COL2 | D61: COL2 | E61: EXPLORA | F61: EXPHQTRVL | G61: HQ Staff - Local Transportation (Airfare, Taxis, & Rental Car/Driver) for Director | H61: =1*9 -> 9 | I61: 250 | J61: 1 | K61: /trip | L61: =I61*H61*J61 -> 2250 | M61: 0 | N61: =SUM(L61:M61) -> 2250 | O61: =9*2 -> 18 | P61: =I61*$H$6 -> 257.5 | Q61: 1 | R61: =O61*P61*Q61 -> 4635 | S61: 0 | T61: =SUM(R61:S61) -> 4635 | U61: =9*2 -> 18 | V61: =I61*$H$6*$H$6 -> 265.225 | W61: 1 | X61: =U61*V61*W61 -> 4774.05 | Y61: 0 | Z61: =SUM(X61:Y61) -> 4774.05 | AA61: =1*9 -> 9 | AB61: =I61*$H$6*$H$6*$H$6 -> 273.18175 | AC61: 1 | AD61: =AA61*AB61*AC61 -> 2458.6358 | AE61: 0 | AF61: =SUM(AD61:AE61) -> 2458.6358 | AG61: =1*9 -> 9 | AH61: =I61*$H$6*$H$6*$H$6*$H$6 -> 281.3772 | AI61: 1 | AJ61: =AG61*AH61*AI61 -> 2532.3948 | AK61: 0 | AL61: =SUM(AJ61:AK61) -> 2532.3948 | AM61: =L61+R61+X61+AD61+AJ61 -> 16650.081 | AN61: =M61+S61+Y61+AE61+AK61 -> 0 | AO61: =SUM(AM61:AN61) -> 16650.081
A62: SUBEXPLORA | B62: 89050 | C62: COL2 | D62: COL2 | E62: EXPLORA | F62: EXPHQTRVL | G62: HQ Staff - Meals and Incidentals for Director | H62: =1*9 -> 9 | I62: 40 | J62: 5 | K62: /day | L62: =I62*H62*J62 -> 1800 | M62: 0 | N62: =SUM(L62:M62) -> 1800 | O62: =9*2 -> 18 | P62: =I62*$H$6 -> 41.2 | Q62: 5 | R62: =O62*P62*Q62 -> 3708 | S62: 0 | T62: =SUM(R62:S62) -> 3708 | U62: =9*2 -> 18 | V62: =I62*$H$6*$H$6 -> 42.436 | W62: 4 | X62: =U62*V62*W62 -> 3055.392 | Y62: 0 | Z62: =SUM(X62:Y62) -> 3055.392 | AA62: =1*9 -> 9 | AB62: =I62*$H$6*$H$6*$H$6 -> 43.70908 | AC62: 4 | AD62: =AA62*AB62*AC62 -> 1573.5269 | AE62: 0 | AF62: =SUM(AD62:AE62) -> 1573.5269 | AG62: =1*9 -> 9 | AH62: =I62*$H$6*$H$6*$H$6*$H$6 -> 45.020352 | AI62: 4 | AJ62: =AG62*AH62*AI62 -> 1620.7327 | AK62: 0 | AL62: =SUM(AJ62:AK62) -> 1620.7327 | AM62: =L62+R62+X62+AD62+AJ62 -> 11757.652 | AN62: =M62+S62+Y62+AE62+AK62 -> 0 | AO62: =SUM(AM62:AN62) -> 11757.652
A63: SUBEXPLORA | B63: 89050 | C63: COL2 | D63: COL2 | E63: EXPLORA | F63: EXPHQTRVL | G63: HQ Staff - Lodging for Director | H63: =1*9 -> 9 | I63: 80 | J63: 4 | K63: /day | L63: =I63*H63*J63 -> 2880 | M63: 0 | N63: =SUM(L63:M63) -> 2880 | O63: =9*2 -> 18 | P63: =I63*$H$6 -> 82.4 | Q63: 4 | R63: =O63*P63*Q63 -> 5932.8 | S63: 0 | T63: =SUM(R63:S63) -> 5932.8 | U63: =9*2 -> 18 | V63: =I63*$H$6*$H$6 -> 84.872 | W63: 3 | X63: =U63*V63*W63 -> 4583.088 | Y63: 0 | Z63: =SUM(X63:Y63) -> 4583.088 | AA63: =1*9 -> 9 | AB63: =I63*$H$6*$H$6*$H$6 -> 87.41816 | AC63: 3 | AD63: =AA63*AB63*AC63 -> 2360.2903 | AE63: 0 | AF63: =SUM(AD63:AE63) -> 2360.2903 | AG63: =1*9 -> 9 | AH63: =I63*$H$6*$H$6*$H$6*$H$6 -> 90.040705 | AI63: 3 | AJ63: =AG63*AH63*AI63 -> 2431.099 | AK63: 0 | AL63: =SUM(AJ63:AK63) -> 2431.099 | AM63: =L63+R63+X63+AD63+AJ63 -> 18187.277 | AN63: =M63+S63+Y63+AE63+AK63 -> 0 | AO63: =SUM(AM63:AN63) -> 18187.277
A64: SUBEXPLORA | B64: 89050 | C64: COL2 | D64: COL2 | E64: EXPLORA | F64: EXPHQTRVL | G64: HQ Staff - Other Travel Related Expenses for Director | H64: =1*9 -> 9 | I64: 25 | J64: 1 | K64: /trip | L64: =I64*H64*J64 -> 225 | M64: 0 | N64: =SUM(L64:M64) -> 225 | O64: =9*2 -> 18 | P64: =I64*$H$6 -> 25.75 | Q64: 1 | R64: =O64*P64*Q64 -> 463.5 | S64: 0 | T64: =SUM(R64:S64) -> 463.5 | U64: =9*2 -> 18 | V64: =I64*$H$6*$H$6 -> 26.5225 | W64: 1 | X64: =U64*V64*W64 -> 477.405 | Y64: 0 | Z64: =SUM(X64:Y64) -> 477.405 | AA64: =1*9 -> 9 | AB64: =I64*$H$6*$H$6*$H$6 -> 27.318175 | AC64: 1 | AD64: =AA64*AB64*AC64 -> 245.86357 | AE64: 0 | AF64: =SUM(AD64:AE64) -> 245.86357 | AG64: =1*9 -> 9 | AH64: =I64*$H$6*$H$6*$H$6*$H$6 -> 28.13772 | AI64: 1 | AJ64: =AG64*AH64*AI64 -> 253.23948 | AK64: 0 | AL64: =SUM(AJ64:AK64) -> 253.23948 | AM64: =L64+R64+X64+AD64+AJ64 -> 1665.0081 | AN64: =M64+S64+Y64+AE64+AK64 -> 0 | AO64: =SUM(AM64:AN64) -> 1665.0081
G65: Subtotal HQ Staff Travel | L65: =SUM(L61:L64) -> 7155 | M65: =SUM(M61:M64) -> 0 | N65: =SUM(N61:N64) -> 7155 | R65: =SUM(R61:R64) -> 14739.3 | S65: =SUM(S61:S64) -> 0 | T65: =SUM(T61:T64) -> 14739.3 | X65: =SUM(X61:X64) -> 12889.935 | Y65: =SUM(Y61:Y64) -> 0 | Z65: =SUM(Z61:Z64) -> 12889.935 | AD65: =SUM(AD61:AD64) -> 6638.3165 | AE65: =SUM(AE61:AE64) -> 0 | AF65: =SUM(AF61:AF64) -> 6638.3165 | AJ65: =SUM(AJ61:AJ64) -> 6837.466 | AK65: =SUM(AK61:AK64) -> 0 | AL65: =SUM(AL61:AL64) -> 6837.466 | AM65: =SUM(AM61:AM64) -> 48260.018 | AN65: =SUM(AN61:AN64) -> 0 | AO65: =SUM(AO61:AO64) -> 48260.018
G67: Field Travel
G68: T.1 Field Staff Travel for Site Visits and M&E
A69: SUBEXPLORA | B69: 89050 | C69: COL2 | D69: COL2 | E69: EXPLORA | F69: EXPT1TRVL | G69: Local Transportation (Airfare, Taxis, & Rental Car/Driver) for Site Visits and M&E | H69: =2*9 -> 18 | I69: 250 | J69: 1 | K69: /trip | L69: =H69*J69*I69 -> 4500 | M69: 0 | N69: =SUM(L69:M69) -> 4500 | O69: =9*4 -> 36 | P69: =I69*$H$6 -> 257.5 | Q69: 1 | R69: =P69*O69*Q69 -> 9270 | S69: 0 | T69: =SUM(R69:S69) -> 9270 | U69: =9*4 -> 36 | V69: =I69*$H$6*$H$6 -> 265.225 | W69: 1 | X69: =U69*V69*W69 -> 9548.1 | Y69: 0 | Z69: =SUM(X69:Y69) -> 9548.1 | AA69: =9*4 -> 36 | AB69: =I69*$H$6*$H$6*$H$6 -> 273.18175 | AC69: 1 | AD69: =AA69*AB69*AC69 -> 9834.543 | AE69: 0 | AF69: =SUM(AD69:AE69) -> 9834.543 | AG69: =2*9 -> 18 | AH69: =I69*$H$6*$H$6*$H$6*$H$6 -> 281.3772 | AI69: 1 | AJ69: =AG69*AH69*AI69 -> 5064.7896 | AK69: 0 | AL69: =SUM(AJ69:AK69) -> 5064.7896 | AM69: =L69+R69+X69+AD69+AJ69 -> 38217.433 | AN69: =M69+S69+Y69+AE69+AK69 -> 0 | AO69: =SUM(AM69:AN69) -> 38217.433
A70: SUBEXPLORA | B70: 89050 | C70: COL2 | D70: COL2 | E70: EXPLORA | F70: EXPT1TRVL | G70: Meals and Incidentals for Site Visits and M&E | H70: =2*9 -> 18 | I70: 40 | J70: 5 | K70: /trip | L70: =H70*J70*I70 -> 3600 | M70: 0 | N70: =SUM(L70:M70) -> 3600 | O70: =9*4 -> 36 | P70: =I70*$H$6 -> 41.2 | Q70: 5 | R70: =P70*O70*Q70 -> 7416 | S70: 0 | T70: =SUM(R70:S70) -> 7416 | U70: =9*4 -> 36 | V70: =I70*$H$6*$H$6 -> 42.436 | W70: 5 | X70: =U70*V70*W70 -> 7638.48 | Y70: 0 | Z70: =SUM(X70:Y70) -> 7638.48 | AA70: =9*4 -> 36 | AB70: =I70*$H$6*$H$6*$H$6 -> 43.70908 | AC70: 5 | AD70: =AA70*AB70*AC70 -> 7867.6344 | AE70: 0 | AF70: =SUM(AD70:AE70) -> 7867.6344 | AG70: =2*9 -> 18 | AH70: =I70*$H$6*$H$6*$H$6*$H$6 -> 45.020352 | AI70: 5 | AJ70: =AG70*AH70*AI70 -> 4051.8317 | AK70: 0 | AL70: =SUM(AJ70:AK70) -> 4051.8317 | AM70: =L70+R70+X70+AD70+AJ70 -> 30573.946 | AN70: =M70+S70+Y70+AE70+AK70 -> 0 | AO70: =SUM(AM70:AN70) -> 30573.946
A71: SUBEXPLORA | B71: 89050 | C71: COL2 | D71: COL2 | E71: EXPLORA | F71: EXPT1TRVL | G71: Lodging for Site Visits and M&E | H71: =2*9 -> 18 | I71: 80 | J71: 5 | K71: /day | L71: =H71*J71*I71 -> 7200 | M71: 0 | N71: =SUM(L71:M71) -> 7200 | O71: =9*4 -> 36 | P71: =I71*$H$6 -> 82.4 | Q71: 5 | R71: =P71*O71*Q71 -> 14832 | S71: 0 | T71: =SUM(R71:S71) -> 14832 | U71: =9*4 -> 36 | V71: =I71*$H$6*$H$6 -> 84.872 | W71: 5 | X71: =U71*V71*W71 -> 15276.96 | Y71: 0 | Z71: =SUM(X71:Y71) -> 15276.96 | AA71: =9*4 -> 36 | AB71: =I71*$H$6*$H$6*$H$6 -> 87.41816 | AC71: 5 | AD71: =AA71*AB71*AC71 -> 15735.269 | AE71: 0 | AF71: =SUM(AD71:AE71) -> 15735.269 | AG71: =2*9 -> 18 | AH71: =I71*$H$6*$H$6*$H$6*$H$6 -> 90.040705 | AI71: 5 | AJ71: =AG71*AH71*AI71 -> 8103.6634 | AK71: 0 | AL71: =SUM(AJ71:AK71) -> 8103.6634 | AM71: =L71+R71+X71+AD71+AJ71 -> 61147.892 | AN71: =M71+S71+Y71+AE71+AK71 -> 0 | AO71: =SUM(AM71:AN71) -> 61147.892
A72: SUBEXPLORA | B72: 89050 | C72: COL2 | D72: COL2 | E72: EXPLORA | F72: EXPT1TRVL | G72: Other Travel Related Expenses for Site Visits and M&E | H72: =2*9 -> 18 | I72: 25 | J72: 1 | K72: /trip | L72: =H72*J72*I72 -> 450 | M72: 0 | N72: =SUM(L72:M72) -> 450 | O72: =9*4 -> 36 | P72: =I72*$H$6 -> 25.75 | Q72: 1 | R72: =P72*O72*Q72 -> 927 | S72: 0 | T72: =SUM(R72:S72) -> 927 | U72: =9*4 -> 36 | V72: =I72*$H$6*$H$6 -> 26.5225 | W72: 1 | X72: =U72*V72*W72 -> 954.81 | Y72: 0 | Z72: =SUM(X72:Y72) -> 954.81 | AA72: =9*4 -> 36 | AB72: =I72*$H$6*$H$6*$H$6 -> 27.318175 | AC72: 1 | AD72: =AA72*AB72*AC72 -> 983.4543 | AE72: 0 | AF72: =SUM(AD72:AE72) -> 983.4543 | AG72: =2*9 -> 18 | AH72: =I72*$H$6*$H$6*$H$6*$H$6 -> 28.13772 | AI72: 1 | AJ72: =AG72*AH72*AI72 -> 506.47896 | AK72: 0 | AL72: =SUM(AJ72:AK72) -> 506.47896 | AM72: =L72+R72+X72+AD72+AJ72 -> 3821.7433 | AN72: =M72+S72+Y72+AE72+AK72 -> 0 | AO72: =SUM(AM72:AN72) -> 3821.7433
G74: T.2 Travel for the Streamlining of School Research Processes in Educational Institutions
A75: SUBEXPLORA | B75: 89050 | C75: COL2 | D75: COL2 | E75: EXPLORA | F75: EXPT2TRVL | G75: Local Transportation (Airfare, Taxis, & Rental Car/Driver) for School Research Leaders & Professionals, and Training Professionals | H75: 0 | I75: 250 | J75: 1 | K75: /trip | L75: =H75*I75*J75 -> 0 | M75: 0 | N75: =SUM(L75:M75) -> 0 | O75: 0 | P75: =I75*$H$6 -> 257.5 | Q75: 1 | R75: =P75*O75*Q75 -> 0 | S75: 0 | T75: =SUM(R75:S75) -> 0 | U75: =(8+8+3)*2 -> 38 | V75: =I75*$H$6*$H$6 -> 265.225 | W75: 1 | X75: =U75*V75*W75 -> 10078.55 | Y75: 0 | Z75: =SUM(X75:Y75) -> 10078.55 | AA75: =(8+8+3)*2 -> 38 | AB75: =I75*$H$6*$H$6*$H$6 -> 273.18175 | AC75: 1 | AD75: =AA75*AB75 -> 10380.907 | AE75: 0 | AF75: =SUM(AD75:AE75) -> 10380.907 | AG75: 0 | AH75: =I75*$H$6*$H$6*$H$6*$H$6 -> 281.3772 | AI75: 1 | AJ75: =AG75*AH75 -> 0 | AK75: 0 | AL75: =SUM(AJ75:AK75) -> 0 | AM75: =L75+R75+X75+AD75+AJ75 -> 20459.457 | AN75: =M75+S75+Y75+AE75+AK75 -> 0 | AO75: =SUM(AM75:AN75) -> 20459.457
A76: SUBEXPLORA | B76: 89050 | C76: COL2 | D76: COL2 | E76: EXPLORA | F76: EXPT2TRVL | G76: Meals and Incidentals for School Research Leaders & Professionals, and Training Professionals | H76: 0 | I76: 40 | J76: 6 | K76: /day | L76: =H76*I76*J76 -> 0 | M76: 0 | N76: =SUM(L76:M76) -> 0 | O76: 0 | P76: =I76*$H$6 -> 41.2 | Q76: 6 | R76: =P76*O76*Q76 -> 0 | S76: 0 | T76: =SUM(R76:S76) -> 0 | U76: =(8+8+3)*2 -> 38 | V76: =I76*$H$6*$H$6 -> 42.436 | W76: 6 | X76: =U76*V76*W76 -> 9675.408 | Y76: 0 | Z76: =SUM(X76:Y76) -> 9675.408 | AA76: =(8+8+3)*2 -> 38 | AB76: =I76*$H$6*$H$6*$H$6 -> 43.70908 | AC76: 6 | AD76: =AA76*AB76 -> 1660.945 | AE76: 0 | AF76: =SUM(AD76:AE76) -> 1660.945 | AG76: 0 | AH76: =I76*$H$6*$H$6*$H$6*$H$6 -> 45.020352 | AI76: 6 | AJ76: =AG76*AH76 -> 0 | AK76: 0 | AL76: =SUM(AJ76:AK76) -> 0 | AM76: =L76+R76+X76+AD76+AJ76 -> 11336.353 | AN76: =M76+S76+Y76+AE76+AK76 -> 0 | AO76: =SUM(AM76:AN76) -> 11336.353
A77: SUBEXPLORA | B77: 89050 | C77: COL2 | D77: COL2 | E77: EXPLORA | F77: EXPT2TRVL | G77: Lodging for School Research Leaders & Professionals, and Training Professionals | H77: 0 | I77: 80 | J77: 5 | K77: /day | L77: =H77*I77*J77 -> 0 | M77: 0 | N77: =SUM(L77:M77) -> 0 | O77: 0 | P77: =I77*$H$6 -> 82.4 | Q77: 5 | R77: =P77*O77*Q77 -> 0 | S77: 0 | T77: =SUM(R77:S77) -> 0 | U77: =(8+8+3)*2 -> 38 | V77: =I77*$H$6*$H$6 -> 84.872 | W77: 5 | X77: =U77*V77*W77 -> 16125.68 | Y77: 0 | Z77: =SUM(X77:Y77) -> 16125.68 | AA77: =(8+8+3)*2 -> 38 | AB77: =I77*$H$6*$H$6*$H$6 -> 87.41816 | AC77: 5 | AD77: =AA77*AB77 -> 3321.8901 | AE77: 0 | AF77: =SUM(AD77:AE77) -> 3321.8901 | AG77: 0 | AH77: =I77*$H$6*$H$6*$H$6*$H$6 -> 90.040705 | AI77: 5 | AJ77: =AG77*AH77 -> 0 | AK77: 0 | AL77: =SUM(AJ77:AK77) -> 0 | AM77: =L77+R77+X77+AD77+AJ77 -> 19447.57 | AN77: =M77+S77+Y77+AE77+AK77 -> 0 | AO77: =SUM(AM77:AN77) -> 19447.57
A78: SUBEXPLORA | B78: 89050 | C78: COL2 | D78: COL2 | E78: EXPLORA | F78: EXPT2TRVL | G78: Other Travel Related Expenses for School Research Leaders & Professionals, and Training Professionals | H78: 0 | I78: 25 | J78: 1 | K78: /trip | L78: =H78*I78*J78 -> 0 | M78: 0 | N78: =SUM(L78:M78) -> 0 | O78: 0 | P78: =I78*$H$6 -> 25.75 | Q78: 1 | R78: =P78*O78*Q78 -> 0 | S78: 0 | T78: =SUM(R78:S78) -> 0 | U78: =(8+8+3)*2 -> 38 | V78: =I78*$H$6*$H$6 -> 26.5225 | W78: 1 | X78: =U78*V78*W78 -> 1007.855 | Y78: 0 | Z78: =SUM(X78:Y78) -> 1007.855 | AA78: =(8+8+3)*2 -> 38 | AB78: =I78*$H$6*$H$6*$H$6 -> 27.318175 | AC78: 1 | AD78: =AA78*AB78 -> 1038.0907 | AE78: 0 | AF78: =SUM(AD78:AE78) -> 1038.0907 | AG78: 0 | AH78: =I78*$H$6*$H$6*$H$6*$H$6 -> 28.13772 | AI78: 1 | AJ78: =AG78*AH78 -> 0 | AK78: 0 | AL78: =SUM(AJ78:AK78) -> 0 | AM78: =L78+R78+X78+AD78+AJ78 -> 2045.9457 | AN78: =M78+S78+Y78+AE78+AK78 -> 0 | AO78: =SUM(AM78:AN78) -> 2045.9457
A79: SUBEXPLORA | B79: 89050 | C79: COL2 | D79: COL2 | E79: EXPLORA | F79: EXPT2TRVL | G79: Local Transportation Stipend for Workshop Leaders | H79: 0 | I79: 7 | J79: 1 | K79: /person | L79: =H79*I79*J79 -> 0 | M79: 0 | N79: =SUM(L79:M79) -> 0 | O79: 0 | P79: =I79*$H$6 -> 7.21 | Q79: 1 | R79: =P79*O79*Q79 -> 0 | S79: 0 | T79: =SUM(R79:S79) -> 0 | U79: =480*5 -> 2400 | V79: =I79*$H$6*$H$6 -> 7.4263 | W79: 1 | X79: =U79*V79*W79 -> 17823.12 | Y79: 0 | Z79: =SUM(X79:Y79) -> 17823.12 | AA79: =480*4 -> 1920 | AB79: =I79*$H$6*$H$6*$H$6 -> 7.649089 | AC79: 1 | AD79: =AA79*AB79 -> 14686.251 | AE79: 0 | AF79: =SUM(AD79:AE79) -> 14686.251 | AG79: 0 | AH79: =I79*$H$6*$H$6*$H$6*$H$6 -> 7.8785617 | AI79: 1 | AJ79: =AG79*AH79 -> 0 | AK79: 0 | AL79: =SUM(AJ79:AK79) -> 0 | AM79: =L79+R79+X79+AD79+AJ79 -> 32509.371 | AN79: =M79+S79+Y79+AE79+AK79 -> 0 | AO79: =SUM(AM79:AN79) -> 32509.371
G81: T.3 Travel for Teacher Training - Nexos
A82: SUBEXPLORA | B82: 89050 | C82: COL2 | D82: COL2 | E82: EXPLORA | F82: EXPT3TRVL | G82: Local Transportation (Airfare, Taxis, & Rental Car/Driver) for Teacher Training Nexos | H82: 35 | I82: 250 | J82: 1 | K82: /trip | L82: =J82*I82*H82 -> 8750 | M82: 0 | N82: =SUM(L82:M82) -> 8750 | O82: 70 | P82: =I82*$H$6 -> 257.5 | Q82: 1 | R82: =O82*P82*Q82 -> 18025 | S82: 0 | T82: =SUM(R82:S82) -> 18025 | U82: 70 | V82: =I82*$H$6*$H$6 -> 265.225 | W82: 1 | X82: =U82*V82*W82 -> 18565.75 | Y82: 0 | Z82: =SUM(X82:Y82) -> 18565.75 | AA82: 70 | AB82: =I82*$H$6*$H$6*$H$6 -> 273.18175 | AC82: 1 | AD82: =AA82*AB82*AC82 -> 19122.722 | AE82: 0 | AF82: =SUM(AD82:AE82) -> 19122.722 | AG82: 35 | AH82: =I82*$H$6*$H$6*$H$6*$H$6 -> 281.3772 | AI82: 1 | AJ82: =AG82*AH82*AI82 -> 9848.2021 | AK82: 0 | AL82: =SUM(AJ82:AK82) -> 9848.2021 | AM82: =L82+R82+X82+AD82+AJ82 -> 74311.675 | AN82: =M82+S82+Y82+AE82+AK82 -> 0 | AO82: =SUM(AM82:AN82) -> 74311.675
A83: SUBEXPLORA | B83: 89050 | C83: COL2 | D83: COL2 | E83: EXPLORA | F83: EXPT3TRVL | G83: Meals and Incidentals for Teacher Training Nexos | H83: 35 | I83: 40 | J83: 6 | K83: /day | L83: =J83*I83*H83 -> 8400 | M83: 0 | N83: =SUM(L83:M83) -> 8400 | O83: 70 | P83: =I83*$H$6 -> 41.2 | Q83: 6 | R83: =O83*P83*Q83 -> 17304 | S83: 0 | T83: =SUM(R83:S83) -> 17304 | U83: 70 | V83: =I83*$H$6*$H$6 -> 42.436 | W83: 6 | X83: =U83*V83*W83 -> 17823.12 | Y83: 0 | Z83: =SUM(X83:Y83) -> 17823.12 | AA83: 70 | AB83: =I83*$H$6*$H$6*$H$6 -> 43.70908 | AC83: 6 | AD83: =AA83*AB83*AC83 -> 18357.814 | AE83: 0 | AF83: =SUM(AD83:AE83) -> 18357.814 | AG83: 35 | AH83: =I83*$H$6*$H$6*$H$6*$H$6 -> 45.020352 | AI83: 6 | AJ83: =AG83*AH83*AI83 -> 9454.274 | AK83: 0 | AL83: =SUM(AJ83:AK83) -> 9454.274 | AM83: =L83+R83+X83+AD83+AJ83 -> 71339.208 | AN83: =M83+S83+Y83+AE83+AK83 -> 0 | AO83: =SUM(AM83:AN83) -> 71339.208
A84: SUBEXPLORA | B84: 89050 | C84: COL2 | D84: COL2 | E84: EXPLORA | F84: EXPT3TRVL | G84: Lodging for Teacher Training Nexos | H84: 35 | I84: 80 | J84: 5 | K84: /day | L84: =J84*I84*H84 -> 14000 | M84: 0 | N84: =SUM(L84:M84) -> 14000 | O84: 70 | P84: =I84*$H$6 -> 82.4 | Q84: 5 | R84: =O84*P84*Q84 -> 28840 | S84: 0 | T84: =SUM(R84:S84) -> 28840 | U84: 70 | V84: =I84*$H$6*$H$6 -> 84.872 | W84: 5 | X84: =U84*V84*W84 -> 29705.2 | Y84: 0 | Z84: =SUM(X84:Y84) -> 29705.2 | AA84: 70 | AB84: =I84*$H$6*$H$6*$H$6 -> 87.41816 | AC84: 5 | AD84: =AA84*AB84*AC84 -> 30596.356 | AE84: 0 | AF84: =SUM(AD84:AE84) -> 30596.356 | AG84: 35 | AH84: =I84*$H$6*$H$6*$H$6*$H$6 -> 90.040705 | AI84: 5 | AJ84: =AG84*AH84*AI84 -> 15757.123 | AK84: 0 | AL84: =SUM(AJ84:AK84) -> 15757.123 | AM84: =L84+R84+X84+AD84+AJ84 -> 118898.68 | AN84: =M84+S84+Y84+AE84+AK84 -> 0 | AO84: =SUM(AM84:AN84) -> 118898.68
A85: SUBEXPLORA | B85: 89050 | C85: COL2 | D85: COL2 | E85: EXPLORA | F85: EXPT3TRVL | G85: Other Travel Related Expenses for Teacher Training Nexos | H85: 35 | I85: 25 | J85: 1 | K85: /trip | L85: =H85*I85*J85 -> 875 | M85: 0 | N85: =SUM(L85:M85) -> 875 | O85: 70 | P85: =I85*$H$6 -> 25.75 | Q85: 1 | R85: =P85*O85*Q85 -> 1802.5 | S85: 0 | T85: =SUM(R85:S85) -> 1802.5 | U85: 70 | V85: =I85*$H$6*$H$6 -> 26.5225 | W85: 1 | X85: =U85*V85*W85 -> 1856.575 | Y85: 0 | Z85: =SUM(X85:Y85) -> 1856.575 | AA85: 70 | AB85: =I85*$H$6*$H$6*$H$6 -> 27.318175 | AC85: 1 | AD85: =AA85*AB85 -> 1912.2722 | AE85: 0 | AF85: =SUM(AD85:AE85) -> 1912.2722 | AG85: 35 | AH85: =I85*$H$6*$H$6*$H$6*$H$6 -> 28.13772 | AI85: 1 | AJ85: =AG85*AH85 -> 984.82021 | AK85: 0 | AL85: =SUM(AJ85:AK85) -> 984.82021 | AM85: =L85+R85+X85+AD85+AJ85 -> 7431.1675 | AN85: =M85+S85+Y85+AE85+AK85 -> 0 | AO85: =SUM(AM85:AN85) -> 7431.1675
G87: T.4 Local Travel in Medellín for Field Staff
A88: SUBEXPLORA | B88: 89050 | C88: COL2 | D88: COL2 | E88: EXPLORA | F88: EXT4FUELEX | G88: Vehicle Fuel Expense | H88: 6 | I88: =300 -> 300 | J88: 1 | K88: /month | L88: =J88*I88*H88 -> 1800 | M88: 0 | N88: =SUM(L88:M88) -> 1800 | O88: 12 | P88: =I88*$H$7 -> 312 | Q88: 1 | R88: =O88*P88*Q88 -> 3744 | S88: 0 | T88: =SUM(R88:S88) -> 3744 | U88: 12 | V88: =I88*$H$7*$H$7 -> 324.48 | W88: 1 | X88: =U88*V88*W88 -> 3893.76 | Y88: 0 | Z88: =SUM(X88:Y88) -> 3893.76 | AA88: 12 | AB88: =I88*$H$7*$H$7*$H$7 -> 337.4592 | AC88: 1 | AD88: =AA88*AB88*AC88 -> 4049.5104 | AE88: 0 | AF88: =SUM(AD88:AE88) -> 4049.5104 | AG88: 9 | AH88: =I88*$H$7*$H$7*$H$7*$H$7 -> 350.95757 | AI88: 1 | AJ88: =AG88*AH88*AI88 -> 3158.6181 | AK88: 0 | AL88: =SUM(AJ88:AK88) -> 3158.6181 | AM88: =L88+R88+X88+AD88+AJ88 -> 16645.889 | AN88: =M88+S88+Y88+AE88+AK88 -> 0 | AO88: =SUM(AM88:AN88) -> 16645.889
G90: T.5 Travel for Advisory Board Meetings - 2 Annually
A91: SUBEXPLORA | B91: 89050 | C91: COL2 | D91: COL2 | E91: EXPLORA | F91: EXPT5TRVL | G91: Local Transportation for Advisory Board Meetings | H91: =2*2 -> 4 | I91: 80 | J91: 1 | K91: /trip | L91: =J91*I91*H91 -> 320 | M91: 0 | N91: =SUM(L91:M91) -> 320 | O91: =2*2 -> 4 | P91: =I91*$H$7 -> 83.2 | Q91: 1 | R91: =O91*P91*Q91 -> 332.8 | S91: 0 | T91: =SUM(R91:S91) -> 332.8 | U91: =2*2 -> 4 | V91: =I91*$H$7*$H$7 -> 86.528 | W91: 1 | X91: =U91*V91*W91 -> 346.112 | Y91: 0 | Z91: =SUM(X91:Y91) -> 346.112 | AA91: =2*2 -> 4 | AB91: =I91*$H$7*$H$7*$H$7 -> 89.98912 | AC91: 1 | AD91: =AA91*AB91*AC91 -> 359.95648 | AE91: 0 | AF91: =SUM(AD91:AE91) -> 359.95648 | AG91: 2 | AH91: =I91*$H$7*$H$7*$H$7*$H$7 -> 93.588685 | AI91: 1 | AJ91: =AG91*AH91*AI91 -> 187.17737 | AK91: 0 | AL91: =SUM(AJ91:AK91) -> 187.17737 | AM91: =L91+R91+X91+AD91+AJ91 -> 1546.0458 | AN91: =M91+S91+Y91+AE91+AK91 -> 0 | AO91: =SUM(AM91:AN91) -> 1546.0458
A92: SUBEXPLORA | B92: 89050 | C92: COL2 | D92: COL2 | E92: EXPLORA | F92: EXPT5TRVL | G92: Meals and Incidentals for Advisory Board Meetings | H92: =2*2 -> 4 | I92: 40 | J92: 2 | K92: /day | L92: =J92*I92*H92 -> 320 | M92: 0 | N92: =SUM(L92:M92) -> 320 | O92: =2*2 -> 4 | P92: =I92*$H$7 -> 41.6 | Q92: 2 | R92: =O92*P92*Q92 -> 332.8 | S92: 0 | T92: =SUM(R92:S92) -> 332.8 | U92: =2*2 -> 4 | V92: =I92*$H$7*$H$7 -> 43.264 | W92: 2 | X92: =U92*V92*W92 -> 346.112 | Y92: 0 | Z92: =SUM(X92:Y92) -> 346.112 | AA92: =2*2 -> 4 | AB92: =I92*$H$7*$H$7*$H$7 -> 44.99456 | AC92: 2 | AD92: =AA92*AB92*AC92 -> 359.95648 | AE92: 0 | AF92: =SUM(AD92:AE92) -> 359.95648 | AG92: 2 | AH92: =I92*$H$7*$H$7*$H$7*$H$7 -> 46.794342 | AI92: 2 | AJ92: =AG92*AH92*AI92 -> 187.17737 | AK92: 0 | AL92: =SUM(AJ92:AK92) -> 187.17737 | AM92: =L92+R92+X92+AD92+AJ92 -> 1546.0458 | AN92: =M92+S92+Y92+AE92+AK92 -> 0 | AO92: =SUM(AM92:AN92) -> 1546.0458
A93: SUBEXPLORA | B93: 89050 | C93: COL2 | D93: COL2 | E93: EXPLORA | F93: EXPT5TRVL | G93: Lodging for Advisory Board Meetings | H93: =2*2 -> 4 | I93: 80 | J93: 2 | K93: /day | L93: =J93*I93*H93 -> 640 | M93: 0 | N93: =SUM(L93:M93) -> 640 | O93: =2*2 -> 4 | P93: =I93*$H$7 -> 83.2 | Q93: 2 | R93: =O93*P93*Q93 -> 665.6 | S93: 0 | T93: =SUM(R93:S93) -> 665.6 | U93: =2*2 -> 4 | V93: =I93*$H$7*$H$7 -> 86.528 | W93: 2 | X93: =U93*V93*W93 -> 692.224 | Y93: 0 | Z93: =SUM(X93:Y93) -> 692.224 | AA93: =2*2 -> 4 | AB93: =I93*$H$7*$H$7*$H$7 -> 89.98912 | AC93: 2 | AD93: =AA93*AB93*AC93 -> 719.91296 | AE93: 0 | AF93: =SUM(AD93:AE93) -> 719.91296 | AG93: 2 | AH93: =I93*$H$7*$H$7*$H$7*$H$7 -> 93.588685 | AI93: 2 | AJ93: =AG93*AH93*AI93 -> 374.35474 | AK93: 0 | AL93: =SUM(AJ93:AK93) -> 374.35474 | AM93: =L93+R93+X93+AD93+AJ93 -> 3092.0917 | AN93: =M93+S93+Y93+AE93+AK93 -> 0 | AO93: =SUM(AM93:AN93) -> 3092.0917
A94: SUBEXPLORA | B94: 89050 | C94: COL2 | D94: COL2 | E94: EXPLORA | F94: EXPT5TRVL | G94: Other Travel Related Expenses for Advisory Board Meetings | H94: =2*2 -> 4 | I94: 25 | J94: 1 | K94: /trip | L94: =J94*I94*H94 -> 100 | M94: 0 | N94: =SUM(L94:M94) -> 100 | O94: =2*2 -> 4 | P94: =I94*$H$7 -> 26 | Q94: 1 | R94: =O94*P94*Q94 -> 104 | S94: 0 | T94: =SUM(R94:S94) -> 104 | U94: =2*2 -> 4 | V94: =I94*$H$7*$H$7 -> 27.04 | W94: 1 | X94: =U94*V94*W94 -> 108.16 | Y94: 0 | Z94: =SUM(X94:Y94) -> 108.16 | AA94: =2*2 -> 4 | AB94: =I94*$H$7*$H$7*$H$7 -> 28.1216 | AC94: 1 | AD94: =AA94*AB94*AC94 -> 112.4864 | AE94: 0 | AF94: =SUM(AD94:AE94) -> 112.4864 | AG94: 2 | AH94: =I94*$H$7*$H$7*$H$7*$H$7 -> 29.246464 | AI94: 1 | AJ94: =AG94*AH94*AI94 -> 58.492928 | AK94: 0 | AL94: =SUM(AJ94:AK94) -> 58.492928 | AM94: =L94+R94+X94+AD94+AJ94 -> 483.13933 | AN94: =M94+S94+Y94+AE94+AK94 -> 0 | AO94: =SUM(AM94:AN94) -> 483.13933
G96: T.6 Travel for Annual Forums for Education Observatories
A97: SUBEXPLORA | B97: 89050 | C97: COL2 | D97: COL2 | E97: EXPLORA | F97: EXPT6TRVL | G97: Local Transportation for Annual Forums | H97: 0 | I97: 50 | J97: 1 | K97: /trip | L97: =J97*I97*H97 -> 0 | M97: 0 | N97: =SUM(L97:M97) -> 0 | O97: 2 | P97: =I97*$H$7 -> 52 | Q97: 1 | R97: =O97*P97*Q97 -> 104 | S97: 0 | T97: =SUM(R97:S97) -> 104 | U97: 2 | V97: =I97*$H$7*$H$7 -> 54.08 | W97: 1 | X97: =U97*V97*W97 -> 108.16 | Y97: 0 | Z97: =SUM(X97:Y97) -> 108.16 | AA97: 0 | AB97: =I97*$H$7*$H$7*$H$7 -> 56.2432 | AC97: 1 | AD97: =AA97*AB97*AC97 -> 0 | AE97: 0 | AF97: =SUM(AD97:AE97) -> 0 | AG97: 0 | AH97: =I97*$H$7*$H$7*$H$7*$H$7 -> 58.492928 | AI97: 1 | AJ97: =AG97*AH97*AI97 -> 0 | AK97: 0 | AL97: =SUM(AJ97:AK97) -> 0 | AM97: =L97+R97+X97+AD97+AJ97 -> 212.16 | AN97: =M97+S97+Y97+AE97+AK97 -> 0 | AO97: =SUM(AM97:AN97) -> 212.16
A98: SUBEXPLORA | B98: 89050 | C98: COL2 | D98: COL2 | E98: EXPLORA | F98: EXPT6TRVL | G98: Meals and Incidentals for Annual Forums | H98: 0 | I98: 40 | J98: 2 | K98: /day | L98: =J98*I98*H98 -> 0 | M98: 0 | N98: =SUM(L98:M98) -> 0 | O98: 2 | P98: =I98*$H$7 -> 41.6 | Q98: 2 | R98: =O98*P98*Q98 -> 166.4 | S98: 0 | T98: =SUM(R98:S98) -> 166.4 | U98: 2 | V98: =I98*$H$7*$H$7 -> 43.264 | W98: 2 | X98: =U98*V98*W98 -> 173.056 | Y98: 0 | Z98: =SUM(X98:Y98) -> 173.056 | AA98: 0 | AB98: =I98*$H$7*$H$7*$H$7 -> 44.99456 | AC98: 2 | AD98: =AA98*AB98*AC98 -> 0 | AE98: 0 | AF98: =SUM(AD98:AE98) -> 0 | AG98: 0 | AH98: =I98*$H$7*$H$7*$H$7*$H$7 -> 46.794342 | AI98: 2 | AJ98: =AG98*AH98*AI98 -> 0 | AK98: 0 | AL98: =SUM(AJ98:AK98) -> 0 | AM98: =L98+R98+X98+AD98+AJ98 -> 339.456 | AN98: =M98+S98+Y98+AE98+AK98 -> 0 | AO98: =SUM(AM98:AN98) -> 339.456
A99: SUBEXPLORA | B99: 89050 | C99: COL2 | D99: COL2 | E99: EXPLORA | F99: EXPT6TRVL | G99: Lodging for Annual Forums | H99: 0 | I99: 80 | J99: 2 | K99: /day | L99: =J99*I99*H99 -> 0 | M99: 0 | N99: =SUM(L99:M99) -> 0 | O99: 2 | P99: =I99*$H$7 -> 83.2 | Q99: 2 | R99: =O99*P99*Q99 -> 332.8 | S99: 0 | T99: =SUM(R99:S99) -> 332.8 | U99: 2 | V99: =I99*$H$7*$H$7 -> 86.528 | W99: 2 | X99: =U99*V99*W99 -> 346.112 | Y99: 0 | Z99: =SUM(X99:Y99) -> 346.112 | AA99: 0 | AB99: =I99*$H$7*$H$7*$H$7 -> 89.98912 | AC99: 2 | AD99: =AA99*AB99*AC99 -> 0 | AE99: 0 | AF99: =SUM(AD99:AE99) -> 0 | AG99: 0 | AH99: =I99*$H$7*$H$7*$H$7*$H$7 -> 93.588685 | AI99: 2 | AJ99: =AG99*AH99*AI99 -> 0 | AK99: 0 | AL99: =SUM(AJ99:AK99) -> 0 | AM99: =L99+R99+X99+AD99+AJ99 -> 678.912 | AN99: =M99+S99+Y99+AE99+AK99 -> 0 | AO99: =SUM(AM99:AN99) -> 678.912
A100: SUBEXPLORA | B100: 89050 | C100: COL2 | D100: COL2 | E100: EXPLORA | F100: EXPT6TRVL | G100: Other Travel Related Expenses for Annual Forums | H100: 0 | I100: 25 | J100: 1 | K100: /trip | L100: =J100*I100*H100 -> 0 | M100: 0 | N100: =SUM(L100:M100) -> 0 | O100: 2 | P100: =I100*$H$7 -> 26 | Q100: 1 | R100: =O100*P100*Q100 -> 52 | S100: 0 | T100: =SUM(R100:S100) -> 52 | U100: 2 | V100: =I100*$H$7*$H$7 -> 27.04 | W100: 1 | X100: =U100*V100*W100 -> 54.08 | Y100: 0 | Z100: =SUM(X100:Y100) -> 54.08 | AA100: 0 | AB100: =I100*$H$7*$H$7*$H$7 -> 28.1216 | AC100: 1 | AD100: =AA100*AB100*AC100 -> 0 | AE100: 0 | AF100: =SUM(AD100:AE100) -> 0 | AG100: 0 | AH100: =I100*$H$7*$H$7*$H$7*$H$7 -> 29.246464 | AI100: 1 | AJ100: =AG100*AH100*AI100 -> 0 | AK100: 0 | AL100: =SUM(AJ100:AK100) -> 0 | AM100: =L100+R100+X100+AD100+AJ100 -> 106.08 | AN100: =M100+S100+Y100+AE100+AK100 -> 0 | AO100: =SUM(AM100:AN100) -> 106.08
G102: T.7 Travel to SMT In-Person Meetings in Bogota
A103: SUBEXPLORA | B103: 89050 | C103: COL2 | D103: COL2 | E103: EXPLORA | F103: EXPT7TRVL | G103: Local Transportation for SMT Meetings | H103: 17 | I103: 50 | J103: 1 | K103: /trip | L103: =J103*I103*H103 -> 850 | M103: 0 | N103: =SUM(L103:M103) -> 850 | O103: 17 | P103: =I103*$H$7 -> 52 | Q103: 1 | R103: =O103*P103*Q103 -> 884 | S103: 0 | T103: =SUM(R103:S103) -> 884 | U103: 17 | V103: =I103*$H$7*$H$7 -> 54.08 | W103: 1 | X103: =U103*V103*W103 -> 919.36 | Y103: 0 | Z103: =SUM(X103:Y103) -> 919.36 | AA103: 17 | AB103: =I103*$H$7*$H$7*$H$7 -> 56.2432 | AC103: 1 | AD103: =AA103*AB103*AC103 -> 956.1344 | AE103: 0 | AF103: =SUM(AD103:AE103) -> 956.1344 | AG103: 17 | AH103: =I103*$H$7*$H$7*$H$7*$H$7 -> 58.492928 | AI103: 1 | AJ103: =AG103*AH103*AI103 -> 994.37978 | AK103: 0 | AL103: =SUM(AJ103:AK103) -> 994.37978 | AM103: =L103+R103+X103+AD103+AJ103 -> 4603.8742 | AN103: =M103+S103+Y103+AE103+AK103 -> 0 | AO103: =SUM(AM103:AN103) -> 4603.8742
A104: SUBEXPLORA | B104: 89050 | C104: COL2 | D104: COL2 | E104: EXPLORA | F104: EXPT7TRVL | G104: Meals and Incidentals for SMT Meetings | H104: 17 | I104: 40 | J104: 1 | K104: /day | L104: =J104*I104*H104 -> 680 | M104: 0 | N104: =SUM(L104:M104) -> 680 | O104: 17 | P104: =I104*$H$7 -> 41.6 | Q104: 1 | R104: =O104*P104*Q104 -> 707.2 | S104: 0 | T104: =SUM(R104:S104) -> 707.2 | U104: 17 | V104: =I104*$H$7*$H$7 -> 43.264 | W104: 1 | X104: =U104*V104*W104 -> 735.488 | Y104: 0 | Z104: =SUM(X104:Y104) -> 735.488 | AA104: 17 | AB104: =I104*$H$7*$H$7*$H$7 -> 44.99456 | AC104: 1 | AD104: =AA104*AB104*AC104 -> 764.90752 | AE104: 0 | AF104: =SUM(AD104:AE104) -> 764.90752 | AG104: 17 | AH104: =I104*$H$7*$H$7*$H$7*$H$7 -> 46.794342 | AI104: 1 | AJ104: =AG104*AH104*AI104 -> 795.50382 | AK104: 0 | AL104: =SUM(AJ104:AK104) -> 795.50382 | AM104: =L104+R104+X104+AD104+AJ104 -> 3683.0993 | AN104: =M104+S104+Y104+AE104+AK104 -> 0 | AO104: =SUM(AM104:AN104) -> 3683.0993
A105: SUBEXPLORA | B105: 89050 | C105: COL2 | D105: COL2 | E105: EXPLORA | F105: EXPT7TRVL | G105: Lodging for SMT Meetings | H105: 17 | I105: 80 | J105: 1 | K105: /day | L105: =J105*I105*H105 -> 1360 | M105: 0 | N105: =SUM(L105:M105) -> 1360 | O105: 17 | P105: =I105*$H$7 -> 83.2 | Q105: 1 | R105: =O105*P105*Q105 -> 1414.4 | S105: 0 | T105: =SUM(R105:S105) -> 1414.4 | U105: 17 | V105: =I105*$H$7*$H$7 -> 86.528 | W105: 1 | X105: =U105*V105*W105 -> 1470.976 | Y105: 0 | Z105: =SUM(X105:Y105) -> 1470.976 | AA105: 17 | AB105: =I105*$H$7*$H$7*$H$7 -> 89.98912 | AC105: 1 | AD105: =AA105*AB105*AC105 -> 1529.815 | AE105: 0 | AF105: =SUM(AD105:AE105) -> 1529.815 | AG105: 17 | AH105: =I105*$H$7*$H$7*$H$7*$H$7 -> 93.588685 | AI105: 1 | AJ105: =AG105*AH105*AI105 -> 1591.0076 | AK105: 0 | AL105: =SUM(AJ105:AK105) -> 1591.0076 | AM105: =L105+R105+X105+AD105+AJ105 -> 7366.1987 | AN105: =M105+S105+Y105+AE105+AK105 -> 0 | AO105: =SUM(AM105:AN105) -> 7366.1987
A106: SUBEXPLORA | B106: 89050 | C106: COL2 | D106: COL2 | E106: EXPLORA | F106: EXPT7TRVL | G106: Other Travel Related Expenses for SMT Meetings | H106: 17 | I106: 25 | J106: 1 | K106: /trip | L106: =J106*I106*H106 -> 425 | M106: 0 | N106: =SUM(L106:M106) -> 425 | O106: 17 | P106: =I106*$H$7 -> 26 | Q106: 1 | R106: =O106*P106*Q106 -> 442 | S106: 0 | T106: =SUM(R106:S106) -> 442 | U106: 17 | V106: =I106*$H$7*$H$7 -> 27.04 | W106: 1 | X106: =U106*V106*W106 -> 459.68 | Y106: 0 | Z106: =SUM(X106:Y106) -> 459.68 | AA106: 17 | AB106: =I106*$H$7*$H$7*$H$7 -> 28.1216 | AC106: 1 | AD106: =AA106*AB106*AC106 -> 478.0672 | AE106: 0 | AF106: =SUM(AD106:AE106) -> 478.0672 | AG106: 17 | AH106: =I106*$H$7*$H$7*$H$7*$H$7 -> 29.246464 | AI106: 1 | AJ106: =AG106*AH106*AI106 -> 497.18989 | AK106: 0 | AL106: =SUM(AJ106:AK106) -> 497.18989 | AM106: =L106+R106+X106+AD106+AJ106 -> 2301.9371 | AN106: =M106+S106+Y106+AE106+AK106 -> 0 | AO106: =SUM(AM106:AN106) -> 2301.9371
G108: T.8 Travel to Annual In-Person Steering Committee Meeting in Bogota
A109: SUBEXPLORA | B109: 89050 | C109: COL2 | D109: COL2 | E109: EXPLORA | F109: EXPT8TRVL | G109: Local Transportation for Steering Committee Meeting | H109: 1 | I109: 50 | J109: 1 | K109: /trip | L109: =J109*I109*H109 -> 50 | M109: 0 | N109: =SUM(L109:M109) -> 50 | O109: 1 | P109: =I109*$H$7 -> 52 | Q109: 1 | R109: =O109*P109*Q109 -> 52 | S109: 0 | T109: =SUM(R109:S109) -> 52 | U109: 1 | V109: =I109*$H$7*$H$7 -> 54.08 | W109: 1 | X109: =U109*V109*W109 -> 54.08 | Y109: 0 | Z109: =SUM(X109:Y109) -> 54.08 | AA109: 1 | AB109: =I109*$H$7*$H$7*$H$7 -> 56.2432 | AC109: 1 | AD109: =AA109*AB109*AC109 -> 56.2432 | AE109: 0 | AF109: =SUM(AD109:AE109) -> 56.2432 | AG109: 1 | AH109: =I109*$H$7*$H$7*$H$7*$H$7 -> 58.492928 | AI109: 1 | AJ109: =AG109*AH109*AI109 -> 58.492928 | AK109: 0 | AL109: =SUM(AJ109:AK109) -> 58.492928 | AM109: =L109+R109+X109+AD109+AJ109 -> 270.81613 | AN109: =M109+S109+Y109+AE109+AK109 -> 0 | AO109: =SUM(AM109:AN109) -> 270.81613
A110: SUBEXPLORA | B110: 89050 | C110: COL2 | D110: COL2 | E110: EXPLORA | F110: EXPT8TRVL | G110: Meals and Incidentals for Steering Committee Meeting | H110: 1 | I110: 40 | J110: 2 | K110: /day | L110: =J110*I110*H110 -> 80 | M110: 0 | N110: =SUM(L110:M110) -> 80 | O110: 1 | P110: =I110*$H$7 -> 41.6 | Q110: 2 | R110: =O110*P110*Q110 -> 83.2 | S110: 0 | T110: =SUM(R110:S110) -> 83.2 | U110: 1 | V110: =I110*$H$7*$H$7 -> 43.264 | W110: 2 | X110: =U110*V110*W110 -> 86.528 | Y110: 0 | Z110: =SUM(X110:Y110) -> 86.528 | AA110: 1 | AB110: =I110*$H$7*$H$7*$H$7 -> 44.99456 | AC110: 2 | AD110: =AA110*AB110*AC110 -> 89.98912 | AE110: 0 | AF110: =SUM(AD110:AE110) -> 89.98912 | AG110: 1 | AH110: =I110*$H$7*$H$7*$H$7*$H$7 -> 46.794342 | AI110: 2 | AJ110: =AG110*AH110*AI110 -> 93.588685 | AK110: 0 | AL110: =SUM(AJ110:AK110) -> 93.588685 | AM110: =L110+R110+X110+AD110+AJ110 -> 433.3058 | AN110: =M110+S110+Y110+AE110+AK110 -> 0 | AO110: =SUM(AM110:AN110) -> 433.3058
A111: SUBEXPLORA | B111: 89050 | C111: COL2 | D111: COL2 | E111: EXPLORA | F111: EXPT8TRVL | G111: Lodging for Steering Committee Meeting | H111: 1 | I111: 80 | J111: 2 | K111: /day | L111: =J111*I111*H111 -> 160 | M111: 0 | N111: =SUM(L111:M111) -> 160 | O111: 1 | P111: =I111*$H$7 -> 83.2 | Q111: 2 | R111: =O111*P111*Q111 -> 166.4 | S111: 0 | T111: =SUM(R111:S111) -> 166.4 | U111: 1 | V111: =I111*$H$7*$H$7 -> 86.528 | W111: 2 | X111: =U111*V111*W111 -> 173.056 | Y111: 0 | Z111: =SUM(X111:Y111) -> 173.056 | AA111: 1 | AB111: =I111*$H$7*$H$7*$H$7 -> 89.98912 | AC111: 2 | AD111: =AA111*AB111*AC111 -> 179.97824 | AE111: 0 | AF111: =SUM(AD111:AE111) -> 179.97824 | AG111: 1 | AH111: =I111*$H$7*$H$7*$H$7*$H$7 -> 93.588685 | AI111: 2 | AJ111: =AG111*AH111*AI111 -> 187.17737 | AK111: 0 | AL111: =SUM(AJ111:AK111) -> 187.17737 | AM111: =L111+R111+X111+AD111+AJ111 -> 866.61161 | AN111: =M111+S111+Y111+AE111+AK111 -> 0 | AO111: =SUM(AM111:AN111) -> 866.61161
A112: SUBEXPLORA | B112: 89050 | C112: COL2 | D112: COL2 | E112: EXPLORA | F112: EXPT8TRVL | G112: Other Travel Related Expenses for Steering Committee Meeting | H112: 1 | I112: 25 | J112: 1 | K112: /trip | L112: =J112*I112*H112 -> 25 | M112: 0 | N112: =SUM(L112:M112) -> 25 | O112: 1 | P112: =I112*$H$7 -> 26 | Q112: 1 | R112: =O112*P112*Q112 -> 26 | S112: 0 | T112: =SUM(R112:S112) -> 26 | U112: 1 | V112: =I112*$H$7*$H$7 -> 27.04 | W112: 1 | X112: =U112*V112*W112 -> 27.04 | Y112: 0 | Z112: =SUM(X112:Y112) -> 27.04 | AA112: 1 | AB112: =I112*$H$7*$H$7*$H$7 -> 28.1216 | AC112: 1 | AD112: =AA112*AB112*AC112 -> 28.1216 | AE112: 0 | AF112: =SUM(AD112:AE112) -> 28.1216 | AG112: 1 | AH112: =I112*$H$7*$H$7*$H$7*$H$7 -> 29.246464 | AI112: 1 | AJ112: =AG112*AH112*AI112 -> 29.246464 | AK112: 0 | AL112: =SUM(AJ112:AK112) -> 29.246464 | AM112: =L112+R112+X112+AD112+AJ112 -> 135.40806 | AN112: =M112+S112+Y112+AE112+AK112 -> 0 | AO112: =SUM(AM112:AN112) -> 135.40806
G114: T.9 Travel for Clubes Explora
A115: SUBEXPLORA | B115: 89050 | C115: COL2 | D115: COL2 | E115: EXPLORA | F115: EXPT9TRVL | G115: Local Transportation (Airfare, Taxis, & Rental Car/Driver) for Clubes Explora | H115: 0 | I115: 250 | J115: 1 | K115: /trip | L115: =J115*I115*H115 -> 0 | M115: 0 | N115: =SUM(L115:M115) -> 0 | O115: 0 | P115: =I115*$H$7 -> 260 | Q115: 1 | R115: =O115*P115*Q115 -> 0 | S115: 0 | T115: =SUM(R115:S115) -> 0 | U115: =4*9 -> 36 | V115: =I115*$H$7*$H$7 -> 270.4 | W115: 1 | X115: =U115*V115*W115 -> 9734.4 | Y115: 0 | Z115: =SUM(X115:Y115) -> 9734.4 | AA115: =4*9 -> 36 | AB115: =I115*$H$7*$H$7*$H$7 -> 281.216 | AC115: 1 | AD115: =AA115*AB115*AC115 -> 10123.776 | AE115: 0 | AF115: =SUM(AD115:AE115) -> 10123.776 | AG115: 0 | AH115: =I115*$H$7*$H$7*$H$7*$H$7 -> 292.46464 | AI115: 1 | AJ115: =AG115*AH115*AI115 -> 0 | AK115: 0 | AL115: =SUM(AJ115:AK115) -> 0 | AM115: =L115+R115+X115+AD115+AJ115 -> 19858.176 | AN115: =M115+S115+Y115+AE115+AK115 -> 0 | AO115: =SUM(AM115:AN115) -> 19858.176
A116: SUBEXPLORA | B116: 89050 | C116: COL2 | D116: COL2 | E116: EXPLORA | F116: EXPT9TRVL | G116: Meals and Incidentals for Clubes Explora | H116: 0 | I116: 40 | J116: 5 | K116: /day | L116: =J116*I116*H116 -> 0 | M116: 0 | N116: =SUM(L116:M116) -> 0 | O116: 0 | P116: =I116*$H$7 -> 41.6 | Q116: 5 | R116: =O116*P116*Q116 -> 0 | S116: 0 | T116: =SUM(R116:S116) -> 0 | U116: =4*9 -> 36 | V116: =I116*$H$7*$H$7 -> 43.264 | W116: 5 | X116: =U116*V116*W116 -> 7787.52 | Y116: 0 | Z116: =SUM(X116:Y116) -> 7787.52 | AA116: =4*9 -> 36 | AB116: =I116*$H$7*$H$7*$H$7 -> 44.99456 | AC116: 5 | AD116: =AA116*AB116*AC116 -> 8099.0208 | AE116: 0 | AF116: =SUM(AD116:AE116) -> 8099.0208 | AG116: 0 | AH116: =I116*$H$7*$H$7*$H$7*$H$7 -> 46.794342 | AI116: 5 | AJ116: =AG116*AH116*AI116 -> 0 | AK116: 0 | AL116: =SUM(AJ116:AK116) -> 0 | AM116: =L116+R116+X116+AD116+AJ116 -> 15886.541 | AN116: =M116+S116+Y116+AE116+AK116 -> 0 | AO116: =SUM(AM116:AN116) -> 15886.541
...

Sheet Budget Summary ProAntioquia
B1: Name of Subawardee: ProAntioquia
B2: USAID RFA No. 7200AA21RFA00001
A4: Line Items | B4: Year 1 | E4: Year 2 | H4: Year 3 | K4: Year 4 | N4: Year 5 | Q4: Total | R4: Total | S4: Grand
B5: USAID | C5: Leverage | D5: Total | E5: USAID | F5: Leverage | G5: Total | H5: USAID | I5: Leverage | J5: Total | K5: USAID | L5: Leverage | M5: Total | N5: USAID | O5: Leverage | P5: Total | Q5: USAID | R5: Leverage | S5: Total
A7: Personnel | B7: ='Budget ProAntioquia'!L33 -> 146525 | C7: ='Budget ProAntioquia'!M33 -> 29706.9 | D7: =SUM(B7:C7) -> 176231.9 | E7: ='Budget ProAntioquia'!R33 -> 180648 | F7: ='Budget ProAntioquia'!S33 -> 33006.272 | G7: =SUM(E7:F7) -> 213654.27 | H7: ='Budget ProAntioquia'!X33 -> 187873.92 | I7: ='Budget ProAntioquia'!Y33 -> 34326.523 | J7: =SUM(H7:I7) -> 222200.44 | K7: ='Budget ProAntioquia'!AD33 -> 195388.88 | L7: ='Budget ProAntioquia'!AE33 -> 35699.584 | M7: =SUM(K7:L7) -> 231088.46 | N7: ='Budget ProAntioquia'!AJ33 -> 175186.32 | O7: ='Budget ProAntioquia'!AK33 -> 35922.73 | P7: =SUM(N7:O7) -> 211109.05 | Q7: ='Budget ProAntioquia'!AM33 -> 885622.12 | R7: ='Budget ProAntioquia'!AN33 -> 168662.01 | S7: ='Budget ProAntioquia'!AO33 -> 1054284.1
A9: Fringe Benefits | B9: ='Budget ProAntioquia'!L39 -> 68799.226 | C9: ='Budget ProAntioquia'!M39 -> 13520.295 | D9: ='Budget ProAntioquia'!N39 -> 82319.521 | E9: ='Budget ProAntioquia'!R39 -> 84668.239 | F9: ='Budget ProAntioquia'!S39 -> 15057.827 | G9: ='Budget ProAntioquia'!T39 -> 99726.066 | H9: ='Budget ProAntioquia'!X39 -> 88054.968 | I9: ='Budget ProAntioquia'!Y39 -> 15660.14 | J9: ='Budget ProAntioquia'!Z39 -> 103715.11 | K9: ='Budget ProAntioquia'!AD39 -> 91577.167 | L9: ='Budget ProAntioquia'!AE39 -> 16286.546 | M9: ='Budget ProAntioquia'!AF39 -> 107863.71 | N9: ='Budget ProAntioquia'!AJ39 -> 83109.782 | O9: ='Budget ProAntioquia'!AK39 -> 16289.034 | P9: ='Budget ProAntioquia'!AL39 -> 99398.816 | Q9: ='Budget ProAntioquia'!AM39 -> 416209.38 | R9: ='Budget ProAntioquia'!AN39 -> 76813.842 | S9: ='Budget ProAntioquia'!AO39 -> 493023.22
A11: Travel | B11: ='Budget ProAntioquia'!L85 -> 18570 | C11: ='Budget ProAntioquia'!M85 -> 0 | D11: ='Budget ProAntioquia'!N85 -> 18570 | E11: ='Budget ProAntioquia'!R85 -> 19700.7 | F11: ='Budget ProAntioquia'!S85 -> 0 | G11: ='Budget ProAntioquia'!T85 -> 19700.7 | H11: ='Budget ProAntioquia'!X85 -> 21801.801 | I11: ='Budget ProAntioquia'!Y85 -> 0 | J11: ='Budget ProAntioquia'!Z85 -> 21801.801 | K11: ='Budget ProAntioquia'!AD85 -> 21847.131 | L11: ='Budget ProAntioquia'!AE85 -> 0 | M11: ='Budget ProAntioquia'!AF85 -> 21847.131 | N11: ='Budget ProAntioquia'!AJ85 -> 21546.523 | O11: ='Budget ProAntioquia'!AK85 -> 0 | P11: ='Budget ProAntioquia'!AL85 -> 21546.523 | Q11: ='Budget ProAntioquia'!AM85 -> 103466.15 | R11: ='Budget ProAntioquia'!AN85 -> 0 | S11: ='Budget ProAntioquia'!AO85 -> 103466.15
A13: Equipment | B13: ='Budget ProAntioquia'!L91 -> 50000 | C13: ='Budget ProAntioquia'!M91 -> 0 | D13: ='Budget ProAntioquia'!N91 -> 50000 | E13: ='Budget ProAntioquia'!R91 -> 0 | F13: ='Budget ProAntioquia'!S91 -> 0 | G13: ='Budget ProAntioquia'!T91 -> 0 | H13: ='Budget ProAntioquia'!X91 -> 0 | I13: ='Budget ProAntioquia'!Y91 -> 0 | J13: ='Budget ProAntioquia'!Z91 -> 0 | K13: ='Budget ProAntioquia'!AD91 -> 0 | L13: ='Budget ProAntioquia'!AE91 -> 0 | M13: ='Budget ProAntioquia'!AF91 -> 0 | N13: ='Budget ProAntioquia'!AJ91 -> 0 | O13: ='Budget ProAntioquia'!AK91 -> 0 | P13: ='Budget ProAntioquia'!AL91 -> 0 | Q13: ='Budget ProAntioquia'!AM91 -> 50000 | R13: ='Budget ProAntioquia'!AN91 -> 0 | S13: ='Budget ProAntioquia'!AO91 -> 50000
A15: Supplies | B15: ='Budget ProAntioquia'!L105 -> 15344.91 | C15: ='Budget ProAntioquia'!M105 -> 3336 | D15: ='Budget ProAntioquia'!N105 -> 18680.91 | E15: ='Budget ProAntioquia'!R105 -> 9270 | F15: ='Budget ProAntioquia'!S105 -> 4466.904 | G15: ='Budget ProAntioquia'!T105 -> 13736.904 | H15: ='Budget ProAntioquia'!X105 -> 9548.1 | I15: ='Budget ProAntioquia'!Y105 -> 4600.9111 | J15: ='Budget ProAntioquia'!Z105 -> 14149.011 | K15: ='Budget ProAntioquia'!AD105 -> 4917.2715 | L15: ='Budget ProAntioquia'!AE105 -> 4738.9385 | M15: ='Budget ProAntioquia'!AF105 -> 9656.21 | N15: ='Budget ProAntioquia'!AJ105 -> 3798.5922 | O15: ='Budget ProAntioquia'!AK105 -> 4881.1066 | P15: ='Budget ProAntioquia'!AL105 -> 8679.6988 | Q15: ='Budget ProAntioquia'!AM105 -> 42878.874 | R15: ='Budget ProAntioquia'!AN105 -> 22023.86 | S15: ='Budget ProAntioquia'!AO105 -> 64902.734
A17: Contractual | B17: ='Budget ProAntioquia'!L119 -> 42850 | C17: ='Budget ProAntioquia'!M119 -> 0 | D17: ='Budget ProAntioquia'!N119 -> 42850 | E17: ='Budget ProAntioquia'!R119 -> 47050 | F17: ='Budget ProAntioquia'!S119 -> 0 | G17: ='Budget ProAntioquia'!T119 -> 47050 | H17: ='Budget ProAntioquia'!X119 -> 22050 | I17: ='Budget ProAntioquia'!Y119 -> 0 | J17: ='Budget ProAntioquia'!Z119 -> 22050 | K17: ='Budget ProAntioquia'!AD119 -> 22050 | L17: ='Budget ProAntioquia'!AE119 -> 0 | M17: ='Budget ProAntioquia'!AF119 -> 22050 | N17: ='Budget ProAntioquia'!AJ119 -> 19950 | O17: ='Budget ProAntioquia'!AK119 -> 0 | P17: ='Budget ProAntioquia'!AL119 -> 19950 | Q17: ='Budget ProAntioquia'!AM119 -> 153950 | R17: ='Budget ProAntioquia'!AN119 -> 0 | S17: ='Budget ProAntioquia'!AO119 -> 153950
A19: Other Direct Costs | B19: ='Budget ProAntioquia'!L160 -> 105566 | C19: ='Budget ProAntioquia'!M160 -> 33306 | D19: ='Budget ProAntioquia'!N160 -> 138872 | E19: ='Budget ProAntioquia'!R160 -> 176388.48 | F19: ='Budget ProAntioquia'!S160 -> 0 | G19: ='Budget ProAntioquia'!T160 -> 176388.48 | H19: ='Budget ProAntioquia'!X160 -> 85222.354 | I19: ='Budget ProAntioquia'!Y160 -> 0 | J19: ='Budget ProAntioquia'!Z160 -> 85222.354 | K19: ='Budget ProAntioquia'!AD160 -> 94155.779 | L19: ='Budget ProAntioquia'!AE160 -> 0 | M19: ='Budget ProAntioquia'!AF160 -> 94155.779 | N19: ='Budget ProAntioquia'!AJ160 -> 20519.592 | O19: ='Budget ProAntioquia'!AK160 -> 0 | P19: ='Budget ProAntioquia'!AL160 -> 20519.592 | Q19: ='Budget ProAntioquia'!AM160 -> 481852.2 | R19: ='Budget ProAntioquia'!AN160 -> 33306 | S19: ='Budget ProAntioquia'!AO160 -> 515158.2
A21: Total Direct Costs | B21: =SUM(B7:B20) -> 447655.14 | C21: =SUM(C7:C20) -> 79869.195 | D21: =SUM(D7:D20) -> 527524.33 | E21: =SUM(E7:E20) -> 517725.42 | F21: =SUM(F7:F20) -> 52531.003 | G21: =SUM(G7:G20) -> 570256.42 | H21: =SUM(H7:H20) -> 414551.14 | I21: =SUM(I7:I20) -> 54587.574 | ... S21: =SUM(S7:S20) -> 2434784.4
A22: Indirect Costs | B22: ='Budget ProAntioquia'!L163 -> 0 | C22: ='Budget ProAntioquia'!M163 -> 0 | D22: ='Budget ProAntioquia'!N163 -> 0 | E22: ='Budget ProAntioquia'!R163 -> 0 | F22: ='Budget ProAntioquia'!S163 -> 0 | G22: ='Budget ProAntioquia'!T163 -> 0 | H22: ='Budget ProAntioquia'!X163 -> 0 | I22: ='Budget ProAntioquia'!Y163 -> 0 | J22: ='Budget ProAntioquia'!Z163 -> 0 | K22: ='Budget ProAntioquia'!AD163 -> 0 | L22: ='Budget ProAntioquia'!AE163 -> 0 | M22: ='Budget ProAntioquia'!AF163 -> 0 | N22: ='Budget ProAntioquia'!AJ163 -> 0 | O22: ='Budget ProAntioquia'!AK163 -> 0 | P22: ='Budget ProAntioquia'!AL163 -> 0 | Q22: ='Budget ProAntioquia'!AM163 -> 0 | R22: ='Budget ProAntioquia'!AN163 -> 0 | S22: ='Budget ProAntioquia'!AO163 -> 0
A23: Total | B23: =B22+B21 -> 447655.14 | C23: =C22+C21 -> 79869.195 | D23: =D22+D21 -> 527524.33 | E23: =E22+E21 -> 517725.42 | F23: =F22+F21 -> 52531.003 | G23: =G22+G21 -> 570256.42 | H23: =H22+H21 -> 414551.14 | I23: =I22+I21 -> 54587.574 | ... S23: =S22+S21 -> 2434784.4

Sheet Budget ProAntioquia
H1: USAID Juntos Aprendemos
H2: ProAntioquia
H3: Subaward Budget
A4: Entity: | B4: P | H4: Country: Colombia
A5: Program-Dept.: | B5: 20300 | G5: Budget Assumptions
A6: Funder-Grant: | B6: USAID800 | G6: Inflation - Locally Purchased Goods/Services - 3% | H6: 1.03
G7: Merit Based Increases for HQ & Field Staff - 4% | H7: 1.04
G9: *Key Personnel
A10: Sage Activity | B10: Sage Object Code/ Line Item | C10: Country Code (DC=0 or CO) | D10: Office Code (DC=0 or CO) | E10: Subcontract Code | F10: Open 1 Code | G10: Line Item | L10: Year 1 | R10: Year 2 | U10: Year 3 | AD10: Year 4 | AJ10: Year 5 | AM10: Total | AN10: Total | AO10: Grand
H11: Unit | I11: Cost | J11: Duration | K11: Type | L11: USAID | M11: Leverage | N11: Total | O11: Unit | P11: Cost | Q11: Duration | R11: USAID | S11: Leverage | T11: Total | U11: Unit | V11: Cost | W11: Duration | X11: USAID | Y11: Leverage | Z11: Total | AA11: Unit | AB11: Cost | AC11: Duration | AD11: USAID | AE11: Leverage | AF11: Total | AG11: Unit | AH11: Cost | AI11: Duration | AJ11: USAID | AK11: Leverage | AL11: Total | AM11: USAID | AN11: Leverage | AO11: Total
G13: Personnel
G14: Headquarters Personnel | H14: LOE
G15: Project Office (Bogota)
A16: SUBPROANT | B16: 89050 | C16: COL2 | D16: COL2 | E16: PROANT | F16: PAPERSNL | G16: Partnerships and Alliances Director* | H16: 1 | I16: =52500/12 -> 4375 | J16: 11 | K16: /months | L16: =J16*I16*H16 -> 48125 | M16: 0 | N16: =SUM(L16:M16) -> 48125 | O16: =H16 -> 1 | P16: =I16*$H$7 -> 4550 | Q16: 12 | R16: =O16*P16*Q16 -> 54600 | S16: 0 | T16: =SUM(R16:S16) -> 54600 | U16: =H16 -> 1 | V16: =+I16*$H$7*$H$7 -> 4732 | W16: 12 | X16: =U16*V16*W16 -> 56784 | Y16: 0 | Z16: =SUM(X16:Y16) -> 56784 | AA16: =U16 -> 1 | AB16: =+I16*$H$7*$H$7*$H$7 -> 4921.28 | AC16: 12 | AD16: =AA16*AB16*AC16 -> 59055.36 | AE16: 0 | AF16: =SUM(AD16:AE16) -> 59055.36 | AG16: =AA16 -> 1 | AH16: =+I16*$H$7*$H$7*$H$7*$H$7 -> 5118.1312 | AI16: 12 | AJ16: =AG16*AH16*AI16 -> 61417.574 | AK16: 0 | AL16: =SUM(AJ16:AK16) -> 61417.574 | AM16: =L16+R16+X16+AD16+AJ16 -> 279981.93 | AN16: =M16+S16+Y16+AE16+AK16 -> 0 | AO16: =SUM(AM16:AN16) -> 279981.93
A17: SUBPROANT | B17: 89050 | C17: COL2 | D17: COL2 | E17: PROANT | F17: PAPERSNL | G17: Partnerships and Alliances Coordinator | H17: 1 | I17: =22500/12 -> 1875 | J17: 9 | K17: /months | L17: =J17*I17*H17 -> 16875 | M17: 0 | N17: =SUM(L17:M17) -> 16875 | O17: =H17 -> 1 | P17: =I17*$H$7 -> 1950 | Q17: 12 | R17: =O17*P17*Q17 -> 23400 | S17: 0 | T17: =SUM(R17:S17) -> 23400 | U17: =H17 -> 1 | V17: =+I17*$H$7*$H$7 -> 2028 | W17: 12 | X17: =U17*V17*W17 -> 24336 | Y17: 0 | Z17: =SUM(X17:Y17) -> 24336 | AA17: =U17 -> 1 | AB17: =+I17*$H$7*$H$7*$H$7 -> 2109.12 | AC17: 12 | AD17: =AA17*AB17*AC17 -> 25309.44 | AE17: 0 | AF17: =SUM(AD17:AE17) -> 25309.44 | AG17: =AA17 -> 1 | AH17: =+I17*$H$7*$H$7*$H$7*$H$7 -> 2193.4848 | AI17: 10 | AJ17: =AG17*AH17*AI17 -> 21934.848 | AK17: 0 | AL17: =SUM(AJ17:AK17) -> 21934.848 | AM17: =L17+R17+X17+AD17+AJ17 -> 111855.29 | AN17: =M17+S17+Y17+AE17+AK17 -> 0 | AO17: =SUM(AM17:AN17) -> 111855.29
G18: ProAntioquia Office
A19: SUBPROANT | B19: 89050 | C19: COL2 | D19: COL2 | E19: PROANT | F19: PAPERSNLEV | G19: Education Director (HQ-ProAntioquia) | H19: 0.3 | I19: 3433 | J19: 11 | K19: /months | L19: 0 | M19: =+H19*I19*J19 -> 11328.9 | N19: =SUM(L19:M19) -> 11328.9 | O19: =H19 -> 0.3 | P19: =I19*$H$7 -> 3570.32 | Q19: 12 | R19: 0 | S19: =+O19*P19*Q19 -> 12853.152 | T19: =SUM(R19:S19) -> 12853.152 | U19: =H19 -> 0.3 | V19: =+I19*$H$7*$H$7 -> 3713.1328 | W19: 12 | X19: 0 | Y19: =+U19*V19*W19 -> 13367.278 | Z19: =SUM(X19:Y19) -> 13367.278 | AA19: =U19 -> 0.3 | AB19: =+I19*$H$7*$H$7*$H$7 -> 3861.6581 | AC19: 12 | AD19: 0 | AE19: =+AA19*AB19*AC19 -> 13901.969 | AF19: =SUM(AD19:AE19) -> 13901.969 | AG19: =AA19 -> 0.3 | AH19: =+I19*$H$7*$H$7*$H$7*$H$7 -> 4016.1244 | AI19: 11 | AJ19: 0 | AK19: =+AG19*AH19*AI19 -> 13253.211 | AL19: =SUM(AJ19:AK19) -> 13253.211 | AM19: =L19+R19+X19+AD19+AJ19 -> 0 | AN19: =M19+S19+Y19+AE19+AK19 -> 64704.51 | AO19: =SUM(AM19:AN19) -> 64704.51
G20: Subtotal HQ Personnel | L20: =SUM(L16:L19) -> 65000 | M20: =SUM(M16:M19) -> 11328.9 | N20: =SUM(N16:N19) -> 76328.9 | R20: =SUM(R16:R19) -> 78000 | S20: =SUM(S16:S19) -> 12853.152 | T20: =SUM(T16:T19) -> 90853.152 | X20: =SUM(X16:X19) -> 81120 | Y20: =SUM(Y16:Y19) -> 13367.278 | Z20: =SUM(Z16:Z19) -> 94487.278 | AB20: =+I20*$H$7*$H$7*$H$7 -> 0 | AD20: =SUM(AD16:AD19) -> 84364.8 | AE20: =SUM(AE16:AE19) -> 13901.969 | AF20: =SUM(AF16:AF19) -> 98266.769 | AJ20: =SUM(AJ16:AJ19) -> 83352.422 | AK20: =SUM(AK16:AK19) -> 13253.211 | AL20: =SUM(AL16:AL19) -> 96605.633 | AM20: =SUM(AM16:AM19) -> 391837.22 | AN20: =SUM(AN16:AN19) -> 64704.51 | AO20: =SUM(AO16:AO19) -> 456541.73
G22: Field Personnel | H22: LOE | AB22: =+I22*$H$7*$H$7*$H$7 -> 0
A23: SUBPROANT | B23: 89050 | C23: COL2 | D23: COL2 | E23: PROANT | F23: PAPERSNL | G23: Teacher Training Specialist | H23: 1 | I23: =31200/12 -> 2600 | J23: 9 | K23: /months | L23: =J23*I23*H23 -> 23400 | M23: 0 | N23: =SUM(L23:M23) -> 23400 | O23: =H23 -> 1 | P23: =I23*$H$7 -> 2704 | Q23: 12 | R23: =O23*P23*Q23 -> 32448 | S23: 0 | T23: =SUM(R23:S23) -> 32448 | U23: =O23 -> 1 | V23: =+I23*$H$7*$H$7 -> 2812.16 | W23: 12 | X23: =U23*V23*W23 -> 33745.92 | Y23: 0 | Z23: =SUM(X23:Y23) -> 33745.92 | AA23: =U23 -> 1 | AB23: =+I23*$H$7*$H$7*$H$7 -> 2924.6464 | AC23: 12 | AD23: =AA23*AB23*AC23 -> 35095.757 | AE23: 0 | AF23: =SUM(AD23:AE23) -> 35095.757 | AG23: =AA23 -> 1 | AH23: =+I23*$H$7*$H$7*$H$7*$H$7 -> 3041.6323 | AI23: 10 | AJ23: =AG23*AH23*AI23 -> 30416.323 | AK23: 0 | AL23: =SUM(AJ23:AK23) -> 30416.323 | AM23: =L23+R23+X23+AD23+AJ23 -> 155106 | AN23: =M23+S23+Y23+AE23+AK23 -> 0 | AO23: =SUM(AM23:AN23) -> 155106
A24: SUBPROANT | B24: 89050 | C24: COL2 | D24: COL2 | E24: PROANT | F24: PAPERSNL | G24: Teacher Training Professionals (3) | H24: 1 | I24: =(15000/12)*3 -> 3750 | J24: 9 | K24: /months | L24: =J24*I24*H24 -> 33750 | M24: 0 | N24: =SUM(L24:M24) -> 33750 | O24: 1 | P24: =I24*$H$7 -> 3900 | Q24: 12 | R24: =P24*Q24*O24 -> 46800 | S24: 0 | T24: =SUM(R24:S24) -> 46800 | U24: 1 | V24: =+I24*$H$7*$H$7 -> 4056 | W24: 12 | X24: =W24*V24*U24 -> 48672 | Y24: 0 | Z24: =SUM(X24:Y24) -> 48672 | AA24: 1 | AB24: =+I24*$H$7*$H$7*$H$7 -> 4218.24 | AC24: 12 | AD24: =AC24*AB24*AA24 -> 50618.88 | AE24: 0 | AF24: =SUM(AD24:AE24) -> 50618.88 | AG24: 1 | AH24: =+I24*$H$7*$H$7*$H$7*$H$7 -> 4386.9696 | AI24: 9 | AJ24: =AI24*AH24*AG24 -> 39482.726 | AK24: 0 | AL24: =SUM(AJ24:AK24) -> 39482.726 | AM24: =L24+R24+X24+AD24+AJ24 -> 219323.61 | AN24: =M24+S24+Y24+AE24+AK24 -> 0 | AO24: =SUM(AM24:AN24) -> 219323.61
A25: SUBPROANT | B25: 89050 | C25: COL2 | D25: COL2 | E25: PROANT | F25: PAPERSNLEV | G25: Administrative Coordinator | H25: 1 | I25: 2000 | J25: 4 | K25: /months | L25: 0 | M25: =+H25*I25*J25 -> 8000 | N25: =SUM(L25:M25) -> 8000 | O25: 1 | P25: =I25*$H$7 -> 2080 | Q25: 4 | R25: 0 | S25: =+O25*P25*Q25 -> 8320 | T25: =SUM(R25:S25) -> 8320 | U25: 1 | V25: =+I25*$H$7*$H$7 -> 2163.2 | W25: 4 | X25: 0 | Y25: =+U25*V25*W25 -> 8652.8 | Z25: =SUM(X25:Y25) -> 8652.8 | AA25: 1 | AB25: =+I25*$H$7*$H$7*$H$7 -> 2249.728 | AC25: 4 | AD25: 0 | AE25: =+AA25*AB25*AC25 -> 8998.912 | AF25: =SUM(AD25:AE25) -> 8998.912 | AG25: 1 | AH25: =+I25*$H$7*$H$7*$H$7*$H$7 -> 2339.7171 | AI25: 4 | AJ25: 0 | AK25: =+AG25*AH25*AI25 -> 9358.8685 | AL25: =SUM(AJ25:AK25) -> 9358.8685 | AM25: =L25+R25+X25+AD25+AJ25 -> 0 | AN25: =M25+S25+Y25+AE25+AK25 -> 43330.58 | AO25: =SUM(AM25:AN25) -> 43330.58
A26: SUBPROANT | B26: 89050 | C26: COL2 | D26: COL2 | E26: PROANT | F26: PAPERSNLEV | G26: Professional Accountant | H26: 1 | I26: 1030 | J26: 3 | K26: /months | L26: 0 | M26: =+H26*I26*J26 -> 3090 | N26: =SUM(L26:M26) -> 3090 | O26: 1 | P26: =I26*$H$7 -> 1071.2 | Q26: 3 | R26: 0 | S26: =+O26*P26*Q26 -> 3213.6 | T26: =SUM(R26:S26) -> 3213.6 | U26: 1 | V26: =+I26*$H$7*$H$7 -> 1114.048 | W26: 3 | X26: 0 | Y26: =+U26*V26*W26 -> 3342.144 | Z26: =SUM(X26:Y26) -> 3342.144 | AA26: 1 | AB26: =+I26*$H$7*$H$7*$H$7 -> 1158.6099 | AC26: 3 | AD26: 0 | AE26: =+AA26*AB26*AC26 -> 3475.8298 | AF26: =SUM(AD26:AE26) -> 3475.8298 | AG26: 1 | AH26: =+I26*$H$7*$H$7*$H$7*$H$7 -> 1204.9543 | AI26: 3 | AJ26: 0 | AK26: =+AG26*AH26*AI26 -> 3614.863 | AL26: =SUM(AJ26:AK26) -> 3614.863 | AM26: =L26+R26+X26+AD26+AJ26 -> 0 | AN26: =M26+S26+Y26+AE26+AK26 -> 16736.437 | AO26: =SUM(AM26:AN26) -> 16736.437
A27: SUBPROANT | B27: 89050 | C27: COL2 | D27: COL2 | E27: PROANT | F27: PAPERSNLEV | G27: Visual Documentation Professional | H27: 1 | I27: 1144 | J27: 2 | K27: /months | L27: 0 | M27: =+H27*I27*J27 -> 2288 | N27: =SUM(L27:M27) -> 2288 | O27: 1 | P27: =I27*$H$7 -> 1189.76 | Q27: 2 | R27: 0 | S27: =+O27*P27*Q27 -> 2379.52 | T27: =SUM(R27:S27) -> 2379.52 | U27: 1 | V27: =+I27*$H$7*$H$7 -> 1237.3504 | W27: 2 | X27: 0 | Y27: =+U27*V27*W27 -> 2474.7008 | Z27: =SUM(X27:Y27) -> 2474.7008 | AA27: 1 | AB27: =+I27*$H$7*$H$7*$H$7 -> 1286.8444 | AC27: 2 | AD27: 0 | AE27: =+AA27*AB27*AC27 -> 2573.6888 | AF27: =SUM(AD27:AE27) -> 2573.6888 | AG27: 1 | AH27: =+I27*$H$7*$H$7*$H$7*$H$7 -> 1338.3182 | AI27: 2 | AJ27: 0 | AK27: =+AG27*AH27*AI27 -> 2676.6364 | AL27: =SUM(AJ27:AK27) -> 2676.6364 | AM27: =L27+R27+X27+AD27+AJ27 -> 0 | AN27: =M27+S27+Y27+AE27+AK27 -> 12392.546 | AO27: =SUM(AM27:AN27) -> 12392.546
A28: SUBPROANT | B28: 89050 | C28: COL2 | D28: COL2 | E28: PROANT | F28: PAPERSNL | G28: Content Development Professional | H28: 1 | I28: =15000/12 -> 1250 | J28: 6 | K28: /months | L28: =J28*I28*H28 -> 7500 | M28: 0 | N28: =SUM(L28:M28) -> 7500 | O28: 1 | P28: =I28*$H$7 -> 1300 | Q28: 0 | R28: =P28*Q28*O28 -> 0 | S28: 0 | T28: =SUM(R28:S28) -> 0 | U28: 1 | V28: =+I28*$H$7*$H$7 -> 1352 | W28: 0 | X28: =W28*V28*U28 -> 0 | Y28: 0 | Z28: =SUM(X28:Y28) -> 0 | AA28: 1 | AB28: =+I28*$H$7*$H$7*$H$7 -> 1406.08 | AC28: 0 | AD28: =AC28*AB28*AA28 -> 0 | AE28: 0 | AF28: =SUM(AD28:AE28) -> 0 | AG28: 1 | AH28: =+I28*$H$7*$H$7*$H$7*$H$7 -> 1462.3232 | AI28: 0 | AJ28: =AI28*AH28*AG28 -> 0 | AK28: 0 | AL28: =SUM(AJ28:AK28) -> 0 | AM28: =L28+R28+X28+AD28+AJ28 -> 7500 | AN28: =M28+S28+Y28+AE28+AK28 -> 0 | AO28: =SUM(AM28:AN28) -> 7500
A29: SUBPROANT | B29: 89050 | C29: COL2 | D29: COL2 | E29: PROANT | F29: PAPERSNL | G29: Finance & Admin Coordinator | H29: 1 | I29: =22500/12 -> 1875 | J29: 9 | K29: /months | L29: =J29*I29*H29 -> 16875 | M29: 0 | N29: =SUM(L29:M29) -> 16875 | O29: =H29 -> 1 | P29: =I29*$H$7 -> 1950 | Q29: 12 | R29: =O29*P29*Q29 -> 23400 | S29: 0 | T29: =SUM(R29:S29) -> 23400 | U29: =O29 -> 1 | V29: =+I29*$H$7*$H$7 -> 2028 | W29: 12 | X29: =U29*V29*W29 -> 24336 | Y29: 0 | Z29: =SUM(X29:Y29) -> 24336 | AA29: =U29 -> 1 | AB29: =+I29*$H$7*$H$7*$H$7 -> 2109.12 | AC29: 12 | AD29: =AA29*AB29*AC29 -> 25309.44 | AE29: 0 | AF29: =SUM(AD29:AE29) -> 25309.44 | AG29: =AA29 -> 1 | AH29: =+I29*$H$7*$H$7*$H$7*$H$7 -> 2193.4848 | AI29: 10 | AJ29: =AG29*AH29*AI29 -> 21934.848 | AK29: 0 | AL29: =SUM(AJ29:AK29) -> 21934.848 | AM29: =L29+R29+X29+AD29+AJ29 -> 111855.29 | AN29: =M29+S29+Y29+AE29+AK29 -> 0 | AO29: =SUM(AM29:AN29) -> 111855.29
A30: SUBPROANT | B30: 89050 | C30: COL2 | D30: COL2 | E30: PROANT | F30: PAPERSNLEV | G30: Operational and Planning Professional | H30: 1 | I30: 1000 | J30: 5 | K30: /months | L30: 0 | M30: =+I30*J30 -> 5000 | N30: =SUM(L30:M30) -> 5000 | O30: 1 | P30: =I30*$H$7 -> 1040 | Q30: 6 | R30: 0 | S30: =+P30*Q30 -> 6240 | T30: =SUM(R30:S30) -> 6240 | U30: 1 | V30: =+I30*$H$7*$H$7 -> 1081.6 | W30: 6 | X30: 0 | Y30: =+V30*W30 -> 6489.6 | Z30: =SUM(X30:Y30) -> 6489.6 | AA30: 1 | AB30: =+I30*$H$7*$H$7*$H$7 -> 1124.864 | AC30: 6 | AD30: 0 | AE30: =+AB30*AC30 -> 6749.184 | AF30: =SUM(AD30:AE30) -> 6749.184 | AG30: 1 | AH30: =+I30*$H$7*$H$7*$H$7*$H$7 -> 1169.8586 | AI30: 6 | AJ30: 0 | AK30: =+AH30*AI30 -> 7019.1514 | AL30: =SUM(AJ30:AK30) -> 7019.1514 | AM30: =L30+R30+X30+AD30+AJ30 -> 0 | AN30: =M30+S30+Y30+AE30+AK30 -> 31497.935 | AO30: =SUM(AM30:AN30) -> 31497.935
G31: Subtotal Field Personnel | L31: =SUM(L23:L30) -> 81525 | M31: =SUM(M23:M30) -> 18378 | N31: =SUM(N23:N30) -> 99903 | R31: =SUM(R23:R30) -> 102648 | S31: =SUM(S23:S30) -> 20153.12 | T31: =SUM(T23:T30) -> 122801.12 | X31: =SUM(X23:X30) -> 106753.92 | Y31: =SUM(Y23:Y30) -> 20959.245 | Z31: =SUM(Z23:Z30) -> 127713.16 | AD31: =SUM(AD23:AD30) -> 111024.08 | AE31: =SUM(AE23:AE30) -> 21797.615 | AF31: =SUM(AF23:AF30) -> 132821.69 | AJ31: =SUM(AJ23:AJ30) -> 91833.897 | AK31: =SUM(AK23:AK30) -> 22669.519 | AL31: =SUM(AL23:AL30) -> 114503.42 | AM31: =SUM(AM23:AM30) -> 493784.89 | AN31: =SUM(AN23:AN30) -> 103957.5 | AO31: =SUM(AO23:AO30) -> 597742.39
G33: Personnel Total | L33: =L31+L20 -> 146525 | M33: =M31+M20 -> 29706.9 | N33: =N31+N20 -> 176231.9 | R33: =R31+R20 -> 180648 | S33: =S31+S20 -> 33006.272 | T33: =T31+T20 -> 213654.27 | X33: =X31+X20 -> 187873.92 | Y33: =Y31+Y20 -> 34326.523 | Z33: =Z31+Z20 -> 222200.44 | AD33: =AD31+AD20 -> 195388.88 | AE33: =AE31+AE20 -> 35699.584 | AF33: =AF31+AF20 -> 231088.46 | AJ33: =AJ31+AJ20 -> 175186.32 | AK33: =AK31+AK20 -> 35922.73 | AL33: =AL31+AL20 -> 211109.05 | AM33: =AM31+AM20 -> 885622.12 | AN33: =AN31+AN20 -> 168662.01 | AO33: =AO31+AO20 -> 1054284.1
G35: Fringe Benefits
A36: SUBPROANT | B36: 89050 | C36: COL2 | D36: COL2 | E36: PROANT | F36: PAFRINGE/ PAFRINGEL | G36: Fringe Benefits – Colombia HQ and Field Staff (above $2,600 monthly) | H36: 0.53864 | L36: =$H$36*(L16+L19+L23) -> 38526.226 | M36: =$H$36*(M16+M19+M23) -> 6102.1987 | N36: =SUM(L36:M36) -> 44628.425 | O36: =H36 -> 0.53864 | R36: =$H$36*(R16+R19+R23) -> 46887.535 | S36: =$H$36*(S16+S19+S23) -> 6923.2218 | T36: =+R36+S36 -> 53810.757 | U36: =H36 -> 0.53864 | X36: =$H$36*(X16+X19+X23) -> 48763.036 | Y36: =$H$36*(Y16+Y19+Y23) -> 7200.1507 | Z36: =SUM(X36:Y36) -> 55963.187 | AA36: =H36 -> 0.53864 | AD36: =$H$36*(AD16+AD19+AD23) -> 50713.558 | AE36: =$H$36*(AE16+AE19+AE23) -> 7488.1567 | AF36: =SUM(AD36:AE36) -> 58201.714 | AG36: =H36 -> 0.53864 | AJ36: =$H$36*(AJ16+AJ19+AJ23) -> 49465.41 | AK36: =$H$36*(AK16+AK19+AK23) -> 7138.7094 | AL36: =SUM(AJ36:AK36) -> 56604.12 | AM36: =+AJ36+AD36+X36+R36+L36 -> 234355.76 | AN36: =+AK36+AE36+Y36+S36+M36 -> 34852.437 | AO36: =+SUM(AM36:AN36) -> 269208.2
A37: SUBPROANT | B37: 89050 | C37: COL2 | D37: COL2 | E37: PROANT | F37: PAFRINGE/ PAFRINGEL | G37: Fringe Benefits - Colombia HQ and Field Staff (below $2,600 monthly) | H37: 0.40364 | L37: =$H$37*(L17+L24+L25+L26+L27+L28+L29+L30) -> 30273 | M37: =$H$37*(M17+M24+M25+M26+M27+M28+M29+M30) -> 7418.0959 | N37: =SUM(L37:M37) -> 37691.096 | O37: =H37 -> 0.40364 | R37: =$H$37*(R17+R24+R25+R26+R27+R28+R29+R30) -> 37780.704 | S37: =$H$37*(S17+S24+S25+S26+S27+S28+S29+S30) -> 8134.6054 | T37: =+R37+S37 -> 45915.309 | U37: =H37 -> 0.40364 | X37: =$H$37*(X17+X24+X25+X26+X27+X28+X29+X30) -> 39291.932 | Y37: =$H$37*(Y17+Y24+Y25+Y26+Y27+Y28+Y29+Y30) -> 8459.9896 | Z37: =SUM(X37:Y37) -> 47751.922 | AA37: =H37 -> 0.40364 | AD37: =$H$37*(AD17+AD24+AD25+AD26+AD27+AD28+AD29+AD30) -> 40863.609 | AE37: =$H$37*(AE17+AE24+AE25+AE26+AE27+AE28+AE29+AE30) -> 8798.3892 | AF37: =SUM(AD37:AE37) -> 49661.999 | AG37: =H37 -> 0.40364 | AJ37: =$H$37*(AJ17+AJ24+AJ25+AJ26+AJ27+AJ28+AJ29+AJ30) -> 33644.372 | AK37: =$H$37*(AK17+AK24+AK25+AK26+AK27+AK28+AK29+AK30) -> 9150.3247 | AL37: =SUM(AJ37:AK37) -> 42794.696 | AM37: =+AJ37+AD37+X37+R37+L37 -> 181853.62 | AN37: =+AK37+AE37+Y37+S37+M37 -> 41961.405 | AO37: =+SUM(AM37:AN37) -> 223815.02
G39: Fringe Benefits Total | L39: =SUM(L36:L37) -> 68799.226 | M39: =SUM(M36:M37) -> 13520.295 | N39: =SUM(N36:N37) -> 82319.521 | R39: =SUM(R36:R37) -> 84668.239 | S39: =SUM(S36:S37) -> 15057.827 | T39: =SUM(T36:T37) -> 99726.066 | X39: =SUM(X36:X37) -> 88054.968 | Y39: =SUM(Y36:Y37) -> 15660.14 | Z39: =SUM(Z36:Z37) -> 103715.11 | AD39: =SUM(AD36:AD37) -> 91577.167 | AE39: =SUM(AE36:AE37) -> 16286.546 | AF39: =SUM(AF36:AF37) -> 107863.71 | AJ39: =SUM(AJ36:AJ37) -> 83109.782 | AK39: =SUM(AK36:AK37) -> 16289.034 | AL39: =SUM(AL36:AL37) -> 99398.816 | AM39: =SUM(AM36:AM38) -> 416209.38 | AN39: =SUM(AN36:AN38) -> 76813.842 | AO39: =SUM(AM39:AN39) -> 493023.22
G41: Travel
G43: HQ Staff Travel
A44: SUBPROANT | B44: 89050 | C44: COL2 | D44: COL2 | E44: PROANT | F44: PAHQTRVL | G44: Local Transportation (Airfare, Taxis, & Rental Car/Driver) for Directors | H44: 2 | I44: 250 | J44: 1 | K44: /trip | L44: =J44*I44*H44 -> 500 | M44: 0 | N44: =SUM(L44:M44) -> 500 | O44: 2 | P44: =I44*$H$6 -> 257.5 | Q44: 1 | R44: =O44*P44*Q44 -> 515 | S44: 0 | T44: =SUM(R44:S44) -> 515 | U44: 2 | V44: =I44*$H$6*$H$6 -> 265.225 | W44: 1 | X44: =U44*V44*W44 -> 530.45 | Y44: 0 | Z44: =SUM(X44:Y44) -> 530.45 | AA44: 2 | AB44: =I44*$H$6*$H$6*$H$6 -> 273.18175 | AC44: 1 | AD44: =AA44*AB44*AC44 -> 546.3635 | AE44: 0 | AF44: =SUM(AD44:AE44) -> 546.3635 | AG44: 2 | AH44: =I44*$H$6*$H$6*$H$6*$H$6 -> 281.3772 | AI44: 1 | AJ44: =AG44*AH44*AI44 -> 562.75441 | AK44: 0 | AL44: =SUM(AJ44:AK44) -> 562.75441 | AM44: =L44+R44+X44+AD44+AJ44 -> 2654.5679 | AN44: =M44+S44+Y44+AE44+AK44 -> 0 | AO44: =SUM(AM44:AN44) -> 2654.5679
A45: SUBPROANT | B45: 89050 | C45: COL2 | D45: COL2 | E45: PROANT | F45: PAHQTRVL | G45: Meals and Incidentals for Directors | H45: 2 | I45: 40 | J45: 5 | K45: /day | L45: =J45*I45*H45 -> 400 | M45: 0 | N45: =SUM(L45:M45) -> 400 | O45: 2 | P45: =I45*$H$6 -> 41.2 | Q45: 5 | R45: =O45*P45*Q45 -> 412 | S45: 0 | T45: =SUM(R45:S45) -> 412 | U45: 2 | V45: =I45*$H$6*$H$6 -> 42.436 | W45: 5 | X45: =U45*V45*W45 -> 424.36 | Y45: 0 | Z45: =SUM(X45:Y45) -> 424.36 | AA45: 2 | AB45: =I45*$H$6*$H$6*$H$6 -> 43.70908 | AC45: 5 | AD45: =AA45*AB45*AC45 -> 437.0908 | AE45: 0 | AF45: =SUM(AD45:AE45) -> 437.0908 | AG45: 2 | AH45: =I45*$H$6*$H$6*$H$6*$H$6 -> 45.020352 | AI45: 5 | AJ45: =AG45*AH45*AI45 -> 450.20352 | AK45: 0 | AL45: =SUM(AJ45:AK45) -> 450.20352 | AM45: =L45+R45+X45+AD45+AJ45 -> 2123.6543 | AN45: =M45+S45+Y45+AE45+AK45 -> 0 | AO45: =SUM(AM45:AN45) -> 2123.6543
A46: SUBPROANT | B46: 89050 | C46: COL2 | D46: COL2 | E46: PROANT | F46: PAHQTRVL | G46: Lodging for Directors | H46: 2 | I46: 80 | J46: 4 | K46: /day | L46: =J46*I46*H46 -> 640 | M46: 0 | N46: =SUM(L46:M46) -> 640 | O46: 2 | P46: =I46*$H$6 -> 82.4 | Q46: 4 | R46: =O46*P46*Q46 -> 659.2 | S46: 0 | T46: =SUM(R46:S46) -> 659.2 | U46: 2 | V46: =I46*$H$6*$H$6 -> 84.872 | W46: 4 | X46: =U46*V46*W46 -> 678.976 | Y46: 0 | Z46: =SUM(X46:Y46) -> 678.976 | AA46: 2 | AB46: =I46*$H$6*$H$6*$H$6 -> 87.41816 | AC46: 4 | AD46: =AA46*AB46*AC46 -> 699.34528 | AE46: 0 | AF46: =SUM(AD46:AE46) -> 699.34528 | AG46: 2 | AH46: =I46*$H$6*$H$6*$H$6*$H$6 -> 90.040705 | AI46: 4 | AJ46: =AG46*AH46*AI46 -> 720.32564 | AK46: 0 | AL46: =SUM(AJ46:AK46) -> 720.32564 | AM46: =L46+R46+X46+AD46+AJ46 -> 3397.8469 | AN46: =M46+S46+Y46+AE46+AK46 -> 0 | AO46: =SUM(AM46:AN46) -> 3397.8469
A47: SUBPROANT | B47: 89050 | C47: COL2 | D47: COL2 | E47: PROANT | F47: PAHQTRVL | G47: Other Travel Related Expenses for Directors | H47: 2 | I47: 25 | J47: 1 | K47: /trip | L47: =J47*I47*H47 -> 50 | M47: 0 | N47: =SUM(L47:M47) -> 50 | O47: 2 | P47: =I47*$H$6 -> 25.75 | Q47: 1 | R47: =O47*P47*Q47 -> 51.5 | S47: 0 | T47: =SUM(R47:S47) -> 51.5 | U47: 2 | V47: =I47*$H$6*$H$6 -> 26.5225 | W47: 1 | X47: =U47*V47*W47 -> 53.045 | Y47: 0 | Z47: =SUM(X47:Y47) -> 53.045 | AA47: 2 | AB47: =I47*$H$6*$H$6*$H$6 -> 27.318175 | AC47: 1 | AD47: =AA47*AB47*AC47 -> 54.63635 | AE47: 0 | AF47: =SUM(AD47:AE47) -> 54.63635 | AG47: 2 | AH47: =I47*$H$6*$H$6*$H$6*$H$6 -> 28.13772 | AI47: 1 | AJ47: =AG47*AH47*AI47 -> 56.275441 | AK47: 0 | AL47: =SUM(AJ47:AK47) -> 56.275441 | AM47: =L47+R47+X47+AD47+AJ47 -> 265.45679 | AN47: =M47+S47+Y47+AE47+AK47 -> 0 | AO47: =SUM(AM47:AN47) -> 265.45679
G48: Subtotal HQ Staff Travel | L48: =SUM(L44:L47) -> 1590 | M48: =SUM(M44:M47) -> 0 | N48: =SUM(N44:N47) -> 1590 | R48: =SUM(R44:R47) -> 1637.7 | S48: =SUM(S44:S47) -> 0 | T48: =SUM(T44:T47) -> 1637.7 | X48: =SUM(X44:X47) -> 1686.831 | Y48: =SUM(Y44:Y47) -> 0 | Z48: =SUM(Z44:Z47) -> 1686.831 | AD48: =SUM(AD44:AD47) -> 1737.4359 | AE48: =SUM(AE44:AE47) -> 0 | AF48: =SUM(AF44:AF47) -> 1737.4359 | AJ48: =SUM(AJ44:AJ47) -> 1789.559 | AK48: =SUM(AK44:AK47) -> 0 | AL48: =SUM(AL44:AL47) -> 1789.559 | AM48: =SUM(AM44:AM47) -> 8441.5259 | AN48: =SUM(AN44:AN47) -> 0 | AO48: =SUM(AO44:AO47) -> 8441.5259
G50: Field Travel
G51: T.1 Field Staff Travel for Site Visits and M&E
A52: SUBPROANT | B52: 89050 | C52: COL2 | D52: COL2 | E52: PROANT | F52: PAT1TRVL | G52: Local Transportation (Airfare, Taxis, & Rental Car/Driver) for Site Visits and M&E | H52: 12 | I52: 250 | J52: 1 | K52: /trip | L52: =J52*I52*H52 -> 3000 | M52: 0 | N52: =SUM(L52:M52) -> 3000 | O52: 12 | P52: =I52*$H$6 -> 257.5 | Q52: 1 | R52: =O52*P52*Q52 -> 3090 | S52: 0 | T52: =SUM(R52:S52) -> 3090 | U52: 12 | V52: =I52*$H$6*$H$6 -> 265.225 | W52: 1 | X52: =U52*V52*W52 -> 3182.7 | Y52: 0 | Z52: =SUM(X52:Y52) -> 3182.7 | AA52: 12 | AB52: =I52*$H$6*$H$6*$H$6 -> 273.18175 | AC52: 1 | AD52: =AA52*AB52*AC52 -> 3278.181 | AE52: 0 | AF52: =SUM(AD52:AE52) -> 3278.181 | AG52: 12 | AH52: =I52*$H$6*$H$6*$H$6*$H$6 -> 281.3772 | AI52: 1 | AJ52: =AG52*AH52*AI52 -> 3376.5264 | AK52: 0 | AL52: =SUM(AJ52:AK52) -> 3376.5264 | AM52: =L52+R52+X52+AD52+AJ52 -> 15927.407 | AN52: =M52+S52+Y52+AE52+AK52 -> 0 | AO52: =SUM(AM52:AN52) -> 15927.407
A53: SUBPROANT | B53: 89050 | C53: COL2 | D53: COL2 | E53: PROANT | F53: PAT1TRVL | G53: Meals and Incidentals for Site Visits and M&E | H53: 12 | I53: 40 | J53: 5 | K53: /day | L53: =J53*I53*H53 -> 2400 | M53: 0 | N53: =SUM(L53:M53) -> 2400 | O53: 12 | P53: =I53*$H$6 -> 41.2 | Q53: 5 | R53: =O53*P53*Q53 -> 2472 | S53: 0 | T53: =SUM(R53:S53) -> 2472 | U53: 12 | V53: =I53*$H$6*$H$6 -> 42.436 | W53: 5 | X53: =U53*V53*W53 -> 2546.16 | Y53: 0 | Z53: =SUM(X53:Y53) -> 2546.16 | AA53: 12 | AB53: =I53*$H$6*$H$6*$H$6 -> 43.70908 | AC53: 5 | AD53: =AA53*AB53*AC53 -> 2622.5448 | AE53: 0 | AF53: =SUM(AD53:AE53) -> 2622.5448 | AG53: 12 | AH53: =I53*$H$6*$H$6*$H$6*$H$6 -> 45.020352 | AI53: 5 | AJ53: =AG53*AH53*AI53 -> 2701.2211 | AK53: 0 | AL53: =SUM(AJ53:AK53) -> 2701.2211 | AM53: =L53+R53+X53+AD53+AJ53 -> 12741.926 | AN53: =M53+S53+Y53+AE53+AK53 -> 0 | AO53: =SUM(AM53:AN53) -> 12741.926
A54: SUBPROANT | B54: 89050 | C54: COL2 | D54: COL2 | E54: PROANT | F54: PAT1TRVL | G54: Lodging for Site Visits and M&E | H54: 12 | I54: 80 | J54: 4 | K54: /day | L54: =J54*I54*H54 -> 3840 | M54: 0 | N54: =SUM(L54:M54) -> 3840 | O54: 12 | P54: =I54*$H$6 -> 82.4 | Q54: 4 | R54: =O54*P54*Q54 -> 3955.2 | S54: 0 | T54: =SUM(R54:S54) -> 3955.2 | U54: 12 | V54: =I54*$H$6*$H$6 -> 84.872 | W54: 4 | X54: =U54*V54*W54 -> 4073.856 | Y54: 0 | Z54: =SUM(X54:Y54) -> 4073.856 | AA54: 12 | AB54: =I54*$H$6*$H$6*$H$6 -> 87.41816 | AC54: 4 | AD54: =AA54*AB54*AC54 -> 4196.0717 | AE54: 0 | AF54: =SUM(AD54:AE54) -> 4196.0717 | AG54: 12 | AH54: =I54*$H$6*$H$6*$H$6*$H$6 -> 90.040705 | AI54: 4 | AJ54: =AG54*AH54*AI54 -> 4321.9538 | AK54: 0 | AL54: =SUM(AJ54:AK54) -> 4321.9538 | AM54: =L54+R54+X54+AD54+AJ54 -> 20387.082 | AN54: =M54+S54+Y54+AE54+AK54 -> 0 | AO54: =SUM(AM54:AN54) -> 20387.082
A55: SUBPROANT | B55: 89050 | C55: COL2 | D55: COL2 | E55: PROANT | F55: PAT1TRVL | G55: Other Travel Related Expenses for Site Visits and M&E | H55: 12 | I55: 25 | J55: 1 | K55: /trip | L55: =J55*I55*H55 -> 300 | M55: 0 | N55: =SUM(L55:M55) -> 300 | O55: 12 | P55: =I55*$H$6 -> 25.75 | Q55: 1 | R55: =O55*P55*Q55 -> 309 | S55: 0 | T55: =SUM(R55:S55) -> 309 | U55: 12 | V55: =I55*$H$6*$H$6 -> 26.5225 | W55: 1 | X55: =U55*V55*W55 -> 318.27 | Y55: 0 | Z55: =SUM(X55:Y55) -> 318.27 | AA55: 12 | AB55: =I55*$H$6*$H$6*$H$6 -> 27.318175 | AC55: 1 | AD55: =AA55*AB55*AC55 -> 327.8181 | AE55: 0 | AF55: =SUM(AD55:AE55) -> 327.8181 | AG55: 12 | AH55: =I55*$H$6*$H$6*$H$6*$H$6 -> 28.13772 | AI55: 1 | AJ55: =AG55*AH55*AI55 -> 337.65264 | AK55: 0 | AL55: =SUM(AJ55:AK55) -> 337.65264 | AM55: =L55+R55+X55+AD55+AJ55 -> 1592.7407 | AN55: =M55+S55+Y55+AE55+AK55 -> 0 | AO55: =SUM(AM55:AN55) -> 1592.7407
G57: T.2 Local Travel in Antioquia for Field Staff
A58: SUBPROANT | B58: 89050 | C58: COL2 | D58: COL2 | E58: PROANT | F58: PAT2FUELEX | G58: Vehicle Fuel Expense | H58: 6 | I58: =300 -> 300 | J58: 1 | K58: /month | L58: =J58*I58*H58 -> 1800 | M58: 0 | N58: =SUM(L58:M58) -> 1800 | O58: 12 | P58: =I58*$H$7 -> 312 | Q58: 1 | R58: =O58*P58*Q58 -> 3744 | S58: 0 | T58: =SUM(R58:S58) -> 3744 | U58: 12 | V58: =I58*$H$7*$H$7 -> 324.48 | W58: 1 | X58: =U58*V58*W58 -> 3893.76 | Y58: 0 | Z58: =SUM(X58:Y58) -> 3893.76 | AA58: 12 | AB58: =I58*$H$7*$H$7*$H$7 -> 337.4592 | AC58: 1 | AD58: =AA58*AB58*AC58 -> 4049.5104 | AE58: 0 | AF58: =SUM(AD58:AE58) -> 4049.5104 | AG58: 9 | AH58: =I58*$H$7*$H$7*$H$7*$H$7 -> 350.95757 | AI58: 1 | AJ58: =AG58*AH58*AI58 -> 3158.6181 | AK58: 0 | AL58: =SUM(AJ58:AK58) -> 3158.6181 | AM58: =L58+R58+X58+AD58+AJ58 -> 16645.889 | AN58: =M58+S58+Y58+AE58+AK58 -> 0 | AO58: =SUM(AM58:AN58) -> 16645.889
G60: T.3 Travel for Advisory Board Meetings - 2 Annually
A61: SUBPROANT | B61: 89050 | C61: COL2 | D61: COL2 | E61: PROANT | F61: PAT3TRVL | G61: Local Transportation for Advisory Board Meetings | H61: =2*2 -> 4 | I61: 80 | J61: 1 | K61: /trip | L61: =J61*I61*H61 -> 320 | M61: 0 | N61: =SUM(L61:M61) -> 320 | O61: 2 | P61: =I61*$H$7 -> 83.2 | Q61: 1 | R61: =O61*P61*Q61 -> 166.4 | S61: 0 | T61: =SUM(R61:S61) -> 166.4 | U61: =2*2 -> 4 | V61: =I61*$H$7*$H$7 -> 86.528 | W61: 1 | X61: =U61*V61*W61 -> 346.112 | Y61: 0 | Z61: =SUM(X61:Y61) -> 346.112 | AA61: =2*2 -> 4 | AB61: =I61*$H$7*$H$7*$H$7 -> 89.98912 | AC61: 1 | AD61: =AA61*AB61*AC61 -> 359.95648 | AE61: 0 | AF61: =SUM(AD61:AE61) -> 359.95648 | AG61: =2*2 -> 4 | AH61: =I61*$H$7*$H$7*$H$7*$H$7 -> 93.588685 | AI61: 1 | AJ61: =AG61*AH61*AI61 -> 374.35474 | AK61: 0 | AL61: =SUM(AJ61:AK61) -> 374.35474 | AM61: =L61+R61+X61+AD61+AJ61 -> 1566.8232 | AN61: =M61+S61+Y61+AE61+AK61 -> 0 | AO61: =SUM(AM61:AN61) -> 1566.8232
A62: SUBPROANT | B62: 89050 | C62: COL2 | D62: COL2 | E62: PROANT | F62: PAT3TRVL | G62: Meals and Incidentals for Advisory Board Meetings | H62: =2*2 -> 4 | I62: 40 | J62: 2 | K62: /day | L62: =J62*I62*H62 -> 320 | M62: 0 | N62: =SUM(L62:M62) -> 320 | O62: 2 | P62: =I62*$H$7 -> 41.6 | Q62: 2 | R62: =O62*P62*Q62 -> 166.4 | S62: 0 | T62: =SUM(R62:S62) -> 166.4 | U62: =2*2 -> 4 | V62: =I62*$H$7*$H$7 -> 43.264 | W62: 2 | X62: =U62*V62*W62 -> 346.112 | Y62: 0 | Z62: =SUM(X62:Y62) -> 346.112 | AA62: =2*2 -> 4 | AB62: =I62*$H$7*$H$7*$H$7 -> 44.99456 | AC62: 2 | AD62: =AA62*AB62*AC62 -> 359.95648 | AE62: 0 | AF62: =SUM(AD62:AE62) -> 359.95648 | AG62: =2*2 -> 4 | AH62: =I62*$H$7*$H$7*$H$7*$H$7 -> 46.794342 | AI62: 2 | AJ62: =AG62*AH62*AI62 -> 374.35474 | AK62: 0 | AL62: =SUM(AJ62:AK62) -> 374.35474 | AM62: =L62+R62+X62+AD62+AJ62 -> 1566.8232 | AN62: =M62+S62+Y62+AE62+AK62 -> 0 | AO62: =SUM(AM62:AN62) -> 1566.8232
A63: SUBPROANT | B63: 89050 | C63: COL2 | D63: COL2 | E63: PROANT | F63: PAT3TRVL | G63: Lodging for Advisory Board Meetings | H63: =2*2 -> 4 | I63: 80 | J63: 2 | K63: /day | L63: =J63*I63*H63 -> 640 | M63: 0 | N63: =SUM(L63:M63) -> 640 | O63: 2 | P63: =I63*$H$7 -> 83.2 | Q63: 2 | R63: =O63*P63*Q63 -> 332.8 | S63: 0 | T63: =SUM(R63:S63) -> 332.8 | U63: =2*2 -> 4 | V63: =I63*$H$7*$H$7 -> 86.528 | W63: 2 | X63: =U63*V63*W63 -> 692.224 | Y63: 0 | Z63: =SUM(X63:Y63) -> 692.224 | AA63: =2*2 -> 4 | AB63: =I63*$H$7*$H$7*$H$7 -> 89.98912 | AC63: 2 | AD63: =AA63*AB63*AC63 -> 719.91296 | AE63: 0 | AF63: =SUM(AD63:AE63) -> 719.91296 | AG63: =2*2 -> 4 | AH63: =I63*$H$7*$H$7*$H$7*$H$7 -> 93.588685 | AI63: 2 | AJ63: =AG63*AH63*AI63 -> 748.70948 | AK63: 0 | AL63: =SUM(AJ63:AK63) -> 748.70948 | AM63: =L63+R63+X63+AD63+AJ63 -> 3133.6464 | AN63: =M63+S63+Y63+AE63+AK63 -> 0 | AO63: =SUM(AM63:AN63) -> 3133.6464
A64: SUBPROANT | B64: 89050 | C64: COL2 | D64: COL2 | E64: PROANT | F64: PAT3TRVL | G64: Other Travel Related Expenses for Advisory Board Meetings | H64: =2*2 -> 4 | I64: 25 | J64: 1 | K64: /trip | L64: =J64*I64*H64 -> 100 | M64: 0 | N64: =SUM(L64:M64) -> 100 | O64: 2 | P64: =I64*$H$7 -> 26 | Q64: 1 | R64: =O64*P64*Q64 -> 52 | S64: 0 | T64: =SUM(R64:S64) -> 52 | U64: =2*2 -> 4 | V64: =I64*$H$7*$H$7 -> 27.04 | W64: 1 | X64: =U64*V64*W64 -> 108.16 | Y64: 0 | Z64: =SUM(X64:Y64) -> 108.16 | AA64: =2*2 -> 4 | AB64: =I64*$H$7*$H$7*$H$7 -> 28.1216 | AC64: 1 | AD64: =AA64*AB64*AC64 -> 112.4864 | AE64: 0 | AF64: =SUM(AD64:AE64) -> 112.4864 | AG64: =2*2 -> 4 | AH64: =I64*$H$7*$H$7*$H$7*$H$7 -> 29.246464 | AI64: 1 | AJ64: =AG64*AH64*AI64 -> 116.98586 | AK64: 0 | AL64: =SUM(AJ64:AK64) -> 116.98586 | AM64: =L64+R64+X64+AD64+AJ64 -> 489.63226 | AN64: =M64+S64+Y64+AE64+AK64 -> 0 | AO64: =SUM(AM64:AN64) -> 489.63226
G66: T.4 Travel for Annual Forums for Education Observatories
A67: SUBPROANT | B67: 89050 | C67: COL2 | D67: COL2 | E67: PROANT | F67: PAT4TRVL | G67: Local Transportation for Annual Forums | H67: 2 | I67: 50 | J67: 1 | K67: /trip | L67: =J67*I67*H67 -> 100 | M67: 0 | N67: =SUM(L67:M67) -> 100 | O67: 0 | P67: =I67*$H$7 -> 52 | Q67: 1 | R67: =O67*P67*Q67 -> 0 | S67: 0 | T67: =SUM(R67:S67) -> 0 | U67: 2 | V67: =I67*$H$7*$H$7 -> 54.08 | W67: 1 | X67: =U67*V67*W67 -> 108.16 | Y67: 0 | Z67: =SUM(X67:Y67) -> 108.16 | AA67: 0 | AB67: =I67*$H$7*$H$7*$H$7 -> 56.2432 | AC67: 1 | AD67: =AA67*AB67*AC67 -> 0 | AE67: 0 | AF67: =SUM(AD67:AE67) -> 0 | AG67: 0 | AH67: =I67*$H$7*$H$7*$H$7*$H$7 -> 58.492928 | AI67: 1 | AJ67: =AG67*AH67*AI67 -> 0 | AK67: 0 | AL67: =SUM(AJ67:AK67) -> 0 | AM67: =L67+R67+X67+AD67+AJ67 -> 208.16 | AN67: =M67+S67+Y67+AE67+AK67 -> 0 | AO67: =SUM(AM67:AN67) -> 208.16
A68: SUBPROANT | B68: 89050 | C68: COL2 | D68: COL2 | E68: PROANT | F68: PAT4TRVL | G68: Meals and Incidentals for Annual Forums | H68: 2 | I68: 40 | J68: 2 | K68: /day | L68: =J68*I68*H68 -> 160 | M68: 0 | N68: =SUM(L68:M68) -> 160 | O68: 0 | P68: =I68*$H$7 -> 41.6 | Q68: 2 | R68: =O68*P68*Q68 -> 0 | S68: 0 | T68: =SUM(R68:S68) -> 0 | U68: 2 | V68: =I68*$H$7*$H$7 -> 43.264 | W68: 2 | X68: =U68*V68*W68 -> 173.056 | Y68: 0 | Z68: =SUM(X68:Y68) -> 173.056 | AA68: 0 | AB68: =I68*$H$7*$H$7*$H$7 -> 44.99456 | AC68: 2 | AD68: =AA68*AB68*AC68 -> 0 | AE68: 0 | AF68: =SUM(AD68:AE68) -> 0 | AG68: 0 | AH68: =I68*$H$7*$H$7*$H$7*$H$7 -> 46.794342 | AI68: 2 | AJ68: =AG68*AH68*AI68 -> 0 | AK68: 0 | AL68: =SUM(AJ68:AK68) -> 0 | AM68: =L68+R68+X68+AD68+AJ68 -> 333.056 | AN68: =M68+S68+Y68+AE68+AK68 -> 0 | AO68: =SUM(AM68:AN68) -> 333.056
A69: SUBPROANT | B69: 89050 | C69: COL2 | D69: COL2 | E69: PROANT | F69: PAT4TRVL | G69: Lodging for Annual Forums | H69: 2 | I69: 80 | J69: 2 | K69: /day | L69: =J69*I69*H69 -> 320 | M69: 0 | N69: =SUM(L69:M69) -> 320 | O69: 0 | P69: =I69*$H$7 -> 83.2 | Q69: 2 | R69: =O69*P69*Q69 -> 0 | S69: 0 | T69: =SUM(R69:S69) -> 0 | U69: 2 | V69: =I69*$H$7*$H$7 -> 86.528 | W69: 2 | X69: =U69*V69*W69 -> 346.112 | Y69: 0 | Z69: =SUM(X69:Y69) -> 346.112 | AA69: 0 | AB69: =I69*$H$7*$H$7*$H$7 -> 89.98912 | AC69: 2 | AD69: =AA69*AB69*AC69 -> 0 | AE69: 0 | AF69: =SUM(AD69:AE69) -> 0 | AG69: 0 | AH69: =I69*$H$7*$H$7*$H$7*$H$7 -> 93.588685 | AI69: 2 | AJ69: =AG69*AH69*AI69 -> 0 | AK69: 0 | AL69: =SUM(AJ69:AK69) -> 0 | AM69: =L69+R69+X69+AD69+AJ69 -> 666.112 | AN69: =M69+S69+Y69+AE69+AK69 -> 0 | AO69: =SUM(AM69:AN69) -> 666.112
A70: SUBPROANT | B70: 89050 | C70: COL2 | D70: COL2 | E70: PROANT | F70: PAT4TRVL | G70: Other Travel Related Expenses for Annual Forums | H70: 2 | I70: 25 | J70: 1 | K70: /trip | L70: =J70*I70*H70 -> 50 | M70: 0 | N70: =SUM(L70:M70) -> 50 | O70: 0 | P70: =I70*$H$7 -> 26 | Q70: 1 | R70: =O70*P70*Q70 -> 0 | S70: 0 | T70: =SUM(R70:S70) -> 0 | U70: 2 | V70: =I70*$H$7*$H$7 -> 27.04 | W70: 1 | X70: =U70*V70*W70 -> 54.08 | Y70: 0 | Z70: =SUM(X70:Y70) -> 54.08 | AA70: 0 | AB70: =I70*$H$7*$H$7*$H$7 -> 28.1216 | AC70: 1 | AD70: =AA70*AB70*AC70 -> 0 | AE70: 0 | AF70: =SUM(AD70:AE70) -> 0 | AG70: 0 | AH70: =I70*$H$7*$H$7*$H$7*$H$7 -> 29.246464 | AI70: 1 | AJ70: =AG70*AH70*AI70 -> 0 | AK70: 0 | AL70: =SUM(AJ70:AK70) -> 0 | AM70: =L70+R70+X70+AD70+AJ70 -> 104.08 | AN70: =M70+S70+Y70+AE70+AK70 -> 0 | AO70: =SUM(AM70:AN70) -> 104.08
G72: T.5 Travel to SMT In-Person Meetings in Bogota
A73: SUBPROANT | B73: 89050 | C73: COL2 | D73: COL2 | E73: PROANT | F73: PAT5TRVL | G73: Local Transportation for SMT Meetings | H73: 17 | I73: 50 | J73: 1 | K73: /trip | L73: =J73*I73*H73 -> 850 | M73: 0 | N73: =SUM(L73:M73) -> 850 | O73: 17 | P73: =I73*$H$7 -> 52 | Q73: 1 | R73: =O73*P73*Q73 -> 884 | S73: 0 | T73: =SUM(R73:S73) -> 884 | U73: 17 | V73: =I73*$H$7*$H$7 -> 54.08 | W73: 1 | X73: =U73*V73*W73 -> 919.36 | Y73: 0 | Z73: =SUM(X73:Y73) -> 919.36 | AA73: 17 | AB73: =I73*$H$7*$H$7*$H$7 -> 56.2432 | AC73: 1 | AD73: =AA73*AB73*AC73 -> 956.1344 | AE73: 0 | AF73: =SUM(AD73:AE73) -> 956.1344 | AG73: 17 | AH73: =I73*$H$7*$H$7*$H$7*$H$7 -> 58.492928 | AI73: 1 | AJ73: =AG73*AH73*AI73 -> 994.37978 | AK73: 0 | AL73: =SUM(AJ73:AK73) -> 994.37978 | AM73: =L73+R73+X73+AD73+AJ73 -> 4603.8742 | AN73: =M73+S73+Y73+AE73+AK73 -> 0 | AO73: =SUM(AM73:AN73) -> 4603.8742
A74: SUBPROANT | B74: 89050 | C74: COL2 | D74: COL2 | E74: PROANT | F74: PAT5TRVL | G74: Meals and Incidentals for SMT Meetings | H74: 17 | I74: 40 | J74: 1 | K74: /day | L74: =J74*I74*H74 -> 680 | M74: 0 | N74: =SUM(L74:M74) -> 680 | O74: 17 | P74: =I74*$H$7 -> 41.6 | Q74: 1 | R74: =O74*P74*Q74 -> 707.2 | S74: 0 | T74: =SUM(R74:S74) -> 707.2 | U74: 17 | V74: =I74*$H$7*$H$7 -> 43.264 | W74: 1 | X74: =U74*V74*W74 -> 735.488 | Y74: 0 | Z74: =SUM(X74:Y74) -> 735.488 | AA74: 17 | AB74: =I74*$H$7*$H$7*$H$7 -> 44.99456 | AC74: 1 | AD74: =AA74*AB74*AC74 -> 764.90752 | AE74: 0 | AF74: =SUM(AD74:AE74) -> 764.90752 | AG74: 17 | AH74: =I74*$H$7*$H$7*$H$7*$H$7 -> 46.794342 | AI74: 1 | AJ74: =AG74*AH74*AI74 -> 795.50382 | AK74: 0 | AL74: =SUM(AJ74:AK74) -> 795.50382 | AM74: =L74+R74+X74+AD74+AJ74 -> 3683.0993 | AN74: =M74+S74+Y74+AE74+AK74 -> 0 | AO74: =SUM(AM74:AN74) -> 3683.0993
A75: SUBPROANT | B75: 89050 | C75: COL2 | D75: COL2 | E75: PROANT | F75: PAT5TRVL | G75: Lodging for SMT Meetings | H75: 17 | I75: 80 | J75: 1 | K75: /day | L75: =J75*I75*H75 -> 1360 | M75: 0 | N75: =SUM(L75:M75) -> 1360 | O75: 17 | P75: =I75*$H$7 -> 83.2 | Q75: 1 | R75: =O75*P75*Q75 -> 1414.4 | S75: 0 | T75: =SUM(R75:S75) -> 1414.4 | U75: 17 | V75: =I75*$H$7*$H$7 -> 86.528 | W75: 1 | X75: =U75*V75*W75 -> 1470.976 | Y75: 0 | Z75: =SUM(X75:Y75) -> 1470.976 | AA75: 17 | AB75: =I75*$H$7*$H$7*$H$7 -> 89.98912 | AC75: 1 | AD75: =AA75*AB75*AC75 -> 1529.815 | AE75: 0 | AF75: =SUM(AD75:AE75) -> 1529.815 | AG75: 17 | AH75: =I75*$H$7*$H$7*$H$7*$H$7 -> 93.588685 | AI75: 1 | AJ75: =AG75*AH75*AI75 -> 1591.0076 | AK75: 0 | AL75: =SUM(AJ75:AK75) -> 1591.0076 | AM75: =L75+R75+X75+AD75+AJ75 -> 7366.1987 | AN75: =M75+S75+Y75+AE75+AK75 -> 0 | AO75: =SUM(AM75:AN75) -> 7366.1987
A76: SUBPROANT | B76: 89050 | C76: COL2 | D76: COL2 | E76: PROANT | F76: PAT5TRVL | G76: Other Travel Related Expenses for SMT Meetings | H76: 17 | I76: 25 | J76: 1 | K76: /trip | L76: =J76*I76*H76 -> 425 | M76: 0 | N76: =SUM(L76:M76) -> 425 | O76: 17 | P76: =I76*$H$7 -> 26 | Q76: 1 | R76: =O76*P76*Q76 -> 442 | S76: 0 | T76: =SUM(R76:S76) -> 442 | U76: 17 | V76: =I76*$H$7*$H$7 -> 27.04 | W76: 1 | X76: =U76*V76*W76 -> 459.68 | Y76: 0 | Z76: =SUM(X76:Y76) -> 459.68 | AA76: 17 | AB76: =I76*$H$7*$H$7*$H$7 -> 28.1216 | AC76: 1 | AD76: =AA76*AB76*AC76 -> 478.0672 | AE76: 0 | AF76: =SUM(AD76:AE76) -> 478.0672 | AG76: 17 | AH76: =I76*$H$7*$H$7*$H$7*$H$7 -> 29.246464 | AI76: 1 | AJ76: =AG76*AH76*AI76 -> 497.18989 | AK76: 0 | AL76: =SUM(AJ76:AK76) -> 497.18989 | AM76: =L76+R76+X76+AD76+AJ76 -> 2301.9371 | AN76: =M76+S76+Y76+AE76+AK76 -> 0 | AO76: =SUM(AM76:AN76) -> 2301.9371
G78: T.6 Travel to Annual In-Person Steering Committee Meeting in Bogota
A79: SUBPROANT | B79: 89050 | C79: COL2 | D79: COL2 | E79: PROANT | F79: PAT6TRVL | G79: Local Transportation for Steering Committee Meeting | H79: 1 | I79: 50 | J79: 1 | K79: /trip | L79: =J79*I79*H79 -> 50 | M79: 0 | N79: =SUM(L79:M79) -> 50 | O79: 1 | P79: =I79*$H$7 -> 52 | Q79: 1 | R79: =O79*P79*Q79 -> 52 | S79: 0 | T79: =SUM(R79:S79) -> 52 | U79: 1 | V79: =I79*$H$7*$H$7 -> 54.08 | W79: 1 | X79: =U79*V79*W79 -> 54.08 | Y79: 0 | Z79: =SUM(X79:Y79) -> 54.08 | AA79: 1 | AB79: =I79*$H$7*$H$7*$H$7 -> 56.2432 | AC79: 1 | AD79: =AA79*AB79*AC79 -> 56.2432 | AE79: 0 | AF79: =SUM(AD79:AE79) -> 56.2432 | AG79: 1 | AH79: =I79*$H$7*$H$7*$H$7*$H$7 -> 58.492928 | AI79: 1 | AJ79: =AG79*AH79*AI79 -> 58.492928 | AK79: 0 | AL79: =SUM(AJ79:AK79) -> 58.492928 | AM79: =L79+R79+X79+AD79+AJ79 -> 270.81613 | AN79: =M79+S79+Y79+AE79+AK79 -> 0 | AO79: =SUM(AM79:AN79) -> 270.81613
A80: SUBPROANT | B80: 89050 | C80: COL2 | D80: COL2 | E80: PROANT | F80: PAT6TRVL | G80: Meals and Incidentals for Steering Committee Meeting | H80: 1 | I80: 40 | J80: 2 | K80: /day | L80: =J80*I80*H80 -> 80 | M80: 0 | N80: =SUM(L80:M80) -> 80 | O80: 1 | P80: =I80*$H$7 -> 41.6 | Q80: 2 | R80: =O80*P80*Q80 -> 83.2 | S80: 0 | T80: =SUM(R80:S80) -> 83.2 | U80: 1 | V80: =I80*$H$7*$H$7 -> 43.264 | W80: 2 | X80: =U80*V80*W80 -> 86.528 | Y80: 0 | Z80: =SUM(X80:Y80) -> 86.528 | AA80: 1 | AB80: =I80*$H$7*$H$7*$H$7 -> 44.99456 | AC80: 2 | AD80: =AA80*AB80*AC80 -> 89.98912 | AE80: 0 | AF80: =SUM(AD80:AE80) -> 89.98912 | AG80: 1 | AH80: =I80*$H$7*$H$7*$H$7*$H$7 -> 46.794342 | AI80: 2 | AJ80: =AG80*AH80*AI80 -> 93.588685 | AK80: 0 | AL80: =SUM(AJ80:AK80) -> 93.588685 | AM80: =L80+R80+X80+AD80+AJ80 -> 433.3058 | AN80: =M80+S80+Y80+AE80+AK80 -> 0 | AO80: =SUM(AM80:AN80) -> 433.3058
A81: SUBPROANT | B81: 89050 | C81: COL2 | D81: COL2 | E81: PROANT | F81: PAT6TRVL | G81: Lodging for Steering Committee Meeting | H81: 1 | I81: 80 | J81: 2 | K81: /day | L81: =J81*I81*H81 -> 160 | M81: 0 | N81: =SUM(L81:M81) -> 160 | O81: 1 | P81: =I81*$H$7 -> 83.2 | Q81: 2 | R81: =O81*P81*Q81 -> 166.4 | S81: 0 | T81: =SUM(R81:S81) -> 166.4 | U81: 1 | V81: =I81*$H$7*$H$7 -> 86.528 | W81: 2 | X81: =U81*V81*W81 -> 173.056 | Y81: 0 | Z81: =SUM(X81:Y81) -> 173.056 | AA81: 1 | AB81: =I81*$H$7*$H$7*$H$7 -> 89.98912 | AC81: 2 | AD81: =AA81*AB81*AC81 -> 179.97824 | AE81: 0 | AF81: =SUM(AD81:AE81) -> 179.97824 | AG81: 1 | AH81: =I81*$H$7*$H$7*$H$7*$H$7 -> 93.588685 | AI81: 2 | AJ81: =AG81*AH81*AI81 -> 187.17737 | AK81: 0 | AL81: =SUM(AJ81:AK81) -> 187.17737 | AM81: =L81+R81+X81+AD81+AJ81 -> 866.61161 | AN81: =M81+S81+Y81+AE81+AK81 -> 0 | AO81: =SUM(AM81:AN81) -> 866.61161
A82: SUBPROANT | B82: 89050 | C82: COL2 | D82: COL2 | E82: PROANT | F82: PAT6TRVL | G82: Other Travel Related Expenses for Steering Committee Meeting | H82: 1 | I82: 25 | J82: 1 | K82: /trip | L82: =J82*I82*H82 -> 25 | M82: 0 | N82: =SUM(L82:M82) -> 25 | O82: 1 | P82: =I82*$H$7 -> 26 | Q82: 1 | R82: =O82*P82*Q82 -> 26 | S82: 0 | T82: =SUM(R82:S82) -> 26 | U82: 1 | V82: =I82*$H$7*$H$7 -> 27.04 | W82: 1 | X82: =U82*V82*W82 -> 27.04 | Y82: 0 | Z82: =SUM(X82:Y82) -> 27.04 | AA82: 1 | AB82: =I82*$H$7*$H$7*$H$7 -> 28.1216 | AC82: 1 | AD82: =AA82*AB82*AC82 -> 28.1216 | AE82: 0 | AF82: =SUM(AD82:AE82) -> 28.1216 | AG82: 1 | AH82: =I82*$H$7*$H$7*$H$7*$H$7 -> 29.246464 | AI82: 1 | AJ82: =AG82*AH82*AI82 -> 29.246464 | AK82: 0 | AL82: =SUM(AJ82:AK82) -> 29.246464 | AM82: =L82+R82+X82+AD82+AJ82 -> 135.40806 | AN82: =M82+S82+Y82+AE82+AK82 -> 0 | AO82: =SUM(AM82:AN82) -> 135.40806
G83: Subtotal Field Travel | L83: =SUM(L52:L82) -> 16980 | M83: =SUM(M52:M82) -> 0 | N83: =SUM(N52:N82) -> 16980 | R83: =SUM(R52:R82) -> 18063 | S83: =SUM(S52:S82) -> 0 | T83: =SUM(T52:T82) -> 18063 | X83: =SUM(X52:X82) -> 20114.97 | Y83: =SUM(Y52:Y82) -> 0 | Z83: =SUM(Z52:Z82) -> 20114.97 | AD83: =SUM(AD52:AD82) -> 20109.695 | AE83: =SUM(AE52:AE82) -> 0 | AF83: =SUM(AF52:AF82) -> 20109.695 | AJ83: =SUM(AJ52:AJ82) -> 19756.964 | AK83: =SUM(AK52:AK82) -> 0 | AL83: =SUM(AL52:AL82) -> 19756.964 | AM83: =L83+R83+X83+AD83+AJ83 -> 95024.628 | AN83: =M83+S83+Y83+AE83+AK83 -> 0 | AO83: =SUM(AM83:AN83) -> 95024.628
G85: Travel Total | L85: =L83+L48 -> 18570 | M85: =M83+M48 -> 0 | N85: =N83+N48 -> 18570 | R85: =R83+R48 -> 19700.7 | S85: =S83+S48 -> 0 | T85: =T83+T48 -> 19700.7 | X85: =X83+X48 -> 21801.801 | Y85: =Y83+Y48 -> 0 | Z85: =Z83+Z48 -> 21801.801 | AD85: =AD83+AD48 -> 21847.131 | AE85: =AE83+AE48 -> 0 | AF85: =AF83+AF48 -> 21847.131 | AJ85: =AJ83+AJ48 -> 21546.523 | AK85: =AK83+AK48 -> 0 | AL85: =AL83+AL48 -> 21546.523 | AM85: =AM83+AM48 -> 103466.15 | AN85: =AN83+AN48 -> 0 | AO85: =AO83+AO48 -> 103466.15
G87: Equipment - Over $5,000 USD
A89: SUBPROANT | B89: 89050 | C89: COL2 | D89: COL2 | E89: PROANT | F89: PAVEHICLE | G89: Vehicle for Field Office | H89: 1 | I89: 50000 | J89: 0 | K89: /unit | L89: =I89*H89 -> 50000 | M89: 0 | N89: =SUM(L89:M89) -> 50000 | O89: 0 | P89: =I89 -> 50000 | R89: =O89*P89 -> 0 | S89: 0 | T89: =SUM(R89:S89) -> 0 | U89: 0 | V89: =I89 -> 50000 | X89: =V89*U89 -> 0 | Y89: 0 | Z89: =SUM(X89:Y89) -> 0 | AA89: 0 | AB89: =I89 -> 50000 | AD89: =AA89*AB89 -> 0 | AE89: 0 | AF89: =SUM(AD89:AE89) -> 0 | AG89: 0 | AH89: =I89 -> 50000 | AJ89: =AH89*AG89 -> 0 | AK89: 0 | AL89: =SUM(AJ89:AK89) -> 0 | AM89: =L89+R89+X89+AD89+AJ89 -> 50000 | AN89: =M89+S89+Y89+AE89+AK89 -> 0 | AO89: =SUM(AM89:AN89) -> 50000
G91: Equipment Total | L91: =SUM(L89:L90) -> 50000 | M91: =SUM(M89:M90) -> 0 | N91: =SUM(N89:N90) -> 50000 | R91: =SUM(R89:R90) -> 0 | S91: =SUM(S89:S90) -> 0 | T91: =SUM(T89:T90) -> 0 | X91: =SUM(X89:X90) -> 0 | Y91: =SUM(Y89:Y90) -> 0 | Z91: =SUM(Z89:Z90) -> 0 | AD91: =SUM(AD89:AD90) -> 0 | AE91: =SUM(AE89:AE90) -> 0 | AF91: =SUM(AF89:AF90) -> 0 | AJ91: =SUM(AJ89:AJ90) -> 0 | AK91: =SUM(AK89:AK90) -> 0 | AL91: =SUM(AL89:AL90) -> 0 | AM91: =SUM(AM89:AM90) -> 50000 | AN91: =SUM(AN89:AN90) -> 0 | AO91: =SUM(AO89:AO90) -> 50000
G93: Supplies - Under $5,000 USD
G95: HQ Office Supplies
A96: SUBPROANT | B96: 89050 | C96: COL2 | D96: COL2 | E96: PROANT | F96: PAHQLAPTOP | G96: Laptops and software | H96: 1 | I96: =Supplies!B31 -> 1204.99 | J96: 1 | K96: /unit | L96: =I96*H96 -> 1204.99 | M96: 0 | N96: =SUM(L96:M96) -> 1204.99 | O96: 0 | P96: =I96*$H$6 -> 1241.1397 | Q96: 1 | R96: =O96*P96 -> 0 | S96: 0 | T96: =SUM(R96:S96) -> 0 | U96: =R96*S96*T96 -> 0 | V96: =I96*$H$6*$H$6 -> 1278.3739 | W96: 1 | X96: =V96*U96 -> 0 | Y96: 0 | Z96: =SUM(X96:Y96) -> 0 | AA96: =X96*Y96*Z96 -> 0 | AB96: =I96*$H$6*$H$6*$H$6 -> 1316.7251 | AC96: 1 | AD96: =AB96*AA96 -> 0 | AE96: 0 | AF96: =SUM(AD96:AE96) -> 0 | AG96: =AD96*AE96*AF96 -> 0 | AH96: =I96*$H$6*$H$6*$H$6*$H$6 -> 1356.2269 | AI96: 1 | AJ96: =AH96*AG96 -> 0 | AK96: 0 | AL96: =SUM(AJ96:AK96) -> 0 | AM96: =L96+R96+X96+AD96+AJ96 -> 1204.99 | AN96: =M96+S96+Y96+AE96+AK96 -> 0 | AO96: =SUM(AM96:AN96) -> 1204.99
A97: SUBPROANT | B97: 89050 | C97: COL2 | D97: COL2 | E97: PROANT | F97: PAHQWORK | G97: Workspaces (Space, furniture, internet access, telephone and meeting room) | H97: 1 | I97: 278 | J97: 12 | K97: /month | L97: 0 | M97: =+H97*I97*J97 -> 3336 | N97: =SUM(L97:M97) -> 3336 | O97: 1.3 | P97: =I97*$H$6 -> 286.34 | Q97: 12 | R97: 0 | S97: =+O97*P97*Q97 -> 4466.904 | T97: =SUM(R97:S97) -> 4466.904 | U97: 1.3 | V97: =I97*$H$6*$H$6 -> 294.9302 | W97: 12 | X97: 0 | Y97: =+U97*V97*W97 -> 4600.9111 | Z97: =SUM(X97:Y97) -> 4600.9111 | AA97: 1.3 | AB97: =I97*$H$6*$H$6*$H$6 -> 303.77811 | AC97: 12 | AD97: 0 | AE97: =+AA97*AB97*AC97 -> 4738.9385 | AF97: =SUM(AD97:AE97) -> 4738.9385 | AG97: 1.3 | AH97: =I97*$H$6*$H$6*$H$6*$H$6 -> 312.89145 | AI97: 12 | AJ97: 0 | AK97: =+AG97*AH97*AI97 -> 4881.1066 | AL97: =SUM(AJ97:AK97) -> 4881.1066 | AM97: =L97+R97+X97+AD97+AJ97 -> 0 | AN97: =M97+S97+Y97+AE97+AK97 -> 22023.86 | AO97: =SUM(AM97:AN97) -> 22023.86
G98: Subtotal HQ Office Supplies | L98: =SUM(L96:L97) -> 1204.99 | M98: =SUM(M96:M97) -> 3336 | N98: =SUM(N96:N97) -> 4540.99 | R98: =SUM(R96:R97) -> 0 | S98: =SUM(S96:S97) -> 4466.904 | T98: =SUM(T96:T97) -> 4466.904 | X98: =SUM(X96:X97) -> 0 | Y98: =SUM(Y96:Y97) -> 4600.9111 | Z98: =SUM(Z96:Z97) -> 4600.9111 | AD98: =SUM(AD96:AD97) -> 0 | AE98: =SUM(AE96:AE97) -> 4738.9385 | AF98: =SUM(AF96:AF97) -> 4738.9385 | AJ98: =SUM(AJ96:AJ97) -> 0 | AK98: =SUM(AK96:AK97) -> 4881.1066 | AL98: =SUM(AL96:AL97) -> 4881.1066 | AM98: =SUM(AM96:AM97) -> 1204.99 | AN98: =SUM(AN96:AN97) -> 22023.86 | AO98: =SUM(AO96:AO97) -> 23228.85
G100: Field Office Supplies
A101: SUBPROANT | B101: 89050 | C101: COL2 | D101: COL2 | E101: PROANT | F101: PAFODESKTP | G101: Desktop computers, laptops and software | H101: 8 | I101: =Supplies!B31 -> 1204.99 | J101: 1 | K101: /unit | L101: =I101*H101 -> 9639.92 | M101: 0 | N101: =SUM(L101:M101) -> 9639.92 | O101: 0 | P101: =I101*$H$6 -> 1241.1397 | Q101: 1 | R101: =O101*P101 -> 0 | S101: 0 | T101: =SUM(R101:S101) -> 0 | U101: =R101*S101*T101 -> 0 | V101: =I101*$H$6*$H$6 -> 1278.3739 | W101: 1 | X101: =V101*U101 -> 0 | Y101: 0 | Z101: =SUM(X101:Y101) -> 0 | AA101: =X101*Y101*Z101 -> 0 | AB101: =I101*$H$6*$H$6*$H$6 -> 1316.7251 | AC101: 1 | AD101: =AB101*AA101 -> 0 | AE101: 0 | AF101: =SUM(AD101:AE101) -> 0 | AG101: =AD101*AE101*AF101 -> 0 | AH101: =I101*$H$6*$H$6*$H$6*$H$6 -> 1356.2269 | AI101: 1 | AJ101: =AH101*AG101 -> 0 | AK101: 0 | AL101: =SUM(AJ101:AK101) -> 0 | AM101: =L101+R101+X101+AD101+AJ101 -> 9639.92 | AN101: =M101+S101+Y101+AE101+AK101 -> 0 | AO101: =SUM(AM101:AN101) -> 9639.92
A102: SUBPROANT | B102: 89050 | C102: COL2 | D102: COL2 | E102: PROANT | F102: PAPPE | G102: Personal Protective Equipment (Gloves, Masks, Hand Sanitizer, Antibacterial Wipes etc.) | H102: 1 | I102: 750 | J102: 6 | K102: /month | L102: =J102*I102*H102 -> 4500 | M102: 0 | N102: =SUM(L102:M102) -> 4500 | O102: 1 | P102: =I102*$H$6 -> 772.5 | Q102: 12 | R102: =Q102*O102*P102 -> 9270 | S102: 0 | T102: =SUM(R102:S102) -> 9270 | U102: 1 | V102: =I102*$H$6*$H$6 -> 795.675 | W102: 12 | X102: =V102*W102*U102 -> 9548.1 | Y102: 0 | Z102: =SUM(X102:Y102) -> 9548.1 | AA102: 1 | AB102: =I102*$H$6*$H$6*$H$6*0.5 -> 409.77263 | AC102: 12 | AD102: =AB102*AA102*AC102 -> 4917.2715 | AE102: 0 | AF102: =SUM(AD102:AE102) -> 4917.2715 | AG102: 1 | AH102: =I102*$H$6*$H$6*$H$6*$H$6*0.5 -> 422.0658 | AI102: 9 | AJ102: =AH102*AG102*AI102 -> 3798.5922 | AK102: 0 | AL102: =SUM(AJ102:AK102) -> 3798.5922 | AM102: =L102+R102+X102+AD102+AJ102 -> 32033.964 | AN102: =M102+S102+Y102+AE102+AK102 -> 0 | AO102: =SUM(AM102:AN102) -> 32033.964
G103: Subtotal Field Office Supplies | L103: =SUM(L101:L102) -> 14139.92 | M103: =SUM(M101:M102) -> 0 | N103: =SUM(N101:N102) -> 14139.92 | R103: =SUM(R101:R102) -> 9270 | S103: =SUM(S101:S102) -> 0 | T103: =SUM(T101:T102) -> 9270 | X103: =SUM(X101:X102) -> 9548.1 | Y103: =SUM(Y101:Y102) -> 0 | Z103: =SUM(Z101:Z102) -> 9548.1 | AD103: =SUM(AD101:AD102) -> 4917.2715 | AE103: =SUM(AE101:AE102) -> 0 | AF103: =SUM(AF101:AF102) -> 4917.2715 | AJ103: =SUM(AJ101:AJ102) -> 3798.5922 | AK103: =SUM(AK101:AK102) -> 0 | AL103: =SUM(AL101:AL102) -> 3798.5922 | AM103: =SUM(AM101:AM102) -> 41673.884 | AN103: =SUM(AN101:AN102) -> 0 | AO103: =SUM(AO101:AO102) -> 41673.884
G105: Supplies Total | L105: =L103+L98 -> 15344.91 | M105: =M103+M98 -> 3336 | N105: =N103+N98 -> 18680.91 | R105: =R103+R98 -> 9270 | S105: =S103+S98 -> 4466.904 | T105: =T103+T98 -> 13736.904 | X105: =X103+X98 -> 9548.1 | Y105: =Y103+Y98 -> 4600.9111 | Z105: =Z103+Z98 -> 14149.011 | AD105: =AD103+AD98 -> 4917.2715 | AE105: =AE103+AE98 -> 4738.9385 | AF105: =AF103+AF98 -> 9656.21 | AJ105: =AJ103+AJ98 -> 3798.5922 | AK105: =AK103+AK98 -> 4881.1066 | AL105: =AL103+AL98 -> 8679.6988 | AM105: =AM103+AM98 -> 42878.874 | AN105: =AN103+AN98 -> 22023.86 | AO105: =AO103+AO98 -> 64902.734
G107: Contractual
G109: Consultants
