Workbook
Name __pd1: [1]Rates!$J$24
Name __pd6: [1]Rates!$J$30
Name __tix1: [1]Rates!$J$40
Name __tix2: [1]Rates!$J$41
Name __tix6: [1]Rates!$J$47
Name ANPDH: '[2]Salary & PR Tax'!#REF!
Name Board: '[3]Schedule E - Other'!$F$102
Name CEE_Consult: #REF!
Name CENIDH: #REF!
Name Consultants: #REF!
Name Equipment: '[4]Schedule D - Equipment'!$E$26
Name fg: #REF!
Name Housing: '[2]Salary & PR Tax'!#REF!
Name inf: [5]Assumptions!$C$75
Name Inflation: '[6]Detail-1'!$J$2
Name Interns: #REF!
Name jenn: #REF!
Name Local_Hire: #REF!
Name Local_Hires: #REF!
Name Merit: '[6]Detail-1'!$J$1
Name padf01: '[7]Level of Effort'!$C$14
Name padf02: '[7]Level of Effort'!$C$15
Name padf03: '[7]Level of Effort'!$C$16
Name padf04: '[7]Level of Effort'!$C$17
Name padf05: [7]Rates!$J$23
Name postdif01: [7]Rates!$J$34
Name postdif02: [7]Rates!$J$65
Name Print_Titles_MI: #REF!
Name sdf: #REF!
Name Travel_Regional: #REF!
Name Travel_WDC: #REF!

Sheet Budget Summary
A1: Partners of the Americas for Venezuela's Farmer-to-Farmer Program Budget
A2: USAID NFO #7200AA19B00002
A4: Line Items | B4: Year 1 | E4: Year 2 | H4: Year 3 | K4: Year 4 | N4: Year 5 | Q4: Total | R4: Total | S4: Grand
B5: USAID | C5: Leverage | D5: Total | E5: USAID | F5: Leverage | G5: Total | H5: USAID | I5: Leverage | J5: Total | K5: USAID | L5: Leverage | M5: Total | N5: USAID | O5: Leverage | P5: Total | Q5: USAID | R5: Leverage | S5: Total
A7: Salaries & Wages | B7: =Budget!I32 -> 622538 | C7: =Budget!J32 -> 343260 | D7: =SUM(B7:C7) -> 965798 | E7: =Budget!O32 -> 884068.02 | F7: =Budget!P32 -> 1162192.5 | G7: =SUM(E7:F7) -> 2046260.5 | H7: =Budget!U32 -> 703799.11 | I7: =Budget!V32 -> 834592.5 | J7: =SUM(H7:I7) -> 1538391.6 | K7: =Budget!AA32 -> 667412.68 | L7: =Budget!AB32 -> 506992.5 | M7: =SUM(K7:L7) -> 1174405.2 | N7: =Budget!AG32 -> 547922.72 | O7: =Budget!AH32 -> 166387.5 | P7: =SUM(N7:O7) -> 714310.22 | Q7: =Budget!AJ32 -> 3425740.5 | R7: =Budget!AK32 -> 3013425 | S7: =Budget!AL32 -> 6439165.5
A9: Fringe Benefits | B9: =Budget!I43 -> 252030.92 | C9: =Budget!J43 -> 0 | D9: =Budget!K43 -> 252030.92 | E9: =Budget!O43 -> 360022.86 | F9: =Budget!P43 -> 0 | G9: =Budget!Q43 -> 360022.86 | H9: =Budget!U43 -> 214720.86 | I9: =Budget!V43 -> 0 | J9: =Budget!W43 -> 214720.86 | K9: =Budget!AA43 -> 182513.76 | L9: =Budget!AB43 -> 0 | M9: =Budget!AC43 -> 182513.76 | N9: =Budget!AG43 -> 146046.92 | O9: =Budget!AH43 -> 0 | P9: =Budget!AI43 -> 146046.92 | Q9: =Budget!AJ43 -> 1155335.3 | R9: =Budget!AK43 -> 0 | S9: =Budget!AL43 -> 1155335.3
A11: Travel & Transportation | B11: =Budget!I97 -> 63646 | C11: =Budget!J97 -> 0 | D11: =Budget!K97 -> 63646 | E11: =Budget!O97 -> 275195.72 | F11: =Budget!P97 -> 0 | G11: =Budget!Q97 -> 275195.72 | H11: =Budget!U97 -> 232008.91 | I11: =Budget!V97 -> 0 | J11: =Budget!W97 -> 232008.91 | K11: =Budget!AA97 -> 236649.09 | L11: =Budget!AB97 -> 0 | M11: =Budget!AC97 -> 236649.09 | N11: =Budget!AG97 -> 93020.951 | O11: =Budget!AH97 -> 0 | P11: =Budget!AI97 -> 93020.951 | Q11: =Budget!AJ97 -> 900520.68 | R11: =Budget!AK97 -> 0 | S11: =Budget!AL97 -> 900520.68
A13: Equipment | B13: =Budget!I104 -> 165700 | C13: =Budget!J104 -> 0 | D13: =Budget!K104 -> 165700 | E13: =Budget!O104 -> 0 | F13: =Budget!P104 -> 0 | G13: =Budget!Q104 -> 0 | H13: =Budget!U104 -> 0 | I13: =Budget!V104 -> 0 | J13: =Budget!W104 -> 0 | K13: =Budget!AA104 -> 0 | L13: =Budget!AB104 -> 0 | M13: =Budget!AC104 -> 0 | N13: =Budget!AG104 -> 0 | O13: =Budget!AH104 -> 0 | P13: =Budget!AI104 -> 0 | Q13: =Budget!AJ104 -> 165700 | R13: =Budget!AK104 -> 0 | S13: =Budget!AL104 -> 165700
A15: Supplies | B15: =Budget!I131 -> 108796.19 | C15: =Budget!J131 -> 0 | D15: =Budget!K131 -> 108796.19 | E15: =Budget!O131 -> 131200 | F15: =Budget!P131 -> 0 | G15: =Budget!Q131 -> 131200 | H15: =Budget!U131 -> 71200 | I15: =Budget!V131 -> 0 | J15: =Budget!W131 -> 71200 | K15: =Budget!AA131 -> 11200 | L15: =Budget!AB131 -> 0 | M15: =Budget!AC131 -> 11200 | N15: =Budget!AG131 -> 8025 | O15: =Budget!AH131 -> 0 | P15: =Budget!AI131 -> 8025 | Q15: =Budget!AJ131 -> 330421.19 | R15: =Budget!AK131 -> 0 | S15: =Budget!AL131 -> 330421.19
A17: Contractual | B17: =Budget!I166 -> 2100186 | C17: =Budget!J166 -> 0 | D17: =Budget!K166 -> 2100186 | E17: =Budget!O166 -> 1963800 | F17: =Budget!P166 -> 0 | G17: =Budget!Q166 -> 1963800 | H17: =Budget!U166 -> 1519200 | I17: =Budget!V166 -> 0 | J17: =Budget!W166 -> 1519200 | K17: =Budget!AA166 -> 944200 | L17: =Budget!AB166 -> 0 | M17: =Budget!AC166 -> 944200 | N17: =Budget!AG166 -> 848000 | O17: =Budget!AH166 -> 0 | P17: =Budget!AI166 -> 848000 | Q17: =Budget!AJ166 -> 7375386 | R17: =Budget!AK166 -> 0 | S17: =Budget!AL166 -> 7375386
A19: Other Direct Costs | B19: =Budget!I200 -> 78710 | C19: =Budget!J200 -> 0 | D19: =Budget!K200 -> 78710 | E19: =Budget!O200 -> 146308.8 | F19: =Budget!P200 -> 0 | G19: =Budget!Q200 -> 146308.8 | H19: =Budget!U200 -> 149234.98 | I19: =Budget!V200 -> 0 | J19: =Budget!W200 -> 149234.98 | K19: =Budget!AA200 -> 152219.68 | L19: =Budget!AB200 -> 0 | M19: =Budget!AC200 -> 152219.68 | N19: =Budget!AG200 -> 107523.4 | O19: =Budget!AH200 -> 0 | P19: =Budget!AI200 -> 107523.4 | Q19: =Budget!AJ200 -> 633996.85 | R19: =Budget!AK200 -> 0 | S19: =Budget!AL200 -> 633996.85
A21: Total Direct Costs | B21: =Budget!I202 -> 3391607.1 | C21: =Budget!J202 -> 343260 | D21: =Budget!K202 -> 3734867.1 | E21: =Budget!O202 -> 3760595.4 | F21: =Budget!P202 -> 1162192.5 | G21: =Budget!Q202 -> 4922787.9 | H21: =Budget!U202 -> 2890163.9 | I21: =Budget!V202 -> 834592.5 | J21: =Budget!W202 -> 3724756.4 | K21: =Budget!AA202 -> 2194195.2 | L21: =Budget!AB202 -> 506992.5 | M21: =Budget!AC202 -> 2701187.7 | N21: =Budget!AG202 -> 1750539 | O21: =Budget!AH202 -> 166387.5 | P21: =Budget!AI202 -> 1916926.5 | Q21: =Budget!AJ202 -> 13987101 | R21: =Budget!AK202 -> 3013425 | S21: =Budget!AL202 -> 17000526
A22: Indirect Costs | B22: =Budget!I203 -> 973052.08 | C22: =Budget!J203 -> 0 | D22: =Budget!K203 -> 973052.08 | E22: =Budget!O203 -> 1078914.8 | F22: =Budget!P203 -> 0 | G22: =Budget!Q203 -> 1078914.8 | H22: =Budget!U203 -> 829188.01 | I22: =Budget!V203 -> 0 | J22: =Budget!W203 -> 829188.01 | K22: =Budget!AA203 -> 629514.6 | L22: =Budget!AB203 -> 0 | M22: =Budget!AC203 -> 629514.6 | N22: =Budget!AG203 -> 502229.64 | O22: =Budget!AH203 -> 0 | P22: =Budget!AI203 -> 502229.64 | Q22: =Budget!AJ203 -> 4012899.2 | R22: =Budget!AK203 -> 0 | S22: =Budget!AL203 -> 4012899.2
A23: Total | B23: =Budget!I204 -> 4364659.2 | C23: =Budget!J204 -> 343260 | D23: =Budget!K204 -> 4707919.2 | E23: =Budget!O204 -> 4839510.2 | F23: =Budget!P204 -> 1162192.5 | G23: =Budget!Q204 -> 6001702.7 | H23: =Budget!U204 -> 3719351.9 | I23: =Budget!V204 -> 834592.5 | J23: =Budget!W204 -> 4553944.4 | K23: =Budget!AA204 -> 2823709.8 | L23: =Budget!AB204 -> 506992.5 | M23: =Budget!AC204 -> 3330702.3 | N23: =Budget!AG204 -> 2252768.6 | O23: =Budget!AH204 -> 166387.5 | P23: =Budget!AI204 -> 2419156.1 | Q23: =Budget!AJ204 -> 18000000 | R23: =Budget!AK204 -> 3013425 | S23: =Budget!AL204 -> 21013425

Sheet Budget
A1: Entity: | B1: P | D1: Partners of the Americas 7200AA19B00002 for Venezuela's Farmer-to-Farmer Program Budget
A2: Program/Dept.: | B2: FTF
A3: Funder-Grant: | B3: USAID671
A5: Actvity | B5: Object | C5: Country | D5: Line Items | I5: Year 1 | O5: Year 2 | R5: Year 3 | AA5: Year 4 | AG5: Year 5 | AJ5: Total | AK5: Total | AL5: Grand
A6: Code | B6: Code | C6: Code | E6: Unit | F6: Cost | G6: Duration | H6: Type | I6: USAID | J6: Leverage | K6: Total | L6: Unit | M6: Cost | N6: Duration | O6: USAID | P6: Leverage | Q6: Total | R6: Unit | S6: Cost | T6: Duration | U6: USAID | V6: Leverage | W6: Total | X6: Unit | Y6: Cost | Z6: Duration | AA6: USAID | AB6: Leverage | AC6: Total | AD6: Unit | AE6: Cost | AF6: Duration | AG6: USAID | AH6: Leverage | AI6: Total | AJ6: USAID | AK6: Leverage | AL6: Total
C7: 0 is DC, VZ is Venezuela
D8: Salary & Wages
D9: Headquarters | E9: LOE
A10: PERSNL | B10: Timesheets | C10: 0 | D10: Program Director | E10: 0.3 | F10: 9730 | G10: 12 | H10: /months | I10: =G10*F10*E10 -> 35028 | J10: 0 | K10: =SUM(I10:J10) -> 35028 | L10: =E10 -> 0.3 | M10: =F10*1.035 -> 10070.55 | N10: 12 | O10: =L10*M10*N10 -> 36253.98 | P10: 0 | Q10: =SUM(O10:P10) -> 36253.98 | R10: =E10 -> 0.3 | S10: =M10*1.035 -> 10423.019 | T10: 12 | U10: =R10*S10*T10 -> 37522.869 | V10: 0 | W10: =SUM(U10:V10) -> 37522.869 | X10: =R10 -> 0.3 | Y10: =S10*1.035 -> 10787.825 | Z10: 12 | AA10: =X10*Y10*Z10 -> 38836.17 | AB10: 0 | AC10: =SUM(AA10:AB10) -> 38836.17 | AD10: =X10 -> 0.3 | AE10: =Y10*1.035 -> 11165.399 | AF10: 12 | AG10: =AD10*AE10*AF10 -> 40195.436 | AH10: 0 | AI10: =SUM(AG10:AH10) -> 40195.436 | AJ10: =I10+O10+U10+AA10+AG10 -> 187836.45 | AK10: =J10+P10+V10+AB10+AH10 -> 0 | AL10: =SUM(AJ10:AK10) -> 187836.45
A11: PERSNL | B11: Timesheets | C11: 0 | D11: Associate Director | E11: 1 | F11: 7500 | G11: 12 | H11: /months | I11: =G11*F11*E11 -> 90000 | J11: 0 | K11: =SUM(I11:J11) -> 90000 | L11: =E11 -> 1 | M11: =F11*1.035 -> 7762.5 | N11: 12 | O11: =L11*M11*N11 -> 93150 | P11: 0 | Q11: =SUM(O11:P11) -> 93150 | R11: =L11 -> 1 | S11: =M11*1.035 -> 8034.1875 | T11: 12 | U11: =R11*S11*T11 -> 96410.25 | V11: 0 | W11: =SUM(U11:V11) -> 96410.25 | X11: =R11 -> 1 | Y11: =S11*1.035 -> 8315.3841 | Z11: 12 | AA11: =X11*Y11*Z11 -> 99784.609 | AB11: 0 | AC11: =SUM(AA11:AB11) -> 99784.609 | AD11: =X11 -> 1 | AE11: =Y11*1.035 -> 8606.4225 | AF11: 12 | AG11: =AD11*AE11*AF11 -> 103277.07 | AH11: 0 | AI11: =SUM(AG11:AH11) -> 103277.07 | AJ11: =I11+O11+U11+AA11+AG11 -> 482621.93 | AK11: =J11+P11+V11+AB11+AH11 -> 0 | AL11: =SUM(AJ11:AK11) -> 482621.93
A12: PERSNL | B12: Timesheets | C12: 0 | D12: Senior Program Officer | E12: 1 | F12: 5834 | G12: 12 | H12: /months | I12: =G12*F12*E12 -> 70008 | J12: 0 | K12: =SUM(I12:J12) -> 70008 | L12: =E12 -> 1 | M12: =F12*1.035 -> 6038.19 | N12: 12 | O12: =L12*M12*N12 -> 72458.28 | P12: 0 | Q12: =SUM(O12:P12) -> 72458.28 | R12: =L12 -> 1 | S12: =M12*1.035 -> 6249.5266 | T12: 12 | U12: =R12*S12*T12 -> 74994.32 | V12: 0 | W12: =SUM(U12:V12) -> 74994.32 | X12: =R12 -> 1 | Y12: =S12*1.035 -> 6468.2601 | Z12: 12 | AA12: =X12*Y12*Z12 -> 77619.121 | AB12: 0 | AC12: =SUM(AA12:AB12) -> 77619.121 | AD12: =X12 -> 1 | AE12: =Y12*1.035 -> 6694.6492 | AF12: 12 | AG12: =AD12*AE12*AF12 -> 80335.79 | AH12: 0 | AI12: =SUM(AG12:AH12) -> 80335.79 | AJ12: =I12+O12+U12+AA12+AG12 -> 375415.51 | AK12: =J12+P12+V12+AB12+AH12 -> 0 | AL12: =SUM(AJ12:AK12) -> 375415.51
D13: Subtotal HQ Salaries | I13: =SUM(I10:I12) -> 195036 | J13: =SUM(J10:J12) -> 0 | K13: =SUM(K10:K12) -> 195036 | O13: =SUM(O10:O12) -> 201862.26 | P13: =SUM(P10:P12) -> 0 | Q13: =SUM(Q10:Q12) -> 201862.26 | U13: =SUM(U10:U12) -> 208927.44 | V13: =SUM(V10:V12) -> 0 | W13: =SUM(W10:W12) -> 208927.44 | AA13: =SUM(AA10:AA12) -> 216239.9 | AB13: =SUM(AB10:AB12) -> 0 | AC13: =SUM(AC10:AC12) -> 216239.9 | AG13: =SUM(AG10:AG12) -> 223808.3 | AH13: =SUM(AH10:AH12) -> 0 | AI13: =SUM(AI10:AI12) -> 223808.3 | AJ13: =SUM(AJ10:AJ12) -> 1045873.9 | AK13: =SUM(AK10:AK12) -> 0 | AL13: =SUM(AL10:AL12) -> 1045873.9
D14: *Key Personnel
D15: Field Salaries | E15: LOE
A16: PERSNL | B16: 7410 Personnel/ 7610 Consultant | C16: VZ | D16: Country Director - Expatriate* | E16: 1 | F16: 14516 | G16: 10 | H16: /months | I16: =E16*F16*G16 -> 145160 | J16: 0 | K16: =SUM(I16:J16) -> 145160 | L16: 1 | M16: =F16*1.035 -> 15024.06 | N16: 12 | O16: =M16*N16*L16 -> 180288.72 | P16: 0 | Q16: =SUM(O16:P16) -> 180288.72 | R16: 1 | S16: =M16*1.035 -> 15549.902 | T16: 2 | U16: =T16*S16*R16 -> 31099.804 | V16: 0 | W16: =SUM(U16:V16) -> 31099.804 | X16: 1 | Y16: =S16*1.035 -> 16094.149 | Z16: 0 | AA16: =Z16*Y16*X16 -> 0 | AB16: 0 | AC16: =SUM(AA16:AB16) -> 0 | AD16: 1 | AE16: =Y16*1.035 -> 16657.444 | AF16: 0 | AG16: =AF16*AE16*AD16 -> 0 | AH16: 0 | AI16: =SUM(AG16:AH16) -> 0 | AJ16: =I16+O16+U16+AA16+AG16 -> 356548.52 | AK16: =J16+P16+V16+AB16+AH16 -> 0 | AL16: =SUM(AJ16:AK16) -> 356548.52
A17: PERSNL | B17: 7410 Personnel/ 7610 Consultant | C17: VZ | D17: Deputy Country Director* | E17: 1 | F17: 6717 | G17: 10 | H17: /months | I17: =E17*F17*G17 -> 67170 | J17: 0 | K17: =SUM(I17:J17) -> 67170 | L17: 1 | M17: =F17*1.035 -> 6952.095 | N17: 12 | O17: =M17*N17*L17 -> 83425.14 | P17: 0 | Q17: =SUM(O17:P17) -> 83425.14 | R17: 1 | S17: =M17*1.035 -> 7195.4183 | T17: 12 | U17: =T17*S17*R17 -> 86345.02 | V17: 0 | W17: =SUM(U17:V17) -> 86345.02 | X17: 1 | Y17: =S17*1.035 -> 7447.258 | Z17: 12 | AA17: =Z17*Y17*X17 -> 89367.096 | AB17: 0 | AC17: =SUM(AA17:AB17) -> 89367.096 | AD17: 1 | AE17: =Y17*1.035 -> 7707.912 | AF17: 12 | AG17: =AF17*AE17*AD17 -> 92494.944 | AH17: 0 | AI17: =SUM(AG17:AH17) -> 92494.944 | AJ17: =I17+O17+U17+AA17+AG17 -> 418802.2 | AK17: =J17+P17+V17+AB17+AH17 -> 0 | AL17: =SUM(AJ17:AK17) -> 418802.2
A18: PERSNL | B18: 7410 Personnel/ 7610 Consultant | C18: VZ | D18: Finance Director | E18: 1 | F18: 4334 | G18: 9 | H18: /months | I18: =E18*F18*G18 -> 39006 | J18: 0 | K18: =SUM(I18:J18) -> 39006 | L18: 1 | M18: =F18*1.035 -> 4485.69 | N18: 12 | O18: =M18*N18*L18 -> 53828.28 | P18: 0 | Q18: =SUM(O18:P18) -> 53828.28 | R18: 1 | S18: =M18*1.035 -> 4642.6891 | T18: 12 | U18: =T18*S18*R18 -> 55712.27 | V18: 0 | W18: =SUM(U18:V18) -> 55712.27 | X18: 1 | Y18: =S18*1.035 -> 4805.1833 | Z18: 12 | AA18: =Z18*Y18*X18 -> 57662.199 | AB18: 0 | AC18: =SUM(AA18:AB18) -> 57662.199 | AD18: 1 | AE18: =Y18*1.035 -> 4973.3647 | AF18: 12 | AG18: =AF18*AE18*AD18 -> 59680.376 | AH18: 0 | AI18: =SUM(AG18:AH18) -> 59680.376 | AJ18: =I18+O18+U18+AA18+AG18 -> 265889.13 | AK18: =J18+P18+V18+AB18+AH18 -> 0 | AL18: =SUM(AJ18:AK18) -> 265889.13
A19: PERSNL | B19: 7410 Personnel/ 7610 Consultant | C19: VZ | D19: Safety & Security Director | E19: 1 | F19: 4334 | G19: 6 | H19: /months | I19: =E19*F19*G19 -> 26004 | J19: 0 | K19: =SUM(I19:J19) -> 26004 | L19: 1 | M19: =F19*1.035 -> 4485.69 | N19: 12 | O19: =M19*N19*L19 -> 53828.28 | P19: 0 | Q19: =SUM(O19:P19) -> 53828.28 | R19: 1 | S19: =M19*1.035 -> 4642.6891 | T19: 12 | U19: =T19*S19*R19 -> 55712.27 | V19: 0 | W19: =SUM(U19:V19) -> 55712.27 | X19: 1 | Y19: =S19*1.035 -> 4805.1833 | Z19: 12 | AA19: =Z19*Y19*X19 -> 57662.199 | AB19: 0 | AC19: =SUM(AA19:AB19) -> 57662.199 | AD19: 1 | AE19: =Y19*1.035 -> 4973.3647 | AF19: 7 | AG19: =AF19*AE19*AD19 -> 34813.553 | AH19: 0 | AI19: =SUM(AG19:AH19) -> 34813.553 | AJ19: =I19+O19+U19+AA19+AG19 -> 228020.3 | AK19: =J19+P19+V19+AB19+AH19 -> 0 | AL19: =SUM(AJ19:AK19) -> 228020.3
A20: PERSNL | B20: 7410 Personnel/ 7610 Consultant | C20: VZ | D20: Compliance Specialist | E20: 1 | F20: 2492 | G20: 6 | H20: /months | I20: =E20*F20*G20 -> 14952 | J20: 0 | K20: =SUM(I20:J20) -> 14952 | L20: 1 | M20: =F20*1.035 -> 2579.22 | N20: 12 | O20: =M20*N20*L20 -> 30950.64 | P20: 0 | Q20: =SUM(O20:P20) -> 30950.64 | R20: 1 | S20: =M20*1.035 -> 2669.4927 | T20: 12 | U20: =T20*S20*R20 -> 32033.912 | V20: 0 | W20: =SUM(U20:V20) -> 32033.912 | X20: 1 | Y20: =S20*1.035 -> 2762.9249 | Z20: 12 | AA20: =Z20*Y20*X20 -> 33155.099 | AB20: 0 | AC20: =SUM(AA20:AB20) -> 33155.099 | AD20: 1 | AE20: =Y20*1.035 -> 2859.6273 | AF20: 7 | AG20: =AF20*AE20*AD20 -> 20017.391 | AH20: 0 | AI20: =SUM(AG20:AH20) -> 20017.391 | AJ20: =I20+O20+U20+AA20+AG20 -> 131109.04 | AK20: =J20+P20+V20+AB20+AH20 -> 0 | AL20: =SUM(AJ20:AK20) -> 131109.04
A21: PERSNL | B21: 7410 Personnel/ 7610 Consultant | C21: VZ | D21: Accountant | E21: 1 | F21: 2492 | G21: 6 | H21: /months | I21: =E21*F21*G21 -> 14952 | J21: 0 | K21: =SUM(I21:J21) -> 14952 | L21: 1 | M21: =F21*1.035 -> 2579.22 | N21: 12 | O21: =M21*N21*L21 -> 30950.64 | P21: 0 | Q21: =SUM(O21:P21) -> 30950.64 | R21: 1 | S21: =M21*1.035 -> 2669.4927 | T21: 12 | U21: =T21*S21*R21 -> 32033.912 | V21: 0 | W21: =SUM(U21:V21) -> 32033.912 | X21: 1 | Y21: =S21*1.035 -> 2762.9249 | Z21: 12 | AA21: =Z21*Y21*X21 -> 33155.099 | AB21: 0 | AC21: =SUM(AA21:AB21) -> 33155.099 | AD21: 1 | AE21: =Y21*1.035 -> 2859.6273 | AF21: 7 | AG21: =AF21*AE21*AD21 -> 20017.391 | AH21: 0 | AI21: =SUM(AG21:AH21) -> 20017.391 | AJ21: =I21+O21+U21+AA21+AG21 -> 131109.04 | AK21: =J21+P21+V21+AB21+AH21 -> 0 | AL21: =SUM(AJ21:AK21) -> 131109.04
A22: PERSNL | B22: 7410 Personnel/ 7610 Consultant | C22: VZ | D22: Administrative Assistant | E22: 1 | F22: 2167 | G22: 6 | H22: /months | I22: =E22*F22*G22 -> 13002 | J22: 0 | K22: =SUM(I22:J22) -> 13002 | L22: 1 | M22: =F22*1.035 -> 2242.845 | N22: 12 | O22: =M22*N22*L22 -> 26914.14 | P22: 0 | Q22: =SUM(O22:P22) -> 26914.14 | R22: 1 | S22: =M22*1.035 -> 2321.3446 | T22: 12 | U22: =T22*S22*R22 -> 27856.135 | V22: 0 | W22: =SUM(U22:V22) -> 27856.135 | X22: 1 | Y22: =S22*1.035 -> 2402.5916 | Z22: 12 | AA22: =Z22*Y22*X22 -> 28831.1 | AB22: 0 | AC22: =SUM(AA22:AB22) -> 28831.1 | AD22: 1 | AE22: =Y22*1.035 -> 2486.6823 | AF22: 7 | AG22: =AF22*AE22*AD22 -> 17406.776 | AH22: 0 | AI22: =SUM(AG22:AH22) -> 17406.776 | AJ22: =I22+O22+U22+AA22+AG22 -> 114010.15 | AK22: =J22+P22+V22+AB22+AH22 -> 0 | AL22: =SUM(AJ22:AK22) -> 114010.15
A23: PERSNL | B23: 7410 Personnel/ 7610 Consultant | C23: VZ | D23: M&E Specialist | E23: 1 | F23: 2492 | G23: 6 | H23: /months | I23: =E23*F23*G23 -> 14952 | J23: 0 | K23: =SUM(I23:J23) -> 14952 | L23: 1 | M23: =F23*1.035 -> 2579.22 | N23: 12 | O23: =M23*N23*L23 -> 30950.64 | P23: 0 | Q23: =SUM(O23:P23) -> 30950.64 | R23: 1 | S23: =M23*1.035 -> 2669.4927 | T23: 12 | U23: =T23*S23*R23 -> 32033.912 | V23: 0 | W23: =SUM(U23:V23) -> 32033.912 | X23: 1 | Y23: =S23*1.035 -> 2762.9249 | Z23: 12 | AA23: =Z23*Y23*X23 -> 33155.099 | AB23: 0 | AC23: =SUM(AA23:AB23) -> 33155.099 | AD23: 1 | AE23: =Y23*1.035 -> 2859.6273 | AF23: 9 | AG23: =AF23*AE23*AD23 -> 25736.646 | AH23: 0 | AI23: =SUM(AG23:AH23) -> 25736.646 | AJ23: =I23+O23+U23+AA23+AG23 -> 136828.3 | AK23: =J23+P23+V23+AB23+AH23 -> 0 | AL23: =SUM(AJ23:AK23) -> 136828.3
A24: PERSNL | B24: 7410 Personnel/ 7610 Consultant | C24: VZ | D24: Community Development Coordinators (CDC) (4 CDCs in Year 1 & 2, 2 CDCs in Year 3-4) | E24: 1 | F24: 2167 | G24: 6 | H24: /months | I24: =E24*F24*G24*4 -> 52008 | J24: 0 | K24: =SUM(I24:J24) -> 52008 | L24: 1 | M24: =F24*1.035 -> 2242.845 | N24: 12 | O24: =M24*N24*L24*4 -> 107656.56 | P24: 0 | Q24: =SUM(O24:P24) -> 107656.56 | R24: 1 | S24: =M24*1.035 -> 2321.3446 | T24: 12 | U24: =T24*S24*R24*2 -> 55712.27 | V24: 0 | W24: =SUM(U24:V24) -> 55712.27 | X24: 1 | Y24: =S24*1.035 -> 2402.5916 | Z24: 6 | AA24: =Z24*Y24*X24*2 -> 28831.1 | AB24: 0 | AC24: =SUM(AA24:AB24) -> 28831.1 | AD24: 1 | AE24: =Y24*1.035 -> 2486.6823 | AF24: 0 | AG24: =AF24*AE24*AD24 -> 0 | AH24: 0 | AI24: =SUM(AG24:AH24) -> 0 | AJ24: =I24+O24+U24+AA24+AG24 -> 244207.93 | AK24: 0 | AL24: =SUM(AJ24:AK24) -> 244207.93
A25: PERSNL | B25: 7410 Personnel/ 7610 Consultant | C25: VZ | D25: Nutrition and Food Safety Specialist | E25: 1 | F25: 3358 | G25: 6 | H25: /months | I25: =E25*F25*G25 -> 20148 | J25: 0 | K25: =SUM(I25:J25) -> 20148 | L25: 1 | M25: =F25*1.035 -> 3475.53 | N25: 12 | O25: =M25*N25*L25 -> 41706.36 | P25: 0 | Q25: =SUM(O25:P25) -> 41706.36 | R25: 1 | S25: =M25*1.035 -> 3597.1735 | T25: 12 | U25: =T25*S25*R25 -> 43166.083 | V25: 0 | W25: =SUM(U25:V25) -> 43166.083 | X25: 1 | Y25: =S25*1.035 -> 3723.0746 | Z25: 12 | AA25: =Z25*Y25*X25 -> 44676.895 | AB25: 0 | AC25: =SUM(AA25:AB25) -> 44676.895 | AD25: 1 | AE25: =Y25*1.035 -> 3853.3822 | AF25: 7 | AG25: =AF25*AE25*AD25 -> 26973.676 | AH25: 0 | AI25: =SUM(AG25:AH25) -> 26973.676 | AJ25: =I25+O25+U25+AA25+AG25 -> 176671.01 | AK25: =J25+P25+V25+AB25+AH25 -> 0 | AL25: =SUM(AJ25:AK25) -> 176671.01
A26: PERSNL | B26: 7410 Personnel/ 7610 Consultant | C26: VZ | D26: Agricultural & Private Sector Specialist* | E26: 1 | F26: 3358 | G26: 6 | H26: /months | I26: =E26*F26*G26 -> 20148 | J26: 0 | K26: =SUM(I26:J26) -> 20148 | L26: 1 | M26: =F26*1.035 -> 3475.53 | N26: 12 | O26: =M26*N26*L26 -> 41706.36 | P26: 0 | Q26: =SUM(O26:P26) -> 41706.36 | R26: 1 | S26: =M26*1.035 -> 3597.1735 | T26: 12 | U26: =T26*S26*R26 -> 43166.083 | V26: 0 | W26: =SUM(U26:V26) -> 43166.083 | X26: 1 | Y26: =S26*1.035 -> 3723.0746 | Z26: 12 | AA26: =Z26*Y26*X26 -> 44676.895 | AB26: 0 | AC26: =SUM(AA26:AB26) -> 44676.895 | AD26: 1 | AE26: =Y26*1.035 -> 3853.3822 | AF26: 7 | AG26: =AF26*AE26*AD26 -> 26973.676 | AH26: 0 | AI26: =SUM(AG26:AH26) -> 26973.676 | AJ26: =I26+O26+U26+AA26+AG26 -> 176671.01 | AK26: =J26+P26+V26+AB26+AH26 -> 0 | AL26: =SUM(AJ26:AK26) -> 176671.01
D27: Subtotal Field Salaries | I27: =SUM(I16:I26) -> 427502 | J27: =SUM(J16:J26) -> 0 | K27: =SUM(K16:K26) -> 427502 | O27: =SUM(O16:O26) -> 682205.76 | P27: =SUM(P16:P26) -> 0 | Q27: =SUM(Q16:Q26) -> 682205.76 | U27: =SUM(U16:U26) -> 494871.67 | V27: =SUM(V16:V26) -> 0 | W27: =SUM(W16:W26) -> 494871.67 | AA27: =SUM(AA16:AA26) -> 451172.78 | AB27: =SUM(AB16:AB26) -> 0 | AC27: =SUM(AC16:AC26) -> 451172.78 | AG27: =SUM(AG16:AG26) -> 324114.43 | AH27: =SUM(AH16:AH26) -> 0 | AI27: =SUM(AI16:AI26) -> 324114.43 | AJ27: =I27+O27+U27+AA27+AG27 -> 2379866.6 | AK27: =J27+P27+V27+AB27+AH27 -> 0 | AL27: =SUM(AJ27:AK27) -> 2379866.6
D29: Local MTC Volunteers | E29: ='Volunteer Numbers'!B9 -> 75 | F29: =Leverage!C3 -> 0 | H29: /day | I29: 0 | J29: =Leverage!B23*Leverage!C23*52*Budget!E29 -> 327600 | K29: =SUM(I29:J29) -> 327600 | L29: ='Volunteer Numbers'!C9 -> 150 | M29: =Leverage!C3 -> 0 | O29: 0 | P29: =Leverage!B23*Leverage!C23*52*Budget!L29 -> 655200 | Q29: =SUM(O29:P29) -> 655200 | R29: ='Volunteer Numbers'!D9 -> 75 | S29: =Leverage!C3 -> 0 | U29: 0 | V29: =Leverage!B23*Leverage!C23*52*Budget!R29 -> 327600 | W29: =SUM(U29:V29) -> 327600 | X29: 0 | Y29: =Leverage!C3 -> 0 | AA29: 0 | AB29: 0 | AC29: =SUM(AA29:AB29) -> 0 | AD29: 0 | AE29: =Leverage!C3 -> 0 | AG29: 0 | AH29: 0 | AI29: =SUM(AG29:AH29) -> 0 | AJ29: =I29+O29+U29+AA29+AG29 -> 0 | AK29: =J29+P29+V29+AB29+AH29 -> 1310400 | AL29: =SUM(AJ29:AK29) -> 1310400
D30: F2F Volunteers | E30: ='Volunteer Numbers'!B5 -> 2 | F30: =Leverage!C4 -> 522 | H30: /day | I30: 0 | J30: =Leverage!B17+Leverage!B18 -> 15660 | K30: =SUM(I30:J30) -> 15660 | L30: ='Volunteer Numbers'!C5 -> 13 | M30: =Leverage!C4 -> 522 | O30: 0 | P30: =Leverage!C17+Leverage!C18 -> 506992.5 | Q30: =SUM(O30:P30) -> 506992.5 | R30: ='Volunteer Numbers'!D5 -> 13 | S30: =Leverage!C4 -> 522 | U30: 0 | V30: =Leverage!D17+Leverage!D18 -> 506992.5 | W30: =SUM(U30:V30) -> 506992.5 | X30: ='Volunteer Numbers'!E5 -> 13 | Y30: =Leverage!C4 -> 522 | AA30: 0 | AB30: =Leverage!E17+Leverage!E18 -> 506992.5 | AC30: =SUM(AA30:AB30) -> 506992.5 | AD30: ='Volunteer Numbers'!F5 -> 4 | AE30: =Leverage!C4 -> 522 | AG30: 0 | AH30: =Leverage!F17+Leverage!F18 -> 166387.5 | AI30: =SUM(AG30:AH30) -> 166387.5 | AJ30: =I30+O30+U30+AA30+AG30 -> 0 | AK30: =J30+P30+V30+AB30+AH30 -> 1703025 | AL30: =SUM(AJ30:AK30) -> 1703025
D32: Salaries & Wages Total | I32: =I29+I27+I13+I30 -> 622538 | J32: =SUM(J29:J30) -> 343260 | K32: =K27+K13+K30+K29 -> 965798 | O32: =O29+O27+O13+O30 -> 884068.02 | P32: =SUM(P29:P30) -> 1162192.5 | Q32: =Q27+Q13+Q30+Q29 -> 2046260.5 | U32: =U29+U27+U13+U30 -> 703799.11 | V32: =SUM(V29:V30) -> 834592.5 | W32: =W27+W13+W30+W29 -> 1538391.6 | AA32: =AA29+AA27+AA13+AA30 -> 667412.68 | AB32: =SUM(AB29:AB30) -> 506992.5 | AC32: =AC27+AC13+AC30+AC29 -> 1174405.2 | AG32: =AG29+AG27+AG13+AG30 -> 547922.72 | AH32: =SUM(AH29:AH30) -> 166387.5 | AI32: =AI27+AI13+AI30+AI29 -> 714310.22 | AJ32: =AJ29+AJ27+AJ13+AJ30 -> 3425740.5 | AK32: =SUM(AK29:AK30) -> 3013425 | AL32: =AL29+AL27+AL13+AL30 -> 6439165.5
D34: Fringe Benefits
A35: FRINGE | B35: 6950 | C35: 0 | D35: Fringe Benefits - Headquarters | E35: 0.2181 | I35: =I13*E35 -> 42537.352 | J35: 0 | K35: =SUM(I35:J35) -> 42537.352 | O35: =O13*$E$35 -> 44026.159 | P35: 0 | Q35: =SUM(O35:P35) -> 44026.159 | U35: =U13*$E$35 -> 45567.074 | V35: 0 | W35: =SUM(U35:V35) -> 45567.074 | AA35: =AA13*$E$35 -> 47161.922 | AB35: 0 | AC35: =SUM(AA35:AB35) -> 47161.922 | AG35: =AG13*$E$35 -> 48812.589 | AH35: 0 | AI35: =SUM(AG35:AH35) -> 48812.589 | AJ35: =I35+O35+U35+AA35+AG35 -> 228105.1 | AK35: =J35+P35+V35+AB35+AH35 -> 0 | AL35: =SUM(AJ35:AK35) -> 228105.1
A36: FRINGE | B36: 7420 | C36: VZ | D36: Fringe Benefits - Field (Excluding Country Director) | E36: 0.3 | I36: =(SUM(I17:I26)*$E$36) -> 84702.6 | J36: 0 | K36: =SUM(I36:J36) -> 84702.6 | O36: =(SUM(O17:O26)*$E$36) -> 150575.11 | P36: 0 | Q36: =SUM(O36:P36) -> 150575.11 | U36: =(SUM(U17:U26)*$E$36) -> 139131.56 | V36: 0 | W36: =SUM(U36:V36) -> 139131.56 | AA36: =(SUM(AA17:AA26)*$E$36) -> 135351.83 | AB36: 0 | AC36: =SUM(AA36:AB36) -> 135351.83 | AG36: =(SUM(AG17:AG26)*$E$36) -> 97234.329 | AH36: 0 | AI36: =SUM(AG36:AH36) -> 97234.329 | AJ36: =I36+O36+U36+AA36+AG36 -> 606995.44 | AK36: =J36+P36+V36+AB36+AH36 -> 0 | AL36: =SUM(AJ36:AK36) -> 606995.44
A37: FRINGE | B37: 6950 | C37: VZ | D37: Expatriate Fringe Benefit Package | E37: 0.1967 | I37: =$E$37*I16 -> 28552.972 | J37: 0 | K37: =SUM(I37:J37) -> 28552.972 | O37: =$E$37*O16 -> 35462.791 | P37: 0 | Q37: =SUM(O37:P37) -> 35462.791 | U37: =$E$37*U16 -> 6117.3315 | V37: 0 | W37: =SUM(U37:V37) -> 6117.3315 | AA37: =$E$37*AA16 -> 0 | AB37: 0 | AC37: =SUM(AA37:AB37) -> 0 | AG37: =$E$37*AG16 -> 0 | AH37: 0 | AI37: =SUM(AG37:AH37) -> 0 | AJ37: =I37+O37+U37+AA37+AG37 -> 70133.095 | AK37: =J37+P37+V37+AB37+AH37 -> 0 | AL37: =SUM(AJ37:AK37) -> 70133.095
A38: COLA | B38: 7481 | C38: VZ | D38: Cost of Living Adjustment (COLA) for Expatriate Country Director | E38: 0.3 | I38: =$E$38*I16 -> 43548 | J38: 0 | K38: =SUM(I38:J38) -> 43548 | O38: =$E$38*O16 -> 54086.616 | P38: 0 | Q38: =SUM(O38:P38) -> 54086.616 | U38: =$E$38*U16 -> 9329.9413 | V38: 0 | W38: =SUM(U38:V38) -> 9329.9413 | AA38: =$E$38*AA16 -> 0 | AB38: 0 | AC38: =SUM(AA38:AB38) -> 0 | AG38: =$E$38*AG16 -> 0 | AH38: 0 | AI38: =SUM(AG38:AH38) -> 0 | AJ38: =I38+O38+U38+AA38+AG38 -> 106964.56 | AK38: =J38+P38+V38+AB38+AH38 -> 0 | AL38: =SUM(AJ38:AK38) -> 106964.56
A39: POST DIFF | B39: 7021 | C39: VZ | D39: Post (Hardship) Differential for Expatriate Country Director | E39: 0.25 | I39: =$E$39*I16 -> 36290 | J39: 0 | K39: =SUM(I39:J39) -> 36290 | O39: =$E$39*O16 -> 45072.18 | P39: 0 | Q39: =SUM(O39:P39) -> 45072.18 | U39: =$E$39*U16 -> 7774.951 | V39: 0 | W39: =SUM(U39:V39) -> 7774.951 | AA39: =$E$39*AA16 -> 0 | AB39: 0 | AC39: =SUM(AA39:AB39) -> 0 | AG39: =$E$39*AG16 -> 0 | AH39: 0 | AI39: =SUM(AG39:AH39) -> 0 | AJ39: =I39+O39+U39+AA39+AG39 -> 89137.131 | AK39: =J39+P39+V39+AB39+AH39 -> 0 | AL39: =SUM(AJ39:AK39) -> 89137.131
A40: HOUSE. ALL | B40: 7485 | C40: VZ | D40: Housing Allowance for Expatriate Country Director | E40: 1 | F40: 2400 | G40: 6 | H40: /month | I40: =G40*F40*E40 -> 14400 | J40: 0 | K40: =SUM(I40:J40) -> 14400 | L40: 1 | M40: =F40 -> 2400 | N40: =N16 -> 12 | O40: =N40*M40*L40 -> 28800 | P40: 0 | Q40: =SUM(O40:P40) -> 28800 | R40: 1 | S40: =F40 -> 2400 | T40: =T16 -> 2 | U40: =T40*S40*R40 -> 4800 | V40: 0 | W40: =SUM(U40:V40) -> 4800 | X40: 0 | Y40: =F40 -> 2400 | Z40: =Z16 -> 0 | AA40: =Z40*Y40*X40 -> 0 | AB40: 0 | AC40: =SUM(AA40:AB40) -> 0 | AD40: 0 | AE40: =F40 -> 2400 | AF40: =AF16 -> 0 | AG40: =AF40*AE40*AD40 -> 0 | AH40: 0 | AI40: =SUM(AG40:AH40) -> 0 | AJ40: =I40+O40+U40+AA40+AG40 -> 48000 | AK40: =J40+P40+V40+AB40+AH40 -> 0 | AL40: =SUM(AJ40:AK40) -> 48000
A41: ANNAIRFAR | B41: 7510 | C41: VZ | D41: Annual Home of Record | E41: 1 | F41: 2000 | G41: 1 | H41: /yearly | I41: =G41*F41*E41 -> 2000 | J41: 0 | K41: =SUM(I41:J41) -> 2000 | L41: 1 | M41: =F41 -> 2000 | N41: 1 | O41: =N41*M41*L41 -> 2000 | P41: 0 | Q41: =SUM(O41:P41) -> 2000 | R41: 1 | S41: =F41 -> 2000 | T41: 1 | U41: =T41*S41*R41 -> 2000 | V41: 0 | W41: =SUM(U41:V41) -> 2000 | X41: 0 | Y41: =F41 -> 2000 | Z41: 0 | AA41: =Z41*Y41*X41 -> 0 | AB41: 0 | AC41: =SUM(AA41:AB41) -> 0 | AD41: 0 | AE41: =F41 -> 2000 | AF41: 0 | AG41: =AF41*AE41*AD41 -> 0 | AH41: 0 | AI41: =SUM(AG41:AH41) -> 0 | AJ41: =I41+O41+U41+AA41+AG41 -> 6000 | AK41: =J41+P41+V41+AB41+AH41 -> 0 | AL41: =SUM(AJ41:AK41) -> 6000
D43: Fringe Benefits Total | I43: =SUM(I35:I42) -> 252030.92 | J43: =SUM(J35:J42) -> 0 | K43: =SUM(K35:K42) -> 252030.92 | O43: =SUM(O35:O42) -> 360022.86 | P43: =SUM(P35:P42) -> 0 | Q43: =SUM(Q35:Q42) -> 360022.86 | U43: =SUM(U35:U42) -> 214720.86 | V43: =SUM(V35:V42) -> 0 | W43: =SUM(W35:W42) -> 214720.86 | AA43: =SUM(AA35:AA42) -> 182513.76 | AB43: =SUM(AB35:AB42) -> 0 | AC43: =SUM(AC35:AC42) -> 182513.76 | AG43: =SUM(AG35:AG42) -> 146046.92 | AH43: =SUM(AH35:AH42) -> 0 | AI43: =SUM(AI35:AI42) -> 146046.92 | AJ43: =SUM(AJ35:AJ42) -> 1155335.3 | AK43: =SUM(AK35:AK42) -> 0 | AL43: =SUM(AL35:AL42) -> 1155335.3
D45: Travel & Transportation
D47: Volunteer Travel - International Airfare
A48: VOLTRAVEL | B48: 7010 | C48: VZ | D48: International Airfare | E48: ='Volunteer Numbers'!B5 -> 2 | F48: 2000 | G48: 1 | H48: /RT | I48: =G48*F48*E48 -> 4000 | J48: 0 | K48: =SUM(I48:J48) -> 4000 | L48: ='Volunteer Numbers'!C4 -> 13 | M48: =F48 -> 2000 | N48: 1 | O48: =L48*M48*N48 -> 26000 | P48: 0 | Q48: =SUM(O48:P48) -> 26000 | R48: ='Volunteer Numbers'!D4 -> 13 | S48: =M48*1.02 -> 2040 | T48: 1 | U48: =R48*S48*T48 -> 26520 | V48: 0 | W48: =SUM(U48:V48) -> 26520 | X48: ='Volunteer Numbers'!E4 -> 13 | Y48: =S48*1.02 -> 2080.8 | Z48: 1 | AA48: =X48*Y48*Z48 -> 27050.4 | AB48: 0 | AC48: =SUM(AA48:AB48) -> 27050.4 | AD48: ='Volunteer Numbers'!F4 -> 4 | AE48: =Y48*1.02 -> 2122.416 | AF48: 1 | AG48: =AD48*AE48*AF48 -> 8489.664 | AH48: 0 | AI48: =SUM(AG48:AH48) -> 8489.664 | AJ48: =I48+O48+U48+AA48+AG48 -> 92060.064 | AK48: =J48+P48+V48+AB48+AH48 -> 0 | AL48: =SUM(AJ48:AK48) -> 92060.064
D49: Total Volunteer Airfare | E49: =E48 -> 2 | I49: =SUM(I48:I48) -> 4000 | J49: =SUM(J48:J48) -> 0 | K49: =SUM(K48:K48) -> 4000 | L49: =SUM(L48:L48) -> 13 | O49: =SUM(O48:O48) -> 26000 | P49: =SUM(P48:P48) -> 0 | Q49: =SUM(Q48:Q48) -> 26000 | R49: =SUM(R48:R48) -> 13 | U49: =SUM(U48:U48) -> 26520 | V49: =SUM(V48:V48) -> 0 | W49: =SUM(W48:W48) -> 26520 | X49: =SUM(X48:X48) -> 13 | AA49: =SUM(AA48:AA48) -> 27050.4 | AB49: =SUM(AB48:AB48) -> 0 | AC49: =SUM(AC48:AC48) -> 27050.4 | AD49: =SUM(AD48:AD48) -> 4 | AG49: =SUM(AG48:AG48) -> 8489.664 | AH49: =SUM(AH48:AH48) -> 0 | AI49: =SUM(AI48:AI48) -> 8489.664 | AJ49: =SUM(AJ48:AJ48) -> 92060.064 | AK49: =SUM(AK48:AK48) -> 0 | AL49: =SUM(AL48:AL48) -> 92060.064
D51: Volunteer Travel-Related Costs
A52: VOLTRVCTS | B52: 7015 | C52: VZ | D52: Meals and Incidentals - (Long Term Assignments) | E52: 0 | F52: 1000 | G52: 0 | H52: /month | I52: =G52*F52*E52 -> 0 | J52: 0 | K52: =SUM(I52:J52) -> 0 | L52: 3 | M52: =F52 -> 1000 | N52: 9 | O52: =L52*M52*N52 -> 27000 | P52: 0 | Q52: =SUM(O52:P52) -> 27000 | R52: 3 | S52: =M52*1.02 -> 1020 | T52: 9 | U52: =R52*S52*T52 -> 27540 | V52: 0 | W52: =SUM(U52:V52) -> 27540 | X52: 3 | Y52: =S52*1.02 -> 1040.4 | Z52: 9 | AA52: =X52*Y52*Z52 -> 28090.8 | AB52: 0 | AC52: =SUM(AA52:AB52) -> 28090.8 | AD52: 1 | AE52: =Y52*1.02 -> 1061.208 | AF52: 9 | AG52: =AD52*AE52*AF52 -> 9550.872 | AH52: 0 | AI52: =SUM(AG52:AH52) -> 9550.872 | AJ52: =I52+O52+U52+AA52+AG52 -> 92181.672 | AK52: =J52+P52+V52+AB52+AH52 -> 0 | AL52: =SUM(AJ52:AK52) -> 92181.672
A53: VOLTRVCTS | B53: 7320 | C53: VZ | D53: Lodging - (Long Term Assignments) | E53: 0 | F53: 1500 | G53: 0 | H53: /month | I53: =G53*F53*E53 -> 0 | J53: 0 | K53: =SUM(I53:J53) -> 0 | L53: 3 | M53: =F53 -> 1500 | N53: 9 | O53: =L53*M53*N53 -> 40500 | P53: 0 | Q53: =SUM(O53:P53) -> 40500 | R53: 3 | S53: =M53*1.02 -> 1530 | T53: 9 | U53: =R53*S53*T53 -> 41310 | V53: 0 | W53: =SUM(U53:V53) -> 41310 | X53: 3 | Y53: =S53*1.02 -> 1560.6 | Z53: 9 | AA53: =X53*Y53*Z53 -> 42136.2 | AB53: 0 | AC53: =SUM(AA53:AB53) -> 42136.2 | AD53: 1 | AE53: =Y53*1.02 -> 1591.812 | AF53: 9 | AG53: =AD53*AE53*AF53 -> 14326.308 | AH53: 0 | AI53: =SUM(AG53:AH53) -> 14326.308 | AJ53: =I53+O53+U53+AA53+AG53 -> 138272.51 | AK53: =J53+P53+V53+AB53+AH53 -> 0 | AL53: =SUM(AJ53:AK53) -> 138272.51
A54: VOLTRVCTS | B54: 7530 | C54: VZ | D54: Local Transportation - (Long Term Assignments) | E54: 0 | F54: =230*2 -> 460 | G54: 0 | H54: /month | I54: =G54*F54*E54 -> 0 | J54: 0 | K54: =SUM(I54:J54) -> 0 | L54: 3 | M54: =F54 -> 460 | N54: 9 | O54: =L54*M54*N54 -> 12420 | P54: 0 | Q54: =SUM(O54:P54) -> 12420 | R54: 3 | S54: =M54*1.02 -> 469.2 | T54: 9 | U54: =R54*S54*T54 -> 12668.4 | V54: 0 | W54: =SUM(U54:V54) -> 12668.4 | X54: 3 | Y54: =S54*1.02 -> 478.584 | Z54: 9 | AA54: =X54*Y54*Z54 -> 12921.768 | AB54: 0 | AC54: =SUM(AA54:AB54) -> 12921.768 | AD54: 1 | AE54: =Y54*1.02 -> 488.15568 | AF54: 9 | AG54: =AD54*AE54*AF54 -> 4393.4011 | AH54: 0 | AI54: =SUM(AG54:AH54) -> 4393.4011 | AJ54: =I54+O54+U54+AA54+AG54 -> 42403.569 | AK54: =J54+P54+V54+AB54+AH54 -> 0 | AL54: =SUM(AJ54:AK54) -> 42403.569
A55: VOLTRVCTS | B55: 7395 Matl./ 7720 Trans. | C55: VZ | D55: Translations & Materials - (Long Term Assignments) | E55: 0 | F55: 500 | G55: 0 | H55: /trip | I55: =G55*F55*E55 -> 0 | J55: 0 | K55: =SUM(I55:J55) -> 0 | L55: 3 | M55: =F55 -> 500 | N55: 1 | O55: =L55*M55*N55 -> 1500 | P55: 0 | Q55: =SUM(O55:P55) -> 1500 | R55: 3 | S55: =M55*1.02 -> 510 | T55: 1 | U55: =R55*S55*T55 -> 1530 | V55: 0 | W55: =SUM(U55:V55) -> 1530 | X55: 3 | Y55: =S55*1.02 -> 520.2 | Z55: 1 | AA55: =X55*Y55*Z55 -> 1560.6 | AB55: 0 | AC55: =SUM(AA55:AB55) -> 1560.6 | AD55: 1 | AE55: =Y55*1.02 -> 530.604 | AF55: 1 | AG55: =AD55*AE55*AF55 -> 530.604 | AH55: 0 | AI55: =SUM(AG55:AH55) -> 530.604 | AJ55: =I55+O55+U55+AA55+AG55 -> 5121.204 | AK55: =J55+P55+V55+AB55+AH55 -> 0 | AL55: =SUM(AJ55:AK55) -> 5121.204
A56: VOLTRVCTS | B56: 7015 | C56: VZ | D56: Meals and Incidentals - (Short Term Assignments) | E56: =$E$49-E52 -> 2 | F56: 100 | G56: 15 | H56: /day | I56: =G56*F56*E56 -> 3000 | J56: 0 | K56: =SUM(I56:J56) -> 3000 | L56: =$L$49-L52 -> 10 | M56: =F56*1.02 -> 102 | N56: 15 | O56: =L56*M56*N56 -> 15300 | P56: 0 | Q56: =SUM(O56:P56) -> 15300 | R56: =$R$49-R52 -> 10 | S56: =M56*1.02 -> 104.04 | T56: 15 | U56: =R56*S56*T56 -> 15606 | V56: 0 | W56: =SUM(U56:V56) -> 15606 | X56: =$X$49-X52 -> 10 | Y56: =S56*1.02 -> 106.1208 | Z56: 15 | AA56: =X56*Y56*Z56 -> 15918.12 | AB56: 0 | AC56: =SUM(AA56:AB56) -> 15918.12 | AD56: =$AD$49-AD52 -> 3 | AE56: =Y56*1.02 -> 108.24322 | AF56: 15 | AG56: =AD56*AE56*AF56 -> 4870.9447 | AH56: 0 | AI56: =SUM(AG56:AH56) -> 4870.9447 | AJ56: =I56+O56+U56+AA56+AG56 -> 54695.065 | AK56: =J56+P56+V56+AB56+AH56 -> 0 | AL56: =SUM(AJ56:AK56) -> 54695.065
A57: VOLTRVCTS | B57: 7320 | C57: VZ | D57: Lodging - (Short Term Assignments) | E57: =$E$49-E53 -> 2 | F57: 120 | G57: 15 | H57: /day | I57: =G57*F57*E57 -> 3600 | J57: 0 | K57: =SUM(I57:J57) -> 3600 | L57: =$L$49-L53 -> 10 | M57: =F57*1.02 -> 122.4 | N57: 15 | O57: =L57*M57*N57 -> 18360 | P57: 0 | Q57: =SUM(O57:P57) -> 18360 | R57: =$R$49-R53 -> 10 | S57: =M57*1.02 -> 124.848 | T57: 15 | U57: =R57*S57*T57 -> 18727.2 | V57: 0 | W57: =SUM(U57:V57) -> 18727.2 | X57: =$X$49-X53 -> 10 | Y57: =S57*1.02 -> 127.34496 | Z57: 15 | AA57: =X57*Y57*Z57 -> 19101.744 | AB57: 0 | AC57: =SUM(AA57:AB57) -> 19101.744 | AD57: =$AD$49-AD53 -> 3 | AE57: =Y57*1.02 -> 129.89186 | AF57: 15 | AG57: =AD57*AE57*AF57 -> 5845.1337 | AH57: 0 | AI57: =SUM(AG57:AH57) -> 5845.1337 | AJ57: =I57+O57+U57+AA57+AG57 -> 65634.078 | AK57: =J57+P57+V57+AB57+AH57 -> 0 | AL57: =SUM(AJ57:AK57) -> 65634.078
A58: VOLTRVCTS | B58: 7530 | C58: VZ | D58: Local Transportation - (Short Term Assignments) | E58: =$E$49-E54 -> 2 | F58: 230 | G58: 1 | H58: /trip | I58: =G58*F58*E58 -> 460 | J58: 0 | K58: =SUM(I58:J58) -> 460 | L58: =$L$49-L54 -> 10 | M58: =F58*1.02 -> 234.6 | N58: 1 | O58: =L58*M58*N58 -> 2346 | P58: 0 | Q58: =SUM(O58:P58) -> 2346 | R58: =$R$49-R54 -> 10 | S58: =M58*1.02 -> 239.292 | T58: 1 | U58: =R58*S58*T58 -> 2392.92 | V58: 0 | W58: =SUM(U58:V58) -> 2392.92 | X58: =$X$49-X54 -> 10 | Y58: =S58*1.02 -> 244.07784 | Z58: 1 | AA58: =X58*Y58*Z58 -> 2440.7784 | AB58: 0 | AC58: =SUM(AA58:AB58) -> 2440.7784 | AD58: =$AD$49-AD54 -> 3 | AE58: =Y58*1.02 -> 248.9594 | AF58: 1 | AG58: =AD58*AE58*AF58 -> 746.87819 | AH58: 0 | AI58: =SUM(AG58:AH58) -> 746.87819 | AJ58: =I58+O58+U58+AA58+AG58 -> 8386.5766 | AK58: =J58+P58+V58+AB58+AH58 -> 0 | AL58: =SUM(AJ58:AK58) -> 8386.5766
A59: VOLTRVCTS | B59: 7395 Matl./ 7720 Trans. | C59: VZ | D59: Translations & Materials - (Short Term Assignments) | E59: =$E$49-E55 -> 2 | F59: 150 | G59: 1 | H59: /trip | I59: =G59*F59*E59 -> 300 | J59: 0 | K59: =SUM(I59:J59) -> 300 | L59: =$L$49-L55 -> 10 | M59: =F59*1.02 -> 153 | N59: 1 | O59: =L59*M59*N59 -> 1530 | P59: 0 | Q59: =SUM(O59:P59) -> 1530 | R59: =$R$49-R55 -> 10 | S59: =M59*1.02 -> 156.06 | T59: 1 | U59: =R59*S59*T59 -> 1560.6 | V59: 0 | W59: =SUM(U59:V59) -> 1560.6 | X59: =$X$49-X55 -> 10 | Y59: =S59*1.02 -> 159.1812 | Z59: 1 | AA59: =X59*Y59*Z59 -> 1591.812 | AB59: 0 | AC59: =SUM(AA59:AB59) -> 1591.812 | AD59: =$AD$49-AD55 -> 3 | AE59: =Y59*1.02 -> 162.36482 | AF59: 1 | AG59: =AD59*AE59*AF59 -> 487.09447 | AH59: 0 | AI59: =SUM(AG59:AH59) -> 487.09447 | AJ59: =I59+O59+U59+AA59+AG59 -> 5469.5065 | AK59: =J59+P59+V59+AB59+AH59 -> 0 | AL59: =SUM(AJ59:AK59) -> 5469.5065
D60: Total Volunteer Travel-Related | I60: =SUM(I52:I59) -> 7360 | J60: =SUM(J52:J59) -> 0 | K60: =SUM(K52:K59) -> 7360 | O60: =SUM(O52:O59) -> 118956 | P60: =SUM(P52:P59) -> 0 | Q60: =SUM(Q52:Q59) -> 118956 | U60: =SUM(U52:U59) -> 121335.12 | V60: =SUM(V52:V59) -> 0 | W60: =SUM(W52:W59) -> 121335.12 | AA60: =SUM(AA52:AA59) -> 123761.82 | AB60: =SUM(AB52:AB59) -> 0 | AC60: =SUM(AC52:AC59) -> 123761.82 | AG60: =SUM(AG52:AG59) -> 40751.236 | AH60: =SUM(AH52:AH59) -> 0 | AI60: =SUM(AI52:AI59) -> 40751.236 | AJ60: =SUM(AJ52:AJ59) -> 412164.18 | AK60: =SUM(AK52:AK59) -> 0 | AL60: =SUM(AL52:AL59) -> 412164.18
D62: Subtotal Volunteer Travel | I62: =I60+I49 -> 11360 | J62: =J60+J49 -> 0 | K62: =SUM(I62:J62) -> 11360 | O62: =O60+O49 -> 144956 | P62: =P60+P49 -> 0 | Q62: =SUM(O62:P62) -> 144956 | U62: =U60+U49 -> 147855.12 | V62: =V60+V49 -> 0 | W62: =SUM(U62:V62) -> 147855.12 | AA62: =AA60+AA49 -> 150812.22 | AB62: =AB60+AB49 -> 0 | AC62: =SUM(AA62:AB62) -> 150812.22 | AG62: =AG60+AG49 -> 49240.9 | AH62: =AH60+AH49 -> 0 | AI62: =SUM(AG62:AH62) -> 49240.9 | AJ62: =AJ60+AJ49 -> 504224.24 | AK62: =AK60+AK49 -> 0 | AL62: =AL60+AL49 -> 504224.24
AK63: =J63+P63+V63+AB63+AH63 -> 0 | AL63: =SUM(AJ63:AK63) -> 0
D64: Staff Travel - International Airfare
A65: STFTRAVEL | B65: 7510 | C65: 0 | D65: International Airfare | E65: 3 | F65: 2000 | G65: 1 | H65: /RT | I65: =G65*F65*E65 -> 6000 | J65: 0 | K65: =SUM(I65:J65) -> 6000 | L65: 8 | M65: =F65*1.02 -> 2040 | N65: 1 | O65: =L65*M65*N65 -> 16320 | P65: 0 | Q65: =SUM(O65:P65) -> 16320 | R65: 8 | S65: =M65*1.02 -> 2080.8 | T65: 1 | U65: =R65*S65*T65 -> 16646.4 | V65: 0 | W65: =SUM(U65:V65) -> 16646.4 | X65: 8 | Y65: =S65*1.02 -> 2122.416 | Z65: 1 | AA65: =X65*Y65*Z65 -> 16979.328 | AB65: 0 | AC65: =SUM(AA65:AB65) -> 16979.328 | AD65: 6 | AE65: =Y65*1.02 -> 2164.8643 | AF65: 1 | AG65: =AD65*AE65*AF65 -> 12989.186 | AH65: 0 | AI65: =SUM(AG65:AH65) -> 12989.186 | AJ65: =I65+O65+U65+AA65+AG65 -> 68934.914 | AK65: =J65+P65+V65+AB65+AH65 -> 0 | AL65: =SUM(AJ65:AK65) -> 68934.914
D66: Total Staff Intl Airfare | E66: =SUM(E65:E65) -> 3 | I66: =SUM(I65:I65) -> 6000 | J66: =SUM(J65:J65) -> 0 | K66: =SUM(K65:K65) -> 6000 | L66: =SUM(L65:L65) -> 8 | O66: =SUM(O65:O65) -> 16320 | P66: =SUM(P65:P65) -> 0 | Q66: =SUM(Q65:Q65) -> 16320 | R66: =SUM(R65:R65) -> 8 | U66: =SUM(U65:U65) -> 16646.4 | V66: =SUM(V65:V65) -> 0 | W66: =SUM(W65:W65) -> 16646.4 | X66: =SUM(X65:X65) -> 8 | AA66: =SUM(AA65:AA65) -> 16979.328 | AB66: =SUM(AB65:AB65) -> 0 | AC66: =SUM(AC65:AC65) -> 16979.328 | AD66: =SUM(AD65:AD65) -> 6 | AG66: =SUM(AG65:AG65) -> 12989.186 | AH66: =SUM(AH65:AH65) -> 0 | AI66: =SUM(AI65:AI65) -> 12989.186 | AJ66: =I66+O66+U66+AA66+AG66 -> 68934.914 | AK66: =J66+P66+V66+AB66+AH66 -> 0 | AL66: =SUM(AJ66:AK66) -> 68934.914
D68: Staff International Travel-Related Costs
A69: STFTRVCTS | B69: 7520 | C69: 0 | D69: Meals and Incidentals | E69: =E66 -> 3 | F69: 100 | G69: 7 | H69: /day | I69: =G69*F69*E69 -> 2100 | J69: 0 | K69: =SUM(I69:J69) -> 2100 | L69: =L65 -> 8 | M69: =F69*1.02 -> 102 | N69: 7 | O69: =L69*M69*N69 -> 5712 | P69: 0 | Q69: =SUM(O69:P69) -> 5712 | R69: =R65 -> 8 | S69: =M69*1.02 -> 104.04 | T69: 7 | U69: =R69*S69*T69 -> 5826.24 | V69: 0 | W69: =SUM(U69:V69) -> 5826.24 | X69: =X65 -> 8 | Y69: =S69*1.02 -> 106.1208 | Z69: 7 | AA69: =X69*Y69*Z69 -> 5942.7648 | AB69: 0 | AC69: =SUM(AA69:AB69) -> 5942.7648 | AD69: =AD65 -> 6 | AE69: =Y69*1.02 -> 108.24322 | AF69: 7 | AG69: =AD69*AE69*AF69 -> 4546.2151 | AH69: 0 | AI69: =SUM(AG69:AH69) -> 4546.2151 | AJ69: =I69+O69+U69+AA69+AG69 -> 24127.22 | AK69: =J69+P69+V69+AB69+AH69 -> 0 | AL69: =SUM(AJ69:AK69) -> 24127.22
A70: STFTRVCTS | B70: 7320 | C70: 0 | D70: Lodging | E70: =E65 -> 3 | F70: 120 | G70: 7 | H70: /day | I70: =G70*F70*E70 -> 2520 | J70: 0 | K70: =SUM(I70:J70) -> 2520 | L70: =L65 -> 8 | M70: =F70*1.02 -> 122.4 | N70: 7 | O70: =L70*M70*N70 -> 6854.4 | P70: 0 | Q70: =SUM(O70:P70) -> 6854.4 | R70: =R65 -> 8 | S70: =M70*1.02 -> 124.848 | T70: 7 | U70: =R70*S70*T70 -> 6991.488 | V70: 0 | W70: =SUM(U70:V70) -> 6991.488 | X70: =X65 -> 8 | Y70: =S70*1.02 -> 127.34496 | Z70: 7 | AA70: =X70*Y70*Z70 -> 7131.3178 | AB70: 0 | AC70: =SUM(AA70:AB70) -> 7131.3178 | AD70: =AD65 -> 6 | AE70: =Y70*1.02 -> 129.89186 | AF70: 7 | AG70: =AD70*AE70*AF70 -> 5455.4581 | AH70: 0 | AI70: =SUM(AG70:AH70) -> 5455.4581 | AJ70: =I70+O70+U70+AA70+AG70 -> 28952.664 | AK70: =J70+P70+V70+AB70+AH70 -> 0 | AL70: =SUM(AJ70:AK70) -> 28952.664
A71: STFTRVCTS | B71: 7530 | C71: 0 | D71: Local Transportation | E71: =E66 -> 3 | F71: 230 | G71: 1 | H71: /trip | I71: =G71*F71*E71 -> 690 | J71: 0 | K71: =SUM(I71:J71) -> 690 | L71: =L66 -> 8 | M71: =F71*1.02 -> 234.6 | N71: 1 | O71: =L71*M71*N71 -> 1876.8 | P71: 0 | Q71: =SUM(O71:P71) -> 1876.8 | R71: =R66 -> 8 | S71: =M71*1.02 -> 239.292 | T71: 1 | U71: =R71*S71*T71 -> 1914.336 | V71: 0 | W71: =SUM(U71:V71) -> 1914.336 | X71: =X66 -> 8 | Y71: =S71*1.02 -> 244.07784 | Z71: 1 | AA71: =X71*Y71*Z71 -> 1952.6227 | AB71: 0 | AC71: =SUM(AA71:AB71) -> 1952.6227 | AD71: =AD66 -> 6 | AE71: =Y71*1.02 -> 248.9594 | AF71: 1 | AG71: =AD71*AE71*AF71 -> 1493.7564 | AH71: 0 | AI71: =SUM(AG71:AH71) -> 1493.7564 | AJ71: =I71+O71+U71+AA71+AG71 -> 7927.5151 | AK71: =J71+P71+V71+AB71+AH71 -> 0 | AL71: =SUM(AJ71:AK71) -> 7927.5151
A72: STFTRVCTS | B72: 7520 | C72: 0 | D72: Other Travel Related Expenses | E72: =E66 -> 3 | F72: 150 | G72: 1 | H72: /trip | I72: =G72*F72*E72 -> 450 | J72: 0 | K72: =SUM(I72:J72) -> 450 | L72: =L66 -> 8 | M72: =F72*1.02 -> 153 | N72: 1 | O72: =L72*M72*N72 -> 1224 | P72: 0 | Q72: =SUM(O72:P72) -> 1224 | R72: =R66 -> 8 | S72: =M72*1.02 -> 156.06 | T72: 1 | U72: =R72*S72*T72 -> 1248.48 | V72: 0 | W72: =SUM(U72:V72) -> 1248.48 | X72: =X66 -> 8 | Y72: =S72*1.02 -> 159.1812 | Z72: 1 | AA72: =X72*Y72*Z72 -> 1273.4496 | AB72: 0 | AC72: =SUM(AA72:AB72) -> 1273.4496 | AD72: =AD66 -> 6 | AE72: =Y72*1.02 -> 162.36482 | AF72: 1 | AG72: =AD72*AE72*AF72 -> 974.18894 | AH72: 0 | AI72: =SUM(AG72:AH72) -> 974.18894 | AJ72: =I72+O72+U72+AA72+AG72 -> 5170.1185 | AK72: =J72+P72+V72+AB72+AH72 -> 0 | AL72: =SUM(AJ72:AK72) -> 5170.1185
D73: Total Staff Intl TRE | I73: =SUM(I69:I72) -> 5760 | J73: =SUM(J69:J72) -> 0 | K73: =SUM(K69:K72) -> 5760 | L73: =SUM(L69:L72) -> 32 | O73: =SUM(O69:O72) -> 15667.2 | P73: =SUM(P69:P72) -> 0 | Q73: =SUM(Q69:Q72) -> 15667.2 | R73: =SUM(R69:R72) -> 32 | U73: =SUM(U69:U72) -> 15980.544 | V73: =SUM(V69:V72) -> 0 | W73: =SUM(W69:W72) -> 15980.544 | X73: =SUM(X69:X72) -> 32 | AA73: =SUM(AA69:AA72) -> 16300.155 | AB73: =SUM(AB69:AB72) -> 0 | AC73: =SUM(AC69:AC72) -> 16300.155 | AD73: =SUM(AD69:AD72) -> 24 | AG73: =SUM(AG69:AG72) -> 12469.618 | AH73: =SUM(AH69:AH72) -> 0 | AI73: =SUM(AI69:AI72) -> 12469.618 | AJ73: =SUM(AJ69:AJ72) -> 66177.517 | AK73: =SUM(AK69:AK72) -> 0 | AL73: =SUM(AL69:AL72) -> 66177.517
D75: Staff Domestic Travel - Local Staff Travel
A76: LOCAL TRVL | B76: 7520 | C76: VZ | D76: Meals and Incidentals (Travel w/ Long Term Volunteers) | E76: =E52 -> 0 | F76: 50 | G76: 5 | H76: /day | I76: =G76*F76*E76 -> 0 | J76: 0 | K76: =SUM(I76:J76) -> 0 | L76: =L52 -> 3 | M76: =F76*1.02 -> 51 | N76: 5 | O76: =L76*M76*N76 -> 765 | P76: 0 | Q76: =SUM(O76:P76) -> 765 | R76: =R52 -> 3 | S76: =M76*1.02 -> 52.02 | T76: 5 | U76: =R76*S76*T76 -> 780.3 | V76: 0 | W76: =SUM(U76:V76) -> 780.3 | X76: =X52 -> 3 | Y76: =S76*1.02 -> 53.0604 | Z76: 5 | AA76: =X76*Y76*Z76 -> 795.906 | AB76: 0 | AC76: =SUM(AA76:AB76) -> 795.906 | AD76: =AD52 -> 1 | AE76: =Y76*1.02 -> 54.121608 | AF76: 5 | AG76: =AD76*AE76*AF76 -> 270.60804 | AH76: 0 | AI76: =SUM(AG76:AH76) -> 270.60804 | AJ76: =I76+O76+U76+AA76+AG76 -> 2611.814 | AK76: =J76+P76+V76+AB76+AH76 -> 0 | AL76: =SUM(AJ76:AK76) -> 2611.814
A77: LOCAL TRVL | B77: 7320 | C77: VZ | D77: Lodging (Travel w/ Long Term Volunteers) | E77: =E53 -> 0 | F77: 120 | G77: 5 | H77: /day | I77: =G77*F77*E77 -> 0 | J77: 0 | K77: =SUM(I77:J77) -> 0 | L77: =L53 -> 3 | M77: =F77*1.02 -> 122.4 | N77: 5 | O77: =L77*M77*N77 -> 1836 | P77: 0 | Q77: =SUM(O77:P77) -> 1836 | R77: =R53 -> 3 | S77: =M77*1.02 -> 124.848 | T77: 5 | U77: =R77*S77*T77 -> 1872.72 | V77: 0 | W77: =SUM(U77:V77) -> 1872.72 | X77: =X53 -> 3 | Y77: =S77*1.02 -> 127.34496 | Z77: 5 | AA77: =X77*Y77*Z77 -> 1910.1744 | AB77: 0 | AC77: =SUM(AA77:AB77) -> 1910.1744 | AD77: =AD53 -> 1 | AE77: =Y77*1.02 -> 129.89186 | AF77: 5 | AG77: =AD77*AE77*AF77 -> 649.4593 | AH77: 0 | AI77: =SUM(AG77:AH77) -> 649.4593 | AJ77: =I77+O77+U77+AA77+AG77 -> 6268.3537 | AK77: =J77+P77+V77+AB77+AH77 -> 0 | AL77: =SUM(AJ77:AK77) -> 6268.3537
A78: LOCAL TRVL | B78: 7530 | C78: VZ | D78: Transportation (Travel w/ Long Term Volunteers) | E78: =E54 -> 0 | F78: 100 | G78: 1 | H78: /trip | I78: =G78*F78*E78 -> 0 | J78: 0 | K78: =SUM(I78:J78) -> 0 | L78: =L54 -> 3 | M78: =F78*1.02 -> 102 | N78: 1 | O78: =L78*M78*N78 -> 306 | P78: 0 | Q78: =SUM(O78:P78) -> 306 | R78: =R54 -> 3 | S78: =M78*1.02 -> 104.04 | T78: 1 | U78: =R78*S78*T78 -> 312.12 | V78: 0 | W78: =SUM(U78:V78) -> 312.12 | X78: =X54 -> 3 | Y78: =S78*1.02 -> 106.1208 | Z78: 1 | AA78: =X78*Y78*Z78 -> 318.3624 | AB78: 0 | AC78: =SUM(AA78:AB78) -> 318.3624 | AD78: =AD54 -> 1 | AE78: =Y78*1.02 -> 108.24322 | AF78: 1 | AG78: =AD78*AE78*AF78 -> 108.24322 | AH78: 0 | AI78: =SUM(AG78:AH78) -> 108.24322 | AJ78: =I78+O78+U78+AA78+AG78 -> 1044.7256 | AK78: =J78+P78+V78+AB78+AH78 -> 0 | AL78: =SUM(AJ78:AK78) -> 1044.7256
A79: LOCAL TRVL | B79: 7520 | C79: VZ | D79: Other Travel Related Expenses (Travel w/ Long Term Volunteers) | E79: =E54 -> 0 | F79: 50 | G79: 1 | H79: /trip | I79: =G79*F79*E79 -> 0 | J79: 0 | K79: =SUM(I79:J79) -> 0 | L79: =L54 -> 3 | M79: =F79*1.02 -> 51 | N79: 1 | O79: =L79*M79*N79 -> 153 | P79: 0 | Q79: =SUM(O79:P79) -> 153 | R79: =R54 -> 3 | S79: =M79*1.02 -> 52.02 | T79: 1 | U79: =R79*S79*T79 -> 156.06 | V79: 0 | W79: =SUM(U79:V79) -> 156.06 | X79: =X54 -> 3 | Y79: =S79*1.02 -> 53.0604 | Z79: 1 | AA79: =X79*Y79*Z79 -> 159.1812 | AB79: 0 | AC79: =SUM(AA79:AB79) -> 159.1812 | AD79: =AD54 -> 1 | AE79: =Y79*1.02 -> 54.121608 | AF79: 1 | AG79: =AD79*AE79*AF79 -> 54.121608 | AH79: 0 | AI79: =SUM(AG79:AH79) -> 54.121608 | AJ79: =I79+O79+U79+AA79+AG79 -> 522.36281 | AK79: =J79+P79+V79+AB79+AH79 -> 0 | AL79: =SUM(AJ79:AK79) -> 522.36281
A80: LOCAL TRVL | B80: 7520 | C80: VZ | D80: Meals and Incidentals (Travel w/ Short Term Volunteers) | E80: =E56 -> 2 | F80: 50 | G80: 15 | H80: /day | I80: =G80*F80*E80 -> 1500 | J80: 0 | K80: =SUM(I80:J80) -> 1500 | L80: =L56 -> 10 | M80: =F80*1.02 -> 51 | N80: 15 | O80: =L80*M80*N80 -> 7650 | P80: 0 | Q80: =SUM(O80:P80) -> 7650 | R80: =R56 -> 10 | S80: =M80*1.02 -> 52.02 | T80: 15 | U80: =R80*S80*T80 -> 7803 | V80: 0 | W80: =SUM(U80:V80) -> 7803 | X80: =X56 -> 10 | Y80: =S80*1.02 -> 53.0604 | Z80: 15 | AA80: =X80*Y80*Z80 -> 7959.06 | AB80: 0 | AC80: =SUM(AA80:AB80) -> 7959.06 | AD80: =AD56 -> 3 | AE80: =Y80*1.02 -> 54.121608 | AF80: 15 | AG80: =AD80*AE80*AF80 -> 2435.4724 | AH80: 0 | AI80: =SUM(AG80:AH80) -> 2435.4724 | AJ80: =I80+O80+U80+AA80+AG80 -> 27347.532 | AK80: =J80+P80+V80+AB80+AH80 -> 0 | AL80: =SUM(AJ80:AK80) -> 27347.532
A81: LOCAL TRVL | B81: 7320 | C81: VZ | D81: Lodging (Travel w/ Short Term Volunteers) | E81: =E57 -> 2 | F81: 120 | G81: 15 | H81: /day | I81: =G81*F81*E81 -> 3600 | J81: 0 | K81: =SUM(I81:J81) -> 3600 | L81: =L57 -> 10 | M81: =F81*1.02 -> 122.4 | N81: 15 | O81: =L81*M81*N81 -> 18360 | P81: 0 | Q81: =SUM(O81:P81) -> 18360 | R81: =R57 -> 10 | S81: =M81*1.02 -> 124.848 | T81: 15 | U81: =R81*S81*T81 -> 18727.2 | V81: 0 | W81: =SUM(U81:V81) -> 18727.2 | X81: =X57 -> 10 | Y81: =S81*1.02 -> 127.34496 | Z81: 15 | AA81: =X81*Y81*Z81 -> 19101.744 | AB81: 0 | AC81: =SUM(AA81:AB81) -> 19101.744 | AD81: =AD57 -> 3 | AE81: =Y81*1.02 -> 129.89186 | AF81: 15 | AG81: =AD81*AE81*AF81 -> 5845.1337 | AH81: 0 | AI81: =SUM(AG81:AH81) -> 5845.1337 | AJ81: =I81+O81+U81+AA81+AG81 -> 65634.078 | AK81: =J81+P81+V81+AB81+AH81 -> 0 | AL81: =SUM(AJ81:AK81) -> 65634.078
A82: LOCAL TRVL | B82: 7530 | C82: VZ | D82: Transportation (Travel w/ Short Term Volunteers) | E82: =E58 -> 2 | F82: 100 | G82: 1 | H82: /trip | I82: =G82*F82*E82 -> 200 | J82: 0 | K82: =SUM(I82:J82) -> 200 | L82: =L58 -> 10 | M82: =F82*1.02 -> 102 | N82: 1 | O82: =L82*M82*N82 -> 1020 | P82: 0 | Q82: =SUM(O82:P82) -> 1020 | R82: =R58 -> 10 | S82: =M82*1.02 -> 104.04 | T82: 1 | U82: =R82*S82*T82 -> 1040.4 | V82: 0 | W82: =SUM(U82:V82) -> 1040.4 | X82: =X58 -> 10 | Y82: =S82*1.02 -> 106.1208 | Z82: 1 | AA82: =X82*Y82*Z82 -> 1061.208 | AB82: 0 | AC82: =SUM(AA82:AB82) -> 1061.208 | AD82: =AD58 -> 3 | AE82: =Y82*1.02 -> 108.24322 | AF82: 1 | AG82: =AD82*AE82*AF82 -> 324.72965 | AH82: 0 | AI82: =SUM(AG82:AH82) -> 324.72965 | AJ82: =I82+O82+U82+AA82+AG82 -> 3646.3376 | AK82: =J82+P82+V82+AB82+AH82 -> 0 | AL82: =SUM(AJ82:AK82) -> 3646.3376
A83: LOCAL TRVL | B83: 7520 | C83: VZ | D83: Other Travel Related Expenses (Travel w/ Short Term Volunteers) | E83: =E58 -> 2 | F83: 50 | G83: 1 | H83: /trip | I83: =G83*F83*E83 -> 100 | J83: 0 | K83: =SUM(I83:J83) -> 100 | L83: =L58 -> 10 | M83: =F83*1.02 -> 51 | N83: 1 | O83: =L83*M83*N83 -> 510 | P83: 0 | Q83: =SUM(O83:P83) -> 510 | R83: =R58 -> 10 | S83: =M83*1.02 -> 52.02 | T83: 1 | U83: =R83*S83*T83 -> 520.2 | V83: 0 | W83: =SUM(U83:V83) -> 520.2 | X83: =X58 -> 10 | Y83: =S83*1.02 -> 53.0604 | Z83: 1 | AA83: =X83*Y83*Z83 -> 530.604 | AB83: 0 | AC83: =SUM(AA83:AB83) -> 530.604 | AD83: =AD58 -> 3 | AE83: =Y83*1.02 -> 54.121608 | AF83: 1 | AG83: =AD83*AE83*AF83 -> 162.36482 | AH83: 0 | AI83: =SUM(AG83:AH83) -> 162.36482 | AJ83: =I83+O83+U83+AA83+AG83 -> 1823.1688 | AK83: =J83+P83+V83+AB83+AH83 -> 0 | AL83: =SUM(AJ83:AK83) -> 1823.1688
A84: LOCAL TRVL | B84: 7530 Travel/ 7320 Lodging | C84: VZ | D84: Local Travel Costs for Site Visits, M&E and Oversight | E84: 4 | F84: 60 | G84: =260/2 -> 130 | H84: /day | I84: =G84*F84*E84 -> 31200 | J84: 0 | K84: =SUM(I84:J84) -> 31200 | L84: 4 | M84: =F84*1.02 -> 61.2 | N84: 260 | O84: =L84*M84*N84 -> 63648 | P84: 0 | Q84: =SUM(O84:P84) -> 63648 | R84: 2 | S84: =M84*1.02 -> 62.424 | T84: 130 | U84: =R84*S84*T84 -> 16230.24 | V84: 0 | W84: =SUM(U84:V84) -> 16230.24 | X84: 2 | Y84: =S84*1.02 -> 63.67248 | Z84: 130 | AA84: =X84*Y84*Z84 -> 16554.845 | AB84: 0 | AC84: =SUM(AA84:AB84) -> 16554.845 | AD84: 1 | AE84: =Y84*1.02 -> 64.94593 | AF84: =260/4 -> 65 | AG84: =AD84*AE84*AF84 -> 4221.4854 | AH84: 0 | AI84: =SUM(AG84:AH84) -> 4221.4854 | AJ84: =I84+O84+U84+AA84+AG84 -> 131854.57 | AK84: =J84+P84+V84+AB84+AH84 -> 0 | AL84: =SUM(AJ84:AK84) -> 131854.57
D85: Total Staff Domestic Travel | I85: =SUM(I76:I84) -> 36600 | J85: =SUM(J76:J84) -> 0 | K85: =SUM(K76:K84) -> 36600 | L85: =SUM(L76:L84) -> 56 | O85: =SUM(O76:O84) -> 94248 | P85: =SUM(P76:P84) -> 0 | Q85: =SUM(Q76:Q84) -> 94248 | R85: =SUM(R76:R84) -> 54 | U85: =SUM(U76:U84) -> 47442.24 | V85: =SUM(V76:V84) -> 0 | W85: =SUM(W76:W84) -> 47442.24 | X85: =SUM(X76:X84) -> 54 | AA85: =SUM(AA76:AA84) -> 48391.085 | AB85: =SUM(AB76:AB84) -> 0 | AC85: =SUM(AC76:AC84) -> 48391.085 | AD85: =SUM(AD76:AD84) -> 17 | AG85: =SUM(AG76:AG84) -> 14071.618 | AH85: =SUM(AH76:AH84) -> 0 | AI85: =SUM(AI76:AI84) -> 14071.618 | AJ85: =SUM(AJ76:AJ84) -> 240752.94 | AK85: =SUM(AK76:AK84) -> 0 | AL85: =SUM(AL76:AL84) -> 240752.94
D87: Staff Travel - US Travel
A88: STFTRAV-US | B88: 7510 | C88: 0 | D88: Workshop / US Trips Airfare | E88: 2 | F88: 585 | G88: 1 | H88: /RT | I88: =G88*F88*E88 -> 1170 | J88: 0 | K88: =SUM(I88:J88) -> 1170 | L88: 2 | M88: =F88*1.02 -> 596.7 | N88: 1 | O88: =L88*M88*N88 -> 1193.4 | P88: 0 | Q88: =SUM(O88:P88) -> 1193.4 | R88: 2 | S88: =M88*1.02 -> 608.634 | T88: 1 | U88: =R88*S88*T88 -> 1217.268 | V88: 0 | W88: =SUM(U88:V88) -> 1217.268 | X88: 2 | Y88: =S88*1.02 -> 620.80668 | Z88: 1 | AA88: =X88*Y88*Z88 -> 1241.6134 | AB88: 0 | AC88: =SUM(AA88:AB88) -> 1241.6134 | AD88: 2 | AE88: =Y88*1.02 -> 633.22281 | AF88: 1 | AG88: =AD88*AE88*AF88 -> 1266.4456 | AH88: 0 | AI88: =SUM(AG88:AH88) -> 1266.4456 | AJ88: =I88+O88+U88+AA88+AG88 -> 6088.727 | AK88: =J88+P88+V88+AB88+AH88 -> 0 | AL88: =SUM(AJ88:AK88) -> 6088.727
A89: STFTRAV-US | B89: 7520 | C89: 0 | D89: Meals and incidentals | E89: 2 | F89: 53 | G89: 6 | H89: /day | I89: =G89*F89*E89 -> 636 | J89: 0 | K89: =SUM(I89:J89) -> 636 | L89: 2 | M89: =F89*1.02 -> 54.06 | N89: 6 | O89: =L89*M89*N89 -> 648.72 | P89: 0 | Q89: =SUM(O89:P89) -> 648.72 | R89: 2 | S89: =M89*1.02 -> 55.1412 | T89: 6 | U89: =R89*S89*T89 -> 661.6944 | V89: 0 | W89: =SUM(U89:V89) -> 661.6944 | X89: 2 | Y89: =S89*1.02 -> 56.244024 | Z89: 6 | AA89: =X89*Y89*Z89 -> 674.92829 | AB89: 0 | AC89: =SUM(AA89:AB89) -> 674.92829 | AD89: 2 | AE89: =Y89*1.02 -> 57.368904 | AF89: 6 | AG89: =AD89*AE89*AF89 -> 688.42685 | AH89: 0 | AI89: =SUM(AG89:AH89) -> 688.42685 | AJ89: =I89+O89+U89+AA89+AG89 -> 3309.7695 | AK89: =J89+P89+V89+AB89+AH89 -> 0 | AL89: =SUM(AJ89:AK89) -> 3309.7695
A90: STFTRAV-US | B90: 7320 | C90: 0 | D90: Lodging | E90: 2 | F90: 110 | G90: 6 | H90: /day | I90: =G90*F90*E90 -> 1320 | J90: 0 | K90: =SUM(I90:J90) -> 1320 | L90: 2 | M90: =F90*1.02 -> 112.2 | N90: 6 | O90: =L90*M90*N90 -> 1346.4 | P90: 0 | Q90: =SUM(O90:P90) -> 1346.4 | R90: 2 | S90: =M90*1.02 -> 114.444 | T90: 6 | U90: =R90*S90*T90 -> 1373.328 | V90: 0 | W90: =SUM(U90:V90) -> 1373.328 | X90: 2 | Y90: =S90*1.02 -> 116.73288 | Z90: 6 | AA90: =X90*Y90*Z90 -> 1400.7946 | AB90: 0 | AC90: =SUM(AA90:AB90) -> 1400.7946 | AD90: 2 | AE90: =Y90*1.02 -> 119.06754 | AF90: 6 | AG90: =AD90*AE90*AF90 -> 1428.8105 | AH90: 0 | AI90: =SUM(AG90:AH90) -> 1428.8105 | AJ90: =I90+O90+U90+AA90+AG90 -> 6869.333 | AK90: =J90+P90+V90+AB90+AH90 -> 0 | AL90: =SUM(AJ90:AK90) -> 6869.333
A91: STFTRAV-US | B91: 7530 | C91: 0 | D91: Transportation | E91: 2 | F91: 250 | G91: 1 | H91: /trip | I91: =G91*F91*E91 -> 500 | J91: 0 | K91: =SUM(I91:J91) -> 500 | L91: 2 | M91: =F91*1.02 -> 255 | N91: 1 | O91: =L91*M91*N91 -> 510 | P91: 0 | Q91: =SUM(O91:P91) -> 510 | R91: 2 | S91: =M91*1.02 -> 260.1 | T91: 1 | U91: =R91*S91*T91 -> 520.2 | V91: 0 | W91: =SUM(U91:V91) -> 520.2 | X91: 2 | Y91: =S91*1.02 -> 265.302 | Z91: 1 | AA91: =X91*Y91*Z91 -> 530.604 | AB91: 0 | AC91: =SUM(AA91:AB91) -> 530.604 | AD91: 2 | AE91: =Y91*1.02 -> 270.60804 | AF91: 1 | AG91: =AD91*AE91*AF91 -> 541.21608 | AH91: 0 | AI91: =SUM(AG91:AH91) -> 541.21608 | AJ91: =I91+O91+U91+AA91+AG91 -> 2602.0201 | AK91: =J91+P91+V91+AB91+AH91 -> 0 | AL91: =SUM(AJ91:AK91) -> 2602.0201
A92: STFTRAV-US | B92: 7520 | C92: 0 | D92: Other Travel Related Expenses | E92: 2 | F92: 150 | G92: 1 | H92: /trip | I92: =G92*F92*E92 -> 300 | J92: 0 | K92: =SUM(I92:J92) -> 300 | L92: 2 | M92: =F92*1.02 -> 153 | N92: 1 | O92: =L92*M92*N92 -> 306 | P92: 0 | Q92: =SUM(O92:P92) -> 306 | R92: 2 | S92: =M92*1.02 -> 156.06 | T92: 1 | U92: =R92*S92*T92 -> 312.12 | V92: 0 | W92: =SUM(U92:V92) -> 312.12 | X92: =X88 -> 2 | Y92: =S92*1.02 -> 159.1812 | Z92: 1 | AA92: =X92*Y92*Z92 -> 318.3624 | AB92: 0 | AC92: =SUM(AA92:AB92) -> 318.3624 | AD92: 2 | AE92: =Y92*1.02 -> 162.36482 | AF92: 1 | AG92: =AD92*AE92*AF92 -> 324.72965 | AH92: 0 | AI92: =SUM(AG92:AH92) -> 324.72965 | AJ92: =I92+O92+U92+AA92+AG92 -> 1561.212 | AK92: =J92+P92+V92+AB92+AH92 -> 0 | AL92: =SUM(AJ92:AK92) -> 1561.212
D93: Total Staff Travel US | I93: =SUM(I88:I92) -> 3926 | J93: =SUM(J88:J92) -> 0 | K93: =SUM(K88:K92) -> 3926 | L93: =SUM(L88:L92) -> 10 | O93: =SUM(O88:O92) -> 4004.52 | P93: =SUM(P88:P92) -> 0 | Q93: =SUM(Q88:Q92) -> 4004.52 | R93: =SUM(R88:R92) -> 10 | U93: =SUM(U88:U92) -> 4084.6104 | V93: =SUM(V88:V92) -> 0 | W93: =SUM(W88:W92) -> 4084.6104 | X93: =SUM(X88:X92) -> 10 | AA93: =SUM(AA88:AA92) -> 4166.3026 | AB93: =SUM(AB88:AB92) -> 0 | AC93: =SUM(AC88:AC92) -> 4166.3026 | AD93: =SUM(AD88:AD92) -> 10 | AG93: =SUM(AG88:AG92) -> 4249.6287 | AH93: =SUM(AH88:AH92) -> 0 | AI93: =SUM(AI88:AI92) -> 4249.6287 | AJ93: =SUM(AJ88:AJ92) -> 20431.062 | AK93: =J93+P93+V93+AB93+AH93 -> 0 | AL93: =SUM(AJ93:AK93) -> 20431.062
D95: Subtotal Staff Travel | I95: =I93+I73+I66+I85 -> 52286 | J95: =J93+J73+J66+J85 -> 0 | K95: =K93+K73+K66+K85 -> 52286 | O95: =O93+O73+O66+O85 -> 130239.72 | P95: =P93+P73+P66+P85 -> 0 | Q95: =Q93+Q73+Q66+Q85 -> 130239.72 | U95: =U93+U73+U66+U85 -> 84153.794 | V95: =V93+V73+V66+V85 -> 0 | W95: =W93+W73+W66+W85 -> 84153.794 | AA95: =AA93+AA73+AA66+AA85 -> 85836.87 | AB95: =AB93+AB73+AB66+AB85 -> 0 | AC95: =AC93+AC73+AC66+AC85 -> 85836.87 | AG95: =AG93+AG73+AG66+AG85 -> 43780.051 | AH95: =AH93+AH73+AH66+AH85 -> 0 | AI95: =AI93+AI73+AI66+AI85 -> 43780.051 | AJ95: =AJ93+AJ73+AJ66+AJ85 -> 396296.44 | AK95: =AK93+AK73+AK66+AK85 -> 0 | AL95: =AL93+AL73+AL66+AL85 -> 396296.44
D97: Travel Total | I97: =I95+I62 -> 63646 | J97: =J95+J62 -> 0 | K97: =K95+K62 -> 63646 | O97: =O95+O62 -> 275195.72 | P97: =P95+P62 -> 0 | Q97: =Q95+Q62 -> 275195.72 | U97: =U95+U62 -> 232008.91 | V97: =V95+V62 -> 0 | W97: =W95+W62 -> 232008.91 | AA97: =AA95+AA62 -> 236649.09 | AB97: =AB95+AB62 -> 0 | AC97: =AC95+AC62 -> 236649.09 | AG97: =AG95+AG62 -> 93020.951 | AH97: =AH95+AH62 -> 0 | AI97: =AI95+AI62 -> 93020.951 | AJ97: =AJ95+AJ62 -> 900520.68 | AK97: =AK95+AK62 -> 0 | AL97: =SUM(AJ97:AK97) -> 900520.68
D99: Equipment
A101: VEHICLE | B101: 7440 | C101: VZ | D101: Vehicles for Field Office | E101: 3 | F101: 53500 | H101: /vehicle | I101: =F101*E101 -> 160500 | J101: 0 | K101: =SUM(I101:J101) -> 160500 | L101: 0 | M101: =F101 -> 53500 | O101: =L101*M101 -> 0 | P101: 0 | Q101: =SUM(O101:P101) -> 0 | R101: 0 | S101: =F101 -> 53500 | U101: =S101*R101 -> 0 | V101: 0 | W101: =SUM(U101:V101) -> 0 | X101: 0 | Y101: =F101 -> 53500 | AA101: =X101*Y101 -> 0 | AB101: 0 | AC101: =SUM(AA101:AB101) -> 0 | AD101: 0 | AE101: =F101 -> 53500 | AG101: =AE101*AD101 -> 0 | AH101: 0 | AI101: =SUM(AG101:AH101) -> 0 | AJ101: =I101+O101+U101+AA101+AG101 -> 160500 | AK101: =J101+P101+V101+AB101+AH101 -> 0 | AL101: =SUM(AJ101:AK101) -> 160500
A102: VEHICLE | B102: 7440 | C102: VZ | D102: Motorcycles for Field Office | E102: 4 | F102: 1300 | H102: /motorcycle | I102: =F102*E102 -> 5200 | J102: 0 | K102: =SUM(I102:J102) -> 5200 | L102: 0 | M102: =F102 -> 1300 | O102: =L102*M102 -> 0 | P102: 0 | Q102: =SUM(O102:P102) -> 0 | R102: 0 | S102: =F102 -> 1300 | U102: =S102*R102 -> 0 | V102: 0 | W102: =SUM(U102:V102) -> 0 | X102: 0 | Y102: =F102 -> 1300 | AA102: =X102*Y102 -> 0 | AB102: 0 | AC102: =SUM(AA102:AB102) -> 0 | AD102: 0 | AE102: =F102 -> 1300 | AG102: =AE102*AD102 -> 0 | AH102: 0 | AI102: =SUM(AG102:AH102) -> 0 | AJ102: =I102+O102+U102+AA102+AG102 -> 5200 | AK102: =J102+P102+V102+AB102+AH102 -> 0 | AL102: =SUM(AJ102:AK102) -> 5200
D104: Equipment Total | I104: =SUM(I101:I103) -> 165700 | J104: =SUM(J101:J103) -> 0 | K104: =SUM(K101:K103) -> 165700 | O104: =SUM(O101:O103) -> 0 | P104: =SUM(P101:P103) -> 0 | Q104: =SUM(Q101:Q103) -> 0 | U104: =SUM(U101:U103) -> 0 | V104: =SUM(V101:V103) -> 0 | W104: =SUM(W101:W103) -> 0 | AA104: =SUM(AA101:AA103) -> 0 | AB104: =SUM(AB101:AB103) -> 0 | AC104: =SUM(AC101:AC103) -> 0 | AG104: =SUM(AG101:AG103) -> 0 | AH104: =SUM(AH101:AH103) -> 0 | AI104: =SUM(AI101:AI103) -> 0 | AJ104: =SUM(AJ101:AJ103) -> 165700 | AK104: =SUM(AK101:AK103) -> 0 | AL104: =SUM(AJ104:AK104) -> 165700
D106: Supplies
D108: HQ Office Supplies
A109: SUPPLIES | B109: 8010 | C109: 0 | D109: Laptop, Bag, Accessories | E109: 3 | F109: =Supplies!B30 -> 1114.97 | H109: /unit | I109: =F109*E109 -> 3344.91 | J109: 0 | K109: =SUM(I109:J109) -> 3344.91 | L109: 0 | M109: =F109 -> 1114.97 | O109: =L109*M109 -> 0 | P109: 0 | Q109: =SUM(O109:P109) -> 0 | R109: =O109*P109*Q109 -> 0 | S109: =F109 -> 1114.97 | U109: =S109*R109 -> 0 | V109: 0 | W109: =SUM(U109:V109) -> 0 | X109: =U109*V109*W109 -> 0 | Y109: =F109 -> 1114.97 | AA109: =Y109*X109 -> 0 | AB109: 0 | AC109: =SUM(AA109:AB109) -> 0 | AD109: =AA109*AB109*AC109 -> 0 | AE109: =F109 -> 1114.97 | AF109: 0 | AG109: =AE109*AD109 -> 0 | AH109: 0 | AI109: =SUM(AG109:AH109) -> 0 | AJ109: =I109+O109+U109+AA109+AG109 -> 3344.91 | AK109: =J109+P109+V109+AB109+AH109 -> 0 | AL109: =SUM(AJ109:AK109) -> 3344.91
A110: SUPPLIES | B110: 8010 | C110: 0 | D110: Camera, Accessories, Memory Card, S&H | E110: =Supplies!C6 -> 1 | F110: =Supplies!B38 -> 488.95 | H110: /unit | I110: =F110*E110 -> 488.95 | J110: 0 | K110: =SUM(I110:J110) -> 488.95 | L110: 0 | M110: =F110 -> 488.95 | O110: =L110*M110 -> 0 | P110: 0 | Q110: =SUM(O110:P110) -> 0 | R110: =O110*P110*Q110 -> 0 | S110: =F110 -> 488.95 | U110: =S110*R110 -> 0 | V110: 0 | W110: =SUM(U110:V110) -> 0 | X110: =U110*V110*W110 -> 0 | Y110: =F110 -> 488.95 | AA110: =Y110*X110 -> 0 | AB110: 0 | AC110: =SUM(AA110:AB110) -> 0 | AD110: =AA110*AB110*AC110 -> 0 | AE110: =F110 -> 488.95 | AG110: =AE110*AD110 -> 0 | AH110: 0 | AI110: =SUM(AG110:AH110) -> 0 | AJ110: =I110+O110+U110+AA110+AG110 -> 488.95 | AK110: =J110+P110+V110+AB110+AH110 -> 0 | AL110: =SUM(AJ110:AK110) -> 488.95
A111: SUPPLIES | B111: 8010 | C111: 0 | D111: LCD Projector | E111: =Supplies!C7 -> 1 | F111: =Supplies!B44 -> 738 | H111: /unit | I111: =F111*E111 -> 738 | J111: 0 | K111: =SUM(I111:J111) -> 738 | L111: 0 | M111: =F111 -> 738 | O111: =L111*M111 -> 0 | P111: 0 | Q111: =SUM(O111:P111) -> 0 | R111: =O111*P111*Q111 -> 0 | S111: =F111 -> 738 | U111: =S111*R111 -> 0 | V111: 0 | W111: =SUM(U111:V111) -> 0 | X111: =U111*V111*W111 -> 0 | Y111: =F111 -> 738 | AA111: =Y111*X111 -> 0 | AB111: 0 | AC111: =SUM(AA111:AB111) -> 0 | AD111: =AA111*AB111*AC111 -> 0 | AE111: =F111 -> 738 | AG111: =AE111*AD111 -> 0 | AH111: 0 | AI111: =SUM(AG111:AH111) -> 0 | AJ111: =I111+O111+U111+AA111+AG111 -> 738 | AK111: =J111+P111+V111+AB111+AH111 -> 0 | AL111: =SUM(AJ111:AK111) -> 738
A112: SUPPLIES | B112: 8010 | C112: 0 | D112: Office Furniture (Includes Desk, Chairs, Table, Shelves, & Filing Cabinet) | E112: 3 | F112: =Supplies!B68 -> 2791 | H112: /unit | I112: =F112*E112 -> 8373 | J112: 0 | K112: =SUM(I112:J112) -> 8373 | L112: 0 | M112: =F112 -> 2791 | O112: =L112*M112 -> 0 | P112: 0 | Q112: =SUM(O112:P112) -> 0 | R112: =O112*P112*Q112 -> 0 | S112: =F112 -> 2791 | U112: =S112*R112 -> 0 | V112: 0 | W112: =SUM(U112:V112) -> 0 | X112: =U112*V112*W112 -> 0 | Y112: =F112 -> 2791 | AA112: =Y112*X112 -> 0 | AB112: 0 | AC112: =SUM(AA112:AB112) -> 0 | AD112: =AA112*AB112*AC112 -> 0 | AE112: =F112 -> 2791 | AG112: =AE112*AD112 -> 0 | AH112: 0 | AI112: =SUM(AG112:AH112) -> 0 | AJ112: =I112+O112+U112+AA112+AG112 -> 8373 | AK112: =J112+P112+V112+AB112+AH112 -> 0 | AL112: =SUM(AJ112:AK112) -> 8373
A113: SUPPLIES | B113: 8010 | C113: 0 | D113: General Office Supplies and Stationary for HQ | E113: 1 | F113: 250 | G113: 12 | H113: /month | I113: =F113*E113*G113 -> 3000 | J113: 0 | K113: =SUM(I113:J113) -> 3000 | L113: 1 | M113: =F113 -> 250 | N113: 12 | O113: =L113*M113*N113 -> 3000 | P113: 0 | Q113: =SUM(O113:P113) -> 3000 | R113: 1 | S113: =F113 -> 250 | T113: 12 | U113: =S113*R113*T113 -> 3000 | V113: 0 | W113: =SUM(U113:V113) -> 3000 | X113: 1 | Y113: =F113 -> 250 | Z113: 12 | AA113: =Y113*X113*Z113 -> 3000 | AB113: 0 | AC113: =SUM(AA113:AB113) -> 3000 | AD113: 1 | AE113: =F113 -> 250 | AF113: 12 | AG113: =AE113*AD113*AF113 -> 3000 | AH113: 0 | AI113: =SUM(AG113:AH113) -> 3000 | AJ113: =I113+O113+U113+AA113+AG113 -> 15000 | AK113: =J113+P113+V113+AB113+AH113 -> 0 | AL113: =SUM(AJ113:AK113) -> 15000
A114: SUPPLIES | B114: 8010 | C114: 0 | D114: Technical Supplies for Volunteer Assignments | E114: =E49 -> 2 | F114: 200 | G114: 1 | H114: /volunteer | I114: =G114*F114*E114 -> 400 | J114: 0 | K114: =SUM(I114:J114) -> 400 | L114: =L49 -> 13 | M114: =F114 -> 200 | N114: 1 | O114: =N114*M114*L114 -> 2600 | P114: 0 | Q114: =SUM(O114:P114) -> 2600 | R114: =R49 -> 13 | S114: =F114 -> 200 | T114: 1 | U114: =T114*S114*R114 -> 2600 | V114: 0 | W114: =SUM(U114:V114) -> 2600 | X114: =X49 -> 13 | Y114: =F114 -> 200 | Z114: 1 | AA114: =Z114*Y114*X114 -> 2600 | AB114: 0 | AC114: =SUM(AA114:AB114) -> 2600 | AD114: =AD49 -> 4 | AE114: =F114 -> 200 | AF114: 1 | AG114: =AF114*AE114*AD114 -> 800 | AH114: 0 | AI114: =SUM(AG114:AH114) -> 800 | AJ114: =I114+O114+U114+AA114+AG114 -> 9000 | AK114: =J114+P114+V114+AB114+AH114 -> 0 | AL114: =SUM(AJ114:AK114) -> 9000
D115: Total HQ Office Supplies | I115: =SUM(I109:I114) -> 16344.86 | J115: =SUM(J109:J114) -> 0 | K115: =SUM(K109:K114) -> 16344.86 | O115: =SUM(O109:O114) -> 5600 | P115: =SUM(P109:P114) -> 0 | Q115: =SUM(Q109:Q114) -> 5600 | U115: =SUM(U109:U114) -> 5600 | V115: =SUM(V109:V114) -> 0 | W115: =SUM(W109:W114) -> 5600 | AA115: =SUM(AA109:AA114) -> 5600 | AB115: =SUM(AB109:AB114) -> 0 | AC115: =SUM(AC109:AC114) -> 5600 | AG115: =SUM(AG109:AG114) -> 3800 | AH115: =SUM(AH109:AH114) -> 0 | AI115: =SUM(AI109:AI114) -> 3800 | AJ115: =I115+O115+U115+AA115+AG115 -> 36944.86 | AK115: =J115+P115+V115+AB115+AH115 -> 0 | AL115: =SUM(AJ115:AK115) -> 36944.86
D117: Field Office Supplies
A118: SUPPLIES | B118: 7455 | C118: VZ | D118: Laptop, Bag, Accessories | E118: 14 | F118: =Supplies!B30 -> 1114.97 | H118: /unit | I118: =F118*E118 -> 15609.58 | J118: 0 | K118: =SUM(I118:J118) -> 15609.58 | L118: 0 | M118: =F118 -> 1114.97 | O118: =L118*M118 -> 0 | P118: 0 | Q118: =SUM(O118:P118) -> 0 | R118: =O118*P118*Q118 -> 0 | S118: =F118 -> 1114.97 | U118: =S118*R118 -> 0 | V118: 0 | W118: =SUM(U118:V118) -> 0 | X118: =U118*V118*W118 -> 0 | Y118: =F118 -> 1114.97 | AA118: =Y118*X118 -> 0 | AB118: 0 | AC118: =SUM(AA118:AB118) -> 0 | AD118: =AA118*AB118*AC118 -> 0 | AE118: =F118 -> 1114.97 | AG118: =AE118*AD118 -> 0 | AH118: 0 | AI118: =SUM(AG118:AH118) -> 0 | AJ118: =I118+O118+U118+AA118+AG118 -> 15609.58 | AK118: =J118+P118+V118+AB118+AH118 -> 0 | AL118: =SUM(AJ118:AK118) -> 15609.58
A119: SUPPLIES | B119: 7455 | C119: VZ | D119: Printer | E119: 2 | F119: =Supplies!B50 -> 860 | H119: /unit | I119: =F119*E119 -> 1720 | J119: 0 | K119: =SUM(I119:J119) -> 1720 | L119: 0 | M119: =F119 -> 860 | O119: =L119*M119 -> 0 | P119: 0 | Q119: =SUM(O119:P119) -> 0 | R119: =O119*P119*Q119 -> 0 | S119: =F119 -> 860 | U119: =S119*R119 -> 0 | V119: 0 | W119: =SUM(U119:V119) -> 0 | X119: =U119*V119*W119 -> 0 | Y119: =F119 -> 860 | AA119: =Y119*X119 -> 0 | AB119: 0 | AC119: =SUM(AA119:AB119) -> 0 | AD119: =AA119*AB119*AC119 -> 0 | AE119: =F119 -> 860 | AG119: =AE119*AD119 -> 0 | AH119: 0 | AI119: =SUM(AG119:AH119) -> 0 | AJ119: =I119+O119+U119+AA119+AG119 -> 1720 | AK119: =J119+P119+V119+AB119+AH119 -> 0 | AL119: =SUM(AJ119:AK119) -> 1720
A120: SUPPLIES | B120: 7455 | C120: VZ | D120: Camera and Accessories | E120: 3 | F120: =Supplies!B38 -> 488.95 | H120: /unit | I120: =F120*E120 -> 1466.85 | J120: 0 | K120: =SUM(I120:J120) -> 1466.85 | L120: 0 | M120: =F120 -> 488.95 | O120: =L120*M120 -> 0 | P120: 0 | Q120: =SUM(O120:P120) -> 0 | R120: =O120*P120*Q120 -> 0 | S120: =F120 -> 488.95 | U120: =S120*R120 -> 0 | V120: 0 | W120: =SUM(U120:V120) -> 0 | X120: =U120*V120*W120 -> 0 | Y120: =F120 -> 488.95 | AA120: =Y120*X120 -> 0 | AB120: 0 | AC120: =SUM(AA120:AB120) -> 0 | AD120: =AA120*AB120*AC120 -> 0 | AE120: =F120 -> 488.95 | AG120: =AE120*AD120 -> 0 | AH120: 0 | AI120: =SUM(AG120:AH120) -> 0 | AJ120: =I120+O120+U120+AA120+AG120 -> 1466.85 | AK120: =J120+P120+V120+AB120+AH120 -> 0 | AL120: =SUM(AJ120:AK120) -> 1466.85
...

Sheet Supplies
A1: Supplies
B2: Rate | C2: Unit | D2: Total
A4: Headquarters
A5: Laptop, Bag, Accessories, Shipping and Handling | B5: =B30 -> 1114.97 | C5: 3 | D5: =B5*C5 -> 3344.91
A6: Camera, Accessories, Memory Card, S&H | B6: =B38 -> 488.95 | C6: 1 | D6: =B6*C6 -> 488.95
A7: LCD Projector | B7: =B44 -> 738 | C7: 1 | D7: =B7*C7 -> 738
A8: Office Furniture (Includes Desk, Chairs, Table, Shelves, & Filing Cabinet) | B8: =B68 -> 2791 | C8: 3 | D8: =B8*C8 -> 8373
A9: Total HQ | D9: =SUM(D5:D8) -> 12944.86
A11: Field Office
A12: Venezuela
A13: Laptop | B13: =B30 -> 1114.97 | C13: 11 | D13: =B13*C13 -> 12264.67
A14: Printer | B14: =B50 -> 860 | C14: 2 | D14: =B14*C14 -> 1720
A15: Camera and Accessories | B15: =B38 -> 488.95 | C15: 3 | D15: =B15*C15 -> 1466.85
A16: Video Camera | B16: =B58 -> 337.95 | C16: 2 | D16: =B16*C16 -> 675.9
A17: LCD projector | B17: =B44 -> 738 | C17: 2 | D17: =B17*C17 -> 1476
A18: Total Field | D18: =SUM(D13:D17) -> 17603.42
A20: Total: | D20: =D18+D9 -> 30548.28
A23: Detailed Quotes for Supplies
A24: Item Detail | B24: Price
A26: Laptop
A27: Dell XPS 15 | B27: 1049.99
A28: Laptop Bag, Accessories | B28: 44.99
A29: Mouse | B29: 19.99
B30: =SUM(B27:B29) -> 1114.97
A32: Digital Camera
A33: Canon - PowerShot SX730 HS 20.3-Megapixel Digital Camera | B33: 380
A34: Camera Bag | B34: 21.95
A35: SanDisk 256GB Ultra microSDXC UHS-I Memory Card | B35: 35
A36: Dynex All in One Memory Card Reader | B36: 32
A37: Shipping and Handling | B37: 20
B38: =SUM(B33:B37) -> 488.95
A40: LCD Projector
A41: BenQ MH535FHD 1080P Projector with Ceiling Mount | B41: 583
A42: Extra Bulb, stand and accessories | B42: 135
A43: Shipping and Handling | B43: 20
B44: =SUM(B41:B43) -> 738
A46: Color Laser Printer
A47: Dell Color Smart Multifunction Printer S2825cdn Color Laser | B47: 390
A48: Toners & Accessories | B48: 450
A49: Shipping and Handling | B49: 20
B50: =SUM(B46:B49) -> 860
A52: Video Camera
A53: Canon VIXIA HF R800 Camcorder with 3 year warranty | B53: 220
A54: Camera Bag | B54: 14.95
A55: Tripod | B55: 43
A56: SanDisk 256GB Ultra microSDXC UHS-I Memory Card | B56: 40
A57: Shipping and Handling | B57: 20
B58: =SUM(B53:B57) -> 337.95
A60: Office Furniture
A61: Desk with Hutch for Storage | B61: 1349
A62: Desk Chair | B62: 269
A63: Bookshelf for Storage | B63: 149
A64: Round Table for Meetings | B64: 300
A65: Chairs for Round Table (Set 2 Chairs) | B65: 175
A66: Filing Cabinets with Lock | B66: 299
A67: Misc. Office Supplies to Set up Desk | B67: 250
B68: =SUM(B61:B67) -> 2791

Sheet Leverage
A2: Leverage Formula Summaries | B2: Per Day | C2: Per Volunteer - Long Term | D2: Per Volunteer - Short Term
A4: Estimated value of F2F volunteer professional time | B4: 522 | C4: 522 | D4: 522
A5: Total Volunteers: | B5: ='Volunteer Numbers'!G5 -> 45 | C5: =G11 -> 10 | D5: =G12 -> 35
A6: Total Days | B6: =SUM(C6:D6) -> 3262.5 | C6: =C5*((365/12)*9) -> 2737.5 | D6: =D5*15 -> 525 | E6: Assuming 9 months average per long term volunteer.
A7: Total LOP Program: | B7: =SUM(C7:D7) -> 1703025 | C7: =C6*C4 -> 1428975 | D7: =D6*D4 -> 274050
A9: Leverage Breakdown By Volunteer Type
A10: Volunteers | B10: FY20 | C10: FY21 | D10: FY22 | E10: FY23 | F10: FY24 | G10: Totals
A11: Long Term | B11: =Budget!E53 -> 0 | C11: =Budget!L53 -> 3 | D11: =Budget!R53 -> 3 | E11: =Budget!X53 -> 3 | F11: =Budget!AD53 -> 1 | G11: =SUM(B11:F11) -> 10
A12: Short Term | B12: =Budget!E57 -> 2 | C12: =Budget!L57 -> 10 | D12: =Budget!R57 -> 10 | E12: =Budget!X57 -> 10 | F12: =Budget!AD57 -> 3 | G12: =SUM(B12:F12) -> 35
A13: Total | B13: =SUM(B11:B12) -> 2 | C13: =SUM(C11:C12) -> 13 | D13: =SUM(D11:D12) -> 13 | E13: =SUM(E11:E12) -> 13 | F13: =SUM(F11:F12) -> 4 | G13: =SUM(G11:G12) -> 45
A15: Value Breakdown By Volunteer Type
A16: Volunteers | B16: FY20 | C16: FY21 | D16: FY22 | E16: FY23 | F16: FY24 | G16: Totals
A17: Long Term | B17: =B11*$C$4*((365/12)*9) -> 0 | C17: =C11*$C$4*((365/12)*9) -> 428692.5 | D17: =D11*$C$4*((365/12)*9) -> 428692.5 | E17: =E11*$C$4*((365/12)*9) -> 428692.5 | F17: =F11*$C$4*((365/12)*9) -> 142897.5 | G17: =SUM(B17:F17) -> 1428975
A18: Short Term | B18: =B12*$D$4*15 -> 15660 | C18: =C12*$D$4*15 -> 78300 | D18: =D12*$D$4*15 -> 78300 | E18: =E12*$D$4*15 -> 78300 | F18: =F12*$D$4*15 -> 23490 | G18: =SUM(B18:F18) -> 274050
A19: Total | B19: =SUM(B17:B18) -> 15660 | C19: =SUM(C17:C18) -> 506992.5 | D19: =SUM(D17:D18) -> 506992.5 | E19: =SUM(E17:E18) -> 506992.5 | F19: =SUM(F17:F18) -> 166387.5 | G19: =SUM(G17:G18) -> 1703025
A21: Leverage Formula Summaries | B21: Per Hour | C21: Average # of Hours/Week
A23: Local MTC Volunteer | B23: 7 | C23: =3*4 -> 12
A24: Total 300 Local MTC Volunteers (3/per MTC) for 1 Year | B24: =300*B23*C23*52 -> 1310400 | C24: =300*C23 -> 3600
A26: Leverage Grand Total
A27: 3013425

Sheet Volunteer Numbers
A2: Recruited and Fielded By Partners Only
A3: Volunteers | B3: FY20 | C3: FY21 | D3: FY22 | E3: FY23 | F3: FY24 | G3: Totals
A4: F2F Venezuela | B4: 2 | C4: 13 | D4: 13 | E4: 13 | F4: 4 | G4: =SUM(B4:F4) -> 45
A5: Total | B5: =SUM(B4:B4) -> 2 | C5: =SUM(C4:C4) -> 13 | D5: =SUM(D4:D4) -> 13 | E5: =SUM(E4:E4) -> 13 | F5: =SUM(F4:F4) -> 4 | G5: =SUM(G4:G4) -> 45
A7: Recruited and Fielded By Partners & Local Implementing Partners
A8: Volunteers | B8: FY20 | C8: FY21 | D8: FY22 | E8: FY23 | F8: FY24 | G8: Totals
A9: Local MTC Volunteers | B9: 75 | C9: 150 | D9: 75 | E9: 0 | F9: 0 | G9: =SUM(B9:F9) -> 300
A10: Total | B10: =SUM(B9:B9) -> 75 | C10: =SUM(C9:C9) -> 150 | D10: =SUM(D9:D9) -> 75 | E10: =SUM(E9:E9) -> 0 | F10: =SUM(F9:F9) -> 0 | G10: =SUM(G9:G9) -> 300
