Workbook

Sheet Summary Budget
A1: Entity: | B1: P
A2: Program-Dept.: | B2: FTF
A3: Funder-Grant: | B3: USDA700
A4: Country Code: | B4: COL2
A5: Subcontract Code: | B5: ICFUNDACION | E5: Item | F5: Unit | G5: # of Units | H5: Unit Value COP | I5: Unit Value USD | J5: Total Value COP | K5: Total Value USD | L5: C4D Contribution COP | M5: Contribution C4D USD | N5: % Contribution C4D | O5: Cotribution IC Cost - Share / COP | P5: Cotribution IC Cost - Share / USD | Q5: % Contribution IC Cost - Share/ | R5: Level of Effort (LOE) | S5: Detail
A6: Sage Activity | B6: Sage Object Code/ Line Item | C6: Sub Name Code | D6: Subcontract Activity Code | E6: 1.Personal (Laboral) | J6: =+SUM(J7:J24) -> 1606446288 | K6: =SUM(K7:K24) -> 364956.28 | L6: =+SUM(L7:L24) -> 1418576688 | M6: =SUM(M7:M24) -> 322275.61 | O6: =+SUM(O7:O24) -> 187869600 | P6: =SUM(P7:P24) -> 42680.661
A7: SUBPRODORG | B7: 89050 | C7: ICFUNDCION | D7: ICFPERPCO | E7: 1.1. Program Coordinator | F7: month | G7: =+'Detailed Budget'!AO4 -> 28 | H7: =+(('Detailed Budget'!D4*'Detailed Budget'!C4)+('Detailed Budget'!Q4*'Detailed Budget'!P4)+('Detailed Budget'!AD4*'Detailed Budget'!AC4))/G7 -> 2139428.6 | I7: =+H7/$E$73 -> 486.04045 | J7: =+H7*G7 -> 59904000 | K7: =+J7/$E$73 -> 13609.133 | L7: =+J7*N7 -> 0 | M7: =+L7/$E$73 -> 0 | N7: =+'Detailed Budget'!F4 -> 0 | O7: =+J7*Q7 -> 59904000 | P7: =+O7/$E$73 -> 13609.133 | Q7: =+'Detailed Budget'!I4 -> 1 | R7: =+'Detailed Budget'!AV4 -> 0.2 | S7: Laura Rivera
A8: SUBPRODORG | B8: 89050 | C8: ICFUNDCION | D8: ICFPERBSC | E8: 1.2. Business Strengthening Coordinator | F8: month | G8: =+'Detailed Budget'!AO5 -> 28 | H8: =+(('Detailed Budget'!D5*'Detailed Budget'!C5)+('Detailed Budget'!Q5*'Detailed Budget'!P5)+('Detailed Budget'!AD5*'Detailed Budget'!AC5))/G8 -> 4409362.3 | I8: =+H8/$E$73 -> 1001.7294 | J8: =+H8*G8 -> 123462144 | K8: =+J8/$E$73 -> 28048.423 | L8: =+J8*N8 -> 123462144 | M8: =+L8/$E$73 -> 28048.423 | N8: =+'Detailed Budget'!F5 -> 1 | O8: =+J8*Q8 -> 0 | P8: =+O8/$E$73 -> 0 | Q8: =+'Detailed Budget'!I5 -> 0 | R8: =+'Detailed Budget'!AV5 -> 1 | S8: Yineth Henao
A9: SUBPRODORG | B9: 89050 | C9: ICFUNDCION | D9: ICFPERCTS | E9: 1.3. Cacao technical specialist | F9: month | G9: =+'Detailed Budget'!AO6 -> 28 | H9: =+(('Detailed Budget'!D6*'Detailed Budget'!C6)+('Detailed Budget'!Q6*'Detailed Budget'!P6)+('Detailed Budget'!AD6*'Detailed Budget'!AC6))/G9 -> 4409362.3 | I9: =+H9/$E$73 -> 1001.7294 | J9: =+H9*G9 -> 123462144 | K9: =+J9/$E$73 -> 28048.423 | L9: =+J9*N9 -> 123462144 | M9: =+L9/$E$73 -> 28048.423 | N9: =+'Detailed Budget'!F6 -> 1 | O9: =+J9*Q9 -> 0 | P9: =+O9/$E$73 -> 0 | Q9: =+'Detailed Budget'!I6 -> 0 | R9: =+'Detailed Budget'!AV6 -> 1 | S9: Juan Gabriel Vargas
A10: SUBPRODORG | B10: 89050 | C10: ICFUNDCION | D10: ICFPERORG | E10: 1.4. Organizational Professional | F10: month | G10: =+'Detailed Budget'!AO7 -> 28 | H10: =+(('Detailed Budget'!D7*'Detailed Budget'!C7)+('Detailed Budget'!Q7*'Detailed Budget'!P7)+('Detailed Budget'!AD7*'Detailed Budget'!AC7))/G10 -> 3423085.7 | I10: =+H10/$E$73 -> 777.66473 | J10: =+H10*G10 -> 95846400 | K10: =+J10/$E$73 -> 21774.612 | L10: =+J10*N10 -> 71884800 | M10: =+L10/$E$73 -> 16330.959 | N10: =+'Detailed Budget'!F7 -> 0.75 | O10: =+J10*Q10 -> 23961600 | P10: =+O10/$E$73 -> 5443.6531 | Q10: =+'Detailed Budget'!I7 -> 0.25 | R10: =+'Detailed Budget'!AV7 -> 0.8 | S10: Por contratar
A11: SUBPRODORG | B11: 89050 | C11: ICFUNDCION | D11: ICFPERF&A | E11: 1.5. F&A Specialist | F11: month | G11: =+'Detailed Budget'!AO8 -> 28 | H11: =+(('Detailed Budget'!D8*'Detailed Budget'!C8)+('Detailed Budget'!Q8*'Detailed Budget'!P8)+('Detailed Budget'!AD8*'Detailed Budget'!AC8))/G11 -> 2032457.1 | I11: =+H11/$E$73 -> 461.73843 | J11: =+H11*G11 -> 56908800 | K11: =+J11/$E$73 -> 12928.676 | L11: =+J11*N11 -> 56908800 | M11: =+L11/$E$73 -> 12928.676 | N11: =+'Detailed Budget'!F8 -> 1 | O11: =+J11*Q11 -> 0 | P11: =+O11/$E$73 -> 0 | Q11: =+'Detailed Budget'!I8 -> 0 | R11: =+'Detailed Budget'!AV8 -> 0.5 | S11: Yuliana Murillo
A12: SUBPRODORG | B12: 89050 | C12: ICFUNDCION | D12: ICFPERBPP | E12: 1.6. Business Partner Professional Antioquia, Córdoba 1 | F12: month | G12: =+'Detailed Budget'!AO9 -> 27 | H12: =+(('Detailed Budget'!D9*'Detailed Budget'!C9)+('Detailed Budget'!Q9*'Detailed Budget'!P9)+('Detailed Budget'!AD9*'Detailed Budget'!AC9))/G12 -> 3728666.7 | I12: =+H12/$E$73 -> 847.08733 | J12: =+H12*G12 -> 100674000 | K12: =+J12/$E$73 -> 22871.358 | L12: =+J12*N12 -> 100674000 | M12: =+L12/$E$73 -> 22871.358 | N12: =+'Detailed Budget'!F9 -> 1 | O12: =+J12*Q12 -> 0 | P12: =+O12/$E$73 -> 0 | Q12: =+'Detailed Budget'!I9 -> 0 | R12: =+'Detailed Budget'!AV9 -> 1 | S12: Business Partner Professional
A13: SUBPRODORG | B13: 89050 | C13: ICFUNDCION | D13: ICFPERBPP | E13: 1.7. Business Partner Professional Antioquia, Córdoba 2 | F13: month | G13: =+'Detailed Budget'!AO10 -> 24 | H13: =+(('Detailed Budget'!D10*'Detailed Budget'!C10)+('Detailed Budget'!Q10*'Detailed Budget'!P10)+('Detailed Budget'!AD10*'Detailed Budget'!AC10))/G13 -> 3675000 | I13: =+H13/$E$73 -> 834.89521 | J13: =+H13*G13 -> 88200000 | K13: =+J13/$E$73 -> 20037.485 | L13: =+J13*N13 -> 88200000 | M13: =+L13/$E$73 -> 20037.485 | N13: =+'Detailed Budget'!F10 -> 1 | O13: =+J13*Q13 -> 0 | P13: =+O13/$E$73 -> 0 | Q13: =+'Detailed Budget'!I10 -> 0 | R13: =+'Detailed Budget'!AV10 -> 1 | S13: Business Partner Professional
A14: SUBPRODORG | B14: 89050 | C14: ICFUNDCION | D14: ICFPERBPP | E14: 1.8. Business Partner Professional Caldas | F14: month | G14: =+'Detailed Budget'!AO11 -> 27 | H14: =+(('Detailed Budget'!D11*'Detailed Budget'!C11)+('Detailed Budget'!Q11*'Detailed Budget'!P11)+('Detailed Budget'!AD11*'Detailed Budget'!AC11))/G14 -> 3728666.7 | I14: =+H14/$E$73 -> 847.08733 | J14: =+H14*G14 -> 100674000 | K14: =+J14/$E$73 -> 22871.358 | L14: =+J14*N14 -> 100674000 | M14: =+L14/$E$73 -> 22871.358 | N14: =+'Detailed Budget'!F11 -> 1 | O14: =+J14*Q14 -> 0 | P14: =+O14/$E$73 -> 0 | Q14: =+'Detailed Budget'!I11 -> 0 | R14: =+'Detailed Budget'!AV11 -> 1 | S14: Business Partner Professional
A15: SUBPRODORG | B15: 89050 | C15: ICFUNDCION | D15: ICFPERBPP | E15: 1.9. Business Partner Professional Guajira, Cesar, Magdalena | F15: month | G15: =+'Detailed Budget'!AO12 -> 27 | H15: =+(('Detailed Budget'!D12*'Detailed Budget'!C12)+('Detailed Budget'!Q12*'Detailed Budget'!P12)+('Detailed Budget'!AD12*'Detailed Budget'!AC12))/G15 -> 3728666.7 | I15: =+H15/$E$73 -> 847.08733 | J15: =+H15*G15 -> 100674000 | K15: =+J15/$E$73 -> 22871.358 | L15: =+J15*N15 -> 100674000 | M15: =+L15/$E$73 -> 22871.358 | N15: =+'Detailed Budget'!F12 -> 1 | O15: =+J15*Q15 -> 0 | P15: =+O15/$E$73 -> 0 | Q15: =+'Detailed Budget'!I12 -> 0 | R15: =+'Detailed Budget'!AV12 -> 1 | S15: Business Partner Professional
A16: SUBPRODORG | B16: 89050 | C16: ICFUNDCION | D16: ICFPERBPP | E16: 1.10. Business Partner Professional Huila | F16: month | G16: =+'Detailed Budget'!AO13 -> 27 | H16: =+(('Detailed Budget'!D13*'Detailed Budget'!C13)+('Detailed Budget'!Q13*'Detailed Budget'!P13)+('Detailed Budget'!AD13*'Detailed Budget'!AC13))/G16 -> 3728666.7 | I16: =+H16/$E$73 -> 847.08733 | J16: =+H16*G16 -> 100674000 | K16: =+J16/$E$73 -> 22871.358 | L16: =+J16*N16 -> 100674000 | M16: =+L16/$E$73 -> 22871.358 | N16: =+'Detailed Budget'!F13 -> 1 | O16: =+J16*Q16 -> 0 | P16: =+O16/$E$73 -> 0 | Q16: =+'Detailed Budget'!I13 -> 0 | R16: =+'Detailed Budget'!AV13 -> 1 | S16: Business Partner Professional
A17: SUBPRODORG | B17: 89050 | C17: ICFUNDCION | D17: ICFPERBPP | E17: 1.11. Business Partner Professional Santander and Bolivar | F17: month | G17: =+'Detailed Budget'!AO14 -> 24 | H17: =+(('Detailed Budget'!D14*'Detailed Budget'!C14)+('Detailed Budget'!Q14*'Detailed Budget'!P14)+('Detailed Budget'!AD14*'Detailed Budget'!AC14))/G17 -> 3675000 | I17: =+H17/$E$73 -> 834.89521 | J17: =+H17*G17 -> 88200000 | K17: =+J17/$E$73 -> 20037.485 | L17: =+J17*N17 -> 88200000 | M17: =+L17/$E$73 -> 20037.485 | N17: =+'Detailed Budget'!F14 -> 1 | O17: =+J17*Q17 -> 0 | P17: =+O17/$E$73 -> 0 | Q17: =+'Detailed Budget'!I14 -> 0 | R17: =+'Detailed Budget'!AV14 -> 1 | S17: Business Partner Professional
A18: SUBPRODORG | B18: 89050 | C18: ICFUNDCION | D18: ICFPERBPP | E18: 1.12. Business Partner Professional Cauca | F18: month | G18: =+'Detailed Budget'!AO15 -> 27 | H18: =+(('Detailed Budget'!D15*'Detailed Budget'!C15)+('Detailed Budget'!Q15*'Detailed Budget'!P15)+('Detailed Budget'!AD15*'Detailed Budget'!AC15))/G18 -> 3728666.7 | I18: =+H18/$E$73 -> 847.08733 | J18: =+H18*G18 -> 100674000 | K18: =+J18/$E$73 -> 22871.358 | L18: =+J18*N18 -> 100674000 | M18: =+L18/$E$73 -> 22871.358 | N18: =+'Detailed Budget'!F15 -> 1 | O18: =+J18*Q18 -> 0 | P18: =+O18/$E$73 -> 0 | Q18: =+'Detailed Budget'!I15 -> 0 | R18: =+'Detailed Budget'!AV15 -> 1 | S18: Business Partner Professional
... A24: SUBPRODORG | B24: 89050 | C24: ICFUNDCION | D24: ICFPERADA | E24: 1.18. Administrative Assistant | F24: month | G24: =+'Detailed Budget'!AO21 -> 28 | H24: =+(('Detailed Budget'!D21*'Detailed Budget'!C21)+('Detailed Budget'!Q21*'Detailed Budget'!P21)+('Detailed Budget'!AD21*'Detailed Budget'!AC21))/G24 -> 2567314.3 | I24: =+H24/$E$73 -> 583.24855 | J24: =+H24*G24 -> 71884800 | K24: =+J24/$E$73 -> 16330.959 | L24: =+J24*N24 -> 71884800 | M24: =+L24/$E$73 -> 16330.959 | N24: =+'Detailed Budget'!F21 -> 1 | O24: =+J24*Q24 -> 0 | P24: =+O24/$E$73 -> 0 | Q24: =+'Detailed Budget'!I21 -> 0 | R24: =+'Detailed Budget'!AV21 -> 1 | S24: Administrative Professiona
E25: 2. Fringe benefits | G25: 0.5829 | J25: =+SUM(J26:J43) -> 9.2212362e+08 | K25: =SUM(K26:K43) -> 209490.23 | L25: =+SUM(L26:L43) -> 8.1647224e+08 | M25: =SUM(M26:M43) -> 185488.1 | O25: =+SUM(O26:O43) -> 1.0565137e+08 | P25: =SUM(P26:P43) -> 24002.129
A26: SUBPRODORG | B26: 89050 | C26: ICFUNDCION | D26: ICFRINPCO | E26: =+E7 -> 1.1. Program Coordinator | F26: Month | G26: =+'Detailed Budget'!AO23 -> 28 | H26: =+(('Detailed Budget'!D23*'Detailed Budget'!C23)+('Detailed Budget'!Q23*'Detailed Budget'!P23)+('Detailed Budget'!AC23*'Detailed Budget'!AD23))/G26 -> 1247072.9 | I26: =+H26/$E$73 -> 283.31298 | J26: =+H26*G26 -> 34918042 | K26: =+J26/$E$73 -> 7932.7635 | L26: =+J26*N26 -> 0 | M26: =+L26/$E$73 -> 0 | N26: =+N7 -> 0 | O26: =+J26*Q26 -> 34918042 | P26: =+O26/$E$73 -> 7932.7635 | Q26: 1 | R26: =+R7 -> 0.2 | S26: By law, social benefits are calculated at 58.29% for personnel affiliated to risk 5, and 51.85% for administrative personnel at risk 1.
A27: SUBPRODORG | B27: 89050 | C27: ICFUNDCION | D27: ICFRINBSC | E27: =+E8 -> 1.2. Business Strengthening Coordinator | F27: Month | G27: =+'Detailed Budget'!AO24 -> 28 | H27: =+(('Detailed Budget'!D24*'Detailed Budget'!C24)+('Detailed Budget'!Q24*'Detailed Budget'!P24)+('Detailed Budget'!AC24*'Detailed Budget'!AD24))/G27 -> 2570217.3 | I27: =+H27/$E$73 -> 583.90805 | J27: =+H27*G27 -> 71966084 | K27: =+J27/$E$73 -> 16349.426 | L27: =+J27*N27 -> 71966084 | M27: =+L27/$E$73 -> 16349.426 | N27: =+N8 -> 1 | O27: =+J27*Q27 -> 0 | P27: =+O27/$E$73 -> 0 | Q27: 0 | R27: =+R8 -> 1
A28: SUBPRODORG | B28: 89050 | C28: ICFUNDCION | D28: ICFRINCTS | E28: =+E9 -> 1.3. Cacao technical specialist | F28: Month | G28: =+'Detailed Budget'!AO25 -> 28 | H28: =+(('Detailed Budget'!D25*'Detailed Budget'!C25)+('Detailed Budget'!Q25*'Detailed Budget'!P25)+('Detailed Budget'!AC25*'Detailed Budget'!AD25))/G28 -> 2570217.3 | I28: =+H28/$E$73 -> 583.90805 | J28: =+H28*G28 -> 71966084 | K28: =+J28/$E$73 -> 16349.426 | L28: =+J28*N28 -> 71966084 | M28: =+L28/$E$73 -> 16349.426 | N28: =+N9 -> 1 | O28: =+J28*Q28 -> 0 | P28: =+O28/$E$73 -> 0 | Q28: 0 | R28: =+R9 -> 1
A29: SUBPRODORG | B29: 89050 | C29: ICFUNDCION | D29: ICFRINORG | E29: =+E10 -> 1.4. Organizational Professional | F29: Month | G29: =+'Detailed Budget'!AO26 -> 28 | H29: =+(('Detailed Budget'!D26*'Detailed Budget'!C26)+('Detailed Budget'!Q26*'Detailed Budget'!P26)+('Detailed Budget'!AC26*'Detailed Budget'!AD26))/G29 -> 1995316.7 | I29: =+H29/$E$73 -> 453.30077 | J29: =+H29*G29 -> 55868867 | K29: =+J29/$E$73 -> 12692.422 | L29: =+J29*N29 -> 41901650 | M29: =+L29/$E$73 -> 9519.3162 | N29: =+N10 -> 0.75 | O29: =+J29*Q29 -> 13967217 | P29: =+O29/$E$73 -> 3173.1054 | Q29: 0.25 | R29: =+R10 -> 0.8
A30: SUBPRODORG | B30: 89050 | C30: ICFUNDCION | D30: ICFRINF&A | E30: =+E11 -> 1.5. F&A Specialist | F30: Month | G30: =+'Detailed Budget'!AO27 -> 28 | H30: =+(('Detailed Budget'!D27*'Detailed Budget'!C27)+('Detailed Budget'!Q27*'Detailed Budget'!P27)+('Detailed Budget'!AC27*'Detailed Budget'!AD27))/G30 -> 1184719.3 | I30: =+H30/$E$73 -> 269.14733 | J30: =+H30*G30 -> 33172140 | K30: =+J30/$E$73 -> 7536.1253 | L30: =+J30*N30 -> 33172140 | M30: =+L30/$E$73 -> 7536.1253 | N30: =+N11 -> 1 | O30: =+J30*Q30 -> 0 | P30: =+O30/$E$73 -> 0 | Q30: 0 | R30: =+R11 -> 0.5
A31: SUBPRODORG | B31: 89050 | C31: ICFUNDCION | D31: ICFRINBPP | E31: =+E12 -> 1.6. Business Partner Professional Antioquia, Córdoba 1 | F31: Month | G31: =+'Detailed Budget'!AO28 -> 27 | H31: =+(('Detailed Budget'!D28*'Detailed Budget'!C28)+('Detailed Budget'!Q28*'Detailed Budget'!P28)+('Detailed Budget'!AC28*'Detailed Budget'!AD28))/G31 -> 2173439.8 | I31: =+H31/$E$73 -> 493.76721 | J31: =+H31*G31 -> 58682875 | K31: =+J31/$E$73 -> 13331.715 | L31: =+J31*N31 -> 58682875 | M31: =+L31/$E$73 -> 13331.715 | N31: =+N12 -> 1 | O31: =+J31*Q31 -> 0 | P31: =+O31/$E$73 -> 0 | Q31: 0 | R31: =+R12 -> 1
A32: SUBPRODORG | B32: 89050 | C32: ICFUNDCION | D32: ICFRINBPP | E32: =+E13 -> 1.7. Business Partner Professional Antioquia, Córdoba 2 | F32: Month | G32: =+'Detailed Budget'!AO29 -> 24 | H32: =+(('Detailed Budget'!D29*'Detailed Budget'!C29)+('Detailed Budget'!Q29*'Detailed Budget'!P29)+('Detailed Budget'!AC29*'Detailed Budget'!AD29))/G32 -> 2142157.5 | I32: =+H32/$E$73 -> 486.66042 | J32: =+H32*G32 -> 51411780 | K32: =+J32/$E$73 -> 11679.85 | L32: =+J32*N32 -> 51411780 | M32: =+L32/$E$73 -> 11679.85 | N32: =+N13 -> 1 | O32: =+J32*Q32 -> 0 | P32: =+O32/$E$73 -> 0 | Q32: 0 | R32: =+R13 -> 1
A33: SUBPRODORG | B33: 89050 | C33: ICFUNDCION | D33: ICFRINBPP | E33: =+E14 -> 1.8. Business Partner Professional Caldas | F33: Month | G33: =+'Detailed Budget'!AO30 -> 27 | H33: =+(('Detailed Budget'!D30*'Detailed Budget'!C30)+('Detailed Budget'!Q30*'Detailed Budget'!P30)+('Detailed Budget'!AC30*'Detailed Budget'!AD30))/G33 -> 2173439.8 | I33: =+H33/$E$73 -> 493.76721 | J33: =+H33*G33 -> 58682875 | K33: =+J33/$E$73 -> 13331.715 | L33: =+J33*N33 -> 58682875 | M33: =+L33/$E$73 -> 13331.715 | N33: =+N14 -> 1 | O33: =+J33*Q33 -> 0 | P33: =+O33/$E$73 -> 0 | Q33: 0 | R33: =+R14 -> 1
A34: SUBPRODORG | B34: 89050 | C34: ICFUNDCION | D34: ICFRINBPP | E34: =+E15 -> 1.9. Business Partner Professional Guajira, Cesar, Magdalena | F34: Month | G34: =+'Detailed Budget'!AO31 -> 27 | H34: =+(('Detailed Budget'!D31*'Detailed Budget'!C31)+('Detailed Budget'!Q31*'Detailed Budget'!P31)+('Detailed Budget'!AC31*'Detailed Budget'!AD31))/G34 -> 2173439.8 | I34: =+H34/$E$73 -> 493.76721 | J34: =+H34*G34 -> 58682875 | K34: =+J34/$E$73 -> 13331.715 | L34: =+J34*N34 -> 58682875 | M34: =+L34/$E$73 -> 13331.715 | N34: =+N15 -> 1 | O34: =+J34*Q34 -> 0 | P34: =+O34/$E$73 -> 0 | Q34: 0 | R34: =+R15 -> 1
A35: SUBPRODORG | B35: 89050 | C35: ICFUNDCION | D35: ICFRINBPP | E35: =+E16 -> 1.10. Business Partner Professional Huila | F35: Month | G35: =+'Detailed Budget'!AO32 -> 27 | H35: =+(('Detailed Budget'!D32*'Detailed Budget'!C32)+('Detailed Budget'!Q32*'Detailed Budget'!P32)+('Detailed Budget'!AC32*'Detailed Budget'!AD32))/G35 -> 2173439.8 | I35: =+H35/$E$73 -> 493.76721 | J35: =+H35*G35 -> 58682875 | K35: =+J35/$E$73 -> 13331.715 | L35: =+J35*N35 -> 58682875 | M35: =+L35/$E$73 -> 13331.715 | N35: =+N16 -> 1 | O35: =+J35*Q35 -> 0 | P35: =+O35/$E$73 -> 0 | Q35: 0 | R35: =+R16 -> 1
A36: SUBPRODORG | B36: 89050 | C36: ICFUNDCION | D36: ICFRINBPP | E36: =+E17 -> 1.11. Business Partner Professional Santander and Bolivar | F36: Month | G36: =+'Detailed Budget'!AO33 -> 24 | H36: =+(('Detailed Budget'!D33*'Detailed Budget'!C33)+('Detailed Budget'!Q33*'Detailed Budget'!P33)+('Detailed Budget'!AC33*'Detailed Budget'!AD33))/G36 -> 2142157.5 | I36: =+H36/$E$73 -> 486.66042 | J36: =+H36*G36 -> 51411780 | K36: =+J36/$E$73 -> 11679.85 | L36: =+J36*N36 -> 51411780 | M36: =+L36/$E$73 -> 11679.85 | N36: =+N17 -> 1 | O36: =+J36*Q36 -> 0 | P36: =+O36/$E$73 -> 0 | Q36: 0 | R36: =+R17 -> 1
A37: SUBPRODORG | B37: 89050 | C37: ICFUNDCION | D37: ICFRINBPP | E37: =+E18 -> 1.12. Business Partner Professional Cauca | F37: Month | G37: =+'Detailed Budget'!AO34 -> 27 | H37: =+(('Detailed Budget'!D34*'Detailed Budget'!C34)+('Detailed Budget'!Q34*'Detailed Budget'!P34)+('Detailed Budget'!AC34*'Detailed Budget'!AD34))/G37 -> 2173439.8 | I37: =+H37/$E$73 -> 493.76721 | J37: =+H37*G37 -> 58682875 | K37: =+J37/$E$73 -> 13331.715 | L37: =+J37*N37 -> 58682875 | M37: =+L37/$E$73 -> 13331.715 | N37: =+N18 -> 1 | O37: =+J37*Q37 -> 0 | P37: =+O37/$E$73 -> 0 | Q37: 0 | R37: =+R18 -> 1
A38: SUBPRODORG | B38: 89050 | C38: ICFUNDCION | D38: ICFRINBPP | E38: =+E19 -> 1.13. Business Partner Professional Tolima 1 | F38: Month | G38: =+'Detailed Budget'!AO35 -> 27 | H38: =+(('Detailed Budget'!D35*'Detailed Budget'!C35)+('Detailed Budget'!Q35*'Detailed Budget'!P35)+('Detailed Budget'!AC35*'Detailed Budget'!AD35))/G38 -> 2173439.8 | I38: =+H38/$E$73 -> 493.76721 | J38: =+H38*G38 -> 58682875 | K38: =+J38/$E$73 -> 13331.715 | L38: =+J38*N38 -> 58682875 | M38: =+L38/$E$73 -> 13331.715 | N38: =+N19 -> 1 | O38: =+J38*Q38 -> 0 | P38: =+O38/$E$73 -> 0 | Q38: 0 | R38: =+R19 -> 1
... A43: SUBPRODORG | B43: 89050 | C43: ICFUNDCION | D43: ICFRINADA | E43: =+E24 -> 1.18. Administrative Assistant | F43: Month | G43: =+'Detailed Budget'!AO40 -> 28 | H43: =+(('Detailed Budget'!D40*'Detailed Budget'!C40)+('Detailed Budget'!Q40*'Detailed Budget'!P40)+('Detailed Budget'!AC40*'Detailed Budget'!AD40))/G43 -> 1331152.5 | I43: =+H43/$E$73 -> 302.41437 | J43: =+H43*G43 -> 37272269 | K43: =+J43/$E$73 -> 8467.6024 | L43: =+J43*N43 -> 37272269 | M43: =+L43/$E$73 -> 8467.6024 | N43: =+N24 -> 1 | O43: =+J43*Q43 -> 0 | P43: =+O43/$E$73 -> 0 | Q43: 0 | R43: =+R24 -> 1
E44: 3. Travel costs | J44: =+SUM(J45:J48) -> 288300000 | K44: =SUM(K45:K48) -> 65496.677 | L44: =+SUM(L45:L48) -> 288300000 | M44: =SUM(M45:M48) -> 65496.677 | O44: =+SUM(O45:O48) -> 0 | P44: =SUM(P45:P48) -> 0
A45: SUBPRODORG | B45: 89050 | C45: ICFUNDCION | D45: ICFAIR | E45: 3.1. Air transportation | F45: round trip | G45: =('Detailed Budget'!C42+'Detailed Budget'!P42+'Detailed Budget'!AC42) -> 51 | H45: ='Detailed Budget'!D42 -> 1000000 | I45: =+H45/$E$73 -> 227.18237 | J45: =+G45*H45 -> 51000000 | K45: =+J45/$E$73 -> 11586.301 | L45: =+J45*N45 -> 51000000 | M45: =+L45/$E$73 -> 11586.301 | N45: 1 | O45: =+J45*Q45 -> 0 | P45: =+O45/$E$73 -> 0 | Q45: 0 | S45: Average cost of travel for the project coordinator, strengthening coordinator, cocoa specialist, organizational specialist and A&F professional. For more details on travel, see the "Workshops and Travel" sheet.
A46: SUBPRODORG | B46: 89050 | C46: ICFUNDCION | D46: ICFTRANS | E46: 3.2. Land transportation | F46: trip | G46: =('Detailed Budget'!C43+'Detailed Budget'!P43+'Detailed Budget'!AC43) -> 375 | H46: ='Detailed Budget'!D43 -> 150000 | I46: =+H46/$E$73 -> 34.077356 | J46: =+G46*H46 -> 56250000 | K46: =+J46/$E$73 -> 12779.008 | L46: =+J46*N46 -> 56250000 | M46: =+L46/$E$73 -> 12779.008 | N46: 1 | O46: =+J46*Q46 -> 0 | P46: =+O46/$E$73 -> 0 | Q46: 0 | S46: Average cost of ground transportation to carry out project activities, this cost was calculated for project personnel. For more details on travel, see the "Workshops and Travel" sheet.
A47: SUBPRODORG | B47: 89050 | C47: ICFUNDCION | D47: IFCLODGING | E47: 3.3. Lodging | F47: ninghts lodging | G47: =('Detailed Budget'!C44+'Detailed Budget'!P44+'Detailed Budget'!AC44) -> 852 | H47: ='Detailed Budget'!D44 -> 100000 | I47: =+H47/$E$73 -> 22.718237 | J47: =+G47*H47 -> 85200000 | K47: =+J47/$E$73 -> 19355.938 | L47: =+J47*N47 -> 85200000 | M47: =+L47/$E$73 -> 19355.938 | N47: 1 | O47: =+J47*Q47 -> 0 | P47: =+O47/$E$73 -> 0 | Q47: 0 | S47: Average cost of lodging to carry out project activities, this cost was calculated for project staff. For more details on travel, see the "Workshops and Travel" sheet.
A48: SUBPRODORG | B48: 89050 | C48: ICFUNDCION | D48: IFCPERDIEM | E48: 3.4. Perdiem | F48: day | G48: =('Detailed Budget'!C45+'Detailed Budget'!P45+'Detailed Budget'!AC45) -> 1065 | H48: ='Detailed Budget'!D45 -> 90000 | I48: =+H48/$E$73 -> 20.446413 | J48: =+G48*H48 -> 95850000 | K48: =+J48/$E$73 -> 21775.43 | L48: =+J48*N48 -> 95850000 | M48: =+L48/$E$73 -> 21775.43 | N48: 1 | O48: =+J48*Q48 -> 0 | P48: =+O48/$E$73 -> 0 | Q48: 0 | S48: Average cost of food to carry out project activities, this cost was calculated for project staff. For more details on travel, see the "Workshops and Travel" sheet.
E49: 4. Professional services (consultants) | J49: =+SUM(J50:J52) -> 662000000 | K49: =SUM(K50:K52) -> 150394.73 | L49: =+SUM(L50:L52) -> 599000000 | M49: =SUM(M50:M52) -> 136082.24 | O49: =+SUM(O50:O51) -> 63000000 | P49: =SUM(P50:P52) -> 14312.489
A50: SUBPRODORG | B50: 89050 | C50: ICFUNDCION | D50: ICFDEVPROD | E50: 4.1. Development of cacao and complementary products business models / Muttuo | F50: product | G50: ='Detailed Budget'!C47+'Detailed Budget'!P47 -> 2 | H50: ='Detailed Budget'!D47 -> 283500000 | I50: =+H50/$E$73 -> 64406.202 | J50: =+G50*H50 -> 567000000 | K50: =+J50/$E$73 -> 128812.4 | L50: =+J50*N50 -> 567000000 | M50: =+L50/$E$73 -> 128812.4 | N50: 1 | O50: =+J50*Q50 -> 0 | P50: =+O50/$E$73 -> 0 | Q50: 0 | S50: Value of consultancies required for A. Development of marketing models for cocoa and for B. Development of marketing models for substitute products". The calculated cost is estimated according to consultancies contracted by IC in other strengthening processes.
A51: SUBPRODORG | B51: 89050 | C51: ICFUNDCION | D51: ICFASSESS | E51: 4.2. Financial feasibility assessments | F51: evaluation | G51: ='Detailed Budget'!P48 -> 15 | H51: ='Detailed Budget'!Q48 -> 4200000 | I51: =+H51/$E$73 -> 954.16596 | J51: =+G51*H51 -> 63000000 | K51: =+J51/$E$73 -> 14312.489 | L51: =+J51*N51 -> 0 | M51: =+L51/$E$73 -> 0 | N51: 0 | O51: =+J51*Q51 -> 63000000 | P51: =+O51/$E$73 -> 14312.489 | Q51: 1 | S51: Counterpart. Value of the credit structures developed by IC Fundación.
A52: SUBPRODORG | B52: 89050 | C52: ICFUNDCION | D52: ICFCONSULT | E52: 4.3. Business consulting (marketing, communications, quality, processes, invoicing) | F52: consulting | G52: ='Detailed Budget'!P49 -> 10 | H52: =+'Detailed Budget'!Q49 -> 3200000 | I52: =+H52/$E$73 -> 726.98359 | J52: =+G52*H52 -> 32000000 | K52: =+J52/$E$73 -> 7269.8359 | L52: =+J52*N52 -> 32000000 | M52: =+L52/$E$73 -> 7269.8359 | N52: 1 | O52: =+J52*Q52 -> 0 | P52: =+O52/$E$73 -> 0 | Q52: 0 | S52: Amount to hire specific consultancies to support business strengthening processes (branding, labels, web page, advice on good quality practices, quality analysis, SGSST, etc.).
E53: 5. Supplies | J53: =+SUM(J54) -> 73148400 | K53: =SUM(K54) -> 16618.027 | L53: =+SUM(L54) -> 73148400 | M53: =SUM(M54) -> 16618.027 | O53: =+SUM(O54) -> 0 | P53: =SUM(P54) -> 0
A54: SUBPRODORG | B54: 89050 | C54: ICFUNDCION | D54: ICFSUPPLY | E54: 5.1. Laptop rental x 13 | F54: month | G54: =('Detailed Budget'!C51+'Detailed Budget'!P51+'Detailed Budget'!AC51) -> 28 | H54: =+('Detailed Budget'!L51+'Detailed Budget'!Y51+'Detailed Budget'!AL51)/G54 -> 2612442.9 | I54: =+H54/$E$73 -> 593.50096 | J54: =+G54*H54 -> 73148400 | K54: =+J54/$E$73 -> 16618.027 | L54: =+'Detailed Budget'!AR51 -> 73148400 | M54: =+L54/$E$73 -> 16618.027 | N54: 0.8 | O54: =+'Detailed Budget'!AT51 -> 0 | P54: =+O54/$E$73 -> 0 | Q54: =+O54/J54 -> 0 | S54: Average cost of computer equipment rental that will be provided to staff members to carry out their activities. 13 computers for 28 months.
E55: 6. Direct operating costs | J55: =+SUM(J56:J61) -> 1350930000 | K55: =SUM(K56:K61) -> 306907.48 | L55: =+SUM(L56:L61) -> 106930000 | M55: =SUM(M56:M61) -> 24292.611 | O55: =+SUM(O56:O61) -> 1244000000 | P55: =SUM(P56:P61) -> 282614.87
A56: SUBPRODORG | B56: 89050 | C56: ICFUNDCION | D56: ICFDIAREF | E56: 6.1. Diagnostic workshop refreshments (snacks and lunches) | F56: workshop | G56: =+Travels!B41 -> 74 | H56: =+Travels!D41*Travels!C41 -> 390000 | I56: =+H56/$E$73 -> 88.601125 | J56: =+G56*H56 -> 28860000 | K56: =+J56/$E$73 -> 6556.4832 | L56: =+J56*N56 -> 28860000 | M56: =+L56/$E$73 -> 6556.4832 | N56: 1 | O56: =+J56*Q56 -> 0 | P56: =+O56/$E$73 -> 0 | Q56: 0 | S56: The value in reference corresponds to the average price of refreshments and lunch in the area. An average of 74 workshops, one for each organization, average number of attendees per workshop is 10 people.
A57: SUBPRODORG | B57: 89050 | C57: ICFUNDCION | D57: ICFDIAMATL | E57: 6.2. Diagnostic workshop materials (stationery: cardboard, markers, cards, etc.) | F57: workshop | G57: =+Travels!B42 -> 74 | H57: =+Travels!D42*Travels!C42 -> 35000 | I57: =+H57/$E$73 -> 7.951383 | J57: =+G57*H57 -> 2590000 | K57: =+J57/$E$73 -> 588.40234 | L57: =+J57*N57 -> 2590000 | M57: =+L57/$E$73 -> 588.40234 | N57: 1 | O57: =+J57*Q57 -> 0 | P57: =+O57/$E$73 -> 0 | Q57: 0 | S57: Estimated average value that includes material for the workshops. An average of 74 workshops for each organization, average number of attendees per workshop 10 people.
A58: SUBPRODORG | B58: 89050 | C58: ICFUNDCION | D58: ICFREFRESH | E58: 6.3. Strengthening workshop refreshments (snacks and lunches) | F58: workshop | G58: =+Travels!B43 -> 222 | H58: =+Travels!D43*Travels!C43 -> 312000 | I58: =+H58/$E$73 -> 70.8809 | J58: =+G58*H58 -> 69264000 | K58: =+J58/$E$73 -> 15735.56 | L58: =+J58*N58 -> 69264000 | M58: =+L58/$E$73 -> 15735.56 | N58: 1 | O58: =+J58*Q58 -> 0 | P58: =+O58/$E$73 -> 0 | Q58: 0 | S58: The value in reference corresponds to the average price of refreshments and lunch in the area. Average 222 workshops three for each organization, average number of attendees per workshop 8 persons.
A59: SUBPRODORG | B59: 89050 | C59: ICFUNDCION | D59: ICFSTRMATL | E59: 6.4. Strengthening workshop materials (stationery: cardboard, markers, cards, etc.) | F59: workshop | G59: =+Travels!B44 -> 222 | H59: =+Travels!D44*Travels!C44 -> 28000 | I59: =+H59/$E$73 -> 6.3611064 | J59: =+G59*H59 -> 6216000 | K59: =+J59/$E$73 -> 1412.1656 | L59: =+J59*N59 -> 6216000 | M59: =+L59/$E$73 -> 1412.1656 | N59: 1 | O59: =+J59*Q59 -> 0 | P59: =+O59/$E$73 -> 0 | Q59: 0 | S59: Estimated average value that includes material for the workshops. Average 222 workshops 3 for each organization. Average number of attendees per workshop 8 people.
A60: SUBPRODORG | B60: 89050 | C60: ICFUNDCION | D60: ICFCAPITAL | E60: 6.5. Credit Resources/Working Capital | F60: global | G60: =+'Detailed Budget'!P57+'Detailed Budget'!AC57 -> 1 | H60: ='Detailed Budget'!Q57 -> 800000000 | I60: =+H60/$E$73 -> 181745.9 | J60: =+G60*H60 -> 800000000 | K60: =+J60/$E$73 -> 181745.9 | L60: =+J60*N60 -> 0 | M60: =+L60/$E$73 -> 0 | N60: 0 | O60: =+J60*Q60 -> 800000000 | P60: =+O60/$E$73 -> 181745.9 | Q60: 1 | S60: Amount available to make loans to some prioritized organizations with capital needs.
A61: SUBPRODORG | B61: 89050 | C61: ICFUNDCION | D61: ICFCAPBUIL | E61: 6.6. IC Fundación-owned producer organization capacity building tools and methodologies (workshop guides, support tools, etc) | F61: asociation | G61: ='Detailed Budget'!C58 -> 74 | H61: =('Detailed Budget'!D58+'Detailed Budget'!Q58+'Detailed Budget'!AD58) -> 6000000 | I61: =+H61/$E$73 -> 1363.0942 | J61: =+G61*H61 -> 444000000 | K61: =+J61/$E$73 -> 100868.97 | L61: =+J61*N61 -> 0 | M61: =+L61/$E$73 -> 0 | N61: 0 | O61: =+J61*Q61 -> 444000000 | P61: =+O61/$E$73 -> 100868.97 | Q61: 1 | S61: Value of IC Foundation's methodology and tools (6 million x partnership for the duration of the project).
E62: 7. Office expenses | J62: =SUM(J63:J67) -> 48721232 | K62: =SUM(K63:K67) -> 11068.605 | L62: =SUM(L63:L67) -> 48721232 | M62: =SUM(M63:M67) -> 11068.605 | O62: =SUM(O63:O67) -> 0 | P62: =SUM(P63:P67) -> 0
A63: SUBPRODORG | B63: 89050 | C63: ICFUNDCION | D63: ICFRECRUIT | E63: 7.1. Staff recruitment assessments (medical exams, remote work visit, etc) | F63: new staff | G63: =+'Detailed Budget'!C60 -> 5 | H63: ='Detailed Budget'!D60 -> 700000 | I63: =+H63/$E$73 -> 159.02766 | J63: =+G63*H63 -> 3500000 | K63: =+J63/$E$73 -> 795.1383 | L63: =+J63*N63 -> 3500000 | M63: =+L63/$E$73 -> 795.1383 | N63: 1 | O63: =+J63*Q63 -> 0 | P63: =+O63/$E$73 -> 0 | Q63: 0 | S63: Average cost necessary for the hiring process of 11 professionals (home visit, background validation, reference validation, entrance exam, etc.).
A64: SUBPRODORG | B64: 89050 | C64: ICFUNDCION | D64: ICFBANKEX | E64: 7.2. Financial/bank expenses | F64: month | G64: =('Detailed Budget'!C61+'Detailed Budget'!P61+'Detailed Budget'!AC61) -> 28 | H64: =+('Detailed Budget'!L61+'Detailed Budget'!Y61+'Detailed Budget'!AL61)/G64 -> 320914.29 | I64: =+H64/$E$73 -> 72.906068 | J64: =+G64*H64 -> 8985600 | K64: =+J64/$E$73 -> 2041.3699 | L64: =+J64*N64 -> 8985600 | M64: =+L64/$E$73 -> 2041.3699 | N64: 1 | O64: =+J64*Q64 -> 0 | P64: =+O64/$E$73 -> 0 | Q64: 0 | S64: Average cost of expenses for commissions generated in the monetization of resources and financial transactions for the development of the activity.
A65: SUBPRODORG | B65: 89050 | C65: ICFUNDCION | D65: ICFADOBE | E65: 7.3. Adobe Acrobat licence | F65: license | G65: ='Detailed Budget'!C62 -> 3 | H65: =+'Detailed Budget'!D62 -> 1000000 | I65: =+H65/$E$73 -> 227.18237 | J65: =+G65*H65 -> 3000000 | K65: =+J65/$E$73 -> 681.54711 | L65: =+J65*N65 -> 3000000 | M65: =+L65/$E$73 -> 681.54711 | N65: 1 | O65: =+J65*Q65 -> 0 | P65: =+O65/$E$73 -> 0 | Q65: 0 | S65: The licenses will be used for the equipment of the project coordinator, C4D agreement coordinator and administrative assistant. The licenses are necessary for the proper management of the documentation that supports the execution of the project.
A66: SUBPRODORG | B66: 89050 | C66: ICFUNDCION | D66: ICFLICENSE | E66: 7.4. Office and antivirus license 13 computers | F66: month | G66: =('Detailed Budget'!C63+'Detailed Budget'!P63+'Detailed Budget'!AC63) -> 28 | H66: =+J66/G66 -> 940479.43 | I66: =+H66/$E$73 -> 213.66035 | J66: =+'Detailed Budget'!AP63 -> 26333424 | K66: =+J66/$E$73 -> 5982.4897 | L66: =+'Detailed Budget'!AR63 -> 26333424 | M66: =+L66/$E$73 -> 5982.4897 | N66: =+L66/J66 -> 1 | O66: =+'Detailed Budget'!AT63 -> 0 | P66: =+O66/$E$73 -> 0 | Q66: =+O66/J66 -> 0 | S66: The office and antivirus licenses will be purchased for the C4D team's computers to ensure proper operation of the 18 computers.
A67: SUBPRODORG | B67: 89050 | C67: ICFUNDCION | D67: ICFLIFEIN | E67: 7.5. Life insurance * 13 | F67: month | G67: =+'Detailed Budget'!C64+'Detailed Budget'!P64+'Detailed Budget'!AC64 -> 28 | H67: =+'Detailed Budget'!AP64/'Summary Budget'!G67 -> 246507.43 | I67: =+H67/$E$73 -> 56.002142 | J67: =+G67*H67 -> 6902208 | K67: =+J67/$E$73 -> 1568.06 | L67: =+'Detailed Budget'!AR64 -> 6902208 | M67: =+L67/$E$73 -> 1568.06 | N67: =+L67/J67 -> 1 | O67: =+'Detailed Budget'!AT64 -> 0 | P67: =+O67/$E$73 -> 0 | Q67: =+O67/J67 -> 0 | S67: Life insurance must be purchased for all IC Foundation employees, which will cover them for a value of $100,000,000.
A68: SUBPRODORG | B68: 89050 | C68: ICFUNDCION | D68: ICFIDC | E68: Administrative expenses | F68: % | G68: ='Detailed Budget'!C65 -> 0.05 | J68: ='Detailed Budget'!AP65 -> 2.4758348e+08 | K68: =+J68/$E$73 -> 56246.601 | L68: =+J68*N68 -> 1.6755743e+08 | M68: =+L68/E73 -> 38066.094 | N68: =+'Detailed Budget'!F67 -> 0.67677145 | O68: =+'Detailed Budget'!AT65 -> 80026049 | P68: =+O68/$E$73 -> 18180.507 | Q68: ='Detailed Budget'!I65 -> 0 | S68: Indirect costs established by IC Fundación at a fixed percentage of 5%. Indirect costs include: statutory audit, SGSST, general management, utilities and leasing, internet, telephony, legal services.
E69: Total proposal COP | J69: =+SUM(J6,J68,J55,J53,J49,J44,J25+J62) -> 5.199253e+09 | K69: =+K6+K25+K44+K49+K53+K55+K68+K62 -> 1181178.6 | Q69: 0
E70: Total contribution C4D | L70: =+L55+L53+L49+L44+L25+L6+L68+L62 -> 3.518706e+09 | M70: =+M6+M25+M44+M49+M53+M55+M68+M62 -> 799387.97 | N70: =+L70/J69 -> 0.67677145 | Q70: 0
E71: Total Cost - Share | O71: =+O6+O25+O44+O49+O53+O55+O68 -> 1.680547e+09 | P71: =+P6+P25+P44+P49+P53+P55+P65+P68 -> 381790.66 | Q71: =+O71/J69 -> 0.32322855
E72: OANDA 1 June
E73: 4401.75

Sheet NM
D3: Initial C4D COP | E3: Initial C4D USD | F3: Cost Share Initial COP | G3: Cost Share Initial USD | H3: Final C4D COP | I3: Final C4D USD | J3: Cost Share Final COP | K3: Cost Share Final USD
C4: 1.Personnel | D4: 1398311640 | E4: =+D4/$C$13 -> 317671.75 | F4: 26529600 | G4: =+F4/$C$13 -> 6027.0574 | H4: ='Summary Budget'!L6 -> 1418576688 | I4: =+H4/$C$13 -> 322275.61 | J4: =+'Summary Budget'!O6 -> 187869600 | K4: =+J4/$C$13 -> 42680.661
C5: 2. Fringe benefits | D5: 6.2630378e+08 | E5: =+D5/$C$13 -> 142285.18 | F5: 11882608 | G5: =+F5/$C$13 -> 2699.519 | H5: ='Summary Budget'!L25 -> 8.1647224e+08 | I5: =+H5/$C$13 -> 185488.1 | J5: =+'Summary Budget'!O25 -> 1.0565137e+08 | K5: =+J5/$C$13 -> 24002.129
C6: 3. Trips | D6: 307650000 | E6: =+D6/$C$13 -> 69892.656 | G6: =+F6/$C$13 -> 0 | H6: ='Summary Budget'!L44 -> 288300000 | I6: =+H6/$C$13 -> 65496.677 | J6: =+'Summary Budget'!O44 -> 0 | K6: =+J6/$C$13 -> 0
C7: 4. Professional services (consultants) | D7: 630000000 | E7: =+D7/$C$13 -> 143124.89 | F7: 63000000 | G7: =+F7/$C$13 -> 14312.489 | H7: ='Summary Budget'!L49 -> 599000000 | I7: =+H7/$C$13 -> 136082.24 | J7: =+'Summary Budget'!O49 -> 63000000 | K7: =+J7/$C$13 -> 14312.489
C8: 5. Materials | D8: 106930000 | E8: =+D8/$C$13 -> 24292.611 | G8: =+F8/$C$13 -> 0 | H8: ='Summary Budget'!L53 -> 73148400 | I8: =+H8/$C$13 -> 16618.027 | J8: =+'Summary Budget'!O53 -> 0 | K8: =+J8/$C$13 -> 0
C9: 6. Direct operating costs | D9: 2.9846531e+08 | E9: =+D9/$C$13 -> 67806.057 | F9: 1.7284191e+09 | G9: =+F9/$C$13 -> 392666.35 | H9: =+'Summary Budget'!L55 -> 106930000 | I9: =+H9/$C$13 -> 24292.611 | J9: =+'Summary Budget'!O55 -> 1244000000 | K9: =+J9/$C$13 -> 282614.87
C10: Administrative expenses | D10: 1.7833871e+08 | E10: =+D10/$C$13 -> 40515.411 | F10: 66877016 | G10: =+F10/$C$13 -> 15193.279 | H10: ='Summary Budget'!L68 -> 1.6755743e+08 | I10: =+H10/$C$13 -> 38066.094 | J10: =+'Summary Budget'!O68 -> 80026049 | K10: =+J10/$C$13 -> 18180.507
D11: =SUM(D4:D10) -> 3.5459994e+09 | E11: =SUM(E4:E10) -> 805588.56 | F11: =SUM(F4:F10) -> 1.8967083e+09 | G11: =SUM(G4:G10) -> 430898.69 | H11: =SUM(H4:H10) -> 3.4699848e+09 | I11: =SUM(I4:I10) -> 788319.36 | J11: =SUM(J4:J10) -> 1.680547e+09 | K11: =SUM(K4:K10) -> 381790.66
C12: Tasa Oanda
C13: 4401.75

Sheet Detailed Budget
A1: 4401.75 | B1: Year 1 | O1: Year 2 | AB1: Year 3
A2: Item | B2: Unit | C2: # of units | D2: Unit Value COP | E2: Unit Value USD | F2: % C4D | G2: C4D Contribution COP | H2: Contribution C4D USD | I2: % IC Cost - Share | J2: Cotribution IC Cost - Share / COP | K2: Cotribution IC Cost - Share / USD | L2: Total Value COP | M2: Total Value USD | O2: Unit | P2: # of units | Q2: Unit Value COP | R2: Unit Value USD | S2: % C4D | T2: C4D Contribution COP | U2: Contribution C4D USD | V2: % IC Cost - Share | W2: Cotribution IC Cost - Share / COP | X2: Cotribution IC Cost - Share / USD | Y2: Total Value COP | Z2: Total Value USD | AB2: Unit | AC2: # of units | AD2: Unit Value COP | AE2: Unit Value USD | AF2: % C4D | AG2: C4D Contribution COP | AH2: Contribution C4D USD | AI2: % IC Cost - Share | AJ2: Cotribution IC Cost - Share / COP | AK2: Cotribution IC Cost - Share / USD | AL2: Total Value COP | AM2: Total Value USD | AO2: Totals Qts. | AP2: Total budget COP | AQ2: Total budget USD | AR2: Total C4D COP | AS2: Total C4D USD | AT2: Total contribution IC Cost - Share / COP | AU2: Total contribution IC Cost - Share / USD | AV2: Level of Effort (LOE) | AW2: Value of base salary COP | AX2: Value of base salary USD
A3: =+'Summary Budget'!E6 -> 1.Personal (Laboral) | G3: =SUM(G4:G21) -> 593328000 | H3: =SUM(H4:H21) -> 134793.66 | J3: =SUM(J4:J21) -> 78600000 | K3: =SUM(K4:K21) -> 17856.534 | L3: =+SUM(L4:L21) -> 671928000 | M3: =SUM(M4:M21) -> 152650.2 | T3: =+SUM(T4:T21) -> 652660800 | U3: =SUM(U4:U21) -> 148273.03 | W3: =+SUM(W4:W21) -> 86460000 | X3: =SUM(X4:X21) -> 19642.188 | Y3: =+SUM(Y4:Y21) -> 739120800 | Z3: =SUM(Z4:Z21) -> 167915.22 | AG3: =SUM(AG4:AG21) -> 172587888 | AH3: =SUM(AH4:AH21) -> 39208.926 | AJ3: =SUM(AJ4:AJ21) -> 22809600 | AK3: =SUM(AK4:AK21) -> 5181.939 | AL3: =+SUM(AL4:AL21) -> 195397488 | AM3: =SUM(AM4:AM21) -> 44390.865 | AP3: =+SUM(AP4:AP21) -> 1606446288 | AQ3: =SUM(AQ4:AQ21) -> 364956.28 | AR3: =+SUM(AR4:AR21) -> 1418576688 | AS3: =SUM(AS4:AS21) -> 322275.61 | AT3: =+SUM(AT4:AT21) -> 187869600 | AU3: =SUM(AU4:AU21) -> 42680.661
A4: =+'Summary Budget'!E7 -> 1.1. Program Coordinator | B4: month | C4: 12 | D4: =+AW4*AV4 -> 2000000 | E4: =+D4/$A$1 -> 454.36474 | F4: 0 | G4: =L4*F4 -> 0 | H4: =+G4/$A$1 -> 0 | I4: 1 | J4: =L4*I4 -> 24000000 | K4: =+J4/$A$1 -> 5452.3769 | L4: =+D4*C4 -> 24000000 | M4: =+L4/$A$1 -> 5452.3769 | O4: mes | P4: 12 | Q4: =+D4*(1+10%) -> 2200000 | R4: =+Q4/$A$1 -> 499.80122 | S4: 0 | T4: =+S4*Y4 -> 0 | U4: =+T4/$A$1 -> 0 | V4: 1 | W4: =+V4*Y4 -> 26400000 | X4: =+W4/$A$1 -> 5997.6146 | Y4: =+Q4*P4 -> 26400000 | Z4: =+Y4/$A$1 -> 5997.6146 | AB4: mes | AC4: 4 | AD4: =+Q4*(1+8%) -> 2376000 | AE4: =+AD4/$A$1 -> 539.78531 | AF4: 0 | AG4: =+AF4*AL4 -> 0 | AH4: =+AG4/$A$1 -> 0 | AI4: 1 | AJ4: =+AI4*AL4 -> 9504000 | AK4: =+AJ4/$A$1 -> 2159.1413 | AL4: =+AD4*AC4 -> 9504000 | AM4: =+AL4/$A$1 -> 2159.1413 | AO4: =+SUM(AC4+P4+C4) -> 28 | AP4: =+L4+Y4+AL4 -> 59904000 | AQ4: =+AP4/$A$1 -> 13609.133 | AR4: =+AP4*F4 -> 0 | AS4: =+AR4/$A$1 -> 0 | AT4: =+AP4*I4 -> 59904000 | AU4: =+AT4/$A$1 -> 13609.133 | AV4: 0.2 | AW4: 10000000 | AX4: =+AW4/$A$1 -> 2271.8237 | BA4: =+L4 -> 24000000 | BB4: =+Y4 -> 26400000 | BC4: =+AL4 -> 9504000 | BH4: =+AR4+AT4-AP4 -> 0
A5: =+'Summary Budget'!E8 -> 1.2. Business Strengthening Coordinator | B5: month | C5: 12 | D5: =+AW5*AV5 -> 4122000 | E5: =+D5/$A$1 -> 936.44573 | F5: 1 | G5: =L5*F5 -> 49464000 | H5: =+G5/$A$1 -> 11237.349 | I5: 0 | J5: =L5*I5 -> 0 | K5: =+J5/$A$1 -> 0 | L5: =+D5*C5*AV5 -> 49464000 | M5: =+L5/$A$1 -> 11237.349 | O5: mes | P5: 12 | Q5: =+D5*(1+10%) -> 4534200 | R5: =+Q5/$A$1 -> 1030.0903 | S5: 1 | T5: =+S5*Y5 -> 54410400 | U5: =+T5/$A$1 -> 12361.084 | V5: 0 | W5: =+V5*Y5 -> 0 | X5: =+W5/$A$1 -> 0 | Y5: =+Q5*P5 -> 54410400 | Z5: =+Y5/$A$1 -> 12361.084 | AB5: mes | AC5: 4 | AD5: =+Q5*(1+8%) -> 4896936 | AE5: =+AD5/$A$1 -> 1112.4975 | AF5: 1 | AG5: =+AF5*AL5 -> 19587744 | AH5: =+AG5/$A$1 -> 4449.9901 | AI5: 0 | AJ5: =+AI5*AL5 -> 0 | AK5: =+AJ5/$A$1 -> 0 | AL5: =+AD5*AC5 -> 19587744 | AM5: =+AL5/$A$1 -> 4449.9901 | AO5: =+SUM(AC5+P5+C5) -> 28 | AP5: =+L5+Y5+AL5 -> 123462144 | AQ5: =+AP5/$A$1 -> 28048.423 | AR5: =+AP5*F5 -> 123462144 | AS5: =+AR5/$A$1 -> 28048.423 | AT5: =+AP5*I5 -> 0 | AU5: =+AT5/$A$1 -> 0 | AV5: 1 | AW5: 4122000 | AX5: =+AW5/$A$1 -> 936.44573 | BH5: =+AR5+AT5-AP5 -> 0
A6: =+'Summary Budget'!E9 -> 1.3. Cacao technical specialist | B6: month | C6: 12 | D6: =+AW6*AV6 -> 4122000 | E6: =+D6/$A$1 -> 936.44573 | F6: 1 | G6: =L6*F6 -> 49464000 | H6: =+G6/$A$1 -> 11237.349 | I6: 0 | J6: =L6*I6 -> 0 | K6: =+J6/$A$1 -> 0 | L6: =+D6*C6*AV6 -> 49464000 | M6: =+L6/$A$1 -> 11237.349 | O6: mes | P6: 12 | Q6: =+D6*(1+10%) -> 4534200 | R6: =+Q6/$A$1 -> 1030.0903 | S6: 1 | T6: =+S6*Y6 -> 54410400 | U6: =+T6/$A$1 -> 12361.084 | V6: 0 | W6: =+V6*Y6 -> 0 | X6: =+W6/$A$1 -> 0 | Y6: =+Q6*P6 -> 54410400 | Z6: =+Y6/$A$1 -> 12361.084 | AB6: mes | AC6: 4 | AD6: =+Q6*(1+8%) -> 4896936 | AE6: =+AD6/$A$1 -> 1112.4975 | AF6: 1 | AG6: =+AF6*AL6 -> 19587744 | AH6: =+AG6/$A$1 -> 4449.9901 | AI6: 0 | AJ6: =+AI6*AL6 -> 0 | AK6: =+AJ6/$A$1 -> 0 | AL6: =+AD6*AC6 -> 19587744 | AM6: =+AL6/$A$1 -> 4449.9901 | AO6: =+SUM(AC6+P6+C6) -> 28 | AP6: =+L6+Y6+AL6 -> 123462144 | AQ6: =+AP6/$A$1 -> 28048.423 | AR6: =+AP6*F6 -> 123462144 | AS6: =+AR6/$A$1 -> 28048.423 | AT6: =+AP6*I6 -> 0 | AU6: =+AT6/$A$1 -> 0 | AV6: 1 | AW6: 4122000 | AX6: =+AW6/$A$1 -> 936.44573 | BH6: =+AR6+AT6-AP6 -> 0
A7: =+'Summary Budget'!E10 -> 1.4. Organizational Professional | B7: month | C7: 12 | D7: =+AW7*AV7 -> 3200000 | E7: =+D7/$A$1 -> 726.98359 | F7: 0.75 | G7: =L7*F7 -> 28800000 | H7: =+G7/$A$1 -> 6542.8523 | I7: 0.25 | J7: =L7*I7 -> 9600000 | K7: =+J7/$A$1 -> 2180.9508 | L7: =+D7*C7 -> 38400000 | M7: =+L7/$A$1 -> 8723.803 | O7: mes | P7: 12 | Q7: =+D7*(1+10%) -> 3520000 | R7: =+Q7/$A$1 -> 799.68194 | S7: 0.75 | T7: =+S7*Y7 -> 31680000 | U7: =+T7/$A$1 -> 7197.1375 | V7: 0.25 | W7: =+V7*Y7 -> 10560000 | X7: =+W7/$A$1 -> 2399.0458 | Y7: =+Q7*P7 -> 42240000 | Z7: =+Y7/$A$1 -> 9596.1833 | AB7: mes | AC7: 4 | AD7: =+Q7*(1+8%) -> 3801600 | AE7: =+AD7/$A$1 -> 863.6565 | AF7: 0.75 | AG7: =+AF7*AL7 -> 11404800 | AH7: =+AG7/$A$1 -> 2590.9695 | AI7: 0.25 | AJ7: =+AI7*AL7 -> 3801600 | AK7: =+AJ7/$A$1 -> 863.6565 | AL7: =+AD7*AC7 -> 15206400 | AM7: =+AL7/$A$1 -> 3454.626 | AO7: =+SUM(AC7+P7+C7) -> 28 | AP7: =+L7+Y7+AL7 -> 95846400 | AQ7: =+AP7/$A$1 -> 21774.612 | AR7: =+AP7*F7 -> 71884800 | AS7: =+AR7/$A$1 -> 16330.959 | AT7: =+AP7*I7 -> 23961600 | AU7: =+AT7/$A$1 -> 5443.6531 | AV7: 0.8 | AW7: 4000000 | AX7: =+AW7/$A$1 -> 908.72948 | BA7: =+L7*20/100 -> 7680000 | BB7: =+Y7*20/100 -> 8448000 | BC7: =+AL7*20/100 -> 3041280 | BH7: =+AR7+AT7-AP7 -> 0
A8: =+'Summary Budget'!E11 -> 1.5. F&A Specialist | B8: month | C8: 12 | D8: =+AW8*AV8 -> 1900000 | E8: =+D8/$A$1 -> 431.6465 | F8: 1 | G8: =L8*F8 -> 22800000 | H8: =+G8/$A$1 -> 5179.7581 | I8: 0 | J8: =L8*I8 -> 0 | K8: =+J8/$A$1 -> 0 | L8: =+D8*C8 -> 22800000 | M8: =+L8/$A$1 -> 5179.7581 | O8: mes | P8: 12 | Q8: =+D8*(1+10%) -> 2090000 | R8: =+Q8/$A$1 -> 474.81115 | S8: 1 | T8: =+S8*Y8 -> 25080000 | U8: =+T8/$A$1 -> 5697.7339 | V8: 0 | W8: =+V8*Y8 -> 0 | X8: =+W8/$A$1 -> 0 | Y8: =+Q8*P8 -> 25080000 | Z8: =+Y8/$A$1 -> 5697.7339 | AB8: mes | AC8: 4 | AD8: =+Q8*(1+8%) -> 2257200 | AE8: =+AD8/$A$1 -> 512.79605 | AF8: 1 | AG8: =+AF8*AL8 -> 9028800 | AH8: =+AG8/$A$1 -> 2051.1842 | AI8: 0 | AJ8: =+AI8*AL8 -> 0 | AK8: =+AJ8/$A$1 -> 0 | AL8: =+AD8*AC8 -> 9028800 | AM8: =+AL8/$A$1 -> 2051.1842 | AO8: =+SUM(AC8+P8+C8) -> 28 | AP8: =+L8+Y8+AL8 -> 56908800 | AQ8: =+AP8/$A$1 -> 12928.676 | AR8: =+AP8*F8 -> 56908800 | AS8: =+AR8/$A$1 -> 12928.676 | AT8: =+AP8*I8 -> 0 | AU8: =+AT8/$A$1 -> 0 | AV8: 0.5 | AW8: 3800000 | AX8: =+AW8/$A$1 -> 863.29301 | BH8: =+AR8+AT8-AP8 -> 0
A9: =+'Summary Budget'!E12 -> 1.6. Business Partner Professional Antioquia, Córdoba 1 | B9: month | C9: 12 | D9: =+AW9*AV9 -> 3500000 | E9: =+D9/$A$1 -> 795.1383 | F9: 1 | G9: =L9*F9 -> 42000000 | H9: =+G9/$A$1 -> 9541.6596 | I9: 0 | J9: =L9*I9 -> 0 | K9: =+J9/$A$1 -> 0 | L9: =+D9*C9 -> 42000000 | M9: =+L9/$A$1 -> 9541.6596 | O9: mes | P9: 12 | Q9: =+D9*(1+10%) -> 3850000 | R9: =+Q9/$A$1 -> 874.65213 | S9: 1 | T9: =+S9*Y9 -> 46200000 | U9: =+T9/$A$1 -> 10495.826 | V9: 0 | W9: =+V9*Y9 -> 0 | X9: =+W9/$A$1 -> 0 | Y9: =+Q9*P9 -> 46200000 | Z9: =+Y9/$A$1 -> 10495.826 | AB9: mes | AC9: 3 | AD9: =+Q9*(1+8%) -> 4158000 | AE9: =+AD9/$A$1 -> 944.6243 | AF9: 1 | AG9: =+AF9*AL9 -> 12474000 | AH9: =+AG9/$A$1 -> 2833.8729 | AI9: 0 | AJ9: =+AI9*AL9 -> 0 | AK9: =+AJ9/$A$1 -> 0 | AL9: =+AD9*AC9 -> 12474000 | AM9: =+AL9/$A$1 -> 2833.8729 | AO9: =+SUM(AC9+P9+C9) -> 27 | AP9: =+L9+Y9+AL9 -> 100674000 | AQ9: =+AP9/$A$1 -> 22871.358 | AR9: =+AP9*F9 -> 100674000 | AS9: =+AR9/$A$1 -> 22871.358 | AT9: =+AP9*I9 -> 0 | AU9: =+AT9/$A$1 -> 0 | AV9: 1 | AW9: 3500000 | AX9: =+AW9/$A$1 -> 795.1383 | BH9: =+AR9+AT9-AP9 -> 0
A10: =+'Summary Budget'!E13 -> 1.7. Business Partner Professional Antioquia, Córdoba 2 | B10: month | C10: 12 | D10: =+AW10*AV10 -> 3500000 | E10: =+D10/$A$1 -> 795.1383 | F10: 1 | G10: =L10*F10 -> 42000000 | H10: =+G10/$A$1 -> 9541.6596 | I10: 0 | J10: =L10*I10 -> 0 | K10: =+J10/$A$1 -> 0 | L10: =+D10*C10 -> 42000000 | M10: =+L10/$A$1 -> 9541.6596 | O10: mes | P10: 12 | Q10: =+D10*(1+10%) -> 3850000 | R10: =+Q10/$A$1 -> 874.65213 | S10: 1 | T10: =+S10*Y10 -> 46200000 | U10: =+T10/$A$1 -> 10495.826 | V10: 0 | W10: =+V10*Y10 -> 0 | X10: =+W10/$A$1 -> 0 | Y10: =+Q10*P10 -> 46200000 | Z10: =+Y10/$A$1 -> 10495.826 | AB10: mes | AC10: 0 | AD10: =+Q10*(1+8%) -> 4158000 | AE10: =+AD10/$A$1 -> 944.6243 | AF10: 1 | AG10: =+AF10*AL10 -> 0 | AH10: =+AG10/$A$1 -> 0 | AI10: 0 | AJ10: =+AI10*AL10 -> 0 | AK10: =+AJ10/$A$1 -> 0 | AL10: =+AD10*AC10 -> 0 | AM10: =+AL10/$A$1 -> 0 | AO10: =+SUM(AC10+P10+C10) -> 24 | AP10: =+L10+Y10+AL10 -> 88200000 | AQ10: =+AP10/$A$1 -> 20037.485 | AR10: =+AP10*F10 -> 88200000 | AS10: =+AR10/$A$1 -> 20037.485 | AT10: =+AP10*I10 -> 0 | AU10: =+AT10/$A$1 -> 0 | AV10: 1 | AW10: 3500000 | AX10: =+AW10/$A$1 -> 795.1383 | BH10: =+AR10+AT10-AP10 -> 0
A11: =+'Summary Budget'!E14 -> 1.8. Business Partner Professional Caldas | B11: month | C11: 12 | D11: =+AW11*AV11 -> 3500000 | E11: =+D11/$A$1 -> 795.1383 | F11: 1 | G11: =L11*F11 -> 42000000 | H11: =+G11/$A$1 -> 9541.6596 | I11: 0 | J11: =L11*I11 -> 0 | K11: =+J11/$A$1 -> 0 | L11: =+D11*C11 -> 42000000 | M11: =+L11/$A$1 -> 9541.6596 | O11: mes | P11: 12 | Q11: =+D11*(1+10%) -> 3850000 | R11: =+Q11/$A$1 -> 874.65213 | S11: 1 | T11: =+S11*Y11 -> 46200000 | U11: =+T11/$A$1 -> 10495.826 | V11: 0 | W11: =+V11*Y11 -> 0 | X11: =+W11/$A$1 -> 0 | Y11: =+Q11*P11 -> 46200000 | Z11: =+Y11/$A$1 -> 10495.826 | AB11: mes | AC11: 3 | AD11: =+Q11*(1+8%) -> 4158000 | AE11: =+AD11/$A$1 -> 944.6243 | AF11: 1 | AG11: =+AF11*AL11 -> 12474000 | AH11: =+AG11/$A$1 -> 2833.8729 | AI11: 0 | AJ11: =+AI11*AL11 -> 0 | AK11: =+AJ11/$A$1 -> 0 | AL11: =+AD11*AC11 -> 12474000 | AM11: =+AL11/$A$1 -> 2833.8729 | AO11: =+SUM(AC11+P11+C11) -> 27 | AP11: =+L11+Y11+AL11 -> 100674000 | AQ11: =+AP11/$A$1 -> 22871.358 | AR11: =+AP11*F11 -> 100674000 | AS11: =+AR11/$A$1 -> 22871.358 | AT11: =+AP11*I11 -> 0 | AU11: =+AT11/$A$1 -> 0 | AV11: 1 | AW11: 3500000 | AX11: =+AW11/$A$1 -> 795.1383 | BH11: =+AR11+AT11-AP11 -> 0
A12: =+'Summary Budget'!E15 -> 1.9. Business Partner Professional Guajira, Cesar, Magdalena | B12: month | C12: 12 | D12: =+AW12*AV12 -> 3500000 | E12: =+D12/$A$1 -> 795.1383 | F12: 1 | G12: =L12*F12 -> 42000000 | H12: =+G12/$A$1 -> 9541.6596 | I12: 0 | J12: =L12*I12 -> 0 | K12: =+J12/$A$1 -> 0 | L12: =+D12*C12 -> 42000000 | M12: =+L12/$A$1 -> 9541.6596 | O12: mes | P12: 12 | Q12: =+D12*(1+10%) -> 3850000 | R12: =+Q12/$A$1 -> 874.65213 | S12: 1 | T12: =+S12*Y12 -> 46200000 | U12: =+T12/$A$1 -> 10495.826 | V12: 0 | W12: =+V12*Y12 -> 0 | X12: =+W12/$A$1 -> 0 | Y12: =+Q12*P12 -> 46200000 | Z12: =+Y12/$A$1 -> 10495.826 | AB12: mes | AC12: 3 | AD12: =+Q12*(1+8%) -> 4158000 | AE12: =+AD12/$A$1 -> 944.6243 | AF12: 1 | AG12: =+AF12*AL12 -> 12474000 | AH12: =+AG12/$A$1 -> 2833.8729 | AI12: 0 | AJ12: =+AI12*AL12 -> 0 | AK12: =+AJ12/$A$1 -> 0 | AL12: =+AD12*AC12 -> 12474000 | AM12: =+AL12/$A$1 -> 2833.8729 | AO12: =+SUM(AC12+P12+C12) -> 27 | AP12: =+L12+Y12+AL12 -> 100674000 | AQ12: =+AP12/$A$1 -> 22871.358 | AR12: =+AP12*F12 -> 100674000 | AS12: =+AR12/$A$1 -> 22871.358 | AT12: =+AP12*I12 -> 0 | AU12: =+AT12/$A$1 -> 0 | AV12: 1 | AW12: 3500000 | AX12: =+AW12/$A$1 -> 795.1383 | BH12: =+AR12+AT12-AP12 -> 0
A13: =+'Summary Budget'!E16 -> 1.10. Business Partner Professional Huila | B13: month | C13: 12 | D13: =+AW13*AV13 -> 3500000 | E13: =+D13/$A$1 -> 795.1383 | F13: 1 | G13: =L13*F13 -> 42000000 | H13: =+G13/$A$1 -> 9541.6596 | I13: 0 | J13: =L13*I13 -> 0 | K13: =+J13/$A$1 -> 0 | L13: =+D13*C13 -> 42000000 | M13: =+L13/$A$1 -> 9541.6596 | O13: mes | P13: 12 | Q13: =+D13*(1+10%) -> 3850000 | R13: =+Q13/$A$1 -> 874.65213 | S13: 1 | T13: =+S13*Y13 -> 46200000 | U13: =+T13/$A$1 -> 10495.826 | V13: 0 | W13: =+V13*Y13 -> 0 | X13: =+W13/$A$1 -> 0 | Y13: =+Q13*P13 -> 46200000 | Z13: =+Y13/$A$1 -> 10495.826 | AB13: mes | AC13: 3 | AD13: =+Q13*(1+8%) -> 4158000 | AE13: =+AD13/$A$1 -> 944.6243 | AF13: 1 | AG13: =+AF13*AL13 -> 12474000 | AH13: =+AG13/$A$1 -> 2833.8729 | AI13: 0 | AJ13: =+AI13*AL13 -> 0 | AK13: =+AJ13/$A$1 -> 0 | AL13: =+AD13*AC13 -> 12474000 | AM13: =+AL13/$A$1 -> 2833.8729 | AO13: =+SUM(AC13+P13+C13) -> 27 | AP13: =+L13+Y13+AL13 -> 100674000 | AQ13: =+AP13/$A$1 -> 22871.358 | AR13: =+AP13*F13 -> 100674000 | AS13: =+AR13/$A$1 -> 22871.358 | AT13: =+AP13*I13 -> 0 | AU13: =+AT13/$A$1 -> 0 | AV13: 1 | AW13: 3500000 | AX13: =+AW13/$A$1 -> 795.1383 | BH13: =+AR13+AT13-AP13 -> 0
A14: =+'Summary Budget'!E17 -> 1.11. Business Partner Professional Santander and Bolivar | B14: month | C14: 12 | D14: =+AW14*AV14 -> 3500000 | E14: =+D14/$A$1 -> 795.1383 | F14: 1 | G14: =L14*F14 -> 42000000 | H14: =+G14/$A$1 -> 9541.6596 | I14: 0 | J14: =L14*I14 -> 0 | K14: =+J14/$A$1 -> 0 | L14: =+D14*C14 -> 42000000 | M14: =+L14/$A$1 -> 9541.6596 | O14: mes | P14: 12 | Q14: =+D14*(1+10%) -> 3850000 | R14: =+Q14/$A$1 -> 874.65213 | S14: 1 | T14: =+S14*Y14 -> 46200000 | U14: =+T14/$A$1 -> 10495.826 | V14: 0 | W14: =+V14*Y14 -> 0 | X14: =+W14/$A$1 -> 0 | Y14: =+Q14*P14 -> 46200000 | Z14: =+Y14/$A$1 -> 10495.826 | AB14: mes | AC14: 0 | AD14: =+Q14*(1+8%) -> 4158000 | AE14: =+AD14/$A$1 -> 944.6243 | AF14: 1 | AG14: =+AF14*AL14 -> 0 | AH14: =+AG14/$A$1 -> 0 | AI14: 0 | AJ14: =+AI14*AL14 -> 0 | AK14: =+AJ14/$A$1 -> 0 | AL14: =+AD14*AC14 -> 0 | AM14: =+AL14/$A$1 -> 0 | AO14: =+SUM(AC14+P14+C14) -> 24 | AP14: =+L14+Y14+AL14 -> 88200000 | AQ14: =+AP14/$A$1 -> 20037.485 | AR14: =+AP14*F14 -> 88200000 | AS14: =+AR14/$A$1 -> 20037.485 | AT14: =+AP14*I14 -> 0 | AU14: =+AT14/$A$1 -> 0 | AV14: 1 | AW14: 3500000 | AX14: =+AW14/$A$1 -> 795.1383 | BH14: =+AR14+AT14-AP14 -> 0
A15: =+'Summary Budget'!E18 -> 1.12. Business Partner Professional Cauca | B15: month | C15: 12 | D15: =+AW15*AV15 -> 3500000 | E15: =+D15/$A$1 -> 795.1383 | F15: 1 | G15: =L15*F15 -> 42000000 | H15: =+G15/$A$1 -> 9541.6596 | I15: 0 | J15: =L15*I15 -> 0 | K15: =+J15/$A$1 -> 0 | L15: =+D15*C15 -> 42000000 | M15: =+L15/$A$1 -> 9541.6596 | O15: mes | P15: 12 | Q15: =+D15*(1+10%) -> 3850000 | R15: =+Q15/$A$1 -> 874.65213 | S15: 1 | T15: =+S15*Y15 -> 46200000 | U15: =+T15/$A$1 -> 10495.826 | V15: 0 | W15: =+V15*Y15 -> 0 | X15: =+W15/$A$1 -> 0 | Y15: =+Q15*P15 -> 46200000 | Z15: =+Y15/$A$1 -> 10495.826 | AB15: mes | AC15: 3 | AD15: =+Q15*(1+8%) -> 4158000 | AE15: =+AD15/$A$1 -> 944.6243 | AF15: 1 | AG15: =+AF15*AL15 -> 12474000 | AH15: =+AG15/$A$1 -> 2833.8729 | AI15: 0 | AJ15: =+AI15*AL15 -> 0 | AK15: =+AJ15/$A$1 -> 0 | AL15: =+AD15*AC15 -> 12474000 | AM15: =+AL15/$A$1 -> 2833.8729 | AO15: =+SUM(AC15+P15+C15) -> 27 | AP15: =+L15+Y15+AL15 -> 100674000 | AQ15: =+AP15/$A$1 -> 22871.358 | AR15: =+AP15*F15 -> 100674000 | AS15: =+AR15/$A$1 -> 22871.358 | AT15: =+AP15*I15 -> 0 | AU15: =+AT15/$A$1 -> 0 | AV15: 1 | AW15: 3500000 | AX15: =+AW15/$A$1 -> 795.1383 | BH15: =+AR15+AT15-AP15 -> 0
A16: =+'Summary Budget'!E19 -> 1.13. Business Partner Professional Tolima 1 | B16: month | C16: 12 | D16: =+AW16*AV16 -> 3500000 | E16: =+D16/$A$1 -> 795.1383 | F16: 1 | G16: =L16*F16 -> 42000000 | H16: =+G16/$A$1 -> 9541.6596 | I16: 0 | J16: =L16*I16 -> 0 | K16: =+J16/$A$1 -> 0 | L16: =+D16*C16 -> 42000000 | M16: =+L16/$A$1 -> 9541.6596 | O16: mes | P16: 12 | Q16: =+D16*(1+10%) -> 3850000 | R16: =+Q16/$A$1 -> 874.65213 | S16: 1 | T16: =+S16*Y16 -> 46200000 | U16: =+T16/$A$1 -> 10495.826 | V16: 0 | W16: =+V16*Y16 -> 0 | X16: =+W16/$A$1 -> 0 | Y16: =+Q16*P16 -> 46200000 | Z16: =+Y16/$A$1 -> 10495.826 | AB16: mes | AC16: 3 | AD16: =+Q16*(1+8%) -> 4158000 | AE16: =+AD16/$A$1 -> 944.6243 | AF16: 1 | AG16: =+AF16*AL16 -> 12474000 | AH16: =+AG16/$A$1 -> 2833.8729 | AI16: 0 | AJ16: =+AI16*AL16 -> 0 | AK16: =+AJ16/$A$1 -> 0 | AL16: =+AD16*AC16 -> 12474000 | AM16: =+AL16/$A$1 -> 2833.8729 | AO16: =+SUM(AC16+P16+C16) -> 27 | AP16: =+L16+Y16+AL16 -> 100674000 | AQ16: =+AP16/$A$1 -> 22871.358 | AR16: =+AP16*F16 -> 100674000 | AS16: =+AR16/$A$1 -> 22871.358 | AT16: =+AP16*I16 -> 0 | AU16: =+AT16/$A$1 -> 0 | AV16: 1 | AW16: 3500000 | AX16: =+AW16/$A$1 -> 795.1383 | BH16: =+AR16+AT16-AP16 -> 0
A17: =+'Summary Budget'!E20 -> 1.14. Business Partner Professional Tolima 2 | B17: month | C17: 12 | D17: =+AW17*AV17 -> 3500000 | E17: =+D17/$A$1 -> 795.1383 | F17: 1 | G17: =L17*F17 -> 42000000 | H17: =+G17/$A$1 -> 9541.6596 | I17: 0 | J17: =L17*I17 -> 0 | K17: =+J17/$A$1 -> 0 | L17: =+D17*C17 -> 42000000 | M17: =+L17/$A$1 -> 9541.6596 | O17: mes | P17: 12 | Q17: =+D17*(1+10%) -> 3850000 | R17: =+Q17/$A$1 -> 874.65213 | S17: 1 | T17: =+S17*Y17 -> 46200000 | U17: =+T17/$A$1 -> 10495.826 | V17: 0 | W17: =+V17*Y17 -> 0 | X17: =+W17/$A$1 -> 0 | Y17: =+Q17*P17 -> 46200000 | Z17: =+Y17/$A$1 -> 10495.826 | AB17: mes | AC17: 3 | AD17: =+Q17*(1+8%) -> 4158000 | AE17: =+AD17/$A$1 -> 944.6243 | AF17: 1 | AG17: =+AF17*AL17 -> 12474000 | AH17: =+AG17/$A$1 -> 2833.8729 | AI17: 0 | AJ17: =+AI17*AL17 -> 0 | AK17: =+AJ17/$A$1 -> 0 | AL17: =+AD17*AC17 -> 12474000 | AM17: =+AL17/$A$1 -> 2833.8729 | AO17: =+SUM(AC17+P17+C17) -> 27 | AP17: =+L17+Y17+AL17 -> 100674000 | AQ17: =+AP17/$A$1 -> 22871.358 | AR17: =+AP17*F17 -> 100674000 | AS17: =+AR17/$A$1 -> 22871.358 | AT17: =+AP17*I17 -> 0 | AU17: =+AT17/$A$1 -> 0 | AV17: 1 | AW17: 3500000 | AX17: =+AW17/$A$1 -> 795.1383 | BH17: =+AR17+AT17-AP17 -> 0
A18: =+'Summary Budget'!E21 -> 1.15. Business Partner Professional Tolima 3 | B18: month | C18: 12 | D18: =+AW18*AV18 -> 1750000 | E18: =+D18/$A$1 -> 397.56915 | F18: 0 | G18: =L18*F18 -> 0 | H18: =+G18/$A$1 -> 0 | I18: 1 | J18: =L18*I18 -> 21000000 | K18: =+J18/$A$1 -> 4770.8298 | L18: =+D18*C18 -> 21000000 | M18: =+L18/$A$1 -> 4770.8298 | O18: mes | P18: 12 | Q18: =+D18*(1+10%) -> 1925000 | R18: =+Q18/$A$1 -> 437.32606 | S18: 0 | T18: =+S18*Y18 -> 0 | U18: =+T18/$A$1 -> 0 | V18: 1 | W18: =+V18*Y18 -> 23100000 | X18: =+W18/$A$1 -> 5247.9128 | Y18: =+Q18*P18 -> 23100000 | Z18: =+Y18/$A$1 -> 5247.9128 | AB18: mes | AC18: 0 | AD18: =+Q18*(1+8%) -> 2079000 | AE18: =+AD18/$A$1 -> 472.31215 | AF18: 0 | AG18: =+AF18*AL18 -> 0 | AH18: =+AG18/$A$1 -> 0 | AI18: 1 | AJ18: =+AI18*AL18 -> 0 | AK18: =+AJ18/$A$1 -> 0 | AL18: =+AD18*AC18 -> 0 | AM18: =+AL18/$A$1 -> 0 | AO18: =+SUM(AC18+P18+C18) -> 24 | AP18: =+L18+Y18+AL18 -> 44100000 | AQ18: =+AP18/$A$1 -> 10018.743 | AR18: =+AP18*F18 -> 0 | AS18: =+AR18/$A$1 -> 0 | AT18: =+AP18*I18 -> 44100000 | AU18: =+AT18/$A$1 -> 10018.743 | AV18: 0.5 | AW18: 3500000 | AX18: =+AW18/$A$1 -> 795.1383 | BH18: =+AR18+AT18-AP18 -> 0
A19: =+'Summary Budget'!E22 -> 1.16. Administrative Coordinator | B19: month | C19: 12 | D19: =+AW19*AV19 -> 2000000 | E19: =+D19/$A$1 -> 454.36474 | F19: 0 | G19: =L19*F19 -> 0 | H19: =+G19/$A$1 -> 0 | I19: 1 | J19: =L19*I19 -> 24000000 | K19: =+J19/$A$1 -> 5452.3769 | L19: =+D19*C19 -> 24000000 | M19: =+L19/$A$1 -> 5452.3769 | O19: mes | P19: 12 | Q19: =+D19*(1+10%) -> 2200000 | R19: =+Q19/$A$1 -> 499.80122 | S19: 0 | T19: =+S19*Y19 -> 0 | U19: =+T19/$A$1 -> 0 | V19: 1 | W19: =+V19*Y19 -> 26400000 | X19: =+W19/$A$1 -> 5997.6146 | Y19: =+Q19*P19 -> 26400000 | Z19: =+Y19/$A$1 -> 5997.6146 | AB19: mes | AC19: 4 | AD19: =+Q19*(1+8%) -> 2376000 | AE19: =+AD19/$A$1 -> 539.78531 | AF19: 0 | AG19: =+AF19*AL19 -> 0 | AH19: =+AG19/$A$1 -> 0 | AI19: 1 | AJ19: =+AI19*AL19 -> 9504000 | AK19: =+AJ19/$A$1 -> 2159.1413 | AL19: =+AD19*AC19 -> 9504000 | AM19: =+AL19/$A$1 -> 2159.1413 | AO19: =+SUM(AC19+P19+C19) -> 28 | AP19: =+L19+Y19+AL19 -> 59904000 | AQ19: =+AP19/$A$1 -> 13609.133 | AR19: =+AP19*F19 -> 0 | AS19: =+AR19/$A$1 -> 0 | AT19: =+AP19*I19 -> 59904000 | AU19: =+AT19/$A$1 -> 13609.133 | AV19: 0.25 | AW19: 8000000 | AX19: =+AW19/$A$1 -> 1817.459 | BH19: =+AR19+AT19-AP19 -> 0
... A21: =+'Summary Budget'!E24 -> 1.18. Administrative Assistant | B21: month | C21: 12 | D21: =+AW21*AV21 -> 2400000 | E21: =+D21/$A$1 -> 545.23769 | F21: 1 | G21: =L21*F21 -> 28800000 | H21: =+G21/$A$1 -> 6542.8523 | I21: 0 | J21: =L21*I21 -> 0 | K21: =+J21/$A$1 -> 0 | L21: =+D21*C21 -> 28800000 | M21: =+L21/$A$1 -> 6542.8523 | O21: mes | P21: 12 | Q21: =+D21*(1+10%) -> 2640000 | R21: =+Q21/$A$1 -> 599.76146 | S21: 1 | T21: =+S21*Y21 -> 31680000 | U21: =+T21/$A$1 -> 7197.1375 | V21: 0 | W21: =+V21*Y21 -> 0 | X21: =+W21/$A$1 -> 0 | Y21: =+Q21*P21 -> 31680000 | Z21: =+Y21/$A$1 -> 7197.1375 | AB21: mes | AC21: 4 | AD21: =+Q21*(1+8%) -> 2851200 | AE21: =+AD21/$A$1 -> 647.74238 | AF21: 1 | AG21: =+AF21*AL21 -> 11404800 | AH21: =+AG21/$A$1 -> 2590.9695 | AI21: 0 | AJ21: =+AI21*AL21 -> 0 | AK21: =+AJ21/$A$1 -> 0 | AL21: =+AD21*AC21 -> 11404800 | AM21: =+AL21/$A$1 -> 2590.9695 | AO21: =+SUM(AC21+P21+C21) -> 28 | AP21: =+L21+Y21+AL21 -> 71884800 | AQ21: =+AP21/$A$1 -> 16330.959 | AR21: =+AP21*F21 -> 71884800 | AS21: =+AR21/$A$1 -> 16330.959 | AT21: =+AP21*I21 -> 0 | AU21: =+AT21/$A$1 -> 0 | AV21: 1 | AW21: 2400000 | AX21: =+AW21/$A$1 -> 545.23769 | BH21: =+AR21+AT21-AP21 -> 0
A22: =+'Summary Budget'!E25 -> 2. Fringe benefits | C22: 0.5829 | G22: =SUM(G23:G40) -> 3.4167777e+08 | H22: =SUM(H23:H40) -> 77623.166 | J22: =SUM(J23:J40) -> 44270340 | K22: =SUM(K23:K40) -> 10057.441 | L22: =+SUM(L23:L40) -> 3.8594811e+08 | M22: =SUM(M23:M40) -> 87680.607 | P22: 0.5829 | T22: =SUM(T23:T40) -> 3.7584555e+08 | U22: =SUM(U23:U40) -> 85385.483 | W22: =SUM(W23:W40) -> 48697374 | X22: =SUM(X23:X40) -> 11063.185 | Y22: =+SUM(Y23:Y40) -> 4.2454292e+08 | Z22: =SUM(Z23:Z40) -> 96448.668 | AC22: 0.5829 | AG22: =SUM(AG23:AG40) -> 98948924 | AH22: =SUM(AH23:AH40) -> 22479.451 | AJ22: =SUM(AJ23:AJ40) -> 12683658 | AK22: =SUM(AK23:AK40) -> 2881.5035 | AL22: =+SUM(AL23:AL40) -> 1.1163258e+08 | AM22: =SUM(AM23:AM40) -> 25360.955 | AP22: =+SUM(AP23:AP40) -> 9.2212362e+08 | AQ22: =SUM(AQ23:AQ40) -> 209490.23 | AR22: =+SUM(AR23:AR40) -> 8.1647224e+08 | AS22: =SUM(AS23:AS40) -> 185488.1 | AT22: =+SUM(AT23:AT40) -> 1.0565137e+08 | AU22: =SUM(AU23:AU40) -> 24002.129 | AV22: LOE (%) | AW22: Fringe benefits (%)
A23: =+A4 -> 1.1. Program Coordinator | B23: month | C23: =+C4 -> 12 | D23: =+D4*AW23 -> 1165800 | E23: =+D23/$A$1 -> 264.84921 | F23: =+F4 -> 0 | G23: =L23*F23 -> 0 | H23: =+G23/$A$1 -> 0 | I23: 1 | J23: =L23*I23 -> 13989600 | K23: =+J23/$A$1 -> 3178.1905 | L23: =+D23*C23 -> 13989600 | M23: =+L23/$A$1 -> 3178.1905 | O23: mes | P23: =+P4 -> 12 | Q23: =+Q4*AW23 -> 1282380 | R23: =+Q23/$A$1 -> 291.33413 | S23: =+S4 -> 0 | T23: =+S23*Y23 -> 0 | U23: =+T23/$A$1 -> 0 | V23: 1 | W23: =+V23*Y23 -> 15388560 | X23: =+W23/$A$1 -> 3496.0095 | Y23: =+Q23*P23 -> 15388560 | Z23: =+Y23/$A$1 -> 3496.0095 | AB23: mes | AC23: =+AC4 -> 4 | AD23: =+AD4*AW23 -> 1384970.4 | AE23: =+AD23/$A$1 -> 314.64086 | AF23: =+AF4 -> 0 | AG23: =+AF23*AL23 -> 0 | AH23: =+AG23/$A$1 -> 0 | AI23: 1 | AJ23: =+AI23*AL23 -> 5539881.6 | AK23: =+AJ23/$A$1 -> 1258.5634 | AL23: =+AD23*AC23 -> 5539881.6 | AM23: =+AL23/$A$1 -> 1258.5634 | AO23: =+AO4 -> 28 | AP23: =+L23+Y23+AL23 -> 34918042 | AQ23: =+AP23/$A$1 -> 7932.7635 | AR23: =+AP23*F23 -> 0 | AS23: =+AR23/$A$1 -> 0 | AT23: =+AP23*I23 -> 34918042 | AU23: =+AT23/$A$1 -> 7932.7635 | AV23: =+AV4 -> 0.2 | AW23: 0.5829 | BH23: =+AR23+AT23-AP23 -> 0
A24: =+A5 -> 1.2. Business Strengthening Coordinator | B24: month | C24: =+C5 -> 12 | D24: =+D5*AW24 -> 2402713.8 | E24: =+D24/$A$1 -> 545.85422 | F24: =+F5 -> 1 | G24: =L24*F24 -> 28832566 | H24: =+G24/$A$1 -> 6550.2506 | I24: 0 | J24: =L24*I24 -> 0 | K24: =+J24/$A$1 -> 0 | L24: =+D24*C24 -> 28832566 | M24: =+L24/$A$1 -> 6550.2506 | O24: mes | P24: =+P5 -> 12 | Q24: =+Q5*AW24 -> 2642985.2 | R24: =+Q24/$A$1 -> 600.43964 | S24: =+S5 -> 1 | T24: =+S24*Y24 -> 31715822 | U24: =+T24/$A$1 -> 7205.2757 | V24: 0 | W24: =+V24*Y24 -> 0 | X24: =+W24/$A$1 -> 0 | Y24: =+Q24*P24 -> 31715822 | Z24: =+Y24/$A$1 -> 7205.2757 | AB24: mes | AC24: =+AC5 -> 4 | AD24: =+AD5*AW24 -> 2854424 | AE24: =+AD24/$A$1 -> 648.47481 | AF24: =+AF5 -> 1 | AG24: =+AF24*AL24 -> 11417696 | AH24: =+AG24/$A$1 -> 2593.8992 | AI24: 0 | AJ24: =+AI24*AL24 -> 0 | AK24: =+AJ24/$A$1 -> 0 | AL24: =+AD24*AC24 -> 11417696 | AM24: =+AL24/$A$1 -> 2593.8992 | AO24: =+AO5 -> 28 | AP24: =+L24+Y24+AL24 -> 71966084 | AQ24: =+AP24/$A$1 -> 16349.426 | AR24: =+AP24*F24 -> 71966084 | AS24: =+AR24/$A$1 -> 16349.426 | AT24: =+AP24*I24 -> 0 | AU24: =+AT24/$A$1 -> 0 | AV24: =+AV5 -> 1 | AW24: 0.5829 | BH24: =+AR24+AT24-AP24 -> 0
A25: =+A6 -> 1.3. Cacao technical specialist | B25: month | C25: =+C6 -> 12 | D25: =+D6*AW25 -> 2402713.8 | E25: =+D25/$A$1 -> 545.85422 | F25: =+F6 -> 1 | G25: =L25*F25 -> 28832566 | H25: =+G25/$A$1 -> 6550.2506 | I25: 0 | J25: =L25*I25 -> 0 | K25: =+J25/$A$1 -> 0 | L25: =+D25*C25 -> 28832566 | M25: =+L25/$A$1 -> 6550.2506 | O25: mes | P25: =+P6 -> 12 | Q25: =+Q6*AW25 -> 2642985.2 | R25: =+Q25/$A$1 -> 600.43964 | S25: =+S6 -> 1 | T25: =+S25*Y25 -> 31715822 | U25: =+T25/$A$1 -> 7205.2757 | V25: 0 | W25: =+V25*Y25 -> 0 | X25: =+W25/$A$1 -> 0 | Y25: =+Q25*P25 -> 31715822 | Z25: =+Y25/$A$1 -> 7205.2757 | AB25: mes | AC25: =+AC6 -> 4 | AD25: =+AD6*AW25 -> 2854424 | AE25: =+AD25/$A$1 -> 648.47481 | AF25: =+AF6 -> 1 | AG25: =+AF25*AL25 -> 11417696 | AH25: =+AG25/$A$1 -> 2593.8992 | AI25: 0 | AJ25: =+AI25*AL25 -> 0 | AK25: =+AJ25/$A$1 -> 0 | AL25: =+AD25*AC25 -> 11417696 | AM25: =+AL25/$A$1 -> 2593.8992 | AO25: =+AO6 -> 28 | AP25: =+L25+Y25+AL25 -> 71966084 | AQ25: =+AP25/$A$1 -> 16349.426 | AR25: =+AP25*F25 -> 71966084 | AS25: =+AR25/$A$1 -> 16349.426 | AT25: =+AP25*I25 -> 0 | AU25: =+AT25/$A$1 -> 0 | AV25: =+AV6 -> 1 | AW25: 0.5829 | BH25: =+AR25+AT25-AP25 -> 0
A26: =+A7 -> 1.4. Organizational Professional | B26: month | C26: =+C7 -> 12 | D26: =+D7*AW26 -> 1865280 | E26: =+D26/$A$1 -> 423.75873 | F26: =+F7 -> 0.75 | G26: =L26*F26 -> 16787520 | H26: =+G26/$A$1 -> 3813.8286 | I26: 0.25 | J26: =L26*I26 -> 5595840 | K26: =+J26/$A$1 -> 1271.2762 | L26: =+D26*C26 -> 22383360 | M26: =+L26/$A$1 -> 5085.1048 | O26: mes | P26: =+P7 -> 12 | Q26: =+Q7*AW26 -> 2051808 | R26: =+Q26/$A$1 -> 466.13461 | S26: =+S7 -> 0.75 | T26: =+S26*Y26 -> 18466272 | U26: =+T26/$A$1 -> 4195.2114 | V26: 0.25 | W26: =+V26*Y26 -> 6155424 | X26: =+W26/$A$1 -> 1398.4038 | Y26: =+Q26*P26 -> 24621696 | Z26: =+Y26/$A$1 -> 5593.6153 | AB26: mes | AC26: =+AC7 -> 4 | AD26: =+AD7*AW26 -> 2215952.6 | AE26: =+AD26/$A$1 -> 503.42537 | AF26: =+AF7 -> 0.75 | AG26: =+AF26*AL26 -> 6647857.9 | AH26: =+AG26/$A$1 -> 1510.2761 | AI26: 0.25 | AJ26: =+AI26*AL26 -> 2215952.6 | AK26: =+AJ26/$A$1 -> 503.42537 | AL26: =+AD26*AC26 -> 8863810.6 | AM26: =+AL26/$A$1 -> 2013.7015 | AO26: =+AO7 -> 28 | AP26: =+L26+Y26+AL26 -> 55868867 | AQ26: =+AP26/$A$1 -> 12692.422 | AR26: =+AP26*F26 -> 41901650 | AS26: =+AR26/$A$1 -> 9519.3162 | AT26: =+AP26*I26 -> 13967217 | AU26: =+AT26/$A$1 -> 3173.1054 | AV26: =+AV7 -> 0.8 | AW26: 0.5829 | BH26: =+AR26+AT26-AP26 -> 0
A27: =+A8 -> 1.5. F&A Specialist | B27: month | C27: =+C8 -> 12 | D27: =+D8*AW27 -> 1107510 | E27: =+D27/$A$1 -> 251.60675 | F27: =+F8 -> 1 | G27: =L27*F27 -> 13290120 | H27: =+G27/$A$1 -> 3019.281 | I27: 0 | J27: =L27*I27 -> 0 | K27: =+J27/$A$1 -> 0 | L27: =+D27*C27 -> 13290120 | M27: =+L27/$A$1 -> 3019.281 | O27: mes | P27: =+P8 -> 12 | Q27: =+Q8*AW27 -> 1218261 | R27: =+Q27/$A$1 -> 276.76742 | S27: =+S8 -> 1 | T27: =+S27*Y27 -> 14619132 | U27: =+T27/$A$1 -> 3321.2091 | V27: 0 | W27: =+V27*Y27 -> 0 | X27: =+W27/$A$1 -> 0 | Y27: =+Q27*P27 -> 14619132 | Z27: =+Y27/$A$1 -> 3321.2091 | AB27: mes | AC27: =+AC8 -> 4 | AD27: =+AD8*AW27 -> 1315721.9 | AE27: =+AD27/$A$1 -> 298.90882 | AF27: =+AF8 -> 1 | AG27: =+AF27*AL27 -> 5262887.5 | AH27: =+AG27/$A$1 -> 1195.6353 | AI27: 0 | AJ27: =+AI27*AL27 -> 0 | AK27: =+AJ27/$A$1 -> 0 | AL27: =+AD27*AC27 -> 5262887.5 | AM27: =+AL27/$A$1 -> 1195.6353 | AO27: =+AO8 -> 28 | AP27: =+L27+Y27+AL27 -> 33172140 | AQ27: =+AP27/$A$1 -> 7536.1253 | AR27: =+AP27*F27 -> 33172140 | AS27: =+AR27/$A$1 -> 7536.1253 | AT27: =+AP27*I27 -> 0 | AU27: =+AT27/$A$1 -> 0 | AV27: =+AV8 -> 0.5 | AW27: 0.5829 | BH27: =+AR27+AT27-AP27 -> 0
A28: =+A9 -> 1.6. Business Partner Professional Antioquia, Córdoba 1 | B28: month | C28: =+C9 -> 12 | D28: =+D9*AW28 -> 2040150 | E28: =+D28/$A$1 -> 463.48611 | F28: =+F9 -> 1 | G28: =L28*F28 -> 24481800 | H28: =+G28/$A$1 -> 5561.8334 | I28: 0 | J28: =L28*I28 -> 0 | K28: =+J28/$A$1 -> 0 | L28: =+D28*C28 -> 24481800 | M28: =+L28/$A$1 -> 5561.8334 | O28: mes | P28: =+P9 -> 12 | Q28: =+Q9*AW28 -> 2244165 | R28: =+Q28/$A$1 -> 509.83472 | S28: =+S9 -> 1 | T28: =+S28*Y28 -> 26929980 | U28: =+T28/$A$1 -> 6118.0167 | V28: 0 | W28: =+V28*Y28 -> 0 | X28: =+W28/$A$1 -> 0 | Y28: =+Q28*P28 -> 26929980 | Z28: =+Y28/$A$1 -> 6118.0167 | AB28: mes | AC28: =+AC9 -> 3 | AD28: =+AD9*AW28 -> 2423698.2 | AE28: =+AD28/$A$1 -> 550.6215 | AF28: =+AF9 -> 1 | AG28: =+AF28*AL28 -> 7271094.6 | AH28: =+AG28/$A$1 -> 1651.8645 | AI28: 0 | AJ28: =+AI28*AL28 -> 0 | AK28: =+AJ28/$A$1 -> 0 | AL28: =+AD28*AC28 -> 7271094.6 | AM28: =+AL28/$A$1 -> 1651.8645 | AO28: =+AO9 -> 27 | AP28: =+L28+Y28+AL28 -> 58682875 | AQ28: =+AP28/$A$1 -> 13331.715 | AR28: =+AP28*F28 -> 58682875 | AS28: =+AR28/$A$1 -> 13331.715 | AT28: =+AP28*I28 -> 0 | AU28: =+AT28/$A$1 -> 0 | AV28: =+AV9 -> 1 | AW28: 0.5829 | BH28: =+AR28+AT28-AP28 -> 0
A29: =+A10 -> 1.7. Business Partner Professional Antioquia, Córdoba 2 | B29: month | C29: =+C10 -> 12 | D29: =+D10*AW29 -> 2040150 | E29: =+D29/$A$1 -> 463.48611 | F29: =+F10 -> 1 | G29: =L29*F29 -> 24481800 | H29: =+G29/$A$1 -> 5561.8334 | I29: 0 | J29: =L29*I29 -> 0 | K29: =+J29/$A$1 -> 0 | L29: =+D29*C29 -> 24481800 | M29: =+L29/$A$1 -> 5561.8334 | O29: mes | P29: =+P10 -> 12 | Q29: =+Q10*AW29 -> 2244165 | R29: =+Q29/$A$1 -> 509.83472 | S29: =+S10 -> 1 | T29: =+S29*Y29 -> 26929980 | U29: =+T29/$A$1 -> 6118.0167 | V29: 0 | W29: =+V29*Y29 -> 0 | X29: =+W29/$A$1 -> 0 | Y29: =+Q29*P29 -> 26929980 | Z29: =+Y29/$A$1 -> 6118.0167 | AB29: mes | AC29: =+AC10 -> 0 | AD29: =+AD10*AW29 -> 2423698.2 | AE29: =+AD29/$A$1 -> 550.6215 | AF29: =+AF10 -> 1 | AG29: =+AF29*AL29 -> 0 | AH29: =+AG29/$A$1 -> 0 | AI29: 0 | AJ29: =+AI29*AL29 -> 0 | AK29: =+AJ29/$A$1 -> 0 | AL29: =+AD29*AC29 -> 0 | AM29: =+AL29/$A$1 -> 0 | AO29: =+AO10 -> 24 | AP29: =+L29+Y29+AL29 -> 51411780 | AQ29: =+AP29/$A$1 -> 11679.85 | AR29: =+AP29*F29 -> 51411780 | AS29: =+AR29/$A$1 -> 11679.85 | AT29: =+AP29*I29 -> 0 | AU29: =+AT29/$A$1 -> 0 | AV29: =+AV10 -> 1 | AW29: 0.5829 | BH29: =+AR29+AT29-AP29 -> 0
A30: =+A11 -> 1.8. Business Partner Professional Caldas | B30: month | C30: =+C11 -> 12 | D30: =+D11*AW30 -> 2040150 | E30: =+D30/$A$1 -> 463.48611 | F30: =+F11 -> 1 | G30: =L30*F30 -> 24481800 | H30: =+G30/$A$1 -> 5561.8334 | I30: 0 | J30: =L30*I30 -> 0 | K30: =+J30/$A$1 -> 0 | L30: =+D30*C30 -> 24481800 | M30: =+L30/$A$1 -> 5561.8334 | O30: mes | P30: =+P11 -> 12 | Q30: =+Q11*AW30 -> 2244165 | R30: =+Q30/$A$1 -> 509.83472 | S30: =+S11 -> 1 | T30: =+S30*Y30 -> 26929980 | U30: =+T30/$A$1 -> 6118.0167 | V30: 0 | W30: =+V30*Y30 -> 0 | X30: =+W30/$A$1 -> 0 | Y30: =+Q30*P30 -> 26929980 | Z30: =+Y30/$A$1 -> 6118.0167 | AB30: mes | AC30: =+AC11 -> 3 | AD30: =+AD11*AW30 -> 2423698.2 | AE30: =+AD30/$A$1 -> 550.6215 | AF30: =+AF11 -> 1 | AG30: =+AF30*AL30 -> 7271094.6 | AH30: =+AG30/$A$1 -> 1651.8645 | AI30: 0 | AJ30: =+AI30*AL30 -> 0 | AK30: =+AJ30/$A$1 -> 0 | AL30: =+AD30*AC30 -> 7271094.6 | AM30: =+AL30/$A$1 -> 1651.8645 | AO30: =+AO11 -> 27 | AP30: =+L30+Y30+AL30 -> 58682875 | AQ30: =+AP30/$A$1 -> 13331.715 | AR30: =+AP30*F30 -> 58682875 | AS30: =+AR30/$A$1 -> 13331.715 | AT30: =+AP30*I30 -> 0 | AU30: =+AT30/$A$1 -> 0 | AV30: =+AV11 -> 1 | AW30: 0.5829 | BH30: =+AR30+AT30-AP30 -> 0
A31: =+A12 -> 1.9. Business Partner Professional Guajira, Cesar, Magdalena | B31: month | C31: =+C12 -> 12 | D31: =+D12*AW31 -> 2040150 | E31: =+D31/$A$1 -> 463.48611 | F31: =+F12 -> 1 | G31: =L31*F31 -> 24481800 | H31: =+G31/$A$1 -> 5561.8334 | I31: 0 | J31: =L31*I31 -> 0 | K31: =+J31/$A$1 -> 0 | L31: =+D31*C31 -> 24481800 | M31: =+L31/$A$1 -> 5561.8334 | O31: mes | P31: =+P12 -> 12 | Q31: =+Q12*AW31 -> 2244165 | R31: =+Q31/$A$1 -> 509.83472 | S31: =+S12 -> 1 | T31: =+S31*Y31 -> 26929980 | U31: =+T31/$A$1 -> 6118.0167 | V31: 0 | W31: =+V31*Y31 -> 0 | X31: =+W31/$A$1 -> 0 | Y31: =+Q31*P31 -> 26929980 | Z31: =+Y31/$A$1 -> 6118.0167 | AB31: mes | AC31: =+AC12 -> 3 | AD31: =+AD12*AW31 -> 2423698.2 | AE31: =+AD31/$A$1 -> 550.6215 | AF31: =+AF12 -> 1 | AG31: =+AF31*AL31 -> 7271094.6 | AH31: =+AG31/$A$1 -> 1651.8645 | AI31: 0 | AJ31: =+AI31*AL31 -> 0 | AK31: =+AJ31/$A$1 -> 0 | AL31: =+AD31*AC31 -> 7271094.6 | AM31: =+AL31/$A$1 -> 1651.8645 | AO31: =+AO12 -> 27 | AP31: =+L31+Y31+AL31 -> 58682875 | AQ31: =+AP31/$A$1 -> 13331.715 | AR31: =+AP31*F31 -> 58682875 | AS31: =+AR31/$A$1 -> 13331.715 | AT31: =+AP31*I31 -> 0 | AU31: =+AT31/$A$1 -> 0 | AV31: =+AV12 -> 1 | AW31: 0.5829 | BH31: =+AR31+AT31-AP31 -> 0
A32: =+A13 -> 1.10. Business Partner Professional Huila | B32: month | C32: =+C13 -> 12 | D32: =+D13*AW32 -> 2040150 | E32: =+D32/$A$1 -> 463.48611 | F32: =+F13 -> 1 | G32: =L32*F32 -> 24481800 | H32: =+G32/$A$1 -> 5561.8334 | I32: 0 | J32: =L32*I32 -> 0 | K32: =+J32/$A$1 -> 0 | L32: =+D32*C32 -> 24481800 | M32: =+L32/$A$1 -> 5561.8334 | O32: mes | P32: =+P13 -> 12 | Q32: =+Q13*AW32 -> 2244165 | R32: =+Q32/$A$1 -> 509.83472 | S32: =+S13 -> 1 | T32: =+S32*Y32 -> 26929980 | U32: =+T32/$A$1 -> 6118.0167 | V32: 0 | W32: =+V32*Y32 -> 0 | X32: =+W32/$A$1 -> 0 | Y32: =+Q32*P32 -> 26929980 | Z32: =+Y32/$A$1 -> 6118.0167 | AB32: mes | AC32: =+AC13 -> 3 | AD32: =+AD13*AW32 -> 2423698.2 | AE32: =+AD32/$A$1 -> 550.6215 | AF32: =+AF13 -> 1 | AG32: =+AF32*AL32 -> 7271094.6 | AH32: =+AG32/$A$1 -> 1651.8645 | AI32: 0 | AJ32: =+AI32*AL32 -> 0 | AK32: =+AJ32/$A$1 -> 0 | AL32: =+AD32*AC32 -> 7271094.6 | AM32: =+AL32/$A$1 -> 1651.8645 | AO32: =+AO13 -> 27 | AP32: =+L32+Y32+AL32 -> 58682875 | AQ32: =+AP32/$A$1 -> 13331.715 | AR32: =+AP32*F32 -> 58682875 | AS32: =+AR32/$A$1 -> 13331.715 | AT32: =+AP32*I32 -> 0 | AU32: =+AT32/$A$1 -> 0 | AV32: =+AV13 -> 1 | AW32: 0.5829 | BH32: =+AR32+AT32-AP32 -> 0
A33: =+A14 -> 1.11. Business Partner Professional Santander and Bolivar | B33: month | C33: =+C14 -> 12 | D33: =+D14*AW33 -> 2040150 | E33: =+D33/$A$1 -> 463.48611 | F33: =+F14 -> 1 | G33: =L33*F33 -> 24481800 | H33: =+G33/$A$1 -> 5561.8334 | I33: 0 | J33: =L33*I33 -> 0 | K33: =+J33/$A$1 -> 0 | L33: =+D33*C33 -> 24481800 | M33: =+L33/$A$1 -> 5561.8334 | O33: mes | P33: =+P14 -> 12 | Q33: =+Q14*AW33 -> 2244165 | R33: =+Q33/$A$1 -> 509.83472 | S33: =+S14 -> 1 | T33: =+S33*Y33 -> 26929980 | U33: =+T33/$A$1 -> 6118.0167 | V33: 0 | W33: =+V33*Y33 -> 0 | X33: =+W33/$A$1 -> 0 | Y33: =+Q33*P33 -> 26929980 | Z33: =+Y33/$A$1 -> 6118.0167 | AB33: mes | AC33: =+AC14 -> 0 | AD33: =+AD14*AW33 -> 2423698.2 | AE33: =+AD33/$A$1 -> 550.6215 | AF33: =+AF14 -> 1 | AG33: =+AF33*AL33 -> 0 | AH33: =+AG33/$A$1 -> 0 | AI33: 0 | AJ33: =+AI33*AL33 -> 0 | AK33: =+AJ33/$A$1 -> 0 | AL33: =+AD33*AC33 -> 0 | AM33: =+AL33/$A$1 -> 0 | AO33: =+AO14 -> 24 | AP33: =+L33+Y33+AL33 -> 51411780 | AQ33: =+AP33/$A$1 -> 11679.85 | AR33: =+AP33*F33 -> 51411780 | AS33: =+AR33/$A$1 -> 11679.85 | AT33: =+AP33*I33 -> 0 | AU33: =+AT33/$A$1 -> 0 | AV33: =+AV14 -> 1 | AW33: 0.5829 | BH33: =+AR33+AT33-AP33 -> 0
A34: =+A15 -> 1.12. Business Partner Professional Cauca | B34: month | C34: =+C15 -> 12 | D34: =+D15*AW34 -> 2040150 | E34: =+D34/$A$1 -> 463.48611 | F34: =+F15 -> 1 | G34: =L34*F34 -> 24481800 | H34: =+G34/$A$1 -> 5561.8334 | I34: 0 | J34: =L34*I34 -> 0 | K34: =+J34/$A$1 -> 0 | L34: =+D34*C34 -> 24481800 | M34: =+L34/$A$1 -> 5561.8334 | O34: mes | P34: =+P15 -> 12 | Q34: =+Q15*AW34 -> 2244165 | R34: =+Q34/$A$1 -> 509.83472 | S34: =+S15 -> 1 | T34: =+S34*Y34 -> 26929980 | U34: =+T34/$A$1 -> 6118.0167 | V34: 0 | W34: =+V34*Y34 -> 0 | X34: =+W34/$A$1 -> 0 | Y34: =+Q34*P34 -> 26929980 | Z34: =+Y34/$A$1 -> 6118.0167 | AB34: mes | AC34: =+AC15 -> 3 | AD34: =+AD15*AW34 -> 2423698.2 | AE34: =+AD34/$A$1 -> 550.6215 | AF34: =+AF15 -> 1 | AG34: =+AF34*AL34 -> 7271094.6 | AH34: =+AG34/$A$1 -> 1651.8645 | AI34: 0 | AJ34: =+AI34*AL34 -> 0 | AK34: =+AJ34/$A$1 -> 0 | AL34: =+AD34*AC34 -> 7271094.6 | AM34: =+AL34/$A$1 -> 1651.8645 | AO34: =+AO15 -> 27 | AP34: =+L34+Y34+AL34 -> 58682875 | AQ34: =+AP34/$A$1 -> 13331.715 | AR34: =+AP34*F34 -> 58682875 | AS34: =+AR34/$A$1 -> 13331.715 | AT34: =+AP34*I34 -> 0 | AU34: =+AT34/$A$1 -> 0 | AV34: =+AV15 -> 1 | AW34: 0.5829 | BH34: =+AR34+AT34-AP34 -> 0
... A40: =+A21 -> 1.18. Administrative Assistant | B40: month | C40: =+C21 -> 12 | D40: =+D21*AW40 -> 1244400 | E40: =+D40/$A$1 -> 282.70574 | F40: =+F21 -> 1 | G40: =L40*F40 -> 14932800 | H40: =+G40/$A$1 -> 3392.4689 | I40: 0 | J40: =L40*I40 -> 0 | K40: =+J40/$A$1 -> 0 | L40: =+D40*C40 -> 14932800 | M40: =+L40/$A$1 -> 3392.4689 | O40: mes | P40: =+P21 -> 12 | Q40: =+Q21*AW40 -> 1368840 | R40: =+Q40/$A$1 -> 310.97632 | S40: =+S21 -> 1 | T40: =+S40*Y40 -> 16426080 | U40: =+T40/$A$1 -> 3731.7158 | V40: 0 | W40: =+V40*Y40 -> 0 | X40: =+W40/$A$1 -> 0 | Y40: =+Q40*P40 -> 16426080 | Z40: =+Y40/$A$1 -> 3731.7158 | AB40: mes | AC40: =+AC21 -> 4 | AD40: =+AD21*AW40 -> 1478347.2 | AE40: =+AD40/$A$1 -> 335.85442 | AF40: =+AF21 -> 1 | AG40: =+AF40*AL40 -> 5913388.8 | AH40: =+AG40/$A$1 -> 1343.4177 | AI40: 0 | AJ40: =+AI40*AL40 -> 0 | AK40: =+AJ40/$A$1 -> 0 | AL40: =+AD40*AC40 -> 5913388.8 | AM40: =+AL40/$A$1 -> 1343.4177 | AO40: =+AO21 -> 28 | AP40: =+L40+Y40+AL40 -> 37272269 | AQ40: =+AP40/$A$1 -> 8467.6024 | AR40: =+AP40*F40 -> 37272269 | AS40: =+AR40/$A$1 -> 8467.6024 | AT40: =+AP40*I40 -> 0 | AU40: =+AT40/$A$1 -> 0 | AV40: =+AV21 -> 1 | AW40: 0.5185 | BH40: =+AR40+AT40-AP40 -> 0
A41: =+'Summary Budget'!E44 -> 3. Travel costs | G41: =SUM(G42:G45) -> 136800000 | H41: =SUM(H42:H45) -> 31078.548 | J41: =SUM(J42:J45) -> 0 | K41: =SUM(K42:K45) -> 0 | L41: =+SUM(L42:L45) -> 136800000 | M41: =SUM(M42:M45) -> 31078.548 | T41: =SUM(T42:T45) -> 141350000 | U41: =SUM(U42:U45) -> 32112.228 | W41: =SUM(W42:W45) -> 0 | X41: =SUM(X42:X45) -> 0 | Y41: =+SUM(Y42:Y45) -> 141350000 | Z41: =SUM(Z42:Z45) -> 32112.228 | AG41: =SUM(AG42:AG45) -> 10150000 | AH41: =SUM(AH42:AH45) -> 2305.9011 | AJ41: =SUM(AJ42:AJ45) -> 0 | AK41: =SUM(AK42:AK45) -> 0 | AL41: =+SUM(AL42:AL45) -> 10150000 | AM41: =SUM(AM42:AM45) -> 2305.9011 | AP41: =+SUM(AP42:AP45) -> 288300000 | AQ41: =SUM(AQ42:AQ45) -> 65496.677 | AR41: =+SUM(AR42:AR45) -> 288300000 | AS41: =SUM(AS42:AS45) -> 65496.677 | AT41: =+SUM(AT42:AT45) -> 0 | AU41: =SUM(AU42:AU45) -> 0
A42: =+'Summary Budget'!E45 -> 3.1. Air transportation | B42: round trip | C42: =+Travels!B35+Travels!B47/3 -> 27 | D42: =+Travels!C35 -> 1000000 | E42: =+D42/$A$1 -> 227.18237 | F42: 1 | G42: =L42*F42 -> 27000000 | H42: =+G42/$A$1 -> 6133.924 | I42: 0 | J42: =L42*I42 -> 0 | K42: =+J42/$A$1 -> 0 | L42: =+C42*D42 -> 27000000 | M42: =+L42/$A$1 -> 6133.924 | O42: =B42 -> round trip | P42: =+Travels!B47/3+10 -> 22 | Q42: =+Travels!C35 -> 1000000 | R42: =+Q42/$A$1 -> 227.18237 | S42: 1 | T42: =+S42*Y42 -> 22000000 | U42: =+T42/$A$1 -> 4998.0122 | V42: 0 | W42: =+V42*Y42 -> 0 | X42: =+W42/$A$1 -> 0 | Y42: =+P42*Q42 -> 22000000 | Z42: =+Y42/$A$1 -> 4998.0122 | AB42: =B42 -> round trip | AC42: 2 | AD42: =+Q42 -> 1000000 | AE42: =+AD42/$A$1 -> 227.18237 | AF42: 1 | AG42: =+AF42*AL42 -> 2000000 | AH42: =+AG42/$A$1 -> 454.36474 | AI42: 0 | AJ42: =+AI42*AL42 -> 0 | AK42: =+AJ42/$A$1 -> 0 | AL42: =+AC42*AD42 -> 2000000 | AM42: =+AL42/$A$1 -> 454.36474 | AP42: =+L42+Y42+AL42 -> 51000000 | AQ42: =+AP42/$A$1 -> 11586.301 | AR42: =+AP42*F42 -> 51000000 | AS42: =+AR42/$A$1 -> 11586.301 | AT42: =+AP42*I42 -> 0 | AU42: =+AT42/$A$1 -> 0 | BH42: =+AR42+AT42-AP42 -> 0
A43: =+'Summary Budget'!E46 -> 3.2. Land transportation | B43: trip | C43: =+Travels!B36+Travels!B48/3 -> 171 | D43: =+Travels!C36 -> 150000 | E43: =+D43/$A$1 -> 34.077356 | F43: 1 | G43: =L43*F43 -> 25650000 | H43: =+G43/$A$1 -> 5827.2278 | I43: 0 | J43: =L43*I43 -> 0 | K43: =+J43/$A$1 -> 0 | L43: =+C43*D43 -> 25650000 | M43: =+L43/$A$1 -> 5827.2278 | O43: =B43 -> trip | P43: =+Travels!B48/3+82 -> 184 | Q43: =+Travels!C36 -> 150000 | R43: =+Q43/$A$1 -> 34.077356 | S43: 1 | T43: =+S43*Y43 -> 27600000 | U43: =+T43/$A$1 -> 6270.2334 | V43: 0 | W43: =+V43*Y43 -> 0 | X43: =+W43/$A$1 -> 0 | Y43: =+P43*Q43 -> 27600000 | Z43: =+Y43/$A$1 -> 6270.2334 | AB43: =B43 -> trip | AC43: 20 | AD43: =+Q43 -> 150000 | AE43: =+AD43/$A$1 -> 34.077356 | AF43: 1 | AG43: =+AF43*AL43 -> 3000000 | AH43: =+AG43/$A$1 -> 681.54711 | AI43: 0 | AJ43: =+AI43*AL43 -> 0 | AK43: =+AJ43/$A$1 -> 0 | AL43: =+AC43*AD43 -> 3000000 | AM43: =+AL43/$A$1 -> 681.54711 | AP43: =+L43+Y43+AL43 -> 56250000 | AQ43: =+AP43/$A$1 -> 12779.008 | AR43: =+AP43*F43 -> 56250000 | AS43: =+AR43/$A$1 -> 12779.008 | AT43: =+AP43*I43 -> 0 | AU43: =+AT43/$A$1 -> 0 | BH43: =+AR43+AT43-AP43 -> 0
A44: =+'Summary Budget'!E47 -> 3.3. Lodging | B44: night | C44: =+Travels!B37+Travels!B49/3 -> 396 | D44: =+Travels!C37 -> 100000 | E44: =+D44/$A$1 -> 22.718237 | F44: 1 | G44: =L44*F44 -> 39600000 | H44: =+G44/$A$1 -> 8996.4219 | I44: 0 | J44: =L44*I44 -> 0 | K44: =+J44/$A$1 -> 0 | L44: =+C44*D44 -> 39600000 | M44: =+L44/$A$1 -> 8996.4219 | O44: =B44 -> night | P44: =+Travels!B49/3+208 -> 436 | Q44: =+Travels!C37 -> 100000 | R44: =+Q44/$A$1 -> 22.718237 | S44: 1 | T44: =+S44*Y44 -> 43600000 | U44: =+T44/$A$1 -> 9905.1514 | V44: 0 | W44: =+V44*Y44 -> 0 | X44: =+W44/$A$1 -> 0 | Y44: =+P44*Q44 -> 43600000 | Z44: =+Y44/$A$1 -> 9905.1514 | AB44: =B44 -> night | AC44: 20 | AD44: =+Q44 -> 100000 | AE44: =+AD44/$A$1 -> 22.718237 | AF44: 1 | AG44: =+AF44*AL44 -> 2000000 | AH44: =+AG44/$A$1 -> 454.36474 | AI44: 0 | AJ44: =+AI44*AL44 -> 0 | AK44: =+AJ44/$A$1 -> 0 | AL44: =+AC44*AD44 -> 2000000 | AM44: =+AL44/$A$1 -> 454.36474 | AP44: =+L44+Y44+AL44 -> 85200000 | AQ44: =+AP44/$A$1 -> 19355.938 | AR44: =+AP44*F44 -> 85200000 | AS44: =+AR44/$A$1 -> 19355.938 | AT44: =+AP44*I44 -> 0 | AU44: =+AT44/$A$1 -> 0 | BH44: =+AR44+AT44-AP44 -> 0
A45: =+'Summary Budget'!E48 -> 3.4. Perdiem | B45: day | C45: =+Travels!B38+Travels!B50/3 -> 495 | D45: =+Travels!C38 -> 90000 | E45: =+D45/$A$1 -> 20.446413 | F45: 1 | G45: =L45*F45 -> 44550000 | H45: =+G45/$A$1 -> 10120.975 | I45: 0 | J45: =L45*I45 -> 0 | K45: =+J45/$A$1 -> 0 | L45: =+C45*D45 -> 44550000 | M45: =+L45/$A$1 -> 10120.975 | O45: =B45 -> day | P45: =+Travels!B50/3+250 -> 535 | Q45: =+Travels!C38 -> 90000 | R45: =+Q45/$A$1 -> 20.446413 | S45: 1 | T45: =+S45*Y45 -> 48150000 | U45: =+T45/$A$1 -> 10938.831 | V45: 0 | W45: =+V45*Y45 -> 0 | X45: =+W45/$A$1 -> 0 | Y45: =+P45*Q45 -> 48150000 | Z45: =+Y45/$A$1 -> 10938.831 | AB45: =B45 -> day | AC45: 35 | AD45: =+Q45 -> 90000 | AE45: =+AD45/$A$1 -> 20.446413 | AF45: 1 | AG45: =+AF45*AL45 -> 3150000 | AH45: =+AG45/$A$1 -> 715.62447 | AI45: 0 | AJ45: =+AI45*AL45 -> 0 | AK45: =+AJ45/$A$1 -> 0 | AL45: =+AC45*AD45 -> 3150000 | AM45: =+AL45/$A$1 -> 715.62447 | AP45: =+L45+Y45+AL45 -> 95850000 | AQ45: =+AP45/$A$1 -> 21775.43 | AR45: =+AP45*F45 -> 95850000 | AS45: =+AR45/$A$1 -> 21775.43 | AT45: =+AP45*I45 -> 0 | AU45: =+AT45/$A$1 -> 0 | BH45: =+AR45+AT45-AP45 -> 0
A46: =+'Summary Budget'!E49 -> 4. Professional services (consultants) | G46: =SUM(G47:G49) -> 283500000 | H46: =SUM(H47:H49) -> 64406.202 | J46: =SUM(J47:J49) -> 0 | K46: =SUM(K47:K49) -> 0 | L46: =+SUM(L47:L49) -> 283500000 | M46: =SUM(M47:M49) -> 64406.202 | T46: =SUM(T47:T49) -> 315500000 | U46: =SUM(U47:U49) -> 71676.038 | W46: =SUM(W47:W49) -> 63000000 | X46: =SUM(X47:X49) -> 14312.489 | Y46: =+SUM(Y47:Y49) -> 378500000 | Z46: =SUM(Z47:Z49) -> 85988.527 | AG46: =SUM(AG47:AG49) -> 0 | AH46: =SUM(AH47:AH49) -> 0 | AJ46: =SUM(AJ47:AJ49) -> 0 | AK46: =SUM(AK47:AK49) -> 0 | AL46: =+SUM(AL47:AL49) -> 0 | AM46: =SUM(AM47:AM49) -> 0 | AP46: =+SUM(AP47:AP49) -> 662000000 | AQ46: =SUM(AQ47:AQ49) -> 150394.73 | AR46: =+SUM(AR47:AR49) -> 599000000 | AS46: =SUM(AS47:AS49) -> 136082.24 | AT46: =+SUM(AT47:AT49) -> 63000000 | AU46: =SUM(AU47:AU49) -> 14312.489 | BC46: =+AT46 -> 63000000
A47: 4.1. Development of cacao and complementary products business models / Muttuo | B47: product | C47: 1 | D47: 283500000 | E47: =+D47/$A$1 -> 64406.202 | F47: 1 | G47: =L47*F47 -> 283500000 | H47: =+G47/$A$1 -> 64406.202 | I47: 0 | J47: =L47*I47 -> 0 | K47: =+J47/$A$1 -> 0 | L47: =+C47*D47 -> 283500000 | M47: =+L47/$A$1 -> 64406.202 | O47: =B47 -> product | P47: 1 | Q47: =D47 -> 283500000 | R47: =+Q47/$A$1 -> 64406.202 | S47: 1 | T47: =+S47*Y47 -> 283500000 | U47: =+T47/$A$1 -> 64406.202 | V47: 0 | W47: =+V47*Y47 -> 0 | X47: =+W47/$A$1 -> 0 | Y47: =+P47*Q47 -> 283500000 | Z47: =+Y47/$A$1 -> 64406.202 | AB47: =B47 -> product | AD47: 0 | AE47: =+AD47/$A$1 -> 0 | AF47: 1 | AG47: =+AF47*AL47 -> 0 | AH47: =+AG47/$A$1 -> 0 | AI47: 0 | AJ47: =+AI47*AL47 -> 0 | AK47: =+AJ47/$A$1 -> 0 | AL47: =+AC47*AD47 -> 0 | AM47: =+AL47/$A$1 -> 0 | AP47: =+L47+Y47+AL47 -> 567000000 | AQ47: =+AP47/$A$1 -> 128812.4 | AR47: =+AP47*F47 -> 567000000 | AS47: =+AR47/$A$1 -> 128812.4 | AT47: =+AP47*I47 -> 0 | AU47: =+AT47/$A$1 -> 0 | BH47: =+AR47+AT47-AP47 -> 0
A48: 4.2. Financial feasibility assessments | B48: evaluation | C48: 0 | D48: 0 | E48: =+D48/$A$1 -> 0 | F48: 0 | G48: =L48*F48 -> 0 | H48: =+G48/$A$1 -> 0 | I48: 1 | J48: =L48*I48 -> 0 | K48: =+J48/$A$1 -> 0 | L48: =+C48*D48 -> 0 | M48: =+L48/$A$1 -> 0 | O48: =B48 -> evaluation | P48: 15 | Q48: 4200000 | R48: =+Q48/$A$1 -> 954.16596 | S48: 0 | T48: =+S48*Y48 -> 0 | U48: =+T48/$A$1 -> 0 | V48: 1 | W48: =+V48*Y48 -> 63000000 | X48: =+W48/$A$1 -> 14312.489 | Y48: =+P48*Q48 -> 63000000 | Z48: =+Y48/$A$1 -> 14312.489 | AB48: =B48 -> evaluation | AE48: =+AD48/$A$1 -> 0 | AF48: 0 | AG48: =+AF48*AL48 -> 0 | AH48: =+AG48/$A$1 -> 0 | AI48: 1 | AJ48: =+AI48*AL48 -> 0 | AK48: =+AJ48/$A$1 -> 0 | AM48: =+AL48/$A$1 -> 0 | AP48: =+L48+Y48+AL48 -> 63000000 | AQ48: =+AP48/$A$1 -> 14312.489 | AR48: =+AP48*F48 -> 0 | AS48: =+AR48/$A$1 -> 0 | AT48: =+AP48*I48 -> 63000000 | AU48: =+AT48/$A$1 -> 14312.489 | BH48: =+AR48+AT48-AP48 -> 0
A49: 4.3. Business consulting (marketing, communications, quality, processes, invoicing) | B49: consulting | E49: =+D49/$A$1 -> 0 | F49: 1 | G49: =L49*F49 -> 0 | H49: =+G49/$A$1 -> 0 | I49: 0 | J49: =L49*I49 -> 0 | K49: =+J49/$A$1 -> 0 | M49: =+L49/$A$1 -> 0 | O49: =B49 -> consulting | P49: 10 | Q49: 3200000 | R49: =+Q49/$A$1 -> 726.98359 | S49: 1 | T49: =+S49*Y49 -> 32000000 | U49: =+T49/$A$1 -> 7269.8359 | V49: 0 | W49: =+V49*Y49 -> 0 | X49: =+W49/$A$1 -> 0 | Y49: =+P49*Q49 -> 32000000 | Z49: =+Y49/$A$1 -> 7269.8359 | AB49: =B49 -> consulting | AE49: =+AD49/$A$1 -> 0 | AF49: 1 | AG49: =+AF49*AL49 -> 0 | AH49: =+AG49/$A$1 -> 0 | AI49: 0 | AJ49: =+AI49*AL49 -> 0 | AK49: =+AJ49/$A$1 -> 0 | AM49: =+AL49/$A$1 -> 0 | AP49: =+L49+Y49+AL49 -> 32000000 | AQ49: =+AP49/$A$1 -> 7269.8359 | AR49: =+AP49*F49 -> 32000000 | AS49: =+AR49/$A$1 -> 7269.8359 | AT49: =+AP49*I49 -> 0 | AU49: =+AT49/$A$1 -> 0 | BH49: =+AR49+AT49-AP49 -> 0
A50: =+'Summary Budget'!E53 -> 5. Supplies | G50: =SUM(G51:G51) -> 30420000 | H50: =SUM(H51:H51) -> 6910.8877 | J50: =SUM(J51:J51) -> 0 | K50: =SUM(K51:K51) -> 0 | L50: =+SUM(L51:L51) -> 30420000 | M50: =SUM(M51:M51) -> 6910.8877 | T50: =SUM(T51:T51) -> 33462000 | U50: =SUM(U51:U51) -> 7601.9765 | W50: =SUM(W51:W51) -> 0 | X50: =SUM(X51:X51) -> 0 | Y50: =+SUM(Y51:Y51) -> 33462000 | Z50: =SUM(Z51:Z51) -> 7601.9765 | AG50: =SUM(AG51:AG51) -> 9266400 | AH50: =SUM(AH51:AH51) -> 2105.1627 | AJ50: =SUM(AJ51:AJ51) -> 0 | AK50: =SUM(AK51:AK51) -> 0 | AL50: =+SUM(AL51:AL51) -> 9266400 | AM50: =SUM(AM51:AM51) -> 2105.1627 | AP50: =+SUM(AP51:AP51) -> 73148400 | AQ50: =SUM(AQ51:AQ51) -> 16618.027 | AR50: =+SUM(AR51:AR51) -> 73148400 | AS50: =SUM(AS51:AS51) -> 16618.027 | AT50: =+SUM(AT51:AT51) -> 0 | AU50: =SUM(AU51:AU51) -> 0
A51: 5.1. Laptop rental x 13 | B51: month | C51: 12 | D51: =195000*13 -> 2535000 | E51: =+D51/$A$1 -> 575.90731 | F51: 1 | G51: =L51*F51 -> 30420000 | H51: =+G51/$A$1 -> 6910.8877 | I51: 0 | J51: =L51*I51 -> 0 | K51: =+J51/$A$1 -> 0 | L51: =+C51*D51 -> 30420000 | M51: =+L51/$A$1 -> 6910.8877 | O51: =B51 -> month | P51: 12 | Q51: =+(195000*(1+10%))*13 -> 2788500 | R51: =+Q51/$A$1 -> 633.49804 | S51: 1 | T51: =+S51*Y51 -> 33462000 | U51: =+T51/$A$1 -> 7601.9765 | V51: 0 | W51: =+V51*Y51 -> 0 | X51: =+W51/$A$1 -> 0 | Y51: =+P51*Q51 -> 33462000 | Z51: =+Y51/$A$1 -> 7601.9765 | AB51: =B51 -> month | AC51: 4 | AD51: =+(195000*(1+10%)*(1+8%))*10 -> 2316600 | AE51: =+AD51/$A$1 -> 526.29068 | AF51: 1 | AG51: =+AF51*AL51 -> 9266400 | AH51: =+AG51/$A$1 -> 2105.1627 | AI51: 0 | AJ51: =+AI51*AL51 -> 0 | AK51: =+AJ51/$A$1 -> 0 | AL51: =+AC51*AD51 -> 9266400 | AM51: =+AL51/$A$1 -> 2105.1627 | AP51: =+L51+Y51+AL51 -> 73148400 | AQ51: =+AP51/$A$1 -> 16618.027 | AR51: =+AP51*F51 -> 73148400 | AS51: =+AR51/$A$1 -> 16618.027 | AT51: =AP51*I51 -> 0 | AU51: =+AT51/$A$1 -> 0 | AZ51: =+AP51/18 -> 4063800 | BA51: =+AZ51*4 -> 16255200 | BC51: =+L51*24/100 -> 7300800 | BD51: =+Y51*24/100 -> 8030880 | BE51: =+AL51*24/100 -> 2223936 | BH51: =+AR51+AT51-AP51 -> 0
A52: =+'Summary Budget'!E55 -> 6. Direct operating costs | G52: =SUM(G53:G58) -> 56610000 | H52: =SUM(H53:H58) -> 12860.794 | J52: =SUM(J53:J58) -> 148000000 | K52: =SUM(K53:K64) -> 33622.991 | L52: =+SUM(L53:L64) -> 228531600 | M52: =SUM(M53:M64) -> 51918.351 | T52: =SUM(T53:T58) -> 45560000 | U52: =SUM(U53:U58) -> 10350.429 | W52: =SUM(W53:W58) -> 1068000000 | X52: =SUM(X53:X58) -> 242630.77 | Y52: =+SUM(Y53:Y64) -> 1132723760 | Z52: =SUM(Z53:Z64) -> 257334.87 | AG52: =SUM(AG53:AG58) -> 4760000 | AH52: =SUM(AH53:AH58) -> 1081.3881 | AJ52: =SUM(AJ53:AJ58) -> 28000000 | AK52: =SUM(AK53:AK58) -> 6361.1064 | AL52: =+SUM(AL53:AL64) -> 38395872 | AM52: =SUM(AM53:AM64) -> 8722.8652 | AP52: =+SUM(AP53:AP58) -> 1350930000 | AQ52: =SUM(AQ53:AQ58) -> 306907.48 | AR52: =+SUM(AR53:AR58) -> 106930000 | AS52: =SUM(AS53:AS58) -> 24292.611 | AT52: =+SUM(AT53:AT58) -> 1244000000 | AU52: =SUM(AU53:AU58) -> 282614.87
A53: 6.1. Diagnostic workshop refreshments (snacks and lunches) | B53: workshop | C53: =Travels!B41 -> 74 | D53: =+Travels!D41*Travels!C41 -> 390000 | E53: =+D53/$A$1 -> 88.601125 | F53: 1 | G53: =L53*F53 -> 28860000 | H53: =+G53/$A$1 -> 6556.4832 | I53: 0 | J53: =L53*I53 -> 0 | K53: =+J53/$A$1 -> 0 | L53: =+C53*D53 -> 28860000 | M53: =+L53/$A$1 -> 6556.4832 | O53: =B53 -> workshop | Q53: 0 | R53: =+Q53/$A$1 -> 0 | S53: 1 | T53: =+S53*Y53 -> 0 | U53: =+T53/$A$1 -> 0 | V53: 0 | W53: =+V53*Y53 -> 0 | X53: =+W53/$A$1 -> 0 | Y53: =+P53*Q53 -> 0 | Z53: =+Y53/$A$1 -> 0 | AB53: =B53 -> workshop | AD53: 0 | AE53: =+AD53/$A$1 -> 0 | AF53: 1 | AG53: =+AF53*AL53 -> 0 | AH53: =+AG53/$A$1 -> 0 | AI53: 0 | AJ53: =+AI53*AL53 -> 0 | AK53: =+AJ53/$A$1 -> 0 | AL53: =+AC53*AD53 -> 0 | AM53: =+AL53/$A$1 -> 0 | AP53: =+L53+Y53+AL53 -> 28860000 | AQ53: =+AP53/$A$1 -> 6556.4832 | AR53: =+AP53*F53 -> 28860000 | AS53: =+AR53/$A$1 -> 6556.4832 | AT53: =+AP53*I53 -> 0 | AU53: =+AT53/$A$1 -> 0 | BH53: =+AR53+AT53-AP53 -> 0
A54: 6.2. Diagnostic workshop materials (stationery: cardboard, markers, cards, etc.) | B54: workshop | C54: =Travels!B42 -> 74 | D54: =+Travels!D42*Travels!C42 -> 35000 | E54: =+D54/$A$1 -> 7.951383 | F54: 1 | G54: =L54*F54 -> 2590000 | H54: =+G54/$A$1 -> 588.40234 | I54: 0 | J54: =L54*I54 -> 0 | K54: =+J54/$A$1 -> 0 | L54: =+C54*D54 -> 2590000 | M54: =+L54/$A$1 -> 588.40234 | O54: =B54 -> workshop | Q54: 0 | R54: =+Q54/$A$1 -> 0 | S54: 1 | T54: =+S54*Y54 -> 0 | U54: =+T54/$A$1 -> 0 | V54: 0 | W54: =+V54*Y54 -> 0 | X54: =+W54/$A$1 -> 0 | Y54: =+P54*Q54 -> 0 | Z54: =+Y54/$A$1 -> 0 | AB54: =B54 -> workshop | AD54: 0 | AE54: =+AD54/$A$1 -> 0 | AF54: 1 | AG54: =+AF54*AL54 -> 0 | AH54: =+AG54/$A$1 -> 0 | AI54: 0 | AJ54: =+AI54*AL54 -> 0 | AK54: =+AJ54/$A$1 -> 0 | AL54: =+AC54*AD54 -> 0 | AM54: =+AL54/$A$1 -> 0 | AP54: =+L54+Y54+AL54 -> 2590000 | AQ54: =+AP54/$A$1 -> 588.40234 | AR54: =+AP54*F54 -> 2590000 | AS54: =+AR54/$A$1 -> 588.40234 | AT54: =+AP54*I54 -> 0 | AU54: =+AT54/$A$1 -> 0 | BH54: =+AR54+AT54-AP54 -> 0
A55: 6.3. Strengthening workshop refreshments (snacks and lunches) | B55: workshop | C55: =+('Summary Budget'!G58/3) -> 74 | D55: =+Travels!D43*Travels!C43 -> 312000 | E55: =+D55/$A$1 -> 70.8809 | F55: 1 | G55: =L55*F55 -> 23088000 | H55: =+G55/$A$1 -> 5245.1866 | I55: 0 | J55: =L55*I55 -> 0 | K55: =+J55/$A$1 -> 0 | L55: =+C55*D55 -> 23088000 | M55: =+L55/$A$1 -> 5245.1866 | O55: =B55 -> workshop | P55: 134 | Q55: =+D55 -> 312000 | R55: =+Q55/$A$1 -> 70.8809 | S55: 1 | T55: =+S55*Y55 -> 41808000 | U55: =+T55/$A$1 -> 9498.0406 | V55: 0 | W55: =+V55*Y55 -> 0 | X55: =+W55/$A$1 -> 0 | Y55: =+P55*Q55 -> 41808000 | Z55: =+Y55/$A$1 -> 9498.0406 | AB55: =B55 -> workshop | AC55: 14 | AD55: =+Q55 -> 312000 | AE55: =+AD55/$A$1 -> 70.8809 | AF55: 1 | AG55: =+AF55*AL55 -> 4368000 | AH55: =+AG55/$A$1 -> 992.33259 | AI55: 0 | AJ55: =+AI55*AL55 -> 0 | AK55: =+AJ55/$A$1 -> 0 | AL55: =+AC55*AD55 -> 4368000 | AM55: =+AL55/$A$1 -> 992.33259 | AP55: =+L55+Y55+AL55 -> 69264000 | AQ55: =+AP55/$A$1 -> 15735.56 | AR55: =+AP55*F55 -> 69264000 | AS55: =+AR55/$A$1 -> 15735.56 | AT55: =+AP55*I55 -> 0 | AU55: =+AT55/$A$1 -> 0 | BH55: =+AR55+AT55-AP55 -> 0
A56: 6.4. Strengthening workshop materials (stationery: cardboard, markers, cards, etc.) | B56: workshop | C56: =+('Summary Budget'!G59/3) -> 74 | D56: =+Travels!D44*Travels!C44 -> 28000 | E56: =+D56/$A$1 -> 6.3611064 | F56: 1 | G56: =L56*F56 -> 2072000 | H56: =+G56/$A$1 -> 470.72187 | I56: 0 | J56: =L56*I56 -> 0 | K56: =+J56/$A$1 -> 0 | L56: =+C56*D56 -> 2072000 | M56: =+L56/$A$1 -> 470.72187 | O56: =B56 -> workshop | P56: 134 | Q56: =+D56 -> 28000 | R56: =+Q56/$A$1 -> 6.3611064 | S56: 1 | T56: =+S56*Y56 -> 3752000 | U56: =+T56/$A$1 -> 852.38825 | V56: 0 | W56: =+V56*Y56 -> 0 | X56: =+W56/$A$1 -> 0 | Y56: =+P56*Q56 -> 3752000 | Z56: =+Y56/$A$1 -> 852.38825 | AB56: =B56 -> workshop | AC56: 14 | AD56: =+Q56 -> 28000 | AE56: =+AD56/$A$1 -> 6.3611064 | AF56: 1 | AG56: =+AF56*AL56 -> 392000 | AH56: =+AG56/$A$1 -> 89.055489 | AI56: 0 | AJ56: =+AI56*AL56 -> 0 | AK56: =+AJ56/$A$1 -> 0 | AL56: =+AC56*AD56 -> 392000 | AM56: =+AL56/$A$1 -> 89.055489 | AP56: =+L56+Y56+AL56 -> 6216000 | AQ56: =+AP56/$A$1 -> 1412.1656 | AR56: =+AP56*F56 -> 6216000 | AS56: =+AR56/$A$1 -> 1412.1656 | AT56: =+AP56*I56 -> 0 | AU56: =+AT56/$A$1 -> 0 | BH56: =+AR56+AT56-AP56 -> 0
A57: 6.5. Credit Resources/Working Capital | B57: global | D57: 0 | E57: =+D57/$A$1 -> 0 | F57: 0 | G57: =L57*F57 -> 0 | H57: =+G57/$A$1 -> 0 | I57: 1 | J57: =L57*I57 -> 0 | K57: =+J57/$A$1 -> 0 | L57: =+C57*D57 -> 0 | M57: =+L57/$A$1 -> 0 | O57: =B57 -> global | P57: 1 | Q57: 800000000 | R57: =+Q57/$A$1 -> 181745.9 | S57: 0 | T57: =+S57*Y57 -> 0 | U57: =+T57/$A$1 -> 0 | V57: 1 | W57: =+V57*Y57 -> 800000000 | X57: =+W57/$A$1 -> 181745.9 | Y57: =+P57*Q57 -> 800000000 | Z57: =+Y57/$A$1 -> 181745.9 | AB57: =B57 -> global | AE57: =+AD57/$A$1 -> 0 | AF57: 0 | AG57: =+AF57*AL57 -> 0 | AH57: =+AG57/$A$1 -> 0 | AI57: 1 | AJ57: =+AI57*AL57 -> 0 | AK57: =+AJ57/$A$1 -> 0 | AL57: =+AC57*AD57 -> 0 | AM57: =+AL57/$A$1 -> 0 | AP57: =+L57+Y57+AL57 -> 800000000 | AQ57: =+AP57/$A$1 -> 181745.9 | AR57: =+AP57*F57 -> 0 | AS57: =+AR57/$A$1 -> 0 | AT57: =+AP57*I57 -> 800000000 | AU57: =+AT57/$A$1 -> 181745.9 | BC57: =+AT57 -> 800000000 | BH57: =+AR57+AT57-AP57 -> 0
A58: 6.6 IC Fundación-owned producer organization capacity building tools and methodologies (workshop guides, support tools, etc) | B58: asociation | C58: 74 | D58: 2000000 | E58: =+D58/$A$1 -> 454.36474 | F58: 0 | G58: =L58*F58 -> 0 | H58: =+G58/$A$1 -> 0 | I58: 1 | J58: =L58*I58 -> 148000000 | K58: =+J58/$A$1 -> 33622.991 | L58: =+C58*D58 -> 148000000 | M58: =+L58/$A$1 -> 33622.991 | O58: =B58 -> asociation | P58: 134 | Q58: 2000000 | R58: =+Q58/$A$1 -> 454.36474 | S58: 0 | T58: =+S58*Y58 -> 0 | U58: =+T58/$A$1 -> 0 | V58: 1 | W58: =+V58*Y58 -> 268000000 | X58: =+W58/$A$1 -> 60884.875 | Y58: =+P58*Q58 -> 268000000 | Z58: =+Y58/$A$1 -> 60884.875 | AB58: =B58 -> asociation | AC58: 14 | AD58: 2000000 | AE58: =+AD58/$A$1 -> 454.36474 | AF58: 0 | AG58: =+AF58*AL58 -> 0 | AH58: =+AG58/$A$1 -> 0 | AI58: 1 | AJ58: =+AI58*AL58 -> 28000000 | AK58: =+AJ58/$A$1 -> 6361.1064 | AL58: =+AC58*AD58 -> 28000000 | AM58: =+AL58/$A$1 -> 6361.1064 | AP58: =+L58+Y58+AL58 -> 444000000 | AQ58: =+AP58/$A$1 -> 100868.97 | AR58: =+AP58*F58 -> 0 | AS58: =+AR58/$A$1 -> 0 | AT58: =+AP58*I58 -> 444000000 | AU58: =+AT58/$A$1 -> 100868.97 | BC58: =+AT58 -> 444000000 | BH58: =+AR58+AT58-AP58 -> 0
A59: 7. Office expenses | G59: =SUM(G60:G64) -> 23921600 | H59: =SUM(H60:H64) -> 5434.5658 | J59: =SUM(J60:J64) -> 0 | K59: =SUM(K60:K64) -> 0 | T59: =SUM(T60:T64) -> 19163760 | U59: =SUM(U60:U64) -> 4353.6684 | W59: =SUM(W60:W64) -> 0 | X59: =SUM(X60:X64) -> 0 | AG59: =SUM(AG60:AG64) -> 5635872 | AH59: =SUM(AH60:AH64) -> 1280.3708 | AJ59: =SUM(AJ60:AJ64) -> 0 | AK59: =SUM(AK60:AK64) -> 0 | AP59: =SUM(AP60:AP64) -> 48721232 | AQ59: =SUM(AQ60:AQ64) -> 11068.605 | AR59: =SUM(AR60:AR64) -> 48721232 | AS59: =SUM(AS60:AS64) -> 11068.605 | AT59: =SUM(AT60:AT64) -> 0 | AU59: =SUM(AU60:AU64) -> 0 | BH59: =+AR59+AT59-AP59 -> 0
A60: 7.1. Staff recruitment assessments (medical exams, remote work visit, etc) | B60: new staff | C60: 5 | D60: 700000 | E60: =+D60/$A$1 -> 159.02766 | F60: 1 | G60: =L60*F60 -> 3500000 | H60: =+G60/$A$1 -> 795.1383 | I60: 0 | J60: =L60*I60 -> 0 | K60: =+J60/$A$1 -> 0 | L60: =+C60*D60 -> 3500000 | M60: =+L60/$A$1 -> 795.1383 | O60: =B60 -> new staff | R60: =+Q60/$A$1 -> 0 | S60: 1 | T60: =+S60*Y60 -> 0 | U60: =+T60/$A$1 -> 0 | V60: 0 | W60: =+V60*Y60 -> 0 | X60: =+W60/$A$1 -> 0 | Y60: =+P60*Q60 -> 0 | Z60: =+Y60/$A$1 -> 0 | AB60: =B60 -> new staff | AE60: =+AD60/$A$1 -> 0 | AF60: 1 | AG60: =+AF60*AL60 -> 0 | AH60: =+AG60/$A$1 -> 0 | AI60: 0 | AJ60: =+AI60*AL60 -> 0 | AK60: =+AJ60/$A$1 -> 0 | AL60: =+AC60*AD60 -> 0 | AM60: =+AL60/$A$1 -> 0 | AP60: =+L60+Y60+AL60 -> 3500000 | AQ60: =+AP60/$A$1 -> 795.1383 | AR60: =+AP60*F60 -> 3500000 | AS60: =+AR60/$A$1 -> 795.1383 | AT60: =+AP60*I60 -> 0 | AU60: =+AT60/$A$1 -> 0 | BH60: =+AR60+AT60-AP60 -> 0
A61: 7.2. Financial/bank expenses | B61: month | C61: 12 | D61: 300000 | E61: =+D61/$A$1 -> 68.154711 | F61: 1 | G61: =L61*F61 -> 3600000 | H61: =+G61/$A$1 -> 817.85653 | I61: 0 | J61: =L61*I61 -> 0 | K61: =+J61/$A$1 -> 0 | L61: =+C61*D61 -> 3600000 | M61: =+L61/$A$1 -> 817.85653 | O61: =B61 -> month | P61: 12 | Q61: =+D61*(1+10%) -> 330000 | R61: =+Q61/$A$1 -> 74.970182 | S61: 1 | T61: =+S61*Y61 -> 3960000 | U61: =+T61/$A$1 -> 899.64219 | V61: 0 | W61: =+V61*Y61 -> 0 | X61: =+W61/$A$1 -> 0 | Y61: =+P61*Q61 -> 3960000 | Z61: =+Y61/$A$1 -> 899.64219 | AB61: =B61 -> month | AC61: 4 | AD61: =+Q61*(1+8%) -> 356400 | AE61: =+AD61/$A$1 -> 80.967797 | AF61: 1 | AG61: =+AF61*AL61 -> 1425600 | AH61: =+AG61/$A$1 -> 323.87119 | AI61: 0 | AJ61: =+AI61*AL61 -> 0 | AK61: =+AJ61/$A$1 -> 0 | AL61: =+AC61*AD61 -> 1425600 | AM61: =+AL61/$A$1 -> 323.87119 | AP61: =+L61+Y61+AL61 -> 8985600 | AQ61: =+AP61/$A$1 -> 2041.3699 | AR61: =+AP61*F61 -> 8985600 | AS61: =+AR61/$A$1 -> 2041.3699 | AT61: =+AP61*I61 -> 0 | AU61: =+AT61/$A$1 -> 0 | BA61: =+BA51/AP51 -> 0.22222222 | BH61: =+AR61+AT61-AP61 -> 0
A62: 7.3 Adobe Acrobat licence | B62: license | C62: 3 | D62: 1000000 | E62: =+D62/$A$1 -> 227.18237 | F62: 1 | G62: =L62*F62 -> 3000000 | H62: =+G62/$A$1 -> 681.54711 | I62: 0 | J62: =L62*I62 -> 0 | K62: =+J62/$A$1 -> 0 | L62: =+C62*D62 -> 3000000 | M62: =+L62/$A$1 -> 681.54711 | O62: =B62 -> license | R62: =+Q62/$A$1 -> 0 | S62: 1 | T62: =+S62*Y62 -> 0 | U62: =+T62/$A$1 -> 0 | V62: 0 | W62: =+V62*Y62 -> 0 | X62: =+W62/$A$1 -> 0 | Z62: =+Y62/$A$1 -> 0 | AB62: =B62 -> license | AE62: =+AD62/$A$1 -> 0 | AF62: 1 | AG62: =+AF62*AL62 -> 0 | AH62: =+AG62/$A$1 -> 0 | AI62: 0 | AJ62: =+AI62*AL62 -> 0 | AK62: =+AJ62/$A$1 -> 0 | AM62: =+AL62/$A$1 -> 0 | AP62: =+L62+Y62+AL62 -> 3000000 | AQ62: =+AP62/$A$1 -> 681.54711 | AR62: =+AP62*F62 -> 3000000 | AS62: =+AR62/$A$1 -> 681.54711 | AT62: =+AP62*I62 -> 0 | AU62: =+AT62/$A$1 -> 0 | BH62: =+AR62+AT62-AP62 -> 0
A63: 7.4 Office and antivirus license 13 computers | B63: month | C63: 12 | D63: =(2200+68000)*13 -> 912600 | E63: =+D63/$A$1 -> 207.32663 | F63: 1 | G63: =L63*F63 -> 10951200 | H63: =+G63/$A$1 -> 2487.9196 | I63: 0 | J63: =L63*I63 -> 0 | K63: =+J63/$A$1 -> 0 | L63: =+C63*D63 -> 10951200 | M63: =+L63/$A$1 -> 2487.9196 | O63: =B63 -> month | P63: 12 | Q63: =+(2200+68000)*(1+10%)*13 -> 1003860 | R63: =+Q63/$A$1 -> 228.05929 | S63: 1 | T63: =+S63*Y63 -> 12046320 | U63: =+T63/$A$1 -> 2736.7115 | V63: 0 | W63: =+V63*Y63 -> 0 | X63: =+W63/$A$1 -> 0 | Y63: =+P63*Q63 -> 12046320 | Z63: =+Y63/$A$1 -> 2736.7115 | AB63: =B63 -> month | AC63: 4 | AD63: =+(2200+68000)*(1+10%)*(1+8%)*10 -> 833976 | AE63: =+AD63/$A$1 -> 189.46464 | AF63: 1 | AG63: =+AF63*AL63 -> 3335904 | AH63: =+AG63/$A$1 -> 757.85858 | AI63: 0 | AJ63: =+AI63*AL63 -> 0 | AK63: =+AJ63/$A$1 -> 0 | AL63: =+AC63*AD63 -> 3335904 | AM63: =+AL63/$A$1 -> 757.85858 | AP63: =+L63+Y63+AL63 -> 26333424 | AQ63: =+AP63/$A$1 -> 5982.4897 | AR63: =+AP63*F63 -> 26333424 | AS63: =+AR63/$A$1 -> 5982.4897 | AT63: =+AP63*I63 -> 0 | AU63: =+AT63/$A$1 -> 0 | AZ63: 42982618 | BA63: =+AZ63/16 -> 2686413.6 | BB63: =+BA63*3 -> 8059240.9 | BH63: =+AR63+AT63-AP63 -> 0
A64: 7.5 Life insurance * 13 | B64: month | C64: 12 | D64: =18400*13 -> 239200 | E64: =+D64/$A$1 -> 54.342023 | F64: 1 | G64: =L64*F64 -> 2870400 | H64: =+G64/$A$1 -> 652.10428 | I64: 0 | J64: =L64*I64 -> 0 | K64: =+J64/$A$1 -> 0 | L64: =+C64*D64 -> 2870400 | M64: =+L64/$A$1 -> 652.10428 | O64: =B64 -> month | P64: 12 | Q64: =18400*(1+10%)*13 -> 263120 | R64: =+Q64/$A$1 -> 59.776225 | S64: 1 | T64: =+S64*Y64 -> 3157440 | U64: =+T64/$A$1 -> 717.3147 | V64: 0 | W64: =+V64*Y64 -> 0 | X64: =+W64/$A$1 -> 0 | Y64: =+P64*Q64 -> 3157440 | Z64: =+Y64/$A$1 -> 717.3147 | AB64: =B64 -> month | AC64: 4 | AD64: =18400*(1+10%)*(1+8%)*10 -> 218592 | AE64: =+AD64/$A$1 -> 49.660249 | AF64: 1 | AG64: =+AF64*AL64 -> 874368 | AH64: =+AG64/$A$1 -> 198.641 | AI64: 0 | AJ64: =+AI64*AL64 -> 0 | AK64: =+AJ64/$A$1 -> 0 | AL64: =+AC64*AD64 -> 874368 | AM64: =+AL64/$A$1 -> 198.641 | AP64: =+L64+Y64+AL64 -> 6902208 | AQ64: =+AP64/$A$1 -> 1568.06 | AR64: =+AP64*F64 -> 6902208 | AS64: =+AR64/$A$1 -> 1568.06 | AT64: =+AP64*I64 -> 0 | AU64: =+AT64/$A$1 -> 0 | BC64: =+AP64/16 -> 431388 | BD64: =+BC64*3 -> 1294164 | BE64: =+BD64/AP64 -> 0.1875 | BH64: =+AR64+AT64-AP64 -> 0
A65: =+'Summary Budget'!E68 -> Administrative expenses | B65: % | C65: 0.05 | G65: =(G52+G50+G46+G41+G22+G59+G3)*C65 -> 73312869 | H65: =+G65/$A$1 -> 16655.391 | J65: =(J52+J50+J46+J41+J22+J59+J3)*C65 -> 13543517 | K65: =+J65/$A$1 -> 3076.8483 | L65: =(L52+L50+L46+L41+L22+L3)*C65 -> 86856386 | M65: =+L65/$A$1 -> 19732.24 | O65: =B65 -> % | P65: =C65 -> 0.05 | R65: =+Q65/$A$1 -> 0 | T65: =(T52+T50+T46+T41+T22+T59+T3)*P65 -> 79177105 | U65: =+T65/$A$1 -> 17987.643 | W65: =(W52+W50+W46+W41+W22+W3)*P65 -> 63307869 | X65: =+W65/$A$1 -> 14382.432 | Y65: =(Y52+Y50+Y46+Y41+Y22+Y3)*P65 -> 1.4248497e+08 | Z65: =+Y65/A1 -> 32370.074 | AB65: =B65 -> % | AC65: =C65 -> 0.05 | AE65: =+AD65/$A$1 -> 0 | AG65: =(AG52+AG50+AG46+AG41+AG22+AG59+AG3)*AC65 -> 15067454 | AH65: =+AG65/A1 -> 3423.06 | AJ65: =(AJ52+AJ50+AJ46+AJ41+AJ22+AJ59+AJ3)*AC65 -> 3174662.9 | AK65: =+AJ65/A1 -> 721.22745 | AL65: =(AL52+AL50+AL46+AL41+AL22+AL3)*AC65 -> 18242117 | AM65: =+AL65/A1 -> 4144.2874 | AP65: =+L65+Y65+AL65 -> 2.4758348e+08 | AQ65: =+AP65/$A$1 -> 56246.601 | AR65: =(AR52+AR50+AR46+AR41+AR3+AR59+AR22)*C65 -> 1.6755743e+08 | AS65: =+AR65/$A$1 -> 38066.094 | AT65: =(AT52+AT50+AT46+AT41+AT22+AT59+AT3)*C65 -> 80026049 | AU65: =+AT65/$A$1 -> 18180.507 | AZ65: =+#REF!/AP65 -> #REF!
A66: Total proposal COP | G66: =(G52+G50+G46+G41+G22+G3+G59+G65) -> 1.5395702e+09 | H66: =+H3+H22+H41+H46+H50+H52+H59+H65 -> 349763.22 | J66: =(J52+J50+J46+J41+J22+J3+J65) -> 284413857 | K66: =+K3+K22+K41+K46+K50+K52+K59+K65 -> 64613.814 | L66: =+SUM(L3,L65,L52,L50,L46,L41,L22) -> 1.8239841e+09 | M66: =+M3+M22+M41+M46+M50+M52+M65 -> 414377.03 | T66: =(T52+T50+T46+T41+T22+T59+T3+T65) -> 1.6627192e+09 | U66: =+U3+U22+U41+U46+U50+U59+U52+U65 -> 377740.49 | W66: =(W52+W50+W46+W41+W22+W3+W59+W65) -> 1.3294652e+09 | X66: =+X3+X22+X41+X46+X50+X52+X59+X65 -> 302031.07 | Y66: =+SUM(Y3,Y65,Y52,Y50,Y46,Y41,Y22) -> 2.9921845e+09 | Z66: =+Z3+Z22+Z41+Z46+Z50+Z52+Z65 -> 679771.56 | AG66: =(AG52+AG50+AG46+AG41+AG22+AG3+AG59+AG65) -> 3.1641654e+08 | AH66: =+AH3+AH22+AH41+AH46+AH50+AH52+AH59+AH65 -> 71884.259 | AJ66: =(AJ52+AJ50+AJ46+AJ41+AJ22+AJ3+AJ59+AJ65) -> 66667921 | AK66: =+AK3+AK22+AK41+AK46+AK50+AK52+AK59+AK65 -> 15145.776 | AL66: =+SUM(AL3,AL65,AL52,AL50,AL46,AL41,AL22) -> 3.8308446e+08 | AM66: =+AM3+AM22+AM41+AM46+AM50+AM52+AM65 -> 87030.036
A67: Total obligated amount C4D | F67: =+AR67/AP67 -> 0.67677145 | L67: =+G66 -> 1.5395702e+09 | Y67: =+T66 -> 1.6627192e+09 | AL67: =+AG66 -> 3.1641654e+08 | AP67: =+AP52+AP50+AP46+AP41+AP22+AP3+AP59+AP65 -> 5.199253e+09 | AQ67: =+AQ3+AQ22+AQ41+AQ46+AQ50+AQ52+AQ59+AQ65 -> 1181178.6 | AR67: =AR3+AR22+AR41+AR46+AR50+AR52+AR59+AR65 -> 3.518706e+09 | AS67: =+AS3+AS22+AS41+AS46+AS50+AS52+AS59+AS65 -> 799387.97 | AT67: =+AP67*I67 -> 0
A68: Total Cost - Share | AT68: =+AT3+AT22+AT41+AT46+AT50+AT52+AT65 -> 1.680547e+09 | AU68: =+AU3+AU22+AU41+AU46+AU50+AU52+AU65 -> 381790.66
D71: =#REF!*F67 -> #REF! | Y71: =#REF!*F67 -> #REF!

Sheet Travels
A2: Department | B2: # Associations | C2: #PSE | D2: #Trips
A3: ANTIOQUIA 6 | B3: 6 | C3: 3 | D3: 3
A4: CALDAS 5 | B4: 5
A5: CORDOBA 6 | B5: 6
A6: LA GUAJIRA 1 | B6: 1 | C6: 1 | D6: 3
A7: BOLIVAR 1 | B7: 1
A8: CESAR 7 | B8: 7
A9: MAGDALENA 1 | B9: 1
A10: HUILA 7 | B10: 7 | C10: 2 | D10: 2
A11: CAUCA | B11: 3
A12: SANTANDER 6 | B12: 6 | C12: 1 | D12: 1
A13: TOLIMA 31 | B13: 31 | C13: 2 | D13: 3
A14: TOTAL | B14: =+SUM(B3:B13) -> 74 | C14: =+SUM(C3:C13) -> 9 | D14: =+SUM(D3:D13) -> 12
A16: COP
B17: Diagnosis | I17: Strengthening
A18: Staff | B18: # Trips | C18: Airline tickets | D18: Lodging 4 nights | E18: Perdiem 5 days | F18: Land transportation | G18: Total | I18: # Trips | J18: Airline tickets | K18: Lodging 4 nights | L18: Perdiem 5 days | M18: Land transportation | N18: Total
A19: =+'Summary Budget'!E7 -> 1.1. Program Coordinator | B19: 1 | C19: 1000000 | D19: 400000 | E19: =90000*5 -> 450000 | F19: 150000 | G19: =+SUM(C19:F19)*B19 -> 2000000 | I19: 3 | J19: 1000000 | K19: 400000 | L19: =90000*5 -> 450000 | M19: 150000 | N19: =+SUM(J19:M19)*I19 -> 6000000
A20: =+'Summary Budget'!E8 -> 1.2. Business Strengthening Coordinator | B20: 4 | C20: 1000000 | D20: 400000 | E20: =90000*5 -> 450000 | F20: 150000 | G20: =+SUM(C20:F20)*B20 -> 8000000 | I20: 9 | J20: 1000000 | K20: 400000 | L20: =90000*5 -> 450000 | M20: 150000 | N20: =+SUM(J20:M20)*I20 -> 18000000
A21: =+'Summary Budget'!E9 -> 1.3. Cacao technical specialist | B21: 4 | C21: 1000000 | D21: 400000 | E21: =90000*5 -> 450000 | F21: 150000 | G21: =+SUM(C21:F21)*B21 -> 8000000 | I21: 9 | J21: 1000000 | K21: 400000 | L21: =90000*5 -> 450000 | M21: 150000 | N21: =+SUM(J21:M21)*I21 -> 18000000
A22: =+'Summary Budget'!E10 -> 1.4. Organizational Professional | B22: 3 | C22: 1000000 | D22: 400000 | E22: =90000*5 -> 450000 | F22: 150000 | G22: =+SUM(C22:F22)*B22 -> 6000000 | I22: 9 | J22: 1000000 | K22: 400000 | L22: =90000*5 -> 450000 | M22: 150000 | N22: =+SUM(J22:M22)*I22 -> 18000000
A23: =+'Summary Budget'!E11 -> 1.5. F&A Specialist | B23: 3 | C23: 1000000 | D23: 400000 | E23: =90000*5 -> 450000 | F23: 150000 | G23: =+SUM(C23:F23)*B23 -> 6000000 | I23: 6 | J23: 1000000 | K23: 400000 | L23: =90000*5 -> 450000 | M23: 150000 | N23: =+SUM(J23:M23)*I23 -> 12000000
A24: =+'Summary Budget'!E12 -> 1.6. Business Partner Professional Antioquia, Córdoba 1 | B24: 3 | C24: 0 | D24: 400000 | E24: =90000*5 -> 450000 | F24: 300000 | G24: =+SUM(C24:F24)*B24 -> 3450000 | I24: 15 | J24: 0 | K24: 400000 | L24: =90000*5 -> 450000 | M24: 300000 | N24: =+SUM(J24:M24)*I24 -> 17250000
A25: =+'Summary Budget'!E13 -> 1.7. Business Partner Professional Antioquia, Córdoba 2 | B25: 3 | C25: 0 | D25: 400000 | E25: =90000*5 -> 450000 | F25: 300000 | G25: =+SUM(C25:F25)*B25 -> 3450000 | I25: 15 | J25: 0 | K25: 400000 | L25: =90000*5 -> 450000 | M25: 300000 | N25: =+SUM(J25:M25)*I25 -> 17250000
A26: =+'Summary Budget'!E14 -> 1.8. Business Partner Professional Caldas | B26: 3 | C26: 0 | D26: 400000 | E26: =90000*5 -> 450000 | F26: 300000 | G26: =+SUM(C26:F26)*B26 -> 3450000 | I26: 15 | J26: 0 | K26: 400000 | L26: =90000*5 -> 450000 | M26: 300000 | N26: =+SUM(J26:M26)*I26 -> 17250000
A27: =+'Summary Budget'!E15 -> 1.9. Business Partner Professional Guajira, Cesar, Magdalena | B27: 3 | C27: 0 | D27: 400000 | E27: =90000*5 -> 450000 | F27: 300000 | G27: =+SUM(C27:F27)*B27 -> 3450000 | I27: 15 | J27: 0 | K27: 400000 | L27: =90000*5 -> 450000 | M27: 300000 | N27: =+SUM(J27:M27)*I27 -> 17250000
A28: =+'Summary Budget'!E16 -> 1.10. Business Partner Professional Huila | B28: 3 | C28: 0 | D28: 400000 | E28: =90000*5 -> 450000 | F28: 300000 | G28: =+SUM(C28:F28)*B28 -> 3450000 | I28: 15 | J28: 0 | K28: 400000 | L28: =90000*5 -> 450000 | M28: 300000 | N28: =+SUM(J28:M28)*I28 -> 17250000
A29: =+'Summary Budget'!E17 -> 1.11. Business Partner Professional Santander and Bolivar | B29: 3 | C29: 0 | D29: 400000 | E29: =90000*5 -> 450000 | F29: 300000 | G29: =+SUM(C29:F29)*B29 -> 3450000 | I29: 15 | J29: 0 | K29: 400000 | L29: =90000*5 -> 450000 | M29: 300000 | N29: =+SUM(J29:M29)*I29 -> 17250000
A30: =+'Summary Budget'!E18 -> 1.12. Business Partner Professional Cauca | B30: 3 | C30: 0 | D30: 400000 | E30: =90000*5 -> 450000 | F30: 300000 | G30: =+SUM(C30:F30)*B30 -> 3450000 | I30: 15 | J30: 0 | K30: 400000 | L30: =90000*5 -> 450000 | M30: 300000 | N30: =+SUM(J30:M30)*I30 -> 17250000
... A32: =+'Summary Budget'!E20 -> 1.14. Business Partner Professional Tolima 2 | B32: 3 | C32: 0 | D32: 400000 | E32: =90000*5 -> 450000 | F32: 300000 | G32: =+SUM(C32:F32)*B32 -> 3450000 | I32: 15 | J32: 0 | K32: 400000 | L32: =90000*5 -> 450000 | M32: 300000 | N32: =+SUM(J32:M32)*I32 -> 17250000
G33: =+SUM(G19:G32) -> 61050000 | N33: =+SUM(N19:N32) -> 227250000
B34: Diagnosis
A35: 2.1. Air transportation | B35: =+SUM(B19:B23) -> 15 | C35: =+C22 -> 1000000 | D35: =+B35*C35 -> 15000000
A36: 2.3. Land transportation | B36: =+SUM(B19:B23)+(SUM(B24:B32)*2) -> 69 | C36: 150000 | D36: =+B36*C36 -> 10350000
A37: 2.4. Lodging | B37: =+SUM(B19:B32)*4 -> 168 | C37: 100000 | D37: =+B37*C37 -> 16800000
A38: 2.5. Perdiem | B38: =+SUM(B19:B32)*5 -> 210 | C38: 90000 | D38: =+B38*C38 -> 18900000 | E38: =+SUM(D35:D38) -> 61050000
B40: Quantity | C40: Assistants | D40: Unit value | E40: Total
A41: Perdiem (snacks and lunches) diagnosis workshop | B41: =+B14 -> 74 | C41: 10 | D41: =20000+14000+5000 -> 39000 | E41: =+D41*C41*B41 -> 28860000
A42: Materials (stationery: cardstock, markers, cards, etc.) diagnosis workshop | B42: =+B41 -> 74 | C42: =+C41 -> 10 | D42: 3500 | E42: =+D42*C42*B42 -> 2590000
A43: Perdiem (snacks and lunches) strengthening workshop | B43: =74*3 -> 222 | C43: 8 | D43: =20000+14000+5000 -> 39000 | E43: =+D43*C43*B43 -> 69264000
A44: Materials (stationery: cardstock, markers, cards, etc.) strengthening workshop | B44: =74*3 -> 222 | C44: =+C43 -> 8 | D44: 3500 | E44: =+D44*C44*B44 -> 6216000
B46: Fortalecimiento
A47: 2.1. Air transportation | B47: =+SUM(I19:I23) -> 36 | C47: 1000000 | D47: =+B47*C47 -> 36000000
A48: 2.3. Land transportation | B48: =+SUM(I19:I23)+(SUM(I24:I32)*2) -> 306 | C48: 150000 | D48: =+B48*C48 -> 45900000
A49: 2.4. Lodging | B49: =+SUM(I19:I32)*4 -> 684 | C49: 100000 | D49: =+B49*C49 -> 68400000
A50: 2.5. Perdiem | B50: =+SUM(I19:I32)*5 -> 855 | C50: 90000 | D50: =+B50*C50 -> 76950000 | E50: =+SUM(D47:D50) -> 227250000 | G50: =+E50+E38 -> 288300000
A53: USD
B54: Diagnosis | I54: Strengthening
A55: Staff | B55: # Trips | C55: Airline tickets | D55: Lodging 4 nights | E55: Perdiem 5 days | F55: Land transportation | G55: Total | I55: # Trips | J55: Airline tickets | K55: Lodging 4 nights | L55: Perdiem 5 days | M55: Land transportation | N55: Total
A56: 3. Trips | B56: 1 | C56: 227 | D56: 91 | E56: 102 | F56: 34 | G56: 454 | I56: 3 | J56: 227 | K56: 91 | L56: 102 | M56: 34 | N56: 1363
A57: 3.1. Air transportation | B57: 4 | C57: 227 | D57: 91 | E57: 102 | F57: 34 | G57: 1817 | I57: 9 | J57: 227 | K57: 91 | L57: 102 | M57: 34 | N57: 4089
A58: 3.2. Land transportation | B58: 4 | C58: 227 | D58: 91 | E58: 102 | F58: 34 | G58: 1817 | I58: 9 | J58: 227 | K58: 91 | L58: 102 | M58: 34 | N58: 4089
A59: 3.3. Lodging | B59: 3 | C59: 227 | D59: 91 | E59: 102 | F59: 34 | G59: 1363 | I59: 9 | J59: 227 | K59: 91 | L59: 102 | M59: 34 | N59: 4089
A60: 3.4. Perdiem | B60: 3 | C60: 227 | D60: 91 | E60: 102 | F60: 34 | G60: 1363 | I60: 6 | J60: 227 | K60: 91 | L60: 102 | M60: 34 | N60: 2726
A61: 4. Professional services (consultants) | B61: 3 | C61: 0 | D61: 91 | E61: 102 | F61: 68 | G61: 784 | I61: 15 | J61: 0 | K61: 91 | L61: 102 | M61: 68 | N61: 3919
A62: 4.1. Construction of cocoa and complementary products business models / Muttuo | B62: 3 | C62: 0 | D62: 91 | E62: 102 | F62: 68 | G62: 784 | I62: 15 | J62: 0 | K62: 91 | L62: 102 | M62: 68 | N62: 3919
A63: 4.2. Financial feasibility assessments | B63: 3 | C63: 0 | D63: 91 | E63: 102 | F63: 68 | G63: 784 | I63: 15 | J63: 0 | K63: 91 | L63: 102 | M63: 68 | N63: 3919
A64: 4.3. Business consulting (marketing, communications, quality, processes, invoicing) | B64: 3 | C64: 0 | D64: 91 | E64: 102 | F64: 68 | G64: 784 | I64: 15 | J64: 0 | K64: 91 | L64: 102 | M64: 68 | N64: 3919
A65: 5. Materials | B65: 3 | C65: 0 | D65: 91 | E65: 102 | F65: 68 | G65: 784 | I65: 15 | J65: 0 | K65: 91 | L65: 102 | M65: 68 | N65: 3919
A66: 5.1. Perdiem (snacks and lunches) diagnostic workshops | B66: 3 | C66: 0 | D66: 91 | E66: 102 | F66: 68 | G66: 784 | I66: 15 | J66: 0 | K66: 91 | L66: 102 | M66: 68 | N66: 3919
A67: 5.2. Materials (stationery: cardboard, markers, cards, etc.) diagnostic workshops | B67: 3 | C67: 0 | D67: 91 | E67: 102 | F67: 68 | G67: 784 | I67: 15 | J67: 0 | K67: 91 | L67: 102 | M67: 68 | N67: 3919
... A69: 5.4. Materiales (stationery: cardboard, markers, cards, etc.) strengthening workshop | B69: 3 | C69: 0 | D69: 91 | E69: 102 | F69: 68 | G69: 784 | I69: 15 | J69: 0 | K69: 91 | L69: 102 | M69: 68 | N69: 3919
G70: 13869 | N70: 51627
B71: Diagnosis
A72: 2.1. Air transportation | B72: 15 | C72: 227 | D72: 3407.74
A73: 2.3. Land transportation | B73: 69 | C73: 34 | D73: 2351.34
A74: 2.4. Lodging | B74: 168 | C74: 23 | D74: 3816.66
A75: 2.5. Perdiem | B75: 210 | C75: 20 | D75: 4293.75 | E75: 13869.48
B77: Quantity | C77: Assistants | D77: Unit value | E77: Total
A78: Perdiem (snacks and lunches) diagnosis workshop | B78: 0 | C78: 10 | D78: 8.86 | E78: 6556.48
A79: Materials (stationery: cardstock, markers, cards, etc.) diagnosis workshop | B79: 0 | C79: 10 | D79: 0.8 | E79: 588.4
A80: Perdiem (snacks and lunches) strengthening workshop | B80: 222 | C80: 8 | D80: 8.86 | E80: 15735.56
A81: Materials (stationery: cardstock, markers, cards, etc.) strengthening workshop | B81: 222 | C81: 8 | D81: 0.8 | E81: 1412.17
B83: Strengthening
A84: 2.1. Air transportation | B84: 36 | C84: 227.18 | D84: 8178.57
A85: 2.3. Land transportation | B85: 306 | C85: 34.08 | D85: 10427.67
A86: 2.4. Lodging | B86: 684 | C86: 22.72 | D86: 15539.27
A87: 2.5. Perdiem | B87: 855 | C87: 20.45 | D87: 17481.68 | E87: 51627.19 | G87: 65496.68

Sheet Deliverables
A1: # | B1: Phase | C1: Products | D1: Deadline
A2: 1 | B2: Planning | C2: Work plan, schedule of activities and monitoring plan that includes the quantitative and qualitative tools of the methodology, knowledge evaluation for the trained personnel and the battery of indicators. | D2: Mes 1
A3: 2 | B3: Phase 1 | C3: Diagnosis of the organizations according to the methodology developed by the Sub-recipient. The results of the special studies conducted by C4D should be used, as well as the characterization surveys processed by the M&E team, specific surveys and focus groups developed by the Sub-recipient along with other secondary information sources. | D3: Mes 5
A4: 3 | B4: Phase 2 | C4: Document containing the classification system of the organizations based on the results of the diagnosis. | D4: Mes 6
A5: 4 | B5: Phase 3 | C5: Report of gaps and opportunities for each of the organizations based on the diagnostic and characterization results. For each organization, the gaps that exist between its current situation and the following classification should be specified in order to determine opportunities for improvement. | D5: Mes 6
A6: 5 | B6: Phase 4 | C6: Memories, attendance lists and photographic records of the socializations held with each of the producer organizations, to share the findings of the diagnosis and characterization, the analysis of gaps and opportunities, and to determine possible action plans and the basis for structuring the strengthening plan and preparing the administrative, financial and commercial plans. | D6: Mes 8
A7: 6 | B7: Phase 5 | C7: Document containing the strengthening plan by association. | D7: Mes 8
A8: 7 | C8: Memories, attendance lists and photographic records of the face-to-face and virtual workshops of at least two types: Organizational Development Core and Leadership Development to develop the administrative, financial and commercial skills of each organization's team. | D8: Mes 12
A9: 8 | B9: Phase 6 | C9: Document containing: In-depth and detailed diagnosis of the cacao commercial situation of each of the organizations including but not limited to: characterization of their customers including demand profile, area of influence, available market, analysis of profitability and commercial processes, bargaining power, efficiency of the operational structure and commercial activities, attention to customer needs, sales arguments, differentiators, advertising and media, total sales history, by customer, region, among others. | D9: Mes 12
A10: 9 | C10: Document containing marketing plans adapted to the current and potential capabilities of each of the organizations. | D10: Mes 12
A11: 10 | C11: Document with the impact analysis and diagnosis of the way in which each organization is communicating with customers and recommendations to optimize communication processes and, if necessary, advertising and digital advertising. Workshop report on contracting and pricing strategies, export plan for organizations that according to the diagnosis are in a position to do so, new opportunities from local and international business rounds and support in the management of current and new business relationships. | D11: Mes 12
A12: 11 | B12: Phase 7 | C12: Feasibility report on the implementation of business models for cacao by-products, by-products of complementary crops and by-products of complementary crops. | D12: Mes 13 Mes 25 Mes 36
A13: 12 | C13: Feasibility report on the financing of associative enterprises. | D13: Mes 16
A14: 13 | B14: Phase 8 | C14: Document containing the result of the final evaluation based on the methodology for measuring the level of enterprise development (NDE), the comparison with the results of the baseline and the recommendations in each of the measurements evaluated. | D14: Mes 13 Mes 25 Mes 36
A15: 14 | B15: Phase 9 | C15: Final report containing: | D15: Mes 13 Mes 25 Mes 36
C17: Results of the implementation of the cacao trade strategy.
C19: Improvement plan and continuity plan for next year, including justification as to why the Sub-recipient should continue implementing the activities.
