Workbook

Sheet Datos Alta
A1: LISTA DE PERSONAL PARA ASEGURAR ANTE EL IMSS
A4: No. | B4: Proyecto | C4: NSS | D4: Digito verificador | E4: Nombre | F4: Apellido paterno | G4: Apellido materno | H4: RFC | I4: CURP | J4: SDI | K4: Tipo de salario | L4: Fecha de movimiento
A5: 1 | B5: DOL423 | C5: 0322921956 | D5: 7 | E5: ALECK FEDERICO | F5: SABAH | G5: MÁRQUEZ MEES | H5: SAMA921026IDA | I5: SAMA921026HDFBRL01 | J5: =Salarios!Q5 -> 2096.9946 | K5: Fijo | L5: 44774
A6: 2 | B6: DOL425 | E6: ALMA CLARISA | F6: RICO | G6: DIAZ | H6: RIDA5903273Q8 | I6: RIDA590327MSRCZL05 | J6: =Salarios!Q6 -> 5591.9926 | K6: Fijo | L6: 44774
A7: 3 | B7: DOL423 | C7: 0220845574 | D7: 7 | E7: ALONSO | F7: SANTIBAÑEZ | G7: COBOS | H7: SACA8403029S2 | I7: SACA840302HDFNBL02 | J7: =Salarios!Q7 -> 4193.9997 | K7: Fijo | L7: 44774
A8: 4 | B8: DOL425 | C8: 3711840238 | D8: 9 | E8: AZUCENA | F8: AGUIRRE | G8: CRESPO | H8: AUCA840406B72 | I8: AUCA840406MMSGRZ05 | J8: =Salarios!Q8 -> 3075.597 | K8: Fijo | L8: 44774
A9: 5 | B9: DOL423 DOL425 DOS452 | C9: 0316831851 | D9: 1 | E9: AZUCENA | F9: SANDOVAL | G9: ALCIBAR | H9: SAAA8311277K9 | I9: SAAA831127MDFNLZ07 | J9: =Salarios!Q9 -> 1404.9929 | K9: Fijo | L9: 44774
A10: 6 | B10: DOL423 | C10: 0101850937 | D10: 0 | E10: DIEGO ORLANDO | F10: MONROY | G10: HERNANDEZ | H10: MOHD851108TV7 | I10: MOHD851108HDFNRG08 | J10: =Salarios!Q10 -> 1328.098 | K10: Fijo | L10: 44774
A11: 7 | B11: DOL423 | C11: 4386663484 | D11: 3 | E11: GABRIEL ORLANDO | F11: VELAZQUEZ | G11: CHAVEZ | H11: VECG660726UJ3 | I11: VECG660726HDFLHB08 | J11: =Salarios!Q11 -> 3075.597 | K11: Fijo | L11: 44774
A12: 8 | B12: DOL425 | C12: 0222705961 | D12: 1 | E12: GRACIELA | F12: VARGAS | G12: GARCIA | H12: VAGG700323462 | I12: VAGG700323MDFRRR07 | J12: =Salarios!Q12 -> 2446.5007 | K12: Fijo | L12: 44774
A13: 9 | B13: DOL425 | C13: 6510820076 | D13: 0 | E13: LIZET | F13: GUEVARA | G13: ALCÁNTARA | H13: GUAL820504N91 | I13: GUAL820504MVZVLZ03 | J13: =Salarios!Q13 -> 1328.098 | K13: Fijo | L13: 44774
A14: 10 | B14: DOL423 | C14: 0218891660 | D14: 1 | E14: MARTHA ISABEL | F14: LOPEZ | G14: ESCOBAR | H14: LOEM890911672 | I14: LOEM890911MTCPSR08 | J14: =Salarios!Q14 -> 2995.2126 | K14: Fijo | L14: 44774
A15: 11 | B15: DOL423 DOL425 DOS452 | C15: 3007750058 | D15: 2 | E15: ROMAN ALBERTO | F15: ROJAS | G15: HERNANDEZ | H15: ROHR750807263 | I15: ROHR750807HDFJRM05 | J15: =Salarios!Q15 -> 4718.2431 | K15: Fijo | L15: 44774
A16: 12 | B16: DOS452 | C16: 7206861046 | D16: 7 | E16: SASKIA | F16: CABRERA | G16: PADILLA | H16: CAPS861227JG4 | I16: CAPS861227MGRBDS06 | J16: =Salarios!Q16 -> 2621.2485 | K16: Fijo | L16: 44774
A17: 13 | B17: DOL425 | C17: 0816918397 | D17: 0 | E17: VERÓNICA | F17: ROMERO | G17: GUERRERO | H17: ROGV910414HY4 | I17: ROGV910414MDFMRR03 | J17: =Salarios!Q17 -> 1957.1943 | K17: Fijo | L17: 44774
A18: 14 | B18: DOL425 | C18: 0322921546 | D18: 6 | E18: VICTORIA | F18: LÓPEZ | G18: CARMONA | H18: LOCV9206101F3 | I18: LOCV920610MNEPRC08 | J18: =Salarios!Q18 -> 1404.9929 | K18: Fijo | L18: 44774
A19: 15 | B19: DOL425 | C19: 3997822075 | D19: 2 | E19: XANNY | F19: HERNANDEZ | G19: HERNANDEZ | H19: HEHX820730P48 | I19: HEHX820730MDFRRN01 | J19: =Salarios!Q19 -> 2096.9946 | K19: Fijo | L19: 44774
A20: 16 | B20: DOS452 | C20: 2007890769 | D20: 6 | E20: YAEL IVONNE | F20: CAYETANO | G20: FIGUEROA | H20: CAFY8901267T0 | I20: CAFY890126MDFYGL06 | J20: =Salarios!Q20 -> 1177.8186 | K20: Fijo | L20: 44774

Sheet Salarios
A1: Determinación del Salario Diario Integrado
F3: USD | K3: Salario diario MXN | O3: Salario base de cotización MXN
A4: No. | B4: Nombre | C4: Appellido paterno | D4: Apellido materno | E4: Fecha de ingreso (Consultoría) | F4: Salario mensual | G4: Fringe mensual | H4: Salario + Fringe mensual | I4: Tipo de cambio promedio a Ago/2022 | K4: Salario mensual | L4: Factor | M4: Salario diario | O4: Salario mensual | P4: Factor de integración | Q4: Salario diario integrado | S4: Promedio de TC
A5: ='Datos Alta'!A5 -> 1 | B5: ='Datos Alta'!E5 -> ALECK FEDERICO | C5: ='Datos Alta'!F5 -> SABAH | D5: ='Datos Alta'!G5 -> MÁRQUEZ MEES | E5: 44287 | F5: 3000 | G5: 746.45 | H5: =F5+G5 -> 3746.45 | I5: =T13 -> 20.291594 | K5: =F5*I5 -> 60874.782 | L5: =ROUND((365/12),2) -> 30.42 | M5: =ROUND((K5/L5),2) -> 2001.14 | O5: =M5 -> 2001.14 | P5: 1.0479 | Q5: =O5*P5 -> 2096.9946 | S5: Mes | T5: Tipo de cambio
A6: ='Datos Alta'!A6 -> 2 | B6: ='Datos Alta'!E6 -> ALMA CLARISA | C6: ='Datos Alta'!F6 -> RICO | D6: ='Datos Alta'!G6 -> DIAZ | E6: 44211 | F6: 8000 | G6: 1341.99 | H6: =F6+G6 -> 9341.99 | I6: =+I5 -> 20.291594 | K6: =F6*I6 -> 162332.75 | L6: =ROUND((365/12),2) -> 30.42 | M6: =ROUND((K6/L6),2) -> 5336.38 | O6: =M6 -> 5336.38 | P6: 1.0479 | Q6: =O6*P6 -> 5591.9926 | S6: Enero | T6: 20.491508
A7: ='Datos Alta'!A7 -> 3 | B7: ='Datos Alta'!E7 -> ALONSO | C7: ='Datos Alta'!F7 -> SANTIBAÑEZ | D7: ='Datos Alta'!G7 -> COBOS | E7: 44579 | F7: 6000 | G7: =7133.66-F7 -> 1133.66 | H7: =F7+G7 -> 7133.66 | I7: =+I6 -> 20.291594 | K7: =F7*I7 -> 121749.56 | L7: =ROUND((365/12),2) -> 30.42 | M7: =ROUND((K7/L7),2) -> 4002.29 | O7: =M7 -> 4002.29 | P7: 1.0479 | Q7: =O7*P7 -> 4193.9997 | S7: Febrero | T7: 20.457671
A8: ='Datos Alta'!A8 -> 4 | B8: ='Datos Alta'!E8 -> AZUCENA | C8: ='Datos Alta'!F8 -> AGUIRRE | D8: ='Datos Alta'!G8 -> CRESPO | E8: 44720 | F8: 4400 | G8: 967 | H8: =F8+G8 -> 5367 | I8: =+I7 -> 20.291594 | K8: =F8*I8 -> 89283.014 | L8: =ROUND((365/12),2) -> 30.42 | M8: =ROUND((K8/L8),2) -> 2935.01 | O8: =M8 -> 2935.01 | P8: 1.0479 | Q8: =O8*P8 -> 3075.597 | S8: Marzo | T8: 20.552674
A9: ='Datos Alta'!A9 -> 5 | B9: ='Datos Alta'!E9 -> AZUCENA | C9: ='Datos Alta'!F9 -> SANDOVAL | D9: ='Datos Alta'!G9 -> ALCIBAR | E9: 44531 | F9: 2010 | G9: 505.95 | H9: =F9+G9 -> 2515.95 | I9: =+I8 -> 20.291594 | K9: =F9*I9 -> 40786.104 | L9: =ROUND((365/12),2) -> 30.42 | M9: =ROUND((K9/L9),2) -> 1340.77 | O9: =M9 -> 1340.77 | P9: 1.0479 | Q9: =O9*P9 -> 1404.9929 | S9: Abril | T9: 20.058981
A10: ='Datos Alta'!A10 -> 6 | B10: ='Datos Alta'!E10 -> DIEGO ORLANDO | C10: ='Datos Alta'!F10 -> MONROY | D10: ='Datos Alta'!G10 -> HERNANDEZ | E10: 44683 | F10: 1900 | G10: 478.96 | H10: =F10+G10 -> 2378.96 | I10: =+I9 -> 20.291594 | K10: =F10*I10 -> 38554.029 | L10: =ROUND((365/12),2) -> 30.42 | M10: =ROUND((K10/L10),2) -> 1267.39 | O10: =M10 -> 1267.39 | P10: 1.0479 | Q10: =O10*P10 -> 1328.098 | S10: Mayo | T10: 20.017672
A11: ='Datos Alta'!A11 -> 7 | B11: ='Datos Alta'!E11 -> GABRIEL ORLANDO | C11: ='Datos Alta'!F11 -> VELAZQUEZ | D11: ='Datos Alta'!G11 -> CHAVEZ | E11: 44683 | F11: 4400 | G11: =5367-F11 -> 967 | H11: =F11+G11 -> 5367 | I11: =+I10 -> 20.291594 | K11: =F11*I11 -> 89283.014 | L11: =ROUND((365/12),2) -> 30.42 | M11: =ROUND((K11/L11),2) -> 2935.01 | O11: =M11 -> 2935.01 | P11: 1.0479 | Q11: =O11*P11 -> 3075.597 | S11: Junio | T11: 19.972969
A12: ='Datos Alta'!A12 -> 8 | B12: ='Datos Alta'!E12 -> GRACIELA | C12: ='Datos Alta'!F12 -> VARGAS | D12: ='Datos Alta'!G12 -> GARCIA | E12: 44739 | F12: 3500 | G12: 868.03 | H12: =F12+G12 -> 4368.03 | I12: =+I11 -> 20.291594 | K12: =F12*I12 -> 71020.579 | L12: =ROUND((365/12),2) -> 30.42 | M12: =ROUND((K12/L12),2) -> 2334.67 | O12: =M12 -> 2334.67 | P12: 1.0479 | Q12: =O12*P12 -> 2446.5007 | S12: Julio | T12: 20.489683
A13: ='Datos Alta'!A13 -> 9 | B13: ='Datos Alta'!E13 -> LIZET | C13: ='Datos Alta'!F13 -> GUEVARA | D13: ='Datos Alta'!G13 -> ALCÁNTARA | E13: 44683 | F13: 1900 | G13: 478.96 | H13: =F13+G13 -> 2378.96 | I13: =+I12 -> 20.291594 | K13: =F13*I13 -> 38554.029 | L13: =ROUND((365/12),2) -> 30.42 | M13: =ROUND((K13/L13),2) -> 1267.39 | O13: =M13 -> 1267.39 | P13: 1.0479 | Q13: =O13*P13 -> 1328.098 | S13: Promedio | T13: =AVERAGE(T6:T12) -> 20.291594
A14: ='Datos Alta'!A14 -> 10 | B14: ='Datos Alta'!E14 -> MARTHA ISABEL | C14: ='Datos Alta'!F14 -> LOPEZ | D14: ='Datos Alta'!G14 -> ESCOBAR | E14: 44645 | F14: 4285 | G14: 955.02 | H14: =F14+G14 -> 5240.02 | I14: =+I13 -> 20.291594 | K14: =F14*I14 -> 86949.48 | L14: =ROUND((365/12),2) -> 30.42 | M14: =ROUND((K14/L14),2) -> 2858.3 | O14: =M14 -> 2858.3 | P14: 1.0479 | Q14: =O14*P14 -> 2995.2126
A15: ='Datos Alta'!A15 -> 11 | B15: ='Datos Alta'!E15 -> ROMAN ALBERTO | C15: ='Datos Alta'!F15 -> ROJAS | D15: ='Datos Alta'!G15 -> HERNANDEZ | E15: 44362 | F15: 6750 | G15: 1211.79 | H15: =F15+G15 -> 7961.79 | I15: =+I14 -> 20.291594 | K15: =F15*I15 -> 136968.26 | L15: =ROUND((365/12),2) -> 30.42 | M15: =ROUND((K15/L15),2) -> 4502.57 | O15: =M15 -> 4502.57 | P15: 1.0479 | Q15: =O15*P15 -> 4718.2431
A16: ='Datos Alta'!A16 -> 12 | B16: ='Datos Alta'!E16 -> SASKIA | C16: ='Datos Alta'!F16 -> CABRERA | D16: ='Datos Alta'!G16 -> PADILLA | E16: 44378 | F16: 3750 | G16: =4649.29-F16 -> 899.29 | H16: =F16+G16 -> 4649.29 | I16: =+I15 -> 20.291594 | K16: =F16*I16 -> 76093.477 | L16: =ROUND((365/12),2) -> 30.42 | M16: =ROUND((K16/L16),2) -> 2501.43 | O16: =M16 -> 2501.43 | P16: 1.0479 | Q16: =O16*P16 -> 2621.2485
A17: ='Datos Alta'!A17 -> 13 | B17: ='Datos Alta'!E17 -> VERÓNICA | C17: ='Datos Alta'!F17 -> ROMERO | D17: ='Datos Alta'!G17 -> GUERRERO | E17: 44728 | F17: 2800 | G17: 697.81 | H17: =F17+G17 -> 3497.81 | I17: =+I16 -> 20.291594 | K17: =F17*I17 -> 56816.463 | L17: =ROUND((365/12),2) -> 30.42 | M17: =ROUND((K17/L17),2) -> 1867.73 | O17: =M17 -> 1867.73 | P17: 1.0479 | Q17: =O17*P17 -> 1957.1943
A18: ='Datos Alta'!A18 -> 14 | B18: ='Datos Alta'!E18 -> VICTORIA | C18: ='Datos Alta'!F18 -> LÓPEZ | D18: ='Datos Alta'!G18 -> CARMONA | E18: 44725 | F18: 2010 | G18: 505.71 | H18: =F18+G18 -> 2515.71 | I18: =+I17 -> 20.291594 | K18: =F18*I18 -> 40786.104 | L18: =ROUND((365/12),2) -> 30.42 | M18: =ROUND((K18/L18),2) -> 1340.77 | O18: =M18 -> 1340.77 | P18: 1.0479 | Q18: =O18*P18 -> 1404.9929
A19: ='Datos Alta'!A19 -> 15 | B19: ='Datos Alta'!E19 -> XANNY | C19: ='Datos Alta'!F19 -> HERNANDEZ | D19: ='Datos Alta'!G19 -> HERNANDEZ | E19: 44655 | F19: 3000 | G19: 746.45 | H19: =F19+G19 -> 3746.45 | I19: =+I18 -> 20.291594 | K19: =F19*I19 -> 60874.782 | L19: =ROUND((365/12),2) -> 30.42 | M19: =ROUND((K19/L19),2) -> 2001.14 | O19: =M19 -> 2001.14 | P19: 1.0479 | Q19: =O19*P19 -> 2096.9946
A20: ='Datos Alta'!A20 -> 16 | B20: ='Datos Alta'!E20 -> YAEL IVONNE | C20: ='Datos Alta'!F20 -> CAYETANO | D20: ='Datos Alta'!G20 -> FIGUEROA | E20: 44636 | F20: 1685 | G20: =2111.68-F20 -> 426.68 | H20: =F20+G20 -> 2111.68 | I20: =+I19 -> 20.291594 | K20: =F20*I20 -> 34191.336 | L20: =ROUND((365/12),2) -> 30.42 | M20: =ROUND((K20/L20),2) -> 1123.98 | O20: =M20 -> 1123.98 | P20: 1.0479 | Q20: =O20*P20 -> 1177.8186

Sheet Factor de integración
A1: Factores de integración
A2: Factores
A3: Años de servicio | B3: Dias vacaiones | C3: Prima vacacional | D3: Aguinaldo 15 días
A4: 1 | B4: 10 | C4: =TRUNC(B4*0.25,2) -> 2.5 | D4: =TRUNC(((365+15+C4)/365),4) -> 1.0479
A5: 2 | B5: 10 | C5: =TRUNC(B5*0.25,2) -> 2.5 | D5: =TRUNC(((365+15+C5)/365),4) -> 1.0479
A6: 3 | B6: 15 | C6: =TRUNC(B6*0.25,2) -> 3.75 | D6: =TRUNC(((365+15+C6)/365),4) -> 1.0513
A7: 4 | B7: 15 | C7: =TRUNC(B7*0.25,2) -> 3.75 | D7: =TRUNC(((365+15+C7)/365),4) -> 1.0513
A8: 5 a 9 | B8: 15 | C8: =TRUNC(B8*0.25,2) -> 3.75 | D8: =TRUNC(((365+15+C8)/365),4) -> 1.0513
A9: 10 a 14 | B9: 16 | C9: =TRUNC(B9*0.25,2) -> 4 | D9: =TRUNC(((365+15+C9)/365),4) -> 1.052
A10: 15 a 19 | B10: 18 | C10: =TRUNC(B10*0.25,2) -> 4.5 | D10: =TRUNC(((365+15+C10)/365),4) -> 1.0534
A11: 20 a 24 | B11: 20 | C11: =TRUNC(B11*0.25,2) -> 5 | D11: =TRUNC(((365+15+C11)/365),4) -> 1.0547
A12: 25 a 29 | B12: 22 | C12: =TRUNC(B12*0.25,2) -> 5.5 | D12: =TRUNC(((365+15+C12)/365),4) -> 1.0561
A13: 30 a 34 | B13: 24 | C13: =TRUNC(B13*0.25,2) -> 6 | D13: =TRUNC(((365+15+C13)/365),4) -> 1.0575
A17: Prestaciones Partners
A19: • Aguinaldo conforme a Ley, equivalente a 15 días de sueldo diario.
A20: • Vacaciones superiores a Ley, iniciando en 10 días por año, y a partir del 3er aniversario de empleo 15 días. Las vacaciones podrán disfrutarse desde el primer mes de empleo conforme a devengo de la proporción por mes trabajado.
A21: • Prima vacacional del 25 %, sobre la base de los días de vacaciones otorgados por POA superiores a Ley.
A22: • Cuotas patronales sobre el 100% de su salario hasta el límite cotizable ante el IMSS.
A23: • Opcional. 80% del costo de Póliza de Seguro de Gastos Médicos Mayores individual que será contratada por POA. Las personas colaboradoras, asumiendo el costo, podrán agregar dependientes en la póliza
