Workbook

Sheet POA Compensation Analysis  
J1: 2019 Baseline * % increase: | L1: =1.05*1*1.03*1*1.03 -> 1.113945
S2: Analysis assuming 5% increase each year
C3: Partners of the Americas Salary Ranges for HONDURAS | T3: Years in | W3: Years in | Y3: NOTES:
C4: Job Positions & Bands | G4: Experience | H4: Minimum USD | I4: Minimum HNL | J4: Midpoint USD | K4: Midpoint HNL | L4: Maximum USD | M4: Maximum HNL | AX4: 37440
C5: Core competencies | E5: Level | F5: Yrs Exp | T5: Position | W5: Position | Y5: - Management Skills: Project mgmt | AX5: =AX4/H6 -> 5.7720592
B6: Officer | C6: Maintenance - Level I Driver - Level II Assistant - Level III | D6: Grade A | E6: I | F6: 0 | G6: Minimum: no degree; no experience; no technical skills. Maximum: Grad school started;or 0-6 month of experience; with some technical skills. | H6: =+('Birches Report Level'!AG13*12)/'Birches Report Level'!AG12 -> 6486.42 | I6: =H6*TRM!$I$9 -> 167920.44 | J6: =+'Grade A'!C7 -> 7348.0357 | K6: =J6*TRM!$I$9 -> 190225.95 | L6: =+'Grade A'!D7 -> 9634.2843 | M6: =L6*TRM!$I$9 -> 249412.35 | O6: =(L10-H6)/6 -> 968.09326 | S6: =H6*1.05 -> 6810.741 | T6: 1 | V6: =S11*1.05 -> 9127.0443 | W6: 7 | Y6: - Leadership Skills: Project mgmt and personnel mgmt
B7: ·Accountant Analyst – Field Office ·Administrative Officer ·Communications Officer ·Communication & Outreach Officer ·Membership Officer ·Program Officer, CPU ·Program Officer, EGC ·Program Officer, EDH | C7: Provide physical and mechanic support Core competencies required: -Ability to write effectively and think critically. -Ability to work in a team as well as independently and demonstrate consistency | H7: No degree. No experience. No technical skills. | S7: =S6*1.05 -> 7151.278 | T7: 2 | V7: =V6*1.05 -> 9583.3965 | W7: 8 | Y7: - I added calculations to show the % increase between each point; I will hide these before sharing | AY7: ,00
E8: II | F8: 2-4 | G8: Minimum: Level I + min 2 years of experience, with some technical skills. | H8: =MEDIAN(H6,J6) -> 6917.2278 | I8: =H8*TRM!$I$9 -> 179073.19 | J8: =+'Grade A'!H7 -> 8701.0731 | K8: =J8*TRM!$I$9 -> 225253.38 | L8: =+'Grade A'!I7 -> 11779.476 | M8: =L8*TRM!$I$9 -> 304947.08 | S8: =S7*1.05 -> 7508.8419 | T8: 3 | Y8: - Note that these % increases are higher than the max 5% estimated increase each year
J9: Bachelors degree + least 2 years of experience. Some technical skills or min 2 years in level I | Q9: =J8/H8 -> 1.2578844 | S9: =S8*1.05 -> 7884.284 | T9: 4
E10: III | F10: 4-6 | G10: Minimum: 2 years of experience in Level II. | H10: =+'Grade A'!L7 -> 7436 | I10: =H10*TRM!$I$9 -> 192503.17 | J10: =+'Grade A'!M7 -> 10176.792 | K10: =J10*TRM!$I$9 -> 263456.8 | L10: =+'Grade A'!N7 -> 12294.98 | M10: =L10*TRM!$I$9 -> 318292.43 | O10: =J10+O6 -> 11144.886 | S10: =S9*1.05 -> 8278.4982 | T10: 5 | AY10: =55000/63000 -> 0.87301587
L11: Masters degree + least 3 years experience level II; some technical skills; preferred min bilingual. | Q11: =L10/J10 -> 1.208139 | S11: =S10*1.05 -> 8692.4231 | T11: 6 | AY11: =100-87 -> 13
B13: Senior Officer | C13: Officer/Technical Officer - Level I Sr. Officer/Sr. Technical Officer - Level II | D13: Grade B | E13: I | F13: 4 | G13: Minimum: 2 years of experience in Officer Level II, or equivalent; management skills demonstrated. | H13: =+'Grade B'!B7 -> 7553 | I13: =H13*TRM!$I$9 -> 195532.06 | J13: =+'Grade B'!C7 -> 11988.5 | K13: =J13*TRM!$I$9 -> 310358.29 | L13: =+'Grade B'!D7 -> 16423.5 | M13: =L13*TRM!$I$9 -> 425171.57 | O13: =(L15-H13)/4 -> 3431 | S13: =H13*1.05 -> 7930.65 | T13: 1 | V13: =S16*1.05 -> 9639.7546 | W13: 5
B14: ·Senior Accountant ·Senior Program Officer, EDH ·Senior Program Officer, EGC ·Senior Program Officer, CPU | C14: Process basic transaction Execute intrincate transactions Core competencies: -Thorough understanding of federal award management (program SOs) -Ability to contribute high-quality subsections of donor/partner reports/proposals -Ability to competently contribute during donor/partner meetings -Ability to manage 1-2 interns | H14: 2 years of experience in Officer Level II, or equivalent; management skills demonstrated. | S14: =S13*1.05 -> 8327.1825 | T14: 2 | V14: =V13*1.05 -> 10121.742 | W14: 6 | AY14: 58000 | BA14: =AY14/AY15 -> 0.92063492 | BB14: =100-92 -> 8
E15: II | F15: 4-7 | G15: Minimum: Masters degree preferred + at least 4 years of experience; 1 year as Sr Officer level I; technical skills required; leadership experience and language desired. Ability to competently serve as interim-Associate Director when necessary. | H15: =+'Grade B'!G7 -> 8662.9823 | I15: =H15*TRM!$I$9 -> 224267.29 | J15: =+'Grade B'!H7 -> 14325.501 | K15: =J15*TRM!$I$9 -> 370858.57 | L15: =+'Grade B'!I7 -> 21277 | M15: =L15*TRM!$I$9 -> 550818.98 | O15: =J15+O13 -> 17756.501 | Q15: =J15/H15 -> 1.6536454 | S15: =S14*1.05 -> 8743.5416 | T15: 3 | V15: =V14*1.05 -> 10627.829 | W15: 7 | AY15: 63000
H16: =H15/L13 -> 0.5274748 | J16: =J15/H15 -> 1.6536454 | L16: Masters degree preferred; 7+ years experience; 3 years as Sr Officer level I; technical skills required and leadership knowledge desired; preferred min bilingual. | Q16: =L15/J15 -> 1.4852535 | S16: =S15*1.05 -> 9180.7187 | T16: 4
B18: Associate Director | C18: Coordinator - Level I Specialist - Level II Sr. Specialist - Level III | D18: Grade C | E18: I | F18: 6 | G18: Minimum: Bachelors degree. 6+ years experience; 2+ years as Sr Officer Level I or II; technical skills and leadership experience required; preferred min bilingual. | H18: =+'Gade C'!B7 -> 10720 | I18: =H18*TRM!$I$9 -> 277519.36 | J18: =+'Gade C'!C7 -> 17186.5 | K18: =J18*TRM!$I$9 -> 444924.11 | L18: =+'Gade C'!D7 -> 23652.5 | M18: =L18*TRM!$I$9 -> 612315.92 | O18: =(L22-H18)/6 -> 3914.0833 | S18: =H18*1.05 -> 11256 | T18: 1 | V18: =S23*1.05 -> 15084.117 | W18: 7 | Y18: - Note that AD level and above are part of the SMT (Senior Management Team)
B19: ·Associate Director, EDH - F2F ·Associate Director, EDH - AVOP ·Associate Director, EGC ·Associate Director, BD ·Associate Director, Membership ·Executive Administrative Officer | C19: Ensure process integrity Manage integrated processes In addition to grade B core competencies: -Ability to write high-quality full sections of proposals/reports -Ability to deliver high-quality, detail-oriented, and professional donor/partner reports -Ability to competently lead a donor/partner meeting -Ability to manage 2-3 staff and/or interns | H19: Bachelors degree. 6+ years experience; 2+ years as Sr Officer Level I or II; technical skills and leadership experience required; preferred min bilingual. | J19: =J18/H18 -> 1.6032183 | L19: =L18/J18 -> 1.3762255 | S19: =S18*1.05 -> 11818.8 | T19: 2 | V19: =V18*1.05 -> 15838.322 | W19: 8
E20: II | F20: 9 | G20: Minimum: 3 additional years experience as AD Level I, or equivalent; international experience desired; or Level I + Masters degree; international experience desired. | H20: =+'Gade C'!G7 -> 12034.189 | I20: =H20*TRM!$I$9 -> 311541.09 | J20: =+'Gade C'!H7 -> 19806.5 | K20: =J20*TRM!$I$9 -> 512750.67 | L20: =+'Gade C'!I7 -> 27185.5 | M20: =L20*TRM!$I$9 -> 703778.22 | S20: =S19*1.05 -> 12409.74 | T20: 3
H21: =H20/L18 -> 0.50879142 | J21: 4 yrs experience as manger/specialist level I; technical skills and leadership experience required; language required; international experience desired. | L21: =L20/J20 -> 1.3725545 | Q21: =J20/H20 -> 1.6458525 | S21: =S20*1.05 -> 13030.227 | T21: 4
E22: III | F22: 12 | G22: Minimum: Level II + Masters degree + 3 additional years experience as AD Level II; international experience desired. Ability to competently serve as interim-Director when necessary. | H22: =+'Gade C'!L7 -> 13049.878 | I22: =H22*TRM!$I$9 -> 337835.24 | J22: =+'Gade C'!M7 -> 23349.158 | K22: =J22*TRM!$I$9 -> 604462.99 | L22: =+'Gade C'!N7 -> 34204.5 | M22: =L22*TRM!$I$9 -> 885486.1 | O22: =J22+O18 -> 27263.241 | S22: =S21*1.05 -> 13681.738 | T22: 5
H23: =H22/L20 -> 0.48003082 | J23: =J22/H22 -> 1.7892242 | L23: Masters degree. 8+ years experience; 3 years as Manager or specialist Level II; international experience desired. | Q23: =L22/J22 -> 1.4649137 | S23: =S22*1.05 -> 14365.825 | T23: 6
B25: Director | C25: Manager - Level I Director - Level II Sr. Director - Level III | D25: Grade D | E25: I | F25: 8 | G25: Minimum: Masters degree and AD Level II or 3 years as AD Level I or equivalent; proven technical skills and leadership experience; 2nd language required; international experience desired. | H25: =+'Grade D'!B7 -> 11000 | I25: =H25*TRM!$I$9 -> 284768 | J25: =+'Grade D'!C7 -> 28000 | K25: =J25*TRM!$I$9 -> 724864 | L25: =+'Grade D'!D7 -> 45000 | M25: =L25*TRM!$I$9 -> 1164960 | O25: =(L29-H25)/6 -> 8470.4322 | S25: =H25*1.05 -> 11550 | T25: 1 | V25: =S30*1.05 -> 15478.105 | W25: 7
B26: ·Director of 100,000 Strong ·Director of EGC ·Director, BD | C26: Analyze - Adapt In addition to Grade C core competencies: -Ability to lead a full proposal (design, strategy, delegation of duties, etc.) -Ability to ensure full programmatic and financial compliance of a federal award from startup through closeout -Ability to manage 3-5 staff, including remote supervision of field staff | H26: manager/specialist Level I + Masters degree and 2 years as manager or equivalent; 2nd language required; international experience desired. | J26: =J25/H25 -> 2.5454545 | L26: =L25/J25 -> 1.6071429 | S26: =S25*1.05 -> 12127.5 | T26: 2 | V26: =V25*1.05 -> 16252.01 | W26: 8
E27: II | F27: 10 | G27: Minimum: At least 2 years as Director Level I, or equivalent. | H27: =+'Grade D'!G7 -> 16544.717 | I27: =H27*TRM!$I$9 -> 428309.64 | J27: =+'Grade D'!H7 -> 33579.5 | K27: =J27*TRM!$I$9 -> 869306.1 | L27: =+'Grade D'!I7 -> 46880.66 | M27: =L27*TRM!$I$9 -> 1213646.5 | S27: =S26*1.05 -> 12733.875 | T27: 3
H28: =H27/L25 -> 0.36766038 | J28: At least 3 years as Director Level I & II. | L28: =L27/J27 -> 1.3961095 | Q28: =J27/H27 -> 2.0296207 | S28: =S27*1.05 -> 13370.569 | T28: 4
E29: III | F29: 12-14 | G29: Minimum: At least 2 years as Director Level II. Ability to competently serve as interim-Sr Director when necessary. | H29: =+'Grade D'!L7 -> 27533.597 | I29: =H29*TRM!$I$9 -> 712789.76 | J29: =+'Grade D'!M7 -> 41447.93 | K29: =J29*TRM!$I$9 -> 1073004 | L29: =+'Grade D'!N7 -> 61822.593 | M29: =L29*TRM!$I$9 -> 1600463.3 | O29: =J29+O25 -> 49918.362 | S29: =S28*1.05 -> 14039.097 | T29: 5
H30: =H29/L27 -> 0.58731249 | J30: =J29/H29 -> 1.5053583 | L30: At least 4 years as Director Level II & III. | Q30: =L29/J29 -> 1.4915725 | S30: =S29*1.05 -> 14741.052 | T30: 6
B32: Director | C32: Deputy Chief of Party/Deputy Project Director - Level I-II Chief of Party/Project Director - Level II-III | D32: Grade E | E32: I | F32: 10 | G32: Minimum: At least 2 years as Director or equivalent; proven high confidence and decision - making; strong leader and manager | H32: =+'Grade E'!B7 -> 52692.549 | I32: =H32*TRM!$I$9 -> 1364104.7 | J32: =+'Grade E'!C7 -> 63939.467 | K32: =J32*TRM!$I$9 -> 1655264.9 | L32: =+'Grade E'!D7 -> 78000 | M32: =L32*TRM!$I$9 -> 2019264 | O32: =(L36-H32)/6 -> 11217.909 | S32: =H32*1.05 -> 55327.176 | T32: 1 | V32: =S37*1.05 -> 74143.708 | W32: 7
B33: ·Director of 100,000 Strong ·Director of EGC ·Director, BD | C33: In addition to Director competencies: -Ability to raise public and/or private funds -Ability to manage multiple federal awards -Ability to execute strategic and operational plans for the units - Ability to manage a full team (staff, interns, contractors), including remote supervision of field staff | H33: At least 2 years as Director; proven high confidence and decision-making; strong leader and manager. | J33: =J32/H32 -> 1.2134442 | L33: =L32/J32 -> 1.2199038 | S33: =S32*1.05 -> 58093.535 | T33: 2 | V33: =V32*1.05 -> 77850.893 | W33: 8
E34: II | F34: 12 | G34: Minimum: Dual or multiple Masters Degrees; at least 2 years as Sr. Director Level I; proven high confidence and decision-making; strong leader and manager. | H34: =+'Grade E'!G7 -> 22000 | I34: =H34*TRM!$I$9 -> 569536 | J34: =+'Grade E'!H7 -> 58000 | K34: =J34*TRM!$I$9 -> 1501504 | L34: =+'Grade E'!I7 -> 94000 | M34: =L34*TRM!$I$9 -> 2433472 | S34: =S33*1.05 -> 60998.212 | T34: 3
H35: =H34/L32 -> 0.28205128 | J35: Dual or multiple Masters Degrees; at least 3 years as Sr. Director; proven high confidence and decision-making; strong leader and manager | L35: =L34/J34 -> 1.6206897 | Q35: =J34/H34 -> 2.6363636 | S35: =S34*1.05 -> 64048.123 | T35: 4
E36: III | F36: 14 | G36: Minimum: PhD "preference"; at least 2 years as Sr. Director. Ability to competently serve as interim Vice - President when necesary. | H36: =+'Grade E'!L7 -> 62633.248 | I36: =H36*TRM!$I$9 -> 1621449.5 | J36: =+'Grade E'!M7 -> 80238.342 | K36: =J36*TRM!$I$9 -> 2077210.2 | L36: 120000 | M36: =L36*TRM!$I$9 -> 3106560 | O36: =J36+O32 -> 91456.25 | S36: =S35*1.05 -> 67250.529 | T36: 5
H37: =H36/L34 -> 0.66631115 | J37: =J36/H36 -> 1.2810822 | L37: PhD preferance required.14+ years of experience; at least 4 years as Sr. Director or equivalent_x000D_ | Q37: =L36/J36 -> 1.4955444 | S37: =S36*1.05 -> 70613.055 | T37: 6

Sheet Birches Report 
G1: Birchis 2023 | N1: Estimado 2024 con incremento del 3.88% | U1: Estimado 2025 con incremento del 4.16%
A2: Level | B2: Purpose | C2: Proposed Field Office Grade | D2: Purpose | E2: Famili | F2: Titulo del trabajo | H2: Bajo | I2: Percentil 25 | J2: Percentil 50 | K2: Percentil 75 | L2: Alto | M2: Media | O2: Bajo | P2: Percentil 25 | Q2: Percentil 50 | R2: Percentil 75 | S2: Alto | T2: Media | V2: Bajo | W2: Percentil 25 | X2: Percentil 50 | Y2: Percentil 75 | Z2: Alto | AA2: Media | AB2: https://www.trabajo.gob.hn/tabla-de-salario-minimo/?utm_source=chatgpt.com
A3: BG-12 | B3: Integrate-Transform | C3: Poa-E | D3: BG-12 Executive/DCOP | E3: GEN-12 | F3: Gerente / Experto reconocido | G3: Máx. | H3: 1453935 | I3: 1603580 | J3: 1753226 | K3: 1958113 | L3: 2163000 | M3: 1790054 | N3: Máx. | O3: =((H3*$AB$15)+H3)/$AB$17 -> 58341.613 | P3: =((I3*$AB$15)+I3)/$AB$17 -> 64346.373 | Q3: =((J3*$AB$15)+J3)/$AB$17 -> 70351.173 | R3: =((K3*$AB$15)+K3)/$AB$17 -> 78572.612 | S3: =((L3*$AB$15)+L3)/$AB$17 -> 86794.051 | T3: =+((1281000*$AB$15)+M3)/$AB$17 -> 71066.007 | U3: Máx. | V3: =((O3*$AB$16)+O3) -> 60768.624 | W3: =((P3*$AB$16)+P3) -> 67023.182 | X3: =((Q3*$AB$16)+Q3) -> 73277.782 | Y3: =((R3*$AB$16)+R3) -> 81841.233 | Z3: =((S3*$AB$16)+S3) -> 90404.684 | AA3: =MEDIAN(V3:Z3) -> 73277.782
G4: Med | H4: 1453835 | I4: 1585506 | J4: 1717176 | K4: 1940088 | L4: 2163000 | M4: 1778004 | N4: Med | O4: =((H4*$AB$15)+H4)/$AB$17 -> 58337.6 | P4: =((I4*$AB$15)+I4)/$AB$17 -> 63621.123 | Q4: =((J4*$AB$15)+J4)/$AB$17 -> 68904.606 | R4: =((K4*$AB$15)+K4)/$AB$17 -> 77849.328 | S4: =((L4*$AB$15)+L4)/$AB$17 -> 86794.051 | T4: =MEDIAN(O4:S4) -> 68904.606 | U4: Med | V4: =((O4*$AB$16)+O4) -> 60764.445 | W4: =((P4*$AB$16)+P4) -> 66267.762 | X4: =((Q4*$AB$16)+Q4) -> 71771.037 | Y4: =((R4*$AB$16)+R4) -> 81087.86 | Z4: =((S4*$AB$16)+S4) -> 90404.684 | AA4: =MEDIAN(V4:Z4) -> 71771.037 | AB4: Para una empresa con 11 a 50 empleados, los incrementos al salario mínimo en Honduras han sido del 5.5 % para 2024 y de nuevo del 5.5 % para 2025. trabajo.gob.hn+2Bloomberg Línea Brasil+2
G5: Min. | H5: 1453735 | I5: 1567430 | J5: 1681126 | K5: 1922063 | L5: 2163000 | M5: 1765954 | N5: Min. | O5: =((H5*$AB$15)+H5)/$AB$17 -> 58333.588 | P5: =((I5*$AB$15)+I5)/$AB$17 -> 62895.793 | Q5: =((J5*$AB$15)+J5)/$AB$17 -> 67458.038 | R5: =((K5*$AB$15)+K5)/$AB$17 -> 77126.045 | S5: =((L5*$AB$15)+L5)/$AB$17 -> 86794.051 | T5: =MEDIAN(O5:S5) -> 67458.038 | U5: Min. | V5: =((O5*$AB$16)+O5) -> 60760.265 | W5: =((P5*$AB$16)+P5) -> 65512.258 | X5: =((Q5*$AB$16)+Q5) -> 70264.292 | Y5: =((R5*$AB$16)+R5) -> 80334.488 | Z5: =((S5*$AB$16)+S5) -> 90404.684 | AA5: =MEDIAN(V5:Z5) -> 70264.292 | AB5: Si tomamos como base un salario mínimo de L 12,560.96 en enero de 2023, el estimado acumulado para octubre de 2025 sería:
E6: DPM-12 | F6: Director nacional | G6: Máx. | H6: 1281000 | I6: 1739664 | J6: 1761060 | K6: 2163000 | L6: 2800000 | M6: 1934687 | N6: Máx. | O6: =((H6*$AB$15)+H6)/$AB$17 -> 51402.302 | P6: =((I6*$AB$15)+I6)/$AB$17 -> 69806.975 | Q6: =((J6*$AB$15)+J6)/$AB$17 -> 70665.526 | R6: =((K6*$AB$15)+K6)/$AB$17 -> 86794.051 | S6: =((L6*$AB$15)+L6)/$AB$17 -> 112354.76 | T6: =MEDIAN(O6:S6) -> 70665.526 | U6: Máx. | V6: =((O6*$AB$16)+O6) -> 53540.638 | W6: =((P6*$AB$16)+P6) -> 72710.945 | X6: =((Q6*$AB$16)+Q6) -> 73605.212 | Y6: =((R6*$AB$16)+R6) -> 90404.684 | Z6: =((S6*$AB$16)+S6) -> 117028.72 | AA6: =MEDIAN(V6:Z6) -> 73605.212
G7: Med | H7: 1281000 | I7: 1467550 | J7: 1739005 | K7: 1862190 | L7: 2333333 | M7: 1750725 | N7: Med | O7: =((H7*$AB$15)+H7)/$AB$17 -> 51402.302 | P7: =((I7*$AB$15)+I7)/$AB$17 -> 58887.938 | Q7: =((J7*$AB$15)+J7)/$AB$17 -> 69780.531 | R7: =((K7*$AB$15)+K7)/$AB$17 -> 74723.539 | S7: =((L7*$AB$15)+L7)/$AB$17 -> 93628.952 | T7: =MEDIAN(O7:S7) -> 69780.531 | U7: Med | V7: =((O7*$AB$16)+O7) -> 53540.638 | W7: =((P7*$AB$16)+P7) -> 61337.676 | X7: =((Q7*$AB$16)+Q7) -> 72683.401 | Y7: =((R7*$AB$16)+R7) -> 77832.038 | Z7: =((S7*$AB$16)+S7) -> 97523.917 | AA7: =MEDIAN(V7:Z7) -> 72683.401
G8: Min. | H8: 1174040 | I8: 1363558 | J8: 1453735 | K8: 1738346 | L8: 2163000 | M8: 1566764 | N8: Min. | O8: =((H8*$AB$15)+H8)/$AB$17 -> 47110.35 | P8: =((I8*$AB$15)+I8)/$AB$17 -> 54715.082 | Q8: =((J8*$AB$15)+J8)/$AB$17 -> 58333.588 | R8: =((K8*$AB$15)+K8)/$AB$17 -> 69754.088 | S8: =((L8*$AB$15)+L8)/$AB$17 -> 86794.051 | T8: =MEDIAN(O8:S8) -> 58333.588 | U8: Min. | V8: =((O8*$AB$16)+O8) -> 49070.141 | W8: =((P8*$AB$16)+P8) -> 56991.23 | X8: =((Q8*$AB$16)+Q8) -> 60760.265 | Y8: =((R8*$AB$16)+R8) -> 72655.858 | Z8: =((S8*$AB$16)+S8) -> 90404.684 | AA8: =MEDIAN(V8:Z8) -> 60760.265
A9: BG-11 | B9: Innovate | D9: BG-11 Country Directors/COP | E9: GEN-11 | F9: Gerente / Especialista con Autoridad | G9: Máx. | H9: 941347 | I9: 1542070 | J9: 1886528 | K9: 2129776 | L9: 3450528 | M9: 1961246 | N9: Máx. | O9: =((H9*$AB$15)+H9)/$AB$17 -> 37773.148 | P9: =((I9*$AB$15)+I9)/$AB$17 -> 61878.18 | Q9: =((J9*$AB$15)+J9)/$AB$17 -> 75700.142 | R9: =((K9*$AB$15)+K9)/$AB$17 -> 85460.882 | S9: =((L9*$AB$15)+L9)/$AB$17 -> 138458.3 | T9: =MEDIAN(O9:S9) -> 75700.142 | U9: Máx. | V9: =((O9*$AB$16)+O9) -> 39344.511 | W9: =((P9*$AB$16)+P9) -> 64452.312 | X9: =((Q9*$AB$16)+Q9) -> 78849.268 | Y9: =((R9*$AB$16)+R9) -> 89016.055 | Z9: =((S9*$AB$16)+S9) -> 144218.17 | AA9: =MEDIAN(V9:Z9) -> 78849.268 | AB9: Después del primer ajuste (2024): L 12,560.96 × 1.055 ≈ L 13,250.11
G10: Med | H10: 760167 | I10: 1309132 | J10: 1452829 | K10: 1846013 | L10: 2239464 | M10: 1538094 | N10: Med | O10: =((H10*$AB$15)+H10)/$AB$17 -> 30502.993 | P10: =((I10*$AB$15)+I10)/$AB$17 -> 52531.147 | Q10: =((J10*$AB$15)+J10)/$AB$17 -> 58297.233 | R10: =((K10*$AB$15)+K10)/$AB$17 -> 74074.409 | S10: =((L10*$AB$15)+L10)/$AB$17 -> 89862.299 | T10: =MEDIAN(O10:S10) -> 58297.233 | U10: Med | V10: =((O10*$AB$16)+O10) -> 31771.917 | W10: =((P10*$AB$16)+P10) -> 54716.442 | X10: =((Q10*$AB$16)+Q10) -> 60722.398 | Y10: =((R10*$AB$16)+R10) -> 77155.905 | Z10: =((S10*$AB$16)+S10) -> 93600.571 | AA10: =MEDIAN(V10:Z10) -> 60722.398 | AB10: Después del segundo ajuste (2025): L 13,250.11 × 1.055 ≈ L 13,993.37
G11: Min. | H11: 578987 | I11: 961524 | J11: 1036042 | K11: 1150800 | L11: 1898048 | M11: 1114941 | N11: Min. | O11: =((H11*$AB$15)+H11)/$AB$17 -> 23232.837 | P11: =((I11*$AB$15)+I11)/$AB$17 -> 38582.785 | Q11: =((J11*$AB$15)+J11)/$AB$17 -> 41572.946 | R11: =((K11*$AB$15)+K11)/$AB$17 -> 46177.806 | S11: =((L11*$AB$15)+L11)/$AB$17 -> 76162.402 | T11: =MEDIAN(O11:S11) -> 41572.946 | U11: Min. | V11: =((O11*$AB$16)+O11) -> 24199.323 | W11: =((P11*$AB$16)+P11) -> 40187.829 | X11: =((Q11*$AB$16)+Q11) -> 43302.381 | Y11: =((R11*$AB$16)+R11) -> 48098.803 | Z11: =((S11*$AB$16)+S11) -> 79330.758 | AA11: =MEDIAN(V11:Z11) -> 43302.381 | AB11: Por tanto, un estimado razonable del salario mínimo para esa categoría en octubre de 2025 sería aproximadamente L 13,993.37, lo que representa un incremento acumulado de alrededor del 11.4 % desde enero de 2023.
E12: DPM-11 | F12: Responsable de programa senior | G12: Máx. | H12: 941347 | I12: 1593906 | J12: 1875008 | K12: 2087050 | L12: 3450528 | M12: 1974961 | N12: Máx. | O12: =((H12*$AB$15)+H12)/$AB$17 -> 37773.148 | P12: =((I12*$AB$15)+I12)/$AB$17 -> 63958.187 | Q12: =((J12*$AB$15)+J12)/$AB$17 -> 75237.883 | R12: =((K12*$AB$15)+K12)/$AB$17 -> 83746.428 | S12: =((L12*$AB$15)+L12)/$AB$17 -> 138458.3 | T12: =MEDIAN(O12:S12) -> 75237.883 | U12: Máx. | V12: =((O12*$AB$16)+O12) -> 39344.511 | W12: =((P12*$AB$16)+P12) -> 66618.848 | X12: =((Q12*$AB$16)+Q12) -> 78367.779 | Y12: =((R12*$AB$16)+R12) -> 87230.28 | Z12: =((S12*$AB$16)+S12) -> 144218.17 | AA12: =MEDIAN(V12:Z12) -> 78367.779
G13: Med | H13: 760167 | I13: 1309132 | J13: 1446312 | K13: 1846013 | L13: 2239464 | M13: 1541168 | N13: Med | O13: =((H13*$AB$15)+H13)/$AB$17 -> 30502.993 | P13: =((I13*$AB$15)+I13)/$AB$17 -> 52531.147 | Q13: =((J13*$AB$15)+J13)/$AB$17 -> 58035.727 | R13: =((K13*$AB$15)+K13)/$AB$17 -> 74074.409 | S13: =((L13*$AB$15)+L13)/$AB$17 -> 89862.299 | T13: =MEDIAN(O13:S13) -> 58035.727 | U13: Med | V13: =((O13*$AB$16)+O13) -> 31771.917 | W13: =((P13*$AB$16)+P13) -> 54716.442 | X13: =((Q13*$AB$16)+Q13) -> 60450.013 | Y13: =((R13*$AB$16)+R13) -> 77155.905 | Z13: =((S13*$AB$16)+S13) -> 93600.571 | AA13: =MEDIAN(V13:Z13) -> 60450.013
G14: Min. | H14: 578987 | I14: 973893 | J14: 1028400 | K14: 1120000 | L14: 1898048 | M14: 1107374 | N14: Min. | O14: =((H14*$AB$15)+H14)/$AB$17 -> 23232.837 | P14: =((I14*$AB$15)+I14)/$AB$17 -> 39079.112 | Q14: =((J14*$AB$15)+J14)/$AB$17 -> 41266.298 | R14: =((K14*$AB$15)+K14)/$AB$17 -> 44941.904 | S14: =((L14*$AB$15)+L14)/$AB$17 -> 76162.402 | T14: =MEDIAN(O14:S14) -> 41266.298 | U14: Min. | V14: =((O14*$AB$16)+O14) -> 24199.323 | W14: =((P14*$AB$16)+P14) -> 40704.803 | X14: =((Q14*$AB$16)+Q14) -> 42982.976 | Y14: =((R14*$AB$16)+R14) -> 46811.487 | Z14: =((S14*$AB$16)+S14) -> 79330.758 | AA14: =MEDIAN(V14:Z14) -> 42982.976
A15: BG-10 | B15: Adapt | C15: Poa-D | D15: BG-10 Project Director | E15: GEN-10 | F15: Profesional experto nivel operativo | G15: Máx. | H15: 815061 | I15: 960251 | J15: 1211352 | K15: 1391583 | L15: 1670873 | M15: 1200348 | N15: Máx. | O15: =((H15*$AB$15)+H15)/$AB$17 -> 32705.708 | P15: =((I15*$AB$15)+I15)/$AB$17 -> 38531.703 | Q15: =((J15*$AB$15)+J15)/$AB$17 -> 48607.558 | R15: =((K15*$AB$15)+K15)/$AB$17 -> 55839.633 | S15: =((L15*$AB$15)+L15)/$AB$17 -> 67046.619 | T15: =MEDIAN(O15:S15) -> 48607.558 | U15: Máx. | V15: =((O15*$AB$16)+O15) -> 34066.265 | W15: =((P15*$AB$16)+P15) -> 40134.622 | X15: =((Q15*$AB$16)+Q15) -> 50629.632 | Y15: =((R15*$AB$16)+R15) -> 58162.562 | Z15: =((S15*$AB$16)+S15) -> 69835.758 | AA15: =MEDIAN(V15:Z15) -> 50629.632 | AB15: 0.0388 | AC15: Inflación del 2024"fuente, Secretaria de Finanzas de Honduras": https://www.sefin.gob.hn/download_file.php?download_file=/wp-content/uploads/2025/liquidacion2024/2-Informe-Cierre-Fiscal-2024.pdf
G16: Med | H16: 658762 | I16: 884411 | J16: 1065812 | K16: 1111487 | L16: 1386043 | M16: 1013324 | N16: Med | O16: =((H16*$AB$15)+H16)/$AB$17 -> 26433.945 | P16: =((I16*$AB$15)+I16)/$AB$17 -> 35488.495 | Q16: =((J16*$AB$15)+J16)/$AB$17 -> 42767.518 | R16: =((K16*$AB$15)+K16)/$AB$17 -> 44600.305 | S16: =((L16*$AB$15)+L16)/$AB$17 -> 55617.331 | T16: =MEDIAN(O16:S16) -> 42767.518 | U16: Med | V16: =((O16*$AB$16)+O16) -> 27533.597 | W16: =((P16*$AB$16)+P16) -> 36964.816 | X16: =((Q16*$AB$16)+Q16) -> 44546.647 | Y16: =((R16*$AB$16)+R16) -> 46455.678 | Z16: =((S16*$AB$16)+S16) -> 57931.012 | AA16: =MEDIAN(V16:Z16) -> 44546.647 | AB16: 0.0416 | AC16: Inflación del 2025 "Fuente Banco central de Honduras": chrome-extension://efaidnbmnnnibpcajpcglclefindmkaj/https://www.bch.hn/estadisticos/GIE/LIBIPC/%C3%8Dndice%20de%20Precios%20al%20Consumidor%20Agosto%202025.pdf
G17: Min. | H17: 457498 | I17: 692264 | J17: 806580 | K17: 1047138 | L17: 1101212 | M17: 826299 | N17: Min. | O17: =((H17*$AB$15)+H17)/$AB$17 -> 18357.885 | P17: =((I17*$AB$15)+I17)/$AB$17 -> 27778.27 | Q17: =((J17*$AB$15)+J17)/$AB$17 -> 32365.393 | R17: =((K17*$AB$15)+K17)/$AB$17 -> 42018.192 | S17: =((L17*$AB$15)+L17)/$AB$17 -> 44188.003 | T17: =MEDIAN(O17:S17) -> 32365.393 | U17: Min. | V17: =((O17*$AB$16)+O17) -> 19121.573 | W17: =((P17*$AB$16)+P17) -> 28933.846 | X17: =((Q17*$AB$16)+Q17) -> 33711.794 | Y17: =((R17*$AB$16)+R17) -> 43766.149 | Z17: =((S17*$AB$16)+S17) -> 46026.224 | AA17: =MEDIAN(V17:Z17) -> 33711.794 | AB17: 25.888 | AC17: TRM
E18: ADM-10 | F18: Especialista Servicios Admin. | G18: Máx. | H18: 1065812 | I18: 1215095 | J18: 1243828 | K18: 1312275 | L18: 1595668 | M18: 1281624 | N18: Máx. | O18: =((H18*$AB$15)+H18)/$AB$17 -> 42767.518 | P18: =((I18*$AB$15)+I18)/$AB$17 -> 48757.752 | Q18: =((J18*$AB$15)+J18)/$AB$17 -> 49910.713 | R18: =((K18*$AB$15)+K18)/$AB$17 -> 52657.265 | S18: =((L18*$AB$15)+L18)/$AB$17 -> 64028.891 | T18: =MEDIAN(O18:S18) -> 49910.713 | U18: Máx. | V18: =((O18*$AB$16)+O18) -> 44546.647 | W18: =((P18*$AB$16)+P18) -> 50786.075 | X18: =((Q18*$AB$16)+Q18) -> 51986.998 | Y18: =((R18*$AB$16)+R18) -> 54847.807 | Z18: =((S18*$AB$16)+S18) -> 66692.492 | AA18: =MEDIAN(V18:Z18) -> 51986.998
G19: Med | H19: 876510 | I19: 1046596 | J19: 1068106 | K19: 1177590 | L19: 1285805 | M19: 1092006 | N19: Med | O19: =((H19*$AB$15)+H19)/$AB$17 -> 35171.453 | P19: =((I19*$AB$15)+I19)/$AB$17 -> 41996.443 | Q19: =((J19*$AB$15)+J19)/$AB$17 -> 42859.569 | R19: =((K19*$AB$15)+K19)/$AB$17 -> 47252.8 | S19: =((L19*$AB$15)+L19)/$AB$17 -> 51595.111 | T19: =MEDIAN(O19:S19) -> 42859.569 | U19: Med | V19: =((O19*$AB$16)+O19) -> 36634.586 | W19: =((P19*$AB$16)+P19) -> 43743.495 | X19: =((Q19*$AB$16)+Q19) -> 44642.527 | Y19: =((R19*$AB$16)+R19) -> 49218.517 | Z19: =((S19*$AB$16)+S19) -> 53741.468 | AA19: =MEDIAN(V19:Z19) -> 44642.527
G20: Min. | H20: 545311 | I20: 816706 | J20: 909534 | K20: 1043345 | L20: 1176239 | M20: 902388 | N20: Min. | O20: =((H20*$AB$15)+H20)/$AB$17 -> 21881.531 | P20: =((I20*$AB$15)+I20)/$AB$17 -> 32771.716 | Q20: =((J20*$AB$15)+J20)/$AB$17 -> 36496.598 | R20: =((K20*$AB$15)+K20)/$AB$17 -> 41865.991 | S20: =((L20*$AB$15)+L20)/$AB$17 -> 47198.589 | T20: =MEDIAN(O20:S20) -> 36496.598 | U20: Min. | V20: =((O20*$AB$16)+O20) -> 22791.802 | W20: =((P20*$AB$16)+P20) -> 34135.02 | X20: =((Q20*$AB$16)+Q20) -> 38014.856 | Y20: =((R20*$AB$16)+R20) -> 43607.617 | Z20: =((S20*$AB$16)+S20) -> 49162.05 | AA20: =MEDIAN(V20:Z20) -> 38014.856
E21: DPM-10 | F21: Responsable de programa senior | G21: Máx. | H21: 857087 | I21: 1111499 | J21: 1274246 | K21: 1584249 | L21: 2126740 | M21: 1367979 | N21: Máx. | O21: =((H21*$AB$15)+H21)/$AB$17 -> 34392.073 | P21: =((I21*$AB$15)+I21)/$AB$17 -> 44600.787 | Q21: =((J21*$AB$15)+J21)/$AB$17 -> 51131.286 | R21: =((K21*$AB$15)+K21)/$AB$17 -> 63570.684 | S21: =((L21*$AB$15)+L21)/$AB$17 -> 85339.057 | T21: =MEDIAN(O21:S21) -> 51131.286 | U21: Máx. | V21: =((O21*$AB$16)+O21) -> 35822.783 | W21: =((P21*$AB$16)+P21) -> 46456.179 | X21: =((Q21*$AB$16)+Q21) -> 53258.348 | Y21: =((R21*$AB$16)+R21) -> 66215.224 | Z21: =((S21*$AB$16)+S21) -> 88889.162 | AA21: =MEDIAN(V21:Z21) -> 53258.348
G22: Med | H22: 680033 | I22: 964818 | J22: 1057479 | K22: 1260085 | L22: 1452336 | M22: 1109861 | N22: Med | O22: =((H22*$AB$15)+H22)/$AB$17 -> 27287.48 | P22: =((I22*$AB$15)+I22)/$AB$17 -> 38714.962 | Q22: =((J22*$AB$15)+J22)/$AB$17 -> 42433.142 | R22: =((K22*$AB$15)+K22)/$AB$17 -> 50563.052 | S22: =((L22*$AB$15)+L22)/$AB$17 -> 58277.45 | T22: =MEDIAN(O22:S22) -> 42433.142 | U22: Med | V22: =((O22*$AB$16)+O22) -> 28422.639 | W22: =((P22*$AB$16)+P22) -> 40325.505 | X22: =((Q22*$AB$16)+Q22) -> 44198.361 | Y22: =((R22*$AB$16)+R22) -> 52666.475 | Z22: =((S22*$AB$16)+S22) -> 60701.792 | AA22: =MEDIAN(V22:Z22) -> 44198.361
G23: Min. | H23: 502979 | I23: 716872 | J23: 807240 | K23: 996061 | L23: 1243740 | M23: 851744 | N23: Min. | O23: =((H23*$AB$15)+H23)/$AB$17 -> 20182.887 | P23: =((I23*$AB$15)+I23)/$AB$17 -> 28765.707 | Q23: =((J23*$AB$15)+J23)/$AB$17 -> 32391.877 | R23: =((K23*$AB$15)+K23)/$AB$17 -> 39968.641 | S23: =((L23*$AB$15)+L23)/$AB$17 -> 49907.181 | T23: =MEDIAN(O23:S23) -> 32391.877 | U23: Min. | V23: =((O23*$AB$16)+O23) -> 21022.495 | W23: =((P23*$AB$16)+P23) -> 29962.361 | X23: =((Q23*$AB$16)+Q23) -> 33739.379 | Y23: =((R23*$AB$16)+R23) -> 41631.336 | Z23: =((S23*$AB$16)+S23) -> 51983.32 | AA23: =MEDIAN(V23:Z23) -> 33739.379
E24: FIN-10 | F24: Experto contable | G24: Máx. | H24: 857087 | I24: 1136760 | J24: 1237256 | K24: 1299991 | L24: 1595668 | M24: 1213294 | N24: Máx. | O24: =((H24*$AB$15)+H24)/$AB$17 -> 34392.073 | P24: =((I24*$AB$15)+I24)/$AB$17 -> 45614.427 | Q24: =((J24*$AB$15)+J24)/$AB$17 -> 49647 | R24: =((K24*$AB$15)+K24)/$AB$17 -> 52164.348 | S24: =((L24*$AB$15)+L24)/$AB$17 -> 64028.891 | T24: =MEDIAN(O24:S24) -> 49647 | U24: Máx. | V24: =((O24*$AB$16)+O24) -> 35822.783 | W24: =((P24*$AB$16)+P24) -> 47511.987 | X24: =((Q24*$AB$16)+Q24) -> 51712.315 | Y24: =((R24*$AB$16)+R24) -> 54334.385 | Z24: =((S24*$AB$16)+S24) -> 66692.492 | AA24: =MEDIAN(V24:Z24) -> 51712.315
G25: Med | H25: 658762 | I25: 887053 | J25: 1053541 | K25: 1173703 | L25: 1297569 | M25: 1012638 | N25: Med | O25: =((H25*$AB$15)+H25)/$AB$17 -> 26433.945 | P25: =((I25*$AB$15)+I25)/$AB$17 -> 35594.509 | Q25: =((J25*$AB$15)+J25)/$AB$17 -> 42275.123 | R25: =((K25*$AB$15)+K25)/$AB$17 -> 47096.828 | S25: =((L25*$AB$15)+L25)/$AB$17 -> 52067.162 | T25: =MEDIAN(O25:S25) -> 42275.123 | U25: Med | V25: =((O25*$AB$16)+O25) -> 27533.597 | W25: =((P25*$AB$16)+P25) -> 37075.241 | X25: =((Q25*$AB$16)+Q25) -> 44033.768 | Y25: =((R25*$AB$16)+R25) -> 49056.056 | Z25: =((S25*$AB$16)+S25) -> 54233.155 | AA25: =MEDIAN(V25:Z25) -> 44033.768
G26: Min. | H26: 457498 | I26: 524145 | J26: 843126 | K26: 1028145 | L26: 1176239 | M26: 811983 | N26: Min. | O26: =((H26*$AB$15)+H26)/$AB$17 -> 18357.885 | P26: =((I26*$AB$15)+I26)/$AB$17 -> 21032.209 | Q26: =((J26*$AB$15)+J26)/$AB$17 -> 33831.864 | R26: =((K26*$AB$15)+K26)/$AB$17 -> 41256.066 | S26: =((L26*$AB$15)+L26)/$AB$17 -> 47198.589 | T26: =MEDIAN(O26:S26) -> 33831.864 | U26: Min. | V26: =((O26*$AB$16)+O26) -> 19121.573 | W26: =((P26*$AB$16)+P26) -> 21907.149 | X26: =((Q26*$AB$16)+Q26) -> 35239.269 | Y26: =((R26*$AB$16)+R26) -> 42972.318 | Z26: =((S26*$AB$16)+S26) -> 49162.05 | AA26: =MEDIAN(V26:Z26) -> 35239.269
E27: FND-10 | F27: Senior Fundraising Post, Fundraising Manager | G27: Máx. | H27: 857087 | I27: 871891 | J27: 984273 | K27: 1184027 | L27: 1460946 | M27: 1071645 | N27: Máx. | O27: =((H27*$AB$15)+H27)/$AB$17 -> 34392.073 | P27: =((I27*$AB$15)+I27)/$AB$17 -> 34986.108 | Q27: =((J27*$AB$15)+J27)/$AB$17 -> 39495.627 | R27: =((K27*$AB$15)+K27)/$AB$17 -> 47511.096 | S27: =((L27*$AB$15)+L27)/$AB$17 -> 58622.941 | T27: =MEDIAN(O27:S27) -> 39495.627 | U27: Máx. | V27: =((O27*$AB$16)+O27) -> 35822.783 | W27: =((P27*$AB$16)+P27) -> 36441.53 | X27: =((Q27*$AB$16)+Q27) -> 41138.645 | Y27: =((R27*$AB$16)+R27) -> 49487.557 | Z27: =((S27*$AB$16)+S27) -> 61061.656 | AA27: =MEDIAN(V27:Z27) -> 41138.645
G28: Med | H28: 680033 | I28: 709429 | J28: 814509 | K28: 987744 | L28: 1221604 | M28: 882664 | N28: Med | O28: =((H28*$AB$15)+H28)/$AB$17 -> 27287.48 | P28: =((I28*$AB$15)+I28)/$AB$17 -> 28467.044 | Q28: =((J28*$AB$15)+J28)/$AB$17 -> 32683.558 | R28: =((K28*$AB$15)+K28)/$AB$17 -> 39634.907 | S28: =((L28*$AB$15)+L28)/$AB$17 -> 49018.937 | T28: =MEDIAN(O28:S28) -> 32683.558 | U28: Med | V28: =((O28*$AB$16)+O28) -> 28422.639 | W28: =((P28*$AB$16)+P28) -> 29651.273 | X28: =((Q28*$AB$16)+Q28) -> 34043.194 | Y28: =((R28*$AB$16)+R28) -> 41283.719 | Z28: =((S28*$AB$16)+S28) -> 51058.125 | AA28: =MEDIAN(V28:Z28) -> 34043.194
G29: Min. | H29: 502979 | I29: 546967 | J29: 644745 | K29: 791460 | L29: 982262 | M29: 693683 | N29: Min. | O29: =((H29*$AB$15)+H29)/$AB$17 -> 20182.887 | P29: =((I29*$AB$15)+I29)/$AB$17 -> 21947.981 | Q29: =((J29*$AB$15)+J29)/$AB$17 -> 25871.489 | R29: =((K29*$AB$15)+K29)/$AB$17 -> 31758.678 | S29: =((L29*$AB$15)+L29)/$AB$17 -> 39414.932 | T29: =MEDIAN(O29:S29) -> 25871.489 | U29: Min. | V29: =((O29*$AB$16)+O29) -> 21022.495 | W29: =((P29*$AB$16)+P29) -> 22861.017 | X29: =((Q29*$AB$16)+Q29) -> 26947.743 | Y29: =((R29*$AB$16)+R29) -> 33079.839 | Z29: =((S29*$AB$16)+S29) -> 41054.593 | AA29: =MEDIAN(V29:Z29) -> 26947.743
E30: HR-10 | F30: Experto en RR.HH. | G30: Máx. | H30: 857087 | I30: 1162995 | J30: 1460946 | K30: 1555867 | L30: 2100460 | M30: 1408031 | N30: Máx. | O30: =((H30*$AB$15)+H30)/$AB$17 -> 34392.073 | P30: =((I30*$AB$15)+I30)/$AB$17 -> 46667.151 | Q30: =((J30*$AB$15)+J30)/$AB$17 -> 58622.941 | R30: =((K30*$AB$15)+K30)/$AB$17 -> 62431.808 | S30: =((L30*$AB$15)+L30)/$AB$17 -> 84284.528 | T30: =MEDIAN(O30:S30) -> 58622.941 | U30: Máx. | V30: =((O30*$AB$16)+O30) -> 35822.783 | W30: =((P30*$AB$16)+P30) -> 48608.505 | X30: =((Q30*$AB$16)+Q30) -> 61061.656 | Y30: =((R30*$AB$16)+R30) -> 65028.971 | Z30: =((S30*$AB$16)+S30) -> 87790.764 | AA30: =MEDIAN(V30:Z30) -> 61061.656
G31: Med | H31: 680033 | I31: 1025330 | J31: 1180125 | K31: 1240225 | L31: 1479152 | M31: 1124346 | N31: Med | O31: =((H31*$AB$15)+H31)/$AB$17 -> 27287.48 | P31: =((I31*$AB$15)+I31)/$AB$17 -> 41143.109 | Q31: =((J31*$AB$15)+J31)/$AB$17 -> 47354.521 | R31: =((K31*$AB$15)+K31)/$AB$17 -> 49766.136 | S31: =((L31*$AB$15)+L31)/$AB$17 -> 59353.488 | T31: =MEDIAN(O31:S31) -> 47354.521 | U31: Med | V31: =((O31*$AB$16)+O31) -> 28422.639 | W31: =((P31*$AB$16)+P31) -> 42854.662 | X31: =((Q31*$AB$16)+Q31) -> 49324.469 | Y31: =((R31*$AB$16)+R31) -> 51836.407 | Z31: =((S31*$AB$16)+S31) -> 61822.593 | AA31: =MEDIAN(V31:Z31) -> 49324.469
G32: Min. | H32: 502979 | I32: 781346 | J32: 857845 | K32: 952144 | L32: 1056820 | M32: 840660 | N32: Min. | O32: =((H32*$AB$15)+H32)/$AB$17 -> 20182.887 | P32: =((I32*$AB$15)+I32)/$AB$17 -> 31352.836 | Q32: =((J32*$AB$15)+J32)/$AB$17 -> 34422.489 | R32: =((K32*$AB$15)+K32)/$AB$17 -> 38206.396 | S32: =((L32*$AB$15)+L32)/$AB$17 -> 42406.699 | T32: =MEDIAN(O32:S32) -> 34422.489 | U32: Min. | V32: =((O32*$AB$16)+O32) -> 21022.495 | W32: =((P32*$AB$16)+P32) -> 32657.114 | X32: =((Q32*$AB$16)+Q32) -> 35854.464 | Y32: =((R32*$AB$16)+R32) -> 39795.782 | Z32: =((S32*$AB$16)+S32) -> 44170.817 | AA32: =MEDIAN(V32:Z32) -> 35854.464
A33: BG-9 | B33: Analyze | D33: BG-9 DCOP/DPD/Director of Function XX | E33: GEN-09 | F33: Profesional nivel operativo | G33: Máx. | H33: 431487 | I33: 820593 | J33: 859600 | K33: 1144676 | L33: 1946078 | M33: 974641 | N33: Máx. | O33: =((H33*$AB$15)+H33)/$AB$17 -> 17314.149 | P33: =((I33*$AB$15)+I33)/$AB$17 -> 32927.689 | Q33: =((J33*$AB$15)+J33)/$AB$17 -> 34492.911 | R33: =((K33*$AB$15)+K33)/$AB$17 -> 45932.07 | S33: =((L33*$AB$15)+L33)/$AB$17 -> 78089.687 | T33: =MEDIAN(O33:S33) -> 34492.911 | U33: Máx. | V33: =((O33*$AB$16)+O33) -> 18034.418 | W33: =((P33*$AB$16)+P33) -> 34297.481 | X33: =((Q33*$AB$16)+Q33) -> 35927.816 | Y33: =((R33*$AB$16)+R33) -> 47842.844 | Z33: =((S33*$AB$16)+S33) -> 81338.218 | AA33: =MEDIAN(V33:Z33) -> 35927.816
G34: Med | H34: 414767 | I34: 675902 | J34: 784178 | K34: 912905 | L34: 1622087 | M34: 823932 | N34: Med | O34: =((H34*$AB$15)+H34)/$AB$17 -> 16643.231 | P34: =((I34*$AB$15)+I34)/$AB$17 -> 27121.717 | Q34: =((J34*$AB$15)+J34)/$AB$17 -> 31466.475 | R34: =((K34*$AB$15)+K34)/$AB$17 -> 36631.865 | S34: =((L34*$AB$15)+L34)/$AB$17 -> 65088.998 | T34: =MEDIAN(O34:S34) -> 31466.475 | U34: Med | V34: =((O34*$AB$16)+O34) -> 17335.589 | W34: =((P34*$AB$16)+P34) -> 28249.98 | X34: =((Q34*$AB$16)+Q34) -> 32775.48 | Y34: =((R34*$AB$16)+R34) -> 38155.75 | Z34: =((S34*$AB$16)+S34) -> 67796.7 | AA34: =MEDIAN(V34:Z34) -> 32775.48
G35: Min. | H35: 398046 | I35: 544206 | J35: 605500 | K35: 690891 | L35: 1374707 | M35: 673222 | N35: Min. | O35: =((H35*$AB$15)+H35)/$AB$17 -> 15972.272 | P35: =((I35*$AB$15)+I35)/$AB$17 -> 21837.191 | Q35: =((J35*$AB$15)+J35)/$AB$17 -> 24296.717 | R35: =((K35*$AB$15)+K35)/$AB$17 -> 27723.176 | S35: =((L35*$AB$15)+L35)/$AB$17 -> 55162.455 | T35: =MEDIAN(O35:S35) -> 24296.717 | U35: Min. | V35: =((O35*$AB$16)+O35) -> 16636.719 | W35: =((P35*$AB$16)+P35) -> 22745.618 | X35: =((Q35*$AB$16)+Q35) -> 25307.46 | Y35: =((R35*$AB$16)+R35) -> 28876.46 | Z35: =((S35*$AB$16)+S35) -> 57457.213 | AA35: =MEDIAN(V35:Z35) -> 25307.46
E36: ADM-09 | F36: Responsable Servicios Administrativos | G36: Máx. | H36: 563226 | I36: 669647 | J36: 816237 | K36: 891313 | L36: 1519105 | M36: 875321 | N36: Máx. | O36: =((H36*$AB$15)+H36)/$AB$17 -> 22600.401 | P36: =((I36*$AB$15)+I36)/$AB$17 -> 26870.724 | Q36: =((J36*$AB$15)+J36)/$AB$17 -> 32752.897 | R36: =((K36*$AB$15)+K36)/$AB$17 -> 35765.449 | S36: =((L36*$AB$15)+L36)/$AB$17 -> 60956.67 | T36: =MEDIAN(O36:S36) -> 32752.897 | U36: Máx. | V36: =((O36*$AB$16)+O36) -> 23540.577 | W36: =((P36*$AB$16)+P36) -> 27988.546 | X36: =((Q36*$AB$16)+Q36) -> 34115.417 | Y36: =((R36*$AB$16)+R36) -> 37253.292 | Z36: =((S36*$AB$16)+S36) -> 63492.468 | AA36: =MEDIAN(V36:Z36) -> 34115.417
G37: Med | H37: 495221 | I37: 645518 | J37: 743226 | K37: 830399 | L37: 1012737 | M37: 744469 | N37: Med | O37: =((H37*$AB$15)+H37)/$AB$17 -> 19871.584 | P37: =((I37*$AB$15)+I37)/$AB$17 -> 25902.507 | Q37: =((J37*$AB$15)+J37)/$AB$17 -> 29823.206 | R37: =((K37*$AB$15)+K37)/$AB$17 -> 33321.171 | S37: =((L37*$AB$15)+L37)/$AB$17 -> 40637.793 | T37: =MEDIAN(O37:S37) -> 29823.206 | U37: Med | V37: =((O37*$AB$16)+O37) -> 20698.242 | W37: =((P37*$AB$16)+P37) -> 26980.051 | X37: =((Q37*$AB$16)+Q37) -> 31063.852 | Y37: =((R37*$AB$16)+R37) -> 34707.332 | Z37: =((S37*$AB$16)+S37) -> 42328.326 | AA37: =MEDIAN(V37:Z37) -> 31063.852
G38: Min. | H38: 427216 | I38: 520001 | J38: 589430 | K38: 739138 | L38: 789728 | M38: 613617 | N38: Min. | O38: =((H38*$AB$15)+H38)/$AB$17 -> 17142.768 | P38: =((I38*$AB$15)+I38)/$AB$17 -> 20865.924 | Q38: =((J38*$AB$15)+J38)/$AB$17 -> 23651.881 | R38: =((K38*$AB$15)+K38)/$AB$17 -> 29659.169 | S38: =((L38*$AB$15)+L38)/$AB$17 -> 31689.178 | T38: =MEDIAN(O38:S38) -> 23651.881 | U38: Min. | V38: =((O38*$AB$16)+O38) -> 17855.907 | W38: =((P38*$AB$16)+P38) -> 21733.946 | X38: =((Q38*$AB$16)+Q38) -> 24635.799 | Y38: =((R38*$AB$16)+R38) -> 30892.99 | Z38: =((S38*$AB$16)+S38) -> 33007.448 | AA38: =MEDIAN(V38:Z38) -> 24635.799
E39: DPM-09 | F39: Responsable de proyecto | G39: Máx. | H39: 489209 | I39: 819342 | J39: 859600 | K39: 1267082 | L39: 1946078 | M39: 1029938 | N39: Máx. | O39: =((H39*$AB$15)+H39)/$AB$17 -> 19630.343 | P39: =((I39*$AB$15)+I39)/$AB$17 -> 32877.49 | Q39: =((J39*$AB$15)+J39)/$AB$17 -> 34492.911 | R39: =((K39*$AB$15)+K39)/$AB$17 -> 50843.819 | S39: =((L39*$AB$15)+L39)/$AB$17 -> 78089.687 | T39: =MEDIAN(O39:S39) -> 34492.911 | U39: Máx. | V39: =((O39*$AB$16)+O39) -> 20446.965 | W39: =((P39*$AB$16)+P39) -> 34245.194 | X39: =((Q39*$AB$16)+Q39) -> 35927.816 | Y39: =((R39*$AB$16)+R39) -> 52958.922 | Z39: =((S39*$AB$16)+S39) -> 81338.218 | AA39: =MEDIAN(V39:Z39) -> 35927.816
G40: Med | H40: 489209 | I40: 690468 | J40: 780720 | K40: 1012737 | L40: 1622087 | M40: 852407 | N40: Med | O40: =((H40*$AB$15)+H40)/$AB$17 -> 19630.343 | P40: =((I40*$AB$15)+I40)/$AB$17 -> 27706.202 | Q40: =((J40*$AB$15)+J40)/$AB$17 -> 31327.717 | R40: =((K40*$AB$15)+K40)/$AB$17 -> 40637.793 | S40: =((L40*$AB$15)+L40)/$AB$17 -> 65088.998 | T40: =MEDIAN(O40:S40) -> 31327.717 | U40: Med | V40: =((O40*$AB$16)+O40) -> 20446.965 | W40: =((P40*$AB$16)+P40) -> 28858.78 | X40: =((Q40*$AB$16)+Q40) -> 32630.95 | Y40: =((R40*$AB$16)+R40) -> 42328.326 | Z40: =((S40*$AB$16)+S40) -> 67796.7 | AA40: =MEDIAN(V40:Z40) -> 32630.95
G41: Min. | H41: 426218 | I41: 543102 | J41: 605500 | K41: 807333 | L41: 1298097 | M41: 674876 | N41: Min. | O41: =((H41*$AB$15)+H41)/$AB$17 -> 17102.722 | P41: =((I41*$AB$15)+I41)/$AB$17 -> 21792.891 | Q41: =((J41*$AB$15)+J41)/$AB$17 -> 24296.717 | R41: =((K41*$AB$15)+K41)/$AB$17 -> 32395.609 | S41: =((L41*$AB$15)+L41)/$AB$17 -> 52088.348 | T41: =MEDIAN(O41:S41) -> 24296.717 | U41: Min. | V41: =((O41*$AB$16)+O41) -> 17814.195 | W41: =((P41*$AB$16)+P41) -> 22699.475 | X41: =((Q41*$AB$16)+Q41) -> 25307.46 | Y41: =((R41*$AB$16)+R41) -> 33743.266 | Z41: =((S41*$AB$16)+S41) -> 54255.224 | AA41: =MEDIAN(V41:Z41) -> 25307.46
E42: FIN-09 | F42: Contable | G42: Máx. | H42: 632580 | I42: 752539 | J42: 828726 | K42: 970470 | L42: 1519105 | M42: 897970 | N42: Máx. | O42: =((H42*$AB$15)+H42)/$AB$17 -> 25383.348 | P42: =((I42*$AB$15)+I42)/$AB$17 -> 30196.906 | Q42: =((J42*$AB$15)+J42)/$AB$17 -> 33254.039 | R42: =((K42*$AB$15)+K42)/$AB$17 -> 38941.758 | S42: =((L42*$AB$15)+L42)/$AB$17 -> 60956.67 | T42: =MEDIAN(O42:S42) -> 33254.039 | U42: Máx. | V42: =((O42*$AB$16)+O42) -> 26439.295 | W42: =((P42*$AB$16)+P42) -> 31453.098 | X42: =((Q42*$AB$16)+Q42) -> 34637.407 | Y42: =((R42*$AB$16)+R42) -> 40561.735 | Z42: =((S42*$AB$16)+S42) -> 63492.468 | AA42: =MEDIAN(V42:Z42) -> 34637.407
G43: Med | H43: 504238 | I43: 630461 | J43: 716310 | K43: 830159 | L43: 1012737 | M43: 737852 | N43: Med | O43: =((H43*$AB$15)+H43)/$AB$17 -> 20233.407 | P43: =((I43*$AB$15)+I43)/$AB$17 -> 25298.319 | Q43: =((J43*$AB$15)+J43)/$AB$17 -> 28743.156 | R43: =((K43*$AB$15)+K43)/$AB$17 -> 33311.541 | S43: =((L43*$AB$15)+L43)/$AB$17 -> 40637.793 | T43: =MEDIAN(O43:S43) -> 28743.156 | U43: Med | V43: =((O43*$AB$16)+O43) -> 21075.116 | W43: =((P43*$AB$16)+P43) -> 26350.729 | X43: =((Q43*$AB$16)+Q43) -> 29938.872 | Y43: =((R43*$AB$16)+R43) -> 34697.301 | Z43: =((S43*$AB$16)+S43) -> 42328.326 | AA43: =MEDIAN(V43:Z43) -> 29938.872
G44: Min. | H44: 361300 | I44: 508382 | J44: 573020 | K44: 622328 | L44: 805439 | M44: 577734 | N44: Min. | O44: =((H44*$AB$15)+H44)/$AB$17 -> 14497.777 | P44: =((I44*$AB$15)+I44)/$AB$17 -> 20399.692 | Q44: =((J44*$AB$15)+J44)/$AB$17 -> 22993.401 | R44: =((K44*$AB$15)+K44)/$AB$17 -> 24971.969 | S44: =((L44*$AB$15)+L44)/$AB$17 -> 32319.609 | T44: =MEDIAN(O44:S44) -> 22993.401 | U44: Min. | V44: =((O44*$AB$16)+O44) -> 15100.884 | W44: =((P44*$AB$16)+P44) -> 21248.319 | X44: =((Q44*$AB$16)+Q44) -> 23949.927 | Y44: =((R44*$AB$16)+R44) -> 26010.803 | Z44: =((S44*$AB$16)+S44) -> 33664.105 | AA44: =MEDIAN(V44:Z44) -> 23949.927
E45: FND-09 | F45: Fundraising Post, Regional Fundraiser | G45: Máx. | H45: 812794 | I45: 828726 | J45: 859600 | K45: 1002691 | L45: 1194791 | M45: 939720 | N45: Máx. | O45: =((H45*$AB$15)+H45)/$AB$17 -> 32614.741 | P45: =((I45*$AB$15)+I45)/$AB$17 -> 33254.039 | Q45: =((J45*$AB$15)+J45)/$AB$17 -> 34492.911 | R45: =((K45*$AB$15)+K45)/$AB$17 -> 40234.681 | S45: =((L45*$AB$15)+L45)/$AB$17 -> 47943.02 | T45: =MEDIAN(O45:S45) -> 34492.911 | U45: Máx. | V45: =((O45*$AB$16)+O45) -> 33971.514 | W45: =((P45*$AB$16)+P45) -> 34637.407 | X45: =((Q45*$AB$16)+Q45) -> 35927.816 | Y45: =((R45*$AB$16)+R45) -> 41908.443 | Z45: =((S45*$AB$16)+S45) -> 49937.449 | AA45: =MEDIAN(V45:Z45) -> 35927.816
G46: Med | H46: 673834 | I46: 716310 | J46: 812794 | K46: 843735 | L46: 949301 | M46: 799195 | N46: Med | O46: =((H46*$AB$15)+H46)/$AB$17 -> 27038.735 | P46: =((I46*$AB$15)+I46)/$AB$17 -> 28743.156 | Q46: =((J46*$AB$15)+J46)/$AB$17 -> 32614.741 | R46: =((K46*$AB$15)+K46)/$AB$17 -> 33856.301 | S46: =((L46*$AB$15)+L46)/$AB$17 -> 38092.316 | T46: =MEDIAN(O46:S46) -> 32614.741 | U46: Med | V46: =((O46*$AB$16)+O46) -> 28163.546 | W46: =((P46*$AB$16)+P46) -> 29938.872 | X46: =((Q46*$AB$16)+Q46) -> 33971.514 | Y46: =((R46*$AB$16)+R46) -> 35264.723 | Z46: =((S46*$AB$16)+S46) -> 39676.956 | AA46: =MEDIAN(V46:Z46) -> 33971.514
G47: Min. | H47: 518942 | I47: 573020 | J47: 684779 | K47: 703811 | L47: 812794 | M47: 658669 | N47: Min. | O47: =((H47*$AB$15)+H47)/$AB$17 -> 20823.43 | P47: =((I47*$AB$15)+I47)/$AB$17 -> 22993.401 | Q47: =((J47*$AB$15)+J47)/$AB$17 -> 27477.921 | R47: =((K47*$AB$15)+K47)/$AB$17 -> 28241.613 | S47: =((L47*$AB$15)+L47)/$AB$17 -> 32614.741 | T47: =MEDIAN(O47:S47) -> 27477.921 | U47: Min. | V47: =((O47*$AB$16)+O47) -> 21689.684 | W47: =((P47*$AB$16)+P47) -> 23949.927 | X47: =((Q47*$AB$16)+Q47) -> 28621.003 | Y47: =((R47*$AB$16)+R47) -> 29416.464 | Z47: =((S47*$AB$16)+S47) -> 33971.514 | AA47: =MEDIAN(V47:Z47) -> 28621.003
E48: HR-09 | F48: Analista Servicios RR.HH. | G48: Máx. | H48: 563226 | I48: 737951 | J48: 859600 | K48: 1020426 | L48: 1519105 | M48: 922669 | N48: Máx. | O48: =((H48*$AB$15)+H48)/$AB$17 -> 22600.401 | P48: =((I48*$AB$15)+I48)/$AB$17 -> 29611.538 | Q48: =((J48*$AB$15)+J48)/$AB$17 -> 34492.911 | R48: =((K48*$AB$15)+K48)/$AB$17 -> 40946.328 | S48: =((L48*$AB$15)+L48)/$AB$17 -> 60956.67 | T48: =MEDIAN(O48:S48) -> 34492.911 | U48: Máx. | V48: =((O48*$AB$16)+O48) -> 23540.577 | W48: =((P48*$AB$16)+P48) -> 30843.378 | X48: =((Q48*$AB$16)+Q48) -> 35927.816 | Y48: =((R48*$AB$16)+R48) -> 42649.695 | Z48: =((S48*$AB$16)+S48) -> 63492.468 | AA48: =MEDIAN(V48:Z48) -> 35927.816
G49: Med | H49: 495221 | I49: 589036 | J49: 716310 | K49: 911641 | L49: 1012737 | M49: 746517 | N49: Med | O49: =((H49*$AB$15)+H49)/$AB$17 -> 19871.584 | P49: =((I49*$AB$15)+I49)/$AB$17 -> 23636.071 | Q49: =((J49*$AB$15)+J49)/$AB$17 -> 28743.156 | R49: =((K49*$AB$15)+K49)/$AB$17 -> 36581.145 | S49: =((L49*$AB$15)+L49)/$AB$17 -> 40637.793 | T49: =MEDIAN(O49:S49) -> 28743.156 | U49: Med | V49: =((O49*$AB$16)+O49) -> 20698.242 | W49: =((P49*$AB$16)+P49) -> 24619.331 | X49: =((Q49*$AB$16)+Q49) -> 29938.872 | Y49: =((R49*$AB$16)+R49) -> 38102.92 | Z49: =((S49*$AB$16)+S49) -> 42328.326 | AA49: =MEDIAN(V49:Z49) -> 29938.872
G50: Min. | H50: 361300 | I50: 466792 | J50: 518942 | K50: 597674 | L50: 983385 | M50: 570366 | N50: Min. | O50: =((H50*$AB$15)+H50)/$AB$17 -> 14497.777 | P50: =((I50*$AB$15)+I50)/$AB$17 -> 18730.822 | Q50: =((J50*$AB$15)+J50)/$AB$17 -> 20823.43 | R50: =((K50*$AB$15)+K50)/$AB$17 -> 23982.685 | S50: =((L50*$AB$15)+L50)/$AB$17 -> 39459.995 | T50: =MEDIAN(O50:S50) -> 20823.43 | U50: Min. | V50: =((O50*$AB$16)+O50) -> 15100.884 | W50: =((P50*$AB$16)+P50) -> 19510.025 | X50: =((Q50*$AB$16)+Q50) -> 21689.684 | Y50: =((R50*$AB$16)+R50) -> 24980.365 | Z50: =((S50*$AB$16)+S50) -> 41101.53 | AA50: =MEDIAN(V50:Z50) -> 21689.684
E51: IT-09 | F51: Analista/ | G51: Máx. | H51: 563226 | I51: 682531 | J51: 801836 | K51: 1013418 | L51: 1225000 | M51: 863354 | N51: Máx. | O51: =((H51*$AB$15)+H51)/$AB$17 -> 22600.401 | P51: =((I51*$AB$15)+I51)/$AB$17 -> 27387.716 | Q51: =((J51*$AB$15)+J51)/$AB$17 -> 32175.032 | R51: =((K51*$AB$15)+K51)/$AB$17 -> 40665.12 | S51: =((L51*$AB$15)+L51)/$AB$17 -> 49155.207 | T51: =MEDIAN(O51:S51) -> 32175.032 | U51: Máx. | V51: =((O51*$AB$16)+O51) -> 23540.577 | W51: =((P51*$AB$16)+P51) -> 28527.045 | X51: =((Q51*$AB$16)+Q51) -> 33513.514 | Y51: =((R51*$AB$16)+R51) -> 42356.789 | Z51: =((S51*$AB$16)+S51) -> 51200.064 | AA51: =MEDIAN(V51:Z51) -> 33513.514
G52: Med | H52: 495221 | I52: 559890 | J52: 624560 | K52: 822696 | L52: 1020833 | M52: 713538 | N52: Med | O52: =((H52*$AB$15)+H52)/$AB$17 -> 19871.584 | P52: =((I52*$AB$15)+I52)/$AB$17 -> 22466.538 | Q52: =((J52*$AB$15)+J52)/$AB$17 -> 25061.532 | R52: =((K52*$AB$15)+K52)/$AB$17 -> 33012.075 | S52: =((L52*$AB$15)+L52)/$AB$17 -> 40962.659 | T52: =MEDIAN(O52:S52) -> 25061.532 | U52: Med | V52: =((O52*$AB$16)+O52) -> 20698.242 | W52: =((P52*$AB$16)+P52) -> 23401.146 | X52: =((Q52*$AB$16)+Q52) -> 26104.091 | Y52: =((R52*$AB$16)+R52) -> 34385.378 | Z52: =((S52*$AB$16)+S52) -> 42666.706 | AA52: =MEDIAN(V52:Z52) -> 26104.091
G53: Min. | H53: 427216 | I53: 437250 | J53: 447283 | K53: 631975 | L53: 816667 | M53: 563722 | N53: Min. | O53: =((H53*$AB$15)+H53)/$AB$17 -> 17142.768 | P53: =((I53*$AB$15)+I53)/$AB$17 -> 17545.399 | Q53: =((J53*$AB$15)+J53)/$AB$17 -> 17947.991 | R53: =((K53*$AB$15)+K53)/$AB$17 -> 25359.071 | S53: =((L53*$AB$15)+L53)/$AB$17 -> 32770.151 | T53: =MEDIAN(O53:S53) -> 17947.991 | U53: Min. | V53: =((O53*$AB$16)+O53) -> 17855.907 | W53: =((P53*$AB$16)+P53) -> 18275.288 | X53: =((Q53*$AB$16)+Q53) -> 18694.627 | Y53: =((R53*$AB$16)+R53) -> 26414.008 | Z53: =((S53*$AB$16)+S53) -> 34133.39 | AA53: =MEDIAN(V53:Z53) -> 18694.627
G54: Máx.
G55: Med
G56: Min.
A57: BG-8 | B57: Apply Basic Concepts | E57: BG-8 Transitional Managerial | G57: Máx. | H57: 627521 | I57: 842534 | J57: 846989 | K57: 898333 | L57: 1543883 | M57: 924420 | N57: Máx. | O57: =+(1281000*$AB$15)+H57 -> 677223.8 | P57: =+(1281000*$AB$15)+I57 -> 892236.8 | Q57: =+(1281000*$AB$15)+J57 -> 896691.8 | R57: =+(1281000*$AB$15)+K57 -> 948035.8 | S57: =+(1281000*$AB$15)+L57 -> 1593585.8 | T57: =MEDIAN(O57:S57) -> 896691.8 | U57: Máx. | V57: =+(1281000*$AB$16)+O57 -> 730513.4 | W57: =+(1281000*$AB$16)+P57 -> 945526.4 | X57: =+(1281000*$AB$16)+Q57 -> 949981.4 | Y57: =+(1281000*$AB$16)+R57 -> 1001325.4 | Z57: =+(1281000*$AB$16)+S57 -> 1646875.4 | AA57: =MEDIAN(V57:Z57) -> 949981.4
G58: Med | H58: 509861 | I58: 668801 | J58: 692818 | K58: 770000 | L58: 1092775 | M58: 710943 | N58: Med | O58: =+(1281000*$AB$15)+H58 -> 559563.8 | P58: =+(1281000*$AB$15)+I58 -> 718503.8 | Q58: =+(1281000*$AB$15)+J58 -> 742520.8 | R58: =+(1281000*$AB$15)+K58 -> 819702.8 | S58: =+(1281000*$AB$15)+L58 -> 1142477.8 | T58: =MEDIAN(O58:S58) -> 742520.8 | U58: Med | V58: =+(1281000*$AB$16)+O58 -> 612853.4 | W58: =+(1281000*$AB$16)+P58 -> 771793.4 | X58: =+(1281000*$AB$16)+Q58 -> 795810.4 | Y58: =+(1281000*$AB$16)+R58 -> 872992.4 | Z58: =+(1281000*$AB$16)+S58 -> 1195767.4 | AA58: =MEDIAN(V58:Z58) -> 795810.4
G59: Min. | H59: 392201 | I59: 423652 | J59: 495068 | K59: 543102 | L59: 641667 | M59: 497466 | N59: Min. | O59: =+(1281000*$AB$15)+H59 -> 441903.8 | P59: =+(1281000*$AB$15)+I59 -> 473354.8 | Q59: =+(1281000*$AB$15)+J59 -> 544770.8 | R59: =+(1281000*$AB$15)+K59 -> 592804.8 | S59: =+(1281000*$AB$15)+L59 -> 691369.8 | T59: =MEDIAN(O59:S59) -> 544770.8 | U59: Min. | V59: =+(1281000*$AB$16)+O59 -> 495193.4 | W59: =+(1281000*$AB$16)+P59 -> 526644.4 | X59: =+(1281000*$AB$16)+Q59 -> 598060.4 | Y59: =+(1281000*$AB$16)+R59 -> 646094.4 | Z59: =+(1281000*$AB$16)+S59 -> 744659.4 | AA59: =MEDIAN(V59:Z59) -> 598060.4
A60: BG-7 | B60: Manage Integrated Processes | C60: Poa-C | D60: BG-7 Manager/Specialist | E60: GEN-07 | F60: Proveedor de servicios / Examinador experto | G60: Máx. | H60: 379497 | I60: 558733 | J60: 648720 | K60: 866495 | L60: 1225700 | M60: 717960 | N60: Máx. | O60: =((H60*$AB$15)+H60)/$AB$17 -> 15227.962 | P60: =((I60*$AB$15)+I60)/$AB$17 -> 22420.111 | Q60: =((J60*$AB$15)+J60)/$AB$17 -> 26030.993 | R60: =((K60*$AB$15)+K60)/$AB$17 -> 34769.585 | S60: =((L60*$AB$15)+L60)/$AB$17 -> 49183.296 | T60: =MEDIAN(O60:S60) -> 26030.993 | U60: Máx. | V60: =((O60*$AB$16)+O60) -> 15861.445 | W60: =((P60*$AB$16)+P60) -> 23352.788 | X60: =((Q60*$AB$16)+Q60) -> 27113.882 | Y60: =((R60*$AB$16)+R60) -> 36215.999 | Z60: =((S60*$AB$16)+S60) -> 51229.321 | AA60: =MEDIAN(V60:Z60) -> 27113.882
G61: Med | H61: 366738 | I61: 445779 | J61: 579858 | K61: 693660 | L61: 1225700 | M61: 604288 | N61: Med | O61: =((H61*$AB$15)+H61)/$AB$17 -> 14715.986 | P61: =((I61*$AB$15)+I61)/$AB$17 -> 17887.64 | Q61: =((J61*$AB$15)+J61)/$AB$17 -> 23267.788 | R61: =((K61*$AB$15)+K61)/$AB$17 -> 27834.286 | S61: =((L61*$AB$15)+L61)/$AB$17 -> 49183.296 | T61: =MEDIAN(O61:S61) -> 23267.788 | U61: Med | V61: =((O61*$AB$16)+O61) -> 15328.171 | W61: =((P61*$AB$16)+P61) -> 18631.766 | X61: =((Q61*$AB$16)+Q61) -> 24235.728 | Y61: =((R61*$AB$16)+R61) -> 28992.193 | Z61: =((S61*$AB$16)+S61) -> 51229.321 | AA61: =MEDIAN(V61:Z61) -> 24235.728
G62: Min. | H62: 273242 | I62: 363805 | J62: 422541 | K62: 585038 | L62: 1225700 | M62: 490616 | N62: Min. | O62: =((H62*$AB$15)+H62)/$AB$17 -> 10964.3 | P62: =((I62*$AB$15)+I62)/$AB$17 -> 14598.294 | Q62: =((J62*$AB$15)+J62)/$AB$17 -> 16955.176 | R62: =((K62*$AB$15)+K62)/$AB$17 -> 23475.644 | S62: =((L62*$AB$15)+L62)/$AB$17 -> 49183.296 | T62: =MEDIAN(O62:S62) -> 16955.176 | U62: Min. | V62: =((O62*$AB$16)+O62) -> 11420.415 | W62: =((P62*$AB$16)+P62) -> 15205.583 | X62: =((Q62*$AB$16)+Q62) -> 17660.511 | Y62: =((R62*$AB$16)+R62) -> 24452.231 | Z62: =((S62*$AB$16)+S62) -> 51229.321 | AA62: =MEDIAN(V62:Z62) -> 17660.511
E63: ADM-07 | F63: Asistente de administración senior | G63: Máx. | H63: 489209 | I63: 571690 | J63: 624167 | K63: 814333 | L63: 1101228 | M63: 711782 | N63: Máx. | O63: =((H63*$AB$15)+H63)/$AB$17 -> 19630.343 | P63: =((I63*$AB$15)+I63)/$AB$17 -> 22940.033 | Q63: =((J63*$AB$15)+J63)/$AB$17 -> 25045.762 | R63: =((K63*$AB$15)+K63)/$AB$17 -> 32676.496 | S63: =((L63*$AB$15)+L63)/$AB$17 -> 44188.645 | T63: =MEDIAN(O63:S63) -> 25045.762 | U63: Máx. | V63: =((O63*$AB$16)+O63) -> 20446.965 | W63: =((P63*$AB$16)+P63) -> 23894.338 | X63: =((Q63*$AB$16)+Q63) -> 26087.665 | Y63: =((R63*$AB$16)+R63) -> 34035.838 | Z63: =((S63*$AB$16)+S63) -> 46026.893 | AA63: =MEDIAN(V63:Z63) -> 26087.665
G64: Med | H64: 469910 | I64: 506907 | J64: 577500 | K64: 631750 | L64: 734154 | M64: 582046 | N64: Med | O64: =((H64*$AB$15)+H64)/$AB$17 -> 18855.937 | P64: =((I64*$AB$15)+I64)/$AB$17 -> 20340.505 | Q64: =((J64*$AB$15)+J64)/$AB$17 -> 23173.169 | R64: =((K64*$AB$15)+K64)/$AB$17 -> 25350.042 | S64: =((L64*$AB$15)+L64)/$AB$17 -> 29459.177 | T64: =MEDIAN(O64:S64) -> 23173.169 | U64: Med | V64: =((O64*$AB$16)+O64) -> 19640.344 | W64: =((P64*$AB$16)+P64) -> 21186.67 | X64: =((Q64*$AB$16)+Q64) -> 24137.173 | Y64: =((R64*$AB$16)+R64) -> 26404.604 | Z64: =((S64*$AB$16)+S64) -> 30684.679 | AA64: =MEDIAN(V64:Z64) -> 24137.173
G65: Min. | H65: 367080 | I65: 386925 | J65: 443333 | K65: 483574 | L65: 595000 | M65: 452309 | N65: Min. | O65: =((H65*$AB$15)+H65)/$AB$17 -> 14729.709 | P65: =((I65*$AB$15)+I65)/$AB$17 -> 15526.023 | Q65: =((J65*$AB$15)+J65)/$AB$17 -> 17789.49 | R65: =((K65*$AB$15)+K65)/$AB$17 -> 19404.229 | S65: =((L65*$AB$15)+L65)/$AB$17 -> 23875.386 | T65: =MEDIAN(O65:S65) -> 17789.49 | U65: Min. | V65: =((O65*$AB$16)+O65) -> 15342.465 | W65: =((P65*$AB$16)+P65) -> 16171.906 | X65: =((Q65*$AB$16)+Q65) -> 18529.533 | Y65: =((R65*$AB$16)+R65) -> 20211.445 | Z65: =((S65*$AB$16)+S65) -> 24868.602 | AA65: =MEDIAN(V65:Z65) -> 18529.533
E66: DPM-07 A | F66: Asistente de programa senior | G66: Máx. | H66: 396528 | I66: 537883 | J66: 674522 | K66: 801749 | L66: 1101228 | M66: 694533 | N66: Máx. | O66: =((H66*$AB$15)+H66)/$AB$17 -> 15911.36 | P66: =((I66*$AB$15)+I66)/$AB$17 -> 21583.47 | Q66: =((J66*$AB$15)+J66)/$AB$17 -> 27066.342 | R66: =((K66*$AB$15)+K66)/$AB$17 -> 32171.541 | S66: =((L66*$AB$15)+L66)/$AB$17 -> 44188.645 | T66: =MEDIAN(O66:S66) -> 27066.342 | U66: Máx. | V66: =((O66*$AB$16)+O66) -> 16573.273 | W66: =((P66*$AB$16)+P66) -> 22481.342 | X66: =((Q66*$AB$16)+Q66) -> 28192.302 | Y66: =((R66*$AB$16)+R66) -> 33509.877 | Z66: =((S66*$AB$16)+S66) -> 46026.893 | AA66: =MEDIAN(V66:Z66) -> 28192.302
G67: Med | H67: 371200 | I67: 458620 | J67: 551541 | K67: 641503 | L67: 877452 | M67: 569375 | N67: Med | O67: =((H67*$AB$15)+H67)/$AB$17 -> 14895.031 | P67: =((I67*$AB$15)+I67)/$AB$17 -> 18402.907 | Q67: =((J67*$AB$15)+J67)/$AB$17 -> 22131.52 | R67: =((K67*$AB$15)+K67)/$AB$17 -> 25741.398 | S67: =((L67*$AB$15)+L67)/$AB$17 -> 35209.253 | T67: =MEDIAN(O67:S67) -> 22131.52 | U67: Med | V67: =((O67*$AB$16)+O67) -> 15514.664 | W67: =((P67*$AB$16)+P67) -> 19168.468 | X67: =((Q67*$AB$16)+Q67) -> 23052.191 | Y67: =((R67*$AB$16)+R67) -> 26812.24 | Z67: =((S67*$AB$16)+S67) -> 36673.958 | AA67: =MEDIAN(V67:Z67) -> 23052.191
G68: Min. | H68: 283483 | I68: 355179 | J68: 407028 | K68: 472978 | L68: 733915 | M68: 444216 | N68: Min. | O68: =((H68*$AB$15)+H68)/$AB$17 -> 11375.237 | P68: =((I68*$AB$15)+I68)/$AB$17 -> 14252.161 | Q68: =((J68*$AB$15)+J68)/$AB$17 -> 16332.69 | R68: =((K68*$AB$15)+K68)/$AB$17 -> 18979.046 | S68: =((L68*$AB$15)+L68)/$AB$17 -> 29449.587 | T68: =MEDIAN(O68:S68) -> 16332.69 | U68: Min. | V68: =((O68*$AB$16)+O68) -> 11848.447 | W68: =((P68*$AB$16)+P68) -> 14845.051 | X68: =((Q68*$AB$16)+Q68) -> 17012.13 | Y68: =((R68*$AB$16)+R68) -> 19768.574 | Z68: =((S68*$AB$16)+S68) -> 30674.69 | AA68: =MEDIAN(V68:Z68) -> 17012.13
E69: FIN-07 | F69: Auxiliar contable experto | G69: Máx. | H69: 388957 | I69: 552568 | J69: 563573 | K69: 808627 | L69: 1101228 | M69: 680377 | N69: Máx. | O69: =((H69*$AB$15)+H69)/$AB$17 -> 15607.561 | P69: =((I69*$AB$15)+I69)/$AB$17 -> 22172.73 | Q69: =((J69*$AB$15)+J69)/$AB$17 -> 22614.324 | R69: =((K69*$AB$15)+K69)/$AB$17 -> 32447.533 | S69: =((L69*$AB$15)+L69)/$AB$17 -> 44188.645 | T69: =MEDIAN(O69:S69) -> 22614.324 | U69: Máx. | V69: =((O69*$AB$16)+O69) -> 16256.835 | W69: =((P69*$AB$16)+P69) -> 23095.116 | X69: =((Q69*$AB$16)+Q69) -> 23555.08 | Y69: =((R69*$AB$16)+R69) -> 33797.35 | Z69: =((S69*$AB$16)+S69) -> 46026.893 | AA69: =MEDIAN(V69:Z69) -> 23555.08
G70: Med | H70: 369886 | I70: 459036 | J70: 484218 | K70: 640732 | L70: 877452 | M70: 558542 | N70: Med | O70: =((H70*$AB$15)+H70)/$AB$17 -> 14842.304 | P70: =((I70*$AB$15)+I70)/$AB$17 -> 18419.6 | Q70: =((J70*$AB$15)+J70)/$AB$17 -> 19430.07 | R70: =((K70*$AB$15)+K70)/$AB$17 -> 25710.461 | S70: =((L70*$AB$15)+L70)/$AB$17 -> 35209.253 | T70: =MEDIAN(O70:S70) -> 19430.07 | U70: Med | V70: =((O70*$AB$16)+O70) -> 15459.744 | W70: =((P70*$AB$16)+P70) -> 19185.855 | X70: =((Q70*$AB$16)+Q70) -> 20238.361 | Y70: =((R70*$AB$16)+R70) -> 26780.016 | Z70: =((S70*$AB$16)+S70) -> 36673.958 | AA70: =MEDIAN(V70:Z70) -> 20238.361
G71: Min. | H71: 273242 | I71: 363014 | J71: 390113 | K71: 469022 | L71: 733915 | M71: 436707 | N71: Min. | O71: =((H71*$AB$15)+H71)/$AB$17 -> 10964.3 | P71: =((I71*$AB$15)+I71)/$AB$17 -> 14566.554 | Q71: =((J71*$AB$15)+J71)/$AB$17 -> 15653.947 | R71: =((K71*$AB$15)+K71)/$AB$17 -> 18820.305 | S71: =((L71*$AB$15)+L71)/$AB$17 -> 29449.587 | T71: =MEDIAN(O71:S71) -> 15653.947 | U71: Min. | V71: =((O71*$AB$16)+O71) -> 11420.415 | W71: =((P71*$AB$16)+P71) -> 15172.522 | X71: =((Q71*$AB$16)+Q71) -> 16305.151 | Y71: =((R71*$AB$16)+R71) -> 19603.23 | Z71: =((S71*$AB$16)+S71) -> 30674.69 | AA71: =MEDIAN(V71:Z71) -> 16305.151
E72: HR-07 | F72: Asistente-experto Servicios RR.HH. | G72: Máx. | H72: 379561 | I72: 628766 | J72: 756889 | K72: 876373 | L72: 1101228 | M72: 749708 | N72: Máx. | O72: =((H72*$AB$15)+H72)/$AB$17 -> 15230.53 | P72: =((I72*$AB$15)+I72)/$AB$17 -> 25230.304 | Q72: =((J72*$AB$15)+J72)/$AB$17 -> 30371.458 | R72: =((K72*$AB$15)+K72)/$AB$17 -> 35165.956 | S72: =((L72*$AB$15)+L72)/$AB$17 -> 44188.645 | T72: =MEDIAN(O72:S72) -> 30371.458 | U72: Máx. | V72: =((O72*$AB$16)+O72) -> 15864.12 | W72: =((P72*$AB$16)+P72) -> 26279.885 | X72: =((Q72*$AB$16)+Q72) -> 31634.91 | Y72: =((R72*$AB$16)+R72) -> 36628.86 | Z72: =((S72*$AB$16)+S72) -> 46026.893 | AA72: =MEDIAN(V72:Z72) -> 31634.91
G73: Med | H73: 361273 | I73: 518781 | J73: 609591 | K73: 689077 | L73: 737643 | M73: 589175 | N73: Med | O73: =((H73*$AB$15)+H73)/$AB$17 -> 14496.693 | P73: =((I73*$AB$15)+I73)/$AB$17 -> 20816.969 | Q73: =((J73*$AB$15)+J73)/$AB$17 -> 24460.875 | R73: =((K73*$AB$15)+K73)/$AB$17 -> 27650.386 | S73: =((L73*$AB$15)+L73)/$AB$17 -> 29599.179 | T73: =MEDIAN(O73:S73) -> 24460.875 | U73: Med | V73: =((O73*$AB$16)+O73) -> 15099.756 | W73: =((P73*$AB$16)+P73) -> 21682.955 | X73: =((Q73*$AB$16)+Q73) -> 25478.447 | Y73: =((R73*$AB$16)+R73) -> 28800.642 | Z73: =((S73*$AB$16)+S73) -> 30830.505 | AA73: =MEDIAN(V73:Z73) -> 25478.447
G74: Min. | H74: 342984 | I74: 385214 | J74: 414246 | K74: 441146 | L74: 590541 | M74: 428642 | N74: Min. | O74: =((H74*$AB$15)+H74)/$AB$17 -> 13762.816 | P74: =((I74*$AB$15)+I74)/$AB$17 -> 15457.366 | Q74: =((J74*$AB$15)+J74)/$AB$17 -> 16622.325 | R74: =((K74*$AB$15)+K74)/$AB$17 -> 17701.733 | S74: =((L74*$AB$15)+L74)/$AB$17 -> 23696.461 | T74: =MEDIAN(O74:S74) -> 16622.325 | U74: Min. | V74: =((O74*$AB$16)+O74) -> 14335.349 | W74: =((P74*$AB$16)+P74) -> 16100.393 | X74: =((Q74*$AB$16)+Q74) -> 17313.814 | Y74: =((R74*$AB$16)+R74) -> 18438.125 | Z74: =((S74*$AB$16)+S74) -> 24682.234 | AA74: =MEDIAN(V74:Z74) -> 17313.814
E75: IT-07 | F75: Webmaster | G75: Máx. | H75: 563920 | I75: 633543 | J75: 703166 | K75: 730027 | L75: 756889 | M75: 674658 | N75: Máx. | O75: =((H75*$AB$15)+H75)/$AB$17 -> 22628.248 | P75: =((I75*$AB$15)+I75)/$AB$17 -> 25421.99 | Q75: =((J75*$AB$15)+J75)/$AB$17 -> 28215.731 | R75: =((K75*$AB$15)+K75)/$AB$17 -> 29293.574 | S75: =((L75*$AB$15)+L75)/$AB$17 -> 30371.458 | T75: =MEDIAN(O75:S75) -> 28215.731 | U75: Máx. | V75: =((O75*$AB$16)+O75) -> 23569.584 | W75: =((P75*$AB$16)+P75) -> 26479.544 | X75: =((Q75*$AB$16)+Q75) -> 29389.505 | Y75: =((R75*$AB$16)+R75) -> 30512.187 | Z75: =((S75*$AB$16)+S75) -> 31634.91 | AA75: =MEDIAN(V75:Z75) -> 29389.505
G76: Med | H76: 469910 | I76: 514308 | J76: 558706 | K76: 584148 | L76: 609591 | M76: 546069 | N76: Med | O76: =((H76*$AB$15)+H76)/$AB$17 -> 18855.937 | P76: =((I76*$AB$15)+I76)/$AB$17 -> 20637.483 | Q76: =((J76*$AB$15)+J76)/$AB$17 -> 22419.028 | R76: =((K76*$AB$15)+K76)/$AB$17 -> 23439.931 | S76: =((L76*$AB$15)+L76)/$AB$17 -> 24460.875 | T76: =MEDIAN(O76:S76) -> 22419.028 | U76: Med | V76: =((O76*$AB$16)+O76) -> 19640.344 | W76: =((P76*$AB$16)+P76) -> 21496.002 | X76: =((Q76*$AB$16)+Q76) -> 23351.659 | Y76: =((R76*$AB$16)+R76) -> 24415.032 | Z76: =((S76*$AB$16)+S76) -> 25478.447 | AA76: =MEDIAN(V76:Z76) -> 23351.659
G77: Min. | H77: 375900 | I77: 395073 | J77: 414246 | K77: 438269 | L77: 462293 | M77: 417479 | N77: Min. | O77: =((H77*$AB$15)+H77)/$AB$17 -> 15083.626 | P77: =((I77*$AB$15)+I77)/$AB$17 -> 15852.976 | Q77: =((J77*$AB$15)+J77)/$AB$17 -> 16622.325 | R77: =((K77*$AB$15)+K77)/$AB$17 -> 17586.289 | S77: =((L77*$AB$15)+L77)/$AB$17 -> 18550.292 | T77: =MEDIAN(O77:S77) -> 16622.325 | U77: Min. | V77: =((O77*$AB$16)+O77) -> 15711.105 | W77: =((P77*$AB$16)+P77) -> 16512.459 | X77: =((Q77*$AB$16)+Q77) -> 17313.814 | Y77: =((R77*$AB$16)+R77) -> 18317.878 | Z77: =((S77*$AB$16)+S77) -> 19321.985 | AA77: =MEDIAN(V77:Z77) -> 17313.814
E78: LOG-07 | F78: Coordinador logístico | G78: Máx. | H78: 495998 | I78: 703166 | J78: 805170 | K78: 868000 | L78: 1101228 | M78: 794712 | N78: Máx. | O78: =((H78*$AB$15)+H78)/$AB$17 -> 19902.763 | P78: =((I78*$AB$15)+I78)/$AB$17 -> 28215.731 | Q78: =((J78*$AB$15)+J78)/$AB$17 -> 32308.815 | R78: =((K78*$AB$15)+K78)/$AB$17 -> 34829.975 | S78: =((L78*$AB$15)+L78)/$AB$17 -> 44188.645 | T78: =MEDIAN(O78:S78) -> 32308.815 | U78: Máx. | V78: =((O78*$AB$16)+O78) -> 20730.718 | W78: =((P78*$AB$16)+P78) -> 29389.505 | X78: =((Q78*$AB$16)+Q78) -> 33652.861 | Y78: =((R78*$AB$16)+R78) -> 36278.902 | Z78: =((S78*$AB$16)+S78) -> 46026.893 | AA78: =MEDIAN(V78:Z78) -> 33652.861
G79: Med | H79: 445612 | I79: 558706 | J79: 644000 | K79: 734154 | L79: 754189 | M79: 627332 | N79: Med | O79: =((H79*$AB$15)+H79)/$AB$17 -> 17880.939 | P79: =((I79*$AB$15)+I79)/$AB$17 -> 22419.028 | Q79: =((J79*$AB$15)+J79)/$AB$17 -> 25841.595 | R79: =((K79*$AB$15)+K79)/$AB$17 -> 29459.177 | S79: =((L79*$AB$15)+L79)/$AB$17 -> 30263.115 | T79: =MEDIAN(O79:S79) -> 25841.595 | U79: Med | V79: =((O79*$AB$16)+O79) -> 18624.786 | W79: =((P79*$AB$16)+P79) -> 23351.659 | X79: =((Q79*$AB$16)+Q79) -> 26916.605 | Y79: =((R79*$AB$16)+R79) -> 30684.679 | Z79: =((S79*$AB$16)+S79) -> 31522.061 | AA79: =MEDIAN(V79:Z79) -> 26916.605
G80: Min. | H80: 367080 | I80: 395226 | J80: 414246 | K80: 420000 | L80: 703208 | M80: 459952 | N80: Min. | O80: =((H80*$AB$15)+H80)/$AB$17 -> 14729.709 | P80: =((I80*$AB$15)+I80)/$AB$17 -> 15859.115 | Q80: =((J80*$AB$15)+J80)/$AB$17 -> 16622.325 | R80: =((K80*$AB$15)+K80)/$AB$17 -> 16853.214 | S80: =((L80*$AB$15)+L80)/$AB$17 -> 28217.416 | T80: =MEDIAN(O80:S80) -> 16622.325 | U80: Min. | V80: =((O80*$AB$16)+O80) -> 15342.465 | W80: =((P80*$AB$16)+P80) -> 16518.854 | X80: =((Q80*$AB$16)+Q80) -> 17313.814 | Y80: =((R80*$AB$16)+R80) -> 17554.308 | Z80: =((S80*$AB$16)+S80) -> 29391.261 | AA80: =MEDIAN(V80:Z80) -> 17313.814
A81: BG-6 | B81: Ensure Process Integrity | D81: BG-6 Coordinator/Jr Specialist | E81: BG-6 Coordinator/Jr Specialist | G81: Máx. | H81: 356742 | I81: 455830 | J81: 530833 | K81: 634244 | L81: 974813 | M81: 566658 | N81: Máx. | O81: =+(1281000*$AB$15)+H81 -> 406444.8 | P81: =+(1281000*$AB$15)+I81 -> 505532.8 | Q81: =+(1281000*$AB$15)+J81 -> 580535.8 | R81: =+(1281000*$AB$15)+K81 -> 683946.8 | S81: =+(1281000*$AB$15)+L81 -> 1024515.8 | T81: =MEDIAN(O81:S81) -> 580535.8 | U81: Máx. | V81: =+(1281000*$AB$16)+O81 -> 459734.4 | W81: =+(1281000*$AB$16)+P81 -> 558822.4 | X81: =+(1281000*$AB$16)+Q81 -> 633825.4 | Y81: =+(1281000*$AB$16)+R81 -> 737236.4 | Z81: =+(1281000*$AB$16)+S81 -> 1077805.4 | AA81: =MEDIAN(V81:Z81) -> 633825.4
G82: Med | H82: 310927 | I82: 391510 | J82: 431479 | K82: 529777 | L82: 771883 | M82: 458949 | N82: Med | O82: =+(1281000*$AB$15)+H82 -> 360629.8 | P82: =+(1281000*$AB$15)+I82 -> 441212.8 | Q82: =+(1281000*$AB$15)+J82 -> 481181.8 | R82: =+(1281000*$AB$15)+K82 -> 579479.8 | S82: =+(1281000*$AB$15)+L82 -> 821585.8 | T82: =MEDIAN(O82:S82) -> 481181.8 | U82: Med | V82: =+(1281000*$AB$16)+O82 -> 413919.4 | W82: =+(1281000*$AB$16)+P82 -> 494502.4 | X82: =+(1281000*$AB$16)+Q82 -> 534471.4 | Y82: =+(1281000*$AB$16)+R82 -> 632769.4 | Z82: =+(1281000*$AB$16)+S82 -> 874875.4 | AA82: =MEDIAN(V82:Z82) -> 534471.4
G83: Min. | H83: 223167 | I83: 289003 | J83: 326650 | K83: 363620 | L83: 603766 | M83: 351239 | N83: Min. | O83: =+(1281000*$AB$15)+H83 -> 272869.8 | P83: =+(1281000*$AB$15)+I83 -> 338705.8 | Q83: =+(1281000*$AB$15)+J83 -> 376352.8 | R83: =+(1281000*$AB$15)+K83 -> 413322.8 | S83: =+(1281000*$AB$15)+L83 -> 653468.8 | T83: =MEDIAN(O83:S83) -> 376352.8 | U83: Min. | V83: =+(1281000*$AB$16)+O83 -> 326159.4 | W83: =+(1281000*$AB$16)+P83 -> 391995.4 | X83: =+(1281000*$AB$16)+Q83 -> 429642.4 | Y83: =+(1281000*$AB$16)+R83 -> 466612.4 | Z83: =+(1281000*$AB$16)+S83 -> 706758.4 | AA83: =MEDIAN(V83:Z83) -> 429642.4
A84: BG-5 | B84: Execute Intricate Transactions | C84: Poa-B | E84: BG-5 Sr. Officer/Sr. Technical | G84: Máx. | H84: 198638 | I84: 372268 | J84: 424667 | K84: 560000 | L84: 863081 | M84: 474314 | N84: Máx. | O84: =+(1281000*$AB$15)+H84 -> 248340.8 | P84: =+(1281000*$AB$15)+I84 -> 421970.8 | Q84: =+(1281000*$AB$15)+J84 -> 474369.8 | R84: =+(1281000*$AB$15)+K84 -> 609702.8 | S84: =+(1281000*$AB$15)+L84 -> 912783.8 | T84: =MEDIAN(O84:S84) -> 474369.8 | U84: Máx. | V84: =+(1281000*$AB$16)+O84 -> 301630.4 | W84: =+(1281000*$AB$16)+P84 -> 475260.4 | X84: =+(1281000*$AB$16)+Q84 -> 527659.4 | Y84: =+(1281000*$AB$16)+R84 -> 662992.4 | Z84: =+(1281000*$AB$16)+S84 -> 966073.4 | AA84: =MEDIAN(V84:Z84) -> 527659.4
G85: Med | H85: 194037 | I85: 307348 | J85: 347067 | K85: 441000 | L85: 719590 | M85: 393121 | N85: Med | O85: =+(1281000*$AB$15)+H85 -> 243739.8 | P85: =+(1281000*$AB$15)+I85 -> 357050.8 | Q85: =+(1281000*$AB$15)+J85 -> 396769.8 | R85: =+(1281000*$AB$15)+K85 -> 490702.8 | S85: =+(1281000*$AB$15)+L85 -> 769292.8 | T85: =MEDIAN(O85:S85) -> 396769.8 | U85: Med | V85: =+(1281000*$AB$16)+O85 -> 297029.4 | W85: =+(1281000*$AB$16)+P85 -> 410340.4 | X85: =+(1281000*$AB$16)+Q85 -> 450059.4 | Y85: =+(1281000*$AB$16)+R85 -> 543992.4 | Z85: =+(1281000*$AB$16)+S85 -> 822582.4 | AA85: =MEDIAN(V85:Z85) -> 450059.4
G86: Min. | H86: 189437 | I86: 237102 | J86: 265216 | K86: 383313 | L86: 634480 | M86: 311927 | N86: Min. | O86: =+(1281000*$AB$15)+H86 -> 239139.8 | P86: =+(1281000*$AB$15)+I86 -> 286804.8 | Q86: =+(1281000*$AB$15)+J86 -> 314918.8 | R86: =+(1281000*$AB$15)+K86 -> 433015.8 | S86: =+(1281000*$AB$15)+L86 -> 684182.8 | T86: =MEDIAN(O86:S86) -> 314918.8 | U86: Min. | V86: =+(1281000*$AB$16)+O86 -> 292429.4 | W86: =+(1281000*$AB$16)+P86 -> 340094.4 | X86: =+(1281000*$AB$16)+Q86 -> 368208.4 | Y86: =+(1281000*$AB$16)+R86 -> 486305.4 | Z86: =+(1281000*$AB$16)+S86 -> 737472.4 | AA86: =MEDIAN(V86:Z86) -> 368208.4
A87: BG-4 | B87: Process Basic Transactions | E87: BG-4 Officer/Technical | G87: Máx. | H87: 240912 | I87: 308723 | J87: 347251 | K87: 421939 | L87: 1464372 | M87: 387778 | N87: Máx. | O87: =+(1281000*$AB$15)+H87 -> 290614.8 | P87: =+(1281000*$AB$15)+I87 -> 358425.8 | Q87: =+(1281000*$AB$15)+J87 -> 396953.8 | R87: =+(1281000*$AB$15)+K87 -> 471641.8 | S87: =+(1281000*$AB$15)+L87 -> 1514074.8 | T87: =MEDIAN(O87:S87) -> 396953.8 | U87: Máx. | V87: =+(1281000*$AB$16)+O87 -> 343904.4 | W87: =+(1281000*$AB$16)+P87 -> 411715.4 | X87: =+(1281000*$AB$16)+Q87 -> 450243.4 | Y87: =+(1281000*$AB$16)+R87 -> 524931.4 | Z87: =+(1281000*$AB$16)+S87 -> 1567364.4 | AA87: =MEDIAN(V87:Z87) -> 450243.4
G88: Med | H88: 225049 | I88: 255799 | J88: 292276 | K88: 374500 | L88: 872186 | M88: 317190 | N88: Med | O88: =+(1281000*$AB$15)+H88 -> 274751.8 | P88: =+(1281000*$AB$15)+I88 -> 305501.8 | Q88: =+(1281000*$AB$15)+J88 -> 341978.8 | R88: =+(1281000*$AB$15)+K88 -> 424202.8 | S88: =+(1281000*$AB$15)+L88 -> 921888.8 | T88: =MEDIAN(O88:S88) -> 341978.8 | U88: Med | V88: =+(1281000*$AB$16)+O88 -> 328041.4 | W88: =+(1281000*$AB$16)+P88 -> 358791.4 | X88: =+(1281000*$AB$16)+Q88 -> 395268.4 | Y88: =+(1281000*$AB$16)+R88 -> 477492.4 | Z88: =+(1281000*$AB$16)+S88 -> 975178.4 | AA88: =MEDIAN(V88:Z88) -> 395268.4
G89: Min. | H89: 171226 | I89: 199970 | J89: 239817 | K89: 278313 | L89: 422561 | M89: 246601 | N89: Min. | O89: =+(1281000*$AB$15)+H89 -> 220928.8 | P89: =+(1281000*$AB$15)+I89 -> 249672.8 | Q89: =+(1281000*$AB$15)+J89 -> 289519.8 | R89: =+(1281000*$AB$15)+K89 -> 328015.8 | S89: =+(1281000*$AB$15)+L89 -> 472263.8 | T89: =MEDIAN(O89:S89) -> 289519.8 | U89: Min. | V89: =+(1281000*$AB$16)+O89 -> 274218.4 | W89: =+(1281000*$AB$16)+P89 -> 302962.4 | X89: =+(1281000*$AB$16)+Q89 -> 342809.4 | Y89: =+(1281000*$AB$16)+R89 -> 381305.4 | Z89: =+(1281000*$AB$16)+S89 -> 525553.4 | AA89: =MEDIAN(V89:Z89) -> 342809.4
A90: BG-3 | B90: Provide General Support | C90: Poa-A | E90: BG-3 Assistant | G90: Máx. | H90: 226380 | I90: 277573 | J90: 315816 | K90: 336152 | L90: 434735 | M90: 311689 | N90: Máx. | O90: =+(1281000*$AB$15)+H90 -> 276082.8 | P90: =+(1281000*$AB$15)+I90 -> 327275.8 | Q90: =+(1281000*$AB$15)+J90 -> 365518.8 | R90: =+(1281000*$AB$15)+K90 -> 385854.8 | S90: =+(1281000*$AB$15)+L90 -> 484437.8 | T90: =MEDIAN(O90:S90) -> 365518.8 | U90: Máx. | V90: =+(1281000*$AB$16)+O90 -> 329372.4 | W90: =+(1281000*$AB$16)+P90 -> 380565.4 | X90: =+(1281000*$AB$16)+Q90 -> 418808.4 | Y90: =+(1281000*$AB$16)+R90 -> 439144.4 | Z90: =+(1281000*$AB$16)+S90 -> 537727.4 | AA90: =MEDIAN(V90:Z90) -> 418808.4
G91: Med | H91: 188650 | I91: 233163 | J91: 252000 | K91: 269046 | L91: 292276 | M91: 249516 | N91: Med | O91: =+(1281000*$AB$15)+H91 -> 238352.8 | P91: =+(1281000*$AB$15)+I91 -> 282865.8 | Q91: =+(1281000*$AB$15)+J91 -> 301702.8 | R91: =+(1281000*$AB$15)+K91 -> 318748.8 | S91: =+(1281000*$AB$15)+L91 -> 341978.8 | T91: =MEDIAN(O91:S91) -> 301702.8 | U91: Med | V91: =+(1281000*$AB$16)+O91 -> 291642.4 | W91: =+(1281000*$AB$16)+P91 -> 336155.4 | X91: =+(1281000*$AB$16)+Q91 -> 354992.4 | Y91: =+(1281000*$AB$16)+R91 -> 372038.4 | Z91: =+(1281000*$AB$16)+S91 -> 395268.4 | AA91: =MEDIAN(V91:Z91) -> 354992.4
G92: Min. | H92: 144912 | I92: 164853 | J92: 179972 | K92: 196287 | L92: 252000 | M92: 187343 | N92: Min. | O92: =+(1281000*$AB$15)+H92 -> 194614.8 | P92: =+(1281000*$AB$15)+I92 -> 214555.8 | Q92: =+(1281000*$AB$15)+J92 -> 229674.8 | R92: =+(1281000*$AB$15)+K92 -> 245989.8 | S92: =+(1281000*$AB$15)+L92 -> 301702.8 | T92: =MEDIAN(O92:S92) -> 229674.8 | U92: Min. | V92: =+(1281000*$AB$16)+O92 -> 247904.4 | W92: =+(1281000*$AB$16)+P92 -> 267845.4 | X92: =+(1281000*$AB$16)+Q92 -> 282964.4 | Y92: =+(1281000*$AB$16)+R92 -> 299279.4 | Z92: =+(1281000*$AB$16)+S92 -> 354992.4 | AA92: =MEDIAN(V92:Z92) -> 282964.4
A93: BG-2 | B93: Provide Mechanical Support | E93: BG-2 Driver | G93: Máx. | H93: 175545 | I93: 221689 | J93: 261611 | K93: 297573 | L93: 395220 | M93: 270752 | N93: Máx. | O93: =+(1281000*$AB$15)+H93 -> 225247.8 | P93: =+(1281000*$AB$15)+I93 -> 271391.8 | Q93: =+(1281000*$AB$15)+J93 -> 311313.8 | R93: =+(1281000*$AB$15)+K93 -> 347275.8 | S93: =+(1281000*$AB$15)+L93 -> 444922.8 | T93: =MEDIAN(O93:S93) -> 311313.8 | U93: Máx. | V93: =+(1281000*$AB$16)+O93 -> 278537.4 | W93: =+(1281000*$AB$16)+P93 -> 324681.4 | X93: =+(1281000*$AB$16)+Q93 -> 364603.4 | Y93: =+(1281000*$AB$16)+R93 -> 400565.4 | Z93: =+(1281000*$AB$16)+S93 -> 498212.4 | AA93: =MEDIAN(V93:Z93) -> 364603.4
G94: Med | H94: 173475 | I94: 189000 | J94: 220575 | K94: 263480 | L94: 317039 | M94: 229338 | N94: Med | O94: =+(1281000*$AB$15)+H94 -> 223177.8 | P94: =+(1281000*$AB$15)+I94 -> 238702.8 | Q94: =+(1281000*$AB$15)+J94 -> 270277.8 | R94: =+(1281000*$AB$15)+K94 -> 313182.8 | S94: =+(1281000*$AB$15)+L94 -> 366741.8 | T94: =MEDIAN(O94:S94) -> 270277.8 | U94: Med | V94: =+(1281000*$AB$16)+O94 -> 276467.4 | W94: =+(1281000*$AB$16)+P94 -> 291992.4 | X94: =+(1281000*$AB$16)+Q94 -> 323567.4 | Y94: =+(1281000*$AB$16)+R94 -> 366472.4 | Z94: =+(1281000*$AB$16)+S94 -> 420031.4 | AA94: =MEDIAN(V94:Z94) -> 323567.4
G95: Min. | H95: 131740 | I95: 168473 | J95: 171405 | K95: 189000 | L95: 276180 | M95: 187923 | N95: Min. | O95: =+(1281000*$AB$15)+H95 -> 181442.8 | P95: =+(1281000*$AB$15)+I95 -> 218175.8 | Q95: =+(1281000*$AB$15)+J95 -> 221107.8 | R95: =+(1281000*$AB$15)+K95 -> 238702.8 | S95: =+(1281000*$AB$15)+L95 -> 325882.8 | T95: =MEDIAN(O95:S95) -> 221107.8 | U95: Min. | V95: =+(1281000*$AB$16)+O95 -> 234732.4 | W95: =+(1281000*$AB$16)+P95 -> 271465.4 | X95: =+(1281000*$AB$16)+Q95 -> 274397.4 | Y95: =+(1281000*$AB$16)+R95 -> 291992.4 | Z95: =+(1281000*$AB$16)+S95 -> 379172.4 | AA95: =MEDIAN(V95:Z95) -> 274397.4
A96: BG-1 | B96: Provide Physical Support | E96: BG-1 Maintenance | G96: Máx. | H96: 173575 | I96: 206825 | J96: 217605 | K96: 254296 | L96: 315816 | M96: 225493 | N96: Máx. | O96: =+(1281000*$AB$15)+H96 -> 223277.8 | P96: =+(1281000*$AB$15)+I96 -> 256527.8 | Q96: =+(1281000*$AB$15)+J96 -> 267307.8 | R96: =+(1281000*$AB$15)+K96 -> 303998.8 | S96: =+(1281000*$AB$15)+L96 -> 365518.8 | T96: =MEDIAN(O96:S96) -> 267307.8 | U96: Máx. | V96: =+(1281000*$AB$16)+O96 -> 276567.4 | W96: =+(1281000*$AB$16)+P96 -> 309817.4 | X96: =+(1281000*$AB$16)+Q96 -> 320597.4 | Y96: =+(1281000*$AB$16)+R96 -> 357288.4 | Z96: =+(1281000*$AB$16)+S96 -> 418808.4 | AA96: =MEDIAN(V96:Z96) -> 320597.4
G97: Med | H97: 161627 | I97: 179964 | J97: 188417 | K97: 213568 | L97: 255421 | M97: 198189 | N97: Med | O97: =+(1281000*$AB$15)+H97 -> 211329.8 | P97: =+(1281000*$AB$15)+I97 -> 229666.8 | Q97: =+(1281000*$AB$15)+J97 -> 238119.8 | R97: =+(1281000*$AB$15)+K97 -> 263270.8 | S97: =+(1281000*$AB$15)+L97 -> 305123.8 | T97: =MEDIAN(O97:S97) -> 238119.8 | U97: Med | V97: =+(1281000*$AB$16)+O97 -> 264619.4 | W97: =+(1281000*$AB$16)+P97 -> 282956.4 | X97: =+(1281000*$AB$16)+Q97 -> 291409.4 | Y97: =+(1281000*$AB$16)+R97 -> 316560.4 | Z97: =+(1281000*$AB$16)+S97 -> 358413.4 | AA97: =MEDIAN(V97:Z97) -> 291409.4
G98: Min. | H98: 129756 | I98: 146194 | J98: 163714 | K98: 186021 | L98: 249240 | M98: 170886 | N98: Min. | O98: =+(1281000*$AB$15)+H98 -> 179458.8 | P98: =+(1281000*$AB$15)+I98 -> 195896.8 | Q98: =+(1281000*$AB$15)+J98 -> 213416.8 | R98: =+(1281000*$AB$15)+K98 -> 235723.8 | S98: =+(1281000*$AB$15)+L98 -> 298942.8 | T98: =MEDIAN(O98:S98) -> 213416.8 | U98: Min. | V98: =+(1281000*$AB$16)+O98 -> 232748.4 | W98: =+(1281000*$AB$16)+P98 -> 249186.4 | X98: =+(1281000*$AB$16)+Q98 -> 266706.4 | Y98: =+(1281000*$AB$16)+R98 -> 289013.4 | Z98: =+(1281000*$AB$16)+S98 -> 352232.4 | AA98: =MEDIAN(V98:Z98) -> 266706.4
V99: =+V98/25.888 -> 8990.5902
A100: remuneración total (salario base + bonificaciones y asignaciones fijas en efectivo + pagos variables/basados en el rendimiento + prestaciones en

Sheet Grade A
A1: Maintenance (Nivel I) | F1: Driver (Nivel II) | K1: Assistant (Nivel III)
B2: Minimum | C2: Median | D2: Maximum | G2: Minimum | H2: Median | I2: Maximum | L2: Minimum | M2: Median | N2: Maximum
A3: Birtches | B3: 6755.3573 | C3: 7875.0713 | D3: 10675.569 | F3: Birtches | G3: 7250.556 | H3: 9219.1462 | I3: 13250.953 | K3: Birtches | L3: 7884.8098 | M3: 10532.585 | N3: 12215.959
A4: PayLab | B4: 6060 | C4: 10542 | D4: 15024 | F4: PayLab | G4: 6825 | H4: 11161 | I4: 15498 | K4: PayLab | L4: 7604 | M4: 11348 | N4: 15092
A5: ONG Local | B5: 5048 | C5: 6821 | D5: 8593 | F5: ONG Local | G5: 6060 | H5: 8183 | I5: 10308 | K5: ONG Local | L5: 7268 | M5: 9821 | N5: 12374
A6: World Salaries | B6: 1778.0439 | C6: 3893.3096 | D6: 6161.1557 | F6: =+A6 -> World Salaries | G6: 2051.9159 | H6: 4001.0816 | I6: 6327.2559 | K6: =+A6 -> World Salaries | L6: 3247.2574 | M6: 6964.6168 | N6: 11037.933
A7: Media | B7: =MEDIAN(B3:B6) -> 5554 | C7: =MEDIAN(C3:C6) -> 7348.0357 | D7: =MEDIAN(D3:D6) -> 9634.2843 | F7: Media | G7: =MEDIAN(G3:G6) -> 6442.5 | H7: =MEDIAN(H3:H6) -> 8701.0731 | I7: =MEDIAN(I3:I6) -> 11779.476 | K7: Media | L7: =MEDIAN(L3:L6) -> 7436 | M7: =MEDIAN(M3:M6) -> 10176.792 | N7: =MEDIAN(N3:N6) -> 12294.98
A8: Promedio | B8: =AVERAGE(B3:B5) -> 5954.4524 | C8: =AVERAGE(C3:C6) -> 7282.8452 | D8: =AVERAGE(D3:D6) -> 10113.431 | F8: Promedio | G8: =AVERAGE(G3:G5) -> 6711.852 | H8: =AVERAGE(H3:H6) -> 8141.0569 | I8: =AVERAGE(I3:I6) -> 11346.052 | K8: Promedio | L8: =AVERAGE(L3:L5) -> 7585.6033 | M8: =AVERAGE(M3:M6) -> 9666.5503 | N8: =AVERAGE(N3:N6) -> 12679.973
A10: HNL Anual | B10: =+B7*TRM!$I$9 -> 143781.95 | C10: =+C7*TRM!$I$9 -> 190225.95 | D10: =+D7*TRM!$I$9 -> 249412.35 | F10: HNL Anual | G10: =+G7*TRM!$I$9 -> 166783.44 | H10: =+H7*TRM!$I$9 -> 225253.38 | I10: =+I7*TRM!$I$9 -> 304947.08 | K10: HNL Anual | L10: =+L7*TRM!$I$9 -> 192503.17 | M10: =+M7*TRM!$I$9 -> 263456.8 | N10: =+N7*TRM!$I$9 -> 318292.43
A11: HNL Mensual | B11: =+B10/12 -> 11981.829 | C11: =+C10/12 -> 15852.162 | D11: =+D10/12 -> 20784.363 | F11: HNL Mensual | G11: =+G10/12 -> 13898.62 | H11: =+H10/12 -> 18771.115 | I11: =+I10/12 -> 25412.257 | K11: HNL Mensual | L11: =+L10/12 -> 16041.931 | M11: =+M10/12 -> 21954.733 | N11: =+N10/12 -> 26524.369
A12: SMLMV / Mes | B12: =+B11/'Birches Report Level'!$AG$13 -> 0.85625045 | C12: =+C11/'Birches Report Level'!$AG$13 -> 1.1328338 | D12: =+D11/'Birches Report Level'!$AG$13 -> 1.4853007 | F12: SMLMV / Mes | G12: =+G11/'Birches Report Level'!$AG$13 -> 0.99322894 | H12: =+H11/'Birches Report Level'!$AG$13 -> 1.3414292 | I12: =+I11/'Birches Report Level'!$AG$13 -> 1.8160212 | K12: SMLMV / Mes | L12: =+L11/'Birches Report Level'!$AG$13 -> 1.1463951 | M12: =+M11/'Birches Report Level'!$AG$13 -> 1.5689382 | N12: =+N11/'Birches Report Level'!$AG$13 -> 1.8954954

Sheet Grade B
A1: Program Officer (Nivel I) | F1: Senior Program Officer (Nivel II)
B2: Minimum | C2: Median | D2: Maximum | G2: Minimum | H2: Median | I2: Maximum
A3: Birtches | B3: 9406.1413 | C3: 12215.959 | D3: 36453.86 | F3: Birtches | G3: 8109.9647 | H3: 14506.002 | I3: 30075.962
A4: PayLab | B4: 6385 | C4: 12187 | D4: 17989 | E4: Admin officer | F4: PayLab | G4: 9216 | H4: 16974 | I4: 24732 | J4: (sales officer)
A5: ONG local | B5: 8721 | C5: 11790 | D5: 14858 | F5: ONG local | G5: 10468 | H5: 14145 | I5: 17822
A6: =+'Grade A'!A6 -> World Salaries | B6: 3530.9796 | C6: 7455.1916 | D6: 11684.951 | F6: =+A6 -> World Salaries | G6: 4113.1026 | H6: 8141.4813 | I6: 12533.478
A7: Media | B7: =MEDIAN(B3:B6) -> 7553 | C7: =MEDIAN(C3:C6) -> 11988.5 | D7: =MEDIAN(D3:D6) -> 16423.5 | F7: Media | G7: =MEDIAN(G3:G6) -> 8662.9823 | H7: =MEDIAN(H3:H6) -> 14325.501 | I7: =MEDIAN(I3:I6) -> 21277
A8: Promedio | B8: =AVERAGE(B3:B6) -> 7010.7802 | C8: =AVERAGE(C3:C6) -> 10912.038 | D8: =AVERAGE(D3:D6) -> 20246.453 | F8: Promedio | G8: =AVERAGE(G3:G6) -> 7976.7668 | H8: =AVERAGE(H3:H6) -> 13441.621 | I8: =AVERAGE(I3:I6) -> 21290.86
A10: HNL Anual | B10: =+B7*TRM!$I$9 -> 195532.06 | C10: =+C7*TRM!$I$9 -> 310358.29 | D10: =+D7*TRM!$I$9 -> 425171.57 | F10: HNL Anual | G10: =+G7*TRM!$I$9 -> 224267.29 | H10: =+H7*TRM!$I$9 -> 370858.57 | I10: =+I7*TRM!$I$9 -> 550818.98
A11: HNL Mensual | B11: =+B10/12 -> 16294.339 | C11: =+C10/12 -> 25863.191 | D11: =+D10/12 -> 35430.964 | F11: HNL Mensual | G11: =+G10/12 -> 18688.941 | H11: =+H10/12 -> 30904.881 | I11: =+I10/12 -> 45901.581
A12: SMLMV / Mes | B12: =+B11/'Birches Report Level'!$AG$13 -> 1.1644328 | C12: =+C11/'Birches Report Level'!$AG$13 -> 1.848246 | D12: =+D11/'Birches Report Level'!$AG$13 -> 2.5319822 | F12: SMLMV / Mes | G12: =+G11/'Birches Report Level'!$AG$13 -> 1.3355568 | H12: =+H11/'Birches Report Level'!$AG$13 -> 2.2085374 | I12: =+I11/'Birches Report Level'!$AG$13 -> 3.2802378

Sheet Gade C
A1: Program Coordinator (Nivel I) | F1: Technical Specialist (Nivel II) | K1: Senior Specialist (Nivel III)
B2: Minimum | C2: Median | D2: Maximum | G2: Minimum | H2: Median | I2: Maximum | L2: Minimum | M2: Median | N2: Maximum
A3: Birtches | B3: 12995.496 | C3: 18034.083 | D3: 32261.599 | F3: Birtches | G3: 14910.378 | H3: 22186.68 | I3: 40743.255 | K3: Birtches | L3: 15099.756 | M3: 23698.315 | N3: 51229.321
A4: PayLab | B4: 8880 | C4: 17400 | D4: 25920 | F4: PayLab | G4: 9158 | H4: 18382 | I4: 27606 | K4: PayLab | L4: 11000 | M4: 23000 | N4: 35000 | O4: Project Manager
A5: ONG local | B5: 12560 | C5: 16973 | D5: 21385 | F5: ONG Local | G5: 15697 | H5: 21231 | I5: 26765 | L5: 19627 | M5: 26518 | N5: 33409
A6: =+'Grade B'!A6 -> World Salaries | B6: 4113.1026 | C6: 8141.4813 | D6: 16897.79 | F6: =+A6 -> World Salaries | G6: 5836.6811 | H6: 11399.104 | I6: 17510.043 | K6: =+F6 -> World Salaries | L6: 8208.4363 | M6: 17938.813 | N6: 28399.258
A7: Media | B7: =MEDIAN(B3:B6) -> 10720 | C7: =MEDIAN(C3:C6) -> 17186.5 | D7: =MEDIAN(D3:D6) -> 23652.5 | F7: Media | G7: =MEDIAN(G3:G6) -> 12034.189 | H7: =MEDIAN(H3:H6) -> 19806.5 | I7: =MEDIAN(I3:I6) -> 27185.5 | K7: Media | L7: =MEDIAN(L3:L6) -> 13049.878 | M7: =MEDIAN(M3:M6) -> 23349.158 | N7: =MEDIAN(N3:N6) -> 34204.5
A8: Promedio | B8: =AVERAGE(B3:B6) -> 9637.1496 | C8: =AVERAGE(C3:C6) -> 15137.141 | D8: =AVERAGE(D3:D6) -> 24116.097 | F8: Promedio | G8: =AVERAGE(G3:G6) -> 11400.515 | H8: =AVERAGE(H3:H6) -> 18299.696 | I8: =AVERAGE(I3:I6) -> 28156.075 | K8: Promedio | L8: =AVERAGE(L3:L6) -> 13483.798 | M8: =AVERAGE(M3:M6) -> 22788.782 | N8: =AVERAGE(N3:N6) -> 37009.395
A10: HNL Anual | B10: =+B7*TRM!$I$9 -> 277519.36 | C10: =+C7*TRM!$I$9 -> 444924.11 | D10: =+D7*TRM!$I$9 -> 612315.92 | F10: HNL Anual | G10: =+G7*TRM!$I$9 -> 311541.09 | H10: =+H7*TRM!$I$9 -> 512750.67 | I10: =+I7*TRM!$I$9 -> 703778.22 | K10: HNL Anual | L10: =+L7*TRM!$I$9 -> 337835.24 | M10: =+M7*TRM!$I$9 -> 604462.99 | N10: =+N7*TRM!$I$9 -> 885486.1
A11: HNL Mensual | B11: =+B10/12 -> 23126.613 | C11: =+C10/12 -> 37077.009 | D11: =+D10/12 -> 51026.327 | F11: HNL Mensual | G11: =+G10/12 -> 25961.757 | H11: =+H10/12 -> 42729.223 | I11: =+I10/12 -> 58648.185 | K11: HNL Mensual | L11: =+L10/12 -> 28152.936 | M11: =+M10/12 -> 50371.916 | N11: =+N10/12 -> 73790.508
A12: SMLMV / Mes | B12: =+B11/'Birches Report Level'!$AG$13 -> 1.6526836 | C12: =+C11/'Birches Report Level'!$AG$13 -> 2.6496126 | D12: =+D11/'Birches Report Level'!$AG$13 -> 3.6464645 | F12: SMLMV / Mes | G12: =+G11/'Birches Report Level'!$AG$13 -> 1.8552898 | H12: =+H11/'Birches Report Level'!$AG$13 -> 3.0535334 | I12: =+I11/'Birches Report Level'!$AG$13 -> 4.1911409 | K12: SMLMV / Mes | L12: =+L11/'Birches Report Level'!$AG$13 -> 2.0118768 | M12: =+M11/'Birches Report Level'!$AG$13 -> 3.5996987 | N12: =+N11/'Birches Report Level'!$AG$13 -> 5.2732478

Sheet Grade D
A1: Project Manager (Nivel I) | F1: Director (Nivel II) | K1: Senior Director (Nivel III)
B2: Minimum | C2: Median | D2: Maximum | G2: Minimum | H2: Median | I2: Maximum | L2: Minimum | M2: Median | N2: Maximum
A3: Birtches | B3: 17335.589 | C3: 31273.835 | D3: 67796.7 | F3: Birtches | G3: 19121.573 | H3: 35108.615 | I3: 51983.32 | K3: Birtches | L3: 27533.597 | M3: 44546.647 | N3: 61822.593
A4: PayLab | B4: 11000 | C4: =(B4+D4)/2 -> 28000 | D4: 45000 | E4: Senior project Manager | F4: PayLab | G4: 13000 | H4: 34000 | I4: 55000 | J4: Technical Director | K4: PayLab | L4: 14000 | M4: 39500 | N4: 65000 | O4: Managing Director
A5: ONG Local | F5: ONG Local | G5: 24541 | H5: 33159 | I5: 41778 | K5: ONG Local | L5: 30671.199 | M5: 41447.93 | N5: 52224.197
A6: =+'Gade C'!A6 -> World Salaries | B6: 10960.677 | C6: 23825.711 | D6: 37870.828 | F6: =+A6 -> World Salaries | G6: 13967.862 | H6: 26773.022 | I6: 40856.768 | K6: =+F6 -> World Salaries
A7: Media | B7: =MEDIAN(+B3,B4,B6) -> 11000 | C7: =MEDIAN(+C3,C4,C6) -> 28000 | D7: =MEDIAN(+D3,D4,D6) -> 45000 | F7: Media | G7: =MEDIAN(G2:G6) -> 16544.717 | H7: =MEDIAN(H2:H6) -> 33579.5 | I7: =MEDIAN(I2:I6) -> 46880.66 | K7: Media | L7: =MEDIAN(L3:L5) -> 27533.597 | M7: =MEDIAN(M3:M5) -> 41447.93 | N7: =MEDIAN(N3:N5) -> 61822.593
A8: Promedio | B8: =AVERAGE(B3,B4,B6) -> 13098.755 | C8: =AVERAGE(C3,C4,C6) -> 27699.849 | D8: =AVERAGE(D3,D4,D6) -> 50222.509 | F8: Promedio | G8: =AVERAGE(G3:G6) -> 17657.609 | H8: =AVERAGE(H3:H6) -> 32260.159 | I8: =AVERAGE(I3:I6) -> 47404.522 | K8: Promedio | L8: =AVERAGE(L3:L5) -> 24068.265 | M8: =AVERAGE(M3:M5) -> 41831.525 | N8: =AVERAGE(N3:N5) -> 59682.263
A10: HNL Anual | B10: =+B7*TRM!$I$9 -> 284768 | C10: =+C7*TRM!$I$9 -> 724864 | D10: =+D7*TRM!$I$9 -> 1164960 | F10: HNL Anual | G10: =+G7*TRM!$I$9 -> 428309.64 | H10: =+H7*TRM!$I$9 -> 869306.1 | I10: =+I7*TRM!$I$9 -> 1213646.5 | K10: HNL Anual | L10: =+L7*TRM!$I$9 -> 712789.76 | M10: =+M7*TRM!$I$9 -> 1073004 | N10: =+N7*TRM!$I$9 -> 1600463.3
A11: HNL Mensual | B11: =+B10/12 -> 23730.667 | C11: =+C10/12 -> 60405.333 | D11: =+D10/12 -> 97080 | F11: HNL Mensual | G11: =+G10/12 -> 35692.47 | H11: =+H10/12 -> 72442.175 | I11: =+I10/12 -> 101137.21 | K11: HNL Mensual | L11: =+L10/12 -> 59399.147 | M11: =+M10/12 -> 89417 | N11: =+N10/12 -> 133371.94
A12: SMLMV / Mes | B12: =+B11/'Birches Report Level'!$AG$13 -> 1.6958507 | C12: =+C11/'Birches Report Level'!$AG$13 -> 4.3167109 | D12: =+D11/'Birches Report Level'!$AG$13 -> 6.9375711 | F12: SMLMV / Mes | G12: =+G11/'Birches Report Level'!$AG$13 -> 2.5506701 | H12: =+H11/'Birches Report Level'!$AG$13 -> 5.1768927 | I12: =+I11/'Birches Report Level'!$AG$13 -> 7.2275092 | K12: SMLMV / Mes | L12: =+L11/'Birches Report Level'!$AG$13 -> 4.2448064 | M12: =+M11/'Birches Report Level'!$AG$13 -> 6.3899547 | N12: =+N11/'Birches Report Level'!$AG$13 -> 9.5310809

Sheet Grade E
A1: (Nivel I) | F1: (Nivel II) | K1: (Nivel III)
B2: Minimum | C2: Median | D2: Maximum | G2: Minimum | H2: Median | I2: Maximum | L2: Minimum | M2: Median | N2: Maximum
A3: Birtches | B3: 65512.258 | C3: 73996.673 | D3: 90404.684 | F3: Birtches | G3: 72227.198 | H3: 80975.22 | I3: 97523.917 | K3: Birtches | L3: 73441.497 | M3: 90404.684 | N3: 117028.72
A4: PayLab | F4: PayLab | G4: 22000 | H4: 58000 | I4: 94000 | J4: chief executive officer | K4: PayLab
A5: ONG Local | B5: 39872.84 | C5: 53882.262 | D5: 67891.687 | F5: ONG Local | G5: 0 | H5: 0 | I5: 0 | L5: 51825 | M5: 70072 | N5: 88319
A6: Propuesta | D6: 78000 | K6: Presupuesto | N6: =+'Budget USDA Salary Categories'!D6 -> 114996
A7: Media | B7: =MEDIAN(B3:B6) -> 52692.549 | C7: =MEDIAN(C3:C6) -> 63939.467 | D7: =MEDIAN(D3:D6) -> 78000 | F7: Media | G7: =MEDIAN(G3:G5) -> 22000 | H7: =MEDIAN(H3:H5) -> 58000 | I7: =MEDIAN(I3:I5) -> 94000 | K7: Media | L7: =MEDIAN(L3:L5) -> 62633.248 | M7: =MEDIAN(M3:M5) -> 80238.342 | N7: =MEDIAN(N3:N6) -> 114996
A8: Promedio | B8: =AVERAGE(B3,B5) -> 52692.549 | C8: =AVERAGE(C3,C5) -> 63939.467 | D8: =AVERAGE(D3,D5,D6) -> 78765.457 | F8: Promedio | G8: =AVERAGE(G3,G4) -> 47113.599 | H8: =AVERAGE(H3,H4) -> 69487.61 | I8: =AVERAGE(I3,I4) -> 95761.958 | K8: Promedio | L8: =AVERAGE(L3) -> 73441.497 | M8: =AVERAGE(M3) -> 90404.684 | N8: =AVERAGE(N3,N5,N6) -> 106781.24
A10: HNL Anual | B10: =+B7*TRM!$I$9 -> 1364104.7 | C10: =+C7*TRM!$I$9 -> 1655264.9 | D10: =+D7*TRM!$I$9 -> 2019264 | F10: HNL Anual | G10: =+G7*TRM!$I$9 -> 569536 | H10: =+H7*TRM!$I$9 -> 1501504 | I10: =+I7*TRM!$I$9 -> 2433472 | K10: HNL Anual | L10: =+L7*TRM!$I$9 -> 1621449.5 | M10: =+M7*TRM!$I$9 -> 2077210.2 | N10: =+N7*TRM!$I$9 -> 2977016.4
A11: HNL Mensual | B11: =+B10/12 -> 113675.39 | C11: =+C10/12 -> 137938.74 | D11: =+D10/12 -> 168272 | F11: HNL Mensual | G11: =+G10/12 -> 47461.333 | H11: =+H10/12 -> 125125.33 | I11: =+I10/12 -> 202789.33 | K11: HNL Mensual | L11: =+L10/12 -> 135120.79 | M11: =+M10/12 -> 173100.85 | N11: =+N10/12 -> 248084.7
A12: SMLMV / Mes | B12: =+B11/'Birches Report Level'!$AG$13 -> 8.1235179 | C12: =+C11/'Birches Report Level'!$AG$13 -> 9.8574356 | D12: =+D11/'Birches Report Level'!$AG$13 -> 12.025123 | F12: SMLMV / Mes | G12: =+G11/'Birches Report Level'!$AG$13 -> 3.3917015 | H12: =+H11/'Birches Report Level'!$AG$13 -> 8.9417584 | I12: =+I11/'Birches Report Level'!$AG$13 -> 14.491815 | K12: SMLMV / Mes | L12: =+L11/'Birches Report Level'!$AG$13 -> 9.6560582 | M12: =+M11/'Birches Report Level'!$AG$13 -> 12.370205 | N12: =+N11/'Birches Report Level'!$AG$13 -> 17.728732

Sheet Budget USDA Salary Categories
C3: 12 | D3: TRM | E3: 25.9679
C4: 12 | D4: TRM | E4: 25.9679 | H4: For field offices
A5: CCN Honduran Field Staff (LOE) | B5: Salario mensaul UDS | C5: Salario mensual HNL | D5: Salario anual UDS | E5: Salario anual HNL | G5: Purpose | H5: Level | I5: Purpose | J5: Proposed Field Office Grade | K5: Purpose
A6: Key Personnel: Chief of Party | B6: 9583 | C6: =+B6*$E$3 -> 248850.39 | D6: =+B6*$C$3 -> 114996 | E6: =+D6*$E$3 -> 2986204.6 | F6: POA D | G6: BG-11 Country Directors | H6: BG-12 | I6: Integrate-Transform | J6: Poa-E | K6: BG-12 Executive
A7: Key Personnel: Deputy Chief of Party | B7: 6500 | C7: =+B7*$E$3 -> 168791.35 | D7: =+B7*$C$3 -> 78000 | E7: =+D7*$E$3 -> 2025496.2 | F7: POA D | G7: BG-9 DCOP/DPD/Director of Function XX | H7: BG-11 | I7: Innovate | K7: BG-11 Country Directors
A8: Policy & Sustainability Specialist | B8: 1500 | C8: =+B8*$E$3 -> 38951.85 | D8: =+B8*$C$3 -> 18000 | E8: =+D8*$E$3 -> 467422.2 | F8: POA C | G8: BG-7 Manager/Specialist | H8: BG-10 | I8: Adapt | J8: Poa-D | K8: BG-10 Project Director/COP
A9: Education Director | B9: 4583 | C9: =+B9*$E$3 -> 119010.89 | D9: =+B9*$C$3 -> 54996 | E9: =+D9*$E$3 -> 1428130.6 | F9: POA D | G9: BG-9 DCOP/DPD/Director of Function XX | H9: BG-9 | I9: Analyze | K9: BG-9 DCOP/DPD/Director of Function XX
A10: Education Specialist | B10: 2000 | C10: =+B10*$E$3 -> 51935.8 | D10: =+B10*$C$3 -> 24000 | E10: =+D10*$E$3 -> 623229.6 | F10: POA C | G10: BG-7 Manager/Specialist | H10: BG-8 | I10: Apply Basic Concepts | K10: BG-8 Transitional Managerial
A11: Education Officer | B11: 1000 | C11: =+B11*$E$3 -> 25967.9 | D11: =+B11*$C$3 -> 12000 | E11: =+D11*$E$3 -> 311614.8 | F11: POA B | G11: BG-4 Officer/Technical | H11: BG-7 | I11: Manage Integrated Processes | J11: Poa-C | K11: BG-7 Manager/Specialist
A12: Nutrition and Health Specialist | B12: 1500 | C12: =+B12*$E$3 -> 38951.85 | D12: =+B12*$C$3 -> 18000 | E12: =+D12*$E$3 -> 467422.2 | F12: POA C | G12: BG-7 Manager/Specialist | H12: BG-6 | I12: Ensure Process Integrity | K12: BG-6 Coordinator/Jr Specialist
A13: Nutrition Officer - (2 Individuals) | B13: 1000 | C13: =+B13*$E$3 -> 25967.9 | D13: =+B13*$C$3 -> 12000 | E13: =+D13*$E$3 -> 311614.8 | F13: POA B | G13: BG-4 Officer/Technical | H13: BG-5 | I13: Execute Intricate Transactions | J13: Poa-B | K13: BG-5 Sr. Officer/Sr. Technical
A14: School Feeding Specialist | B14: 1500 | C14: =+B14*$E$3 -> 38951.85 | D14: =+B14*$C$3 -> 18000 | E14: =+D14*$E$3 -> 467422.2 | F14: POA C | G14: BG-7 Manager/Specialist | H14: BG-4 | I14: Process Basic Transactions | K14: BG-4 Officer/Technical
A15: Food Aid Monitors - (2 Individuals) | B15: 1000 | C15: =+B15*$E$3 -> 25967.9 | D15: =+B15*$C$3 -> 12000 | E15: =+D15*$E$3 -> 311614.8 | F15: POA B | G15: BG-4 Officer/Technical | H15: BG-3 | I15: Provide General Support | J15: Poa-A | K15: BG-3 Assistant
A16: WASH Officer | B16: 1000 | C16: =+B16*$E$3 -> 25967.9 | D16: =+B16*$C$3 -> 12000 | E16: =+D16*$E$3 -> 311614.8 | F16: POA B | G16: BG-4 Officer/Technical | H16: BG-2 | I16: Provide Mechanical Support | K16: BG-2 Driver
A17: Communications Specialist | B17: 1500 | C17: =+B17*$E$3 -> 38951.85 | D17: =+B17*$C$3 -> 18000 | E17: =+D17*$E$3 -> 467422.2 | F17: POA C | G17: BG-7 Manager/Specialist | H17: BG-1 | I17: Provide Physical Support | K17: BG-1 Maintenance
A18: Communications Officer | B18: 1000 | C18: =+B18*$E$3 -> 25967.9 | D18: =+B18*$C$3 -> 12000 | E18: =+D18*$E$3 -> 311614.8 | F18: POA B | G18: BG-4 Officer/Technical
A19: Education & Community Engagement Specialist | B19: 1500 | C19: =+B19*$E$3 -> 38951.85 | D19: =+B19*$C$3 -> 18000 | E19: =+D19*$E$3 -> 467422.2 | F19: POA C | G19: BG-7 Manager/Specialist
A20: Education & Community Engagement Officer | B20: 1000 | C20: =+B20*$E$3 -> 25967.9 | D20: =+B20*$C$3 -> 12000 | E20: =+D20*$E$3 -> 311614.8 | F20: POA B | G20: BG-4 Officer/Technical
A21: Private Sector Specialist | B21: 1500 | C21: =+B21*$E$3 -> 38951.85 | D21: =+B21*$C$3 -> 18000 | E21: =+D21*$E$3 -> 467422.2 | F21: POA C | G21: BG-7 Manager/Specialist
A22: Key Personnel: M&E Director | B22: 4583 | C22: =+B22*$E$3 -> 119010.89 | D22: =+B22*$C$3 -> 54996 | E22: =+D22*$E$3 -> 1428130.6 | F22: POA D | G22: BG-9 DCOP/DPD/Director of Function XX
A23: M&E Specialist | B23: 2000 | C23: =+B23*$E$3 -> 51935.8 | D23: =+B23*$C$3 -> 24000 | E23: =+D23*$E$3 -> 623229.6 | F23: POA C | G23: BG-7 Manager/Specialist
A24: M&E Officer | B24: 1250 | C24: =+B24*$E$3 -> 32459.875 | D24: =+B24*$C$3 -> 15000 | E24: =+D24*$E$3 -> 389518.5 | F24: POA B | G24: BG-4 Officer/Technical
A25: Supply Chain Manager | B25: 5000 | C25: =+B25*$E$3 -> 129839.5 | D25: =+B25*$C$3 -> 60000 | E25: =+D25*$E$3 -> 1558074 | F25: POA D | G25: BG-9 DCOP/DPD/Director of Function XX
A26: In-Country Logistics Specialist | B26: 2000 | C26: =+B26*$E$3 -> 51935.8 | D26: =+B26*$C$3 -> 24000 | E26: =+D26*$E$3 -> 623229.6 | F26: POA C | G26: BG-7 Manager/Specialist
A27: US Commodity Logistics Specialist | B27: 2000 | C27: =+B27*$E$3 -> 51935.8 | D27: =+B27*$C$3 -> 24000 | E27: =+D27*$E$3 -> 623229.6 | F27: POA C | G27: BG-7 Manager/Specialist
A28: Warehouse Manager | B28: 1250 | C28: =+B28*$E$3 -> 32459.875 | D28: =+B28*$C$3 -> 15000 | E28: =+D28*$E$3 -> 389518.5 | F28: POA C | G28: BG-7 Manager/Specialist
A29: Warehouse Officer - (2 Individuals) | B29: 1000 | C29: =+B29*$E$3 -> 25967.9 | D29: =+B29*$C$3 -> 12000 | E29: =+D29*$E$3 -> 311614.8 | F29: POA B | G29: BG-4 Officer/Technical
... A39: Driver - (2 Individuals) | B39: 500 | C39: =+B39*$E$3 -> 12983.95 | D39: =+B39*$C$3 -> 6000 | E39: =+D39*$E$3 -> 155807.4 | F39: POA A | G39: BG-2 Driver

Sheet Birches Report Level
E1: Birchis 2023 | L1: Estimado 2025 con incremento del 11.4% | S1: Estimado 2024 con incremento del 3% | Z1: Estimado 2025 con incremento del 3%
A2: Level | B2: Purpose | C2: Proposed Field Office Grade | D2: Purpose | F2: Bajo | G2: Percentil 25 | H2: Percentil 50 | I2: Percentil 75 | J2: Alto | K2: Media | M2: Bajo | N2: Percentil 25 | O2: Percentil 50 | P2: Percentil 75 | Q2: Alto | R2: Media | T2: Bajo | U2: Percentil 25 | V2: Percentil 50 | W2: Percentil 75 | X2: Alto | Y2: Media | AA2: Bajo | AB2: Percentil 25 | AC2: Percentil 50 | AD2: Percentil 75 | AE2: Alto | AF2: Media | AG2: https://www.trabajo.gob.hn/tabla-de-salario-minimo/?utm_source=chatgpt.com
A3: BG-12 | B3: Integrate-Transform | C3: Poa-E | D3: BG-12 Executive/DCOP | E3: Máx. | F3: 1281000 | G3: 1668232 | H3: 1757143 | I3: 2163000 | J3: 2800000 | K3: 1898529 | L3: Máx. | M3: =((F3*$AG$11)+F3)/$AG$12 -> 54925.448 | N3: =((G3*$AG$11)+G3)/$AG$12 -> 71528.798 | O3: =((H3*$AG$11)+H3)/$AG$12 -> 75341.036 | P3: =((I3*$AG$11)+I3)/$AG$12 -> 92742.97 | Q3: =((J3*$AG$11)+J3)/$AG$12 -> 120055.62 | R3: =MEDIAN(M3:Q3) -> 75341.036 | S3: Máx. | T3: =((F3*$AG$9)+F3)/$AG$12 -> 50966.857 | U3: =((G3*$AG$9)+G3)/$AG$12 -> 66373.569 | V3: =((H3*$AG$9)+H3)/$AG$12 -> 69911.051 | W3: =((I3*$AG$9)+I3)/$AG$12 -> 86058.792 | X3: =((J3*$AG$9)+J3)/$AG$12 -> 111402.97 | Y3: =MEDIAN(T3:X3) -> 69911.051 | Z3: Máx. | AA3: =(T3*$AG$10)+T3 -> 52495.863 | AB3: =(U3*$AG$10)+U3 -> 68364.776 | AC3: =(V3*$AG$10)+V3 -> 72008.383 | AD3: =(W3*$AG$10)+W3 -> 88640.555 | AE3: =(X3*$AG$10)+X3 -> 114745.06 | AF3: =MEDIAN(AA3:AE3) -> 72008.383
E4: Med | F4: 1281000 | G4: 1464121 | H4: 1728090 | I4: 1937393 | J4: 2333333 | K4: 1757545 | L4: Med | M4: =((F4*$AG$11)+F4)/$AG$12 -> 54925.448 | N4: =((G4*$AG$11)+G4)/$AG$12 -> 62777.129 | O4: =((H4*$AG$11)+H4)/$AG$12 -> 74095.33 | P4: =((I4*$AG$11)+I4)/$AG$12 -> 83069.616 | Q4: =((J4*$AG$11)+J4)/$AG$12 -> 100046.34 | R4: =MEDIAN(M4:Q4) -> 74095.33 | S4: Med | T4: =((F4*$AG$9)+F4)/$AG$12 -> 50966.857 | U4: =((G4*$AG$9)+G4)/$AG$12 -> 58252.651 | V4: =((H4*$AG$9)+H4)/$AG$12 -> 68755.126 | W4: =((I4*$AG$9)+I4)/$AG$12 -> 77082.617 | X4: =((J4*$AG$9)+J4)/$AG$12 -> 92835.792 | Y4: =MEDIAN(T4:X4) -> 68755.126 | Z4: Med | AA4: =(T4*$AG$10)+T4 -> 52495.863 | AB4: =(U4*$AG$10)+U4 -> 60000.231 | AC4: =(V4*$AG$10)+V4 -> 70817.78 | AD4: =(W4*$AG$10)+W4 -> 79395.096 | AE4: =(X4*$AG$10)+X4 -> 95620.866 | AF4: =MEDIAN(AA4:AE4) -> 70817.78 | AG4: Para una empresa con 11 a 50 empleados, los incrementos al salario mínimo en Honduras han sido del 5.5 % para 2024 y de nuevo del 5.5 % para 2025. trabajo.gob.hn+2Bloomberg Línea Brasil+2
E5: Min. | F5: 1174040 | G5: 1375440 | H5: 1567430 | I5: 1770426 | J5: 2163000 | K5: 1616561 | L5: Min. | M5: =((F5*$AG$11)+F5)/$AG$12 -> 50339.323 | N5: =((G5*$AG$11)+G5)/$AG$12 -> 58974.753 | O5: =((H5*$AG$11)+H5)/$AG$12 -> 67206.71 | P5: =((I5*$AG$11)+I5)/$AG$12 -> 75910.571 | Q5: =((J5*$AG$11)+J5)/$AG$12 -> 92742.97 | R5: =MEDIAN(M5:Q5) -> 67206.71 | S5: Min. | T5: =((F5*$AG$9)+F5)/$AG$12 -> 46711.264 | U5: =((G5*$AG$9)+G5)/$AG$12 -> 54724.32 | V5: =((H5*$AG$9)+H5)/$AG$12 -> 62362.983 | W5: =((I5*$AG$9)+I5)/$AG$12 -> 70439.539 | X5: =((J5*$AG$9)+J5)/$AG$12 -> 86058.792 | Y5: =MEDIAN(T5:X5) -> 62362.983 | Z5: Min. | AA5: =(T5*$AG$10)+T5 -> 48112.602 | AB5: =(U5*$AG$10)+U5 -> 56366.05 | AC5: =(V5*$AG$10)+V5 -> 64233.872 | AD5: =(W5*$AG$10)+W5 -> 72552.725 | AE5: =(X5*$AG$10)+X5 -> 88640.555 | AF5: =MEDIAN(AA5:AE5) -> 64233.872 | AG5: Si tomamos como base un salario mínimo de L 12,560.96 en enero de 2023, el estimado acumulado para octubre de 2025 sería:
A6: BG-11 | B6: Innovate | D6: BG-11 Country Directors/COP | E6: Máx. | F6: 941347 | G6: 1542070 | H6: 1886528 | I6: 2129776 | J6: 3450528 | K6: 1961246 | L6: Máx. | M6: =((F6*$AG$11)+F6)/$AG$12 -> 40362.143 | N6: =((G6*$AG$11)+G6)/$AG$12 -> 66119.349 | O6: =((H6*$AG$11)+H6)/$AG$12 -> 80888.677 | P6: =((I6*$AG$11)+I6)/$AG$12 -> 91318.424 | Q6: =((J6*$AG$11)+J6)/$AG$12 -> 147948.32 | R6: =MEDIAN(M6:Q6) -> 80888.677 | S6: Máx. | T6: =((F6*$AG$9)+F6)/$AG$12 -> 37453.16 | U6: =((G6*$AG$9)+G6)/$AG$12 -> 61353.99 | V6: =((H6*$AG$9)+H6)/$AG$12 -> 75058.863 | W6: =((I6*$AG$9)+I6)/$AG$12 -> 84736.916 | X6: =((J6*$AG$9)+J6)/$AG$12 -> 137285.38 | Y6: =MEDIAN(T6:X6) -> 75058.863 | Z6: Máx. | AA6: =+(T6*$AG$10)+T6 -> 38576.755 | AB6: =+(U6*$AG$10)+U6 -> 63194.61 | AC6: =+(V6*$AG$10)+V6 -> 77310.629 | AD6: =+(W6*$AG$10)+W6 -> 87279.023 | AE6: =+(X6*$AG$10)+X6 -> 141403.94 | AF6: =MEDIAN(AA6:AE6) -> 77310.629 | AG6: Después del primer ajuste (2024): L 12,560.96 × 1.055 ≈ L 13,250.11
E7: Med | F7: 760167 | G7: 1309132 | H7: 1452829 | I7: 1846013 | J7: 2239464 | K7: 1538094 | L7: Med | M7: =((F7*$AG$11)+F7)/$AG$12 -> 32593.687 | N7: =((G7*$AG$11)+G7)/$AG$12 -> 56131.664 | O7: =((H7*$AG$11)+H7)/$AG$12 -> 62292.962 | P7: =((I7*$AG$11)+I7)/$AG$12 -> 79151.515 | Q7: =((J7*$AG$11)+J7)/$AG$12 -> 96021.517 | R7: =MEDIAN(M7:Q7) -> 62292.962 | S7: Med | T7: =((F7*$AG$9)+F7)/$AG$12 -> 30244.592 | U7: =((G7*$AG$9)+G7)/$AG$12 -> 52086.139 | V7: =((H7*$AG$9)+H7)/$AG$12 -> 57803.379 | W7: =((I7*$AG$9)+I7)/$AG$12 -> 73446.902 | X7: =((J7*$AG$9)+J7)/$AG$12 -> 89101.048 | Y7: =MEDIAN(T7:X7) -> 57803.379 | Z7: Med | AA7: =+(T7*$AG$10)+T7 -> 31151.93 | AB7: =+(U7*$AG$10)+U7 -> 53648.723 | AC7: =+(V7*$AG$10)+V7 -> 59537.48 | AD7: =+(W7*$AG$10)+W7 -> 75650.309 | AE7: =+(X7*$AG$10)+X7 -> 91774.079 | AF7: =MEDIAN(AA7:AE7) -> 59537.48 | AG7: Después del segundo ajuste (2025): L 13,250.11 × 1.055 ≈ L 13,993.37
E8: Min. | F8: 578987 | G8: 961524 | H8: 1036042 | I8: 1150800 | J8: 1898048 | K8: 1114941 | L8: Min. | M8: =((F8*$AG$11)+F8)/$AG$12 -> 24825.231 | N8: =((G8*$AG$11)+G8)/$AG$12 -> 41227.273 | O8: =((H8*$AG$11)+H8)/$AG$12 -> 44422.382 | P8: =((I8*$AG$11)+I8)/$AG$12 -> 49342.862 | Q8: =((J8*$AG$11)+J8)/$AG$12 -> 81382.621 | R8: =MEDIAN(M8:Q8) -> 44422.382 | S8: Min. | T8: =((F8*$AG$9)+F8)/$AG$12 -> 23036.025 | U8: =((G8*$AG$9)+G8)/$AG$12 -> 38255.938 | V8: =((H8*$AG$9)+H8)/$AG$12 -> 41220.769 | W8: =((I8*$AG$9)+I8)/$AG$12 -> 45786.619 | X8: =((J8*$AG$9)+J8)/$AG$12 -> 75517.206 | Y8: =MEDIAN(T8:X8) -> 41220.769 | Z8: Min. | AA8: =+(T8*$AG$10)+T8 -> 23727.106 | AB8: =+(U8*$AG$10)+U8 -> 39403.616 | AC8: =+(V8*$AG$10)+V8 -> 42457.392 | AD8: =+(W8*$AG$10)+W8 -> 47160.218 | AE8: =+(X8*$AG$10)+X8 -> 77782.723 | AF8: =MEDIAN(AA8:AE8) -> 42457.392 | AG8: Por tanto, un estimado razonable del salario mínimo para esa categoría en octubre de 2025 sería aproximadamente L 13,993.37, lo que representa un incremento acumulado de alrededor del 11.4 % desde enero de 2023.
A9: BG-10 | B9: Adapt | C9: Poa-D | D9: BG-10 Project Director | E9: Máx. | F9: 815061 | G9: 1078766 | H9: 1237256 | I9: 1460946 | J9: 2126740 | K9: 1277641 | L9: Máx. | M9: =((F9*$AG$11)+F9)/$AG$12 -> 34947.378 | N9: =((G9*$AG$11)+G9)/$AG$12 -> 46254.259 | O9: =((H9*$AG$11)+H9)/$AG$12 -> 53049.836 | P9: =((I9*$AG$11)+I9)/$AG$12 -> 62640.994 | Q9: =((J9*$AG$11)+J9)/$AG$12 -> 91188.249 | R9: =MEDIAN(M9:Q9) -> 53049.836 | S9: Máx. | T9: =((F9*$AG$9)+F9)/$AG$12 -> 32428.648 | U9: =((G9*$AG$9)+G9)/$AG$12 -> 42920.619 | V9: =((H9*$AG$9)+H9)/$AG$12 -> 49226.425 | W9: =((I9*$AG$9)+I9)/$AG$12 -> 58126.328 | X9: =((J9*$AG$9)+J9)/$AG$12 -> 84616.123 | Y9: =MEDIAN(T9:X9) -> 49226.425 | Z9: Máx. | AA9: =+(T9*$AG$10)+T9 -> 33401.507 | AB9: =+(U9*$AG$10)+U9 -> 44208.237 | AC9: =+(V9*$AG$10)+V9 -> 50703.217 | AD9: =+(W9*$AG$10)+W9 -> 59870.118 | AE9: =+(X9*$AG$10)+X9 -> 87154.607 | AF9: =MEDIAN(AA9:AE9) -> 50703.217 | AG9: 0.03 | AH9: Por Instrucción de HO | AI9: 0.0388 | AJ9: Inflación del 2024"fuente, Secretaria de Finanzas de Honduras": https://www.sefin.gob.hn/download_file.php?download_file=/wp-content/uploads/2025/liquidacion2024/2-Informe-Cierre-Fiscal-2024.pdf
E10: Med | F10: 658762 | G10: 913182 | H10: 1065812 | I10: 1217462 | J10: 1479152 | K10: 1054481 | L10: Med | M10: =((F10*$AG$11)+F10)/$AG$12 -> 28245.744 | N10: =((G10*$AG$11)+G10)/$AG$12 -> 39154.513 | O10: =((H10*$AG$11)+H10)/$AG$12 -> 45698.83 | P10: =((I10*$AG$11)+I10)/$AG$12 -> 52201.129 | Q10: =((J10*$AG$11)+J10)/$AG$12 -> 63421.613 | R10: =MEDIAN(M10:Q10) -> 45698.83 | S10: Med | T10: =((F10*$AG$9)+F10)/$AG$12 -> 26210.015 | U10: =((G10*$AG$9)+G10)/$AG$12 -> 36332.566 | V10: =((H10*$AG$9)+H10)/$AG$12 -> 42405.221 | W10: =((I10*$AG$9)+I10)/$AG$12 -> 48438.885 | X10: =((J10*$AG$9)+J10)/$AG$12 -> 58850.686 | Y10: =MEDIAN(T10:X10) -> 42405.221 | Z10: Med | AA10: =+(T10*$AG$10)+T10 -> 26996.315 | AB10: =+(U10*$AG$10)+U10 -> 37422.543 | AC10: =+(V10*$AG$10)+V10 -> 43677.378 | AD10: =+(W10*$AG$10)+W10 -> 49892.052 | AE10: =+(X10*$AG$10)+X10 -> 60616.207 | AF10: =MEDIAN(AA10:AE10) -> 43677.378 | AG10: 0.03 | AH10: Por Instrucción de HO | AI10: 0.0416 | AJ10: Inflación del 2025 "Fuente Banco central de Honduras": chrome-extension://efaidnbmnnnibpcajpcglclefindmkaj/https://www.bch.hn/estadisticos/GIE/LIBIPC/%C3%8Dndice%20de%20Precios%20al%20Consumidor%20Agosto%202025.pdf
E11: Min. | F11: 457498 | G11: 705246 | H11: 840000 | I11: 1018463 | J11: 1243740 | K11: 831321 | L11: Min. | M11: =((F11*$AG$11)+F11)/$AG$12 -> 19616.146 | N11: =((G11*$AG$11)+G11)/$AG$12 -> 30238.839 | O11: =((H11*$AG$11)+H11)/$AG$12 -> 36016.687 | P11: =((I11*$AG$11)+I11)/$AG$12 -> 43668.647 | Q11: =((J11*$AG$11)+J11)/$AG$12 -> 53327.851 | R11: =MEDIAN(M11:Q11) -> 36016.687 | S11: Min. | T11: =((F11*$AG$9)+F11)/$AG$12 -> 18202.369 | U11: =((G11*$AG$9)+G11)/$AG$12 -> 28059.463 | V11: =((H11*$AG$9)+H11)/$AG$12 -> 33420.89 | W11: =((I11*$AG$9)+I11)/$AG$12 -> 40521.357 | X11: =((J11*$AG$9)+J11)/$AG$12 -> 49484.402 | Y11: =MEDIAN(T11:X11) -> 33420.89 | Z11: Min. | AA11: =+(T11*$AG$10)+T11 -> 18748.441 | AB11: =+(U11*$AG$10)+U11 -> 28901.247 | AC11: =+(V11*$AG$10)+V11 -> 34423.517 | AD11: =+(W11*$AG$10)+W11 -> 41736.998 | AE11: =+(X11*$AG$10)+X11 -> 50968.934 | AF11: =MEDIAN(AA11:AE11) -> 34423.517 | AG11: 0.11 | AH11: SMLV
A12: BG-9 | B12: Analyze | D12: BG-9 DCOP/DPD/Director of Function XX | E12: Máx. | F12: 431487 | G12: 786095 | H12: 853252 | I12: 1169733 | J12: 1946078 | K12: 957927 | L12: Máx. | M12: =((F12*$AG$11)+F12)/$AG$12 -> 18500.872 | N12: =((G12*$AG$11)+G12)/$AG$12 -> 33705.402 | O12: =((H12*$AG$11)+H12)/$AG$12 -> 36584.893 | P12: =((I12*$AG$11)+I12)/$AG$12 -> 50154.652 | Q12: =((J12*$AG$11)+J12)/$AG$12 -> 83442.003 | R12: =MEDIAN(M12:Q12) -> 36584.893 | S12: Máx. | T12: =((F12*$AG$9)+F12)/$AG$12 -> 17167.476 | U12: =((G12*$AG$9)+G12)/$AG$12 -> 31276.184 | V12: =((H12*$AG$9)+H12)/$AG$12 -> 33948.144 | W12: =((I12*$AG$9)+I12)/$AG$12 -> 46539.902 | X12: =((J12*$AG$9)+J12)/$AG$12 -> 77428.165 | Y12: =MEDIAN(T12:X12) -> 33948.144 | Z12: Máx. | AA12: =+(T12*$AG$10)+T12 -> 17682.5 | AB12: =+(U12*$AG$10)+U12 -> 32214.469 | AC12: =+(V12*$AG$10)+V12 -> 34966.589 | AD12: =+(W12*$AG$10)+W12 -> 47936.099 | AE12: =+(X12*$AG$10)+X12 -> 79751.01 | AF12: =MEDIAN(AA12:AE12) -> 34966.589 | AG12: 25.888 | AH12: TRM
E13: Med | F13: 414767 | G13: 673834 | H13: 748250 | I13: 931103 | J13: 1622087 | K13: 798360 | L13: Med | M13: =((F13*$AG$11)+F13)/$AG$12 -> 17783.968 | N13: =((G13*$AG$11)+G13)/$AG$12 -> 28891.986 | O13: =((H13*$AG$11)+H13)/$AG$12 -> 32082.722 | P13: =((I13*$AG$11)+I13)/$AG$12 -> 39922.911 | Q13: =((J13*$AG$11)+J13)/$AG$12 -> 69550.238 | R13: =MEDIAN(M13:Q13) -> 32082.722 | S13: Med | T13: =((F13*$AG$9)+F13)/$AG$12 -> 16502.241 | U13: =((G13*$AG$9)+G13)/$AG$12 -> 26809.681 | V13: =((H13*$AG$9)+H13)/$AG$12 -> 29770.453 | W13: =((I13*$AG$9)+I13)/$AG$12 -> 37045.584 | X13: =((J13*$AG$9)+J13)/$AG$12 -> 64537.609 | Y13: =MEDIAN(T13:X13) -> 29770.453 | Z13: Med | AA13: =+(T13*$AG$10)+T13 -> 16997.308 | AB13: =+(U13*$AG$10)+U13 -> 27613.971 | AC13: =+(V13*$AG$10)+V13 -> 30663.567 | AD13: =+(W13*$AG$10)+W13 -> 38156.952 | AE13: =+(X13*$AG$10)+X13 -> 66473.737 | AF13: =MEDIAN(AA13:AE13) -> 30663.567 | AG13: 13993.37 | AH13: SMLV
E14: Min. | F14: 361300 | G14: 518942 | H14: 584900 | I14: 703811 | J14: 1374707 | K14: 638793 | L14: Min. | M14: =((F14*$AG$11)+F14)/$AG$12 -> 15491.463 | N14: =((G14*$AG$11)+G14)/$AG$12 -> 22250.681 | O14: =((H14*$AG$11)+H14)/$AG$12 -> 25078.762 | P14: =((I14*$AG$11)+I14)/$AG$12 -> 30177.31 | Q14: =((J14*$AG$11)+J14)/$AG$12 -> 58943.324 | R14: =MEDIAN(M14:Q14) -> 25078.762 | S14: Min. | T14: =((F14*$AG$9)+F14)/$AG$12 -> 14374.961 | U14: =((G14*$AG$9)+G14)/$AG$12 -> 20647.028 | V14: =((H14*$AG$9)+H14)/$AG$12 -> 23271.284 | W14: =((I14*$AG$9)+I14)/$AG$12 -> 28002.369 | X14: =((J14*$AG$9)+J14)/$AG$12 -> 54695.156 | Y14: =MEDIAN(T14:X14) -> 23271.284 | Z14: Min. | AA14: =+(T14*$AG$10)+T14 -> 14806.21 | AB14: =+(U14*$AG$10)+U14 -> 21266.439 | AC14: =+(V14*$AG$10)+V14 -> 23969.423 | AD14: =+(W14*$AG$10)+W14 -> 28842.44 | AE14: =+(X14*$AG$10)+X14 -> 56336.011 | AF14: =MEDIAN(AA14:AE14) -> 23969.423
A15: BG-8 | B15: Apply Basic Concepts | D15: BG-8 Transitional Managerial | E15: Máx. | F15: 627521 | G15: 842534 | H15: 846989 | I15: 898333 | J15: 1543883 | K15: 924420 | L15: Máx. | M15: =((F15*$AG$11)+F15)/$AG$12 -> 26906.223 | N15: =((G15*$AG$11)+G15)/$AG$12 -> 36125.338 | O15: =((H15*$AG$11)+H15)/$AG$12 -> 36316.355 | P15: =((I15*$AG$11)+I15)/$AG$12 -> 38517.832 | Q15: =((J15*$AG$11)+J15)/$AG$12 -> 66197.085 | R15: =MEDIAN(M15:Q15) -> 36316.355 | S15: Máx. | T15: =((F15*$AG$9)+F15)/$AG$12 -> 24967.036 | U15: =((G15*$AG$9)+G15)/$AG$12 -> 33521.71 | V15: =((H15*$AG$9)+H15)/$AG$12 -> 33698.96 | W15: =((I15*$AG$9)+I15)/$AG$12 -> 35741.772 | X15: =((J15*$AG$9)+J15)/$AG$12 -> 61426.124 | Y15: =MEDIAN(T15:X15) -> 33698.96 | Z15: Máx. | AA15: =+(T15*$AG$10)+T15 -> 25716.047 | AB15: =+(U15*$AG$10)+U15 -> 34527.361 | AC15: =+(V15*$AG$10)+V15 -> 34709.929 | AD15: =+(W15*$AG$10)+W15 -> 36814.025 | AE15: =+(X15*$AG$10)+X15 -> 63268.907 | AF15: =MEDIAN(AA15:AE15) -> 34709.929
E16: Med | F16: 509861 | G16: 668801 | H16: 692818 | I16: 770000 | J16: 1092775 | K16: 710943 | L16: Med | M16: =((F16*$AG$11)+F16)/$AG$12 -> 21861.315 | N16: =((G16*$AG$11)+G16)/$AG$12 -> 28676.186 | O16: =((H16*$AG$11)+H16)/$AG$12 -> 29705.963 | P16: =((I16*$AG$11)+I16)/$AG$12 -> 33015.297 | Q16: =((J16*$AG$11)+J16)/$AG$12 -> 46854.923 | R16: =MEDIAN(M16:Q16) -> 29705.963 | S16: Med | T16: =((F16*$AG$9)+F16)/$AG$12 -> 20285.724 | U16: =((G16*$AG$9)+G16)/$AG$12 -> 26609.434 | V16: =((H16*$AG$9)+H16)/$AG$12 -> 27564.993 | W16: =((I16*$AG$9)+I16)/$AG$12 -> 30635.816 | X16: =((J16*$AG$9)+J16)/$AG$12 -> 43477.992 | Y16: =MEDIAN(T16:X16) -> 27564.993 | Z16: Med | AA16: =+(T16*$AG$10)+T16 -> 20894.296 | AB16: =+(U16*$AG$10)+U16 -> 27407.717 | AC16: =+(V16*$AG$10)+V16 -> 28391.943 | AD16: =+(W16*$AG$10)+W16 -> 31554.89 | AE16: =+(X16*$AG$10)+X16 -> 44782.331 | AF16: =MEDIAN(AA16:AE16) -> 28391.943
E17: Min. | F17: 392201 | G17: 423652 | H17: 495068 | I17: 543102 | J17: 641667 | K17: 497466 | L17: Min. | M17: =((F17*$AG$11)+F17)/$AG$12 -> 16816.406 | N17: =((G17*$AG$11)+G17)/$AG$12 -> 18164.93 | O17: =((H17*$AG$11)+H17)/$AG$12 -> 21227.035 | P17: =((I17*$AG$11)+I17)/$AG$12 -> 23286.589 | Q17: =((J17*$AG$11)+J17)/$AG$12 -> 27512.762 | R17: =MEDIAN(M17:Q17) -> 21227.035 | S17: Min. | T17: =((F17*$AG$9)+F17)/$AG$12 -> 15604.412 | U17: =((G17*$AG$9)+G17)/$AG$12 -> 16855.746 | V17: =((H17*$AG$9)+H17)/$AG$12 -> 19697.159 | W17: =((I17*$AG$9)+I17)/$AG$12 -> 21608.276 | X17: =((J17*$AG$9)+J17)/$AG$12 -> 25529.86 | Y17: =MEDIAN(T17:X17) -> 19697.159 | Z17: Min. | AA17: =+(T17*$AG$10)+T17 -> 16072.545 | AB17: =+(U17*$AG$10)+U17 -> 17361.419 | AC17: =+(V17*$AG$10)+V17 -> 20288.073 | AD17: =+(W17*$AG$10)+W17 -> 22256.525 | AE17: =+(X17*$AG$10)+X17 -> 26295.756 | AF17: =MEDIAN(AA17:AE17) -> 20288.073
A18: BG-7 | B18: Manage Integrated Processes | C18: Poa-C | D18: BG-7 Manager/Specialist | E18: Máx. | F18: 379497 | G18: 554366 | H18: 695712 | I18: 866996 | J18: 1225700 | K18: 712178 | L18: Máx. | M18: =((F18*$AG$11)+F18)/$AG$12 -> 16271.696 | N18: =((G18*$AG$11)+G18)/$AG$12 -> 23769.556 | O18: =((H18*$AG$11)+H18)/$AG$12 -> 29830.049 | P18: =((I18*$AG$11)+I18)/$AG$12 -> 37174.195 | Q18: =((J18*$AG$11)+J18)/$AG$12 -> 52554.35 | R18: =MEDIAN(M18:Q18) -> 29830.049 | S18: Máx. | T18: =((F18*$AG$9)+F18)/$AG$12 -> 15098.961 | U18: =((G18*$AG$9)+G18)/$AG$12 -> 22056.435 | V18: =((H18*$AG$9)+H18)/$AG$12 -> 27680.136 | W18: =((I18*$AG$9)+I18)/$AG$12 -> 34494.974 | X18: =((J18*$AG$9)+J18)/$AG$12 -> 48766.649 | Y18: =MEDIAN(T18:X18) -> 27680.136 | Z18: Máx. | AA18: =+(T18*$AG$10)+T18 -> 15551.93 | AB18: =+(U18*$AG$10)+U18 -> 22718.128 | AC18: =+(V18*$AG$10)+V18 -> 28510.54 | AD18: =+(W18*$AG$10)+W18 -> 35529.823 | AE18: =+(X18*$AG$10)+X18 -> 50229.648 | AF18: =MEDIAN(AA18:AE18) -> 28510.54
E19: Med | F19: 361273 | G19: 469910 | H19: 567000 | I19: 662081 | J19: 1225700 | K19: 584607 | L19: Med | M19: =((F19*$AG$11)+F19)/$AG$12 -> 15490.306 | N19: =((G19*$AG$11)+G19)/$AG$12 -> 20148.335 | O19: =((H19*$AG$11)+H19)/$AG$12 -> 24311.264 | P19: =((I19*$AG$11)+I19)/$AG$12 -> 28388.053 | Q19: =((J19*$AG$11)+J19)/$AG$12 -> 52554.35 | R19: =MEDIAN(M19:Q19) -> 24311.264 | S19: Med | T19: =((F19*$AG$9)+F19)/$AG$12 -> 14373.887 | U19: =((G19*$AG$9)+G19)/$AG$12 -> 18696.203 | V19: =((H19*$AG$9)+H19)/$AG$12 -> 22559.101 | W19: =((I19*$AG$9)+I19)/$AG$12 -> 26342.067 | X19: =((J19*$AG$9)+J19)/$AG$12 -> 48766.649 | Y19: =MEDIAN(T19:X19) -> 22559.101 | Z19: Med | AA19: =+(T19*$AG$10)+T19 -> 14805.104 | AB19: =+(U19*$AG$10)+U19 -> 19257.089 | AC19: =+(V19*$AG$10)+V19 -> 23235.874 | AD19: =+(W19*$AG$10)+W19 -> 27132.329 | AE19: =+(X19*$AG$10)+X19 -> 50229.648 | AF19: =MEDIAN(AA19:AE19) -> 23235.874
E20: Min. | F20: 273242 | G20: 367080 | H20: 414246 | I20: 489209 | J20: 1225700 | K20: 457036 | L20: Min. | M20: =((F20*$AG$11)+F20)/$AG$12 -> 11715.8 | N20: =((G20*$AG$11)+G20)/$AG$12 -> 15739.292 | O20: =((H20*$AG$11)+H20)/$AG$12 -> 17761.629 | P20: =((I20*$AG$11)+I20)/$AG$12 -> 20975.819 | Q20: =((J20*$AG$11)+J20)/$AG$12 -> 52554.35 | R20: =MEDIAN(M20:Q20) -> 17761.629 | S20: Min. | T20: =((F20*$AG$9)+F20)/$AG$12 -> 10871.418 | U20: =((G20*$AG$9)+G20)/$AG$12 -> 14604.929 | V20: =((H20*$AG$9)+H20)/$AG$12 -> 16481.512 | W20: =((I20*$AG$9)+I20)/$AG$12 -> 19464.048 | X20: =((J20*$AG$9)+J20)/$AG$12 -> 48766.649 | Y20: =MEDIAN(T20:X20) -> 16481.512 | Z20: Min. | AA20: =+(T20*$AG$10)+T20 -> 11197.56 | AB20: =+(U20*$AG$10)+U20 -> 15043.077 | AC20: =+(V20*$AG$10)+V20 -> 16975.957 | AD20: =+(W20*$AG$10)+W20 -> 20047.969 | AE20: =+(X20*$AG$10)+X20 -> 50229.648 | AF20: =MEDIAN(AA20:AE20) -> 16975.957
A21: BG-6 | B21: Ensure Process Integrity | D21: BG-6 Coordinator/Jr Specialist | E21: Máx. | F21: 356742 | G21: 455830 | H21: 530833 | I21: 634244 | J21: 974813 | K21: 566658 | L21: Máx. | M21: =((F21*$AG$11)+F21)/$AG$12 -> 15296.03 | N21: =((G21*$AG$11)+G21)/$AG$12 -> 19544.627 | O21: =((H21*$AG$11)+H21)/$AG$12 -> 22760.531 | P21: =((I21*$AG$11)+I21)/$AG$12 -> 27194.485 | Q21: =((J21*$AG$11)+J21)/$AG$12 -> 41797.065 | R21: =MEDIAN(M21:Q21) -> 22760.531 | S21: Máx. | T21: =((F21*$AG$9)+F21)/$AG$12 -> 14193.613 | U21: =((G21*$AG$9)+G21)/$AG$12 -> 18136.005 | V21: =((H21*$AG$9)+H21)/$AG$12 -> 21120.132 | W21: =((I21*$AG$9)+I21)/$AG$12 -> 25234.523 | X21: =((J21*$AG$9)+J21)/$AG$12 -> 38784.664 | Y21: =MEDIAN(T21:X21) -> 21120.132 | Z21: Máx. | AA21: =+(T21*$AG$10)+T21 -> 14619.422 | AB21: =+(U21*$AG$10)+U21 -> 18680.085 | AC21: =+(V21*$AG$10)+V21 -> 21753.736 | AD21: =+(W21*$AG$10)+W21 -> 25991.558 | AE21: =+(X21*$AG$10)+X21 -> 39948.204 | AF21: =MEDIAN(AA21:AE21) -> 21753.736
E22: Med | F22: 310927 | G22: 391510 | H22: 431479 | I22: 529777 | J22: 771883 | K22: 458949 | L22: Med | M22: =((F22*$AG$11)+F22)/$AG$12 -> 13331.62 | N22: =((G22*$AG$11)+G22)/$AG$12 -> 16786.778 | O22: =((H22*$AG$11)+H22)/$AG$12 -> 18500.529 | P22: =((I22*$AG$11)+I22)/$AG$12 -> 22715.253 | Q22: =((J22*$AG$11)+J22)/$AG$12 -> 33096.034 | R22: =MEDIAN(M22:Q22) -> 18500.529 | S22: Med | T22: =((F22*$AG$9)+F22)/$AG$12 -> 12370.782 | U22: =((G22*$AG$9)+G22)/$AG$12 -> 15576.92 | V22: =((H22*$AG$9)+H22)/$AG$12 -> 17167.157 | W22: =((I22*$AG$9)+I22)/$AG$12 -> 21078.118 | X22: =((J22*$AG$9)+J22)/$AG$12 -> 30710.734 | Y22: =MEDIAN(T22:X22) -> 17167.157 | Z22: Med | AA22: =+(T22*$AG$10)+T22 -> 12741.906 | AB22: =+(U22*$AG$10)+U22 -> 16044.227 | AC22: =+(V22*$AG$10)+V22 -> 17682.172 | AD22: =+(W22*$AG$10)+W22 -> 21710.461 | AE22: =+(X22*$AG$10)+X22 -> 31632.056 | AF22: =MEDIAN(AA22:AE22) -> 17682.172
E23: Min. | F23: 223167 | G23: 289003 | H23: 326650 | I23: 363620 | J23: 603766 | K23: 351239 | L23: Min. | M23: =((F23*$AG$11)+F23)/$AG$12 -> 9568.7334 | N23: =((G23*$AG$11)+G23)/$AG$12 -> 12391.584 | O23: =((H23*$AG$11)+H23)/$AG$12 -> 14005.775 | P23: =((I23*$AG$11)+I23)/$AG$12 -> 15590.938 | Q23: =((J23*$AG$11)+J23)/$AG$12 -> 25887.68 | R23: =MEDIAN(M23:Q23) -> 14005.775 | S23: Min. | T23: =((F23*$AG$9)+F23)/$AG$12 -> 8879.0949 | U23: =((G23*$AG$9)+G23)/$AG$12 -> 11498.497 | V23: =((H23*$AG$9)+H23)/$AG$12 -> 12996.35 | W23: =((I23*$AG$9)+I23)/$AG$12 -> 14467.267 | X23: =((J23*$AG$9)+J23)/$AG$12 -> 24021.901 | Y23: =MEDIAN(T23:X23) -> 12996.35 | Z23: Min. | AA23: =+(T23*$AG$10)+T23 -> 9145.4678 | AB23: =+(U23*$AG$10)+U23 -> 11843.452 | AC23: =+(V23*$AG$10)+V23 -> 13386.24 | AD23: =+(W23*$AG$10)+W23 -> 14901.285 | AE23: =+(X23*$AG$10)+X23 -> 24742.558 | AF23: =MEDIAN(AA23:AE23) -> 13386.24
A24: BG-5 | B24: Execute Intricate Transactions | C24: Poa-B | D24: BG-5 Sr. Officer/Sr. Technical | E24: Máx. | F24: 198638 | G24: 372268 | H24: 424667 | I24: 560000 | J24: 863081 | K24: 474314 | L24: Máx. | M24: =((F24*$AG$11)+F24)/$AG$12 -> 8517.0032 | N24: =((G24*$AG$11)+G24)/$AG$12 -> 15961.738 | O24: =((H24*$AG$11)+H24)/$AG$12 -> 18208.451 | P24: =((I24*$AG$11)+I24)/$AG$12 -> 24011.125 | Q24: =((J24*$AG$11)+J24)/$AG$12 -> 37006.332 | R24: =MEDIAN(M24:Q24) -> 18208.451 | S24: Máx. | T24: =((F24*$AG$9)+F24)/$AG$12 -> 7903.1652 | U24: =((G24*$AG$9)+G24)/$AG$12 -> 14811.343 | V24: =((H24*$AG$9)+H24)/$AG$12 -> 16896.13 | W24: =((I24*$AG$9)+I24)/$AG$12 -> 22280.593 | X24: =((J24*$AG$9)+J24)/$AG$12 -> 34339.209 | Y24: =MEDIAN(T24:X24) -> 16896.13 | Z24: Máx. | AA24: =+(T24*$AG$10)+T24 -> 8140.2601 | AB24: =+(U24*$AG$10)+U24 -> 15255.683 | AC24: =+(V24*$AG$10)+V24 -> 17403.014 | AD24: =+(W24*$AG$10)+W24 -> 22949.011 | AE24: =+(X24*$AG$10)+X24 -> 35369.385 | AF24: =MEDIAN(AA24:AE24) -> 17403.014
E25: Med | F25: 194037 | G25: 307348 | H25: 347067 | I25: 441000 | J25: 719590 | K25: 393121 | L25: Med | M25: =((F25*$AG$11)+F25)/$AG$12 -> 8319.7261 | N25: =((G25*$AG$11)+G25)/$AG$12 -> 13178.163 | O25: =((H25*$AG$11)+H25)/$AG$12 -> 14881.195 | P25: =((I25*$AG$11)+I25)/$AG$12 -> 18908.761 | Q25: =((J25*$AG$11)+J25)/$AG$12 -> 30853.867 | R25: =MEDIAN(M25:Q25) -> 14881.195 | S25: Med | T25: =((F25*$AG$9)+F25)/$AG$12 -> 7720.1062 | U25: =((G25*$AG$9)+G25)/$AG$12 -> 12228.385 | V25: =((H25*$AG$9)+H25)/$AG$12 -> 13808.676 | W25: =((I25*$AG$9)+I25)/$AG$12 -> 17545.967 | X25: =((J25*$AG$9)+J25)/$AG$12 -> 28630.165 | Y25: =MEDIAN(T25:X25) -> 13808.676 | Z25: Med | AA25: =+(T25*$AG$10)+T25 -> 7951.7094 | AB25: =+(U25*$AG$10)+U25 -> 12595.237 | AC25: =+(V25*$AG$10)+V25 -> 14222.937 | AD25: =+(W25*$AG$10)+W25 -> 18072.346 | AE25: =+(X25*$AG$10)+X25 -> 29489.069 | AF25: =MEDIAN(AA25:AE25) -> 14222.937
E26: Min. | F26: 189437 | G26: 237102 | H26: 265216 | I26: 383313 | J26: 634480 | K26: 311927 | L26: Min. | M26: =((F26*$AG$11)+F26)/$AG$12 -> 8122.4919 | N26: =((G26*$AG$11)+G26)/$AG$12 -> 10166.225 | O26: =((H26*$AG$11)+H26)/$AG$12 -> 11371.669 | P26: =((I26*$AG$11)+I26)/$AG$12 -> 16435.315 | Q26: =((J26*$AG$11)+J26)/$AG$12 -> 27204.604 | R26: =MEDIAN(M26:Q26) -> 11371.669 | S26: Min. | T26: =((F26*$AG$9)+F26)/$AG$12 -> 7537.0871 | U26: =((G26*$AG$9)+G26)/$AG$12 -> 9433.5236 | V26: =((H26*$AG$9)+H26)/$AG$12 -> 10552.089 | W26: =((I26*$AG$9)+I26)/$AG$12 -> 15250.788 | X26: =((J26*$AG$9)+J26)/$AG$12 -> 25243.912 | Y26: =MEDIAN(T26:X26) -> 10552.089 | Z26: Min. | AA26: =+(T26*$AG$10)+T26 -> 7763.1997 | AB26: =+(U26*$AG$10)+U26 -> 9716.5293 | AC26: =+(V26*$AG$10)+V26 -> 10868.652 | AD26: =+(W26*$AG$10)+W26 -> 15708.311 | AE26: =+(X26*$AG$10)+X26 -> 26001.23 | AF26: =MEDIAN(AA26:AE26) -> 10868.652
A27: BG-4 | B27: Process Basic Transactions | D27: BG-4 Officer/Technical | E27: Máx. | F27: 240912 | G27: 308723 | H27: 347251 | I27: 421939 | J27: 1464372 | K27: 387778 | L27: Máx. | M27: =((F27*$AG$11)+F27)/$AG$12 -> 10329.586 | N27: =((G27*$AG$11)+G27)/$AG$12 -> 13237.119 | O27: =((H27*$AG$11)+H27)/$AG$12 -> 14889.084 | P27: =((I27*$AG$11)+I27)/$AG$12 -> 18091.482 | Q27: =((J27*$AG$11)+J27)/$AG$12 -> 62787.891 | R27: =MEDIAN(M27:Q27) -> 14889.084 | S27: Máx. | T27: =((F27*$AG$9)+F27)/$AG$12 -> 9585.1112 | U27: =((G27*$AG$9)+G27)/$AG$12 -> 12283.092 | V27: =((H27*$AG$9)+H27)/$AG$12 -> 13815.997 | W27: =((I27*$AG$9)+I27)/$AG$12 -> 16787.592 | X27: =((J27*$AG$9)+J27)/$AG$12 -> 58262.638 | Y27: =MEDIAN(T27:X27) -> 13815.997 | Z27: Máx. | AA27: =+(T27*$AG$10)+T27 -> 9872.6646 | AB27: =+(U27*$AG$10)+U27 -> 12651.585 | AC27: =+(V27*$AG$10)+V27 -> 14230.477 | AD27: =+(W27*$AG$10)+W27 -> 17291.219 | AE27: =+(X27*$AG$10)+X27 -> 60010.517 | AF27: =MEDIAN(AA27:AE27) -> 14230.477
E28: Med | F28: 225049 | G28: 255799 | H28: 292276 | I28: 374500 | J28: 872186 | K28: 317190 | L28: Med | M28: =((F28*$AG$11)+F28)/$AG$12 -> 9649.4279 | N28: =((G28*$AG$11)+G28)/$AG$12 -> 10967.896 | O28: =((H28*$AG$11)+H28)/$AG$12 -> 12531.921 | P28: =((I28*$AG$11)+I28)/$AG$12 -> 16057.44 | Q28: =((J28*$AG$11)+J28)/$AG$12 -> 37396.727 | R28: =MEDIAN(M28:Q28) -> 12531.921 | S28: Med | T28: =((F28*$AG$9)+F28)/$AG$12 -> 8953.9737 | U28: =((G28*$AG$9)+G28)/$AG$12 -> 10177.417 | V28: =((H28*$AG$9)+H28)/$AG$12 -> 11628.719 | W28: =((I28*$AG$9)+I28)/$AG$12 -> 14900.147 | X28: =((J28*$AG$9)+J28)/$AG$12 -> 34701.467 | Y28: =MEDIAN(T28:X28) -> 11628.719 | Z28: Med | AA28: =+(T28*$AG$10)+T28 -> 9222.5929 | AB28: =+(U28*$AG$10)+U28 -> 10482.739 | AC28: =+(V28*$AG$10)+V28 -> 11977.581 | AD28: =+(W28*$AG$10)+W28 -> 15347.151 | AE28: =+(X28*$AG$10)+X28 -> 35742.511 | AF28: =MEDIAN(AA28:AE28) -> 11977.581
E29: Min. | F29: 171226 | G29: 199970 | H29: 239817 | I29: 278313 | J29: 422561 | K29: 246601 | L29: Min. | M29: =((F29*$AG$11)+F29)/$AG$12 -> 7341.6587 | N29: =((G29*$AG$11)+G29)/$AG$12 -> 8574.1154 | O29: =((H29*$AG$11)+H29)/$AG$12 -> 10282.636 | P29: =((I29*$AG$11)+I29)/$AG$12 -> 11933.229 | Q29: =((J29*$AG$11)+J29)/$AG$12 -> 18118.152 | R29: =MEDIAN(M29:Q29) -> 10282.636 | S29: Min. | T29: =((F29*$AG$9)+F29)/$AG$12 -> 6812.5301 | U29: =((G29*$AG$9)+G29)/$AG$12 -> 7956.1612 | V29: =((H29*$AG$9)+H29)/$AG$12 -> 9541.5447 | W29: =((I29*$AG$9)+I29)/$AG$12 -> 11073.176 | X29: =((J29*$AG$9)+J29)/$AG$12 -> 16812.339 | Y29: =MEDIAN(T29:X29) -> 9541.5447 | Z29: Min. | AA29: =+(T29*$AG$10)+T29 -> 7016.906 | AB29: =+(U29*$AG$10)+U29 -> 8194.846 | AC29: =+(V29*$AG$10)+V29 -> 9827.7911 | AD29: =+(W29*$AG$10)+W29 -> 11405.372 | AE29: =+(X29*$AG$10)+X29 -> 17316.709 | AF29: =MEDIAN(AA29:AE29) -> 9827.7911
A30: BG-3 | B30: Provide General Support | C30: Poa-A | D30: BG-3 Assistant | E30: Máx. | F30: 226380 | G30: 277573 | H30: 315816 | I30: 336152 | J30: 434735 | K30: 311689 | L30: Máx. | M30: =((F30*$AG$11)+F30)/$AG$12 -> 9706.4972 | N30: =((G30*$AG$11)+G30)/$AG$12 -> 11901.5 | O30: =((H30*$AG$11)+H30)/$AG$12 -> 13541.245 | P30: =((I30*$AG$11)+I30)/$AG$12 -> 14413.192 | Q30: =((J30*$AG$11)+J30)/$AG$12 -> 18640.136 | R30: =MEDIAN(M30:Q30) -> 13541.245 | S30: Máx. | T30: =((F30*$AG$9)+F30)/$AG$12 -> 9006.9299 | U30: =((G30*$AG$9)+G30)/$AG$12 -> 11043.734 | V30: =((H30*$AG$9)+H30)/$AG$12 -> 12565.3 | W30: =((I30*$AG$9)+I30)/$AG$12 -> 13374.404 | X30: =((J30*$AG$9)+J30)/$AG$12 -> 17296.703 | Y30: =MEDIAN(T30:X30) -> 12565.3 | Z30: Máx. | AA30: =+(T30*$AG$10)+T30 -> 9277.1377 | AB30: =+(U30*$AG$10)+U30 -> 11375.046 | AC30: =+(V30*$AG$10)+V30 -> 12942.259 | AD30: =+(W30*$AG$10)+W30 -> 13775.636 | AE30: =+(X30*$AG$10)+X30 -> 17815.604 | AF30: =MEDIAN(AA30:AE30) -> 12942.259
E31: Med | F31: 188650 | G31: 233163 | H31: 252000 | I31: 269046 | J31: 292276 | K31: 249516 | L31: Med | M31: =((F31*$AG$11)+F31)/$AG$12 -> 8088.7477 | N31: =((G31*$AG$11)+G31)/$AG$12 -> 9997.332 | O31: =((H31*$AG$11)+H31)/$AG$12 -> 10805.006 | P31: =((I31*$AG$11)+I31)/$AG$12 -> 11535.888 | Q31: =((J31*$AG$11)+J31)/$AG$12 -> 12531.921 | R31: =MEDIAN(M31:Q31) -> 10805.006 | S31: Med | T31: =((F31*$AG$9)+F31)/$AG$12 -> 7505.7749 | U31: =((G31*$AG$9)+G31)/$AG$12 -> 9276.8035 | V31: =((H31*$AG$9)+H31)/$AG$12 -> 10026.267 | W31: =((I31*$AG$9)+I31)/$AG$12 -> 10704.472 | X31: =((J31*$AG$9)+J31)/$AG$12 -> 11628.719 | Y31: =MEDIAN(T31:X31) -> 10026.267 | Z31: Med | AA31: =+(T31*$AG$10)+T31 -> 7730.9481 | AB31: =+(U31*$AG$10)+U31 -> 9555.1076 | AC31: =+(V31*$AG$10)+V31 -> 10327.055 | AD31: =+(W31*$AG$10)+W31 -> 11025.607 | AE31: =+(X31*$AG$10)+X31 -> 11977.581 | AF31: =MEDIAN(AA31:AE31) -> 10327.055
E32: Min. | F32: 144912 | G32: 164853 | H32: 179972 | I32: 196287 | J32: 252000 | K32: 187343 | L32: Min. | M32: =((F32*$AG$11)+F32)/$AG$12 -> 6213.3931 | N32: =((G32*$AG$11)+G32)/$AG$12 -> 7068.4035 | O32: =((H32*$AG$11)+H32)/$AG$12 -> 7716.661 | P32: =((I32*$AG$11)+I32)/$AG$12 -> 8416.1994 | Q32: =((J32*$AG$11)+J32)/$AG$12 -> 10805.006 | R32: =MEDIAN(M32:Q32) -> 7716.661 | S32: Min. | T32: =((F32*$AG$9)+F32)/$AG$12 -> 5765.581 | U32: =((G32*$AG$9)+G32)/$AG$12 -> 6558.969 | V32: =((H32*$AG$9)+H32)/$AG$12 -> 7160.5053 | W32: =((I32*$AG$9)+I32)/$AG$12 -> 7809.6265 | X32: =((J32*$AG$9)+J32)/$AG$12 -> 10026.267 | Y32: =MEDIAN(T32:X32) -> 7160.5053 | Z32: Min. | AA32: =+(T32*$AG$10)+T32 -> 5938.5484 | AB32: =+(U32*$AG$10)+U32 -> 6755.7381 | AC32: =+(V32*$AG$10)+V32 -> 7375.3204 | AD32: =+(W32*$AG$10)+W32 -> 8043.9153 | AE32: =+(X32*$AG$10)+X32 -> 10327.055 | AF32: =MEDIAN(AA32:AE32) -> 7375.3204
A33: BG-2 | B33: Provide Mechanical Support | D33: BG-2 Driver | E33: Máx. | F33: 175545 | G33: 221689 | H33: 261611 | I33: 297573 | J33: 395220 | K33: 270752 | L33: Máx. | M33: =((F33*$AG$11)+F33)/$AG$12 -> 7526.8445 | N33: =((G33*$AG$11)+G33)/$AG$12 -> 9505.3612 | O33: =((H33*$AG$11)+H33)/$AG$12 -> 11217.097 | P33: =((I33*$AG$11)+I33)/$AG$12 -> 12759.04 | Q33: =((J33*$AG$11)+J33)/$AG$12 -> 16945.851 | R33: =MEDIAN(M33:Q33) -> 11217.097 | S33: Máx. | T33: =((F33*$AG$9)+F33)/$AG$12 -> 6984.3692 | U33: =((G33*$AG$9)+G33)/$AG$12 -> 8820.2901 | V33: =((H33*$AG$9)+H33)/$AG$12 -> 10408.658 | W33: =((I33*$AG$9)+I33)/$AG$12 -> 11839.47 | X33: =((J33*$AG$9)+J33)/$AG$12 -> 15724.529 | Y33: =MEDIAN(T33:X33) -> 10408.658 | Z33: Máx. | AA33: =+(T33*$AG$10)+T33 -> 7193.9003 | AB33: =+(U33*$AG$10)+U33 -> 9084.8988 | AC33: =+(V33*$AG$10)+V33 -> 10720.917 | AD33: =+(W33*$AG$10)+W33 -> 12194.654 | AE33: =+(X33*$AG$10)+X33 -> 16196.265 | AF33: =MEDIAN(AA33:AE33) -> 10720.917
E34: Med | F34: 173475 | G34: 189000 | H34: 220575 | I34: 263480 | J34: 317039 | K34: 229338 | L34: Med | M34: =((F34*$AG$11)+F34)/$AG$12 -> 7438.0891 | N34: =((G34*$AG$11)+G34)/$AG$12 -> 8103.7546 | O34: =((H34*$AG$11)+H34)/$AG$12 -> 9457.5962 | P34: =((I34*$AG$11)+I34)/$AG$12 -> 11297.234 | Q34: =((J34*$AG$11)+J34)/$AG$12 -> 13593.684 | R34: =MEDIAN(M34:Q34) -> 9457.5962 | S34: Med | T34: =((F34*$AG$9)+F34)/$AG$12 -> 6902.0106 | U34: =((G34*$AG$9)+G34)/$AG$12 -> 7519.7002 | V34: =((H34*$AG$9)+H34)/$AG$12 -> 8775.9676 | W34: =((I34*$AG$9)+I34)/$AG$12 -> 10483.019 | X34: =((J34*$AG$9)+J34)/$AG$12 -> 12613.959 | Y34: =MEDIAN(T34:X34) -> 8775.9676 | Z34: Med | AA34: =+(T34*$AG$10)+T34 -> 7109.0709 | AB34: =+(U34*$AG$10)+U34 -> 7745.2913 | AC34: =+(V34*$AG$10)+V34 -> 9039.2467 | AD34: =+(W34*$AG$10)+W34 -> 10797.51 | AE34: =+(X34*$AG$10)+X34 -> 12992.378 | AF34: =MEDIAN(AA34:AE34) -> 9039.2467
E35: Min. | F35: 131740 | G35: 168473 | H35: 171405 | I35: 189000 | J35: 276180 | K35: 187923 | L35: Min. | M35: =((F35*$AG$11)+F35)/$AG$12 -> 5648.6171 | N35: =((G35*$AG$11)+G35)/$AG$12 -> 7223.6183 | O35: =((H35*$AG$11)+H35)/$AG$12 -> 7349.3337 | P35: =((I35*$AG$11)+I35)/$AG$12 -> 8103.7546 | Q35: =((J35*$AG$11)+J35)/$AG$12 -> 11841.772 | R35: =MEDIAN(M35:Q35) -> 7349.3337 | S35: Min. | T35: =((F35*$AG$9)+F35)/$AG$12 -> 5241.5096 | U35: =((G35*$AG$9)+G35)/$AG$12 -> 6702.9971 | V35: =((H35*$AG$9)+H35)/$AG$12 -> 6819.652 | W35: =((I35*$AG$9)+I35)/$AG$12 -> 7519.7002 | X35: =((J35*$AG$9)+J35)/$AG$12 -> 10988.311 | Y35: =MEDIAN(T35:X35) -> 6819.652 | Z35: Min. | AA35: =+(T35*$AG$10)+T35 -> 5398.7549 | AB35: =+(U35*$AG$10)+U35 -> 6904.0871 | AC35: =+(V35*$AG$10)+V35 -> 7024.2415 | AD35: =+(W35*$AG$10)+W35 -> 7745.2913 | AE35: =+(X35*$AG$10)+X35 -> 11317.961 | AF35: =MEDIAN(AA35:AE35) -> 7024.2415
A36: BG-1 | B36: Provide Physical Support | D36: BG-1 Maintenance | E36: Máx. | F36: 173575 | G36: 206825 | H36: 217605 | I36: 254296 | J36: 315816 | K36: 225493 | L36: Máx. | M36: =((F36*$AG$11)+F36)/$AG$12 -> 7442.3768 | N36: =((G36*$AG$11)+G36)/$AG$12 -> 8868.0373 | O36: =((H36*$AG$11)+H36)/$AG$12 -> 9330.2515 | P36: =((I36*$AG$11)+I36)/$AG$12 -> 10903.452 | Q36: =((J36*$AG$11)+J36)/$AG$12 -> 13541.245 | R36: =MEDIAN(M36:Q36) -> 9330.2515 | S36: Máx. | T36: =((F36*$AG$9)+F36)/$AG$12 -> 6905.9893 | U36: =((G36*$AG$9)+G36)/$AG$12 -> 8228.8995 | V36: =((H36*$AG$9)+H36)/$AG$12 -> 8657.8009 | W36: =((I36*$AG$9)+I36)/$AG$12 -> 10117.617 | X36: =((J36*$AG$9)+J36)/$AG$12 -> 12565.3 | Y36: =MEDIAN(T36:X36) -> 8657.8009 | Z36: Máx. | AA36: =+(T36*$AG$10)+T36 -> 7113.1689 | AB36: =+(U36*$AG$10)+U36 -> 8475.7665 | AC36: =+(V36*$AG$10)+V36 -> 8917.5349 | AD36: =+(W36*$AG$10)+W36 -> 10421.146 | AE36: =+(X36*$AG$10)+X36 -> 12942.259 | AF36: =MEDIAN(AA36:AE36) -> 8917.5349
E37: Med | F37: 161627 | G37: 179964 | H37: 188417 | I37: 213568 | J37: 255421 | K37: 198189 | L37: Med | M37: =((F37*$AG$11)+F37)/$AG$12 -> 6930.0823 | N37: =((G37*$AG$11)+G37)/$AG$12 -> 7716.318 | O37: =((H37*$AG$11)+H37)/$AG$12 -> 8078.7573 | P37: =((I37*$AG$11)+I37)/$AG$12 -> 9157.157 | Q37: =((J37*$AG$11)+J37)/$AG$12 -> 10951.688 | R37: =MEDIAN(M37:Q37) -> 8078.7573 | S37: Med | T37: =((F37*$AG$9)+F37)/$AG$12 -> 6430.6169 | U37: =((G37*$AG$9)+G37)/$AG$12 -> 7160.187 | V37: =((H37*$AG$9)+H37)/$AG$12 -> 7496.5046 | W37: =((I37*$AG$9)+I37)/$AG$12 -> 8497.1817 | X37: =((J37*$AG$9)+J37)/$AG$12 -> 10162.378 | Y37: =MEDIAN(T37:X37) -> 7496.5046 | Z37: Med | AA37: =+(T37*$AG$10)+T37 -> 6623.5354 | AB37: =+(U37*$AG$10)+U37 -> 7374.9926 | AC37: =+(V37*$AG$10)+V37 -> 7721.3997 | AD37: =+(W37*$AG$10)+W37 -> 8752.0972 | AE37: =+(X37*$AG$10)+X37 -> 10467.249 | AF37: =MEDIAN(AA37:AE37) -> 7721.3997
E38: Min. | F38: 129756 | G38: 146194 | H38: 163714 | I38: 186021 | J38: 249240 | K38: 170886 | L38: Min. | M38: =((F38*$AG$11)+F38)/$AG$12 -> 5563.5491 | N38: =((G38*$AG$11)+G38)/$AG$12 -> 6268.3614 | O38: =((H38*$AG$11)+H38)/$AG$12 -> 7019.5666 | P38: =((I38*$AG$11)+I38)/$AG$12 -> 7976.024 | Q38: =((J38*$AG$11)+J38)/$AG$12 -> 10686.666 | R38: =MEDIAN(M38:Q38) -> 7019.5666 | S38: Min. | T38: =((F38*$AG$9)+F38)/$AG$12 -> 5162.5726 | U38: =((G38*$AG$9)+G38)/$AG$12 -> 5816.5876 | V38: =((H38*$AG$9)+H38)/$AG$12 -> 6513.6519 | W38: =((I38*$AG$9)+I38)/$AG$12 -> 7401.1754 | X38: =((J38*$AG$9)+J38)/$AG$12 -> 9916.4555 | Y38: =MEDIAN(T38:X38) -> 6513.6519 | Z38: Min. | AA38: =+(T38*$AG$10)+T38 -> 5317.4498 | AB38: =+(U38*$AG$10)+U38 -> 5991.0852 | AC38: =+(V38*$AG$10)+V38 -> 6709.0614 | AD38: =+(W38*$AG$10)+W38 -> 7623.2107 | AE38: =+(X38*$AG$10)+X38 -> 10213.949 | AF38: =MEDIAN(AA38:AE38) -> 6709.0614
A40: remuneración total (salario base + bonificaciones y asignaciones fijas en efectivo + pagos variables/basados en el rendimiento + prestaciones en

Sheet ONGLocal
B1: Role | C1: Titles | D1: Entry | F1: Mid | H1: Top
A2: 1 | B2: Manual Staff | C2: Gardener; Cook; Office Maintenance; Security Guard | D2: 10891 | E2: =(D2/TRM!$I$9)*12 -> 5048.3622 | F2: 14718 | G2: =(F2/TRM!$I$9)*12 -> 6822.3115 | H2: 18545 | I2: =(H2/TRM!$I$9)*12 -> 8596.2608 | K2: =+E2/G2 -> 0.73997826 | L2: =+G2/I2 -> 0.7936371
A3: 2 | B3: Drivers | C3: Driver | D3: 13070 | E3: =(D3/TRM!$I$9)*12 -> 6058.4054 | F3: 17662 | G3: =(F3/TRM!$I$9)*12 -> 8186.9592 | H3: 22254 | I3: =(H3/TRM!$I$9)*12 -> 10315.513
A4: 3 | B4: Office Support | C4: Receptionist; Clerk | D4: 15684 | E4: =(D4/TRM!$I$9)*12 -> 7270.0865 | F4: 21195 | G4: =(F4/TRM!$I$9)*12 -> 9824.6292 | H4: 26705 | I4: =(H4/TRM!$I$9)*12 -> 12378.708
A5: 4 | B5: General administrative support; process basic transactions | C5: Administrative Assistant, Warehouse Keeper; Procurement Assistant, Finance Assistant | D5: 18821 | E5: =(D5/TRM!$I$9)*12 -> 8724.1965 | F5: 25434 | G5: =(F5/TRM!$I$9)*12 -> 11789.555 | H5: 32047 | I5: =(H5/TRM!$I$9)*12 -> 14854.913
A6: 5 | B6: Specialized process support; process more advanced transactions | C6: Administrative Officer, Fleet Officer, Human Resources Assistant | D6: 22585 | E6: =(D6/TRM!$I$9)*12 -> 10468.943 | F6: 30521 | G6: =(F6/TRM!$I$9)*12 -> 14147.559 | H6: 38456 | I6: =(H6/TRM!$I$9)*12 -> 17825.711
A7: 6 | B7: Comprehensive process support; consistent quality across transactions involving multiple processes | C7: Fleet Manager; Warehouse Officer; Transportation Officer; Logistics MIS Officer; Supply Chain Monitoring Officer; Procurement Officer | D7: 27102 | E7: =(D7/TRM!$I$9)*12 -> 12562.732 | F7: 36625 | G7: =(F7/TRM!$I$9)*12 -> 16976.978 | H7: 46147 | I7: =(H7/TRM!$I$9)*12 -> 21390.76
A8: 7 | B8: Advanced support; oversee & integrate related transactions | C8: Project Officer, Technical Associate , Administrative Manager, Logistics Officer, Human Resources Officer, Communications Officer | D8: 33878 | E8: =(D8/TRM!$I$9)*12 -> 15703.646 | F8: 45781 | G8: =(F8/TRM!$I$9)*12 -> 21221.106 | H8: 57684 | I8: =(H8/TRM!$I$9)*12 -> 26738.566
A9: 8 | B9: Management of a key function or projects | C9: Project Officer Sr, Warehouse Manager; Procurement Manager, Finance Officer Sr; Project/Grant Accountant, Communications Manager | D9: 42347 | E9: =(D9/TRM!$I$9)*12 -> 19629.326 | F9: 57226 | G9: =(F9/TRM!$I$9)*12 -> 26526.267 | H9: 72105 | I9: =(H9/TRM!$I$9)*12 -> 33423.208
A10: 9 | B10: Comprehensive management of a department or program; comprehensive technical advice | C10: Program Manager I; Project Manager,Technical Advisor I, Operations Manager; Regional Safeguarding Officer, Logistics Manager, Deputy Finance Manager, Human Resources Manager;Risk and Compliance Manager | D10: 52934 | E10: =(D10/TRM!$I$9)*12 -> 24536.774 | F10: 71533 | G10: =(F10/TRM!$I$9)*12 -> 33158.066 | H10: 90132 | I10: =(H10/TRM!$I$9)*12 -> 41779.357
A11: 10 | B11: Complex management & complex technical advice; adapt programs/policies | C11: Technical Advisor II, Deputy Chief of Party I, Supply Chain Manager; Regional Manager, Finance Manager | D11: 66168 | E11: =(D11/TRM!$I$9)*12 -> 30671.199 | F11: 89417 | G11: =(F11/TRM!$I$9)*12 -> 41447.93 | H11: 112665 | I11: =(H11/TRM!$I$9)*12 -> 52224.197
A12: 11 | B12: Leadership & high level management of programming; innovate, design new processes | C12: Chief of Party I; Deputy Chief of Party II, Head of Operations | D12: 86019 | E12: =(D12/TRM!$I$9)*12 -> 39872.837 | F12: 116242 | G12: =(F12/TRM!$I$9)*12 -> 53882.262 | H12: 146465 | I12: =(H12/TRM!$I$9)*12 -> 67891.687
A13: 12 | B13: Overall country leadership; integrate diverse specializations into a robust program | C13: Chief of Party II | D13: 111825 | E13: =(D13/TRM!$I$9)*12 -> 51834.827 | F13: 151114 | G13: =(F13/TRM!$I$9)*12 -> 70046.663 | H13: 190404 | I13: =(H13/TRM!$I$9)*12 -> 88258.962

Sheet World Salaries
C1: Entry | E1: Mid | H1: Top
A2: Maintenance | B2: I | C2: =+(50580+41480)/2 -> 46030 | D2: =(C2/TRM!$I$9) -> 1778.0439 | E2: =+(106780+94800)/2 -> 100790 | F2: =+E2/12 -> 8399.1667 | G2: =(E2/TRM!$I$9) -> 3893.3096 | H2: =+(169000+150000)/2 -> 159500 | I2: =(H2/TRM!$I$9) -> 6161.1557
A3: Driver | B3: II | C3: 53120 | D3: =(C3/TRM!$I$9) -> 2051.9159 | E3: 103580 | F3: =+E3/12 -> 8631.6667 | G3: =(E3/TRM!$I$9) -> 4001.0816 | H3: 163800 | I3: =(H3/TRM!$I$9) -> 6327.2559
A4: Assistant | B4: III | C4: =+(76570+91560)/2 -> 84065 | D4: =(C4/TRM!$I$9) -> 3247.2574 | E4: =+(163800+196800)/2 -> 180300 | F4: =+E4/12 -> 15025 | G4: =(E4/TRM!$I$9) -> 6964.6168 | H4: =+(263200+308300)/2 -> 285750 | I4: =(H4/TRM!$I$9) -> 11037.933
A5: Officer/Technical Officer | B5: I | C5: =+(87060+95760)/2 -> 91410 | D5: =(C5/TRM!$I$9) -> 3530.9796 | E5: =+(180300+205700)/2 -> 193000 | F5: =+E5/12 -> 16083.333 | G5: =(E5/TRM!$I$9) -> 7455.1916 | H5: =+(279400+325600)/2 -> 302500 | I5: =(H5/TRM!$I$9) -> 11684.951
A6: Sr. Officer/Sr. Technical Officer | B6: II | C6: =(99220+109720+110500)/3 -> 106480 | D6: =(C6/TRM!$I$9) -> 4113.1026 | E6: =+(207800+210500+214000)/3 -> 210766.67 | F6: =+E6/12 -> 17563.889 | G6: =(E6/TRM!$I$9) -> 8141.4813 | H6: =+(320500+325600+327300)/3 -> 324466.67 | I6: =(H6/TRM!$I$9) -> 12533.478
A7: Coordinator | B7: I | C7: =+(143200+117860)/2 -> 130530 | D7: =(C6/TRM!$I$9) -> 4113.1026 | E7: =+(311700+243000)/2 -> 277350 | F7: =+E7/12 -> 23112.5 | G7: =(E6/TRM!$I$9) -> 8141.4813 | H7: =+(496100+378800)/2 -> 437450 | I7: =(H7/TRM!$I$9) -> 16897.79
A8: Specialist | B8: II | C8: =+(167100+136200+150000)/3 -> 151100 | D8: =(C8/TRM!$I$9) -> 5836.6811 | E8: =+(325800+275800+283700)/3 -> 295100 | F8: =+E8/12 -> 24591.667 | G8: =(E8/TRM!$I$9) -> 11399.104 | H8: =+(496100+430000+433800)/3 -> 453300 | I8: =(H8/TRM!$I$9) -> 17510.043
A9: Sr. Specialist | B9: III | C9: 212500 | D9: =(C9/TRM!$I$9) -> 8208.4363 | E9: 464400 | F9: =+E9/12 -> 38700 | G9: =(E9/TRM!$I$9) -> 17938.813 | H9: 735200 | I9: =(H9/TRM!$I$9) -> 28399.258
A10: Manager | B10: I | C10: =(294700+272800)/2 -> 283750 | D10: =(C10/TRM!$I$9) -> 10960.677 | E10: =(643400+590200)/2 -> 616800 | F10: =+E10/12 -> 51400 | G10: =(E10/TRM!$I$9) -> 23825.711 | H10: =(1021800+939000)/2 -> 980400 | I10: =(H10/TRM!$I$9) -> 37870.828
A11: Director | B11: II | C11: =361600 -> 361600 | D11: =(C11/TRM!$I$9) -> 13967.862 | E11: =693100 -> 693100 | F11: =+E11/12 -> 57758.333 | G11: =(E11/TRM!$I$9) -> 26773.022 | H11: =1057700 -> 1057700 | I11: =(H11/TRM!$I$9) -> 40856.768

Sheet TRM
I9: 25.888

Sheet POA Compensation Org. Reference
J1: 2019 Baseline * % increase: | L1: =1.05*1*1.03*1*1.03 -> 1.113945
S2: Analysis assuming 5% increase each year
C3: Partners of the Americas Salary Ranges for HONDURAS | T3: Years in | W3: Years in | Y3: NOTES:
C4: Job Positions & Bands | G4: Experience | H4: Minimum USD | I4: Minimum HNL | J4: Midpoint USD | K4: Midpoint HNL | L4: Maximum USD | M4: Maximum HNL | AX4: 37440
C5: Core competencies | E5: Level | F5: Yrs Exp | T5: Position | W5: Position | Y5: - Management Skills: Project mgmt | AX5: =AX4/H6 -> 5.0938776
B6: Officer | C6: Maintenance Driver Assistant | D6: Grade A | E6: I | F6: 0 | G6: Minimum: no degree; no experience; no technical skills. Maximum: Grad school started;or 0-6 month of experience; with some technical skills. | H6: 7350 | I6: =H6*TRM!$I$9 -> 190276.8 | J6: 10240 | K6: =J6*TRM!$I$9 -> 265093.12 | L6: 11920 | M6: =L6*TRM!$I$9 -> 308584.96 | O6: =(L10-H6)/6 -> 1001.6667 | S6: =H6*1.05 -> 7717.5 | T6: 1 | V6: =S11*1.05 -> 10342.188 | W6: 7 | Y6: - Leadership Skills: Project mgmt and personnel mgmt
B7: ·Accountant Analyst – Field Office ·Administrative Officer ·Communications Officer ·Communication & Outreach Officer ·Membership Officer ·Program Officer, CPU ·Program Officer, EGC ·Program Officer, EDH | C7: Provide physical and mechanic support Core competencies required: -Ability to write effectively and think critically. -Ability to work in a team as well as independently and demonstrate consistency | H7: No degree. No experience. No technical skills. | S7: =S6*1.05 -> 8103.375 | T7: 2 | V7: =V6*1.05 -> 10859.298 | W7: 8 | Y7: - I added calculations to show the % increase between each point; I will hide these before sharing | AY7: ,00
E8: II | F8: 2-4 | G8: Minimum: Level I + min 2 years of experience, with some technical skills. | H8: 7800 | I8: =H8*TRM!$I$9 -> 201926.4 | J8: 10700 | K8: =J8*TRM!$I$9 -> 277001.6 | L8: 12250 | M8: =L8*TRM!$I$9 -> 317128 | S8: =S7*1.05 -> 8508.5438 | T8: 3 | Y8: - Note that these % increases are higher than the max 5% estimated increase each year
J9: Bachelors degree + least 2 years of experience. Some technical skills or min 2 years in level I | Q9: =J8/H8 -> 1.3717949 | S9: =S8*1.05 -> 8933.9709 | T9: 4
E10: III | F10: 4-6 | G10: Minimum: 2 years of experience in Level II. | H10: 8350 | I10: =H10*TRM!$I$9 -> 216164.8 | J10: 11140 | K10: =J10*TRM!$I$9 -> 288392.32 | L10: 13360 | M10: =L10*TRM!$I$9 -> 345863.68 | O10: =J10+O6 -> 12141.667 | S10: =S9*1.05 -> 9380.6695 | T10: 5 | AY10: =55000/63000 -> 0.87301587
L11: Masters degree + least 3 years experience level II; some technical skills; preferred min bilingual. | Q11: =L10/J10 -> 1.1992819 | S11: =S10*1.05 -> 9849.703 | T11: 6 | AY11: =100-87 -> 13
B13: Senior Officer | C13: Officer/Technical Officer Sr. Officer/Sr. Technical Officer | D13: Grade B | E13: I | F13: 4 | G13: Minimum: 2 years of experience in Officer Level II, or equivalent; management skills demonstrated. | H13: 17820 | I13: =H13*TRM!$I$9 -> 461324.16 | J13: 22440 | K13: =J13*TRM!$I$9 -> 580926.72 | L13: 25520 | M13: =L13*TRM!$I$9 -> 660661.76 | O13: =(L15-H13)/4 -> 2420 | S13: =H13*1.05 -> 18711 | T13: 1 | V13: =S16*1.05 -> 22743.337 | W13: 5
B14: ·Senior Accountant ·Senior Program Officer, EDH ·Senior Program Officer, EGC ·Senior Program Officer, CPU | C14: Process basic transaction Execute intrincate transactions Core competencies: -Thorough understanding of federal award management (program SOs) -Ability to contribute high-quality subsections of donor/partner reports/proposals -Ability to competently contribute during donor/partner meetings -Ability to manage 1-2 interns | H14: 2 years of experience in Officer Level II, or equivalent; management skills demonstrated. | S14: =S13*1.05 -> 19646.55 | T14: 2 | V14: =V13*1.05 -> 23880.504 | W14: 6 | AY14: 58000 | BA14: =AY14/AY15 -> 0.92063492 | BB14: =100-92 -> 8
E15: II | F15: 4-7 | G15: Minimum: Masters degree preferred + at least 4 years of experience; 1 year as Sr Officer level I; technical skills required; leadership experience and language desired. Ability to competently serve as interim-Associate Director when necessary. | H15: 18830 | I15: =H15*TRM!$I$9 -> 487471.04 | J15: 23160 | K15: =J15*TRM!$I$9 -> 599566.08 | L15: 27500 | M15: =L15*TRM!$I$9 -> 711920 | O15: =J15+O13 -> 25580 | Q15: =J15/H15 -> 1.2299522 | S15: =S14*1.05 -> 20628.877 | T15: 3 | V15: =V14*1.05 -> 25074.53 | W15: 7 | AY15: 63000
H16: =H15/L13 -> 0.73785266 | J16: =J15/H15 -> 1.2299522 | L16: Masters degree preferred; 7+ years experience; 3 years as Sr Officer level I; technical skills required and leadership knowledge desired; preferred min bilingual. | Q16: =L15/J15 -> 1.1873921 | S16: =S15*1.05 -> 21660.321 | T16: 4
B18: Associate Director | C18: Coordinator Specialist Sr. Specialist | D18: Grade C | E18: I | F18: 6 | G18: Minimum: Bachelors degree. 6+ years experience; 2+ years as Sr Officer Level I or II; technical skills and leadership experience required; preferred min bilingual. | H18: 22880 | I18: =H18*TRM!$I$9 -> 592317.44 | J18: =27170 -> 27170 | K18: =J18*TRM!$I$9 -> 703376.96 | L18: 32180 | M18: =L18*TRM!$I$9 -> 833075.84 | O18: =(L22-H18)/6 -> 3836.6667 | S18: =H18*1.05 -> 24024 | T18: 1 | V18: =S23*1.05 -> 32194.458 | W18: 7 | Y18: - Note that AD level and above are part of the SMT (Senior Management Team)
B19: ·Associate Director, EDH - F2F ·Associate Director, EDH - AVOP ·Associate Director, EGC ·Associate Director, BD ·Associate Director, Membership ·Executive Administrative Officer | C19: Ensure process integrity Manage integrated processes In addition to grade B core competencies: -Ability to write high-quality full sections of proposals/reports -Ability to deliver high-quality, detail-oriented, and professional donor/partner reports -Ability to competently lead a donor/partner meeting -Ability to manage 2-3 staff and/or interns | H19: Bachelors degree. 6+ years experience; 2+ years as Sr Officer Level I or II; technical skills and leadership experience required; preferred min bilingual. | J19: =J18/H18 -> 1.1875 | L19: =L18/J18 -> 1.1843946 | S19: =S18*1.05 -> 25225.2 | T19: 2 | V19: =V18*1.05 -> 33804.181 | W19: 8
E20: II | F20: 9 | G20: Minimum: 3 additional years experience as AD Level I, or equivalent; international experience desired; or Level I + Masters degree; international experience desired. | H20: =27630 -> 27630 | I20: =H20*TRM!$I$9 -> 715285.44 | J20: 33190 | K20: =J20*TRM!$I$9 -> 859222.72 | L20: =39450 -> 39450 | M20: =L20*TRM!$I$9 -> 1021281.6 | S20: =S19*1.05 -> 26486.46 | T20: 3
H21: =H20/L18 -> 0.85860783 | J21: 4 yrs experience as manger/specialist level I; technical skills and leadership experience required; language required; international experience desired. | L21: =L20/J20 -> 1.188611 | Q21: =J20/H20 -> 1.2012305 | S21: =S20*1.05 -> 27810.783 | T21: 4
E22: III | F22: 12 | G22: Minimum: Level II + Masters degree + 3 additional years experience as AD Level II; international experience desired. Ability to competently serve as interim-Director when necessary. | H22: =32830 -> 32830 | I22: =H22*TRM!$I$9 -> 849903.04 | J22: 37320 | K22: =J22*TRM!$I$9 -> 966140.16 | L22: 45900 | M22: =L22*TRM!$I$9 -> 1188259.2 | O22: =J22+O18 -> 41156.667 | S22: =S21*1.05 -> 29201.322 | T22: 5
H23: =H22/L20 -> 0.83219265 | J23: =J22/H22 -> 1.1367652 | L23: Masters degree. 8+ years experience; 3 years as Manager or specialist Level II; international experience desired. | Q23: =L22/J22 -> 1.2299035 | S23: =S22*1.05 -> 30661.388 | T23: 6
B25: Director | C25: Manager Director Sr. Director | D25: Grade D | E25: I | F25: 8 | G25: Minimum: Masters degree and AD Level II or 3 years as AD Level I or equivalent; proven technical skills and leadership experience; 2nd language required; international experience desired. | H25: 39540 | I25: =H25*TRM!$I$9 -> 1023611.5 | J25: =48450 -> 48450 | K25: =J25*TRM!$I$9 -> 1254273.6 | L25: 57460 | M25: =L25*TRM!$I$9 -> 1487524.5 | O25: =(L29-H25)/6 -> 4550 | S25: =H25*1.05 -> 41517 | T25: 1 | V25: =S30*1.05 -> 55636.751 | W25: 7
B26: ·Director of 100,000 Strong ·Director of EGC ·Director, BD | C26: Analyze - Adapt In addition to Grade C core competencies: -Ability to lead a full proposal (design, strategy, delegation of duties, etc.) -Ability to ensure full programmatic and financial compliance of a federal award from startup through closeout -Ability to manage 3-5 staff, including remote supervision of field staff | H26: manager/specialist Level I + Masters degree and 2 years as manager or equivalent; 2nd language required; international experience desired. | J26: =J25/H25 -> 1.2253414 | L26: =L25/J25 -> 1.1859649 | S26: =S25*1.05 -> 43592.85 | T26: 2 | V26: =V25*1.05 -> 58418.588 | W26: 8
E27: II | F27: 10 | G27: Minimum: At least 2 years as Director Level I, or equivalent. | H27: =45890 -> 45890 | I27: =H27*TRM!$I$9 -> 1188000.3 | J27: 51240 | K27: =J27*TRM!$I$9 -> 1326501.1 | L27: =61720 -> 61720 | M27: =L27*TRM!$I$9 -> 1597807.4 | S27: =S26*1.05 -> 45772.493 | T27: 3
H28: =H27/L25 -> 0.79864253 | J28: At least 3 years as Director Level I & II. | L28: =L27/J27 -> 1.2045277 | Q28: =J27/H27 -> 1.1165831 | S28: =S27*1.05 -> 48061.117 | T28: 4
E29: III | F29: 12-14 | G29: Minimum: At least 2 years as Director Level II. Ability to competently serve as interim-Sr Director when necessary. | H29: =50130 -> 50130 | I29: =H29*TRM!$I$9 -> 1297765.4 | J29: =55700 -> 55700 | K29: =J29*TRM!$I$9 -> 1441961.6 | L29: 66840 | M29: =L29*TRM!$I$9 -> 1730353.9 | O29: =J29+O25 -> 60250 | S29: =S28*1.05 -> 50464.173 | T29: 5
H30: =H29/L27 -> 0.81221646 | J30: =J29/H29 -> 1.1111111 | L30: At least 4 years as Director Level II & III. | Q30: =L29/J29 -> 1.2 | S30: =S29*1.05 -> 52987.382 | T30: 6
B32: Director | C32: Deputy Chief of Party/Deputy Project Director Chief of Party/Project Director | D32: Grade E | E32: I | F32: 10 | G32: Minimum: At least 2 years as Director or equivalent; proven high confidence and decision - making; strong leader and manager | H32: 60000 | I32: =H32*TRM!$I$9 -> 1553280 | J32: =74000 -> 74000 | K32: =J32*TRM!$I$9 -> 1915712 | L32: 87000 | M32: =L32*TRM!$I$9 -> 2252256 | O32: =(L36-H32)/6 -> 10000 | S32: =H32*1.05 -> 63000 | T32: 1 | V32: =S37*1.05 -> 84426.025 | W32: 7
B33: ·Director of 100,000 Strong ·Director of EGC ·Director, BD | C33: In addition to Director competencies: -Ability to raise public and/or private funds -Ability to manage multiple federal awards -Ability to execute strategic and operational plans for the units - Ability to manage a full team (staff, interns, contractors), including remote supervision of field staff | H33: At least 2 years as Director; proven high confidence and decision-making; strong leader and manager. | J33: =J32/H32 -> 1.2333333 | L33: =L32/J32 -> 1.1756757 | S33: =S32*1.05 -> 66150 | T33: 2 | V33: =V32*1.05 -> 88647.327 | W33: 8
E34: II | F34: 12 | G34: Minimum: Dual or multiple Masters Degrees; at least 2 years as Sr. Director Level I; proven high confidence and decision-making; strong leader and manager. | H34: =80000 -> 80000 | I34: =H34*TRM!$I$9 -> 2071040 | J34: 95000 | K34: =J34*TRM!$I$9 -> 2459360 | L34: =113000 -> 113000 | M34: =L34*TRM!$I$9 -> 2925344 | S34: =S33*1.05 -> 69457.5 | T34: 3
H35: =H34/L32 -> 0.91954023 | J35: Dual or multiple Masters Degrees; at least 3 years as Sr. Director; proven high confidence and decision-making; strong leader and manager | L35: =L34/J34 -> 1.1894737 | Q35: =J34/H34 -> 1.1875 | S35: =S34*1.05 -> 72930.375 | T35: 4
E36: III | F36: 14 | G36: Minimum: PhD "preference"; at least 2 years as Sr. Director. Ability to competently serve as interim Vice - President when necesary. | H36: 100000 | I36: =H36*TRM!$I$9 -> 2588800 | J36: =117000 -> 117000 | K36: =J36*TRM!$I$9 -> 3028896 | L36: 120000 | M36: =L36*TRM!$I$9 -> 3106560 | O36: =J36+O32 -> 127000 | S36: =S35*1.05 -> 76576.894 | T36: 5
H37: =H36/L34 -> 0.88495575 | J37: =J36/H36 -> 1.17 | L37: PhD preferance required.14+ years of experience; at least 4 years as Sr. Director or equivalent_x000D_ | Q37: =L36/J36 -> 1.025641 | S37: =S36*1.05 -> 80405.738 | T37: 6
