Workbook

Sheet Listing
A1: Inventory & Equipment Listing Report
A3: Project Name or Admin Department:
A4: Grant Number (if applicable):
A5: Inventory as of: | C5: 45322
A6: # | B6: Photo | C6: Description of Inventory & Equipment | D6: Condition | E6: Brand | F6: Model | G6: Serial # | H6: Method of Acquisition | I6: Acquisition/ Purchase Date | J6: Purchase Price | K6: % Charged to Grant | L6: Amount Charged to Grant | M6: Current Price | N6: Useful Life in Days | O6: Current Price Charged to Grant | P6: Grant | Q6: Type of Equipment/ Supply | R6: Useful Life | S6: City & Physical Location | T6: Responsible Person | U6: Notes
A7: Equipment (over $5,000 USD)
A8: 1 | I8: 45047 | J8: 18000 | K8: 1 | L8: =IF(J8="","",(K8*J8)) -> 18000 | M8: =IF(IF(J8="","",(1-((_xlfn.DAYS($C$5,I8)))/N8)*L8)<0,0,(IF(J8="","",(1-((_xlfn.DAYS($C$5,I8)))/N8)*L8))) -> 15287.671 | N8: =IF(J8="", "", IF(R8=Sheet1!$B$13, 365, VLOOKUP(R8, Sheet1!$B$9:$C$18, 2, FALSE) * 365)) -> 1825 | O8: =IF(J8="","",(K8*M8)) -> 15287.671 | Q8: Vehicle | R8: =IF(Q8="","",(VLOOKUP(Q8,Sheet1!$A$9:$B$18,2))) -> 5 Years
A9: 2 | L9: =IF(J9="","",(K9*J9)) | M9: =IF(IF(J9="","",(1-((_xlfn.DAYS($C$5,I9)))/N9)*L9)<0,0,(IF(J9="","",(1-((_xlfn.DAYS($C$5,I9)))/N9)*L9))) | N9: =IF(J9="", "", IF(R9=Sheet1!$B$13, 365, VLOOKUP(R9, Sheet1!$B$9:$C$18, 2, FALSE) * 365)) | O9: =IF(J9="","",(K9*M9)) | R9: =IF(Q9="","",(VLOOKUP(Q9,Sheet1!$A$9:$B$18,2)))
A10: 3 | L10: =IF(J10="","",(K10*J10)) | M10: =IF(IF(J10="","",(1-((_xlfn.DAYS($C$5,I10)))/N10)*L10)<0,0,(IF(J10="","",(1-((_xlfn.DAYS($C$5,I10)))/N10)*L10))) | N10: =IF(J10="", "", IF(R10=Sheet1!$B$13, 365, VLOOKUP(R10, Sheet1!$B$9:$C$18, 2, FALSE) * 365)) | O10: =IF(J10="","",(K10*M10)) | R10: =IF(Q10="","",(VLOOKUP(Q10,Sheet1!$A$9:$B$18,2)))
A11: 4 | L11: =IF(J11="","",(K11*J11)) | M11: =IF(IF(J11="","",(1-((_xlfn.DAYS($C$5,I11)))/N11)*L11)<0,0,(IF(J11="","",(1-((_xlfn.DAYS($C$5,I11)))/N11)*L11))) | N11: =IF(J11="", "", IF(R11=Sheet1!$B$13, 365, VLOOKUP(R11, Sheet1!$B$9:$C$18, 2, FALSE) * 365)) | O11: =IF(J11="","",(K11*M11)) | R11: =IF(Q11="","",(VLOOKUP(Q11,Sheet1!$A$9:$B$18,2)))
A12: 5 | L12: =IF(J12="","",(K12*J12)) | M12: =IF(IF(J12="","",(1-((_xlfn.DAYS($C$5,I12)))/N12)*L12)<0,0,(IF(J12="","",(1-((_xlfn.DAYS($C$5,I12)))/N12)*L12))) | N12: =IF(J12="", "", IF(R12=Sheet1!$B$13, 365, VLOOKUP(R12, Sheet1!$B$9:$C$18, 2, FALSE) * 365)) | O12: =IF(J12="","",(K12*M12)) | R12: =IF(Q12="","",(VLOOKUP(Q12,Sheet1!$A$9:$B$18,2)))
A13: 6 | L13: =IF(J13="","",(K13*J13)) | M13: =IF(IF(J13="","",(1-((_xlfn.DAYS($C$5,I13)))/N13)*L13)<0,0,(IF(J13="","",(1-((_xlfn.DAYS($C$5,I13)))/N13)*L13))) | N13: =IF(J13="", "", IF(R13=Sheet1!$B$13, 365, VLOOKUP(R13, Sheet1!$B$9:$C$18, 2, FALSE) * 365)) | O13: =IF(J13="","",(K13*M13)) | R13: =IF(Q13="","",(VLOOKUP(Q13,Sheet1!$A$9:$B$18,2)))
A14: 7 | L14: =IF(J14="","",(K14*J14)) | M14: =IF(IF(J14="","",(1-((_xlfn.DAYS($C$5,I14)))/N14)*L14)<0,0,(IF(J14="","",(1-((_xlfn.DAYS($C$5,I14)))/N14)*L14))) | N14: =IF(J14="", "", IF(R14=Sheet1!$B$13, 365, VLOOKUP(R14, Sheet1!$B$9:$C$18, 2, FALSE) * 365)) | O14: =IF(J14="","",(K14*M14)) | R14: =IF(Q14="","",(VLOOKUP(Q14,Sheet1!$A$9:$B$18,2)))
A15: 8 | L15: =IF(J15="","",(K15*J15)) | M15: =IF(IF(J15="","",(1-((_xlfn.DAYS($C$5,I15)))/N15)*L15)<0,0,(IF(J15="","",(1-((_xlfn.DAYS($C$5,I15)))/N15)*L15))) | N15: =IF(J15="", "", IF(R15=Sheet1!$B$13, 365, VLOOKUP(R15, Sheet1!$B$9:$C$18, 2, FALSE) * 365)) | O15: =IF(J15="","",(K15*M15)) | R15: =IF(Q15="","",(VLOOKUP(Q15,Sheet1!$A$9:$B$18,2)))
A16: 9 | L16: =IF(J16="","",(K16*J16)) | M16: =IF(IF(J16="","",(1-((_xlfn.DAYS($C$5,I16)))/N16)*L16)<0,0,(IF(J16="","",(1-((_xlfn.DAYS($C$5,I16)))/N16)*L16))) | N16: =IF(J16="", "", IF(R16=Sheet1!$B$13, 365, VLOOKUP(R16, Sheet1!$B$9:$C$18, 2, FALSE) * 365)) | O16: =IF(J16="","",(K16*M16)) | R16: =IF(Q16="","",(VLOOKUP(Q16,Sheet1!$A$9:$B$18,2)))
A17: 10 | L17: =IF(J17="","",(K17*J17)) | M17: =IF(IF(J17="","",(1-((_xlfn.DAYS($C$5,I17)))/N17)*L17)<0,0,(IF(J17="","",(1-((_xlfn.DAYS($C$5,I17)))/N17)*L17))) | N17: =IF(J17="", "", IF(R17=Sheet1!$B$13, 365, VLOOKUP(R17, Sheet1!$B$9:$C$18, 2, FALSE) * 365)) | O17: =IF(J17="","",(K17*M17)) | R17: =IF(Q17="","",(VLOOKUP(Q17,Sheet1!$A$9:$B$18,2)))
A18: Inventory & Supplies (under $5,000 USD)
A19: 1 | I19: 45047 | J19: 150 | K19: 1 | L19: =IF(J19="","",(K19*J19)) -> 150 | M19: =IF(IF(J19="","",(1-((_xlfn.DAYS($C$5,I19)))/N19)*L19)<0,0,(IF(J19="","",(1-((_xlfn.DAYS($C$5,I19)))/N19)*L19))) -> 36.986301 | N19: =IF(J19="", "", IF(R19=Sheet1!$B$13, 365, VLOOKUP(R19, Sheet1!$B$9:$C$18, 2, FALSE) * 365)) -> 365 | O19: =IF(J19="","",(K19*M19)) -> 36.986301 | Q19: General Supplies | R19: =IF(Q19="","",(VLOOKUP(Q19,Sheet1!$A$9:$B$18,2))) -> 1 Year
A20: 2 | L20: =IF(J20="","",(K20*J20)) | M20: =IF(IF(J20="","",(1-((_xlfn.DAYS($C$5,I20)))/N20)*L20)<0,0,(IF(J20="","",(1-((_xlfn.DAYS($C$5,I20)))/N20)*L20))) | N20: =IF(J20="", "", IF(R20=Sheet1!$B$13, 365, VLOOKUP(R20, Sheet1!$B$9:$C$18, 2, FALSE) * 365)) | O20: =IF(J20="","",(K20*M20)) | R20: =IF(Q20="","",(VLOOKUP(Q20,Sheet1!$A$9:$B$18,2)))
A21: 3 | L21: =IF(J21="","",(K21*J21)) | M21: =IF(IF(J21="","",(1-((_xlfn.DAYS($C$5,I21)))/N21)*L21)<0,0,(IF(J21="","",(1-((_xlfn.DAYS($C$5,I21)))/N21)*L21))) | N21: =IF(J21="", "", IF(R21=Sheet1!$B$13, 365, VLOOKUP(R21, Sheet1!$B$9:$C$18, 2, FALSE) * 365)) | O21: =IF(J21="","",(K21*M21)) | R21: =IF(Q21="","",(VLOOKUP(Q21,Sheet1!$A$9:$B$18,2)))
A22: 4 | L22: =IF(J22="","",(K22*J22)) | M22: =IF(IF(J22="","",(1-((_xlfn.DAYS($C$5,I22)))/N22)*L22)<0,0,(IF(J22="","",(1-((_xlfn.DAYS($C$5,I22)))/N22)*L22))) | N22: =IF(J22="", "", IF(R22=Sheet1!$B$13, 365, VLOOKUP(R22, Sheet1!$B$9:$C$18, 2, FALSE) * 365)) | O22: =IF(J22="","",(K22*M22)) | R22: =IF(Q22="","",(VLOOKUP(Q22,Sheet1!$A$9:$B$18,2)))
A23: 5 | L23: =IF(J23="","",(K23*J23)) | M23: =IF(IF(J23="","",(1-((_xlfn.DAYS($C$5,I23)))/N23)*L23)<0,0,(IF(J23="","",(1-((_xlfn.DAYS($C$5,I23)))/N23)*L23))) | N23: =IF(J23="", "", IF(R23=Sheet1!$B$13, 365, VLOOKUP(R23, Sheet1!$B$9:$C$18, 2, FALSE) * 365)) | O23: =IF(J23="","",(K23*M23)) | R23: =IF(Q23="","",(VLOOKUP(Q23,Sheet1!$A$9:$B$18,2)))
A24: 6 | L24: =IF(J24="","",(K24*J24)) | M24: =IF(IF(J24="","",(1-((_xlfn.DAYS($C$5,I24)))/N24)*L24)<0,0,(IF(J24="","",(1-((_xlfn.DAYS($C$5,I24)))/N24)*L24))) | N24: =IF(J24="", "", IF(R24=Sheet1!$B$13, 365, VLOOKUP(R24, Sheet1!$B$9:$C$18, 2, FALSE) * 365)) | O24: =IF(J24="","",(K24*M24)) | R24: =IF(Q24="","",(VLOOKUP(Q24,Sheet1!$A$9:$B$18,2)))
A25: 7 | L25: =IF(J25="","",(K25*J25)) | M25: =IF(IF(J25="","",(1-((_xlfn.DAYS($C$5,I25)))/N25)*L25)<0,0,(IF(J25="","",(1-((_xlfn.DAYS($C$5,I25)))/N25)*L25))) | N25: =IF(J25="", "", IF(R25=Sheet1!$B$13, 365, VLOOKUP(R25, Sheet1!$B$9:$C$18, 2, FALSE) * 365)) | O25: =IF(J25="","",(K25*M25)) | R25: =IF(Q25="","",(VLOOKUP(Q25,Sheet1!$A$9:$B$18,2)))
A26: 8 | L26: =IF(J26="","",(K26*J26)) | M26: =IF(IF(J26="","",(1-((_xlfn.DAYS($C$5,I26)))/N26)*L26)<0,0,(IF(J26="","",(1-((_xlfn.DAYS($C$5,I26)))/N26)*L26))) | N26: =IF(J26="", "", IF(R26=Sheet1!$B$13, 365, VLOOKUP(R26, Sheet1!$B$9:$C$18, 2, FALSE) * 365)) | O26: =IF(J26="","",(K26*M26)) | R26: =IF(Q26="","",(VLOOKUP(Q26,Sheet1!$A$9:$B$18,2)))
A27: 9 | L27: =IF(J27="","",(K27*J27)) | M27: =IF(IF(J27="","",(1-((_xlfn.DAYS($C$5,I27)))/N27)*L27)<0,0,(IF(J27="","",(1-((_xlfn.DAYS($C$5,I27)))/N27)*L27))) | N27: =IF(J27="", "", IF(R27=Sheet1!$B$13, 365, VLOOKUP(R27, Sheet1!$B$9:$C$18, 2, FALSE) * 365)) | O27: =IF(J27="","",(K27*M27)) | R27: =IF(Q27="","",(VLOOKUP(Q27,Sheet1!$A$9:$B$18,2)))
A28: 10 | L28: =IF(J28="","",(K28*J28)) | M28: =IF(IF(J28="","",(1-((_xlfn.DAYS($C$5,I28)))/N28)*L28)<0,0,(IF(J28="","",(1-((_xlfn.DAYS($C$5,I28)))/N28)*L28))) | N28: =IF(J28="", "", IF(R28=Sheet1!$B$13, 365, VLOOKUP(R28, Sheet1!$B$9:$C$18, 2, FALSE) * 365)) | O28: =IF(J28="","",(K28*M28)) | R28: =IF(Q28="","",(VLOOKUP(Q28,Sheet1!$A$9:$B$18,2)))
A29: 11 | L29: =IF(J29="","",(K29*J29)) | M29: =IF(IF(J29="","",(1-((_xlfn.DAYS($C$5,I29)))/N29)*L29)<0,0,(IF(J29="","",(1-((_xlfn.DAYS($C$5,I29)))/N29)*L29))) | N29: =IF(J29="", "", IF(R29=Sheet1!$B$13, 365, VLOOKUP(R29, Sheet1!$B$9:$C$18, 2, FALSE) * 365)) | O29: =IF(J29="","",(K29*M29)) | R29: =IF(Q29="","",(VLOOKUP(Q29,Sheet1!$A$9:$B$18,2)))
A30: 12 | L30: =IF(J30="","",(K30*J30)) | M30: =IF(IF(J30="","",(1-((_xlfn.DAYS($C$5,I30)))/N30)*L30)<0,0,(IF(J30="","",(1-((_xlfn.DAYS($C$5,I30)))/N30)*L30))) | N30: =IF(J30="", "", IF(R30=Sheet1!$B$13, 365, VLOOKUP(R30, Sheet1!$B$9:$C$18, 2, FALSE) * 365)) | O30: =IF(J30="","",(K30*M30)) | R30: =IF(Q30="","",(VLOOKUP(Q30,Sheet1!$A$9:$B$18,2)))
A31: 13 | L31: =IF(J31="","",(K31*J31)) | M31: =IF(IF(J31="","",(1-((_xlfn.DAYS($C$5,I31)))/N31)*L31)<0,0,(IF(J31="","",(1-((_xlfn.DAYS($C$5,I31)))/N31)*L31))) | N31: =IF(J31="", "", IF(R31=Sheet1!$B$13, 365, VLOOKUP(R31, Sheet1!$B$9:$C$18, 2, FALSE) * 365)) | O31: =IF(J31="","",(K31*M31)) | R31: =IF(Q31="","",(VLOOKUP(Q31,Sheet1!$A$9:$B$18,2)))
... A48: 30 | L48: =IF(J48="","",(K48*J48)) | M48: =IF(IF(J48="","",(1-((_xlfn.DAYS($C$5,I48)))/N48)*L48)<0,0,(IF(J48="","",(1-((_xlfn.DAYS($C$5,I48)))/N48)*L48))) | N48: =IF(J48="", "", IF(R48=Sheet1!$B$13, 365, VLOOKUP(R48, Sheet1!$B$9:$C$18, 2, FALSE) * 365)) | O48: =IF(J48="","",(K48*M48)) | R48: =IF(Q48="","",(VLOOKUP(Q48,Sheet1!$A$9:$B$18,2)))
A49: Total | J49: =SUM(J8:J17,J20:J48) -> 18000 | L49: =SUM(L8:L17,L20:L48) -> 18000 | M49: =SUM(M8:M17,M20:M48) -> 15287.671 | O49: =SUM(O8:O17,O20:O48) -> 15287.671 | R49: =IF(Q49="","",(VLOOKUP(Q49,Sheet1!$A$9:$B$18,2)))
A52: Submitted by name:
A54: Signature: | D54: Date:
A58: Reviewed & Approved by name:
A60: Signature: | D60: Date:

Sheet Sheet1
A2: New
A3: Good
A4: Bad
A5: Damaged
A6: Lost
B8: ADS Method Compliant with GAAP
A9: Agricultural machinery and equipment | B9: 10 Years | C9: 10 | D9: https://www.irs.gov/publications/p946 | E9: https://www.irs.gov/publications/p946#en_US_2022_publink1000107772
A10: Audio/Visual Equipment | B10: 10 Years | C10: 10 | D10: https://smallbusiness.chron.com/accounting-gaap-long-depreciate-used-fixed-assets-73880.html
A11: Computer/Laptop Tablet/Information Systems | B11: 5 Years | C11: 5 | D11: https://smallbusiness.chron.com/accounting-gaap-long-depreciate-used-fixed-assets-73880.html | E11: https://www.henssler.com/how-small-businesses-write-off-equipment-purchases-2/ | F11: https://www.irs.gov/publications/p946#en_US_2022_publink1000107772
A12: Furniture and fixtures (such as desks, files, and safes) | B12: 10 Years | C12: 10 | D12: https://www.irs.gov/publications/p946 | E12: https://www.henssler.com/how-small-businesses-write-off-equipment-purchases-2/ | F12: https://www.irs.gov/publications/p946#en_US_2022_publink1000107772
A13: General Supplies | B13: 1 Year | C13: 1 | D13: https://www.henssler.com/how-small-businesses-write-off-equipment-purchases-2/ | E13: https://www.irs.gov/businesses/small-businesses-self-employed/tangible-property-final-regulations#:~:text=Section%20162%20of%20the%20Internal,supplies%2C%20repairs%2C%20and%20maintenance.
A14: Laboratory or Forensic Equipment | B14: 10 Years | C14: 10 | D14: https://www.irs.gov/irm/part1/irm_01-035-006
A15: Other Equipment ($5K+) | B15: 10 Years | C15: 10 | D15: https://smallbusiness.chron.com/accounting-gaap-long-depreciate-used-fixed-assets-73880.html | E15: https://www.irs.gov/irm/part1/irm_01-035-006 | F15: https://www.irs.gov/publications/p946#en_US_2022_publink1000107772
A16: Printer/Projector/Fax/Copier, etc. | B16: 6 Years | C16: 6 | D16: https://www.irs.gov/publications/p946 | E16: https://www.irs.gov/publications/p946#en_US_2022_publink1000107772
A17: Telecommunications/Phone | B17: 4 Years | C17: 4 | D17: https://www.ey.com/en_gl/tax-guides/worldwide-capital-and-fixed-assets-guideey-worldwide-capital-and-fixed-assets-guide-2023.pdf
A18: Vehicle | B18: 5 Years | C18: 5 | D18: https://www.irs.gov/irm/part1/irm_01-035-006 | E18: https://www.henssler.com/how-small-businesses-write-off-equipment-purchases-2/
A21: Purchased
A22: Donated
