Workbook

Sheet Instructions
B1: Partners of the Americas
B2: Interest Allocation Worksheet
B3: Disaggregating interest earned between CCC Cash Advances and Monetization Proceeds
B5: Step 1: CCC funds advance is received in the POA general operating bank account.
B7: Step 2: Funds received for award XXX, monetization sales proceeds and/or CCC cash advances, are transferred from the general operating bank account into bank interest-bearing account XXX.
B9: Step 3: Determine the total amount of funds required to cover the programmatic expenses to be paid.
B11: Step 4: Transfer the amount determined on step 3 from account XXX to operating bank account, from which payments are processed. This is designed to maximize the time porgram funds remain in the interest-bearing account, allowing them to earn interest until the funds are needed for disbursement. By transferring only the amount required at the time payments are made, the organization minimizes idle balances in the opertaing account while maintaining efficient cash management and compliance with program requirements.
B13: Step 5: Interest accrues and posts to XXX account monthly, per the bank statement.
B15: Step 6: The worksheet automatically allocates the monthly interest between CCC Advances and Monetization Proceeds, proportional to each source's AVERAGE DAILY BALANCE for the month (not just the ending balance).

Sheet Summary
A1: Cumulative Interest Allocation Summary
A2: One row per month, linked live to that month's Alloc tab. Add a new row each time you add a new month's tab pair.
A4: Month | B4: Total Interest Posted | C4: CCC Avg Daily Bal | D4: Monetization Avg Daily Bal | E4: CCC % | F4: Monetization % | G4: CCC Interest ($) | H4: Monetization Interest ($) | I4: Notes
A5: ='Alloc - Jan 2026'!B4 -> 46023 | B5: ='Alloc - Jan 2026'!B5 -> 279.68 | C5: ='Alloc - Jan 2026'!B13 -> 0 | D5: ='Alloc - Jan 2026'!B14 -> 174100.81 | E5: ='Alloc - Jan 2026'!B18 -> 0 | F5: ='Alloc - Jan 2026'!B19 -> 1 | G5: ='Alloc - Jan 2026'!B21 -> 0 | H5: ='Alloc - Jan 2026'!B22 -> 279.68 | I5: First month - opening balances = 0
A6: ='Alloc - Feb 2026'!B4 -> 46054 | B6: ='Alloc - Feb 2026'!B5 -> 2748.77 | C6: ='Alloc - Feb 2026'!B13 -> 0 | D6: ='Alloc - Feb 2026'!B14 -> 1079705 | E6: ='Alloc - Feb 2026'!B18 -> 0 | F6: ='Alloc - Feb 2026'!B19 -> 1 | G6: ='Alloc - Feb 2026'!B21 -> 0 | H6: ='Alloc - Feb 2026'!B22 -> 2748.77 | I6: Opening balances linked from March close
A7: ='Alloc - Mar 2026'!B4 -> 46082 | B7: ='Alloc - Mar 2026'!B5 -> 2987.86 | C7: ='Alloc - Mar 2026'!B13 -> 0 | D7: ='Alloc - Mar 2026'!B14 -> 1082453.8 | E7: ='Alloc - Mar 2026'!B18 -> 0 | F7: ='Alloc - Mar 2026'!B19 -> 1 | G7: ='Alloc - Mar 2026'!B21 -> 0 | H7: ='Alloc - Mar 2026'!B22 -> 2987.86
A8: ='Alloc - Apr 2026'!B4 -> 46113 | B8: ='Alloc - Apr 2026'!B5 -> 24716.64 | C8: ='Alloc - Apr 2026'!B13 -> 0 | D8: ='Alloc - Apr 2026'!B14 -> 9252904.4 | E8: ='Alloc - Apr 2026'!B18 -> 0 | F8: ='Alloc - Apr 2026'!B19 -> 1 | G8: ='Alloc - Apr 2026'!B21 -> 0 | H8: ='Alloc - Apr 2026'!B22 -> 24716.64
A9: ='Alloc - May 2026'!B4 -> 46143 | B9: ='Alloc - May 2026'!B5 -> 31244.79 | C9: ='Alloc - May 2026'!B13 -> 0 | D9: ='Alloc - May 2026'!B14 -> 11319463 | E9: ='Alloc - May 2026'!B18 -> 0 | F9: ='Alloc - May 2026'!B19 -> 1 | G9: ='Alloc - May 2026'!B21 -> 0 | H9: ='Alloc - May 2026'!B22 -> 31244.79
A10: ='Alloc - June 2026'!B4 -> 46174 | B10: ='Alloc - June 2026'!B5 -> 30319.77 | C10: ='Alloc - June 2026'!B13 -> 0 | D10: ='Alloc - June 2026'!B14 -> 11350490 | E10: ='Alloc - June 2026'!B18 -> 0 | F10: ='Alloc - June 2026'!B19 -> 1 | G10: ='Alloc - June 2026'!B21 -> 0 | H10: ='Alloc - June 2026'!B22 -> 30319.77
A12: Running Totals -> | G12: =SUM(G5:G11) -> 0 | H12: =SUM(H5:H11) -> 92297.51
A13: (Extend the SUM ranges above as you add monthly rows.)

Sheet Ledger - Jan 2026
A1: USDA602 Transaction Ledger - Mar 2026
A2: Enter every transaction affecting the interest-bearing account. Balances and days-held calculate automatically.
A4: Month Start Date | B4: 46023 | D4: Month End Date | E4: =EOMONTH(B4,0) -> 46053
A6: Date | B6: Transaction Description | C6: Source / Type | D6: Amount (+/-) | E6: CCC Portion ($) | F6: Monetization Portion ($) | G6: CCC Advance Balance | H6: Monetization Balance | I6: Total Balance | J6: Days Held | K6: Notes / Source Doc
A7: 46023 | B7: Beginning balance carried forward | C7: Other | E7: 0 | F7: 0 | G7: =E7 -> 0 | H7: =F7 -> 0 | I7: =G7+H7 -> 0 | J7: =A8-A7 -> 26 | K7: First month on this worksheet - opening balances = 0
A8: 46049 | B8: Commodity monetization sale proceeds deposited | C8: Monetization Deposit | D8: 1079425 | E8: 0 | F8: =D8 -> 1079425 | G8: =G7+E8 -> 0 | H8: =H7+F8 -> 1079425 | I8: =G8+H8 -> 1079425 | J8: =E4-A8+1 -> 5 | K8: Source: CCC advance letter, tranche #4
E9: 0 | K9: Source: monetization sale settlement stmt
B13: Check: Days Held should sum to total days in month -> | J13: =SUM(J7:J11) -> 31
B14: Days in month -> | J14: =E4-B4+1 -> 31

Sheet Alloc - Jan 2026
A1: Monthly Interest Allocation - Mar 2026
A2: Allocates the interest posted this month between CCC Advances and Monetization Proceeds, proportional to average daily balance.
A4: Bank Statement Month | B4: ='Ledger - Jan 2026'!B4 -> 46023
A5: Total Interest Posted This Month ($) | B5: 279.68 | D5: <- Enter from bank statement (blue input)
A7: Average Daily Balance Calculation
A8: CCC Advance - Sum(Balance x Days Held) | B8: =SUMPRODUCT('Ledger - Jan 2026'!G7:G11,'Ledger - Jan 2026'!J7:J11) -> 0
A9: Monetization - Sum(Balance x Days Held) | B9: =SUMPRODUCT('Ledger - Jan 2026'!H7:H11,'Ledger - Jan 2026'!J7:J11) -> 5397125
A10: Total - Sum(Balance x Days Held) | B10: =SUMPRODUCT('Ledger - Jan 2026'!I7:I11,'Ledger - Jan 2026'!J7:J11) -> 5397125
A11: Days in Month | B11: ='Ledger - Jan 2026'!E4-'Ledger - Jan 2026'!B4+1 -> 31
A13: CCC Advance - Average Daily Balance | B13: =B8/B11 -> 0
A14: Monetization - Average Daily Balance | B14: =B9/B11 -> 174100.81
A15: Total - Average Daily Balance | B15: =B13+B14 -> 174100.81
A17: Interest Allocation
A18: CCC Share of Average Daily Balance (%) | B18: =B13/B15 -> 0
A19: Monetization Share of Average Daily Balance (%) | B19: =B14/B15 -> 1
A21: CCC Advance - Interest Allocated ($) | B21: =$B$5*B18 -> 0
A22: Monetization - Interest Allocated ($) | B22: =$B$5*B19 -> 279.68
A23: Check: CCC + Monetization = Total Interest Posted | B23: =B21+B22-B5 -> 0
A25: Next Step
A26: Record the two amounts above as 'CCC Interest' and 'Monetization Interest' transactions in NEXT month's Ledger tab (dated the day the interest posted), then record the CCC remittance separately once wired to Treasury.
A28: Disposition Reminder
A29: CCC interest: remit to federal government via PMS, unless within the $500/year retention threshold across all federal awards (2 CFR 200.305). Monetization interest: generally added to program income per award terms - confirm with USDA602 Amendment.

Sheet Ledger - Feb 2026
A1: USDA602 Transaction Ledger - Feb 2026
A2: Enter every transaction affecting the interest-bearing account. Balances and days-held calculate automatically.
A4: Month Start Date | B4: 46054 | D4: Month End Date | E4: =EOMONTH(B4,0) -> 46081
A6: Date | B6: Transaction Description | C6: Source / Type | D6: Amount (+/-) | E6: CCC Portion ($) | F6: Monetization Portion ($) | G6: CCC Advance Balance | H6: Monetization Balance | I6: Total Balance | J6: Days Held | K6: Notes / Source Doc
A7: 46054 | B7: Beginning balance carried forward from March | C7: Other | E7: ='Ledger - Jan 2026'!G11 -> 0 | F7: ='Ledger - Jan 2026'!F8 -> 1079425 | G7: =E7 -> 0 | H7: =F7 -> 1079425 | I7: =G7+H7 -> 1079425 | J7: =A8-A7 -> 0 | K7: Linked to March closing balances - see formula
A8: 46054 | B8: Jan interest earned | C8: CCC Interest | D8: ='Alloc - Jan 2026'!B22 -> 279.68 | F8: 280 | G8: =G7+E8 -> 0 | H8: =H7+F8 -> 1079705 | I8: =G8+H8 -> 1079705 | J8: =E4-A8+1 -> 28 | K8: Linked to Alloc - Mar 2026 CCC interest allocation
K9: Linked to Alloc - Mar 2026 Monetization interest allocation
K10: Source: CCC advance letter, tranche #5
K11: Remitted per 2 CFR 200.305 - confirm PMS confirmation # on file
K12: Pro-rata draw based on prior day's ending balances
B14: Check: Days Held should sum to total days in month -> | J14: =SUM(J7:J12) -> 28
B15: Days in month -> | J15: =E4-B4+1 -> 28

Sheet Alloc - Feb 2026
A1: Monthly Interest Allocation - Feb 2026
A2: Allocates the interest posted this month between CCC Advances and Monetization Proceeds, proportional to average daily balance.
A4: Bank Statement Month | B4: ='Ledger - Feb 2026'!B4 -> 46054
A5: Total Interest Posted This Month ($) | B5: 2748.77 | D5: <- Enter from bank statement (blue input)
A7: Average Daily Balance Calculation
A8: CCC Advance - Sum(Balance x Days Held) | B8: =SUMPRODUCT('Ledger - Feb 2026'!G7:G12,'Ledger - Feb 2026'!J7:J12) -> 0
A9: Monetization - Sum(Balance x Days Held) | B9: =SUMPRODUCT('Ledger - Feb 2026'!H7:H12,'Ledger - Feb 2026'!J7:J12) -> 30231740
A10: Total - Sum(Balance x Days Held) | B10: =SUMPRODUCT('Ledger - Feb 2026'!I7:I12,'Ledger - Feb 2026'!J7:J12) -> 30231740
A11: Days in Month | B11: ='Ledger - Feb 2026'!E4-'Ledger - Feb 2026'!B4+1 -> 28
A13: CCC Advance - Average Daily Balance | B13: =B8/B11 -> 0
A14: Monetization - Average Daily Balance | B14: =B9/B11 -> 1079705
A15: Total - Average Daily Balance | B15: =B13+B14 -> 1079705
A17: Interest Allocation
A18: CCC Share of Average Daily Balance (%) | B18: =B13/B15 -> 0
A19: Monetization Share of Average Daily Balance (%) | B19: =B14/B15 -> 1
A21: CCC Advance - Interest Allocated ($) | B21: =$B$5*B18 -> 0
A22: Monetization - Interest Allocated ($) | B22: =$B$5*B19 -> 2748.77
A23: Check: CCC + Monetization = Total Interest Posted | B23: =B21+B22-B5 -> 0
A25: Next Step
A26: Record the two amounts above as 'CCC Interest' and 'Monetization Interest' transactions in NEXT month's Ledger tab (dated the day the interest posted), then record the CCC remittance separately once wired to Treasury.
A28: Disposition Reminder
A29: CCC interest: remit to federal government via PMS, unless within the $500/year retention threshold across all federal awards (2 CFR 200.305). Monetization interest: generally added to program income per award terms - confirm with USDA602 Amendment.

Sheet Ledger - Mar 2026
A1: USDA602 Transaction Ledger - Mar 2026
A2: Enter every transaction affecting the interest-bearing account. Balances and days-held calculate automatically.
A4: Month Start Date | B4: 46082 | D4: Month End Date | E4: =EOMONTH(B4,0) -> 46112
A6: Date | B6: Transaction Description | C6: Source / Type | D6: Amount (+/-) | E6: CCC Portion ($) | F6: Monetization Portion ($) | G6: CCC Advance Balance | H6: Monetization Balance | I6: Total Balance | J6: Days Held | K6: Notes / Source Doc
A7: 46082 | B7: Beginning balance carried forward from March | C7: Other | E7: ='Ledger - Jan 2026'!G11 -> 0 | F7: ='Ledger - Feb 2026'!H10 -> 0 | G7: =E7 -> 0 | H7: ='Ledger - Feb 2026'!H8 -> 1079705 | I7: =G7+H7 -> 1079705 | J7: =A8-A7 -> 0 | K7: Linked to March closing balances - see formula
A8: 46082 | B8: Feb Interest | C8: Monetization Interest | D8: ='Alloc - Feb 2026'!B22 -> 2748.77 | F8: =D8 -> 2748.77 | H8: =H7+F8 -> 1082453.8 | I8: =G8+H8 -> 1082453.8 | J8: =E4-A8+1 -> 31 | K8: Linked to Alloc - Mar 2026 Monetization interest allocation
K9: Source: CCC advance letter, tranche #5
K10: Remitted per 2 CFR 200.305 - confirm PMS confirmation # on file
K11: Pro-rata draw based on prior day's ending balances
B13: Check: Days Held should sum to total days in month -> | J13: =SUM(J7:J11) -> 31
B14: Days in month -> | J14: =E4-B4+1 -> 31

Sheet Alloc - Mar 2026
A1: Monthly Interest Allocation - Mar 2026
A2: Allocates the interest posted this month between CCC Advances and Monetization Proceeds, proportional to average daily balance.
A4: Bank Statement Month | B4: ='Ledger - Mar 2026'!B4 -> 46082
A5: Total Interest Posted This Month ($) | B5: 2987.86 | D5: <- Enter from bank statement (blue input)
A7: Average Daily Balance Calculation
A8: CCC Advance - Sum(Balance x Days Held) | B8: =SUMPRODUCT('Ledger - Feb 2026'!G7:G12,'Ledger - Feb 2026'!J7:J12) -> 0
A9: Monetization - Sum(Balance x Days Held) | B9: =SUMPRODUCT('Ledger - Mar 2026'!H7:H12,'Ledger - Mar 2026'!J7:J12) -> 33556067
A10: Total - Sum(Balance x Days Held) | B10: =SUMPRODUCT('Ledger - Mar 2026'!I7:I12,'Ledger - Mar 2026'!J7:J12) -> 33556067
A11: Days in Month | B11: ='Ledger - Mar 2026'!E4-'Ledger - Mar 2026'!B4+1 -> 31
A13: CCC Advance - Average Daily Balance | B13: =B8/B11 -> 0
A14: Monetization - Average Daily Balance | B14: =B9/B11 -> 1082453.8
A15: Total - Average Daily Balance | B15: =B13+B14 -> 1082453.8
A17: Interest Allocation
A18: CCC Share of Average Daily Balance (%) | B18: =B13/B15 -> 0
A19: Monetization Share of Average Daily Balance (%) | B19: =B14/B15 -> 1
A21: CCC Advance - Interest Allocated ($) | B21: =$B$5*B18 -> 0
A22: Monetization - Interest Allocated ($) | B22: =$B$5*B19 -> 2987.86
A23: Check: CCC + Monetization = Total Interest Posted | B23: =B21+B22-B5 -> 0
A25: Next Step
A26: Record the two amounts above as 'CCC Interest' and 'Monetization Interest' transactions in NEXT month's Ledger tab (dated the day the interest posted), then record the CCC remittance separately once wired to Treasury.
A28: Disposition Reminder
A29: CCC interest: remit to federal government via PMS, unless within the $500/year retention threshold across all federal awards (2 CFR 200.305). Monetization interest: generally added to program income per award terms - confirm with USDA602 Amendment.

Sheet Ledger - Apr 2026
A1: USDA602 Transaction Ledger - Apr 2026
A2: Enter every transaction affecting the interest-bearing account. Balances and days-held calculate automatically.
A4: Month Start Date | B4: 46113 | D4: Month End Date | E4: =EOMONTH(B4,0) -> 46142
A6: Date | B6: Transaction Description | C6: Source / Type | D6: Amount (+/-) | E6: CCC Portion ($) | F6: Monetization Portion ($) | G6: CCC Advance Balance | H6: Monetization Balance | I6: Total Balance | J6: Days Held | K6: Notes / Source Doc
A7: 46113 | B7: Beginning balance carried forward from March | C7: Other | E7: ='Ledger - Jan 2026'!G11 -> 0 | F7: ='Ledger - Mar 2026'!H9 -> 0 | G7: =E7 -> 0 | H7: ='Ledger - Mar 2026'!H8 -> 1082453.8 | I7: =G7+H7 -> 1082453.8 | J7: =A8-A7 -> 0 | K7: Linked to March closing balances - see formula
A8: 46113 | B8: March Interest | C8: Monetization Interest | D8: ='Alloc - Mar 2026'!B5 -> 2987.86 | E8: ='Ledger - Jan 2026'!G12 -> 0 | F8: =D8 -> 2987.86 | G8: =E8 -> 0 | H8: =H7+F8 -> 1085441.6 | I8: =G8+H8 -> 1085441.6 | J8: =A9-A8 -> 6 | K8: Linked to March closing balances - see formula
A9: 46119 | B9: Commodity monetization sale proceeds deposited | C9: Monetization Deposit | D9: 10209329 | E9: 0 | F9: =D9 -> 10209329 | G9: =G7+E9 -> 0 | H9: =H8+F9 -> 11294770 | I9: =G9+H9 -> 11294770 | J9: =E4-A9+1 -> 24 | K9: Linked to Alloc - Mar 2026 CCC interest allocation
K10: Linked to Alloc - Mar 2026 Monetization interest allocation
K11: Source: CCC advance letter, tranche #5
K12: Remitted per 2 CFR 200.305 - confirm PMS confirmation # on file
K13: Pro-rata draw based on prior day's ending balances
B15: Check: Days Held should sum to total days in month -> | J15: =SUM(J7:J13) -> 30
B16: Days in month -> | J16: =E4-B4+1 -> 30

Sheet Alloc - Apr 2026
A1: Monthly Interest Allocation - Apr 2026
A2: Allocates the interest posted this month between CCC Advances and Monetization Proceeds, proportional to average daily balance.
A4: Bank Statement Month | B4: ='Ledger - Apr 2026'!B4 -> 46113
A5: Total Interest Posted This Month ($) | B5: 24716.64 | D5: <- Enter from bank statement (blue input)
A7: Average Daily Balance Calculation
A8: CCC Advance - Sum(Balance x Days Held) | B8: =SUMPRODUCT('Ledger - Mar 2026'!G7:G12,'Ledger - Mar 2026'!J7:J12) -> 0
A9: Monetization - Sum(Balance x Days Held) | B9: =SUMPRODUCT('Ledger - Apr 2026'!H7:H12,'Ledger - Apr 2026'!J7:J12) -> 2.7758713e+08
A10: Total - Sum(Balance x Days Held) | B10: =SUMPRODUCT('Ledger - Apr 2026'!I7:I12,'Ledger - Apr 2026'!J7:J12) -> 2.7758713e+08
A11: Days in Month | B11: ='Ledger - Apr 2026'!E4-'Ledger - Apr 2026'!B4+1 -> 30
A13: CCC Advance - Average Daily Balance | B13: =B8/B11 -> 0
A14: Monetization - Average Daily Balance | B14: =B9/B11 -> 9252904.4
A15: Total - Average Daily Balance | B15: =B13+B14 -> 9252904.4
A17: Interest Allocation
A18: CCC Share of Average Daily Balance (%) | B18: =B13/B15 -> 0
A19: Monetization Share of Average Daily Balance (%) | B19: =B14/B15 -> 1
A21: CCC Advance - Interest Allocated ($) | B21: =$B$5*B18 -> 0
A22: Monetization - Interest Allocated ($) | B22: =$B$5*B19 -> 24716.64
A23: Check: CCC + Monetization = Total Interest Posted | B23: =B21+B22-B5 -> 0
A25: Next Step
A26: Record the two amounts above as 'CCC Interest' and 'Monetization Interest' transactions in NEXT month's Ledger tab (dated the day the interest posted), then record the CCC remittance separately once wired to Treasury.
A28: Disposition Reminder
A29: CCC interest: remit to federal government via PMS, unless within the $500/year retention threshold across all federal awards (2 CFR 200.305). Monetization interest: generally added to program income per award terms - confirm with USDA602 Amendment.

Sheet Ledger - May 2026
A1: USDA602 Transaction Ledger - May 2026
A2: Enter every transaction affecting the interest-bearing account. Balances and days-held calculate automatically.
A4: Month Start Date | B4: 46143 | D4: Month End Date | E4: =EOMONTH(B4,0) -> 46173
A6: Date | B6: Transaction Description | C6: Source / Type | D6: Amount (+/-) | E6: CCC Portion ($) | F6: Monetization Portion ($) | G6: CCC Advance Balance | H6: Monetization Balance | I6: Total Balance | J6: Days Held | K6: Notes / Source Doc
A7: 46143 | B7: Beginning balance carried forward from March | C7: Other | E7: ='Ledger - Jan 2026'!G11 -> 0 | F7: ='Ledger - Apr 2026'!H9 -> 11294770 | G7: =E7 -> 0 | H7: =F7 -> 11294770 | I7: =G7+H7 -> 11294770 | J7: =A8-A7 -> 0 | K7: Linked to March closing balances - see formula
A8: 46143 | B8: Apr Interest | C8: Monetization Interest | D8: ='Alloc - Apr 2026'!B22 -> 24716.64 | E8: ='Ledger - Jan 2026'!G12 -> 0 | F8: =D8 -> 24716.64 | G8: =E8 -> 0 | H8: =H7+F8 -> 11319487 | I8: =G8+H8 -> 11319487 | J8: =A9-A8 -> 28 | K8: Linked to March closing balances - see formula
A9: 46171 | B9: Interest Adj with April Analysis fee | C9: Monetization Interest | D9: -242.08 | F9: =D9 -> -242.08 | H9: =H8+F9 -> 11319245 | I9: =G9+H9 -> 11319245 | J9: =E4-A9+1 -> 3 | K9: Linked to Alloc - Mar 2026 CCC interest allocation
K10: Linked to Alloc - Mar 2026 Monetization interest allocation
K11: Source: CCC advance letter, tranche #5
K12: Remitted per 2 CFR 200.305 - confirm PMS confirmation # on file
K13: Pro-rata draw based on prior day's ending balances
B15: Check: Days Held should sum to total days in month -> | J15: =SUM(J7:J13) -> 31
B16: Days in month -> | J16: =E4-B4+1 -> 31

Sheet Alloc - May 2026
A1: Monthly Interest Allocation - May 2026
A2: Allocates the interest posted this month between CCC Advances and Monetization Proceeds, proportional to average daily balance.
A4: Bank Statement Month | B4: ='Ledger - May 2026'!B4 -> 46143
A5: Total Interest Posted This Month ($) | B5: 31244.79 | D5: <- Enter from bank statement (blue input)
A7: Average Daily Balance Calculation
A8: CCC Advance - Sum(Balance x Days Held) | B8: =SUMPRODUCT('Ledger - Feb 2026'!G7:G12,'Ledger - Feb 2026'!J7:J12) -> 0
A9: Monetization - Sum(Balance x Days Held) | B9: =SUMPRODUCT('Ledger - May 2026'!H7:H12,'Ledger - May 2026'!J7:J12) -> 3.5090336e+08
A10: Total - Sum(Balance x Days Held) | B10: =SUMPRODUCT('Ledger - May 2026'!I7:I12,'Ledger - May 2026'!J7:J12) -> 3.5090336e+08
A11: Days in Month | B11: ='Ledger - May 2026'!E4-'Ledger - May 2026'!B4+1 -> 31
A13: CCC Advance - Average Daily Balance | B13: =B8/B11 -> 0
A14: Monetization - Average Daily Balance | B14: =B9/B11 -> 11319463
A15: Total - Average Daily Balance | B15: =B13+B14 -> 11319463
A17: Interest Allocation
A18: CCC Share of Average Daily Balance (%) | B18: =B13/B15 -> 0
A19: Monetization Share of Average Daily Balance (%) | B19: =B14/B15 -> 1
A21: CCC Advance - Interest Allocated ($) | B21: =$B$5*B18 -> 0
A22: Monetization - Interest Allocated ($) | B22: =$B$5*B19 -> 31244.79
A23: Check: CCC + Monetization = Total Interest Posted | B23: =B21+B22-B5 -> 0
A25: Next Step
A26: Record the two amounts above as 'CCC Interest' and 'Monetization Interest' transactions in NEXT month's Ledger tab (dated the day the interest posted), then record the CCC remittance separately once wired to Treasury.
A28: Disposition Reminder
A29: CCC interest: remit to federal government via PMS, unless within the $500/year retention threshold across all federal awards (2 CFR 200.305). Monetization interest: generally added to program income per award terms - confirm with USDA602 Amendment.

Sheet Ledger - June 2026
A1: USDA602 Transaction Ledger - June 2026
A2: Enter every transaction affecting the interest-bearing account. Balances and days-held calculate automatically.
A4: Month Start Date | B4: 46174 | D4: Month End Date | E4: =EOMONTH(B4,0) -> 46203
A6: Date | B6: Transaction Description | C6: Source / Type | D6: Amount (+/-) | E6: CCC Portion ($) | F6: Monetization Portion ($) | G6: CCC Advance Balance | H6: Monetization Balance | I6: Total Balance | J6: Days Held | K6: Notes / Source Doc
A7: 46174 | B7: Beginning balance carried forward from March | C7: Other | E7: ='Ledger - Jan 2026'!G11 -> 0 | F7: ='Ledger - May 2026'!H9 -> 11319245 | G7: =E7 -> 0 | H7: =F7 -> 11319245 | I7: =G7+H7 -> 11319245 | J7: =A8-A7 -> 0 | K7: Linked to March closing balances - see formula
A8: 46174 | B8: May Interest | C8: Monetization Interest | D8: ='Alloc - Apr 2026'!B22 -> 24716.64 | E8: ='Ledger - Jan 2026'!G12 -> 0 | F8: ='Alloc - May 2026'!B22 -> 31244.79 | G8: =E8 -> 0 | H8: =H7+F8 -> 11350490 | I8: =G8+H8 -> 11350490 | J8: =E4-A8+1 -> 30 | K8: Linked to March closing balances - see formula
K9: Linked to Alloc - Mar 2026 CCC interest allocation
K10: Linked to Alloc - Mar 2026 Monetization interest allocation
K11: Source: CCC advance letter, tranche #5
K12: Remitted per 2 CFR 200.305 - confirm PMS confirmation # on file
K13: Pro-rata draw based on prior day's ending balances
B15: Check: Days Held should sum to total days in month -> | J15: =SUM(J7:J13) -> 30
B16: Days in month -> | J16: =E4-B4+1 -> 30

Sheet Alloc - June 2026
A1: Monthly Interest Allocation - June 2026
A2: Allocates the interest posted this month between CCC Advances and Monetization Proceeds, proportional to average daily balance.
A4: Bank Statement Month | B4: ='Ledger - June 2026'!B4 -> 46174
A5: Total Interest Posted This Month ($) | B5: 30319.77 | D5: <- Enter from bank statement (blue input)
A7: Average Daily Balance Calculation
A8: CCC Advance - Sum(Balance x Days Held) | B8: =SUMPRODUCT('Ledger - Feb 2026'!G7:G12,'Ledger - Feb 2026'!J7:J12) -> 0
A9: Monetization - Sum(Balance x Days Held) | B9: =SUMPRODUCT('Ledger - June 2026'!H7:H12,'Ledger - June 2026'!J7:J12) -> 340514685
A10: Total - Sum(Balance x Days Held) | B10: =SUMPRODUCT('Ledger - June 2026'!I7:I12,'Ledger - June 2026'!J7:J12) -> 340514685
A11: Days in Month | B11: ='Ledger - June 2026'!E4-'Ledger - June 2026'!B4+1 -> 30
A13: CCC Advance - Average Daily Balance | B13: =B8/B11 -> 0
A14: Monetization - Average Daily Balance | B14: =B9/B11 -> 11350490
A15: Total - Average Daily Balance | B15: =B13+B14 -> 11350490
A17: Interest Allocation
A18: CCC Share of Average Daily Balance (%) | B18: =B13/B15 -> 0
A19: Monetization Share of Average Daily Balance (%) | B19: =B14/B15 -> 1
A21: CCC Advance - Interest Allocated ($) | B21: =$B$5*B18 -> 0
A22: Monetization - Interest Allocated ($) | B22: =$B$5*B19 -> 30319.77
A23: Check: CCC + Monetization = Total Interest Posted | B23: =B21+B22-B5 -> 0
A25: Next Step
A26: Record the two amounts above as 'CCC Interest' and 'Monetization Interest' transactions in NEXT month's Ledger tab (dated the day the interest posted), then record the CCC remittance separately once wired to Treasury.
A28: Disposition Reminder
A29: CCC interest: remit to federal government via PMS, unless within the $500/year retention threshold across all federal awards (2 CFR 200.305). Monetization interest: generally added to program income per award terms - confirm with USDA602 Amendment.
