Workbook

Sheet Resumen
A1: Fundación Partners of the Americas Colombia NIT 901.802.108-7 Vigencia: Año Fiscal 2024
A2: Ingresos | B2: Monto en Cop $ | C2: Gastos | D2: Monto en Cop $
C3: Detalle | D3: Total
A4: =+'Ingresos Fundación POA'!A2 -> Aportes iniciales de fundadores | B4: =+'Ingresos Fundación POA'!B2 -> 12000000 | C4: 1.Personal (Laboral) | D4: =+'Budget Fundación POA'!AX8 -> 36000000
A5: =+'Ingresos Fundación POA'!A3 -> Donaciones recibidas de terceros | B5: =+'Ingresos Fundación POA'!B3 -> 18000000 | C5: 2.Prestaciones Sociales | D5: =+'Budget Fundación POA'!AX13 -> 18665280
A6: =+'Ingresos Fundación POA'!A4 -> Subvenciones privadas | B6: =+'Ingresos Fundación POA'!B4 -> 20000000 | C6: 3.Viajes y transportes | D6: =+'Budget Fundación POA'!AX18 -> 8000000
A7: =+'Ingresos Fundación POA'!A5 -> Convenios de colaboración con Partners of the Americas | B7: =+'Ingresos Fundación POA'!B5 -> 32000000 | C7: 4. Servicios profesionales (consultores) | D7: =+'Budget Fundación POA'!AX23 -> 33350000
A8: =+'Ingresos Fundación POA'!A6 -> Ingresos por servicios prestados | B8: =+'Ingresos Fundación POA'!B6 -> 28000000 | C8: =+'Budget Fundación POA'!A24 -> 5. Materiales y suministros | D8: =+'Budget Fundación POA'!AX28 -> 4480000
C9: =+'Budget Fundación POA'!A29 -> 6. Costos Directos | D9: =+'Budget Fundación POA'!AX32 -> 3040000
A10: Total | B10: =SUM(B4:B8) -> 110000000 | C10: Total | D10: =SUM(D4:D9) -> 103535280
A12: Disponibilidad final ** | B12: =+B10-D10 -> 6464720
A13: **Los excedentes que se generen serán reinvertidos en la vigencia del año 2025

Sheet Ingresos Fundación POA
A1: Presupuesto de Ingresos Fundación Partners of the Americas Colombia NIT 901.802.108-7 Vigencia: Año Fiscal 2024
A2: Aportes iniciales de fundadores | B2: 12000000
A3: Donaciones recibidas de terceros | B3: 18000000
A4: Subvenciones privadas | B4: 20000000
A5: Convenios de colaboración con Partners of the Americas | B5: =4000000*8 -> 32000000
A6: Ingresos por servicios prestados | B6: =3500000*8 -> 28000000
A7: Total ingresos | B7: =SUM(B2:B6) -> 110000000

Sheet Budget Fundación POA
A1: Presupuesto Gastos Fundación Partners of the Americas Colombia NIT 901.802.108-7 Vigencia: Año Fiscal 2024
B2: Mes 1 | F2: Mes 2 | J2: Marzo | N2: Abril | R2: Mayo | V2: Junio | Z2: Julio | AD2: Agosto | AH2: Septiembre | AL2: Octubre | AP2: Noviembre | AT2: Diciembre
A3: Item | B3: Unidad | C3: Cantidad | D3: Valor unitario Pesos COL$ | E3: Valor total Pesos COL$ | F3: Unidad | G3: Cantidad | H3: Valor unitario Pesos COL$ | I3: Valor total Pesos COL$ | J3: Unidad | K3: Cantidad | L3: Valor unitario Pesos COL$ | M3: Valor total Pesos COL$ | N3: Unidad | O3: Cantidad | P3: Valor unitario Pesos COL$ | Q3: Valor total Pesos COL$ | R3: Unidad | S3: Cantidad | T3: Valor unitario Pesos COL$ | U3: Valor total Pesos COL$ | V3: Unidad | W3: Cantidad | X3: Valor unitario Pesos COL$ | Y3: Valor total Pesos COL$ | Z3: Unidad | AA3: Cantidad | AB3: Valor unitario Pesos COL$ | AC3: Valor total Pesos COL$ | AD3: Unidad | AE3: Cantidad | AF3: Valor unitario Pesos COL$ | AG3: Valor total Pesos COL$ | AH3: Unidad | AI3: Cantidad | AJ3: Valor unitario Pesos COL$ | AK3: Valor total Pesos COL$ | AL3: Unidad | AM3: Cantidad | AN3: Valor unitario Pesos COL$ | AO3: Valor total Pesos COL$ | AP3: Unidad | AQ3: Cantidad | AR3: Valor unitario Pesos COL$ | AS3: Valor total Pesos COL$ | AT3: Unidad | AU3: Cantidad | AV3: Valor unitario Pesos COL$ | AW3: Valor total Pesos COL$ | AX3: Total
A4: 1.Personal (Laboral)
A5: Director | N5: Mes | O5: 0 | P5: 3000000 | Q5: =O5*P5 -> 0 | R5: Mes | S5: 1 | T5: 3000000 | U5: =S5*T5 -> 3000000 | V5: Mes | W5: 1 | X5: 3000000 | Y5: =W5*X5 -> 3000000 | Z5: Mes | AA5: 1 | AB5: 3000000 | AC5: =AA5*AB5 -> 3000000 | AD5: Mes | AE5: 1 | AF5: 3000000 | AG5: =AE5*AF5 -> 3000000 | AH5: Mes | AI5: 1 | AJ5: 3000000 | AK5: =AI5*AJ5 -> 3000000 | AL5: Mes | AM5: 1 | AN5: 3000000 | AO5: =AM5*AN5 -> 3000000 | AP5: Mes | AQ5: 1 | AR5: 3000000 | AS5: =AQ5*AR5 -> 3000000 | AT5: Mes | AU5: 1 | AV5: 3000000 | AW5: =AU5*AV5 -> 3000000 | AX5: =+AW5+AS5+AO5+AK5+AG5+AC5+Y5+U5+Q5+M5+I5+E5+D5 -> 24000000
A6: Contador | N6: Mes | O6: 0 | P6: 1500000 | Q6: =O6*P6 -> 0 | R6: Mes | S6: 1 | T6: 1500000 | U6: =S6*T6 -> 1500000 | V6: Mes | W6: 1 | X6: 1500000 | Y6: =W6*X6 -> 1500000 | Z6: Mes | AA6: 1 | AB6: 1500000 | AC6: =AA6*AB6 -> 1500000 | AD6: Mes | AE6: 1 | AF6: 1500000 | AG6: =AE6*AF6 -> 1500000 | AH6: Mes | AI6: 1 | AJ6: 1500000 | AK6: =AI6*AJ6 -> 1500000 | AL6: Mes | AM6: 1 | AN6: 1500000 | AO6: =AM6*AN6 -> 1500000 | AP6: Mes | AQ6: 1 | AR6: 1500000 | AS6: =AQ6*AR6 -> 1500000 | AT6: Mes | AU6: 1 | AV6: 1500000 | AW6: =AU6*AV6 -> 1500000 | AX6: =+AW6+AS6+AO6+AK6+AG6+AC6+Y6+U6+Q6+M6+I6+E6+D6 -> 12000000
A8: Subtotal | M8: =SUM(M5:M7) -> 0 | Q8: =SUM(Q5:Q7) -> 0 | U8: =SUM(U5:U7) -> 4500000 | Y8: =SUM(Y5:Y7) -> 4500000 | AC8: =SUM(AC5:AC7) -> 4500000 | AG8: =SUM(AG5:AG7) -> 4500000 | AK8: =SUM(AK5:AK7) -> 4500000 | AO8: =SUM(AO5:AO7) -> 4500000 | AS8: =SUM(AS5:AS7) -> 4500000 | AW8: =SUM(AW5:AW7) -> 4500000 | AX8: =+AW8+AS8+AO8+AK8+AG8+AC8+Y8+U8+Q8+M8+I8+E8+D8 -> 36000000
A9: 2.Prestaciones Sociales
A10: Director | N10: Mes | O10: 0 | P10: 1555440 | Q10: =O10*P10 -> 0 | R10: Mes | S10: 1 | T10: 1555440 | U10: =S10*T10 -> 1555440 | V10: Mes | W10: 1 | X10: 1555440 | Y10: =W10*X10 -> 1555440 | Z10: Mes | AA10: 1 | AB10: 1555440 | AC10: =AA10*AB10 -> 1555440 | AD10: Mes | AE10: 1 | AF10: 1555440 | AG10: =AE10*AF10 -> 1555440 | AH10: Mes | AI10: 1 | AJ10: 1555440 | AK10: =AI10*AJ10 -> 1555440 | AL10: Mes | AM10: 1 | AN10: 1555440 | AO10: =AM10*AN10 -> 1555440 | AP10: Mes | AQ10: 1 | AR10: 1555440 | AS10: =AQ10*AR10 -> 1555440 | AT10: Mes | AU10: 1 | AV10: 1555440 | AW10: =AU10*AV10 -> 1555440 | AX10: =+AW10+AS10+AO10+AK10+AG10+AC10+Y10+U10+Q10+M10+I10+E10+D10 -> 12443520
A11: Contador | N11: Mes | O11: 0 | P11: 777720 | Q11: =O11*P11 -> 0 | R11: Mes | S11: 1 | T11: 777720 | U11: =S11*T11 -> 777720 | V11: Mes | W11: 1 | X11: 777720 | Y11: =W11*X11 -> 777720 | Z11: Mes | AA11: 1 | AB11: 777720 | AC11: =AA11*AB11 -> 777720 | AD11: Mes | AE11: 1 | AF11: 777720 | AG11: =AE11*AF11 -> 777720 | AH11: Mes | AI11: 1 | AJ11: 777720 | AK11: =AI11*AJ11 -> 777720 | AL11: Mes | AM11: 1 | AN11: 777720 | AO11: =AM11*AN11 -> 777720 | AP11: Mes | AQ11: 1 | AR11: 777720 | AS11: =AQ11*AR11 -> 777720 | AT11: Mes | AU11: 1 | AV11: 777720 | AW11: =AU11*AV11 -> 777720 | AX11: =+AW11+AS11+AO11+AK11+AG11+AC11+Y11+U11+Q11+M11+I11+E11+D11 -> 6221760
A13: Subtotal | M13: =SUM(M9:M11) -> 0 | Q13: =SUM(Q9:Q11) -> 0 | U13: =SUM(U9:U11) -> 2333160 | Y13: =SUM(Y9:Y11) -> 2333160 | AC13: =SUM(AC9:AC11) -> 2333160 | AG13: =SUM(AG9:AG11) -> 2333160 | AK13: =SUM(AK9:AK11) -> 2333160 | AO13: =SUM(AO9:AO11) -> 2333160 | AS13: =SUM(AS9:AS11) -> 2333160 | AW13: =SUM(AW9:AW11) -> 2333160 | AX13: =+AW13+AS13+AO13+AK13+AG13+AC13+Y13+U13+Q13+M13+I13+E13+D13 -> 18665280
A14: 3.Viajes y transportes
A15: Viajes para gestión donaciones | N15: Mes | O15: 0 | P15: 1000000 | Q15: =O15*P15 -> 0 | R15: Mes | S15: 1 | T15: 1000000 | U15: =S15*T15 -> 1000000 | V15: Mes | W15: 1 | X15: 1000000 | Y15: =W15*X15 -> 1000000 | Z15: Mes | AA15: 1 | AB15: 1000000 | AC15: =AA15*AB15 -> 1000000 | AD15: Mes | AE15: 1 | AF15: 1000000 | AG15: =AE15*AF15 -> 1000000 | AH15: Mes | AI15: 1 | AJ15: 1000000 | AK15: =AI15*AJ15 -> 1000000 | AL15: Mes | AM15: 1 | AN15: 1000000 | AO15: =AM15*AN15 -> 1000000 | AP15: Mes | AQ15: 1 | AR15: 1000000 | AS15: =AQ15*AR15 -> 1000000 | AT15: Mes | AU15: 1 | AV15: 1000000 | AW15: =AU15*AV15 -> 1000000 | AX15: =+AW15+AS15+AO15+AK15+AG15+AC15+Y15+U15+Q15+M15+I15+E15+D15 -> 8000000
A18: Subtotal | M18: =SUM(M15:M17) -> 0 | Q18: =SUM(Q15:Q17) -> 0 | U18: =SUM(U15:U17) -> 1000000 | Y18: =SUM(Y15:Y17) -> 1000000 | AC18: =SUM(AC15:AC17) -> 1000000 | AG18: =SUM(AG15:AG17) -> 1000000 | AK18: =SUM(AK15:AK17) -> 1000000 | AO18: =SUM(AO15:AO17) -> 1000000 | AS18: =SUM(AS15:AS17) -> 1000000 | AW18: =SUM(AW15:AW17) -> 1000000 | AX18: =+AW18+AS18+AO18+AK18+AG18+AC18+Y18+U18+Q18+M18+I18+E18+D18 -> 8000000
A19: 4. Servicios profesionales (consultores)
A20: Asesores jurídicos | J20: Mes | K20: 0.5 | L20: 2500000 | M20: =K20*L20 -> 1250000 | N20: Mes | O20: 1 | P20: 2500000 | Q20: =O20*P20 -> 2500000 | R20: Mes | S20: 1 | T20: 2500000 | U20: =S20*T20 -> 2500000 | V20: Mes | W20: 1 | X20: 2500000 | Y20: =W20*X20 -> 2500000 | Z20: Mes | AA20: 1 | AB20: 2500000 | AC20: =AA20*AB20 -> 2500000 | AD20: Mes | AE20: 1 | AF20: 2500000 | AG20: =AE20*AF20 -> 2500000 | AH20: Mes | AI20: 1 | AJ20: 2500000 | AK20: =AI20*AJ20 -> 2500000 | AL20: Mes | AM20: 1 | AN20: 2500000 | AO20: =AM20*AN20 -> 2500000 | AP20: Mes | AQ20: 1 | AR20: 2500000 | AS20: =AQ20*AR20 -> 2500000 | AT20: Mes | AU20: 1 | AV20: 2500000 | AW20: =AU20*AV20 -> 2500000 | AX20: =+AW20+AS20+AO20+AK20+AG20+AC20+Y20+U20+Q20+M20+I20+E20+D20 -> 23750000
A21: Asesores fiscal | N21: Mes | O21: 0 | P21: 1200000 | Q21: =O21*P21 -> 0 | R21: Mes | S21: 1 | T21: 1200000 | U21: =S21*T21 -> 1200000 | V21: Mes | W21: 1 | X21: 1200000 | Y21: =W21*X21 -> 1200000 | Z21: Mes | AA21: 1 | AB21: 1200000 | AC21: =AA21*AB21 -> 1200000 | AD21: Mes | AE21: 1 | AF21: 1200000 | AG21: =AE21*AF21 -> 1200000 | AH21: Mes | AI21: 1 | AJ21: 1200000 | AK21: =AI21*AJ21 -> 1200000 | AL21: Mes | AM21: 1 | AN21: 1200000 | AO21: =AM21*AN21 -> 1200000 | AP21: Mes | AQ21: 1 | AR21: 1200000 | AS21: =AQ21*AR21 -> 1200000 | AT21: Mes | AU21: 1 | AV21: 1200000 | AW21: =AU21*AV21 -> 1200000 | AX21: =+AW21+AS21+AO21+AK21+AG21+AC21+Y21+U21+Q21+M21+I21+E21+D21 -> 9600000
A23: Subtotal | M23: =SUM(M20:M22) -> 1250000 | Q23: =SUM(Q20:Q22) -> 2500000 | U23: =SUM(U20:U22) -> 3700000 | Y23: =SUM(Y20:Y22) -> 3700000 | AC23: =SUM(AC20:AC22) -> 3700000 | AG23: =SUM(AG20:AG22) -> 3700000 | AK23: =SUM(AK20:AK22) -> 3700000 | AO23: =SUM(AO20:AO22) -> 3700000 | AS23: =SUM(AS20:AS22) -> 3700000 | AW23: =SUM(AW20:AW22) -> 3700000 | AX23: =+AW23+AS23+AO23+AK23+AG23+AC23+Y23+U23+Q23+M23+I23+E23+D23 -> 33350000
A24: 5. Materiales y suministros | AX24: =+AW24+AS24+AO24+AK24+AG24+AC24+Y24+U24+Q24+M24+I24+E24+D24 -> 0
A25: Papelería | M25: =K25*L25 -> 0 | N25: Mes | O25: 0 | P25: 100000 | Q25: =O25*P25 -> 0 | R25: Mes | S25: 1 | T25: 100000 | U25: =S25*T25 -> 100000 | V25: Mes | W25: 1 | X25: 100000 | Y25: =W25*X25 -> 100000 | Z25: Mes | AA25: 1 | AB25: 100000 | AC25: =AA25*AB25 -> 100000 | AD25: Mes | AE25: 1 | AF25: 100000 | AG25: =AE25*AF25 -> 100000 | AH25: Mes | AI25: 1 | AJ25: 100000 | AK25: =AI25*AJ25 -> 100000 | AL25: Mes | AM25: 1 | AN25: 100000 | AO25: =AM25*AN25 -> 100000 | AP25: Mes | AQ25: 1 | AR25: 100000 | AS25: =AQ25*AR25 -> 100000 | AT25: Mes | AU25: 1 | AV25: 100000 | AW25: =AU25*AV25 -> 100000 | AX25: =+AW25+AS25+AO25+AK25+AG25+AC25+Y25+U25+Q25+M25+I25+E25+D25 -> 800000
A26: Alquiler equipo de computo | R26: Mes | S26: 2 | T26: 230000 | U26: =S26*T26 -> 460000 | V26: Mes | W26: 2 | X26: 230000 | Y26: =W26*X26 -> 460000 | Z26: Mes | AA26: 2 | AB26: 230000 | AC26: =AA26*AB26 -> 460000 | AD26: Mes | AE26: 2 | AF26: 230000 | AG26: =AE26*AF26 -> 460000 | AH26: Mes | AI26: 2 | AJ26: 230000 | AK26: =AI26*AJ26 -> 460000 | AL26: Mes | AM26: 2 | AN26: 230000 | AO26: =AM26*AN26 -> 460000 | AP26: Mes | AQ26: 2 | AR26: 230000 | AS26: =AQ26*AR26 -> 460000 | AT26: Mes | AU26: 2 | AV26: 230000 | AW26: =AU26*AV26 -> 460000 | AX26: =+AW26+AS26+AO26+AK26+AG26+AC26+Y26+U26+Q26+M26+I26+E26+D26 -> 3680000
A28: Subtotal | M28: =SUM(M25:M27) -> 0 | Q28: =SUM(Q25:Q27) -> 0 | U28: =SUM(U25:U27) -> 560000 | Y28: =SUM(Y25:Y27) -> 560000 | AC28: =SUM(AC25:AC27) -> 560000 | AG28: =SUM(AG25:AG27) -> 560000 | AK28: =SUM(AK25:AK27) -> 560000 | AO28: =SUM(AO25:AO27) -> 560000 | AS28: =SUM(AS25:AS27) -> 560000 | AW28: =SUM(AW25:AW27) -> 560000 | AX28: =+AW28+AS28+AO28+AK28+AG28+AC28+Y28+U28+Q28+M28+I28+E28+D28 -> 4480000
A29: 6. Costos Directos
A30: Comunicación | M30: =K30*L30 -> 0 | N30: Mes | O30: 0 | P30: 100000 | Q30: =O30*P30 -> 0 | R30: Mes | S30: 1 | T30: 150000 | U30: =S30*T30 -> 150000 | V30: Mes | W30: 1 | X30: 150000 | Y30: =W30*X30 -> 150000 | Z30: Mes | AA30: 1 | AB30: 150000 | AC30: =AA30*AB30 -> 150000 | AD30: Mes | AE30: 1 | AF30: 150000 | AG30: =AE30*AF30 -> 150000 | AH30: Mes | AI30: 1 | AJ30: 150000 | AK30: =AI30*AJ30 -> 150000 | AL30: Mes | AM30: 1 | AN30: 150000 | AO30: =AM30*AN30 -> 150000 | AP30: Mes | AQ30: 1 | AR30: 150000 | AS30: =AQ30*AR30 -> 150000 | AT30: Mes | AU30: 1 | AV30: 150000 | AW30: =AU30*AV30 -> 150000 | AX30: =+AW30+AS30+AO30+AK30+AG30+AC30+Y30+U30+Q30+M30+I30+E30+D30 -> 1200000
A31: Puestos de trabajo | M31: =K31*L31 -> 0 | N31: Mes | O31: 0 | P31: 100000 | Q31: =O31*P31 -> 0 | R31: Mes | S31: 2 | T31: 115000 | U31: =S31*T31 -> 230000 | V31: Mes | W31: 2 | X31: 115000 | Y31: =W31*X31 -> 230000 | Z31: Mes | AA31: 2 | AB31: 115000 | AC31: =AA31*AB31 -> 230000 | AD31: Mes | AE31: 2 | AF31: 115000 | AG31: =AE31*AF31 -> 230000 | AH31: Mes | AI31: 2 | AJ31: 115000 | AK31: =AI31*AJ31 -> 230000 | AL31: Mes | AM31: 2 | AN31: 115000 | AO31: =AM31*AN31 -> 230000 | AP31: Mes | AQ31: 2 | AR31: 115000 | AS31: =AQ31*AR31 -> 230000 | AT31: Mes | AU31: 2 | AV31: 115000 | AW31: =AU31*AV31 -> 230000 | AX31: =+AW31+AS31+AO31+AK31+AG31+AC31+Y31+U31+Q31+M31+I31+E31+D31 -> 1840000
A32: Subtotal | E32: =SUM(E30:E31) -> 0 | I32: =SUM(I30:I31) -> 0 | M32: =SUM(M30:M31) -> 0 | Q32: =SUM(Q30:Q31) -> 0 | U32: =SUM(U30:U31) -> 380000 | Y32: =SUM(Y30:Y31) -> 380000 | AC32: =SUM(AC30:AC31) -> 380000 | AG32: =SUM(AG30:AG31) -> 380000 | AK32: =SUM(AK30:AK31) -> 380000 | AO32: =SUM(AO30:AO31) -> 380000 | AS32: =SUM(AS30:AS31) -> 380000 | AW32: =SUM(AW30:AW31) -> 380000 | AX32: =+AW32+AS32+AO32+AK32+AG32+AC32+Y32+U32+Q32+M32+I32+E32+D32 -> 3040000
A33: TOTAL | E33: =E8+E13+E18+E23+E28+E32 -> 0 | I33: =I8+I13+I18+I23+I28+I32 -> 0 | M33: =M8+M13+M18+M23+M28+M32 -> 1250000 | Q33: =Q8+Q13+Q18+Q23+Q28+Q32 -> 2500000 | U33: =U8+U13+U18+U23+U28+U32 -> 12473160 | Y33: =Y8+Y13+Y18+Y23+Y28+Y32 -> 12473160 | AC33: =AC8+AC13+AC18+AC23+AC28+AC32 -> 12473160 | AG33: =AG8+AG13+AG18+AG23+AG28+AG32 -> 12473160 | AK33: =AK8+AK13+AK18+AK23+AK28+AK32 -> 12473160 | AO33: =AO8+AO13+AO18+AO23+AO28+AO32 -> 12473160 | AS33: =AS8+AS13+AS18+AS23+AS28+AS32 -> 12473160 | AW33: =AW8+AW13+AW18+AW23+AW28+AW32 -> 12473160 | AX33: =+AW33+AS33+AO33+AK33+AG33+AC33+Y33+U33+Q33+M33+I33+E33+D33 -> 103535280

Sheet Prestaciones
B1: Presupuesto Fundación Partners of the Americas Colombia Vigencia: Año Fiscal 2024
B3: Salud | C3: 8.5
B4: Pensión | C4: 12
B5: Sena | C5: 2
B6: ICBF | C6: 3
B7: Caja de compesación | C7: 4
B8: Prima | C8: 8.33
B9: Cesantias | C9: 8.33
B10: Intereses Cesantias | C10: 1
B11: Vacaciones | C11: 4.166
B12: ARL Riesgo I | C12: 0.522
B13: Total Prestaciones | C13: =SUM(C3:C12) -> 51.848
