Workbook
Name \a: '[1]CUADRO No 4'!#REF!
Name \c: #REF!
Name \i: #REF!
Name \P: #REF!
Name \r: #REF!
Name __pd1: [2]Rates!$J$24
Name __pd6: [2]Rates!$J$30
Name __tix1: [2]Rates!$J$40
Name __tix2: [2]Rates!$J$41
Name __tix6: [2]Rates!$J$47
Name _1: #REF!
Name _1998: #REF!
Name _1999: #REF!
Name _2: #REF!
Name _2000: #REF!
Name _2001: #REF!
Name _2002: #REF!
Name _3: #REF!
Name _4: #REF!
Name _5: #REF!
Name _6: #REF!
Name _7: #REF!
Name _8: #REF!
Name _fmi1: [3]PAGOFMI!$A$1:$L$51
Name _fmi2: [3]PAGOFMI!$P$1:$AA$51
Name _fmi3: [3]PAGORES!$AC$1:$AN$43
Name _fmi4: [3]PAGORES!$AP$1:$BA$44
Name _PIB01: [4]SUPUESTOS!#REF!
Name _PIB02: [5]SUPUESTOS!#REF!
Name _PIB95: [4]SUPUESTOS!$J$47
Name _PIB96: [4]SUPUESTOS!$K$47
Name _PIB97: [6]SUPUESTOS!$L$47
Name _PIB98: [6]SUPUESTOS!$M$47
Name _PIB99: [6]SUPUESTOS!$N$47
Name _RES9397: #REF!
Name _rez2: '[3]PAGOS VIGENCIA t'!$A$57:$AH$108
Name _rez3: [3]PAGORES!$A$1:$M$37
Name _rez4: [3]PAGORES!$O$1:$AN$43
Name a: #REF!
Name A_2002: #REF!
Name A_CAPITAL: [9]Hoja4!$B$3:$O$34
Name A_DEPTOS: [9]Hoja4!$B$76:$N$108
Name A_impresión_IM: #REF!
Name A_MUNPIOS: [9]Hoja4!$B$39:$N$71
Name AAA: [10]proyecINGRESOS99!$L$1:$T$97
Name AEFormar: [11]Variables!$C$5
Name Ajustado: #REF!
Name almuerzo: [11]Variables!$C$18
Name alquilertableta: [11]Variables!$C$21
Name ANEXO_No.: #REF!
Name ANEXO_No._5: #REF!
Name ANPDH: '[12]Salary & PR Tax'!#REF!
Name aprnac: [13]GASTOS!#REF!
Name APROPIACIONES_PAC_Y_REZAGO_1999___2000: #REF!
Name aprprp: [13]GASTOS!#REF!
Name asigbas: #REF!
Name asigbasempu: #REF!
Name asigbasisten: #REF!
Name asigmen: #REF!
Name auxalm: #REF!

Sheet Budget Summary
B1: Partners of the Americas Fertilize Right Colombia Budget 2023
B2: USDA-FAS-10960-0700-10-23-0012 CFDA: 10.960 Technical Agricultural Assistance
A4: Line Items | B4: Year 1 | E4: Year 2 | H4: Year 3 | K4: Year 4 | N4: Total | O4: Total | P4: Grand
B5: USDA | C5: Cost Share | D5: Total | E5: USDA | F5: Cost Share | G5: Total | H5: USDA | I5: Cost Share | J5: Total | K5: USDA | L5: Cost Share | M5: Total | N5: USDA | O5: Cost Share | P5: Total
A7: Personnel | B7: =Budget!F29 -> 139520.83 | C7: =Budget!G29 -> 0 | D7: =SUM(B7:C7) -> 139520.83 | E7: =Budget!L29 -> 163800 | F7: =Budget!M29 -> 0 | G7: =SUM(E7:F7) -> 163800 | H7: =Budget!R29 -> 171990 | I7: =Budget!S29 -> 0 | J7: =SUM(H7:I7) -> 171990 | K7: =Budget!X29 -> 108322.35 | L7: =Budget!Y29 -> 0 | M7: =SUM(K7:L7) -> 108322.35 | N7: =Budget!AA29 -> 583633.18 | O7: =Budget!AB29 -> 0 | P7: =Budget!AC29 -> 583633.18
A9: Fringe Benefits | B9: =Budget!F41 -> 56107.429 | C9: =Budget!G41 -> 0 | D9: =Budget!H41 -> 56107.429 | E9: =Budget!L41 -> 66647.128 | F9: =Budget!M41 -> 0 | G9: =Budget!N41 -> 66647.128 | H9: =Budget!R41 -> 69979.484 | I9: =Budget!S41 -> 0 | J9: =Budget!T41 -> 69979.484 | K9: =Budget!X41 -> 44089.053 | L9: =Budget!Y41 -> 0 | M9: =Budget!Z41 -> 44089.053 | N9: =Budget!AA41 -> 236823.09 | O9: =Budget!AB41 -> 0 | P9: =Budget!AC41 -> 236823.09
A11: Travel | B11: =Budget!F64 -> 13735 | C11: =Budget!G64 -> 0 | D11: =Budget!H64 -> 13735 | E11: =Budget!L64 -> 16601.4 | F11: =Budget!M64 -> 0 | G11: =Budget!N64 -> 16601.4 | H11: =Budget!R64 -> 17034.162 | I11: =Budget!S64 -> 0 | J11: =Budget!T64 -> 17034.162 | K11: =Budget!X64 -> 13025.739 | L11: =Budget!Y64 -> 0 | M11: =Budget!Z64 -> 13025.739 | N11: =Budget!AA64 -> 60396.301 | O11: =Budget!AB64 -> 0 | P11: =Budget!AC64 -> 60396.301
A13: Equipment | B13: =Budget!F70 -> 0 | C13: =Budget!G70 -> 0 | D13: =Budget!H70 -> 0 | E13: =Budget!L70 -> 0 | F13: =Budget!M70 -> 0 | G13: =Budget!N70 -> 0 | H13: =Budget!R70 -> 0 | I13: =Budget!S70 -> 0 | J13: =Budget!T70 -> 0 | K13: =Budget!X70 -> 0 | L13: =Budget!Y70 -> 0 | M13: =Budget!Z70 -> 0 | N13: =Budget!AA70 -> 0 | O13: =Budget!AB70 -> 0 | P13: =Budget!AC70 -> 0
A15: Supplies | B15: =Budget!F85 -> 22000 | C15: =Budget!G85 -> 0 | D15: =Budget!H85 -> 22000 | E15: =Budget!L85 -> 4926 | F15: =Budget!M85 -> 0 | G15: =Budget!N85 -> 4926 | H15: =Budget!R85 -> 5055.42 | I15: =Budget!S85 -> 0 | J15: =Budget!T85 -> 5055.42 | K15: =Budget!X85 -> 3242.7221 | L15: =Budget!Y85 -> 0 | M15: =Budget!Z85 -> 3242.7221 | N15: =Budget!AA85 -> 35224.142 | O15: =Budget!AB85 -> 0 | P15: =Budget!AC85 -> 35224.142
A17: Contractual | B17: =Budget!F94 -> 103000 | C17: =Budget!G94 -> 0 | D17: =Budget!H94 -> 103000 | E17: =Budget!L94 -> 340000 | F17: =Budget!M94 -> 0 | G17: =Budget!N94 -> 340000 | H17: =Budget!R94 -> 340000 | I17: =Budget!S94 -> 0 | J17: =Budget!T94 -> 340000 | K17: =Budget!X94 -> 77000 | L17: =Budget!Y94 -> 0 | M17: =Budget!Z94 -> 77000 | N17: =Budget!AA94 -> 860000 | O17: =Budget!AB94 -> 0 | P17: =Budget!AC94 -> 860000
A19: Other Direct Costs | B19: =Budget!F132 -> 47825 | C19: =Budget!G132 -> 40000 | D19: =Budget!H132 -> 87825 | E19: =Budget!L132 -> 175081 | F19: =Budget!M132 -> 78250 | G19: =Budget!N132 -> 253331 | H19: =Budget!R132 -> 39986.73 | I19: =Budget!S132 -> 19750 | J19: =Budget!T132 -> 59736.73 | K19: =Budget!X132 -> 58642.416 | L19: =Budget!Y132 -> 13500 | M19: =Budget!Z132 -> 72142.416 | N19: =Budget!AA132 -> 321535.15 | O19: =Budget!AB132 -> 151500 | P19: =Budget!AC132 -> 473035.15
A21: Total Direct Costs | B21: =Budget!F134 -> 382188.26 | C21: =Budget!G134 -> 40000 | D21: =Budget!H134 -> 422188.26 | E21: =Budget!L134 -> 767055.53 | F21: =Budget!M134 -> 78250 | G21: =Budget!N134 -> 845305.53 | H21: =Budget!R134 -> 644045.8 | I21: =Budget!S134 -> 19750 | J21: =Budget!T134 -> 663795.8 | K21: =Budget!X134 -> 304322.28 | L21: =Budget!Y134 -> 13500 | M21: =Budget!Z134 -> 317822.28 | N21: =Budget!AA134 -> 2097611.9 | O21: =Budget!AB134 -> 151500 | P21: =Budget!AC134 -> 2249111.9
A22: Indirect Costs | B22: =Budget!F135 -> 108082.84 | C22: =Budget!G135 -> 0 | D22: =Budget!H135 -> 108082.84 | E22: =Budget!L135 -> 216923.3 | F22: =Budget!M135 -> 0 | G22: =Budget!N135 -> 216923.3 | H22: =Budget!R135 -> 182136.15 | I22: =Budget!S135 -> 0 | J22: =Budget!T135 -> 182136.15 | K22: =Budget!X135 -> 86062.34 | L22: =Budget!Y135 -> 0 | M22: =Budget!Z135 -> 86062.34 | N22: =Budget!AA135 -> 593204.64 | O22: =Budget!AB135 -> 0 | P22: =Budget!AC135 -> 593204.64
A23: Total | B23: =Budget!F136 -> 490271.1 | C23: =Budget!G136 -> 40000 | D23: =Budget!H136 -> 530271.1 | E23: =Budget!L136 -> 983978.83 | F23: =Budget!M136 -> 78250 | G23: =Budget!N136 -> 1062228.8 | H23: =Budget!R136 -> 826181.95 | I23: =Budget!S136 -> 19750 | J23: =Budget!T136 -> 845931.95 | K23: =Budget!X136 -> 390384.62 | L23: =Budget!Y136 -> 13500 | M23: =Budget!Z136 -> 403884.62 | N23: =Budget!AA136 -> 2690816.5 | O23: =Budget!AB136 -> 151500 | P23: =Budget!AC136 -> 2842316.5

Sheet Budget
B1: Partners of the Americas Fertilize Right Colombia Budget 2023
B2: USDA-FAS-10960-0700-10-23-0012 CFDA: 10.960 Technical Agricultural Assistance
B3: Duration: 3 Years, 7.5 months
B4: Country: Colombia
A5: Budget Assumptions
A6: Inflation - US Based Goods/Services - 2% | B6: 1.02
A7: Inflation - Locally Purchased Goods/Services - 3% | B7: 1.03
A8: Merit Based Increases for HQ & Field Staff - 5% | B8: 1.05
A10: *Key Personnel
A11: Line Items | F11: Year 1 | L11: Year 2 | O11: Year 3 | X11: Year 4 | AA11: Total | AB11: Total | AC11: Grand
B12: Unit | C12: Cost | D12: Duration | E12: Type | F12: USDA | G12: Cost Share | H12: Total | I12: Unit | J12: Cost | K12: Duration | L12: USDA | M12: Cost Share | N12: Total | O12: Unit | P12: Cost | Q12: Duration | R12: USDA | S12: Cost Share | T12: Total | U12: Unit | V12: Cost | W12: Duration | X12: USDA | Y12: Cost Share | Z12: Total | AA12: USDA | AB12: Cost Share | AC12: Total
A14: Personnel
A15: Headquarters Personnel | B15: LOE
A16: Program Director | B16: 0.1 | C16: =120000/12 -> 10000 | D16: 12 | E16: /months | F16: =D16*C16*B16 -> 12000 | G16: 0 | H16: =SUM(F16:G16) -> 12000 | I16: =B16 -> 0.1 | J16: =C16*$B$8 -> 10500 | K16: 12 | L16: =I16*J16*K16 -> 12600 | M16: 0 | N16: =SUM(L16:M16) -> 12600 | O16: =B16 -> 0.1 | P16: =C16*$B$8*$B$8 -> 11025 | Q16: 12 | R16: =O16*P16*Q16 -> 13230 | S16: 0 | T16: =SUM(R16:S16) -> 13230 | U16: =O16 -> 0.1 | V16: =C16*$B$8*$B$8*$B$8 -> 11576.25 | W16: 7.5 | X16: =U16*V16*W16 -> 8682.1875 | Y16: 0 | Z16: =SUM(X16:Y16) -> 8682.1875 | AA16: =F16+L16+R16+X16 -> 46512.188 | AB16: =G16+M16+S16+Y16 -> 0 | AC16: =SUM(AA16:AB16) -> 46512.188
A17: Technical Advisor - Senior Program Officer | B17: 0.55 | C17: =65000/12 -> 5416.6667 | D17: 12 | E17: /months | F17: =D17*C17*B17 -> 35750 | G17: 0 | H17: =SUM(F17:G17) -> 35750 | I17: =B17 -> 0.55 | J17: =C17*$B$8 -> 5687.5 | K17: 12 | L17: =I17*J17*K17 -> 37537.5 | M17: 0 | N17: =SUM(L17:M17) -> 37537.5 | O17: =I17 -> 0.55 | P17: =C17*$B$8*$B$8 -> 5971.875 | Q17: 12 | R17: =O17*P17*Q17 -> 39414.375 | S17: 0 | T17: =SUM(R17:S17) -> 39414.375 | U17: =O17 -> 0.55 | V17: =C17*$B$8*$B$8*$B$8 -> 6270.4688 | W17: 7.5 | X17: =U17*V17*W17 -> 25865.684 | Y17: 0 | Z17: =SUM(X17:Y17) -> 25865.684 | AA17: =F17+L17+R17+X17 -> 138567.56 | AB17: =G17+M17+S17+Y17 -> 0 | AC17: =SUM(AA17:AB17) -> 138567.56
A18: Subtotal HQ Personnel | F18: =SUM(F16:F17) -> 47750 | G18: =SUM(G16:G17) -> 0 | H18: =SUM(H16:H17) -> 47750 | L18: =SUM(L16:L17) -> 50137.5 | M18: =SUM(M16:M17) -> 0 | N18: =SUM(N16:N17) -> 50137.5 | R18: =SUM(R16:R17) -> 52644.375 | S18: =SUM(S16:S17) -> 0 | T18: =SUM(T16:T17) -> 52644.375 | X18: =SUM(X16:X17) -> 34547.871 | Y18: =SUM(Y16:Y17) -> 0 | Z18: =SUM(Z16:Z17) -> 34547.871 | AA18: =SUM(AA16:AA17) -> 185079.75 | AB18: =SUM(AB16:AB17) -> 0 | AC18: =SUM(AC16:AC17) -> 185079.75
A20: Field Personnel | B20: LOE
A21: Deputy Director* | B21: 1 | C21: =50000/12 -> 4166.6667 | D21: 11 | E21: /months | F21: =D21*C21*B21 -> 45833.333 | G21: 0 | H21: =SUM(F21:G21) -> 45833.333 | I21: =+B21 -> 1 | J21: =C21*$B$8 -> 4375 | K21: 12 | L21: =J21*K21*I21 -> 52500 | M21: 0 | N21: =SUM(L21:M21) -> 52500 | O21: =+B21 -> 1 | P21: =C21*$B$8*$B$8 -> 4593.75 | Q21: 12 | R21: =Q21*P21*O21 -> 55125 | S21: 0 | T21: =SUM(R21:S21) -> 55125 | U21: =+B21 -> 1 | V21: =C21*$B$8*$B$8*$B$8 -> 4823.4375 | W21: 7.5 | X21: =W21*V21*U21 -> 36175.781 | Y21: 0 | Z21: =SUM(X21:Y21) -> 36175.781 | AA21: =F21+L21+R21+X21 -> 189634.11 | AB21: =G21+M21+S21+Y21 -> 0 | AC21: =SUM(AA21:AB21) -> 189634.11
A22: Finance & Administration Director | B22: 0.15 | C22: =45000/12 -> 3750 | D22: 11 | E22: /months | F22: =D22*C22*B22 -> 6187.5 | G22: 0 | H22: =SUM(F22:G22) -> 6187.5 | I22: =+B22 -> 0.15 | J22: =C22*$B$8 -> 3937.5 | K22: 12 | L22: =J22*K22*I22 -> 7087.5 | M22: 0 | N22: =SUM(L22:M22) -> 7087.5 | O22: =+B22 -> 0.15 | P22: =C22*$B$8*$B$8 -> 4134.375 | Q22: 12 | R22: =Q22*P22*O22 -> 7441.875 | S22: 0 | T22: =SUM(R22:S22) -> 7441.875 | U22: =+B22 -> 0.15 | V22: =C22*$B$8*$B$8*$B$8 -> 4341.0938 | W22: 7.5 | X22: =W22*V22*U22 -> 4883.7305 | Y22: 0 | Z22: =SUM(X22:Y22) -> 4883.7305 | AA22: =F22+L22+R22+X22 -> 25600.605 | AB22: =G22+M22+S22+Y22 -> 0 | AC22: =SUM(AA22:AB22) -> 25600.605
A23: Communications Officer | B23: 0.15 | C23: =25000/12 -> 2083.3333 | D23: 9 | E23: /months | F23: =D23*C23*B23 -> 2812.5 | G23: 0 | H23: =SUM(F23:G23) -> 2812.5 | I23: =+B23 -> 0.15 | J23: =C23*$B$8 -> 2187.5 | K23: 12 | L23: =J23*K23*I23 -> 3937.5 | M23: 0 | N23: =SUM(L23:M23) -> 3937.5 | O23: =+B23 -> 0.15 | P23: =C23*$B$8*$B$8 -> 2296.875 | Q23: 12 | R23: =Q23*P23*O23 -> 4134.375 | S23: 0 | T23: =SUM(R23:S23) -> 4134.375 | U23: =+B23 -> 0.15 | V23: =C23*$B$8*$B$8*$B$8 -> 2411.7188 | W23: 6 | X23: =W23*V23*U23 -> 2170.5469 | Y23: 0 | Z23: =SUM(X23:Y23) -> 2170.5469 | AA23: =F23+L23+R23+X23 -> 13054.922 | AB23: =G23+M23+S23+Y23 -> 0 | AC23: =SUM(AA23:AB23) -> 13054.922
A24: Accountant | B24: 1 | C24: =21000/12 -> 1750 | D24: 9 | E24: /months | F24: =D24*C24*B24 -> 15750 | G24: 0 | H24: =SUM(F24:G24) -> 15750 | I24: =+B24 -> 1 | J24: =C24*$B$8 -> 1837.5 | K24: 12 | L24: =J24*K24*I24 -> 22050 | M24: 0 | N24: =SUM(L24:M24) -> 22050 | O24: =+B24 -> 1 | P24: =C24*$B$8*$B$8 -> 1929.375 | Q24: 12 | R24: =Q24*P24*O24 -> 23152.5 | S24: 0 | T24: =SUM(R24:S24) -> 23152.5 | U24: =+B24 -> 1 | V24: =C24*$B$8*$B$8*$B$8 -> 2025.8438 | W24: 6 | X24: =W24*V24*U24 -> 12155.062 | Y24: 0 | Z24: =SUM(X24:Y24) -> 12155.062 | AA24: =F24+L24+R24+X24 -> 73107.562 | AB24: =G24+M24+S24+Y24 -> 0 | AC24: =SUM(AA24:AB24) -> 73107.562
A25: M&E Director | B25: 0.15 | C25: =45000/12 -> 3750 | D25: 11 | E25: /months | F25: =D25*C25*B25 -> 6187.5 | G25: 0 | H25: =SUM(F25:G25) -> 6187.5 | I25: =+B25 -> 0.15 | J25: =C25*$B$8 -> 3937.5 | K25: 12 | L25: =J25*K25*I25 -> 7087.5 | M25: 0 | N25: =SUM(L25:M25) -> 7087.5 | O25: =+B25 -> 0.15 | P25: =C25*$B$8*$B$8 -> 4134.375 | Q25: 12 | R25: =Q25*P25*O25 -> 7441.875 | S25: 0 | T25: =SUM(R25:S25) -> 7441.875 | U25: =+B25 -> 0.15 | V25: =C25*$B$8*$B$8*$B$8 -> 4341.0938 | W25: 7.5 | X25: =W25*V25*U25 -> 4883.7305 | Y25: 0 | Z25: =SUM(X25:Y25) -> 4883.7305 | AA25: =F25+L25+R25+X25 -> 25600.605 | AB25: =G25+M25+S25+Y25 -> 0 | AC25: =SUM(AA25:AB25) -> 25600.605
A26: M&E Assistant | B26: 1 | C26: =20000/12 -> 1666.6667 | D26: 9 | E26: /months | F26: =D26*C26*B26 -> 15000 | G26: 0 | H26: =SUM(F26:G26) -> 15000 | I26: =+B26 -> 1 | J26: =C26*$B$8 -> 1750 | K26: 12 | L26: =J26*K26*I26 -> 21000 | M26: 0 | N26: =SUM(L26:M26) -> 21000 | O26: =+B26 -> 1 | P26: =C26*$B$8*$B$8 -> 1837.5 | Q26: 12 | R26: =Q26*P26*O26 -> 22050 | S26: 0 | T26: =SUM(R26:S26) -> 22050 | U26: =+B26 -> 1 | V26: =C26*$B$8*$B$8*$B$8 -> 1929.375 | W26: 7 | X26: =W26*V26*U26 -> 13505.625 | Y26: 0 | Z26: =SUM(X26:Y26) -> 13505.625 | AA26: =F26+L26+R26+X26 -> 71555.625 | AB26: =G26+M26+S26+Y26 -> 0 | AC26: =SUM(AA26:AB26) -> 71555.625
A27: Subtotal Field Personnel | F27: =SUM(F21:F26) -> 91770.833 | G27: =SUM(G21:G26) -> 0 | H27: =SUM(H21:H26) -> 91770.833 | L27: =SUM(L21:L26) -> 113662.5 | M27: =SUM(M21:M26) -> 0 | N27: =SUM(N21:N26) -> 113662.5 | R27: =SUM(R21:R26) -> 119345.63 | S27: =SUM(S21:S26) -> 0 | T27: =SUM(T21:T26) -> 119345.63 | X27: =SUM(X21:X26) -> 73774.477 | Y27: =SUM(Y21:Y26) -> 0 | Z27: =SUM(Z21:Z26) -> 73774.477 | AA27: =SUM(AA21:AA26) -> 398553.43 | AB27: =SUM(AB21:AB26) -> 0 | AC27: =SUM(AA27:AB27) -> 398553.43
A29: Personnel Total | F29: =F27+F18 -> 139520.83 | G29: =G27+G18 -> 0 | H29: =H27+H18 -> 139520.83 | L29: =L27+L18 -> 163800 | M29: =M27+M18 -> 0 | N29: =N27+N18 -> 163800 | R29: =R27+R18 -> 171990 | S29: =S27+S18 -> 0 | T29: =T27+T18 -> 171990 | X29: =X27+X18 -> 108322.35 | Y29: =Y27+Y18 -> 0 | Z29: =Z27+Z18 -> 108322.35 | AA29: =AA27+AA18 -> 583633.18 | AB29: =AB27+AB18 -> 0 | AC29: =AC27+AC18 -> 583633.18
A31: Fringe Benefits
A32: HQ Fringe Benefits | B32: LOE
A33: Fringe Benefits - Headquarters | B33: 0.2347 | F33: =(F18)*$B$33 -> 11206.925 | G33: 0 | H33: =SUM(F33:G33) -> 11206.925 | L33: =(L18)*$B$33 -> 11767.271 | M33: 0 | N33: =SUM(L33:M33) -> 11767.271 | R33: =(R18)*$B$33 -> 12355.635 | S33: 0 | T33: =SUM(R33:S33) -> 12355.635 | X33: =(X18)*$B$33 -> 8108.3853 | Y33: 0 | Z33: =SUM(X33:Y33) -> 8108.3853 | AA33: =F33+L33+R33+X33 -> 43438.216 | AB33: =G33+M33+S33+Y33 -> 0 | AC33: =SUM(AA33:AB33) -> 43438.216
A34: Subtotal HQ Fringe Benefits | F34: =SUM(F33:F33) -> 11206.925 | G34: =SUM(G33:G33) -> 0 | H34: =SUM(H33:H33) -> 11206.925 | L34: =SUM(L33:L33) -> 11767.271 | M34: =SUM(M33:M33) -> 0 | N34: =SUM(N33:N33) -> 11767.271 | R34: =SUM(R33:R33) -> 12355.635 | S34: =SUM(S33:S33) -> 0 | T34: =SUM(T33:T33) -> 12355.635 | X34: =SUM(X33:X33) -> 8108.3853 | Y34: =SUM(Y33:Y33) -> 0 | Z34: =SUM(Z33:Z33) -> 8108.3853 | AA34: =SUM(AA33:AA33) -> 43438.216 | AB34: =SUM(AB33:AB33) -> 0 | AC34: =SUM(AC33:AC33) -> 43438.216
A36: Field Fringe Benefits
A37: Fringe Benefits CCN - Colombia (above $3,100 monthly) | B37: 0.53864 | F37: =(F21+F22+F25)*$B$37 -> 31353.337 | G37: 0 | H37: =SUM(F37:G37) -> 31353.337 | L37: =(L21+L22+L25)*$B$37 -> 35913.822 | M37: 0 | N37: =SUM(L37:M37) -> 35913.822 | R37: =(R21+R22+R25)*$B$37 -> 37709.513 | S37: 0 | T37: =SUM(R37:S37) -> 37709.513 | X37: =(X21+X22+X25)*$B$37 -> 24746.868 | Y37: 0 | Z37: =SUM(X37:Y37) -> 24746.868 | AA37: =F37+L37+R37+X37 -> 129723.54 | AB37: =G37+M37+S37+Y37 -> 0 | AC37: =SUM(AA37:AB37) -> 129723.54
A38: Fringe Benefits CCN - Colombia (below $3,100 monthly) | B38: 0.40364 | F38: =(F24+F26+F23)*$B$38 -> 13547.167 | G38: 0 | H38: =SUM(F38:G38) -> 13547.167 | L38: =(L24+L26+L23)*$B$38 -> 18966.035 | M38: 0 | N38: =SUM(L38:M38) -> 18966.035 | R38: =(R24+R26+R23)*$B$38 -> 19914.336 | S38: 0 | T38: =SUM(R38:S38) -> 19914.336 | X38: =(X24+X26+X23)*$B$38 -> 11233.799 | Y38: 0 | Z38: =SUM(X38:Y38) -> 11233.799 | AA38: =F38+L38+R38+X38 -> 63661.338 | AB38: =G38+M38+S38+Y38 -> 0 | AC38: =SUM(AA38:AB38) -> 63661.338
A39: Subtotal Field Fringe Benefits | F39: =SUM(F37:F38) -> 44900.504 | G39: =SUM(G37:G38) -> 0 | H39: =SUM(H37:H38) -> 44900.504 | L39: =SUM(L37:L38) -> 54879.857 | M39: =SUM(M37:M38) -> 0 | N39: =SUM(N37:N38) -> 54879.857 | R39: =SUM(R37:R38) -> 57623.849 | S39: =SUM(S37:S38) -> 0 | T39: =SUM(T37:T38) -> 57623.849 | X39: =SUM(X37:X38) -> 35980.667 | Y39: =SUM(Y37:Y38) -> 0 | Z39: =SUM(Z37:Z38) -> 35980.667 | AA39: =SUM(AA37:AA38) -> 193384.88 | AB39: =SUM(AB37:AB38) -> 0 | AC39: =SUM(AC37:AC38) -> 193384.88
A41: Fringe Benefits Total | F41: =F39+F34 -> 56107.429 | G41: =G39+G34 -> 0 | H41: =H39+H34 -> 56107.429 | L41: =L39+L34 -> 66647.128 | M41: =M39+M34 -> 0 | N41: =N39+N34 -> 66647.128 | R41: =R39+R34 -> 69979.484 | S41: =S39+S34 -> 0 | T41: =T39+T34 -> 69979.484 | X41: =X39+X34 -> 44089.053 | Y41: =Y39+Y34 -> 0 | Z41: =Z39+Z34 -> 44089.053 | AA41: =AA39+AA34 -> 236823.09 | AB41: =AB39+AB34 -> 0 | AC41: =AC39+AC34 -> 236823.09
A43: Travel
A45: HQ Travel
A46: T.1 Project Management Travel to Field
A47: International Airfare to Colombia | B47: 2 | C47: 800 | D47: 1 | E47: /trip | F47: =D47*C47*B47 -> 1600 | G47: 0 | H47: =SUM(F47:G47) -> 1600 | I47: 2 | J47: =C47*$B$6 -> 816 | K47: 1 | L47: =I47*J47*K47 -> 1632 | M47: 0 | N47: =SUM(L47:M47) -> 1632 | O47: 2 | P47: =C47*$B$6*$B$6 -> 832.32 | Q47: 1 | R47: =O47*P47*Q47 -> 1664.64 | S47: 0 | T47: =SUM(R47:S47) -> 1664.64 | U47: 2 | V47: =C47*$B$6*$B$6*$B$6 -> 848.9664 | W47: 1 | X47: =U47*V47*W47 -> 1697.9328 | Y47: 0 | Z47: =SUM(X47:Y47) -> 1697.9328 | AA47: =F47+L47+R47+X47 -> 6594.5728 | AB47: =G47+M47+S47+Y47 -> 0 | AC47: =SUM(AA47:AB47) -> 6594.5728
A48: Meals and Incidentals | B48: =$B$47 -> 2 | C48: 90 | D48: 10 | E48: /day | F48: =D48*C48*B48 -> 1800 | G48: 0 | H48: =SUM(F48:G48) -> 1800 | I48: =$I$47 -> 2 | J48: =C48*$B$6 -> 91.8 | K48: 10 | L48: =I48*J48*K48 -> 1836 | M48: 0 | N48: =SUM(L48:M48) -> 1836 | O48: =$O$47 -> 2 | P48: =C48*$B$6*$B$6 -> 93.636 | Q48: 10 | R48: =O48*P48*Q48 -> 1872.72 | S48: 0 | T48: =SUM(R48:S48) -> 1872.72 | U48: =$U$47 -> 2 | V48: =C48*$B$6*$B$6*$B$6 -> 95.50872 | W48: 10 | X48: =U48*V48*W48 -> 1910.1744 | Y48: 0 | Z48: =SUM(X48:Y48) -> 1910.1744 | AA48: =F48+L48+R48+X48 -> 7418.8944 | AB48: =G48+M48+S48+Y48 -> 0 | AC48: =SUM(AA48:AB48) -> 7418.8944
A49: Lodging | B49: =$B$47 -> 2 | C49: 120 | D49: 10 | E49: /night | F49: =D49*C49*B49 -> 2400 | G49: 0 | H49: =SUM(F49:G49) -> 2400 | I49: =$I$47 -> 2 | J49: =C49*$B$6 -> 122.4 | K49: 10 | L49: =I49*J49*K49 -> 2448 | M49: 0 | N49: =SUM(L49:M49) -> 2448 | O49: =$O$47 -> 2 | P49: =C49*$B$6*$B$6 -> 124.848 | Q49: 10 | R49: =O49*P49*Q49 -> 2496.96 | S49: 0 | T49: =SUM(R49:S49) -> 2496.96 | U49: =$U$47 -> 2 | V49: =C49*$B$6*$B$6*$B$6 -> 127.34496 | W49: 10 | X49: =U49*V49*W49 -> 2546.8992 | Y49: 0 | Z49: =SUM(X49:Y49) -> 2546.8992 | AA49: =F49+L49+R49+X49 -> 9891.8592 | AB49: =G49+M49+S49+Y49 -> 0 | AC49: =SUM(AA49:AB49) -> 9891.8592
A50: Local Transportation | B50: =$B$47 -> 2 | C50: 25 | D50: 10 | E50: /day | F50: =D50*C50*B50 -> 500 | G50: 0 | H50: =SUM(F50:G50) -> 500 | I50: =$I$47 -> 2 | J50: =C50*$B$6 -> 25.5 | K50: 10 | L50: =I50*J50*K50 -> 510 | M50: 0 | N50: =SUM(L50:M50) -> 510 | O50: =$O$47 -> 2 | P50: =C50*$B$6*$B$6 -> 26.01 | Q50: 10 | R50: =O50*P50*Q50 -> 520.2 | S50: 0 | T50: =SUM(R50:S50) -> 520.2 | U50: =$U$47 -> 2 | V50: =C50*$B$6*$B$6*$B$6 -> 26.5302 | W50: 10 | X50: =U50*V50*W50 -> 530.604 | Y50: 0 | Z50: =SUM(X50:Y50) -> 530.604 | AA50: =F50+L50+R50+X50 -> 2060.804 | AB50: =G50+M50+S50+Y50 -> 0 | AC50: =SUM(AA50:AB50) -> 2060.804
A51: Other Travel Related Expenses | B51: =$B$47 -> 2 | C51: 50 | D51: 1 | E51: /trip | F51: =D51*C51*B51 -> 100 | G51: 0 | H51: =SUM(F51:G51) -> 100 | I51: =$I$47 -> 2 | J51: =C51*$B$6 -> 51 | K51: 1 | L51: =I51*J51*K51 -> 102 | M51: 0 | N51: =SUM(L51:M51) -> 102 | O51: =$O$47 -> 2 | P51: =C51*$B$6*$B$6 -> 52.02 | Q51: 1 | R51: =O51*P51*Q51 -> 104.04 | S51: 0 | T51: =SUM(R51:S51) -> 104.04 | U51: =$U$47 -> 2 | V51: =C51*$B$6*$B$6*$B$6 -> 53.0604 | W51: 1 | X51: =U51*V51*W51 -> 106.1208 | Y51: 0 | Z51: =SUM(X51:Y51) -> 106.1208 | AA51: =F51+L51+R51+X51 -> 412.1608 | AB51: =G51+M51+S51+Y51 -> 0 | AC51: =SUM(AA51:AB51) -> 412.1608
A52: Subtotal HQ Travel | F52: =SUM(F47:F51) -> 6400 | G52: =SUM(G47:G51) -> 0 | H52: =SUM(H47:H51) -> 6400 | L52: =SUM(L47:L51) -> 6528 | M52: =SUM(M47:M51) -> 0 | N52: =SUM(N47:N51) -> 6528 | R52: =SUM(R47:R51) -> 6658.56 | S52: =SUM(S47:S51) -> 0 | T52: =SUM(T47:T51) -> 6658.56 | X52: =SUM(X47:X51) -> 6791.7312 | Y52: =SUM(Y47:Y51) -> 0 | Z52: =SUM(Z47:Z51) -> 6791.7312 | AA52: =SUM(AA47:AA51) -> 26378.291 | AB52: =SUM(AB47:AB51) -> 0 | AC52: =SUM(AC47:AC51) -> 26378.291
A54: Field Travel
A55: Local Travel for M&E, Training, and Capacity Building
A56: Transportation (Airfare, Taxis, & Rental Car/Driver) | B56: =(9) -> 9 | C56: 250 | D56: 1 | E56: /trip | F56: =D56*C56*B56 -> 2250 | G56: 0 | H56: =SUM(F56:G56) -> 2250 | I56: =(12) -> 12 | J56: =C56*$B$7 -> 257.5 | K56: 1 | L56: =I56*J56*K56 -> 3090 | M56: 0 | N56: =SUM(L56:M56) -> 3090 | O56: 12 | P56: =C56*$B$7*$B$7 -> 265.225 | Q56: 1 | R56: =O56*P56*Q56 -> 3182.7 | S56: 0 | T56: =SUM(R56:S56) -> 3182.7 | U56: 7 | V56: =C56*$B$7*$B$7*$B$7 -> 273.18175 | W56: 1 | X56: =U56*V56*W56 -> 1912.2723 | Y56: 0 | Z56: =SUM(X56:Y56) -> 1912.2723 | AA56: =F56+L56+R56+X56 -> 10434.972 | AB56: =G56+M56+S56+Y56 -> 0 | AC56: =SUM(AA56:AB56) -> 10434.972
A57: Meals and Incidentals | B57: =$B$56 -> 9 | C57: 80 | D57: 3 | E57: /day | F57: =D57*C57*B57 -> 2160 | G57: 0 | H57: =SUM(F57:G57) -> 2160 | I57: =$I$56 -> 12 | J57: =C57*$B$7 -> 82.4 | K57: 3 | L57: =I57*J57*K57 -> 2966.4 | M57: 0 | N57: =SUM(L57:M57) -> 2966.4 | O57: =$O$56 -> 12 | P57: =C57*$B$7*$B$7 -> 84.872 | Q57: 3 | R57: =O57*P57*Q57 -> 3055.392 | S57: 0 | T57: =SUM(R57:S57) -> 3055.392 | U57: =$U$56 -> 7 | V57: =C57*$B$7*$B$7*$B$7 -> 87.41816 | W57: 3 | X57: =U57*V57*W57 -> 1835.7814 | Y57: 0 | Z57: =SUM(X57:Y57) -> 1835.7814 | AA57: =F57+L57+R57+X57 -> 10017.573 | AB57: =G57+M57+S57+Y57 -> 0 | AC57: =SUM(AA57:AB57) -> 10017.573
A58: Lodging | B58: =$B$56 -> 9 | C58: 100 | D58: 3 | E58: /night | F58: =D58*C58*B58 -> 2700 | G58: 0 | H58: =SUM(F58:G58) -> 2700 | I58: =$I$56 -> 12 | J58: =C58*$B$7 -> 103 | K58: 3 | L58: =I58*J58*K58 -> 3708 | M58: 0 | N58: =SUM(L58:M58) -> 3708 | O58: =$O$56 -> 12 | P58: =C58*$B$7*$B$7 -> 106.09 | Q58: 3 | R58: =O58*P58*Q58 -> 3819.24 | S58: 0 | T58: =SUM(R58:S58) -> 3819.24 | U58: =$U$56 -> 7 | V58: =C58*$B$7*$B$7*$B$7 -> 109.2727 | W58: 3 | X58: =U58*V58*W58 -> 2294.7267 | Y58: 0 | Z58: =SUM(X58:Y58) -> 2294.7267 | AA58: =F58+L58+R58+X58 -> 12521.967 | AB58: =G58+M58+S58+Y58 -> 0 | AC58: =SUM(AA58:AB58) -> 12521.967
A59: Other Travel Related Expenses | B59: =$B$56 -> 9 | C59: 25 | D59: 1 | E59: /trip | F59: =D59*C59*B59 -> 225 | G59: 0 | H59: =SUM(F59:G59) -> 225 | I59: =$I$56 -> 12 | J59: =C59*$B$7 -> 25.75 | K59: 1 | L59: =I59*J59*K59 -> 309 | M59: 0 | N59: =SUM(L59:M59) -> 309 | O59: =$O$56 -> 12 | P59: =C59*$B$7*$B$7 -> 26.5225 | Q59: 1 | R59: =O59*P59*Q59 -> 318.27 | S59: 0 | T59: =SUM(R59:S59) -> 318.27 | U59: =$U$56 -> 7 | V59: =C59*$B$7*$B$7*$B$7 -> 27.318175 | W59: 1 | X59: =U59*V59*W59 -> 191.22723 | Y59: 0 | Z59: =SUM(X59:Y59) -> 191.22723 | AA59: =F59+L59+R59+X59 -> 1043.4972 | AB59: =G59+M59+S59+Y59 -> 0 | AC59: =SUM(AA59:AB59) -> 1043.4972
A62: Subtotal Field Travel | F62: =SUM(F55:F61) -> 7335 | G62: =SUM(G55:G61) -> 0 | H62: =SUM(H55:H61) -> 7335 | L62: =SUM(L55:L61) -> 10073.4 | M62: =SUM(M55:M61) -> 0 | N62: =SUM(N55:N61) -> 10073.4 | R62: =SUM(R55:R61) -> 10375.602 | S62: =SUM(S55:S61) -> 0 | T62: =SUM(T55:T61) -> 10375.602 | X62: =SUM(X55:X61) -> 6234.0075 | Y62: =SUM(Y55:Y61) -> 0 | Z62: =SUM(Z55:Z61) -> 6234.0075 | AA62: =SUM(AA55:AA61) -> 34018.01 | AB62: =SUM(AB55:AB61) -> 0 | AC62: =SUM(AC55:AC61) -> 34018.01
A64: Travel Total | F64: =F62+F52 -> 13735 | G64: =G62+G52 -> 0 | H64: =H62+H52 -> 13735 | L64: =L62+L52 -> 16601.4 | M64: =M62+M52 -> 0 | N64: =N62+N52 -> 16601.4 | R64: =R62+R52 -> 17034.162 | S64: =S62+S52 -> 0 | T64: =T62+T52 -> 17034.162 | X64: =X62+X52 -> 13025.739 | Y64: =Y62+Y52 -> 0 | Z64: =Z62+Z52 -> 13025.739 | AA64: =AA62+AA52 -> 60396.301 | AB64: =AB62+AB52 -> 0 | AC64: =AC62+AC52 -> 60396.301
A66: Equipment
A68: None | B68: 0 | C68: 0 | E68: 0 | F68: =C68*B68 -> 0 | G68: 0 | H68: =SUM(F68:G68) -> 0 | I68: 0 | J68: =C68 -> 0 | L68: =I68*J68 -> 0 | M68: 0 | N68: =SUM(L68:M68) -> 0 | O68: 0 | P68: =C68 -> 0 | R68: =P68*O68 -> 0 | S68: 0 | T68: =SUM(R68:S68) -> 0 | U68: 0 | V68: =C68 -> 0 | X68: =U68*V68 -> 0 | Y68: 0 | Z68: =SUM(X68:Y68) -> 0 | AA68: =F68+L68+R68+X68 -> 0 | AB68: =G68+M68+S68+Y68 -> 0 | AC68: =SUM(AA68:AB68) -> 0
A70: Equipment Total | F70: =SUM(F68:F69) -> 0 | G70: =SUM(G68:G69) -> 0 | H70: =SUM(H68:H69) -> 0 | L70: =SUM(L68:L69) -> 0 | M70: =SUM(M68:M69) -> 0 | N70: =SUM(N68:N69) -> 0 | R70: =SUM(R68:R69) -> 0 | S70: =SUM(S68:S69) -> 0 | T70: =SUM(T68:T69) -> 0 | X70: =SUM(X68:X69) -> 0 | Y70: =SUM(Y68:Y69) -> 0 | Z70: =SUM(Z68:Z69) -> 0 | AA70: =SUM(AA68:AA69) -> 0 | AB70: =SUM(AB68:AB69) -> 0 | AC70: =SUM(AA70:AB70) -> 0
A72: Supplies
A74: HQ Office Supplies
A75: Laptop, Bag, Accessories | B75: 2 | C75: 1200 | D75: 1 | E75: /unit | F75: =C75*B75 -> 2400 | G75: 0 | H75: =SUM(F75:G75) -> 2400 | I75: 0 | J75: =C75*$B$6 -> 1224 | K75: 0 | L75: =I75*J75 -> 0 | M75: 0 | N75: =SUM(L75:M75) -> 0 | O75: =L75*M75*N75 -> 0 | P75: =C75*$B$6*$B$6 -> 1248.48 | Q75: 0 | R75: =P75*O75 -> 0 | S75: 0 | T75: =SUM(R75:S75) -> 0 | U75: =R75*S75*T75 -> 0 | V75: =C75*$B$6*$B$6*$B$6 -> 1273.4496 | W75: 0 | X75: =V75*U75 -> 0 | Y75: 0 | Z75: =SUM(X75:Y75) -> 0 | AA75: =F75+L75+R75+X75 -> 2400 | AB75: =G75+M75+S75+Y75 -> 0 | AC75: =SUM(AA75:AB75) -> 2400
A76: Program Specific Office Supplies and Stationary for HQ | B76: 1 | C76: 150 | D76: 12 | E76: /month | F76: =C76*B76*D76 -> 1800 | G76: 0 | H76: =SUM(F76:G76) -> 1800 | I76: 1 | J76: =C76*$B$6 -> 153 | K76: 12 | L76: =I76*J76*K76 -> 1836 | M76: 0 | N76: =SUM(L76:M76) -> 1836 | O76: 1 | P76: =C76*$B$6*$B$6 -> 156.06 | Q76: 12 | R76: =P76*O76*Q76 -> 1872.72 | S76: 0 | T76: =SUM(R76:S76) -> 1872.72 | U76: 1 | V76: =C76*$B$6*$B$6*$B$6 -> 159.1812 | W76: 7.5 | X76: =V76*U76*W76 -> 1193.859 | Y76: 0 | Z76: =SUM(X76:Y76) -> 1193.859 | AA76: =F76+L76+R76+X76 -> 6702.579 | AB76: =G76+M76+S76+Y76 -> 0 | AC76: =SUM(AA76:AB76) -> 6702.579
A77: Subtotal HQ Office Supplies | F77: =SUM(F75:F76) -> 4200 | G77: =SUM(G75:G76) -> 0 | H77: =SUM(H75:H76) -> 4200 | L77: =SUM(L75:L76) -> 1836 | M77: =SUM(M75:M76) -> 0 | N77: =SUM(N75:N76) -> 1836 | R77: =SUM(R75:R76) -> 1872.72 | S77: =SUM(S75:S76) -> 0 | T77: =SUM(T75:T76) -> 1872.72 | X77: =SUM(X75:X76) -> 1193.859 | Y77: =SUM(Y75:Y76) -> 0 | Z77: =SUM(Z75:Z76) -> 1193.859 | AA77: =SUM(AA75:AA76) -> 9102.579 | AB77: =SUM(AB75:AB76) -> 0 | AC77: =SUM(AA77:AB77) -> 9102.579
A79: Field Office Supplies
A80: Laptop, Bag, & Accessories | B80: 9 | C80: 1200 | D80: 1 | E80: /unit | F80: =C80*B80 -> 10800 | G80: 0 | H80: =SUM(F80:G80) -> 10800 | I80: 0 | J80: =C80*$B$7 -> 1236 | K80: 1 | L80: =I80*J80 -> 0 | M80: 0 | N80: =SUM(L80:M80) -> 0 | O80: =L80*M80*N80 -> 0 | P80: =C80*$B$7*$B$7 -> 1273.08 | Q80: 1 | R80: =P80*O80 -> 0 | S80: 0 | T80: =SUM(R80:S80) -> 0 | U80: =R80*S80*T80 -> 0 | V80: =C80*$B$7*$B$7*$B$7 -> 1311.2724 | W80: 0 | X80: =V80*U80 -> 0 | Y80: 0 | Z80: =SUM(X80:Y80) -> 0 | AA80: =F80+L80+R80+X80 -> 10800 | AB80: =G80+M80+S80+Y80 -> 0 | AC80: =SUM(AA80:AB80) -> 10800
A81: Office Furniture (Includes Desk, Chairs, Table, Shelves, & Filing Cabinet) - Main Office & 2 Satellite Offices | B81: 1 | C81: 5000 | D81: 1 | E81: /unit | F81: =C81*B81 -> 5000 | G81: 0 | H81: =SUM(F81:G81) -> 5000 | I81: 0 | J81: =C81*$B$7 -> 5150 | K81: 1 | L81: =I81*J81 -> 0 | M81: 0 | N81: =SUM(L81:M81) -> 0 | O81: =L81*M81*N81 -> 0 | P81: =C81*$B$7*$B$7 -> 5304.5 | Q81: 1 | R81: =P81*O81 -> 0 | S81: 0 | T81: =SUM(R81:S81) -> 0 | U81: =R81*S81*T81 -> 0 | V81: =C81*$B$7*$B$7*$B$7 -> 5463.635 | W81: 1 | X81: =V81*U81 -> 0 | Y81: 0 | Z81: =SUM(X81:Y81) -> 0 | AA81: =F81+L81+R81+X81 -> 5000 | AB81: =G81+M81+S81+Y81 -> 0 | AC81: =SUM(AA81:AB81) -> 5000
A82: General Office Supplies, PPE, and Stationary for Field Office | B82: 1 | C82: 250 | D82: 8 | E82: /month | F82: =D82*C82*B82 -> 2000 | G82: 0 | H82: =SUM(F82:G82) -> 2000 | I82: 1 | J82: =C82*$B$7 -> 257.5 | K82: 12 | L82: =K82*I82*J82 -> 3090 | M82: 0 | N82: =SUM(L82:M82) -> 3090 | O82: 1 | P82: =C82*$B$7*$B$7 -> 265.225 | Q82: 12 | R82: =P82*Q82*O82 -> 3182.7 | S82: 0 | T82: =SUM(R82:S82) -> 3182.7 | U82: 1 | V82: =C82*$B$7*$B$7*$B$7 -> 273.18175 | W82: 7.5 | X82: =V82*U82*W82 -> 2048.8631 | Y82: 0 | Z82: =SUM(X82:Y82) -> 2048.8631 | AA82: =F82+L82+R82+X82 -> 10321.563 | AB82: =G82+M82+S82+Y82 -> 0 | AC82: =SUM(AA82:AB82) -> 10321.563
A83: Subtotal Field Office Supplies | F83: =SUM(F80:F82) -> 17800 | G83: =SUM(G80:G82) -> 0 | H83: =SUM(H80:H82) -> 17800 | L83: =SUM(L80:L82) -> 3090 | M83: =SUM(M80:M82) -> 0 | N83: =SUM(N80:N82) -> 3090 | R83: =SUM(R80:R82) -> 3182.7 | S83: =SUM(S80:S82) -> 0 | T83: =SUM(T80:T82) -> 3182.7 | X83: =SUM(X80:X82) -> 2048.8631 | Y83: =SUM(Y80:Y82) -> 0 | Z83: =SUM(Z80:Z82) -> 2048.8631 | AA83: =SUM(AA80:AA82) -> 26121.563 | AB83: =SUM(AB80:AB82) -> 0 | AC83: =SUM(AC80:AC82) -> 26121.563
A85: Supplies Total | F85: =F83+F77 -> 22000 | G85: =G83+G77 -> 0 | H85: =H83+H77 -> 22000 | L85: =L83+L77 -> 4926 | M85: =M83+M77 -> 0 | N85: =N83+N77 -> 4926 | R85: =R83+R77 -> 5055.42 | S85: =S83+S77 -> 0 | T85: =T83+T77 -> 5055.42 | X85: =X83+X77 -> 3242.7221 | Y85: =Y83+Y77 -> 0 | Z85: =Z83+Z77 -> 3242.7221 | AA85: =AA83+AA77 -> 35224.142 | AB85: =AB83+AB77 -> 0 | AC85: =AB85+AA85 -> 35224.142
A87: Contractual
A89: Contracts
A90: Subrecipient to Agrosavia | B90: 1 | C90: 43000 | D90: 1 | E90: /unit | F90: =D90*C90*B90 -> 43000 | G90: 0 | H90: =SUM(F90:G90) -> 43000 | I90: 1 | J90: 340000 | K90: 1 | L90: =K90*J90*I90 -> 340000 | M90: 0 | N90: =SUM(L90:M90) -> 340000 | O90: 1 | P90: =J90 -> 340000 | Q90: 1 | R90: =Q90*P90*O90 -> 340000 | S90: 0 | T90: =SUM(R90:S90) -> 340000 | U90: 1 | V90: 77000 | W90: 1 | X90: =W90*V90*U90 -> 77000 | Y90: 0 | Z90: =SUM(X90:Y90) -> 77000 | AA90: =F90+L90+R90+X90 -> 800000 | AB90: =G90+M90+S90+Y90 -> 0 | AC90: =SUM(AA90:AB90) -> 800000
A91: Contract for Application (PaLaTierra) Development | B91: 1 | C91: 40000 | D91: 1 | E91: /unit | F91: =D91*C91*B91 -> 40000 | G91: 0 | H91: =SUM(F91:G91) -> 40000 | I91: 0 | J91: =C91 -> 40000 | K91: 0 | L91: =K91*J91*I91 -> 0 | M91: 0 | N91: =SUM(L91:M91) -> 0 | O91: 0 | P91: =C91 -> 40000 | Q91: 0 | R91: =Q91*P91*O91 -> 0 | S91: 0 | T91: =SUM(R91:S91) -> 0 | U91: 0 | V91: =C91 -> 40000 | W91: 0 | X91: =W91*V91*U91 -> 0 | Y91: 0 | Z91: =SUM(X91:Y91) -> 0 | AA91: =F91+L91+R91+X91 -> 40000 | AB91: =G91+M91+S91+Y91 -> 0 | AC91: =SUM(AA91:AB91) -> 40000
A92: Contract for Website Development | B92: 1 | C92: 20000 | D92: 1 | E92: /unit | F92: =D92*C92*B92 -> 20000 | G92: 0 | H92: =SUM(F92:G92) -> 20000 | I92: 0 | J92: =C92 -> 20000 | K92: 0 | L92: =K92*J92*I92 -> 0 | M92: 0 | N92: =SUM(L92:M92) -> 0 | O92: 0 | P92: =C92 -> 20000 | Q92: 0 | R92: =Q92*P92*O92 -> 0 | S92: 0 | T92: =SUM(R92:S92) -> 0 | U92: 0 | V92: =C92 -> 20000 | W92: 0 | X92: =W92*V92*U92 -> 0 | Y92: 0 | Z92: =SUM(X92:Y92) -> 0 | AA92: =F92+L92+R92+X92 -> 20000 | AB92: =G92+M92+S92+Y92 -> 0 | AC92: =SUM(AA92:AB92) -> 20000
A94: Contractual Total | F94: =SUM(F90:F92) -> 103000 | G94: =SUM(G90:G92) -> 0 | H94: =SUM(H90:H92) -> 103000 | L94: =SUM(L90:L92) -> 340000 | M94: =SUM(M90:M92) -> 0 | N94: =SUM(N90:N92) -> 340000 | R94: =SUM(R90:R92) -> 340000 | S94: =SUM(S90:S92) -> 0 | T94: =SUM(T90:T92) -> 340000 | X94: =SUM(X90:X92) -> 77000 | Y94: =SUM(Y90:Y92) -> 0 | Z94: =SUM(Z90:Z92) -> 77000 | AA94: =SUM(AA90:AA92) -> 860000 | AB94: =SUM(AB90:AB92) -> 0 | AC94: =SUM(AC90:AC92) -> 860000
A96: Other Direct Costs
A98: HQ - Other Direct Costs
A99: Dues, Licenses & Subscriptions | B99: 1 | C99: 250 | D99: 12 | E99: /month | F99: =D99*C99*B99 -> 3000 | G99: 0 | H99: =SUM(F99:G99) -> 3000 | I99: 1 | J99: =C99*$B$6 -> 255 | K99: 12 | L99: =I99*J99*K99 -> 3060 | M99: 0 | N99: =SUM(L99:M99) -> 3060 | O99: 1 | P99: =C99*$B$6*$B$6 -> 260.1 | Q99: 12 | R99: =O99*P99*Q99 -> 3121.2 | S99: 0 | T99: =SUM(R99:S99) -> 3121.2 | U99: 1 | V99: =C99*$B$6*$B$6*$B$6 -> 265.302 | W99: 7.5 | X99: =U99*V99*W99 -> 1989.765 | Y99: 0 | Z99: =SUM(X99:Y99) -> 1989.765 | AA99: =F99+L99+R99+X99 -> 11170.965 | AB99: =G99+M99+S99+Y99 -> 0 | AC99: =SUM(AA99:AB99) -> 11170.965
A100: Meetings/Events - HQ | B100: 1 | C100: 1000 | D100: 1 | E100: /year | F100: =D100*C100*B100 -> 1000 | G100: 0 | H100: =SUM(F100:G100) -> 1000 | I100: 1 | J100: =C100*$B$6 -> 1020 | K100: 1 | L100: =I100*J100*K100 -> 1020 | M100: 0 | N100: =SUM(L100:M100) -> 1020 | O100: 1 | P100: =C100*$B$6*$B$6 -> 1040.4 | Q100: 1 | R100: =O100*P100*Q100 -> 1040.4 | S100: 0 | T100: =SUM(R100:S100) -> 1040.4 | U100: 1 | V100: =C100*$B$6*$B$6*$B$6 -> 1061.208 | W100: 1 | X100: =U100*V100*W100 -> 1061.208 | Y100: 0 | Z100: =SUM(X100:Y100) -> 1061.208 | AA100: =F100+L100+R100+X100 -> 4121.608 | AB100: =G100+M100+S100+Y100 -> 0 | AC100: =SUM(AA100:AB100) -> 4121.608
A101: Subtotal HQ Other Direct Costs | F101: =SUM(F99:F100) -> 4000 | G101: =SUM(G99:G100) -> 0 | H101: =SUM(H99:H100) -> 4000 | L101: =SUM(L99:L100) -> 4080 | M101: =SUM(M99:M100) -> 0 | N101: =SUM(N99:N100) -> 4080 | R101: =SUM(R99:R100) -> 4161.6 | S101: =SUM(S99:S100) -> 0 | T101: =SUM(T99:T100) -> 4161.6 | X101: =SUM(X99:X100) -> 3050.973 | Y101: =SUM(Y99:Y100) -> 0 | Z101: =SUM(Z99:Z100) -> 3050.973 | AA101: =SUM(AA99:AA100) -> 15292.573 | AB101: =SUM(AB99:AB100) -> 0 | AC101: =SUM(AC99:AC100) -> 15292.573
A103: Field Office (FO) - Other Direct Costs
A104: Dues, Licenses, & Subscriptions | B104: 1 | C104: 325 | D104: 9 | E104: /month | F104: =D104*C104*B104 -> 2925 | G104: 0 | H104: =SUM(F104:G104) -> 2925 | I104: 1 | J104: =C104*$B$7 -> 334.75 | K104: 12 | L104: =I104*J104*K104 -> 4017 | M104: 0 | N104: =SUM(L104:M104) -> 4017 | O104: 1 | P104: =C104*$B$7*$B$7 -> 344.7925 | Q104: 12 | R104: =Q104*P104*O104 -> 4137.51 | S104: 0 | T104: =SUM(R104:S104) -> 4137.51 | U104: 1 | V104: =C104*$B$7*$B$7*$B$7 -> 355.13628 | W104: 3 | X104: =W104*V104*U104 -> 1065.4088 | Y104: 0 | Z104: =SUM(X104:Y104) -> 1065.4088 | AA104: =F104+L104+R104+X104 -> 12144.919 | AB104: =G104+M104+S104+Y104 -> 0 | AC104: =SUM(AA104:AB104) -> 12144.919
A105: Courier Fees/ Postage Services | B105: 1 | C105: 25 | D105: 6 | E105: /month | F105: =D105*C105*B105 -> 150 | G105: 0 | H105: =SUM(F105:G105) -> 150 | I105: 1 | J105: =C105*$B$7 -> 25.75 | K105: 12 | L105: =I105*J105*K105 -> 309 | M105: 0 | N105: =SUM(L105:M105) -> 309 | O105: 1 | P105: =C105*$B$7*$B$7 -> 26.5225 | Q105: 12 | R105: =Q105*P105*O105 -> 318.27 | S105: 0 | T105: =SUM(R105:S105) -> 318.27 | U105: 1 | V105: =C105*$B$7*$B$7*$B$7 -> 27.318175 | W105: 3 | X105: =W105*V105*U105 -> 81.954525 | Y105: 0 | Z105: =SUM(X105:Y105) -> 81.954525 | AA105: =F105+L105+R105+X105 -> 859.22452 | AB105: =G105+M105+S105+Y105 -> 0 | AC105: =SUM(AA105:AB105) -> 859.22452
A106: Banking & Cash Handling Fees | B106: 1 | C106: 150 | D106: 9 | E106: /month | F106: =D106*C106*B106 -> 1350 | G106: 0 | H106: =SUM(F106:G106) -> 1350 | I106: 1 | J106: =C106*$B$7 -> 154.5 | K106: 12 | L106: =I106*J106*K106 -> 1854 | M106: 0 | N106: =SUM(L106:M106) -> 1854 | O106: 1 | P106: =C106*$B$7*$B$7 -> 159.135 | Q106: 12 | R106: =Q106*P106*O106 -> 1909.62 | S106: 0 | T106: =SUM(R106:S106) -> 1909.62 | U106: 1 | V106: =C106*$B$7*$B$7*$B$7 -> 163.90905 | W106: 3 | X106: =W106*V106*U106 -> 491.72715 | Y106: 0 | Z106: =SUM(X106:Y106) -> 491.72715 | AA106: =F106+L106+R106+X106 -> 5605.3471 | AB106: =G106+M106+S106+Y106 -> 0 | AC106: =SUM(AA106:AB106) -> 5605.3471
A107: Procurement/Advertising/Recruitment Fees | B107: 1 | C107: 500 | D107: 1 | E107: /year | F107: =D107*C107*B107 -> 500 | G107: 0 | H107: =SUM(F107:G107) -> 500 | I107: 1 | J107: =C107*$B$7 -> 515 | K107: 1 | L107: =I107*J107*K107 -> 515 | M107: 0 | N107: =SUM(L107:M107) -> 515 | O107: 1 | P107: =C107*$B$7*$B$7 -> 530.45 | Q107: 1 | R107: =Q107*P107*O107 -> 530.45 | S107: 0 | T107: =SUM(R107:S107) -> 530.45 | U107: 1 | V107: =C107*$B$7*$B$7*$B$7 -> 546.3635 | W107: 1 | X107: =W107*V107*U107 -> 546.3635 | Y107: 0 | Z107: =SUM(X107:Y107) -> 546.3635 | AA107: =F107+L107+R107+X107 -> 2091.8135 | AB107: =G107+M107+S107+Y107 -> 0 | AC107: =SUM(AA107:AB107) -> 2091.8135
A108: Meetings and Events | B108: 1 | C108: 150 | D108: 6 | E108: /month | F108: =D108*C108*B108 -> 900 | G108: 0 | H108: =SUM(F108:G108) -> 900 | I108: 1 | J108: =C108*$B$7 -> 154.5 | K108: 12 | L108: =I108*J108*K108 -> 1854 | M108: 0 | N108: =SUM(L108:M108) -> 1854 | O108: 1 | P108: =C108*$B$7*$B$7 -> 159.135 | Q108: 12 | R108: =Q108*P108*O108 -> 1909.62 | S108: 0 | T108: =SUM(R108:S108) -> 1909.62 | U108: 1 | V108: =C108*$B$7*$B$7*$B$7 -> 163.90905 | W108: 3 | X108: =W108*V108*U108 -> 491.72715 | Y108: 0 | Z108: =SUM(X108:Y108) -> 491.72715 | AA108: =F108+L108+R108+X108 -> 5155.3471 | AB108: =G108+M108+S108+Y108 -> 0 | AC108: =SUM(AA108:AB108) -> 5155.3471
A109: Office Communications (Ex. Phone, Internet, Email) | B109: 1 | C109: 350 | D109: 6 | E109: /month | F109: =D109*C109*B109 -> 2100 | G109: 0 | H109: =SUM(F109:G109) -> 2100 | I109: 1 | J109: =C109*$B$7 -> 360.5 | K109: 12 | L109: =I109*J109*K109 -> 4326 | M109: 0 | N109: =SUM(L109:M109) -> 4326 | O109: 1 | P109: =C109*$B$7*$B$7 -> 371.315 | Q109: 12 | R109: =Q109*P109*O109 -> 4455.78 | S109: 0 | T109: =SUM(R109:S109) -> 4455.78 | U109: 1 | V109: =C109*$B$7*$B$7*$B$7 -> 382.45445 | W109: 3 | X109: =W109*V109*U109 -> 1147.3634 | Y109: 0 | Z109: =SUM(X109:Y109) -> 1147.3634 | AA109: =F109+L109+R109+X109 -> 12029.143 | AB109: =G109+M109+S109+Y109 -> 0 | AC109: =SUM(AA109:AB109) -> 12029.143
A110: Office Rent & Office Maintenance & Utilities | B110: 1 | C110: 750 | D110: 6 | E110: /month | F110: =D110*C110*B110 -> 4500 | G110: 0 | H110: =SUM(F110:G110) -> 4500 | I110: 1 | J110: =C110*$B$7 -> 772.5 | K110: 12 | L110: =I110*J110*K110 -> 9270 | M110: 0 | N110: =SUM(L110:M110) -> 9270 | O110: 1 | P110: =C110*$B$7*$B$7 -> 795.675 | Q110: 12 | R110: =Q110*P110*O110 -> 9548.1 | S110: 0 | T110: =SUM(R110:S110) -> 9548.1 | U110: 1 | V110: =C110*$B$7*$B$7*$B$7 -> 819.54525 | W110: 3 | X110: =W110*V110*U110 -> 2458.6358 | Y110: 0 | Z110: =SUM(X110:Y110) -> 2458.6358 | AA110: =F110+L110+R110+X110 -> 25776.736 | AB110: =G110+M110+S110+Y110 -> 0 | AC110: =SUM(AA110:AB110) -> 25776.736
A111: Payroll and Accounting Costs | B111: 1 | C111: 100 | D111: 9 | E111: /month | F111: =D111*C111*B111 -> 900 | G111: 0 | H111: =SUM(F111:G111) -> 900 | I111: 1 | J111: =C111*$B$7 -> 103 | K111: 12 | L111: =I111*J111*K111 -> 1236 | M111: 0 | N111: =SUM(L111:M111) -> 1236 | O111: 1 | P111: =C111*$B$7*$B$7 -> 106.09 | Q111: 12 | R111: =Q111*P111*O111 -> 1273.08 | S111: 0 | T111: =SUM(R111:S111) -> 1273.08 | U111: 1 | V111: =C111*$B$7*$B$7*$B$7 -> 109.2727 | W111: 3 | X111: =W111*V111*U111 -> 327.8181 | Y111: 0 | Z111: =SUM(X111:Y111) -> 327.8181 | AA111: =F111+L111+R111+X111 -> 3736.8981 | AB111: =G111+M111+S111+Y111 -> 0 | AC111: =SUM(AA111:AB111) -> 3736.8981
A112: Legal Fees | B112: 1 | C112: 1000 | D112: 1 | E112: /year | F112: =D112*C112*B112 -> 1000 | G112: 0 | H112: =SUM(F112:G112) -> 1000 | I112: 1 | J112: =C112*$B$7 -> 1030 | K112: 1 | L112: =I112*J112*K112 -> 1030 | M112: 0 | N112: =SUM(L112:M112) -> 1030 | O112: 1 | P112: =C112*$B$7*$B$7 -> 1060.9 | Q112: 1 | R112: =Q112*P112*O112 -> 1060.9 | S112: 0 | T112: =SUM(R112:S112) -> 1060.9 | U112: 1 | V112: =C112*$B$7*$B$7*$B$7 -> 1092.727 | W112: 1 | X112: =W112*V112*U112 -> 1092.727 | Y112: 0 | Z112: =SUM(X112:Y112) -> 1092.727 | AA112: =F112+L112+R112+X112 -> 4183.627 | AB112: =G112+M112+S112+Y112 -> 0 | AC112: =SUM(AA112:AB112) -> 4183.627
A114: Activities
A115: Soil Tests | B115: 500 | C115: 25 | D115: 1 | E115: /test | F115: 0 | G115: =D115*C115*B115 -> 12500 | H115: =SUM(F115:G115) -> 12500 | I115: 750 | J115: =C115 -> 25 | K115: 1 | L115: 0 | M115: =K115*J115*I115 -> 18750 | N115: =SUM(L115:M115) -> 18750 | O115: 750 | P115: =C115 -> 25 | Q115: 1 | R115: 0 | S115: =Q115*P115*O115 -> 18750 | T115: =SUM(R115:S115) -> 18750 | U115: 500 | V115: =C115 -> 25 | W115: 1 | X115: 0 | Y115: =W115*V115*U115 -> 12500 | Z115: =SUM(X115:Y115) -> 12500 | AA115: =F115+L115+R115+X115 -> 0 | AB115: =G115+M115+S115+Y115 -> 62500 | AC115: =SUM(AA115:AB115) -> 62500
A116: Demonstration Plots (includes land, labor, seeds, tools, & maintenance) | B116: 1 | C116: 15000 | D116: 1 | E116: /plot | F116: =C116*B116 -> 15000 | G116: =B116*D116*6500 -> 6500 | H116: =SUM(F116:G116) -> 21500 | I116: 9 | J116: =C116 -> 15000 | K116: 1 | L116: =I116*J116 -> 135000 | M116: =I116*K116*6500 -> 58500 | N116: =SUM(L116:M116) -> 193500 | O116: 0 | P116: =C116 -> 15000 | Q116: 1 | R116: =P116*O116 -> 0 | S116: =Q116*O116*5000 -> 0 | T116: =SUM(R116:S116) -> 0 | U116: 0 | V116: =C116 -> 15000 | W116: 0 | X116: =V116*U116 -> 0 | Y116: 0 | Z116: =SUM(X116:Y116) -> 0 | AA116: =F116+L116+R116+X116 -> 150000 | AB116: =G116+M116+S116+Y116 -> 65000 | AC116: =SUM(AA116:AB116) -> 215000
A117: License and Use of Existing PaLaTierra App | B117: 1 | C117: 20000 | D117: 1 | E117: /unit | F117: 0 | G117: =B117*C117 -> 20000 | H117: =SUM(F117:G117) -> 20000 | I117: 0 | J117: =C117 -> 20000 | K117: 1 | L117: =I117*J117 -> 0 | M117: 0 | N117: =SUM(L117:M117) -> 0 | O117: 0 | P117: =C117 -> 20000 | Q117: 1 | R117: =P117*O117 -> 0 | S117: 0 | T117: =SUM(R117:S117) -> 0 | U117: 0 | V117: =C117 -> 20000 | W117: 1 | X117: =V117*U117 -> 0 | Y117: 0 | Z117: =SUM(X117:Y117) -> 0 | AA117: =F117+L117+R117+X117 -> 0 | AB117: =G117+M117+S117+Y117 -> 20000 | AC117: =SUM(AA117:AB117) -> 20000
A118: Printing of Educational Materials & Resources | B118: 1 | C118: 1000 | D118: 1 | E118: /unit | F118: =C118*B118 -> 1000 | G118: 0 | H118: =SUM(F118:G118) -> 1000 | I118: 1 | J118: =C118 -> 1000 | K118: 0 | L118: =I118*J118 -> 1000 | M118: 0 | N118: =SUM(L118:M118) -> 1000 | O118: 0 | P118: =C118 -> 1000 | Q118: 0 | R118: =P118*O118 -> 0 | S118: 0 | T118: =SUM(R118:S118) -> 0 | U118: 0 | V118: =C118 -> 1000 | W118: 0 | X118: =V118*U118 -> 0 | Y118: 0 | Z118: =SUM(X118:Y118) -> 0 | AA118: =F118+L118+R118+X118 -> 2000 | AB118: =G118+M118+S118+Y118 -> 0 | AC118: =SUM(AA118:AB118) -> 2000
A119: Dissemination of Extension Materials | B119: 1 | C119: 1000 | D119: 1 | E119: /year | F119: 0 | G119: =B119*C119 -> 1000 | H119: =SUM(F119:G119) -> 1000 | I119: 1 | J119: =C119 -> 1000 | K119: 1 | L119: 0 | M119: =I119*J119 -> 1000 | N119: =SUM(L119:M119) -> 1000 | O119: 1 | P119: =C119 -> 1000 | Q119: 1 | R119: 0 | S119: =+O119*P119 -> 1000 | T119: =SUM(R119:S119) -> 1000 | U119: 1 | V119: =C119 -> 1000 | W119: 1 | X119: 0 | Y119: =+U119*V119 -> 1000 | Z119: =SUM(X119:Y119) -> 1000 | AA119: =F119+L119+R119+X119 -> 0 | AB119: =G119+M119+S119+Y119 -> 4000 | AC119: =SUM(AA119:AB119) -> 4000
A120: Community of Practice Roundtables | B120: 2 | C120: 250 | D120: 1 | E120: /meeting | F120: =C120*B120 -> 500 | G120: 0 | H120: =SUM(F120:G120) -> 500 | I120: 4 | J120: =C120 -> 250 | K120: 1 | L120: =I120*J120 -> 1000 | M120: 0 | N120: =SUM(L120:M120) -> 1000 | O120: 4 | P120: =C120 -> 250 | Q120: 1 | R120: =P120*O120 -> 1000 | S120: 0 | T120: =SUM(R120:S120) -> 1000 | U120: 2 | V120: =C120 -> 250 | W120: 0 | X120: =V120*U120 -> 500 | Y120: 0 | Z120: =SUM(X120:Y120) -> 500 | AA120: =F120+L120+R120+X120 -> 3000 | AB120: =G120+M120+S120+Y120 -> 0 | AC120: =SUM(AA120:AB120) -> 3000
A121: Registration for Conferences on Climate and Fertilizer | B121: 2 | C121: 2500 | D121: 1 | E121: /year | F121: =C121*B121 -> 5000 | G121: 0 | H121: =SUM(F121:G121) -> 5000 | I121: 2 | J121: =C121 -> 2500 | K121: 1 | L121: =I121*J121 -> 5000 | M121: 0 | N121: =SUM(L121:M121) -> 5000 | O121: 2 | P121: =C121 -> 2500 | Q121: 1 | R121: =P121*O121 -> 5000 | S121: 0 | T121: =SUM(R121:S121) -> 5000 | U121: 2 | V121: =C121 -> 2500 | W121: 1 | X121: =V121*U121 -> 5000 | Y121: 0 | Z121: =SUM(X121:Y121) -> 5000 | AA121: =F121+L121+R121+X121 -> 20000 | AB121: =G121+M121+S121+Y121 -> 0 | AC121: =SUM(AA121:AB121) -> 20000
A122: Annual Community of Practice Summit | B122: 0 | C122: 40000 | D122: 1 | E122: /workshop | F122: =C122*B122 -> 0 | G122: 0 | H122: =SUM(F122:G122) -> 0 | I122: 0 | J122: =C122 -> 40000 | K122: 1 | L122: =I122*J122 -> 0 | M122: 0 | N122: =SUM(L122:M122) -> 0 | O122: 0 | P122: =C122 -> 40000 | Q122: 1 | R122: =P122*O122 -> 0 | S122: 0 | T122: =SUM(R122:S122) -> 0 | U122: 1 | V122: =C122 -> 40000 | W122: 1 | X122: =V122*U122 -> 40000 | Y122: 0 | Z122: =SUM(X122:Y122) -> 40000 | AA122: =F122+L122+R122+X122 -> 40000 | AB122: =G122+M122+S122+Y122 -> 0 | AC122: =SUM(AA122:AB122) -> 40000
A124: Monitoring, Evaluation, and Collection of Reliable Data
A125: M&E Database Set-up and Subscription | B125: 1 | C125: 3500 | D125: 1 | E125: /year | F125: =D125*C125*B125 -> 3500 | G125: 0 | H125: =SUM(F125:G125) -> 3500 | I125: 1 | J125: =C125*$B$6 -> 3570 | K125: 1 | L125: =K125*J125*I125 -> 3570 | M125: 0 | N125: =SUM(L125:M125) -> 3570 | O125: 1 | P125: =C125*$B$6*$B$6 -> 3641.4 | Q125: 1 | R125: =Q125*P125*O125 -> 3641.4 | S125: 0 | T125: =SUM(R125:R125) -> 3641.4 | U125: 1 | V125: =C125*$B$6*$B$6*$B$6 -> 3714.228 | W125: 0.5 | X125: =W125*V125*U125 -> 1857.114 | Y125: 0 | Z125: =SUM(X125:Y125) -> 1857.114 | AA125: =F125+L125+R125+X125 -> 12568.514 | AB125: =G125+M125+S125+Y125 -> 0 | AC125: =SUM(AA125:AB125) -> 12568.514
A126: Data Collection Tools | B126: 1 | C126: 1500 | D126: 1 | E126: /unit | F126: =C126*B126 -> 1500 | G126: 0 | H126: =SUM(F126:G126) -> 1500 | I126: 0 | J126: =C126*$B$6 -> 1530 | K126: 1 | L126: =I126*J126 -> 0 | M126: 0 | N126: =SUM(L126:M126) -> 0 | O126: 0 | P126: =C126*$B$6*$B$6 -> 1560.6 | Q126: 1 | R126: =P126*O126 -> 0 | S126: 0 | T126: =SUM(R126:S126) -> 0 | U126: 0 | V126: =C126*$B$6*$B$6*$B$6 -> 1591.812 | W126: 1 | X126: =V126*U126 -> 0 | Y126: 0 | Z126: =SUM(X126:Y126) -> 0 | AA126: =F126+L126+R126+X126 -> 1500 | AB126: =G126+M126+S126+Y126 -> 0 | AC126: =SUM(AA126:AB126) -> 1500
A127: On-going M&E Training Workshops | B127: 4 | C127: 250 | D127: 1 | E127: /workshop | F127: =C127*B127 -> 1000 | G127: 0 | H127: =SUM(F127:G127) -> 1000 | I127: 4 | J127: =C127*$B$6 -> 255 | K127: 1 | L127: =I127*J127 -> 1020 | M127: 0 | N127: =SUM(L127:M127) -> 1020 | O127: 4 | P127: =C127*$B$6*$B$6 -> 260.1 | Q127: 1 | R127: =P127*O127 -> 1040.4 | S127: 0 | T127: =SUM(R127:S127) -> 1040.4 | U127: 2 | V127: =C127*$B$6*$B$6*$B$6 -> 265.302 | W127: 1 | X127: =V127*U127 -> 530.604 | Y127: 0 | Z127: =SUM(X127:Y127) -> 530.604 | AA127: =F127+L127+R127+X127 -> 3591.004 | AB127: =G127+M127+S127+Y127 -> 0 | AC127: =SUM(AA127:AB127) -> 3591.004
A128: Monitoring Guidelines Creation, Translation & Printing | B128: 1 | C128: 1000 | D128: 1 | E128: /document | F128: =C128*B128 -> 1000 | G128: 0 | H128: =SUM(F128:G128) -> 1000 | I128: 0 | J128: =C128*$B$6 -> 1020 | K128: 1 | L128: =I128*J128 -> 0 | M128: 0 | N128: =SUM(L128:M128) -> 0 | O128: 0 | P128: =C128*$B$6*$B$6 -> 1040.4 | Q128: 1 | R128: =P128*O128 -> 0 | S128: 0 | T128: =SUM(R128:S128) -> 0 | U128: 0 | V128: =C128*$B$6*$B$6*$B$6 -> 1061.208 | W128: 1 | X128: =V128*U128 -> 0 | Y128: 0 | Z128: =SUM(X128:Y128) -> 0 | AA128: =F128+L128+R128+X128 -> 1000 | AB128: =G128+M128+S128+Y128 -> 0 | AC128: =SUM(AA128:AB128) -> 1000
...
