Workbook
Name \A: #REF!
Name \A: #REF!
Name \P: #REF!
Name \P: #REF!
Name \S: #REF!
Name _______sho1: '[3]Detailed Budget-SAVE'!#REF!
Name __2DAI_1: #N/A
Name __3FEE: #N/A
Name __AFP1: #N/A
Name __AFP2: #N/A
Name __AFP3: #N/A
Name __AFP4: #N/A
Name __AMP1: #N/A
Name __AMP2: #N/A
Name __AMP3: #N/A
Name __AMP4: #N/A
Name __DAI4: #N/A
Name __EES1: #N/A
Name __EES2: #N/A
Name __EES3: #N/A
Name __EES4: #N/A
Name __EXT1: #N/A
Name __EXT2: #N/A
Name __EXT3: #N/A
Name __EXT4: #N/A
Name __FCP1: #N/A
Name __FCP2: #N/A
Name __FCP3: #N/A
Name __FCP4: #N/A
Name __FRI1: #N/A
Name __FRI4: #N/A
Name __HRA1: #N/A
Name __HRA2: #N/A
Name __HRA3: #N/A
Name __HRA4: #N/A
Name __inf1: #REF!
Name __LT4: [4]Parameters!$B$40
Name __ODC1: #N/A
Name __ODC2: #N/A
Name __POL1: #N/A
Name __POL2: #N/A
Name __POL3: #N/A
Name __POL4: #N/A
Name __TOT1: #N/A
Name __TOT2: #N/A
Name __TRV1: #N/A
Name __TRV2: #N/A
Name _060: #REF!
Name _1_1: #REF!
Name _13th_and_14th_month: [5]Parameters!$D$62
Name _2_1034: #REF!
Name _2DAI_1: #N/A
Name _3_1440: #REF!
Name _3FEE: #N/A
Name _4_2: #REF!
Name _5_3: #REF!
Name _AFP1: #N/A
Name _AFP2: #N/A
Name _AFP3: #N/A
Name _AFP4: #N/A

Sheet USDA Budget Summary
A1: ATTACHMENT C-1
A2: Budget Summary
A4: Program (FFPr or MGD): | B4: FFPr
A5: Country of Operation: | B5: Colombia
A6: Implementing Organization: | B6: Partners of the Americas Inc.
A7: Fiscal Year: | B7: 2024
A8: Agreement Number: | B8: USDA-FAS-10.606-0700-20-(514)
A10: Total Amount of Federal Funds Requested
A11: Funding Source (FAS for MGD) (CCC for FFPr) | B11: Funding Year | C11: Commodity Cost | D11: Freight Cost | E11: Administrative Costs (cash portion) | F11: Total Federal Funding Obligated
B12: 2020 | C12: 21924000 | D12: 9591750 | E12: 2280000 | F12: 33795750
B13: 2024 | C13: 9000000 | D13: 0 | E13: 0 | F13: =E13+D13+C13 -> 9000000
A15: Project Operating Budget
A16: Expense Type | B16: Monetization Proceeds (FFPr Only) | C16: FAS or CCC Funds (CCC is Admin Only) | D16: Cost Share | E16: Total w/out Cost Share | F16: Total w/Cost Share
A17: Administration
A18: Salaries/Personnel | B18: ='Program Budget'!T48-C18 -> 1352931.2 | C18: 430000 | D18: ='Program Budget'!U48 -> 0 | E18: =B18+C18 -> 1782931.2 | F18: =B18+C18+D18 -> 1782931.2
A19: Benefits | B19: ='Program Budget'!T60-C19 -> 735534.89 | C19: 225648 | D19: ='Program Budget'!U60 -> 0 | E19: =B19+C19 -> 961182.89 | F19: =B19+C19+D19 -> 961182.89
A20: Travel | B20: ='Program Budget'!T77-C20 -> 258899.22 | C20: 39104 | D20: ='Program Budget'!U77 -> 0 | E20: =B20+C20 -> 298003.22 | F20: =B20+C20+D20 -> 298003.22
A21: Professional Services/Contractual | B21: ='Program Budget'!T101-C21 -> 1563376.9 | C21: 862147.25 | D21: ='Program Budget'!U101 -> 0 | E21: =B21+C21 -> 2425524.1 | F21: =B21+C21+D21 -> 2425524.1
A22: Equipment | B22: ='Program Budget'!T106-C22 -> 0 | C22: 72554.43 | D22: ='Program Budget'!U106 -> 0 | E22: =B22+C22 -> 72554.43 | F22: =B22+C22+D22 -> 72554.43
A23: Office | B23: ='Program Budget'!T118-C23 -> 448367.27 | C23: 81389.57 | D23: ='Program Budget'!U118 -> 0 | E23: =B23+C23 -> 529756.84 | F23: =B23+C23+D23 -> 529756.84
A24: Supplies | B24: ='Program Budget'!T129-C24 -> 159456.88 | C24: 41096 | D24: ='Program Budget'!U129 -> 0 | E24: =B24+C24 -> 200552.88 | F24: =B24+C24+D24 -> 200552.88
A25: Other | B25: ='Program Budget'!T141-C25 -> 64958.728 | C25: 19760 | D25: ='Program Budget'!U141 -> 0 | E25: =B25+C25 -> 84718.728 | F25: =B25+C25+D25 -> 84718.728
A26: Total Administration | B26: =SUM(B18:B25) -> 4583525.1 | C26: =SUM(C18:C25) -> 1771699.2 | D26: =SUM(D18:D25) -> 0 | E26: =SUM(E18:E25) -> 6355224.3 | F26: =SUM(F18:F25) -> 6355224.3
A28: Activities
A29: Activity 1: Value Chain Development (Value Chain Analysis, Carbon Assessment, and Living Incomes) | B29: ='Program Budget'!T195 -> 272696.75 | C29: 0 | D29: ='Program Budget'!U195 -> 0 | E29: =B29+C29 -> 272696.75 | F29: =B29+C29+D29 -> 272696.75
A30: Activity 2: Producer Organization Development & Commercialization | B30: ='Program Budget'!T272 -> 2209930.1 | C30: 0 | D30: ='Program Budget'!U272 -> 312219.19 | E30: =B30+C30 -> 2209930.1 | F30: =B30+C30+D30 -> 2522149.3
A31: Activity 3: Agriculture Extension and Production Support | B31: ='Program Budget'!T369 -> 7469424.7 | C31: 0 | D31: ='Program Budget'!U369 -> 939590.56 | E31: =B31+C31 -> 7469424.7 | F31: =B31+C31+D31 -> 8409015.3
A32: Activity 4: Post-Harvest Aggregation & Processing | B32: ='Program Budget'!T442 -> 1992268.2 | C32: 0 | D32: ='Program Budget'!U442 -> 141928.5 | E32: =B32+C32 -> 1992268.2 | F32: =B32+C32+D32 -> 2134196.7
A33: Activity 5: Ensure Financial Service/ Capital Access for Actors in the Value Chains | B33: ='Program Budget'!T516 -> 1105173.6 | C33: 0 | D33: ='Program Budget'!U516 -> 584189.75 | E33: =B33+C33 -> 1105173.6 | F33: =B33+C33+D33 -> 1689363.4
A34: Activity 6: Innovation and Job Creation Through Youth Engagement | B34: ='Program Budget'!T596 -> 819624.4 | C34: 0 | D34: ='Program Budget'!U596 -> 0 | E34: =B34+C34 -> 819624.4 | F34: =B34+C34+D34 -> 819624.4
A35: Activity 7: Establishment of Regional Community of Practice | B35: ='Program Budget'!T666 -> 1274251 | C35: 0 | D35: ='Program Budget'!U666 -> 0 | E35: =B35+C35 -> 1274251 | F35: =B35+C35+D35 -> 1274251
A36: Activity 8: Financial Services: Endowment Establishment, Fundraising and Management | B36: ='Program Budget'!T729 -> 3539784.8 | C36: 0 | D36: ='Program Budget'!U729 -> 0 | E36: =B36+C36 -> 3539784.8 | F36: =B36+C36+D36 -> 3539784.8
A37: Total Activities | B37: =SUM(B29:B36) -> 18683154 | C37: =SUM(C29:C36) -> 0 | D37: =SUM(D29:D36) -> 1977928 | E37: =SUM(E29:E36) -> 18683154 | F37: =SUM(F29:F36) -> 20661082
A39: Commodity and Food Purchases (N/A to FFPr)
A40: Commodity Procurement | B40: 0 | C40: 0 | D40: 0 | E40: =B40+C40 -> 0 | F40: =B40+C40+D40 -> 0
A41: Food Vouchers (N/A to MGD)
A42: Cash Transfers (N/A to MGD)
A43: Total Commodity Procurement | B43: =SUM(B40:B42) -> 0 | C43: =SUM(C40:C42) -> 0 | D43: =SUM(D40:D42) -> 0 | E43: =SUM(E40:E42) -> 0 | F43: =SUM(F40:F42) -> 0
A45: ITSH (N/A to FFPr)
A46: Salaries | B46: 0 | C46: 0 | D46: 0 | E46: =B46+C46 -> 0 | F46: =B46+C46+D46 -> 0
A47: Benefits | B47: 0 | C47: 0 | D47: 0 | E47: =B47+C47 -> 0 | F47: =B47+C47+D47 -> 0
A48: Transportation | B48: 0 | C48: 0 | D48: 0 | E48: =B48+C48 -> 0 | F48: =B48+C48+D48 -> 0
A49: Professional Services | B49: 0 | C49: 0 | D49: =0 -> 0 | E49: =B49+C49 -> 0 | F49: =B49+C49+D49 -> 0
A50: Warehouse | B50: 0 | C50: 0 | D50: 0 | E50: =B50+C50 -> 0 | F50: =B50+C50+D50 -> 0
A51: Supplies | B51: 0 | C51: 0 | D51: 0 | E51: =B51+C51 -> 0 | F51: =B51+C51+D51 -> 0
A52: Other | B52: 0 | C52: 0 | D52: 0 | E52: =B52+C52 -> 0 | F52: =B52+C52+D52 -> 0
A53: Total ITSH | B53: =SUM(B46:B52) -> 0 | C53: 0 | D53: =SUM(D46:D52) -> 0 | E53: =SUM(E46:E52) -> 0 | F53: =SUM(F46:F52) -> 0
A55: Total Direct Costs | B55: =B26+B37+B53+B43 -> 23266679 | C55: =C26+C37+C53+C43 -> 1771699.2 | D55: =D26+D37+D53+D43 -> 1977928 | E55: =E43+E37+E26+E53 -> 25038378 | F55: =F43+F37+F26+F53 -> 27016306
A57: Indirect Costs
A58: ICR on Administration | B58: =Admin!T144-C58 -> 1320067.5 | C58: 508300.75 | E58: =B58+C58 -> 1828368.2
A59: ICR on Activities | B59: ='Program Budget'!T739-E58 -> 4476117.8 | C59: =C37*0.2828 -> 0 | E59: =B59+C59 -> 4476117.8
A60: ICR on Commodity and Food Purchases (N/A to FFPr) | B60: =B43*0.2828 -> 0 | C60: =C43*0.2828 -> 0 | E60: =B60+C60 -> 0
A61: ICR on ITSH (N/A to FFPr) | B61: =B53*0.2828 -> 0 | C61: =C53*0.2828 -> 0 | E61: =B61+C61 -> 0
A62: Total Indirect Costs | B62: =SUM(B58:B61) -> 5796185.3 | C62: =SUM(C58:C61) -> 508300.75 | E62: =SUM(E58:E61) -> 6304486.1
A64: Anticipated Program Income | F64: =932916 -> 932916
A66: Grand Total Costs | B66: =(B62+B55) -> 29062864 | C66: =(C62+C55) -> 2280000 | D66: =(D62+D55) -> 1977928 | E66: =(E62+E55) -> 31342864 | F66: =(F55+E62) -> 33320792
A68: Total Amount of Federal Award (Total Federal Funds Requested Plus Cost Share): | F68: =F13+D66+F12 -> 44773678
E70: =E66*10% -> 3134286.4

Sheet Program Budget
D1: Partners of the Americas – Food for Progress Colombia
D2: NOFO: USDA-FAS-10.606-0700-20-(514) [Original], USDA-FAS-10606-0700-Merit2024 [Merit Extension]
D3: Duration: 7.5 Years
D4: Country: Colombia
D5: Budget Assumptions:
A6: Entity: | B6: P | D6: Inflation - US Based Goods/Services | E6: 1.03
A7: Program-Dept.: | B7: 30100 | D7: Inflation - Locally Purchased Goods/Services | E7: 1.04
A8: Funder-Grant: | B8: USDA700 | D8: Merit Based Increases for HQ & Field Staff | E8: 1.05
A10: Activity (Budget Code) | B10: Account Code | C10: Country Code (USA or COL2) | D10: BUDGET ITEM | E10: Year 1 - 4 Total inception through 09/30/2024 | F10: UNIT | G10: RATE/ UNIT | H10: Level of Effort (LOE) Year 5 | I10: # of Units | J10: Year 5 (10/1/24 - 9/30/25) | K10: Level of Effort (LOE) Year 6 | L10: # of Units | M10: Year 6 (10/1/25 - 09/30/26) | N10: Level of Effort (LOE) Year 7 | O10: # of Units | P10: Year 7 (10/1/26 - 09/30/27) | Q10: Level of Effort (LOE) Year 8 | R10: # of Units | S10: Year 8 (10/1/27 - 3/31/28) | T10: TOTAL USDA | U10: TOTAL COST SHARE | V10: PROJECT GRAND TOTAL
D11: Salaries/Personnel (Administration)
D12: CCN Colombia Field Staff (LOE)
A13: PERSNL | B13: 50000 | C13: USA | D13: Key Personnel: Chief of Party | E13: 225257 | F13: Month | G13: =171000/12 -> 14250 | H13: ='LOE Breakdown by Year'!D11 -> 0.1 | I13: 12 | J13: =I13*G13*H13 -> 17100 | K13: ='LOE Breakdown by Year'!D51 -> 0.05 | L13: 12 | M13: =L13*G13*$K13*$E$8 -> 8977.5 | N13: ='LOE Breakdown by Year'!D91 -> 0.05 | O13: 12 | P13: =O13*G13*$N13*$E$8*$E$8 -> 9426.375 | Q13: ='LOE Breakdown by Year'!D131 -> 0.05 | R13: 0 | S13: =R13*G13*$Q13*$E$8*$E$8*$E$8 -> 0 | T13: =SUM(P13,M13,J13,E13,S13) -> 260760.88 | U13: 0 | V13: =SUM(T13:U13) -> 260760.88
A14: PERSNL | B14: 70000 | C14: COL2 | D14: Deputy Chief of Party / Value Chain Strengthening Director | F14: Month | G14: =60000/12 -> 5000 | H14: ='LOE Breakdown by Year'!D12 -> 0.1 | I14: 12 | J14: =I14*G14*H14 -> 6000 | K14: ='LOE Breakdown by Year'!D52 -> 0.25 | L14: 12 | M14: =L14*G14*$K14*$E$8 -> 15750 | N14: ='LOE Breakdown by Year'!D92 -> 0.25 | O14: 12 | P14: =O14*G14*$N14*$E$8*$E$8 -> 16537.5 | Q14: ='LOE Breakdown by Year'!D132 -> 0.25 | R14: 6 | S14: =R14*G14*$Q14*$E$8*$E$8*$E$8 -> 8682.1875 | T14: =SUM(P14,M14,J14,E14,S14) -> 46969.688 | U14: 0 | V14: =SUM(T14:U14) -> 46969.688
A15: PERSNL | B15: 70000 | C15: COL2 | D15: Key Personnel: Technical Director | E15: 0 | F15: Month | G15: =55000/12 -> 4583.3333 | H15: ='LOE Breakdown by Year'!D13 -> 0.05 | I15: 12 | J15: =I15*G15*H15 -> 2750 | K15: ='LOE Breakdown by Year'!D53 -> 0.05 | L15: 12 | M15: =L15*G15*$K15*$E$8 -> 2887.5 | N15: ='LOE Breakdown by Year'!D93 -> 0.05 | O15: 12 | P15: =O15*G15*$N15*$E$8*$E$8 -> 3031.875 | Q15: ='LOE Breakdown by Year'!D133 -> 0.05 | R15: 5 | S15: =R15*G15*$Q15*$E$8*$E$8*$E$8 -> 1326.4453 | T15: =SUM(P15,M15,J15,E15,S15) -> 9995.8203 | U15: 0 | V15: =SUM(T15:U15) -> 9995.8203
A16: PERSNL | B16: 70000 | C16: COL2 | D16: Activity Lead Agribusiness Senior Specialist (Cacao) | E16: 0 | F16: Month | G16: =34000/12 -> 2833.3333 | H16: ='LOE Breakdown by Year'!D14 -> 0.1 | I16: 12 | J16: =I16*G16*H16 -> 3400 | K16: ='LOE Breakdown by Year'!D54 -> 0 | L16: 12 | M16: =L16*G16*$K16*$E$8 -> 0 | N16: ='LOE Breakdown by Year'!D94 -> 0 | O16: 12 | P16: =O16*G16*$N16*$E$8*$E$8 -> 0 | Q16: ='LOE Breakdown by Year'!D134 -> 0 | R16: 2 | S16: =R16*G16*$Q16*$E$8*$E$8*$E$8 -> 0 | T16: =SUM(P16,M16,J16,E16,S16) -> 3400 | U16: 0 | V16: =SUM(T16:U16) -> 3400
A17: PERSNL | B17: 70000 | C17: COL2 | D17: Cacao Field Officer | F17: Month | G17: =16000/12 -> 1333.3333 | H17: ='LOE Breakdown by Year'!D15 -> 0 | I17: 12 | J17: =I17*G17*H17 -> 0 | K17: ='LOE Breakdown by Year'!D55 -> 0 | L17: 12 | M17: =L17*G17*$K17*$E$8 -> 0 | N17: ='LOE Breakdown by Year'!D95 -> 0 | O17: 12 | P17: =O17*G17*$N17*$E$8*$E$8 -> 0 | Q17: ='LOE Breakdown by Year'!D135 -> 0 | R17: 0 | S17: =R17*G17*$Q17*$E$8*$E$8*$E$8 -> 0 | T17: =SUM(P17,M17,J17,E17,S17) -> 0 | U17: 0 | V17: =SUM(T17:U17) -> 0
A18: PERSNL | B18: 70000 | C18: COL2 | D18: Cacao & Complementary Crop Technical Field Leader (2) | F18: Month | G18: =(21000/12)*2 -> 3500 | H18: ='LOE Breakdown by Year'!D16 -> 0 | I18: 6 | J18: =I18*G18*H18 -> 0 | K18: ='LOE Breakdown by Year'!D56 -> 0 | L18: 12 | M18: =L18*G18*$K18*$E$8 -> 0 | N18: ='LOE Breakdown by Year'!D96 -> 0 | O18: 12 | P18: =O18*G18*$N18*$E$8*$E$8 -> 0 | Q18: ='LOE Breakdown by Year'!D136 -> 0 | R18: 0 | S18: =R18*G18*$Q18*$E$8*$E$8*$E$8 -> 0 | T18: =SUM(P18,M18,J18,E18,S18) -> 0 | U18: 0 | V18: =SUM(T18:U18) -> 0
A19: PERSNL | B19: 70000 | C19: COL2 | D19: Extension Agents (45 in Y5 and 25 in Y6) | E19: 0 | F19: Month | G19: =1000 -> 1000 | H19: ='LOE Breakdown by Year'!D17 -> 0 | I19: 12 | J19: =I19*(G19*45)*H19 -> 0 | K19: ='LOE Breakdown by Year'!D57 -> 0 | L19: 12 | M19: =L19*((G19*25))*$K19*$E$8 -> 0 | N19: ='LOE Breakdown by Year'!D97 -> 0 | O19: 0 | P19: =O19*(G19*0)*$N19*$E$8*$E$8 -> 0 | Q19: ='LOE Breakdown by Year'!D137 -> 0 | R19: 0 | S19: =R19*G19*$Q19*$E$8*$E$8*$E$8 -> 0 | T19: =SUM(P19,M19,J19,E19,S19) -> 0 | U19: 0 | V19: =SUM(T19:U19) -> 0
A20: PERSNL | B20: 70000 | C20: COL2 | D20: Activity Lead Agribusiness Senior Specialist (Complementary Crop) | E20: 0 | F20: Month | G20: =34000/12 -> 2833.3333 | H20: ='LOE Breakdown by Year'!D18 -> 0 | I20: 12 | J20: =I20*G20*H20 -> 0 | K20: ='LOE Breakdown by Year'!D58 -> 0 | L20: 12 | M20: =L20*G20*$K20*$E$8 -> 0 | N20: ='LOE Breakdown by Year'!D98 -> 0 | O20: 12 | P20: =O20*G20*$N20*$E$8*$E$8 -> 0 | Q20: ='LOE Breakdown by Year'!D138 -> 0 | R20: 0 | S20: =R20*G20*$Q20*$E$8*$E$8*$E$8 -> 0 | T20: =SUM(P20,M20,J20,E20,S20) -> 0 | U20: 0 | V20: =SUM(T20:U20) -> 0
A21: PERSNL | B21: 70000 | C21: COL2 | D21: Complementary Crops Field Officer | F21: Month | G21: =0/12 -> 0 | H21: ='LOE Breakdown by Year'!D19 -> 0 | I21: 0 | J21: =I21*G21*H21 -> 0 | K21: ='LOE Breakdown by Year'!D59 -> 0 | L21: 12 | M21: =L21*G21*$K21*$E$8 -> 0 | N21: ='LOE Breakdown by Year'!D99 -> 0 | O21: 12 | P21: =O21*G21*$N21*$E$8*$E$8 -> 0 | Q21: ='LOE Breakdown by Year'!D139 -> 0 | R21: 0 | S21: =R21*G21*$Q21*$E$8*$E$8*$E$8 -> 0 | T21: =SUM(P21,M21,J21,E21,S21) -> 0 | U21: 0 | V21: =SUM(T21:U21) -> 0
A22: PERSNL | B22: 70000 | C22: COL2 | D22: EPSEAS Specialist | E22: 0 | F22: Month | G22: =0/12 -> 0 | H22: ='LOE Breakdown by Year'!D20 -> 0 | I22: 0 | J22: =I22*G22*H22 -> 0 | K22: ='LOE Breakdown by Year'!D60 -> 0 | L22: 12 | M22: =L22*G22*$K22*$E$8 -> 0 | N22: ='LOE Breakdown by Year'!D100 -> 0 | O22: 12 | P22: =O22*G22*$N22*$E$8*$E$8 -> 0 | Q22: ='LOE Breakdown by Year'!D140 -> 0 | R22: 0 | S22: =R22*G22*$Q22*$E$8*$E$8*$E$8 -> 0 | T22: =SUM(P22,M22,J22,E22,S22) -> 0 | U22: 0 | V22: =SUM(T22:U22) -> 0
A23: PERSNL | B23: 70000 | C23: COL2 | D23: Extension Agents for EPSEAS (20 in Y6 and 25 in Y7) | E23: 0 | F23: Month | G23: 1000 | H23: ='LOE Breakdown by Year'!D21 -> 0 | I23: 0 | J23: =I23*G23*H23 -> 0 | K23: ='LOE Breakdown by Year'!D61 -> 0 | L23: 12 | M23: =L23*((1000*20))*$K23*$E$8 -> 0 | N23: ='LOE Breakdown by Year'!D101 -> 0 | O23: 12 | P23: =O23*G23*$N23*$E$8*$E$8 -> 0 | Q23: ='LOE Breakdown by Year'!D141 -> 0 | R23: 0 | S23: =R23*G23*$Q23*$E$8*$E$8*$E$8 -> 0 | T23: =SUM(P23,M23,J23,E23,S23) -> 0 | U23: 0 | V23: =SUM(T23:U23) -> 0
A24: PERSNL | B24: 70000 | C24: COL2 | D24: Senior M&E Director | E24: 28275.7 | F24: Month | G24: =75000/12 -> 6250 | H24: ='LOE Breakdown by Year'!D22 -> 0.1 | I24: 12 | J24: =I24*G24*H24 -> 7500 | K24: ='LOE Breakdown by Year'!D62 -> 0.05 | L24: 12 | M24: =L24*G24*$K24*$E$8 -> 3937.5 | N24: ='LOE Breakdown by Year'!D102 -> 0.05 | O24: 12 | P24: =O24*G24*$N24*$E$8*$E$8 -> 4134.375 | Q24: ='LOE Breakdown by Year'!D142 -> 0.05 | R24: 6 | S24: =R24*G24*$Q24*$E$8*$E$8*$E$8 -> 2170.5469 | T24: =SUM(P24,M24,J24,E24,S24) -> 46018.122 | U24: 0 | V24: =SUM(T24:U24) -> 46018.122
A25: PERSNL | B25: 70000 | C25: COL2 | D25: Senior M&E Specialist | E25: 24675.7 | F25: Month | G25: =34000/12 -> 2833.3333 | H25: ='LOE Breakdown by Year'!D23 -> 0.1 | I25: 12 | J25: =I25*G25*H25 -> 3400 | K25: ='LOE Breakdown by Year'!D63 -> 0.05 | L25: 12 | M25: =L25*G25*$K25*$E$8 -> 1785 | N25: ='LOE Breakdown by Year'!D103 -> 0.05 | O25: 12 | P25: =O25*G25*$N25*$E$8*$E$8 -> 1874.25 | Q25: ='LOE Breakdown by Year'!D143 -> 0.05 | R25: 6 | S25: =R25*G25*$Q25*$E$8*$E$8*$E$8 -> 983.98125 | T25: =SUM(P25,M25,J25,E25,S25) -> 32718.931 | U25: 0 | V25: =SUM(T25:U25) -> 32718.931
A26: PERSNL | B26: 70000 | C26: COL2 | D26: M&E Specialist | E26: 22491.26 | F26: Month | G26: =30000/12 -> 2500 | H26: ='LOE Breakdown by Year'!D24 -> 0.1 | I26: 12 | J26: =I26*G26*H26 -> 3000 | K26: ='LOE Breakdown by Year'!D64 -> 0.05 | L26: 12 | M26: =L26*G26*$K26*$E$8 -> 1575 | N26: ='LOE Breakdown by Year'!D104 -> 0.05 | O26: 12 | P26: =O26*G26*$N26*$E$8*$E$8 -> 1653.75 | Q26: ='LOE Breakdown by Year'!D144 -> 0.05 | R26: 3 | S26: =R26*G26*$Q26*$E$8*$E$8*$E$8 -> 434.10938 | T26: =SUM(P26,M26,J26,E26,S26) -> 29154.119 | U26: 0 | V26: =SUM(T26:U26) -> 29154.119
A27: PERSNL | B27: 70000 | C27: COL2 | D27: M&E Officer | E27: 30491.26 | F27: Month | G27: =12000/12 -> 1000 | H27: ='LOE Breakdown by Year'!D25 -> 0.1 | I27: 12 | J27: =I27*G27*H27 -> 1200 | K27: ='LOE Breakdown by Year'!D65 -> 0.05 | L27: 12 | M27: =L27*G27*$K27*$E$8 -> 630 | N27: ='LOE Breakdown by Year'!D105 -> 0.05 | O27: 12 | P27: =O27*G27*$N27*$E$8*$E$8 -> 661.5 | Q27: ='LOE Breakdown by Year'!D145 -> 0.05 | R27: 3 | S27: =R27*G27*$Q27*$E$8*$E$8*$E$8 -> 173.64375 | T27: =SUM(P27,M27,J27,E27,S27) -> 33156.404 | U27: 0 | V27: =SUM(T27:U27) -> 33156.404
A28: PERSNL | B28: 70000 | C28: COL2 | D28: Partnerships and Investment Director | E28: 36550 | F28: Month | G28: =55000/12 -> 4583.3333 | H28: ='LOE Breakdown by Year'!D26 -> 0.1 | I28: 12 | J28: =I28*G28*H28 -> 5500 | K28: ='LOE Breakdown by Year'!D66 -> 0.05 | L28: 12 | M28: =L28*G28*$K28*$E$8 -> 2887.5 | N28: ='LOE Breakdown by Year'!D106 -> 0.05 | O28: 12 | P28: =O28*G28*$N28*$E$8*$E$8 -> 3031.875 | Q28: ='LOE Breakdown by Year'!D146 -> 0.05 | R28: 0 | S28: =R28*G28*$Q28*$E$8*$E$8*$E$8 -> 0 | T28: =SUM(P28,M28,J28,E28,S28) -> 47969.375 | U28: 0 | V28: =SUM(T28:U28) -> 47969.375
A29: PERSNL | B29: 70000 | C29: COL2 | D29: Partnerships and Investment Specialist | E29: 0 | F29: Month | G29: =21000/12 -> 1750 | H29: ='LOE Breakdown by Year'!D27 -> 0.1 | I29: 12 | J29: =I29*G29*H29 -> 2100 | K29: ='LOE Breakdown by Year'!D67 -> 0 | L29: 12 | M29: =L29*G29*$K29*$E$8 -> 0 | N29: ='LOE Breakdown by Year'!D107 -> 0 | O29: 12 | P29: =O29*G29*$N29*$E$8*$E$8 -> 0 | Q29: ='LOE Breakdown by Year'!D147 -> 0 | R29: 0 | S29: =R29*G29*$Q29*$E$8*$E$8*$E$8 -> 0 | T29: =SUM(P29,M29,J29,E29,S29) -> 2100 | U29: 0 | V29: =SUM(T29:U29) -> 2100
A30: PERSNL | B30: 70000 | C30: COL2 | D30: Organizational Strengthening Specialist | E30: 0 | F30: Month | G30: =21000/12 -> 1750 | H30: ='LOE Breakdown by Year'!D28 -> 0.1 | I30: 12 | J30: =I30*G30*H30 -> 2100 | K30: ='LOE Breakdown by Year'!D68 -> 0 | L30: 12 | M30: =L30*G30*$K30*$E$8 -> 0 | N30: ='LOE Breakdown by Year'!D108 -> 0 | O30: 12 | P30: =O30*G30*$N30*$E$8*$E$8 -> 0 | Q30: ='LOE Breakdown by Year'!D148 -> 0 | R30: 0 | S30: =R30*G30*$Q30*$E$8*$E$8*$E$8 -> 0 | T30: =SUM(P30,M30,J30,E30,S30) -> 2100 | U30: 0 | V30: =SUM(T30:U30) -> 2100
A31: PERSNL | B31: 70000 | C31: COL2 | D31: Value Chain Strengthening Director | E31: 0 | F31: Month | G31: =0/12 -> 0 | H31: ='LOE Breakdown by Year'!D29 -> 0.1 | I31: 12 | J31: =I31*G31*H31 -> 0 | K31: ='LOE Breakdown by Year'!D69 -> 0.05 | L31: 12 | M31: =L31*G31*$K31*$E$8 -> 0 | N31: ='LOE Breakdown by Year'!D109 -> 0.05 | O31: 12 | P31: =O31*G31*$N31*$E$8*$E$8 -> 0 | Q31: ='LOE Breakdown by Year'!D149 -> 0.05 | R31: 4 | S31: =R31*G31*$Q31*$E$8*$E$8*$E$8 -> 0 | T31: =SUM(P31,M31,J31,E31,S31) -> 0 | U31: 0 | V31: =SUM(T31:U31) -> 0
A32: PERSNL | B32: 70000 | C32: COL2 | D32: Communications Specialist | E32: 0 | F32: Month | G32: =21000/12 -> 1750 | H32: ='LOE Breakdown by Year'!D30 -> 0.1 | I32: 12 | J32: =I32*G32*H32 -> 2100 | K32: ='LOE Breakdown by Year'!D70 -> 0.1 | L32: 12 | M32: =L32*G32*$K32*$E$8 -> 2205 | N32: ='LOE Breakdown by Year'!D110 -> 0.1 | O32: 12 | P32: =O32*G32*$N32*$E$8*$E$8 -> 2315.25 | Q32: ='LOE Breakdown by Year'!D150 -> 0.1 | R32: 0 | S32: =R32*G32*$Q32*$E$8*$E$8*$E$8 -> 0 | T32: =SUM(P32,M32,J32,E32,S32) -> 6620.25 | U32: 0 | V32: =SUM(T32:U32) -> 6620.25
A33: PERSNL | B33: 70000 | C33: COL2 | D33: Value Chain Specialist | E33: 0 | F33: Month | G33: =30000/12 -> 2500 | H33: ='LOE Breakdown by Year'!D31 -> 0.1 | I33: 12 | J33: =I33*G33*H33 -> 3000 | K33: ='LOE Breakdown by Year'!D71 -> 0 | L33: 12 | M33: =L33*G33*$K33*$E$8 -> 0 | N33: ='LOE Breakdown by Year'!D111 -> 0 | O33: 12 | P33: =O33*G33*$N33*$E$8*$E$8 -> 0 | Q33: ='LOE Breakdown by Year'!D151 -> 0 | R33: 0 | S33: =R33*G33*$Q33*$E$8*$E$8*$E$8 -> 0 | T33: =SUM(P33,M33,J33,E33,S33) -> 3000 | U33: 0 | V33: =SUM(T33:U33) -> 3000
A34: PERSNL | B34: 70000 | C34: COL2 | D34: Contracts & Compliance Director | E34: 29123.27 | F34: Month | G34: =55000/12 -> 4583.3333 | H34: ='LOE Breakdown by Year'!D32 -> 0.1 | I34: 12 | J34: =I34*G34*H34 -> 5500 | K34: ='LOE Breakdown by Year'!D72 -> 0.1 | L34: 12 | M34: =L34*G34*$K34*$E$8 -> 5775 | N34: ='LOE Breakdown by Year'!D112 -> 0.1 | O34: 12 | P34: =O34*G34*$N34*$E$8*$E$8 -> 6063.75 | Q34: ='LOE Breakdown by Year'!D152 -> 0.1 | R34: 3 | S34: =R34*G34*$Q34*$E$8*$E$8*$E$8 -> 1591.7344 | T34: =SUM(P34,M34,J34,E34,S34) -> 48053.754 | U34: 0 | V34: =SUM(T34:U34) -> 48053.754
A35: PERSNL | B35: 70000 | C35: COL2 | D35: Grants & Procurement Specialist (2) | E35: 0 | F35: Month | G35: =(21000/12)*2 -> 3500 | H35: ='LOE Breakdown by Year'!D33 -> 0.05 | I35: 12 | J35: =I35*G35*H35 -> 2100 | K35: ='LOE Breakdown by Year'!D73 -> 0.1 | L35: 12 | M35: =L35*G35*$K35*$E$8 -> 4410 | N35: ='LOE Breakdown by Year'!D113 -> 0.1 | O35: 12 | P35: =O35*G35*$N35*$E$8*$E$8 -> 4630.5 | Q35: ='LOE Breakdown by Year'!D153 -> 0.1 | R35: 0 | S35: =R35*G35*$Q35*$E$8*$E$8*$E$8 -> 0 | T35: =SUM(P35,M35,J35,E35,S35) -> 11140.5 | U35: 0 | V35: =SUM(T35:U35) -> 11140.5
A36: PERSNL | B36: 70000 | C36: COL2 | D36: F&A Director | E36: 170750.48 | F36: Month | G36: =(72000/12)*87.99% -> 5279.4 | H36: ='LOE Breakdown by Year'!D34 -> 0.15 | I36: 12 | J36: =I36*G36*H36 -> 9502.92 | K36: ='LOE Breakdown by Year'!D74 -> 0.15 | L36: 12 | M36: =L36*G36*$K36*$E$8 -> 9978.066 | N36: ='LOE Breakdown by Year'!D114 -> 0.15 | O36: 12 | P36: =O36*G36*$N36*$E$8*$E$8 -> 10476.969 | Q36: ='LOE Breakdown by Year'!D154 -> 0.15 | R36: 6 | S36: =R36*G36*$Q36*$E$8*$E$8*$E$8 -> 5500.4089 | T36: =SUM(P36,M36,J36,E36,S36) -> 206208.84 | U36: 0 | V36: =SUM(T36:U36) -> 206208.84
A37: PERSNL | B37: 70000 | C37: COL2 | D37: Accounting & Finance Specialist | E37: 0 | F37: Month | G37: =21000/12 -> 1750 | H37: ='LOE Breakdown by Year'!D35 -> 0.1 | I37: 12 | J37: =I37*G37*H37 -> 2100 | K37: ='LOE Breakdown by Year'!D75 -> 0.2 | L37: 12 | M37: =L37*G37*$K37*$E$8 -> 4410 | N37: ='LOE Breakdown by Year'!D115 -> 0.2 | O37: 12 | P37: =O37*G37*$N37*$E$8*$E$8 -> 4630.5 | Q37: ='LOE Breakdown by Year'!D155 -> 0.2 | R37: 3 | S37: =R37*G37*$Q37*$E$8*$E$8*$E$8 -> 1215.5063 | T37: =SUM(P37,M37,J37,E37,S37) -> 12356.006 | U37: 0 | V37: =SUM(T37:U37) -> 12356.006
A38: PERSNL | B38: 70000 | C38: COL2 | D38: Accountant | E38: 57428.39 | F38: Month | G38: =(21000/12) -> 1750 | H38: ='LOE Breakdown by Year'!D36 -> 0.1 | I38: 12 | J38: =I38*G38*H38 -> 2100 | K38: ='LOE Breakdown by Year'!D76 -> 0.2 | L38: 12 | M38: =L38*G38*$K38*$E$8 -> 4410 | N38: ='LOE Breakdown by Year'!D116 -> 0.2 | O38: 12 | P38: =O38*G38*$N38*$E$8*$E$8 -> 4630.5 | Q38: ='LOE Breakdown by Year'!D156 -> 0.2 | R38: 5 | S38: =R38*G38*$Q38*$E$8*$E$8*$E$8 -> 2025.8438 | T38: =SUM(P38,M38,J38,E38,S38) -> 70594.734 | U38: 0 | V38: =SUM(T38:U38) -> 70594.734
A39: PERSNL | B39: 70000 | C39: COL2 | D39: Finance & Admin Coordinator - 50% LOE | E39: 0 | F39: Month | G39: =31000/12 -> 2583.3333 | H39: ='LOE Breakdown by Year'!D37 -> 0.1 | I39: 12 | J39: =I39*G39*H39 -> 3100 | K39: ='LOE Breakdown by Year'!D77 -> 0.1 | L39: 12 | M39: =L39*G39*$K39*$E$8 -> 3255 | N39: ='LOE Breakdown by Year'!D117 -> 0.1 | O39: 12 | P39: =O39*G39*$N39*$E$8*$E$8 -> 3417.75 | Q39: ='LOE Breakdown by Year'!D157 -> 0.1 | R39: 6 | S39: =R39*G39*$Q39*$E$8*$E$8*$E$8 -> 1794.3188 | T39: =SUM(P39,M39,J39,E39,S39) -> 11567.069 | U39: 0 | V39: =SUM(T39:U39) -> 11567.069
A40: PERSNL | B40: 70000 | C40: COL2 | D40: Administrative Officer | E40: 31713.93 | F40: Month | G40: =12000/12 -> 1000 | H40: ='LOE Breakdown by Year'!D38 -> 0.1 | I40: 12 | J40: =I40*G40*H40 -> 1200 | K40: ='LOE Breakdown by Year'!D78 -> 0.3 | L40: 12 | M40: =L40*G40*$K40*$E$8 -> 3780 | N40: ='LOE Breakdown by Year'!D118 -> 0.3 | O40: 12 | P40: =O40*G40*$N40*$E$8*$E$8 -> 3969 | Q40: ='LOE Breakdown by Year'!D158 -> 0.3 | R40: 3 | S40: =R40*G40*$Q40*$E$8*$E$8*$E$8 -> 1041.8625 | T40: =SUM(P40,M40,J40,E40,S40) -> 41704.793 | U40: 0 | V40: =SUM(T40:U40) -> 41704.793
A41: PERSNL | B41: 70000 | C41: COL2 | D41: Human Resource Manager | E41: 0 | F41: Month | G41: =(35000/12)*67% -> 1954.1667 | H41: ='LOE Breakdown by Year'!D39 -> 0.1 | I41: 12 | J41: =I41*G41*H41 -> 2345 | K41: ='LOE Breakdown by Year'!D79 -> 0.3 | L41: 12 | M41: =L41*G41*$K41*$E$8 -> 7386.75 | N41: ='LOE Breakdown by Year'!D119 -> 0.3 | O41: 12 | P41: =O41*G41*$N41*$E$8*$E$8 -> 7756.0875 | Q41: ='LOE Breakdown by Year'!D159 -> 0.3 | R41: 6 | S41: =R41*G41*$Q41*$E$8*$E$8*$E$8 -> 4071.9459 | T41: =SUM(P41,M41,J41,E41,S41) -> 21559.783 | U41: 0 | V41: =SUM(T41:U41) -> 21559.783
A42: PERSNL | B42: 70000 | C42: COL2 | D42: Human Resource Specialist | E42: 0 | F42: Month | G42: =21000/12 -> 1750 | H42: ='LOE Breakdown by Year'!D40 -> 0.1 | I42: 12 | J42: =I42*G42*H42 -> 2100 | K42: ='LOE Breakdown by Year'!D80 -> 0.3 | L42: 12 | M42: =L42*G42*$K42*$E$8 -> 6615 | N42: ='LOE Breakdown by Year'!D120 -> 0.3 | O42: 12 | P42: =O42*G42*$N42*$E$8*$E$8 -> 6945.75 | Q42: ='LOE Breakdown by Year'!D160 -> 0.3 | R42: 3 | S42: =R42*G42*$Q42*$E$8*$E$8*$E$8 -> 1823.2594 | T42: =SUM(P42,M42,J42,E42,S42) -> 17484.009 | U42: 0 | V42: =SUM(T42:U42) -> 17484.009
D43: Headquarters (HQ) Support (LOE)
A44: PERSNL | B44: 50000 | C44: USA | D44: Senior Program Director | E44: 105808.88 | F44: Month | G44: =150000/12 -> 12500 | H44: ='LOE Breakdown by Year'!D42 -> 0.25 | I44: 12 | J44: =I44*G44*H44 -> 37500 | K44: ='LOE Breakdown by Year'!D82 -> 0.25 | L44: 12 | M44: =L44*G44*$K44*$E$8 -> 39375 | N44: ='LOE Breakdown by Year'!D122 -> 0.25 | O44: 12 | P44: =O44*G44*$N44*$E$8*$E$8 -> 41343.75 | Q44: ='LOE Breakdown by Year'!D162 -> 0.25 | R44: 6 | S44: =R44*G44*$Q44*$E$8*$E$8*$E$8 -> 21705.469 | T44: =SUM(P44,M44,J44,E44,S44) -> 245733.1 | U44: 0 | V44: =SUM(T44:U44) -> 245733.1
A45: PERSNL | B45: 50000 | C45: USA | D45: Associate Director | E45: =317426.65-146724 -> 170702.65 | F45: Month | G45: =100000/12 -> 8333.3333 | H45: ='LOE Breakdown by Year'!D43 -> 0.65 | I45: 12 | J45: =I45*G45*H45 -> 65000 | K45: ='LOE Breakdown by Year'!D83 -> 0.65 | L45: 12 | M45: =L45*G45*$K45*$E$8 -> 68250 | N45: ='LOE Breakdown by Year'!D123 -> 0.65 | O45: 12 | P45: =O45*G45*$N45*$E$8*$E$8 -> 71662.5 | Q45: ='LOE Breakdown by Year'!D163 -> 0.65 | R45: 6 | S45: =R45*G45*$Q45*$E$8*$E$8*$E$8 -> 37622.812 | T45: =SUM(P45,M45,J45,E45,S45) -> 413237.96 | U45: 0 | V45: =SUM(T45:U45) -> 413237.96
A46: PERSNL | B46: 50000 | C46: USA | D46: Senior Program Officer | E46: 0 | F46: Month | G46: =70000/12 -> 5833.3333 | H46: ='LOE Breakdown by Year'!D44 -> 0.61 | I46: 12 | J46: =I46*G46*H46 -> 42700 | K46: ='LOE Breakdown by Year'!D84 -> 0.61 | L46: 12 | M46: =L46*G46*$K46*$E$8 -> 44835 | N46: ='LOE Breakdown by Year'!D124 -> 0.61 | O46: 12 | P46: =O46*G46*$N46*$E$8*$E$8 -> 47076.75 | Q46: ='LOE Breakdown by Year'!D164 -> 0.61 | R46: 6 | S46: =R46*G46*$Q46*$E$8*$E$8*$E$8 -> 24715.294 | T46: =SUM(P46,M46,J46,E46,S46) -> 159327.04 | U46: 0 | V46: =SUM(T46:U46) -> 159327.04
D48: Total Personnel | E48: =SUM(E13:E47) -> 933268.52 | J48: =SUM(J13:J46) -> 234397.92 | M48: =SUM(M13:M46) -> 243114.82 | P48: =SUM(P13:P46) -> 255270.56 | S48: =SUM(S13:S46) -> 116879.37 | T48: =SUM(T13:T46) -> 1782931.2 | U48: =SUM(U13:U46) -> 0 | V48: =SUM(V13:V46) -> 1782931.2 | W48: =SUM(V48,V176,V230,V307,V404,V477,V551,V631,V701) -> 8060160.8
D50: Fringe Benefits
A51: FRINGE | B51: 70015 | C51: COL2 | D51: Fringe Benefits CCN - Colombia (above $3,350 monthly) | E51: 38320.45 | F51: % | G51: 0.53864 | J51: =(J15+J24+J28+J31+J34+J36+J14)*$G$51 -> 19796.593 | M51: =(M15+M24+M28+M31+M34+M36+M14)*$G$51 -> 22200.352 | P51: =(P15+P24+P28+P31+P34+P36+P14)*$G$51 -> 23310.37 | S51: =(S15+S24+S28+S31+S34+S36+S14)*$G$51 -> 10380.305 | T51: =SUM(P51,M51,J51,E51,S51) -> 114008.07 | U51: 0 | V51: =SUM(T51:U51) -> 114008.07
A52: FRINGE | B52: 70015 | C52: COL2 | D52: Fringe Benefits CCN - Colombia (below $3,350 monthly) | E52: 221449.96 | F52: % | G52: 0.44864 | J52: =(J16+J17+J18+J19+J20+J21+J22+J23+J25+J26+J27+J29+J30+J32+J33+J35+J37+J38+J39+J40+J41+J42)*$G$52 -> 15857.181 | M52: =(M16+M17+M18+M19+M20+M21+M22+M23+M25+M26+M27+M29+M30+M32+M33+M35+M37+M38+M39+M40+M41+M42)*$G$52 -> 18152.76 | P52: =(P16+P17+P18+P19+P20+P21+P22+P23+P25+P26+P27+P29+P30+P32+P33+P35+P37+P38+P39+P40+P41+P42)*$G$52 -> 19060.397 | S52: =(S16+S17+S18+S19+S20+S21+S22+S23+S25+S26+S27+S29+S30+S32+S33+S35+S37+S38+S39+S40+S41+S42)*$G$52 -> 6085.5642 | T52: =SUM(P52,M52,J52,E52,S52) -> 280605.86 | U52: 0 | V52: =SUM(T52:U52) -> 280605.86
A53: FRINGE | B53: 50900 | C53: USA | D53: Fringe Benefits - HQ (23.47%) | E53: 99333.38 | F53: % | G53: 0.2347 | J53: =(J44+J45+J46)*$G$53 -> 34078.44 | M53: =(M44+M45+M46)*$G$53 -> 35782.362 | P53: =(P44+P45+P46)*$G$53 -> 37571.48 | S53: =(S44+S45+S46)*$G$53 -> 19725.027 | T53: =SUM(P53,M53,J53,E53,S53) -> 226490.69 | U53: 0 | V53: =SUM(T53:U53) -> 226490.69
A54: POST DIFF | B54: 50202 | C54: COL2 | D54: Post (Hardship) Differential for Chief of Party | E54: 59486.73 | F54: % | G54: 0.15 | J54: =J13*$G$54 -> 2565 | M54: =M13*$G$54 -> 1346.625 | P54: =P13*$G$54 -> 1413.9562 | S54: =S13*$G$54 -> 0 | T54: =SUM(P54,M54,J54,E54,S54) -> 64812.311 | U54: 0 | V54: =SUM(T54:U54) -> 64812.311
A55: FRINGE | B55: 50900 | C55: USA | D55: Fringe Benefits Package for Chief of Party | E55: 64022.09 | F55: % | G55: 0.5647 | J55: =J13*$G$55 -> 9656.37 | M55: =M13*$G$55 -> 5069.5943 | P55: =P13*$G$55 -> 5323.074 | S55: =S13*$G$55 -> 0 | T55: =SUM(P55,M55,J55,E55,S55) -> 84071.128 | U55: 0 | V55: =SUM(T55:U55) -> 84071.128
A56: HOUSE. ALL | B56: 50203 | C56: COL2 | D56: Housing Allowance for Chief of Party | E56: 68428.33 | F56: Month | G56: 3000 | I56: 12 | J56: =G56*I56 -> 36000 | L56: 12 | M56: =G56*L56*$E$7 -> 37440 | O56: 12 | P56: =G56*O56*$E$7*$E$7 -> 38937.6 | R56: 0 | S56: =R56*G56*$E$7*$E$7*$E$7 -> 0 | T56: =SUM(P56,M56,J56,E56,S56) -> 180805.93 | U56: 0 | V56: =SUM(T56:U56) -> 180805.93
A57: REALLOC | B57: 50205 | C57: COL2 | D57: Reallocation & Demobilization Allowance for Chief of Party | E57: 1565.26 | F57: Year | G57: 2583.93 | I57: 0 | J57: =G57*I57 -> 0 | L57: 0 | M57: =G57*L57*$E$7 -> 0 | O57: 1 | P57: =G57*O57*$E$7*$E$7 -> 2794.7787 | R57: 0 | S57: =R57*G57*$E$7*$E$7*$E$7 -> 0 | T57: =SUM(P57,M57,J57,E57,S57) -> 4360.0387 | U57: 0 | V57: =SUM(T57:U57) -> 4360.0387
A58: R&RTRIP | B58: 50206 | C58: COL2 | D58: Annual Home of Record for Chief of Party | E58: 1357.75 | F58: Year | G58: 1100 | I58: 1 | J58: =G58*I58 -> 1100 | L58: 1 | M58: =G58*L58*$E$7 -> 1144 | O58: 1 | P58: =G58*O58*$E$7*$E$7 -> 1189.76 | R58: 1 | S58: =R58*G58*$E$7*$E$7*$E$7 -> 1237.3504 | T58: =SUM(P58,M58,J58,E58,S58) -> 6028.8604 | U58: 0 | V58: =SUM(T58:U58) -> 6028.8604
D60: Total Fringe Benefits | E60: =SUM(E51:E59) -> 553963.95 | J60: =SUM(J51:J59) -> 119053.58 | M60: =SUM(M51:M59) -> 121135.69 | P60: =SUM(P51:P59) -> 129601.42 | S60: =SUM(S51:S59) -> 37428.247 | T60: =SUM(T51:T59) -> 961182.89 | U60: =SUM(U51:U59) -> 0 | V60: =SUM(V51:V59) -> 961182.89
D62: Travel
D63: HQ Staff Travel - International
A64: STFTRAVEL | B64: 86040 | C64: USA | D64: Airfare - DC-Colombia - HQ Project Management Trip | E64: 12141.75 | F64: Trip | G64: 800 | I64: 4 | J64: =G64*I64 -> 3200 | L64: 4 | M64: =G64*L64*$E$7 -> 3328 | O64: 4 | P64: =G64*O64*$E$7*$E$7 -> 3461.12 | R64: 4 | S64: =R64*G64*$E$7*$E$7*$E$7 -> 3599.5648 | T64: =SUM(P64,M64,J64,E64,S64) -> 25730.435 | U64: 0 | V64: =SUM(T64:U64) -> 25730.435
A65: STFTRVCTS | B65: 86030 (Lodging)/ 86050 (M&IE) | C65: USA | D65: Lodging and M&IE - HQ Project Management Trip | E65: 13828.71 | F65: Day | G65: =166+120 -> 286 | I65: =I64*5 -> 20 | J65: =G65*I65 -> 5720 | L65: =L64*5 -> 20 | M65: =G65*L65*$E$7 -> 5948.8 | O65: =O64*5 -> 20 | P65: =G65*O65*$E$7*$E$7 -> 6186.752 | R65: =R64*5 -> 20 | S65: =R65*G65*$E$7*$E$7*$E$7 -> 6434.2221 | T65: =SUM(P65,M65,J65,E65,S65) -> 38118.484 | U65: 0 | V65: =SUM(T65:U65) -> 38118.484
A66: STFTRVCTS | B66: 86000 | C66: USA | D66: Local Transportation – HQ Project Management Trip | E66: 1104.45 | F66: Trip | G66: 100 | I66: =I64 -> 4 | J66: =G66*I66 -> 400 | L66: =L64 -> 4 | M66: =G66*L66*$E$7 -> 416 | O66: =O64 -> 4 | P66: =G66*O66*$E$7*$E$7 -> 432.64 | R66: =R64 -> 4 | S66: =R66*G66*$E$7*$E$7*$E$7 -> 449.9456 | T66: =SUM(P66,M66,J66,E66,S66) -> 2803.0356 | U66: 0 | V66: =SUM(T66:U66) -> 2803.0356
A67: STFTRVCTS | B67: 86050 | C67: USA | D67: Other Travel Related Expenses – HQ Project Management Trip | E67: 118.18 | F67: Trip | G67: 25 | I67: =I64 -> 4 | J67: =G67*I67 -> 100 | L67: =L64 -> 4 | M67: =G67*L67*$E$7 -> 104 | O67: =O64 -> 4 | P67: =G67*O67*$E$7*$E$7 -> 108.16 | R67: =R64 -> 4 | S67: =R67*G67*$E$7*$E$7*$E$7 -> 112.4864 | T67: =SUM(P67,M67,J67,E67,S67) -> 542.8264 | U67: 0 | V67: =SUM(T67:U67) -> 542.8264
D68: Colombia Staff Travel - International
A69: INTLTRVLCO | B69: 86040 | C69: COL2 | D69: Airfare - Roundtrip - Colombia to USA | E69: =722.14+843.97+2684+661.75+3905.7-177 -> 8640.56 | F69: Trip | G69: 800 | I69: 4 | J69: =G69*I69 -> 3200 | L69: 4 | M69: =G69*L69*$E$6 -> 3296 | O69: 4 | P69: =G69*O69*$E$6*$E$6 -> 3394.88 | R69: 4 | S69: =R69*G69*$E$6*$E$6*$E$6 -> 3496.7264 | T69: =SUM(P69,M69,J69,E69,S69) -> 22028.166 | U69: 0 | V69: =SUM(T69:U69) -> 22028.166
A70: INTLTRVLCO | B70: 86030 (Lodging)/ 86050 (M&IE) | C70: COL2 | D70: Lodging and M&IE for Colombia Staff Travel | E70: =1063.2+432+46.87+3624.64+1849.98+1143.7 -> 8160.39 | F70: Day | G70: =72+188 -> 260 | I70: =10*I69 -> 40 | J70: =G70*I70 -> 10400 | L70: =10*L69 -> 40 | M70: =G70*L70*$E$6 -> 10712 | O70: =10*O69 -> 40 | P70: =G70*O70*$E$6*$E$6 -> 11033.36 | R70: =10*R69 -> 40 | S70: =R70*G70*$E$6*$E$6*$E$6 -> 11364.361 | T70: =SUM(P70,M70,J70,E70,S70) -> 51670.111 | U70: 0 | V70: =SUM(T70:U70) -> 51670.111
A71: INTLTRVLCO | B71: 86000 | C71: COL2 | D71: Local Transportation for Colombia Staff Travel | E71: 895.05 | F71: Trip | G71: 100 | I71: =I69 -> 4 | J71: =G71*I71 -> 400 | L71: =L69 -> 4 | M71: =G71*L71*$E$6 -> 412 | O71: =O69 -> 4 | P71: =G71*O71*$E$6*$E$6 -> 424.36 | R71: =R69 -> 4 | S71: =R71*G71*$E$6*$E$6*$E$6 -> 437.0908 | T71: =SUM(P71,M71,J71,E71,S71) -> 2568.5008 | U71: 0 | V71: =SUM(T71:U71) -> 2568.5008
A72: INTLTRVLCO | B72: 86050 | C72: COL2 | D72: Other Travel Related Expenses for Colombia Staff Travel | E72: =165.86+208.63 -> 374.49 | F72: Trip | G72: 25 | I72: =I69 -> 4 | J72: =G72*I72 -> 100 | L72: =L69 -> 4 | M72: =G72*L72*$E$6 -> 103 | O72: =O69 -> 4 | P72: =G72*O72*$E$6*$E$6 -> 106.09 | R72: =R69 -> 4 | S72: =R72*G72*$E$6*$E$6*$E$6 -> 109.2727 | T72: =SUM(P72,M72,J72,E72,S72) -> 792.8527 | U72: 0 | V72: =SUM(T72:U72) -> 792.8527
D73: Colombia Local Staff Travel - Domestic
A74: LOCAL TRVL | B74: 86000 | C74: COL2 | D74: Vehicle/Motorcycle Fuel Expense | E74: 9640.86 | F74: Month | G74: 200 | I74: 12 | J74: =G74*I74 -> 2400 | L74: 12 | M74: =L74*G74*$E$7 -> 2496 | O74: 12 | P74: =O74*G74*$E$7*$E$7 -> 2595.84 | R74: 3 | S74: =R74*G74*$E$7*$E$7*$E$7 -> 674.9184 | T74: =SUM(P74,M74,J74,E74,S74) -> 17807.618 | U74: 0 | V74: =SUM(T74:U74) -> 17807.618
A75: LOCAL TRVL | B75: 86000 | C75: COL2 | D75: Local Transportation – Training, M&E, & Data Collection | E75: 32433.77 | F75: Trip | G75: 100 | I75: =12*3 -> 36 | J75: =G75*I75 -> 3600 | L75: =12*3 -> 36 | M75: =L75*G75*$E$7 -> 3744 | O75: =12*3 -> 36 | P75: =O75*G75*$E$7*$E$7 -> 3893.76 | R75: =3*3 -> 9 | S75: =R75*G75*$E$7*$E$7*$E$7 -> 1012.3776 | T75: =SUM(P75,M75,J75,E75,S75) -> 44683.908 | U75: 0 | V75: =SUM(T75:U75) -> 44683.908
A76: LOCAL TRVL | B76: 86030 (Lodging)/ 86050 (M&IE) | C76: COL2 | D76: Lodging and M&IE - Training, M&E, & Data Collection | E76: 14326.42 | F76: Day | G76: =77+80 -> 157 | I76: =4*I75 -> 144 | J76: =G76*I76 -> 22608 | L76: =4*L75 -> 144 | M76: =L76*G76*$E$7 -> 23512.32 | O76: =4*O75 -> 144 | P76: =O76*G76*$E$7*$E$7 -> 24452.813 | R76: =4*R75 -> 36 | S76: =R76*G76*$E$7*$E$7*$E$7 -> 6357.7313 | T76: =SUM(P76,M76,J76,E76,S76) -> 91257.284 | U76: 0 | V76: =SUM(T76:U76) -> 91257.284
D77: Total Travel | E77: =SUM(E63:E76) -> 101664.63 | J77: =SUM(J63:J76) -> 52128 | M77: =SUM(M63:M76) -> 54072.12 | P77: =SUM(P63:P76) -> 56089.775 | S77: =SUM(S63:S76) -> 34048.697 | T77: =SUM(T63:T76) -> 298003.22 | U77: =SUM(U63:U76) -> 0 | V77: =SUM(V63:V76) -> 298003.22
D79: Professional Services/Contractual
A80: PAYROLL | B80: 82100 (Audit)/ 81030 (Payroll) | C80: COL2 | D80: Payroll, Accounting and Audit Costs - (Auditoria Fiscal & Program Specific Audits) | E80: 26306.36 | F80: Year | G80: 13000 | I80: 1 | J80: =I80*G80 -> 13000 | L80: 1 | M80: =L80*G80 -> 13000 | O80: 1 | P80: =O80*G80 -> 13000 | R80: 0.5 | S80: =R80*G80 -> 6500 | T80: =SUM(P80,M80,J80,E80,S80) -> 71806.36 | U80: 0 | V80: =SUM(T80:U80) -> 71806.36
A81: LEGAL | B81: 81010 | C81: COL2 | D81: Legal Fees | E81: 22150.08 | F81: Year | G81: =2625+1800 -> 4425 | I81: 1 | J81: =I81*G81 -> 4425 | L81: 1 | M81: =L81*G81 -> 4425 | O81: 1 | P81: =O81*G81 -> 4425 | R81: 1 | S81: =R81*G81 -> 4425 | T81: =SUM(P81,M81,J81,E81,S81) -> 39850.08 | U81: 0 | V81: =SUM(T81:U81) -> 39850.08
A82: MONETIZE | B82: 81010 | C82: USA | D82: Monetization Agent Fee | E82: 512975 | F82: % | G82: 0.025 | I82: 1 | J82: =G82*9000000 -> 225000 | L82: 0 | M82: 0 | O82: 0 | P82: =O82*G82 -> 0 | R82: 0 | S82: =R82*G82 -> 0 | T82: =SUM(P82,M82,J82,E82,S82) -> 737975 | U82: 0 | V82: =SUM(T82:U82) -> 737975
A83: MONEASSMT | B83: 81010 | C83: COL2 | D83: Post Monetization Assessment | E83: 47918.55 | F83: Unit | G83: =E83 -> 47918.55 | I83: 0 | J83: =I83*G83 -> 0 | L83: 0 | M83: =L83*G83 -> 0 | O83: 0 | P83: =O83*G83 -> 0 | R83: 0 | S83: =R83*G83 -> 0 | T83: =SUM(P83,M83,J83,E83,S83) -> 47918.55 | U83: 0 | V83: =SUM(T83:U83) -> 47918.55
A84: SECURITY | B84: 86110 | C84: COL2 | D84: Security Plan and Advisors | E84: 0 | F84: Year | G84: 25000 | I84: 1 | J84: =I84*G84 -> 25000 | L84: 1 | M84: =L84*G84 -> 25000 | O84: 1 | P84: =O84*G84 -> 25000 | R84: 0.5 | S84: =R84*G84 -> 12500 | T84: =SUM(P84,M84,J84,E84,S84) -> 87500 | U84: 0 | V84: =SUM(T84:U84) -> 87500
A85: CONSULT | B85: 81000 | C85: COL2 | D85: HQ Consultants & Advisory Support Services | E85: 68599.1 | F85: Month | G85: 1125 | I85: 12 | J85: =I85*G85 -> 13500 | L85: 12 | M85: =L85*G85 -> 13500 | O85: 12 | P85: =O85*G85 -> 13500 | R85: 6 | S85: =R85*G85 -> 6750 | T85: =SUM(P85,M85,J85,E85,S85) -> 115849.1 | U85: 0 | V85: =SUM(T85:U85) -> 115849.1
D86: Monitoring, Evaluation, and Collection of Reliable Data
D87: Evaluations
A88: BASELINE | B88: 81010 | C88: COL2 | D88: Baseline Evaluation | E88: 151977.65 | F88: Unit | G88: =E88 -> 151977.65 | I88: 0 | J88: =I88*G88 -> 0 | L88: 0 | M88: =L88*G88 -> 0 | O88: 0 | P88: =O88*G88 -> 0 | R88: 0 | S88: =R88*G88 -> 0 | T88: =SUM(P88,M88,J88,E88,S88) -> 151977.65 | U88: 0 | V88: =SUM(T88:U88) -> 151977.65
A89: MIDTERM | B89: 81010 | C89: COL2 | D89: Midterm Evaluation | E89: 18463 | F89: Unit | G89: 166537 | I89: 1 | J89: =I89*G89 -> 166537 | L89: 0 | M89: =L89*G89 -> 0 | O89: 0 | P89: =O89*G89 -> 0 | R89: 0 | S89: =R89*G89 -> 0 | T89: =SUM(P89,M89,J89,E89,S89) -> 185000 | U89: 0 | V89: =SUM(T89:U89) -> 185000
A90: ENDLINE | B90: 81010 | C90: COL2 | D90: Final Evaluation | E90: 0 | F90: Unit | G90: 225000 | I90: 0 | J90: =I90*G90 -> 0 | L90: 0 | M90: =L90*G90 -> 0 | O90: 0 | P90: =O90*G90 -> 0 | R90: 1 | S90: =R90*G90 -> 225000 | T90: =SUM(P90,M90,J90,E90,S90) -> 225000 | U90: 0 | V90: =SUM(T90:U90) -> 225000
A91: VALUECHAIN | B91: 81010 | C91: COL2 | D91: Value Chain Analysis, Carbon Assessment, and Living Incomes | E91: 542898.59 | F91: Subrecipient | G91: =E91 -> 542898.59 | I91: 1 | J91: 31587 | L91: 0 | M91: =L91*G91 -> 0 | O91: 1 | P91: 43803.95 | R91: 0 | S91: =R91*G91 -> 0 | T91: =SUM(P91,M91,J91,E91,S91) -> 618289.54 | U91: 0 | V91: =SUM(T91:U91) -> 618289.54
D92: Monitoring Guidelines Development
A93: M&ETRAIN | B93: 81021 (Translation)/ 85300 (Printing) | C93: COL2 | D93: Monitoring Guidelines Creation, Translation & Printing | E93: 0 | F93: Document | G93: 6000 | I93: 1 | J93: =I93*G93 -> 6000 | L93: 0 | M93: =L93*G93 -> 0 | O93: 0 | P93: =O93*G93 -> 0 | R93: 0 | S93: =R93*I93 -> 0 | T93: =SUM(P93,M93,J93,E93,S93) -> 6000 | U93: 0 | V93: =SUM(T93:U93) -> 6000
A94: M&ETRAIN | B94: 87000 | C94: COL2 | D94: Monitoring Guidelines Staff Training Workshop | E94: 63.84 | F94: Workshop | G94: 6800 | I94: 1 | J94: =I94*G94 -> 6800 | L94: 1 | M94: =L94*G94 -> 6800 | O94: 1 | P94: =O94*G94 -> 6800 | R94: 0 | S94: =R94*G94 -> 0 | T94: =SUM(P94,M94,J94,E94,S94) -> 20463.84 | U94: 0 | V94: =SUM(T94:U94) -> 20463.84
D95: M&E Database
A96: M&EDATA | B96: 81000 | C96: USA | D96: M&E Software Setup | E96: 33269.83 | F96: Year | G96: =E96 -> 33269.83 | I96: 0 | J96: =I96*G96 -> 0 | L96: 0 | M96: =L96*G96 -> 0 | O96: 0 | P96: =O96*G96 -> 0 | R96: 0 | S96: =R96*G96 -> 0 | T96: =SUM(P96,M96,J96,E96,S96) -> 33269.83 | U96: 0 | V96: =SUM(T96:U96) -> 33269.83
A97: M&EDATA | B97: 89400 | C97: USA | D97: M&E Software Fee (Annual) | E97: 44624.18 | F97: Year | G97: 10000 | I97: 1 | J97: =I97*G97 -> 10000 | L97: 1 | M97: =L97*G97 -> 10000 | O97: 1 | P97: =O97*G97 -> 10000 | R97: 1 | S97: =R97*G97 -> 10000 | T97: =SUM(P97,M97,J97,E97,S97) -> 84624.18 | U97: 0 | V97: =SUM(T97:U97) -> 84624.18
A98: M&EDATA | B98: 87000 | C98: USA | D98: M&E Software Training | E98: 0 | F98: Year | G98: 0 | I98: 1 | J98: =I98*G98 -> 0 | M98: =L98*G98 -> 0 | P98: =O98*G98 -> 0 | S98: =R98*G98 -> 0 | T98: =SUM(P98,M98,J98,E98,S98) -> 0 | U98: 0 | V98: =SUM(T98:U98) -> 0
D99: Monitoring, Evaluation, and Collection of Reliable Data Subtotal | E99: =SUM(E87:E98) -> 791297.09 | J99: =SUM(J87:J98) -> 220924 | M99: =SUM(M87:M98) -> 16800 | P99: =SUM(P87:P98) -> 60603.95 | S99: =SUM(S87:S98) -> 235000 | T99: =SUM(T87:T98) -> 1324625 | U99: =SUM(U87:U98) -> 0 | V99: =SUM(V87:V98) -> 1324625 | W99: =V99/T741 -> 0.042262412
D101: Total Professional Services/Contractual | E101: =SUM(E80:E98) -> 1469246.2 | J101: =SUM(J80:J98) -> 501849 | M101: =SUM(M80:M98) -> 72725 | P101: =SUM(P80:P98) -> 116528.95 | S101: =SUM(S80:S98) -> 265175 | T101: =SUM(T80:T98) -> 2425524.1 | U101: =SUM(U80:U98) -> 0 | V101: =SUM(T101:U101) -> 2425524.1
D103: Equipment
A104: VEHICLE | B104: 85200 | C104: COL2 | D104: Vehicles for Field Office | E104: 72554.43 | F104: Unit | G104: =E104 -> 72554.43 | I104: 0 | J104: =I104*G104 -> 0 | L104: 0 | M104: =L104*G104 -> 0 | O104: 0 | P104: =O104*G104 -> 0 | R104: 0 | S104: =R104*I104 -> 0 | T104: =SUM(P104,M104,J104,E104,S104) -> 72554.43 | U104: 0 | V104: =SUM(T104:U104) -> 72554.43
D106: Total Equipment | E106: =SUM(E104:E104) -> 72554.43 | J106: =SUM(J104:J104) -> 0 | M106: =SUM(M104:M104) -> 0 | P106: =SUM(P104:P104) -> 0 | S106: =SUM(S104:S104) -> 0 | T106: =SUM(T104:T105) -> 72554.43 | U106: =SUM(U104:U104) -> 0 | V106: =SUM(T106:U106) -> 72554.43
D108: Office Expenses
D109: Office in Bogota
A110: COMM | B110: 82350 | C110: COL2/USA | D110: Courier fees/services/Postage | E110: 1093.45 | F110: Month | G110: 30 | I110: 12 | J110: =I110*G110 -> 360 | L110: 12 | M110: =L110*G110*$E$7 -> 374.4 | O110: 12 | P110: =O110*G110*$E$7*$E$7 -> 389.376 | R110: 6 | S110: =R110*G110*$E$7*$E$7*$E$7 -> 202.47552 | T110: =SUM(P110,M110,J110,E110,S110) -> 2419.7015 | U110: 0 | V110: =SUM(T110:U110) -> 2419.7015
...

Sheet Project Funds Snapshots
B2: FFPR Program Budget Summary Sheet
C3: Total USDA Project | D3: Direct $ | E3: Direct % | F3: Indirect Costs $ | G3: Indirect %
B5: OVERALL PROJECT BUDGET | C5: ='USDA Budget Summary'!F66 -> 33320792 | D5: ='USDA Budget Summary'!F55 -> 27016306 | E5: =D5/C5 -> 0.81079423 | F5: ='USDA Budget Summary'!E62 -> 6304486.1 | G5: =F5/C5 -> 0.18920577
B6: USDA | C6: ='USDA Budget Summary'!B66+'USDA Budget Summary'!C66 -> 31342864 | D6: ='USDA Budget Summary'!E55 -> 25038378 | E6: =D6/C6 -> 0.79885418 | F6: ='USDA Budget Summary'!E62 -> 6304486.1 | G6: =F6/C6 -> 0.20114582
B7: Cost Share | C7: ='USDA Budget Summary'!D66 -> 1977928 | D7: ='USDA Budget Summary'!D26+'USDA Budget Summary'!D37 -> 1977928 | E7: =D7/C7 -> 1 | F7: 0 | G7: =F7/C7 -> 0
C9: Total USDA Project | D9: Direct $ | E9: Direct % | F9: Indirect Costs $ | G9: Cost Share $ | H9: % of Direct Funds by Partner
B11: BUDGET BY PARTNER
B12: POA | C12: ='USDA Budget Summary'!F66-C13 -> 32318199 | D12: =C12-F12-G12-G13 -> 24035785 | E12: =D12/SUM($C$12:$C$13) -> 0.72134495 | F12: ='USDA Budget Summary'!E62 -> 6304486.1 | G12: ='USDA Budget Summary'!D37-'Project Funds Snapshots'!G13 -> 1965708.8 | H12: =(G12+D12)/SUM($C$12:$C$13) -> 0.78033841
B13: Sub 1 - Fundación Julio y Astrida Carrizosa ONG | C13: ='Detailed Budget'!T107 -> 1002592.9 | D13: ='Sub Budget Fundacion IC'!T103 -> 953995.54 | E13: =D13/SUM($C$12:$C$13) -> 0.028630638 | F13: ='Sub Budget Fundacion IC'!T107 -> 48596.357 | G13: ='Sub Budget Fundacion IC'!T110 -> 12219.19 | H13: =(G13+D13)/SUM($C$12:$C$13) -> 0.028997352
C15: Total USDA Project | D15: Direct $ | E15: Direct % | F15: Indirect Costs $ | G15: Cost Share $ | H15: % of Direct Funds by Activity
B16: BUDGET BY ACTIVITY
B17: Admin | C17: =F17+D17+G17 -> 8183592.5 | D17: ='USDA Budget Summary'!E26 -> 6355224.3 | E17: =D17/SUM($C$17:$C$25) -> 0.19072817 | F17: =Admin!T144 -> 1828368.2 | G17: 0 | H17: =(G17+D17)/SUM($C$17:$C$25) -> 0.19072817
B18: Activity 1 | C18: =F18+D18+G18 -> 352228.29 | D18: ='USDA Budget Summary'!B29 -> 272696.75 | E18: =D18/SUM($C$17:$C$25) -> 0.0081839679 | F18: ='Activity 1'!T84 -> 79531.545 | G18: 0 | H18: =(G18+D18)/SUM($C$17:$C$25) -> 0.0081839679
B19: Activity 2 | C19: =F19+D19+G19 -> 3152067.9 | D19: ='USDA Budget Summary'!B30 -> 2209930.1 | E19: =D19/SUM($C$17:$C$25) -> 0.066322745 | F19: ='Activity 2'!T92 -> 629918.83 | G19: 312219 | H19: =(G19+D19)/SUM($C$17:$C$25) -> 0.075692824
B20: Activity 3 | C20: =F20+D20+G20 -> 10538868 | D20: ='USDA Budget Summary'!B31 -> 7469424.7 | E20: =D20/SUM($C$17:$C$25) -> 0.2241667 | F20: ='Activity 3'!T111 -> 2129853.1 | G20: 939590.56 | H20: =(G20+D20)/SUM($C$17:$C$25) -> 0.25236498
B21: Activity 4 | C21: =F21+D21+G21 -> 2703803.2 | D21: ='USDA Budget Summary'!B32 -> 1992268.2 | E21: =D21/SUM($C$17:$C$25) -> 0.05979044 | F21: ='Activity 4'!T93 -> 569606.02 | G21: 141929 | H21: =(G21+D21)/SUM($C$17:$C$25) -> 0.064049905
B22: Activity 5 | C22: =F22+D22+G22 -> 2003731.7 | D22: ='USDA Budget Summary'!B33 -> 1105173.6 | E22: =D22/SUM($C$17:$C$25) -> 0.033167632 | F22: ='Activity 5'!T86 -> 314368.06 | G22: 584190 | H22: =(G22+D22)/SUM($C$17:$C$25) -> 0.050699899
B23: Activity 6 | C23: =F23+D23+G23 -> 1053847.6 | D23: ='USDA Budget Summary'!B34 -> 819624.4 | E23: =D23/SUM($C$17:$C$25) -> 0.024597946 | F23: ='Activity 6'!T93 -> 234223.2 | G23: 0 | H23: =(G23+D23)/SUM($C$17:$C$25) -> 0.024597946
B24: Activity 7 | C24: =F24+D24+G24 -> 1637495.4 | D24: ='USDA Budget Summary'!B35 -> 1274251 | E24: =D24/SUM($C$17:$C$25) -> 0.038241854 | F24: ='Activity 7'!T90 -> 363244.35 | G24: 0 | H24: =(G24+D24)/SUM($C$17:$C$25) -> 0.038241854
B25: Activity 8 | C25: =F25+D25+G25 -> 3695213.1 | D25: ='USDA Budget Summary'!B36 -> 3539784.8 | E25: =D25/SUM($C$17:$C$25) -> 0.10623333 | F25: ='Activity 8'!T81 -> 155428.33 | G25: 0 | H25: =(G25+D25)/SUM($C$17:$C$25) -> 0.10623333
C27: Total USDA Project | D27: Direct $ | E27: Direct % | F27: Indirect Costs $ | G27: Cost Share $ | H27: % of Direct Funds by Activity and Subrecipient
B28: DETAILS BY ACTIVITY & SUBRECIPIENT
B29: Admin - POA | C29: =C17 -> 8183592.5 | D29: =D17 -> 6355224.3 | E29: =D29/SUM($C$29:$C$38) -> 0.19072817 | F29: =Admin!T144 -> 1828368.2 | G29: =Admin!T147 -> 0 | H29: =(G29+D29)/SUM($C$29:$C$38) -> 0.19072817
B30: Activity 1 - POA | C30: =C18 -> 352228.29 | D30: =D18 -> 272696.75 | E30: =D30/SUM($C$29:$C$38) -> 0.0081839679 | F30: ='Activity 1'!T84 -> 79531.545 | G30: ='Activity 1'!T87 -> 0 | H30: =(G30+D30)/SUM($C$29:$C$38) -> 0.0081839679
B31: Activity 2 - POA | C31: =C19-C32 -> 2149475 | D31: =D19-D32 -> 1255934.6 | E31: =D31/SUM($C$29:$C$38) -> 0.037692155 | F31: ='Activity 2'!T92 -> 629918.83 | G31: ='Activity 2'!T96 -> 300000 | H31: =(G31+D31)/SUM($C$29:$C$38) -> 0.046695527
B32: Activity 2 - Sub 1 - Fundación Julio y Astrida Carrizosa ONG | C32: =C13 -> 1002592.9 | D32: ='Sub Budget Fundacion IC'!T103 -> 953995.54 | E32: =D32/SUM($C$29:$C$38) -> 0.02863059 | F32: ='Sub Budget Fundacion IC'!T107 -> 48596.357 | G32: ='Sub Budget Fundacion IC'!T110 -> 12219.19 | H32: =(G32+D32)/SUM($C$29:$C$38) -> 0.028997303
B33: Activity 3 - POA | C33: =C20 -> 10538868 | D33: =D20 -> 7469424.7 | E33: =D33/SUM($C$29:$C$38) -> 0.2241667 | F33: ='Activity 3'!T111 -> 2129853.1 | G33: ='Activity 3'!T114+'Activity 3'!T115+'Activity 3'!T116 -> 939590.56 | H33: =(G33+D33)/SUM($C$29:$C$38) -> 0.25236498
B34: Activity 4 - POA | C34: =C21 -> 2703803.2 | D34: =D21 -> 1992268.2 | E34: =D34/SUM($C$29:$C$38) -> 0.05979044 | F34: ='Activity 4'!T93 -> 569606.02 | G34: ='Activity 4'!T96+'Activity 4'!T97 -> 141928.58 | H34: =(G34+D34)/SUM($C$29:$C$38) -> 0.064049893
B35: Activity 5 - POA | C35: =C22 -> 2003731.7 | D35: =D22 -> 1105173.6 | E35: =D35/SUM($C$29:$C$38) -> 0.033167632 | F35: ='Activity 5'!T86 -> 314368.06 | G35: ='Activity 5'!T89 -> 584189.75 | H35: =(G35+D35)/SUM($C$29:$C$38) -> 0.050699892
B36: Activity 6 - POA | C36: =C23 -> 1053847.6 | D36: =D23 -> 819624.4 | E36: =D36/SUM($C$29:$C$38) -> 0.024597946 | F36: ='Activity 6'!T93 -> 234223.2 | G36: ='Activity 6'!T96 -> 0 | H36: =(G36+D36)/SUM($C$29:$C$38) -> 0.024597946
B37: Activity 7 - POA | C37: =C24 -> 1637495.4 | D37: =D24 -> 1274251 | E37: =D37/SUM($C$29:$C$38) -> 0.038241854 | F37: ='Activity 7'!T90 -> 363244.35 | G37: ='Activity 7'!T93 -> 0 | H37: =(G37+D37)/SUM($C$29:$C$38) -> 0.038241854
B38: Activity 8 - POA | C38: =C25 -> 3695213.1 | D38: =D25 -> 3539784.8 | E38: =D38/SUM($C$29:$C$38) -> 0.10623333 | F38: ='Activity 8'!T81 -> 155428.33 | G38: ='Activity 8'!T84 -> 0 | H38: =(G38+D38)/SUM($C$29:$C$38) -> 0.10623333

Sheet Detailed Budget
A2: Item | B2: Type of Unit | C2: Year 1 -4 Total Inception through 09/30/2024 | D2: Year 5 (10/1/24 - 9/30/25) | H2: Year 6 (10/1/25 - 09/30/26) | L2: Year 7 (10/1/26 - 09/30/27) | P2: Year 8 (10/1/27 - 3/31/28) | T2: Total
D3: Cost | E3: Quantity | F3: Percent Allocated | G3: Total | H3: Cost | I3: Quantity | J3: Percent Allocated | K3: Total | L3: Cost | M3: Quantity | N3: Percent Allocated | O3: Total | P3: Cost | Q3: Quantity | R3: Percent Allocated | S3: Total
A4: Direct Costs
A5: Salaries
A6: USN/TCN Staff
A7: ='Program Budget'!D13 -> Key Personnel: Chief of Party | B7: ='Program Budget'!F15 -> Month | C7: =Admin!C7+'Activity 1'!C7+'Activity 2'!C7+'Activity 3'!C7+'Activity 4'!C7+'Activity 5'!C7+'Activity 6'!C7+'Activity 7'!C7+'Activity 8'!C7 -> 568684.69 | D7: ='Program Budget'!G13 -> 14250 | E7: ='Program Budget'!I13 -> 12 | F7: =Admin!F7+'Activity 1'!F7+'Activity 2'!F7+'Activity 3'!F7+'Activity 4'!F7+'Activity 5'!F7+'Activity 6'!F7+'Activity 7'!F7+'Activity 8'!F7 -> 1 | G7: =D7*E7*F7 -> 171000 | H7: =D7*1.05 -> 14962.5 | I7: ='Program Budget'!L13 -> 12 | J7: =Admin!J7+'Activity 1'!J7+'Activity 2'!J7+'Activity 3'!J7+'Activity 4'!J7+'Activity 5'!J7+'Activity 6'!J7+'Activity 7'!J7+'Activity 8'!J7 -> 1 | K7: =H7*I7*J7 -> 179550 | L7: =H7*1.05 -> 15710.625 | M7: ='Program Budget'!O13 -> 12 | N7: =Admin!N7+'Activity 1'!N7+'Activity 2'!N7+'Activity 3'!N7+'Activity 4'!N7+'Activity 5'!N7+'Activity 6'!N7+'Activity 7'!N7+'Activity 8'!N7 -> 1 | O7: =L7*M7*N7 -> 188527.5 | P7: =L7*1.05 -> 16496.156 | Q7: ='Program Budget'!R13 -> 0 | R7: =Admin!R10+'Activity 1'!R10+'Activity 2'!R10+'Activity 3'!R10+'Activity 4'!R10+'Activity 5'!R10+'Activity 6'!R10+'Activity 7'!R10+'Activity 8'!R10 -> 1 | S7: =P7*Q7*R4 -> 0 | T7: =C7+G7+K7+O7+S7 -> 1107762.2
A8: Total: Expatriate Salaries & Wages | C8: =SUM(C7:C7) -> 568684.69 | G8: =SUM(G7:G7) -> 171000 | K8: =SUM(K7:K7) -> 179550 | O8: =SUM(O7:O7) -> 188527.5 | S8: =SUM(S7:S7) -> 0 | T8: =+C8+G8+K8+O8+S8 -> 1107762.2
A9: CNN Staff
A10: ='Program Budget'!D14 -> Deputy Chief of Party / Value Chain Strengthening Director | B10: ='Program Budget'!F14 -> Month | C10: =Admin!C10+'Activity 1'!C10+'Activity 2'!C10+'Activity 3'!C10+'Activity 4'!C10+'Activity 5'!C10+'Activity 6'!C10+'Activity 7'!C10+'Activity 8'!C10 -> 0 | D10: ='Program Budget'!G14 -> 5000 | E10: ='Program Budget'!I14 -> 12 | F10: =Admin!F10+'Activity 1'!F10+'Activity 2'!F10+'Activity 3'!F10+'Activity 4'!F10+'Activity 5'!F10+'Activity 6'!F10+'Activity 7'!F10+'Activity 8'!F10 -> 1 | G10: =D10*E10*F10 -> 60000 | H10: =D10*1.05 -> 5250 | I10: ='Program Budget'!L14 -> 12 | J10: =Admin!J10+'Activity 1'!J10+'Activity 2'!J10+'Activity 3'!J10+'Activity 4'!J10+'Activity 5'!J10+'Activity 6'!J10+'Activity 7'!J10+'Activity 8'!J10 -> 1 | K10: =H10*I10*J10 -> 63000 | L10: =H10*1.05 -> 5512.5 | M10: ='Program Budget'!O14 -> 12 | N10: =Admin!N10+'Activity 1'!N10+'Activity 2'!N10+'Activity 3'!N10+'Activity 4'!N10+'Activity 5'!N10+'Activity 6'!N10+'Activity 7'!N10+'Activity 8'!N10 -> 1 | O10: =L10*M10*N10 -> 66150 | P10: =L10*1.05 -> 5788.125 | Q10: ='Program Budget'!R14 -> 6 | R10: =Admin!R10+'Activity 1'!R10+'Activity 2'!R10+'Activity 3'!R10+'Activity 4'!R10+'Activity 5'!R10+'Activity 6'!R10+'Activity 7'!R10+'Activity 8'!R10 -> 1 | S10: =P10*Q10*R7 -> 34728.75 | T10: =C10+G10+K10+O10+S10 -> 223878.75
A11: ='Program Budget'!D15 -> Key Personnel: Technical Director | B11: ='Program Budget'!F15 -> Month | C11: =Admin!C11+'Activity 1'!C11+'Activity 2'!C11+'Activity 3'!C11+'Activity 4'!C11+'Activity 5'!C11+'Activity 6'!C11+'Activity 7'!C11+'Activity 8'!C11 -> 296291.11 | D11: ='Program Budget'!G15 -> 4583.3333 | E11: ='Program Budget'!I15 -> 12 | F11: =Admin!F11+'Activity 1'!F11+'Activity 2'!F11+'Activity 3'!F11+'Activity 4'!F11+'Activity 5'!F11+'Activity 6'!F11+'Activity 7'!F11+'Activity 8'!F11 -> 1 | G11: =D11*E11*F11 -> 55000 | H11: =D11*1.05 -> 4812.5 | I11: ='Program Budget'!L15 -> 12 | J11: =Admin!J11+'Activity 1'!J11+'Activity 2'!J11+'Activity 3'!J11+'Activity 4'!J11+'Activity 5'!J11+'Activity 6'!J11+'Activity 7'!J11+'Activity 8'!J11 -> 1 | K11: =H11*I11*J11 -> 57750 | L11: =H11*1.05 -> 5053.125 | M11: ='Program Budget'!O15 -> 12 | N11: =Admin!N11+'Activity 1'!N11+'Activity 2'!N11+'Activity 3'!N11+'Activity 4'!N11+'Activity 5'!N11+'Activity 6'!N11+'Activity 7'!N11+'Activity 8'!N11 -> 1 | O11: =L11*M11*N11 -> 60637.5 | P11: =L11*1.05 -> 5305.7812 | Q11: ='Program Budget'!R15 -> 5 | R11: =Admin!R11+'Activity 1'!R11+'Activity 2'!R11+'Activity 3'!R11+'Activity 4'!R11+'Activity 5'!R11+'Activity 6'!R11+'Activity 7'!R11+'Activity 8'!R11 -> 1 | S11: =P11*Q11*R11 -> 26528.906 | T11: =C11+G11+K11+O11+S11 -> 496207.52
A12: ='Program Budget'!D16 -> Activity Lead Agribusiness Senior Specialist (Cacao) | B12: ='Program Budget'!F16 -> Month | C12: =Admin!C12+'Activity 1'!C12+'Activity 2'!C12+'Activity 3'!C12+'Activity 4'!C12+'Activity 5'!C12+'Activity 6'!C12+'Activity 7'!C12+'Activity 8'!C12 -> 160735.87 | D12: ='Program Budget'!G16 -> 2833.3333 | E12: ='Program Budget'!I16 -> 12 | F12: =Admin!F12+'Activity 1'!F12+'Activity 2'!F12+'Activity 3'!F12+'Activity 4'!F12+'Activity 5'!F12+'Activity 6'!F12+'Activity 7'!F12+'Activity 8'!F12 -> 1 | G12: =D12*E12*F12 -> 34000 | H12: =D12*1.05 -> 2975 | I12: ='Program Budget'!L16 -> 12 | J12: =Admin!J12+'Activity 1'!J12+'Activity 2'!J12+'Activity 3'!J12+'Activity 4'!J12+'Activity 5'!J12+'Activity 6'!J12+'Activity 7'!J12+'Activity 8'!J12 -> 1 | K12: =H12*I12*J12 -> 35700 | L12: =H12*1.05 -> 3123.75 | M12: ='Program Budget'!O16 -> 12 | N12: =Admin!N12+'Activity 1'!N12+'Activity 2'!N12+'Activity 3'!N12+'Activity 4'!N12+'Activity 5'!N12+'Activity 6'!N12+'Activity 7'!N12+'Activity 8'!N12 -> 1 | O12: =L12*M12*N12 -> 37485 | P12: =L12*1.05 -> 3279.9375 | Q12: ='Program Budget'!R16 -> 2 | R12: =Admin!R12+'Activity 1'!R12+'Activity 2'!R12+'Activity 3'!R12+'Activity 4'!R12+'Activity 5'!R12+'Activity 6'!R12+'Activity 7'!R12+'Activity 8'!R12 -> 1 | S12: =P12*Q12*R12 -> 6559.875 | T12: =C12+G12+K12+O12+S12 -> 274480.74
A13: ='Program Budget'!D17 -> Cacao Field Officer | B13: ='Program Budget'!F17 -> Month | C13: =Admin!C13+'Activity 1'!C13+'Activity 2'!C13+'Activity 3'!C13+'Activity 4'!C13+'Activity 5'!C13+'Activity 6'!C13+'Activity 7'!C13+'Activity 8'!C13 -> 0 | D13: ='Program Budget'!G17 -> 1333.3333 | E13: ='Program Budget'!I17 -> 12 | F13: =Admin!F13+'Activity 1'!F13+'Activity 2'!F13+'Activity 3'!F13+'Activity 4'!F13+'Activity 5'!F13+'Activity 6'!F13+'Activity 7'!F13+'Activity 8'!F13 -> 1 | G13: =D13*E13*F13 -> 16000 | H13: =D13*1.05 -> 1400 | I13: ='Program Budget'!L17 -> 12 | J13: =Admin!J13+'Activity 1'!J13+'Activity 2'!J13+'Activity 3'!J13+'Activity 4'!J13+'Activity 5'!J13+'Activity 6'!J13+'Activity 7'!J13+'Activity 8'!J13 -> 1 | K13: =H13*I13*J13 -> 16800 | L13: =H13*1.05 -> 1470 | M13: ='Program Budget'!O17 -> 12 | N13: =Admin!N13+'Activity 1'!N13+'Activity 2'!N13+'Activity 3'!N13+'Activity 4'!N13+'Activity 5'!N13+'Activity 6'!N13+'Activity 7'!N13+'Activity 8'!N13 -> 1 | O13: =L13*M13*N13 -> 17640 | P13: =L13*1.05 -> 1543.5 | Q13: ='Program Budget'!R17 -> 0 | R13: =Admin!R13+'Activity 1'!R13+'Activity 2'!R13+'Activity 3'!R13+'Activity 4'!R13+'Activity 5'!R13+'Activity 6'!R13+'Activity 7'!R13+'Activity 8'!R13 -> 1 | S13: =P13*Q13*R13 -> 0 | T13: =C13+G13+K13+O13+S13 -> 50440
A14: ='Program Budget'!D18 -> Cacao & Complementary Crop Technical Field Leader (2) | B14: ='Program Budget'!F18 -> Month | C14: =Admin!C14+'Activity 1'!C14+'Activity 2'!C14+'Activity 3'!C14+'Activity 4'!C14+'Activity 5'!C14+'Activity 6'!C14+'Activity 7'!C14+'Activity 8'!C14 -> 0 | D14: ='Program Budget'!G18 -> 3500 | E14: ='Program Budget'!I18 -> 6 | F14: =Admin!F14+'Activity 1'!F14+'Activity 2'!F14+'Activity 3'!F14+'Activity 4'!F14+'Activity 5'!F14+'Activity 6'!F14+'Activity 7'!F14+'Activity 8'!F14 -> 1 | G14: =D14*E14*F14 -> 21000 | H14: =D14*1.05 -> 3675 | I14: ='Program Budget'!L18 -> 12 | J14: =Admin!J14+'Activity 1'!J14+'Activity 2'!J14+'Activity 3'!J14+'Activity 4'!J14+'Activity 5'!J14+'Activity 6'!J14+'Activity 7'!J14+'Activity 8'!J14 -> 1 | K14: =H14*I14*J14 -> 44100 | L14: =H14*1.05 -> 3858.75 | M14: ='Program Budget'!O18 -> 12 | N14: =Admin!N14+'Activity 1'!N14+'Activity 2'!N14+'Activity 3'!N14+'Activity 4'!N14+'Activity 5'!N14+'Activity 6'!N14+'Activity 7'!N14+'Activity 8'!N14 -> 1 | O14: =L14*M14*N14 -> 46305 | P14: =L14*1.05 -> 4051.6875 | Q14: ='Program Budget'!R18 -> 0 | R14: =Admin!R14+'Activity 1'!R14+'Activity 2'!R14+'Activity 3'!R14+'Activity 4'!R14+'Activity 5'!R14+'Activity 6'!R14+'Activity 7'!R14+'Activity 8'!R14 -> 1 | S14: =P14*Q14*R14 -> 0 | T14: =C14+G14+K14+O14+S14 -> 111405
A15: ='Program Budget'!D19 -> Extension Agents (45 in Y5 and 25 in Y6) | B15: ='Program Budget'!F19 -> Month | C15: =Admin!C15+'Activity 1'!C15+'Activity 2'!C15+'Activity 3'!C15+'Activity 4'!C15+'Activity 5'!C15+'Activity 6'!C15+'Activity 7'!C15+'Activity 8'!C15 -> 187435.61 | D15: ='Program Budget'!G19 -> 1000 | E15: ='Program Budget'!I19 -> 12 | F15: =Admin!F15+'Activity 1'!F15+'Activity 2'!F15+'Activity 3'!F15+'Activity 4'!F15+'Activity 5'!F15+'Activity 6'!F15+'Activity 7'!F15+'Activity 8'!F15 -> 1 | G15: =(D15*45)*E15*F15 -> 540000 | H15: =D15*1.05 -> 1050 | I15: ='Program Budget'!L19 -> 12 | J15: =Admin!J15+'Activity 1'!J15+'Activity 2'!J15+'Activity 3'!J15+'Activity 4'!J15+'Activity 5'!J15+'Activity 6'!J15+'Activity 7'!J15+'Activity 8'!J15 -> 1 | K15: =(H15*25)*I15*J15 -> 315000 | L15: =H15*1.05 -> 1102.5 | M15: ='Program Budget'!O19 -> 0 | N15: =Admin!N15+'Activity 1'!N15+'Activity 2'!N15+'Activity 3'!N15+'Activity 4'!N15+'Activity 5'!N15+'Activity 6'!N15+'Activity 7'!N15+'Activity 8'!N15 -> 1 | O15: =L15*M15*N15 -> 0 | P15: =L15*1.05 -> 1157.625 | Q15: ='Program Budget'!R19 -> 0 | R15: =Admin!R15+'Activity 1'!R15+'Activity 2'!R15+'Activity 3'!R15+'Activity 4'!R15+'Activity 5'!R15+'Activity 6'!R15+'Activity 7'!R15+'Activity 8'!R15 -> 1 | S15: =P15*Q15*R15 -> 0 | T15: =C15+G15+K15+O15+S15 -> 1042435.6
A16: ='Program Budget'!D20 -> Activity Lead Agribusiness Senior Specialist (Complementary Crop) | B16: ='Program Budget'!F20 -> Month | C16: =Admin!C16+'Activity 1'!C16+'Activity 2'!C16+'Activity 3'!C16+'Activity 4'!C16+'Activity 5'!C16+'Activity 6'!C16+'Activity 7'!C16+'Activity 8'!C16 -> 151336.3 | D16: ='Program Budget'!G20 -> 2833.3333 | E16: ='Program Budget'!I20 -> 12 | F16: =Admin!F16+'Activity 1'!F16+'Activity 2'!F16+'Activity 3'!F16+'Activity 4'!F16+'Activity 5'!F16+'Activity 6'!F16+'Activity 7'!F16+'Activity 8'!F16 -> 1 | G16: =D16*E16*F16 -> 34000 | H16: =D16*1.05 -> 2975 | I16: ='Program Budget'!L20 -> 12 | J16: =Admin!J16+'Activity 1'!J16+'Activity 2'!J16+'Activity 3'!J16+'Activity 4'!J16+'Activity 5'!J16+'Activity 6'!J16+'Activity 7'!J16+'Activity 8'!J16 -> 1 | K16: =H16*I16*J16 -> 35700 | L16: =H16*1.05 -> 3123.75 | M16: ='Program Budget'!O20 -> 12 | N16: =Admin!N16+'Activity 1'!N16+'Activity 2'!N16+'Activity 3'!N16+'Activity 4'!N16+'Activity 5'!N16+'Activity 6'!N16+'Activity 7'!N16+'Activity 8'!N16 -> 1 | O16: =L16*M16*N16 -> 37485 | P16: =L16*1.05 -> 3279.9375 | Q16: ='Program Budget'!R20 -> 0 | R16: =Admin!R16+'Activity 1'!R16+'Activity 2'!R16+'Activity 3'!R16+'Activity 4'!R16+'Activity 5'!R16+'Activity 6'!R16+'Activity 7'!R16+'Activity 8'!R16 -> 1 | S16: =P16*Q16*R16 -> 0 | T16: =C16+G16+K16+O16+S16 -> 258521.3
A17: ='Program Budget'!D21 -> Complementary Crops Field Officer | B17: ='Program Budget'!F21 -> Month | C17: =Admin!C17+'Activity 1'!C17+'Activity 2'!C17+'Activity 3'!C17+'Activity 4'!C17+'Activity 5'!C17+'Activity 6'!C17+'Activity 7'!C17+'Activity 8'!C17 -> 0 | D17: ='Program Budget'!G21 -> 0 | E17: ='Program Budget'!I21 -> 0 | F17: =Admin!F17+'Activity 1'!F17+'Activity 2'!F17+'Activity 3'!F17+'Activity 4'!F17+'Activity 5'!F17+'Activity 6'!F17+'Activity 7'!F17+'Activity 8'!F17 -> 1 | G17: =D17*E17*F17 -> 0 | H17: =D17*1.05 -> 0 | I17: ='Program Budget'!L21 -> 12 | J17: =Admin!J17+'Activity 1'!J17+'Activity 2'!J17+'Activity 3'!J17+'Activity 4'!J17+'Activity 5'!J17+'Activity 6'!J17+'Activity 7'!J17+'Activity 8'!J17 -> 1 | K17: =H17*I17*J17 -> 0 | L17: =H17*1.05 -> 0 | M17: ='Program Budget'!O21 -> 12 | N17: =Admin!N17+'Activity 1'!N17+'Activity 2'!N17+'Activity 3'!N17+'Activity 4'!N17+'Activity 5'!N17+'Activity 6'!N17+'Activity 7'!N17+'Activity 8'!N17 -> 1 | O17: =L17*M17*N17 -> 0 | P17: =L17*1.05 -> 0 | Q17: ='Program Budget'!R21 -> 0 | R17: =Admin!R17+'Activity 1'!R17+'Activity 2'!R17+'Activity 3'!R17+'Activity 4'!R17+'Activity 5'!R17+'Activity 6'!R17+'Activity 7'!R17+'Activity 8'!R17 -> 1 | S17: =P17*Q17*R17 -> 0 | T17: =C17+G17+K17+O17+S17 -> 0
A18: ='Program Budget'!D22 -> EPSEAS Specialist | B18: ='Program Budget'!F22 -> Month | C18: =Admin!C18+'Activity 1'!C18+'Activity 2'!C18+'Activity 3'!C18+'Activity 4'!C18+'Activity 5'!C18+'Activity 6'!C18+'Activity 7'!C18+'Activity 8'!C18 -> 0 | D18: ='Program Budget'!G22 -> 0 | E18: ='Program Budget'!I22 -> 0 | F18: =Admin!F18+'Activity 1'!F18+'Activity 2'!F18+'Activity 3'!F18+'Activity 4'!F18+'Activity 5'!F18+'Activity 6'!F18+'Activity 7'!F18+'Activity 8'!F18 -> 1 | G18: =D18*E18*F18 -> 0 | H18: =D18*1.05 -> 0 | I18: ='Program Budget'!L22 -> 12 | J18: =Admin!J18+'Activity 1'!J18+'Activity 2'!J18+'Activity 3'!J18+'Activity 4'!J18+'Activity 5'!J18+'Activity 6'!J18+'Activity 7'!J18+'Activity 8'!J18 -> 1 | K18: =H18*I18*J18 -> 0 | L18: =H18*1.05 -> 0 | M18: ='Program Budget'!O22 -> 12 | N18: =Admin!N18+'Activity 1'!N18+'Activity 2'!N18+'Activity 3'!N18+'Activity 4'!N18+'Activity 5'!N18+'Activity 6'!N18+'Activity 7'!N18+'Activity 8'!N18 -> 1 | O18: =L18*M18*N18 -> 0 | P18: =L18*1.05 -> 0 | Q18: ='Program Budget'!R22 -> 0 | R18: =Admin!R18+'Activity 1'!R18+'Activity 2'!R18+'Activity 3'!R18+'Activity 4'!R18+'Activity 5'!R18+'Activity 6'!R18+'Activity 7'!R18+'Activity 8'!R18 -> 1 | S18: =P18*Q18*R18 -> 0 | T18: =C18+G18+K18+O18+S18 -> 0
A19: ='Program Budget'!D23 -> Extension Agents for EPSEAS (20 in Y6 and 25 in Y7) | B19: ='Program Budget'!F23 -> Month | C19: =Admin!C19+'Activity 1'!C19+'Activity 2'!C19+'Activity 3'!C19+'Activity 4'!C19+'Activity 5'!C19+'Activity 6'!C19+'Activity 7'!C19+'Activity 8'!C19 -> 0 | D19: ='Program Budget'!G23 -> 1000 | E19: ='Program Budget'!I23 -> 0 | F19: =Admin!F19+'Activity 1'!F19+'Activity 2'!F19+'Activity 3'!F19+'Activity 4'!F19+'Activity 5'!F19+'Activity 6'!F19+'Activity 7'!F19+'Activity 8'!F19 -> 1 | G19: =D19*E19*F19 -> 0 | H19: =D19*1.05 -> 1050 | I19: ='Program Budget'!L23 -> 12 | J19: =Admin!J19+'Activity 1'!J19+'Activity 2'!J19+'Activity 3'!J19+'Activity 4'!J19+'Activity 5'!J19+'Activity 6'!J19+'Activity 7'!J19+'Activity 8'!J19 -> 1 | K19: =(H19*20)*I19*J19 -> 252000 | L19: =H19*1.05 -> 1102.5 | M19: ='Program Budget'!O23 -> 12 | N19: =Admin!N19+'Activity 1'!N19+'Activity 2'!N19+'Activity 3'!N19+'Activity 4'!N19+'Activity 5'!N19+'Activity 6'!N19+'Activity 7'!N19+'Activity 8'!N19 -> 1 | O19: =(L19*25)*M19*N19 -> 330750 | P19: =L19*1.05 -> 1157.625 | Q19: ='Program Budget'!R23 -> 0 | R19: =Admin!R19+'Activity 1'!R19+'Activity 2'!R19+'Activity 3'!R19+'Activity 4'!R19+'Activity 5'!R19+'Activity 6'!R19+'Activity 7'!R19+'Activity 8'!R19 -> 1 | S19: =P19*Q19*R19 -> 0 | T19: =C19+G19+K19+O19+S19 -> 582750
A20: ='Program Budget'!D24 -> Senior M&E Director | B20: ='Program Budget'!F24 -> Month | C20: =Admin!C20+'Activity 1'!C20+'Activity 2'!C20+'Activity 3'!C20+'Activity 4'!C20+'Activity 5'!C20+'Activity 6'!C20+'Activity 7'!C20+'Activity 8'!C20 -> 124292.19 | D20: ='Program Budget'!G24 -> 6250 | E20: ='Program Budget'!I24 -> 12 | F20: =Admin!F20+'Activity 1'!F20+'Activity 2'!F20+'Activity 3'!F20+'Activity 4'!F20+'Activity 5'!F20+'Activity 6'!F20+'Activity 7'!F20+'Activity 8'!F20 -> 1 | G20: =D20*E20*F20 -> 75000 | H20: =D20*1.05 -> 6562.5 | I20: ='Program Budget'!L24 -> 12 | J20: =Admin!J20+'Activity 1'!J20+'Activity 2'!J20+'Activity 3'!J20+'Activity 4'!J20+'Activity 5'!J20+'Activity 6'!J20+'Activity 7'!J20+'Activity 8'!J20 -> 1 | K20: =H20*I20*J20 -> 78750 | L20: =H20*1.05 -> 6890.625 | M20: ='Program Budget'!O24 -> 12 | N20: =Admin!N20+'Activity 1'!N20+'Activity 2'!N20+'Activity 3'!N20+'Activity 4'!N20+'Activity 5'!N20+'Activity 6'!N20+'Activity 7'!N20+'Activity 8'!N20 -> 1 | O20: =L20*M20*N20 -> 82687.5 | P20: =L20*1.05 -> 7235.1562 | Q20: ='Program Budget'!R24 -> 6 | R20: =Admin!R20+'Activity 1'!R20+'Activity 2'!R20+'Activity 3'!R20+'Activity 4'!R20+'Activity 5'!R20+'Activity 6'!R20+'Activity 7'!R20+'Activity 8'!R20 -> 1 | S20: =P20*Q20*R20 -> 43410.938 | T20: =C20+G20+K20+O20+S20 -> 404140.63
A21: ='Program Budget'!D25 -> Senior M&E Specialist | B21: ='Program Budget'!F25 -> Month | C21: =Admin!C21+'Activity 1'!C21+'Activity 2'!C21+'Activity 3'!C21+'Activity 4'!C21+'Activity 5'!C21+'Activity 6'!C21+'Activity 7'!C21+'Activity 8'!C21 -> 97588.95 | D21: ='Program Budget'!G25 -> 2833.3333 | E21: ='Program Budget'!I25 -> 12 | F21: =Admin!F21+'Activity 1'!F21+'Activity 2'!F21+'Activity 3'!F21+'Activity 4'!F21+'Activity 5'!F21+'Activity 6'!F21+'Activity 7'!F21+'Activity 8'!F21 -> 1 | G21: =D21*E21*F21 -> 34000 | H21: =D21*1.05 -> 2975 | I21: ='Program Budget'!L25 -> 12 | J21: =Admin!J21+'Activity 1'!J21+'Activity 2'!J21+'Activity 3'!J21+'Activity 4'!J21+'Activity 5'!J21+'Activity 6'!J21+'Activity 7'!J21+'Activity 8'!J21 -> 1 | K21: =H21*I21*J21 -> 35700 | L21: =H21*1.05 -> 3123.75 | M21: ='Program Budget'!O25 -> 12 | N21: =Admin!N21+'Activity 1'!N21+'Activity 2'!N21+'Activity 3'!N21+'Activity 4'!N21+'Activity 5'!N21+'Activity 6'!N21+'Activity 7'!N21+'Activity 8'!N21 -> 1 | O21: =L21*M21*N21 -> 37485 | P21: =L21*1.05 -> 3279.9375 | Q21: ='Program Budget'!R25 -> 6 | R21: =Admin!R21+'Activity 1'!R21+'Activity 2'!R21+'Activity 3'!R21+'Activity 4'!R21+'Activity 5'!R21+'Activity 6'!R21+'Activity 7'!R21+'Activity 8'!R21 -> 1 | S21: =P21*Q21*R21 -> 19679.625 | T21: =C21+G21+K21+O21+S21 -> 224453.58
A22: ='Program Budget'!D26 -> M&E Specialist | B22: ='Program Budget'!F26 -> Month | C22: =Admin!C22+'Activity 1'!C22+'Activity 2'!C22+'Activity 3'!C22+'Activity 4'!C22+'Activity 5'!C22+'Activity 6'!C22+'Activity 7'!C22+'Activity 8'!C22 -> 77001.795 | D22: ='Program Budget'!G26 -> 2500 | E22: ='Program Budget'!I26 -> 12 | F22: =Admin!F22+'Activity 1'!F22+'Activity 2'!F22+'Activity 3'!F22+'Activity 4'!F22+'Activity 5'!F22+'Activity 6'!F22+'Activity 7'!F22+'Activity 8'!F22 -> 1 | G22: =D22*E22*F22 -> 30000 | H22: =D22*1.05 -> 2625 | I22: ='Program Budget'!L26 -> 12 | J22: =Admin!J22+'Activity 1'!J22+'Activity 2'!J22+'Activity 3'!J22+'Activity 4'!J22+'Activity 5'!J22+'Activity 6'!J22+'Activity 7'!J22+'Activity 8'!J22 -> 1 | K22: =H22*I22*J22 -> 31500 | L22: =H22*1.05 -> 2756.25 | M22: ='Program Budget'!O26 -> 12 | N22: =Admin!N22+'Activity 1'!N22+'Activity 2'!N22+'Activity 3'!N22+'Activity 4'!N22+'Activity 5'!N22+'Activity 6'!N22+'Activity 7'!N22+'Activity 8'!N22 -> 1 | O22: =L22*M22*N22 -> 33075 | P22: =L22*1.05 -> 2894.0625 | Q22: ='Program Budget'!R26 -> 3 | R22: =Admin!R22+'Activity 1'!R22+'Activity 2'!R22+'Activity 3'!R22+'Activity 4'!R22+'Activity 5'!R22+'Activity 6'!R22+'Activity 7'!R22+'Activity 8'!R22 -> 1 | S22: =P22*Q22*R22 -> 8682.1875 | T22: =C22+G22+K22+O22+S22 -> 180258.98
A23: ='Program Budget'!D27 -> M&E Officer | B23: ='Program Budget'!F27 -> Month | C23: =Admin!C23+'Activity 1'!C23+'Activity 2'!C23+'Activity 3'!C23+'Activity 4'!C23+'Activity 5'!C23+'Activity 6'!C23+'Activity 7'!C23+'Activity 8'!C23 -> 48959.525 | D23: ='Program Budget'!G27 -> 1000 | E23: ='Program Budget'!I27 -> 12 | F23: =Admin!F23+'Activity 1'!F23+'Activity 2'!F23+'Activity 3'!F23+'Activity 4'!F23+'Activity 5'!F23+'Activity 6'!F23+'Activity 7'!F23+'Activity 8'!F23 -> 1 | G23: =D23*E23*F23 -> 12000 | H23: =D23*1.05 -> 1050 | I23: ='Program Budget'!L27 -> 12 | J23: =Admin!J23+'Activity 1'!J23+'Activity 2'!J23+'Activity 3'!J23+'Activity 4'!J23+'Activity 5'!J23+'Activity 6'!J23+'Activity 7'!J23+'Activity 8'!J23 -> 1 | K23: =H23*I23*J23 -> 12600 | L23: =H23*1.05 -> 1102.5 | M23: ='Program Budget'!O27 -> 12 | N23: =Admin!N23+'Activity 1'!N23+'Activity 2'!N23+'Activity 3'!N23+'Activity 4'!N23+'Activity 5'!N23+'Activity 6'!N23+'Activity 7'!N23+'Activity 8'!N23 -> 1 | O23: =L23*M23*N23 -> 13230 | P23: =L23*1.05 -> 1157.625 | Q23: ='Program Budget'!R27 -> 3 | R23: =Admin!R23+'Activity 1'!R23+'Activity 2'!R23+'Activity 3'!R23+'Activity 4'!R23+'Activity 5'!R23+'Activity 6'!R23+'Activity 7'!R23+'Activity 8'!R23 -> 1 | S23: =P23*Q23*R23 -> 3472.875 | T23: =C23+G23+K23+O23+S23 -> 90262.4
A24: ='Program Budget'!D28 -> Partnerships and Investment Director | B24: ='Program Budget'!F28 -> Month | C24: =Admin!C24+'Activity 1'!C24+'Activity 2'!C24+'Activity 3'!C24+'Activity 4'!C24+'Activity 5'!C24+'Activity 6'!C24+'Activity 7'!C24+'Activity 8'!C24 -> 235574.48 | D24: ='Program Budget'!G28 -> 4583.3333 | E24: ='Program Budget'!I28 -> 12 | F24: =Admin!F24+'Activity 1'!F24+'Activity 2'!F24+'Activity 3'!F24+'Activity 4'!F24+'Activity 5'!F24+'Activity 6'!F24+'Activity 7'!F24+'Activity 8'!F24 -> 1 | G24: =D24*E24*F24 -> 55000 | H24: =D24*1.05 -> 4812.5 | I24: ='Program Budget'!L28 -> 12 | J24: =Admin!J24+'Activity 1'!J24+'Activity 2'!J24+'Activity 3'!J24+'Activity 4'!J24+'Activity 5'!J24+'Activity 6'!J24+'Activity 7'!J24+'Activity 8'!J24 -> 1 | K24: =H24*I24*J24 -> 57750 | L24: =H24*1.05 -> 5053.125 | M24: ='Program Budget'!O28 -> 12 | N24: =Admin!N24+'Activity 1'!N24+'Activity 2'!N24+'Activity 3'!N24+'Activity 4'!N24+'Activity 5'!N24+'Activity 6'!N24+'Activity 7'!N24+'Activity 8'!N24 -> 1 | O24: =L24*M24*N24 -> 60637.5 | P24: =L24*1.05 -> 5305.7812 | Q24: ='Program Budget'!R28 -> 0 | R24: =Admin!R24+'Activity 1'!R24+'Activity 2'!R24+'Activity 3'!R24+'Activity 4'!R24+'Activity 5'!R24+'Activity 6'!R24+'Activity 7'!R24+'Activity 8'!R24 -> 1 | S24: =P24*Q24*R24 -> 0 | T24: =C24+G24+K24+O24+S24 -> 408961.98
A25: ='Program Budget'!D29 -> Partnerships and Investment Specialist | B25: ='Program Budget'!F29 -> Month | C25: =Admin!C25+'Activity 1'!C25+'Activity 2'!C25+'Activity 3'!C25+'Activity 4'!C25+'Activity 5'!C25+'Activity 6'!C25+'Activity 7'!C25+'Activity 8'!C25 -> 0 | D25: ='Program Budget'!G29 -> 1750 | E25: ='Program Budget'!I29 -> 12 | F25: =Admin!F25+'Activity 1'!F25+'Activity 2'!F25+'Activity 3'!F25+'Activity 4'!F25+'Activity 5'!F25+'Activity 6'!F25+'Activity 7'!F25+'Activity 8'!F25 -> 1 | G25: =D25*E25*F25 -> 21000 | H25: =D25*1.05 -> 1837.5 | I25: ='Program Budget'!L29 -> 12 | J25: =Admin!J25+'Activity 1'!J25+'Activity 2'!J25+'Activity 3'!J25+'Activity 4'!J25+'Activity 5'!J25+'Activity 6'!J25+'Activity 7'!J25+'Activity 8'!J25 -> 1 | K25: =H25*I25*J25 -> 22050 | L25: =H25*1.05 -> 1929.375 | M25: ='Program Budget'!O29 -> 12 | N25: =Admin!N25+'Activity 1'!N25+'Activity 2'!N25+'Activity 3'!N25+'Activity 4'!N25+'Activity 5'!N25+'Activity 6'!N25+'Activity 7'!N25+'Activity 8'!N25 -> 1 | O25: =L25*M25*N25 -> 23152.5 | P25: =L25*1.05 -> 2025.8438 | Q25: ='Program Budget'!R29 -> 0 | R25: =Admin!R25+'Activity 1'!R25+'Activity 2'!R25+'Activity 3'!R25+'Activity 4'!R25+'Activity 5'!R25+'Activity 6'!R25+'Activity 7'!R25+'Activity 8'!R25 -> 1 | S25: =P25*Q25*R25 -> 0 | T25: =C25+G25+K25+O25+S25 -> 66202.5
A26: ='Program Budget'!D30 -> Organizational Strengthening Specialist | B26: ='Program Budget'!F30 -> Month | C26: =Admin!C26+'Activity 1'!C26+'Activity 2'!C26+'Activity 3'!C26+'Activity 4'!C26+'Activity 5'!C26+'Activity 6'!C26+'Activity 7'!C26+'Activity 8'!C26 -> 0 | D26: ='Program Budget'!G30 -> 1750 | E26: ='Program Budget'!I30 -> 12 | F26: =Admin!F26+'Activity 1'!F26+'Activity 2'!F26+'Activity 3'!F26+'Activity 4'!F26+'Activity 5'!F26+'Activity 6'!F26+'Activity 7'!F26+'Activity 8'!F26 -> 1 | G26: =D26*E26*F26 -> 21000 | H26: =D26*1.05 -> 1837.5 | I26: ='Program Budget'!L30 -> 12 | J26: =Admin!J26+'Activity 1'!J26+'Activity 2'!J26+'Activity 3'!J26+'Activity 4'!J26+'Activity 5'!J26+'Activity 6'!J26+'Activity 7'!J26+'Activity 8'!J26 -> 1 | K26: =H26*I26*J26 -> 22050 | L26: =H26*1.05 -> 1929.375 | M26: ='Program Budget'!O30 -> 12 | N26: =Admin!N26+'Activity 1'!N26+'Activity 2'!N26+'Activity 3'!N26+'Activity 4'!N26+'Activity 5'!N26+'Activity 6'!N26+'Activity 7'!N26+'Activity 8'!N26 -> 1 | O26: =L26*M26*N26 -> 23152.5 | P26: =L26*1.05 -> 2025.8438 | Q26: ='Program Budget'!R30 -> 0 | R26: =Admin!R26+'Activity 1'!R26+'Activity 2'!R26+'Activity 3'!R26+'Activity 4'!R26+'Activity 5'!R26+'Activity 6'!R26+'Activity 7'!R26+'Activity 8'!R26 -> 1 | S26: =P26*Q26*R26 -> 0 | T26: =C26+G26+K26+O26+S26 -> 66202.5
A27: ='Program Budget'!D31 -> Value Chain Strengthening Director | B27: ='Program Budget'!F31 -> Month | C27: =Admin!C27+'Activity 1'!C27+'Activity 2'!C27+'Activity 3'!C27+'Activity 4'!C27+'Activity 5'!C27+'Activity 6'!C27+'Activity 7'!C27+'Activity 8'!C27 -> 0 | D27: ='Program Budget'!G31 -> 0 | E27: ='Program Budget'!I31 -> 12 | F27: =Admin!F27+'Activity 1'!F27+'Activity 2'!F27+'Activity 3'!F27+'Activity 4'!F27+'Activity 5'!F27+'Activity 6'!F27+'Activity 7'!F27+'Activity 8'!F27 -> 1 | G27: =D27*E27*F27 -> 0 | H27: =D27*1.05 -> 0 | I27: ='Program Budget'!L31 -> 12 | J27: =Admin!J27+'Activity 1'!J27+'Activity 2'!J27+'Activity 3'!J27+'Activity 4'!J27+'Activity 5'!J27+'Activity 6'!J27+'Activity 7'!J27+'Activity 8'!J27 -> 1 | K27: =H27*I27*J27 -> 0 | L27: =H27*1.05 -> 0 | M27: ='Program Budget'!O31 -> 12 | N27: =Admin!N27+'Activity 1'!N27+'Activity 2'!N27+'Activity 3'!N27+'Activity 4'!N27+'Activity 5'!N27+'Activity 6'!N27+'Activity 7'!N27+'Activity 8'!N27 -> 1 | O27: =L27*M27*N27 -> 0 | P27: =L27*1.05 -> 0 | Q27: ='Program Budget'!R31 -> 4 | R27: =Admin!R27+'Activity 1'!R27+'Activity 2'!R27+'Activity 3'!R27+'Activity 4'!R27+'Activity 5'!R27+'Activity 6'!R27+'Activity 7'!R27+'Activity 8'!R27 -> 1 | S27: =P27*Q27*R27 -> 0 | T27: =C27+G27+K27+O27+S27 -> 0
A28: ='Program Budget'!D32 -> Communications Specialist | B28: ='Program Budget'!F32 -> Month | C28: =Admin!C28+'Activity 1'!C28+'Activity 2'!C28+'Activity 3'!C28+'Activity 4'!C28+'Activity 5'!C28+'Activity 6'!C28+'Activity 7'!C28+'Activity 8'!C28 -> 0 | D28: ='Program Budget'!G32 -> 1750 | E28: ='Program Budget'!I32 -> 12 | F28: =Admin!F28+'Activity 1'!F28+'Activity 2'!F28+'Activity 3'!F28+'Activity 4'!F28+'Activity 5'!F28+'Activity 6'!F28+'Activity 7'!F28+'Activity 8'!F28 -> 1 | G28: =D28*E28*F28 -> 21000 | H28: =D28*1.05 -> 1837.5 | I28: ='Program Budget'!L32 -> 12 | J28: =Admin!J28+'Activity 1'!J28+'Activity 2'!J28+'Activity 3'!J28+'Activity 4'!J28+'Activity 5'!J28+'Activity 6'!J28+'Activity 7'!J28+'Activity 8'!J28 -> 1 | K28: =H28*I28*J28 -> 22050 | L28: =H28*1.05 -> 1929.375 | M28: ='Program Budget'!O32 -> 12 | N28: =Admin!N28+'Activity 1'!N28+'Activity 2'!N28+'Activity 3'!N28+'Activity 4'!N28+'Activity 5'!N28+'Activity 6'!N28+'Activity 7'!N28+'Activity 8'!N28 -> 1 | O28: =L28*M28*N28 -> 23152.5 | P28: =L28*1.05 -> 2025.8438 | Q28: ='Program Budget'!R32 -> 0 | R28: =Admin!R28+'Activity 1'!R28+'Activity 2'!R28+'Activity 3'!R28+'Activity 4'!R28+'Activity 5'!R28+'Activity 6'!R28+'Activity 7'!R28+'Activity 8'!R28 -> 1 | S28: =P28*Q28*R28 -> 0 | T28: =C28+G28+K28+O28+S28 -> 66202.5
A29: ='Program Budget'!D33 -> Value Chain Specialist | B29: ='Program Budget'!F33 -> Month | C29: =Admin!C29+'Activity 1'!C29+'Activity 2'!C29+'Activity 3'!C29+'Activity 4'!C29+'Activity 5'!C29+'Activity 6'!C29+'Activity 7'!C29+'Activity 8'!C29 -> 0 | D29: ='Program Budget'!G33 -> 2500 | E29: ='Program Budget'!I33 -> 12 | F29: =Admin!F29+'Activity 1'!F29+'Activity 2'!F29+'Activity 3'!F29+'Activity 4'!F29+'Activity 5'!F29+'Activity 6'!F29+'Activity 7'!F29+'Activity 8'!F29 -> 1 | G29: =D29*E29*F29 -> 30000 | H29: =D29*1.05 -> 2625 | I29: ='Program Budget'!L33 -> 12 | J29: =Admin!J29+'Activity 1'!J29+'Activity 2'!J29+'Activity 3'!J29+'Activity 4'!J29+'Activity 5'!J29+'Activity 6'!J29+'Activity 7'!J29+'Activity 8'!J29 -> 1 | K29: =H29*I29*J29 -> 31500 | L29: =H29*1.05 -> 2756.25 | M29: ='Program Budget'!O33 -> 12 | N29: =Admin!N29+'Activity 1'!N29+'Activity 2'!N29+'Activity 3'!N29+'Activity 4'!N29+'Activity 5'!N29+'Activity 6'!N29+'Activity 7'!N29+'Activity 8'!N29 -> 1 | O29: =L29*M29*N29 -> 33075 | P29: =L29*1.05 -> 2894.0625 | Q29: ='Program Budget'!R33 -> 0 | R29: =Admin!R29+'Activity 1'!R29+'Activity 2'!R29+'Activity 3'!R29+'Activity 4'!R29+'Activity 5'!R29+'Activity 6'!R29+'Activity 7'!R29+'Activity 8'!R29 -> 1 | S29: =P29*Q29*R29 -> 0 | T29: =C29+G29+K29+O29+S29 -> 94575
A30: ='Program Budget'!D34 -> Contracts & Compliance Director | B30: ='Program Budget'!F34 -> Month | C30: =Admin!C30+'Activity 1'!C30+'Activity 2'!C30+'Activity 3'!C30+'Activity 4'!C30+'Activity 5'!C30+'Activity 6'!C30+'Activity 7'!C30+'Activity 8'!C30 -> 166155.63 | D30: ='Program Budget'!G34 -> 4583.3333 | E30: ='Program Budget'!I34 -> 12 | F30: =Admin!F30+'Activity 1'!F30+'Activity 2'!F30+'Activity 3'!F30+'Activity 4'!F30+'Activity 5'!F30+'Activity 6'!F30+'Activity 7'!F30+'Activity 8'!F30 -> 1 | G30: =D30*E30*F30 -> 55000 | H30: =D30*1.05 -> 4812.5 | I30: ='Program Budget'!L34 -> 12 | J30: =Admin!J30+'Activity 1'!J30+'Activity 2'!J30+'Activity 3'!J30+'Activity 4'!J30+'Activity 5'!J30+'Activity 6'!J30+'Activity 7'!J30+'Activity 8'!J30 -> 1 | K30: =H30*I30*J30 -> 57750 | L30: =H30*1.05 -> 5053.125 | M30: ='Program Budget'!O34 -> 12 | N30: =Admin!N30+'Activity 1'!N30+'Activity 2'!N30+'Activity 3'!N30+'Activity 4'!N30+'Activity 5'!N30+'Activity 6'!N30+'Activity 7'!N30+'Activity 8'!N30 -> 1 | O30: =L30*M30*N30 -> 60637.5 | P30: =L30*1.05 -> 5305.7812 | Q30: ='Program Budget'!R34 -> 3 | R30: =Admin!R30+'Activity 1'!R30+'Activity 2'!R30+'Activity 3'!R30+'Activity 4'!R30+'Activity 5'!R30+'Activity 6'!R30+'Activity 7'!R30+'Activity 8'!R30 -> 1 | S30: =P30*Q30*R30 -> 15917.344 | T30: =C30+G30+K30+O30+S30 -> 355460.47
A31: ='Program Budget'!D35 -> Grants & Procurement Specialist (2) | B31: ='Program Budget'!F35 -> Month | C31: =Admin!C31+'Activity 1'!C31+'Activity 2'!C31+'Activity 3'!C31+'Activity 4'!C31+'Activity 5'!C31+'Activity 6'!C31+'Activity 7'!C31+'Activity 8'!C31 -> 0 | D31: ='Program Budget'!G35 -> 3500 | E31: ='Program Budget'!I35 -> 12 | F31: =Admin!F31+'Activity 1'!F31+'Activity 2'!F31+'Activity 3'!F31+'Activity 4'!F31+'Activity 5'!F31+'Activity 6'!F31+'Activity 7'!F31+'Activity 8'!F31 -> 1 | G31: =D31*E31*F31 -> 42000 | H31: =D31*1.05 -> 3675 | I31: ='Program Budget'!L35 -> 12 | J31: =Admin!J31+'Activity 1'!J31+'Activity 2'!J31+'Activity 3'!J31+'Activity 4'!J31+'Activity 5'!J31+'Activity 6'!J31+'Activity 7'!J31+'Activity 8'!J31 -> 1 | K31: =H31*I31*J31 -> 44100 | L31: =H31*1.05 -> 3858.75 | M31: ='Program Budget'!O35 -> 12 | N31: =Admin!N31+'Activity 1'!N31+'Activity 2'!N31+'Activity 3'!N31+'Activity 4'!N31+'Activity 5'!N31+'Activity 6'!N31+'Activity 7'!N31+'Activity 8'!N31 -> 1 | O31: =L31*M31*N31 -> 46305 | P31: =L31*1.05 -> 4051.6875 | Q31: ='Program Budget'!R35 -> 0 | R31: =Admin!R31+'Activity 1'!R31+'Activity 2'!R31+'Activity 3'!R31+'Activity 4'!R31+'Activity 5'!R31+'Activity 6'!R31+'Activity 7'!R31+'Activity 8'!R31 -> 1 | S31: =P31*Q31*R31 -> 0 | T31: =C31+G31+K31+O31+S31 -> 132405
... A38: ='Program Budget'!D42 -> Human Resource Specialist | B38: ='Program Budget'!F42 -> Month | C38: =Admin!C38+'Activity 1'!C38+'Activity 2'!C38+'Activity 3'!C38+'Activity 4'!C38+'Activity 5'!C38+'Activity 6'!C38+'Activity 7'!C38+'Activity 8'!C38 -> 0 | D38: ='Program Budget'!G42 -> 1750 | E38: ='Program Budget'!I42 -> 12 | F38: =Admin!F38+'Activity 1'!F38+'Activity 2'!F38+'Activity 3'!F38+'Activity 4'!F38+'Activity 5'!F38+'Activity 6'!F38+'Activity 7'!F38+'Activity 8'!F38 -> 1 | G38: =D38*E38*F38 -> 21000 | H38: =D38*1.05 -> 1837.5 | I38: ='Program Budget'!L42 -> 12 | J38: =Admin!J38+'Activity 1'!J38+'Activity 2'!J38+'Activity 3'!J38+'Activity 4'!J38+'Activity 5'!J38+'Activity 6'!J38+'Activity 7'!J38+'Activity 8'!J38 -> 1 | K38: =H38*I38*J38 -> 22050 | L38: =H38*1.05 -> 1929.375 | M38: ='Program Budget'!O42 -> 12 | N38: =Admin!N38+'Activity 1'!N38+'Activity 2'!N38+'Activity 3'!N38+'Activity 4'!N38+'Activity 5'!N38+'Activity 6'!N38+'Activity 7'!N38+'Activity 8'!N38 -> 1 | O38: =L38*M38*N38 -> 23152.5 | P38: =L38*1.05 -> 2025.8438 | Q38: ='Program Budget'!R42 -> 3 | R38: =Admin!R38+'Activity 1'!R38+'Activity 2'!R38+'Activity 3'!R38+'Activity 4'!R38+'Activity 5'!R38+'Activity 6'!R38+'Activity 7'!R38+'Activity 8'!R38 -> 1 | S38: =P38*Q38*R38 -> 6077.5312 | T38: =C38+G38+K38+O38+S38 -> 72280.031
A39: Total Local Salary Cost | C39: =SUM(C10:C38) -> 1906309.2 | G39: =SUM(G10:G38) -> 1333302.8 | K39: =SUM(K10:K38) -> 1422017.9 | O39: =SUM(O10:O38) -> 1228518.8 | S39: =SUM(S10:S38) -> 243951.8 | T39: =C39+G39+K39+O39+S39 -> 6134100.5
A40: HQ Staff
A41: ='Program Budget'!D44 -> Senior Program Director | B41: ='Program Budget'!F44 -> Month | C41: =Admin!C41 -> 105808.88 | D41: ='Program Budget'!G44 -> 12500 | E41: =Admin!E41 -> 12 | F41: =Admin!F41 -> 0.25 | G41: =D41*E41*F41 -> 37500 | H41: =D41*1.05 -> 13125 | I41: ='Program Budget'!L44 -> 12 | J41: ='Program Budget'!K44 -> 0.25 | K41: =H41*I41*J41 -> 39375 | L41: =H41*1.05 -> 13781.25 | M41: ='Program Budget'!O44 -> 12 | N41: ='Program Budget'!N44 -> 0.25 | O41: =L41*M41*N41 -> 41343.75 | P41: =L41*1.05 -> 14470.312 | Q41: ='Program Budget'!R44 -> 6 | R41: ='Program Budget'!Q44 -> 0.25 | S41: =P41*Q41*R41 -> 21705.469 | T41: =C41+G41+K41+O41+S41 -> 245733.1
A42: ='Program Budget'!D45 -> Associate Director | B42: ='Program Budget'!F45 -> Month | C42: =Admin!C42 -> 170702.65 | D42: ='Program Budget'!G45 -> 8333.3333 | E42: =Admin!E42 -> 12 | F42: =Admin!F42 -> 0.65 | G42: =D42*E42*F42 -> 65000 | H42: =D42*1.05 -> 8750 | I42: ='Program Budget'!L45 -> 12 | J42: ='Program Budget'!K45 -> 0.65 | K42: =H42*I42*J42 -> 68250 | L42: =H42*1.05 -> 9187.5 | M42: ='Program Budget'!O45 -> 12 | N42: ='Program Budget'!N45 -> 0.65 | O42: =L42*M42*N42 -> 71662.5 | P42: =L42*1.05 -> 9646.875 | Q42: ='Program Budget'!R45 -> 6 | R42: ='Program Budget'!Q45 -> 0.65 | S42: =P42*Q42*R42 -> 37622.813 | T42: =C42+G42+K42+O42+S42 -> 413237.96
A43: ='Program Budget'!D46 -> Senior Program Officer | B43: ='Program Budget'!F46 -> Month | C43: =Admin!C43 -> 0 | D43: ='Program Budget'!G46 -> 5833.3333 | E43: =Admin!E43 -> 12 | F43: =Admin!F43 -> 0.61 | G43: =D43*E43*F43 -> 42700 | H43: =D43*1.05 -> 6125 | I43: ='Program Budget'!L46 -> 12 | J43: ='Program Budget'!K46 -> 0.61 | K43: =H43*I43*J43 -> 44835 | L43: =H43*1.05 -> 6431.25 | M43: ='Program Budget'!O46 -> 12 | N43: ='Program Budget'!N46 -> 0.61 | O43: =L43*M43*N43 -> 47076.75 | P43: =L43*1.05 -> 6752.8125 | Q43: ='Program Budget'!R46 -> 6 | R43: ='Program Budget'!Q46 -> 0.61 | S43: =P43*Q43*R43 -> 24715.294 | T43: =C43+G43+K43+O43+S43 -> 159327.04
A44: Total HQ Staff | C44: =SUM(C41:C43) -> 276511.53 | G44: =SUM(G41:G43) -> 145200 | K44: =SUM(K41:K43) -> 152460 | O44: =SUM(O41:O43) -> 160083 | S44: =SUM(S41:S43) -> 84043.575 | T44: =+C44+G44+K44+O44+S44 -> 818298.1
A46: Subtotal: Salaries & Wages | C46: =C44+C39+C8 -> 2751505.4 | G46: =G44+G39+G8 -> 1649502.8 | K46: =K44+K39+K8 -> 1754027.9 | O46: =O44+O39+O8 -> 1577129.3 | S46: =S44+S39+S8 -> 327995.37 | T46: =+C46+G46+K46+O46+S46 -> 8060160.8
A47: Fringe
A48: USN/TCN Staff | B48: ='Program Budget'!F51 -> % | C48: =Admin!C48+'Activity 1'!C43+'Activity 2'!C43+'Activity 3'!C43+'Activity 4'!C42+'Activity 5'!C42+'Activity 6'!C42+'Activity 7'!C42+'Activity 8'!C42 -> 87985.6 | D48: =G8 -> 171000 | E48: 1 | F48: ='Program Budget'!G55 -> 0.5647 | G48: =D48*E48*F48 -> 96563.7 | H48: =K8 -> 179550 | I48: 1 | J48: =F48 -> 0.5647 | K48: =H48*I48*J48 -> 101391.88 | L48: =O8 -> 188527.5 | M48: 1 | N48: =J48 -> 0.5647 | O48: =L48*M48*N48 -> 106461.48 | P48: =S8 -> 0 | Q48: 1 | R48: =N48 -> 0.5647 | S48: =P48*Q48*R48 -> 0 | T48: =C48+G48+K48+O48+S48 -> 392402.66
A49: CCN - Colombia (above $3,350 monthly) | B49: ='Program Budget'!F52 -> % | C49: =Admin!C49+'Activity 1'!C44+'Activity 2'!C44+'Activity 3'!C44+'Activity 4'!C43+'Activity 5'!C43+'Activity 6'!C43+'Activity 7'!C43+'Activity 8'!C43 -> 102223.2 | D49: =G10+G11+G20+G24+G27+G30+G32 -> 363352.8 | E49: 1 | F49: ='Program Budget'!G51 -> 0.53864 | G49: =D49*E49*F49 -> 195716.35 | H49: =K10+K11+K20+K24+K27+K30+K32 -> 381520.44 | I49: 1 | J49: =F49 -> 0.53864 | K49: =H49*I49*J49 -> 205502.17 | L49: =O10+O11+O20+O24+O27+O30+O32 -> 400596.46 | M49: 1 | N49: =J49 -> 0.53864 | O49: =L49*M49*N49 -> 215777.28 | P49: =S10+S11+S20+S24+S27+S30+S32 -> 157255.33 | Q49: 1 | R49: =N49 -> 0.53864 | S49: =P49*Q49*R49 -> 84704.011 | T49: =C49+G49+K49+O49+S49 -> 803923.01
A50: CCN - Colombia (below $3,350 monthly) | B50: ='Program Budget'!F53 -> % | C50: =Admin!C50+'Activity 1'!C45+'Activity 2'!C45+'Activity 3'!C45+'Activity 4'!C44+'Activity 5'!C44+'Activity 6'!C44+'Activity 7'!C44+'Activity 8'!C44 -> 915013.36 | D50: =G39-D49 -> 969950 | E50: 1 | F50: ='Program Budget'!G52 -> 0.44864 | G50: =D50*E50*F50 -> 435158.37 | H50: =K39-H49 -> 1040497.5 | I50: 1 | J50: =F50 -> 0.44864 | K50: =H50*I50*J50 -> 466808.8 | L50: =O39-L49 -> 827922.38 | M50: 1 | N50: =J50 -> 0.44864 | O50: =L50*M50*N50 -> 371439.09 | P50: =S39-P49 -> 86696.466 | Q50: 1 | R50: =N50 -> 0.44864 | S50: =P50*Q50*R50 -> 38895.502 | T50: =C50+G50+K50+O50+S50 -> 2227315.1
A51: HQ Staff | B51: ='Program Budget'!F53 -> % | C51: =Admin!C51 -> 99333.38 | D51: =G44 -> 145200 | E51: 1 | F51: ='Program Budget'!G53 -> 0.2347 | G51: =D51*E51*F51 -> 34078.44 | H51: =K44 -> 152460 | I51: 1 | J51: =F51 -> 0.2347 | K51: =H51*I51*J51 -> 35782.362 | L51: =O44 -> 160083 | M51: 1 | N51: =J51 -> 0.2347 | O51: =L51*M51*N51 -> 37571.48 | P51: =S44 -> 84043.575 | Q51: 1 | R51: =N51 -> 0.2347 | S51: =P51*Q51*R51 -> 19725.027 | T51: =C51+G51+K51+O51+S51 -> 226490.69
A52: Total: Fringe Benefits | C52: =+SUM(C48:C51) -> 1204555.5 | G52: =+SUM(G48:G51) -> 761516.86 | K52: =+SUM(K48:K51) -> 809485.22 | O52: =+SUM(O48:O51) -> 731249.33 | S52: =+SUM(S48:S51) -> 143324.54 | T52: =+C52+G52+K52+O52+S52 -> 3650131.5
A53: Allowances
A54: USN/TCN Staff
A55: ='Program Budget'!D54 -> Post (Hardship) Differential for Chief of Party | B55: ='Program Budget'!F54 -> % | C55: =Admin!C55+'Activity 1'!C48+'Activity 2'!C48+'Activity 3'!C48+'Activity 4'!C48+'Activity 5'!C48+'Activity 6'!C48+'Activity 7'!C48+'Activity 8'!C48 -> 76841.54 | D55: =G8 -> 171000 | E55: 1 | F55: ='Program Budget'!G54 -> 0.15 | G55: =D55*E55*F55 -> 25650 | H55: =K8 -> 179550 | I55: 1 | J55: =F55 -> 0.15 | K55: =H55*I55*J55 -> 26932.5 | L55: =O8 -> 188527.5 | M55: 1 | N55: =J55 -> 0.15 | O55: =L55*M55*N55 -> 28279.125 | P55: =S8 -> 0 | Q55: 1 | R55: =N55 -> 0.15 | S55: =P55*Q55*R55 -> 0 | T55: =C55+G55+K55+O55+S55 -> 157703.16
A56: ='Program Budget'!D56 -> Housing Allowance for Chief of Party | B56: ='Program Budget'!F56 -> Month | C56: ='Program Budget'!E56 -> 68428.33 | D56: ='Program Budget'!G56 -> 3000 | E56: ='Program Budget'!I56 -> 12 | F56: 1 | G56: =D56*E56*F56 -> 36000 | H56: =D56*1.04 -> 3120 | I56: ='Program Budget'!L56 -> 12 | J56: =F56 -> 1 | K56: =H56*I56*J56 -> 37440 | L56: =H56*1.04 -> 3244.8 | M56: ='Program Budget'!O56 -> 12 | N56: =J56 -> 1 | O56: =L56*M56*N56 -> 38937.6 | P56: =L56*1.04 -> 3374.592 | Q56: ='Program Budget'!R56 -> 0 | R56: 0 | S56: =P56*Q56*R56 -> 0 | T56: =C56+G56+K56+O56+S56 -> 180805.93
A57: ='Program Budget'!D57 -> Reallocation & Demobilization Allowance for Chief of Party | B57: ='Program Budget'!F57 -> Year | C57: ='Program Budget'!E57 -> 1565.26 | D57: ='Program Budget'!G57 -> 2583.93 | E57: ='Program Budget'!I57 -> 0 | F57: 0 | G57: =D57*E57*F57 -> 0 | H57: =D57*1.04 -> 2687.2872 | I57: ='Program Budget'!L57 -> 0 | J57: 0 | K57: =H57*I57*J57 -> 0 | L57: =H57*1.04 -> 2794.7787 | M57: ='Program Budget'!O57 -> 1 | N57: 1 | O57: =L57*M57*N57 -> 2794.7787 | P57: =L57*1.04 -> 2906.5698 | Q57: ='Program Budget'!R57 -> 0 | R57: 0 | S57: =P57*Q57*R57 -> 0 | T57: =C57+G57+K57+O57+S57 -> 4360.0387
A58: ='Program Budget'!D58 -> Annual Home of Record for Chief of Party | B58: ='Program Budget'!F58 -> Year | C58: ='Program Budget'!E58 -> 1357.75 | D58: ='Program Budget'!G58 -> 1100 | E58: ='Program Budget'!I58 -> 1 | F58: 1 | G58: =D58*E58*F58 -> 1100 | H58: =D58*1.04 -> 1144 | I58: ='Program Budget'!L58 -> 1 | J58: 1 | K58: =H58*I58*J58 -> 1144 | L58: =H58*1.04 -> 1189.76 | M58: ='Program Budget'!O58 -> 1 | N58: 1 | O58: =L58*M58*N58 -> 1189.76 | P58: =L58*1.04 -> 1237.3504 | Q58: ='Program Budget'!R58 -> 1 | R58: 1 | S58: =P58*Q58*R58 -> 1237.3504 | T58: =C58+G58+K58+O58+S58 -> 6028.8604
A59: Total: Allowances | C59: =SUM(C54:C58) -> 148192.88 | G59: =SUM(G54:G58) -> 62750 | K59: =SUM(K54:K58) -> 65516.5 | O59: =SUM(O54:O58) -> 71201.264 | S59: =SUM(S54:S58) -> 1237.3504 | T59: =C59+G59+K59+O59+S59 -> 348897.99
A61: Subtotal: Benefits | C61: =C59+C52 -> 1352748.4 | G61: =G59+G52 -> 824266.86 | K61: =K59+K52 -> 875001.72 | O61: =O59+O52 -> 802450.6 | S61: =S59+S52 -> 144561.89 | T61: =+C61+G61+K61+O61+S61 -> 3999029.5
A62: International Travel
A63: ='Program Budget'!D64 -> Airfare - DC-Colombia - HQ Project Management Trip | B63: ='Program Budget'!F64 -> Trip | C63: =Admin!C63 -> 12141.75 | D63: =Admin!D63 -> 800 | E63: =Admin!E63 -> 4 | F63: 1 | G63: =D63*E63*F63 -> 3200 | H63: =D63*1.04 -> 832 | I63: =Admin!I63 -> 4 | J63: 1 | K63: =H63*I63*J63 -> 3328 | L63: =H63*1.04 -> 865.28 | M63: =Admin!M63 -> 4 | N63: 1 | O63: =L63*M63*N63 -> 3461.12 | P63: =L63*1.04 -> 899.8912 | Q63: =Admin!Q63 -> 4 | R63: 1 | S63: =P63*Q63*R63 -> 3599.5648 | T63: =C63+G63+K63+O63+S63 -> 25730.435
A64: ='Program Budget'!D69 -> Airfare - Roundtrip - Colombia to USA | B64: ='Program Budget'!F69 -> Trip | C64: =Admin!C64 -> 8640.56 | D64: =Admin!D64 -> 800 | E64: =Admin!E64 -> 4 | F64: 1 | G64: =D64*E64*F64 -> 3200 | H64: =D64*1.03 -> 824 | I64: =Admin!I64 -> 4 | J64: 1 | K64: =H64*I64*J64 -> 3296 | L64: =H64*1.03 -> 848.72 | M64: =Admin!M64 -> 4 | N64: 1 | O64: =L64*M64*N64 -> 3394.88 | P64: =L64*1.03 -> 874.1816 | Q64: =Admin!Q64 -> 4 | R64: 1 | S64: =P64*Q64*R64 -> 3496.7264 | T64: =C64+G64+K64+O64+S64 -> 22028.166
A65: ='Activity 6'!A51 -> International Airfare for Young Agriculture Entrepreneur International Exchange | B65: ='Activity 6'!B51 -> Trip | C65: ='Activity 6'!C51 -> 19061.17 | D65: ='Activity 6'!D51 -> 2000 | E65: ='Activity 6'!E51 -> 11 | F65: 1 | G65: =D65*E65*F65 -> 22000 | H65: =D65*1.04 -> 2080 | I65: ='Activity 6'!I51 -> 0 | J65: 0 | K65: =H65*I65*J65 -> 0 | L65: =H65*1.04 -> 2163.2 | M65: ='Activity 6'!M51 -> 0 | N65: 0 | O65: =L65*M65*N65 -> 0 | P65: =L65*1.04 -> 2249.728 | Q65: ='Activity 6'!Q51 -> 0 | R65: 0 | S65: =P65*Q65*R65 -> 0 | T65: =C65+G65+K65+O65+S65 -> 41061.17
A66: ='Activity 7'!A51 -> International & Domestic Airfare for Conferences & Forums | B66: ='Activity 7'!B51 -> Trip | C66: ='Activity 7'!C51 -> 0 | D66: ='Activity 7'!D51 -> 1200 | E66: ='Activity 7'!E51 -> 2 | F66: 1 | G66: =D66*E66*F66 -> 2400 | H66: =D66*1.04 -> 1248 | I66: ='Activity 7'!I51 -> 2 | J66: 1 | K66: =H66*I66*J66 -> 2496 | L66: =H66*1.04 -> 1297.92 | M66: ='Activity 7'!M51 -> 2 | N66: 1 | O66: =L66*M66*N66 -> 2595.84 | P66: =L66*1.04 -> 1349.8368 | Q66: ='Activity 7'!Q51 -> 2 | R66: 1 | S66: =P66*Q66*R66 -> 2699.6736 | T66: =C66+G66+K66+O66+S66 -> 10191.514
A67: Local Travel | T67: =C67+G67+K67+O67+S67 -> 0
A68: ='Program Budget'!D66 -> Local Transportation – HQ Project Management Trip | B68: ='Program Budget'!F66 -> Trip | C68: =Admin!C66 -> 1104.45 | D68: =Admin!D66 -> 100 | E68: =Admin!E66 -> 4 | F68: 1 | G68: =D68*E68*F68 -> 400 | H68: =D68*1.04 -> 104 | I68: =Admin!I66 -> 4 | J68: 1 | K68: =H68*I68*J68 -> 416 | L68: =H68*1.04 -> 108.16 | M68: =Admin!M66 -> 4 | N68: 1 | O68: =L68*M68*N68 -> 432.64 | P68: =L68*1.04 -> 112.4864 | Q68: =Admin!Q66 -> 4 | R68: 1 | S68: =P68*Q68*R68 -> 449.9456 | T68: =C68+G68+K68+O68+S68 -> 2803.0356
A69: ='Program Budget'!D71 -> Local Transportation for Colombia Staff Travel | B69: ='Program Budget'!F75 -> Trip | C69: =Admin!C67 -> 895.05 | D69: =Admin!D67 -> 100 | E69: =Admin!E67 -> 4 | F69: 1 | G69: =D69*E69*F69 -> 400 | H69: =D69*1.03 -> 103 | I69: =Admin!I67 -> 4 | J69: 1 | K69: =H69*I69*J69 -> 412 | L69: =H69*1.03 -> 106.09 | M69: =Admin!M67 -> 4 | N69: 1 | O69: =L69*M69*N69 -> 424.36 | P69: =L69*1.03 -> 109.2727 | Q69: =Admin!Q67 -> 4 | R69: 1 | S69: =P69*Q69*R69 -> 437.0908 | T69: =C69+G69+K69+O69+S69 -> 2568.5008
A70: ='Program Budget'!D75 -> Local Transportation – Training, M&E, & Data Collection | B70: ='Program Budget'!F75 -> Trip | C70: =Admin!C68 -> 32433.77 | D70: =Admin!D68 -> 100 | E70: =Admin!E68 -> 36 | F70: 1 | G70: =D70*E70*F70 -> 3600 | H70: =D70*1.04 -> 104 | I70: =Admin!I68 -> 36 | J70: 1 | K70: =H70*I70*J70 -> 3744 | L70: =H70*1.04 -> 108.16 | M70: =Admin!M68 -> 36 | N70: 1 | O70: =L70*M70*N70 -> 3893.76 | P70: =L70*1.04 -> 112.4864 | Q70: =Admin!Q68 -> 9 | R70: 1 | S70: =P70*Q70*R70 -> 1012.3776 | T70: =C70+G70+K70+O70+S70 -> 44683.908
A71: ='Activity 2'!A52 -> Local Transportation – Training & Data Collection | B71: ='Activity 2'!B52 -> Trip | C71: ='Activity 2'!C52 -> 6403.93 | D71: ='Activity 2'!D52 -> 300 | E71: ='Activity 2'!E52 -> 12 | F71: 1 | G71: =D71*E71*F71 -> 3600 | H71: =D71*1.04 -> 312 | I71: ='Activity 2'!I52 -> 12 | J71: 1 | K71: =H71*I71*J71 -> 3744 | L71: =H71*1.04 -> 324.48 | M71: ='Activity 2'!M52 -> 12 | N71: 1 | O71: =L71*M71*N71 -> 3893.76 | P71: =L71*1.04 -> 337.4592 | Q71: ='Activity 2'!Q52 -> 3 | R71: 1 | S71: =P71*Q71*R71 -> 1012.3776 | T71: =C71+G71+K71+O71+S71 -> 18654.068
A72: ='Activity 2'!A53 -> Transport Stipend for Fedecafe Extension Agents for Boot Camp | B72: ='Activity 2'!B53 -> Participant | C72: ='Activity 2'!C53 -> 0 | D72: ='Activity 2'!D53 -> 250 | E72: ='Activity 2'!E53 -> 0 | F72: 1 | G72: =D72*E72*F72 -> 0 | H72: =D72*1.04 -> 260 | I72: ='Activity 2'!I53 -> 0 | J72: 1 | K72: =H72*I72*J72 -> 0 | L72: =H72*1.04 -> 270.4 | M72: ='Activity 2'!M53 -> 0 | N72: 1 | O72: =L72*M72*N72 -> 0 | P72: =L72*1.04 -> 281.216 | Q72: ='Activity 2'!Q53 -> 0 | R72: 1 | S72: =P72*Q72*R72 -> 0 | T72: =C72+G72+K72+O72+S72 -> 0
A73: ='Activity 3'!A53 -> Local Transportation – Training & Data Collection | B73: ='Activity 3'!B53 -> Trip | C73: ='Activity 3'!C53 -> 172784.9 | D73: ='Activity 3'!D53 -> 650 | E73: ='Activity 3'!E53 -> 72 | F73: 1 | G73: =D73*E73*F73 -> 46800 | H73: =D73*1.04 -> 676 | I73: ='Activity 3'!I53 -> 72 | J73: 1 | K73: =H73*I73*J73 -> 48672 | L73: =H73*1.04 -> 703.04 | M73: ='Activity 3'!M53 -> 72 | N73: 1 | O73: =L73*M73*N73 -> 50618.88 | P73: =L73*1.04 -> 731.1616 | Q73: ='Activity 3'!Q53 -> 6 | R73: 1 | S73: =P73*Q73*R73 -> 4386.9696 | T73: =C73+G73+K73+O73+S73 -> 323262.75
A74: ='Activity 3'!A54 -> Transport Stipend for Cacao Farmers for Boot Camp | B74: ='Activity 3'!B54 -> Participant | C74: ='Activity 3'!C54 -> 0 | D74: ='Activity 3'!D54 -> 250 | E74: ='Activity 3'!E54 -> 45 | F74: 1 | G74: =D74*E74*F74 -> 11250 | H74: =D74*1.04 -> 260 | I74: ='Activity 3'!I54 -> 45 | J74: 1 | K74: =H74*I74*J74 -> 11700 | L74: =H74*1.04 -> 270.4 | M74: ='Activity 3'!M54 -> 45 | N74: 1 | O74: =L74*M74*N74 -> 12168 | P74: =L74*1.04 -> 281.216 | Q74: ='Activity 3'!Q54 -> 0 | R74: 1 | S74: =P74*Q74*R74 -> 0 | T74: =C74+G74+K74+O74+S74 -> 35118
A75: ='Activity 3'!A55 -> Transport Stipend for Producers Representatives on Cacao and Complementary Crops | B75: ='Activity 3'!B55 -> Participant | C75: ='Activity 3'!C55 -> 0 | D75: ='Activity 3'!D55 -> 250 | E75: ='Activity 3'!E55 -> 45 | F75: 1 | G75: =D75*E75*F75 -> 11250 | H75: =D75*1.04 -> 260 | I75: ='Activity 3'!I55 -> 45 | J75: 1 | K75: =H75*I75*J75 -> 11700 | L75: =H75*1.04 -> 270.4 | M75: ='Activity 3'!M55 -> 45 | N75: 1 | O75: =L75*M75*N75 -> 12168 | P75: =L75*1.04 -> 281.216 | Q75: ='Activity 3'!Q55 -> 0 | R75: 1 | S75: =P75*Q75*R75 -> 0 | T75: =C75+G75+K75+O75+S75 -> 35118
A76: ='Activity 3'!A56 -> Transport, Lodging & M&IE for 3 Months for Students of Cacao Extension Professionalization Program | B76: ='Activity 3'!B56 -> Participant | C76: ='Activity 3'!C56 -> 0 | D76: ='Activity 3'!D56 -> 4200 | E76: ='Activity 3'!E56 -> 12 | F76: 1 | G76: =D76*E76*F76 -> 50400 | H76: =D76*1.04 -> 4368 | I76: ='Activity 3'!I56 -> 13 | J76: 1 | K76: =H76*I76*J76 -> 56784 | L76: =H76*1.04 -> 4542.72 | M76: ='Activity 3'!M56 -> 0 | N76: 1 | O76: =L76*M76*N76 -> 0 | P76: =L76*1.04 -> 4724.4288 | Q76: ='Activity 3'!Q56 -> 0 | R76: 0 | S76: =P76*Q76*R76 -> 0 | T76: =C76+G76+K76+O76+S76 -> 107184
A77: ='Activity 4'!A51 -> Local Transportation – Training & Data Collection | B77: ='Activity 4'!B51 -> Trip | C77: ='Activity 4'!C51 -> 10363.09 | D77: ='Activity 4'!D51 -> 300 | E77: ='Activity 4'!E51 -> 12 | F77: 1 | G77: =D77*E77*F77 -> 3600 | H77: =D77*1.04 -> 312 | I77: ='Activity 4'!I51 -> 12 | J77: 1 | K77: =H77*I77*J77 -> 3744 | L77: =H77*1.04 -> 324.48 | M77: ='Activity 4'!M51 -> 12 | N77: 1 | O77: =L77*M77*N77 -> 3893.76 | P77: =L77*1.04 -> 337.4592 | Q77: ='Activity 4'!Q51 -> 6 | R77: 1 | S77: =P77*Q77*R77 -> 2024.7552 | T77: =C77+G77+K77+O77+S77 -> 23625.605
A78: ='Activity 5'!A51 -> Local Transportation to Bogota for Business Plan Presentation to ANDEAN | B78: ='Activity 5'!B51 -> Trip | C78: ='Activity 5'!C51 -> 2024 | D78: ='Activity 5'!D51 -> 100 | E78: ='Activity 5'!E51 -> 0 | F78: 0 | G78: =D78*E78*F78 -> 0 | H78: =D78*1.04 -> 104 | I78: ='Activity 5'!I51 -> 0 | J78: 0 | K78: =H78*I78*J78 -> 0 | L78: =H78*1.04 -> 108.16 | M78: ='Activity 5'!M51 -> 0 | N78: 0 | O78: =L78*M78*N78 -> 0 | P78: =L78*1.04 -> 112.4864 | Q78: ='Activity 5'!Q51 -> 0 | R78: 0 | S78: =P78*Q78*R78 -> 0 | T78: =C78+G78+K78+O78+S78 -> 2024
A79: ='Activity 6'!A55 -> Local Transportation for Young Agriculture Entrepreneur International Exchange | B79: ='Activity 6'!B55 -> Day | C79: ='Activity 6'!C55 -> 4511.69 | D79: ='Activity 6'!D55 -> 25 | E79: ='Activity 6'!E55 -> 154 | F79: 1 | G79: =D79*E79*F79 -> 3850 | H79: =D79*1.04 -> 26 | I79: ='Activity 6'!I55 -> 0 | J79: 0 | K79: =H79*I79*J79 -> 0 | L79: =H79*1.04 -> 27.04 | M79: ='Activity 6'!M55 -> 0 | N79: 0 | O79: =L79*M79*N79 -> 0 | P79: =L79*1.04 -> 28.1216 | Q79: ='Activity 6'!Q55 -> 0 | R79: 0 | S79: =P79*Q79*R79 -> 0 | T79: =C79+G79+K79+O79+S79 -> 8361.69
A80: ='Activity 7'!A53 -> Local Travel for Meetings and Cacao Council | B80: ='Activity 7'!B53 -> Month | C80: ='Activity 7'!C53 -> 12523.1 | D80: ='Activity 7'!D53 -> 200 | E80: ='Activity 7'!E53 -> 12 | F80: 1 | G80: =D80*E80*F80 -> 2400 | H80: =D80*1.04 -> 208 | I80: ='Activity 7'!I53 -> 12 | J80: 1 | K80: =H80*I80*J80 -> 2496 | L80: =H80*1.04 -> 216.32 | M80: ='Activity 7'!M53 -> 12 | N80: 1 | O80: =L80*M80*N80 -> 2595.84 | P80: =L80*1.04 -> 224.9728 | Q80: ='Activity 7'!Q53 -> 4 | R80: 1 | S80: =P80*Q80*R80 -> 899.8912 | T80: =C80+G80+K80+O80+S80 -> 20914.831
A81: ='Activity 7'!A54 -> Local Transportation for Conferences & Forums | B81: ='Activity 7'!B54 -> Trip | C81: ='Activity 7'!C54 -> 0 | D81: ='Activity 7'!D54 -> 300 | E81: ='Activity 7'!E54 -> 2 | F81: 1 | G81: =D81*E81*F81 -> 600 | H81: =D81*1.04 -> 312 | I81: ='Activity 7'!I54 -> 2 | J81: 1 | K81: =H81*I81*J81 -> 624 | L81: =H81*1.04 -> 324.48 | M81: ='Activity 7'!M54 -> 2 | N81: 1 | O81: =L81*M81*N81 -> 648.96 | P81: =L81*1.04 -> 337.4592 | Q81: ='Activity 7'!Q54 -> 2 | R81: 1 | S81: =P81*Q81*R81 -> 674.9184 | T81: =C81+G81+K81+O81+S81 -> 2547.8784
A82: ='Activity 7'!A55 -> Colombia Young Producers Stipends for Exchange Trip | B82: ='Activity 7'!B55 -> Trip | C82: ='Activity 7'!C55 -> 17263.26 | D82: ='Activity 7'!D55 -> 10000 | E82: ='Activity 7'!E55 -> 0 | F82: 0 | G82: =D82*E82*F82 -> 0 | H82: =D82*1.04 -> 10400 | I82: ='Activity 7'!I55 -> 5 | J82: 1 | K82: =H82*I82*J82 -> 52000 | L82: =H82*1.04 -> 10816 | M82: ='Activity 7'!M55 -> 5 | N82: 1 | O82: =L82*M82*N82 -> 54080 | P82: =L82*1.04 -> 11248.64 | Q82: ='Activity 7'!Q55 -> 0 | R82: 0 | S82: =P82*Q82*R82 -> 0 | T82: =C82+G82+K82+O82+S82 -> 123343.26
A83: ='Activity 8'!A51 -> Local Travel for Meetings | B83: ='Activity 8'!B51 -> Trip | C83: ='Activity 8'!C51 -> 5000 | D83: ='Activity 8'!D51 -> 25 | E83: ='Activity 8'!E51 -> 60 | F83: 1 | G83: =D83*E83*F83 -> 1500 | H83: =D83*1.04 -> 26 | I83: ='Activity 8'!I51 -> 0 | J83: 0 | K83: =H83*I83*J83 -> 0 | L83: =H83*1.04 -> 27.04 | M83: ='Activity 8'!M51 -> 0 | N83: 0 | O83: =L83*M83*N83 -> 0 | P83: =L83*1.04 -> 28.1216 | Q83: ='Activity 8'!Q51 -> 0 | R83: 0 | S83: =P83*Q83*R83 -> 0 | T83: =C83+G83+K83+O83+S83 -> 6500
A84: Vehicle Fuel | G84: =D84*E84*F84 -> 0 | T84: =C84+G84+K84+O84+S84 -> 0
A85: =Admin!A70 -> Vehicle/Motorcycle Fuel Expense | B85: =Admin!B70 -> Month | C85: =Admin!C70 -> 9640.86 | D85: =Admin!D70 -> 200 | E85: =Admin!E70 -> 12 | F85: 1 | G85: =D85*E85*F85 -> 2400 | H85: =D85*1.04 -> 208 | I85: =Admin!I70 -> 12 | J85: 1 | K85: =H85*I85*J85 -> 2496 | L85: =H85*1.04 -> 216.32 | M85: =Admin!M70 -> 12 | N85: 1 | O85: =L85*M85*N85 -> 2595.84 | P85: =L85*1.04 -> 224.9728 | Q85: =Admin!Q70 -> 3 | R85: 1 | S85: =P85*Q85*R85 -> 674.9184 | T85: =C85+G85+K85+O85+S85 -> 17807.618
A86: ='Activity 3'!A58 -> Motorcycle Fuel Expense for Extension Agents | B86: ='Activity 3'!B58 -> Month | C86: ='Activity 3'!C58+'Activity 4'!C53 -> 125947.34 | D86: ='Activity 3'!D58+'Activity 4'!D53 -> 3300 | E86: ='Activity 3'!E58 -> 12 | F86: 1 | G86: =D86*E86*F86 -> 39600 | H86: =D86*1.04 -> 3432 | I86: ='Activity 3'!I58 -> 12 | J86: 1 | K86: =H86*I86*J86 -> 41184 | L86: =H86*1.04 -> 3569.28 | M86: ='Activity 3'!M58 -> 12 | N86: 1 | O86: =L86*M86*N86 -> 42831.36 | P86: =L86*1.04 -> 3712.0512 | Q86: ='Activity 3'!Q58 -> 0 | R86: 0 | S86: =P86*Q86*R86 -> 0 | T86: =C86+G86+K86+O86+S86 -> 249562.7
A87: Per Diem | T87: =C87+G87+K87+O87+S87 -> 0
A88: =Admin!A72 -> Lodging and M&IE - HQ Project Management Trip | B88: =Admin!B72 -> Day | C88: =Admin!C72 -> 13828.71 | D88: =Admin!D72 -> 286 | E88: =Admin!E72 -> 20 | F88: 1 | G88: =D88*E88*F88 -> 5720 | H88: =D88*1.04 -> 297.44 | I88: =Admin!I72 -> 20 | J88: 1 | K88: =H88*I88*J88 -> 5948.8 | L88: =H88*1.04 -> 309.3376 | M88: =Admin!M72 -> 20 | N88: 1 | O88: =L88*M88*N88 -> 6186.752 | P88: =L88*1.04 -> 321.7111 | Q88: ='Program Budget'!R65 -> 20 | R88: 1 | S88: =P88*Q88*R88 -> 6434.2221 | T88: =C88+G88+K88+O88+S88 -> 38118.484
A89: =Admin!A73 -> Other Travel Related Expenses – HQ Project Management Trip | B89: =Admin!B73 -> Trip | C89: =Admin!C73 -> 118.18 | D89: =Admin!D73 -> 25 | E89: =Admin!E73 -> 4 | F89: 1 | G89: =D89*E89*F89 -> 100 | H89: =D89*1.04 -> 26 | I89: =Admin!I73 -> 4 | J89: 1 | K89: =H89*I89*J89 -> 104 | L89: =H89*1.04 -> 27.04 | M89: =Admin!M73 -> 4 | N89: 1 | O89: =L89*M89*N89 -> 108.16 | P89: =L89*1.04 -> 28.1216 | Q89: ='Program Budget'!R67 -> 4 | R89: 1 | S89: =P89*Q89*R89 -> 112.4864 | T89: =C89+G89+K89+O89+S89 -> 542.8264
A90: =Admin!A74 -> Lodging and M&IE for Colombia Staff Travel | B90: =Admin!B74 -> Day | C90: =Admin!C74 -> 8160.39 | D90: =Admin!D74 -> 260 | E90: =Admin!E74 -> 40 | F90: 1 | G90: =D90*E90*F90 -> 10400 | H90: =D90*1.03 -> 267.8 | I90: =Admin!I74 -> 40 | J90: 1 | K90: =H90*I90*J90 -> 10712 | L90: =H90*1.03 -> 275.834 | M90: =Admin!M74 -> 40 | N90: 1 | O90: =L90*M90*N90 -> 11033.36 | P90: =L90*1.03 -> 284.10902 | Q90: ='Program Budget'!R70 -> 40 | R90: 1 | S90: =P90*Q90*R90 -> 11364.361 | T90: =C90+G90+K90+O90+S90 -> 51670.111
A91: =Admin!A75 -> Other Travel Related Expenses for Colombia Staff Travel | B91: =Admin!B75 -> Trip | C91: =Admin!C75 -> 374.49 | D91: =Admin!D75 -> 25 | E91: =Admin!E75 -> 4 | F91: 1 | G91: =D91*E91*F91 -> 100 | H91: =D91*1.03 -> 25.75 | I91: =Admin!I75 -> 4 | J91: 1 | K91: =H91*I91*J91 -> 103 | L91: =H91*1.03 -> 26.5225 | M91: =Admin!M75 -> 4 | N91: 1 | O91: =L91*M91*N91 -> 106.09 | P91: =L91*1.03 -> 27.318175 | Q91: ='Program Budget'!R72 -> 4 | R91: 1 | S91: =P91*Q91*R91 -> 109.2727 | T91: =C91+G91+K91+O91+S91 -> 792.8527
A92: ='Activity 2'!A57 -> Lodging and M&IE - Training, & Data Collection | B92: ='Activity 2'!B57 -> Day | C92: ='Activity 2'!C57+'Activity 3'!C60+'Activity 4'!C55+Admin!C76 -> 74971.51 | D92: ='Activity 2'!D57 -> 157 | E92: ='Activity 2'!E57+'Activity 3'!E60+'Activity 4'!E55+Admin!E76 -> 432 | F92: 1 | G92: =D92*E92*F92 -> 67824 | H92: =D92*1.04 -> 163.28 | I92: ='Activity 2'!I57+'Activity 3'!I60+'Activity 4'!I55+Admin!I76 -> 432 | J92: 1 | K92: =H92*I92*J92 -> 70536.96 | L92: =H92*1.04 -> 169.8112 | M92: ='Activity 2'!M57+'Activity 3'!M60+'Activity 4'!M55+Admin!M76 -> 432 | N92: 1 | O92: =L92*M92*N92 -> 73358.438 | P92: =L92*1.04 -> 176.60365 | Q92: ='Activity 2'!Q57+'Activity 3'!Q60+'Activity 4'!Q55+Admin!Q76 -> 81 | R92: 1 | S92: =P92*Q92*R92 -> 14304.895 | T92: =C92+G92+K92+O92+S92 -> 300995.8
A93: ='Activity 5'!A53 -> Lodging and M&IE in Bogota for Business Plan Presentation to ANDEAN | B93: ='Activity 5'!B53 -> Day | C93: ='Activity 5'!C53 -> 1680 | D93: ='Activity 5'!D53 -> 100 | E93: ='Activity 5'!E53 -> 0 | F93: 0 | G93: =D93*E93*F93 -> 0 | H93: =D93*1.04 -> 104 | I93: ='Activity 5'!I53 -> 0 | J93: 0 | K93: =H93*I93*J93 -> 0 | L93: =H93*1.04 -> 108.16 | M93: ='Activity 5'!M53 -> 0 | N93: 0 | O93: =L93*M93*N93 -> 0 | P93: =L93*1.04 -> 112.4864 | Q93: ='Activity 5'!Q53 -> 0 | R93: 0 | S93: =P93*Q93*R93 -> 0 | T93: =C93+G93+K93+O93+S93 -> 1680
A94: ='Activity 6'!A57 -> Student Lodging and M&IE - Bogota - Business Plan Presentation to RCP | B94: ='Activity 6'!B57 -> Day | C94: ='Activity 6'!C57 -> 3864.88 | D94: ='Activity 6'!D57 -> 100 | E94: ='Activity 6'!E57 -> 0 | F94: 0 | G94: =D94*E94*F94 -> 0 | H94: =D94*1.04 -> 104 | I94: ='Activity 6'!I57 -> 0 | J94: 0 | K94: =H94*I94*J94 -> 0 | L94: =H94*1.04 -> 108.16 | M94: ='Activity 6'!M57 -> 0 | N94: 0 | O94: =L94*M94*N94 -> 0 | P94: =L94*1.04 -> 112.4864 | Q94: ='Activity 6'!Q57 -> 0 | R94: 0 | S94: =P94*Q94*R94 -> 0 | T94: =C94+G94+K94+O94+S94 -> 3864.88
A95: ='Activity 6'!A58 -> Lodging M&IE for Young Agriculture Entrepreneur International Exchange | B95: ='Activity 6'!B58 -> Day | C95: ='Activity 6'!C58 -> 19247.39 | D95: ='Activity 6'!D58 -> 100 | E95: ='Activity 6'!E58 -> 154 | F95: 1 | G95: =D95*E95*F95 -> 15400 | H95: =D95*1.04 -> 104 | I95: ='Activity 6'!I58 -> 0 | J95: 0 | K95: =H95*I95*J95 -> 0 | L95: =H95*1.04 -> 108.16 | M95: ='Activity 6'!M58 -> 0 | N95: 0 | O95: =L95*M95*N95 -> 0 | P95: =L95*1.04 -> 112.4864 | Q95: ='Activity 6'!Q58 -> 0 | R95: 0 | S95: =P95*Q95*R95 -> 0 | T95: =C95+G95+K95+O95+S95 -> 34647.39
A96: ='Activity 6'!A59 -> Other Travel Related Expenses for Young Agriculture Entrepreneur International Exchange | B96: ='Activity 6'!B59 -> Trip | C96: ='Activity 6'!C59 -> 919.07 | D96: ='Activity 6'!D59 -> 25 | E96: ='Activity 6'!E59 -> 11 | F96: 1 | G96: =D96*E96*F96 -> 275 | H96: =D96*1.04 -> 26 | I96: ='Activity 6'!I59 -> 0 | J96: 0 | K96: =H96*I96*J96 -> 0 | L96: =H96*1.04 -> 27.04 | M96: ='Activity 6'!M59 -> 0 | N96: 0 | O96: =L96*M96*N96 -> 0 | P96: =L96*1.04 -> 28.1216 | Q96: ='Activity 6'!Q59 -> 0 | R96: 0 | S96: =P96*Q96*R96 -> 0 | T96: =C96+G96+K96+O96+S96 -> 1194.07
A97: ='Activity 7'!A57 -> Lodging & M&IE for Conferences & Forums | B97: ='Activity 7'!B57 -> Day | C97: ='Activity 7'!C57 -> 0 | D97: ='Activity 7'!D57 -> 349 | E97: ='Activity 7'!E57 -> 12 | F97: 1 | G97: =D97*E97*F97 -> 4188 | H97: =D97*1.04 -> 362.96 | I97: ='Activity 7'!I57 -> 12 | J97: 1 | K97: =H97*I97*J97 -> 4355.52 | L97: =H97*1.04 -> 377.4784 | M97: ='Activity 7'!M57 -> 12 | N97: 1 | O97: =L97*M97*N97 -> 4529.7408 | P97: =L97*1.04 -> 392.57754 | Q97: ='Activity 7'!Q57 -> 12 | R97: 1 | S97: =P97*Q97*R97 -> 4710.9304 | T97: =C97+G97+K97+O97+S97 -> 17784.191
A99: Subtotal: Travel | C99: =SUM(C63:C98) -> 563903.54 | G99: =SUM(G63:G98) -> 316457 | K99: =SUM(K63:K98) -> 340596.28 | O99: =SUM(O63:O98) -> 295019.54 | S99: =SUM(S63:S98) -> 58405.377 | T99: =SUM(T63:T98) -> 1574381.7
A100: Professional Services
A101: =Admin!A80 -> Payroll, Accounting and Audit Costs - (Auditoria Fiscal & Program Specific Audits) | B101: =Admin!B80 -> Year | C101: =Admin!C80 -> 26306.36 | D101: =Admin!D80 -> 13000 | E101: =Admin!E80 -> 1 | F101: 1 | G101: =D101*E101*F101 -> 13000 | H101: =D101 -> 13000 | I101: =Admin!I80 -> 1 | J101: 1 | K101: =H101*I101*J101 -> 13000 | L101: =H101 -> 13000 | M101: =Admin!M80 -> 1 | N101: 1 | O101: =L101*M101*N101 -> 13000 | P101: =L101 -> 13000 | Q101: =Admin!Q80 -> 0.5 | R101: 1 | S101: =P101*Q101*R101 -> 6500 | T101: =C101+G101+K101+O101+S101 -> 71806.36
A102: =Admin!A81 -> Legal Fees | B102: =Admin!B81 -> Year | C102: =Admin!C81 -> 22150.08 | D102: =Admin!D81 -> 4425 | E102: =Admin!E81 -> 1 | F102: 1 | G102: =D102*E102*F102 -> 4425 | H102: =D102 -> 4425 | I102: =Admin!I81 -> 1 | J102: 1 | K102: =H102*I102*J102 -> 4425 | L102: =H102 -> 4425 | M102: =Admin!M81 -> 1 | N102: 1 | O102: =L102*M102*N102 -> 4425 | P102: =L102 -> 4425 | Q102: =Admin!Q81 -> 1 | R102: 1 | S102: =P102*Q102*R102 -> 4425 | T102: =C102+G102+K102+O102+S102 -> 39850.08
A103: =Admin!A82 -> Monetization Agent Fee | B103: =Admin!B82 -> % | C103: =Admin!C82 -> 512975 | D103: =Admin!D82 -> 9000000 | E103: =Admin!E82 -> 1 | F103: 0.025 | G103: =D103*E103*F103 -> 225000 | H103: =D103 -> 9000000 | I103: =Admin!I82 -> 0 | J103: 0 | K103: =H103*I103*J103 -> 0 | L103: =H103 -> 9000000 | M103: =Admin!M82 -> 0 | N103: 0 | O103: =L103*M103*N103 -> 0 | P103: =L103 -> 9000000 | Q103: =Admin!Q82 -> 0 | R103: 1 | S103: =P103*Q103*R103 -> 0 | T103: =C103+G103+K103+O103+S103 -> 737975
A104: =Admin!A83 -> Post Monetization Assessment | B104: =Admin!B83 -> Unit | C104: =Admin!C83 -> 47918.55 | D104: =Admin!D83 -> 47918.55 | E104: =Admin!E83 -> 0 | F104: 0 | G104: =D104*E104*F104 -> 0 | H104: =D104 -> 47918.55 | I104: =Admin!I83 -> 0 | J104: 0 | K104: =H104*I104*J104 -> 0 | L104: =H104 -> 47918.55 | M104: =Admin!M83 -> 0 | N104: 0 | O104: =L104*M104*N104 -> 0 | P104: =L104 -> 47918.55 | Q104: =Admin!Q83 -> 0 | R104: 1 | S104: =P104*Q104*R104 -> 0 | T104: =C104+G104+K104+O104+S104 -> 47918.55
A105: =Admin!A84 -> Security Plan and Advisors | B105: =Admin!B84 -> Year | C105: =Admin!C84 -> 0 | D105: =Admin!D84 -> 25000 | E105: =Admin!E84 -> 1 | F105: 1 | G105: =D105*E105*F105 -> 25000 | H105: =D105 -> 25000 | I105: =Admin!I84 -> 1 | J105: 1 | K105: =H105*I105*J105 -> 25000 | L105: =H105 -> 25000 | M105: =Admin!M84 -> 1 | N105: 1 | O105: =L105*M105*N105 -> 25000 | P105: =L105 -> 25000 | Q105: =Admin!Q84 -> 0.5 | R105: 1 | S105: =P105*Q105*R105 -> 12500 | T105: =C105+G105+K105+O105+S105 -> 87500
A106: =Admin!A85 -> HQ Consultants & Advisory Support Services | B106: =Admin!B85 -> Month | C106: =Admin!C85 -> 68599.1 | D106: =Admin!D85 -> 1125 | E106: =Admin!E85 -> 12 | F106: 1 | G106: =D106*E106*F106 -> 13500 | H106: =D106 -> 1125 | I106: =Admin!I85 -> 12 | J106: 1 | K106: =H106*I106*J106 -> 13500 | L106: =H106 -> 1125 | M106: =Admin!M85 -> 12 | N106: 1 | O106: =L106*M106*N106 -> 13500 | P106: =L106 -> 1125 | Q106: =Admin!Q85 -> 6 | R106: 1 | S106: =P106*Q106*R106 -> 6750 | T106: =C106+G106+K106+O106+S106 -> 115849.1
A107: ='Activity 2'!A61 -> Subrecipient: Training for Producer Organizations - Fundación Julio y Astrida Carrizosa ONG (IC Fundación) | B107: ='Activity 2'!B61 -> Subrecipient | C107: ='Activity 2'!C61 -> 358416.28 | D107: ='Activity 2'!D61 -> 441000 | E107: ='Activity 2'!E61 -> 1 | F107: 1 | G107: =D107*E107*F107 -> 441000 | H107: ='Activity 2'!H61 -> 203176.62 | I107: ='Activity 2'!I61 -> 1 | J107: 1 | K107: =H107*I107*J107 -> 203176.62 | L107: ='Activity 2'!L61 -> 0 | M107: ='Activity 2'!M61 -> 1 | N107: 1 | O107: =L107*M107*N107 -> 0 | P107: ='Activity 2'!PD61 -> 0 | Q107: ='Activity 2'!Q61 -> 0 | R107: 0 | S107: =P107*Q107*R107 -> 0 | T107: =C107+G107+K107+O107+S107 -> 1002592.9
A108: ='Activity 2'!A62 -> Business Plan Advisory Services for Agribusiness Entrepreneurship Grants | B108: ='Activity 2'!B62 -> Contract | C108: ='Activity 2'!C62 -> 0 | D108: ='Activity 2'!D62 -> 0 | E108: ='Activity 2'!E62 -> 0 | F108: 0 | G108: =D108*E108*F108 -> 0 | H108: ='Activity 2'!H62 -> 0 | I108: ='Activity 2'!I62 -> 1 | J108: 1 | K108: =H108*I108*J108 -> 0 | L108: ='Activity 2'!L62 -> 0 | M108: ='Activity 2'!M62 -> 1 | N108: 1 | O108: =L108*M108*N108 -> 0 | P108: ='Activity 2'!PD62 -> 0 | Q108: ='Activity 2'!Q62 -> 0 | R108: 0 | S108: =P108*Q108*R108 -> 0 | T108: =C108+G108+K108+O108+S108 -> 0
A109: ='Activity 3'!A64 -> Subrecipient: Digital Extension tools/GIS | B109: ='Activity 3'!B64 -> Subrecipient | C109: ='Activity 3'!C64 -> 20000 | D109: ='Activity 3'!D64 -> 20000 | E109: ='Activity 3'!E64 -> 0 | F109: 0 | G109: =D109*E109*F109 -> 0 | H109: ='Activity 3'!H64 -> 20000 | I109: ='Activity 3'!I64 -> 0 | J109: 0 | K109: =H109*I109*J109 -> 0 | L109: ='Activity 3'!L64 -> 20000 | M109: ='Activity 3'!M64 -> 0 | N109: 0 | O109: =L109*M109*N109 -> 0 | P109: ='Activity 3'!P64 -> 20000 | Q109: ='Activity 3'!AQ4 -> 0 | R109: 0 | S109: =P109*Q109*R109 -> 0 | T109: =C109+G109+K109+O109+S109 -> 20000
A110: ='Activity 3'!A65 -> Subrecipient: Food Safety/Gene Editing | B110: ='Activity 3'!B65 -> Subrecipient | C110: ='Activity 3'!C65 -> 0 | D110: ='Activity 3'!D65 -> 0 | E110: ='Activity 3'!E65 -> 0 | F110: 0 | G110: =D110*E110*F110 -> 0 | H110: ='Activity 3'!H65 -> 0 | I110: ='Activity 3'!I65 -> 0 | J110: 0 | K110: =H110*I110*J110 -> 0 | L110: ='Activity 3'!L65 -> 0 | M110: ='Activity 3'!M65 -> 0 | N110: 0 | O110: =L110*M110*N110 -> 0 | P110: ='Activity 3'!P65 -> 0 | Q110: ='Activity 3'!AQ5 -> 0 | R110: 0 | S110: =P110*Q110*R110 -> 0 | T110: =C110+G110+K110+O110+S110 -> 0
...

Sheet Admin
A2: Item | B2: Type of Unit | C2: Year 1 -4 Total Inception through 09/30/2024 | D2: Year 5 (10/1/24 - 9/30/25) | H2: Year 6 (10/1/25 - 09/30/26) | L2: Year 7 (10/1/26 - 09/30/27) | P2: Year 8 (10/1/27 - 3/31/28) | T2: Total
D3: Cost | E3: Quantity | F3: Percent Allocated | G3: Total | H3: Cost | I3: Quantity | J3: Percent Allocated | K3: Total | L3: Cost | M3: Quantity | N3: Percent Allocated | O3: Total | P3: Cost | Q3: Quantity | R3: Percent Allocated | S3: Total | AC3: Chart of Accounts
A4: Direct Costs | AB4: Line# | AC4: Account | AD4: Account Name
A5: Salaries
A6: USN/TCN Staff
A7: ='Program Budget'!D13 -> Key Personnel: Chief of Party | B7: ='Program Budget'!F13 -> Month | C7: ='Program Budget'!E13 -> 225257 | D7: ='Program Budget'!G13 -> 14250 | E7: ='Program Budget'!I13 -> 12 | F7: ='Program Budget'!H13 -> 0.1 | G7: =D7*E7*F7 -> 17100 | H7: =D7*1.05 -> 14962.5 | I7: ='Program Budget'!L13 -> 12 | J7: ='Program Budget'!K13 -> 0.05 | K7: =H7*I7*J7 -> 8977.5 | L7: =H7*1.05 -> 15710.625 | M7: ='Program Budget'!O13 -> 12 | N7: ='Program Budget'!N13 -> 0.05 | O7: =L7*M7*N7 -> 9426.375 | P7: =L7*1.05 -> 16496.156 | Q7: ='Program Budget'!R13 -> 0 | R7: ='Program Budget'!Q13 -> 0.05 | S7: =P7*Q7*R7 -> 0 | T7: =C7+G7+K7+O7+S7 -> 260760.88 | AB7: 180 | AC7: 50-01-2-020 | AD7: DIR-USN (Expat) Labor
A8: Total: Expatriate Salaries & Wages | C8: =SUM(C7:C7) -> 225257 | G8: =SUM(G7:G7) -> 17100 | K8: =SUM(K7:K7) -> 8977.5 | O8: =SUM(O7:O7) -> 9426.375 | S8: =SUM(S7:S7) -> 0 | T8: =+C8+G8+K8+O8+S8 -> 260760.88
A9: CNN Staff
A10: ='Program Budget'!D14 -> Deputy Chief of Party / Value Chain Strengthening Director | B10: ='Program Budget'!F14 -> Month | C10: ='Program Budget'!E14 -> 0 | D10: ='Program Budget'!G14 -> 5000 | E10: ='Program Budget'!I14 -> 12 | F10: ='Program Budget'!H14 -> 0.1 | G10: =D10*E10*F10 -> 6000 | H10: =D10*1.05 -> 5250 | I10: ='Program Budget'!L14 -> 12 | J10: ='Program Budget'!K14 -> 0.25 | K10: =H10*I10*J10 -> 15750 | L10: =H10*1.05 -> 5512.5 | M10: 12 | N10: ='Program Budget'!N14 -> 0.25 | O10: =L10*M10*N10 -> 16537.5 | P10: =L10*1.05 -> 5788.125 | Q10: ='Program Budget'!R14 -> 6 | R10: ='Program Budget'!Q14 -> 0.25 | S10: =P10*Q10*R10 -> 8682.1875 | T10: =C10+G10+K10+O10+S10 -> 46969.688 | AB10: 180 | AC10: 50-01-2-020 | AD10: DIR-USN (Expat) Labor
A11: ='Program Budget'!D15 -> Key Personnel: Technical Director | B11: ='Program Budget'!F15 -> Month | C11: ='Program Budget'!E15 -> 0 | D11: ='Program Budget'!G15 -> 4583.3333 | E11: ='Program Budget'!I15 -> 12 | F11: ='Program Budget'!H15 -> 0.05 | G11: =D11*E11*F11 -> 2750 | H11: =D11*1.05 -> 4812.5 | I11: ='Program Budget'!L15 -> 12 | J11: ='Program Budget'!K15 -> 0.05 | K11: =H11*I11*J11 -> 2887.5 | L11: =H11*1.05 -> 5053.125 | M11: ='Program Budget'!O14 -> 12 | N11: ='Program Budget'!N15 -> 0.05 | O11: =L11*M11*N11 -> 3031.875 | P11: =L11*1.05 -> 5305.7812 | Q11: ='Program Budget'!R15 -> 5 | R11: ='Program Budget'!Q15 -> 0.05 | S11: =P11*Q11*R11 -> 1326.4453 | T11: =C11+G11+K11+O11+S11 -> 9995.8203
A12: ='Program Budget'!D16 -> Activity Lead Agribusiness Senior Specialist (Cacao) | B12: ='Program Budget'!F16 -> Month | C12: ='Program Budget'!E16 -> 0 | D12: ='Program Budget'!G16 -> 2833.3333 | E12: ='Program Budget'!I16 -> 12 | F12: ='Program Budget'!H16 -> 0.1 | G12: =D12*E12*F12 -> 3400 | H12: =D12*1.05 -> 2975 | I12: ='Program Budget'!L16 -> 12 | J12: ='Program Budget'!K16 -> 0 | K12: =H12*I12*J12 -> 0 | L12: =H12*1.05 -> 3123.75 | M12: ='Program Budget'!O15 -> 12 | N12: ='Program Budget'!N16 -> 0 | O12: =L12*M12*N12 -> 0 | P12: =L12*1.05 -> 3279.9375 | Q12: ='Program Budget'!R16 -> 2 | R12: ='Program Budget'!Q16 -> 0 | S12: =P12*Q12*R12 -> 0 | T12: =C12+G12+K12+O12+S12 -> 3400
A13: ='Program Budget'!D17 -> Cacao Field Officer | B13: ='Program Budget'!F17 -> Month | C13: ='Program Budget'!E17 -> 0 | D13: ='Program Budget'!G17 -> 1333.3333 | E13: ='Program Budget'!I17 -> 12 | F13: ='Program Budget'!H17 -> 0 | G13: =D13*E13*F13 -> 0 | H13: =D13*1.05 -> 1400 | I13: ='Program Budget'!L17 -> 12 | J13: ='Program Budget'!K17 -> 0 | K13: =H13*I13*J13 -> 0 | L13: =H13*1.05 -> 1470 | M13: ='Program Budget'!O16 -> 12 | N13: ='Program Budget'!N17 -> 0 | O13: =L13*M13*N13 -> 0 | P13: =L13*1.05 -> 1543.5 | Q13: ='Program Budget'!R17 -> 0 | R13: ='Program Budget'!Q17 -> 0 | S13: =P13*Q13*R13 -> 0 | T13: =C13+G13+K13+O13+S13 -> 0
A14: ='Program Budget'!D18 -> Cacao & Complementary Crop Technical Field Leader (2) | B14: ='Program Budget'!F18 -> Month | C14: ='Program Budget'!E18 -> 0 | D14: ='Program Budget'!G18 -> 3500 | E14: ='Program Budget'!I18 -> 6 | F14: ='Program Budget'!H18 -> 0 | G14: =D14*E14*F14 -> 0 | H14: =D14*1.05 -> 3675 | I14: ='Program Budget'!L18 -> 12 | J14: ='Program Budget'!K18 -> 0 | K14: =H14*I14*J14 -> 0 | L14: =H14*1.05 -> 3858.75 | M14: ='Program Budget'!O17 -> 12 | N14: ='Program Budget'!N18 -> 0 | O14: =L14*M14*N14 -> 0 | P14: =L14*1.05 -> 4051.6875 | Q14: ='Program Budget'!R18 -> 0 | R14: ='Program Budget'!Q18 -> 0 | S14: =P14*Q14*R14 -> 0 | T14: =C14+G14+K14+O14+S14 -> 0
A15: ='Program Budget'!D19 -> Extension Agents (45 in Y5 and 25 in Y6) | B15: ='Program Budget'!F19 -> Month | C15: ='Program Budget'!E19 -> 0 | D15: ='Program Budget'!G19 -> 1000 | E15: ='Program Budget'!I19 -> 12 | F15: ='Program Budget'!H19 -> 0 | G15: =D15*E15*F15 -> 0 | H15: =D15*1.05 -> 1050 | I15: ='Program Budget'!L19 -> 12 | J15: ='Program Budget'!K19 -> 0 | K15: =H15*I15*J15 -> 0 | L15: =H15*1.05 -> 1102.5 | M15: ='Program Budget'!O18 -> 12 | N15: ='Program Budget'!N19 -> 0 | O15: =L15*M15*N15 -> 0 | P15: =L15*1.05 -> 1157.625 | Q15: ='Program Budget'!R19 -> 0 | R15: ='Program Budget'!Q19 -> 0 | S15: =P15*Q15*R15 -> 0 | T15: =C15+G15+K15+O15+S15 -> 0
A16: ='Program Budget'!D20 -> Activity Lead Agribusiness Senior Specialist (Complementary Crop) | B16: ='Program Budget'!F20 -> Month | C16: ='Program Budget'!E20 -> 0 | D16: ='Program Budget'!G20 -> 2833.3333 | E16: ='Program Budget'!I20 -> 12 | F16: ='Program Budget'!H20 -> 0 | G16: =D16*E16*F16 -> 0 | H16: =D16*1.05 -> 2975 | I16: ='Program Budget'!L20 -> 12 | J16: ='Program Budget'!K20 -> 0 | K16: =H16*I16*J16 -> 0 | L16: =H16*1.05 -> 3123.75 | M16: ='Program Budget'!O19 -> 0 | N16: ='Program Budget'!N20 -> 0 | O16: =L16*M16*N16 -> 0 | P16: =L16*1.05 -> 3279.9375 | Q16: ='Program Budget'!R20 -> 0 | R16: ='Program Budget'!Q20 -> 0 | S16: =P16*Q16*R16 -> 0 | T16: =C16+G16+K16+O16+S16 -> 0
A17: ='Program Budget'!D21 -> Complementary Crops Field Officer | B17: ='Program Budget'!F21 -> Month | C17: ='Program Budget'!E21 -> 0 | D17: ='Program Budget'!G21 -> 0 | E17: ='Program Budget'!I21 -> 0 | F17: ='Program Budget'!H21 -> 0 | G17: =D17*E17*F17 -> 0 | H17: =D17*1.05 -> 0 | I17: ='Program Budget'!L21 -> 12 | J17: ='Program Budget'!K21 -> 0 | K17: =H17*I17*J17 -> 0 | L17: =H17*1.05 -> 0 | M17: ='Program Budget'!O20 -> 12 | N17: ='Program Budget'!N21 -> 0 | O17: =L17*M17*N17 -> 0 | P17: =L17*1.05 -> 0 | Q17: ='Program Budget'!R21 -> 0 | R17: ='Program Budget'!Q21 -> 0 | S17: =P17*Q17*R17 -> 0 | T17: =C17+G17+K17+O17+S17 -> 0
A18: ='Program Budget'!D22 -> EPSEAS Specialist | B18: ='Program Budget'!F22 -> Month | C18: ='Program Budget'!E22 -> 0 | D18: ='Program Budget'!G22 -> 0 | E18: ='Program Budget'!I22 -> 0 | F18: ='Program Budget'!H22 -> 0 | G18: =D18*E18*F18 -> 0 | H18: =D18*1.05 -> 0 | I18: ='Program Budget'!L22 -> 12 | J18: ='Program Budget'!K22 -> 0 | K18: =H18*I18*J18 -> 0 | L18: =H18*1.05 -> 0 | M18: ='Program Budget'!O21 -> 12 | N18: ='Program Budget'!N22 -> 0 | O18: =L18*M18*N18 -> 0 | P18: =L18*1.05 -> 0 | Q18: ='Program Budget'!R22 -> 0 | R18: ='Program Budget'!Q22 -> 0 | S18: =P18*Q18*R18 -> 0 | T18: =C18+G18+K18+O18+S18 -> 0
A19: ='Program Budget'!D23 -> Extension Agents for EPSEAS (20 in Y6 and 25 in Y7) | B19: ='Program Budget'!F23 -> Month | C19: ='Program Budget'!E23 -> 0 | D19: ='Program Budget'!G23 -> 1000 | E19: ='Program Budget'!I23 -> 0 | F19: ='Program Budget'!H23 -> 0 | G19: =D19*E19*F19 -> 0 | H19: =D19*1.05 -> 1050 | I19: ='Program Budget'!L23 -> 12 | J19: ='Program Budget'!K23 -> 0 | K19: =H19*I19*J19 -> 0 | L19: =H19*1.05 -> 1102.5 | M19: ='Program Budget'!O22 -> 12 | N19: ='Program Budget'!N23 -> 0 | O19: =L19*M19*N19 -> 0 | P19: =L19*1.05 -> 1157.625 | Q19: ='Program Budget'!R23 -> 0 | R19: ='Program Budget'!Q23 -> 0 | S19: =P19*Q19*R19 -> 0 | T19: =C19+G19+K19+O19+S19 -> 0
A20: ='Program Budget'!D24 -> Senior M&E Director | B20: ='Program Budget'!F24 -> Month | C20: ='Program Budget'!E24 -> 28275.7 | D20: ='Program Budget'!G24 -> 6250 | E20: ='Program Budget'!I24 -> 12 | F20: ='Program Budget'!H24 -> 0.1 | G20: =D20*E20*F20 -> 7500 | H20: =D20*1.05 -> 6562.5 | I20: ='Program Budget'!L24 -> 12 | J20: ='Program Budget'!K24 -> 0.05 | K20: =H20*I20*J20 -> 3937.5 | L20: =H20*1.05 -> 6890.625 | M20: ='Program Budget'!O23 -> 12 | N20: ='Program Budget'!N24 -> 0.05 | O20: =L20*M20*N20 -> 4134.375 | P20: =L20*1.05 -> 7235.1562 | Q20: ='Program Budget'!R24 -> 6 | R20: ='Program Budget'!Q24 -> 0.05 | S20: =P20*Q20*R20 -> 2170.5469 | T20: =C20+G20+K20+O20+S20 -> 46018.122
A21: ='Program Budget'!D25 -> Senior M&E Specialist | B21: ='Program Budget'!F25 -> Month | C21: ='Program Budget'!E25 -> 24675.7 | D21: ='Program Budget'!G25 -> 2833.3333 | E21: ='Program Budget'!I25 -> 12 | F21: ='Program Budget'!H25 -> 0.1 | G21: =D21*E21*F21 -> 3400 | H21: =D21*1.05 -> 2975 | I21: ='Program Budget'!L25 -> 12 | J21: ='Program Budget'!K25 -> 0.05 | K21: =H21*I21*J21 -> 1785 | L21: =H21*1.05 -> 3123.75 | M21: ='Program Budget'!O24 -> 12 | N21: ='Program Budget'!N25 -> 0.05 | O21: =L21*M21*N21 -> 1874.25 | P21: =L21*1.05 -> 3279.9375 | Q21: ='Program Budget'!R25 -> 6 | R21: ='Program Budget'!Q25 -> 0.05 | S21: =P21*Q21*R21 -> 983.98125 | T21: =C21+G21+K21+O21+S21 -> 32718.931
A22: ='Program Budget'!D26 -> M&E Specialist | B22: ='Program Budget'!F26 -> Month | C22: ='Program Budget'!E26 -> 22491.26 | D22: ='Program Budget'!G26 -> 2500 | E22: ='Program Budget'!I26 -> 12 | F22: ='Program Budget'!H26 -> 0.1 | G22: =D22*E22*F22 -> 3000 | H22: =D22*1.05 -> 2625 | I22: ='Program Budget'!L26 -> 12 | J22: ='Program Budget'!K26 -> 0.05 | K22: =H22*I22*J22 -> 1575 | L22: =H22*1.05 -> 2756.25 | M22: ='Program Budget'!O25 -> 12 | N22: ='Program Budget'!N26 -> 0.05 | O22: =L22*M22*N22 -> 1653.75 | P22: =L22*1.05 -> 2894.0625 | Q22: ='Program Budget'!R26 -> 3 | R22: ='Program Budget'!Q26 -> 0.05 | S22: =P22*Q22*R22 -> 434.10938 | T22: =C22+G22+K22+O22+S22 -> 29154.119
... A29: ='Program Budget'!D33 -> Value Chain Specialist | B29: ='Program Budget'!F33 -> Month | C29: ='Program Budget'!E33 -> 0 | D29: ='Program Budget'!G33 -> 2500 | E29: ='Program Budget'!I33 -> 12 | F29: ='Program Budget'!H33 -> 0.1 | G29: =D29*E29*F29 -> 3000 | H29: =D29*1.05 -> 2625 | I29: ='Program Budget'!L33 -> 12 | J29: ='Program Budget'!K33 -> 0 | K29: =H29*I29*J29 -> 0 | L29: =H29*1.05 -> 2756.25 | M29: ='Program Budget'!O32 -> 12 | N29: ='Program Budget'!N33 -> 0 | O29: =L29*M29*N29 -> 0 | P29: =L29*1.05 -> 2894.0625 | Q29: ='Program Budget'!R33 -> 0 | R29: ='Program Budget'!Q33 -> 0 | S29: =P29*Q29*R29 -> 0 | T29: =C29+G29+K29+O29+S29 -> 3000
A30: ='Program Budget'!D34 -> Contracts & Compliance Director | B30: ='Program Budget'!F34 -> Month | C30: ='Program Budget'!E34 -> 29123.27 | D30: ='Program Budget'!G34 -> 4583.3333 | E30: ='Program Budget'!I34 -> 12 | F30: ='Program Budget'!H34 -> 0.1 | G30: =D30*E30*F30 -> 5500 | H30: =D30*1.05 -> 4812.5 | I30: ='Program Budget'!L34 -> 12 | J30: ='Program Budget'!K34 -> 0.1 | K30: =H30*I30*J30 -> 5775 | L30: =H30*1.05 -> 5053.125 | M30: ='Program Budget'!O33 -> 12 | N30: ='Program Budget'!N34 -> 0.1 | O30: =L30*M30*N30 -> 6063.75 | P30: =L30*1.05 -> 5305.7812 | Q30: ='Program Budget'!R34 -> 3 | R30: ='Program Budget'!Q34 -> 0.1 | S30: =P30*Q30*R30 -> 1591.7344 | T30: =C30+G30+K30+O30+S30 -> 48053.754 | AB30: 180 | AC30: 50-01-2-020 | AD30: DIR-USN (Expat) Labor
A31: ='Program Budget'!D35 -> Grants & Procurement Specialist (2) | B31: ='Program Budget'!F35 -> Month | C31: ='Program Budget'!E35 -> 0 | D31: ='Program Budget'!G35 -> 3500 | E31: ='Program Budget'!I35 -> 12 | F31: ='Program Budget'!H35 -> 0.05 | G31: =D31*E31*F31 -> 2100 | H31: =D31*1.05 -> 3675 | I31: ='Program Budget'!L35 -> 12 | J31: ='Program Budget'!K35 -> 0.1 | K31: =H31*I31*J31 -> 4410 | L31: =H31*1.05 -> 3858.75 | M31: ='Program Budget'!O34 -> 12 | N31: ='Program Budget'!N35 -> 0.1 | O31: =L31*M31*N31 -> 4630.5 | P31: =L31*1.05 -> 4051.6875 | Q31: ='Program Budget'!R35 -> 0 | R31: ='Program Budget'!Q35 -> 0.1 | S31: =P31*Q31*R31 -> 0 | T31: =C31+G31+K31+O31+S31 -> 11140.5 | AB31: 180 | AC31: 50-01-2-020 | AD31: DIR-USN (Expat) Labor
A32: ='Program Budget'!D36 -> F&A Director | B32: ='Program Budget'!F36 -> Month | C32: ='Program Budget'!E36 -> 170750.48 | D32: ='Program Budget'!G36 -> 5279.4 | E32: ='Program Budget'!I36 -> 12 | F32: ='Program Budget'!H36 -> 0.15 | G32: =D32*E32*F32 -> 9502.92 | H32: =D32*1.05 -> 5543.37 | I32: ='Program Budget'!L36 -> 12 | J32: ='Program Budget'!K36 -> 0.15 | K32: =H32*I32*J32 -> 9978.066 | L32: =H32*1.05 -> 5820.5385 | M32: ='Program Budget'!O35 -> 12 | N32: ='Program Budget'!N36 -> 0.15 | O32: =L32*M32*N32 -> 10476.969 | P32: =L32*1.05 -> 6111.5654 | Q32: ='Program Budget'!R36 -> 6 | R32: ='Program Budget'!Q36 -> 0.15 | S32: =P32*Q32*R32 -> 5500.4089 | T32: =C32+G32+K32+O32+S32 -> 206208.84 | AB32: 180 | AC32: 50-01-2-020 | AD32: DIR-USN (Expat) Labor
A33: ='Program Budget'!D37 -> Accounting & Finance Specialist | B33: ='Program Budget'!F37 -> Month | C33: ='Program Budget'!E37 -> 0 | D33: ='Program Budget'!G37 -> 1750 | E33: ='Program Budget'!I37 -> 12 | F33: ='Program Budget'!H37 -> 0.1 | G33: =D33*E33*F33 -> 2100 | H33: =D33*1.05 -> 1837.5 | I33: ='Program Budget'!L37 -> 12 | J33: ='Program Budget'!K37 -> 0.2 | K33: =H33*I33*J33 -> 4410 | L33: =H33*1.05 -> 1929.375 | M33: ='Program Budget'!O36 -> 12 | N33: ='Program Budget'!N37 -> 0.2 | O33: =L33*M33*N33 -> 4630.5 | P33: =L33*1.05 -> 2025.8438 | Q33: ='Program Budget'!R37 -> 3 | R33: ='Program Budget'!Q37 -> 0.2 | S33: =P33*Q33*R33 -> 1215.5063 | T33: =C33+G33+K33+O33+S33 -> 12356.006 | AB33: 180 | AC33: 50-01-2-020 | AD33: DIR-USN (Expat) Labor
A34: ='Program Budget'!D38 -> Accountant | B34: ='Program Budget'!F38 -> Month | C34: ='Program Budget'!E38 -> 57428.39 | D34: ='Program Budget'!G38 -> 1750 | E34: ='Program Budget'!I38 -> 12 | F34: ='Program Budget'!H38 -> 0.1 | G34: =D34*E34*F34 -> 2100 | H34: =D34*1.05 -> 1837.5 | I34: ='Program Budget'!L38 -> 12 | J34: ='Program Budget'!K38 -> 0.2 | K34: =H34*I34*J34 -> 4410 | L34: =H34*1.05 -> 1929.375 | M34: ='Program Budget'!O37 -> 12 | N34: ='Program Budget'!N38 -> 0.2 | O34: =L34*M34*N34 -> 4630.5 | P34: =L34*1.05 -> 2025.8438 | Q34: ='Program Budget'!R38 -> 5 | R34: ='Program Budget'!Q38 -> 0.2 | S34: =P34*Q34*R34 -> 2025.8438 | T34: =C34+G34+K34+O34+S34 -> 70594.734
A35: ='Program Budget'!D39 -> Finance & Admin Coordinator - 50% LOE | B35: ='Program Budget'!F39 -> Month | C35: ='Program Budget'!E39 -> 0 | D35: ='Program Budget'!G39 -> 2583.3333 | E35: ='Program Budget'!I39 -> 12 | F35: ='Program Budget'!H39 -> 0.1 | G35: =D35*E35*F35 -> 3100 | H35: =D35*1.05 -> 2712.5 | I35: ='Program Budget'!L39 -> 12 | J35: ='Program Budget'!K39 -> 0.1 | K35: =H35*I35*J35 -> 3255 | L35: =H35*1.05 -> 2848.125 | M35: ='Program Budget'!O38 -> 12 | N35: ='Program Budget'!N39 -> 0.1 | O35: =L35*M35*N35 -> 3417.75 | P35: =L35*1.05 -> 2990.5313 | Q35: ='Program Budget'!R39 -> 6 | R35: ='Program Budget'!Q39 -> 0.1 | S35: =P35*Q35*R35 -> 1794.3188 | T35: =C35+G35+K35+O35+S35 -> 11567.069
A36: ='Program Budget'!D40 -> Administrative Officer | B36: ='Program Budget'!F40 -> Month | C36: ='Program Budget'!E40 -> 31713.93 | D36: ='Program Budget'!G40 -> 1000 | E36: ='Program Budget'!I40 -> 12 | F36: ='Program Budget'!H40 -> 0.1 | G36: =D36*E36*F36 -> 1200 | H36: =D36*1.05 -> 1050 | I36: ='Program Budget'!L40 -> 12 | J36: ='Program Budget'!K40 -> 0.3 | K36: =H36*I36*J36 -> 3780 | L36: =H36*1.05 -> 1102.5 | M36: ='Program Budget'!O39 -> 12 | N36: ='Program Budget'!N40 -> 0.3 | O36: =L36*M36*N36 -> 3969 | P36: =L36*1.05 -> 1157.625 | Q36: ='Program Budget'!R40 -> 3 | R36: ='Program Budget'!Q40 -> 0.3 | S36: =P36*Q36*R36 -> 1041.8625 | T36: =C36+G36+K36+O36+S36 -> 41704.793
A37: ='Program Budget'!D41 -> Human Resource Manager | B37: ='Program Budget'!F41 -> Month | C37: ='Program Budget'!E41 -> 0 | D37: ='Program Budget'!G41 -> 1954.1667 | E37: ='Program Budget'!I41 -> 12 | F37: ='Program Budget'!H41 -> 0.1 | G37: =D37*E37*F37 -> 2345 | H37: =D37*1.05 -> 2051.875 | I37: ='Program Budget'!L41 -> 12 | J37: ='Program Budget'!K41 -> 0.3 | K37: =H37*I37*J37 -> 7386.75 | L37: =H37*1.05 -> 2154.4688 | M37: ='Program Budget'!O40 -> 12 | N37: ='Program Budget'!N41 -> 0.3 | O37: =L37*M37*N37 -> 7756.0875 | P37: =L37*1.05 -> 2262.1922 | Q37: ='Program Budget'!R41 -> 6 | R37: ='Program Budget'!Q41 -> 0.3 | S37: =P37*Q37*R37 -> 4071.9459 | T37: =C37+G37+K37+O37+S37 -> 21559.783 | AB37: 180 | AC37: 50-01-2-020 | AD37: DIR-USN (Expat) Labor
A38: ='Program Budget'!D42 -> Human Resource Specialist | B38: ='Program Budget'!F42 -> Month | C38: ='Program Budget'!E42 -> 0 | D38: ='Program Budget'!G42 -> 1750 | E38: ='Program Budget'!I42 -> 12 | F38: ='Program Budget'!H42 -> 0.1 | G38: =D38*E38*F38 -> 2100 | H38: =D38*1.05 -> 1837.5 | I38: ='Program Budget'!L42 -> 12 | J38: ='Program Budget'!K42 -> 0.3 | K38: =H38*I38*J38 -> 6615 | L38: =H38*1.05 -> 1929.375 | M38: ='Program Budget'!O41 -> 12 | N38: ='Program Budget'!N42 -> 0.3 | O38: =L38*M38*N38 -> 6945.75 | P38: =L38*1.05 -> 2025.8438 | Q38: ='Program Budget'!R42 -> 3 | R38: ='Program Budget'!Q42 -> 0.3 | S38: =P38*Q38*R38 -> 1823.2594 | T38: =C38+G38+K38+O38+S38 -> 17484.009 | AB38: 180 | AC38: 50-01-2-020 | AD38: DIR-USN (Expat) Labor
A39: Total Local Salary Cost | C39: =SUM(C10:C38) -> 431499.99 | G39: =SUM(G10:G38) -> 72097.92 | K39: =SUM(K10:K38) -> 81677.316 | O39: =SUM(O10:O38) -> 85761.182 | S39: =SUM(S10:S38) -> 32835.794 | T39: =C39+G39+K39+O39+S39 -> 703872.2
A40: HQ Staff
A41: ='Program Budget'!D44 -> Senior Program Director | B41: ='Program Budget'!F44 -> Month | C41: ='Program Budget'!E44 -> 105808.88 | D41: ='Program Budget'!G44 -> 12500 | E41: ='Program Budget'!I44 -> 12 | F41: ='Program Budget'!H44 -> 0.25 | G41: =D41*E41*F41 -> 37500 | H41: =D41*1.05 -> 13125 | I41: ='Program Budget'!L44 -> 12 | J41: ='Program Budget'!K44 -> 0.25 | K41: =H41*I41*J41 -> 39375 | L41: =H41*1.05 -> 13781.25 | M41: ='Program Budget'!O44 -> 12 | N41: ='Program Budget'!N44 -> 0.25 | O41: =L41*M41*N41 -> 41343.75 | P41: =L41*1.05 -> 14470.312 | Q41: ='Program Budget'!R44 -> 6 | R41: ='Program Budget'!Q44 -> 0.25 | S41: =P41*Q41*R41 -> 21705.469 | T41: =C41+G41+K41+O41+S41 -> 245733.1 | AB41: 180 | AC41: 50-01-2-020 | AD41: DIR-USN (Expat) Labor
A42: ='Program Budget'!D45 -> Associate Director | B42: ='Program Budget'!F45 -> Month | C42: ='Program Budget'!E45 -> 170702.65 | D42: ='Program Budget'!G45 -> 8333.3333 | E42: ='Program Budget'!I45 -> 12 | F42: ='Program Budget'!H45 -> 0.65 | G42: =D42*E42*F42 -> 65000 | H42: =D42*1.05 -> 8750 | I42: ='Program Budget'!L45 -> 12 | J42: ='Program Budget'!K45 -> 0.65 | K42: =H42*I42*J42 -> 68250 | L42: =H42*1.05 -> 9187.5 | M42: ='Program Budget'!O45 -> 12 | N42: ='Program Budget'!N45 -> 0.65 | O42: =L42*M42*N42 -> 71662.5 | P42: =L42*1.05 -> 9646.875 | Q42: ='Program Budget'!R45 -> 6 | R42: ='Program Budget'!Q45 -> 0.65 | S42: =P42*Q42*R42 -> 37622.813 | T42: =C42+G42+K42+O42+S42 -> 413237.96
A43: ='Program Budget'!D46 -> Senior Program Officer | B43: ='Program Budget'!F46 -> Month | C43: ='Program Budget'!E46 -> 0 | D43: ='Program Budget'!G46 -> 5833.3333 | E43: ='Program Budget'!I46 -> 12 | F43: ='Program Budget'!H46 -> 0.61 | G43: =D43*E43*F43 -> 42700 | H43: =D43*1.05 -> 6125 | I43: ='Program Budget'!L46 -> 12 | J43: ='Program Budget'!K46 -> 0.61 | K43: =H43*I43*J43 -> 44835 | L43: =H43*1.05 -> 6431.25 | M43: ='Program Budget'!O46 -> 12 | N43: ='Program Budget'!N46 -> 0.61 | O43: =L43*M43*N43 -> 47076.75 | P43: =L43*1.05 -> 6752.8125 | Q43: ='Program Budget'!R46 -> 6 | R43: ='Program Budget'!Q46 -> 0.61 | S43: =P43*Q43*R43 -> 24715.294 | T43: =C43+G43+K43+O43+S43 -> 159327.04 | AB43: 180 | AC43: 50-01-2-020 | AD43: DIR-USN (Expat) Labor
A44: Total HQ Staff | C44: =SUM(C41:C43) -> 276511.53 | G44: =SUM(G41:G43) -> 145200 | K44: =SUM(K41:K43) -> 152460 | O44: =SUM(O41:O43) -> 160083 | S44: =SUM(S41:S43) -> 84043.575 | T44: =+C44+G44+K44+O44+S44 -> 818298.1
A46: Subtotal: Salaries & Wages | C46: =C44+C39+C8 -> 933268.52 | G46: =G44+G39+G8 -> 234397.92 | K46: =K44+K39+K8 -> 243114.82 | O46: =O44+O39+O8 -> 255270.56 | S46: =S44+S39+S8 -> 116879.37 | T46: =+C46+G46+K46+O46+S46 -> 1782931.2
A47: Fringe
A48: USN/TCN Staff | B48: ='Program Budget'!F51 -> % | C48: ='Program Budget'!E55 -> 64022.09 | D48: =G8 -> 17100 | E48: 1 | F48: ='Program Budget'!G55 -> 0.5647 | G48: =D48*E48*F48 -> 9656.37 | H48: =K8 -> 8977.5 | I48: 1 | J48: =F48 -> 0.5647 | K48: =H48*I48*J48 -> 5069.5943 | L48: =O8 -> 9426.375 | M48: 1 | N48: =J48 -> 0.5647 | O48: =L48*M48*N48 -> 5323.074 | P48: =S8 -> 0 | Q48: 1 | R48: =N48 -> 0.5647 | S48: =P48*Q48*R48 -> 0 | T48: =C48+G48+K48+O48+S48 -> 84071.128 | AB48: 194 | AC48: 50-03-0-020 | AD48: DIR-Allocated USN Fringe
A49: CCN - Colombia (above $3,350 monthly) | B49: ='Program Budget'!F52 -> % | C49: ='Program Budget'!E51 -> 38320.45 | D49: =G10+G11+G20+G24+G27+G30+G32 -> 36752.92 | E49: 1 | F49: ='Program Budget'!G51 -> 0.53864 | G49: =D49*E49*F49 -> 19796.593 | H49: =K10+K11+K20+K24+K27+K30+K32 -> 41215.566 | I49: 1 | J49: =F49 -> 0.53864 | K49: =H49*I49*J49 -> 22200.352 | L49: =O10+O11+O20+O24+O27+O30+O32 -> 43276.344 | M49: 1 | N49: =J49 -> 0.53864 | O49: =L49*M49*N49 -> 23310.37 | P49: =S10+S11+S20+S24+S27+S30+S32 -> 19271.323 | Q49: 1 | R49: =N49 -> 0.53864 | S49: =P49*Q49*R49 -> 10380.305 | T49: =C49+G49+K49+O49+S49 -> 114008.07 | AB49: 197 | AC49: 50-03-0-050 | AD49: DIR-CCN Fringe
A50: CCN - Colombia (below $3,350 monthly) | B50: ='Program Budget'!F53 -> % | C50: ='Program Budget'!E52 -> 221449.96 | D50: =G39-D49 -> 35345 | E50: 1 | F50: ='Program Budget'!G52 -> 0.44864 | G50: =D50*E50*F50 -> 15857.181 | H50: =K39-H49 -> 40461.75 | I50: 1 | J50: =F50 -> 0.44864 | K50: =H50*I50*J50 -> 18152.76 | L50: =O39-L49 -> 42484.837 | M50: 1 | N50: =J50 -> 0.44864 | O50: =L50*M50*N50 -> 19060.397 | P50: =S39-P49 -> 13564.471 | Q50: 1 | R50: =N50 -> 0.44864 | S50: =P50*Q50*R50 -> 6085.5642 | T50: =C50+G50+K50+O50+S50 -> 280605.86
A51: HQ Staff | B51: ='Program Budget'!F53 -> % | C51: ='Program Budget'!E53 -> 99333.38 | D51: =G44 -> 145200 | E51: 1 | F51: ='Program Budget'!G53 -> 0.2347 | G51: =D51*E51*F51 -> 34078.44 | H51: =K44 -> 152460 | I51: 1 | J51: =F51 -> 0.2347 | K51: =H51*I51*J51 -> 35782.362 | L51: =O44 -> 160083 | M51: 1 | N51: =J51 -> 0.2347 | O51: =L51*M51*N51 -> 37571.48 | P51: =S44 -> 84043.575 | Q51: 1 | R51: =N51 -> 0.2347 | S51: =P51*Q51*R51 -> 19725.027 | T51: =C51+G51+K51+O51+S51 -> 226490.69 | AB51: 193 | AC51: 50-03-0-010 | AD51: DIR-Allocated HQ Fringe
A52: Total: Fringe Benefits | C52: =+SUM(C48:C51) -> 423125.88 | G52: =+SUM(G48:G51) -> 79388.584 | K52: =+SUM(K48:K51) -> 81205.068 | O52: =+SUM(O48:O51) -> 85265.322 | S52: =+SUM(S48:S51) -> 36190.897 | T52: =+C52+G52+K52+O52+S52 -> 705175.75
A53: Allowances
A54: USN/TCN Staff | AB54: 202 | AC54: 50-04-8-003 | AD54: DIR-COLA
A55: ='Program Budget'!D54 -> Post (Hardship) Differential for Chief of Party | B55: ='Program Budget'!F54 -> % | C55: ='Program Budget'!E54 -> 59486.73 | D55: =G8 -> 17100 | E55: 1 | F55: ='Program Budget'!G54 -> 0.15 | G55: =D55*E55*F55 -> 2565 | H55: =K8 -> 8977.5 | I55: 1 | J55: =F55 -> 0.15 | K55: =H55*I55*J55 -> 1346.625 | L55: =O8 -> 9426.375 | M55: 1 | N55: =J55 -> 0.15 | O55: =L55*M55*N55 -> 1413.9562 | P55: =S8 -> 0 | Q55: 1 | R55: =N55 -> 0.15 | S55: =P55*Q55*R55 -> 0 | T55: =C55+G55+K55+O55+S55 -> 64812.311
A56: ='Program Budget'!D56 -> Housing Allowance for Chief of Party | B56: ='Program Budget'!F56 -> Month | C56: ='Program Budget'!E56 -> 68428.33 | D56: ='Program Budget'!G56 -> 3000 | E56: ='Program Budget'!I56 -> 12 | F56: 1 | G56: =D56*E56*F56 -> 36000 | H56: =D56*1.04 -> 3120 | I56: ='Program Budget'!L56 -> 12 | J56: =F56 -> 1 | K56: =H56*I56*J56 -> 37440 | L56: =H56*1.04 -> 3244.8 | M56: ='Program Budget'!O56 -> 12 | N56: =J56 -> 1 | O56: =L56*M56*N56 -> 38937.6 | P56: =L56*1.04 -> 3374.592 | Q56: ='Program Budget'!R56 -> 0 | R56: =N56 -> 1 | S56: =P56*Q56*R56 -> 0 | T56: =C56+G56+K56+O56+S56 -> 180805.93
A57: ='Program Budget'!D57 -> Reallocation & Demobilization Allowance for Chief of Party | B57: ='Program Budget'!F57 -> Year | C57: ='Program Budget'!E57 -> 1565.26 | D57: ='Program Budget'!G57 -> 2583.93 | E57: ='Program Budget'!I57 -> 0 | F57: 0 | G57: =D57*E57*F57 -> 0 | H57: =D57*1.04 -> 2687.2872 | I57: ='Program Budget'!L57 -> 0 | J57: 0 | K57: =H57*I57*J57 -> 0 | L57: =H57*1.04 -> 2794.7787 | M57: ='Program Budget'!O57 -> 1 | N57: 1 | O57: =L57*M57*N57 -> 2794.7787 | P57: =L57*1.04 -> 2906.5698 | Q57: ='Program Budget'!R57 -> 0 | R57: 0 | S57: =P57*Q57*R57 -> 0 | T57: =C57+G57+K57+O57+S57 -> 4360.0387
A58: ='Program Budget'!D58 -> Annual Home of Record for Chief of Party | B58: ='Program Budget'!F58 -> Year | C58: ='Program Budget'!E58 -> 1357.75 | D58: ='Program Budget'!G58 -> 1100 | E58: ='Program Budget'!I58 -> 1 | F58: 1 | G58: =D58*E58*F58 -> 1100 | H58: =D58*1.04 -> 1144 | I58: ='Program Budget'!L58 -> 1 | J58: =F58 -> 1 | K58: =H58*I58*J58 -> 1144 | L58: =H58*1.04 -> 1189.76 | M58: ='Program Budget'!O58 -> 1 | N58: =J58 -> 1 | O58: =L58*M58*N58 -> 1189.76 | P58: =L58*1.04 -> 1237.3504 | Q58: ='Program Budget'!R58 -> 1 | R58: 1 | S58: =P58*Q58*R58 -> 1237.3504 | T58: =C58+G58+K58+O58+S58 -> 6028.8604
A59: Total: Allowances | C59: =SUM(C54:C58) -> 130838.07 | G59: =SUM(G54:G58) -> 39665 | K59: =SUM(K54:K58) -> 39930.625 | O59: =SUM(O54:O58) -> 44336.095 | S59: =SUM(S54:S58) -> 1237.3504 | T59: =C59+G59+K59+O59+S59 -> 256007.14
A61: Subtotal: Benefits | C61: =C59+C52 -> 553963.95 | G61: =G59+G52 -> 119053.58 | K61: =K59+K52 -> 121135.69 | O61: =O59+O52 -> 129601.42 | S61: =S59+S52 -> 37428.247 | T61: =+C61+G61+K61+O61+S61 -> 961182.89 | AB61: 287 | AC61: 51-04-2-050 | AD61: DIR-Int Travel Other
A62: International Travel
A63: ='Program Budget'!D64 -> Airfare - DC-Colombia - HQ Project Management Trip | B63: ='Program Budget'!F64 -> Trip | C63: ='Program Budget'!E64 -> 12141.75 | D63: ='Program Budget'!G64 -> 800 | E63: ='Program Budget'!I64 -> 4 | F63: 1 | G63: =D63*E63*F63 -> 3200 | H63: =D63*1.04 -> 832 | I63: ='Program Budget'!L64 -> 4 | J63: 1 | K63: =H63*I63*J63 -> 3328 | L63: =H63*1.04 -> 865.28 | M63: ='Program Budget'!O64 -> 4 | N63: 1 | O63: =L63*M63*N63 -> 3461.12 | P63: =L63*1.04 -> 899.8912 | Q63: ='Program Budget'!R64 -> 4 | R63: 1 | S63: =P63*Q63*R63 -> 3599.5648 | T63: =C63+G63+K63+O63+S63 -> 25730.435 | AB63: 180 | AC63: 50-01-2-020 | AD63: DIR-USN (Expat) Labor
A64: ='Program Budget'!D69 -> Airfare - Roundtrip - Colombia to USA | B64: ='Program Budget'!F69 -> Trip | C64: ='Program Budget'!E69 -> 8640.56 | D64: ='Program Budget'!G69 -> 800 | E64: ='Program Budget'!I69 -> 4 | F64: 1 | G64: =D64*E64*F64 -> 3200 | H64: =D64*1.03 -> 824 | I64: ='Program Budget'!L69 -> 4 | J64: 1 | K64: =H64*I64*J64 -> 3296 | L64: =H64*1.03 -> 848.72 | M64: ='Program Budget'!O69 -> 4 | N64: 1 | O64: =L64*M64*N64 -> 3394.88 | P64: =L64*1.03 -> 874.1816 | Q64: ='Program Budget'!R69 -> 4 | R64: 1 | S64: =P64*Q64*R64 -> 3496.7264 | T64: =C64+G64+K64+O64+S64 -> 22028.166 | AB64: 180 | AC64: 50-01-2-020 | AD64: DIR-USN (Expat) Labor
A65: Local Travel
A66: ='Program Budget'!D66 -> Local Transportation – HQ Project Management Trip | B66: ='Program Budget'!F66 -> Trip | C66: ='Program Budget'!E66 -> 1104.45 | D66: ='Program Budget'!G66 -> 100 | E66: ='Program Budget'!I66 -> 4 | F66: 1 | G66: =D66*E66*F66 -> 400 | H66: =D66*1.04 -> 104 | I66: ='Program Budget'!L66 -> 4 | J66: 1 | K66: =H66*I66*J66 -> 416 | L66: =H66*1.04 -> 108.16 | M66: ='Program Budget'!O66 -> 4 | N66: 1 | O66: =L66*M66*N66 -> 432.64 | P66: =L66*1.04 -> 112.4864 | Q66: ='Program Budget'!R66 -> 4 | R66: 1 | S66: =P66*Q66*R66 -> 449.9456 | T66: =C66+G66+K66+O66+S66 -> 2803.0356 | AB66: 180 | AC66: 50-01-2-020 | AD66: DIR-USN (Expat) Labor
A67: ='Program Budget'!D71 -> Local Transportation for Colombia Staff Travel | B67: ='Program Budget'!F75 -> Trip | C67: ='Program Budget'!E71 -> 895.05 | D67: ='Program Budget'!G71 -> 100 | E67: ='Program Budget'!I71 -> 4 | F67: 1 | G67: =D67*E67*F67 -> 400 | H67: =D67*1.03 -> 103 | I67: ='Program Budget'!L71 -> 4 | J67: 1 | K67: =H67*I67*J67 -> 412 | L67: =H67*1.03 -> 106.09 | M67: ='Program Budget'!O71 -> 4 | N67: 1 | O67: =L67*M67*N67 -> 424.36 | P67: =L67*1.03 -> 109.2727 | Q67: ='Program Budget'!R71 -> 4 | R67: 1 | S67: =P67*Q67*R67 -> 437.0908 | T67: =C67+G67+K67+O67+S67 -> 2568.5008 | AB67: 180 | AC67: 50-01-2-020 | AD67: DIR-USN (Expat) Labor
A68: ='Program Budget'!D75 -> Local Transportation – Training, M&E, & Data Collection | B68: ='Program Budget'!F75 -> Trip | C68: ='Program Budget'!E75 -> 32433.77 | D68: ='Program Budget'!G75 -> 100 | E68: ='Program Budget'!I75 -> 36 | F68: 1 | G68: =D68*E68*F68 -> 3600 | H68: =D68*1.04 -> 104 | I68: ='Program Budget'!L75 -> 36 | J68: 1 | K68: =H68*I68*J68 -> 3744 | L68: =H68*1.04 -> 108.16 | M68: ='Program Budget'!O75 -> 36 | N68: 1 | O68: =L68*M68*N68 -> 3893.76 | P68: =L68*1.04 -> 112.4864 | Q68: ='Program Budget'!R75 -> 9 | R68: 1 | S68: =P68*Q68*R68 -> 1012.3776 | T68: =C68+G68+K68+O68+S68 -> 44683.908 | AB68: 180 | AC68: 50-01-2-020 | AD68: DIR-USN (Expat) Labor
A69: Vehicle Fuel
A70: ='Program Budget'!D74 -> Vehicle/Motorcycle Fuel Expense | B70: ='Program Budget'!F74 -> Month | C70: ='Program Budget'!E74 -> 9640.86 | D70: ='Program Budget'!G74 -> 200 | E70: ='Program Budget'!I74 -> 12 | F70: 1 | G70: =D70*E70*F70 -> 2400 | H70: =D70*1.04 -> 208 | I70: ='Program Budget'!L74 -> 12 | J70: 1 | K70: =H70*I70*J70 -> 2496 | L70: =H70*1.04 -> 216.32 | M70: ='Program Budget'!O74 -> 12 | N70: 1 | O70: =L70*M70*N70 -> 2595.84 | P70: =L70*1.04 -> 224.9728 | Q70: ='Program Budget'!R74 -> 3 | R70: 1 | S70: =P70*Q70*R70 -> 674.9184 | T70: =C70+G70+K70+O70+S70 -> 17807.618 | AB70: 180 | AC70: 50-01-2-020 | AD70: DIR-USN (Expat) Labor
A71: Per Diem
A72: ='Program Budget'!D65 -> Lodging and M&IE - HQ Project Management Trip | B72: ='Program Budget'!F65 -> Day | C72: ='Program Budget'!E65 -> 13828.71 | D72: ='Program Budget'!G65 -> 286 | E72: ='Program Budget'!I65 -> 20 | F72: 1 | G72: =D72*E72*F72 -> 5720 | H72: =D72*1.04 -> 297.44 | I72: ='Program Budget'!L65 -> 20 | J72: 1 | K72: =H72*I72*J72 -> 5948.8 | L72: =H72*1.04 -> 309.3376 | M72: ='Program Budget'!O65 -> 20 | N72: 1 | O72: =L72*M72*N72 -> 6186.752 | P72: =L72*1.04 -> 321.7111 | Q72: ='Program Budget'!R65 -> 20 | R72: 1 | S72: =P72*Q72*R72 -> 6434.2221 | T72: =C72+G72+K72+O72+S72 -> 38118.484 | AB72: 180 | AC72: 50-01-2-020 | AD72: DIR-USN (Expat) Labor
A73: ='Program Budget'!D67 -> Other Travel Related Expenses – HQ Project Management Trip | B73: ='Program Budget'!F67 -> Trip | C73: ='Program Budget'!E67 -> 118.18 | D73: ='Program Budget'!G67 -> 25 | E73: ='Program Budget'!I67 -> 4 | F73: 1 | G73: =D73*E73*F73 -> 100 | H73: =D73*1.04 -> 26 | I73: ='Program Budget'!L67 -> 4 | J73: 1 | K73: =H73*I73*J73 -> 104 | L73: =H73*1.04 -> 27.04 | M73: ='Program Budget'!O67 -> 4 | N73: 1 | O73: =L73*M73*N73 -> 108.16 | P73: =L73*1.04 -> 28.1216 | Q73: ='Program Budget'!R67 -> 4 | R73: 1 | S73: =P73*Q73*R73 -> 112.4864 | T73: =C73+G73+K73+O73+S73 -> 542.8264 | AB73: 180 | AC73: 50-01-2-020 | AD73: DIR-USN (Expat) Labor
A74: ='Program Budget'!D70 -> Lodging and M&IE for Colombia Staff Travel | B74: ='Program Budget'!F70 -> Day | C74: ='Program Budget'!E70 -> 8160.39 | D74: ='Program Budget'!G70 -> 260 | E74: ='Program Budget'!I70 -> 40 | F74: 1 | G74: =D74*E74*F74 -> 10400 | H74: =D74*1.03 -> 267.8 | I74: ='Program Budget'!L70 -> 40 | J74: 1 | K74: =H74*I74*J74 -> 10712 | L74: =H74*1.03 -> 275.834 | M74: ='Program Budget'!O70 -> 40 | N74: 1 | O74: =L74*M74*N74 -> 11033.36 | P74: =L74*1.03 -> 284.10902 | Q74: ='Program Budget'!R70 -> 40 | R74: 1 | S74: =P74*Q74*R74 -> 11364.361 | T74: =C74+G74+K74+O74+S74 -> 51670.111 | AB74: 180 | AC74: 50-01-2-020 | AD74: DIR-USN (Expat) Labor
A75: ='Program Budget'!D72 -> Other Travel Related Expenses for Colombia Staff Travel | B75: ='Program Budget'!F72 -> Trip | C75: ='Program Budget'!E72 -> 374.49 | D75: ='Program Budget'!G72 -> 25 | E75: ='Program Budget'!I72 -> 4 | F75: 1 | G75: =D75*E75*F75 -> 100 | H75: =D75*1.03 -> 25.75 | I75: ='Program Budget'!L72 -> 4 | J75: 1 | K75: =H75*I75*J75 -> 103 | L75: =H75*1.03 -> 26.5225 | M75: ='Program Budget'!O72 -> 4 | N75: 1 | O75: =L75*M75*N75 -> 106.09 | P75: =L75*1.03 -> 27.318175 | Q75: ='Program Budget'!R72 -> 4 | R75: 1 | S75: =P75*Q75*R75 -> 109.2727 | T75: =C75+G75+K75+O75+S75 -> 792.8527 | AB75: 180 | AC75: 50-01-2-020 | AD75: DIR-USN (Expat) Labor
A76: ='Program Budget'!D76 -> Lodging and M&IE - Training, M&E, & Data Collection | B76: ='Program Budget'!F76 -> Day | C76: ='Program Budget'!E76 -> 14326.42 | D76: ='Program Budget'!G76 -> 157 | E76: ='Program Budget'!I76 -> 144 | F76: 1 | G76: =D76*E76*F76 -> 22608 | H76: =D76*1.04 -> 163.28 | I76: ='Program Budget'!L76 -> 144 | J76: 1 | K76: =H76*I76*J76 -> 23512.32 | L76: =H76*1.04 -> 169.8112 | M76: ='Program Budget'!O76 -> 144 | N76: 1 | O76: =L76*M76*N76 -> 24452.813 | P76: =L76*1.04 -> 176.60365 | Q76: ='Program Budget'!R76 -> 36 | R76: 1 | S76: =P76*Q76*R76 -> 6357.7313 | T76: =C76+G76+K76+O76+S76 -> 91257.284 | AB76: 180 | AC76: 50-01-2-020 | AD76: DIR-USN (Expat) Labor
A78: Subtotal: Travel | C78: =SUM(C62:C77) -> 101664.63 | G78: =SUM(G62:G77) -> 52128 | K78: =SUM(K62:K77) -> 54072.12 | O78: =SUM(O62:O77) -> 56089.775 | S78: =SUM(S62:S77) -> 34048.697 | T78: =+C78+G78+K78+O78+S78 -> 298003.22
A79: Professional Services
A80: ='Program Budget'!D80 -> Payroll, Accounting and Audit Costs - (Auditoria Fiscal & Program Specific Audits) | B80: ='Program Budget'!F80 -> Year | C80: ='Program Budget'!E80 -> 26306.36 | D80: ='Program Budget'!G80 -> 13000 | E80: ='Program Budget'!I80 -> 1 | F80: 1 | G80: =D80*E80*F80 -> 13000 | H80: =D80 -> 13000 | I80: ='Program Budget'!L80 -> 1 | J80: 1 | K80: =H80*I80*J80 -> 13000 | L80: =H80 -> 13000 | M80: ='Program Budget'!O80 -> 1 | N80: 1 | O80: =L80*M80*N80 -> 13000 | P80: =L80 -> 13000 | Q80: ='Program Budget'!R80 -> 0.5 | R80: 1 | S80: =P80*Q80*R80 -> 6500 | T80: =C80+G80+K80+O80+S80 -> 71806.36
A81: ='Program Budget'!D81 -> Legal Fees | B81: ='Program Budget'!F81 -> Year | C81: ='Program Budget'!E81 -> 22150.08 | D81: ='Program Budget'!G81 -> 4425 | E81: ='Program Budget'!I81 -> 1 | F81: 1 | G81: =D81*E81*F81 -> 4425 | H81: =D81 -> 4425 | I81: ='Program Budget'!L81 -> 1 | J81: 1 | K81: =H81*I81*J81 -> 4425 | L81: =H81 -> 4425 | M81: ='Program Budget'!O81 -> 1 | N81: 1 | O81: =L81*M81*N81 -> 4425 | P81: =L81 -> 4425 | Q81: ='Program Budget'!R81 -> 1 | R81: 1 | S81: =P81*Q81*R81 -> 4425 | T81: =C81+G81+K81+O81+S81 -> 39850.08
A82: ='Program Budget'!D82 -> Monetization Agent Fee | B82: ='Program Budget'!F82 -> % | C82: ='Program Budget'!E82 -> 512975 | D82: 9000000 | E82: ='Program Budget'!I82 -> 1 | F82: 0.025 | G82: =D82*E82*F82 -> 225000 | H82: 0 | I82: ='Program Budget'!L82 -> 0 | J82: 0 | K82: =H82*I82*J82 -> 0 | L82: =H82 -> 0 | M82: ='Program Budget'!O82 -> 0 | N82: 0 | O82: =L82*M82*N82 -> 0 | P82: =L82 -> 0 | Q82: ='Program Budget'!R82 -> 0 | R82: 0 | S82: =P82*Q82*R82 -> 0 | T82: =C82+G82+K82+O82+S82 -> 737975
A83: ='Program Budget'!D83 -> Post Monetization Assessment | B83: ='Program Budget'!F83 -> Unit | C83: ='Program Budget'!E83 -> 47918.55 | D83: ='Program Budget'!G83 -> 47918.55 | E83: ='Program Budget'!I83 -> 0 | F83: 0 | G83: =D83*E83*F83 -> 0 | H83: =D83 -> 47918.55 | I83: ='Program Budget'!L83 -> 0 | J83: 0 | K83: =H83*I83*J83 -> 0 | L83: =H83 -> 47918.55 | M83: ='Program Budget'!O83 -> 0 | N83: 0 | O83: =L83*M83*N83 -> 0 | P83: =L83 -> 47918.55 | Q83: ='Program Budget'!R83 -> 0 | R83: 0 | S83: =P83*Q83*R83 -> 0 | T83: =C83+G83+K83+O83+S83 -> 47918.55
A84: ='Program Budget'!D84 -> Security Plan and Advisors | B84: ='Program Budget'!F84 -> Year | C84: ='Program Budget'!E84 -> 0 | D84: ='Program Budget'!G84 -> 25000 | E84: ='Program Budget'!I84 -> 1 | F84: 1 | G84: =D84*E84*F84 -> 25000 | H84: =D84 -> 25000 | I84: ='Program Budget'!L84 -> 1 | J84: 1 | K84: =H84*I84*J84 -> 25000 | L84: =H84 -> 25000 | M84: ='Program Budget'!O84 -> 1 | N84: 1 | O84: =L84*M84*N84 -> 25000 | P84: =L84 -> 25000 | Q84: ='Program Budget'!R84 -> 0.5 | R84: 1 | S84: =P84*Q84*R84 -> 12500 | T84: =C84+G84+K84+O84+S84 -> 87500
A85: ='Program Budget'!D85 -> HQ Consultants & Advisory Support Services | B85: ='Program Budget'!F85 -> Month | C85: ='Program Budget'!E85 -> 68599.1 | D85: ='Program Budget'!G85 -> 1125 | E85: ='Program Budget'!I85 -> 12 | F85: 1 | G85: =D85*E85*F85 -> 13500 | H85: =D85 -> 1125 | I85: ='Program Budget'!L85 -> 12 | J85: 1 | K85: =H85*I85*J85 -> 13500 | L85: =H85 -> 1125 | M85: ='Program Budget'!O85 -> 12 | N85: 1 | O85: =L85*M85*N85 -> 13500 | P85: =L85 -> 1125 | Q85: ='Program Budget'!R85 -> 6 | R85: 1 | S85: =P85*Q85*R85 -> 6750 | T85: =C85+G85+K85+O85+S85 -> 115849.1 | AB85: 670 | AC85: 61-01-1-003 | AD85: DIR_Sub-AW (No Fee)
A86: Evaluations
A87: ='Program Budget'!D88 -> Baseline Evaluation | B87: ='Program Budget'!F88 -> Unit | C87: ='Program Budget'!E88 -> 151977.65 | D87: ='Program Budget'!G88 -> 151977.65 | E87: ='Program Budget'!I88 -> 0 | F87: 0 | G87: =D87*E87*F87 -> 0 | H87: =D87 -> 151977.65 | I87: ='Program Budget'!L88 -> 0 | J87: 0 | K87: =H87*I87*J87 -> 0 | L87: =H87 -> 151977.65 | M87: ='Program Budget'!O88 -> 0 | N87: 0 | O87: =L87*M87*N87 -> 0 | P87: =L87 -> 151977.65 | Q87: ='Program Budget'!R88 -> 0 | R87: 0 | S87: =P87*Q87*R87 -> 0 | T87: =C87+G87+K87+O87+S87 -> 151977.65
A88: ='Program Budget'!D89 -> Midterm Evaluation | B88: ='Program Budget'!F89 -> Unit | C88: ='Program Budget'!E89 -> 18463 | D88: ='Program Budget'!G89 -> 166537 | E88: ='Program Budget'!I89 -> 1 | F88: 1 | G88: =D88*E88*F88 -> 166537 | H88: =D88 -> 166537 | I88: ='Program Budget'!L89 -> 0 | J88: 0 | K88: =H88*I88*J88 -> 0 | L88: =H88 -> 166537 | M88: ='Program Budget'!O89 -> 0 | N88: 0 | O88: =L88*M88*N88 -> 0 | P88: =L88 -> 166537 | Q88: ='Program Budget'!R89 -> 0 | R88: 0 | S88: =P88*Q88*R88 -> 0 | T88: =C88+G88+K88+O88+S88 -> 185000
A89: ='Program Budget'!D90 -> Final Evaluation | B89: ='Program Budget'!F90 -> Unit | C89: ='Program Budget'!E90 -> 0 | D89: ='Program Budget'!G90 -> 225000 | E89: ='Program Budget'!I90 -> 0 | F89: 0 | G89: =D89*E89*F89 -> 0 | H89: =D89 -> 225000 | I89: ='Program Budget'!L90 -> 0 | J89: 0 | K89: =H89*I89*J89 -> 0 | L89: =H89 -> 225000 | M89: ='Program Budget'!O90 -> 0 | N89: 0 | O89: =L89*M89*N89 -> 0 | P89: =L89 -> 225000 | Q89: ='Program Budget'!R90 -> 1 | R89: 1 | S89: =P89*Q89*R89 -> 225000 | T89: =C89+G89+K89+O89+S89 -> 225000
A90: ='Program Budget'!D91 -> Value Chain Analysis, Carbon Assessment, and Living Incomes | B90: ='Program Budget'!F91 -> Subrecipient | C90: ='Program Budget'!E91 -> 542898.59 | D90: ='Program Budget'!J91 -> 31587 | E90: ='Program Budget'!I91 -> 1 | F90: 1 | G90: 31587 | H90: ='Program Budget'!M91 -> 0 | I90: ='Program Budget'!L91 -> 0 | J90: 0 | K90: =H90*I90*J90 -> 0 | L90: ='Program Budget'!P91 -> 43803.95 | M90: ='Program Budget'!O91 -> 1 | N90: 1 | O90: 44000 | P90: ='Program Budget'!S91 -> 0 | Q90: ='Program Budget'!R91 -> 0 | R90: 0 | S90: =P90*Q90*R90 -> 0 | T90: =C90+G90+K90+O90+S90 -> 618485.59
A91: Monitoring Guidelines Development
A92: ='Program Budget'!D93 -> Monitoring Guidelines Creation, Translation & Printing | B92: ='Program Budget'!F93 -> Document | C92: ='Program Budget'!E93 -> 0 | D92: ='Program Budget'!G93 -> 6000 | E92: ='Program Budget'!I93 -> 1 | F92: 1 | G92: =D92*E92*F92 -> 6000 | H92: =D92 -> 6000 | I92: ='Program Budget'!L93 -> 0 | J92: 0 | K92: =H92*I92*J92 -> 0 | L92: =H92 -> 6000 | M92: ='Program Budget'!O93 -> 0 | N92: 0 | O92: =L92*M92*N92 -> 0 | P92: =L92 -> 6000 | Q92: ='Program Budget'!R93 -> 0 | R92: 0 | S92: =P92*Q92*R92 -> 0 | T92: =C92+G92+K92+O92+S92 -> 6000
A93: ='Program Budget'!D94 -> Monitoring Guidelines Staff Training Workshop | B93: ='Program Budget'!F94 -> Workshop | C93: ='Program Budget'!E94 -> 63.84 | D93: ='Program Budget'!G94 -> 6800 | E93: ='Program Budget'!I94 -> 1 | F93: 1 | G93: =D93*E93*F93 -> 6800 | H93: =D93 -> 6800 | I93: ='Program Budget'!L94 -> 1 | J93: 1 | K93: =H93*I93*J93 -> 6800 | L93: =H93 -> 6800 | M93: ='Program Budget'!O94 -> 1 | N93: 1 | O93: =L93*M93*N93 -> 6800 | P93: =L93 -> 6800 | Q93: ='Program Budget'!R94 -> 0 | R93: 0 | S93: =P93*Q93*R93 -> 0 | T93: =C93+G93+K93+O93+S93 -> 20463.84
A94: M&E Database
A95: ='Program Budget'!D96 -> M&E Software Setup | B95: ='Program Budget'!F96 -> Year | C95: ='Program Budget'!E96 -> 33269.83 | D95: ='Program Budget'!G96 -> 33269.83 | E95: ='Program Budget'!I96 -> 0 | F95: 0 | G95: =D95*E95*F95 -> 0 | H95: =D95 -> 33269.83 | I95: ='Program Budget'!L96 -> 0 | J95: 0 | K95: =H95*I95*J95 -> 0 | L95: =H95 -> 33269.83 | M95: ='Program Budget'!O96 -> 0 | N95: 0 | O95: =L95*M95*N95 -> 0 | P95: =L95 -> 33269.83 | Q95: ='Program Budget'!R96 -> 0 | R95: 0 | S95: =P95*Q95*R95 -> 0 | T95: =C95+G95+K95+O95+S95 -> 33269.83
A96: ='Program Budget'!D97 -> M&E Software Fee (Annual) | B96: ='Program Budget'!F97 -> Year | C96: ='Program Budget'!E97 -> 44624.18 | D96: ='Program Budget'!G97 -> 10000 | E96: ='Program Budget'!I97 -> 1 | F96: 1 | G96: =D96*E96*F96 -> 10000 | H96: =D96 -> 10000 | I96: ='Program Budget'!L97 -> 1 | J96: 1 | K96: =H96*I96*J96 -> 10000 | L96: =H96 -> 10000 | M96: ='Program Budget'!O97 -> 1 | N96: 1 | O96: =L96*M96*N96 -> 10000 | P96: =L96 -> 10000 | Q96: ='Program Budget'!R97 -> 1 | R96: 1 | S96: =P96*Q96*R96 -> 10000 | T96: =C96+G96+K96+O96+S96 -> 84624.18
A97: ='Program Budget'!D98 -> M&E Software Training | B97: ='Program Budget'!F98 -> Year | C97: ='Program Budget'!E98 -> 0 | D97: ='Program Budget'!G98 -> 0 | E97: ='Program Budget'!I98 -> 1 | F97: 1 | G97: =D97*E97*F97 -> 0 | H97: =D97 -> 0 | I97: ='Program Budget'!L98 -> 0 | J97: 0 | K97: =H97*I97*J97 -> 0 | L97: =H97 -> 0 | M97: ='Program Budget'!O98 -> 0 | N97: 0 | O97: =L97*M97*N97 -> 0 | P97: =L97 -> 0 | Q97: ='Program Budget'!R98 -> 0 | R97: 0 | S97: =P97*Q97*R97 -> 0 | T97: =C97+G97+K97+O97+S97 -> 0
AB98: 319 | AC98: 51-08-1-004 | AD98: DIR-Office Utilities
A99: Subtotal: Professional Services/Contractual | C99: =SUM(C80:C98) -> 1469246.2 | G99: =SUM(G80:G98) -> 501849 | K99: =SUM(K80:K98) -> 72725 | O99: =SUM(O80:O98) -> 116725 | S99: =SUM(S80:S98) -> 265175 | T99: =+C99+G99+K99+O99+S99 -> 2425720.2
A100: Equipment (>$5000/unit)
A101: ='Program Budget'!D104 -> Vehicles for Field Office | B101: ='Program Budget'!F104 -> Unit | C101: ='Program Budget'!E104 -> 72554.43 | D101: ='Program Budget'!G104 -> 72554.43 | E101: ='Program Budget'!I104 -> 0 | F101: 0 | G101: =D101*E101*F101 -> 0 | H101: =D101 -> 72554.43 | I101: ='Program Budget'!L104 -> 0 | J101: 0 | K101: =H101*I101*J101 -> 0 | L101: =H101 -> 72554.43 | M101: ='Program Budget'!O104 -> 0 | N101: 0 | O101: =L101*M101*N101 -> 0 | P101: =L101 -> 72554.43 | Q101: ='Program Budget'!R104 -> 0 | R101: 0 | S101: =P101*Q101*R101 -> 0 | T101: =C101+G101+K101+O101+S101 -> 72554.43
AB102: 297 | AC102: 51-05-1-002 | AD102: DIR-Office Equipment
A103: Subtotal: Equipment | C103: =SUM(C101:C102) -> 72554.43 | G103: =SUM(G101:G102) -> 0 | K103: =SUM(K101:K102) -> 0 | O103: =SUM(O101:O102) -> 0 | S103: =SUM(S101:S102) -> 0 | T103: =+C103+G103+K103+O103+S103 -> 72554.43
A104: Office
A105: ='Program Budget'!D110 -> Courier fees/services/Postage | B105: ='Program Budget'!F110 -> Month | C105: ='Program Budget'!E110 -> 1093.45 | D105: ='Program Budget'!G110 -> 30 | E105: ='Program Budget'!I110 -> 12 | F105: 1 | G105: =D105*E105*F105 -> 360 | H105: =D105*1.04 -> 31.2 | I105: ='Program Budget'!L110 -> 12 | J105: 1 | K105: =H105*I105*J105 -> 374.4 | L105: =H105*1.04 -> 32.448 | M105: ='Program Budget'!O110 -> 12 | N105: 1 | O105: =L105*M105*N105 -> 389.376 | P105: =L105*1.04 -> 33.74592 | Q105: ='Program Budget'!R110 -> 6 | R105: 1 | S105: =P105*Q105*R105 -> 202.47552 | T105: =C105+G105+K105+O105+S105 -> 2419.7015
A106: ='Program Budget'!D111 -> Email/Internet | B106: ='Program Budget'!F111 -> Month | C106: ='Program Budget'!E111 -> 17482.46 | D106: ='Program Budget'!G111 -> 375 | E106: ='Program Budget'!I111 -> 12 | F106: 1 | G106: =D106*E106*F106 -> 4500 | H106: =D106*1.04 -> 390 | I106: ='Program Budget'!L111 -> 12 | J106: 1 | K106: =H106*I106*J106 -> 4680 | L106: =H106*1.04 -> 405.6 | M106: ='Program Budget'!O111 -> 12 | N106: 1 | O106: =L106*M106*N106 -> 4867.2 | P106: =L106*1.04 -> 421.824 | Q106: ='Program Budget'!R111 -> 6 | R106: 1 | S106: =P106*Q106*R106 -> 2530.944 | T106: =C106+G106+K106+O106+S106 -> 34060.604
A107: ='Program Budget'!D112 -> Recruitment/Procurement Advertising | B107: ='Program Budget'!F112 -> Year | C107: ='Program Budget'!E112 -> 15559.67 | D107: ='Program Budget'!G112 -> 3500 | E107: ='Program Budget'!I112 -> 1 | F107: 1 | G107: =D107*E107*F107 -> 3500 | H107: =D107*1.04 -> 3640 | I107: ='Program Budget'!L112 -> 1 | J107: 1 | K107: =H107*I107*J107 -> 3640 | L107: =H107*1.04 -> 3785.6 | M107: ='Program Budget'!O112 -> 1 | N107: 1 | O107: =L107*M107*N107 -> 3785.6 | P107: =L107*1.04 -> 3937.024 | Q107: ='Program Budget'!R112 -> 0.5 | R107: 1 | S107: =P107*Q107*R107 -> 1968.512 | T107: =C107+G107+K107+O107+S107 -> 28453.782
A108: ='Program Budget'!D113 -> Office Rent, Utilities & Security (Bogota) | B108: ='Program Budget'!F113 -> Month | C108: ='Program Budget'!E113 -> 114429.83 | D108: ='Program Budget'!G113 -> 4000 | E108: ='Program Budget'!I113 -> 12 | F108: 1 | G108: =D108*E108*F108 -> 48000 | H108: =D108*1.04 -> 4160 | I108: ='Program Budget'!L113 -> 12 | J108: 1 | K108: =H108*I108*J108 -> 49920 | L108: =H108*1.04 -> 4326.4 | M108: ='Program Budget'!O113 -> 12 | N108: 1 | O108: =L108*M108*N108 -> 51916.8 | P108: =L108*1.04 -> 4499.456 | Q108: ='Program Budget'!R113 -> 6 | R108: 1 | S108: =P108*Q108*R108 -> 26996.736 | T108: =C108+G108+K108+O108+S108 -> 291263.37
A109: ='Program Budget'!D114 -> Banking and Cash Handling Fees | B109: ='Program Budget'!F114 -> Month | C109: ='Program Budget'!E114 -> 6601.99 | D109: ='Program Budget'!G114 -> 200 | E109: ='Program Budget'!I114 -> 12 | F109: 1 | G109: =D109*E109*F109 -> 2400 | H109: =D109*1.04 -> 208 | I109: ='Program Budget'!L114 -> 12 | J109: 1 | K109: =H109*I109*J109 -> 2496 | L109: =H109*1.04 -> 216.32 | M109: ='Program Budget'!O114 -> 12 | N109: 1 | O109: =L109*M109*N109 -> 2595.84 | P109: =L109*1.04 -> 224.9728 | Q109: ='Program Budget'!R114 -> 6 | R109: 1 | S109: =P109*Q109*R109 -> 1349.8368 | T109: =C109+G109+K109+O109+S109 -> 15443.667
A110: ='Program Budget'!D115 -> Office Meeting Expenses and IT/Communications | B110: ='Program Budget'!F115 -> Month | C110: ='Program Budget'!E115 -> 23514.01 | D110: ='Program Budget'!G115 -> 600 | E110: ='Program Budget'!I115 -> 12 | F110: 1 | G110: =D110*E110*F110 -> 7200 | H110: =D110*1.04 -> 624 | I110: ='Program Budget'!L115 -> 12 | J110: 1 | K110: =H110*I110*J110 -> 7488 | L110: =H110*1.04 -> 648.96 | M110: ='Program Budget'!O115 -> 12 | N110: 1 | O110: =L110*M110*N110 -> 7787.52 | P110: =L110*1.04 -> 674.9184 | Q110: ='Program Budget'!R115 -> 6 | R110: 1 | S110: =P110*Q110*R110 -> 4049.5104 | T110: =C110+G110+K110+O110+S110 -> 50039.04
...

Sheet Activity 1
A2: Item | B2: Type of Unit | C2: Year 1 -4 Total Inception through 09/30/2024 | D2: Year 5 (10/1/24 - 9/30/25) | H2: Year 6 (10/1/25 - 09/30/26) | L2: Year 7 (10/1/26 - 09/30/27) | P2: Year 8 (10/1/27 - 3/31/28) | T2: Total
D3: Cost | E3: Quantity | F3: Percent Allocated | G3: Total | H3: Cost | I3: Quantity | J3: Percent Allocated | K3: Total | L3: Cost | M3: Quantity | N3: Percent Allocated | O3: Total | P3: Cost | Q3: Quantity | R3: Percent Allocated | S3: Total | AC3: Chart of Accounts
A4: Direct Costs | AB4: Line# | AC4: Account | AD4: Account Name
A5: Salaries
A6: USN/TCN Staff
A7: ='Program Budget'!D146 -> Key Personnel: Chief of Party | B7: ='Program Budget'!F146 -> Month | C7: ='Program Budget'!E146 -> 106264 | D7: ='Program Budget'!G146 -> 14250 | E7: ='Program Budget'!I146 -> 12 | F7: ='Program Budget'!H146 -> 0 | G7: =D7*E7*F7 -> 0 | H7: =D7*1.05 -> 14962.5 | I7: ='Program Budget'!L146 -> 12 | J7: ='Program Budget'!K146 -> 0 | K7: =H7*I7*J7 -> 0 | L7: =H7*1.05 -> 15710.625 | M7: ='Program Budget'!O146 -> 12 | N7: ='Program Budget'!N146 -> 0 | O7: =L7*M7*N7 -> 0 | P7: =L7*1.05 -> 16496.156 | Q7: ='Program Budget'!R146 -> 0 | R7: ='Program Budget'!Q146 -> 0 | S7: =P7*Q7*R7 -> 0 | T7: =C7+G7+K7+O7+S7 -> 106264 | AB7: 180 | AC7: 50-01-2-020 | AD7: DIR-USN (Expat) Labor
A8: Total: Expatriate Salaries & Wages | C8: =SUM(C7:C7) -> 106264 | G8: =SUM(G7:G7) -> 0 | K8: =SUM(K7:K7) -> 0 | O8: =SUM(O7:O7) -> 0 | S8: =SUM(S7:S7) -> 0 | T8: =+C8+G8+K8+O8+S8 -> 106264
A9: CCN Staff
A10: ='Program Budget'!D147 -> Deputy Chief of Party / Value Chain Strengthening Director | B10: ='Program Budget'!F146 -> Month | C10: ='Program Budget'!E147 -> 0 | D10: ='Program Budget'!G146 -> 14250 | E10: ='Program Budget'!I146 -> 12 | F10: ='Program Budget'!H146 -> 0 | G10: =D10*E10*F10 -> 0 | H10: =D10*1.05 -> 14962.5 | I10: ='Program Budget'!L146 -> 12 | J10: ='Program Budget'!K146 -> 0 | K10: =H10*I10*J10 -> 0 | L10: =H10*1.05 -> 15710.625 | M10: ='Program Budget'!O146 -> 12 | N10: ='Program Budget'!N145 -> 0 | O10: =L10*M10*N10 -> 0 | P10: =L10*1.05 -> 16496.156 | Q10: ='Program Budget'!R146 -> 0 | R10: ='Program Budget'!Q146 -> 0 | S10: =P10*Q10*R10 -> 0 | T10: =C10+G10+K10+O10+S10 -> 0 | AB10: 180 | AC10: 50-01-2-020 | AD10: DIR-USN (Expat) Labor
A11: ='Program Budget'!D148 -> Key Personnel: Technical Director | B11: ='Program Budget'!F147 -> Month | C11: ='Program Budget'!E148 -> 22300.32 | D11: ='Program Budget'!G147 -> 5000 | E11: ='Program Budget'!I147 -> 12 | F11: ='Program Budget'!H147 -> 0 | G11: =D11*E11*F11 -> 0 | H11: =D11*1.05 -> 5250 | I11: ='Program Budget'!L147 -> 12 | J11: ='Program Budget'!K147 -> 0 | K11: =H11*I11*J11 -> 0 | L11: =H11*1.05 -> 5512.5 | M11: ='Program Budget'!O147 -> 12 | N11: ='Program Budget'!N146 -> 0 | O11: =L11*M11*N11 -> 0 | P11: =L11*1.05 -> 5788.125 | Q11: ='Program Budget'!R147 -> 6 | R11: ='Program Budget'!Q147 -> 0 | S11: =P11*Q11*R11 -> 0 | T11: =C11+G11+K11+O11+S11 -> 22300.32 | AB11: 180 | AC11: 50-01-2-020 | AD11: DIR-USN (Expat) Labor
A12: ='Program Budget'!D149 -> Activity Lead Agribusiness Senior Specialist (Cacao) | B12: ='Program Budget'!F148 -> Month | C12: ='Program Budget'!E149 -> 3487.19 | D12: ='Program Budget'!G148 -> 4583.3333 | E12: ='Program Budget'!I148 -> 12 | F12: ='Program Budget'!H148 -> 0 | G12: =D12*E12*F12 -> 0 | H12: =D12*1.05 -> 4812.5 | I12: ='Program Budget'!L148 -> 12 | J12: ='Program Budget'!K148 -> 0 | K12: =H12*I12*J12 -> 0 | L12: =H12*1.05 -> 5053.125 | M12: ='Program Budget'!O148 -> 12 | N12: ='Program Budget'!N147 -> 0 | O12: =L12*M12*N12 -> 0 | P12: =L12*1.05 -> 5305.7812 | Q12: ='Program Budget'!R148 -> 5 | R12: ='Program Budget'!Q148 -> 0 | S12: =P12*Q12*R12 -> 0 | T12: =C12+G12+K12+O12+S12 -> 3487.19 | AB12: 180 | AC12: 50-01-2-020 | AD12: DIR-USN (Expat) Labor
A13: ='Program Budget'!D150 -> Cacao Field Officer | B13: ='Program Budget'!F149 -> Month | C13: ='Program Budget'!E150 -> 0 | D13: ='Program Budget'!G149 -> 2833.3333 | E13: ='Program Budget'!I149 -> 12 | F13: ='Program Budget'!H149 -> 0 | G13: =D13*E13*F13 -> 0 | H13: =D13*1.05 -> 2975 | I13: ='Program Budget'!L149 -> 12 | J13: ='Program Budget'!K149 -> 0 | K13: =H13*I13*J13 -> 0 | L13: =H13*1.05 -> 3123.75 | M13: ='Program Budget'!O149 -> 12 | N13: ='Program Budget'!N148 -> 0 | O13: =L13*M13*N13 -> 0 | P13: =L13*1.05 -> 3279.9375 | Q13: ='Program Budget'!R149 -> 2 | R13: ='Program Budget'!Q149 -> 0 | S13: =P13*Q13*R13 -> 0 | T13: =C13+G13+K13+O13+S13 -> 0 | AB13: 180 | AC13: 50-01-2-020 | AD13: DIR-USN (Expat) Labor
A14: ='Program Budget'!D151 -> Cacao & Complementary Crop Technical Field Leader (2) | B14: ='Program Budget'!F150 -> Month | C14: ='Program Budget'!E151 -> 0 | D14: ='Program Budget'!G150 -> 1333.3333 | E14: ='Program Budget'!I150 -> 12 | F14: ='Program Budget'!H150 -> 0 | G14: =D14*E14*F14 -> 0 | H14: =D14*1.05 -> 1400 | I14: ='Program Budget'!L150 -> 12 | J14: ='Program Budget'!K150 -> 0 | K14: =H14*I14*J14 -> 0 | L14: =H14*1.05 -> 1470 | M14: ='Program Budget'!O150 -> 12 | N14: ='Program Budget'!N149 -> 0 | O14: =L14*M14*N14 -> 0 | P14: =L14*1.05 -> 1543.5 | Q14: ='Program Budget'!R150 -> 0 | R14: ='Program Budget'!Q150 -> 0 | S14: =P14*Q14*R14 -> 0 | T14: =C14+G14+K14+O14+S14 -> 0
A15: ='Program Budget'!D152 -> Extension Agents (45 in Y5 and 25 in Y6) | B15: ='Program Budget'!F151 -> Month | C15: ='Program Budget'!E152 -> 3487.19 | D15: ='Program Budget'!G151 -> 3500 | E15: ='Program Budget'!I151 -> 6 | F15: ='Program Budget'!H151 -> 0 | G15: =D15*E15*F15 -> 0 | H15: =D15*1.05 -> 3675 | I15: ='Program Budget'!L151 -> 12 | J15: ='Program Budget'!K151 -> 0 | K15: =H15*I15*J15 -> 0 | L15: =H15*1.05 -> 3858.75 | M15: ='Program Budget'!O151 -> 12 | N15: ='Program Budget'!N150 -> 0 | O15: =L15*M15*N15 -> 0 | P15: =L15*1.05 -> 4051.6875 | Q15: ='Program Budget'!R151 -> 0 | R15: ='Program Budget'!Q151 -> 0 | S15: =P15*Q15*R15 -> 0 | T15: =C15+G15+K15+O15+S15 -> 3487.19
A16: ='Program Budget'!D153 -> Activity Lead Agribusiness Senior Specialist (Complementary Crop) | B16: ='Program Budget'!F152 -> Month | C16: ='Program Budget'!E153 -> 0 | D16: ='Program Budget'!G152 -> 1000 | E16: ='Program Budget'!I152 -> 12 | F16: ='Program Budget'!H152 -> 0 | G16: =D16*E16*F16 -> 0 | H16: =D16*1.05 -> 1050 | I16: ='Program Budget'!L152 -> 12 | J16: ='Program Budget'!K152 -> 0 | K16: =H16*I16*J16 -> 0 | L16: =H16*1.05 -> 1102.5 | M16: ='Program Budget'!O152 -> 0 | N16: ='Program Budget'!N151 -> 0 | O16: =L16*M16*N16 -> 0 | P16: =L16*1.05 -> 1157.625 | Q16: ='Program Budget'!R152 -> 0 | R16: ='Program Budget'!Q152 -> 0 | S16: =P16*Q16*R16 -> 0 | T16: =C16+G16+K16+O16+S16 -> 0
A17: ='Program Budget'!D154 -> Complementary Crops Field Officer | B17: ='Program Budget'!F153 -> Month | C17: ='Program Budget'!E154 -> 0 | D17: ='Program Budget'!G153 -> 2833.3333 | E17: ='Program Budget'!I153 -> 12 | F17: ='Program Budget'!H153 -> 0 | G17: =D17*E17*F17 -> 0 | H17: =D17*1.05 -> 2975 | I17: ='Program Budget'!L153 -> 12 | J17: ='Program Budget'!K153 -> 0 | K17: =H17*I17*J17 -> 0 | L17: =H17*1.05 -> 3123.75 | M17: ='Program Budget'!O153 -> 12 | N17: ='Program Budget'!N152 -> 0 | O17: =L17*M17*N17 -> 0 | P17: =L17*1.05 -> 3279.9375 | Q17: ='Program Budget'!R153 -> 0 | R17: ='Program Budget'!Q153 -> 0 | S17: =P17*Q17*R17 -> 0 | T17: =C17+G17+K17+O17+S17 -> 0 | AB17: 180 | AC17: 50-01-2-020 | AD17: DIR-USN (Expat) Labor
A18: ='Program Budget'!D155 -> EPSEAS Specialist | B18: ='Program Budget'!F154 -> Month | C18: ='Program Budget'!E155 -> 0 | D18: ='Program Budget'!G154 -> 0 | E18: ='Program Budget'!I154 -> 0 | F18: ='Program Budget'!H154 -> 0 | G18: =D18*E18*F18 -> 0 | H18: =D18*1.05 -> 0 | I18: ='Program Budget'!L154 -> 12 | J18: ='Program Budget'!K154 -> 0 | K18: =H18*I18*J18 -> 0 | L18: =H18*1.05 -> 0 | M18: ='Program Budget'!O154 -> 12 | N18: ='Program Budget'!N153 -> 0 | O18: =L18*M18*N18 -> 0 | P18: =L18*1.05 -> 0 | Q18: ='Program Budget'!R154 -> 0 | R18: ='Program Budget'!Q154 -> 0 | S18: =P18*Q18*R18 -> 0 | T18: =C18+G18+K18+O18+S18 -> 0 | AB18: 180 | AC18: 50-01-2-020 | AD18: DIR-USN (Expat) Labor
A19: ='Program Budget'!D156 -> Extension Agents for EPSEAS (20 in Y6 and 25 in Y7) | B19: ='Program Budget'!F155 -> Month | C19: ='Program Budget'!E156 -> 0 | D19: ='Program Budget'!G155 -> 0 | E19: ='Program Budget'!I155 -> 0 | F19: ='Program Budget'!H155 -> 0 | G19: =D19*E19*F19 -> 0 | H19: =D19*1.05 -> 0 | I19: ='Program Budget'!L155 -> 12 | J19: ='Program Budget'!K155 -> 0 | K19: =H19*I19*J19 -> 0 | L19: =H19*1.05 -> 0 | M19: ='Program Budget'!O155 -> 12 | N19: ='Program Budget'!N154 -> 0 | O19: =L19*M19*N19 -> 0 | P19: =L19*1.05 -> 0 | Q19: ='Program Budget'!R155 -> 0 | R19: ='Program Budget'!Q155 -> 0 | S19: =P19*Q19*R19 -> 0 | T19: =C19+G19+K19+O19+S19 -> 0
A20: ='Program Budget'!D157 -> Senior M&E Director | B20: ='Program Budget'!F156 -> Month | C20: ='Program Budget'!E157 -> 0 | D20: ='Program Budget'!G156 -> 1000 | E20: ='Program Budget'!I156 -> 0 | F20: ='Program Budget'!H156 -> 0 | G20: =D20*E20*F20 -> 0 | H20: =D20*1.05 -> 1050 | I20: ='Program Budget'!L156 -> 12 | J20: ='Program Budget'!K156 -> 0 | K20: =H20*I20*J20 -> 0 | L20: =H20*1.05 -> 1102.5 | M20: ='Program Budget'!O156 -> 12 | N20: ='Program Budget'!N155 -> 0 | O20: =L20*M20*N20 -> 0 | P20: =L20*1.05 -> 1157.625 | Q20: ='Program Budget'!R156 -> 0 | R20: ='Program Budget'!Q156 -> 0 | S20: =P20*Q20*R20 -> 0 | T20: =C20+G20+K20+O20+S20 -> 0
A21: ='Program Budget'!D158 -> Senior M&E Specialist | B21: ='Program Budget'!F157 -> Month | C21: ='Program Budget'!E158 -> 0 | D21: ='Program Budget'!G157 -> 6250 | E21: ='Program Budget'!I157 -> 12 | F21: ='Program Budget'!H157 -> 0 | G21: =D21*E21*F21 -> 0 | H21: =D21*1.05 -> 6562.5 | I21: ='Program Budget'!L157 -> 12 | J21: ='Program Budget'!K157 -> 0 | K21: =H21*I21*J21 -> 0 | L21: =H21*1.05 -> 6890.625 | M21: ='Program Budget'!O157 -> 12 | N21: ='Program Budget'!N156 -> 0 | O21: =L21*M21*N21 -> 0 | P21: =L21*1.05 -> 7235.1562 | Q21: ='Program Budget'!R157 -> 6 | R21: ='Program Budget'!Q157 -> 0 | S21: =P21*Q21*R21 -> 0 | T21: =C21+G21+K21+O21+S21 -> 0 | AB21: 180 | AC21: 50-01-2-020 | AD21: DIR-USN (Expat) Labor
A22: ='Program Budget'!D159 -> M&E Specialist | B22: ='Program Budget'!F158 -> Month | C22: ='Program Budget'!E159 -> 6230.78 | D22: ='Program Budget'!G158 -> 2833.3333 | E22: ='Program Budget'!I158 -> 12 | F22: ='Program Budget'!H158 -> 0 | G22: =D22*E22*F22 -> 0 | H22: =D22*1.05 -> 2975 | I22: ='Program Budget'!L158 -> 12 | J22: ='Program Budget'!K158 -> 0 | K22: =H22*I22*J22 -> 0 | L22: =H22*1.05 -> 3123.75 | M22: ='Program Budget'!O158 -> 12 | N22: ='Program Budget'!N157 -> 0 | O22: =L22*M22*N22 -> 0 | P22: =L22*1.05 -> 3279.9375 | Q22: ='Program Budget'!R158 -> 6 | R22: ='Program Budget'!Q158 -> 0 | S22: =P22*Q22*R22 -> 0 | T22: =C22+G22+K22+O22+S22 -> 6230.78
A23: ='Program Budget'!D160 -> M&E Officer | B23: ='Program Budget'!F159 -> Month | C23: ='Program Budget'!E160 -> 4230.77 | D23: ='Program Budget'!G159 -> 2500 | E23: ='Program Budget'!I159 -> 12 | F23: ='Program Budget'!H159 -> 0 | G23: =D23*E23*F23 -> 0 | H23: =D23*1.05 -> 2625 | I23: ='Program Budget'!L159 -> 12 | J23: ='Program Budget'!K159 -> 0 | K23: =H23*I23*J23 -> 0 | L23: =H23*1.05 -> 2756.25 | M23: ='Program Budget'!O159 -> 12 | N23: ='Program Budget'!N158 -> 0 | O23: =L23*M23*N23 -> 0 | P23: =L23*1.05 -> 2894.0625 | Q23: ='Program Budget'!R159 -> 3 | R23: ='Program Budget'!Q159 -> 0 | S23: =P23*Q23*R23 -> 0 | T23: =C23+G23+K23+O23+S23 -> 4230.77
A24: ='Program Budget'!D161 -> Partnerships and Investment Director | B24: ='Program Budget'!F160 -> Month | C24: ='Program Budget'!E161 -> 17435.93 | D24: ='Program Budget'!G160 -> 1000 | E24: ='Program Budget'!I160 -> 12 | F24: ='Program Budget'!H160 -> 0 | G24: =D24*E24*F24 -> 0 | H24: =D24*1.05 -> 1050 | I24: ='Program Budget'!L160 -> 12 | J24: ='Program Budget'!K160 -> 0 | K24: =H24*I24*J24 -> 0 | L24: =H24*1.05 -> 1102.5 | M24: ='Program Budget'!O160 -> 12 | N24: ='Program Budget'!N159 -> 0 | O24: =L24*M24*N24 -> 0 | P24: =L24*1.05 -> 1157.625 | Q24: ='Program Budget'!R160 -> 3 | R24: ='Program Budget'!Q160 -> 0 | S24: =P24*Q24*R24 -> 0 | T24: =C24+G24+K24+O24+S24 -> 17435.93 | AB24: 180 | AC24: 50-01-2-020 | AD24: DIR-USN (Expat) Labor
A25: ='Program Budget'!D162 -> Partnerships and Investment Specialist | B25: ='Program Budget'!F161 -> Month | C25: ='Program Budget'!E162 -> 0 | D25: ='Program Budget'!G161 -> 4583.3333 | E25: ='Program Budget'!I161 -> 12 | F25: ='Program Budget'!H161 -> 0 | G25: =D25*E25*F25 -> 0 | H25: =D25*1.05 -> 4812.5 | I25: ='Program Budget'!L161 -> 12 | J25: ='Program Budget'!K161 -> 0 | K25: =H25*I25*J25 -> 0 | L25: =H25*1.05 -> 5053.125 | M25: ='Program Budget'!O161 -> 12 | N25: ='Program Budget'!N160 -> 0 | O25: =L25*M25*N25 -> 0 | P25: =L25*1.05 -> 5305.7812 | Q25: ='Program Budget'!R161 -> 0 | R25: ='Program Budget'!Q161 -> 0 | S25: =P25*Q25*R25 -> 0 | T25: =C25+G25+K25+O25+S25 -> 0 | AB25: 180 | AC25: 50-01-2-020 | AD25: DIR-USN (Expat) Labor
A26: ='Program Budget'!D163 -> Organizational Strengthening Specialist | B26: ='Program Budget'!F162 -> Month | C26: ='Program Budget'!E163 -> 0 | D26: ='Program Budget'!G162 -> 1750 | E26: ='Program Budget'!I162 -> 12 | F26: ='Program Budget'!H162 -> 0 | G26: =D26*E26*F26 -> 0 | H26: =D26*1.05 -> 1837.5 | I26: ='Program Budget'!L162 -> 12 | J26: ='Program Budget'!K162 -> 0 | K26: =H26*I26*J26 -> 0 | L26: =H26*1.05 -> 1929.375 | M26: ='Program Budget'!O162 -> 12 | N26: ='Program Budget'!N161 -> 0 | O26: =L26*M26*N26 -> 0 | P26: =L26*1.05 -> 2025.8438 | Q26: ='Program Budget'!R162 -> 0 | R26: ='Program Budget'!Q162 -> 0 | S26: =P26*Q26*R26 -> 0 | T26: =C26+G26+K26+O26+S26 -> 0
A27: ='Program Budget'!D164 -> Value Chain Strengthening Director | B27: ='Program Budget'!F163 -> Month | C27: ='Program Budget'!E164 -> 0 | D27: ='Program Budget'!G163 -> 1750 | E27: ='Program Budget'!I163 -> 12 | F27: ='Program Budget'!H163 -> 0 | G27: =D27*E27*F27 -> 0 | H27: =D27*1.05 -> 1837.5 | I27: ='Program Budget'!L163 -> 12 | J27: ='Program Budget'!K163 -> 0 | K27: =H27*I27*J27 -> 0 | L27: =H27*1.05 -> 1929.375 | M27: ='Program Budget'!O163 -> 12 | N27: ='Program Budget'!N162 -> 0 | O27: =L27*M27*N27 -> 0 | P27: =L27*1.05 -> 2025.8438 | Q27: ='Program Budget'!R163 -> 0 | R27: ='Program Budget'!Q163 -> 0 | S27: =P27*Q27*R27 -> 0 | T27: =C27+G27+K27+O27+S27 -> 0
A28: ='Program Budget'!D165 -> Communications Specialist | B28: ='Program Budget'!F164 -> Month | C28: ='Program Budget'!E165 -> 0 | D28: ='Program Budget'!G164 -> 0 | E28: ='Program Budget'!I164 -> 12 | F28: ='Program Budget'!H164 -> 0 | G28: =D28*E28*F28 -> 0 | H28: =D28*1.05 -> 0 | I28: ='Program Budget'!L164 -> 12 | J28: ='Program Budget'!K164 -> 0 | K28: =H28*I28*J28 -> 0 | L28: =H28*1.05 -> 0 | M28: ='Program Budget'!O164 -> 12 | N28: ='Program Budget'!N163 -> 0 | O28: =L28*M28*N28 -> 0 | P28: =L28*1.05 -> 0 | Q28: ='Program Budget'!R164 -> 4 | R28: ='Program Budget'!Q164 -> 0 | S28: =P28*Q28*R28 -> 0 | T28: =C28+G28+K28+O28+S28 -> 0 | AB28: 180 | AC28: 50-01-2-020 | AD28: DIR-USN (Expat) Labor
A29: ='Program Budget'!D166 -> Value Chain Specialist | B29: ='Program Budget'!F165 -> Month | C29: ='Program Budget'!E166 -> 0 | D29: ='Program Budget'!G165 -> 1750 | E29: ='Program Budget'!I165 -> 12 | F29: ='Program Budget'!H165 -> 0 | G29: =D29*E29*F29 -> 0 | H29: =D29*1.05 -> 1837.5 | I29: ='Program Budget'!L165 -> 12 | J29: ='Program Budget'!K165 -> 0 | K29: =H29*I29*J29 -> 0 | L29: =H29*1.05 -> 1929.375 | M29: ='Program Budget'!O165 -> 12 | N29: ='Program Budget'!N164 -> 0 | O29: =L29*M29*N29 -> 0 | P29: =L29*1.05 -> 2025.8438 | Q29: ='Program Budget'!R165 -> 0 | R29: ='Program Budget'!Q165 -> 0 | S29: =P29*Q29*R29 -> 0 | T29: =C29+G29+K29+O29+S29 -> 0 | AB29: 180 | AC29: 50-01-2-020 | AD29: DIR-USN (Expat) Labor
A30: ='Program Budget'!D167 -> Contracts & Compliance Director | B30: ='Program Budget'!F166 -> Month | C30: ='Program Budget'!E167 -> 5692.33 | D30: ='Program Budget'!G166 -> 2500 | E30: ='Program Budget'!I166 -> 12 | F30: ='Program Budget'!H166 -> 0 | G30: =D30*E30*F30 -> 0 | H30: =D30*1.05 -> 2625 | I30: ='Program Budget'!L166 -> 12 | J30: ='Program Budget'!K166 -> 0 | K30: =H30*I30*J30 -> 0 | L30: =H30*1.05 -> 2756.25 | M30: ='Program Budget'!O166 -> 12 | N30: ='Program Budget'!N165 -> 0 | O30: =L30*M30*N30 -> 0 | P30: =L30*1.05 -> 2894.0625 | Q30: ='Program Budget'!R166 -> 0 | R30: ='Program Budget'!Q166 -> 0 | S30: =P30*Q30*R30 -> 0 | T30: =C30+G30+K30+O30+S30 -> 5692.33
A31: ='Program Budget'!D168 -> Grants & Procurement Specialist (2) | B31: ='Program Budget'!F167 -> Month | C31: ='Program Budget'!E168 -> 0 | D31: ='Program Budget'!G167 -> 4583.3333 | E31: ='Program Budget'!I167 -> 12 | F31: ='Program Budget'!H167 -> 0 | G31: =D31*E31*F31 -> 0 | H31: =D31*1.05 -> 4812.5 | I31: ='Program Budget'!L167 -> 12 | J31: ='Program Budget'!K167 -> 0 | K31: =H31*I31*J31 -> 0 | L31: =H31*1.05 -> 5053.125 | M31: ='Program Budget'!O167 -> 12 | N31: ='Program Budget'!N166 -> 0 | O31: =L31*M31*N31 -> 0 | P31: =L31*1.05 -> 5305.7812 | Q31: ='Program Budget'!R167 -> 3 | R31: ='Program Budget'!Q167 -> 0 | S31: =P31*Q31*R31 -> 0 | T31: =C31+G31+K31+O31+S31 -> 0
A32: ='Program Budget'!D169 -> F&A Director | B32: ='Program Budget'!F168 -> Month | C32: ='Program Budget'!E169 -> 5230.78 | D32: ='Program Budget'!G168 -> 3500 | E32: ='Program Budget'!I168 -> 12 | F32: ='Program Budget'!H168 -> 0 | G32: =D32*E32*F32 -> 0 | H32: =D32*1.05 -> 3675 | I32: ='Program Budget'!L168 -> 12 | J32: ='Program Budget'!K168 -> 0 | K32: =H32*I32*J32 -> 0 | L32: =H32*1.05 -> 3858.75 | M32: ='Program Budget'!O168 -> 12 | N32: ='Program Budget'!N167 -> 0 | O32: =L32*M32*N32 -> 0 | P32: =L32*1.05 -> 4051.6875 | Q32: ='Program Budget'!R168 -> 0 | R32: ='Program Budget'!Q168 -> 0 | S32: =P32*Q32*R32 -> 0 | T32: =C32+G32+K32+O32+S32 -> 5230.78
A33: ='Program Budget'!D170 -> Accounting & Finance Specialist | B33: ='Program Budget'!F169 -> Month | C33: ='Program Budget'!E170 -> 0 | D33: ='Program Budget'!G169 -> 5279.4 | E33: ='Program Budget'!I169 -> 12 | F33: ='Program Budget'!H169 -> 0 | G33: =D33*E33*F33 -> 0 | H33: =D33*1.05 -> 5543.37 | I33: ='Program Budget'!L169 -> 12 | J33: ='Program Budget'!K169 -> 0 | K33: =H33*I33*J33 -> 0 | L33: =H33*1.05 -> 5820.5385 | M33: ='Program Budget'!O169 -> 12 | N33: ='Program Budget'!N168 -> 0 | O33: =L33*M33*N33 -> 0 | P33: =L33*1.05 -> 6111.5654 | Q33: ='Program Budget'!R169 -> 6 | R33: ='Program Budget'!Q169 -> 0 | S33: =P33*Q33*R33 -> 0 | T33: =C33+G33+K33+O33+S33 -> 0 | AB33: 180 | AC33: 50-01-2-020 | AD33: DIR-USN (Expat) Labor
A34: ='Program Budget'!D171 -> Accountant | B34: ='Program Budget'!F170 -> Month | C34: ='Program Budget'!E171 -> 0 | D34: ='Program Budget'!G170 -> 1750 | E34: ='Program Budget'!I170 -> 12 | F34: ='Program Budget'!H170 -> 0 | G34: =D34*E34*F34 -> 0 | H34: =D34*1.05 -> 1837.5 | I34: ='Program Budget'!L170 -> 12 | J34: ='Program Budget'!K170 -> 0 | K34: =H34*I34*J34 -> 0 | L34: =H34*1.05 -> 1929.375 | M34: ='Program Budget'!O170 -> 12 | N34: ='Program Budget'!N169 -> 0 | O34: =L34*M34*N34 -> 0 | P34: =L34*1.05 -> 2025.8438 | Q34: ='Program Budget'!R170 -> 3 | R34: ='Program Budget'!Q170 -> 0 | S34: =P34*Q34*R34 -> 0 | T34: =C34+G34+K34+O34+S34 -> 0
A35: ='Program Budget'!D172 -> Finance & Admin Coordinator - 50% LOE | B35: ='Program Budget'!F171 -> Month | C35: ='Program Budget'!E172 -> 0 | D35: ='Program Budget'!G171 -> 1750 | E35: ='Program Budget'!I171 -> 12 | F35: ='Program Budget'!H171 -> 0 | G35: =D35*E35*F35 -> 0 | H35: =D35*1.05 -> 1837.5 | I35: ='Program Budget'!L171 -> 12 | J35: ='Program Budget'!K171 -> 0 | K35: =H35*I35*J35 -> 0 | L35: =H35*1.05 -> 1929.375 | M35: ='Program Budget'!O171 -> 12 | N35: ='Program Budget'!N170 -> 0 | O35: =L35*M35*N35 -> 0 | P35: =L35*1.05 -> 2025.8438 | Q35: ='Program Budget'!R171 -> 5 | R35: ='Program Budget'!Q171 -> 0 | S35: =P35*Q35*R35 -> 0 | T35: =C35+G35+K35+O35+S35 -> 0 | AB35: 180 | AC35: 50-01-2-020 | AD35: DIR-USN (Expat) Labor
A36: ='Program Budget'!D173 -> Administrative Officer | B36: ='Program Budget'!F172 -> Month | C36: ='Program Budget'!E173 -> 0 | D36: ='Program Budget'!G172 -> 2583.3333 | E36: ='Program Budget'!I172 -> 12 | F36: ='Program Budget'!H172 -> 0 | G36: =D36*E36*F36 -> 0 | H36: =D36*1.05 -> 2712.5 | I36: ='Program Budget'!L172 -> 12 | J36: ='Program Budget'!K172 -> 0 | K36: =H36*I36*J36 -> 0 | L36: =H36*1.05 -> 2848.125 | M36: ='Program Budget'!O172 -> 12 | N36: ='Program Budget'!N171 -> 0 | O36: =L36*M36*N36 -> 0 | P36: =L36*1.05 -> 2990.5313 | Q36: ='Program Budget'!R172 -> 6 | R36: ='Program Budget'!Q172 -> 0 | S36: =P36*Q36*R36 -> 0 | T36: =C36+G36+K36+O36+S36 -> 0 | AB36: 180 | AC36: 50-01-2-020 | AD36: DIR-USN (Expat) Labor
A37: ='Program Budget'!D174 -> Human Resource Manager | B37: ='Program Budget'!F173 -> Month | C37: ='Program Budget'!E174 -> 0 | D37: ='Program Budget'!G173 -> 1000 | E37: ='Program Budget'!I173 -> 12 | F37: ='Program Budget'!H173 -> 0 | G37: =D37*E37*F37 -> 0 | H37: =D37*1.05 -> 1050 | I37: ='Program Budget'!L173 -> 12 | J37: ='Program Budget'!K173 -> 0 | K37: =H37*I37*J37 -> 0 | L37: =H37*1.05 -> 1102.5 | M37: ='Program Budget'!O173 -> 12 | N37: ='Program Budget'!N172 -> 0 | O37: =L37*M37*N37 -> 0 | P37: =L37*1.05 -> 1157.625 | Q37: ='Program Budget'!R173 -> 3 | R37: ='Program Budget'!Q173 -> 0 | S37: =P37*Q37*R37 -> 0 | T37: =C37+G37+K37+O37+S37 -> 0 | AB37: 180 | AC37: 50-01-2-020 | AD37: DIR-USN (Expat) Labor
A38: ='Program Budget'!D175 -> Human Resource Specialist | B38: ='Program Budget'!F174 -> Month | C38: ='Program Budget'!E175 -> 0 | D38: ='Program Budget'!G174 -> 1954.1667 | E38: ='Program Budget'!I174 -> 12 | F38: ='Program Budget'!H174 -> 0 | G38: =D38*E38*F38 -> 0 | H38: =D38*1.05 -> 2051.875 | I38: ='Program Budget'!L174 -> 12 | J38: ='Program Budget'!K174 -> 0 | K38: =H38*I38*J38 -> 0 | L38: =H38*1.05 -> 2154.4688 | M38: ='Program Budget'!O174 -> 12 | N38: ='Program Budget'!N173 -> 0 | O38: =L38*M38*N38 -> 0 | P38: =L38*1.05 -> 2262.1922 | Q38: ='Program Budget'!R174 -> 6 | R38: ='Program Budget'!Q174 -> 0 | S38: =P38*Q38*R38 -> 0 | T38: =C38+G38+K38+O38+S38 -> 0 | AB38: 180 | AC38: 50-01-2-020 | AD38: DIR-USN (Expat) Labor
A39: Total Local Salary Cost | C39: =SUM(C10:C38) -> 68095.29 | G39: =SUM(G10:G38) -> 0 | K39: =SUM(K10:K38) -> 0 | O39: =SUM(O10:O38) -> 0 | S39: =SUM(S10:S38) -> 0 | T39: =C39+G39+K39+O39+S39 -> 68095.29
A41: Subtotal: Salaries & Wages | C41: =C39+C8 -> 174359.29 | G41: =G39+G8 -> 0 | K41: =K39+K8 -> 0 | O41: =O39+O8 -> 0 | S41: =S39+S8 -> 0 | T41: =+C41+G41+K41+O41+S41 -> 174359.29
A42: Fringe
A43: USN/TCN Staff | B43: ='Program Budget'!F179 -> % | C43: ='Program Budget'!E182 -> 2950.12 | D43: =G8 -> 0 | E43: 1 | F43: ='Program Budget'!G182 -> 0.5647 | G43: =D43*E43*F43 -> 0 | H43: =K8 -> 0 | I43: 1 | J43: =F43 -> 0.5647 | K43: =H43*I43*J43 -> 0 | L43: =O8 -> 0 | M43: 1 | N43: =J43 -> 0.5647 | O43: =L43*M43*N43 -> 0 | P43: =S8 -> 0 | Q43: 1 | R43: =N43 -> 0.5647 | S43: =P43*Q43*R43 -> 0 | T43: =C43+G43+K43+O43+S43 -> 2950.12 | AB43: 194 | AC43: 50-03-0-020 | AD43: DIR-Allocated USN Fringe
A44: CCN - Colombia (above $3,350 monthly) | B44: ='Program Budget'!F179 -> % | C44: ='Program Budget'!E179 -> 7867 | D44: =G12+G11+G21+G25+G28+G31+G33 -> 0 | E44: 1 | F44: ='Program Budget'!G179 -> 0.53864 | G44: =D44*E44*F44 -> 0 | H44: =K12+K11+K21+K25+K28+K31+K33 -> 0 | I44: 1 | J44: =F44 -> 0.53864 | K44: =H44*I44*J44 -> 0 | L44: =O12+O11+O21+O25+O28+O31+O33 -> 0 | M44: 1 | N44: =J44 -> 0.53864 | O44: =L44*M44*N44 -> 0 | P44: =S12+S11+S21+S25+S28+S31+S33 -> 0 | Q44: 1 | R44: =N44 -> 0.53864 | S44: =P44*Q44*R44 -> 0 | T44: =C44+G44+K44+O44+S44 -> 7867 | AB44: 197 | AC44: 50-03-0-050 | AD44: DIR-CCN Fringe
A45: CCN - Colombia (below $3,350 monthly) | B45: ='Program Budget'!F180 -> % | C45: ='Program Budget'!E180 -> 78279.3 | D45: =G39-D44 -> 0 | E45: 1 | F45: ='Program Budget'!G180 -> 0.44864 | G45: =D45*E45*F45 -> 0 | H45: =K39-H44 -> 0 | I45: 1 | J45: =F45 -> 0.44864 | K45: =H45*I45*J45 -> 0 | L45: =O39-L44 -> 0 | M45: 1 | N45: =J45 -> 0.44864 | O45: =L45*M45*N45 -> 0 | P45: =S39-P44 -> 0 | Q45: 1 | R45: =N45 -> 0.44864 | S45: =P45*Q45*R45 -> 0 | T45: =C45+G45+K45+O45+S45 -> 78279.3 | AB45: 197 | AC45: 50-03-0-050 | AD45: DIR-CCN Fringe
A46: Total: Fringe Benefits | C46: =+SUM(C43:C45) -> 89096.42 | G46: =+SUM(G43:G45) -> 0 | K46: =+SUM(K43:K45) -> 0 | O46: =+SUM(O43:O45) -> 0 | S46: =+SUM(S43:S45) -> 0 | T46: =+C46+G46+K46+O46+S46 -> 89096.42
A47: Allowances | T47: =+C47+G47+K47+O47+S47 -> 0
A48: ='Program Budget'!D181 -> Post (Hardship) Differential for Chief of Party | B48: ='Program Budget'!F181 -> % | C48: ='Program Budget'!E181 -> 9241.04 | D48: =G8 -> 0 | E48: 1 | F48: ='Program Budget'!G181 -> 0.15 | G48: =D48*E48*F48 -> 0 | H48: =K8 -> 0 | I48: 1 | J48: =F48 -> 0.15 | K48: =H48*I48*J48 -> 0 | L48: =O8 -> 0 | M48: 1 | N48: =J48 -> 0.15 | O48: =L48*M48*N48 -> 0 | P48: =S8 -> 0 | Q48: 1 | R48: =N48 -> 0.15 | S48: =P48*Q48*R48 -> 0 | T48: =C48+G48+K48+O48+S48 -> 9241.04
A49: Total: Allowances | C49: =SUM(C48:C48) -> 9241.04 | G49: =SUM(G48:G48) -> 0 | K49: =SUM(K48:K48) -> 0 | O49: =SUM(O48:O48) -> 0 | S49: =SUM(S48:S48) -> 0 | T49: =C49+G49+K49+O49+S49 -> 9241.04
A51: Subtotal: Benefits | C51: =C49+C46 -> 98337.46 | G51: =G49+G46 -> 0 | K51: =K49+K46 -> 0 | O51: =O49+O46 -> 0 | S51: =S49+S46 -> 0 | T51: =+C51+G51+K51+O51+S51 -> 98337.46 | AB51: 287 | AC51: 51-04-2-050 | AD51: DIR-Int Travel Other
A52: Local Travel
A53: None | C53: 0 | G53: =D53*E53*F53 -> 0 | K53: =H53*I53*J53 -> 0 | O53: =L53*M53*N53 -> 0 | S53: =P53*Q53*R53 -> 0 | T53: =C53+G53+K53+O53+S53 -> 0
A54: Per Diem
A55: None | C55: 0 | G55: =D55*E55*F55 -> 0 | K55: =H55*I55*J55 -> 0 | O55: =L55*M55*N55 -> 0 | S55: =P55*Q55*R55 -> 0 | T55: =C55+G55+K55+O55+S55 -> 0
A57: Subtotal: Travel | C57: =SUM(C52:C55) -> 0 | G57: =SUM(G52:G55) -> 0 | K57: =SUM(K52:K55) -> 0 | O57: =SUM(O52:O55) -> 0 | S57: =SUM(S52:S55) -> 0 | T57: =+C57+G57+K57+O57+S57 -> 0
A58: Professional Services
A59: None | C59: 0 | G59: =D59*E59*F59 -> 0 | K59: =H59*I59*J59 -> 0 | O59: =L59*M59*N59 -> 0 | S59: =P59*Q59*R59 -> 0 | T59: =C59+G59+K59+O59+S59 -> 0
A61: Subtotal: Professional Services/Contractual | C61: =SUM(C59:C59) -> 0 | G61: =SUM(G59:G59) -> 0 | K61: =SUM(K59:K59) -> 0 | O61: =SUM(O59:O59) -> 0 | S61: =SUM(S59:S59) -> 0 | T61: =SUM(T59:T59) -> 0
A62: Equipment (>$5000/unit)
A63: None | C63: 0 | G63: =D63*E63*F63 -> 0 | K63: =H63*I63*J63 -> 0 | O63: =L63*M63*N63 -> 0 | S63: =P63*Q63*R63 -> 0 | T63: =C63+G63+K63+O63+S63 -> 0 | AB63: 298 | AC63: 51-05-1-003 | AD63: DIR-Furniture
A64: Subtotal: Equipment | C64: =SUM(C63:C63) -> 0 | G64: =SUM(G63:G63) -> 0 | K64: =SUM(K63:K63) -> 0 | O64: =SUM(O63:O63) -> 0 | S64: =SUM(S63:S63) -> 0 | T64: =+C64+G64+K64+O64+S64 -> 0
A65: Office
A66: None | C66: 0 | G66: =D66*E66*F66 -> 0 | K66: =H66*I66*J66 -> 0 | O66: =L66*M66*N66 -> 0 | S66: =P66*Q66*R66 -> 0 | T66: =C66+G66+K66+O66+S66 -> 0
A67: Subtotal: Office | C67: =SUM(C63:C63) -> 0 | G67: =SUM(G63:G63) -> 0 | K67: =SUM(K63:K63) -> 0 | O67: =SUM(O63:O63) -> 0 | S67: =SUM(S63:S63) -> 0 | T67: =+C67+G67+K67+O67+S67 -> 0 | AB67: 236 | AC67: 51-02-1-001 | AD67: DIR-Prof. Serv Labor
A68: Supplies | AB68: 236 | AC68: 51-02-1-001 | AD68: DIR-Prof. Serv Labor
A69: None | C69: 0 | G69: =D69*E69*F69 -> 0 | K69: =H69*I69*J69 -> 0 | O69: =L69*M69*N69 -> 0 | S69: =P69*Q69*R69 -> 0 | T69: =C69+G69+K69+O69+S69 -> 0
A71: Subtotal: Supplies | C71: =SUM(C69:C70) -> 0 | G71: =SUM(G69:G70) -> 0 | K71: =SUM(K69:K70) -> 0 | O71: =SUM(O69:O70) -> 0 | S71: =SUM(S69:S70) -> 0 | T71: =+C71+G71+K71+O71+S71 -> 0
A72: Other Direct Cost
A73: Training
A74: None | C74: 0 | G74: =D74*E74*F74 -> 0 | K74: =H74*I74*J74 -> 0 | O74: =L74*M74*N74 -> 0 | S74: =P74*Q74*R74 -> 0 | T74: =C74+G74+K74+O74+S74 -> 0
A76: Subtotal: Other Direct Cost | C76: =SUM(C73:C74) -> 0 | G76: =SUM(G73:G74) -> 0 | K76: =SUM(K73:K74) -> 0 | O76: =SUM(O73:O74) -> 0 | S76: =SUM(S73:S74) -> 0 | T76: =+C76+G76+K76+O76+S76 -> 0 | AB76: 250 | AC76: 51-02-2-008 | AD76: DIR-Security
AB77: 317 | AC77: 51-08-1-002 | AD77: DIR-Office Make Ready
A78: Total Direct Cost | C78: =C41+C51+C57+C67+C71+C61+C76 -> 272696.75 | G78: =G41+G51+G57+G67+G71+G61+G76 -> 0 | K78: =K41+K51+K57+K67+K71+K61+K76 -> 0 | O78: =O41+O51+O57+O67+O71+O61+O76 -> 0 | S78: =S41+S51+S57+S67+S71+S61+S76 -> 0 | T78: =T41+T51+T57+T67+T71+T61+T76 -> 272696.75 | AB78: 318 | AC78: 51-08-1-003 | AD78: DIR-Office Maintenance
A80: Indirect Costs
A81: ICR on Administration | B81: % | C81: 0 | D81: 0 | E81: 0 | F81: 0.2828 | G81: =D81*E81*F81 -> 0 | H81: 0 | I81: 0 | J81: 0.2828 | K81: =H81*I81*J81 -> 0 | L81: 0 | M81: 0 | N81: 0.2828 | O81: =L81*M81*N81 -> 0 | P81: 0 | Q81: 0 | R81: 0.2828 | S81: =P81*Q81*R81 -> 0 | T81: =C81+G81+K81+O81+S81 -> 0
A82: ICR on Activities | B82: % | C82: 79531.545 | D82: =G78 -> 0 | E82: 0 | F82: 0.2828 | G82: =D82*E82*F82 -> 0 | H82: =K78 -> 0 | I82: 0 | J82: 0.2828 | K82: =H82*I82*J82 -> 0 | L82: =O78 -> 0 | M82: 0 | N82: 0.2828 | O82: =L82*M82*N82 -> 0 | P82: =S78 -> 0 | Q82: 0 | R82: 0.2828 | S82: =P82*Q82*R82 -> 0 | T82: =C82+G82+K82+O82+S82 -> 79531.545
A84: Subtotal Indirect Cost | C84: =SUM(C81:C83) -> 79531.545 | G84: =SUM(G81:G83) -> 0 | K84: =SUM(K81:K83) -> 0 | O84: =SUM(O81:O83) -> 0 | S84: =SUM(S81:S83) -> 0 | T84: =SUM(T81:T83) -> 79531.545
A86: Total Estimated Cost (Direct Cost + Indirect Cost) | C86: =C78+C84 -> 352228.29 | G86: =G78+G84 -> 0 | K86: =K78+K84 -> 0 | O86: =O78+O84 -> 0 | S86: =S78+S84 -> 0 | T86: =C86+G86+K86+O86+S86 -> 352228.29
A87: Total Cost Share (for reference) | C87: ='Program Budget'!U195 -> 0 | G87: =D87*E87*F87 -> 0 | K87: =H87*I87*J87 -> 0 | O87: =L87*M87*N87 -> 0 | S87: =P87*Q87*R87 -> 0 | T87: =C87+G87+K87+O87+S87 -> 0
A88: Total Estimated Cost (Direct Cost + Indirect Cost+ Cost Share) | C88: =C86+C87 -> 352228.29 | G88: =G86+G87 -> 0 | K88: =K86+K87 -> 0 | O88: =O86+O87 -> 0 | S88: =S86+S87 -> 0 | T88: =C88+G88+K88+O88+S88 -> 352228.29
A90: Anticipated Program Income (baked in costs and this is for reference)

Sheet Activity 2
A2: Item | B2: Type of Unit | C2: Year 1 -4 Total Inception through 09/30/2024 | D2: Year 5 (10/1/24 - 9/30/25) | H2: Year 6 (10/1/25 - 09/30/26) | L2: Year 7 (10/1/26 - 09/30/27) | P2: Year 8 (10/1/27 - 3/31/28) | T2: Total
D3: Cost | E3: Quantity | F3: Percent Allocated | G3: Total | H3: Cost | I3: Quantity | J3: Percent Allocated | K3: Total | L3: Cost | M3: Quantity | N3: Percent Allocated | O3: Total | P3: Cost | Q3: Quantity | R3: Percent Allocated | S3: Total | AC3: Chart of Accounts
A4: Direct Costs | AB4: Line# | AC4: Account | AD4: Account Name
A5: Salaries
A6: USN/TCN Staff
A7: ='Program Budget'!D200 -> Key Personnel: Chief of Party | B7: ='Program Budget'!F200 -> Month | C7: ='Program Budget'!E200 -> 40245 | D7: ='Program Budget'!G200 -> 14250 | E7: ='Program Budget'!I200 -> 12 | F7: ='Program Budget'!H200 -> 0.15 | G7: =D7*E7*F7 -> 25650 | H7: =D7*1.05 -> 14962.5 | I7: ='Program Budget'!L200 -> 12 | J7: ='Program Budget'!K200 -> 0.19 | K7: =H7*I7*J7 -> 34114.5 | L7: =H7*1.05 -> 15710.625 | M7: ='Program Budget'!O200 -> 12 | N7: ='Program Budget'!N200 -> 0.19 | O7: =L7*M7*N7 -> 35820.225 | P7: =L7*1.05 -> 16496.156 | Q7: ='Program Budget'!R200 -> 0 | R7: ='Program Budget'!Q200 -> 0.19 | S7: =P7*Q7*R7 -> 0 | T7: =C7+G7+K7+O7+S7 -> 135829.73 | AB7: 180 | AC7: 50-01-2-020 | AD7: DIR-USN (Expat) Labor
A8: Total: Expatriate Salaries & Wages | C8: =SUM(C7:C7) -> 40245 | G8: =SUM(G7:G7) -> 25650 | K8: =SUM(K7:K7) -> 34114.5 | O8: =SUM(O7:O7) -> 35820.225 | S8: =SUM(S7:S7) -> 0 | T8: =+C8+G8+K8+O8+S8 -> 135829.73
A9: CCN Staff
A10: ='Program Budget'!D201 -> Deputy Chief of Party / Value Chain Strengthening Director | B10: ='Program Budget'!F201 -> Month | C10: ='Program Budget'!E201 -> 0 | D10: ='Program Budget'!G201 -> 5000 | E10: ='Program Budget'!I201 -> 12 | F10: ='Program Budget'!H201 -> 0.15 | G10: =D10*E10*F10 -> 9000 | H10: =D10*1.05 -> 5250 | I10: ='Program Budget'!L201 -> 12 | J10: ='Program Budget'!K201 -> 0.15 | K10: =H10*I10*J10 -> 9450 | L10: =H10*1.05 -> 5512.5 | M10: ='Program Budget'!O201 -> 12 | N10: ='Program Budget'!N201 -> 0.15 | O10: =L10*M10*N10 -> 9922.5 | P10: =L10*1.05 -> 5788.125 | Q10: ='Program Budget'!R201 -> 6 | R10: ='Program Budget'!Q201 -> 0.15 | S10: =P10*Q10*R10 -> 5209.3125 | T10: =C10+G10+K10+O10+S10 -> 33581.812 | AB10: 180 | AC10: 50-01-2-020 | AD10: DIR-USN (Expat) Labor
A11: ='Program Budget'!D202 -> Key Personnel: Technical Director | B11: ='Program Budget'!F202 -> Month | C11: ='Program Budget'!E202 -> 0 | D11: ='Program Budget'!G202 -> 4583.3333 | E11: ='Program Budget'!I202 -> 12 | F11: ='Program Budget'!H202 -> 0.1 | G11: =D11*E11*F11 -> 5500 | H11: =D11*1.05 -> 4812.5 | I11: ='Program Budget'!L202 -> 12 | J11: ='Program Budget'!K202 -> 0.2 | K11: =H11*I11*J11 -> 11550 | L11: =H11*1.05 -> 5053.125 | M11: ='Program Budget'!O202 -> 12 | N11: ='Program Budget'!N202 -> 0.2 | O11: =L11*M11*N11 -> 12127.5 | P11: =L11*1.05 -> 5305.7812 | Q11: ='Program Budget'!R202 -> 5 | R11: ='Program Budget'!Q202 -> 0.2 | S11: =P11*Q11*R11 -> 5305.7812 | T11: =C11+G11+K11+O11+S11 -> 34483.281 | AB11: 180 | AC11: 50-01-2-020 | AD11: DIR-USN (Expat) Labor
A12: ='Program Budget'!D203 -> Activity Lead Agribusiness Senior Specialist (Cacao) | B12: ='Program Budget'!F203 -> Month | C12: ='Program Budget'!E203 -> 0 | D12: ='Program Budget'!G203 -> 2833.3333 | E12: ='Program Budget'!I203 -> 12 | F12: ='Program Budget'!H203 -> 0.15 | G12: =D12*E12*F12 -> 5100 | H12: =D12*1.05 -> 2975 | I12: ='Program Budget'!L203 -> 12 | J12: ='Program Budget'!K203 -> 0.1 | K12: =H12*I12*J12 -> 3570 | L12: =H12*1.05 -> 3123.75 | M12: ='Program Budget'!O203 -> 12 | N12: ='Program Budget'!N203 -> 0.1 | O12: =L12*M12*N12 -> 3748.5 | P12: =L12*1.05 -> 3279.9375 | Q12: ='Program Budget'!R203 -> 2 | R12: ='Program Budget'!Q203 -> 0.1 | S12: =P12*Q12*R12 -> 655.9875 | T12: =C12+G12+K12+O12+S12 -> 13074.487 | AB12: 180 | AC12: 50-01-2-020 | AD12: DIR-USN (Expat) Labor
A13: ='Program Budget'!D204 -> Cacao Field Officer | B13: ='Program Budget'!F204 -> Month | C13: ='Program Budget'!E204 -> 0 | D13: ='Program Budget'!G204 -> 1333.3333 | E13: ='Program Budget'!I204 -> 12 | F13: ='Program Budget'!H204 -> 0 | G13: =D13*E13*F13 -> 0 | H13: =D13*1.05 -> 1400 | I13: ='Program Budget'!L204 -> 12 | J13: ='Program Budget'!K204 -> 0 | K13: =H13*I13*J13 -> 0 | L13: =H13*1.05 -> 1470 | M13: ='Program Budget'!O204 -> 12 | N13: ='Program Budget'!N204 -> 0 | O13: =L13*M13*N13 -> 0 | P13: =L13*1.05 -> 1543.5 | Q13: ='Program Budget'!R204 -> 0 | R13: ='Program Budget'!Q204 -> 0 | S13: =P13*Q13*R13 -> 0 | T13: =C13+G13+K13+O13+S13 -> 0 | AB13: 180 | AC13: 50-01-2-020 | AD13: DIR-USN (Expat) Labor
A14: ='Program Budget'!D205 -> Cacao & Complementary Crop Technical Field Leader (2) | B14: ='Program Budget'!F205 -> Month | C14: ='Program Budget'!E205 -> 0 | D14: ='Program Budget'!G205 -> 3500 | E14: ='Program Budget'!I205 -> 6 | F14: ='Program Budget'!H205 -> 0 | G14: =D14*E14*F14 -> 0 | H14: =D14*1.05 -> 3675 | I14: ='Program Budget'!L205 -> 12 | J14: ='Program Budget'!K205 -> 0 | K14: =H14*I14*J14 -> 0 | L14: =H14*1.05 -> 3858.75 | M14: ='Program Budget'!O205 -> 12 | N14: ='Program Budget'!N205 -> 0 | O14: =L14*M14*N14 -> 0 | P14: =L14*1.05 -> 4051.6875 | Q14: ='Program Budget'!R205 -> 0 | R14: ='Program Budget'!Q205 -> 0 | S14: =P14*Q14*R14 -> 0 | T14: =C14+G14+K14+O14+S14 -> 0
A15: ='Program Budget'!D206 -> Extension Agents (45 in Y5 and 25 in Y6) | B15: ='Program Budget'!F206 -> Month | C15: ='Program Budget'!E206 -> 0 | D15: ='Program Budget'!G206 -> 1000 | E15: ='Program Budget'!I206 -> 12 | F15: ='Program Budget'!H206 -> 0 | G15: =D15*E15*F15 -> 0 | H15: =D15*1.05 -> 1050 | I15: ='Program Budget'!L206 -> 12 | J15: ='Program Budget'!K206 -> 0 | K15: =H15*I15*J15 -> 0 | L15: =H15*1.05 -> 1102.5 | M15: ='Program Budget'!O206 -> 0 | N15: ='Program Budget'!N206 -> 0 | O15: =L15*M15*N15 -> 0 | P15: =L15*1.05 -> 1157.625 | Q15: ='Program Budget'!R206 -> 0 | R15: ='Program Budget'!Q206 -> 0 | S15: =P15*Q15*R15 -> 0 | T15: =C15+G15+K15+O15+S15 -> 0
