Workbook
Name agentfee: #REF!
Name agentfee: Assumptions!$D$51
Name avrent: #REF!
Name avrent: Assumptions!$D$93
Name Category: #REF!
Name Check25: 'SF424'!$A$5
Name Check26: 'SF424'!$A$6
Name Check27: 'SF424'!$A$7
Name Check28: 'SF424'!$D$5
Name Check29: 'SF424'!$D$6
Name Check30: 'SF424'!$D$7
Name Check32: 'SF424'!$A$126
Name Check33: 'SF424'!$A$127
Name Check35: 'SF424'!$A$129
Name Check36: 'SF424'!$A$131
Name coffee: #REF!
Name coffee: Assumptions!$D$90
Name consairfare: #REF!
Name consairfare: Assumptions!$D$76
Name consground: #REF!
Name consground: Assumptions!$D$77
Name conslodg: #REF!
Name conslodg: Assumptions!$D$78
Name consmeals: #REF!
Name consmeals: Assumptions!$D$79
Name consmisc: #REF!
Name consmisc: Assumptions!$D$80
Name DL_Country: '[1]Line-Item Budget'!#REF!
Name DL_Country: #REF!
Name DL_TotalDOL: #REF!
Name Dropdown1: 'SF424'!$G$5
Name Dropdown2: 'SF424'!#REF!
Name EQ_Country: '[1]Line-Item Budget'!#REF!
Name EQ_Country: #REF!
Name EQ_TotalDOL: '[1]Line-Item Budget'!#REF!
Name EQ_TotalDOL: #REF!
Name er: #REF!
Name er: Assumptions!$B$13
Name ground: #REF!
Name ground: Assumptions!$D$55
Name inmuniz: #REF!
Name inmuniz: Assumptions!$D$53
Name intairfare: #REF!
Name intairfare: Assumptions!$D$48
Name intcalls: #REF!
Name intcalls: Assumptions!#REF!
Name intcons: #REF!
Name intcons: Assumptions!$D$73
Name intmisc: #REF!
Name intmisc: Assumptions!$D$56
Name livingq: #REF!
Name livingq: Assumptions!#REF!
Name Local_transport_part: [1]Assumptions!$B$10:$D$10
Name localairfare: #REF!
Name localairfare: Assumptions!$D$69
Name localcons: #REF!
Name localcons: Assumptions!$D$75
Name locallodg: #REF!
Name locallodg: Assumptions!$D$66
Name localmeals: #REF!

Sheet Assumptions
A1: GENERAL ASSUMPTIONS
A3: Header Information:
B4: Partners of America
B5: DONOR: | C5: USDOL
B6: Country: | C6: Ecuador
B7: Program Name: | C7: Project to Improve Adherence to International Labor Standards in the Agricultural Sector in Ecuador
B8: Grant Number: | C8: FOA-ILAB-23-28
B9: Period of Performance: | C9: 48 months | F9: to
A11: Rates:
B12: 0.2828 | C12: NICRA - POA
B13: 0 | C13: Exchange Rate
B14: Inflation - US Based Goods/Services | C14: 1.03
B15: Inflation - Locally Purchased Goods/Services | C15: 1.04
B16: Merit Based Increases for HO & Field Staff | C16: 1.05
A19: ODC Escalation
B20: Escalation Percentage: | D20: 0.03 | G20: Year 1 | H20: Year 2 | I20: Year 3 | J20: Year 2 | M20: Year 3 | N20: Year 2 | O20: Year 2 | P20: Year 4 | Q20: Year 2 | R20: Year 2 | S20: Year 5 | T20: Year 2 | U20: Year 2 | V20: Year 6 | W20: Year 2 | X20: Year 2 | Y20: Year 7 | Z20: Year 2 | AA20: Year 2 | AB20: Year 8 | AC20: Year 2 | AD20: Year 2 | AE20: Year 9 | AF20: Year 2 | AG20: Year 2 | AH20: Year 10
G21: 45292
G22: 45657
G23: 1 | J23: =G23*SUM(1+$D$20) -> 1.03 | M23: =J23*SUM(1+$D$20) -> 1.0609 | P23: =M23*SUM(1+$D$20) -> 1.092727 | S23: =P23*SUM(1+$D$20) -> 1.1255088 | V23: =S23*SUM(1+$D$20) -> 1.1592741 | Y23: =V23*SUM(1+$D$20) -> 1.1940523 | AB23: =Y23*SUM(1+$D$20) -> 1.2298739 | AE23: =AB23*SUM(1+$D$20) -> 1.2667701 | AH23: =AE23*SUM(1+$D$20) -> 1.3047732
A26: Annual Salary Increases for International Staff
A28: Standard Increase Percentage: | D28: 0.04
A29: Annual Salary Escalation Date: | D29: 45566
M30: Percent | S30: Increase Factor | AB30: Percent | AH30: Increase Factor
B32: Year 1 | C32: =G21 -> 45292 | D32: =D29 -> 45566 | E32: =ROUND((D32-C32)/30,0) -> 9 | F32: / | G32: 12 | J32: @ | M32: 0 | P32: =E32/G32*M32 -> 0 | V32: 12 | Y32: @ | AB32: 0 | AE32: =T32/V32*AB32 -> 0
E33: =12-E32 -> 3 | F33: / | G33: 12 | J33: @ | M33: =IF(M32=0,D28,SUM(M32+1)*SUM(1+D28)-1) -> 0.04 | P33: =E33/G33*M33 -> 0.01 | S33: =SUM(1+SUM(P32:P33)) -> 1.01 | V33: 12 | Y33: @ | AB33: =IF(AB32=0,S28,SUM(AB32+1)*SUM(1+S28)-1) -> 0 | AE33: =T33/V33*AB33 -> 0 | AH33: =SUM(1+SUM(AE32:AE33)) -> 1
A35: Annual Salary Increases for Local Staff
A37: Standard Increase Percentage: | D37: 0.05
A38: Annual Salary Escalation Date: | D38: 45474
M39: Percent | S39: Increase Factor | AB39: Percent | AH39: Increase Factor
B41: Year 1 | C41: =G21 -> 45292 | D41: =D38 -> 45474 | E41: =ROUND((D41-C41)/30,0) -> 6 | F41: / | G41: 12 | J41: @ | M41: 0 | P41: =E41/G41*M41 -> 0 | V41: 12 | Y41: @ | AB41: 0 | AE41: =T41/V41*AB41 -> 0
E42: =12-E41 -> 6 | F42: / | G42: 12 | J42: @ | M42: =IF(M41=0,D37,SUM(M41+1)*SUM(1+D38)-1) -> 0.05 | P42: =E42/G42*M42 -> 0.025 | S42: =SUM(1+SUM(P41:P42)) -> 1.025 | V42: 12 | Y42: @ | AB42: =IF(AB41=0,S37,SUM(AB41+1)*SUM(1+S38)-1) -> 0 | AE42: =T42/V42*AB42 -> 0 | AH42: =SUM(1+SUM(AE41:AE42)) -> 1
B46: International Travel | C46: Cell Name | D46: Unit Cost | E46: Base
B47: Quito
B48: Airfare | C48: intairfare | E48: round trip coach
B49: Lodging | C49: usaidlodg | D49: 200 | E49: per night
B50: Meals and Incidentals | C50: usaidmeals | D50: 119 | E50: per day
B51: Agent fee | C51: agentfee | E51: per ticket
B52: Visa | C52: visa | D52: 150
B53: Inmunizations | C53: inmuniz | D53: 150
B54: Medex | C54: medex
B55: Freedom Services | C55: ground | E55: round trip to/from airport
B56: Other Misc costs | C56: intmisc
B59: Incountry Operating Costs - Local Costs
B61: Domestic Travel | D61: Lodging | E61: M&IE | F61: Total
B62: Quito | D62: =190*50% -> 95 | E62: =105*50% -> 52.5 | F62: =SUM(D62:E62) -> 147.5
B63: Cotopaxi | D63: =122*50% -> 61 | E63: =94*50% -> 47 | F63: =SUM(D63:E63) -> 108
B64: El Oro | D64: =122*50% -> 61 | E64: =94*50% -> 47 | F64: =SUM(D64:E64) -> 108 | Q64: 39114 | AF64: 39114
B65: Average Rates | D65: =AVERAGE(D62:D64) -> 72.333333 | E65: =AVERAGE(E62:E64) -> 48.833333 | F65: =SUM(D65:E65) -> 121.16667 | Q65: 39114 | AF65: 39114
B66: Lodging - Local Staff | C66: locallodg | D66: 0 | E66: per day | Q66: 39114 | AF66: 39114
B67: Meals - Local Staff | C67: localmeals | D67: 0 | E67: per day | Q67: 39114 | AF67: 39114
B68: Miscellaneous - Local Staff | C68: localmisc | D68: 0 | E68: per trip | Q68: 39114 | AF68: 39114
B69: Airfare | C69: localairfare | D69: 175 | E69: round trip coach
B71: Training | C71: Cell Name | D71: Unit Cost | E71: Base
B72: Consultant costs
B73: International Consultant | C73: intcons | D73: 0 | E73: honorarium per day
B74: Regional Consultant | C74: regcons | D74: 0 | E74: honorarium per day
B75: Local Consultant | C75: localcons | D75: 300 | E75: honorarium per day
B76: Travel - airfare | C76: consairfare | D76: 0 | E76: per trip
B77: Travel - ground transp | C77: consground | D77: 0 | E77: per trip
B78: Lodging | C78: conslodg | D78: 0 | E78: per night
B79: Meals and Incidentals | C79: consmeals | D79: 0 | E79: per day
B80: Miscellaneous | C80: consmisc | D80: 0 | E80: per trip
B81: Participant costs
B82: Local transport part | C82: parttransp | D82: 4 | E82: per part
B83: Airfare | C83: partairfare | D83: 175 | E83: per trip
B84: Ground Transportation | C84: partground | D84: 9 | E84: per trip
B85: Lodging | C85: partlodg | D85: 25 | E85: per night
B86: Meals and Incidentals | C86: partmeals | D86: =E64 -> 47 | E86: per day
B87: Travel Day Lunch | C87: tdlunch | D87: 12 | E87: per day
B88: Miscellaneous | C88: partmisc | D88: 0 | E88: per trip
B89: Meeting Costs
B90: Coffee Break | C90: coffee | D90: 4 | E90: per person per day
B91: Lunch | C91: lunch | D91: 12 | E91: per person per day
B92: Room Rental | C92: roomrent | D92: 0 | E92: per day
B93: AV Rental | C93: avrent | D93: 0 | E93: per day
B94: Materials & Supplies | C94: mats | D94: 0 | E94: per workshop
B95: Materials & Supplies | C95: partmats | D95: 0 | E95: per participant
B96: Printing costs | C96: print | D96: 50 | E96: per workshop
B97: Printing costs | C97: partprint | D97: 3 | E97: per participant

Sheet Budget Summary
A1: Project Budget Summary
A2: Partners of the Americas
A3: Project to Improve Adherence to International Labor Standards in the Agricultural Sector in Ecuador Improve Adherence to International Labor Standards in the Agricultural Sector in Ecuador
A4: 48 Months
A6: BUDGET SUMMARY CATEGORIES | B6: YEAR 1 | C6: YEAR 2 | D6: YEAR 3 | E6: YEAR 4 | F6: TOTAL FEDERAL FUNDS REQUESTED
A8: 1. PERSONNEL | B8: ='Line-Item Budget'!J29 -> 300905 | C8: ='Line-Item Budget'!L29 -> 375921 | D8: ='Line-Item Budget'!N29 -> 394717.05 | E8: ='Line-Item Budget'!P29 -> 375790.16 | F8: =SUM(B8:E8) -> 1447333.2
A9: 2. FRINGE BENEFITS | B9: ='Line-Item Budget'!J36 -> 128207.47 | C9: ='Line-Item Budget'!L36 -> 155066.69 | D9: ='Line-Item Budget'!N36 -> 162820.03 | E9: ='Line-Item Budget'!P36 -> 154208.46 | F9: =SUM(B9:E9) -> 600302.65
A10: 3. TRAVEL | B10: ='Line-Item Budget'!J54 -> 6938 | C10: ='Line-Item Budget'!L54 -> 42561.48 | D10: ='Line-Item Budget'!N54 -> 42194.838 | E10: ='Line-Item Budget'!P54 -> 33203.173 | F10: =SUM(B10:E10) -> 124897.49
A11: 4. EQUIPMENT | B11: ='Line-Item Budget'!J58 -> 0 | C11: ='Line-Item Budget'!L58 -> 0 | D11: ='Line-Item Budget'!N58 -> 0 | E11: ='Line-Item Budget'!P58 -> 0 | F11: =SUM(B11:E11) -> 0
A12: 5. SUPPLIES | B12: ='Line-Item Budget'!J63 -> 9907.2 | C12: ='Line-Item Budget'!L63 -> 1560 | D12: ='Line-Item Budget'!N63 -> 1622.4 | E12: ='Line-Item Budget'!P63 -> 1687.296 | F12: =SUM(B12:E12) -> 14776.896
A13: 6. CONTRACTUAL | B13: ='Line-Item Budget'!J72 -> 144056.5 | C13: ='Line-Item Budget'!L72 -> 259736.74 | D13: ='Line-Item Budget'!N72 -> 282479.41 | E13: ='Line-Item Budget'!P72 -> 164016.89 | F13: =SUM(B13:E13) -> 850289.54
A14: 7. CONSTRUCTION | B14: 0 | C14: 0 | D14: 0 | E14: 0 | F14: =SUM(B14:E14) -> 0
A15: 8. OTHER DIRECT COSTS | B15: ='Line-Item Budget'!J142 -> 176625.2 | C15: ='Line-Item Budget'!L142 -> 190655.96 | D15: ='Line-Item Budget'!N142 -> 151871.03 | E15: ='Line-Item Budget'!P142 -> 138290.45 | F15: =SUM(B15:E15) -> 657442.64
A17: 9. TOTAL DIRECT COSTS (Lines 1-8) | B17: =SUM(B8:B15) -> 766639.36 | C17: =SUM(C8:C15) -> 1025501.9 | D17: =SUM(D8:D15) -> 1035704.8 | E17: =SUM(E8:E15) -> 867196.43 | F17: =SUM(F8:F15) -> 3695042.4
A18: 10. INDIRECT COSTS | B18: ='Line-Item Budget'!J146 -> 216805.61 | C18: ='Line-Item Budget'!L146 -> 290011.93 | D18: ='Line-Item Budget'!N146 -> 292897.3 | E18: ='Line-Item Budget'!P146 -> 245243.15 | F18: =SUM(B18:E18) -> 1044958
A19: 11. TOTAL COSTS (Lines 9-10) | B19: =SUM(B17:B18) -> 983444.98 | C19: =SUM(C17:C18) -> 1315513.8 | D19: =SUM(D17:D18) -> 1328602.1 | E19: =SUM(E17:E18) -> 1112439.6 | F19: =SUM(F17:F18) -> 4740000.4

Sheet Line-Item Budget
D1: Project Line-Item Budget
D2: Partners of the Americas
D3: Project to Improve Adherence to International Labor Standards in the Agricultural Sector in Ecuador Improve Adherence to International Labor Standards in the Agricultural Sector in Ecuador
D4: 48 Months
A5: Entity: | B5: P | D5: Cost Assumptions
A6: Program-Dept.: | B6: 20200 | D6: Inflation - US Based Goods/Services | E6: 1.03
A7: Funder-Grant: | B7: DOL427 | D7: Inflation - Locally Purchased Goods/Services | E7: 1.04
D8: Merit Based Increases for HO & Field Staff | E8: 1.05
A10: Activity Code | B10: Account Code | C10: Country Code | D10: BUDGET ITEM | E10: CATEGORY | F10: LOE | G10: UNIT | H10: # of Units | I10: RATE / UNIT | J10: Year 1 | K10: # of Units | L10: Year 2 | M10: # of Units | N10: Year 3 | O10: # of Units | P10: Year 4 | Q10: TOTAL DOL | R10: TOTAL COST SHARING | S10: PROJECT GRAND TOTAL
D11: Personnel
D12: Key Personnel
A13: PERSNL-PD | B13: 70000 | C13: ECU | D13: Project Director (100%) - Alexis Naranjo | E13: Salaries | F13: 1 | G13: Month | H13: 12 | I13: =72000/12 -> 6000 | J13: =H13*I13*F13 -> 72000 | K13: 12 | L13: =K13*I13*$E$8 -> 75600 | M13: 12 | N13: =(M13*I13*$E$8*$E$8) -> 79380 | O13: 12 | P13: =O13*I13*$E$8*$E$8*$E$8 -> 83349 | Q13: =SUM(J13+L13+N13+P13) -> 310329 | R13: 0 | S13: =SUM(Q13:R13) -> 310329
A14: PERSNL-M&E | B14: 70000 | C14: ECU | D14: Monitoring and Evaluation (M&E) Officer (100%) - Mónica Rentería | E14: Salaries | F14: 1 | G14: Month | H14: 12 | I14: =40000/12 -> 3333.3333 | J14: =H14*I14*F14 -> 40000 | K14: 12 | L14: =K14*I14*$E$8 -> 42000 | M14: 12 | N14: =(M14*I14*$E$8*$E$8) -> 44100 | O14: 12 | P14: =O14*I14*$E$8*$E$8*$E$8 -> 46305 | Q14: =SUM(J14+L14+N14+P14) -> 172405 | R14: 0 | S14: =SUM(Q14:R14) -> 172405
D16: Other Professional Personnel
A17: PERSNL-PSL | B17: 70000 | C17: ECU | D17: Public Sector Liaison (100%)- Luis Almagor | E17: Salaries | F17: 1 | G17: Month | H17: 9 | I17: =35000/12 -> 2916.6667 | J17: =H17*I17*F17 -> 26250 | K17: 12 | L17: =K17*I17*$E$8 -> 36750 | M17: 12 | N17: =(M17*I17*$E$8*$E$8) -> 38587.5 | O17: 9 | P17: =O17*I17*$E$8*$E$8*$E$8 -> 30387.656 | Q17: =SUM(J17+L17+N17+P17) -> 131975.16 | R17: 0 | S17: =SUM(Q17:R17) -> 131975.16
A18: PERSNL-COM | B18: 70000 | C18: ECU | D18: Communications Specialist (100%) - Emilia Bayas | E18: Salaries | F18: 1 | G18: Month | H18: 9 | I18: 1979 | J18: =H18*I18*F18 -> 17811 | K18: 12 | L18: =K18*I18*$E$8 -> 24935.4 | M18: 12 | N18: =(M18*I18*$E$8*$E$8) -> 26182.17 | O18: 9 | P18: =O18*I18*$E$8*$E$8*$E$8 -> 20618.459 | Q18: =SUM(J18+L18+N18+P18) -> 89547.029 | R18: 0 | S18: =SUM(Q18:R18) -> 89547.029
A19: PERSNL-SAF | B19: 70000 | C19: ECU | D19: Occupational Safety and Health Specialist (100%) - César Ávila | E19: Salaries | F19: 1 | G19: Month | H19: 9 | I19: =35000/12 -> 2916.6667 | J19: =H19*I19*F19 -> 26250 | K19: 12 | L19: =K19*I19*$E$8 -> 36750 | M19: 12 | N19: =(M19*I19*$E$8*$E$8) -> 38587.5 | O19: 9 | P19: =O19*I19*$E$8*$E$8*$E$8 -> 30387.656 | Q19: =SUM(J19+L19+N19+P19) -> 131975.16 | R19: 0 | S19: =SUM(Q19:R19) -> 131975.16
A20: PERSNL-F&A | B20: 70000 | C20: ECU | D20: Finance & Administration Manager (100%) | E20: Salaries | F20: 1 | G20: Month | H20: 12 | I20: 4355 | J20: =H20*I20*F20 -> 52260 | K20: 12 | L20: =K20*I20*$E$8 -> 54873 | M20: 12 | N20: =(M20*I20*$E$8*$E$8) -> 57616.65 | O20: 12 | P20: =O20*I20*$E$8*$E$8*$E$8 -> 60497.483 | Q20: =SUM(J20+L20+N20+P20) -> 225247.13 | R20: 0 | S20: =SUM(Q20:R20) -> 225247.13
A21: PERSNL-OPS | B21: 70000 | C21: ECU | D21: Operations Coordinator (100%) | E21: Salaries | F21: 1 | G21: Month | H21: 12 | I21: =34000/12 -> 2833.3333 | J21: =H21*I21*F21 -> 34000 | K21: 12 | L21: =K21*I21*$E$8 -> 35700 | M21: 12 | N21: =(M21*I21*$E$8*$E$8) -> 37485 | O21: 11 | P21: =O21*I21*$E$8*$E$8*$E$8 -> 36079.313 | Q21: =SUM(J21+L21+N21+P21) -> 143264.31 | R21: 0 | S21: =SUM(Q21:R21) -> 143264.31
A22: PERSNL-RCC | B22: 70000 | C22: ECU | D22: Regional Coordinator 1, Cotopaxi (100%) | E22: Salaries | F22: 1 | G22: Month | H22: 9 | I22: =15000/12-62 -> 1188 | J22: =H22*I22*F22 -> 10692 | K22: 12 | L22: =K22*I22*$E$8 -> 14968.8 | M22: 12 | N22: =(M22*I22*$E$8*$E$8) -> 15717.24 | O22: 9 | P22: =O22*I22*$E$8*$E$8*$E$8 -> 12377.327 | Q22: =SUM(J22+L22+N22+P22) -> 53755.367 | R22: 0 | S22: =SUM(Q22:R22) -> 53755.367
A23: PERSNL-RCO | B23: 70000 | C23: ECU | D23: Regional Coordinator 2, El Oro (100%) | E23: Salaries | F23: 1 | G23: Month | H23: 9 | I23: =15000/12-62 -> 1188 | J23: =H23*I23*F23 -> 10692 | K23: 12 | L23: =K23*I23*$E$8 -> 14968.8 | M23: 12 | N23: =(M23*I23*$E$8*$E$8) -> 15717.24 | O23: 9 | P23: =O23*I23*$E$8*$E$8*$E$8 -> 12377.327 | Q23: =SUM(J23+L23+N23+P23) -> 53755.367 | R23: 0 | S23: =SUM(Q23:R23) -> 53755.367
D25: Home Office Support
A26: PERSNL-PM | B26: 50000 | C26: USA | D26: Project Manager (10%) | E26: Salaries | F26: 0.1 | G26: Month | H26: 12 | I26: =(135000/12)*0.1 -> 1125 | J26: =H26*I26*F26 -> 1350 | K26: 12 | L26: =K26*I26*$E$8 -> 14175 | M26: 12 | N26: =(M26*I26*$E$8*$E$8) -> 14883.75 | O26: 12 | P26: =O26*I26*$E$8*$E$8*$E$8 -> 15627.938 | Q26: =SUM(J26+L26+N26+P26) -> 46036.688 | R26: 0 | S26: =SUM(Q26:R26) -> 46036.688
A27: PERSNL-PO | B27: 50000 | C27: USA | D27: Program Officer (40%) | E27: Salaries | F27: 0.4 | G27: Month | H27: 12 | I27: =(60000/12)*0.4 -> 2000 | J27: =H27*I27*F27 -> 9600 | K27: 12 | L27: =K27*I27*$E$8 -> 25200 | M27: 12 | N27: =(M27*I27*$E$8*$E$8) -> 26460 | O27: 12 | P27: =O27*I27*$E$8*$E$8*$E$8 -> 27783 | Q27: =SUM(J27+L27+N27+P27) -> 89043 | R27: 0 | S27: =SUM(Q27:R27) -> 89043
D29: Total Personnel | J29: =SUM(J13:J27) -> 300905 | L29: =SUM(L13:L27) -> 375921 | N29: =SUM(N13:N27) -> 394717.05 | P29: =SUM(P13:P27) -> 375790.16 | Q29: =SUM(Q13:Q27) -> 1447333.2 | R29: =SUM(R13:R27) -> 0 | S29: =SUM(Q29:R29) -> 1447333.2
D30: Fringe Benefits
D32: Fringe Benefits
A33: FRINGE-EC | B33: 70015 | C33: ECU | D33: Fringe benefits - Ecuador | E33: Fringe Benefits | G33: Month | I33: 0.4333 | J33: =SUM(J13:J23)*$I33 -> 125637.5 | L33: =SUM(L13:L23)*$I33 -> 145825.38 | N33: =SUM(N13:N23)*$I33 -> 153116.65 | P33: =SUM(P13:P23)*$I33 -> 144019.92 | Q33: =SUM(J33+L33+N33+P33) -> 568599.45 | R33: 0 | S33: =SUM(Q33:R33) -> 568599.45
A34: FRINGE | B34: 50900 | C34: USA | D34: Fringe benefits - Home Office Support | E34: Fringe Benefits | G34: Month | I34: 0.2347 | J34: =SUM(J26:J27)*$I$34 -> 2569.965 | L34: =SUM(L26:L27)*$I$34 -> 9241.3125 | N34: =SUM(N26:N27)*$I$34 -> 9703.3781 | P34: =SUM(P26:P27)*$I$34 -> 10188.547 | Q34: =SUM(J34+L34+N34+P34) -> 31703.203 | R34: 0 | S34: =SUM(Q34:R34) -> 31703.203
D36: Total Fringe Benefits | J36: =SUM(J33:J35) -> 128207.47 | L36: =SUM(L33:L35) -> 155066.69 | N36: =SUM(N33:N35) -> 162820.03 | P36: =SUM(P33:P35) -> 154208.46 | Q36: =SUM(Q33:Q35) -> 600302.65 | R36: =SUM(R34:R34) -> 0 | S36: =SUM(S33:S35) -> 600302.65
D37: Travel
D38: T1: Post-award Meeting with ILAB
A39: EC.T1.A | B39: 86040 | C39: ECU/USA | D39: Airfare - Ecuador-DC | E39: Travel | G39: Trip | I39: 650 | J39: =H39*I39 -> 0 | K39: 2 | L39: =K39*I39*$E$7 -> 1352 | M39: 0 | N39: =M39*I39*$E$7*$E$7 -> 0 | O39: 0 | P39: =O39*I39*$E$7*$E$7*$E$7 -> 0 | Q39: =SUM(J39+L39+N39+P39) -> 1352 | R39: - | S39: =SUM(Q39:R39) -> 1352
A40: EC.T1.B | B40: 86030 (Lodging)/ 86050 (M&IE) | C40: ECU/USA | D40: Lodging and M&IE in DC | E40: Travel | G40: Day | I40: =(258+79)*90% -> 303.3 | J40: =H40*I40 -> 0 | K40: 10 | L40: =K40*I40*$E$7 -> 3154.32 | M40: 0 | N40: =M40*I40*$E$7*$E$7 -> 0 | O40: 0 | P40: =O40*I40*$E$7*$E$7*$E$7 -> 0 | Q40: =SUM(J40+L40+N40+P40) -> 3154.32 | R40: - | S40: =SUM(Q40:R40) -> 3154.32
A41: EC.T1.C | B41: 86000 | C41: ECU/USA | D41: Local transportation in DC | E41: Travel | G41: Day | I41: 60 | J41: =H41*I41 -> 0 | K41: 10 | L41: =K41*I41*$E$7 -> 624 | M41: 0 | N41: =M41*I41*$E$7*$E$7 -> 0 | O41: 0 | P41: =O41*I41*$E$7*$E$7*$E$7 -> 0 | Q41: =SUM(J41+L41+N41+P41) -> 624 | R41: - | S41: =SUM(Q41:R41) -> 624
A42: EC.T1.D | B42: 86050 | C42: ECU/USA | D42: U.S. Visa Fees | E42: Travel | G42: Trip | I42: 160 | J42: =H42*I42 -> 0 | K42: 2 | L42: =K42*I42*$E$7 -> 332.8 | M42: 0 | N42: =M42*I42*$E$7*$E$7 -> 0 | O42: 0 | P42: =O42*I42*$E$7*$E$7*$E$7 -> 0 | Q42: =SUM(J42+L42+N42+P42) -> 332.8 | R42: - | S42: =SUM(Q42:R42) -> 332.8
D43: T2: Field Personnel Annual Visits with ILAB
A44: EC.T2.A | B44: 86040 | C44: ECU | D44: Airfare - Ecuador-DC | E44: Travel | G44: Trip | H44: 2 | I44: 650 | J44: =H44*I44 -> 1300 | K44: 2 | L44: =K44*I44*$E$7 -> 1352 | M44: 2 | N44: =M44*I44*$E$7*$E$7 -> 1406.08 | O44: 2 | P44: =O44*I44*$E$7*$E$7*$E$7 -> 1462.3232 | Q44: =SUM(J44+L44+N44+P44) -> 5520.4032 | R44: - | S44: =SUM(Q44:R44) -> 5520.4032
A45: EC.T2.B | B45: 86030 (Lodging)/ 86050 (M&IE) | C45: ECU | D45: Lodging and M&IE in DC | E45: Travel | G45: Day | H45: 5 | I45: =(258+79)*90% -> 303.3 | J45: =H45*I45 -> 1516.5 | K45: 10 | L45: =K45*I45*$E$7 -> 3154.32 | M45: 10 | N45: =M45*I45*$E$7*$E$7 -> 3280.4928 | O45: 10 | P45: =O45*I45*$E$7*$E$7*$E$7 -> 3411.7125 | Q45: =SUM(J45+L45+N45+P45) -> 11363.025 | R45: - | S45: =SUM(Q45:R45) -> 11363.025
A46: EC.T2.C | B46: 86000 | C46: ECU | D46: Local transportation in DC | E46: Travel | G46: Day | H46: 5 | I46: 60 | J46: =H46*I46 -> 300 | K46: 10 | L46: =K46*I46*$E$7 -> 624 | M46: 10 | N46: =M46*I46*$E$7*$E$7 -> 648.96 | O46: 10 | P46: =O46*I46*$E$7*$E$7*$E$7 -> 674.9184 | Q46: =SUM(J46+L46+N46+P46) -> 2247.8784 | R46: - | S46: =SUM(Q46:R46) -> 2247.8784
D47: T3: Home Support Annual Visits to Field
A48: EC.T3.A | B48: 86040 | C48: ECU | D48: Airfare - DC - Ecuador | E48: Travel | G48: Trip | H48: 1 | I48: 650 | J48: =H48*I48 -> 650 | K48: 1 | L48: =K48*I48*$E$7 -> 676 | M48: 1 | N48: =M48*I48*$E$7*$E$7 -> 703.04 | O48: 1 | P48: =O48*I48*$E$7*$E$7*$E$7 -> 731.1616 | Q48: =SUM(J48+L48+N48+P48) -> 2760.2016 | R48: - | S48: =SUM(Q48:R48) -> 2760.2016
A49: EC.T3.B | B49: 86030 (Lodging)/ 86050 (M&IE) | C49: ECU | D49: Lodging and M&IE in Quito | E49: Travel | G49: Day | H49: 5 | I49: =(295)*90% -> 265.5 | J49: =H49*I49 -> 1327.5 | K49: 7 | L49: =K49*I49*$E$7 -> 1932.84 | M49: 7 | N49: =M49*I49*$E$7*$E$7 -> 2010.1536 | O49: 7 | P49: =O49*I49*$E$7*$E$7*$E$7 -> 2090.5597 | Q49: =SUM(J49+L49+N49+P49) -> 7361.0533 | R49: - | S49: =SUM(Q49:R49) -> 7361.0533
A50: EC.T3.C | B50: 86000 | C50: ECU | D50: Local transportation in Quito | E50: Travel | G50: Day | H50: 5 | I50: 60 | J50: =H50*I50 -> 300 | K50: 7 | L50: =K50*I50*$E$7 -> 436.8 | M50: 7 | N50: =M50*I50*$E$7*$E$7 -> 454.272 | O50: 7 | P50: =O50*I50*$E$7*$E$7*$E$7 -> 472.44288 | Q50: =SUM(J50+L50+N50+P50) -> 1663.5149 | R50: - | S50: =SUM(Q50:R50) -> 1663.5149
A51: EC.T3.D | B51: 86050 | C51: ECU | D51: Ecuador Visa Fees | E51: Travel | G51: Trip | H51: 1 | I51: 160 | J51: =H51*I51 -> 160 | K51: 1 | L51: =K51*I51*$E$7 -> 166.4 | M51: 1 | N51: =M51*I51*$E$7*$E$7 -> 173.056 | O51: 1 | P51: =O51*I51*$E$7*$E$7*$E$7 -> 179.97824 | Q51: =SUM(J51+L51+N51+P51) -> 679.43424 | R51: - | S51: =SUM(Q51:R51) -> 679.43424
A52: EC.T4.A | B52: 86000 (Transport)/ 86030 (Lodging)/ 86050 (M&IE) | C52: ECU | D52: T4: Domestic Travel to Field (See Travel Detail Tab) | J52: =' Activities Detail'!M292 -> 1384 | L52: =' Activities Detail'!P292 -> 28756 | N52: =' Activities Detail'!S292 -> 33518.784 | P52: =' Activities Detail'!V292 -> 24180.077 | Q52: =SUM(J52+L52+N52+P52) -> 87838.861 | S52: =SUM(Q52:R52) -> 87838.861
D54: Total Travel | J54: =SUM(J39:J52) -> 6938 | L54: =SUM(L39:L52) -> 42561.48 | N54: =SUM(N39:N52) -> 42194.838 | P54: =SUM(P39:P52) -> 33203.173 | Q54: =SUM(Q39:Q52) -> 124897.49 | R54: =SUM(R39:R52) -> 0 | S54: =SUM(Q54:R54) -> 124897.49
D55: Equipment
A56: NONE | B56: NONE | C56: NONE | D56: None | E56: Equipment | G56: Unit | K56: 0 | L56: =K56*I56*Assumptions!$C$15 -> 0 | M56: 0 | N56: =M56*I56*Assumptions!$C$15*Assumptions!$C$15 -> 0 | O56: 0 | P56: =O56*I56*Assumptions!$C$15*Assumptions!$C$15*Assumptions!$C$15 -> 0 | Q56: =SUM(J56+L56+N56+P56) -> 0 | R56: 0 | S56: =SUM(Q56:R56) -> 0
D58: Total Equipment | J58: =SUM(J56) -> 0 | L58: =SUM(L56) -> 0 | N58: =SUM(N56) -> 0 | P58: =SUM(P56) -> 0 | Q58: =SUM(Q56) -> 0 | R58: =SUM(R56) -> 0 | S58: =SUM(Q58:R58) -> 0
D59: Supplies
A60: LAPTOP | B60: 82401 | C60: ECU/USA | D60: Laptop computers & software | E60: Supplies | G60: Unit | H60: 7 | I60: =1254.6 -> 1254.6 | J60: =H60*I60 -> 8782.2 | L60: =K60*I60*$E$7 -> 0 | M60: 0 | N60: =M60*I60*$E$7*$E$7 -> 0 | O60: 0 | P60: =O60*I60*$E$7*$E$7*$E$7 -> 0 | Q60: =SUM(J60+L60+N60+P60) -> 8782.2 | R60: 0 | S60: =SUM(Q60:R60) -> 8782.2
A61: SUPPLIES | B61: 82401 | C61: ECU/USA | D61: Office supplies | E61: Supplies | G61: Month | H61: 9 | I61: 125 | J61: =I61*H61 -> 1125 | K61: 12 | L61: =K61*I61*$E$7 -> 1560 | M61: 12 | N61: =M61*I61*$E$7*$E$7 -> 1622.4 | O61: 12 | P61: =O61*I61*$E$7*$E$7*$E$7 -> 1687.296 | Q61: =SUM(J61+L61+N61+P61) -> 5994.696 | R61: 0 | S61: =SUM(Q61:R61) -> 5994.696
D63: Total Supplies | J63: =SUM(J60:J61) -> 9907.2 | L63: =SUM(L60:L61) -> 1560 | N63: =SUM(N60:N61) -> 1622.4 | P63: =SUM(P60:P61) -> 1687.296 | Q63: =SUM(Q60:Q61) -> 14776.896 | R63: =SUM(R60:R61) -> 0 | S63: =SUM(Q63:R63) -> 14776.896
D64: Contractual
A66: EXPOFLOR | B66: 89050 | C66: ECU | D66: Expoflores | E66: Contractual | G66: Contract | H66: 1 | J66: 10000 | K66: 1 | L66: 20000 | M66: 1 | N66: 20000 | O66: 1 | P66: 10000 | Q66: =SUM(J66+L66+N66+P66) -> 60000 | S66: =SUM(Q66:R66) -> 60000
A67: CLAC | B67: 89050 | C67: ECU | D67: CLAC | E67: Contractual | G67: Contract | H67: 1 | K67: 1 | L67: 15000 | M67: 1 | N67: 15000 | O67: 1 | P67: 10000 | Q67: =SUM(J67+L67+N67+P67) -> 40000 | S67: =SUM(Q67:R67) -> 40000
A68: ASTAC | B68: 89050 | C68: ECU | D68: ASTAC | E68: Contractual | G68: Contract | H68: 1 | K68: 1 | L68: 7500 | M68: 1 | N68: 10000 | O68: 1 | P68: 17500 | Q68: =SUM(J68+L68+N68+P68) -> 35000 | S68: =SUM(Q68:R68) -> 35000
A69: ASOPRO | B69: 89050 | C69: ECU | D69: ASOPROTRABAN | E69: Contractual | G69: Contract | H69: 1 | K69: 1 | L69: 7500 | M69: 1 | N69: 10000 | O69: 1 | P69: 17500 | Q69: =SUM(J69+L69+N69+P69) -> 35000 | S69: =SUM(Q69:R69) -> 35000
A70: BANABIO | B70: 89050 | C70: ECU | D70: BANABIO | E70: Contractual | G70: Contract | H70: 1 | L70: 15000 | N70: 15000 | O70: 1 | P70: 10000 | Q70: =SUM(J70+L70+N70+P70) -> 40000 | S70: =SUM(Q70:R70) -> 40000
A71: SUBINDES | B71: 89050 | C71: ECU | D71: INDES | E71: Contractual | G71: Contract | H71: 1 | J71: ='INDES Sub Budget Summary'!B19 -> 134056.5 | K71: 1 | L71: ='INDES Sub Budget Summary'!C19 -> 194736.74 | M71: 1 | N71: ='INDES Sub Budget Summary'!D19 -> 212479.41 | O71: 1 | P71: ='INDES Sub Budget Summary'!E19 -> 99016.895 | Q71: =SUM(J71+L71+N71+P71) -> 640289.54 | S71: =SUM(Q71:R71) -> 640289.54
D72: Total Contractual | J72: =SUM(J65:J71) -> 144056.5 | L72: =SUM(L65:L71) -> 259736.74 | N72: =SUM(N65:N71) -> 282479.41 | P72: =SUM(P65:P71) -> 164016.89 | Q72: =SUM(Q65:Q71) -> 850289.54 | R72: =SUM(R65:R71) -> 0 | S72: =SUM(S65:S71) -> 850289.54
D73: Other Direct Costs
D74: Project Office
A75: BANK FEES | B75: 90900 | C75: ECU | D75: Banking and cash handling fees | E75: Office Expenses | G75: Month | H75: 12 | I75: 50 | J75: =H75*I75 -> 600 | K75: 12 | L75: =K75*I75*$E$7 -> 624 | M75: 12 | N75: =M75*I75*$E$7*$E$7 -> 648.96 | O75: 12 | P75: =O75*I75*$E$7*$E$7*$E$7 -> 674.9184 | Q75: =SUM(J75+L75+N75+P75) -> 2547.8784 | R75: 0 | S75: =SUM(Q75:R75) -> 2547.8784
A76: COURIER | B76: 82350 | C76: ECU | D76: Courier fees/services | E76: Office Expenses | G76: Year | H76: 1 | I76: 70 | J76: =H76*I76 -> 70 | K76: 1 | L76: =K76*I76*$E$7 -> 72.8 | M76: 1 | N76: =M76*I76*$E$7*$E$7 -> 75.712 | O76: 1 | P76: =O76*I76*$E$7*$E$7*$E$7 -> 78.74048 | Q76: =SUM(J76+L76+N76+P76) -> 297.25248 | R76: 0 | S76: =SUM(Q76:R76) -> 297.25248
A77: RECRUIT | B77: 90450 | C77: ECU/USA | D77: Recruitment/Procurement Advertising | E77: Office Expenses | G77: Per position | H77: 4 | I77: 262.56 | J77: =H77*I77 -> 1050.24 | L77: =K77*I77*$E$7 -> 0 | N77: =M77*I77*$E$7*$E$7 -> 0 | P77: =O77*I77*$E$7*$E$7*$E$7 -> 0 | Q77: =SUM(J77+L77+N77+P77) -> 1050.24 | R77: 0 | S77: =SUM(Q77:R77) -> 1050.24
A78: COMM | B78: 82030 | C78: ECU | D78: Communications Costs (Data) | E78: Office Expenses | G78: Month | H78: 9 | I78: 150 | J78: =H78*I78 -> 1350 | K78: 12 | L78: =K78*I78*$E$7 -> 1872 | M78: 12 | N78: =M78*I78*$E$7*$E$7 -> 1946.88 | O78: 12 | P78: =O78*I78*$E$7*$E$7*$E$7 -> 2024.7552 | Q78: =SUM(J78+L78+N78+P78) -> 7193.6352 | R78: 0 | S78: =SUM(Q78:R78) -> 7193.6352
A79: RENT & UT | B79: 85180 | C79: ECU | D79: Coworking office space (includes utilities, Wi-Fi, coffee) | E79: Office Expenses | G79: Month | H79: 9 | I79: 1500 | J79: =H79*I79 -> 13500 | K79: 12 | L79: =K79*I79*$E$7 -> 18720 | M79: 12 | N79: =M79*I79*$E$7*$E$7 -> 19468.8 | O79: 12 | P79: =O79*I79*$E$7*$E$7*$E$7 -> 20247.552 | Q79: =SUM(J79+L79+N79+P79) -> 71936.352 | R79: 0 | S79: =SUM(Q79:R79) -> 71936.352
A80: PROP&LIAB | B80: 89500 | C80: ECU | D80: Property and liability insurance | E80: Office Expenses | G80: Year | H80: 1 | I80: 250 | J80: =H80*I80 -> 250 | K80: 1 | L80: =K80*I80*$E$7 -> 260 | M80: 1 | N80: =M80*I80*$E$7*$E$7 -> 270.4 | O80: 1 | P80: =O80*I80*$E$7*$E$7*$E$7 -> 281.216 | Q80: =SUM(J80+L80+N80+P80) -> 1061.616 | R80: 0 | S80: =SUM(Q80:R80) -> 1061.616
A81: LEGAL | B81: 90100 | C81: ECU | D81: Legal fees | E81: Office Expenses | G81: Year | H81: 1 | I81: 2200 | J81: =I81*H81 -> 2200 | K81: 1 | L81: =K81*I81*$E$7 -> 2288 | M81: 1 | N81: =M81*I81*$E$7*$E$7 -> 2379.52 | O81: 1 | P81: =O81*I81*$E$7*$E$7*$E$7 -> 2474.7008 | Q81: =SUM(J81+L81+N81+P81) -> 9342.2208 | R81: 0 | S81: =SUM(Q81:R81) -> 9342.2208
A82: PAYROLL | B82: 81030 | C82: ECU | D82: Payroll Processing | E82: Office Expenses | G82: Month | H82: 12 | I82: 350 | J82: =H82*I82 -> 4200 | K82: 12 | L82: =K82*I82*$E$7 -> 4368 | M82: 12 | N82: =M82*I82*$E$7*$E$7 -> 4542.72 | O82: 12 | P82: =O82*I82*$E$7*$E$7*$E$7 -> 4724.4288 | Q82: =SUM(J82+L82+N82+P82) -> 17835.149 | R82: - | S82: =SUM(Q82:R82) -> 17835.149
A83: SUBSCRIPT | B83: 89400 | C83: ECU/USA | D83: HR platform for timekeeping and expense reporting | E83: Office Expenses | G83: Month | H83: 12 | I83: 150 | J83: =H83*I83 -> 1800 | K83: 12 | L83: =K83*I83*$E$7 -> 1872 | M83: 12 | N83: =M83*I83*$E$7*$E$7 -> 1946.88 | O83: 12 | P83: =O83*I83*$E$7*$E$7*$E$7 -> 2024.7552 | Q83: =SUM(J83+L83+N83+P83) -> 7643.6352 | R83: 0 | S83: =SUM(Q83:R83) -> 7643.6352
A84: SUBSCRIPT | B84: 89400 | C84: ECU/USA | D84: Zoom license and platform subscriptions | E84: Office Expenses | G84: Year | H84: 1 | I84: 1120 | J84: =H84*I84 -> 1120 | K84: 1 | L84: =K84*I84*$E$7 -> 1164.8 | M84: 1 | N84: =M84*I84*$E$7*$E$7 -> 1211.392 | O84: 1 | P84: =O84*I84*$E$7*$E$7*$E$7 -> 1259.8477 | Q84: =SUM(J84+L84+N84+P84) -> 4756.0397 | R84: 0 | S84: =SUM(Q84:R84) -> 4756.0397
A85: SECURITY | B85: 86110 | C85: ECU | D85: Security Provider | E85: Office Expenses | G85: Month | H85: 12 | I85: 333.33 | J85: =H85*I85 -> 3999.96 | K85: 12 | L85: =K85*I85*$E$7 -> 4159.9584 | M85: 12 | N85: =M85*I85*$E$7*$E$7 -> 4326.3567 | O85: 12 | P85: =O85*I85*$E$7*$E$7*$E$7 -> 4499.411 | Q85: =SUM(J85+L85+N85+P85) -> 16985.686 | R85: 0 | S85: =SUM(Q85:R85) -> 16985.686
A86: VISUALCOM | B86: 89400 | C86: ECU | D86: Visual Asset Communications | E86: Office Expenses | G86: Year | H86: 1 | I86: 5000 | J86: =H86*I86 -> 5000 | K86: 0 | L86: 20000 | M86: 1 | N86: 15000 | O86: 0 | P86: 10000 | Q86: =SUM(J86+L86+N86+P86) -> 50000 | R86: 0 | S86: =SUM(Q86:R86) -> 50000
D87: Subtotal Project Office, Audit, Communications | J87: =SUM(J75:J86) -> 35140.2 | L87: =SUM(L75:L86) -> 55401.558 | N87: =SUM(N75:N86) -> 51817.621 | P87: =SUM(P75:P86) -> 48290.326 | Q87: =SUM(Q75:Q86) -> 190649.7 | S87: =SUM(S75:S86) -> 190649.7
D88: Outcome 1
A89: See activities tab | B89: See activities tab | C89: ECU | D89: Activity 1.1. Assess labor law enforcement institutions, processes, and services: challenges and opportunities for action to address child labor and forced labor | E89: Outcome1 | J89: =' Activities Detail'!M15 -> 5400 | Q89: =SUM(J89+L89+N89+P89) -> 5400 | S89: =SUM(Q89:R89) -> 5400
A90: See activities tab | B90: See activities tab | C90: ECU | D90: Activity 1.2. Strengthen intersectoral coordination by re-invigorating referral mechanisms and strengthening Consejos and Juntas: | E90: Outcome1 | J90: =' Activities Detail'!M24 -> 4800 | L90: =' Activities Detail'!P24 -> 3744 | Q90: =SUM(J90+L90+N90+P90) -> 8544 | S90: =SUM(Q90:R90) -> 8544
A91: See activities tab | B91: See activities tab | C91: ECU | D91: Activity 1.3. Develop government capacity building strategy applying assessment results | E91: Outcome1 | J91: =' Activities Detail'!M34 -> 0 | L91: =' Activities Detail'!P34 -> 0 | N91: =' Activities Detail'!S34 -> 0 | P91: =' Activities Detail'!V34 -> 0 | Q91: =SUM(J91+L91+N91+P91) -> 0 | S91: =SUM(Q91:R91) -> 0
A92: See activities tab | B92: See activities tab | C92: ECU | D92: Activity 1.4. Develop, deliver, and institutionalize tailored capacity building for government officials: | E92: Outcome1 | J92: =' Activities Detail'!M42 -> 0 | L92: =' Activities Detail'!P42 -> 2184 | N92: =' Activities Detail'!S42 -> 2271.36 | P92: =' Activities Detail'!V42 -> 1181.1072 | Q92: =SUM(J92+L92+N92+P92) -> 5636.4672 | S92: =SUM(Q92:R92) -> 5636.4672
A93: See activities tab | B93: See activities tab | C93: ECU | D93: Activity 1.5. Strengthen digital child labor tracking and public reporting/accountability: | E93: Outcome1 | J93: =' Activities Detail'!M55 -> 75000 | L93: =' Activities Detail'!P55 -> 0 | N93: =' Activities Detail'!S55 -> 0 | P93: =' Activities Detail'!V55 -> 0 | Q93: =SUM(J93+L93+N93+P93) -> 75000 | S93: =SUM(Q93:R93) -> 75000
A94: See activities tab | B94: See activities tab | C94: ECU | D94: Activity 1.6. Partner with GADs to integrate enforcement processes and capacity building into local community development plans and budgets: | E94: Outcome1 | J94: =' Activities Detail'!M73 -> 0 | L94: =' Activities Detail'!P73 -> 5896.8 | N94: =' Activities Detail'!S73 -> 6132.672 | P94: =' Activities Detail'!V73 -> 4251.9859 | Q94: =SUM(J94+L94+N94+P94) -> 16281.458 | S94: =SUM(Q94:R94) -> 16281.458
A95: See activities tab | B95: See activities tab | C95: ECU | D95: Activity 1.7 Disseminate successes: | E95: Outcome1 | J95: =' Activities Detail'!M92 -> 0 | L95: =' Activities Detail'!P92 -> 0 | N95: =' Activities Detail'!S92 -> 5191.68 | P95: =' Activities Detail'!V92 -> 3599.5648 | Q95: =SUM(J95+L95+N95+P95) -> 8791.2448 | S95: =SUM(Q95:R95) -> 8791.2448
J96: =SUM(J89:J95) -> 85200 | L96: =SUM(L89:L95) -> 11824.8 | N96: =SUM(N89:N95) -> 13595.712 | P96: =SUM(P89:P95) -> 9032.6579 | Q96: =SUM(Q89:Q95) -> 119653.17 | S96: =SUM(Q96:R96) -> 119653.17
D97: Outcome 2
A98: See activities tab | B98: See activities tab | C98: ECU | D98: Activity 2.1. Assess rural workers’ information needs, work experiences, and trusted organizations | E98: Outcome2 | J98: =' Activities Detail'!M100 -> 4500 | L98: =' Activities Detail'!P100 -> 0 | N98: =' Activities Detail'!S100 -> 0 | P98: =' Activities Detail'!V100 -> 0 | Q98: =SUM(J98+L98+N98+P98) -> 4500 | S98: =SUM(Q98:R98) -> 4500
A99: See activities tab | B99: See activities tab | C99: ECU | D99: Activity 2.2. Build capacity of worker organizations, producer associations, and other actors to reach workers to understand their rights | E99: Outcome2 | J99: =' Activities Detail'!M117 -> 0 | L99: =' Activities Detail'!P117 -> 7644 | N99: =' Activities Detail'!S117 -> 7949.76 | P99: =' Activities Detail'!V117 -> 0 | Q99: =SUM(J99+L99+N99+P99) -> 15593.76 | S99: =SUM(Q99:R99) -> 15593.76
A100: See activities tab | B100: See activities tab | C100: ECU | D100: Activity 2.3. Institutionalize worker and community training and awareness-raising | E100: Outcome2 | J100: =' Activities Detail'!M131 -> 0 | L100: =' Activities Detail'!P131 -> 0 | N100: =' Activities Detail'!S131 -> 0 | P100: =' Activities Detail'!V131 -> 7649.0752 | Q100: =SUM(J100+L100+N100+P100) -> 7649.0752 | S100: =SUM(Q100:R100) -> 7649.0752
A101: See activities tab | B101: See activities tab | C101: ECU | D101: Activity 2.4. Establish and convene neutral spaces for bipartite and tripartite social dialogue | E101: Outcome2 | J101: =' Activities Detail'!M140 -> 0 | L101: =' Activities Detail'!P140 -> 1726.4 | N101: =' Activities Detail'!S140 -> 5386.368 | P101: =' Activities Detail'!V140 -> 1867.2742 | Q101: =SUM(J101+L101+N101+P101) -> 8980.0422 | S101: =SUM(Q101:R101) -> 8980.0422
A102: See activities tab | B102: See activities tab | C102: ECU | D102: Activity 2.5. Train small, medium, and large employers to engage workers, understand workers’ rights, and monitor rights compliance in their supply chains | E102: Outcome2 | J102: =' Activities Detail'!M149 -> 0 | L102: =' Activities Detail'!P149 -> 14352 | N102: =' Activities Detail'!S149 -> 14926.08 | P102: =' Activities Detail'!V149 -> 0 | Q102: =SUM(J102+L102+N102+P102) -> 29278.08 | S102: =SUM(Q102:R102) -> 29278.08
A103: See activities tab | B103: See activities tab | C103: ECU | D103: 2.6 Partner with GADs to integrate the above training, awareness-raising, and social dialogue activities into community development plans | E103: Outcome2 | J103: =' Activities Detail'!M163 -> 0 | L103: =' Activities Detail'!P163 -> 0 | N103: =' Activities Detail'!S163 -> 886.912 | P103: =' Activities Detail'!V163 -> 922.38848 | Q103: =SUM(J103+L103+N103+P103) -> 1809.3005 | S103: =SUM(Q103:R103) -> 1809.3005
A104: See activities tab | B104: See activities tab | C104: ECU | D104: Activity 2.7. Generate new opportunities for learning among civil society, workers, government, private sector, and others. | E104: Outcome2 | J104: =' Activities Detail'!M182 -> 0 | L104: =' Activities Detail'!P182 -> 0 | N104: =' Activities Detail'!S182 -> 3547.648 | P104: =' Activities Detail'!V182 -> 3689.5539 | Q104: =SUM(J104+L104+N104+P104) -> 7237.2019 | S104: =SUM(Q104:R104) -> 7237.2019
A105: See activities tab | B105: See activities tab | C105: ECU | D105: Activity 2.8. Assess changes in rural workers’, business, Community-Based Organizations, and government officials’ knowledge, skills, and practices. | E105: Outcome2 | J105: =' Activities Detail'!M201 -> 0 | L105: =' Activities Detail'!P201 -> 2184 | N105: =' Activities Detail'!S201 -> 2271.36 | P105: =' Activities Detail'!V201 -> 2362.2144 | Q105: =SUM(J105+L105+N105+P105) -> 6817.5744 | S105: =SUM(Q105:R105) -> 6817.5744
D106: Subtotal Outcome 2 | J106: =SUM(J98:J105) -> 4500 | L106: =SUM(L98:L105) -> 25906.4 | N106: =SUM(N98:N105) -> 34968.128 | P106: =SUM(P98:P105) -> 16490.506 | Q106: =SUM(Q98:Q105) -> 81865.034 | S106: =SUM(Q106:R106) -> 81865.034
D107: Outcome 3 | S107: =SUM(Q107:R107) -> 0
A108: See activities tab | B108: See activities tab | C108: ECU | D108: Activity 3.1- Undertake Remediation Constraints and Opportunities Analysis | E108: Outcome3 | J108: 0 | L108: 0 | N108: 0 | P108: 0 | Q108: 0 | S108: =SUM(Q108:R108) -> 0
A109: See activities tab | B109: See activities tab | C109: ECU | D109: Activity 3.2 Validate analysis and select pilot remediation mechanism designs | E109: Outcome3 | J109: =' Activities Detail'!M232 -> 0 | L109: =' Activities Detail'!P232 -> 2808 | N109: =' Activities Detail'!S232 -> 0 | P109: =' Activities Detail'!V232 -> 0 | Q109: =SUM(J109+L109+N109+P109) -> 2808 | S109: =SUM(Q109:R109) -> 2808
A110: See activities tab | B110: See activities tab | C110: ECU | D110: Activity 3.3. Engage partners to design, implement, and monitor pilot remediations solutions | E110: Outcome3 | J110: =' Activities Detail'!M239 -> 0 | L110: =' Activities Detail'!P239 -> 13416 | N110: =' Activities Detail'!S239 -> 27905.28 | P110: =' Activities Detail'!V239 -> 0 | Q110: =SUM(J110+L110+N110+P110) -> 41321.28 | S110: =SUM(Q110:R110) -> 41321.28
...

Sheet US & Local Summaries
A1: =Assumptions!B4 -> Partners of America
A2: =Assumptions!B5 -> DONOR: | F2: =Assumptions!C5 -> USDOL
A3: =Assumptions!B6 -> Country: | F3: =Assumptions!C6 -> Ecuador
A4: =Assumptions!B7 -> Program Name: | F4: =Assumptions!C7 -> Project to Improve Adherence to International Labor Standards in the Agricultural Sector in Ecuador
A5: =Assumptions!B8 -> Grant Number: | F5: =Assumptions!C8 -> FOA-ILAB-23-28
A6: =Assumptions!B9 -> Period of Performance: | F6: =Assumptions!C9 -> 48 months | I6: =Assumptions!G9 -> 0
A8: US COSTS
A10: Line Item | F10: =#REF! -> #REF! | I10: =#REF! -> #REF! | L10: =#REF! -> #REF! | O10: =#REF! -> #REF! | R10: =#REF! -> #REF! | U10: Total
A12: Salaries | F12: =#REF! -> #REF! | I12: =#REF! -> #REF! | L12: =#REF! -> #REF! | O12: =#REF! -> #REF! | R12: =#REF! -> #REF! | U12: =SUM(F12,I12,L12,O12,R12) -> #REF!
A13: Fringe Benefits | F13: =#REF! -> #REF! | I13: =#REF! -> #REF! | L13: =#REF! -> #REF! | O13: =#REF! -> #REF! | R13: =#REF! -> #REF! | U13: =SUM(F13,I13,L13,O13,R13) -> #REF!
A14: Travel | F14: =#REF! -> #REF! | I14: =#REF! -> #REF! | L14: =#REF! -> #REF! | O14: =#REF! -> #REF! | R14: =#REF! -> #REF! | U14: =SUM(F14,I14,L14,O14,R14) -> #REF!
A15: Equipment | F15: =#REF! -> #REF! | I15: =#REF! -> #REF! | L15: =#REF! -> #REF! | O15: =#REF! -> #REF! | R15: =#REF! -> #REF! | U15: =SUM(F15,I15,L15,O15,R15) -> #REF!
A16: Materials and Supplies | F16: =#REF! -> #REF! | I16: =#REF! -> #REF! | L16: =#REF! -> #REF! | O16: =#REF! -> #REF! | R16: =#REF! -> #REF! | U16: =SUM(F16,I16,L16,O16,R16) -> #REF!
A17: Consultants | F17: =#REF! -> #REF! | I17: =#REF! -> #REF! | L17: =#REF! -> #REF! | O17: =#REF! -> #REF! | R17: =#REF! -> #REF! | U17: =SUM(F17,I17,L17,O17,R17) -> #REF!
A18: Contractual | F18: =#REF! -> #REF! | I18: =#REF! -> #REF! | L18: =#REF! -> #REF! | O18: =#REF! -> #REF! | R18: =#REF! -> #REF! | U18: =SUM(F18,I18,L18,O18,R18) -> #REF!
A19: Other Direct Costs | F19: =#REF! -> #REF! | I19: =#REF! -> #REF! | L19: =#REF! -> #REF! | O19: =#REF! -> #REF! | R19: =#REF! -> #REF! | U19: =SUM(F19,I19,L19,O19,R19) -> #REF!
A20: Subtotal | F20: =#REF! -> #REF! | I20: =#REF! -> #REF! | L20: =#REF! -> #REF! | O20: =#REF! -> #REF! | R20: =#REF! -> #REF! | U20: =SUM(F20,I20,L20,O20,R20) -> #REF!
A22: Service Center (excluding subcontractors) | F22: =#REF! -> #REF! | I22: =#REF! -> #REF! | L22: =#REF! -> #REF! | O22: =#REF! -> #REF! | R22: =#REF! -> #REF! | U22: =SUM(F22,I22,L22,O22,R22) -> #REF!
A23: Service Center on Subcontractors | F23: =#REF! -> #REF! | I23: =#REF! -> #REF! | L23: =#REF! -> #REF! | O23: =#REF! -> #REF! | R23: =#REF! -> #REF! | U23: =SUM(F23,I23,L23,O23,R23) -> #REF!
A25: F&A Costs | F25: =#REF! -> #REF! | I25: =#REF! -> #REF! | L25: =#REF! -> #REF! | O25: =#REF! -> #REF! | R25: =#REF! -> #REF! | U25: =SUM(F25,I25,L25,O25,R25) -> #REF!
A26: F&A Costs (Applied to Subcontracts) | F26: =#REF! -> #REF! | I26: =#REF! -> #REF! | L26: =#REF! -> #REF! | O26: =#REF! -> #REF! | R26: =#REF! -> #REF! | U26: =SUM(F26,I26,L26,O26,R26) -> #REF!
A28: Total per year | F28: =SUM(F20:F27) -> #REF! | I28: =SUM(I20:I27) -> #REF! | L28: =SUM(L20:L27) -> #REF! | O28: =SUM(O20:O27) -> #REF! | R28: =SUM(R20:R27) -> #REF! | U28: =SUM(E28:T28) -> #REF!
A30: IN-COUNTRY COSTS
A32: Line Item | F32: =F10 -> #REF! | I32: =I10 -> #REF! | L32: =L10 -> #REF! | O32: =O10 -> #REF! | R32: =R10 -> #REF! | U32: =U10 -> Total
A34: Salaries | F34: =#REF! -> #REF! | I34: =#REF! -> #REF! | L34: =#REF! -> #REF! | O34: =#REF! -> #REF! | R34: =#REF! -> #REF! | U34: =SUM(F34,I34,L34,O34,R34) -> #REF!
A35: Fringe Benefits | F35: =#REF! -> #REF! | I35: =#REF! -> #REF! | L35: =#REF! -> #REF! | O35: =#REF! -> #REF! | R35: =#REF! -> #REF! | U35: =SUM(F35,I35,L35,O35,R35) -> #REF!
A36: Travel | F36: =#REF! -> #REF! | I36: =#REF! -> #REF! | L36: =#REF! -> #REF! | O36: =#REF! -> #REF! | R36: =#REF! -> #REF! | U36: =SUM(F36,I36,L36,O36,R36) -> #REF!
A37: Equipment | F37: =#REF! -> #REF! | I37: =#REF! -> #REF! | L37: =#REF! -> #REF! | O37: =#REF! -> #REF! | R37: =#REF! -> #REF! | U37: =SUM(F37,I37,L37,O37,R37) -> #REF!
A38: Materials and Supplies | F38: =#REF! -> #REF! | I38: =#REF! -> #REF! | L38: =#REF! -> #REF! | O38: =#REF! -> #REF! | R38: =#REF! -> #REF! | U38: =SUM(F38,I38,L38,O38,R38) -> #REF!
A39: Consultants | F39: =#REF! -> #REF! | I39: =#REF! -> #REF! | L39: =#REF! -> #REF! | O39: =#REF! -> #REF! | R39: =#REF! -> #REF! | U39: =SUM(F39,I39,L39,O39,R39) -> #REF!
A40: Contractual | F40: =#REF! -> #REF! | I40: =#REF! -> #REF! | L40: =#REF! -> #REF! | O40: =#REF! -> #REF! | R40: =#REF! -> #REF! | U40: =SUM(F40,I40,L40,O40,R40) -> #REF!
A41: Other Direct Costs | F41: =#REF! -> #REF! | I41: =#REF! -> #REF! | L41: =#REF! -> #REF! | O41: =#REF! -> #REF! | R41: =#REF! -> #REF! | U41: =SUM(F41,I41,L41,O41,R41) -> #REF!
A42: Subtotal | F42: =#REF! -> #REF! | I42: =#REF! -> #REF! | L42: =#REF! -> #REF! | O42: =#REF! -> #REF! | R42: =#REF! -> #REF! | U42: =SUM(F42,I42,L42,O42,R42) -> #REF!
A44: Service Center (excluding subcontractors) | F44: =#REF! -> #REF! | I44: =#REF! -> #REF! | L44: =#REF! -> #REF! | O44: =#REF! -> #REF! | R44: =#REF! -> #REF! | U44: =SUM(F44,I44,L44,O44,R44) -> #REF!
A45: Service Center on Subcontractors | F45: =#REF! -> #REF! | I45: =#REF! -> #REF! | L45: =#REF! -> #REF! | O45: =#REF! -> #REF! | R45: =#REF! -> #REF! | U45: =SUM(F45,I45,L45,O45,R45) -> #REF!
A47: F&A Costs | F47: =#REF! -> #REF! | I47: =#REF! -> #REF! | L47: =#REF! -> #REF! | O47: =#REF! -> #REF! | R47: =#REF! -> #REF! | U47: =SUM(F47,I47,L47,O47,R47) -> #REF!
A48: F&A Costs (Applied to Subcontracts) | F48: =#REF! -> #REF! | I48: =#REF! -> #REF! | L48: =#REF! -> #REF! | O48: =#REF! -> #REF! | R48: =#REF! -> #REF! | U48: =SUM(F48,I48,L48,O48,R48) -> #REF!
A50: Total per year | F50: =SUM(F42:F49) -> #REF! | I50: =SUM(I42:I49) -> #REF! | L50: =SUM(L42:L49) -> #REF! | O50: =SUM(O42:O49) -> #REF! | R50: =SUM(R42:R49) -> #REF! | U50: =SUM(F50,I50,L50,O50,R50) -> #REF!
A52: Grand Total | F52: =SUM(F50,F28) -> #REF! | I52: =SUM(I50,I28) -> #REF! | L52: =SUM(L50,L28) -> #REF! | O52: =SUM(O50,O28) -> #REF! | R52: =SUM(R50,R28) -> #REF! | U52: =SUM(F52,I52,L52,O52,R52) -> #REF!

Sheet TA Summary
B1: =Assumptions!$B$4 -> Partners of America
B2: =CONCATENATE(Assumptions!$B5," ",Assumptions!$C5) -> DONOR: USDOL
B3: =CONCATENATE(Assumptions!$B6," ",Assumptions!$C6) -> Country: Ecuador
B4: =CONCATENATE(Assumptions!$B7," ",Assumptions!$C7) -> Program Name: Project to Improve Adherence to International Labor Standards in the Agricultural Sector in Ecuador
B5: =CONCATENATE(Assumptions!$B8," ",Assumptions!$C8) -> Grant Number: FOA-ILAB-23-28
B7: TOTAL FUNDING FOR EXPATRIATE AND IN-COUNTRY TECHNICAL ASSISTANCE
B9: Line Item | C9: =#REF! -> #REF! | F9: =#REF! -> #REF! | I9: =#REF! -> #REF! | L9: =#REF! -> #REF! | O9: =#REF! -> #REF! | S9: Total
A11: 6.a | B11: Expatriate Technical Assistance
B12: Program and Technical Staff - US Hires | C12: =SUM(#REF!,#REF!) -> #REF! | F12: =SUM(#REF!,#REF!) -> #REF! | I12: =SUM(#REF!,#REF!) -> #REF! | L12: =SUM(#REF!,#REF!) -> #REF! | O12: =SUM(#REF!,#REF!) -> #REF! | S12: =SUM(C12:O12) -> #REF!
B13: STA US Hires | C13: =SUM(#REF!) -> #REF! | F13: =SUM(#REF!) -> #REF! | I13: =SUM(#REF!) -> #REF! | L13: =SUM(#REF!) -> #REF! | O13: =SUM(#REF!) -> #REF! | S13: =SUM(C13:O13) -> #REF!
B14: Regional Hires | C14: =SUM(#REF!,#REF!) -> #REF! | F14: =SUM(#REF!,#REF!) -> #REF! | I14: =SUM(#REF!,#REF!) -> #REF! | L14: =SUM(#REF!,#REF!) -> #REF! | O14: =SUM(#REF!,#REF!) -> #REF! | S14: =SUM(C14:O14) -> #REF!
B15: International Consultants | C15: =SUM(#REF!) -> #REF! | F15: =SUM(#REF!) -> #REF! | I15: =SUM(#REF!) -> #REF! | L15: =SUM(#REF!) -> #REF! | O15: =SUM(#REF!) -> #REF! | S15: =SUM(C15:O15) -> #REF!
B16: Fringe Benefits US Hires | C16: =SUM(#REF!,#REF!,#REF!) -> #REF! | F16: =SUM(#REF!,#REF!,#REF!) -> #REF! | I16: =SUM(#REF!,#REF!,#REF!) -> #REF! | L16: =SUM(#REF!,#REF!,#REF!) -> #REF! | O16: =SUM(#REF!,#REF!,#REF!) -> #REF! | S16: =SUM(C16:O16) -> #REF!
B17: Fringe Benefits Regional Hires | C17: =SUM(#REF!) -> #REF! | F17: =SUM(#REF!) -> #REF! | I17: =SUM(#REF!) -> #REF! | L17: =SUM(#REF!) -> #REF! | O17: =SUM(#REF!) -> #REF! | S17: =SUM(C17:O17) -> #REF!
B18: Allowances | C18: =SUM(#REF!) -> #REF! | F18: =SUM(#REF!) -> #REF! | I18: =SUM(#REF!) -> #REF! | L18: =SUM(#REF!) -> #REF! | O18: =SUM(#REF!) -> #REF! | S18: =SUM(C18:O18) -> #REF!
B19: International Travel | C19: =#REF! -> #REF! | F19: =#REF! -> #REF! | I19: =#REF! -> #REF! | L19: =#REF! -> #REF! | O19: =#REF! -> #REF! | S19: =SUM(C19:O19) -> #REF!
B20: International Consultants Travel | C20: =SUM(#REF!) -> #REF! | F20: =SUM(#REF!) -> #REF! | I20: =SUM(#REF!) -> #REF! | L20: =SUM(#REF!) -> #REF! | O20: =SUM(#REF!) -> #REF! | S20: =SUM(C20:O20) -> #REF!
B21: Total Expatriate TA | C21: =SUM(C12:C20) -> #REF! | F21: =SUM(F12:F20) -> #REF! | I21: =SUM(I12:I20) -> #REF! | L21: =SUM(L12:L20) -> #REF! | O21: =SUM(O12:O20) -> #REF! | S21: =SUM(C21:O21) -> #REF!
B23: Country Offices
B24: Program and Technical Staff - Local Hires | C24: =#REF! -> #REF! | F24: =#REF! -> #REF! | I24: =#REF! -> #REF! | L24: =#REF! -> #REF! | O24: =#REF! -> #REF! | S24: =SUM(O24,C24,F24,I24,L24) -> #REF!
B25: Support Staff - Local Hires | C25: =#REF! -> #REF! | F25: =#REF! -> #REF! | I25: =#REF! -> #REF! | L25: =#REF! -> #REF! | O25: =#REF! -> #REF! | S25: =SUM(O25,C25,F25,I25,L25) -> #REF!
B26: Local Consultants Labor | C26: =SUM(#REF!) -> #REF! | F26: =SUM(#REF!) -> #REF! | I26: =SUM(#REF!) -> #REF! | L26: =SUM(#REF!) -> #REF! | O26: =SUM(#REF!) -> #REF! | S26: =SUM(O26,C26,F26,I26,L26) -> #REF!
B27: Fringe Benefits - Local Hires | C27: =#REF! -> #REF! | F27: =#REF! -> #REF! | I27: =#REF! -> #REF! | L27: =#REF! -> #REF! | O27: =#REF! -> #REF! | S27: =SUM(O27,C27,F27,I27,L27) -> #REF!
B28: Domestic Travel | C28: =#REF! -> #REF! | F28: =#REF! -> #REF! | I28: =#REF! -> #REF! | L28: =#REF! -> #REF! | O28: =#REF! -> #REF! | S28: =SUM(O28,C28,F28,I28,L28) -> #REF!
B29: Local Consultants Travel | C29: =SUM(#REF!) -> #REF! | F29: =SUM(#REF!) -> #REF! | I29: =SUM(#REF!) -> #REF! | L29: =SUM(#REF!) -> #REF! | O29: =SUM(#REF!) -> #REF! | S29: =SUM(O29,C29,F29,I29,L29) -> #REF!
B30: Total Cooperating Country Nationals TA | C30: =SUM(C23:C29) -> #REF! | F30: =SUM(F23:F29) -> #REF! | I30: =SUM(I23:I29) -> #REF! | L30: =SUM(L23:L29) -> #REF! | O30: =SUM(O23:O29) -> #REF! | S30: =SUM(C30:O30) -> #REF!
B32: Total Technical Assistance Costs | C32: =SUM(C30,C21) -> #REF! | F32: =SUM(F30,F21) -> #REF! | I32: =SUM(I30,I21) -> #REF! | L32: =SUM(L30,L21) -> #REF! | O32: =SUM(O30,O21) -> #REF! | S32: =SUM(C32:O32) -> #REF!

Sheet Funding By Partner
A1: =Assumptions!$B$4 -> Partners of America
A2: =CONCATENATE(Assumptions!$B5," ",Assumptions!$C5) -> DONOR: USDOL
A3: =CONCATENATE(Assumptions!$B6," ",Assumptions!$C6) -> Country: Ecuador
A4: =CONCATENATE(Assumptions!$B7," ",Assumptions!$C7) -> Program Name: Project to Improve Adherence to International Labor Standards in the Agricultural Sector in Ecuador
A5: =CONCATENATE(Assumptions!$B8," ",Assumptions!$C8) -> Grant Number: FOA-ILAB-23-28
A7: TOTAL FUNDING BY PARTNER
A9: Partner | B9: =Assumptions!G20 -> Year 1 | E9: =Assumptions!J20 -> Year 2 | H9: =Assumptions!M20 -> Year 3 | K9: =Assumptions!P20 -> Year 4 | N9: =Assumptions!S20 -> Year 5 | Q9: Total
B10: Federal Funding | C10: Non-Federal Funding | E10: Federal Funding | F10: Non-Federal Funding | H10: Federal Funding | I10: Non-Federal Funding | K10: Federal Funding | L10: Non-Federal Funding | N10: Federal Funding | O10: Non-Federal Funding | Q10: Federal Funding | R10: Non-Federal Funding | T10: If RFA requests for Cost Share - Unhide columns "C", "F", "I", "L", "O" and "Q"
T11: Double-checks
A12: Jhpiego Corporation | B12: =B35-SUM(B13:B33) -> #REF! | E12: =E35-SUM(E13:E33) -> #REF! | H12: =H35-SUM(H13:H33) -> #REF! | K12: =K35-SUM(K13:K33) -> #REF! | N12: =N35-SUM(N13:N33) -> #REF! | Q12: =SUM(B12,E12,H12,K12,N12) -> #REF! | R12: =SUM(C12,F12,I12,L12,O12,#REF!,#REF!,#REF!,#REF!,#REF!) -> #REF! | T12: =SUM(B12:P12) -> #REF!
A14: =#REF! -> #REF! | B14: =#REF! -> #REF! | E14: =#REF! -> #REF! | H14: =#REF! -> #REF! | K14: =#REF! -> #REF! | N14: =#REF! -> #REF! | Q14: =SUM(B14,E14,H14,K14,N14) -> #REF! | R14: =SUM(O14,L14,I14,F14,C14) -> 0 | T14: =SUM(B14:P14) -> #REF!
A16: =#REF! -> #REF! | B16: =#REF! -> #REF! | E16: =#REF! -> #REF! | H16: =#REF! -> #REF! | K16: =#REF! -> #REF! | N16: =#REF! -> #REF! | Q16: =SUM(B16,E16,H16,K16,N16) -> #REF! | R16: =SUM(O16,L16,I16,F16,C16) -> 0 | T16: =SUM(B16:P16) -> #REF!
A18: =#REF! -> #REF! | B18: =#REF! -> #REF! | E18: =#REF! -> #REF! | H18: =#REF! -> #REF! | K18: =#REF! -> #REF! | N18: =#REF! -> #REF! | Q18: =SUM(B18,E18,H18,K18,N18) -> #REF! | R18: =SUM(O18,L18,I18,F18,C18) -> 0 | T18: =SUM(B18:P18) -> #REF!
A20: =#REF! -> #REF! | B20: =#REF! -> #REF! | E20: =#REF! -> #REF! | H20: =#REF! -> #REF! | K20: =#REF! -> #REF! | N20: =#REF! -> #REF! | Q20: =SUM(B20,E20,H20,K20,N20) -> #REF! | R20: =SUM(O20,L20,I20,F20,C20) -> 0 | T20: =SUM(B20:P20) -> #REF!
A22: =#REF! -> #REF! | B22: =#REF! -> #REF! | E22: =#REF! -> #REF! | H22: =#REF! -> #REF! | K22: =#REF! -> #REF! | N22: =#REF! -> #REF! | Q22: =SUM(B22,E22,H22,K22,N22) -> #REF! | R22: =SUM(O22,L22,I22,F22,C22) -> 0 | T22: =SUM(B22:P22) -> #REF!
A24: =#REF! -> #REF! | B24: =#REF! -> #REF! | E24: =#REF! -> #REF! | H24: =#REF! -> #REF! | K24: =#REF! -> #REF! | N24: =#REF! -> #REF! | Q24: =SUM(B24,E24,H24,K24,N24) -> #REF! | R24: =SUM(O24,L24,I24,F24,C24) -> 0 | T24: =SUM(B24:P24) -> #REF!
A26: =#REF! -> #REF! | B26: =#REF! -> #REF! | E26: =#REF! -> #REF! | H26: =#REF! -> #REF! | K26: =#REF! -> #REF! | N26: =#REF! -> #REF! | Q26: =SUM(B26,E26,H26,K26,N26) -> #REF! | R26: =SUM(O26,L26,I26,F26,C26) -> 0 | T26: =SUM(B26:P26) -> #REF!
A28: =#REF! -> #REF! | B28: =#REF! -> #REF! | E28: =#REF! -> #REF! | H28: =#REF! -> #REF! | K28: =#REF! -> #REF! | N28: =#REF! -> #REF! | Q28: =SUM(B28,E28,H28,K28,N28) -> #REF! | R28: =SUM(O28,L28,I28,F28,C28) -> 0 | T28: =SUM(B28:P28) -> #REF!
A30: =#REF! -> #REF! | B30: =#REF! -> #REF! | E30: =#REF! -> #REF! | H30: =#REF! -> #REF! | K30: =#REF! -> #REF! | N30: =#REF! -> #REF! | Q30: =SUM(B30,E30,H30,K30,N30) -> #REF! | R30: =SUM(O30,L30,I30,F30,C30) -> 0 | T30: =SUM(B30:P30) -> #REF!
Q32: =SUM(N32,K32,H32,E32,B32) -> 0 | R32: =SUM(O32,L32,I32,F32,C32) -> 0 | T32: =SUM(B32:P32) -> 0
A35: TOTAL COSTS | B35: =#REF! -> #REF! | C35: =SUM(C11:C34) -> 0 | E35: =#REF! -> #REF! | F35: =SUM(F11:F34) -> 0 | H35: =#REF! -> #REF! | I35: =SUM(I11:I34) -> 0 | K35: =#REF! -> #REF! | L35: =SUM(L11:L34) -> 0 | N35: =#REF! -> #REF! | O35: =SUM(O11:O34) -> 0 | Q35: =SUM(B35,E35,H35,K35,N35) -> #REF! | R35: =SUM(O35,L35,I35,F35,C35) -> 0 | T35: =SUM(B35:P35) -> #REF!

Sheet LOE Table
A1: =Assumptions!$B$4 -> Partners of America
A2: =CONCATENATE(Assumptions!$B5," ",Assumptions!$C5) -> DONOR: USDOL | Q2: Escalation Factor:
A3: =CONCATENATE(Assumptions!$B6," ",Assumptions!$C6) -> Country: Ecuador | Q3: Inflation Rate:
A4: =CONCATENATE(Assumptions!$B7," ",Assumptions!$C7) -> Program Name: Project to Improve Adherence to International Labor Standards in the Agricultural Sector in Ecuador
A5: =CONCATENATE(Assumptions!$B8," ",Assumptions!$C8) -> Grant Number: FOA-ILAB-23-28
A7: LEVEL OF EFFORT TABLE
A9: PERSONNEL | C9: =#REF! -> #REF! | F9: =#REF! -> #REF! | I9: =Assumptions!M20 -> Year 3 | L9: =#REF! -> #REF! | O9: =#REF! -> #REF! | R9: Total | T9: Calculation
A10: Position Description | B10: Unit | C10: Units | F10: Units | I10: Units | L10: Units | O10: Units | R10: % | S10: US$ | T10: Check: | V10: show
V11: =IF(SUM(S12:S190)=0,"hide","show") -> #REF!
A12: =#REF! -> #REF! | V12: =IF(SUM(S20:S190)=0,"hide","show") -> #REF!
A13: =#REF! -> #REF! | V13: =IF(SUM(S14:S18)=0,"hide","show") -> #REF!
A14: =#REF! -> #REF! | B14: % | C14: =#REF! -> #REF! | F14: =#REF! -> #REF! | I14: =#REF! -> #REF! | L14: =#REF! -> #REF! | O14: =#REF! -> #REF! | R14: =C14+F14+I14+L14+O14 -> #REF! | S14: =#REF! -> #REF! | V14: =IF(S14=0,"hide","show") -> #REF!
A15: =#REF! -> #REF! | B15: % | C15: =#REF! -> #REF! | F15: =#REF! -> #REF! | I15: =#REF! -> #REF! | L15: =#REF! -> #REF! | O15: =#REF! -> #REF! | R15: =C15+F15+I15+L15+O15 -> #REF! | S15: =#REF! -> #REF! | V15: =IF(S15=0,"hide","show") -> #REF!
A16: =#REF! -> #REF! | B16: % | C16: =#REF! -> #REF! | F16: =#REF! -> #REF! | I16: =#REF! -> #REF! | L16: =#REF! -> #REF! | O16: =#REF! -> #REF! | R16: =C16+F16+I16+L16+O16 -> #REF! | S16: =#REF! -> #REF! | V16: =IF(S16=0,"hide","show") -> #REF!
A17: =#REF! -> #REF! | B17: % | C17: =#REF! -> #REF! | F17: =#REF! -> #REF! | I17: =#REF! -> #REF! | L17: =#REF! -> #REF! | O17: =#REF! -> #REF! | R17: =C17+F17+I17+L17+O17 -> #REF! | S17: =#REF! -> #REF! | V17: =IF(S17=0,"hide","show") -> #REF!
A18: =#REF! -> #REF! | B18: % | C18: =#REF! -> #REF! | F18: =#REF! -> #REF! | I18: =#REF! -> #REF! | L18: =#REF! -> #REF! | O18: =#REF! -> #REF! | R18: =C18+F18+I18+L18+O18 -> #REF! | S18: =#REF! -> #REF! | V18: =IF(S18=0,"hide","show") -> #REF!
V19: =IF(SUM(S20:S110)=0,"hide","show") -> #REF!
A20: =#REF! -> #REF! | V20: =IF(SUM(S21:S25)=0,"hide","show") -> #REF!
A21: =#REF! -> #REF! | B21: % | C21: =#REF! -> #REF! | F21: =#REF! -> #REF! | I21: =#REF! -> #REF! | L21: =#REF! -> #REF! | O21: =#REF! -> #REF! | R21: =C21+F21+I21+L21+O21 -> #REF! | S21: =#REF! -> #REF! | V21: =IF(S21=0,"hide","show") -> #REF!
A22: =#REF! -> #REF! | B22: % | C22: =#REF! -> #REF! | F22: =#REF! -> #REF! | I22: =#REF! -> #REF! | L22: =#REF! -> #REF! | O22: =#REF! -> #REF! | R22: =C22+F22+I22+L22+O22 -> #REF! | S22: =#REF! -> #REF! | V22: =IF(S22=0,"hide","show") -> #REF!
A23: =#REF! -> #REF! | B23: % | C23: =#REF! -> #REF! | F23: =#REF! -> #REF! | I23: =#REF! -> #REF! | L23: =#REF! -> #REF! | O23: =#REF! -> #REF! | R23: =C23+F23+I23+L23+O23 -> #REF! | S23: =#REF! -> #REF! | V23: =IF(S23=0,"hide","show") -> #REF!
A24: =#REF! -> #REF! | B24: % | C24: =#REF! -> #REF! | F24: =#REF! -> #REF! | I24: =#REF! -> #REF! | L24: =#REF! -> #REF! | O24: =#REF! -> #REF! | R24: =C24+F24+I24+L24+O24 -> #REF! | S24: =#REF! -> #REF! | V24: =IF(S24=0,"hide","show") -> #REF!
A25: =#REF! -> #REF! | B25: % | C25: =#REF! -> #REF! | F25: =#REF! -> #REF! | I25: =#REF! -> #REF! | L25: =#REF! -> #REF! | O25: =#REF! -> #REF! | R25: =C25+F25+I25+L25+O25 -> #REF! | S25: =#REF! -> #REF! | V25: =IF(S25=0,"hide","show") -> #REF!
V26: =IF(SUM(S27:S190)=0,"hide","show") -> #REF!
A27: =#REF! -> #REF! | V27: =IF(SUM(S28:S190)=0,"hide","show") -> #REF!
A28: =#REF! -> #REF! | V28: =IF(SUM(S29:S110)=0,"hide","show") -> #REF!
A29: =#REF! -> #REF! | B29: % | C29: =#REF! -> #REF! | F29: =#REF! -> #REF! | I29: =#REF! -> #REF! | L29: =#REF! -> #REF! | O29: =#REF! -> #REF! | R29: =C29+F29+I29+L29+O29 -> #REF! | S29: =#REF! -> #REF! | V29: =IF(S29=0,"hide","show") -> #REF!
A30: =#REF! -> #REF! | B30: % | C30: =#REF! -> #REF! | F30: =#REF! -> #REF! | I30: =#REF! -> #REF! | L30: =#REF! -> #REF! | O30: =#REF! -> #REF! | R30: =C30+F30+I30+L30+O30 -> #REF! | S30: =#REF! -> #REF! | V30: =IF(S30=0,"hide","show") -> #REF!
A31: =#REF! -> #REF! | B31: % | C31: =#REF! -> #REF! | F31: =#REF! -> #REF! | I31: =#REF! -> #REF! | L31: =#REF! -> #REF! | O31: =#REF! -> #REF! | R31: =C31+F31+I31+L31+O31 -> #REF! | S31: =#REF! -> #REF! | V31: =IF(S31=0,"hide","show") -> #REF!
A32: =#REF! -> #REF! | B32: % | C32: =#REF! -> #REF! | F32: =#REF! -> #REF! | I32: =#REF! -> #REF! | L32: =#REF! -> #REF! | O32: =#REF! -> #REF! | R32: =C32+F32+I32+L32+O32 -> #REF! | S32: =#REF! -> #REF! | V32: =IF(S32=0,"hide","show") -> #REF!
A33: =#REF! -> #REF! | B33: % | C33: =#REF! -> #REF! | F33: =#REF! -> #REF! | I33: =#REF! -> #REF! | L33: =#REF! -> #REF! | O33: =#REF! -> #REF! | R33: =C33+F33+I33+L33+O33 -> #REF! | S33: =#REF! -> #REF! | V33: =IF(S33=0,"hide","show") -> #REF!
A34: =#REF! -> #REF! | B34: % | C34: =#REF! -> #REF! | F34: =#REF! -> #REF! | I34: =#REF! -> #REF! | L34: =#REF! -> #REF! | O34: =#REF! -> #REF! | R34: =C34+F34+I34+L34+O34 -> #REF! | S34: =#REF! -> #REF! | V34: =IF(S34=0,"hide","show") -> #REF!
A35: =#REF! -> #REF! | B35: % | C35: =#REF! -> #REF! | F35: =#REF! -> #REF! | I35: =#REF! -> #REF! | L35: =#REF! -> #REF! | O35: =#REF! -> #REF! | R35: =C35+F35+I35+L35+O35 -> #REF! | S35: =#REF! -> #REF! | V35: =IF(S35=0,"hide","show") -> #REF!
A36: =#REF! -> #REF! | B36: % | C36: =#REF! -> #REF! | F36: =#REF! -> #REF! | I36: =#REF! -> #REF! | L36: =#REF! -> #REF! | O36: =#REF! -> #REF! | R36: =C36+F36+I36+L36+O36 -> #REF! | S36: =#REF! -> #REF! | V36: =IF(S36=0,"hide","show") -> #REF!
A37: =#REF! -> #REF! | B37: % | C37: =#REF! -> #REF! | F37: =#REF! -> #REF! | I37: =#REF! -> #REF! | L37: =#REF! -> #REF! | O37: =#REF! -> #REF! | R37: =C37+F37+I37+L37+O37 -> #REF! | S37: =#REF! -> #REF! | V37: =IF(S37=0,"hide","show") -> #REF!
A38: =#REF! -> #REF! | B38: % | C38: =#REF! -> #REF! | F38: =#REF! -> #REF! | I38: =#REF! -> #REF! | L38: =#REF! -> #REF! | O38: =#REF! -> #REF! | R38: =C38+F38+I38+L38+O38 -> #REF! | S38: =#REF! -> #REF! | V38: =IF(S38=0,"hide","show") -> #REF!
A39: =#REF! -> #REF! | B39: % | C39: =#REF! -> #REF! | F39: =#REF! -> #REF! | I39: =#REF! -> #REF! | L39: =#REF! -> #REF! | O39: =#REF! -> #REF! | R39: =C39+F39+I39+L39+O39 -> #REF! | S39: =#REF! -> #REF! | V39: =IF(S39=0,"hide","show") -> #REF!
A40: =#REF! -> #REF! | B40: % | C40: =#REF! -> #REF! | F40: =#REF! -> #REF! | I40: =#REF! -> #REF! | L40: =#REF! -> #REF! | O40: =#REF! -> #REF! | R40: =C40+F40+I40+L40+O40 -> #REF! | S40: =#REF! -> #REF! | V40: =IF(S40=0,"hide","show") -> #REF!
... A114: =#REF! -> #REF! | B114: % | C114: =#REF! -> #REF! | F114: =#REF! -> #REF! | I114: =#REF! -> #REF! | L114: =#REF! -> #REF! | O114: =#REF! -> #REF! | R114: =C114+F114+I114+L114+O114 -> #REF! | S114: =#REF! -> #REF! | V114: =IF(S114=0,"hide","show") -> #REF!
V115: =IF(SUM(S117:S190)=0,"hide","show") -> #REF!
A116: =#REF! -> #REF! | V116: =IF(SUM(S117:S190)=0,"hide","show") -> #REF!
A117: =#REF! -> #REF! | B117: % | C117: =#REF! -> #REF! | F117: =#REF! -> #REF! | I117: =#REF! -> #REF! | L117: =#REF! -> #REF! | O117: =#REF! -> #REF! | R117: =C117+F117+I117+L117+O117 -> #REF! | S117: =#REF! -> #REF! | V117: =IF(S117=0,"hide","show") -> #REF!
A118: =#REF! -> #REF! | B118: % | C118: =#REF! -> #REF! | F118: =#REF! -> #REF! | I118: =#REF! -> #REF! | L118: =#REF! -> #REF! | O118: =#REF! -> #REF! | R118: =C118+F118+I118+L118+O118 -> #REF! | S118: =#REF! -> #REF! | V118: =IF(S118=0,"hide","show") -> #REF!
A119: =#REF! -> #REF! | B119: % | C119: =#REF! -> #REF! | F119: =#REF! -> #REF! | I119: =#REF! -> #REF! | L119: =#REF! -> #REF! | O119: =#REF! -> #REF! | R119: =C119+F119+I119+L119+O119 -> #REF! | S119: =#REF! -> #REF! | V119: =IF(S119=0,"hide","show") -> #REF!
A120: =#REF! -> #REF! | B120: % | C120: =#REF! -> #REF! | F120: =#REF! -> #REF! | I120: =#REF! -> #REF! | L120: =#REF! -> #REF! | O120: =#REF! -> #REF! | R120: =C120+F120+I120+L120+O120 -> #REF! | S120: =#REF! -> #REF! | V120: =IF(S120=0,"hide","show") -> #REF!
A121: =#REF! -> #REF! | B121: % | C121: =#REF! -> #REF! | F121: =#REF! -> #REF! | I121: =#REF! -> #REF! | L121: =#REF! -> #REF! | O121: =#REF! -> #REF! | R121: =C121+F121+I121+L121+O121 -> #REF! | S121: =#REF! -> #REF! | V121: =IF(S121=0,"hide","show") -> #REF!
A122: =#REF! -> #REF! | B122: % | C122: =#REF! -> #REF! | F122: =#REF! -> #REF! | I122: =#REF! -> #REF! | L122: =#REF! -> #REF! | O122: =#REF! -> #REF! | R122: =C122+F122+I122+L122+O122 -> #REF! | S122: =#REF! -> #REF! | V122: =IF(S122=0,"hide","show") -> #REF!
A123: =#REF! -> #REF! | B123: % | C123: =#REF! -> #REF! | F123: =#REF! -> #REF! | I123: =#REF! -> #REF! | L123: =#REF! -> #REF! | O123: =#REF! -> #REF! | R123: =C123+F123+I123+L123+O123 -> #REF! | S123: =#REF! -> #REF! | V123: =IF(S123=0,"hide","show") -> #REF!
A124: =#REF! -> #REF! | B124: % | C124: =#REF! -> #REF! | F124: =#REF! -> #REF! | I124: =#REF! -> #REF! | L124: =#REF! -> #REF! | O124: =#REF! -> #REF! | R124: =C124+F124+I124+L124+O124 -> #REF! | S124: =#REF! -> #REF! | V124: =IF(S124=0,"hide","show") -> #REF!
A125: =#REF! -> #REF! | B125: % | C125: =#REF! -> #REF! | F125: =#REF! -> #REF! | I125: =#REF! -> #REF! | L125: =#REF! -> #REF! | O125: =#REF! -> #REF! | R125: =C125+F125+I125+L125+O125 -> #REF! | S125: =#REF! -> #REF! | V125: =IF(S125=0,"hide","show") -> #REF!
A126: =#REF! -> #REF! | B126: % | C126: =#REF! -> #REF! | F126: =#REF! -> #REF! | I126: =#REF! -> #REF! | L126: =#REF! -> #REF! | O126: =#REF! -> #REF! | R126: =C126+F126+I126+L126+O126 -> #REF! | S126: =#REF! -> #REF! | V126: =IF(S126=0,"hide","show") -> #REF!
A127: =#REF! -> #REF! | B127: % | C127: =#REF! -> #REF! | F127: =#REF! -> #REF! | I127: =#REF! -> #REF! | L127: =#REF! -> #REF! | O127: =#REF! -> #REF! | R127: =C127+F127+I127+L127+O127 -> #REF! | S127: =#REF! -> #REF! | V127: =IF(S127=0,"hide","show") -> #REF!
A128: =#REF! -> #REF! | B128: % | C128: =#REF! -> #REF! | F128: =#REF! -> #REF! | I128: =#REF! -> #REF! | L128: =#REF! -> #REF! | O128: =#REF! -> #REF! | R128: =C128+F128+I128+L128+O128 -> #REF! | S128: =#REF! -> #REF! | V128: =IF(S128=0,"hide","show") -> #REF!
... A190: =#REF! -> #REF! | B190: % | C190: =#REF! -> #REF! | F190: =#REF! -> #REF! | I190: =#REF! -> #REF! | L190: =#REF! -> #REF! | O190: =#REF! -> #REF! | R190: =C190+F190+I190+L190+O190 -> #REF! | S190: =#REF! -> #REF! | V190: =IF(S190=0,"hide","show") -> #REF!
V191: =IF(SUM(S193:S212)=0,"hide","show") -> #REF!
A192: =#REF! -> #REF! | V192: =IF(SUM(S194:S212)=0,"hide","show") -> #REF!
A193: =#REF! -> #REF! | V193: =IF(SUM(S194:S198)=0,"hide","show") -> #REF!
A194: =#REF! -> #REF! | B194: % | C194: =#REF! -> #REF! | F194: =#REF! -> #REF! | I194: =#REF! -> #REF! | L194: =#REF! -> #REF! | O194: =#REF! -> #REF! | R194: =C194+F194+I194+L194+O194 -> #REF! | S194: =#REF! -> #REF! | V194: =IF(S194=0,"hide","show") -> #REF!
A195: =#REF! -> #REF! | B195: % | C195: =#REF! -> #REF! | F195: =#REF! -> #REF! | I195: =#REF! -> #REF! | L195: =#REF! -> #REF! | O195: =#REF! -> #REF! | R195: =C195+F195+I195+L195+O195 -> #REF! | S195: =#REF! -> #REF! | V195: =IF(S195=0,"hide","show") -> #REF!
A196: =#REF! -> #REF! | B196: % | C196: =#REF! -> #REF! | F196: =#REF! -> #REF! | I196: =#REF! -> #REF! | L196: =#REF! -> #REF! | O196: =#REF! -> #REF! | R196: =C196+F196+I196+L196+O196 -> #REF! | S196: =#REF! -> #REF! | V196: =IF(S196=0,"hide","show") -> #REF!
A197: =#REF! -> #REF! | B197: % | C197: =#REF! -> #REF! | F197: =#REF! -> #REF! | I197: =#REF! -> #REF! | L197: =#REF! -> #REF! | O197: =#REF! -> #REF! | R197: =C197+F197+I197+L197+O197 -> #REF! | S197: =#REF! -> #REF! | V197: =IF(S197=0,"hide","show") -> #REF!
A198: =#REF! -> #REF! | B198: % | C198: =#REF! -> #REF! | F198: =#REF! -> #REF! | I198: =#REF! -> #REF! | L198: =#REF! -> #REF! | O198: =#REF! -> #REF! | R198: =C198+F198+I198+L198+O198 -> #REF! | S198: =#REF! -> #REF! | V198: =IF(S198=0,"hide","show") -> #REF!
V199: =IF(SUM(S201:S205)=0,"hide","show") -> #REF!
A200: =#REF! -> #REF! | V200: =IF(SUM(S201:S205)=0,"hide","show") -> #REF!
A201: =#REF! -> #REF! | B201: % | C201: =#REF! -> #REF! | F201: =#REF! -> #REF! | I201: =#REF! -> #REF! | L201: =#REF! -> #REF! | O201: =#REF! -> #REF! | R201: =C201+F201+I201+L201+O201 -> #REF! | S201: =#REF! -> #REF! | V201: =IF(S201=0,"hide","show") -> #REF!
A202: =#REF! -> #REF! | B202: % | C202: =#REF! -> #REF! | F202: =#REF! -> #REF! | I202: =#REF! -> #REF! | L202: =#REF! -> #REF! | O202: =#REF! -> #REF! | R202: =C202+F202+I202+L202+O202 -> #REF! | S202: =#REF! -> #REF! | V202: =IF(S202=0,"hide","show") -> #REF!
A203: =#REF! -> #REF! | B203: % | C203: =#REF! -> #REF! | F203: =#REF! -> #REF! | I203: =#REF! -> #REF! | L203: =#REF! -> #REF! | O203: =#REF! -> #REF! | R203: =C203+F203+I203+L203+O203 -> #REF! | S203: =#REF! -> #REF! | V203: =IF(S203=0,"hide","show") -> #REF!
A204: =#REF! -> #REF! | B204: % | C204: =#REF! -> #REF! | F204: =#REF! -> #REF! | I204: =#REF! -> #REF! | L204: =#REF! -> #REF! | O204: =#REF! -> #REF! | R204: =C204+F204+I204+L204+O204 -> #REF! | S204: =#REF! -> #REF! | V204: =IF(S204=0,"hide","show") -> #REF!
A205: =#REF! -> #REF! | B205: % | C205: =#REF! -> #REF! | F205: =#REF! -> #REF! | I205: =#REF! -> #REF! | L205: =#REF! -> #REF! | O205: =#REF! -> #REF! | R205: =C205+F205+I205+L205+O205 -> #REF! | S205: =#REF! -> #REF! | V205: =IF(S205=0,"hide","show") -> #REF!
V206: =IF(SUM(S208:S212)=0,"hide","show") -> #REF!
A207: =#REF! -> #REF! | V207: =IF(SUM(S208:S212)=0,"hide","show") -> #REF!
A208: =#REF! -> #REF! | B208: % | C208: =#REF! -> #REF! | F208: =#REF! -> #REF! | I208: =#REF! -> #REF! | L208: =#REF! -> #REF! | O208: =#REF! -> #REF! | R208: =C208+F208+I208+L208+O208 -> #REF! | S208: =#REF! -> #REF! | V208: =IF(S208=0,"hide","show") -> #REF!
A209: =#REF! -> #REF! | B209: % | C209: =#REF! -> #REF! | F209: =#REF! -> #REF! | I209: =#REF! -> #REF! | L209: =#REF! -> #REF! | O209: =#REF! -> #REF! | R209: =C209+F209+I209+L209+O209 -> #REF! | S209: =#REF! -> #REF! | V209: =IF(S209=0,"hide","show") -> #REF!
A210: =#REF! -> #REF! | B210: % | C210: =#REF! -> #REF! | F210: =#REF! -> #REF! | I210: =#REF! -> #REF! | L210: =#REF! -> #REF! | O210: =#REF! -> #REF! | R210: =C210+F210+I210+L210+O210 -> #REF! | S210: =#REF! -> #REF! | V210: =IF(S210=0,"hide","show") -> #REF!
A211: =#REF! -> #REF! | B211: % | C211: =#REF! -> #REF! | F211: =#REF! -> #REF! | I211: =#REF! -> #REF! | L211: =#REF! -> #REF! | O211: =#REF! -> #REF! | R211: =C211+F211+I211+L211+O211 -> #REF! | S211: =#REF! -> #REF! | V211: =IF(S211=0,"hide","show") -> #REF!
A212: =#REF! -> #REF! | B212: % | C212: =#REF! -> #REF! | F212: =#REF! -> #REF! | I212: =#REF! -> #REF! | L212: =#REF! -> #REF! | O212: =#REF! -> #REF! | R212: =C212+F212+I212+L212+O212 -> #REF! | S212: =#REF! -> #REF! | V212: =IF(S212=0,"hide","show") -> #REF!
V213: =IF(SUM(S215:S219)=0,"hide","show") -> #REF!
A214: =#REF! -> #REF! | V214: =IF(SUM(S215:S219)=0,"hide","show") -> #REF!
A215: =#REF! -> #REF! | B215: % | C215: =#REF! -> #REF! | F215: =#REF! -> #REF! | I215: =#REF! -> #REF! | L215: =#REF! -> #REF! | O215: =#REF! -> #REF! | R215: =C215+F215+I215+L215+O215 -> #REF! | S215: =#REF! -> #REF! | V215: =IF(S215=0,"hide","show") -> #REF!
A216: =#REF! -> #REF! | B216: % | C216: =#REF! -> #REF! | F216: =#REF! -> #REF! | I216: =#REF! -> #REF! | L216: =#REF! -> #REF! | O216: =#REF! -> #REF! | R216: =C216+F216+I216+L216+O216 -> #REF! | S216: =#REF! -> #REF! | V216: =IF(S216=0,"hide","show") -> #REF!
A217: =#REF! -> #REF! | B217: % | C217: =#REF! -> #REF! | F217: =#REF! -> #REF! | I217: =#REF! -> #REF! | L217: =#REF! -> #REF! | O217: =#REF! -> #REF! | R217: =C217+F217+I217+L217+O217 -> #REF! | S217: =#REF! -> #REF! | V217: =IF(S217=0,"hide","show") -> #REF!
A218: =#REF! -> #REF! | B218: % | C218: =#REF! -> #REF! | F218: =#REF! -> #REF! | I218: =#REF! -> #REF! | L218: =#REF! -> #REF! | O218: =#REF! -> #REF! | R218: =C218+F218+I218+L218+O218 -> #REF! | S218: =#REF! -> #REF! | V218: =IF(S218=0,"hide","show") -> #REF!
A219: =#REF! -> #REF! | B219: % | C219: =#REF! -> #REF! | F219: =#REF! -> #REF! | I219: =#REF! -> #REF! | L219: =#REF! -> #REF! | O219: =#REF! -> #REF! | R219: =C219+F219+I219+L219+O219 -> #REF! | S219: =#REF! -> #REF! | V219: =IF(S219=0,"hide","show") -> #REF!
V220: =IF(SUM(S222:S228)=0,"hide","show") -> #REF!
A221: =#REF! -> #REF! | C221: =SUM(C13:C19) -> #REF! | F221: =SUM(F13:F19) -> #REF! | I221: =SUM(I13:I19) -> #REF! | L221: =SUM(L13:L19) -> #REF! | O221: =SUM(O13:O19) -> #REF! | R221: =C221+F221+I221+L221+O221 -> #REF! | S221: =#REF! -> #REF! | V221: =IF(S221=0,"hide","show") -> #REF!
A222: =#REF! -> #REF! | C222: =SUM(C20:C26) -> #REF! | F222: =SUM(F20:F26) -> #REF! | I222: =SUM(I20:I26) -> #REF! | L222: =SUM(L20:L26) -> #REF! | O222: =SUM(O20:O26) -> #REF! | R222: =C222+F222+I222+L222+O222 -> #REF! | S222: =#REF! -> #REF! | V222: =IF(S222=0,"hide","show") -> #REF!
A223: =#REF! -> #REF! | C223: =SUM(C28:C115) -> #REF! | F223: =SUM(F28:F115) -> #REF! | I223: =SUM(I28:I115) -> #REF! | L223: =SUM(L28:L115) -> #REF! | O223: =SUM(O28:O115) -> #REF! | R223: =C223+F223+I223+L223+O223 -> #REF! | S223: =#REF! -> #REF! | V223: =IF(S223=0,"hide","show") -> #REF!
A224: =#REF! -> #REF! | C224: =SUM(C116:C191) -> #REF! | F224: =SUM(F116:F191) -> #REF! | I224: =SUM(I116:I191) -> #REF! | L224: =SUM(L116:L191) -> #REF! | O224: =SUM(O116:O191) -> #REF! | R224: =C224+F224+I224+L224+O224 -> #REF! | S224: =#REF! -> #REF! | V224: =IF(S224=0,"hide","show") -> #REF!
A225: =#REF! -> #REF! | C225: =SUM(C193:C199) -> #REF! | F225: =SUM(F193:F199) -> #REF! | I225: =SUM(I193:I199) -> #REF! | L225: =SUM(L193:L199) -> #REF! | O225: =SUM(O193:O199) -> #REF! | R225: =C225+F225+I225+L225+O225 -> #REF! | S225: =#REF! -> #REF! | V225: =IF(S225=0,"hide","show") -> #REF!
A226: =#REF! -> #REF! | C226: =SUM(C200:C206) -> #REF! | F226: =SUM(F200:F206) -> #REF! | I226: =SUM(I200:I206) -> #REF! | L226: =SUM(L200:L206) -> #REF! | O226: =SUM(O200:O206) -> #REF! | R226: =C226+F226+I226+L226+O226 -> #REF! | S226: =#REF! -> #REF! | V226: =IF(S226=0,"hide","show") -> #REF!
A227: =#REF! -> #REF! | C227: =SUM(C207:C213) -> #REF! | F227: =SUM(F207:F213) -> #REF! | I227: =SUM(I207:I213) -> #REF! | L227: =SUM(L207:L213) -> #REF! | O227: =SUM(O207:O213) -> #REF! | R227: =C227+F227+I227+L227+O227 -> #REF! | S227: =#REF! -> #REF! | V227: =IF(S227=0,"hide","show") -> #REF!
A228: =#REF! -> #REF! | C228: =SUM(C214:C219) -> #REF! | F228: =SUM(F214:F219) -> #REF! | I228: =SUM(I214:I219) -> #REF! | L228: =SUM(L214:L219) -> #REF! | O228: =SUM(O214:O219) -> #REF! | R228: =C228+F228+I228+L228+O228 -> #REF! | S228: =#REF! -> #REF! | V228: =IF(S228=0,"hide","show") -> #REF!
V229: =IF(S230=0,"hide","show") -> #REF!
A230: Total Labor | C230: =SUM(C12:C219)/100% -> #REF! | F230: =SUM(F12:F219)/100% -> #REF! | I230: =SUM(I12:I219)/100% -> #REF! | L230: =SUM(L12:L219)/100% -> #REF! | O230: =SUM(O12:O219)/100% -> #REF! | R230: =SUM(R20:R219)/100% -> #REF! | S230: =SUM(S13:S219)/100% -> #REF! | T230: =SUM(S12:S219) -> #REF! | V230: =IF(S230=0,"hide","show") -> #REF!

Sheet Total Budget by Sponsored Class
B1: =Assumptions!B4 -> Partners of America
B2: =Assumptions!B5 -> DONOR: | C2: =Assumptions!C5 -> USDOL
B3: =Assumptions!B6 -> Country: | C3: =Assumptions!C6 -> Ecuador
B4: =Assumptions!B7 -> Program Name: | C4: =Assumptions!C7 -> Project to Improve Adherence to International Labor Standards in the Agricultural Sector in Ecuador
B5: =Assumptions!B8 -> Grant Number: | C5: =Assumptions!C8 -> FOA-ILAB-23-28
B6: =Assumptions!B9 -> Period of Performance: | C6: =Assumptions!C9 -> 48 months | H6: =Assumptions!G9 -> 0
B8: TOTAL BUDGET SUMMARY BY SPONSORED CLASS
H10: US COSTS for ION | I10: 78 - 12345678
A12: SF424a | B12: Sponsored Class | C12: Description | D12: G/L | E12: Description | H12: Total | I12: =#REF! -> #REF! | L12: =#REF! -> #REF! | O12: =#REF! -> #REF! | R12: =#REF! -> #REF! | U12: =#REF! -> #REF!
A14: Personnel | B14: 610000 | C14: Salaries & Wages: Faculty and Senior Staff | H14: =SUM(I14,L14,O14,R14,U14) -> #REF! | I14: =SUM('US Costs by Sponsored Class'!I14,'Incountry Costs by GL USD'!I15) -> #REF! | L14: =SUM('US Costs by Sponsored Class'!L14,'Incountry Costs by GL USD'!L15) -> #REF! | O14: =SUM('US Costs by Sponsored Class'!O14,'Incountry Costs by GL USD'!O15) -> #REF! | R14: =SUM('US Costs by Sponsored Class'!R14,'Incountry Costs by GL USD'!R15) -> #REF! | U14: =SUM('US Costs by Sponsored Class'!U14,'Incountry Costs by GL USD'!U15) -> #REF!
B15: 612000 | C15: Salaries & Wages: Administrative Staff | H15: =SUM(I15,L15,O15,R15,U15) -> #REF! | I15: ='US Costs by Sponsored Class'!I15 -> #REF! | L15: ='US Costs by Sponsored Class'!L15 -> #REF! | O15: ='US Costs by Sponsored Class'!O15 -> #REF! | R15: ='US Costs by Sponsored Class'!R15 -> #REF! | U15: ='US Costs by Sponsored Class'!U15 -> #REF!
A17: Fringe Benefits | B17: 620000 | C17: Fringe Benefits | H17: =SUM(I17,L17,O17,R17,U17) -> #REF! | I17: =SUM('US Costs by Sponsored Class'!I16,'Incountry Costs by GL USD'!I16) -> #REF! | L17: =SUM('US Costs by Sponsored Class'!L16,'Incountry Costs by GL USD'!L16) -> #REF! | O17: =SUM('US Costs by Sponsored Class'!O16,'Incountry Costs by GL USD'!O16) -> #REF! | R17: =SUM('US Costs by Sponsored Class'!R16,'Incountry Costs by GL USD'!R16) -> #REF! | U17: =SUM('US Costs by Sponsored Class'!U16,'Incountry Costs by GL USD'!U16) -> #REF!
A19: Travel | B19: 652000 | C19: Travel Domestic | H19: =SUM(I19,L19,O19,R19,U19) -> #REF! | I19: =SUM('US Costs by Sponsored Class'!I18,'Incountry Costs by GL USD'!I17) -> #REF! | L19: =SUM('US Costs by Sponsored Class'!L18,'Incountry Costs by GL USD'!L17) -> #REF! | O19: =SUM('US Costs by Sponsored Class'!O18,'Incountry Costs by GL USD'!O17) -> #REF! | R19: =SUM('US Costs by Sponsored Class'!R18,'Incountry Costs by GL USD'!R17) -> #REF! | U19: =SUM('US Costs by Sponsored Class'!U18,'Incountry Costs by GL USD'!U17) -> #REF!
B20: 652100 | C20: Travel Foreign | H20: =SUM(I20,L20,O20,R20,U20) -> #REF! | I20: =SUM('US Costs by Sponsored Class'!H19,'Incountry Costs by GL USD'!I18:I19) -> #REF! | L20: =SUM('US Costs by Sponsored Class'!K19,'Incountry Costs by GL USD'!L18:L19) -> #REF! | O20: =SUM('US Costs by Sponsored Class'!N19,'Incountry Costs by GL USD'!O18:O19) -> #REF! | R20: =SUM('US Costs by Sponsored Class'!Q19,'Incountry Costs by GL USD'!R18:R19) -> #REF! | U20: =SUM('US Costs by Sponsored Class'!T19,'Incountry Costs by GL USD'!U18:U19) -> #REF!
A22: Supplies | B22: 630000 | C22: Supplies & Materials | H22: =SUM(I22,L22,O22,R22,U22) -> #REF! | I22: =SUM('US Costs by Sponsored Class'!I21:I22,'Incountry Costs by GL USD'!I20:I29) -> #REF! | L22: =SUM('US Costs by Sponsored Class'!L21:L22,'Incountry Costs by GL USD'!L20:L29) -> #REF! | O22: =SUM('US Costs by Sponsored Class'!O21:O22,'Incountry Costs by GL USD'!O20:O29) -> #REF! | R22: =SUM('US Costs by Sponsored Class'!R21:R22,'Incountry Costs by GL USD'!R20:R29) -> #REF! | U22: =SUM('US Costs by Sponsored Class'!U21:U22,'Incountry Costs by GL USD'!U20:U29) -> #REF!
D24: 633032 | E24: Office Supplies
D25: 633037 | E25: Publications/Journals/Subscriptions
D26: 635001 | E26: Electricity
D27: 635010 | E27: Utilities: Water
D28: 640282 | E28: Delivery/Courier Service
A30: Equipment | B30: 653400 | C30: Equipment | H30: =SUM(I30,L30,O30,R30,U30) -> #REF! | I30: =SUM('US Costs by Sponsored Class'!I29,'Incountry Costs by GL USD'!I30) -> #REF! | L30: =SUM('US Costs by Sponsored Class'!L29,'Incountry Costs by GL USD'!L30) -> #REF! | O30: =SUM('US Costs by Sponsored Class'!O29,'Incountry Costs by GL USD'!O30) -> #REF! | R30: =SUM('US Costs by Sponsored Class'!R29,'Incountry Costs by GL USD'!R30) -> #REF! | U30: =SUM('US Costs by Sponsored Class'!U29,'Incountry Costs by GL USD'!U30) -> #REF!
A32: Contractual | B32: 640300 | C32: Contractual Services | H32: =SUM(I32,L32,O32,R32,U32) -> #REF! | I32: =SUM('US Costs by Sponsored Class'!I31,'Incountry Costs by GL USD'!I32:I44) -> #REF! | L32: =SUM('US Costs by Sponsored Class'!L31,'Incountry Costs by GL USD'!L32:L44) -> #REF! | O32: =SUM('US Costs by Sponsored Class'!O31,'Incountry Costs by GL USD'!O32:O44) -> #REF! | R32: =SUM('US Costs by Sponsored Class'!R31,'Incountry Costs by GL USD'!R32:R44) -> #REF! | U32: =SUM('US Costs by Sponsored Class'!U31,'Incountry Costs by GL USD'!U32:U44) -> #REF!
B33: 640500 | C33: Consultant | H33: =SUM(I33,L33,O33,R33,U33) -> #REF! | I33: =SUM('US Costs by Sponsored Class'!I32,'Incountry Costs by GL USD'!I45) -> #REF! | L33: =SUM('US Costs by Sponsored Class'!L32,'Incountry Costs by GL USD'!L45) -> #REF! | O33: =SUM('US Costs by Sponsored Class'!O32,'Incountry Costs by GL USD'!O45) -> #REF! | R33: =SUM('US Costs by Sponsored Class'!R32,'Incountry Costs by GL USD'!R45) -> #REF! | U33: =SUM('US Costs by Sponsored Class'!U32,'Incountry Costs by GL USD'!U45) -> #REF!
B34: 642400 | C34: Subaward | H34: =SUM(I34,L34,O34,R34,U34) -> #REF! | I34: =SUM('US Costs by Sponsored Class'!I33,'Incountry Costs by GL USD'!I46) -> #REF! | L34: =SUM('US Costs by Sponsored Class'!L33,'Incountry Costs by GL USD'!L46) -> #REF! | O34: =SUM('US Costs by Sponsored Class'!O33,'Incountry Costs by GL USD'!O46) -> #REF! | R34: =SUM('US Costs by Sponsored Class'!R33,'Incountry Costs by GL USD'!R46) -> #REF! | U34: =SUM('US Costs by Sponsored Class'!U33,'Incountry Costs by GL USD'!U46) -> #REF!
B35: 637000 | C35: Repairs & Maintenance | H35: =SUM(I35,L35,O35,R35,U35) -> #REF! | I35: =SUM('US Costs by Sponsored Class'!I34,'Incountry Costs by GL USD'!I31) -> #REF! | L35: =SUM('US Costs by Sponsored Class'!L34,'Incountry Costs by GL USD'!L31) -> #REF! | O35: =SUM('US Costs by Sponsored Class'!O34,'Incountry Costs by GL USD'!O31) -> #REF! | R35: =SUM('US Costs by Sponsored Class'!R34,'Incountry Costs by GL USD'!R31) -> #REF! | U35: =SUM('US Costs by Sponsored Class'!U34,'Incountry Costs by GL USD'!U31) -> #REF!
A37: Other | B37: 640102 | C37: Leased Facilities External | H37: =SUM(I37,L37,O37,R37,U37) -> #REF! | I37: =SUM('US Costs by Sponsored Class'!I36,'Incountry Costs by GL USD'!I47) -> #REF! | L37: =SUM('US Costs by Sponsored Class'!L36,'Incountry Costs by GL USD'!L47) -> #REF! | O37: =SUM('US Costs by Sponsored Class'!O36,'Incountry Costs by GL USD'!O47) -> #REF! | R37: =SUM('US Costs by Sponsored Class'!R36,'Incountry Costs by GL USD'!R47) -> #REF! | U37: =SUM('US Costs by Sponsored Class'!U36,'Incountry Costs by GL USD'!U47) -> #REF!
B38: 641400 | C38: Telecommunications | H38: =SUM(I38,L38,O38,R38,U38) -> #REF! | I38: =SUM('US Costs by Sponsored Class'!I37,'Incountry Costs by GL USD'!I48) -> #REF! | L38: =SUM('US Costs by Sponsored Class'!L37,'Incountry Costs by GL USD'!L48) -> #REF! | O38: =SUM('US Costs by Sponsored Class'!O37,'Incountry Costs by GL USD'!O48) -> #REF! | R38: =SUM('US Costs by Sponsored Class'!R37,'Incountry Costs by GL USD'!R48) -> #REF! | U38: =SUM('US Costs by Sponsored Class'!U37,'Incountry Costs by GL USD'!U48) -> #REF!
B39: 642500 | C39: Other Expenses | H39: =SUM(I39,L39,O39,R39,U39) -> #REF! | I39: =SUM('US Costs by Sponsored Class'!I38,'Incountry Costs by GL USD'!I49:I54) -> #REF! | L39: =SUM('US Costs by Sponsored Class'!L38,'Incountry Costs by GL USD'!L49:L54) -> #REF! | O39: =SUM('US Costs by Sponsored Class'!O38,'Incountry Costs by GL USD'!O49:O54) -> #REF! | R39: =SUM('US Costs by Sponsored Class'!R38,'Incountry Costs by GL USD'!R49:R54) -> #REF! | U39: =SUM('US Costs by Sponsored Class'!U38,'Incountry Costs by GL USD'!U49:U54) -> #REF!
B40: 643000 | C40: Other Expenses (Excluded from F&A) | H40: =SUM(I40,L40,O40,R40,U40) -> #REF! | I40: =SUM('US Costs by Sponsored Class'!I39,'Incountry Costs by GL USD'!I55:I56) -> #REF! | L40: =SUM('US Costs by Sponsored Class'!L39,'Incountry Costs by GL USD'!L55:L56) -> #REF! | O40: =SUM('US Costs by Sponsored Class'!O39,'Incountry Costs by GL USD'!O55:O56) -> #REF! | R40: =SUM('US Costs by Sponsored Class'!R39,'Incountry Costs by GL USD'!R55:R56) -> #REF! | U40: =SUM('US Costs by Sponsored Class'!U39,'Incountry Costs by GL USD'!U55:U56) -> #REF!
B42: Subtotal | H42: =SUM(I42,L42,O42,R42,U42) -> #REF! | I42: =SUM(I13:I41) -> #REF! | L42: =SUM(L13:L41) -> #REF! | O42: =SUM(O13:O41) -> #REF! | R42: =SUM(R13:R41) -> #REF! | U42: =SUM(U13:U41) -> #REF!
B44: 690007 | C44: Service Center | H44: =SUM(I44,L44,O44,R44,U44) -> #REF! | I44: ='US Costs by Sponsored Class'!I43 -> #REF! | L44: ='US Costs by Sponsored Class'!L43 -> #REF! | O44: ='US Costs by Sponsored Class'!O43 -> #REF! | R44: ='US Costs by Sponsored Class'!R43 -> #REF! | U44: ='US Costs by Sponsored Class'!U43 -> #REF!
B46: 699999 | C46: F&A | H46: =SUM(I46,L46,O46,R46,U46) -> #REF! | I46: ='US Costs by Sponsored Class'!I45 -> #REF! | L46: ='US Costs by Sponsored Class'!L45 -> #REF! | O46: ='US Costs by Sponsored Class'!O45 -> #REF! | R46: ='US Costs by Sponsored Class'!R45 -> #REF! | U46: ='US Costs by Sponsored Class'!U45 -> #REF!
B48: Total per year | H48: =SUM(I48,L48,O48,R48,U48) -> #REF! | I48: =SUM(I42:I47) -> #REF! | L48: =SUM(L42:L47) -> #REF! | O48: =SUM(O42:O47) -> #REF! | R48: =SUM(R42:R47) -> #REF! | U48: =SUM(U42:U47) -> #REF!
B50: Calculation check

Sheet US Costs by Sponsored Class
B1: =Assumptions!B4 -> Partners of America
B2: =Assumptions!B5 -> DONOR: | C2: =Assumptions!C5 -> USDOL
B3: =Assumptions!B6 -> Country: | C3: =Assumptions!C6 -> Ecuador
B4: =Assumptions!B7 -> Program Name: | C4: =Assumptions!C7 -> Project to Improve Adherence to International Labor Standards in the Agricultural Sector in Ecuador
B5: =Assumptions!B8 -> Grant Number: | C5: =Assumptions!C8 -> FOA-ILAB-23-28
B6: =Assumptions!B9 -> Period of Performance: | C6: =Assumptions!C9 -> 48 months | E6: =Assumptions!G9 -> 0
B8: BUDGET SUMMARY BY G/L
D10: US COSTS for ION | E10: 78 - 12345678
A12: SF424a | B12: Sponsored Class | C12: Description | D12: G/L | E12: Description | H12: Workplan Year Budget | I12: =#REF! -> #REF! | L12: =#REF! -> #REF! | O12: =#REF! -> #REF! | R12: =#REF! -> #REF! | U12: =#REF! -> #REF!
A14: Personnel | B14: 610000 | C14: Salaries & Wages: Faculty and Senior Staff | D14: 613001 | E14: Salary: Non-Administrative Staff | H14: =SUM(I14,L14,O14,R14,U14) -> #REF! | I14: =SUMIF(#REF!,$B$14,#REF!) -> #REF! | L14: =SUMIF(#REF!,$B$14,#REF!) -> #REF! | O14: =SUMIF(#REF!,$B$14,#REF!) -> #REF! | R14: =SUMIF(#REF!,$B$14,#REF!) -> #REF! | U14: =SUMIF(#REF!,$B$14,#REF!) -> #REF!
B15: 612000 | C15: Salaries & Wages: Administrative Staff | D15: 612001 | E15: Salary: Administrative Staff | H15: =SUM(I15,L15,O15,R15,U15) -> #REF! | I15: =SUMIF(#REF!,$B$15,#REF!) -> #REF! | L15: =SUMIF(#REF!,$B$15,#REF!) -> #REF! | O15: =SUMIF(#REF!,$B$15,#REF!) -> #REF! | R15: =SUMIF(#REF!,$B$15,#REF!) -> #REF! | U15: =SUMIF(#REF!,$B$15,#REF!) -> #REF!
A16: Fringe Benefits | B16: 620000 | C16: Fringe Benefits | D16: 620001 | E16: Fringe Benefits: Staff | H16: =SUM(I16,L16,O16,R16,U16) -> #REF! | I16: =SUMIF(#REF!,$B$16,#REF!) -> #REF! | L16: =SUMIF(#REF!,$B$16,#REF!) -> #REF! | O16: =SUMIF(#REF!,$B$16,#REF!) -> #REF! | R16: =SUMIF(#REF!,$B$16,#REF!) -> #REF! | U16: =SUMIF(#REF!,$B$16,#REF!) -> #REF!
D17: 620002 | E17: Fringe Benefits: Allowances
A18: Travel | B18: 652000 | C18: Travel Domestic | H18: =SUM(I18,L18,O18,R18,U18) -> #REF! | I18: =SUMIF(#REF!,$B$18,#REF!) -> #REF! | L18: =SUMIF(#REF!,$B$18,#REF!) -> #REF! | O18: =SUMIF(#REF!,$B$18,#REF!) -> #REF! | R18: =SUMIF(#REF!,$B$18,#REF!) -> #REF! | U18: =SUMIF(#REF!,$B$18,#REF!) -> #REF!
B19: 652100 | C19: Travel Foreign | H19: =SUM(I19,L19,O19,R19,U19) -> #REF! | I19: =SUMIF(#REF!,$B$19,#REF!) -> #REF! | L19: =SUMIF(#REF!,$B$19,#REF!) -> #REF! | O19: =SUMIF(#REF!,$B$19,#REF!) -> #REF! | R19: =SUMIF(#REF!,$B$19,#REF!) -> #REF! | U19: =SUMIF(#REF!,$B$19,#REF!) -> #REF!
A21: Supplies | B21: 630000 | C21: Supplies & Materials | D21: 631001 | E21: Furniture | H21: =SUM(I21,L21,O21,R21,U21) -> #REF! | I21: =SUMIF(#REF!,$B$21,#REF!) -> #REF! | L21: =SUMIF(#REF!,$B$21,#REF!) -> #REF! | O21: =SUMIF(#REF!,$B$21,#REF!) -> #REF! | R21: =SUMIF(#REF!,$B$21,#REF!) -> #REF! | U21: =SUMIF(#REF!,$B$21,#REF!) -> #REF!
D22: 631003 | E22: Non-capital PC purchases | H22: =SUM(I22,L22,O22,R22,U22) -> #REF! | I22: =SUMIF(#REF!,$B$21,#REF!) -> #REF! | L22: =SUMIF(#REF!,$B$21,#REF!) -> #REF! | O22: =SUMIF(#REF!,$B$21,#REF!) -> #REF! | R22: =SUMIF(#REF!,$B$21,#REF!) -> #REF! | U22: =SUMIF(#REF!,$B$21,#REF!) -> #REF!
D23: 633032 | E23: Office Supplies | H23: =SUM(I23,L23,O23,R23,U23,#REF!,#REF!,#REF!,#REF!,#REF!) -> #REF!
D24: 633037 | E24: Publications/Journals/Subscriptions | H24: =SUM(I24,L24,O24,R24,U24,#REF!,#REF!,#REF!,#REF!,#REF!) -> #REF!
D25: 635001 | E25: Electricity | H25: =SUM(I25,L25,O25,R25,U25,#REF!,#REF!,#REF!,#REF!,#REF!) -> #REF!
D26: 635010 | E26: Utilities: Water | H26: =SUM(I26,L26,O26,R26,U26,#REF!,#REF!,#REF!,#REF!,#REF!) -> #REF!
D27: 640282 | E27: Delivery/Courier Service | H27: =SUM(I27,L27,O27,R27,U27,#REF!,#REF!,#REF!,#REF!,#REF!) -> #REF!
A29: Equipment | B29: 653400 | C29: Equipment | H29: =SUM(I29,L29,O29,R29,U29) -> #REF! | I29: =SUMIF(#REF!,$B$29,#REF!) -> #REF! | L29: =SUMIF(#REF!,$B$29,#REF!) -> #REF! | O29: =SUMIF(#REF!,$B$29,#REF!) -> #REF! | R29: =SUMIF(#REF!,$B$29,#REF!) -> #REF! | U29: =SUMIF(#REF!,$B$29,#REF!) -> #REF!
A31: Contractual | B31: 640300 | C31: Contractual Services | H31: =SUM(I31,L31,O31,R31,U31) -> #REF! | I31: =SUMIF(#REF!,$B$31,#REF!) -> #REF! | L31: =SUMIF(#REF!,$B$31,#REF!) -> #REF! | O31: =SUMIF(#REF!,$B$31,#REF!) -> #REF! | R31: =SUMIF(#REF!,$B$31,#REF!) -> #REF! | U31: =SUMIF(#REF!,$B$31,#REF!) -> #REF!
B32: 640500 | C32: Consultant | H32: =SUM(I32,L32,O32,R32,U32) -> #REF! | I32: =SUMIF(#REF!,$B$32,#REF!) -> #REF! | L32: =SUMIF(#REF!,$B$32,#REF!) -> #REF! | O32: =SUMIF(#REF!,$B$32,#REF!) -> #REF! | R32: =SUMIF(#REF!,$B$32,#REF!) -> #REF! | U32: =SUMIF(#REF!,$B$32,#REF!) -> #REF!
B33: 642400 | C33: Subaward | H33: =SUM(I33,L33,O33,R33,U33) -> #REF! | I33: =SUMIF(#REF!,$B$33,#REF!) -> #REF! | L33: =SUMIF(#REF!,$B$33,#REF!) -> #REF! | O33: =SUMIF(#REF!,$B$33,#REF!) -> #REF! | R33: =SUMIF(#REF!,$B$33,#REF!) -> #REF! | U33: =SUMIF(#REF!,$B$33,#REF!) -> #REF!
B34: 637000 | C34: Repairs & Maintenance | H34: =SUM(I34,L34,O34,R34,U34) -> #REF! | I34: =SUMIF(#REF!,$B$34,#REF!) -> #REF! | L34: =SUMIF(#REF!,$B$34,#REF!) -> #REF! | O34: =SUMIF(#REF!,$B$34,#REF!) -> #REF! | R34: =SUMIF(#REF!,$B$34,#REF!) -> #REF! | U34: =SUMIF(#REF!,$B$34,#REF!) -> #REF!
A36: Other | B36: 640102 | C36: Leased Facilities External | H36: =SUM(I36,L36,O36,R36,U36) -> #REF! | I36: =SUMIF(#REF!,$B$36,#REF!) -> #REF! | L36: =SUMIF(#REF!,$B$36,#REF!) -> #REF! | O36: =SUMIF(#REF!,$B$36,#REF!) -> #REF! | R36: =SUMIF(#REF!,$B$36,#REF!) -> #REF! | U36: =SUMIF(#REF!,$B$36,#REF!) -> #REF!
B37: 641400 | C37: Telecommunications | H37: =SUM(I37,L37,O37,R37,U37) -> #REF! | I37: =SUMIF(#REF!,$B$37,#REF!) -> #REF! | L37: =SUMIF(#REF!,$B$37,#REF!) -> #REF! | O37: =SUMIF(#REF!,$B$37,#REF!) -> #REF! | R37: =SUMIF(#REF!,$B$37,#REF!) -> #REF! | U37: =SUMIF(#REF!,$B$37,#REF!) -> #REF!
B38: 642500 | C38: Other Expenses | H38: =SUM(I38,L38,O38,R38,U38) -> #REF! | I38: =SUMIF(#REF!,$B$38,#REF!) -> #REF! | L38: =SUMIF(#REF!,$B$38,#REF!) -> #REF! | O38: =SUMIF(#REF!,$B$38,#REF!) -> #REF! | R38: =SUMIF(#REF!,$B$38,#REF!) -> #REF! | U38: =SUMIF(#REF!,$B$38,#REF!) -> #REF!
B39: 643000 | C39: Other Expenses (Excluded from F&A) | H39: =SUM(I39,L39,O39,R39,U39) -> #REF! | I39: =SUMIF(#REF!,$B$39,#REF!) -> #REF! | L39: =SUMIF(#REF!,$B$39,#REF!) -> #REF! | O39: =SUMIF(#REF!,$B$39,#REF!) -> #REF! | R39: =SUMIF(#REF!,$B$39,#REF!) -> #REF! | U39: =SUMIF(#REF!,$B$39,#REF!) -> #REF!
B41: Subtotal | H41: =SUM(I41,L41,O41,R41,U41) -> #REF! | I41: =SUM(L13:L40) -> #REF! | L41: =SUM(O13:O40) -> #REF! | O41: =SUM(R13:R40) -> #REF! | R41: =SUM(U13:U40) -> #REF! | U41: =SUM(X13:X40) -> 0
B43: 690007 | C43: Service Center | H43: =SUM(I43,L43,O43,R43,U43) -> #REF! | I43: =SUMIF(#REF!,$B$43,#REF!) -> #REF! | L43: =SUMIF(#REF!,$B$43,#REF!) -> #REF! | O43: =SUMIF(#REF!,$B$43,#REF!) -> #REF! | R43: =SUMIF(#REF!,$B$43,#REF!) -> #REF! | U43: =SUMIF(#REF!,$B$43,#REF!) -> #REF!
B45: 699999 | C45: F&A | H45: =SUM(I45,L45,O45,R45,U45) -> #REF! | I45: =SUMIF(#REF!,$B$45,#REF!) -> #REF! | L45: =SUMIF(#REF!,$B$45,#REF!) -> #REF! | O45: =SUMIF(#REF!,$B$45,#REF!) -> #REF! | R45: =SUMIF(#REF!,$B$45,#REF!) -> #REF! | U45: =SUMIF(#REF!,$B$45,#REF!) -> #REF!
B47: Total per year | H47: =SUM(H41:H46) -> #REF! | I47: =SUM(I41:I46) -> #REF! | L47: =SUM(L41:L46) -> #REF! | O47: =SUM(O41:O46) -> #REF! | R47: =SUM(R41:R46) -> #REF! | U47: =SUM(U41:U46) -> #REF!
B49: Calculation check | I49: =SUM(#REF!,#REF!,#REF!) -> #REF! | L49: =SUM(#REF!,#REF!,#REF!) -> #REF! | O49: =SUM(#REF!,#REF!,#REF!) -> #REF! | R49: =SUM(#REF!,#REF!,#REF!) -> #REF! | U49: =SUM(#REF!,#REF!,#REF!) -> #REF!

Sheet Incountry Costs by GL USD
D1: Jhpiego Corporation
D2: =Assumptions!B5 -> DONOR: | E2: =Assumptions!C5 -> USDOL
D3: =Assumptions!B6 -> Country: | E3: =Assumptions!C6 -> Ecuador
D4: =Assumptions!B7 -> Program Name: | E4: =Assumptions!C7 -> Project to Improve Adherence to International Labor Standards in the Agricultural Sector in Ecuador
D5: =Assumptions!B8 -> Grant Number: | E5: =Assumptions!C8 -> FOA-ILAB-23-28
D6: =Assumptions!B9 -> Period of Performance: | E6: =Assumptions!C9 -> 48 months | H6: =Assumptions!G9 -> 0
D8: BUDGET SUMMARY BY G/L in USD
D10: IN-COUNTRY COSTS by Jhpiego FISCAL YEAR
E11: IN-COUNTRY ION: | I11: 21 - 987654321 | L11: 22 - 987654322 | O11: 23 - 987654323 | R11: 24 - 987654324 | U11: 25 - 987654325
A13: SF424a | B13: Sponsored Class | C13: Description | D13: G/L | E13: Description | H13: Workplan Year Budget | I13: =#REF! -> #REF! | L13: =#REF! -> #REF! | O13: =#REF! -> #REF! | R13: =#REF! -> #REF! | U13: =#REF! -> #REF!
A15: Personnel | B15: 610000 | C15: Salaries & Wages | D15: 616112 | E15: In-country Salaries | H15: =SUM(I15,L15,O15,R15,U15) -> #REF! | I15: =SUMIF(#REF!,$D$15,#REF!) -> #REF! | L15: =SUMIF(#REF!,$D$15,#REF!) -> #REF! | O15: =SUMIF(#REF!,$D$15,#REF!) -> #REF! | R15: =SUMIF(#REF!,$D$15,#REF!) -> #REF! | U15: =SUMIF(#REF!,$D$15,#REF!) -> #REF!
A16: Fringe Benefits | B16: 620000 | C16: Fringe Benefits | D16: 620112 | E16: In-country Fringe | H16: =SUM(I16,L16,O16,R16,U16) -> #REF! | I16: =SUMIF(#REF!,$D$16,#REF!) -> #REF! | L16: =SUMIF(#REF!,$D$16,#REF!) -> #REF! | O16: =SUMIF(#REF!,$D$16,#REF!) -> #REF! | R16: =SUMIF(#REF!,$D$16,#REF!) -> #REF! | U16: =SUMIF(#REF!,$D$16,#REF!) -> #REF!
A17: Travel | B17: 652000 | C17: Travel Domestic | D17: 652201 | E17: Trainee Travel | H17: =SUM(I17,L17,O17,R17,U17) -> #REF! | I17: =SUMIF(#REF!,$D$17,#REF!) -> #REF! | L17: =SUMIF(#REF!,$D$17,#REF!) -> #REF! | O17: =SUMIF(#REF!,$D$17,#REF!) -> #REF! | R17: =SUMIF(#REF!,$D$17,#REF!) -> #REF! | U17: =SUMIF(#REF!,$D$17,#REF!) -> #REF!
B18: 652100 | C18: Travel Foreign | D18: 652101 | E18: Travel Foreign | H18: =SUM(I18,L18,O18,R18,U18) -> #REF! | I18: =SUMIF(#REF!,$D$18,#REF!) -> #REF! | L18: =SUMIF(#REF!,$D$18,#REF!) -> #REF! | O18: =SUMIF(#REF!,$D$18,#REF!) -> #REF! | R18: =SUMIF(#REF!,$D$18,#REF!) -> #REF! | U18: =SUMIF(#REF!,$D$18,#REF!) -> #REF!
D19: 652102 | E19: Travel Overseas Local | H19: =SUM(I19,L19,O19,R19,U19) -> #REF! | I19: =SUMIF(#REF!,$D$19,#REF!) -> #REF! | L19: =SUMIF(#REF!,$D$19,#REF!) -> #REF! | O19: =SUMIF(#REF!,$D$19,#REF!) -> #REF! | R19: =SUMIF(#REF!,$D$19,#REF!) -> #REF! | U19: =SUMIF(#REF!,$D$19,#REF!) -> #REF!
A20: Supplies | B20: 630000 | C20: Supplies & Materials | D20: 631001 | E20: Furniture | H20: =SUM(I20,L20,O20,R20,U20) -> #REF! | I20: =SUMIF(#REF!,$D$20,#REF!) -> #REF! | L20: =SUMIF(#REF!,$D$20,#REF!) -> #REF! | O20: =SUMIF(#REF!,$D$20,#REF!) -> #REF! | R20: =SUMIF(#REF!,$D$20,#REF!) -> #REF! | U20: =SUMIF(#REF!,$D$20,#REF!) -> #REF!
B21: 630000 | C21: Supplies & Materials | D21: 631003 | E21: Non-capital PC purchases | H21: =SUM(I21,L21,O21,R21,U21) -> #REF! | I21: =SUMIF(#REF!,$D$21,#REF!) -> #REF! | L21: =SUMIF(#REF!,$D$21,#REF!) -> #REF! | O21: =SUMIF(#REF!,$D$21,#REF!) -> #REF! | R21: =SUMIF(#REF!,$D$21,#REF!) -> #REF! | U21: =SUMIF(#REF!,$D$21,#REF!) -> #REF!
B22: 630000 | C22: Supplies & Materials | D22: 633027 | E22: Supplies & Other PSC | H22: =SUM(I22,L22,O22,R22,U22) -> #REF! | I22: =SUMIF(#REF!,$D$22,#REF!) -> #REF! | J22: =SUMIF(#REF!,$D$22,#REF!) -> #REF! | K22: =SUMIF(#REF!,$D$22,#REF!) -> #REF! | L22: =SUMIF(#REF!,$D$22,#REF!) -> #REF! | M22: =SUMIF(#REF!,$D$22,#REF!) -> #REF! | N22: =SUMIF(#REF!,$D$22,#REF!) -> #REF! | O22: =SUMIF(#REF!,$D$22,#REF!) -> #REF! | P22: =SUMIF(#REF!,$D$22,#REF!) -> #REF! | ... W22: =SUMIF(#REF!,$D$22,#REF!) -> #REF!
B23: 630000 | C23: Supplies & Materials | D23: 633032 | E23: Office Supplies | H23: =SUM(I23,L23,O23,R23,U23) -> #REF! | I23: =SUMIF(#REF!,$D$23,#REF!) -> #REF! | L23: =SUMIF(#REF!,$D$23,#REF!) -> #REF! | O23: =SUMIF(#REF!,$D$23,#REF!) -> #REF! | R23: =SUMIF(#REF!,$D$23,#REF!) -> #REF! | U23: =SUMIF(#REF!,$D$23,#REF!) -> #REF!
B24: 630000 | C24: Supplies & Materials | D24: 630064 | E24: Medical Supplies | H24: =SUM(I24,L24,O24,R24,U24) -> #REF! | I24: 0 | L24: =SUMIF(#REF!,$D$23,#REF!) -> #REF! | O24: =SUMIF(#REF!,$D$23,#REF!) -> #REF! | R24: =SUMIF(#REF!,$D$23,#REF!) -> #REF! | U24: =SUMIF(#REF!,$D$23,#REF!) -> #REF!
B25: 630000 | C25: Supplies & Materials | D25: 633002 | E25: Expendable Supplies | H25: =SUM(I25,L25,O25,R25,U25) -> #REF! | I25: 0 | L25: =SUMIF(#REF!,$D$23,#REF!) -> #REF! | O25: =SUMIF(#REF!,$D$23,#REF!) -> #REF! | R25: =SUMIF(#REF!,$D$23,#REF!) -> #REF! | U25: =SUMIF(#REF!,$D$23,#REF!) -> #REF!
B26: 630000 | C26: Supplies & Materials | D26: 633037 | E26: Publications/Journals/Subscriptions | H26: =SUM(I26,L26,O26,R26,U26) -> #REF! | I26: =SUMIF(#REF!,$D$26,#REF!) -> #REF! | L26: =SUMIF(#REF!,$D$26,#REF!) -> #REF! | O26: =SUMIF(#REF!,$D$26,#REF!) -> #REF! | R26: =SUMIF(#REF!,$D$26,#REF!) -> #REF! | U26: =SUMIF(#REF!,$D$26,#REF!) -> #REF!
B27: 630000 | C27: Supplies & Materials | D27: 635001 | E27: Electricity | H27: =SUM(I27,L27,O27,R27,U27) -> #REF! | I27: =SUMIF(#REF!,$D$27,#REF!) -> #REF! | L27: =SUMIF(#REF!,$D$27,#REF!) -> #REF! | O27: =SUMIF(#REF!,$D$27,#REF!) -> #REF! | R27: =SUMIF(#REF!,$D$27,#REF!) -> #REF! | U27: =SUMIF(#REF!,$D$27,#REF!) -> #REF!
B28: 630000 | C28: Supplies & Materials | D28: 635010 | E28: Utilities: Water | H28: =SUM(I28,L28,O28,R28,U28) -> #REF! | I28: =SUMIF(#REF!,$D$28,#REF!) -> #REF! | L28: =SUMIF(#REF!,$D$28,#REF!) -> #REF! | O28: =SUMIF(#REF!,$D$28,#REF!) -> #REF! | R28: =SUMIF(#REF!,$D$28,#REF!) -> #REF! | U28: =SUMIF(#REF!,$D$28,#REF!) -> #REF!
B29: 630000 | C29: Supplies & Materials | D29: 640282 | E29: Delivery/Courier Service | H29: =SUM(I29,L29,O29,R29,U29) -> #REF! | I29: =SUMIF(#REF!,$D$29,#REF!) -> #REF! | L29: =SUMIF(#REF!,$D$29,#REF!) -> #REF! | O29: =SUMIF(#REF!,$D$29,#REF!) -> #REF! | R29: =SUMIF(#REF!,$D$29,#REF!) -> #REF! | U29: =SUMIF(#REF!,$D$29,#REF!) -> #REF!
A30: Equipment | B30: 653400 | C30: Equipment | D30: 631099 | E30: Equipment Purchases - SRM only | H30: =SUM(I30,L30,O30,R30,U30) -> #REF! | I30: =SUMIF(#REF!,$D$30,#REF!) -> #REF! | L30: =SUMIF(#REF!,$D$30,#REF!) -> #REF! | O30: =SUMIF(#REF!,$D$30,#REF!) -> #REF! | R30: =SUMIF(#REF!,$D$30,#REF!) -> #REF! | U30: =SUMIF(#REF!,$D$30,#REF!) -> #REF!
A31: Contractual | B31: 637000 | C31: Repairs & Maintenance | D31: 637001 | E31: Equipment Maintenance Agreements | H31: =SUM(I31,L31,O31,R31,U31) -> #REF! | I31: =SUMIF(#REF!,$D$31,#REF!) -> #REF! | L31: =SUMIF(#REF!,$D$31,#REF!) -> #REF! | O31: =SUMIF(#REF!,$D$31,#REF!) -> #REF! | R31: =SUMIF(#REF!,$D$31,#REF!) -> #REF! | U31: =SUMIF(#REF!,$D$31,#REF!) -> #REF!
B32: 640300 | C32: Contractual Services | D32: 640101 | E32: Rental Short-Term | H32: =SUM(I32,L32,O32,R32,U32) -> #REF! | I32: =SUMIF(#REF!,$D$32,#REF!) -> #REF! | L32: =SUMIF(#REF!,$D$32,#REF!) -> #REF! | O32: =SUMIF(#REF!,$D$32,#REF!) -> #REF! | R32: =SUMIF(#REF!,$D$32,#REF!) -> #REF! | U32: =SUMIF(#REF!,$D$32,#REF!) -> #REF!
B33: 640300 | C33: Contractual Services | D33: 640202 | E33: Equipment Lease Payment | H33: =SUM(I33,L33,O33,R33,U33) -> #REF! | I33: =SUMIF(#REF!,$D$33,#REF!) -> #REF! | L33: =SUMIF(#REF!,$D$33,#REF!) -> #REF! | O33: =SUMIF(#REF!,$D$33,#REF!) -> #REF! | R33: =SUMIF(#REF!,$D$33,#REF!) -> #REF! | U33: =SUMIF(#REF!,$D$33,#REF!) -> #REF!
B34: 640300 | C34: Contractual Services | D34: 640205 | E34: Motor Vehicle Leasing | H34: =SUM(I34,L34,O34,R34,U34) -> #REF! | I34: =SUMIF(#REF!,$D$34,#REF!) -> #REF! | L34: =SUMIF(#REF!,$D$34,#REF!) -> #REF! | O34: =SUMIF(#REF!,$D$34,#REF!) -> #REF! | R34: =SUMIF(#REF!,$D$34,#REF!) -> #REF! | U34: =SUMIF(#REF!,$D$34,#REF!) -> #REF!
B35: 640300 | C35: Contractual Services | D35: 640301 | E35: Contractual Services - General | H35: =SUM(I35,L35,O35,R35,U35) -> #REF! | I35: =SUMIF(#REF!,$D$35,#REF!) -> #REF! | L35: =SUMIF(#REF!,$D$35,#REF!) -> #REF! | O35: =SUMIF(#REF!,$D$35,#REF!) -> #REF! | R35: =SUMIF(#REF!,$D$35,#REF!) -> #REF! | U35: =SUMIF(#REF!,$D$35,#REF!) -> #REF!
B36: 640300 | C36: Contractual Services | D36: 640317 | E36: Contractual Services - Ground Maintenance | H36: =SUM(I36,L36,O36,R36,U36) -> #REF! | I36: =SUMIF(#REF!,$D$36,#REF!) -> #REF! | L36: =SUMIF(#REF!,$D$36,#REF!) -> #REF! | O36: =SUMIF(#REF!,$D$36,#REF!) -> #REF! | R36: =SUMIF(#REF!,$D$36,#REF!) -> #REF! | U36: =SUMIF(#REF!,$D$36,#REF!) -> #REF!
B37: 640300 | C37: Contractual Services | D37: 640318 | E37: Contractual Services - Cleaning | H37: =SUM(I37,L37,O37,R37,U37) -> #REF! | I37: =SUMIF(#REF!,$D$37,#REF!) -> #REF! | L37: =SUMIF(#REF!,$D$37,#REF!) -> #REF! | O37: =SUMIF(#REF!,$D$37,#REF!) -> #REF! | R37: =SUMIF(#REF!,$D$37,#REF!) -> #REF! | U37: =SUMIF(#REF!,$D$37,#REF!) -> #REF!
B38: 640300 | C38: Contractual Services | D38: 640321 | E38: Contractual Services - Off-Site Storage | H38: =SUM(I38,L38,O38,R38,U38) -> #REF! | I38: =SUMIF(#REF!,$D$38,#REF!) -> #REF! | L38: =SUMIF(#REF!,$D$38,#REF!) -> #REF! | O38: =SUMIF(#REF!,$D$38,#REF!) -> #REF! | R38: =SUMIF(#REF!,$D$38,#REF!) -> #REF! | U38: =SUMIF(#REF!,$D$38,#REF!) -> #REF!
B39: 640300 | C39: Contractual Services | D39: 640341 | E39: Contractual Services - Security Services | H39: =SUM(I39,L39,O39,R39,U39) -> #REF! | I39: =SUMIF(#REF!,$D$39,#REF!) -> #REF! | L39: =SUMIF(#REF!,$D$39,#REF!) -> #REF! | O39: =SUMIF(#REF!,$D$39,#REF!) -> #REF! | R39: =SUMIF(#REF!,$D$39,#REF!) -> #REF! | U39: =SUMIF(#REF!,$D$39,#REF!) -> #REF!
B40: 640300 | C40: Contractual Services | D40: 640351 | E40: Legal Fees | H40: =SUM(I40,L40,O40,R40,U40) -> #REF! | I40: =SUMIF(#REF!,$D$40,#REF!) -> #REF! | L40: =SUMIF(#REF!,$D$40,#REF!) -> #REF! | O40: =SUMIF(#REF!,$D$40,#REF!) -> #REF! | R40: =SUMIF(#REF!,$D$40,#REF!) -> #REF! | U40: =SUMIF(#REF!,$D$40,#REF!) -> #REF!
B41: 640300 | C41: Contractual Services | D41: 640361 | E41: Accounting/Auditing Expense | H41: =SUM(I41,L41,O41,R41,U41) -> #REF! | I41: =SUMIF(#REF!,$D$41,#REF!) -> #REF! | L41: =SUMIF(#REF!,$D$41,#REF!) -> #REF! | O41: =SUMIF(#REF!,$D$41,#REF!) -> #REF! | R41: =SUMIF(#REF!,$D$41,#REF!) -> #REF! | U41: =SUMIF(#REF!,$D$41,#REF!) -> #REF!
B42: 640300 | C42: Contractual Services | D42: 640381 | E42: Professional Services - External | H42: =SUM(I42,L42,O42,R42,U42) -> #REF! | I42: =SUMIF(#REF!,$D$42,#REF!) -> #REF! | L42: =SUMIF(#REF!,$D$42,#REF!) -> #REF! | O42: =SUMIF(#REF!,$D$42,#REF!) -> #REF! | R42: =SUMIF(#REF!,$D$42,#REF!) -> #REF! | U42: =SUMIF(#REF!,$D$42,#REF!) -> #REF!
B43: 640300 | C43: Contractual Services | D43: 640455 | E43: Software Maintenance Agreeement | H43: =SUM(I43,L43,O43,R43,U43) -> #REF! | I43: =SUMIF(#REF!,$D$43,#REF!) -> #REF! | L43: =SUMIF(#REF!,$D$43,#REF!) -> #REF! | O43: =SUMIF(#REF!,$D$43,#REF!) -> #REF! | R43: =SUMIF(#REF!,$D$43,#REF!) -> #REF! | U43: =SUMIF(#REF!,$D$43,#REF!) -> #REF!
B44: 640300 | C44: Contractual Services | D44: 642501 | E44: Printing | H44: =SUM(I44,L44,O44,R44,U44) -> #REF! | I44: =SUMIF(#REF!,$D$44,#REF!) -> #REF! | L44: =SUMIF(#REF!,$D$44,#REF!) -> #REF! | O44: =SUMIF(#REF!,$D$44,#REF!) -> #REF! | R44: =SUMIF(#REF!,$D$44,#REF!) -> #REF! | U44: =SUMIF(#REF!,$D$44,#REF!) -> #REF!
B45: 640500 | C45: Contractual Services | D45: 640501 | E45: Consultant Fees | H45: =SUM(I45,L45,O45,R45,U45) -> #REF! | I45: =SUMIF(#REF!,$D$45,#REF!) -> #REF! | L45: =SUMIF(#REF!,$D$45,#REF!) -> #REF! | O45: =SUMIF(#REF!,$D$45,#REF!) -> #REF! | R45: =SUMIF(#REF!,$D$45,#REF!) -> #REF! | U45: =SUMIF(#REF!,$D$45,#REF!) -> #REF!
B46: 642400 | C46: Subaward | D46: 642405 | E46: Subaward General | H46: =SUM(I46,L46,O46,R46,U46) -> #REF! | I46: =SUMIF(#REF!,$D$46,#REF!) -> #REF! | L46: =SUMIF(#REF!,$D$46,#REF!) -> #REF! | O46: =SUMIF(#REF!,$D$46,#REF!) -> #REF! | R46: =SUMIF(#REF!,$D$46,#REF!) -> #REF! | U46: =SUMIF(#REF!,$D$46,#REF!) -> #REF!
A47: Other | B47: 640102 | C47: Leased Facilities External | D47: 640102 | E47: Leased Facilities External | H47: =SUM(I47,L47,O47,R47,U47) -> #REF! | I47: =SUMIF(#REF!,$D$47,#REF!) -> #REF! | L47: =SUMIF(#REF!,$D$47,#REF!) -> #REF! | O47: =SUMIF(#REF!,$D$47,#REF!) -> #REF! | R47: =SUMIF(#REF!,$D$47,#REF!) -> #REF! | U47: =SUMIF(#REF!,$D$47,#REF!) -> #REF!
B48: 641400 | C48: Telecommunications | D48: 641402 | E48: Telephone Long Distance | H48: =SUM(I48,L48,O48,R48,U48) -> #REF! | I48: =SUMIF(#REF!,$D$48,#REF!) -> #REF! | L48: =SUMIF(#REF!,$D$48,#REF!) -> #REF! | O48: =SUMIF(#REF!,$D$48,#REF!) -> #REF! | R48: =SUMIF(#REF!,$D$48,#REF!) -> #REF! | U48: =SUMIF(#REF!,$D$48,#REF!) -> #REF!
B49: 642500 | C49: Other Expenses | D49: 640403 | E49: Memberships/Dues | H49: =SUM(I49,L49,O49,R49,U49) -> #REF! | I49: =SUMIF(#REF!,$D$49,#REF!) -> #REF! | L49: =SUMIF(#REF!,$D$49,#REF!) -> #REF! | O49: =SUMIF(#REF!,$D$49,#REF!) -> #REF! | R49: =SUMIF(#REF!,$D$49,#REF!) -> #REF! | U49: =SUMIF(#REF!,$D$49,#REF!) -> #REF!
B50: 642500 | C50: Other Expenses | D50: 642002 | E50: Meals Non-Travel & Entertainment | H50: =SUM(I50,L50,O50,R50,U50) -> #REF! | I50: =SUMIF(#REF!,$D$50,#REF!) -> #REF! | L50: =SUMIF(#REF!,$D$50,#REF!) -> #REF! | O50: =SUMIF(#REF!,$D$50,#REF!) -> #REF! | R50: =SUMIF(#REF!,$D$50,#REF!) -> #REF! | U50: =SUMIF(#REF!,$D$50,#REF!) -> #REF!
B51: 642500 | C51: Other Expenses | D51: 642211 | E51: Insurance - General | H51: =SUM(I51,L51,O51,R51,U51) -> #REF! | I51: =SUMIF(#REF!,$D$51,#REF!) -> #REF! | L51: =SUMIF(#REF!,$D$51,#REF!) -> #REF! | O51: =SUMIF(#REF!,$D$51,#REF!) -> #REF! | R51: =SUMIF(#REF!,$D$51,#REF!) -> #REF! | U51: =SUMIF(#REF!,$D$51,#REF!) -> #REF!
B52: 642500 | C52: Other Expenses | D52: 643012 | E52: VAT Tax Paid | H52: =SUM(I52,L52,O52,R52,U52) -> #REF! | I52: =SUMIF(#REF!,$D$52,#REF!) -> #REF! | L52: =SUMIF(#REF!,$D$52,#REF!) -> #REF! | O52: =SUMIF(#REF!,$D$52,#REF!) -> #REF! | R52: =SUMIF(#REF!,$D$52,#REF!) -> #REF! | U52: =SUMIF(#REF!,$D$52,#REF!) -> #REF!
B53: 642500 | C53: Other Expenses | D53: 647001 | E53: Training | H53: =SUM(I53,L53,O53,R53,U53) -> #REF! | I53: =SUMIF(#REF!,$D$53,#REF!) -> #REF! | L53: =SUMIF(#REF!,$D$53,#REF!) -> #REF! | O53: =SUMIF(#REF!,$D$53,#REF!) -> #REF! | R53: =SUMIF(#REF!,$D$53,#REF!) -> #REF! | U53: =SUMIF(#REF!,$D$53,#REF!) -> #REF!
B54: 642500 | C54: Other Expenses | D54: 651851 | E54: Bank Service Charges | H54: =SUM(I54,L54,O54,R54,U54) -> #REF! | I54: =SUMIF(#REF!,$D$54,#REF!) -> #REF! | L54: =SUMIF(#REF!,$D$54,#REF!) -> #REF! | O54: =SUMIF(#REF!,$D$54,#REF!) -> #REF! | R54: =SUMIF(#REF!,$D$54,#REF!) -> #REF! | U54: =SUMIF(#REF!,$D$54,#REF!) -> #REF!
B55: 643000 | C55: Other Expenses Excluded | D55: 622502 | E55: Travel Insurance | H55: =SUM(I55,L55,O55,R55,U55) -> #REF! | I55: =SUMIF(#REF!,$D$55,#REF!) -> #REF! | L55: =SUMIF(#REF!,$D$55,#REF!) -> #REF! | O55: =SUMIF(#REF!,$D$55,#REF!) -> #REF! | R55: =SUMIF(#REF!,$D$55,#REF!) -> #REF! | U55: =SUMIF(#REF!,$D$55,#REF!) -> #REF!
B56: 643000 | C56: Other Expenses Excluded | D56: 651901 | E56: Foreign Currency Exchange Gain/Loss | H56: =SUM(I56,L56,O56,R56,U56) -> #REF! | I56: =SUMIF(#REF!,$D$56,#REF!) -> #REF! | L56: =SUMIF(#REF!,$D$56,#REF!) -> #REF! | O56: =SUMIF(#REF!,$D$56,#REF!) -> #REF! | R56: =SUMIF(#REF!,$D$56,#REF!) -> #REF! | U56: =SUMIF(#REF!,$D$56,#REF!) -> #REF!
B58: Total per year | D58: Total per year | H58: =SUM(I58,L58,O58,R58,U58) -> #REF! | I58: =SUM(I14:I57) -> #REF! | L58: =SUM(L14:L57) -> #REF! | O58: =SUM(O14:O57) -> #REF! | R58: =SUM(R14:R57) -> #REF! | U58: =SUM(U14:U57) -> #REF!
B60: Calculation check

Sheet IC by GL in LC
D1: Jhpiego Corporation
D2: =Assumptions!B5 -> DONOR: | E2: ='Incountry Costs by GL USD'!E2 -> USDOL
D3: =Assumptions!B6 -> Country: | E3: ='Incountry Costs by GL USD'!E3 -> Ecuador
D4: =Assumptions!B7 -> Program Name: | E4: ='Incountry Costs by GL USD'!E4 -> Project to Improve Adherence to International Labor Standards in the Agricultural Sector in Ecuador
D5: =Assumptions!B8 -> Grant Number: | E5: ='Incountry Costs by GL USD'!E5 -> FOA-ILAB-23-28
D6: =Assumptions!B9 -> Period of Performance: | E6: ='Incountry Costs by GL USD'!E6 -> 48 months | H6: ='Incountry Costs by GL USD'!H6 -> 0
D8: BUDGET SUMMARY BY G/L in USD
D10: IN-COUNTRY COSTS in LOCAL CURRENCY | I10: US$1= | L10: =er -> 0 | O10: local currency | V10: US$1=
E11: IN-COUNTRY ION: | I11: ='Incountry Costs by GL USD'!I11 -> 21 - 987654321 | L11: ='Incountry Costs by GL USD'!L11 -> 22 - 987654322 | O11: ='Incountry Costs by GL USD'!O11 -> 23 - 987654323 | R11: ='Incountry Costs by GL USD'!R11 -> 24 - 987654324 | U11: ='Incountry Costs by GL USD'!U11 -> 25 - 987654325
A13: SF424a | B13: Sponsored Class | C13: Description | D13: G/L | E13: Description | H13: Workplan Year Budget | I13: =#REF! -> #REF! | L13: =#REF! -> #REF! | O13: =#REF! -> #REF! | R13: =#REF! -> #REF! | U13: =#REF! -> #REF!
A15: Personnel | B15: 610000 | C15: Salaries & Wages | D15: 616112 | E15: In-country Salaries | H15: ='Incountry Costs by GL USD'!H15*$L$10 -> #REF! | I15: ='Incountry Costs by GL USD'!I15*$L$10 -> #REF! | L15: ='Incountry Costs by GL USD'!L15*$L$10 -> #REF! | O15: ='Incountry Costs by GL USD'!O15*$L$10 -> #REF! | R15: ='Incountry Costs by GL USD'!R15*$L$10 -> #REF! | U15: ='Incountry Costs by GL USD'!U15*$L$10 -> #REF!
A16: Fringe Benefits | B16: 620000 | C16: Fringe Benefits | D16: 620112 | E16: In-country Fringe | H16: ='Incountry Costs by GL USD'!H16*$L$10 -> #REF! | I16: ='Incountry Costs by GL USD'!I16*$L$10 -> #REF! | L16: ='Incountry Costs by GL USD'!L16*$L$10 -> #REF! | O16: ='Incountry Costs by GL USD'!O16*$L$10 -> #REF! | R16: ='Incountry Costs by GL USD'!R16*$L$10 -> #REF! | U16: ='Incountry Costs by GL USD'!U16*$L$10 -> #REF!
A17: Travel | B17: 652000 | C17: Travel Domestic | D17: 652201 | E17: Trainee Travel | H17: ='Incountry Costs by GL USD'!H17*$L$10 -> #REF! | I17: ='Incountry Costs by GL USD'!I17*$L$10 -> #REF! | L17: ='Incountry Costs by GL USD'!L17*$L$10 -> #REF! | O17: ='Incountry Costs by GL USD'!O17*$L$10 -> #REF! | R17: ='Incountry Costs by GL USD'!R17*$L$10 -> #REF! | U17: ='Incountry Costs by GL USD'!U17*$L$10 -> #REF!
B18: 652100 | C18: Travel Foreign | D18: 652101 | E18: Travel Foreign | H18: ='Incountry Costs by GL USD'!H18*$L$10 -> #REF! | I18: ='Incountry Costs by GL USD'!I18*$L$10 -> #REF! | L18: ='Incountry Costs by GL USD'!L18*$L$10 -> #REF! | O18: ='Incountry Costs by GL USD'!O18*$L$10 -> #REF! | R18: ='Incountry Costs by GL USD'!R18*$L$10 -> #REF! | U18: ='Incountry Costs by GL USD'!U18*$L$10 -> #REF!
D19: 652102 | E19: Travel Overseas Local | H19: ='Incountry Costs by GL USD'!H19*$L$10 -> #REF! | I19: ='Incountry Costs by GL USD'!I19*$L$10 -> #REF! | L19: ='Incountry Costs by GL USD'!L19*$L$10 -> #REF! | O19: ='Incountry Costs by GL USD'!O19*$L$10 -> #REF! | R19: ='Incountry Costs by GL USD'!R19*$L$10 -> #REF! | U19: ='Incountry Costs by GL USD'!U19*$L$10 -> #REF!
A20: Supplies | B20: 630000 | C20: Supplies & Materials | D20: 631001 | E20: Furniture | H20: ='Incountry Costs by GL USD'!H20*$L$10 -> #REF! | I20: ='Incountry Costs by GL USD'!I20*$L$10 -> #REF! | L20: ='Incountry Costs by GL USD'!L20*$L$10 -> #REF! | O20: ='Incountry Costs by GL USD'!O20*$L$10 -> #REF! | R20: ='Incountry Costs by GL USD'!R20*$L$10 -> #REF! | U20: ='Incountry Costs by GL USD'!U20*$L$10 -> #REF!
B21: 630000 | C21: Supplies & Materials | D21: 631003 | E21: Non-capital PC purchases | H21: ='Incountry Costs by GL USD'!H21*$L$10 -> #REF! | I21: ='Incountry Costs by GL USD'!I21*$L$10 -> #REF! | L21: ='Incountry Costs by GL USD'!L21*$L$10 -> #REF! | O21: ='Incountry Costs by GL USD'!O21*$L$10 -> #REF! | R21: ='Incountry Costs by GL USD'!R21*$L$10 -> #REF! | U21: ='Incountry Costs by GL USD'!U21*$L$10 -> #REF!
B22: 630000 | C22: Supplies & Materials | D22: 633032 | E22: Office Supplies | H22: ='Incountry Costs by GL USD'!H23*$L$10 -> #REF! | I22: ='Incountry Costs by GL USD'!I23*$L$10 -> #REF! | L22: ='Incountry Costs by GL USD'!L23*$L$10 -> #REF! | O22: ='Incountry Costs by GL USD'!O23*$L$10 -> #REF! | R22: ='Incountry Costs by GL USD'!R23*$L$10 -> #REF! | U22: ='Incountry Costs by GL USD'!U23*$L$10 -> #REF!
B23: 630000 | C23: Supplies & Materials | D23: 633037 | E23: Publications/Journals/Subscriptions | H23: ='Incountry Costs by GL USD'!H26*$L$10 -> #REF! | I23: ='Incountry Costs by GL USD'!I26*$L$10 -> #REF! | L23: ='Incountry Costs by GL USD'!L26*$L$10 -> #REF! | O23: ='Incountry Costs by GL USD'!O26*$L$10 -> #REF! | R23: ='Incountry Costs by GL USD'!R26*$L$10 -> #REF! | U23: ='Incountry Costs by GL USD'!U26*$L$10 -> #REF!
B24: 630000 | C24: Supplies & Materials | D24: 635001 | E24: Electricity | H24: ='Incountry Costs by GL USD'!H27*$L$10 -> #REF! | I24: ='Incountry Costs by GL USD'!I27*$L$10 -> #REF! | L24: ='Incountry Costs by GL USD'!L27*$L$10 -> #REF! | O24: ='Incountry Costs by GL USD'!O27*$L$10 -> #REF! | R24: ='Incountry Costs by GL USD'!R27*$L$10 -> #REF! | U24: ='Incountry Costs by GL USD'!U27*$L$10 -> #REF!
B25: 630000 | C25: Supplies & Materials | D25: 635010 | E25: Utilities: Water | H25: ='Incountry Costs by GL USD'!H28*$L$10 -> #REF! | I25: ='Incountry Costs by GL USD'!I28*$L$10 -> #REF! | L25: ='Incountry Costs by GL USD'!L28*$L$10 -> #REF! | O25: ='Incountry Costs by GL USD'!O28*$L$10 -> #REF! | R25: ='Incountry Costs by GL USD'!R28*$L$10 -> #REF! | U25: ='Incountry Costs by GL USD'!U28*$L$10 -> #REF!
B26: 630000 | C26: Supplies & Materials | D26: 640282 | E26: Delivery/Courier Service | H26: ='Incountry Costs by GL USD'!H29*$L$10 -> #REF! | I26: ='Incountry Costs by GL USD'!I29*$L$10 -> #REF! | L26: ='Incountry Costs by GL USD'!L29*$L$10 -> #REF! | O26: ='Incountry Costs by GL USD'!O29*$L$10 -> #REF! | R26: ='Incountry Costs by GL USD'!R29*$L$10 -> #REF! | U26: ='Incountry Costs by GL USD'!U29*$L$10 -> #REF!
A27: Equipment | B27: 653400 | C27: Equipment | D27: 631099 | E27: Equipment Purchases - SRM only | H27: ='Incountry Costs by GL USD'!H30*$L$10 -> #REF! | I27: ='Incountry Costs by GL USD'!I30*$L$10 -> #REF! | L27: ='Incountry Costs by GL USD'!L30*$L$10 -> #REF! | O27: ='Incountry Costs by GL USD'!O30*$L$10 -> #REF! | R27: ='Incountry Costs by GL USD'!R30*$L$10 -> #REF! | U27: ='Incountry Costs by GL USD'!U30*$L$10 -> #REF!
A28: Contractual | B28: 637000 | C28: Repairs & Maintenance | D28: 637001 | E28: Equipment Maintenance Agreements | H28: ='Incountry Costs by GL USD'!H31*$L$10 -> #REF! | I28: ='Incountry Costs by GL USD'!I31*$L$10 -> #REF! | L28: ='Incountry Costs by GL USD'!L31*$L$10 -> #REF! | O28: ='Incountry Costs by GL USD'!O31*$L$10 -> #REF! | R28: ='Incountry Costs by GL USD'!R31*$L$10 -> #REF! | U28: ='Incountry Costs by GL USD'!U31*$L$10 -> #REF!
B29: 640300 | C29: Contractual Services | D29: 640101 | E29: Rental Short-Term | H29: ='Incountry Costs by GL USD'!H32*$L$10 -> #REF! | I29: ='Incountry Costs by GL USD'!I32*$L$10 -> #REF! | L29: ='Incountry Costs by GL USD'!L32*$L$10 -> #REF! | O29: ='Incountry Costs by GL USD'!O32*$L$10 -> #REF! | R29: ='Incountry Costs by GL USD'!R32*$L$10 -> #REF! | U29: ='Incountry Costs by GL USD'!U32*$L$10 -> #REF!
B30: 640300 | C30: Contractual Services | D30: 640202 | E30: Equipment Lease Payment | H30: ='Incountry Costs by GL USD'!H33*$L$10 -> #REF! | I30: ='Incountry Costs by GL USD'!I33*$L$10 -> #REF! | L30: ='Incountry Costs by GL USD'!L33*$L$10 -> #REF! | O30: ='Incountry Costs by GL USD'!O33*$L$10 -> #REF! | R30: ='Incountry Costs by GL USD'!R33*$L$10 -> #REF! | U30: ='Incountry Costs by GL USD'!U33*$L$10 -> #REF!
B31: 640300 | C31: Contractual Services | D31: 640205 | E31: Motor Vehicle Leasing | H31: ='Incountry Costs by GL USD'!H34*$L$10 -> #REF! | I31: ='Incountry Costs by GL USD'!I34*$L$10 -> #REF! | L31: ='Incountry Costs by GL USD'!L34*$L$10 -> #REF! | O31: ='Incountry Costs by GL USD'!O34*$L$10 -> #REF! | R31: ='Incountry Costs by GL USD'!R34*$L$10 -> #REF! | U31: ='Incountry Costs by GL USD'!U34*$L$10 -> #REF!
B32: 640300 | C32: Contractual Services | D32: 640301 | E32: Contractual Services - General | H32: ='Incountry Costs by GL USD'!H35*$L$10 -> #REF! | I32: ='Incountry Costs by GL USD'!I35*$L$10 -> #REF! | L32: ='Incountry Costs by GL USD'!L35*$L$10 -> #REF! | O32: ='Incountry Costs by GL USD'!O35*$L$10 -> #REF! | R32: ='Incountry Costs by GL USD'!R35*$L$10 -> #REF! | U32: ='Incountry Costs by GL USD'!U35*$L$10 -> #REF!
B33: 640300 | C33: Contractual Services | D33: 640317 | E33: Contractual Services - Ground Maintenance | H33: ='Incountry Costs by GL USD'!H36*$L$10 -> #REF! | I33: ='Incountry Costs by GL USD'!I36*$L$10 -> #REF! | L33: ='Incountry Costs by GL USD'!L36*$L$10 -> #REF! | O33: ='Incountry Costs by GL USD'!O36*$L$10 -> #REF! | R33: ='Incountry Costs by GL USD'!R36*$L$10 -> #REF! | U33: ='Incountry Costs by GL USD'!U36*$L$10 -> #REF!
B34: 640300 | C34: Contractual Services | D34: 640318 | E34: Contractual Services - Cleaning | H34: ='Incountry Costs by GL USD'!H37*$L$10 -> #REF! | I34: ='Incountry Costs by GL USD'!I37*$L$10 -> #REF! | L34: ='Incountry Costs by GL USD'!L37*$L$10 -> #REF! | O34: ='Incountry Costs by GL USD'!O37*$L$10 -> #REF! | R34: ='Incountry Costs by GL USD'!R37*$L$10 -> #REF! | U34: ='Incountry Costs by GL USD'!U37*$L$10 -> #REF!
B35: 640300 | C35: Contractual Services | D35: 640321 | E35: Contractual Services - Off-Site Storage | H35: ='Incountry Costs by GL USD'!H38*$L$10 -> #REF! | I35: ='Incountry Costs by GL USD'!I38*$L$10 -> #REF! | L35: ='Incountry Costs by GL USD'!L38*$L$10 -> #REF! | O35: ='Incountry Costs by GL USD'!O38*$L$10 -> #REF! | R35: ='Incountry Costs by GL USD'!R38*$L$10 -> #REF! | U35: ='Incountry Costs by GL USD'!U38*$L$10 -> #REF!
B36: 640300 | C36: Contractual Services | D36: 640341 | E36: Contractual Services - Security Services | H36: ='Incountry Costs by GL USD'!H39*$L$10 -> #REF! | I36: ='Incountry Costs by GL USD'!I39*$L$10 -> #REF! | L36: ='Incountry Costs by GL USD'!L39*$L$10 -> #REF! | O36: ='Incountry Costs by GL USD'!O39*$L$10 -> #REF! | R36: ='Incountry Costs by GL USD'!R39*$L$10 -> #REF! | U36: ='Incountry Costs by GL USD'!U39*$L$10 -> #REF!
B37: 640300 | C37: Contractual Services | D37: 640351 | E37: Legal Fees | H37: ='Incountry Costs by GL USD'!H40*$L$10 -> #REF! | I37: ='Incountry Costs by GL USD'!I40*$L$10 -> #REF! | L37: ='Incountry Costs by GL USD'!L40*$L$10 -> #REF! | O37: ='Incountry Costs by GL USD'!O40*$L$10 -> #REF! | R37: ='Incountry Costs by GL USD'!R40*$L$10 -> #REF! | U37: ='Incountry Costs by GL USD'!U40*$L$10 -> #REF!
B38: 640300 | C38: Contractual Services | D38: 640361 | E38: Accounting/Auditing Expense | H38: ='Incountry Costs by GL USD'!H41*$L$10 -> #REF! | I38: ='Incountry Costs by GL USD'!I41*$L$10 -> #REF! | L38: ='Incountry Costs by GL USD'!L41*$L$10 -> #REF! | O38: ='Incountry Costs by GL USD'!O41*$L$10 -> #REF! | R38: ='Incountry Costs by GL USD'!R41*$L$10 -> #REF! | U38: ='Incountry Costs by GL USD'!U41*$L$10 -> #REF!
B39: 640300 | C39: Contractual Services | D39: 640381 | E39: Professional Services - External | H39: ='Incountry Costs by GL USD'!H42*$L$10 -> #REF! | I39: ='Incountry Costs by GL USD'!I42*$L$10 -> #REF! | L39: ='Incountry Costs by GL USD'!L42*$L$10 -> #REF! | O39: ='Incountry Costs by GL USD'!O42*$L$10 -> #REF! | R39: ='Incountry Costs by GL USD'!R42*$L$10 -> #REF! | U39: ='Incountry Costs by GL USD'!U42*$L$10 -> #REF!
B40: 640300 | C40: Contractual Services | D40: 640455 | E40: Software Maintenance Agreeement | H40: ='Incountry Costs by GL USD'!H43*$L$10 -> #REF! | I40: ='Incountry Costs by GL USD'!I43*$L$10 -> #REF! | L40: ='Incountry Costs by GL USD'!L43*$L$10 -> #REF! | O40: ='Incountry Costs by GL USD'!O43*$L$10 -> #REF! | R40: ='Incountry Costs by GL USD'!R43*$L$10 -> #REF! | U40: ='Incountry Costs by GL USD'!U43*$L$10 -> #REF!
B41: 640300 | C41: Contractual Services | D41: 640501 | E41: Consultant Fees | H41: ='Incountry Costs by GL USD'!H45*$L$10 -> #REF! | I41: ='Incountry Costs by GL USD'!I45*$L$10 -> #REF! | L41: ='Incountry Costs by GL USD'!L45*$L$10 -> #REF! | O41: ='Incountry Costs by GL USD'!O45*$L$10 -> #REF! | R41: ='Incountry Costs by GL USD'!R45*$L$10 -> #REF! | U41: ='Incountry Costs by GL USD'!U45*$L$10 -> #REF!
B42: 640300 | C42: Contractual Services | D42: 642501 | E42: Printing | H42: ='Incountry Costs by GL USD'!H44*$L$10 -> #REF! | I42: ='Incountry Costs by GL USD'!I44*$L$10 -> #REF! | L42: ='Incountry Costs by GL USD'!L44*$L$10 -> #REF! | O42: ='Incountry Costs by GL USD'!O44*$L$10 -> #REF! | R42: ='Incountry Costs by GL USD'!R44*$L$10 -> #REF! | U42: ='Incountry Costs by GL USD'!U44*$L$10 -> #REF!
B43: 642400 | C43: Subaward | D43: 642405 | E43: Subaward General | H43: ='Incountry Costs by GL USD'!H46*$L$10 -> #REF! | I43: ='Incountry Costs by GL USD'!I46*$L$10 -> #REF! | L43: ='Incountry Costs by GL USD'!L46*$L$10 -> #REF! | O43: ='Incountry Costs by GL USD'!O46*$L$10 -> #REF! | R43: ='Incountry Costs by GL USD'!R46*$L$10 -> #REF! | U43: ='Incountry Costs by GL USD'!U46*$L$10 -> #REF!
A44: Other | B44: 640102 | C44: Leased Facilities External | D44: 640102 | E44: Leased Facilities External | H44: ='Incountry Costs by GL USD'!H47*$L$10 -> #REF! | I44: ='Incountry Costs by GL USD'!I47*$L$10 -> #REF! | L44: ='Incountry Costs by GL USD'!L47*$L$10 -> #REF! | O44: ='Incountry Costs by GL USD'!O47*$L$10 -> #REF! | R44: ='Incountry Costs by GL USD'!R47*$L$10 -> #REF! | U44: ='Incountry Costs by GL USD'!U47*$L$10 -> #REF!
B45: 641400 | C45: Telecommunications | D45: 641402 | E45: Telephone Long Distance | H45: ='Incountry Costs by GL USD'!H48*$L$10 -> #REF! | I45: ='Incountry Costs by GL USD'!I48*$L$10 -> #REF! | L45: ='Incountry Costs by GL USD'!L48*$L$10 -> #REF! | O45: ='Incountry Costs by GL USD'!O48*$L$10 -> #REF! | R45: ='Incountry Costs by GL USD'!R48*$L$10 -> #REF! | U45: ='Incountry Costs by GL USD'!U48*$L$10 -> #REF!
B46: 642500 | C46: Other Expenses | D46: 640403 | E46: Memberships/Dues | H46: ='Incountry Costs by GL USD'!H49*$L$10 -> #REF! | I46: ='Incountry Costs by GL USD'!I49*$L$10 -> #REF! | L46: ='Incountry Costs by GL USD'!L49*$L$10 -> #REF! | O46: ='Incountry Costs by GL USD'!O49*$L$10 -> #REF! | R46: ='Incountry Costs by GL USD'!R49*$L$10 -> #REF! | U46: ='Incountry Costs by GL USD'!U49*$L$10 -> #REF!
B47: 642500 | C47: Other Expenses | D47: 642002 | E47: Meals Non-Travel & Entertainment | H47: ='Incountry Costs by GL USD'!H50*$L$10 -> #REF! | I47: ='Incountry Costs by GL USD'!I50*$L$10 -> #REF! | L47: ='Incountry Costs by GL USD'!L50*$L$10 -> #REF! | O47: ='Incountry Costs by GL USD'!O50*$L$10 -> #REF! | R47: ='Incountry Costs by GL USD'!R50*$L$10 -> #REF! | U47: ='Incountry Costs by GL USD'!U50*$L$10 -> #REF!
B48: 642500 | C48: Other Expenses | D48: 642211 | E48: Insurance - General | H48: ='Incountry Costs by GL USD'!H51*$L$10 -> #REF! | I48: ='Incountry Costs by GL USD'!I51*$L$10 -> #REF! | L48: ='Incountry Costs by GL USD'!L51*$L$10 -> #REF! | O48: ='Incountry Costs by GL USD'!O51*$L$10 -> #REF! | R48: ='Incountry Costs by GL USD'!R51*$L$10 -> #REF! | U48: ='Incountry Costs by GL USD'!U51*$L$10 -> #REF!
B49: 642500 | C49: Other Expenses | D49: 643012 | E49: VAT Tax Paid | H49: ='Incountry Costs by GL USD'!H52*$L$10 -> #REF! | I49: ='Incountry Costs by GL USD'!I52*$L$10 -> #REF! | L49: ='Incountry Costs by GL USD'!L52*$L$10 -> #REF! | O49: ='Incountry Costs by GL USD'!O52*$L$10 -> #REF! | R49: ='Incountry Costs by GL USD'!R52*$L$10 -> #REF! | U49: ='Incountry Costs by GL USD'!U52*$L$10 -> #REF!
B50: 642500 | C50: Other Expenses | D50: 647001 | E50: Training | H50: ='Incountry Costs by GL USD'!H53*$L$10 -> #REF! | I50: ='Incountry Costs by GL USD'!I53*$L$10 -> #REF! | L50: ='Incountry Costs by GL USD'!L53*$L$10 -> #REF! | O50: ='Incountry Costs by GL USD'!O53*$L$10 -> #REF! | R50: ='Incountry Costs by GL USD'!R53*$L$10 -> #REF! | U50: ='Incountry Costs by GL USD'!U53*$L$10 -> #REF!
B51: 642500 | C51: Other Expenses | D51: 651851 | E51: Bank Service Charges | H51: ='Incountry Costs by GL USD'!H54*$L$10 -> #REF! | I51: ='Incountry Costs by GL USD'!I54*$L$10 -> #REF! | L51: ='Incountry Costs by GL USD'!L54*$L$10 -> #REF! | O51: ='Incountry Costs by GL USD'!O54*$L$10 -> #REF! | R51: ='Incountry Costs by GL USD'!R54*$L$10 -> #REF! | U51: ='Incountry Costs by GL USD'!U54*$L$10 -> #REF!
B52: 643000 | C52: Other Expenses Excluded | D52: 622502 | E52: Travel Insurance | H52: ='Incountry Costs by GL USD'!H55*$L$10 -> #REF! | I52: ='Incountry Costs by GL USD'!I55*$L$10 -> #REF! | L52: ='Incountry Costs by GL USD'!L55*$L$10 -> #REF! | O52: ='Incountry Costs by GL USD'!O55*$L$10 -> #REF! | R52: ='Incountry Costs by GL USD'!R55*$L$10 -> #REF! | U52: ='Incountry Costs by GL USD'!U55*$L$10 -> #REF!
B53: 643000 | C53: Other Expenses Excluded | D53: 651901 | E53: Foreign Currency Exchange Gain/Loss | H53: ='Incountry Costs by GL USD'!H56*$L$10 -> #REF! | I53: ='Incountry Costs by GL USD'!I56*$L$10 -> #REF! | L53: ='Incountry Costs by GL USD'!L56*$L$10 -> #REF! | O53: ='Incountry Costs by GL USD'!O56*$L$10 -> #REF! | R53: ='Incountry Costs by GL USD'!R56*$L$10 -> #REF! | U53: ='Incountry Costs by GL USD'!U56*$L$10 -> #REF!
B55: Total per year | D55: Total per year | H55: =SUM(I55,L55,O55,R55,U55,#REF!,#REF!,#REF!,#REF!,#REF!) -> #REF! | I55: =SUM(I14:I54) -> #REF! | L55: =SUM(L14:L54) -> #REF! | O55: =SUM(O14:O54) -> #REF! | R55: =SUM(R14:R54) -> #REF! | U55: =SUM(U14:U54) -> #REF!
B57: Calculation check | I57: =#REF! -> #REF! | L57: =#REF! -> #REF! | O57: =#REF! -> #REF! | R57: =#REF! -> #REF! | U57: =#REF! -> #REF!

Sheet Office Budget
A1: =Assumptions!$B$4 -> Partners of America
A2: =CONCATENATE(Assumptions!$B5," ",Assumptions!$C5) -> DONOR: USDOL
A3: =CONCATENATE(Assumptions!$B6," ",Assumptions!$C6) -> Country: Ecuador
A4: =CONCATENATE(Assumptions!$B7," ",Assumptions!$C7) -> Program Name: Project to Improve Adherence to International Labor Standards in the Agricultural Sector in Ecuador | G4: QUESTION: should annual cost be included in detailed budget and percent applied there?
A5: =CONCATENATE(Assumptions!$B8," ",Assumptions!$C8) -> Grant Number: FOA-ILAB-23-28 | G5: OR should allocation be shown at 100%?
G6: PORTFOLIO? OR DIRECT LABOR?
A7: COUNTRY OFFICE BUDGET
A10: SF424a | B10: Sponsored Class | C10: GL | D10: Description | E10: Annual Cost | G10: Annual Cost | I10: Office Costs Allocated to this Program | K10: Monthly Cost
A11: Categories | E11: Local Currency | G11: USD | I11: % | K11: USD
E13: Exchange rate | F13: US$1= | G13: 1 | I13: Percent: | J13: 1 | K13: # of months | L13: 12
A16: Personnel | B16: Salaries & Wages | C16: 616112 | D16: In-Country Salaries | F16: /year | G16: =E16/$G$13 -> 0 | H16: /year | K16: =G16/$L$13 -> 0 | L16: /month
A17: Fringe Benefits | B17: Fringe Benefits | C17: 620112 | D17: In-Country Fringe | F17: /year | G17: =E17/$G$13 -> 0 | H17: /year | K17: =G17/$L$13 -> 0 | L17: /month
A18: Travel | B18: Travel Foreign (Overseas Local) | C18: 652102 | D18: Taxi Services | F18: /year | G18: =E18/$G$13 -> 0 | H18: /year | K18: =G18/$L$13 -> 0 | L18: /month
A19: Supplies | B19: Supplies & Materials | C19: 635001 | D19: Utilities: Electricity | F19: /year | G19: =E19/$G$13 -> 0 | H19: /year | K19: =G19/$L$13 -> 0 | L19: /month
B20: Supplies & Materials | C20: 635010 | D20: Utilities: Water | F20: /year | G20: =E20/$G$13 -> 0 | H20: /year | K20: =G20/$L$13 -> 0 | L20: /month
B21: Supplies & Materials | C21: 633032 | D21: Kitchen Supplies | F21: /year | G21: =E21/$G$13 -> 0 | H21: /year | K21: =G21/$L$13 -> 0 | L21: /month
B22: Supplies & Materials | C22: 640282 | D22: Courier Services | F22: /year | G22: =E22/$G$13 -> 0 | H22: /year | K22: =G22/$L$13 -> 0 | L22: /month
A23: Equipment | B23: Equipment | C23: 653400 | D23: Equipment Purchases - SRM only | F23: /year | G23: =E23/$G$13 -> 0 | H23: /year | K23: =G23/$L$13 -> 0 | L23: /month
A24: Contractual | B24: Contractual Services | C24: 640341 | D24: Contracts: Security | F24: /year | G24: =E24/$G$13 -> 0 | H24: /year | K24: =G24/$L$13 -> 0 | L24: /month
B25: Contractual Services | C25: 640318 | D25: Contracts: Office Cleaning | F25: /year | G25: =E25/$G$13 -> 0 | H25: /year | K25: =G25/$L$13 -> 0 | L25: /month
B26: Contractual Services | C26: 640361 | D26: Contracts: Annual Audit fees | F26: /year | G26: =E26/$G$13 -> 0 | H26: /year | K26: =G26/$L$13 -> 0 | L26: /month
B27: Contractual Services | C27: 640351 | D27: Contracts: Legal Services | F27: /year | G27: =E27/$G$13 -> 0 | H27: /year | K27: =G27/$L$13 -> 0 | L27: /month
B28: Contractual Services | C28: 640205 | D28: Contracts: Vehicle Rental | F28: /year | G28: =E28/$G$13 -> 0 | H28: /year | K28: =G28/$L$13 -> 0 | L28: /month
B29: Contractual Services | C29: 642501 | D29: Office stationery (printing) | F29: /year | G29: =E29/$G$13 -> 0 | H29: /year | K29: =G29/$L$13 -> 0 | L29: /month
B30: Contractual Services | C30: 642501 | D30: Advertising | F30: /year | G30: =E30/$G$13 -> 0 | H30: /year | K30: =G30/$L$13 -> 0 | L30: /month
B31: Contractual Services | C31: 640318 | D31: Office waste removal | F31: /year | G31: =E31/$G$13 -> 0 | H31: /year | K31: =G31/$L$13 -> 0 | L31: /month
B32: Contractual Services | C32: 640301 | D32: ISTS services | F32: /year | G32: =E32/$G$13 -> 0 | H32: /year | K32: =G32/$L$13 -> 0 | L32: /month
B33: Contractual Services | C33: 640301 | D33: Vehicle maintenance | F33: /year | G33: =E33/$G$13 -> 0 | H33: /year | K33: =G33/$L$13 -> 0 | L33: /month
B34: Contractual Services | C34: 640321 | D34: Warehousing/Storage Services | F34: /year | G34: =E34/$G$13 -> 0 | H34: /year | K34: =G34/$L$13 -> 0 | L34: /month
B35: Contractual Services | C35: 642501 | D35: Advertising for recruitment | F35: /year | G35: =E35/$G$13 -> 0 | H35: /year | K35: =G35/$L$13 -> 0 | L35: /month
B36: Contractual Services | C36: 640301 | D36: Vehicle Tracking System (office pool vehicle) | F36: /year | G36: =E36/$G$13 -> 0 | H36: /year | K36: =G36/$L$13 -> 0 | L36: /month
B37: Contractual Services | C37: 640455 | D37: Lisences and renewals | F37: /year | G37: =E37/$G$13 -> 0 | H37: /year | K37: =G37/$L$13 -> 0 | L37: /month
A38: Other | B38: Leased Facilities External | C38: 640102 | D38: Office rent | F38: /year | G38: =E38/$G$13 -> 0 | H38: /year | K38: =G38/$L$13 -> 0 | L38: /month
B39: Leased Facilities External | C39: 640102 | D39: Office Leasehold improvements | F39: /year | G39: =E39/$G$13 -> 0 | H39: /year | K39: =G39/$L$13 -> 0 | L39: /month
B40: Other Expenses | C40: 651851 | D40: Bank charges | F40: /year | G40: =E40/$G$13 -> 0 | H40: /year | K40: =G40/$L$13 -> 0 | L40: /month
B41: Other Expenses | C41: 642211 | D41: Vehicle insurance | F41: /year | G41: =E41/$G$13 -> 0 | H41: /year | K41: =G41/$L$13 -> 0 | L41: /month
B42: Other Expenses | C42: 642002 | D42: Refreshments for office business meetings | F42: /year | G42: =E42/$G$13 -> 0 | H42: /year | K42: =G42/$L$13 -> 0 | L42: /month
B43: Other Expenses | C43: 640403 | D43: NGO Annual fees | F43: /year | G43: =E43/$G$13 -> 0 | H43: /year | K43: =G43/$L$13 -> 0 | L43: /month
B44: Other Expenses | C44: 642002 | D44: staff Development events | F44: /year | G44: =E44/$G$13 -> 0 | H44: /year | K44: =G44/$L$13 -> 0 | L44: /month
B45: Telecommunications | C45: 641402 | D45: Office Internet | F45: /year | G45: =E45/$G$13 -> 0 | H45: /year | K45: =G45/$L$13 -> 0 | L45: /month
B46: Telecommunications | C46: 641402 | D46: Communications | F46: /year | G46: =E46/$G$13 -> 0 | H46: /year | K46: =G46/$L$13 -> 0 | L46: /month
B47: Telecommunications | C47: 641402 | D47: Staff Airtime | F47: /year | G47: =E47/$G$13 -> 0 | H47: /year | K47: =G47/$L$13 -> 0 | L47: /month
D48: add other costs as necessary | F48: /year | G48: =E48/$G$13 -> 0 | H48: /year | K48: =G48/$L$13 -> 0 | L48: /month
D49: add other costs as necessary | F49: /year | G49: =E49/$G$13 -> 0 | H49: /year | K49: =G49/$L$13 -> 0 | L49: /month
D50: Total | E50: =SUM(E16:E49) -> 0 | F50: /year | G50: =SUM(G16:G49) -> 0 | H50: /year | K50: =SUM(K16:K49) -> 0 | L50: month

Sheet  Activities Detail
D1: Partners of America
D2: DONOR: | E2: =Assumptions!C5 -> USDOL
D3: Country: | E3: =Assumptions!C6 -> Ecuador
D4: Program Name: | E4: =Assumptions!C7 -> Project to Improve Adherence to International Labor Standards in the Agricultural Sector in Ecuador
D5: Grant Number: | E5: =Assumptions!C8 -> FOA-ILAB-23-28
D6: Period of Performance: | E6: =Assumptions!C9 -> 48 months
A7: Entity: | B7: P
A8: Program-Dept.: | B8: 20200
A9: Funder-Grant: | B9: DOL427
A10: Activity Code | B10: Account Code | C10: Country Code | D10: ACTIVITY DESCRIPTION | E10: Units | G10: Cost | H10: Base | I10: # of days | K10: ='Line-Item Budget'!J10 -> Year 1 | N10: ='Line-Item Budget'!L10 -> Year 2 | Q10: ='Line-Item Budget'!N10 -> Year 3 | T10: ='Line-Item Budget'!P10 -> Year 4 | W10: Total
K11: # Activities | M11: Amount | N11: # Activities | P11: Amount | Q11: # Activities | S11: Amount | T11: # Activities | V11: Amount
D12: ODC Escalation Factor | E12: 0.04 | M12: 1 | P12: =$M$12*SUM(1+$E$12) -> 1.04 | S12: =$P$12*SUM(1+$E$12) -> 1.0816 | V12: =$S$12*SUM(1+$E$12) -> 1.124864
D13: MEETINGS
A14: Activity Code | B14: Account Code | C14: Country Code
D15: Activity 1.1. Assess labor law enforcement institutions, processes, and services: challenges and opportunities for action to address child labor and forced labor | I15: 1 | K15: =3*6 -> 18 | M15: =SUM(L17:L21) -> 5400 | N15: 0 | P15: =SUM(O17:O21) -> 0 | Q15: 0 | S15: =SUM(R17:R21) -> 0 | T15: 0 | V15: =SUM(U17:U21) -> 0 | W15: =SUM(M15,P15,S15,V15) -> 5400
D16: Project activities costs
D17: Local transportation (training site) | F17: Individual | G17: =parttransp -> 4 | H17: /day | I17: =IF(E17=0,0,I15) -> 0 | J17: =E17*G17*I17 -> 0 | L17: =$J17*K15*M$12 -> 0 | O17: =$J17*N15*P$12 -> 0 | R17: =$J17*Q15*S$12 -> 0 | U17: =$J17*T15*V$12 -> 0 | W17: =U17+R17+O17+L17 -> 0
D18: Lunch/coffee breaks | F18: Individual | G18: =coffee+lunch -> 16 | H18: /day | I18: =IF(E18=0,0,I15) -> 0 | J18: =E18*G18*I18 -> 0 | L18: =$J18*K15*M$12 -> 0 | O18: =$J18*N15*P$12 -> 0 | R18: =$J18*Q15*S$12 -> 0 | U18: =$J18*T15*V$12 -> 0 | W18: =U18+R18+O18+L18 -> 0
D19: Printing (Photocopies) | F19: activity | G19: =print -> 50 | H19: =F19 -> activity | I19: =IF(E19=0,0,1) -> 0 | J19: =E19*G19*I19 -> 0 | L19: =$J19*K15*M$12 -> 0 | O19: =$J19*N15*P$12 -> 0 | R19: =$J19*Q15*S$12 -> 0 | U19: =$J19*T15*V$12 -> 0 | W19: =U19+R19+O19+L19 -> 0
A20: EC.1.1.A | B20: 81000 | C20: ECU | D20: Local Consultant (Assessments) | E20: 1 | F20: Individual | G20: =localcons -> 300 | H20: /day | I20: 1 | J20: =E20*G20*I20 -> 300 | L20: =$J20*K15*M$12 -> 5400 | O20: =$J20*N15*P$12 -> 0 | R20: =$J20*Q15*S$12 -> 0 | U20: =$J20*T15*V$12 -> 0 | W20: =U20+R20+O20+L20 -> 5400
W21: =U21+R21+O21+L21 -> 0
D22: ACTIVITY TOTAL | H22: =SUM(J16:J21) -> 300
D24: Activity 1.2. Strengthen intersectoral coordination by re-invigorating referral mechanisms and strengthening Consejos and Juntas: | I24: 1 | K24: 12 | M24: =SUM(L26:L31) -> 4800 | N24: 12 | P24: =SUM(O26:O31) -> 3744 | Q24: 0 | S24: =SUM(R26:R31) -> 0 | T24: 0 | V24: =SUM(U26:U31) -> 0 | W24: =SUM(M24,P24,S24,V24,) -> 8544
D25: Workshop activities costs
D26: Local transportation (training site) | F26: Individual | G26: =parttransp -> 4 | H26: /day | I26: =IF(E26=0,0,I24) -> 0 | J26: =E26*G26*I26 -> 0 | L26: =$J26*K24*M$12 -> 0 | O26: =$J26*N24*P$12 -> 0 | R26: =$J26*Q24*S$12 -> 0 | U26: =$J26*T24*V$12 -> 0 | W26: =U26+R26+O26+L26 -> 0
D27: Lunch/coffee breaks | F27: Individual | G27: =coffee+lunch -> 16 | H27: /day | I27: =IF(E27=0,0,I24) -> 0 | J27: =E27*G27*I27 -> 0 | L27: =$J27*K24*M$12 -> 0 | O27: =$J27*N24*P$12 -> 0 | R27: =$J27*Q24*S$12 -> 0 | U27: =$J27*T24*V$12 -> 0 | W27: =U27+R27+O27+L27 -> 0
D28: Materials & Supplies | F28: workshop | G28: 25 | H28: =F28 -> workshop | I28: =IF(E28=0,0,1) -> 0 | J28: =E28*G28*I28 -> 0 | L28: =$J28*K24*M$12 -> 0 | O28: =$J28*N24*P$12 -> 0 | R28: =$J28*Q24*S$12 -> 0 | U28: =$J28*T24*V$12 -> 0 | W28: =U28+R28+O28+L28 -> 0
A29: EC.1.2.A | B29: 85300 | C29: ECU | D29: Printing (Guide) | E29: 6 | F29: canton | G29: 200 | H29: =F29 -> canton | I29: =IF(E29=0,0,1) -> 1 | J29: =E29*G29*I29 -> 1200 | L29: =$J29*M$12 -> 1200 | R29: =$J29*Q24*S$12 -> 0 | U29: =$J29*T24*V$12 -> 0 | W29: =U29+R29+O29+L29 -> 1200
A30: EC.1.2.B | B30: 81000 | C30: ECU | D30: Local Consultant (Guide Development) | E30: 1 | F30: Individual | G30: =localcons -> 300 | H30: /day | I30: 1 | J30: =E30*G30*I30 -> 300 | L30: =$J30*K24*M$12 -> 3600 | O30: =$J30*N24*P$12 -> 3744 | R30: =$J30*Q24*S$12 -> 0 | U30: =$J30*T24*V$12 -> 0 | W30: =U30+R30+O30+L30 -> 7344
D32: ACTIVITY TOTAL | H32: =SUM(J25:J31) -> 1500
D34: Activity 1.3. Develop government capacity building strategy applying assessment results | I34: 1 | M34: =SUM(L36:L39) -> 0 | N34: =3*6 -> 18 | P34: =SUM(O36:O39) -> 0 | Q34: =3*6 -> 18 | S34: =SUM(R36:R39) -> 0 | T34: =2*6 -> 12 | V34: =SUM(U36:U39) -> 0 | W34: =SUM(M34,P34,S34,V34,) -> 0
D35: Project activities costs | W35: =U35+R35+O35+L35 -> 0
D36: Local transportation (training site) | F36: Individual | G36: =parttransp -> 4 | H36: /day | I36: =IF(E36=0,0,I34) -> 0 | J36: =E36*G36*I36 -> 0 | L36: =$J36*K34*M$12 -> 0 | O36: =$J36*N34*P$12 -> 0 | R36: =$J36*Q34*S$12 -> 0 | U36: =$J36*T34*V$12 -> 0 | W36: =U36+R36+O36+L36 -> 0
D37: Lunch/coffee breaks | F37: Individual | G37: =coffee+lunch -> 16 | H37: /day | I37: =IF(E37=0,0,I34) -> 0 | J37: =E37*G37*I37 -> 0 | L37: =$J37*K34*M$12 -> 0 | O37: =$J37*N34*P$12 -> 0 | R37: =$J37*Q34*S$12 -> 0 | U37: =$J37*T34*V$12 -> 0 | W37: =U37+R37+O37+L37 -> 0
D38: Printing (Photocopies) | F38: activity | G38: 15 | H38: =F38 -> activity | I38: =IF(E38=0,0,1) -> 0 | J38: =E38*G38*I38 -> 0 | L38: =$J38*K34*M$12 -> 0 | O38: =$J38*N34*P$12 -> 0 | R38: =$J38*Q34*S$12 -> 0 | U38: =$J38*T34*V$12 -> 0 | W38: =U38+R38+O38+L38 -> 0
D40: ACTIVITY TOTAL | H40: =SUM(J35:J39) -> 0
D42: Activity 1.4. Develop, deliver, and institutionalize tailored capacity building for government officials: | I42: 1 | M42: =SUM(L44:L46) -> 0 | N42: 6 | P42: =SUM(O44:O46) -> 2184 | Q42: 6 | S42: =SUM(R44:R46) -> 2271.36 | T42: 3 | V42: =SUM(U44:U46) -> 1181.1072 | W42: =SUM(M42,P42,S42,V42,) -> 5636.4672
D43: Project activities costs
A44: EC.1.4.A | B44: 86000 | C44: ECU | D44: Local transportation (El Oro) | E44: 15 | F44: Individual | G44: =parttransp -> 4 | H44: /day | I44: =IF(E44=0,0,I42) -> 1 | J44: =E44*G44*I44 -> 60 | L44: =$J44*K42*M$12 -> 0 | O44: =$J44*N42*P$12 -> 374.4 | R44: =$J44*Q42*S$12 -> 389.376 | U44: =$J44*T42*V$12 -> 202.47552 | W44: =U44+R44+O44+L44 -> 966.25152
A45: EC.1.4.B | B45: 87000 | C45: ECU | D45: Lunch/coffee breaks | E45: 15 | F45: Individual | G45: =coffee+lunch -> 16 | H45: /day | I45: =IF(E45=0,0,I42) -> 1 | J45: =E45*G45*I45 -> 240 | L45: =$J45*K42*M$12 -> 0 | O45: =$J45*N42*P$12 -> 1497.6 | R45: =$J45*Q42*S$12 -> 1557.504 | U45: =$J45*T42*V$12 -> 809.90208 | W45: =U45+R45+O45+L45 -> 3865.0061
A46: EC.1.4.C | B46: 85300 | C46: ECU | D46: Printing (Photocopies) | E46: 1 | F46: activity | G46: =print -> 50 | H46: =F46 -> activity | I46: =IF(E46=0,0,1) -> 1 | J46: =E46*G46*I46 -> 50 | L46: =$J46*K42*M$12 -> 0 | O46: =$J46*N42*P$12 -> 312 | R46: =$J46*Q42*S$12 -> 324.48 | U46: =$J46*T42*V$12 -> 168.7296 | W46: =U46+R46+O46+L46 -> 805.2096
D47: Staff from outside training site
D48: Transportation (El Oro) | E48: 2 | F48: Individual | G48: =localairfare -> 175 | H48: /trip | I48: =IF(E48=0,0,1) -> 1 | J48: =E48*G48*I48 -> 350 | L48: =$J48*K$42*M$12 -> 0 | O48: =$J48*N$42*P$12 -> 2184 | R48: =$J48*Q$42*S$12 -> 2271.36 | U48: =$J48*T$42*V$12 -> 1181.1072
D49: Ground transportation (El Oro) | E49: 2 | F49: Individual | G49: =partground -> 9 | H49: /day | I49: =IF(E49=0,0,1) -> 1 | J49: =E49*G49*I49 -> 18 | L49: =$J49*K$42*M$12 -> 0 | O49: =$J49*N$42*P$12 -> 112.32 | R49: =$J49*Q$42*S$12 -> 116.8128 | U49: =$J49*T$42*V$12 -> 60.742656
D50: Lodging | F50: Individual | G50: =partlodg -> 25 | H50: /day | I50: =IF(E50=0,0,1) -> 0 | J50: =E50*G50*I50 -> 0 | L50: =$J50*K$42*M$12 -> 0 | O50: =$J50*N$42*P$12 -> 0 | R50: =$J50*Q$42*S$12 -> 0 | U50: =$J50*T$42*V$12 -> 0 | W50: =U50+R50+O50+L50 -> 0
D51: M&IE | F51: Individual | G51: =partmeals -> 47 | H51: /day | I51: =IF(E51=0,0,1) -> 0 | J51: =E51*G51*I51 -> 0 | L51: =$J51*K$42*M$12 -> 0 | O51: =$J51*N$42*P$12 -> 0 | R51: =$J51*Q$42*S$12 -> 0 | U51: =$J51*T$42*V$12 -> 0 | W51: =U51+R51+O51+L51 -> 0
W52: =U52+R52+O52+L52 -> 0
D53: ACTIVITY TOTAL | H53: =SUM(J43:J52) -> 718
D55: Activity 1.5. Strengthen digital child labor tracking and public reporting/accountability: | I55: 1 | K55: 1 | M55: =SUM(L57) -> 75000 | N55: 1 | P55: =SUM(O57) -> 0 | Q55: 1 | S55: =SUM(R57) -> 0 | T55: 1 | V55: =SUM(U57) -> 0 | W55: =SUM(M55,P55,S55,V55,) -> 75000
D56: Project activities costs | W56: =U56+R56+O56+L56 -> 0
A57: EC.1.5.A | B57: 81010 | C57: ECU | D57: Software Development | E57: 1 | F57: each | G57: 75000 | H57: /software | I57: 0 | J57: =E57*G57*I57 -> 0 | L57: =G57 -> 75000 | O57: =$J57*N55*P$12 -> 0 | R57: =$J57*Q55*S$12 -> 0 | U57: =$J57*T55*V$12 -> 0 | W57: =U57+R57+O57+L57 -> 75000
W58: =U58+R58+O58+L58 -> 0
D59: Staff from outside site | W59: 0
D60: Transportation (El Oro) | E60: 2 | F60: Individual | G60: =localairfare -> 175 | H60: /trip | I60: =IF(E60=0,0,1) -> 1 | J60: =E60*G60*I60 -> 350 | L60: =$J60*$K$55*M$12 -> 350 | O60: =$J60*$N$55*P$12 -> 364 | R60: =$J60*$Q$55*S$12 -> 378.56 | U60: =$J60*$T$55*V$12 -> 393.7024 | W60: 0
D61: Ground transportation (El Oro) | E61: 2 | F61: Individual | G61: =partground -> 9 | H61: /day | I61: =IF(E61=0,0,1) -> 1 | J61: =E61*G61*I61 -> 18 | L61: =$J61*$K$55*M$12 -> 18 | O61: =$J61*$N$55*P$12 -> 18.72 | R61: =$J61*$Q$55*S$12 -> 19.4688 | U61: =$J61*$T$55*V$12 -> 20.247552 | W61: 0
D62: Lodging | E62: =E60+E61 -> 4 | F62: Individual | G62: =partlodg -> 25 | H62: /day | I62: =IF(E62=0,0,1) -> 1 | J62: =E62*G62*I62 -> 100 | L62: =$J62*$K$55*M$12 -> 100 | O62: =$J62*$N$55*P$12 -> 104 | R62: =$J62*$Q$55*S$12 -> 108.16 | U62: =$J62*$T$55*V$12 -> 112.4864 | W62: 0
D63: M&IE | E63: =E62 -> 4 | F63: Individual | G63: =partmeals -> 47 | H63: /day | I63: =IF(E63=0,0,1) -> 1 | J63: =E63*G63*I63 -> 188 | L63: =$J63*$K$55*M$12 -> 188 | O63: =$J63*$N$55*P$12 -> 195.52 | R63: =$J63*$Q$55*S$12 -> 203.3408 | U63: =$J63*$T$55*V$12 -> 211.47443 | W63: 0
W64: 0
D65: =D59 -> Staff from outside site | W65: 0
D66: Transportation (Cotopaxi) | E66: 2 | F66: Individual | G66: =partground -> 9 | H66: /trip | I66: =IF(E66=0,0,1) -> 1 | J66: =E66*G66*I66 -> 18 | L66: =$J66*K$55*M$12 -> 18 | O66: =$J66*N$55*P$12 -> 18.72 | R66: =$J66*Q$55*S$12 -> 19.4688 | U66: =$J66*T$55*V$12 -> 20.247552 | W66: 0
D67: Ground transportation (Cotopaxi) | E67: 2 | F67: Individual | G67: =partground -> 9 | H67: /day | I67: =IF(E67=0,0,1) -> 1 | J67: =E67*G67*I67 -> 18 | L67: =$J67*K$55*M$12 -> 18 | O67: =$J67*N$55*P$12 -> 18.72 | R67: =$J67*Q$55*S$12 -> 19.4688 | U67: =$J67*T$55*V$12 -> 20.247552 | W67: 0
D68: Lodging | F68: Individual | G68: =partlodg -> 25 | H68: /day | I68: =IF(E68=0,0,1) -> 0 | J68: =E68*G68*I68 -> 0 | L68: =$J68*K$55*M$12 -> 0 | O68: =$J68*N$55*P$12 -> 0 | R68: =$J68*Q$55*S$12 -> 0 | U68: =$J68*T$55*V$12 -> 0 | W68: 0
D69: M&IE | F69: Individual | G69: =partmeals -> 47 | H69: /day | I69: =IF(E69=0,0,1) -> 0 | J69: =E69*G69*I69 -> 0 | L69: =$J69*K$55*M$12 -> 0 | O69: =$J69*N$55*P$12 -> 0 | R69: =$J69*Q$55*S$12 -> 0 | U69: =$J69*T$55*V$12 -> 0 | W69: 0
L70: =$J70*$K$55*M$12 -> 0 | O70: =$J70*$N$55*P$12 -> 0 | R70: =$J70*$Q$55*S$12 -> 0
D71: ACTIVITY TOTAL | H71: =SUM(J56:J70) -> 692
D73: Activity 1.6. Partner with GADs to integrate enforcement processes and capacity building into local community development plans and budgets: | I73: 1 | M73: =SUM(L75:L77) -> 0 | N73: =3*6 -> 18 | P73: =SUM(O75:O77) -> 5896.8 | Q73: 18 | S73: =SUM(R75:R77) -> 6132.672 | T73: 12 | V73: =SUM(U75:U77) -> 4251.9859 | W73: =SUM(M73,P73,S73,V73,) -> 16281.458
D74: Training/workshop/project activities costs | W74: =U74+R74+O74+L74 -> 0
A75: EC.1.6.A | B75: 86000 | C75: ECU | D75: Local transportation (training site) | E75: 15 | F75: Individual | G75: =parttransp -> 4 | H75: /day | I75: =IF(E75=0,0,I73) -> 1 | J75: =E75*G75*I75 -> 60 | L75: =$J75*K73*M$12 -> 0 | O75: =$J75*N73*P$12 -> 1123.2 | R75: =$J75*Q73*S$12 -> 1168.128 | U75: =$J75*T73*V$12 -> 809.90208 | W75: =U75+R75+O75+L75 -> 3101.2301
A76: EC.1.6.B | B76: 87000 | C76: ECU | D76: Lunch/coffee breaks | E76: 15 | F76: Individual | G76: =coffee+lunch -> 16 | H76: /day | I76: =IF(E76=0,0,I73) -> 1 | J76: =E76*G76*I76 -> 240 | L76: =$J76*K73*M$12 -> 0 | O76: =$J76*N73*P$12 -> 4492.8 | R76: =$J76*Q73*S$12 -> 4672.512 | U76: =$J76*T73*V$12 -> 3239.6083 | W76: =U76+R76+O76+L76 -> 12404.92
A77: EC.1.6.C | B77: 85300 | C77: ECU | D77: Printing (Photocopies) | E77: 1 | F77: activity | G77: 15 | H77: =F77 -> activity | I77: =IF(E77=0,0,1) -> 1 | J77: =E77*G77*I77 -> 15 | L77: =$J77*K73*M$12 -> 0 | O77: =$J77*N73*P$12 -> 280.8 | R77: =$J77*Q73*S$12 -> 292.032 | U77: =$J77*T73*V$12 -> 202.47552 | W77: =U77+R77+O77+L77 -> 775.30752
W78: =U78+R78+O78+L78 -> 0
D79: Staff from outside site | W79: 0
D80: Transportation (El Oro) | E80: 2 | F80: Individual | G80: =localairfare -> 175 | H80: /trip | I80: =IF(E80=0,0,1) -> 1 | J80: =E80*G80*I80 -> 350 | O80: =$J80*3*P$12 -> 1092 | R80: =$J80*3*S$12 -> 1135.68 | U80: =$J80*2*V$12 -> 787.4048 | W80: 0
D81: Ground transportation (El Oro) | E81: 2 | F81: Individual | G81: =partground -> 9 | H81: /day | I81: =IF(E81=0,0,1) -> 1 | J81: =E81*G81*I81 -> 18 | O81: =$J81*3*P$12 -> 56.16 | R81: =$J81*3*S$12 -> 58.4064 | U81: =$J81*2*V$12 -> 40.495104 | W81: 0
D82: Lodging | E82: =E80+E81 -> 4 | F82: Individual | G82: =partlodg -> 25 | H82: /day | I82: =IF(E82=0,0,1) -> 1 | J82: =E82*G82*I82 -> 100 | O82: =$J82*3*P$12 -> 312 | R82: =$J82*3*S$12 -> 324.48 | U82: =$J82*2*V$12 -> 224.9728 | W82: 0
D83: M&IE | E83: =E82 -> 4 | F83: Individual | G83: =partmeals -> 47 | H83: /day | I83: =IF(E83=0,0,1) -> 1 | J83: =E83*G83*I83 -> 188 | O83: =$J83*3*P$12 -> 586.56 | R83: =$J83*3*S$12 -> 610.0224 | U83: =$J83*2*V$12 -> 422.94886 | W83: 0
W84: 0
D85: Staff from outside training site | J85: =E85*G85*I85 -> 0 | O85: =$J85*N73*P$12 -> 0 | R85: =$J85*Q73*S$12 -> 0 | U85: =$J85*T73*V$12 -> 0 | W85: 0
D86: Transportation (Cotopaxi) | E86: 2 | F86: Individual | G86: =partground -> 9 | H86: /trip | I86: =IF(E86=0,0,1) -> 1 | J86: =E86*G86*I86 -> 18 | O86: =$J86*3*P$12 -> 56.16 | R86: =$J86*3*S$12 -> 58.4064 | U86: =$J86*2*V$12 -> 40.495104 | W86: 0
D87: Ground transportation (Cotopaxi) | E87: 2 | F87: Individual | G87: =partground -> 9 | H87: /day | I87: =IF(E87=0,0,1) -> 1 | J87: =E87*G87*I87 -> 18 | O87: =$J87*3*P$12 -> 56.16 | R87: =$J87*3*S$12 -> 58.4064 | U87: =$J87*2*V$12 -> 40.495104 | W87: 0
D88: Lodging | F88: Individual | G88: =partlodg -> 25 | H88: /day | I88: =IF(E88=0,0,I73) -> 0 | J88: =E88*G88*I88 -> 0 | O88: =$J88*3*P$12 -> 0 | R88: =$J88*3*S$12 -> 0 | U88: =$J88*2*V$12 -> 0 | W88: =U88+R88+O88+L88 -> 0
D89: M&IE | F89: Individual | G89: =partmeals -> 47 | H89: /day | I89: =IF(E89=0,0,I73) -> 0 | J89: =E89*G89*I89 -> 0 | O89: =$J89*3*P$12 -> 0 | R89: =$J89*3*S$12 -> 0 | U89: =$J89*2*V$12 -> 0 | W89: =U89+R89+O89+L89 -> 0
D90: ACTIVITY TOTAL | H90: =SUM(J74:J89) -> 1007
D92: Activity 1.7 Disseminate successes: | I92: 1 | M92: =SUM(L94:L97) -> 0 | N92: 0 | P92: =SUM(O94:O97) -> 0 | Q92: 6 | S92: =SUM(R94:R97) -> 5191.68 | T92: 4 | V92: =SUM(U94:U97) -> 3599.5648 | W92: =SUM(M92,P92,S92,V92,) -> 8791.2448
D93: Meetings/Forums/Seminars | W93: =U93+R93+O93+L93 -> 0
A94: EC.1.7.A | B94: 86000 | C94: ECU | D94: Local transportation (training site) | E94: 15 | F94: Individual | G94: =parttransp -> 4 | H94: /day | I94: =IF(E94=0,0,I92) -> 1 | J94: =E94*G94*I94 -> 60 | L94: =$J94*K92*M$12 -> 0 | O94: =$J94*N92*P$12 -> 0 | R94: =$J94*Q92*S$12 -> 389.376 | U94: =$J94*T92*V$12 -> 269.96736 | W94: =U94+R94+O94+L94 -> 659.34336
A95: EC.1.7.B | B95: 87000 | C95: ECU | D95: Lunch/coffee breaks | E95: 15 | F95: Individual | G95: =coffee+lunch -> 16 | H95: /day | I95: =IF(E95=0,0,I92) -> 1 | J95: =E95*G95*I95 -> 240 | L95: =$J95*K92*M$12 -> 0 | O95: =$J95*N92*P$12 -> 0 | R95: =$J95*Q92*S$12 -> 1557.504 | U95: =$J95*T92*V$12 -> 1079.8694 | W95: =U95+R95+O95+L95 -> 2637.3734
A96: EC.1.7.C | B96: 82420 | C96: ECU | D96: Materials & Supplies (Media Dissemination) | E96: 500 | F96: workshop | G96: 1 | H96: =F96 -> workshop | I96: 1 | J96: =E96*G96*I96 -> 500 | L96: =$J96*K92*M$12 -> 0 | O96: =$J96*N92*P$12 -> 0 | R96: =$J96*Q92*S$12 -> 3244.8 | U96: =$J96*T92*V$12 -> 2249.728 | W96: =U96+R96+O96+L96 -> 5494.528
D98: ACTIVITY TOTAL | H98: =SUM(J93:J97) -> 800
D100: Activity 2.1. Assess rural workers’ information needs, work experiences, and trusted organizations | I100: 1 | K100: 1 | M100: =SUM(L102) -> 4500 | N100: 0 | P100: =SUM(O102:O114) -> 0 | Q100: 0 | S100: =SUM(R102:R114) -> 0 | T100: 0 | V100: =SUM(U102:U114) -> 0 | W100: =SUM(M100,P100,S100,V100,) -> 4500
D101: Training/workshop/project activities costs | W101: =U101+R101+O101+L101 -> 0
A102: EC.2.1.A | B102: 81000 | C102: ECU | D102: Local Consultant (surveys, KIIs, etc.) | E102: 15 | F102: Individual | G102: =localcons -> 300 | H102: /day | I102: 1 | J102: =E102*G102*I102 -> 4500 | L102: =$J102*K100*M$12 -> 4500 | O102: =$J102*N100*P$12 -> 0 | R102: =$J102*Q100*S$12 -> 0 | U102: =$J102*T100*V$12 -> 0 | W102: =U102+R102+O102+L102 -> 4500
W103: =U103+R103+O103+L103 -> 0
D104: Staff from outside site | W104: 0
D105: Transportation (El Oro) | E105: 2 | F105: Individual | G105: =localairfare -> 175 | H105: /trip | I105: =IF(E105=0,0,1) -> 1 | J105: =E105*G105*I105 -> 350 | L105: =$J105*$K$100*M$12 -> 350 | W105: 0
D106: Ground transportation (El Oro) | E106: 2 | F106: Individual | G106: =partground -> 9 | H106: /day | I106: =IF(E106=0,0,1) -> 1 | J106: =E106*G106*I106 -> 18 | L106: =$J106*$K$100*M$12 -> 18 | W106: 0
D107: Lodging | E107: =E105+E106 -> 4 | F107: Individual | G107: =partlodg -> 25 | H107: /day | I107: =IF(E107=0,0,1) -> 1 | J107: =E107*G107*I107 -> 100 | L107: =$J107*$K$100*M$12 -> 100 | W107: 0
D108: M&IE | E108: =E107 -> 4 | F108: Individual | G108: =partmeals -> 47 | H108: /day | I108: =IF(E108=0,0,1) -> 1 | J108: =E108*G108*I108 -> 188 | L108: =$J108*$K$100*M$12 -> 188 | W108: 0
W109: 0
D110: Staff from outside training site | J110: =E110*G110*I110 -> 0 | W110: 0
...

Sheet INDES Sub Budget Summary
A1: Sub-Award Budget Summary
A2: INDES Sub-Recipient
A3: ='INDES Sub Line-Item Budget'!E3:T3 -> #VALUE!
A4: 48 Months
A6: BUDGET SUMMARY CATEGORIES | B6: YEAR 1 | C6: YEAR 2 | D6: YEAR 3 | E6: YEAR 4 | F6: TOTAL FEDERAL FUNDS REQUESTED
A8: 1. PERSONNEL | B8: ='INDES Sub Line-Item Budget'!K19 -> 82683 | C8: ='INDES Sub Line-Item Budget'!M19 -> 89506.2 | D8: ='INDES Sub Line-Item Budget'!O19 -> 93981.51 | E8: ='INDES Sub Line-Item Budget'!Q19 -> 49340.293 | F8: =SUM(B8:E8) -> 315511
A9: 2. FRINGE BENEFITS | B9: ='INDES Sub Line-Item Budget'!K25 -> 35826.544 | C9: ='INDES Sub Line-Item Budget'!M25 -> 38783.036 | D9: ='INDES Sub Line-Item Budget'!O25 -> 40722.188 | E9: ='INDES Sub Line-Item Budget'!Q25 -> 21379.149 | F9: =SUM(B9:E9) -> 136710.92
A10: 3. TRAVEL | B10: ='INDES Sub Line-Item Budget'!K29 -> 120 | C10: ='INDES Sub Line-Item Budget'!M29 -> 11246.56 | D10: ='INDES Sub Line-Item Budget'!O29 -> 13372.902 | E10: ='INDES Sub Line-Item Budget'!Q29 -> 4155.2476 | F10: =SUM(B10:E10) -> 28894.71
A11: 4. EQUIPMENT | B11: ='INDES Sub Line-Item Budget'!K33 -> 0 | C11: ='INDES Sub Line-Item Budget'!M33 -> 0 | D11: ='INDES Sub Line-Item Budget'!O33 -> 0 | E11: ='INDES Sub Line-Item Budget'!Q33 -> 0 | F11: =SUM(B11:E11) -> 0
A12: 5. SUPPLIES | B12: ='INDES Sub Line-Item Budget'!K37 -> 540 | C12: ='INDES Sub Line-Item Budget'!M37 -> 748.8 | D12: ='INDES Sub Line-Item Budget'!O37 -> 778.752 | E12: ='INDES Sub Line-Item Budget'!Q37 -> 404.95104 | F12: =SUM(B12:E12) -> 2472.503
A13: 6. CONTRACTUAL | B13: ='INDES Sub Line-Item Budget'!K40 -> 0 | C13: ='INDES Sub Line-Item Budget'!M40 -> 0 | D13: ='INDES Sub Line-Item Budget'!O40 -> 0 | E13: ='INDES Sub Line-Item Budget'!Q40 -> 0 | F13: =SUM(B13:E13) -> 0
A14: 7. CONSTRUCTION | B14: 0 | C14: 0 | D14: 0 | E14: 0 | F14: =SUM(B14:E14) -> 0
A15: 8. OTHER DIRECT COSTS | B15: ='INDES Sub Line-Item Budget'!K61 -> 2700 | C15: ='INDES Sub Line-Item Budget'!M61 -> 36748.8 | D15: ='INDES Sub Line-Item Budget'!O61 -> 44307.744 | E15: ='INDES Sub Line-Item Budget'!Q61 -> 14735.718 | F15: =SUM(B15:E15) -> 98492.262
A17: 9. TOTAL DIRECT COSTS (Lines 1-8) | B17: =SUM(B8:B15) -> 121869.54 | C17: =SUM(C8:C15) -> 177033.4 | D17: =SUM(D8:D15) -> 193163.1 | E17: =SUM(E8:E15) -> 90015.359 | F17: =SUM(F8:F15) -> 582081.4
A18: 10. INDIRECT COSTS | B18: ='INDES Sub Line-Item Budget'!K65 -> 12186.954 | C18: ='INDES Sub Line-Item Budget'!M65 -> 17703.34 | D18: ='INDES Sub Line-Item Budget'!O65 -> 19316.31 | E18: ='INDES Sub Line-Item Budget'!Q65 -> 9001.5359 | F18: =SUM(B18:E18) -> 58208.14
A19: 11. TOTAL COSTS (Lines 9-10) | B19: =SUM(B17:B18) -> 134056.5 | C19: =SUM(C17:C18) -> 194736.74 | D19: =SUM(D17:D18) -> 212479.41 | E19: =SUM(E17:E18) -> 99016.895 | F19: =SUM(F17:F18) -> 640289.54

Sheet INDES Sub Line-Item Budget
E1: Project Line-Item Budget
E2: ='INDES Sub Budget Summary'!A2:F2 -> 0
E3: Project to Improve Adherence to International Labor Standards in the Agricultural Sector in Ecuador Improve Adherence to International Labor Standards in the Agricultural Sector in Ecuador
E4: 48 Months
E5: Cost Assumptions
E6: Inflation - US Based Goods/Services | F6: 1.03
E7: Inflation - Locally Purchased Goods/Services | F7: 1.04
E8: Merit Based Increases for HO & Field Staff | F8: 1.05
A10: Activity Code | B10: Account Code | C10: Country Code | D10: Sub Budget Code | E10: BUDGET ITEM | F10: CATEGORY | G10: LOE | H10: UNIT | I10: # of Units | J10: RATE / UNIT | K10: Year 1 | L10: # of Units | M10: Year 2 | N10: # of Units | O10: Year 3 | P10: # of Units | Q10: Year 4 | R10: TOTAL DOL | S10: TOTAL COST SHARING | T10: PROJECT GRAND TOTAL
E11: Personnel
E13: Professional Personnel
A14: SUBINDES | B14: 89050 | C14: ECU | D14: INDESPERPC | E14: Project Coordinator | F14: Salaries | G14: 0.4 | H14: Month | I14: 9 | J14: 3125 | K14: =I14*J14*G14 -> 11250 | L14: 12 | M14: =L14*J14*$F$8*G14 -> 15750 | N14: 12 | O14: =(N14*J14*$F$8*$F$8)*G14 -> 16537.5 | P14: 6 | Q14: =P14*J14*$F$8*$F$8*$F$8*G14 -> 8682.1875 | R14: =SUM(K14+M14+O14+Q14) -> 52219.688 | S14: 0 | T14: =SUM(R14:S14) -> 52219.688
A15: SUBINDES | B15: 89050 | C15: ECU | D15: INDESPERTO | E15: Technical Officer x 2 | F15: Salaries | G15: 2 | H15: Month | I15: 9 | J15: =25000/12 -> 2083.3333 | K15: =I15*J15*G15 -> 37500 | L15: 12 | M15: =L15*J15*$F$8 -> 26250 | N15: 12 | O15: =(N15*J15*$F$8*$F$8) -> 27562.5 | P15: 6 | Q15: =P15*J15*$F$8*$F$8*$F$8 -> 14470.312 | R15: =SUM(K15+M15+O15+Q15) -> 105782.81 | S15: 0 | T15: =SUM(R15:S15) -> 105782.81
A16: SUBINDES | B16: 89050 | C16: ECU | D16: INDESPERME | E16: M&E Officer | F16: Salaries | G16: 1 | H16: Month | I16: 9 | J16: =25000/12 -> 2083.3333 | K16: =I16*J16*G16 -> 18750 | L16: 12 | M16: =L16*J16*$F$8 -> 26250 | N16: 12 | O16: =(N16*J16*$F$8*$F$8) -> 27562.5 | P16: 6 | Q16: =P16*J16*$F$8*$F$8*$F$8 -> 14470.312 | R16: =SUM(K16+M16+O16+Q16) -> 87032.812 | S16: 0 | T16: =SUM(R16:S16) -> 87032.812
A17: SUBINDES | B17: 89050 | C17: ECU | D17: INDESPERFA | E17: Finance & Administration Officer | F17: Salaries | G17: 1 | H17: Month | I17: 9 | J17: 1687 | K17: =I17*J17*G17 -> 15183 | L17: 12 | M17: =L17*J17*$F$8 -> 21256.2 | N17: 12 | O17: =(N17*J17*$F$8*$F$8) -> 22319.01 | P17: 6 | Q17: =P17*J17*$F$8*$F$8*$F$8 -> 11717.48 | R17: =SUM(K17+M17+O17+Q17) -> 70475.69 | S17: 0 | T17: =SUM(R17:S17) -> 70475.69
E19: Total Personnel | K19: =SUM(K12:K17) -> 82683 | M19: =SUM(M12:M17) -> 89506.2 | O19: =SUM(O12:O17) -> 93981.51 | Q19: =SUM(Q12:Q17) -> 49340.293 | R19: =SUM(R12:R17) -> 315511 | S19: =SUM(S12:S17) -> 0 | T19: =SUM(R19:S19) -> 315511
E20: Fringe Benefits
E22: Fringe Benefits
A23: SUBINDES | B23: 89050 | C23: ECU | D23: INDESFRING | E23: Fringe benefits - Ecuador | F23: Fringe Benefits | H23: Month | J23: 0.4333 | K23: =SUM(K12:K17)*$J23 -> 35826.544 | M23: =SUM(M12:M17)*$J23 -> 38783.036 | O23: =SUM(O12:O17)*$J23 -> 40722.188 | Q23: =SUM(Q12:Q17)*$J23 -> 21379.149 | R23: =SUM(K23+M23+O23+Q23) -> 136710.92 | S23: 0 | T23: =SUM(R23:S23) -> 136710.92
E25: Total Fringe Benefits | K25: =SUM(K23:K24) -> 35826.544 | M25: =SUM(M23:M24) -> 38783.036 | O25: =SUM(O23:O24) -> 40722.188 | Q25: =SUM(Q23:Q24) -> 21379.149 | R25: =SUM(R23:R24) -> 136710.92 | S25: =SUM(S23:S24) -> 0 | T25: =SUM(T23:T24) -> 136710.92
E26: Travel
A27: SUBINDES | B27: 89050 | C27: ECU | D27: INDESLOCTR | E27: T3: Domestic Travel to Field (See Travel Detail Tab) | K27: ='INDES Sub Activities Detail'!J279 -> 120 | M27: ='INDES Sub Activities Detail'!M279 -> 11246.56 | O27: ='INDES Sub Activities Detail'!P279 -> 13372.902 | Q27: ='INDES Sub Activities Detail'!S279 -> 4155.2476 | R27: =SUM(K27+M27+O27+Q27) -> 28894.71 | T27: =SUM(R27:S27) -> 28894.71
E29: Total Travel | K29: =SUM(K27:K27) -> 120 | M29: =SUM(M27:M27) -> 11246.56 | O29: =SUM(O27:O27) -> 13372.902 | Q29: =SUM(Q27:Q27) -> 4155.2476 | R29: =SUM(R27:R27) -> 28894.71 | S29: =SUM(S27:S27) -> 0 | T29: =SUM(R29:S29) -> 28894.71
E30: Equipment
A31: None | B31: None | C31: None | D31: None | E31: None | F31: Equipment | H31: Unit | L31: 0 | M31: =L31*J31*Assumptions!$C$15 -> 0 | N31: 0 | O31: =N31*J31*Assumptions!$C$15*Assumptions!$C$15 -> 0 | P31: 0 | Q31: =P31*J31*Assumptions!$C$15*Assumptions!$C$15*Assumptions!$C$15 -> 0 | R31: =SUM(K31+M31+O31+Q31) -> 0 | S31: 0 | T31: =SUM(R31:S31) -> 0
E33: Total Equipment | K33: =SUM(K31) -> 0 | M33: =SUM(M31) -> 0 | O33: =SUM(O31) -> 0 | Q33: =SUM(Q31) -> 0 | R33: =SUM(R31) -> 0 | S33: =SUM(S31) -> 0 | T33: =SUM(R33:S33) -> 0
E34: Supplies
A35: SUBINDES | B35: 89050 | C35: ECU | D35: INDESUPP | E35: Office supplies | F35: Supplies | H35: Month | I35: 9 | J35: 60 | K35: =J35*I35 -> 540 | L35: 12 | M35: =L35*J35*$F$7 -> 748.8 | N35: 12 | O35: =N35*J35*$F$7*$F$7 -> 778.752 | P35: 6 | Q35: =P35*J35*$F$7*$F$7*$F$7 -> 404.95104 | R35: =SUM(K35+M35+O35+Q35) -> 2472.503 | S35: 0 | T35: =SUM(R35:S35) -> 2472.503
E37: Total Supplies | K37: =SUM(K35:K35) -> 540 | M37: =SUM(M35:M35) -> 748.8 | O37: =SUM(O35:O35) -> 778.752 | Q37: =SUM(Q35:Q35) -> 404.95104 | R37: =SUM(R35:R35) -> 2472.503 | S37: =SUM(S35:S35) -> 0 | T37: =SUM(R37:S37) -> 2472.503
E38: Contractual
E40: Total Contractual | K40: =SUM(K39:K39) -> 0 | M40: =SUM(M39:M39) -> 0 | O40: =SUM(O39:O39) -> 0 | Q40: =SUM(Q39:Q39) -> 0 | R40: =SUM(R39:R39) -> 0 | S40: =SUM(S39:S39) -> 0 | T40: =SUM(T39:T39) -> 0
E41: Other Direct Costs
E42: Project Office
A43: SUBINDES | B43: 89050 | C43: ECU | D43: INDESOFF | E43: Office space (includes utilities, Wi-Fi, coffee) | F43: Office Expenses | H43: Month | I43: 9 | J43: 300 | K43: =I43*J43 -> 2700 | L43: 12 | M43: =L43*J43*$F$7 -> 3744 | N43: 12 | O43: =N43*J43*$F$7*$F$7 -> 3893.76 | P43: 6 | Q43: =P43*J43*$F$7*$F$7*$F$7 -> 2024.7552 | R43: =SUM(K43+M43+O43+Q43) -> 12362.515 | S43: 0 | T43: =SUM(R43:S43) -> 12362.515
E44: Outcome 1
A45: SUBINDES | B45: 89050 | C45: ECU | D45: INDES1.4 | E45: Activity 1.4. Develop, deliver, and institutionalize tailored capacity building for government officials: | F45: Outcome1 | K45: ='INDES Sub Activities Detail'!J16 -> 0 | M45: ='INDES Sub Activities Detail'!M16 -> 2808 | O45: ='INDES Sub Activities Detail'!P16 -> 2920.32 | Q45: ='INDES Sub Activities Detail'!S16 -> 1518.5664 | R45: =SUM(K45+M45+O45+Q45) -> 7246.8864 | T45: =SUM(R45:S45) -> 7246.8864
A46: SUBINDES | B46: 89050 | C46: ECU | D46: INDES1.6 | E46: Activity 1.6. Partner with GADs to integrate enforcement processes and capacity building into local community development plans and budgets: | F46: Outcome1 | K46: ='INDES Sub Activities Detail'!J31 -> 0 | M46: ='INDES Sub Activities Detail'!M31 -> 2948.4 | O46: ='INDES Sub Activities Detail'!P31 -> 3066.336 | Q46: ='INDES Sub Activities Detail'!S31 -> 2125.993 | R46: =SUM(K46+M46+O46+Q46) -> 8140.729 | T46: =SUM(R46:S46) -> 8140.729
A47: SUBINDES | B47: 89050 | C47: ECU | D47: INDES1.7 | E47: Activity 1.7 Disseminate successes: | F47: Outcome1 | K47: ='INDES Sub Activities Detail'!J46 -> 0 | M47: ='INDES Sub Activities Detail'!M46 -> 0 | O47: ='INDES Sub Activities Detail'!P46 -> 0 | Q47: ='INDES Sub Activities Detail'!S46 -> 337.4592 | R47: =SUM(K47+M47+O47+Q47) -> 337.4592 | T47: =SUM(R47:S47) -> 337.4592
E48: Outcome 2
A49: SUBINDES | B49: 89050 | C49: ECU | D49: INDES2.2 | E49: Activity 2.2. Build capacity of worker organizations, producer associations, and other actors to reach workers to understand their rights | F49: Outcome2 | K49: ='INDES Sub Activities Detail'!J53 -> 0 | M49: ='INDES Sub Activities Detail'!M53 -> 9204 | O49: ='INDES Sub Activities Detail'!P53 -> 9572.16 | Q49: ='INDES Sub Activities Detail'!S53 -> 0 | R49: =SUM(K49+M49+O49+Q49) -> 18776.16 | T49: =SUM(R49:S49) -> 18776.16
A50: SUBINDES | B50: 89050 | C50: ECU | D50: INDES2.3 | E50: Activity 2.3. Institutionalize worker and community training and awareness-raising | F50: Outcome2 | K50: ='INDES Sub Activities Detail'!J67 -> 0 | M50: ='INDES Sub Activities Detail'!M67 -> 0 | O50: ='INDES Sub Activities Detail'!P67 -> 0 | Q50: ='INDES Sub Activities Detail'!S67 -> 3824.5376 | R50: =SUM(K50+M50+O50+Q50) -> 3824.5376 | T50: =SUM(R50:S50) -> 3824.5376
A51: SUBINDES | B51: 89050 | C51: ECU | D51: INDES2.4 | E51: Activity 2.4. Establish and convene neutral spaces for bipartite and tripartite social dialogue | F51: Outcome2 | K51: ='INDES Sub Activities Detail'!J75 -> 0 | M51: ='INDES Sub Activities Detail'!M75 -> 1726.4 | O51: ='INDES Sub Activities Detail'!P75 -> 5386.368 | Q51: ='INDES Sub Activities Detail'!S75 -> 1867.2742 | R51: =SUM(K51+M51+O51+Q51) -> 8980.0422 | T51: =SUM(R51:S51) -> 8980.0422
A52: SUBINDES | B52: 89050 | C52: ECU | D52: INDES2.5 | E52: Activity 2.5. Train small, medium, and large employers to engage workers, understand workers’ rights, and monitor rights compliance in their supply chains | F52: Outcome2 | K52: ='INDES Sub Activities Detail'!J83 -> 0 | M52: ='INDES Sub Activities Detail'!M83 -> 5304 | O52: ='INDES Sub Activities Detail'!P83 -> 5516.16 | Q52: ='INDES Sub Activities Detail'!S83 -> 0 | R52: =SUM(K52+M52+O52+Q52) -> 10820.16 | T52: =SUM(R52:S52) -> 10820.16
A53: SUBINDES | B53: 89050 | C53: ECU | D53: INDES2.7 | E53: Activity 2.7. Generate new opportunities for learning among civil society, workers, government, private sector, and others. | F53: Outcome2 | K53: ='INDES Sub Activities Detail'!J91 -> 0 | M53: ='INDES Sub Activities Detail'!M91 -> 0 | O53: ='INDES Sub Activities Detail'!P91 -> 973.44 | Q53: ='INDES Sub Activities Detail'!S91 -> 1012.3776 | R53: =SUM(K53+M53+O53+Q53) -> 1985.8176 | T53: =SUM(R53:S53) -> 1985.8176
A54: SUBINDES | B54: 89050 | C54: ECU | D54: INDES2.8 | E54: Activity 2.8. Assess changes in rural workers’, business, Community-Based Organizations, and government officials’ knowledge, skills, and practices. | F54: Outcome2 | K54: ='INDES Sub Activities Detail'!J104 -> 0 | M54: ='INDES Sub Activities Detail'!M104 -> 0 | O54: ='INDES Sub Activities Detail'!P104 -> 1946.88 | Q54: ='INDES Sub Activities Detail'!S104 -> 2024.7552 | R54: =SUM(K54+M54+O54+Q54) -> 3971.6352 | T54: =SUM(R54:S54) -> 3971.6352
E55: Outcome 3 | T55: =SUM(R55:S55) -> 0
A56: SUBINDES | B56: 89050 | C56: ECU | D56: INDES3.1 | E56: Activity 3.1- Undertake Remediation Constraints and Opportunities Analysis | F56: Outcome3 | K56: ='INDES Sub Activities Detail'!J118 -> 0 | M56: ='INDES Sub Activities Detail'!M118 -> 302 | O56: ='INDES Sub Activities Detail'!P118 -> 0 | Q56: ='INDES Sub Activities Detail'!S118 -> 0 | R56: =SUM(K56+M56+O56+Q56) -> 302 | T56: =SUM(R56:S56) -> 302
A57: SUBINDES | B57: 89050 | C57: ECU | D57: INDES3.2 | E57: Activity 3.2 Validate analysis and select pilot remediation mechanism designs | F57: Outcome3 | K57: ='INDES Sub Activities Detail'!J129 -> 0 | M57: ='INDES Sub Activities Detail'!M129 -> 2808 | O57: ='INDES Sub Activities Detail'!P129 -> 0 | Q57: ='INDES Sub Activities Detail'!S129 -> 0 | R57: =SUM(K57+M57+O57+Q57) -> 2808 | T57: =SUM(R57:S57) -> 2808
A58: SUBINDES | B58: 89050 | C58: ECU | D58: INDES3.3 | E58: Activity 3.3. Engage partners to design, implement, and monitor pilot remediations solutions | F58: Outcome3 | K58: ='INDES Sub Activities Detail'!J137 -> 0 | M58: ='INDES Sub Activities Detail'!M137 -> 104 | O58: ='INDES Sub Activities Detail'!P137 -> 216.32 | Q58: ='INDES Sub Activities Detail'!S137 -> 0 | R58: =SUM(K58+M58+O58+Q58) -> 320.32 | T58: =SUM(R58:S58) -> 320.32
A59: SUBINDES | B59: 89050 | C59: ECU | D59: INDES3.4 | E59: Activity 3.4. Finalize and institutionalize proven grievance and restitution mechanisms | F59: Outcome3 | K59: ='INDES Sub Activities Detail'!J149 -> 0 | M59: ='INDES Sub Activities Detail'!M149 -> 2600 | O59: ='INDES Sub Activities Detail'!P149 -> 5408 | Q59: ='INDES Sub Activities Detail'!S149 -> 0 | R59: =SUM(K59+M59+O59+Q59) -> 8008 | T59: =SUM(R59:S59) -> 8008
A60: SUBINDES | B60: 89050 | C60: ECU | D60: INDES3.6 | E60: Activity 3.6. Engage medium and large producers to strengthen grievance and restitution mechanisms in their workplaces and supply chains | F60: Outcome3 | K60: ='INDES Sub Activities Detail'!J163 -> 0 | M60: ='INDES Sub Activities Detail'!M163 -> 5200 | O60: ='INDES Sub Activities Detail'!P163 -> 5408 | Q60: ='INDES Sub Activities Detail'!S163 -> 0 | R60: =SUM(K60+M60+O60+Q60) -> 10608 | T60: =SUM(R60:S60) -> 10608
E61: Total Other Direct Costs | K61: =SUM(K43:K60) -> 2700 | M61: =SUM(M43:M60) -> 36748.8 | O61: =SUM(O43:O60) -> 44307.744 | Q61: =SUM(Q43:Q60) -> 14735.718 | R61: =SUM(R43:R60) -> 98492.262 | S61: =SUM(S46:S49) -> 0 | T61: =SUM(T43:T60) -> 98492.262
E63: Total Direct Costs | K63: =SUM(K19+K25+K29+K37++K61+K40+K33) -> 121869.54 | M63: =SUM(M19+M25+M29+M37++M61+M40+M33) -> 177033.4 | O63: =SUM(O19+O25+O29+O37++O61+O40+O33) -> 193163.1 | Q63: =SUM(Q19+Q25+Q29+Q37++Q61+Q40+Q33) -> 90015.359 | R63: =SUM(R19+R25+R29+R37++R61+R40+R33) -> 582081.4 | S63: =SUM(S19+S25+S29+S37++S61+S40+S33) -> 0 | T63: =SUM(T19+T25+T29+T37++T61+T40+T33) -> 582081.4
A65: SUBINDES | B65: 89050 | C65: ECU | D65: INDESIDC | E65: De minimis rate | F65: Indirect Charges | J65: 0.1 | K65: =(K63)*J65 -> 12186.954 | M65: =(M63)*J65 -> 17703.34 | O65: =(O63)*J65 -> 19316.31 | Q65: =(Q63)*J65 -> 9001.5359 | R65: =SUM(K65+M65+O65+Q65) -> 58208.14 | S65: 0 | T65: =SUM(R65:S65) -> 58208.14
E67: TOTAL PROGRAM COSTS | K67: =K63+K65 -> 134056.5 | M67: =M63+M65 -> 194736.74 | O67: =O63+O65 -> 212479.41 | Q67: =Q63+Q65 -> 99016.895 | R67: =R63+R65 -> 640289.54 | S67: =S63+S65 -> 0 | T67: =SUM(R67:S67) -> 640289.54

Sheet INDES Sub Activities Detail
A1: ='INDES Sub Line-Item Budget'!E2:T2 -> #VALUE!
A2: DONOR: | B2: =Assumptions!C5 -> USDOL
A3: Country: | B3: =Assumptions!C6 -> Ecuador
A4: Program Name: | B4: =Assumptions!C7 -> Project to Improve Adherence to International Labor Standards in the Agricultural Sector in Ecuador
A5: Grant Number: | B5: =Assumptions!C8 -> FOA-ILAB-23-28
A6: Period of Performance: | B6: =Assumptions!C9 -> 48 months
A10: ACTIVITY DESCRIPTION | B10: Units | D10: Cost | E10: Base | F10: # of days | H10: ='INDES Sub Line-Item Budget'!K10 -> Year 1 | K10: ='INDES Sub Line-Item Budget'!M10 -> Year 2 | N10: ='INDES Sub Line-Item Budget'!O10 -> Year 3 | Q10: ='INDES Sub Line-Item Budget'!Q10 -> Year 4 | T10: Total
H11: # Activities | J11: Amount | K11: # Activities | M11: Amount | N11: # Activities | P11: Amount | Q11: # Activities | S11: Amount
A12: ODC Escalation Factor | B12: 0.04 | J12: 1 | M12: =$J$12*SUM(1+$B$12) -> 1.04 | P12: =$M$12*SUM(1+$B$12) -> 1.0816 | S12: =$P$12*SUM(1+$B$12) -> 1.124864
A13: MEETINGS
A16: =' Activities Detail'!D42:H42 -> #VALUE! | F16: 1 | J16: =SUM(I18:I20) -> 0 | K16: 6 | M16: =SUM(L18:L20) -> 2808 | N16: 6 | P16: =SUM(O18:O20) -> 2920.32 | Q16: 3 | S16: =SUM(R18:R20) -> 1518.5664 | T16: =SUM(J16,M16,P16,S16,) -> 7246.8864
A17: Training/workshop/project activities costs
A18: Local transportation (Cotopaxi) | B18: 20 | C18: Individual | D18: =parttransp -> 4 | E18: /day | F18: =IF(B18=0,0,F16) -> 1 | G18: =B18*D18*F18 -> 80 | I18: =$G18*H16*J$12 -> 0 | L18: =$G18*K16*M$12 -> 499.2 | O18: =$G18*N16*P$12 -> 519.168 | R18: =$G18*Q16*S$12 -> 269.96736
A19: Lunch/coffee breaks | B19: 20 | C19: Individual | D19: =coffee+lunch -> 16 | E19: /day | F19: =IF(B19=0,0,F16) -> 1 | G19: =B19*D19*F19 -> 320 | I19: =$G19*H16*J$12 -> 0 | L19: =$G19*K16*M$12 -> 1996.8 | O19: =$G19*N16*P$12 -> 2076.672 | R19: =$G19*Q16*S$12 -> 1079.8694
A20: Printing (Photocopies) | B20: 1 | C20: activity | D20: =print -> 50 | E20: =C20 -> activity | F20: =IF(B20=0,0,1) -> 1 | G20: =B20*D20*F20 -> 50 | I20: =$G20*H16*J$12 -> 0 | L20: =$G20*K16*M$12 -> 312 | O20: =$G20*N16*P$12 -> 324.48 | R20: =$G20*Q16*S$12 -> 168.7296
A22: Staff from outside training site | G22: =B22*D22*F22 -> 0
A23: Transportation (Cotopaxi) | B23: 2 | C23: Individual | D23: =partground -> 9 | E23: /trip | F23: =IF(B23=0,0,1) -> 1 | G23: =B23*D23*F23 -> 18 | I23: =$G23*H23*J$12 -> 0 | L23: =$G23*$K$16*M$12 -> 112.32 | O23: =$G23*$N$16*P$12 -> 116.8128 | R23: =$G23*$Q$16*S$12 -> 60.742656
A24: Ground transportation (Cotopaxi) | B24: 2 | C24: Individual | D24: =partground -> 9 | E24: /day | F24: =IF(B24=0,0,1) -> 1 | G24: =B24*D24*F24 -> 18 | I24: =$G24*J$12 -> 18 | L24: =$G24*$K$16*M$12 -> 112.32 | O24: =$G24*$N$16*P$12 -> 116.8128 | R24: =$G24*$Q$16*S$12 -> 60.742656
A25: Lodging | C25: Individual | D25: =partlodg -> 25 | E25: /day | F25: 1 | G25: =B25*D25*F25 -> 0 | I25: =$G25*J$12 -> 0 | L25: =$G25*$K$16*M$12 -> 0 | O25: =$G25*$N$16*P$12 -> 0 | R25: =$G25*$Q$16*S$12 -> 0
A26: M&IE (excluding lunch) | B26: 2 | C26: Individual | D26: =partmeals -> 47 | E26: /day | F26: 1 | G26: =B26*D26*F26 -> 94 | I26: =$G26*J$12 -> 94 | L26: =$G26*$K$16*M$12 -> 586.56 | O26: =$G26*$N$16*P$12 -> 610.0224 | R26: =$G26*$Q$16*S$12 -> 317.21165
A27: Travel Day Lunch | B27: 2 | C27: Individual | D27: =parttransp -> 4 | E27: /trip | F27: 1 | G27: =B27*D27*F27 -> 8 | I27: =$G27*J$12 -> 8 | L27: =$G27*$K$16*M$12 -> 49.92 | O27: =$G27*$N$16*P$12 -> 51.9168 | R27: =$G27*$Q$16*S$12 -> 26.996736
A28: ACTIVITY TOTAL | E28: =SUM(G17:G27) -> 588
A31: =' Activities Detail'!D73:H73 -> #VALUE! | F31: 1 | J31: =SUM(I33:I35) -> 0 | K31: 9 | M31: =SUM(L33:L35) -> 2948.4 | N31: 9 | P31: =SUM(O33:O35) -> 3066.336 | Q31: 6 | S31: =SUM(R33:R35) -> 2125.993 | T31: =SUM(J31,M31,P31,S31,) -> 8140.729
A32: Training/workshop/project activities costs
A33: Local transportation (training site) | B33: 15 | C33: Individual | D33: =parttransp -> 4 | E33: /day | F33: =IF(B33=0,0,F31) -> 1 | G33: =B33*D33*F33 -> 60 | I33: =$G33*H31*J$12 -> 0 | L33: =$G33*K31*M$12 -> 561.6 | O33: =$G33*N31*P$12 -> 584.064 | R33: =$G33*Q31*S$12 -> 404.95104
A34: Lunch/coffee breaks | B34: 15 | C34: Individual | D34: =coffee+lunch -> 16 | E34: /day | F34: =IF(B34=0,0,F31) -> 1 | G34: =B34*D34*F34 -> 240 | I34: =$G34*H31*J$12 -> 0 | L34: =$G34*K31*M$12 -> 2246.4 | O34: =$G34*N31*P$12 -> 2336.256 | R34: =$G34*Q31*S$12 -> 1619.8042
A35: Printing (Photocopies) | B35: 1 | C35: activity | D35: 15 | E35: =C35 -> activity | F35: =IF(B35=0,0,1) -> 1 | G35: =B35*D35*F35 -> 15 | I35: =$G35*H31*J$12 -> 0 | L35: =$G35*K31*M$12 -> 140.4 | O35: =$G35*N31*P$12 -> 146.016 | R35: =$G35*Q31*S$12 -> 101.23776
A37: Staff from outside training site
A38: Transportation (Cotopaxi) | B38: 2 | C38: Individual | D38: =partground -> 9 | E38: /trip | F38: =IF(B38=0,0,1) -> 1 | G38: =B38*D38*F38 -> 18 | I38: =$G38*H31*J$12 -> 0 | L38: =$G38*K31*M$12 -> 168.48 | O38: =$G38*N31*P$12 -> 175.2192 | R38: =$G38*Q31*S$12 -> 121.48531
A39: Ground transportation (Cotopaxi) | B39: 2 | C39: Individual | D39: =partground -> 9 | E39: /day | F39: =IF(B39=0,0,1) -> 1 | G39: =B39*D39*F39 -> 18 | I39: =$G39*H31*J$12 -> 0 | L39: =$G39*K31*M$12 -> 168.48 | O39: =$G39*N31*P$12 -> 175.2192 | R39: =$G39*Q31*S$12 -> 121.48531
A40: Lodging | C40: Individual | D40: =partlodg -> 25 | E40: /day | F40: =IF(B40=0,0,F31) -> 0 | G40: =B40*D40*F40 -> 0 | I40: =$G40*H31*J$12 -> 0 | L40: =$G40*K31*M$12 -> 0 | O40: =$G40*N31*P$12 -> 0 | R40: =$G40*Q31*S$12 -> 0
A41: M&IE (excluding lunch) | B41: 4 | C41: Individual | D41: =partmeals -> 47 | E41: /day | F41: =IF(B41=0,0,F31) -> 1 | G41: =B41*D41*F41 -> 188 | I41: =$G41*H31*J$12 -> 0 | L41: =$G41*K31*M$12 -> 1759.68 | O41: =$G41*N31*P$12 -> 1830.0672 | R41: =$G41*Q31*S$12 -> 1268.8466
A42: Travel Day Lunch | B42: 4 | C42: Individual | D42: =parttransp -> 4 | E42: /trip | F42: 1 | G42: =B42*D42*F42 -> 16 | I42: =$G42*H31*J$12 -> 0 | L42: =$G42*K31*M$12 -> 149.76 | O42: =$G42*N31*P$12 -> 155.7504 | R42: =$G42*Q31*S$12 -> 107.98694
D43: 0 | G43: =B43*D43 -> 0 | I43: =$G43*H31*J$12 -> 0 | L43: =$G43*K31*M$12 -> 0 | O43: =$G43*N31*P$12 -> 0 | R43: =$G43*Q31*S$12 -> 0
A44: ACTIVITY TOTAL | E44: =SUM(G32:G43) -> 555
A46: Activity 1.7 Disseminate successes: | F46: 1 | J46: =SUM(I48:I49) -> 0 | K46: 0 | M46: =SUM(L48:L49) -> 0 | N46: 0 | P46: =SUM(O48:O49) -> 0 | Q46: 1 | S46: =SUM(R48:R49) -> 337.4592 | T46: =SUM(J46,M46,P46,S46,) -> 337.4592
A47: Training/workshop/project activities costs
A48: Local transportation (training site) | B48: 15 | C48: Individual | D48: =parttransp -> 4 | E48: /day | F48: =IF(B48=0,0,F46) -> 1 | G48: =B48*D48*F48 -> 60 | I48: =$G48*H46*J$12 -> 0 | L48: =$G48*K46*M$12 -> 0 | O48: =$G48*N46*P$12 -> 0 | R48: =$G48*Q46*S$12 -> 67.49184
A49: Lunch/coffee breaks | B49: 15 | C49: Individual | D49: =coffee+lunch -> 16 | E49: /day | F49: =IF(B49=0,0,F46) -> 1 | G49: =B49*D49*F49 -> 240 | I49: =$G49*H46*J$12 -> 0 | L49: =$G49*K46*M$12 -> 0 | O49: =$G49*N46*P$12 -> 0 | R49: =$G49*Q46*S$12 -> 269.96736
A50: ACTIVITY TOTAL | E50: =SUM(G47:G49) -> 300
A53: =' Activities Detail'!D117:H117 -> #VALUE! | F53: 3 | J53: =SUM(I55:I58) -> 0 | K53: 3 | M53: =SUM(L55:L58) -> 9204 | N53: 3 | P53: =SUM(O55:O58) -> 9572.16 | Q53: 0 | S53: =SUM(R55:R64) -> 0 | T53: =SUM(J53,M53,P53,S53,) -> 18776.16
A54: Training/workshop/project activities costs
A55: Local transportation (training site) | B55: 20 | C55: Individual | D55: =parttransp -> 4 | E55: /day | F55: =IF(B55=0,0,F53) -> 3 | G55: =B55*D55*F55 -> 240 | I55: =$G55*H53*J$12 -> 0 | L55: =$G55*K53*M$12 -> 748.8 | O55: =$G55*N53*P$12 -> 778.752 | R55: =$G55*Q53*S$12 -> 0
A56: Lunch/coffee breaks | B56: 20 | C56: Individual | D56: =coffee+lunch -> 16 | E56: /day | F56: =IF(B56=0,0,F53) -> 3 | G56: =B56*D56*F56 -> 960 | I56: =$G56*H53*J$12 -> 0 | L56: =$G56*K53*M$12 -> 2995.2 | O56: =$G56*N53*P$12 -> 3115.008 | R56: =$G56*Q53*S$12 -> 0
A57: Materials & Supplies (community fairs/radio spots) | B57: 1 | C57: campaign | D57: 1500 | E57: =C57 -> campaign | F57: =IF(B57=0,0,1) -> 1 | G57: =B57*D57*F57 -> 1500 | I57: =$G57*H53*J$12 -> 0 | L57: =$G57*K53*M$12 -> 4680 | O57: =$G57*N53*P$12 -> 4867.2 | R57: =$G57*Q53*S$12 -> 0
A58: Printing (Photocopies) | B58: 5 | C58: activity | D58: =print -> 50 | E58: =C58 -> activity | F58: =IF(B58=0,0,1) -> 1 | G58: =B58*D58*F58 -> 250 | I58: =$G58*H53*J$12 -> 0 | L58: =$G58*K53*M$12 -> 780 | O58: =$G58*N53*P$12 -> 811.2 | R58: =$G58*Q53*S$12 -> 0
A59: Staff from outside training site
A60: Transportation (Cotopaxi) | B60: 2 | C60: Individual | D60: =partground -> 9 | E60: /trip | F60: =IF(B60=0,0,1) -> 1 | G60: =B60*D60*F60 -> 18 | I60: =$G60*H53*J$12 -> 0 | L60: =$G60*K53*M$12 -> 56.16 | O60: =$G60*N53*P$12 -> 58.4064 | R60: =$G60*Q53*S$12 -> 0
A61: Ground transportation (Cotopaxi) | B61: 2 | C61: Individual | D61: =partground -> 9 | E61: /day | F61: =IF(B61=0,0,1) -> 1 | G61: =B61*D61*F61 -> 18 | I61: =$G61*H53*J$12 -> 0 | L61: =$G61*K53*M$12 -> 56.16 | O61: =$G61*N53*P$12 -> 58.4064 | R61: =$G61*Q53*S$12 -> 0
A62: Lodging | C62: Individual | D62: =partlodg -> 25 | E62: /day | F62: =IF(B62=0,0,F53) -> 0 | G62: =B62*D62*F62 -> 0 | I62: =$G62*H53*J$12 -> 0 | L62: =$G62*K53*M$12 -> 0 | O62: =$G62*N53*P$12 -> 0 | R62: =$G62*Q53*S$12 -> 0
A63: M&IE (excluding lunch) | B63: 4 | C63: Individual | D63: =partmeals -> 47 | E63: /day | F63: =IF(B63=0,0,F53) -> 3 | G63: =B63*D63*F63 -> 564 | I63: =$G63*H53*J$12 -> 0 | L63: =$G63*K53*M$12 -> 1759.68 | O63: =$G63*N53*P$12 -> 1830.0672 | R63: =$G63*Q53*S$12 -> 0
A64: Travel Day Lunch | B64: 4 | C64: Individual | D64: =D63 -> 47 | E64: /trip | F64: 1 | G64: =B64*D64*F64 -> 188 | I64: =$G64*H53*J$12 -> 0 | L64: =$G64*K53*M$12 -> 586.56 | O64: =$G64*N53*P$12 -> 610.0224 | R64: =$G64*Q53*S$12 -> 0
A65: ACTIVITY TOTAL | E65: =SUM(G54:G64) -> 3738
A67: =' Activities Detail'!D131:H131 -> #VALUE! | F67: 2 | J67: =SUM(I69:I71) -> 0 | K67: 0 | M67: =SUM(L69:L71) -> 0 | N67: 0 | P67: =SUM(O69:O71) -> 0 | Q67: 4 | S67: =SUM(R69:R71) -> 3824.5376 | T67: =SUM(J67,M67,P67,S67,) -> 3824.5376
A68: ToT activities costs
A69: Local transportation (training site) | B69: 20 | C69: Individual | D69: =parttransp -> 4 | E69: /day | F69: =IF(B69=0,0,F67) -> 2 | G69: =B69*D69*F69 -> 160 | I69: =$G69*H67*J$12 -> 0 | L69: =$G69*K67*M$12 -> 0 | O69: =$G69*N67*P$12 -> 0 | R69: =$G69*Q67*S$12 -> 719.91296
A70: Lunch/coffee breaks | B70: 20 | C70: Individual | D70: =coffee+lunch -> 16 | E70: /day | F70: =IF(B70=0,0,F67) -> 2 | G70: =B70*D70*F70 -> 640 | I70: =$G70*H67*J$12 -> 0 | L70: =$G70*K67*M$12 -> 0 | O70: =$G70*N67*P$12 -> 0 | R70: =$G70*Q67*S$12 -> 2879.6518
A71: Printing (Photocopies) | B71: 1 | C71: activity | D71: =print -> 50 | E71: =C71 -> activity | F71: =IF(B71=0,0,1) -> 1 | G71: =B71*D71*F71 -> 50 | I71: =$G71*H67*J$12 -> 0 | L71: =$G71*K67*M$12 -> 0 | O71: =$G71*N67*P$12 -> 0 | R71: =$G71*Q67*S$12 -> 224.9728
A72: ACTIVITY TOTAL | E72: =SUM(G68:G71) -> 850
A75: =' Activities Detail'!D140:H140 -> #VALUE! | F75: 1 | H75: 0 | J75: =SUM(I77:I79) -> 0 | K75: 4 | M75: =SUM(L77:L79) -> 1726.4 | N75: 12 | P75: =SUM(O77:O79) -> 5386.368 | Q75: 4 | S75: =SUM(R77:R79) -> 1867.2742 | T75: =SUM(J75,M75,P75,S75,) -> 8980.0422
A76: Training/workshop/project activities costs
A77: Local transportation (training site) | B77: 20 | C77: Individual | D77: =parttransp -> 4 | E77: /day | F77: =IF(B77=0,0,F75) -> 1 | G77: =B77*D77*F77 -> 80 | I77: =$G77*H75*J$12 -> 0 | L77: =$G77*K75*M$12 -> 332.8 | O77: =$G77*N75*P$12 -> 1038.336 | R77: =$G77*Q75*S$12 -> 359.95648
A78: Lunch/coffee breaks | B78: 20 | C78: Individual | D78: =coffee+lunch -> 16 | E78: /day | F78: =IF(B78=0,0,F75) -> 1 | G78: =B78*D78*F78 -> 320 | I78: =$G78*H75*J$12 -> 0 | L78: =$G78*K75*M$12 -> 1331.2 | O78: =$G78*N75*P$12 -> 4153.344 | R78: =$G78*Q75*S$12 -> 1439.8259
A79: Printing (Photocopies) | B79: 1 | C79: activity | D79: 15 | E79: =C79 -> activity | F79: =IF(B79=0,0,1) -> 1 | G79: =B79*D79*F79 -> 15 | I79: =$G79*H75*J$12 -> 0 | L79: =$G79*K75*M$12 -> 62.4 | O79: =$G79*N75*P$12 -> 194.688 | R79: =$G79*Q75*S$12 -> 67.49184
A80: ACTIVITY TOTAL | E80: =SUM(G76:G79) -> 415
A83: =' Activities Detail'!D149:H149 -> #VALUE! | F83: 2 | J83: =SUM(I85:I88) -> 0 | K83: 6 | M83: =SUM(L85:L88) -> 5304 | N83: 6 | P83: =SUM(O85:O88) -> 5516.16 | Q83: 0 | S83: =SUM(R85:R88) -> 0 | T83: =SUM(J83,M83,P83,S83,) -> 10820.16
A84: Training/workshop/project activities costs
A85: Local transportation (training site) | B85: 20 | C85: Individual | D85: =parttransp -> 4 | E85: /day | F85: =IF(B85=0,0,F83) -> 2 | G85: =B85*D85*F85 -> 160 | I85: =$G85*H83*J$12 -> 0 | L85: =$G85*K83*M$12 -> 998.4 | O85: =$G85*N83*P$12 -> 1038.336 | R85: =$G85*Q83*S$12 -> 0
A86: Lunch/coffee breaks | B86: 20 | C86: Individual | D86: =coffee+lunch -> 16 | E86: /day | F86: =IF(B86=0,0,F83) -> 2 | G86: =B86*D86*F86 -> 640 | I86: =$G86*H83*J$12 -> 0 | L86: =$G86*K83*M$12 -> 3993.6 | O86: =$G86*N83*P$12 -> 4153.344 | R86: =$G86*Q83*S$12 -> 0
A87: Printing (Photocopies) | B87: 1 | C87: activity | D87: =print -> 50 | E87: =C87 -> activity | F87: =IF(B87=0,0,1) -> 1 | G87: =B87*D87*F87 -> 50 | I87: =$G87*H83*J$12 -> 0 | L87: =$G87*K83*M$12 -> 312 | O87: =$G87*N83*P$12 -> 324.48 | R87: =$G87*Q83*S$12 -> 0
A89: ACTIVITY TOTAL | E89: =SUM(G84:G88) -> 850
A91: =' Activities Detail'!D182:H182 -> #VALUE! | F91: 1 | J91: =SUM(I93:I95) -> 0 | K91: 0 | M91: =SUM(L93:L95) -> 0 | N91: 2 | P91: =SUM(O93:O95) -> 973.44 | Q91: 2 | S91: =SUM(R93:R95) -> 1012.3776 | T91: =SUM(J91,M91,P91,S91,) -> 1985.8176
A92: Training/workshop/project activities costs
A93: Local transportation (training site) | B93: 20 | C93: Individual | D93: =parttransp -> 4 | E93: /day | F93: =IF(B93=0,0,F91) -> 1 | G93: =B93*D93*F93 -> 80 | I93: =$G93*H91*J$12 -> 0 | L93: =$G93*K91*M$12 -> 0 | O93: =$G93*N91*P$12 -> 173.056 | R93: =$G93*Q91*S$12 -> 179.97824
A94: Lunch/coffee breaks | B94: 20 | C94: Individual | D94: =coffee+lunch -> 16 | E94: /day | F94: =IF(B94=0,0,F91) -> 1 | G94: =B94*D94*F94 -> 320 | I94: =$G94*H91*J$12 -> 0 | L94: =$G94*K91*M$12 -> 0 | O94: =$G94*N91*P$12 -> 692.224 | R94: =$G94*Q91*S$12 -> 719.91296
A95: Printing (Photocopies) | B95: 1 | C95: activity | D95: =print -> 50 | E95: =C95 -> activity | F95: =IF(B95=0,0,1) -> 1 | G95: =B95*D95*F95 -> 50 | I95: =$G95*H91*J$12 -> 0 | L95: =$G95*K91*M$12 -> 0 | O95: =$G95*N91*P$12 -> 108.16 | R95: =$G95*Q91*S$12 -> 112.4864
A96: Staff from outside training site
A97: Transportation (Cotopaxi) | B97: 2 | C97: Individual | D97: =partground -> 9 | E97: /trip | F97: =IF(B97=0,0,1) -> 1 | G97: =B97*D97*F97 -> 18 | I97: =$G97*H91*J$12 -> 0 | L97: =$G97*K91*M$12 -> 0 | O97: =$G97*$N$91*P$12 -> 38.9376 | R97: =$G97*$Q$91*S$12 -> 40.495104
A98: Ground transportation (Cotopaxi) | B98: 2 | C98: Individual | D98: =partground -> 9 | E98: /day | F98: =IF(B98=0,0,1) -> 1 | G98: =B98*D98*F98 -> 18 | I98: =$G98*H91*J$12 -> 0 | L98: =$G98*K91*M$12 -> 0 | O98: =$G98*$N$91*P$12 -> 38.9376 | R98: =$G98*$Q$91*S$12 -> 40.495104
A99: Lodging | C99: Individual | D99: =partlodg -> 25 | E99: /day | F99: =IF(B99=0,0,F91) -> 0 | G99: =B99*D99*F99 -> 0 | I99: =$G99*H91*J$12 -> 0 | L99: =$G99*K91*M$12 -> 0 | O99: =$G99*$N$91*P$12 -> 0 | R99: =$G99*$Q$91*S$12 -> 0
A100: M&IE (excluding lunch) | B100: 4 | C100: Individual | D100: =partmeals -> 47 | E100: /day | F100: =IF(B100=0,0,F91) -> 1 | G100: =B100*D100*F100 -> 188 | I100: =$G100*H91*J$12 -> 0 | L100: =$G100*K91*M$12 -> 0 | O100: =$G100*$N$91*P$12 -> 406.6816 | R100: =$G100*$Q$91*S$12 -> 422.94886
A101: Travel Day Lunch | B101: 4 | C101: Individual | D101: =parttransp -> 4 | E101: /trip | F101: 1 | G101: =B101*D101*F101 -> 16 | I101: =$G101*H91*J$12 -> 0 | L101: =$G101*K91*M$12 -> 0 | O101: =$G101*$N$91*P$12 -> 34.6112 | R101: =$G101*$Q$91*S$12 -> 35.995648
A102: ACTIVITY TOTAL | E102: =SUM(G92:G101) -> 690
A104: =' Activities Detail'!D201:H201 -> #VALUE! | F104: 1 | J104: =SUM(I106:I108) -> 0 | K104: 0 | M104: =SUM(L106:L108) -> 0 | N104: 4 | P104: =SUM(O106:O108) -> 1946.88 | Q104: 4 | S104: =SUM(R106:R108) -> 2024.7552 | T104: =SUM(J104,M104,P104,S104,) -> 3971.6352
A105: Training/workshop/project activities costs
A106: Local transportation (training site) | B106: 20 | C106: Individual | D106: =parttransp -> 4 | E106: /day | F106: =IF(B106=0,0,F104) -> 1 | G106: =B106*D106*F106 -> 80 | I106: =$G106*H104*J$12 -> 0 | L106: =$G106*K104*M$12 -> 0 | O106: =$G106*N104*P$12 -> 346.112 | R106: =$G106*Q104*S$12 -> 359.95648
A107: Lunch/coffee breaks | B107: 20 | C107: Individual | D107: =coffee+lunch -> 16 | E107: /day | F107: =IF(B107=0,0,F104) -> 1 | G107: =B107*D107*F107 -> 320 | I107: =$G107*H104*J$12 -> 0 | L107: =$G107*K104*M$12 -> 0 | O107: =$G107*N104*P$12 -> 1384.448 | R107: =$G107*Q104*S$12 -> 1439.8259
A108: Printing (Photocopies) | B108: 1 | C108: activity | D108: =print -> 50 | E108: =C108 -> activity | F108: =IF(B108=0,0,1) -> 1 | G108: =B108*D108*F108 -> 50 | I108: =$G108*H104*J$12 -> 0 | L108: =$G108*K104*M$12 -> 0 | O108: =$G108*N104*P$12 -> 216.32 | R108: =$G108*Q104*S$12 -> 224.9728
A109: Trainees from outside training site
A110: Transportation (training city) | B110: 2 | C110: Individual | D110: =partground -> 9 | E110: /trip | F110: =IF(B110=0,0,1) -> 1 | G110: =B110*D110*F110 -> 18 | I110: =$G110*H104*J$12 -> 0 | L110: =$G110*K104*M$12 -> 0 | O110: =$G110*$N$104*P$12 -> 77.8752 | R110: =$G110*$Q$104*S$12 -> 80.990208
A111: Ground transportation (training city) | B111: 2 | C111: Individual | D111: =partground -> 9 | E111: /day | F111: =IF(B111=0,0,1) -> 1 | G111: =B111*D111*F111 -> 18 | I111: =$G111*H104*J$12 -> 0 | L111: =$G111*K104*M$12 -> 0 | O111: =$G111*$N$104*P$12 -> 77.8752 | R111: =$G111*$Q$104*S$12 -> 80.990208
A112: Lodging | B112: =B110+B111 -> 4 | C112: Individual | D112: =partlodg -> 25 | E112: /day | F112: =IF(B112=0,0,F104) -> 1 | G112: =B112*D112*F112 -> 100 | I112: =$G112*H104*J$12 -> 0 | L112: =$G112*K104*M$12 -> 0 | O112: =$G112*$N$104*P$12 -> 432.64 | R112: =$G112*$Q$104*S$12 -> 449.9456
A113: M&IE (excluding lunch) | B113: =B112 -> 4 | C113: Individual | D113: =partmeals -> 47 | E113: /day | F113: =IF(B113=0,0,F104) -> 1 | G113: =B113*D113*F113 -> 188 | I113: =$G113*H104*J$12 -> 0 | L113: =$G113*K104*M$12 -> 0 | O113: =$G113*$N$104*P$12 -> 813.3632 | R113: =$G113*$Q$104*S$12 -> 845.89773
A114: Travel Day Lunch | B114: =B113 -> 4 | C114: Individual | D114: =parttransp -> 4 | E114: /trip | F114: 1 | G114: =B114*D114*F114 -> 16 | I114: =$G114*H104*J$12 -> 0 | L114: =$G114*K104*M$12 -> 0 | O114: =$G114*$N$104*P$12 -> 69.2224 | R114: =$G114*$Q$104*S$12 -> 71.991296
A115: ACTIVITY TOTAL | E115: =SUM(G105:G114) -> 790
A118: =' Activities Detail'!D222:H222 -> #VALUE! | F118: 2 | J118: =SUM(I120:I126) -> 0 | K118: 6 | M118: 302 | N118: 0 | P118: =SUM(O120:O126) -> 0 | Q118: 0 | S118: =SUM(R120:R126) -> 0 | T118: =SUM(J118,M118,P118,S118,) -> 302
A119: Training/workshop/project activities costs | L119: =302/6 -> 50.333333
A121: Staff from outside training site | G121: =B121*D121*F121 -> 0 | I121: =$G121*H118*J$12 -> 0 | L121: =$G121*1*M$12 -> 0 | O121: =$G121*N118*P$12 -> 0 | R121: =$G121*Q118*S$12 -> 0
A122: Transportation (Cotopaxi) | B122: 1 | C122: Individual | D122: =partground -> 9 | E122: /trip | F122: 2 | G122: =B122*D122*F122 -> 18 | I122: =$G122*H118*J$12 -> 0 | L122: =$G122*1*M$12 -> 18.72 | O122: =$G122*N118*P$12 -> 0 | R122: =$G122*Q118*S$12 -> 0
A123: Ground transportation (Cotopaxi) | B123: 1 | C123: Individual | D123: =partground -> 9 | E123: /day | F123: 2 | G123: =B123*D123*F123 -> 18 | I123: =$G123*H118*J$12 -> 0 | L123: =$G123*1*M$12 -> 18.72 | O123: =$G123*N118*P$12 -> 0 | R123: =$G123*Q118*S$12 -> 0
...

Sheet Travel
A1: Travel Budget
A2: YEAR 1
A3: Position Traveling | B3: From-To | C3: Activity/ Purpose | D3: # of Trips/YR | E3: Transport (Int'l/trip) | F3: Total Transport | G3: # of Days/Trip | H3: M&IE Rate | I3: Total M&IE | J3: Lodging Rate (Int'l) | K3: Total Lodging | L3: Ground Transfers | M3: Travel Other | N3: Total
A4: International Travel
A5: M&E Officer | B5: ex. Washington, DC to San Jose, Costa Rica | C5: ex. Monitoring & Evaluation | D5: 1 | E5: 1200 | F5: =D5*E5 -> 1200 | G5: 5 | H5: 126 | I5: =G5*H5 -> 630 | J5: 147 | K5: =G5*J5 -> 735 | L5: 50 | M5: 30 | N5: =SUM(F5,I5,K5,L5,M5) -> 2645
F6: =D6*E6 -> 0 | I6: =G6*H6 -> 0 | K6: =G6*J6 -> 0 | N6: =SUM(F6,I6,K6,L6,M6) -> 0
A7: Domestic Travel
A8: M&E Officer | B8: Quito to El Oro | F8: =D8*E8 -> 0 | I8: =G8*H8 -> 0 | K8: =G8*J8 -> 0 | N8: =SUM(F8,I8,K8,L8,M8) -> 0
A9: Project Director | B9: Quito to El Oro | F9: =D9*E9 -> 0 | I9: =G9*H9 -> 0 | K9: =G9*J9 -> 0 | N9: =SUM(F9,I9,K9,L9,M9) -> 0
A10: M&E Officer | B10: Quito to Cotopaxi | F10: =D10*E10 -> 0 | I10: =G10*H10 -> 0 | K10: =G10*J10 -> 0 | N10: =SUM(F10,I10,K10,L10,M10) -> 0
A11: Project Director | B11: Quito to Cotopaxi | F11: =D11*E11 -> 0 | I11: =G11*H11 -> 0 | K11: =G11*J11 -> 0 | N11: =SUM(F11,I11,K11,L11,M11) -> 0
A12: Total Year 1 | F12: =SUM(F5:F6,F8) -> 1200 | I12: =SUM(I5:I6,I8) -> 630 | K12: =SUM(K5:K6,K8) -> 735 | N12: =SUM(N5:N6,N8) -> 2645
A13: YEAR 2
A14: Position Traveling | B14: To-From | C14: Activity/ Purpose | D14: # of Trips/YR | E14: Transport (Int'l/trip) | F14: Total Transport $ | G14: # of Days/Trip | H14: M&IE Rate | I14: Total M&IE | J14: Lodging Rate (Int'l) | K14: Total Lodging | L14: Ground Transfers | M14: Travel Other | N14: Total
A15: International Travel
F16: =D16*E16 -> 0 | I16: =G16*H16 -> 0 | K16: =G16*J16 -> 0 | N16: =SUM(F16,I16,K16,L16,M16) -> 0
F17: =D17*E17 -> 0 | I17: =G17*H17 -> 0 | K17: =G17*J17 -> 0 | N17: =SUM(F17,I17,K17,L17,M17) -> 0
A18: Domestic Travel
F19: =D19*E19 -> 0 | I19: =G19*H19 -> 0 | K19: =G19*J19 -> 0 | N19: =SUM(F19,I19,K19,L19,M19) -> 0
A20: Total Year 2 | F20: =SUM(F16:F17,F19) -> 0 | I20: =SUM(I16:I17,I19) -> 0 | K20: =SUM(K16:K17,K19) -> 0 | N20: =SUM(N16:N17,N19) -> 0
A21: YEAR 3
A22: Position Traveling | B22: To-From | C22: Activity/ Purpose | D22: # of Trips/YR | E22: Transport (Int'l/trip) | F22: Total Transport $ | G22: # of Days/Trip | H22: M&IE Rate | I22: Total M&IE | J22: Lodging Rate (Int'l) | K22: Total Lodging | L22: Ground Transfers | M22: Travel Other | N22: Total
A23: International Travel
F24: =D24*E24 -> 0 | I24: =G24*H24 -> 0 | K24: =G24*J24 -> 0 | N24: =SUM(F24,I24,K24,L24,M24) -> 0
F25: =D25*E25 -> 0 | I25: =G25*H25 -> 0 | K25: =G25*J25 -> 0 | N25: =SUM(F25,I25,K25,L25,M25) -> 0
A26: Domestic Travel
F27: =D27*E27 -> 0 | I27: =G27*H27 -> 0 | K27: =G27*J27 -> 0 | N27: =SUM(F27,I27,K27,L27,M27) -> 0
A28: Total Year 3 | F28: =SUM(F24:F25,F27) -> 0 | I28: =SUM(I24:I25,I27) -> 0 | K28: =SUM(K24:K25,K27) -> 0 | N28: =SUM(N24:N25,N27) -> 0
A29: YEAR 4
A30: Position Traveling | B30: To-From | C30: Activity/ Purpose | D30: # of Trips/YR | E30: Transport (Int'l/trip) | F30: Total Transport $ | G30: # of Days/Trip | H30: M&IE Rate | I30: Total M&IE | J30: Lodging Rate (Int'l) | K30: Total Lodging | L30: Ground Transfers | M30: Travel Other | N30: Total
A31: International Travel
F32: =D32*E32 -> 0 | I32: =G32*H32 -> 0 | K32: =G32*J32 -> 0 | N32: =SUM(F32,I32,K32,L32,M32) -> 0
F33: =D33*E33 -> 0 | I33: =G33*H33 -> 0 | K33: =G33*J33 -> 0 | N33: =SUM(F33,I33,K33,L33,M33) -> 0
F34: =D34*E34 -> 0 | I34: =G34*H34 -> 0 | K34: =G34*J34 -> 0 | N34: =SUM(F34,I34,K34,L34,M34) -> 0
A35: Domestic Travel
F36: =D36*E36 -> 0 | I36: =G36*H36 -> 0 | K36: =G36*J36 -> 0 | N36: =SUM(F36,I36,K36,L36,M36) -> 0
A37: Total Year 4 | F37: =SUM(F32:F34,F36) -> 0 | I37: =SUM(I32:I34,I36) -> 0 | K37: =SUM(K32:K34,K36) -> 0 | N37: =SUM(N32:N34,N36) -> 0
A38: TOTAL ALL YEARS | F38: =SUM(F12,F20,F28,F37) -> 1200 | I38: =SUM(I12,I20,I28,I37) -> 630 | K38: =SUM(K12,K20,K28,K37) -> 735 | N38: =SUM(N12,N20,N28,N37) -> 2645

Sheet HO LOE
A1: =Assumptions!$B$4 -> Partners of America
A2: =CONCATENATE(Assumptions!$B5," ",Assumptions!$C5) -> DONOR: USDOL
A3: =CONCATENATE(Assumptions!$B6," ",Assumptions!$C6) -> Country: Ecuador
A4: =CONCATENATE(Assumptions!$B7," ",Assumptions!$C7) -> Program Name: Project to Improve Adherence to International Labor Standards in the Agricultural Sector in Ecuador
A5: =CONCATENATE(Assumptions!$B8," ",Assumptions!$C8) -> Grant Number: FOA-ILAB-23-28
A7: HOME OFFICE SUPPORT
A9: Position | B9: Name | C9: Current Annual Salary | D9: Projected Annual Salary | E9: =#REF! -> #REF! | H9: =#REF! -> #REF! | K9: =#REF! -> #REF! | N9: =#REF! -> #REF! | Q9: =#REF! -> #REF! | T9: =#REF! -> #REF! | W9: =#REF! -> #REF! | Z9: =#REF! -> #REF! | AC9: =#REF! -> #REF! | AF9: =#REF! -> #REF! | AI9: Total
E10: LOE % | F10: Amount | G10: Number of Days | H10: LOE % | I10: Amount | J10: Number of Days | K10: LOE % | L10: Amount | M10: Number of Days | N10: LOE % | O10: Amount | P10: Number of Days | Q10: LOE % | R10: Amount | S10: Number of Days | T10: LOE % | U10: Amount | V10: Number of Days | W10: LOE % | X10: Amount | Y10: Number of Days | Z10: LOE % | AA10: Amount | AB10: Number of Days | AC10: LOE % | AD10: Amount | AE10: Number of Days | AF10: LOE % | AG10: Amount | AH10: Number of Days | AI10: LOE % | AJ10: Amount | AK10: Number of Days
B11: Escalation Rate | D11: 1.04 | F11: =Assumptions!S33 -> 1.01 | I11: =F11*(1+#REF!) -> #REF! | L11: =I11*(1+#REF!) -> #REF! | O11: =L11*(1+#REF!) -> #REF! | R11: =O11*(1+#REF!) -> #REF! | U11: =R11*(1+#REF!) -> #REF! | X11: =U11*(1+#REF!) -> #REF! | AA11: =X11*(1+#REF!) -> #REF! | AD11: =AA11*(1+#REF!) -> #REF! | AG11: =AD11*(1+#REF!) -> #REF!
A12: Program Management
A14: Position | B14: Name | C14: Current Monthly Salary | D14: Projected Monthly Salary | E14: LOE % | F14: Total | G14: Number of Days | T14: LOE % | U14: Total | V14: Number of Days
A16: GPO Director | D16: 100000 | E16: 0.1 | F16: =E16*D16*F$11 -> 10100 | G16: =E16*260 -> 26 | H16: 0 | I16: =H16*$D16*I$11 -> #REF! | J16: =H16*260 -> 0 | K16: 0 | L16: =K16*$D16*L$11 -> #REF! | M16: =K16*260 -> 0 | N16: 0 | O16: =N16*$D16*O$11 -> #REF! | P16: =N16*260 -> 0 | Q16: 0 | R16: =Q16*$D16*R$11 -> #REF! | S16: =Q16*260 -> 0 | T16: 0 | U16: =T16*S16*U$11 -> #REF! | V16: =T16*260 -> 0 | W16: 0 | X16: =W16*$D16*X$11 -> #REF! | Y16: =W16*260 -> 0 | Z16: 0 | AA16: =Z16*$D16*AA$11 -> #REF! | AB16: =Z16*260 -> 0 | AC16: 0.05 | AD16: =AC16*$D16*AD$11 -> #REF! | AE16: =AC16*260 -> 13 | AF16: 0 | AG16: =AF16*$D16*AG$11 -> #REF! | AH16: =AF16*260 -> 0 | AI16: =SUM(E16,H16,K16,N16,Q16,T16,W16,Z16,AC16,AF16) -> 0.15 | AJ16: =SUM(F16,I16,L16,O16,R16,U16,X16,AA16,AD16,AG16) -> #REF! | AK16: =SUM(G16,J16,M16,P16,S16,V16,Y16,AB16,AE16,AH16) -> 39
A17: Associate GPO Director | D17: 100000 | E17: 0.1 | F17: =E17*D17*F$11 -> 10100 | G17: =E17*260 -> 26 | H17: 0 | I17: =H17*$D17*I$11 -> #REF! | J17: =H17*260 -> 0 | K17: 0 | L17: =K17*$D17*L$11 -> #REF! | M17: =K17*260 -> 0 | N17: 0 | O17: =N17*$D17*O$11 -> #REF! | P17: =N17*260 -> 0 | Q17: 0 | R17: =Q17*$D17*R$11 -> #REF! | S17: =Q17*260 -> 0 | T17: 0 | U17: =T17*S17*U$11 -> #REF! | V17: =T17*260 -> 0 | W17: 0 | X17: =W17*$D17*X$11 -> #REF! | Y17: =W17*260 -> 0 | Z17: 0 | AA17: =Z17*$D17*AA$11 -> #REF! | AB17: =Z17*260 -> 0 | AC17: 0 | AD17: =AC17*$D17*AD$11 -> #REF! | AE17: =AC17*260 -> 0 | AF17: 0 | AG17: =AF17*$D17*AG$11 -> #REF! | AH17: =AF17*260 -> 0 | AI17: =SUM(E17,H17,K17,N17,Q17,T17,W17,Z17,AC17,AF17) -> 0.1 | AJ17: =SUM(F17,I17,L17,O17,R17,U17,X17,AA17,AD17,AG17) -> #REF! | AK17: =SUM(G17,J17,M17,P17,S17,V17,Y17,AB17,AE17,AH17) -> 26
A18: Regional Team Leader | D18: 100000 | E18: 0.1 | F18: =E18*D18*F$11 -> 10100 | G18: =E18*260 -> 26 | H18: 0 | I18: =H18*$D18*I$11 -> #REF! | J18: =H18*260 -> 0 | K18: 0 | L18: =K18*$D18*L$11 -> #REF! | M18: =K18*260 -> 0 | N18: 0 | O18: =N18*$D18*O$11 -> #REF! | P18: =N18*260 -> 0 | Q18: 0 | R18: =Q18*$D18*R$11 -> #REF! | S18: =Q18*260 -> 0 | T18: 0 | U18: =T18*S18*U$11 -> #REF! | V18: =T18*260 -> 0 | W18: 0 | X18: =W18*$D18*X$11 -> #REF! | Y18: =W18*260 -> 0 | Z18: 0.05 | AA18: =Z18*$D18*AA$11 -> #REF! | AB18: =Z18*260 -> 13 | AC18: 0 | AD18: =AC18*$D18*AD$11 -> #REF! | AE18: =AC18*260 -> 0 | AF18: 0.05 | AG18: =AF18*$D18*AG$11 -> #REF! | AH18: =AF18*260 -> 13 | AI18: =SUM(E18,H18,K18,N18,Q18,T18,W18,Z18,AC18,AF18) -> 0.2 | AJ18: =SUM(F18,I18,L18,O18,R18,U18,X18,AA18,AD18,AG18) -> #REF! | AK18: =SUM(G18,J18,M18,P18,S18,V18,Y18,AB18,AE18,AH18) -> 52
A19: Program Officer | D19: 100000 | E19: 0.1 | F19: =E19*D19*F$11 -> 10100 | G19: =E19*260 -> 26 | H19: 0 | I19: =H19*$D19*I$11 -> #REF! | J19: =H19*260 -> 0 | K19: 0 | L19: =K19*$D19*L$11 -> #REF! | M19: =K19*260 -> 0 | N19: 0 | O19: =N19*$D19*O$11 -> #REF! | P19: =N19*260 -> 0 | Q19: 0 | R19: =Q19*$D19*R$11 -> #REF! | S19: =Q19*260 -> 0 | T19: 0 | U19: =T19*S19*U$11 -> #REF! | V19: =T19*260 -> 0 | W19: 0 | X19: =W19*$D19*X$11 -> #REF! | Y19: =W19*260 -> 0 | Z19: 0 | AA19: =Z19*$D19*AA$11 -> #REF! | AB19: =Z19*260 -> 0 | AC19: 0 | AD19: =AC19*$D19*AD$11 -> #REF! | AE19: =AC19*260 -> 0 | AF19: 0 | AG19: =AF19*$D19*AG$11 -> #REF! | AH19: =AF19*260 -> 0 | AI19: =SUM(E19,H19,K19,N19,Q19,T19,W19,Z19,AC19,AF19) -> 0.1 | AJ19: =SUM(F19,I19,L19,O19,R19,U19,X19,AA19,AD19,AG19) -> #REF! | AK19: =SUM(G19,J19,M19,P19,S19,V19,Y19,AB19,AE19,AH19) -> 26
A20: Program Coordinator | D20: 100000 | E20: 0.1 | F20: =E20*D20*F$11 -> 10100 | G20: =E20*260 -> 26 | H20: 0 | I20: =H20*$D20*I$11 -> #REF! | J20: =H20*260 -> 0 | K20: 0 | L20: =K20*$D20*L$11 -> #REF! | M20: =K20*260 -> 0 | N20: 0 | O20: =N20*$D20*O$11 -> #REF! | P20: =N20*260 -> 0 | Q20: 0 | R20: =Q20*$D20*R$11 -> #REF! | S20: =Q20*260 -> 0 | T20: 0 | U20: =T20*S20*U$11 -> #REF! | V20: =T20*260 -> 0 | W20: 0 | X20: =W20*$D20*X$11 -> #REF! | Y20: =W20*260 -> 0 | Z20: 0 | AA20: =Z20*$D20*AA$11 -> #REF! | AB20: =Z20*260 -> 0 | AC20: 0 | AD20: =AC20*$D20*AD$11 -> #REF! | AE20: =AC20*260 -> 0 | AF20: 0 | AG20: =AF20*$D20*AG$11 -> #REF! | AH20: =AF20*260 -> 0 | AI20: =SUM(E20,H20,K20,N20,Q20,T20,W20,Z20,AC20,AF20) -> 0.1 | AJ20: =SUM(F20,I20,L20,O20,R20,U20,X20,AA20,AD20,AG20) -> #REF! | AK20: =SUM(G20,J20,M20,P20,S20,V20,Y20,AB20,AE20,AH20) -> 26
A21: M&E | D21: 100000 | E21: 0.1 | F21: =E21*D21*F$11 -> 10100 | G21: =E21*260 -> 26 | H21: 0 | I21: =H21*$D21*I$11 -> #REF! | J21: =H21*260 -> 0 | K21: 0 | L21: =K21*$D21*L$11 -> #REF! | M21: =K21*260 -> 0 | N21: 0 | O21: =N21*$D21*O$11 -> #REF! | P21: =N21*260 -> 0 | Q21: 0 | R21: =Q21*$D21*R$11 -> #REF! | S21: =Q21*260 -> 0 | T21: 0 | U21: =T21*S21*U$11 -> #REF! | V21: =T21*260 -> 0 | W21: 0 | X21: =W21*$D21*X$11 -> #REF! | Y21: =W21*260 -> 0 | Z21: 0 | AA21: =Z21*$D21*AA$11 -> #REF! | AB21: =Z21*260 -> 0 | AC21: 0 | AD21: =AC21*$D21*AD$11 -> #REF! | AE21: =AC21*260 -> 0 | AF21: 0 | AG21: =AF21*$D21*AG$11 -> #REF! | AH21: =AF21*260 -> 0 | AI21: =SUM(E21,H21,K21,N21,Q21,T21,W21,Z21,AC21,AF21) -> 0.1 | AJ21: =SUM(F21,I21,L21,O21,R21,U21,X21,AA21,AD21,AG21) -> #REF! | AK21: =SUM(G21,J21,M21,P21,S21,V21,Y21,AB21,AE21,AH21) -> 26
A22: M&E | D22: 100000 | E22: 0.1 | F22: =E22*D22*F$11 -> 10100 | G22: =E22*260 -> 26 | H22: 0 | I22: =H22*$D22*I$11 -> #REF! | J22: =H22*260 -> 0 | K22: 0 | L22: =K22*$D22*L$11 -> #REF! | M22: =K22*260 -> 0 | N22: 0 | O22: =N22*$D22*O$11 -> #REF! | P22: =N22*260 -> 0 | Q22: 0 | R22: =Q22*$D22*R$11 -> #REF! | S22: =Q22*260 -> 0 | T22: 0 | U22: =T22*S22*U$11 -> #REF! | V22: =T22*260 -> 0 | W22: 0 | X22: =W22*$D22*X$11 -> #REF! | Y22: =W22*260 -> 0 | Z22: 0 | AA22: =Z22*$D22*AA$11 -> #REF! | AB22: =Z22*260 -> 0 | AC22: 0 | AD22: =AC22*$D22*AD$11 -> #REF! | AE22: =AC22*260 -> 0 | AF22: 0 | AG22: =AF22*$D22*AG$11 -> #REF! | AH22: =AF22*260 -> 0 | AI22: =SUM(E22,H22,K22,N22,Q22,T22,W22,Z22,AC22,AF22) -> 0.1 | AJ22: =SUM(F22,I22,L22,O22,R22,U22,X22,AA22,AD22,AG22) -> #REF! | AK22: =SUM(G22,J22,M22,P22,S22,V22,Y22,AB22,AE22,AH22) -> 26
A23: Pubs
A24: Senior Graphic Designer | D24: 100000 | E24: 0.1 | F24: =E24*D24*F$11 -> 10100 | G24: =E24*260 -> 26 | H24: 0 | I24: =H24*$D24*I$11 -> #REF! | J24: =H24*260 -> 0 | K24: 0 | L24: =K24*$D24*L$11 -> #REF! | M24: =K24*260 -> 0 | N24: 0 | O24: =N24*$D24*O$11 -> #REF! | P24: =N24*260 -> 0 | Q24: 0 | R24: =Q24*$D24*R$11 -> #REF! | S24: =Q24*260 -> 0 | T24: 0 | U24: =T24*S24*U$11 -> #REF! | V24: =T24*260 -> 0 | W24: 0.05 | X24: =W24*$D24*X$11 -> #REF! | Y24: =W24*260 -> 13 | Z24: 0 | AA24: =Z24*$D24*AA$11 -> #REF! | AB24: =Z24*260 -> 0 | AC24: 0 | AD24: =AC24*$D24*AD$11 -> #REF! | AE24: =AC24*260 -> 0 | AF24: 0 | AG24: =AF24*$D24*AG$11 -> #REF! | AH24: =AF24*260 -> 0 | AI24: =SUM(E24,H24,K24,N24,Q24,T24,W24,Z24,AC24,AF24) -> 0.15 | AJ24: =SUM(F24,I24,L24,O24,R24,U24,X24,AA24,AD24,AG24) -> #REF! | AK24: =SUM(G24,J24,M24,P24,S24,V24,Y24,AB24,AE24,AH24) -> 39
A25: Editor | D25: 100000 | E25: 0.1 | F25: =E25*D25*F$11 -> 10100 | G25: =E25*260 -> 26 | H25: 0 | I25: =H25*$D25*I$11 -> #REF! | J25: =H25*260 -> 0 | K25: 0 | L25: =K25*$D25*L$11 -> #REF! | M25: =K25*260 -> 0 | N25: 0 | O25: =N25*$D25*O$11 -> #REF! | P25: =N25*260 -> 0 | Q25: 0 | R25: =Q25*$D25*R$11 -> #REF! | S25: =Q25*260 -> 0 | T25: 0 | U25: =T25*S25*U$11 -> #REF! | V25: =T25*260 -> 0 | W25: 0 | X25: =W25*$D25*X$11 -> #REF! | Y25: =W25*260 -> 0 | Z25: 0.05 | AA25: =Z25*$D25*AA$11 -> #REF! | AB25: =Z25*260 -> 13 | AC25: 0 | AD25: =AC25*$D25*AD$11 -> #REF! | AE25: =AC25*260 -> 0 | AF25: 0 | AG25: =AF25*$D25*AG$11 -> #REF! | AH25: =AF25*260 -> 0 | AI25: =SUM(E25,H25,K25,N25,Q25,T25,W25,Z25,AC25,AF25) -> 0.15 | AJ25: =SUM(F25,I25,L25,O25,R25,U25,X25,AA25,AD25,AG25) -> #REF! | AK25: =SUM(G25,J25,M25,P25,S25,V25,Y25,AB25,AE25,AH25) -> 39
A26: Translator | D26: 100000 | E26: 0.1 | F26: =E26*D26*F$11 -> 10100 | G26: =E26*260 -> 26 | H26: 0 | I26: =H26*$D26*I$11 -> #REF! | J26: =H26*260 -> 0 | K26: 0 | L26: =K26*$D26*L$11 -> #REF! | M26: =K26*260 -> 0 | N26: 0 | O26: =N26*$D26*O$11 -> #REF! | P26: =N26*260 -> 0 | Q26: 0 | R26: =Q26*$D26*R$11 -> #REF! | S26: =Q26*260 -> 0 | T26: 0 | U26: =T26*S26*U$11 -> #REF! | V26: =T26*260 -> 0 | W26: 0 | X26: =W26*$D26*X$11 -> #REF! | Y26: =W26*260 -> 0 | Z26: 0 | AA26: =Z26*$D26*AA$11 -> #REF! | AB26: =Z26*260 -> 0 | AC26: 0 | AD26: =AC26*$D26*AD$11 -> #REF! | AE26: =AC26*260 -> 0 | AF26: 0 | AG26: =AF26*$D26*AG$11 -> #REF! | AH26: =AF26*260 -> 0 | AI26: =SUM(E26,H26,K26,N26,Q26,T26,W26,Z26,AC26,AF26) -> 0.1 | AJ26: =SUM(F26,I26,L26,O26,R26,U26,X26,AA26,AD26,AG26) -> #REF! | AK26: =SUM(G26,J26,M26,P26,S26,V26,Y26,AB26,AE26,AH26) -> 26
A27: Publications Manager | D27: 100000 | E27: 0.1 | F27: =E27*D27*F$11 -> 10100 | G27: =E27*260 -> 26 | H27: 0 | I27: =H27*$D27*I$11 -> #REF! | J27: =H27*260 -> 0 | K27: 0 | L27: =K27*$D27*L$11 -> #REF! | M27: =K27*260 -> 0 | N27: 0 | O27: =N27*$D27*O$11 -> #REF! | P27: =N27*260 -> 0 | Q27: 0 | R27: =Q27*$D27*R$11 -> #REF! | S27: =Q27*260 -> 0 | T27: 0 | U27: =T27*S27*U$11 -> #REF! | V27: =T27*260 -> 0 | W27: 0 | X27: =W27*$D27*X$11 -> #REF! | Y27: =W27*260 -> 0 | Z27: 0 | AA27: =Z27*$D27*AA$11 -> #REF! | AB27: =Z27*260 -> 0 | AC27: 0 | AD27: =AC27*$D27*AD$11 -> #REF! | AE27: =AC27*260 -> 0 | AF27: 0 | AG27: =AF27*$D27*AG$11 -> #REF! | AH27: =AF27*260 -> 0 | AI27: =SUM(E27,H27,K27,N27,Q27,T27,W27,Z27,AC27,AF27) -> 0.1 | AJ27: =SUM(F27,I27,L27,O27,R27,U27,X27,AA27,AD27,AG27) -> #REF! | AK27: =SUM(G27,J27,M27,P27,S27,V27,Y27,AB27,AE27,AH27) -> 26
B28: Subtotal Program Management | F28: =SUM(F12:F27) -> 111100 | I28: =SUM(I12:I27) -> #REF! | L28: =SUM(L12:L27) -> #REF! | O28: =SUM(O12:O27) -> #REF! | R28: =SUM(R12:R27) -> #REF! | U28: =SUM(U12:U27) -> #REF! | X28: =SUM(X12:X27) -> #REF! | AA28: =SUM(AA12:AA27) -> #REF! | AD28: =SUM(AD12:AD27) -> #REF! | AG28: =SUM(AG12:AG27) -> #REF!
