Workbook
Name \A: #REF!
Name \P: #REF!
Name \S: #REF!
Name _______sho1: #REF!
Name __2DAI_1: #N/A
Name __3FEE: #N/A
Name __AFP1: #N/A
Name __AFP2: #N/A
Name __AFP3: #N/A
Name __AFP4: #N/A
Name __AMP1: #N/A
Name __AMP2: #N/A
Name __AMP3: #N/A
Name __AMP4: #N/A
Name __DAI4: #N/A
Name __EES1: #N/A
Name __EES2: #N/A
Name __EES3: #N/A
Name __EES4: #N/A
Name __EXT1: #N/A
Name __EXT2: #N/A
Name __EXT3: #N/A
Name __EXT4: #N/A
Name __FCP1: #N/A
Name __FCP2: #N/A
Name __FCP3: #N/A
Name __FCP4: #N/A
Name __FRI1: #N/A
Name __FRI4: #N/A
Name __HRA1: #N/A
Name __HRA2: #N/A
Name __HRA3: #N/A
Name __HRA4: #N/A
Name __inf1: #REF!
Name __LT4: #REF!
Name __ODC1: #N/A
Name __ODC2: #N/A
Name __POL1: #N/A
Name __POL2: #N/A
Name __POL3: #N/A
Name __POL4: #N/A
Name __TOT1: #N/A
Name __TOT2: #N/A
Name __TRV1: #N/A
Name __TRV2: #N/A
Name _060: #REF!
Name _1_1: #REF!
Name _13th_and_14th_month: #REF!
Name _2_1034: #REF!
Name _2DAI_1: #N/A
Name _3_1440: #REF!
Name _3FEE: #N/A
Name _4_2: #REF!
Name _5_3: #REF!
Name _AFP1: #N/A
Name _AFP2: #N/A
Name _AFP3: #N/A
Name _AFP4: #N/A
Name _AMP1: #N/A
Name _AMP2: #N/A

Sheet USDA Budget Summary
A1: Attachment 9
A2: Proposed Budget Summary
A4: Program (FFPr or MGD): | B4: FFPr
A5: Country of Operation: | B5: Mauritania
A6: Implementing Organization: | B6: Partners of the Americas Inc.
A7: Fiscal Year: | B7: 2023
A8: Agreement Number: | B8: USDA-FAS-10.606-0700-23-(557) | H8: 39.656979
A10: Total Amount of Federal Funds Requested
A11: Funding Source (FAS for MGD) (CCC for FFPr) | B11: Funding Year | C11: Commodity Cost | D11: Freight Cost | E11: Administrative Costs (cash portion) | F11: Total Federal Funding Obligated
B12: 2023 | C12: 28250000 | D12: 5900000 | E12: 1400000 | F12: =E12+D12+C12 -> 35550000
A14: Project Operating Budget
A15: Expense Type | B15: Monetization Proceeds (FFPr Only) | C15: FAS or CCC Funds (CCC is Admin Only) | D15: Cost Share | E15: Total w/out Cost Share | F15: Total w/Cost Share
A16: Administration
A17: Salaries/Personnel | B17: =Admin!W33-C17 -> 340514.28 | C17: 484000 | D17: ='Program Budget'!W34 -> 0 | E17: =B17+C17 -> 824514.28 | F17: =B17+C17+D17 -> 824514.28
A18: Benefits | B18: =Admin!W51-C18 -> 140988.73 | C18: 265417 | D18: ='Program Budget'!W49 -> 0 | E18: =B18+C18 -> 406405.73 | F18: =B18+C18+D18 -> 406405.73
A19: Travel | B19: =Admin!W68-C19 -> 170974.97 | C19: 37563 | D19: ='Program Budget'!W66 -> 0 | E19: =B19+C19 -> 208537.97 | F19: =B19+C19+D19 -> 208537.97
A20: Professional Services/Contractual | B20: =Admin!W91-C20 -> 1167600 | C20: 250000 | D20: ='Program Budget'!W92 -> 0 | E20: =B20+C20 -> 1417600 | F20: =B20+C20+D20 -> 1417600
A21: Equipment | B21: =Admin!W95-C21 -> 130000 | C21: 0 | D21: ='Program Budget'!W97 -> 0 | E21: =B21+C21 -> 130000 | F21: =B21+C21+D21 -> 130000
A22: Office | B22: =Admin!W108-C22 -> 369492.55 | C22: 14990 | D22: ='Program Budget'!W114 -> 0 | E22: =B22+C22 -> 384482.55 | F22: =B22+C22+D22 -> 384482.55
A23: Supplies | B23: =Admin!W122-C23 -> 11144.42 | C23: 25968 | D23: ='Program Budget'!W129 -> 0 | E23: =B23+C23 -> 37112.42 | F23: =B23+C23+D23 -> 37112.42
A24: Other | B24: =Admin!W135-C24 -> 65166.843 | C24: 13425 | D24: 0 | E24: =B24+C24 -> 78591.843 | F24: =B24+C24+D24 -> 78591.843
A25: Total Administration | B25: =SUM(B17:B24) -> 2395881.8 | C25: =SUM(C17:C24) -> 1091363 | D25: =SUM(D17:D24) -> 0 | E25: =SUM(E17:E24) -> 3487244.8 | F25: =SUM(F17:F24) -> 3487244.8
A27: Activities
A28: Activity 1: Increase Production and Farmer Resiliency | B28: ='Activity 1'!W78 -> 2088882 | C28: 0 | D28: ='Program Budget'!W201 -> 0 | E28: =B28+C28 -> 2088882 | F28: =B28+C28+D28 -> 2088882
A29: Activity 2: Promote Regenerative Agriculture with Agropastoralists | B29: ='Activity 2'!W75 -> 1825819 | C29: 0 | D29: ='Program Budget'!W259 -> 0 | E29: =B29+C29 -> 1825819 | F29: =B29+C29+D29 -> 1825819
A30: Activity 3: Improve the Agricultural-Enabling Environment | B30: ='Activity 3'!W84 -> 1995172.4 | C30: 0 | D30: =ROUND('Program Budget'!W326,0) -> 0 | E30: =B30+C30 -> 1995172.4 | F30: =B30+C30+D30 -> 1995172.4
A31: Activity 4: Build Capacity for Post-harvest | B31: ='Activity 4'!W82 -> 2604012.7 | C31: 0 | D31: =ROUNDUP(SUM('Activity 4'!W91:W94),0) -> 600000 | E31: =B31+C31 -> 2604012.7 | F31: =B31+C31+D31 -> 3204012.7
A32: Total Activities | B32: =SUM(B28:B31) -> 8513886.2 | C32: =SUM(C28:C31) -> 0 | D32: =SUM(D28:D31) -> 600000 | E32: =SUM(E28:E31) -> 8513886.2 | F32: =SUM(F28:F31) -> 9113886.2
A34: Commodity and Food Purchases (N/A to FFPr)
A35: Commodity Procurement | B35: 0 | C35: 0 | D35: 0 | E35: =B35+C35 -> 0 | F35: =B35+C35+D35 -> 0
A36: Food Vouchers (N/A to MGD)
A37: Cash Transfers (N/A to MGD)
A38: Total Commodity Procurement | B38: =SUM(B35:B37) -> 0 | C38: =SUM(C35:C37) -> 0 | D38: =SUM(D35:D37) -> 0 | E38: =SUM(E35:E37) -> 0 | F38: =SUM(F35:F37) -> 0
A40: ITSH (N/A to FFPr)
A41: Salaries | B41: 0 | C41: 0 | D41: 0 | E41: =B41+C41 -> 0 | F41: =B41+C41+D41 -> 0
A42: Benefits | B42: 0 | C42: 0 | D42: 0 | E42: =B42+C42 -> 0 | F42: =B42+C42+D42 -> 0
A43: Transportation | B43: 0 | C43: 0 | D43: 0 | E43: =B43+C43 -> 0 | F43: =B43+C43+D43 -> 0
A44: Professional Services | B44: 0 | C44: 0 | D44: =0 -> 0 | E44: =B44+C44 -> 0 | F44: =B44+C44+D44 -> 0
A45: Warehouse | B45: 0 | C45: 0 | D45: 0 | E45: =B45+C45 -> 0 | F45: =B45+C45+D45 -> 0
A46: Supplies | B46: 0 | C46: 0 | D46: 0 | E46: =B46+C46 -> 0 | F46: =B46+C46+D46 -> 0
A47: Other | B47: 0 | C47: 0 | D47: 0 | E47: =B47+C47 -> 0 | F47: =B47+C47+D47 -> 0
A48: Total ITSH | B48: =SUM(B41:B47) -> 0 | C48: 0 | D48: =SUM(D41:D47) -> 0 | E48: =SUM(E41:E47) -> 0 | F48: =SUM(F41:F47) -> 0
A50: Total Direct Costs | B50: =B25+B32+B48+B38 -> 10909768 | C50: =C25+C32+C48+C38 -> 1091363 | D50: =D25+D32+D48+D38 -> 600000 | E50: =E38+E32+E25+E48 -> 12001131 | F50: =F38+F32+F25+F48 -> 12601131
A52: Indirect Costs
A53: ICR on Administration | B53: =ROUND((B25*0.2828),0) -> 677555 | C53: =ROUND(C25*0.2828,0) -> 308637 | E53: =B53+C53 -> 986192
A54: ICR on Activities | B54: =ROUND((B32)*0.2828,0) -> 2407727 | C54: =C32*0.2828 -> 0 | E54: =B54+C54 -> 2407727
A55: ICR on Commodity and Food Purchases (N/A to FFPr) | B55: =B38*0.2828 -> 0 | C55: =C38*0.2828 -> 0 | E55: =B55+C55 -> 0
A56: ICR on ITSH (N/A to FFPr) | B56: =B48*0.2828 -> 0 | C56: =C48*0.2828 -> 0 | E56: =B56+C56 -> 0
A57: Total Indirect Costs | B57: =ROUND(SUM(B53:B56),0) -> 3085282 | C57: =ROUND(SUM(C53:C56),0) -> 308637 | E57: =ROUND(SUM(E53:E56),0) -> 3393919
A59: Anticipated Program Income | F59: 7878
A61: Grand Total Costs | B61: =(B57+B50) -> 13995050 | C61: =(C57+C50) -> 1400000 | D61: =(D57+D50) -> 600000 | E61: =(E57+E50) -> 15395050 | F61: =(F50+E57) -> 15995050
A63: Total Amount of Federal Award (Total Federal Funds Requested Plus Cost Share): | F63: =F12+D61 -> 36150000
E66: =E61*10% -> 1539505

Sheet Detailed Budget
A2: Item | B2: Type of Unit | C2: Year 1 | G2: Year 2 | K2: Year 3 | O2: Year 4 | S2: Year 5 | W2: Total
C3: Cost | D3: Quantity | E3: Percent Allocated | F3: Total | G3: Cost | H3: Quantity | I3: Percent Allocated | J3: Total | K3: Cost | L3: Quantity | M3: Percent Allocated | N3: Total | O3: Cost | P3: Quantity | Q3: Percent Allocated | R3: Total | S3: Cost | T3: Quantity | U3: Percent Allocated | V3: Total
A4: Direct Costs
A5: Salaries
A6: USN/TCN Staff
A7: ='Program Budget'!D12 -> Key Personnel: Ex-pat Chief of Party | B7: ='Program Budget'!F13 -> Month | C7: ='Program Budget'!H12 -> 12083.333 | D7: ='Program Budget'!G12 -> 12 | E7: =Admin!E7+'Activity 1'!E7+'Activity 2'!E7+'Activity 3'!E7+'Activity 4'!E7 -> 1 | F7: =C7*D7*E7 -> 145000 | G7: =C7*1.04 -> 12566.667 | H7: ='Program Budget'!K12 -> 12 | I7: =Admin!I7+'Activity 1'!I7+'Activity 2'!I7+'Activity 3'!I7+'Activity 4'!I7 -> 1 | J7: =G7*H7*I7 -> 150800 | K7: =G7*1.04 -> 13069.333 | L7: ='Program Budget'!N12 -> 12 | M7: =Admin!M7+'Activity 1'!M7+'Activity 2'!M7+'Activity 3'!M7+'Activity 4'!M7 -> 1 | N7: =K7*L7*M7 -> 156832 | O7: =K7*1.04 -> 13592.107 | P7: ='Program Budget'!Q12 -> 12 | Q7: =Admin!Q7+'Activity 1'!Q7+'Activity 2'!Q7+'Activity 3'!Q7+'Activity 4'!Q7 -> 1 | R7: =O7*P7*Q7 -> 163105.28 | S7: =O7*1.04 -> 14135.791 | T7: ='Program Budget'!T12 -> 12 | U7: =Admin!U7+'Activity 1'!U7+'Activity 2'!U7+'Activity 3'!U7+'Activity 4'!U7 -> 1 | V7: =S7*T7*U7 -> 169629.49 | W7: =F7+J7+N7+R7+V7 -> 785366.77
A8: Total: Expatriate Salaries & Wages | F8: =SUM(F7:F7) -> 145000 | J8: =SUM(J7:J7) -> 150800 | N8: =SUM(N7:N7) -> 156832 | R8: =SUM(R7:R7) -> 163105.28 | V8: =SUM(V7:V7) -> 169629.49 | W8: =+F8+J8+N8+R8+V8 -> 785366.77
A9: CNN Staff
A10: ='Program Budget'!D13 -> Deputy Chief of Party | B10: ='Program Budget'!F12 -> Month | C10: ='Program Budget'!H13 -> 7500 | D10: ='Program Budget'!G13 -> 6 | E10: =Admin!E10+'Activity 1'!E10+'Activity 2'!E10+'Activity 3'!E10+'Activity 4'!E10 -> 1 | F10: =C10*D10*E10 -> 45000 | G10: =C10*1.04 -> 7800 | H10: ='Program Budget'!K13 -> 12 | I10: =Admin!I10+'Activity 1'!I10+'Activity 2'!I10+'Activity 3'!I10+'Activity 4'!I10 -> 1 | J10: =G10*H10*I10 -> 93600 | K10: =G10*1.04 -> 8112 | L10: ='Program Budget'!N13 -> 12 | M10: =Admin!M10+'Activity 1'!M10+'Activity 2'!M10+'Activity 3'!M10+'Activity 4'!M10 -> 1 | N10: =K10*L10*M10 -> 97344 | O10: =K10*1.04 -> 8436.48 | P10: ='Program Budget'!Q13 -> 12 | Q10: =Admin!Q10+'Activity 1'!Q10+'Activity 2'!Q10+'Activity 3'!Q10+'Activity 4'!Q10 -> 1 | R10: =O10*P10*Q10 -> 101237.76 | S10: =O10*1.04 -> 8773.9392 | T10: ='Program Budget'!T13 -> 6 | U10: =Admin!U10+'Activity 1'!U10+'Activity 2'!U10+'Activity 3'!U10+'Activity 4'!U10 -> 1 | V10: =S10*T10*U10 -> 52643.635 | W10: =F10+J10+N10+R10+V10 -> 389825.4
A11: ='Program Budget'!D14 -> Technical Lead Component 1 | B11: ='Program Budget'!F14 -> Month | C11: ='Program Budget'!H14 -> 3333.3333 | D11: ='Program Budget'!G14 -> 6 | E11: =Admin!E11+'Activity 1'!E11+'Activity 2'!E11+'Activity 3'!E11+'Activity 4'!E11 -> 1 | F11: =C11*D11*E11 -> 20000 | G11: =C11*1.04 -> 3466.6667 | H11: ='Program Budget'!K14 -> 12 | I11: =Admin!I11+'Activity 1'!I11+'Activity 2'!I11+'Activity 3'!I11+'Activity 4'!I11 -> 1 | J11: =G11*H11*I11 -> 41600 | K11: =G11*1.04 -> 3605.3333 | L11: ='Program Budget'!N14 -> 12 | M11: =Admin!M11+'Activity 1'!M11+'Activity 2'!M11+'Activity 3'!M11+'Activity 4'!M11 -> 1 | N11: =K11*L11*M11 -> 43264 | O11: =K11*1.04 -> 3749.5467 | P11: ='Program Budget'!Q14 -> 12 | Q11: =Admin!Q11+'Activity 1'!Q11+'Activity 2'!Q11+'Activity 3'!Q11+'Activity 4'!Q11 -> 1 | R11: =O11*P11*Q11 -> 44994.56 | S11: =O11*1.04 -> 3899.5285 | T11: ='Program Budget'!T14 -> 9 | U11: =Admin!U11+'Activity 1'!U11+'Activity 2'!U11+'Activity 3'!U11+'Activity 4'!U11 -> 1 | V11: =S11*T11*U11 -> 35095.757 | W11: =F11+J11+N11+R11+V11 -> 184954.32
A12: ='Program Budget'!D15 -> Technical Lead Component 2 | B12: ='Program Budget'!F15 -> Month | C12: ='Program Budget'!H15 -> 3333.3333 | D12: ='Program Budget'!G15 -> 6 | E12: =Admin!E12+'Activity 1'!E12+'Activity 2'!E12+'Activity 3'!E12+'Activity 4'!E12 -> 1 | F12: =C12*D12*E12 -> 20000 | G12: =C12*1.04 -> 3466.6667 | H12: ='Program Budget'!K15 -> 12 | I12: =Admin!I12+'Activity 1'!I12+'Activity 2'!I12+'Activity 3'!I12+'Activity 4'!I12 -> 1 | J12: =G12*H12*I12 -> 41600 | K12: =G12*1.04 -> 3605.3333 | L12: ='Program Budget'!N15 -> 12 | M12: =Admin!M12+'Activity 1'!M12+'Activity 2'!M12+'Activity 3'!M12+'Activity 4'!M12 -> 1 | N12: =K12*L12*M12 -> 43264 | O12: =K12*1.04 -> 3749.5467 | P12: ='Program Budget'!Q15 -> 12 | Q12: =Admin!Q12+'Activity 1'!Q12+'Activity 2'!Q12+'Activity 3'!Q12+'Activity 4'!Q12 -> 1 | R12: =O12*P12*Q12 -> 44994.56 | S12: =O12*1.04 -> 3899.5285 | T12: ='Program Budget'!T15 -> 9 | U12: =Admin!U12+'Activity 1'!U12+'Activity 2'!U12+'Activity 3'!U12+'Activity 4'!U12 -> 1 | V12: =S12*T12*U12 -> 35095.757 | W12: =F12+J12+N12+R12+V12 -> 184954.32
A13: ='Program Budget'!D16 -> Technical Lead Component 3 | B13: ='Program Budget'!F16 -> Month | C13: ='Program Budget'!H16 -> 3333.3333 | D13: ='Program Budget'!G16 -> 6 | E13: =Admin!E13+'Activity 1'!E13+'Activity 2'!E13+'Activity 3'!E13+'Activity 4'!E13 -> 1 | F13: =C13*D13*E13 -> 20000 | G13: =C13*1.04 -> 3466.6667 | H13: ='Program Budget'!K16 -> 12 | I13: =Admin!I13+'Activity 1'!I13+'Activity 2'!I13+'Activity 3'!I13+'Activity 4'!I13 -> 1 | J13: =G13*H13*I13 -> 41600 | K13: =G13*1.04 -> 3605.3333 | L13: ='Program Budget'!N16 -> 12 | M13: =Admin!M13+'Activity 1'!M13+'Activity 2'!M13+'Activity 3'!M13+'Activity 4'!M13 -> 1 | N13: =K13*L13*M13 -> 43264 | O13: =K13*1.04 -> 3749.5467 | P13: ='Program Budget'!Q16 -> 12 | Q13: =Admin!Q13+'Activity 1'!Q13+'Activity 2'!Q13+'Activity 3'!Q13+'Activity 4'!Q13 -> 1 | R13: =O13*P13*Q13 -> 44994.56 | S13: =O13*1.04 -> 3899.5285 | T13: ='Program Budget'!T16 -> 9 | U13: =Admin!U13+'Activity 1'!U13+'Activity 2'!U13+'Activity 3'!U13+'Activity 4'!U13 -> 1 | V13: =S13*T13*U13 -> 35095.757 | W13: =F13+J13+N13+R13+V13 -> 184954.32
A14: ='Program Budget'!D17 -> Specialist Component 2 | B14: ='Program Budget'!F17 -> Month | C14: ='Program Budget'!H17 -> 1666.6667 | D14: ='Program Budget'!G17 -> 6 | E14: =Admin!E14+'Activity 1'!E14+'Activity 2'!E14+'Activity 3'!E14+'Activity 4'!E14 -> 1 | F14: =C14*D14*E14 -> 10000 | G14: =C14*1.04 -> 1733.3333 | H14: ='Program Budget'!K17 -> 12 | I14: =Admin!I14+'Activity 1'!I14+'Activity 2'!I14+'Activity 3'!I14+'Activity 4'!I14 -> 1 | J14: =G14*H14*I14 -> 20800 | K14: =G14*1.04 -> 1802.6667 | L14: ='Program Budget'!N17 -> 12 | M14: =Admin!M14+'Activity 1'!M14+'Activity 2'!M14+'Activity 3'!M14+'Activity 4'!M14 -> 1 | N14: =K14*L14*M14 -> 21632 | O14: =K14*1.04 -> 1874.7733 | P14: ='Program Budget'!Q17 -> 12 | Q14: =Admin!Q14+'Activity 1'!Q14+'Activity 2'!Q14+'Activity 3'!Q14+'Activity 4'!Q14 -> 1 | R14: =O14*P14*Q14 -> 22497.28 | S14: =O14*1.04 -> 1949.7643 | T14: ='Program Budget'!T17 -> 6 | U14: =Admin!U14+'Activity 1'!U14+'Activity 2'!U14+'Activity 3'!U14+'Activity 4'!U14 -> 1 | V14: =S14*T14*U14 -> 11698.586 | W14: =F14+J14+N14+R14+V14 -> 86627.866
A15: ='Program Budget'!D18 -> Specialist Component 3 | B15: ='Program Budget'!F18 -> Month | C15: ='Program Budget'!H18 -> 1666.6667 | D15: ='Program Budget'!G18 -> 6 | E15: =Admin!E15+'Activity 1'!E15+'Activity 2'!E15+'Activity 3'!E15+'Activity 4'!E15 -> 1 | F15: =C15*D15*E15 -> 10000 | G15: =C15*1.04 -> 1733.3333 | H15: ='Program Budget'!K18 -> 12 | I15: =Admin!I15+'Activity 1'!I15+'Activity 2'!I15+'Activity 3'!I15+'Activity 4'!I15 -> 1 | J15: =G15*H15*I15 -> 20800 | K15: =G15*1.04 -> 1802.6667 | L15: ='Program Budget'!N18 -> 12 | M15: =Admin!M15+'Activity 1'!M15+'Activity 2'!M15+'Activity 3'!M15+'Activity 4'!M15 -> 1 | N15: =K15*L15*M15 -> 21632 | O15: =K15*1.04 -> 1874.7733 | P15: ='Program Budget'!Q18 -> 12 | Q15: =Admin!Q15+'Activity 1'!Q15+'Activity 2'!Q15+'Activity 3'!Q15+'Activity 4'!Q15 -> 1 | R15: =O15*P15*Q15 -> 22497.28 | S15: =O15*1.04 -> 1949.7643 | T15: ='Program Budget'!T18 -> 6 | U15: =Admin!U15+'Activity 1'!U15+'Activity 2'!U15+'Activity 3'!U15+'Activity 4'!U15 -> 1 | V15: =S15*T15*U15 -> 11698.586 | W15: =F15+J15+N15+R15+V15 -> 86627.866
A16: ='Program Budget'!D19 -> Specialist Component 4 | B16: ='Program Budget'!F19 -> Month | C16: ='Program Budget'!H19 -> 1666.6667 | D16: ='Program Budget'!G19 -> 6 | E16: =Admin!E16+'Activity 1'!E16+'Activity 2'!E16+'Activity 3'!E16+'Activity 4'!E16 -> 1 | F16: =C16*D16*E16 -> 10000 | G16: =C16*1.04 -> 1733.3333 | H16: ='Program Budget'!K19 -> 12 | I16: =Admin!I16+'Activity 1'!I16+'Activity 2'!I16+'Activity 3'!I16+'Activity 4'!I16 -> 1 | J16: =G16*H16*I16 -> 20800 | K16: =G16*1.04 -> 1802.6667 | L16: ='Program Budget'!N19 -> 12 | M16: =Admin!M16+'Activity 1'!M16+'Activity 2'!M16+'Activity 3'!M16+'Activity 4'!M16 -> 1 | N16: =K16*L16*M16 -> 21632 | O16: =K16*1.04 -> 1874.7733 | P16: ='Program Budget'!Q19 -> 12 | Q16: =Admin!Q16+'Activity 1'!Q16+'Activity 2'!Q16+'Activity 3'!Q16+'Activity 4'!Q16 -> 1 | R16: =O16*P16*Q16 -> 22497.28 | S16: =O16*1.04 -> 1949.7643 | T16: ='Program Budget'!T19 -> 6 | U16: =Admin!U16+'Activity 1'!U16+'Activity 2'!U16+'Activity 3'!U16+'Activity 4'!U16 -> 1 | V16: =S16*T16*U16 -> 11698.586 | W16: =F16+J16+N16+R16+V16 -> 86627.866
A17: ='Program Budget'!D20 -> Extension Agents (20 Individuals) | B17: ='Program Budget'!F20 -> Month | C17: ='Program Budget'!H20 -> 23333.333 | D17: ='Program Budget'!G20 -> 3 | E17: 1 | F17: =C17*D17*E17 -> 70000 | G17: =C17*1.04 -> 24266.667 | H17: ='Program Budget'!K20 -> 12 | I17: =Admin!I14+'Activity 1'!I17+'Activity 2'!I17+'Activity 3'!I17+'Activity 4'!I17 -> 1 | J17: =G17*H17*I17 -> 291200 | K17: =G17*1.04 -> 25237.333 | L17: ='Program Budget'!N20 -> 6 | M17: =Admin!M14+'Activity 1'!M17+'Activity 2'!M17+'Activity 3'!M17+'Activity 4'!M17 -> 1 | N17: =K17*L17*M17 -> 151424 | O17: =K17*1.04 -> 26246.827 | P17: ='Program Budget'!Q20 -> 0 | Q17: =Admin!Q14+'Activity 1'!Q17+'Activity 2'!Q17+'Activity 3'!Q17+'Activity 4'!Q17 -> 0 | R17: =O17*P17*Q17 -> 0 | S17: =O17*1.04 -> 27296.7 | T17: ='Program Budget'!T20 -> 0 | U17: =Admin!U14+'Activity 1'!U17+'Activity 2'!U17+'Activity 3'!U17+'Activity 4'!U17 -> 0 | V17: =S17*T17*U17 -> 0 | W17: =F17+J17+N17+R17+V17 -> 512624
A18: ='Program Budget'!D21 -> M&E Director | B18: ='Program Budget'!F21 -> Month | C18: ='Program Budget'!H21 -> 3750 | D18: ='Program Budget'!G21 -> 9 | E18: =Admin!E18+'Activity 1'!E18+'Activity 2'!E18+'Activity 3'!E18+'Activity 4'!E18 -> 1 | F18: =C18*D18*E18 -> 33750 | G18: =C18*1.04 -> 3900 | H18: ='Program Budget'!K21 -> 12 | I18: =Admin!I18+'Activity 1'!I18+'Activity 2'!I18+'Activity 3'!I18+'Activity 4'!I18 -> 1 | J18: =G18*H18*I18 -> 46800 | K18: =G18*1.04 -> 4056 | L18: ='Program Budget'!N21 -> 12 | M18: =Admin!M18+'Activity 1'!M18+'Activity 2'!M18+'Activity 3'!M18+'Activity 4'!M18 -> 1 | N18: =K18*L18*M18 -> 48672 | O18: =K18*1.04 -> 4218.24 | P18: ='Program Budget'!Q21 -> 12 | Q18: =Admin!Q18+'Activity 1'!Q18+'Activity 2'!Q18+'Activity 3'!Q18+'Activity 4'!Q18 -> 1 | R18: =O18*P18*Q18 -> 50618.88 | S18: =O18*1.04 -> 4386.9696 | T18: ='Program Budget'!T21 -> 12 | U18: =Admin!U18+'Activity 1'!U18+'Activity 2'!U18+'Activity 3'!U18+'Activity 4'!U18 -> 1 | V18: =S18*T18*U18 -> 52643.635 | W18: =F18+J18+N18+R18+V18 -> 232484.52
A19: ='Program Budget'!D22 -> M&E Specialist | B19: ='Program Budget'!F22 -> Month | C19: ='Program Budget'!H22 -> 2083.3333 | D19: ='Program Budget'!G22 -> 6 | E19: =Admin!E19+'Activity 1'!E19+'Activity 2'!E19+'Activity 3'!E19+'Activity 4'!E19 -> 1 | F19: =C19*D19*E19 -> 12500 | G19: =C19*1.04 -> 2166.6667 | H19: ='Program Budget'!K22 -> 12 | I19: =Admin!I19+'Activity 1'!I19+'Activity 2'!I19+'Activity 3'!I19+'Activity 4'!I19 -> 1 | J19: =G19*H19*I19 -> 26000 | K19: =G19*1.04 -> 2253.3333 | L19: ='Program Budget'!N22 -> 12 | M19: =Admin!M19+'Activity 1'!M19+'Activity 2'!M19+'Activity 3'!M19+'Activity 4'!M19 -> 1 | N19: =K19*L19*M19 -> 27040 | O19: =K19*1.04 -> 2343.4667 | P19: ='Program Budget'!Q22 -> 12 | Q19: =Admin!Q19+'Activity 1'!Q19+'Activity 2'!Q19+'Activity 3'!Q19+'Activity 4'!Q19 -> 1 | R19: =O19*P19*Q19 -> 28121.6 | S19: =O19*1.04 -> 2437.2053 | T19: ='Program Budget'!T22 -> 10 | U19: =Admin!U19+'Activity 1'!U19+'Activity 2'!U19+'Activity 3'!U19+'Activity 4'!U19 -> 1 | V19: =S19*T19*U19 -> 24372.053 | W19: =F19+J19+N19+R19+V19 -> 118033.65
A20: ='Program Budget'!D23 -> F&A Director | B20: ='Program Budget'!F23 -> Month | C20: ='Program Budget'!H23 -> 6666.6667 | D20: ='Program Budget'!G23 -> 9 | E20: =Admin!E20+'Activity 1'!E20+'Activity 2'!E20+'Activity 3'!E20+'Activity 4'!E20 -> 1 | F20: =C20*D20*E20 -> 60000 | G20: =C20*1.04 -> 6933.3333 | H20: ='Program Budget'!K23 -> 12 | I20: =Admin!I20+'Activity 1'!I20+'Activity 2'!I20+'Activity 3'!I20+'Activity 4'!I20 -> 1 | J20: =G20*H20*I20 -> 83200 | K20: =G20*1.04 -> 7210.6667 | L20: ='Program Budget'!N23 -> 12 | M20: =Admin!M20+'Activity 1'!M20+'Activity 2'!M20+'Activity 3'!M20+'Activity 4'!M20 -> 1 | N20: =K20*L20*M20 -> 86528 | O20: =K20*1.04 -> 7499.0933 | P20: ='Program Budget'!Q23 -> 12 | Q20: =Admin!Q20+'Activity 1'!Q20+'Activity 2'!Q20+'Activity 3'!Q20+'Activity 4'!Q20 -> 1 | R20: =O20*P20*Q20 -> 89989.12 | S20: =O20*1.04 -> 7799.0571 | T20: ='Program Budget'!T23 -> 12 | U20: =Admin!U20+'Activity 1'!U20+'Activity 2'!U20+'Activity 3'!U20+'Activity 4'!U20 -> 1 | V20: =S20*T20*U20 -> 93588.685 | W20: =F20+J20+N20+R20+V20 -> 413305.8
A21: ='Program Budget'!D24 -> Human Resource Manager | B21: ='Program Budget'!F24 -> Month | C21: ='Program Budget'!H24 -> 2916.6667 | D21: ='Program Budget'!G24 -> 9 | E21: =Admin!E21+'Activity 1'!E21+'Activity 2'!E21+'Activity 3'!E21+'Activity 4'!E21 -> 1 | F21: =C21*D21*E21 -> 26250 | G21: =C21*1.04 -> 3033.3333 | H21: ='Program Budget'!K24 -> 12 | I21: =Admin!I21+'Activity 1'!I21+'Activity 2'!I21+'Activity 3'!I21+'Activity 4'!I21 -> 1 | J21: =G21*H21*I21 -> 36400 | K21: =G21*1.04 -> 3154.6667 | L21: ='Program Budget'!N24 -> 12 | M21: =Admin!M21+'Activity 1'!M21+'Activity 2'!M21+'Activity 3'!M21+'Activity 4'!M21 -> 1 | N21: =K21*L21*M21 -> 37856 | O21: =K21*1.04 -> 3280.8533 | P21: ='Program Budget'!Q24 -> 12 | Q21: =Admin!Q21+'Activity 1'!Q21+'Activity 2'!Q21+'Activity 3'!Q21+'Activity 4'!Q21 -> 1 | R21: =O21*P21*Q21 -> 39370.24 | S21: =O21*1.04 -> 3412.0875 | T21: ='Program Budget'!T24 -> 10 | U21: =Admin!U21+'Activity 1'!U21+'Activity 2'!U21+'Activity 3'!U21+'Activity 4'!U21 -> 1 | V21: =S21*T21*U21 -> 34120.875 | W21: =F21+J21+N21+R21+V21 -> 173997.11
A22: ='Program Budget'!D25 -> Contracts & Compliance Specialist | B22: ='Program Budget'!F25 -> Month | C22: ='Program Budget'!H25 -> 2916.6667 | D22: ='Program Budget'!G25 -> 6 | E22: =Admin!E22+'Activity 1'!E22+'Activity 2'!E22+'Activity 3'!E22+'Activity 4'!E22 -> 1 | F22: =C22*D22*E22 -> 17500 | G22: =C22*1.04 -> 3033.3333 | H22: ='Program Budget'!K25 -> 12 | I22: =Admin!I22+'Activity 1'!I22+'Activity 2'!I22+'Activity 3'!I22+'Activity 4'!I22 -> 1 | J22: =G22*H22*I22 -> 36400 | K22: =G22*1.04 -> 3154.6667 | L22: ='Program Budget'!N25 -> 12 | M22: =Admin!M22+'Activity 1'!M22+'Activity 2'!M22+'Activity 3'!M22+'Activity 4'!M22 -> 1 | N22: =K22*L22*M22 -> 37856 | O22: =K22*1.04 -> 3280.8533 | P22: ='Program Budget'!Q25 -> 12 | Q22: =Admin!Q22+'Activity 1'!Q22+'Activity 2'!Q22+'Activity 3'!Q22+'Activity 4'!Q22 -> 1 | R22: =O22*P22*Q22 -> 39370.24 | S22: =O22*1.04 -> 3412.0875 | T22: ='Program Budget'!T25 -> 9 | U22: =Admin!U22+'Activity 1'!U22+'Activity 2'!U22+'Activity 3'!U22+'Activity 4'!U22 -> 1 | V22: =S22*T22*U22 -> 30708.787 | W22: =F22+J22+N22+R22+V22 -> 161835.03
A23: ='Program Budget'!D26 -> Accountant | B23: ='Program Budget'!F26 -> Month | C23: ='Program Budget'!H26 -> 1666.6667 | D23: 20 | E23: =Admin!E23+'Activity 1'!E23+'Activity 2'!E23+'Activity 3'!E23+'Activity 4'!E23 -> 1 | F23: =C23*D23*E23 -> 33333.333 | G23: =C23*1.04 -> 1733.3333 | H23: ='Program Budget'!K26 -> 12 | I23: =Admin!I23+'Activity 1'!I23+'Activity 2'!I23+'Activity 3'!I23+'Activity 4'!I23 -> 1 | J23: =G23*H23*I23 -> 20800 | K23: =G23*1.04 -> 1802.6667 | L23: ='Program Budget'!N26 -> 12 | M23: =Admin!M23+'Activity 1'!M23+'Activity 2'!M23+'Activity 3'!M23+'Activity 4'!M23 -> 1 | N23: =K23*L23*M23 -> 21632 | O23: =K23*1.04 -> 1874.7733 | P23: ='Program Budget'!Q26 -> 12 | Q23: =Admin!Q23+'Activity 1'!Q23+'Activity 2'!Q23+'Activity 3'!Q23+'Activity 4'!Q23 -> 1 | R23: =O23*P23*Q23 -> 22497.28 | S23: =O23*1.04 -> 1949.7643 | T23: ='Program Budget'!T26 -> 10 | U23: =Admin!U23+'Activity 1'!U23+'Activity 2'!U23+'Activity 3'!U23+'Activity 4'!U23 -> 1 | V23: =S23*T23*U23 -> 19497.643 | W23: =F23+J23+N23+R23+V23 -> 117760.26
A24: ='Program Budget'!D27 -> Administrative Assistant | B24: ='Program Budget'!F27 -> Month | C24: ='Program Budget'!H27 -> 833.33333 | D24: ='Program Budget'!G27 -> 7 | E24: =Admin!E24+'Activity 1'!E24+'Activity 2'!E24+'Activity 3'!E24+'Activity 4'!E24 -> 1 | F24: =C24*D24*E24 -> 5833.3333 | G24: =C24*1.04 -> 866.66667 | H24: ='Program Budget'!K27 -> 12 | I24: =Admin!I24+'Activity 1'!I24+'Activity 2'!I24+'Activity 3'!I24+'Activity 4'!I24 -> 1 | J24: =G24*H24*I24 -> 10400 | K24: =G24*1.04 -> 901.33333 | L24: ='Program Budget'!N27 -> 12 | M24: =Admin!M24+'Activity 1'!M24+'Activity 2'!M24+'Activity 3'!M24+'Activity 4'!M24 -> 1 | N24: =K24*L24*M24 -> 10816 | O24: =K24*1.04 -> 937.38667 | P24: ='Program Budget'!Q27 -> 12 | Q24: =Admin!Q24+'Activity 1'!Q24+'Activity 2'!Q24+'Activity 3'!Q24+'Activity 4'!Q24 -> 1 | R24: =O24*P24*Q24 -> 11248.64 | S24: =O24*1.04 -> 974.88213 | T24: ='Program Budget'!T27 -> 10 | U24: =Admin!U24+'Activity 1'!U24+'Activity 2'!U24+'Activity 3'!U24+'Activity 4'!U24 -> 1 | V24: =S24*T24*U24 -> 9748.8213 | W24: =F24+J24+N24+R24+V24 -> 48046.795
A25: ='Program Budget'!D28 -> Security Guards | B25: ='Program Budget'!F28 -> Month | C25: ='Program Budget'!H28 -> 666.66667 | D25: ='Program Budget'!G28 -> 8 | E25: =Admin!E25+'Activity 1'!E25+'Activity 2'!E25+'Activity 3'!E25+'Activity 4'!E25 -> 1 | F25: =C25*D25*E25 -> 5333.3333 | G25: =C25*1.04 -> 693.33333 | H25: ='Program Budget'!K28 -> 12 | I25: =Admin!I25+'Activity 1'!I25+'Activity 2'!I25+'Activity 3'!I25+'Activity 4'!I25 -> 1 | J25: =G25*H25*I25 -> 8320 | K25: =G25*1.04 -> 721.06667 | L25: ='Program Budget'!N28 -> 12 | M25: =Admin!M25+'Activity 1'!M25+'Activity 2'!M25+'Activity 3'!M25+'Activity 4'!M25 -> 1 | N25: =K25*L25*M25 -> 8652.8 | O25: =K25*1.04 -> 749.90933 | P25: ='Program Budget'!Q28 -> 12 | Q25: =Admin!Q25+'Activity 1'!Q25+'Activity 2'!Q25+'Activity 3'!Q25+'Activity 4'!Q25 -> 1 | R25: =O25*P25*Q25 -> 8998.912 | S25: =O25*1.04 -> 779.90571 | T25: ='Program Budget'!T28 -> 10 | U25: =Admin!U25+'Activity 1'!U25+'Activity 2'!U25+'Activity 3'!U25+'Activity 4'!U25 -> 1 | V25: =S25*T25*U25 -> 7799.0571 | W25: =F25+J25+N25+R25+V25 -> 39104.102
A26: ='Program Budget'!D29 -> Driver (2 Individuals) | B26: ='Program Budget'!F29 -> Month | C26: ='Program Budget'!H29 -> 1333.3333 | D26: ='Program Budget'!G29 -> 6 | E26: =Admin!E26+'Activity 1'!E26+'Activity 2'!E26+'Activity 3'!E26+'Activity 4'!E26 -> 1 | F26: =C26*D26*E26 -> 8000 | G26: =C26*1.04 -> 1386.6667 | H26: ='Program Budget'!K29 -> 12 | I26: =Admin!I26+'Activity 1'!I26+'Activity 2'!I26+'Activity 3'!I26+'Activity 4'!I26 -> 1 | J26: =G26*H26*I26 -> 16640 | K26: =G26*1.04 -> 1442.1333 | L26: ='Program Budget'!N29 -> 12 | M26: =Admin!M26+'Activity 1'!M26+'Activity 2'!M26+'Activity 3'!M26+'Activity 4'!M26 -> 1 | N26: =K26*L26*M26 -> 17305.6 | O26: =K26*1.04 -> 1499.8187 | P26: ='Program Budget'!Q29 -> 12 | Q26: =Admin!Q26+'Activity 1'!Q26+'Activity 2'!Q26+'Activity 3'!Q26+'Activity 4'!Q26 -> 1 | R26: =O26*P26*Q26 -> 17997.824 | S26: =O26*1.04 -> 1559.8114 | T26: ='Program Budget'!T29 -> 9 | U26: =Admin!U26+'Activity 1'!U26+'Activity 2'!U26+'Activity 3'!U26+'Activity 4'!U26 -> 1 | V26: =S26*T26*U26 -> 14038.303 | W26: =F26+J26+N26+R26+V26 -> 73981.727
A27: Total Local Salary Cost | F27: =SUM(F10:F26) -> 407500 | J27: =SUM(J10:J26) -> 856960 | N27: =SUM(N10:N26) -> 739814.4 | R27: =SUM(R10:R26) -> 611926.02 | V27: =SUM(V10:V26) -> 479544.52 | W27: =F27+J27+N27+R27+V27 -> 3095744.9
A28: HQ Staff
A29: ='Program Budget'!D31 -> Senior Program Director | B29: ='Program Budget'!F31 -> Month | C29: ='Program Budget'!H31 -> 11250 | D29: ='Program Budget'!G31 -> 12 | E29: ='Program Budget'!E31 -> 0.2 | F29: =C29*D29*E29 -> 27000 | G29: =C29*1.04 -> 11700 | H29: ='Program Budget'!K31 -> 12 | I29: ='Program Budget'!J31 -> 0.2 | J29: =G29*H29*I29 -> 28080 | K29: =G29*1.04 -> 12168 | L29: ='Program Budget'!N31 -> 12 | M29: ='Program Budget'!M31 -> 0.2 | N29: =K29*L29*M29 -> 29203.2 | O29: =K29*1.04 -> 12654.72 | P29: ='Program Budget'!Q31 -> 12 | Q29: ='Program Budget'!P31 -> 0.2 | R29: =O29*P29*Q29 -> 30371.328 | S29: =O29*1.04 -> 13160.909 | T29: ='Program Budget'!T31 -> 12 | U29: ='Program Budget'!S31 -> 0.2 | V29: =S29*T29*U29 -> 31586.181 | W29: =F29+J29+N29+R29+V29 -> 146240.71
A30: ='Program Budget'!D32 -> HO Project Manager | B30: ='Program Budget'!F32 -> Month | C30: ='Program Budget'!H32 -> 6916.6667 | D30: ='Program Budget'!G32 -> 12 | E30: ='Program Budget'!E32 -> 1 | F30: =C30*D30*E30 -> 83000 | G30: =C30*1.04 -> 7193.3333 | H30: ='Program Budget'!K32 -> 12 | I30: ='Program Budget'!J32 -> 1 | J30: =G30*H30*I30 -> 86320 | K30: =G30*1.04 -> 7481.0667 | L30: ='Program Budget'!N32 -> 12 | M30: ='Program Budget'!M32 -> 1 | N30: =K30*L30*M30 -> 89772.8 | O30: =K30*1.04 -> 7780.3093 | P30: ='Program Budget'!Q32 -> 12 | Q30: ='Program Budget'!P32 -> 1 | R30: =O30*P30*Q30 -> 93363.712 | S30: =O30*1.04 -> 8091.5217 | T30: ='Program Budget'!T32 -> 12 | U30: ='Program Budget'!S32 -> 1 | V30: =S30*T30*U30 -> 97098.26 | W30: =F30+J30+N30+R30+V30 -> 449554.77
A31: Total HQ Staff | F31: =SUM(F29:F30) -> 110000 | J31: =SUM(J29:J30) -> 114400 | N31: =SUM(N29:N30) -> 118976 | R31: =SUM(R29:R30) -> 123735.04 | V31: =SUM(V29:V30) -> 128684.44 | W31: =+F31+J31+N31+R31+V31 -> 595795.48
A33: Subtotal: Salaries & Wages | F33: =F31+F27+F8 -> 662500 | J33: =J31+J27+J8 -> 1122160 | N33: =N31+N27+N8 -> 1015622.4 | R33: =R31+R27+R8 -> 898766.34 | V33: =V31+V27+V8 -> 777858.45 | W33: =+F33+J33+N33+R33+V33 -> 4476907.2
A34: Fringe
A35: USN/TCN Staff | B35: ='Program Budget'!F37 -> % | C35: =F8 -> 145000 | D35: 1 | E35: ='Program Budget'!H39 -> 0.2347 | F35: =C35*D35*E35 -> 34031.5 | G35: =J8 -> 150800 | H35: 1 | I35: =E35 -> 0.2347 | J35: =G35*H35*I35 -> 35392.76 | K35: =N8 -> 156832 | L35: 1 | M35: =I35 -> 0.2347 | N35: =K35*L35*M35 -> 36808.47 | O35: =R8 -> 163105.28 | P35: 1 | Q35: =M35 -> 0.2347 | R35: =O35*P35*Q35 -> 38280.809 | S35: =V8 -> 169629.49 | T35: 1 | U35: =Q35 -> 0.2347 | V35: =S35*T35*U35 -> 39812.042 | W35: =F35+J35+N35+R35+V35 -> 184325.58
A36: CCN Staff | B36: ='Program Budget'!F38 -> % | C36: =F27 -> 407500 | D36: 1 | E36: ='Program Budget'!H37 -> 0.2692 | F36: =C36*D36*E36 -> 109699 | G36: =J27 -> 856960 | H36: 1 | I36: =E36 -> 0.2692 | J36: =G36*H36*I36 -> 230693.63 | K36: =N27 -> 739814.4 | L36: 1 | M36: =I36 -> 0.2692 | N36: =K36*L36*M36 -> 199158.04 | O36: =R27 -> 611926.02 | P36: 1 | Q36: =M36 -> 0.2692 | R36: =O36*P36*Q36 -> 164730.48 | S36: =V27 -> 479544.52 | T36: 1 | U36: =Q36 -> 0.2692 | V36: =S36*T36*U36 -> 129093.39 | W36: =F36+J36+N36+R36+V36 -> 833374.54
A37: HQ Staff | B37: ='Program Budget'!F39 -> % | C37: =F31 -> 110000 | D37: 1 | E37: ='Program Budget'!H38 -> 0.2347 | F37: =C37*D37*E37 -> 25817 | G37: =J31 -> 114400 | H37: 1 | I37: =E37 -> 0.2347 | J37: =G37*H37*I37 -> 26849.68 | K37: =N31 -> 118976 | L37: 1 | M37: =I37 -> 0.2347 | N37: =K37*L37*M37 -> 27923.667 | O37: =R31 -> 123735.04 | P37: 1 | Q37: =M37 -> 0.2347 | R37: =O37*P37*Q37 -> 29040.614 | S37: =V31 -> 128684.44 | T37: 1 | U37: =Q37 -> 0.2347 | V37: =S37*T37*U37 -> 30202.238 | W37: =F37+J37+N37+R37+V37 -> 139833.2
A38: Total: Fringe Benefits | F38: =+SUM(F35:F37) -> 169547.5 | J38: =+SUM(J35:J37) -> 292936.07 | N38: =+SUM(N35:N37) -> 263890.17 | R38: =+SUM(R35:R37) -> 232051.91 | V38: =+SUM(V35:V37) -> 199107.67 | W38: =+F38+J38+N38+R38+V38 -> 1157533.3
A39: Allowances
A40: USN/TCN Staff
A41: ='Program Budget'!D40 -> Cost of Living Adjustment for Ex-pat Chief of Party | B41: ='Program Budget'!F40 -> % | C41: =F8 -> 145000 | D41: 1 | E41: ='Program Budget'!H40 -> 0.15 | F41: =C41*D41*E41 -> 21750 | G41: =J8 -> 150800 | H41: 1 | I41: =E41 -> 0.15 | J41: =G41*H41*I41 -> 22620 | K41: =N8 -> 156832 | L41: 1 | M41: =I41 -> 0.15 | N41: =K41*L41*M41 -> 23524.8 | O41: =R8 -> 163105.28 | P41: 1 | Q41: =M41 -> 0.15 | R41: =O41*P41*Q41 -> 24465.792 | S41: =V8 -> 169629.49 | T41: 1 | U41: =Q41 -> 0.15 | V41: =S41*T41*U41 -> 25444.424 | W41: =F41+J41+N41+R41+V41 -> 117805.02
A42: ='Program Budget'!D41 -> Post Hardship for Ex-pat Chief of Party | B42: ='Program Budget'!F41 -> % | C42: =F7 -> 145000 | D42: 1 | E42: ='Program Budget'!H41 -> 0.35 | F42: =C42*D42*E42 -> 50750 | G42: =J7 -> 150800 | H42: 1 | I42: =E42 -> 0.35 | J42: =G42*H42*I42 -> 52780 | K42: =N7 -> 156832 | L42: 1 | M42: =I42 -> 0.35 | N42: =K42*L42*M42 -> 54891.2 | O42: =R7 -> 163105.28 | P42: 1 | Q42: =M42 -> 0.35 | R42: =O42*P42*Q42 -> 57086.848 | S42: =V7 -> 169629.49 | T42: 1 | U42: =Q42 -> 0.35 | V42: =S42*T42*U42 -> 59370.322 | W42: =F42+J42+N42+R42+V42 -> 274878.37
A43: ='Program Budget'!D42 -> Housing Allowance for Chief of Party | B43: ='Program Budget'!F42 -> Month | C43: ='Program Budget'!H42 -> 1600 | D43: ='Program Budget'!G42 -> 12 | E43: 1 | F43: =C43*D43*E43 -> 19200 | G43: =C43*1.04 -> 1664 | H43: ='Program Budget'!K42 -> 12 | I43: =E43 -> 1 | J43: =G43*H43*I43 -> 19968 | K43: =G43*1.04 -> 1730.56 | L43: ='Program Budget'!N42 -> 12 | M43: =I43 -> 1 | N43: =K43*L43*M43 -> 20766.72 | O43: =K43*1.04 -> 1799.7824 | P43: ='Program Budget'!Q42 -> 12 | Q43: =M43 -> 1 | R43: =O43*P43*Q43 -> 21597.389 | S43: =O43*1.04 -> 1871.7737 | T43: ='Program Budget'!T42 -> 12 | U43: =Q43 -> 1 | V43: =S43*T43*U43 -> 22461.284 | W43: =F43+J43+N43+R43+V43 -> 103993.39
A44: ='Program Budget'!D43 -> Reallocation & Demobilization Flight for Chief of Party and Spouse | B44: ='Program Budget'!F43 -> Trip | C44: ='Program Budget'!H43 -> 1700 | D44: ='Program Budget'!G43 -> 2 | E44: 1 | F44: =C44*D44*E44 -> 3400 | G44: =C44*1.04 -> 1768 | H44: ='Program Budget'!K43 -> 0 | I44: 0 | J44: =G44*H44*I44 -> 0 | K44: =G44*1.04 -> 1838.72 | L44: ='Program Budget'!N43 -> 0 | M44: 0 | N44: =K44*L44*M44 -> 0 | O44: =K44*1.04 -> 1912.2688 | P44: ='Program Budget'!Q43 -> 0 | Q44: 0 | R44: =O44*P44*Q44 -> 0 | S44: =O44*1.04 -> 1988.7596 | T44: ='Program Budget'!T43 -> 2 | U44: 1 | V44: =S44*T44*U44 -> 3977.5191 | W44: =F44+J44+N44+R44+V44 -> 7377.5191
A45: ='Program Budget'!D44 -> Reallocation & Demobilization Extra Baggage for Chief of Party and Spouse | B45: ='Program Budget'!F44 -> Trip | C45: ='Program Budget'!H44 -> 150 | D45: ='Program Budget'!G44 -> 2 | E45: 1 | F45: =C45*D45*E45 -> 300 | G45: =C45*1.04 -> 156 | H45: ='Program Budget'!K44 -> 0 | I45: 0 | J45: =G45*H45*I45 -> 0 | K45: =G45*1.04 -> 162.24 | L45: ='Program Budget'!N44 -> 0 | M45: 0 | N45: =K45*L45*M45 -> 0 | O45: =K45*1.04 -> 168.7296 | P45: ='Program Budget'!Q44 -> 0 | Q45: 0 | R45: =O45*P45*Q45 -> 0 | S45: =O45*1.04 -> 175.47878 | T45: ='Program Budget'!T44 -> 2 | U45: 1 | V45: =S45*T45*U45 -> 350.95757 | W45: =F45+J45+N45+R45+V45 -> 650.95757
A46: ='Program Budget'!D45 -> Reallocation & Demobilization - Shipment of Households Good (by Land & Sea) | B46: ='Program Budget'!F45 -> Year | C46: ='Program Budget'!H45 -> 21382 | D46: ='Program Budget'!G45 -> 1 | E46: 1 | F46: =C46*D46*E46 -> 21382 | G46: =C46*1.04 -> 22237.28 | H46: ='Program Budget'!K45 -> 0 | I46: 0 | J46: =G46*H46*I46 -> 0 | K46: =G46*1.04 -> 23126.771 | L46: ='Program Budget'!N45 -> 0 | M46: 0 | N46: =K46*L46*M46 -> 0 | O46: =K46*1.04 -> 24051.842 | P46: ='Program Budget'!Q45 -> 0 | Q46: 0 | R46: =O46*P46*Q46 -> 0 | S46: =O46*1.04 -> 25013.916 | T46: ='Program Budget'!T45 -> 1 | U46: 1 | V46: =S46*T46*U46 -> 25013.916 | W46: =F46+J46+N46+R46+V46 -> 46395.916
A47: ='Program Budget'!D46 -> Reallocation & Demobilization - Customs 20% and Taxes 3% | B47: ='Program Budget'!F46 -> Year | C47: ='Program Budget'!H46 -> 4917.86 | D47: ='Program Budget'!G46 -> 1 | E47: 1 | F47: =C47*D47*E47 -> 4917.86 | G47: =C47*1.04 -> 5114.5744 | H47: ='Program Budget'!K46 -> 0 | I47: 0 | J47: =G47*H47*I47 -> 0 | K47: =G47*1.04 -> 5319.1574 | L47: ='Program Budget'!N46 -> 0 | M47: 0 | N47: =K47*L47*M47 -> 0 | O47: =K47*1.04 -> 5531.9237 | P47: ='Program Budget'!Q46 -> 0 | Q47: 0 | R47: =O47*P47*Q47 -> 0 | S47: =O47*1.04 -> 5753.2006 | T47: ='Program Budget'!T46 -> 1 | U47: 1 | V47: =ROUNDUP(S47*T47*U47,0) -> 5754 | W47: =F47+J47+N47+R47+V47 -> 10671.86
A48: ='Program Budget'!D47 -> Annual Home of Record & R&R for Chief of Party | B48: ='Program Budget'!F47 -> Trip | C48: ='Program Budget'!H47 -> 1700 | D48: ='Program Budget'!G47 -> 0 | E48: 1 | F48: =C48*D48*E48 -> 0 | G48: =C48*1.04 -> 1768 | H48: ='Program Budget'!K47 -> 1 | I48: =E48 -> 1 | J48: =G48*H48*I48 -> 1768 | K48: =G48*1.04 -> 1838.72 | L48: ='Program Budget'!N47 -> 1 | M48: =I48 -> 1 | N48: =K48*L48*M48 -> 1838.72 | O48: =K48*1.04 -> 1912.2688 | P48: ='Program Budget'!Q47 -> 1 | Q48: =M48 -> 1 | R48: =O48*P48*Q48 -> 1912.2688 | S48: =O48*1.04 -> 1988.7596 | T48: ='Program Budget'!T47 -> 1 | U48: =Q48 -> 1 | V48: =S48*T48*U48 -> 1988.7596 | W48: =F48+J48+N48+R48+V48 -> 7507.7484
A49: Total: Allowances | F49: =SUM(F40:F48) -> 121699.86 | J49: =SUM(J40:J48) -> 97136 | N49: =SUM(N40:N48) -> 101021.44 | R49: =SUM(R40:R48) -> 105062.3 | V49: =SUM(V40:V48) -> 144361.18 | W49: =F49+J49+N49+R49+V49 -> 569280.78
A51: Subtotal: Benefits | F51: =F49+F38 -> 291247.36 | J51: =J49+J38 -> 390072.07 | N51: =N49+N38 -> 364911.61 | R51: =R49+R38 -> 337114.2 | V51: =V49+V38 -> 343468.85 | W51: =+F51+J51+N51+R51+V51 -> 1726814.1
A52: International Travel
A53: ='Program Budget'!D53 -> Airfare - DC-Mauritania - HQ Project Management Trip | B53: ='Program Budget'!F53 -> Trip | C53: ='Program Budget'!H53 -> 1700 | D53: ='Program Budget'!G53 -> 4 | E53: 1 | F53: =C53*D53*E53 -> 6800 | G53: =C53*1.04 -> 1768 | H53: ='Program Budget'!K53 -> 4 | I53: 1 | J53: =G53*H53*I53 -> 7072 | K53: =G53*1.04 -> 1838.72 | L53: ='Program Budget'!N53 -> 4 | M53: 1 | N53: =K53*L53*M53 -> 7354.88 | O53: =K53*1.04 -> 1912.2688 | P53: ='Program Budget'!Q53 -> 4 | Q53: 1 | R53: =O53*P53*Q53 -> 7649.0752 | S53: =O53*1.04 -> 1988.7596 | T53: ='Program Budget'!T53 -> 4 | U53: 1 | V53: =S53*T53*U53 -> 7955.0382 | W53: =F53+J53+N53+R53+V53 -> 36830.993
A54: ='Program Budget'!D58 -> Airfare - Roundtrip - Mauritania to USA | B54: ='Program Budget'!F58 -> Trip | C54: ='Program Budget'!H58 -> 1700 | D54: ='Program Budget'!G58 -> 3 | E54: 1 | F54: =C54*D54*E54 -> 5100 | G54: =C54*1.04 -> 1768 | H54: ='Program Budget'!K58 -> 3 | I54: 1 | J54: =G54*H54*I54 -> 5304 | K54: =G54*1.04 -> 1838.72 | L54: ='Program Budget'!N58 -> 3 | M54: 1 | N54: =K54*L54*M54 -> 5516.16 | O54: =K54*1.04 -> 1912.2688 | P54: ='Program Budget'!Q58 -> 3 | Q54: 1 | R54: =O54*P54*Q54 -> 5736.8064 | S54: =O54*1.04 -> 1988.7596 | T54: ='Program Budget'!T58 -> 3 | U54: 1 | V54: =S54*T54*U54 -> 5966.2787 | W54: =F54+J54+N54+R54+V54 -> 27623.245
A55: Local Travel
A56: ='Program Budget'!D55 -> Local Transportation – HQ Project Management Trip | B56: ='Program Budget'!F55 -> Trip | C56: ='Program Budget'!H55 -> 250 | D56: ='Program Budget'!G55 -> 4 | E56: 1 | F56: =C56*D56*E56 -> 1000 | G56: =C56*1.04 -> 260 | H56: ='Program Budget'!K55 -> 4 | I56: 1 | J56: =G56*H56*I56 -> 1040 | K56: =G56*1.04 -> 270.4 | L56: ='Program Budget'!N55 -> 4 | M56: 1 | N56: =K56*L56*M56 -> 1081.6 | O56: =K56*1.04 -> 281.216 | P56: ='Program Budget'!Q55 -> 4 | Q56: 1 | R56: =O56*P56*Q56 -> 1124.864 | S56: =O56*1.04 -> 292.46464 | T56: ='Program Budget'!T55 -> 4 | U56: 1 | V56: =S56*T56*U56 -> 1169.8586 | W56: =F56+J56+N56+R56+V56 -> 5416.3226
A57: ='Program Budget'!D60 -> Local Transportation for Mauritania Staff Travel | B57: ='Program Budget'!F64 -> Trip | C57: ='Program Budget'!H60 -> 250 | D57: ='Program Budget'!G60 -> 3 | E57: 1 | F57: =C57*D57*E57 -> 750 | G57: =C57*1.04 -> 260 | H57: ='Program Budget'!K60 -> 3 | I57: 1 | J57: =G57*H57*I57 -> 780 | K57: =G57*1.04 -> 270.4 | L57: ='Program Budget'!N60 -> 3 | M57: 1 | N57: =K57*L57*M57 -> 811.2 | O57: =K57*1.04 -> 281.216 | P57: ='Program Budget'!Q60 -> 3 | Q57: 1 | R57: =O57*P57*Q57 -> 843.648 | S57: =O57*1.04 -> 292.46464 | T57: ='Program Budget'!T60 -> 3 | U57: 1 | V57: =S57*T57*U57 -> 877.39392 | W57: =F57+J57+N57+R57+V57 -> 4062.2419
A58: ='Program Budget'!D64 -> Local Transportation – Training, M&E, & Data Collection | B58: ='Program Budget'!F64 -> Trip | C58: ='Program Budget'!H64 -> 100 | D58: ='Program Budget'!G64 -> 36 | E58: 1 | F58: =C58*D58*E58 -> 3600 | G58: =C58*1.04 -> 104 | H58: ='Program Budget'!K64 -> 36 | I58: 1 | J58: =G58*H58*I58 -> 3744 | K58: =G58*1.04 -> 108.16 | L58: ='Program Budget'!N64 -> 36 | M58: 1 | N58: =K58*L58*M58 -> 3893.76 | O58: =K58*1.04 -> 112.4864 | P58: ='Program Budget'!Q64 -> 36 | Q58: 1 | R58: =O58*P58*Q58 -> 4049.5104 | S58: =O58*1.04 -> 116.98586 | T58: ='Program Budget'!T64 -> 36 | U58: 1 | V58: =S58*T58*U58 -> 4211.4908 | W58: =F58+J58+N58+R58+V58 -> 19498.761
A59: ='Program Budget'!D189 -> Local Transportation for Trainings | B59: ='Program Budget'!F189 -> Trip | C59: ='Program Budget'!H189 -> 100 | D59: ='Activity 1'!D41+'Activity 2'!D40+'Activity 3'!D41+'Activity 4'!D39 -> 24 | E59: 1 | F59: =C59*D59*E59 -> 2400 | G59: =C59*1.04 -> 104 | H59: ='Activity 1'!H41+'Activity 2'!H40+'Activity 3'!H41+'Activity 4'!H39 -> 48 | I59: 1 | J59: =G59*H59*I59 -> 4992 | K59: =G59*1.04 -> 108.16 | L59: ='Activity 1'!L41+'Activity 2'!L40+'Activity 3'!L41+'Activity 4'!L39 -> 48 | M59: 1 | N59: =K59*L59*M59 -> 5191.68 | O59: =K59*1.04 -> 112.4864 | P59: ='Activity 1'!P41+'Activity 2'!P40+'Activity 3'!P41+'Activity 4'!P39 -> 48 | Q59: 1 | R59: =O59*P59*Q59 -> 5399.3472 | S59: =O59*1.04 -> 116.98586 | T59: ='Activity 1'!T41+'Activity 2'!T40+'Activity 3'!T41+'Activity 4'!T39 -> 36 | U59: 1 | V59: =S59*T59*U59 -> 4211.4908 | W59: =F59+J59+N59+R59+V59 -> 22194.518
A60: ='Program Budget'!D191 -> Transport Stipends for Participants to attend Trainings | B60: ='Program Budget'!F191 -> Participant | C60: ='Program Budget'!H191 -> 10 | D60: ='Program Budget'!G191 -> 6000 | E60: 1 | F60: =C60*D60*E60 -> 60000 | G60: =C60*1.04 -> 10.4 | H60: ='Program Budget'!K191 -> 6000 | I60: 1 | J60: =G60*H60*I60 -> 62400 | K60: =G60*1.04 -> 10.816 | L60: ='Program Budget'!N191 -> 0 | M60: 1 | N60: =K60*L60*M60 -> 0 | O60: =K60*1.04 -> 11.24864 | P60: ='Program Budget'!Q191 -> 0 | Q60: 1 | R60: =O60*P60*Q60 -> 0 | S60: =O60*1.04 -> 11.698586 | T60: ='Program Budget'!T191 -> 0 | U60: 1 | V60: =S60*T60*U60 -> 0 | W60: =F60+J60+N60+R60+V60 -> 122400
A61: ='Program Budget'!D252 -> Transport Stipends for Participants to attend Farmer Field Schools | B61: ='Program Budget'!F252 -> Participant | C61: ='Program Budget'!H252 -> 10 | D61: ='Program Budget'!G252 -> 0 | E61: 1 | F61: =C61*D61*E61 -> 0 | G61: =C61*1.04 -> 10.4 | H61: ='Program Budget'!K252 -> 1000 | I61: 1 | J61: =G61*H61*I61 -> 10400 | K61: =G61*1.04 -> 10.816 | L61: ='Program Budget'!N252 -> 1000 | M61: 1 | N61: =K61*L61*M61 -> 10816 | O61: =K61*1.04 -> 11.24864 | P61: ='Program Budget'!Q252 -> 1000 | Q61: 1 | R61: =O61*P61*Q61 -> 11248.64 | S61: =O61*1.04 -> 11.698586 | T61: ='Program Budget'!T252 -> 0 | U61: 1 | V61: =S61*T61*U61 -> 0 | W61: =F61+J61+N61+R61+V61 -> 32464.64
A62: ='Program Budget'!D382 -> Transport Costs for Trade Shows and Events | B62: ='Program Budget'!F382 -> Trip | C62: ='Program Budget'!H382 -> 1800 | D62: ='Program Budget'!G382 -> 4 | E62: 1 | F62: =C62*D62*E62 -> 7200 | G62: =C62*1.04 -> 1872 | H62: ='Program Budget'!K382 -> 4 | I62: 1 | J62: =G62*H62*I62 -> 7488 | K62: =G62*1.04 -> 1946.88 | L62: ='Program Budget'!N382 -> 4 | M62: 1 | N62: =K62*L62*M62 -> 7787.52 | O62: =K62*1.04 -> 2024.7552 | P62: ='Program Budget'!Q382 -> 4 | Q62: 1 | R62: =O62*P62*Q62 -> 8099.0208 | S62: =O62*1.04 -> 2105.7454 | T62: ='Program Budget'!T382 -> 4 | U62: 1 | V62: =S62*T62*U62 -> 8422.9816 | W62: =F62+J62+N62+R62+V62 -> 38997.522
A63: Vehicle Fuel
A64: =Admin!A60 -> Motorcycle and Vehicle Fuel Expense | B64: ='Program Budget'!F188 -> Month | C64: =Admin!C60+'Activity 1'!C44+'Activity 2'!C43+'Activity 3'!C43+'Activity 4'!C42 -> 740 | D64: ='Activity 1'!D44 -> 3 | E64: 1 | F64: =C64*D64*E64 -> 2220 | G64: =C64*1.04 -> 769.6 | H64: ='Program Budget'!K189 -> 12 | I64: 1 | J64: =G64*H64*I64 -> 9235.2 | K64: =G64*1.04 -> 800.384 | L64: ='Program Budget'!N188 -> 12 | M64: 1 | N64: =K64*L64*M64 -> 9604.608 | O64: =K64*1.04 -> 832.39936 | P64: ='Program Budget'!Q188 -> 12 | Q64: 1 | R64: =O64*P64*Q64 -> 9988.7923 | S64: =O64*1.04 -> 865.69533 | T64: ='Program Budget'!T188 -> 7 | U64: 1 | V64: =S64*T64*U64 -> 6059.8673 | W64: =F64+J64+N64+R64+V64 -> 37108.468
A65: Per Diem
A66: ='Program Budget'!D54 -> Lodging and M&IE - HQ Project Management Trip | B66: ='Program Budget'!F54 -> Day | C66: ='Program Budget'!H54 -> 169 | D66: ='Program Budget'!G54 -> 28 | E66: 1 | F66: =C66*D66*E66 -> 4732 | G66: =C66*1.04 -> 175.76 | H66: ='Program Budget'!K54 -> 28 | I66: 1 | J66: =G66*H66*I66 -> 4921.28 | K66: =G66*1.04 -> 182.7904 | L66: ='Program Budget'!N54 -> 28 | M66: 1 | N66: =K66*L66*M66 -> 5118.1312 | O66: =K66*1.04 -> 190.10202 | P66: ='Program Budget'!Q54 -> 28 | Q66: 1 | R66: =O66*P66*Q66 -> 5322.8564 | S66: =O66*1.04 -> 197.7061 | T66: ='Program Budget'!T54 -> 28 | U66: 1 | V66: =S66*T66*U66 -> 5535.7707 | W66: =F66+J66+N66+R66+V66 -> 25630.038
A67: ='Program Budget'!D56 -> Other Travel Related Expenses – HQ Project Management Trip | B67: ='Program Budget'!F56 -> Trip | C67: ='Program Budget'!H56 -> 50 | D67: ='Program Budget'!G56 -> 4 | E67: 1 | F67: =C67*D67*E67 -> 200 | G67: =C67*1.04 -> 52 | H67: ='Program Budget'!K56 -> 4 | I67: 1 | J67: =G67*H67*I67 -> 208 | K67: =G67*1.04 -> 54.08 | L67: ='Program Budget'!N56 -> 4 | M67: 1 | N67: =K67*L67*M67 -> 216.32 | O67: =K67*1.04 -> 56.2432 | P67: ='Program Budget'!Q56 -> 4 | Q67: 1 | R67: =O67*P67*Q67 -> 224.9728 | S67: =O67*1.04 -> 58.492928 | T67: ='Program Budget'!T56 -> 4 | U67: 1 | V67: =S67*T67*U67 -> 233.97171 | W67: =F67+J67+N67+R67+V67 -> 1083.2645
A68: ='Program Budget'!D59 -> Lodging and M&IE for Mauritania Staff Travel | B68: ='Program Budget'!F59 -> Day | C68: ='Program Budget'!H59 -> 169 | D68: ='Program Budget'!G59 -> 21 | E68: 1 | F68: =C68*D68*E68 -> 3549 | G68: =C68*1.04 -> 175.76 | H68: ='Program Budget'!K59 -> 21 | I68: 1 | J68: =G68*H68*I68 -> 3690.96 | K68: =G68*1.04 -> 182.7904 | L68: ='Program Budget'!N59 -> 21 | M68: 1 | N68: =K68*L68*M68 -> 3838.5984 | O68: =K68*1.04 -> 190.10202 | P68: ='Program Budget'!Q59 -> 21 | Q68: 1 | R68: =O68*P68*Q68 -> 3992.1423 | S68: =O68*1.04 -> 197.7061 | T68: ='Program Budget'!T59 -> 21 | U68: 1 | V68: =S68*T68*U68 -> 4151.828 | W68: =F68+J68+N68+R68+V68 -> 19222.529
A69: ='Program Budget'!D61 -> Other Travel Related Expenses for Mauritania Staff Travel | B69: ='Program Budget'!F61 -> Trip | C69: ='Program Budget'!H61 -> 50 | D69: ='Program Budget'!G61 -> 3 | E69: 1 | F69: =C69*D69*E69 -> 150 | G69: =C69*1.04 -> 52 | H69: ='Program Budget'!K61 -> 3 | I69: 1 | J69: =G69*H69*I69 -> 156 | K69: =G69*1.04 -> 54.08 | L69: ='Program Budget'!N61 -> 3 | M69: 1 | N69: =K69*L69*M69 -> 162.24 | O69: =K69*1.04 -> 56.2432 | P69: ='Program Budget'!Q61 -> 3 | Q69: 1 | R69: =O69*P69*Q69 -> 168.7296 | S69: =O69*1.04 -> 58.492928 | T69: ='Program Budget'!T61 -> 3 | U69: 1 | V69: =S69*T69*U69 -> 175.47878 | W69: =F69+J69+N69+R69+V69 -> 812.44838
A70: ='Program Budget'!D65 -> Lodging and M&IE - Training, M&E, & Data Collection | B70: ='Program Budget'!F65 -> Day | C70: ='Program Budget'!H65 -> 78 | D70: ='Program Budget'!G65 -> 144 | E70: 1 | F70: =C70*D70*E70 -> 11232 | G70: =C70*1.04 -> 81.12 | H70: ='Program Budget'!K65 -> 144 | I70: 1 | J70: =G70*H70*I70 -> 11681.28 | K70: =G70*1.04 -> 84.3648 | L70: ='Program Budget'!N65 -> 144 | M70: 1 | N70: =K70*L70*M70 -> 12148.531 | O70: =K70*1.04 -> 87.739392 | P70: ='Program Budget'!Q65 -> 144 | Q70: 1 | R70: =O70*P70*Q70 -> 12634.472 | S70: =O70*1.04 -> 91.248968 | T70: ='Program Budget'!T65 -> 144 | U70: 1 | V70: =S70*T70*U70 -> 13139.851 | W70: =F70+J70+N70+R70+V70 -> 60836.135
A71: ='Program Budget'!D190 -> Lodging and M&IE for Trainings | B71: ='Program Budget'!F190 -> Day | C71: ='Program Budget'!H190 -> 78 | D71: ='Activity 1'!D46+'Activity 2'!D45+'Activity 3'!D45+'Activity 4'!D44 -> 72 | E71: 1 | F71: =C71*D71*E71 -> 5616 | G71: =C71*1.04 -> 81.12 | H71: ='Activity 1'!H46+'Activity 2'!H45+'Activity 3'!H45+'Activity 4'!H44 -> 144 | I71: 1 | J71: =G71*H71*I71 -> 11681.28 | K71: =G71*1.04 -> 84.3648 | L71: ='Activity 1'!L46+'Activity 2'!L45+'Activity 3'!L45+'Activity 4'!L44 -> 144 | M71: 1 | N71: =K71*L71*M71 -> 12148.531 | O71: =K71*1.04 -> 87.739392 | P71: ='Activity 1'!P46+'Activity 2'!P45+'Activity 3'!P45+'Activity 4'!P44 -> 144 | Q71: 1 | R71: =O71*P71*Q71 -> 12634.472 | S71: =O71*1.04 -> 91.248968 | T71: ='Activity 1'!T46+'Activity 2'!T45+'Activity 3'!T45+'Activity 4'!T44 -> 108 | U71: 1 | V71: =S71*T71*U71 -> 9854.8885 | W71: =F71+J71+N71+R71+V71 -> 51935.172
A72: ='Program Budget'!D307 -> Lodging and M&IE for PASP Program Participant | B72: ='Program Budget'!F307 -> Week | C72: ='Program Budget'!H307 -> 160 | D72: ='Program Budget'!G307 -> 0 | E72: 1 | F72: =C72*D72*E72 -> 0 | G72: =C72*1.04 -> 166.4 | H72: ='Program Budget'!K307 -> 400 | I72: 1 | J72: =G72*H72*I72 -> 66560 | K72: =G72*1.04 -> 173.056 | L72: ='Program Budget'!N307 -> 400 | M72: 1 | N72: =K72*L72*M72 -> 69222.4 | O72: =K72*1.04 -> 179.97824 | P72: ='Program Budget'!Q307 -> 400 | Q72: 1 | R72: =O72*P72*Q72 -> 71991.296 | S72: =O72*1.04 -> 187.17737 | T72: ='Program Budget'!T307 -> 0 | U72: 1 | V72: =S72*T72*U72 -> 0 | W72: =F72+J72+N72+R72+V72 -> 207773.7
A73: ='Program Budget'!D383 -> Lodging and M&IE for Trade Shows and Events | B73: ='Program Budget'!F383 -> Day | C73: ='Program Budget'!H383 -> 160 | D73: ='Program Budget'!G383 -> 20 | E73: 1 | F73: =C73*D73*E73 -> 3200 | G73: =C73*1.04 -> 166.4 | H73: ='Program Budget'!K383 -> 20 | I73: 1 | J73: =G73*H73*I73 -> 3328 | K73: =G73*1.04 -> 173.056 | L73: ='Program Budget'!N383 -> 20 | M73: 1 | N73: =K73*L73*M73 -> 3461.12 | O73: =K73*1.04 -> 179.97824 | P73: ='Program Budget'!Q383 -> 20 | Q73: 1 | R73: =O73*P73*Q73 -> 3599.5648 | S73: =O73*1.04 -> 187.17737 | T73: ='Program Budget'!T383 -> 20 | U73: 1 | V73: =S73*T73*U73 -> 3743.5474 | W73: =F73+J73+N73+R73+V73 -> 17332.232
A75: Subtotal: Travel | F75: =SUM(F53:F74) -> 117749 | J75: =SUM(J53:J74) -> 214682 | N75: =SUM(N53:N74) -> 158373.28 | R75: =SUM(R53:R74) -> 164708.21 | V75: =SUM(V53:V74) -> 75709.736 | W75: =SUM(W53:W74) -> 731222.23
A76: Professional Services
A77: ='Program Budget'!D69 -> Monetization Agent Fee | B77: ='Program Budget'!F69 -> % | C77: ='Program Budget'!I69+'Program Budget'!L69 -> 280000 | D77: 0.5 | E77: 1 | F77: =C77*D77*E77 -> 140000 | G77: =C77 -> 280000 | H77: 0.5 | I77: 1 | J77: =G77*H77*I77 -> 140000 | K77: =G77 -> 280000 | L77: ='Program Budget'!N69 -> 0 | M77: 1 | N77: =K77*L77*M77 -> 0 | O77: =K77 -> 280000 | P77: ='Program Budget'!Q699 -> 0 | Q77: 1 | R77: =O77*P77*Q77 -> 0 | S77: =O77 -> 280000 | T77: ='Program Budget'!T69 -> 0 | U77: 1 | V77: =S77*T77*U77 -> 0 | W77: =F77+J77+N77+R77+V77 -> 280000
A78: ='Program Budget'!D70 -> Monetization Impact Assessment | B78: ='Program Budget'!F70 -> Unit | C78: ='Program Budget'!H70 -> 48000 | D78: ='Program Budget'!G70 -> 0 | E78: 1 | F78: =C78*D78*E78 -> 0 | G78: =C78 -> 48000 | H78: ='Program Budget'!K70 -> 1 | I78: 1 | J78: =G78*H78*I78 -> 48000 | K78: =G78 -> 48000 | L78: ='Program Budget'!N70 -> 0 | M78: 1 | N78: =K78*L78*M78 -> 0 | O78: =K78 -> 48000 | P78: ='Program Budget'!Q70 -> 0 | Q78: 1 | R78: =O78*P78*Q78 -> 0 | S78: =O78 -> 48000 | T78: ='Program Budget'!T70 -> 0 | U78: 1 | V78: =S78*T78*U78 -> 0 | W78: =F78+J78+N78+R78+V78 -> 48000
A79: ='Program Budget'!D71 -> Audit Costs - (Program Specific Audits) | B79: ='Program Budget'!F71 -> Year | C79: ='Program Budget'!H71 -> 8000 | D79: ='Program Budget'!G71 -> 1 | E79: 1 | F79: =C79*D79*E79 -> 8000 | G79: =C79 -> 8000 | H79: ='Program Budget'!K71 -> 1 | I79: 1 | J79: =G79*H79*I79 -> 8000 | K79: =G79 -> 8000 | L79: ='Program Budget'!N71 -> 1 | M79: 1 | N79: =K79*L79*M79 -> 8000 | O79: =K79 -> 8000 | P79: ='Program Budget'!Q71 -> 1 | Q79: 1 | R79: =O79*P79*Q79 -> 8000 | S79: =O79 -> 8000 | T79: ='Program Budget'!T71 -> 1 | U79: 1 | V79: =S79*T79*U79 -> 8000 | W79: =F79+J79+N79+R79+V79 -> 40000
A80: ='Program Budget'!D72 -> Legal Fees | B80: ='Program Budget'!F72 -> Year | C80: ='Program Budget'!H72 -> 3000 | D80: ='Program Budget'!G72 -> 1 | E80: 1 | F80: =C80*D80*E80 -> 3000 | G80: =C80 -> 3000 | H80: ='Program Budget'!K72 -> 1 | I80: 1 | J80: =G80*H80*I80 -> 3000 | K80: =G80 -> 3000 | L80: ='Program Budget'!N72 -> 1 | M80: 1 | N80: =K80*L80*M80 -> 3000 | O80: =K80 -> 3000 | P80: ='Program Budget'!Q72 -> 1 | Q80: 1 | R80: =O80*P80*Q80 -> 3000 | S80: =O80 -> 3000 | T80: ='Program Budget'!T72 -> 1 | U80: 1 | V80: =S80*T80*U80 -> 3000 | W80: =F80+J80+N80+R80+V80 -> 15000
A81: ='Program Budget'!D73 -> Security Services, Risk Assessments, & Security Assessment | B81: ='Program Budget'!F73 -> Year | C81: =Admin!C74+'Activity 1'!C52+'Activity 2'!C53+'Activity 3'!C51+'Activity 4'!C50 -> 26500 | D81: ='Program Budget'!G73 -> 1 | E81: 1 | F81: =C81*D81*E81 -> 26500 | G81: =C81 -> 26500 | H81: ='Program Budget'!K73 -> 1 | I81: 1 | J81: =G81*H81*I81 -> 26500 | K81: =G81 -> 26500 | L81: ='Program Budget'!N73 -> 1 | M81: 1 | N81: =K81*L81*M81 -> 26500 | O81: =K81 -> 26500 | P81: ='Program Budget'!Q73 -> 1 | Q81: 1 | R81: =O81*P81*Q81 -> 26500 | S81: =O81 -> 26500 | T81: ='Program Budget'!T73 -> 1 | U81: 1 | V81: =S81*T81*U81 -> 26500 | W81: =F81+J81+N81+R81+V81 -> 132500
A82: ='Program Budget'!D74 -> Short-Term Technical Advisors | B82: ='Program Budget'!F74 -> Month | C82: =Admin!C75+'Activity 1'!C53+'Activity 2'!C54+'Activity 3'!C52+'Activity 4'!C51 -> 2575 | D82: ='Program Budget'!G74 -> 9 | E82: 1 | F82: =C82*D82*E82 -> 23175 | G82: =C82 -> 2575 | H82: ='Program Budget'!K74 -> 12 | I82: 1 | J82: =G82*H82*I82 -> 30900 | K82: =G82 -> 2575 | L82: ='Program Budget'!N74 -> 12 | M82: 1 | N82: =K82*L82*M82 -> 30900 | O82: =K82 -> 2575 | P82: ='Program Budget'!Q74 -> 12 | Q82: 1 | R82: =O82*P82*Q82 -> 30900 | S82: =O82 -> 2575 | T82: ='Program Budget'!T74 -> 9 | U82: 1 | V82: =S82*T82*U82 -> 23175 | W82: =F82+J82+N82+R82+V82 -> 139050
A83: ='Program Budget'!D75 -> Start-up Consultant | B83: ='Program Budget'!F75 -> Day | C83: ='Program Budget'!H75 -> 705 | D83: ='Program Budget'!G75 -> 30 | E83: 1 | F83: =C83*D83*E83 -> 21150 | G83: =C83 -> 705 | H83: ='Program Budget'!K75 -> 0 | I83: 1 | J83: =G83*H83*I83 -> 0 | K83: =G83 -> 705 | L83: ='Program Budget'!N75 -> 0 | M83: 1 | N83: =K83*L83*M83 -> 0 | O83: =K83 -> 705 | P83: ='Program Budget'!Q75 -> 0 | Q83: 1 | R83: =O83*P83*Q83 -> 0 | S83: =O83 -> 705 | T83: ='Program Budget'!T75 -> 0 | U83: 1 | V83: =S83*T83*U83 -> 0 | W83: =F83+J83+N83+R83+V83 -> 21150
A84: ='Program Budget'!D76 -> Technical Advisor of Trade Promotion & Strategic Partnership & Investment | B84: ='Program Budget'!F76 -> Month | C84: =150000/12 -> 12500 | D84: ='Program Budget'!G76 -> 12 | E84: =Admin!E77+'Activity 1'!E54+'Activity 2'!E55+'Activity 3'!E53+'Activity 4'!E52 -> 0.3 | F84: =C84*D84*E84 -> 45000 | G84: =C84 -> 12500 | H84: 12 | I84: =Admin!I77+'Activity 1'!I54+'Activity 2'!I55+'Activity 3'!I53+'Activity 4'!I52 -> 0.3 | J84: =G84*H84*I84 -> 45000 | K84: =G84 -> 12500 | L84: 12 | M84: =Admin!M77+'Activity 1'!M54+'Activity 2'!M55+'Activity 3'!M53+'Activity 4'!M52 -> 0.3 | N84: =K84*L84*M84 -> 45000 | O84: =K84 -> 12500 | P84: 12 | Q84: =Admin!Q77+'Activity 1'!Q54+'Activity 2'!Q55+'Activity 3'!Q53+'Activity 4'!Q52 -> 0.3 | R84: =O84*P84*Q84 -> 45000 | S84: =O84 -> 12500 | T84: 9 | U84: =Admin!U77+'Activity 1'!U54+'Activity 2'!U55+'Activity 3'!U53+'Activity 4'!U52 -> 0.3 | V84: =S84*T84*U84 -> 33750 | W84: =F84+J84+N84+R84+V84 -> 213750
A85: ='Program Budget'!D174 -> Contract to 6th Grain for GIS Mapping and Remote Sensing Technologies | B85: ='Program Budget'!F174 -> Unit | C85: ='Program Budget'!H174 -> 300000 | D85: ='Program Budget'!G174 -> 0.5 | E85: 1 | F85: =C85*D85*E85 -> 150000 | G85: =C85 -> 300000 | H85: ='Program Budget'!K174 -> 0.5 | I85: 1 | J85: =G85*H85*I85 -> 150000 | K85: =G85 -> 300000 | L85: ='Program Budget'!N174 -> 0 | M85: 1 | N85: =K85*L85*M85 -> 0 | O85: =K85 -> 300000 | P85: ='Program Budget'!Q174 -> 0 | Q85: 1 | R85: =O85*P85*Q85 -> 0 | S85: =O85 -> 300000 | T85: ='Program Budget'!T174 -> 0 | U85: 1 | V85: =S85*T85*U85 -> 0 | W85: =F85+J85+N85+R85+V85 -> 300000
A86: ='Program Budget'!D175 -> Expert Technical Irrigation Hydrology Engineers - one for large scale infrastructure and one for on-farm irrigation | B86: ='Program Budget'!F175 -> Month | C86: ='Program Budget'!H175 -> 6000 | D86: ='Program Budget'!G175 -> 6 | E86: 1 | F86: =C86*D86*E86 -> 36000 | G86: =C86 -> 6000 | H86: ='Program Budget'!K175 -> 0 | I86: 1 | J86: =G86*H86*I86 -> 0 | K86: =G86 -> 6000 | L86: ='Program Budget'!N175 -> 0 | M86: 1 | N86: =K86*L86*M86 -> 0 | O86: =K86 -> 6000 | P86: ='Program Budget'!Q175 -> 0 | Q86: 1 | R86: =O86*P86*Q86 -> 0 | S86: =O86 -> 6000 | T86: ='Program Budget'!T175 -> 0 | U86: 1 | V86: =S86*T86*U86 -> 0 | W86: =F86+J86+N86+R86+V86 -> 36000
A87: ='Program Budget'!D234 -> Consultant to Design Materials for Outreach and Awareness Campaign including Translation | B87: ='Program Budget'!F234 -> Unit | C87: ='Program Budget'!H234 -> 30000 | D87: ='Program Budget'!G234 -> 1 | E87: 1 | F87: =C87*D87*E87 -> 30000 | G87: =C87 -> 30000 | H87: ='Program Budget'!K234 -> 0 | I87: 1 | J87: =G87*H87*I87 -> 0 | K87: =G87 -> 30000 | L87: ='Program Budget'!N234 -> 0 | M87: 1 | N87: =K87*L87*M87 -> 0 | O87: =K87 -> 30000 | P87: ='Program Budget'!Q234 -> 0 | Q87: 1 | R87: =O87*P87*Q87 -> 0 | S87: =O87 -> 30000 | T87: ='Program Budget'!T234 -> 0 | U87: 1 | V87: =S87*T87*U87 -> 0 | W87: =F87+J87+N87+R87+V87 -> 30000
A88: ='Program Budget'!D235 -> Contract for Dissemination of Outreach and Awareness Campaigns | B88: ='Program Budget'!F235 -> Year | C88: ='Program Budget'!H235 -> 60000 | D88: ='Program Budget'!G235 -> 0 | E88: 1 | F88: =C88*D88*E88 -> 0 | G88: =C88 -> 60000 | H88: ='Program Budget'!K235 -> 0 | I88: 1 | J88: =G88*H88*I88 -> 0 | K88: =G88 -> 60000 | L88: ='Program Budget'!N235 -> 1 | M88: 1 | N88: =K88*L88*M88 -> 60000 | O88: =K88 -> 60000 | P88: ='Program Budget'!Q235 -> 1 | Q88: 1 | R88: =O88*P88*Q88 -> 60000 | S88: =O88 -> 60000 | T88: ='Program Budget'!T235 -> 1 | U88: 1 | V88: =S88*T88*U88 -> 60000 | W88: =F88+J88+N88+R88+V88 -> 180000
A89: ='Program Budget'!D236 -> Contract Nurseries in Mauritania and Senegal | B89: ='Program Budget'!F236 -> Contract | C89: ='Program Budget'!H236 -> 10000 | D89: ='Program Budget'!G236 -> 5 | E89: 1 | F89: =C89*D89*E89 -> 50000 | G89: =C89 -> 10000 | H89: ='Program Budget'!K236 -> 0 | I89: 1 | J89: =G89*H89*I89 -> 0 | K89: =G89 -> 10000 | L89: ='Program Budget'!N236 -> 0 | M89: 1 | N89: =K89*L89*M89 -> 0 | O89: =K89 -> 10000 | P89: ='Program Budget'!Q236 -> 0 | Q89: 1 | R89: =O89*P89*Q89 -> 0 | S89: =O89 -> 10000 | T89: ='Program Budget'!T236 -> 0 | U89: 1 | V89: =S89*T89*U89 -> 0 | W89: =F89+J89+N89+R89+V89 -> 50000
A90: ='Program Budget'!D237 -> Consultant to Create Outreach and Sensitization Materials for Social Behavioral Change Activities | B90: ='Program Budget'!F237 -> Month | C90: ='Program Budget'!H237 -> 3000 | D90: ='Program Budget'!G237 -> 0 | E90: 1 | F90: =C90*D90*E90 -> 0 | G90: =C90 -> 3000 | H90: ='Program Budget'!K237 -> 2 | I90: 1 | J90: =G90*H90*I90 -> 6000 | K90: =G90 -> 3000 | L90: ='Program Budget'!N237 -> 2 | M90: 1 | N90: =K90*L90*M90 -> 6000 | O90: =K90 -> 3000 | P90: ='Program Budget'!Q237 -> 2 | Q90: 1 | R90: =O90*P90*Q90 -> 6000 | S90: =O90 -> 3000 | T90: ='Program Budget'!T237 -> 0 | U90: 1 | V90: =S90*T90*U90 -> 0 | W90: =F90+J90+N90+R90+V90 -> 18000
A91: ='Program Budget'!D292 -> Develop Modules for PASP Certification Program | B91: ='Program Budget'!F292 -> Contract | C91: ='Program Budget'!H292 -> 20000 | D91: ='Program Budget'!G292 -> 1 | E91: 1 | F91: =C91*D91*E91 -> 20000 | G91: =C91 -> 20000 | H91: ='Program Budget'!K292 -> 0 | I91: 1 | J91: =G91*H91*I91 -> 0 | K91: =G91 -> 20000 | L91: ='Program Budget'!N292 -> 0 | M91: 1 | N91: =K91*L91*M91 -> 0 | O91: =K91 -> 20000 | P91: ='Program Budget'!Q292 -> 0 | Q91: 1 | R91: =O91*P91*Q91 -> 0 | S91: =O91 -> 20000 | T91: ='Program Budget'!T292 -> 0 | U91: 1 | V91: =S91*T91*U91 -> 0 | W91: =F91+J91+N91+R91+V91 -> 20000
A92: ='Program Budget'!D359 -> Cold Chain Feasibility Study | B92: ='Program Budget'!F359 -> Contract | C92: ='Program Budget'!H359 -> 350000 | D92: ='Program Budget'!G359 -> 0.5 | E92: 1 | F92: =C92*D92*E92 -> 175000 | G92: =C92 -> 350000 | H92: ='Program Budget'!K359 -> 0.5 | I92: 1 | J92: =G92*H92*I92 -> 175000 | K92: =G92 -> 350000 | L92: ='Program Budget'!N359 -> 0 | M92: 1 | N92: =K92*L92*M92 -> 0 | O92: =K92 -> 350000 | P92: ='Program Budget'!Q359 -> 0 | Q92: 1 | R92: =O92*P92*Q92 -> 0 | S92: =O92 -> 350000 | T92: ='Program Budget'!T359 -> 0 | U92: 1 | V92: =S92*T92*U92 -> 0 | W92: =F92+J92+N92+R92+V92 -> 350000
A93: ='Program Budget'!D77 -> Monitoring, Evaluation, and Collection of Reliable Data
A94: ='Program Budget'!D78 -> Evaluations
A95: ='Program Budget'!D79 -> Baseline Evaluation | B95: ='Program Budget'!F79 -> Unit | C95: ='Program Budget'!H79 -> 150000 | D95: ='Program Budget'!G79 -> 1 | E95: 1 | F95: =C95*D95*E95 -> 150000 | G95: =C95 -> 150000 | H95: ='Program Budget'!K79 -> 0 | I95: 1 | J95: =G95*H95*I95 -> 0 | K95: =G95 -> 150000 | L95: ='Program Budget'!N79 -> 0 | M95: 1 | N95: =K95*L95*M95 -> 0 | O95: =K95 -> 150000 | P95: ='Program Budget'!Q79 -> 0 | Q95: 1 | R95: =O95*P95*Q95 -> 0 | S95: =O95 -> 150000 | T95: ='Program Budget'!T79 -> 0 | U95: 1 | V95: =S95*T95*U95 -> 0 | W95: =F95+J95+N95+R95+V95 -> 150000
A96: ='Program Budget'!D80 -> Midterm Evaluation | B96: ='Program Budget'!F80 -> Unit | C96: ='Program Budget'!H80 -> 160000 | D96: ='Program Budget'!G80 -> 0 | E96: 1 | F96: =C96*D96*E96 -> 0 | G96: =C96 -> 160000 | H96: ='Program Budget'!K80 -> 0 | I96: 1 | J96: =G96*H96*I96 -> 0 | K96: =G96 -> 160000 | L96: ='Program Budget'!N80 -> 1 | M96: 1 | N96: =K96*L96*M96 -> 160000 | O96: =K96 -> 160000 | P96: ='Program Budget'!Q80 -> 0 | Q96: 1 | R96: =O96*P96*Q96 -> 0 | S96: =O96 -> 160000 | T96: ='Program Budget'!T80 -> 0 | U96: 1 | V96: =S96*T96*U96 -> 0 | W96: =F96+J96+N96+R96+V96 -> 160000
A97: ='Program Budget'!D81 -> Final Evaluation | B97: ='Program Budget'!F81 -> Unit | C97: ='Program Budget'!H81 -> 175000 | D97: ='Program Budget'!G81 -> 0 | E97: 1 | F97: =C97*D97*E97 -> 0 | G97: =C97 -> 175000 | H97: ='Program Budget'!K81 -> 0 | I97: 1 | J97: =G97*H97*I97 -> 0 | K97: =G97 -> 175000 | L97: ='Program Budget'!N81 -> 0 | M97: 1 | N97: =K97*L97*M97 -> 0 | O97: =K97 -> 175000 | P97: ='Program Budget'!Q81 -> 0 | Q97: 1 | R97: =O97*P97*Q97 -> 0 | S97: =O97 -> 175000 | T97: ='Program Budget'!T81 -> 1 | U97: 1 | V97: =S97*T97*U97 -> 175000 | W97: =F97+J97+N97+R97+V97 -> 175000
A98: ='Program Budget'!D82 -> Impact Evaluation | B98: ='Program Budget'!F82 -> Unit | C98: ='Program Budget'!H82 -> 200000 | D98: ='Program Budget'!G82 -> 0 | E98: 1 | F98: =C98*D98*E98 -> 0 | G98: =C98 -> 200000 | H98: ='Program Budget'!K82 -> 0 | I98: 1 | J98: =G98*H98*I98 -> 0 | K98: =G98 -> 200000 | L98: ='Program Budget'!N82 -> 0 | M98: 1 | N98: =K98*L98*M98 -> 0 | O98: =K98 -> 200000 | P98: ='Program Budget'!Q82 -> 0 | Q98: 1 | R98: =O98*P98*Q98 -> 0 | S98: =O98 -> 200000 | T98: ='Program Budget'!T82 -> 1 | U98: 1 | V98: =S98*T98*U98 -> 200000 | W98: =F98+J98+N98+R98+V98 -> 200000
A99: ='Program Budget'!D83 -> Special Study | B99: ='Program Budget'!F83 -> Unit | C99: ='Program Budget'!H83 -> 100000 | D99: ='Program Budget'!G83 -> 0 | E99: 1 | F99: =C99*D99*E99 -> 0 | G99: =C99 -> 100000 | H99: ='Program Budget'!K83 -> 1 | I99: 1 | J99: =G99*H99*I99 -> 100000 | K99: =G99 -> 100000 | L99: ='Program Budget'!N83 -> 1 | M99: 1 | N99: =K99*L99*M99 -> 100000 | O99: =K99 -> 100000 | P99: ='Program Budget'!Q83 -> 0 | Q99: 1 | R99: =O99*P99*Q99 -> 0 | S99: =O99 -> 100000 | T99: ='Program Budget'!T83 -> 0 | U99: 1 | V99: =S99*T99*U99 -> 0 | W99: =F99+J99+N99+R99+V99 -> 200000
A100: ='Program Budget'!D84 -> Monitoring Guidelines Development
A101: ='Program Budget'!D85 -> Monitoring Guidelines Creation, Translation & Printing | B101: ='Program Budget'!F85 -> Document | C101: ='Program Budget'!H85 -> 10000 | D101: ='Program Budget'!G85 -> 1 | E101: 1 | F101: =C101*D101*E101 -> 10000 | G101: =C101 -> 10000 | H101: ='Program Budget'!K85 -> 0 | I101: 1 | J101: =G101*H101*I101 -> 0 | K101: =G101 -> 10000 | L101: ='Program Budget'!N85 -> 0 | M101: 1 | N101: =K101*L101*M101 -> 0 | O101: =K101 -> 10000 | P101: ='Program Budget'!Q85 -> 0 | Q101: 1 | R101: =O101*P101*Q101 -> 0 | S101: =O101 -> 10000 | T101: ='Program Budget'!T85 -> 0 | U101: 1 | V101: =S101*T101*U101 -> 0 | W101: =F101+J101+N101+R101+V101 -> 10000
A102: ='Program Budget'!D86 -> Monitoring Guidelines Revision, Translation & Printing | B102: ='Program Budget'!F86 -> Year | C102: ='Program Budget'!H86 -> 2000 | D102: ='Program Budget'!G86 -> 0 | E102: 1 | F102: =C102*D102*E102 -> 0 | G102: =C102 -> 2000 | H102: ='Program Budget'!K86 -> 1 | I102: 1 | J102: =G102*H102*I102 -> 2000 | K102: =G102 -> 2000 | L102: ='Program Budget'!N86 -> 1 | M102: 1 | N102: =K102*L102*M102 -> 2000 | O102: =K102 -> 2000 | P102: ='Program Budget'!Q86 -> 1 | Q102: 1 | R102: =O102*P102*Q102 -> 2000 | S102: =O102 -> 2000 | T102: ='Program Budget'!T86 -> 1 | U102: 1 | V102: =S102*T102*U102 -> 2000 | W102: =F102+J102+N102+R102+V102 -> 8000
A103: ='Program Budget'!D87 -> Monitoring Guidelines Staff Training on Indicators and Data Collection/Analysis | B103: ='Program Budget'!F87 -> Workshop | C103: ='Program Budget'!H87 -> 6000 | D103: ='Program Budget'!G87 -> 1 | E103: 1 | F103: =C103*D103*E103 -> 6000 | G103: =C103 -> 6000 | H103: ='Program Budget'!K87 -> 1 | I103: 1 | J103: =G103*H103*I103 -> 6000 | K103: =G103 -> 6000 | L103: ='Program Budget'!N87 -> 1 | M103: 1 | N103: =K103*L103*M103 -> 6000 | O103: =K103 -> 6000 | P103: ='Program Budget'!Q87 -> 1 | Q103: 1 | R103: =O103*P103*Q103 -> 6000 | S103: =O103 -> 6000 | T103: ='Program Budget'!T87 -> 1 | U103: 1 | V103: =S103*T103*U103 -> 6000 | W103: =F103+J103+N103+R103+V103 -> 30000
A104: ='Program Budget'!D88 -> M&E Database
...

Sheet Admin
A2: Item | B2: Type of Unit | C2: Year 1 | G2: Year 2 | K2: Year 3 | O2: Year 4 | S2: Year 5 | W2: Total
C3: Cost | D3: Quantity | E3: Percent Allocated | F3: Total | G3: Cost | H3: Quantity | I3: Percent Allocated | J3: Total | K3: Cost | L3: Quantity | M3: Percent Allocated | N3: Total | O3: Cost | P3: Quantity | Q3: Percent Allocated | R3: Total | S3: Cost | T3: Quantity | U3: Percent Allocated | V3: Total | AF3: Chart of Accounts
A4: Direct Costs | AE4: Line# | AF4: Account | AG4: Account Name
A5: Salaries
A6: USN/TCN Staff
A7: ='Program Budget'!D12 -> Key Personnel: Ex-pat Chief of Party | B7: ='Program Budget'!F13 -> Month | C7: ='Program Budget'!H12 -> 12083.333 | D7: ='Program Budget'!G12 -> 12 | E7: ='Program Budget'!E12 -> 0.2 | F7: =C7*D7*E7 -> 29000 | G7: =C7*1.04 -> 12566.667 | H7: ='Program Budget'!K12 -> 12 | I7: ='Program Budget'!J12 -> 0.05 | J7: =G7*H7*I7 -> 7540 | K7: =G7*1.04 -> 13069.333 | L7: ='Program Budget'!N12 -> 12 | M7: ='Program Budget'!M12 -> 0.05 | N7: =K7*L7*M7 -> 7841.6 | O7: =K7*1.04 -> 13592.107 | P7: ='Program Budget'!Q12 -> 12 | Q7: ='Program Budget'!P12 -> 0.05 | R7: =O7*P7*Q7 -> 8155.264 | S7: =O7*1.04 -> 14135.791 | T7: ='Program Budget'!T12 -> 12 | U7: ='Program Budget'!S12 -> 0.05 | V7: =S7*T7*U7 -> 8481.4746 | W7: =F7+J7+N7+R7+V7 -> 61018.339 | AE7: 180 | AF7: 50-01-2-020 | AG7: DIR-USN (Expat) Labor
A8: Total: Expatriate Salaries & Wages | F8: =SUM(F7:F7) -> 29000 | J8: =SUM(J7:J7) -> 7540 | N8: =SUM(N7:N7) -> 7841.6 | R8: =SUM(R7:R7) -> 8155.264 | V8: =SUM(V7:V7) -> 8481.4746 | W8: =+F8+J8+N8+R8+V8 -> 61018.339
A9: CNN Staff
A10: ='Program Budget'!D13 -> Deputy Chief of Party | B10: ='Program Budget'!F12 -> Month | C10: ='Program Budget'!H13 -> 7500 | D10: ='Program Budget'!G13 -> 6 | E10: ='Program Budget'!E13 -> 0.2 | F10: =C10*D10*E10 -> 9000 | G10: =C10*1.04 -> 7800 | H10: ='Program Budget'!K13 -> 12 | I10: ='Program Budget'!J13 -> 0 | J10: =G10*H10*I10 -> 0 | K10: =G10*1.04 -> 8112 | L10: ='Program Budget'!N13 -> 12 | M10: ='Program Budget'!M13 -> 0 | N10: =K10*L10*M10 -> 0 | O10: =K10*1.04 -> 8436.48 | P10: ='Program Budget'!Q13 -> 12 | Q10: ='Program Budget'!P13 -> 0 | R10: =O10*P10*Q10 -> 0 | S10: =O10*1.04 -> 8773.9392 | T10: ='Program Budget'!T13 -> 6 | U10: ='Program Budget'!S13 -> 0 | V10: =S10*T10*U10 -> 0 | W10: =F10+J10+N10+R10+V10 -> 9000 | AE10: 180 | AF10: 50-01-2-020 | AG10: DIR-USN (Expat) Labor
A11: ='Program Budget'!D14 -> Technical Lead Component 1 | B11: ='Program Budget'!F14 -> Month | C11: ='Program Budget'!H14 -> 3333.3333 | D11: ='Program Budget'!G14 -> 6 | E11: ='Program Budget'!E14 -> 0.25 | F11: =C11*D11*E11 -> 5000 | G11: =C11*1.04 -> 3466.6667 | H11: ='Program Budget'!K14 -> 12 | I11: ='Program Budget'!J14 -> 0 | J11: =G11*H11*I11 -> 0 | K11: =G11*1.04 -> 3605.3333 | L11: ='Program Budget'!N14 -> 12 | M11: ='Program Budget'!M14 -> 0 | N11: =K11*L11*M11 -> 0 | O11: =K11*1.04 -> 3749.5467 | P11: ='Program Budget'!Q14 -> 12 | Q11: ='Program Budget'!P14 -> 0 | R11: =O11*P11*Q11 -> 0 | S11: =O11*1.04 -> 3899.5285 | T11: ='Program Budget'!T14 -> 9 | U11: ='Program Budget'!S14 -> 0 | V11: =S11*T11*U11 -> 0 | W11: =F11+J11+N11+R11+V11 -> 5000 | AE11: 180 | AF11: 50-01-2-020 | AG11: DIR-USN (Expat) Labor
A12: ='Program Budget'!D15 -> Technical Lead Component 2 | B12: ='Program Budget'!F15 -> Month | C12: ='Program Budget'!H15 -> 3333.3333 | D12: ='Program Budget'!G15 -> 6 | E12: ='Program Budget'!E15 -> 0.25 | F12: =C12*D12*E12 -> 5000 | G12: =C12*1.04 -> 3466.6667 | H12: ='Program Budget'!K15 -> 12 | I12: ='Program Budget'!J15 -> 0 | J12: =G12*H12*I12 -> 0 | K12: =G12*1.04 -> 3605.3333 | L12: ='Program Budget'!N15 -> 12 | M12: ='Program Budget'!M15 -> 0 | N12: =K12*L12*M12 -> 0 | O12: =K12*1.04 -> 3749.5467 | P12: ='Program Budget'!Q15 -> 12 | Q12: ='Program Budget'!P15 -> 0 | R12: =O12*P12*Q12 -> 0 | S12: =O12*1.04 -> 3899.5285 | T12: ='Program Budget'!T15 -> 9 | U12: ='Program Budget'!S15 -> 0 | V12: =S12*T12*U12 -> 0 | W12: =F12+J12+N12+R12+V12 -> 5000 | AE12: 180 | AF12: 50-01-2-020 | AG12: DIR-USN (Expat) Labor
A13: ='Program Budget'!D16 -> Technical Lead Component 3 | B13: ='Program Budget'!F16 -> Month | C13: ='Program Budget'!H16 -> 3333.3333 | D13: ='Program Budget'!G16 -> 6 | E13: ='Program Budget'!E16 -> 0.25 | F13: =C13*D13*E13 -> 5000 | G13: =C13*1.04 -> 3466.6667 | H13: ='Program Budget'!K16 -> 12 | I13: ='Program Budget'!J16 -> 0 | J13: =G13*H13*I13 -> 0 | K13: =G13*1.04 -> 3605.3333 | L13: ='Program Budget'!N16 -> 12 | M13: ='Program Budget'!M16 -> 0 | N13: =K13*L13*M13 -> 0 | O13: =K13*1.04 -> 3749.5467 | P13: ='Program Budget'!Q16 -> 12 | Q13: ='Program Budget'!P16 -> 0 | R13: =O13*P13*Q13 -> 0 | S13: =O13*1.04 -> 3899.5285 | T13: ='Program Budget'!T16 -> 9 | U13: ='Program Budget'!S16 -> 0 | V13: =S13*T13*U13 -> 0 | W13: =F13+J13+N13+R13+V13 -> 5000 | AE13: 180 | AF13: 50-01-2-020 | AG13: DIR-USN (Expat) Labor
A14: ='Program Budget'!D17 -> Specialist Component 2 | B14: ='Program Budget'!F17 -> Month | C14: ='Program Budget'!H17 -> 1666.6667 | D14: ='Program Budget'!G17 -> 6 | E14: ='Program Budget'!E17 -> 0.2 | F14: =C14*D14*E14 -> 2000 | G14: =C14*1.04 -> 1733.3333 | H14: ='Program Budget'!K17 -> 12 | I14: ='Program Budget'!J17 -> 0 | J14: =G14*H14*I14 -> 0 | K14: =G14*1.04 -> 1802.6667 | L14: ='Program Budget'!N17 -> 12 | M14: ='Program Budget'!M17 -> 0 | N14: =K14*L14*M14 -> 0 | O14: =K14*1.04 -> 1874.7733 | P14: ='Program Budget'!Q17 -> 12 | Q14: ='Program Budget'!P17 -> 0 | R14: =O14*P14*Q14 -> 0 | S14: =O14*1.04 -> 1949.7643 | T14: ='Program Budget'!T17 -> 6 | U14: ='Program Budget'!S17 -> 0 | V14: =S14*T14*U14 -> 0 | W14: =F14+J14+N14+R14+V14 -> 2000 | AE14: 180 | AF14: 50-01-2-020 | AG14: DIR-USN (Expat) Labor
A15: ='Program Budget'!D18 -> Specialist Component 3 | B15: ='Program Budget'!F18 -> Month | C15: ='Program Budget'!H18 -> 1666.6667 | D15: ='Program Budget'!G18 -> 6 | E15: ='Program Budget'!E18 -> 0.2 | F15: =C15*D15*E15 -> 2000 | G15: =C15*1.04 -> 1733.3333 | H15: ='Program Budget'!K18 -> 12 | I15: ='Program Budget'!J18 -> 0 | J15: =G15*H15*I15 -> 0 | K15: =G15*1.04 -> 1802.6667 | L15: ='Program Budget'!N18 -> 12 | M15: ='Program Budget'!M18 -> 0 | N15: =K15*L15*M15 -> 0 | O15: =K15*1.04 -> 1874.7733 | P15: ='Program Budget'!Q18 -> 12 | Q15: ='Program Budget'!P18 -> 0 | R15: =O15*P15*Q15 -> 0 | S15: =O15*1.04 -> 1949.7643 | T15: ='Program Budget'!T18 -> 6 | U15: ='Program Budget'!S18 -> 0 | V15: =S15*T15*U15 -> 0 | W15: =F15+J15+N15+R15+V15 -> 2000
A16: ='Program Budget'!D19 -> Specialist Component 4 | B16: ='Program Budget'!F19 -> Month | C16: ='Program Budget'!H19 -> 1666.6667 | D16: ='Program Budget'!G19 -> 6 | E16: ='Program Budget'!E19 -> 0.2 | F16: =C16*D16*E16 -> 2000 | G16: =C16*1.04 -> 1733.3333 | H16: ='Program Budget'!K19 -> 12 | I16: ='Program Budget'!J19 -> 0 | J16: =G16*H16*I16 -> 0 | K16: =G16*1.04 -> 1802.6667 | L16: ='Program Budget'!N19 -> 12 | M16: ='Program Budget'!M19 -> 0 | N16: =K16*L16*M16 -> 0 | O16: =K16*1.04 -> 1874.7733 | P16: ='Program Budget'!Q19 -> 12 | Q16: ='Program Budget'!P19 -> 0 | R16: =O16*P16*Q16 -> 0 | S16: =O16*1.04 -> 1949.7643 | T16: ='Program Budget'!T19 -> 6 | U16: ='Program Budget'!S19 -> 0 | V16: =S16*T16*U16 -> 0 | W16: =F16+J16+N16+R16+V16 -> 2000
A17: ='Program Budget'!D20 -> Extension Agents (20 Individuals) | B17: ='Program Budget'!F20 -> Month | C17: ='Program Budget'!H20 -> 23333.333 | D17: ='Program Budget'!G20 -> 3 | E17: ='Program Budget'!E20 -> 0.1 | F17: =C17*D17*E17 -> 7000 | G17: =C17*1.04 -> 24266.667 | H17: ='Program Budget'!K20 -> 12 | I17: ='Program Budget'!J20 -> 0 | J17: =G17*H17*I17 -> 0 | K17: =G17*1.04 -> 25237.333 | L17: ='Program Budget'!N20 -> 6 | M17: ='Program Budget'!M20 -> 0 | N17: =K17*L17*M17 -> 0 | O17: =K17*1.04 -> 26246.827 | P17: ='Program Budget'!Q20 -> 0 | Q17: ='Program Budget'!P20 -> 0 | R17: =O17*P17*Q17 -> 0 | S17: =O17*1.04 -> 27296.7 | T17: ='Program Budget'!T20 -> 0 | U17: ='Program Budget'!S20 -> 0 | V17: =S17*T17*U17 -> 0 | W17: =F17+J17+N17+R17+V17 -> 7000
A18: ='Program Budget'!D21 -> M&E Director | B18: ='Program Budget'!F21 -> Month | C18: ='Program Budget'!H21 -> 3750 | D18: ='Program Budget'!G21 -> 9 | E18: ='Program Budget'!E21 -> 0.15 | F18: =C18*D18*E18 -> 5062.5 | G18: =C18*1.04 -> 3900 | H18: ='Program Budget'!K21 -> 12 | I18: ='Program Budget'!J21 -> 0.05 | J18: =G18*H18*I18 -> 2340 | K18: =G18*1.04 -> 4056 | L18: ='Program Budget'!N21 -> 12 | M18: ='Program Budget'!M21 -> 0.05 | N18: =K18*L18*M18 -> 2433.6 | O18: =K18*1.04 -> 4218.24 | P18: ='Program Budget'!Q21 -> 12 | Q18: ='Program Budget'!P21 -> 0.05 | R18: =O18*P18*Q18 -> 2530.944 | S18: =O18*1.04 -> 4386.9696 | T18: ='Program Budget'!T21 -> 12 | U18: ='Program Budget'!S21 -> 0.05 | V18: =S18*T18*U18 -> 2632.1818 | W18: =F18+J18+N18+R18+V18 -> 14999.226 | AE18: 180 | AF18: 50-01-2-020 | AG18: DIR-USN (Expat) Labor
A19: ='Program Budget'!D22 -> M&E Specialist | B19: ='Program Budget'!F22 -> Month | C19: ='Program Budget'!H22 -> 2083.3333 | D19: ='Program Budget'!G22 -> 6 | E19: ='Program Budget'!E22 -> 0.15 | F19: =C19*D19*E19 -> 1875 | G19: =C19*1.04 -> 2166.6667 | H19: ='Program Budget'!K22 -> 12 | I19: ='Program Budget'!J22 -> 0.05 | J19: =G19*H19*I19 -> 1300 | K19: =G19*1.04 -> 2253.3333 | L19: ='Program Budget'!N22 -> 12 | M19: ='Program Budget'!M22 -> 0.05 | N19: =K19*L19*M19 -> 1352 | O19: =K19*1.04 -> 2343.4667 | P19: ='Program Budget'!Q22 -> 12 | Q19: ='Program Budget'!P22 -> 0.05 | R19: =O19*P19*Q19 -> 1406.08 | S19: =O19*1.04 -> 2437.2053 | T19: ='Program Budget'!T22 -> 10 | U19: ='Program Budget'!S22 -> 0.05 | V19: =S19*T19*U19 -> 1218.6027 | W19: =F19+J19+N19+R19+V19 -> 7151.6827 | AE19: 180 | AF19: 50-01-2-020 | AG19: DIR-USN (Expat) Labor
A20: ='Program Budget'!D23 -> F&A Director | B20: ='Program Budget'!F23 -> Month | C20: ='Program Budget'!H23 -> 6666.6667 | D20: ='Program Budget'!G23 -> 9 | E20: ='Program Budget'!E23 -> 0.2 | F20: =C20*D20*E20 -> 12000 | G20: =C20*1.04 -> 6933.3333 | H20: ='Program Budget'!K23 -> 12 | I20: ='Program Budget'!J23 -> 0.1 | J20: =G20*H20*I20 -> 8320 | K20: =G20*1.04 -> 7210.6667 | L20: ='Program Budget'!N23 -> 12 | M20: ='Program Budget'!M23 -> 0.1 | N20: =K20*L20*M20 -> 8652.8 | O20: =K20*1.04 -> 7499.0933 | P20: ='Program Budget'!Q23 -> 12 | Q20: ='Program Budget'!P23 -> 0.1 | R20: =O20*P20*Q20 -> 8998.912 | S20: =O20*1.04 -> 7799.0571 | T20: ='Program Budget'!T23 -> 12 | U20: ='Program Budget'!S23 -> 0.1 | V20: =S20*T20*U20 -> 9358.8685 | W20: =F20+J20+N20+R20+V20 -> 47330.58 | AE20: 180 | AF20: 50-01-2-020 | AG20: DIR-USN (Expat) Labor
A21: ='Program Budget'!D24 -> Human Resource Manager | B21: ='Program Budget'!F24 -> Month | C21: ='Program Budget'!H24 -> 2916.6667 | D21: ='Program Budget'!G24 -> 9 | E21: ='Program Budget'!E24 -> 0.25 | F21: =C21*D21*E21 -> 6562.5 | G21: =C21*1.04 -> 3033.3333 | H21: ='Program Budget'!K24 -> 12 | I21: ='Program Budget'!J24 -> 0.1 | J21: =G21*H21*I21 -> 3640 | K21: =G21*1.04 -> 3154.6667 | L21: ='Program Budget'!N24 -> 12 | M21: ='Program Budget'!M24 -> 0.05 | N21: =K21*L21*M21 -> 1892.8 | O21: =K21*1.04 -> 3280.8533 | P21: ='Program Budget'!Q24 -> 12 | Q21: ='Program Budget'!P24 -> 0.05 | R21: =O21*P21*Q21 -> 1968.512 | S21: =O21*1.04 -> 3412.0875 | T21: ='Program Budget'!T24 -> 10 | U21: ='Program Budget'!S24 -> 0.05 | V21: =S21*T21*U21 -> 1706.0437 | W21: =F21+J21+N21+R21+V21 -> 15769.856
A22: ='Program Budget'!D25 -> Contracts & Compliance Specialist | B22: ='Program Budget'!F25 -> Month | C22: ='Program Budget'!H25 -> 2916.6667 | D22: ='Program Budget'!G25 -> 6 | E22: ='Program Budget'!E25 -> 0.1 | F22: =C22*D22*E22 -> 1750 | G22: =C22*1.04 -> 3033.3333 | H22: ='Program Budget'!K25 -> 12 | I22: ='Program Budget'!J25 -> 0.05 | J22: =G22*H22*I22 -> 1820 | K22: =G22*1.04 -> 3154.6667 | L22: ='Program Budget'!N25 -> 12 | M22: ='Program Budget'!M25 -> 0.05 | N22: =K22*L22*M22 -> 1892.8 | O22: =K22*1.04 -> 3280.8533 | P22: ='Program Budget'!Q25 -> 12 | Q22: ='Program Budget'!P25 -> 0.05 | R22: =O22*P22*Q22 -> 1968.512 | S22: =O22*1.04 -> 3412.0875 | T22: ='Program Budget'!T25 -> 9 | U22: ='Program Budget'!S25 -> 0.05 | V22: =S22*T22*U22 -> 1535.4394 | W22: =F22+J22+N22+R22+V22 -> 8966.7514 | AE22: 180 | AF22: 50-01-2-020 | AG22: DIR-USN (Expat) Labor
A23: ='Program Budget'!D26 -> Accountant | B23: ='Program Budget'!F26 -> Month | C23: ='Program Budget'!H26 -> 1666.6667 | D23: ='Program Budget'!G26 -> 7 | E23: ='Program Budget'!E26 -> 0.2 | F23: =C23*D23*E23 -> 2333.3333 | G23: =C23*1.04 -> 1733.3333 | H23: ='Program Budget'!K26 -> 12 | I23: ='Program Budget'!J26 -> 0.2 | J23: =G23*H23*I23 -> 4160 | K23: =G23*1.04 -> 1802.6667 | L23: ='Program Budget'!N26 -> 12 | M23: ='Program Budget'!M26 -> 0.2 | N23: =K23*L23*M23 -> 4326.4 | O23: =K23*1.04 -> 1874.7733 | P23: ='Program Budget'!Q26 -> 12 | Q23: ='Program Budget'!P26 -> 0.2 | R23: =O23*P23*Q23 -> 4499.456 | S23: =O23*1.04 -> 1949.7643 | T23: ='Program Budget'!T26 -> 10 | U23: ='Program Budget'!S26 -> 0.2 | V23: =S23*T23*U23 -> 3899.5285 | W23: =F23+J23+N23+R23+V23 -> 19218.718 | AE23: 180 | AF23: 50-01-2-020 | AG23: DIR-USN (Expat) Labor
A24: ='Program Budget'!D27 -> Administrative Assistant | B24: ='Program Budget'!F27 -> Month | C24: ='Program Budget'!H27 -> 833.33333 | D24: ='Program Budget'!G27 -> 7 | E24: ='Program Budget'!E27 -> 0.2 | F24: =C24*D24*E24 -> 1166.6667 | G24: =C24*1.04 -> 866.66667 | H24: ='Program Budget'!K27 -> 12 | I24: ='Program Budget'!J27 -> 0.2 | J24: =G24*H24*I24 -> 2080 | K24: =G24*1.04 -> 901.33333 | L24: ='Program Budget'!N27 -> 12 | M24: ='Program Budget'!M27 -> 0.2 | N24: =K24*L24*M24 -> 2163.2 | O24: =K24*1.04 -> 937.38667 | P24: ='Program Budget'!Q27 -> 12 | Q24: ='Program Budget'!P27 -> 0.2 | R24: =O24*P24*Q24 -> 2249.728 | S24: =O24*1.04 -> 974.88213 | T24: ='Program Budget'!T27 -> 10 | U24: ='Program Budget'!S27 -> 0.2 | V24: =S24*T24*U24 -> 1949.7643 | W24: =F24+J24+N24+R24+V24 -> 9609.3589 | AE24: 180 | AF24: 50-01-2-020 | AG24: DIR-USN (Expat) Labor
A25: ='Program Budget'!D28 -> Security Guards | B25: ='Program Budget'!F28 -> Month | C25: ='Program Budget'!H28 -> 666.66667 | D25: ='Program Budget'!G28 -> 8 | E25: ='Program Budget'!E28 -> 0.2 | F25: =C25*D25*E25 -> 1066.6667 | G25: =C25*1.04 -> 693.33333 | H25: ='Program Budget'!K28 -> 12 | I25: ='Program Budget'!J28 -> 0.05 | J25: =G25*H25*I25 -> 416 | K25: =G25*1.04 -> 721.06667 | L25: ='Program Budget'!N28 -> 12 | M25: ='Program Budget'!M28 -> 0.05 | N25: =K25*L25*M25 -> 432.64 | O25: =K25*1.04 -> 749.90933 | P25: ='Program Budget'!Q28 -> 12 | Q25: ='Program Budget'!P28 -> 0.05 | R25: =O25*P25*Q25 -> 449.9456 | S25: =O25*1.04 -> 779.90571 | T25: ='Program Budget'!T28 -> 10 | U25: ='Program Budget'!S28 -> 0.05 | V25: =S25*T25*U25 -> 389.95285 | W25: =F25+J25+N25+R25+V25 -> 2755.2051 | AE25: 180 | AF25: 50-01-2-020 | AG25: DIR-USN (Expat) Labor
A26: ='Program Budget'!D29 -> Driver (2 Individuals) | B26: ='Program Budget'!F29 -> Month | C26: ='Program Budget'!H29 -> 1333.3333 | D26: ='Program Budget'!G29 -> 6 | E26: ='Program Budget'!E29 -> 0.2 | F26: =C26*D26*E26 -> 1600 | G26: =C26*1.04 -> 1386.6667 | H26: ='Program Budget'!K29 -> 12 | I26: ='Program Budget'!J29 -> 0.05 | J26: =G26*H26*I26 -> 832 | K26: =G26*1.04 -> 1442.1333 | L26: ='Program Budget'!N29 -> 12 | M26: ='Program Budget'!M29 -> 0.05 | N26: =K26*L26*M26 -> 865.28 | O26: =K26*1.04 -> 1499.8187 | P26: ='Program Budget'!Q29 -> 12 | Q26: ='Program Budget'!P29 -> 0.05 | R26: =O26*P26*Q26 -> 899.8912 | S26: =O26*1.04 -> 1559.8114 | T26: ='Program Budget'!T29 -> 9 | U26: ='Program Budget'!S29 -> 0.05 | V26: =S26*T26*U26 -> 701.91514 | W26: =F26+J26+N26+R26+V26 -> 4899.0863 | AE26: 180 | AF26: 50-01-2-020 | AG26: DIR-USN (Expat) Labor
A27: Total Local Salary Cost | F27: =SUM(F10:F26) -> 70416.667 | J27: =SUM(J10:J26) -> 24908 | N27: =SUM(N10:N26) -> 24011.52 | R27: =SUM(R10:R26) -> 24971.981 | V27: =SUM(V10:V26) -> 23392.297 | W27: =F27+J27+N27+R27+V27 -> 167700.46
A28: HQ Staff
A29: ='Program Budget'!D31 -> Senior Program Director | B29: ='Program Budget'!F31 -> Month | C29: ='Program Budget'!H31 -> 11250 | D29: ='Program Budget'!G31 -> 12 | E29: ='Program Budget'!E31 -> 0.2 | F29: =C29*D29*E29 -> 27000 | G29: =C29*1.04 -> 11700 | H29: ='Program Budget'!K31 -> 12 | I29: ='Program Budget'!J31 -> 0.2 | J29: =G29*H29*I29 -> 28080 | K29: =G29*1.04 -> 12168 | L29: ='Program Budget'!N31 -> 12 | M29: ='Program Budget'!M31 -> 0.2 | N29: =K29*L29*M29 -> 29203.2 | O29: =K29*1.04 -> 12654.72 | P29: ='Program Budget'!Q31 -> 12 | Q29: ='Program Budget'!P31 -> 0.2 | R29: =O29*P29*Q29 -> 30371.328 | S29: =O29*1.04 -> 13160.909 | T29: ='Program Budget'!T31 -> 12 | U29: ='Program Budget'!S31 -> 0.2 | V29: =S29*T29*U29 -> 31586.181 | W29: =F29+J29+N29+R29+V29 -> 146240.71 | AE29: 180 | AF29: 50-01-2-020 | AG29: DIR-USN (Expat) Labor
A30: ='Program Budget'!D32 -> HO Project Manager | B30: ='Program Budget'!F32 -> Month | C30: ='Program Budget'!H32 -> 6916.6667 | D30: ='Program Budget'!G32 -> 12 | E30: ='Program Budget'!E32 -> 1 | F30: =C30*D30*E30 -> 83000 | G30: =C30*1.04 -> 7193.3333 | H30: ='Program Budget'!K32 -> 12 | I30: ='Program Budget'!J32 -> 1 | J30: =G30*H30*I30 -> 86320 | K30: =G30*1.04 -> 7481.0667 | L30: ='Program Budget'!N32 -> 12 | M30: ='Program Budget'!M32 -> 1 | N30: =K30*L30*M30 -> 89772.8 | O30: =K30*1.04 -> 7780.3093 | P30: ='Program Budget'!Q32 -> 12 | Q30: ='Program Budget'!P32 -> 1 | R30: =O30*P30*Q30 -> 93363.712 | S30: =O30*1.04 -> 8091.5217 | T30: ='Program Budget'!T32 -> 12 | U30: ='Program Budget'!S32 -> 1 | V30: =S30*T30*U30 -> 97098.26 | W30: =F30+J30+N30+R30+V30 -> 449554.77 | AE30: 180 | AF30: 50-01-2-020 | AG30: DIR-USN (Expat) Labor
A31: Total HQ Staff | F31: =SUM(F29:F30) -> 110000 | J31: =SUM(J29:J30) -> 114400 | N31: =SUM(N29:N30) -> 118976 | R31: =SUM(R29:R30) -> 123735.04 | V31: =SUM(V29:V30) -> 128684.44 | W31: =+F31+J31+N31+R31+V31 -> 595795.48
A33: Subtotal: Salaries & Wages | F33: =F31+F27+F8 -> 209416.67 | J33: =J31+J27+J8 -> 146848 | N33: =N31+N27+N8 -> 150829.12 | R33: =R31+R27+R8 -> 156862.28 | V33: =V31+V27+V8 -> 160558.21 | W33: =+F33+J33+N33+R33+V33 -> 824514.28
A34: Fringe
A35: USN/TCN Staff | B35: ='Program Budget'!F37 -> % | C35: =F8 -> 29000 | D35: 1 | E35: ='Program Budget'!H39 -> 0.2347 | F35: =C35*D35*E35 -> 6806.3 | G35: =J8 -> 7540 | H35: 1 | I35: =E35 -> 0.2347 | J35: =G35*H35*I35 -> 1769.638 | K35: =N8 -> 7841.6 | L35: 1 | M35: =I35 -> 0.2347 | N35: =K35*L35*M35 -> 1840.4235 | O35: =R8 -> 8155.264 | P35: 1 | Q35: =M35 -> 0.2347 | R35: =O35*P35*Q35 -> 1914.0405 | S35: =V8 -> 8481.4746 | T35: 1 | U35: =Q35 -> 0.2347 | V35: =S35*T35*U35 -> 1990.6021 | W35: =F35+J35+N35+R35+V35 -> 14321.004 | AE35: 194 | AF35: 50-03-0-020 | AG35: DIR-Allocated USN Fringe
A36: CCN Staff | B36: ='Program Budget'!F38 -> % | C36: =F27 -> 70416.667 | D36: 1 | E36: ='Program Budget'!H37 -> 0.2692 | F36: =C36*D36*E36 -> 18956.167 | G36: =J27 -> 24908 | H36: 1 | I36: =E36 -> 0.2692 | J36: =G36*H36*I36 -> 6705.2336 | K36: =N27 -> 24011.52 | L36: 1 | M36: =I36 -> 0.2692 | N36: =K36*L36*M36 -> 6463.9012 | O36: =R27 -> 24971.981 | P36: 1 | Q36: =M36 -> 0.2692 | R36: =O36*P36*Q36 -> 6722.4572 | S36: =V27 -> 23392.297 | T36: 1 | U36: =Q36 -> 0.2692 | V36: =S36*T36*U36 -> 6297.2063 | W36: =F36+J36+N36+R36+V36 -> 45144.965 | AE36: 197 | AF36: 50-03-0-050 | AG36: DIR-CCN Fringe
A37: HQ Staff | B37: ='Program Budget'!F39 -> % | C37: =F31 -> 110000 | D37: 1 | E37: ='Program Budget'!H38 -> 0.2347 | F37: =C37*D37*E37 -> 25817 | G37: =J31 -> 114400 | H37: 1 | I37: =E37 -> 0.2347 | J37: =G37*H37*I37 -> 26849.68 | K37: =N31 -> 118976 | L37: 1 | M37: =I37 -> 0.2347 | N37: =K37*L37*M37 -> 27923.667 | O37: =R31 -> 123735.04 | P37: 1 | Q37: =M37 -> 0.2347 | R37: =O37*P37*Q37 -> 29040.614 | S37: =V31 -> 128684.44 | T37: 1 | U37: =Q37 -> 0.2347 | V37: =S37*T37*U37 -> 30202.238 | W37: =F37+J37+N37+R37+V37 -> 139833.2 | AE37: 193 | AF37: 50-03-0-010 | AG37: DIR-Allocated HQ Fringe
A38: Total: Fringe Benefits | F38: =+SUM(F35:F37) -> 51579.467 | J38: =+SUM(J35:J37) -> 35324.552 | N38: =+SUM(N35:N37) -> 36227.992 | R38: =+SUM(R35:R37) -> 37677.112 | V38: =+SUM(V35:V37) -> 38490.047 | W38: =+F38+J38+N38+R38+V38 -> 199299.17
A39: Allowances
A40: USN/TCN Staff | AE40: 202 | AF40: 50-04-8-003 | AG40: DIR-COLA
A41: ='Program Budget'!D40 -> Cost of Living Adjustment for Ex-pat Chief of Party | B41: ='Program Budget'!F40 -> % | C41: =F8 -> 29000 | D41: 1 | E41: ='Program Budget'!H40 -> 0.15 | F41: =C41*D41*E41 -> 4350 | G41: =J8 -> 7540 | H41: 1 | I41: =E41 -> 0.15 | J41: =G41*H41*I41 -> 1131 | K41: =N8 -> 7841.6 | L41: 1 | M41: =I41 -> 0.15 | N41: =K41*L41*M41 -> 1176.24 | O41: =R8 -> 8155.264 | P41: 1 | Q41: =M41 -> 0.15 | R41: =O41*P41*Q41 -> 1223.2896 | S41: =V8 -> 8481.4746 | T41: 1 | U41: =Q41 -> 0.15 | V41: =S41*T41*U41 -> 1272.2212 | W41: =F41+J41+N41+R41+V41 -> 9152.7508
A42: ='Program Budget'!D41 -> Post Hardship for Ex-pat Chief of Party | B42: ='Program Budget'!F41 -> % | C42: =F7 -> 29000 | D42: 1 | E42: ='Program Budget'!H41 -> 0.35 | F42: =C42*D42*E42 -> 10150 | G42: =J7 -> 7540 | H42: 1 | I42: =E42 -> 0.35 | J42: =G42*H42*I42 -> 2639 | K42: =N7 -> 7841.6 | L42: 1 | M42: =I42 -> 0.35 | N42: =K42*L42*M42 -> 2744.56 | O42: =R7 -> 8155.264 | P42: 1 | Q42: =M42 -> 0.35 | R42: =O42*P42*Q42 -> 2854.3424 | S42: =V7 -> 8481.4746 | T42: 1 | U42: =Q42 -> 0.35 | V42: =S42*T42*U42 -> 2968.5161 | W42: =F42+J42+N42+R42+V42 -> 21356.418
A43: ='Program Budget'!D42 -> Housing Allowance for Chief of Party | B43: ='Program Budget'!F42 -> Month | C43: ='Program Budget'!H42 -> 1600 | D43: ='Program Budget'!G42 -> 12 | E43: 1 | F43: =C43*D43*E43 -> 19200 | G43: =C43*1.04 -> 1664 | H43: ='Program Budget'!K42 -> 12 | I43: =E43 -> 1 | J43: =G43*H43*I43 -> 19968 | K43: =G43*1.04 -> 1730.56 | L43: ='Program Budget'!N42 -> 12 | M43: =I43 -> 1 | N43: =K43*L43*M43 -> 20766.72 | O43: =K43*1.04 -> 1799.7824 | P43: ='Program Budget'!Q42 -> 12 | Q43: =M43 -> 1 | R43: =O43*P43*Q43 -> 21597.389 | S43: =O43*1.04 -> 1871.7737 | T43: ='Program Budget'!T42 -> 12 | U43: =Q43 -> 1 | V43: =S43*T43*U43 -> 22461.284 | W43: =F43+J43+N43+R43+V43 -> 103993.39
A44: ='Program Budget'!D43 -> Reallocation & Demobilization Flight for Chief of Party and Spouse | B44: ='Program Budget'!F43 -> Trip | C44: ='Program Budget'!H43 -> 1700 | D44: ='Program Budget'!G43 -> 2 | E44: 1 | F44: =C44*D44*E44 -> 3400 | G44: =C44*1.04 -> 1768 | H44: ='Program Budget'!K43 -> 0 | I44: 0 | J44: =G44*H44*I44 -> 0 | K44: =G44*1.04 -> 1838.72 | L44: ='Program Budget'!N43 -> 0 | M44: 0 | N44: =K44*L44*M44 -> 0 | O44: =K44*1.04 -> 1912.2688 | P44: ='Program Budget'!Q43 -> 0 | Q44: 0 | R44: =O44*P44*Q44 -> 0 | S44: =O44*1.04 -> 1988.7596 | T44: ='Program Budget'!T43 -> 2 | U44: 1 | V44: =S44*T44*U44 -> 3977.5191 | W44: =F44+J44+N44+R44+V44 -> 7377.5191
A45: ='Program Budget'!D44 -> Reallocation & Demobilization Extra Baggage for Chief of Party and Spouse | B45: ='Program Budget'!F44 -> Trip | C45: ='Program Budget'!H44 -> 150 | D45: ='Program Budget'!G44 -> 2 | E45: 1 | F45: =C45*D45*E45 -> 300 | G45: =C45*1.04 -> 156 | H45: ='Program Budget'!K44 -> 0 | I45: 0 | J45: =G45*H45*I45 -> 0 | K45: =G45*1.04 -> 162.24 | L45: ='Program Budget'!N44 -> 0 | M45: 0 | N45: =K45*L45*M45 -> 0 | O45: =K45*1.04 -> 168.7296 | P45: ='Program Budget'!Q44 -> 0 | Q45: 0 | R45: =O45*P45*Q45 -> 0 | S45: =O45*1.04 -> 175.47878 | T45: ='Program Budget'!T44 -> 2 | U45: 1 | V45: =S45*T45*U45 -> 350.95757 | W45: =F45+J45+N45+R45+V45 -> 650.95757
A46: ='Program Budget'!D45 -> Reallocation & Demobilization - Shipment of Households Good (by Land & Sea) | B46: ='Program Budget'!F45 -> Year | C46: ='Program Budget'!H45 -> 21382 | D46: ='Program Budget'!G45 -> 1 | E46: 1 | F46: =C46*D46*E46 -> 21382 | G46: =C46*1.04 -> 22237.28 | H46: ='Program Budget'!K45 -> 0 | I46: 0 | J46: =G46*H46*I46 -> 0 | K46: =G46*1.04 -> 23126.771 | L46: ='Program Budget'!N45 -> 0 | M46: 0 | N46: =K46*L46*M46 -> 0 | O46: =K46*1.04 -> 24051.842 | P46: ='Program Budget'!Q45 -> 0 | Q46: 0 | R46: =O46*P46*Q46 -> 0 | S46: =O46*1.04 -> 25013.916 | T46: ='Program Budget'!T45 -> 1 | U46: 1 | V46: =S46*T46*U46 -> 25013.916 | W46: =F46+J46+N46+R46+V46 -> 46395.916
A47: ='Program Budget'!D46 -> Reallocation & Demobilization - Customs 20% and Taxes 3% | B47: ='Program Budget'!F46 -> Year | C47: ='Program Budget'!H46 -> 4917.86 | D47: ='Program Budget'!G46 -> 1 | E47: 1 | F47: =C47*D47*E47 -> 4917.86 | G47: =C47*1.04 -> 5114.5744 | H47: ='Program Budget'!K46 -> 0 | I47: 0 | J47: =G47*H47*I47 -> 0 | K47: =G47*1.04 -> 5319.1574 | L47: ='Program Budget'!N46 -> 0 | M47: 0 | N47: =K47*L47*M47 -> 0 | O47: =K47*1.04 -> 5531.9237 | P47: ='Program Budget'!Q46 -> 0 | Q47: 0 | R47: =O47*P47*Q47 -> 0 | S47: =O47*1.04 -> 5753.2006 | T47: ='Program Budget'!T46 -> 1 | U47: 1 | V47: =ROUNDUP(S47*T47*U47,0) -> 5754 | W47: =F47+J47+N47+R47+V47 -> 10671.86
A48: ='Program Budget'!D47 -> Annual Home of Record & R&R for Chief of Party | B48: ='Program Budget'!F47 -> Trip | C48: ='Program Budget'!H47 -> 1700 | D48: ='Program Budget'!G47 -> 0 | E48: 1 | F48: =C48*D48*E48 -> 0 | G48: =C48*1.04 -> 1768 | H48: ='Program Budget'!K47 -> 1 | I48: =E48 -> 1 | J48: =G48*H48*I48 -> 1768 | K48: =G48*1.04 -> 1838.72 | L48: ='Program Budget'!N47 -> 1 | M48: =I48 -> 1 | N48: =K48*L48*M48 -> 1838.72 | O48: =K48*1.04 -> 1912.2688 | P48: ='Program Budget'!Q47 -> 1 | Q48: =M48 -> 1 | R48: =O48*P48*Q48 -> 1912.2688 | S48: =O48*1.04 -> 1988.7596 | T48: ='Program Budget'!T47 -> 1 | U48: =Q48 -> 1 | V48: =S48*T48*U48 -> 1988.7596 | W48: =F48+J48+N48+R48+V48 -> 7507.7484
A49: Total: Allowances | F49: =SUM(F40:F48) -> 63699.86 | J49: =SUM(J40:J48) -> 25506 | N49: =SUM(N40:N48) -> 26526.24 | R49: =SUM(R40:R48) -> 27587.29 | V49: =SUM(V40:V48) -> 63787.174 | W49: =F49+J49+N49+R49+V49 -> 207106.56
A51: Subtotal: Benefits | F51: =F49+F38 -> 115279.33 | J51: =J49+J38 -> 60830.552 | N51: =N49+N38 -> 62754.232 | R51: =R49+R38 -> 65264.401 | V51: =V49+V38 -> 102277.22 | W51: =+F51+J51+N51+R51+V51 -> 406405.73 | AE51: 287 | AF51: 51-04-2-050 | AG51: DIR-Int Travel Other
A52: International Travel
A53: ='Program Budget'!D53 -> Airfare - DC-Mauritania - HQ Project Management Trip | B53: ='Program Budget'!F53 -> Trip | C53: ='Program Budget'!H53 -> 1700 | D53: ='Program Budget'!G53 -> 4 | E53: 1 | F53: =C53*D53*E53 -> 6800 | G53: =C53*1.04 -> 1768 | H53: ='Program Budget'!K53 -> 4 | I53: 1 | J53: =G53*H53*I53 -> 7072 | K53: =G53*1.04 -> 1838.72 | L53: ='Program Budget'!N53 -> 4 | M53: 1 | N53: =K53*L53*M53 -> 7354.88 | O53: =K53*1.04 -> 1912.2688 | P53: ='Program Budget'!Q53 -> 4 | Q53: 1 | R53: =O53*P53*Q53 -> 7649.0752 | S53: =O53*1.04 -> 1988.7596 | T53: ='Program Budget'!T53 -> 4 | U53: 1 | V53: =S53*T53*U53 -> 7955.0382 | W53: =F53+J53+N53+R53+V53 -> 36830.993 | AE53: 180 | AF53: 50-01-2-020 | AG53: DIR-USN (Expat) Labor
A54: ='Program Budget'!D58 -> Airfare - Roundtrip - Mauritania to USA | B54: ='Program Budget'!F58 -> Trip | C54: ='Program Budget'!H58 -> 1700 | D54: ='Program Budget'!G58 -> 3 | E54: 1 | F54: =C54*D54*E54 -> 5100 | G54: =C54*1.04 -> 1768 | H54: ='Program Budget'!K58 -> 3 | I54: 1 | J54: =G54*H54*I54 -> 5304 | K54: =G54*1.04 -> 1838.72 | L54: ='Program Budget'!N58 -> 3 | M54: 1 | N54: =K54*L54*M54 -> 5516.16 | O54: =K54*1.04 -> 1912.2688 | P54: ='Program Budget'!Q58 -> 3 | Q54: 1 | R54: =O54*P54*Q54 -> 5736.8064 | S54: =O54*1.04 -> 1988.7596 | T54: ='Program Budget'!T58 -> 3 | U54: 1 | V54: =S54*T54*U54 -> 5966.2787 | W54: =F54+J54+N54+R54+V54 -> 27623.245 | AE54: 180 | AF54: 50-01-2-020 | AG54: DIR-USN (Expat) Labor
A55: Local Travel
A56: ='Program Budget'!D55 -> Local Transportation – HQ Project Management Trip | B56: ='Program Budget'!F55 -> Trip | C56: ='Program Budget'!H55 -> 250 | D56: ='Program Budget'!G55 -> 4 | E56: 1 | F56: =C56*D56*E56 -> 1000 | G56: =C56*1.04 -> 260 | H56: ='Program Budget'!K55 -> 4 | I56: 1 | J56: =G56*H56*I56 -> 1040 | K56: =G56*1.04 -> 270.4 | L56: ='Program Budget'!N55 -> 4 | M56: 1 | N56: =K56*L56*M56 -> 1081.6 | O56: =K56*1.04 -> 281.216 | P56: ='Program Budget'!Q55 -> 4 | Q56: 1 | R56: =O56*P56*Q56 -> 1124.864 | S56: =O56*1.04 -> 292.46464 | T56: ='Program Budget'!T55 -> 4 | U56: 1 | V56: =S56*T56*U56 -> 1169.8586 | W56: =F56+J56+N56+R56+V56 -> 5416.3226 | AE56: 180 | AF56: 50-01-2-020 | AG56: DIR-USN (Expat) Labor
A57: ='Program Budget'!D60 -> Local Transportation for Mauritania Staff Travel | B57: ='Program Budget'!F64 -> Trip | C57: ='Program Budget'!H60 -> 250 | D57: ='Program Budget'!G60 -> 3 | E57: 1 | F57: =C57*D57*E57 -> 750 | G57: =C57*1.04 -> 260 | H57: ='Program Budget'!K60 -> 3 | I57: 1 | J57: =G57*H57*I57 -> 780 | K57: =G57*1.04 -> 270.4 | L57: ='Program Budget'!N60 -> 3 | M57: 1 | N57: =K57*L57*M57 -> 811.2 | O57: =K57*1.04 -> 281.216 | P57: ='Program Budget'!Q60 -> 3 | Q57: 1 | R57: =O57*P57*Q57 -> 843.648 | S57: =O57*1.04 -> 292.46464 | T57: ='Program Budget'!T60 -> 3 | U57: 1 | V57: =S57*T57*U57 -> 877.39392 | W57: =F57+J57+N57+R57+V57 -> 4062.2419 | AE57: 180 | AF57: 50-01-2-020 | AG57: DIR-USN (Expat) Labor
A58: ='Program Budget'!D64 -> Local Transportation – Training, M&E, & Data Collection | B58: ='Program Budget'!F64 -> Trip | C58: ='Program Budget'!H64 -> 100 | D58: ='Program Budget'!G64 -> 36 | E58: 1 | F58: =C58*D58*E58 -> 3600 | G58: =C58*1.04 -> 104 | H58: ='Program Budget'!K64 -> 36 | I58: 1 | J58: =G58*H58*I58 -> 3744 | K58: =G58*1.04 -> 108.16 | L58: ='Program Budget'!N64 -> 36 | M58: 1 | N58: =K58*L58*M58 -> 3893.76 | O58: =K58*1.04 -> 112.4864 | P58: ='Program Budget'!Q64 -> 36 | Q58: 1 | R58: =O58*P58*Q58 -> 4049.5104 | S58: =O58*1.04 -> 116.98586 | T58: ='Program Budget'!T64 -> 36 | U58: 1 | V58: =S58*T58*U58 -> 4211.4908 | W58: =F58+J58+N58+R58+V58 -> 19498.761 | AE58: 180 | AF58: 50-01-2-020 | AG58: DIR-USN (Expat) Labor
A59: Vehicle Fuel
A60: ='Program Budget'!D63 -> Motorcycle and Vehicle Fuel Expense | B60: ='Program Budget'!F63 -> Month | C60: ='Program Budget'!H63 -> 150 | D60: ='Program Budget'!G63 -> 3 | E60: 1 | F60: =C60*D60*E60 -> 450 | G60: =C60*1.04 -> 156 | H60: ='Program Budget'!K63 -> 12 | I60: 1 | J60: =G60*H60*I60 -> 1872 | K60: =G60*1.04 -> 162.24 | L60: ='Program Budget'!N63 -> 12 | M60: 1 | N60: =K60*L60*M60 -> 1946.88 | O60: =K60*1.04 -> 168.7296 | P60: ='Program Budget'!Q63 -> 12 | Q60: 1 | R60: =O60*P60*Q60 -> 2024.7552 | S60: =O60*1.04 -> 175.47878 | T60: ='Program Budget'!T63 -> 7 | U60: 1 | V60: =S60*T60*U60 -> 1228.3515 | W60: =F60+J60+N60+R60+V60 -> 7521.9867 | AE60: 180 | AF60: 50-01-2-020 | AG60: DIR-USN (Expat) Labor
A61: Per Diem
A62: ='Program Budget'!D54 -> Lodging and M&IE - HQ Project Management Trip | B62: ='Program Budget'!F54 -> Day | C62: ='Program Budget'!H54 -> 169 | D62: ='Program Budget'!G54 -> 28 | E62: 1 | F62: =C62*D62*E62 -> 4732 | G62: =C62*1.04 -> 175.76 | H62: ='Program Budget'!K54 -> 28 | I62: 1 | J62: =G62*H62*I62 -> 4921.28 | K62: =G62*1.04 -> 182.7904 | L62: ='Program Budget'!N54 -> 28 | M62: 1 | N62: =K62*L62*M62 -> 5118.1312 | O62: =K62*1.04 -> 190.10202 | P62: ='Program Budget'!Q54 -> 28 | Q62: 1 | R62: =O62*P62*Q62 -> 5322.8564 | S62: =O62*1.04 -> 197.7061 | T62: ='Program Budget'!T54 -> 28 | U62: 1 | V62: =S62*T62*U62 -> 5535.7707 | W62: =F62+J62+N62+R62+V62 -> 25630.038 | AE62: 180 | AF62: 50-01-2-020 | AG62: DIR-USN (Expat) Labor
A63: ='Program Budget'!D56 -> Other Travel Related Expenses – HQ Project Management Trip | B63: ='Program Budget'!F56 -> Trip | C63: ='Program Budget'!H56 -> 50 | D63: ='Program Budget'!G56 -> 4 | E63: 1 | F63: =C63*D63*E63 -> 200 | G63: =C63*1.04 -> 52 | H63: ='Program Budget'!K56 -> 4 | I63: 1 | J63: =G63*H63*I63 -> 208 | K63: =G63*1.04 -> 54.08 | L63: ='Program Budget'!N56 -> 4 | M63: 1 | N63: =K63*L63*M63 -> 216.32 | O63: =K63*1.04 -> 56.2432 | P63: ='Program Budget'!Q56 -> 4 | Q63: 1 | R63: =O63*P63*Q63 -> 224.9728 | S63: =O63*1.04 -> 58.492928 | T63: ='Program Budget'!T56 -> 4 | U63: 1 | V63: =S63*T63*U63 -> 233.97171 | W63: =F63+J63+N63+R63+V63 -> 1083.2645 | AE63: 180 | AF63: 50-01-2-020 | AG63: DIR-USN (Expat) Labor
A64: ='Program Budget'!D59 -> Lodging and M&IE for Mauritania Staff Travel | B64: ='Program Budget'!F59 -> Day | C64: ='Program Budget'!H59 -> 169 | D64: ='Program Budget'!G59 -> 21 | E64: 1 | F64: =C64*D64*E64 -> 3549 | G64: =C64*1.04 -> 175.76 | H64: ='Program Budget'!K59 -> 21 | I64: 1 | J64: =G64*H64*I64 -> 3690.96 | K64: =G64*1.04 -> 182.7904 | L64: ='Program Budget'!N59 -> 21 | M64: 1 | N64: =K64*L64*M64 -> 3838.5984 | O64: =K64*1.04 -> 190.10202 | P64: ='Program Budget'!Q59 -> 21 | Q64: 1 | R64: =O64*P64*Q64 -> 3992.1423 | S64: =O64*1.04 -> 197.7061 | T64: ='Program Budget'!T59 -> 21 | U64: 1 | V64: =S64*T64*U64 -> 4151.828 | W64: =F64+J64+N64+R64+V64 -> 19222.529 | AE64: 180 | AF64: 50-01-2-020 | AG64: DIR-USN (Expat) Labor
A65: ='Program Budget'!D61 -> Other Travel Related Expenses for Mauritania Staff Travel | B65: ='Program Budget'!F61 -> Trip | C65: ='Program Budget'!H61 -> 50 | D65: ='Program Budget'!G61 -> 3 | E65: 1 | F65: =C65*D65*E65 -> 150 | G65: =C65*1.04 -> 52 | H65: ='Program Budget'!K61 -> 3 | I65: 1 | J65: =G65*H65*I65 -> 156 | K65: =G65*1.04 -> 54.08 | L65: ='Program Budget'!N61 -> 3 | M65: 1 | N65: =K65*L65*M65 -> 162.24 | O65: =K65*1.04 -> 56.2432 | P65: ='Program Budget'!Q61 -> 3 | Q65: 1 | R65: =O65*P65*Q65 -> 168.7296 | S65: =O65*1.04 -> 58.492928 | T65: ='Program Budget'!T61 -> 3 | U65: 1 | V65: =S65*T65*U65 -> 175.47878 | W65: =F65+J65+N65+R65+V65 -> 812.44838 | AE65: 180 | AF65: 50-01-2-020 | AG65: DIR-USN (Expat) Labor
A66: ='Program Budget'!D65 -> Lodging and M&IE - Training, M&E, & Data Collection | B66: ='Program Budget'!F65 -> Day | C66: ='Program Budget'!H65 -> 78 | D66: ='Program Budget'!G65 -> 144 | E66: 1 | F66: =C66*D66*E66 -> 11232 | G66: =C66*1.04 -> 81.12 | H66: ='Program Budget'!K65 -> 144 | I66: 1 | J66: =G66*H66*I66 -> 11681.28 | K66: =G66*1.04 -> 84.3648 | L66: ='Program Budget'!N65 -> 144 | M66: 1 | N66: =K66*L66*M66 -> 12148.531 | O66: =K66*1.04 -> 87.739392 | P66: ='Program Budget'!Q65 -> 144 | Q66: 1 | R66: =O66*P66*Q66 -> 12634.472 | S66: =O66*1.04 -> 91.248968 | T66: ='Program Budget'!T65 -> 144 | U66: 1 | V66: =S66*T66*U66 -> 13139.851 | W66: =F66+J66+N66+R66+V66 -> 60836.135 | AE66: 180 | AF66: 50-01-2-020 | AG66: DIR-USN (Expat) Labor
A68: Subtotal: Travel | F68: =SUM(F52:F67) -> 37563 | J68: =SUM(J52:J67) -> 40469.52 | N68: =SUM(N52:N67) -> 42088.301 | R68: =SUM(R52:R67) -> 43771.833 | V68: =SUM(V52:V67) -> 44645.312 | W68: =+F68+J68+N68+R68+V68 -> 208537.97
A69: Professional Services
A70: ='Program Budget'!D69 -> Monetization Agent Fee | B70: ='Program Budget'!F69 -> % | C70: =14000000*'Program Budget'!H69 -> 280000 | D70: 0.5 | E70: 1 | F70: =C70*D70*E70 -> 140000 | G70: =C70 -> 280000 | H70: 0.5 | I70: 1 | J70: =G70*H70*I70 -> 140000 | K70: =G70 -> 280000 | L70: ='Program Budget'!N69 -> 0 | M70: 0 | N70: =K70*L70*M70 -> 0 | O70: =K70 -> 280000 | P70: ='Program Budget'!Q69 -> 0 | Q70: 0 | R70: =O70*P70*Q70 -> 0 | S70: =O70 -> 280000 | T70: ='Program Budget'!T69 -> 0 | U70: 0 | V70: =S70*T70*U70 -> 0 | W70: =F70+J70+N70+R70+V70 -> 280000
A71: ='Program Budget'!D70 -> Monetization Impact Assessment | B71: ='Program Budget'!F70 -> Unit | C71: ='Program Budget'!H70 -> 48000 | D71: ='Program Budget'!G70 -> 0 | E71: 1 | F71: =C71*D71*E71 -> 0 | G71: =C71 -> 48000 | H71: ='Program Budget'!K70 -> 1 | I71: 1 | J71: =G71*H71*I71 -> 48000 | K71: =G71 -> 48000 | L71: ='Program Budget'!N70 -> 0 | M71: 0 | N71: =K71*L71*M71 -> 0 | O71: =K71 -> 48000 | P71: ='Program Budget'!Q70 -> 0 | Q71: 0 | R71: =O71*P71*Q71 -> 0 | S71: =O71 -> 48000 | T71: ='Program Budget'!T70 -> 0 | U71: 0 | V71: =S71*T71*U71 -> 0 | W71: =F71+J71+N71+R71+V71 -> 48000
A72: ='Program Budget'!D71 -> Audit Costs - (Program Specific Audits) | B72: ='Program Budget'!F71 -> Year | C72: ='Program Budget'!H71 -> 8000 | D72: ='Program Budget'!G71 -> 1 | E72: 1 | F72: =C72*D72*E72 -> 8000 | G72: =C72 -> 8000 | H72: ='Program Budget'!K71 -> 1 | I72: 1 | J72: =G72*H72*I72 -> 8000 | K72: =G72 -> 8000 | L72: ='Program Budget'!N71 -> 1 | M72: 1 | N72: =K72*L72*M72 -> 8000 | O72: =K72 -> 8000 | P72: ='Program Budget'!Q71 -> 1 | Q72: 1 | R72: =O72*P72*Q72 -> 8000 | S72: =O72 -> 8000 | T72: ='Program Budget'!T71 -> 1 | U72: 1 | V72: =S72*T72*U72 -> 8000 | W72: =F72+J72+N72+R72+V72 -> 40000
A73: ='Program Budget'!D72 -> Legal Fees | B73: ='Program Budget'!F72 -> Year | C73: ='Program Budget'!H72 -> 3000 | D73: ='Program Budget'!G72 -> 1 | E73: 1 | F73: =C73*D73*E73 -> 3000 | G73: =C73 -> 3000 | H73: ='Program Budget'!K72 -> 1 | I73: 1 | J73: =G73*H73*I73 -> 3000 | K73: =G73 -> 3000 | L73: ='Program Budget'!N72 -> 1 | M73: 1 | N73: =K73*L73*M73 -> 3000 | O73: =K73 -> 3000 | P73: ='Program Budget'!Q72 -> 1 | Q73: 1 | R73: =O73*P73*Q73 -> 3000 | S73: =O73 -> 3000 | T73: ='Program Budget'!T72 -> 1 | U73: 1 | V73: =S73*T73*U73 -> 3000 | W73: =F73+J73+N73+R73+V73 -> 15000
A74: ='Program Budget'!D73 -> Security Services, Risk Assessments, & Security Assessment | B74: ='Program Budget'!F73 -> Year | C74: ='Program Budget'!H73 -> 500 | D74: ='Program Budget'!G73 -> 1 | E74: 1 | F74: =C74*D74*E74 -> 500 | G74: =C74 -> 500 | H74: ='Program Budget'!K73 -> 1 | I74: 1 | J74: =G74*H74*I74 -> 500 | K74: =G74 -> 500 | L74: ='Program Budget'!N73 -> 1 | M74: 1 | N74: =K74*L74*M74 -> 500 | O74: =K74 -> 500 | P74: ='Program Budget'!Q73 -> 1 | Q74: 1 | R74: =O74*P74*Q74 -> 500 | S74: =O74 -> 500 | T74: ='Program Budget'!T73 -> 1 | U74: 1 | V74: =S74*T74*U74 -> 500 | W74: =F74+J74+N74+R74+V74 -> 2500
A75: ='Program Budget'!D74 -> Short-Term Technical Advisors | B75: ='Program Budget'!F74 -> Month | C75: ='Program Budget'!H74 -> 425 | D75: ='Program Budget'!G74 -> 9 | E75: 1 | F75: =C75*D75*E75 -> 3825 | G75: =C75 -> 425 | H75: ='Program Budget'!K74 -> 12 | I75: 1 | J75: =G75*H75*I75 -> 5100 | K75: =G75 -> 425 | L75: ='Program Budget'!N74 -> 12 | M75: 1 | N75: =K75*L75*M75 -> 5100 | O75: =K75 -> 425 | P75: ='Program Budget'!Q74 -> 12 | Q75: 1 | R75: =O75*P75*Q75 -> 5100 | S75: =O75 -> 425 | T75: ='Program Budget'!T74 -> 9 | U75: 1 | V75: =S75*T75*U75 -> 3825 | W75: =F75+J75+N75+R75+V75 -> 22950 | AE75: 670 | AF75: 61-01-1-003 | AG75: DIR_Sub-AW (No Fee)
A76: ='Program Budget'!D75 -> Start-up Consultant | B76: ='Program Budget'!F75 -> Day | C76: ='Program Budget'!H75 -> 705 | D76: ='Program Budget'!G75 -> 30 | E76: 1 | F76: =C76*D76*E76 -> 21150 | G76: =C76 -> 705 | H76: ='Program Budget'!K75 -> 0 | I76: 1 | J76: =G76*H76*I76 -> 0 | K76: =G76 -> 705 | L76: ='Program Budget'!N75 -> 0 | M76: 0 | N76: =K76*L76*M76 -> 0 | O76: =K76 -> 705 | P76: ='Program Budget'!Q75 -> 0 | Q76: 0 | R76: =O76*P76*Q76 -> 0 | S76: =O76 -> 705 | T76: ='Program Budget'!T75 -> 0 | U76: 0 | V76: =S76*T76*U76 -> 0 | W76: =F76+J76+N76+R76+V76 -> 21150 | AE76: 670 | AF76: 61-01-1-003 | AG76: DIR_Sub-AW (No Fee)
A77: ='Program Budget'!D76 -> Technical Advisor of Trade Promotion & Strategic Partnership & Investment | B77: ='Program Budget'!F76 -> Month | C77: =(150000/12) -> 12500 | D77: ='Program Budget'!G76 -> 12 | E77: 0.15 | F77: =C77*D77*E77 -> 22500 | G77: =C77 -> 12500 | H77: ='Program Budget'!K76 -> 0 | I77: 0 | J77: =G77*H77*I77 -> 0 | K77: =G77 -> 12500 | L77: ='Program Budget'!N76 -> 0 | M77: 0 | N77: =K77*L77*M77 -> 0 | O77: =K77 -> 12500 | P77: ='Program Budget'!Q76 -> 0 | Q77: 0 | R77: =O77*P77*Q77 -> 0 | S77: =O77 -> 12500 | T77: ='Program Budget'!T76 -> 0 | U77: 0 | V77: =S77*T77*U77 -> 0 | W77: =F77+J77+N77+R77+V77 -> 22500
A78: ='Program Budget'!D78 -> Evaluations
A79: ='Program Budget'!D79 -> Baseline Evaluation | B79: ='Program Budget'!F79 -> Unit | C79: ='Program Budget'!H79 -> 150000 | D79: ='Program Budget'!G79 -> 1 | E79: 1 | F79: =C79*D79*E79 -> 150000 | G79: =C79 -> 150000 | H79: ='Program Budget'!K79 -> 0 | I79: 0 | J79: =G79*H79*I79 -> 0 | K79: =G79 -> 150000 | L79: ='Program Budget'!N79 -> 0 | M79: 0 | N79: =K79*L79*M79 -> 0 | O79: =K79 -> 150000 | P79: ='Program Budget'!Q79 -> 0 | Q79: 0 | R79: =O79*P79*Q79 -> 0 | S79: =O79 -> 150000 | T79: ='Program Budget'!T79 -> 0 | U79: 0 | V79: =S79*T79*U79 -> 0 | W79: =F79+J79+N79+R79+V79 -> 150000
A80: ='Program Budget'!D80 -> Midterm Evaluation | B80: ='Program Budget'!F80 -> Unit | C80: ='Program Budget'!H80 -> 160000 | D80: ='Program Budget'!G80 -> 0 | E80: 0 | F80: =C80*D80*E80 -> 0 | G80: =C80 -> 160000 | H80: ='Program Budget'!K80 -> 0 | I80: 0 | J80: =G80*H80*I80 -> 0 | K80: =G80 -> 160000 | L80: ='Program Budget'!N80 -> 1 | M80: 1 | N80: =K80*L80*M80 -> 160000 | O80: =K80 -> 160000 | P80: ='Program Budget'!Q80 -> 0 | Q80: 0 | R80: =O80*P80*Q80 -> 0 | S80: =O80 -> 160000 | T80: ='Program Budget'!T80 -> 0 | U80: 0 | V80: =S80*T80*U80 -> 0 | W80: =F80+J80+N80+R80+V80 -> 160000
A81: ='Program Budget'!D81 -> Final Evaluation | B81: ='Program Budget'!F81 -> Unit | C81: ='Program Budget'!H81 -> 175000 | D81: ='Program Budget'!G81 -> 0 | E81: 0 | F81: =C81*D81*E81 -> 0 | G81: =C81 -> 175000 | H81: ='Program Budget'!K81 -> 0 | I81: 0 | J81: =G81*H81*I81 -> 0 | K81: =G81 -> 175000 | L81: ='Program Budget'!N81 -> 0 | M81: 0 | N81: =K81*L81*M81 -> 0 | O81: =K81 -> 175000 | P81: ='Program Budget'!Q81 -> 0 | Q81: 0 | R81: =O81*P81*Q81 -> 0 | S81: =O81 -> 175000 | T81: ='Program Budget'!T81 -> 1 | U81: 1 | V81: =S81*T81*U81 -> 175000 | W81: =F81+J81+N81+R81+V81 -> 175000
A82: ='Program Budget'!D82 -> Impact Evaluation | B82: ='Program Budget'!F82 -> Unit | C82: ='Program Budget'!H82 -> 200000 | D82: ='Program Budget'!G82 -> 0 | E82: 0 | F82: =C82*D82*E82 -> 0 | G82: =C82 -> 200000 | H82: ='Program Budget'!K82 -> 0 | I82: 0 | J82: =G82*H82*I82 -> 0 | K82: =G82 -> 200000 | L82: ='Program Budget'!N82 -> 0 | M82: 0 | N82: =K82*L82*M82 -> 0 | O82: =K82 -> 200000 | P82: ='Program Budget'!Q82 -> 0 | Q82: 0 | R82: =O82*P82*Q82 -> 0 | S82: =O82 -> 200000 | T82: ='Program Budget'!T82 -> 1 | U82: 1 | V82: =S82*T82*U82 -> 200000 | W82: =F82+J82+N82+R82+V82 -> 200000
A83: ='Program Budget'!D83 -> Special Study | B83: ='Program Budget'!F83 -> Unit | C83: ='Program Budget'!H83 -> 100000 | D83: ='Program Budget'!G83 -> 0 | E83: 0 | F83: =C83*D83*E83 -> 0 | G83: =C83 -> 100000 | H83: ='Program Budget'!K83 -> 1 | I83: 1 | J83: =G83*H83*I83 -> 100000 | K83: =G83 -> 100000 | L83: ='Program Budget'!N83 -> 1 | M83: 1 | N83: =K83*L83*M83 -> 100000 | O83: =K83 -> 100000 | P83: ='Program Budget'!Q83 -> 0 | Q83: 0 | R83: =O83*P83*Q83 -> 0 | S83: =O83 -> 100000 | T83: ='Program Budget'!T83 -> 0 | U83: 0 | V83: =S83*T83*U83 -> 0 | W83: =F83+J83+N83+R83+V83 -> 200000
A84: ='Program Budget'!D84 -> Monitoring Guidelines Development
A85: ='Program Budget'!D85 -> Monitoring Guidelines Creation, Translation & Printing | B85: ='Program Budget'!F85 -> Document | C85: ='Program Budget'!H85 -> 10000 | D85: ='Program Budget'!G85 -> 1 | E85: 1 | F85: =C85*D85*E85 -> 10000 | G85: =C85 -> 10000 | H85: ='Program Budget'!K85 -> 0 | I85: 0 | J85: =G85*H85*I85 -> 0 | K85: =G85 -> 10000 | L85: ='Program Budget'!N85 -> 0 | M85: 0 | N85: =K85*L85*M85 -> 0 | O85: =K85 -> 10000 | P85: ='Program Budget'!Q85 -> 0 | Q85: 0 | R85: =O85*P85*Q85 -> 0 | S85: =O85 -> 10000 | T85: ='Program Budget'!T85 -> 0 | U85: 0 | V85: =S85*T85*U85 -> 0 | W85: =F85+J85+N85+R85+V85 -> 10000
A86: ='Program Budget'!D86 -> Monitoring Guidelines Revision, Translation & Printing | B86: ='Program Budget'!F86 -> Year | C86: ='Program Budget'!H86 -> 2000 | D86: ='Program Budget'!G86 -> 0 | E86: 0 | F86: =C86*D86*E86 -> 0 | G86: =C86 -> 2000 | H86: ='Program Budget'!K86 -> 1 | I86: 1 | J86: =G86*H86*I86 -> 2000 | K86: =G86 -> 2000 | L86: ='Program Budget'!N86 -> 1 | M86: 1 | N86: =K86*L86*M86 -> 2000 | O86: =K86 -> 2000 | P86: ='Program Budget'!Q86 -> 1 | Q86: 1 | R86: =O86*P86*Q86 -> 2000 | S86: =O86 -> 2000 | T86: ='Program Budget'!T86 -> 1 | U86: 1 | V86: =S86*T86*U86 -> 2000 | W86: =F86+J86+N86+R86+V86 -> 8000
A87: ='Program Budget'!D87 -> Monitoring Guidelines Staff Training on Indicators and Data Collection/Analysis | B87: ='Program Budget'!F87 -> Workshop | C87: ='Program Budget'!H87 -> 6000 | D87: ='Program Budget'!G87 -> 1 | E87: 1 | F87: =C87*D87*E87 -> 6000 | G87: =C87 -> 6000 | H87: ='Program Budget'!K87 -> 1 | I87: 1 | J87: =G87*H87*I87 -> 6000 | K87: =G87 -> 6000 | L87: ='Program Budget'!N87 -> 1 | M87: 1 | N87: =K87*L87*M87 -> 6000 | O87: =K87 -> 6000 | P87: ='Program Budget'!Q87 -> 1 | Q87: 1 | R87: =O87*P87*Q87 -> 6000 | S87: =O87 -> 6000 | T87: ='Program Budget'!T87 -> 1 | U87: 1 | V87: =S87*T87*U87 -> 6000 | W87: =F87+J87+N87+R87+V87 -> 30000
A88: ='Program Budget'!D88 -> M&E Database
A89: ='Program Budget'!D89 -> M&E Database Platform Subscription (includes training) | B89: ='Program Budget'!F89 -> Year | C89: ='Program Budget'!H89 -> 6500 | D89: ='Program Budget'!G89 -> 1 | E89: 1 | F89: =C89*D89*E89 -> 6500 | G89: =C89 -> 6500 | H89: ='Program Budget'!K89 -> 1 | I89: 1 | J89: =G89*H89*I89 -> 6500 | K89: =G89 -> 6500 | L89: ='Program Budget'!N89 -> 1 | M89: 1 | N89: =K89*L89*M89 -> 6500 | O89: =K89 -> 6500 | P89: ='Program Budget'!Q89 -> 1 | Q89: 1 | R89: =O89*P89*Q89 -> 6500 | S89: =O89 -> 6500 | T89: ='Program Budget'!T89 -> 1 | U89: 1 | V89: =S89*T89*U89 -> 6500 | W89: =F89+J89+N89+R89+V89 -> 32500
AE90: 319 | AF90: 51-08-1-004 | AG90: DIR-Office Utilities
A91: Subtotal: Professional Services/Contractual | F91: =SUM(F70:F90) -> 371475 | J91: =SUM(J70:J90) -> 319100 | N91: =SUM(N70:N90) -> 291100 | R91: =SUM(R70:R90) -> 31100 | V91: =SUM(V70:V90) -> 404825 | W91: =+F91+J91+N91+R91+V91 -> 1417600
A92: Equipment (>$5000/unit)
A93: ='Program Budget'!D95 -> Vehicles for Field Office | B93: ='Program Budget'!F95 -> Unit | C93: ='Program Budget'!H95 -> 65000 | D93: ='Program Budget'!G95 -> 2 | E93: 1 | F93: =C93*D93*E93 -> 130000 | G93: =C93 -> 65000 | H93: ='Program Budget'!K95 -> 0 | I93: 0 | J93: =G93*H93*I93 -> 0 | K93: =G93 -> 65000 | L93: ='Program Budget'!N95 -> 0 | M93: 0 | N93: =K93*L93*M93 -> 0 | O93: =K93 -> 65000 | P93: ='Program Budget'!Q95 -> 0 | Q93: 0 | R93: =O93*P93*Q93 -> 0 | S93: =O93 -> 65000 | T93: ='Program Budget'!T95 -> 0 | U93: 0 | V93: =S93*T93*U93 -> 0 | W93: =F93+J93+N93+R93+V93 -> 130000
AE94: 297 | AF94: 51-05-1-002 | AG94: DIR-Office Equipment
A95: Subtotal: Equipment | F95: =SUM(F93:F94) -> 130000 | J95: =SUM(J93:J94) -> 0 | N95: =SUM(N93:N94) -> 0 | R95: =SUM(R93:R94) -> 0 | V95: =SUM(V93:V94) -> 0 | W95: =+F95+J95+N95+R95+V95 -> 130000
A96: Office
A97: ='Program Budget'!D101 -> Communications Costs (Internet, Phone, Data) (Nouakchott) | B97: ='Program Budget'!F101 -> Month | C97: ='Program Budget'!H101 -> 200 | D97: ='Program Budget'!G101 -> 3 | E97: 1 | F97: =C97*D97*E97 -> 600 | G97: =C97*1.04 -> 208 | H97: ='Program Budget'!K101 -> 12 | I97: 1 | J97: =G97*H97*I97 -> 2496 | K97: =G97*1.04 -> 216.32 | L97: ='Program Budget'!N101 -> 12 | M97: 1 | N97: =K97*L97*M97 -> 2595.84 | O97: =K97*1.04 -> 224.9728 | P97: ='Program Budget'!Q101 -> 12 | Q97: 1 | R97: =O97*P97*Q97 -> 2699.6736 | S97: =O97*1.04 -> 233.97171 | T97: ='Program Budget'!T101 -> 6 | U97: 1 | V97: =S97*T97*U97 -> 1403.8303 | W97: =F97+J97+N97+R97+V97 -> 9795.3439
A98: ='Program Budget'!D102 -> Office Rent, Utilities & Security (Nouakchott) | B98: ='Program Budget'!F102 -> Month | C98: ='Program Budget'!H102 -> 3100 | D98: ='Program Budget'!G102 -> 3 | E98: 1 | F98: =C98*D98*E98 -> 9300 | G98: =C98*1.04 -> 3224 | H98: ='Program Budget'!K102 -> 12 | I98: 1 | J98: =G98*H98*I98 -> 38688 | K98: =G98*1.04 -> 3352.96 | L98: ='Program Budget'!N102 -> 12 | M98: 1 | N98: =K98*L98*M98 -> 40235.52 | O98: =K98*1.04 -> 3487.0784 | P98: ='Program Budget'!Q102 -> 12 | Q98: 1 | R98: =O98*P98*Q98 -> 41844.941 | S98: =O98*1.04 -> 3626.5615 | T98: ='Program Budget'!T102 -> 6 | U98: 1 | V98: =S98*T98*U98 -> 21759.369 | W98: =F98+J98+N98+R98+V98 -> 151827.83
A99: ='Program Budget'!D104 -> Communications Costs (Internet, Phone, Data) (Rosso) | B99: ='Program Budget'!F104 -> Month | C99: ='Program Budget'!H104 -> 100 | D99: ='Program Budget'!G104 -> 3 | E99: 1 | F99: =C99*D99*E99 -> 300 | G99: =C99*1.04 -> 104 | H99: ='Program Budget'!K104 -> 12 | I99: 1 | J99: =G99*H99*I99 -> 1248 | K99: =G99*1.04 -> 108.16 | L99: ='Program Budget'!N104 -> 12 | M99: 1 | N99: =K99*L99*M99 -> 1297.92 | O99: =K99*1.04 -> 112.4864 | P99: ='Program Budget'!Q104 -> 12 | Q99: 1 | R99: =O99*P99*Q99 -> 1349.8368 | S99: =O99*1.04 -> 116.98586 | T99: ='Program Budget'!T104 -> 6 | U99: 1 | V99: =S99*T99*U99 -> 701.91514 | W99: =F99+J99+N99+R99+V99 -> 4897.6719
A100: ='Program Budget'!D105 -> Office Rent, Utilities & Security (Rosso) | B100: ='Program Budget'!F105 -> Month | C100: ='Program Budget'!H105 -> 2500 | D100: ='Program Budget'!G105 -> 3 | E100: 1 | F100: =C100*D100*E100 -> 7500 | G100: =C100*1.04 -> 2600 | H100: ='Program Budget'!K105 -> 12 | I100: 1 | J100: =G100*H100*I100 -> 31200 | K100: =G100*1.04 -> 2704 | L100: ='Program Budget'!N105 -> 12 | M100: 1 | N100: =K100*L100*M100 -> 32448 | O100: =K100*1.04 -> 2812.16 | P100: ='Program Budget'!Q105 -> 12 | Q100: 1 | R100: =O100*P100*Q100 -> 33745.92 | S100: =O100*1.04 -> 2924.6464 | T100: ='Program Budget'!T105 -> 6 | U100: 1 | V100: =S100*T100*U100 -> 17547.878 | W100: =F100+J100+N100+R100+V100 -> 122441.8
A101: ='Program Budget'!D107 -> Banking and Cash Handling Fees | B101: ='Program Budget'!F107 -> Month | C101: ='Program Budget'!H107 -> 100 | D101: ='Program Budget'!G107 -> 9 | E101: 1 | F101: =C101*D101*E101 -> 900 | G101: =C101*1.04 -> 104 | H101: ='Program Budget'!K107 -> 12 | I101: 1 | J101: =G101*H101*I101 -> 1248 | K101: =G101*1.04 -> 108.16 | L101: ='Program Budget'!N107 -> 12 | M101: 1 | N101: =K101*L101*M101 -> 1297.92 | O101: =K101*1.04 -> 112.4864 | P101: ='Program Budget'!Q107 -> 12 | Q101: 1 | R101: =O101*P101*Q101 -> 1349.8368 | S101: =O101*1.04 -> 116.98586 | T101: ='Program Budget'!T107 -> 6 | U101: 1 | V101: =S101*T101*U101 -> 701.91514 | W101: =F101+J101+N101+R101+V101 -> 5497.6719
A102: ='Program Budget'!D108 -> Courier fees/services/Postage | B102: ='Program Budget'!F108 -> Month | C102: ='Program Budget'!H108 -> 35 | D102: ='Program Budget'!G108 -> 9 | E102: 1 | F102: =C102*D102*E102 -> 315 | G102: =C102*1.04 -> 36.4 | H102: ='Program Budget'!K108 -> 12 | I102: 1 | J102: =G102*H102*I102 -> 436.8 | K102: =G102*1.04 -> 37.856 | L102: ='Program Budget'!N108 -> 12 | M102: 1 | N102: =K102*L102*M102 -> 454.272 | O102: =K102*1.04 -> 39.37024 | P102: ='Program Budget'!Q108 -> 12 | Q102: 1 | R102: =O102*P102*Q102 -> 472.44288 | S102: =O102*1.04 -> 40.94505 | T102: ='Program Budget'!T108 -> 6 | U102: 1 | V102: =S102*T102*U102 -> 245.6703 | W102: =F102+J102+N102+R102+V102 -> 1924.1852
A103: ='Program Budget'!D109 -> Recruitment/Procurement Advertising | B103: ='Program Budget'!F109 -> Year | C103: ='Program Budget'!H109 -> 500 | D103: ='Program Budget'!G109 -> 1 | E103: 1 | F103: =C103*D103*E103 -> 500 | G103: =C103*1.04 -> 520 | H103: ='Program Budget'!K109 -> 1 | I103: 1 | J103: =G103*H103*I103 -> 520 | K103: =G103*1.04 -> 540.8 | L103: ='Program Budget'!N109 -> 1 | M103: 1 | N103: =K103*L103*M103 -> 540.8 | O103: =K103*1.04 -> 562.432 | P103: ='Program Budget'!Q109 -> 1 | Q103: 1 | R103: =O103*P103*Q103 -> 562.432 | S103: =O103*1.04 -> 584.92928 | T103: ='Program Budget'!T109 -> 1 | U103: 1 | V103: =S103*T103*U103 -> 584.92928 | W103: =F103+J103+N103+R103+V103 -> 2708.1613
A104: ='Program Budget'!D110 -> Meeting Expenses | B104: ='Program Budget'!F110 -> Month | C104: ='Program Budget'!H110 -> 250 | D104: ='Program Budget'!G110 -> 9 | E104: 1 | F104: =C104*D104*E104 -> 2250 | G104: =C104*1.04 -> 260 | H104: ='Program Budget'!K110 -> 12 | I104: 1 | J104: =G104*H104*I104 -> 3120 | K104: =G104*1.04 -> 270.4 | L104: ='Program Budget'!N110 -> 12 | M104: 1 | N104: =K104*L104*M104 -> 3244.8 | O104: =K104*1.04 -> 281.216 | P104: ='Program Budget'!Q110 -> 12 | Q104: 1 | R104: =O104*P104*Q104 -> 3374.592 | S104: =O104*1.04 -> 292.46464 | T104: ='Program Budget'!T110 -> 6 | U104: 1 | V104: =S104*T104*U104 -> 1754.7878 | W104: =F104+J104+N104+R104+V104 -> 13744.18
...

Sheet Activity 1
A2: Item | B2: Type of Unit | C2: Year 1 | G2: Year 2 | K2: Year 3 | O2: Year 4 | S2: Year 5 | W2: Total
C3: Cost | D3: Quantity | E3: Percent Allocated | F3: Total | G3: Cost | H3: Quantity | I3: Percent Allocated | J3: Total | K3: Cost | L3: Quantity | M3: Percent Allocated | N3: Total | O3: Cost | P3: Quantity | Q3: Percent Allocated | R3: Total | S3: Cost | T3: Quantity | U3: Percent Allocated | V3: Total | AF3: Chart of Accounts
A4: Direct Costs | AE4: Line# | AF4: Account | AG4: Account Name
A5: Salaries
A6: USN/TCN Staff
A7: ='Program Budget'!D12 -> Key Personnel: Ex-pat Chief of Party | B7: ='Program Budget'!F13 -> Month | C7: ='Program Budget'!H12 -> 12083.333 | D7: ='Program Budget'!G12 -> 12 | E7: ='Program Budget'!E146 -> 0.2 | F7: =C7*D7*E7 -> 29000 | G7: =C7*1.04 -> 12566.667 | H7: ='Program Budget'!K12 -> 12 | I7: ='Program Budget'!J146 -> 0.25 | J7: =G7*H7*I7 -> 37700 | K7: =G7*1.04 -> 13069.333 | L7: ='Program Budget'!N12 -> 12 | M7: ='Program Budget'!M146 -> 0.25 | N7: =K7*L7*M7 -> 39208 | O7: =K7*1.04 -> 13592.107 | P7: ='Program Budget'!Q12 -> 12 | Q7: ='Program Budget'!P146 -> 0.25 | R7: =O7*P7*Q7 -> 40776.32 | S7: =O7*1.04 -> 14135.791 | T7: ='Program Budget'!T12 -> 12 | U7: ='Program Budget'!S146 -> 0.25 | V7: =S7*T7*U7 -> 42407.373 | W7: =F7+J7+N7+R7+V7 -> 189091.69 | AE7: 180 | AF7: 50-01-2-020 | AG7: DIR-USN (Expat) Labor
A8: Total: Expatriate Salaries & Wages | F8: =SUM(F7:F7) -> 29000 | J8: =SUM(J7:J7) -> 37700 | N8: =SUM(N7:N7) -> 39208 | R8: =SUM(R7:R7) -> 40776.32 | V8: =SUM(V7:V7) -> 42407.373 | W8: =+F8+J8+N8+R8+V8 -> 189091.69
A9: CCN Staff
A10: ='Program Budget'!D13 -> Deputy Chief of Party | B10: ='Program Budget'!F12 -> Month | C10: ='Program Budget'!H13 -> 7500 | D10: ='Program Budget'!G13 -> 6 | E10: ='Program Budget'!E147 -> 0.1 | F10: =C10*D10*E10 -> 4500 | G10: =C10*1.04 -> 7800 | H10: ='Program Budget'!K13 -> 12 | I10: ='Program Budget'!J147 -> 0.1 | J10: =G10*H10*I10 -> 9360 | K10: =G10*1.04 -> 8112 | L10: ='Program Budget'!N13 -> 12 | M10: ='Program Budget'!M147 -> 0.1 | N10: =K10*L10*M10 -> 9734.4 | O10: =K10*1.04 -> 8436.48 | P10: ='Program Budget'!Q13 -> 12 | Q10: ='Program Budget'!P147 -> 0.1 | R10: =O10*P10*Q10 -> 10123.776 | S10: =O10*1.04 -> 8773.9392 | T10: ='Program Budget'!T13 -> 6 | U10: ='Program Budget'!S147 -> 0.1 | V10: =S10*T10*U10 -> 5264.3635 | W10: =F10+J10+N10+R10+V10 -> 38982.54 | AE10: 180 | AF10: 50-01-2-020 | AG10: DIR-USN (Expat) Labor
A11: ='Program Budget'!D148 -> Technical Lead Component 1 | B11: ='Program Budget'!F14 -> Month | C11: ='Program Budget'!H148 -> 3333.3333 | D11: ='Program Budget'!G148 -> 6 | E11: ='Program Budget'!E148 -> 0.75 | F11: =C11*D11*E11 -> 15000 | G11: =C11*1.04 -> 3466.6667 | H11: ='Program Budget'!K148 -> 12 | I11: ='Program Budget'!J148 -> 1 | J11: =G11*H11*I11 -> 41600 | K11: =G11*1.04 -> 3605.3333 | L11: ='Program Budget'!N148 -> 12 | M11: ='Program Budget'!M148 -> 1 | N11: =K11*L11*M11 -> 43264 | O11: =K11*1.04 -> 3749.5467 | P11: ='Program Budget'!Q148 -> 12 | Q11: ='Program Budget'!P148 -> 1 | R11: =O11*P11*Q11 -> 44994.56 | S11: =O11*1.04 -> 3899.5285 | T11: ='Program Budget'!T148 -> 9 | U11: ='Program Budget'!S148 -> 1 | V11: =S11*T11*U11 -> 35095.757 | W11: =F11+J11+N11+R11+V11 -> 179954.32 | AE11: 180 | AF11: 50-01-2-020 | AG11: DIR-USN (Expat) Labor
A12: ='Program Budget'!D149 -> Technical Lead Component 2 | B12: ='Program Budget'!F15 -> Month | C12: ='Program Budget'!H149 -> 3333.3333 | D12: ='Program Budget'!G149 -> 6 | E12: ='Program Budget'!E149 -> 0 | F12: =C12*D12*E12 -> 0 | G12: =C12*1.04 -> 3466.6667 | H12: ='Program Budget'!K149 -> 12 | I12: ='Program Budget'!J149 -> 0 | J12: =G12*H12*I12 -> 0 | K12: =G12*1.04 -> 3605.3333 | L12: ='Program Budget'!N149 -> 12 | M12: ='Program Budget'!M149 -> 0 | N12: =K12*L12*M12 -> 0 | O12: =K12*1.04 -> 3749.5467 | P12: ='Program Budget'!Q149 -> 12 | Q12: ='Program Budget'!P149 -> 0 | R12: =O12*P12*Q12 -> 0 | S12: =O12*1.04 -> 3899.5285 | T12: ='Program Budget'!T149 -> 9 | U12: ='Program Budget'!S149 -> 0 | V12: =S12*T12*U12 -> 0 | W12: =F12+J12+N12+R12+V12 -> 0 | AE12: 180 | AF12: 50-01-2-020 | AG12: DIR-USN (Expat) Labor
A13: ='Program Budget'!D150 -> Technical Lead Component 3 | B13: ='Program Budget'!F16 -> Month | C13: ='Program Budget'!H150 -> 3333.3333 | D13: ='Program Budget'!G150 -> 6 | E13: ='Program Budget'!E150 -> 0 | F13: =C13*D13*E13 -> 0 | G13: =C13*1.04 -> 3466.6667 | H13: ='Program Budget'!K150 -> 12 | I13: ='Program Budget'!J150 -> 0 | J13: =G13*H13*I13 -> 0 | K13: =G13*1.04 -> 3605.3333 | L13: ='Program Budget'!N150 -> 12 | M13: ='Program Budget'!M150 -> 0 | N13: =K13*L13*M13 -> 0 | O13: =K13*1.04 -> 3749.5467 | P13: ='Program Budget'!Q150 -> 12 | Q13: ='Program Budget'!P150 -> 0 | R13: =O13*P13*Q13 -> 0 | S13: =O13*1.04 -> 3899.5285 | T13: ='Program Budget'!T150 -> 9 | U13: ='Program Budget'!S150 -> 0 | V13: =S13*T13*U13 -> 0 | W13: =F13+J13+N13+R13+V13 -> 0 | AE13: 180 | AF13: 50-01-2-020 | AG13: DIR-USN (Expat) Labor
A14: ='Program Budget'!D151 -> Specialist Component 2 | B14: ='Program Budget'!F17 -> Month | C14: ='Program Budget'!H151 -> 1666.6667 | D14: ='Program Budget'!G151 -> 6 | E14: ='Program Budget'!E151 -> 0 | F14: =C14*D14*E14 -> 0 | G14: =C14*1.04 -> 1733.3333 | H14: ='Program Budget'!K151 -> 12 | I14: ='Program Budget'!J151 -> 0 | J14: =G14*H14*I14 -> 0 | K14: =G14*1.04 -> 1802.6667 | L14: ='Program Budget'!N151 -> 12 | M14: ='Program Budget'!M151 -> 0 | N14: =K14*L14*M14 -> 0 | O14: =K14*1.04 -> 1874.7733 | P14: ='Program Budget'!Q151 -> 12 | Q14: ='Program Budget'!P151 -> 0 | R14: =O14*P14*Q14 -> 0 | S14: =O14*1.04 -> 1949.7643 | T14: ='Program Budget'!T151 -> 6 | U14: ='Program Budget'!S151 -> 0 | V14: =S14*T14*U14 -> 0 | W14: =F14+J14+N14+R14+V14 -> 0
A15: ='Program Budget'!D152 -> Specialist Component 3 | B15: ='Program Budget'!F18 -> Month | C15: ='Program Budget'!H152 -> 1666.6667 | D15: ='Program Budget'!G152 -> 6 | E15: ='Program Budget'!E152 -> 0 | F15: =C15*D15*E15 -> 0 | G15: =C15*1.04 -> 1733.3333 | H15: ='Program Budget'!K152 -> 12 | I15: ='Program Budget'!J152 -> 0 | J15: =G15*H15*I15 -> 0 | K15: =G15*1.04 -> 1802.6667 | L15: ='Program Budget'!N152 -> 12 | M15: ='Program Budget'!M152 -> 0 | N15: =K15*L15*M15 -> 0 | O15: =K15*1.04 -> 1874.7733 | P15: ='Program Budget'!Q152 -> 12 | Q15: ='Program Budget'!P152 -> 0 | R15: =O15*P15*Q15 -> 0 | S15: =O15*1.04 -> 1949.7643 | T15: ='Program Budget'!T152 -> 6 | U15: ='Program Budget'!S152 -> 0 | V15: =S15*T15*U15 -> 0 | W15: =F15+J15+N15+R15+V15 -> 0
A16: ='Program Budget'!D153 -> Specialist Component 4 | B16: ='Program Budget'!F19 -> Month | C16: ='Program Budget'!H153 -> 1666.6667 | D16: ='Program Budget'!G153 -> 6 | E16: ='Program Budget'!E153 -> 0 | F16: =C16*D16*E16 -> 0 | G16: =C16*1.04 -> 1733.3333 | H16: ='Program Budget'!K153 -> 12 | I16: ='Program Budget'!J153 -> 0 | J16: =G16*H16*I16 -> 0 | K16: =G16*1.04 -> 1802.6667 | L16: ='Program Budget'!N153 -> 12 | M16: ='Program Budget'!M153 -> 0 | N16: =K16*L16*M16 -> 0 | O16: =K16*1.04 -> 1874.7733 | P16: ='Program Budget'!Q153 -> 12 | Q16: ='Program Budget'!P153 -> 0 | R16: =O16*P16*Q16 -> 0 | S16: =O16*1.04 -> 1949.7643 | T16: ='Program Budget'!T153 -> 6 | U16: ='Program Budget'!S153 -> 0 | V16: =S16*T16*U16 -> 0 | W16: =F16+J16+N16+R16+V16 -> 0
A17: ='Program Budget'!D154 -> Extension Agents (20 Individuals) | B17: ='Program Budget'!F20 -> Month | C17: ='Program Budget'!H154 -> 23333.333 | D17: ='Program Budget'!G154 -> 3 | E17: ='Program Budget'!E154 -> 0.25 | F17: =C17*D17*E17 -> 17500 | G17: =C17*1.04 -> 24266.667 | H17: ='Program Budget'!K154 -> 12 | I17: ='Program Budget'!J154 -> 0.45 | J17: =G17*H17*I17 -> 131040 | K17: =G17*1.04 -> 25237.333 | L17: ='Program Budget'!N154 -> 6 | M17: ='Program Budget'!M154 -> 0.45 | N17: =K17*L17*M17 -> 68140.8 | O17: =K17*1.04 -> 26246.827 | P17: ='Program Budget'!Q154 -> 0 | Q17: ='Program Budget'!P154 -> 0 | R17: =O17*P17*Q17 -> 0 | S17: =O17*1.04 -> 27296.7 | T17: ='Program Budget'!T154 -> 0 | U17: ='Program Budget'!S154 -> 0 | V17: =S17*T17*U17 -> 0 | W17: =F17+J17+N17+R17+V17 -> 216680.8 | AE17: 180 | AF17: 50-01-2-020 | AG17: DIR-USN (Expat) Labor
A18: ='Program Budget'!D155 -> M&E Director | B18: ='Program Budget'!F21 -> Month | C18: ='Program Budget'!H155 -> 3750 | D18: ='Program Budget'!G155 -> 9 | E18: ='Program Budget'!E155 -> 0.3 | F18: =C18*D18*E18 -> 10125 | G18: =C18*1.04 -> 3900 | H18: ='Program Budget'!K155 -> 12 | I18: ='Program Budget'!J155 -> 0.25 | J18: =G18*H18*I18 -> 11700 | K18: =G18*1.04 -> 4056 | L18: ='Program Budget'!N155 -> 12 | M18: ='Program Budget'!M155 -> 0.25 | N18: =K18*L18*M18 -> 12168 | O18: =K18*1.04 -> 4218.24 | P18: ='Program Budget'!Q155 -> 12 | Q18: ='Program Budget'!P155 -> 0.25 | R18: =O18*P18*Q18 -> 12654.72 | S18: =O18*1.04 -> 4386.9696 | T18: ='Program Budget'!T155 -> 12 | U18: ='Program Budget'!S155 -> 0.25 | V18: =S18*T18*U18 -> 13160.909 | W18: =F18+J18+N18+R18+V18 -> 59808.629 | AE18: 180 | AF18: 50-01-2-020 | AG18: DIR-USN (Expat) Labor
A19: ='Program Budget'!D156 -> M&E Specialist | B19: ='Program Budget'!F22 -> Month | C19: ='Program Budget'!H156 -> 2083.3333 | D19: ='Program Budget'!G156 -> 6 | E19: ='Program Budget'!E156 -> 0.2 | F19: =C19*D19*E19 -> 2500 | G19: =C19*1.04 -> 2166.6667 | H19: ='Program Budget'!K156 -> 12 | I19: ='Program Budget'!J156 -> 0.25 | J19: =G19*H19*I19 -> 6500 | K19: =G19*1.04 -> 2253.3333 | L19: ='Program Budget'!N156 -> 12 | M19: ='Program Budget'!M156 -> 0.25 | N19: =K19*L19*M19 -> 6760 | O19: =K19*1.04 -> 2343.4667 | P19: ='Program Budget'!Q156 -> 12 | Q19: ='Program Budget'!P156 -> 0.25 | R19: =O19*P19*Q19 -> 7030.4 | S19: =O19*1.04 -> 2437.2053 | T19: ='Program Budget'!T156 -> 10 | U19: ='Program Budget'!S156 -> 0.25 | V19: =S19*T19*U19 -> 6093.0133 | W19: =F19+J19+N19+R19+V19 -> 28883.413 | AE19: 180 | AF19: 50-01-2-020 | AG19: DIR-USN (Expat) Labor
A20: ='Program Budget'!D157 -> F&A Director | B20: ='Program Budget'!F23 -> Month | C20: ='Program Budget'!H157 -> 6666.6667 | D20: ='Program Budget'!G157 -> 9 | E20: ='Program Budget'!E157 -> 0.2 | F20: =C20*D20*E20 -> 12000 | G20: =C20*1.04 -> 6933.3333 | H20: ='Program Budget'!K157 -> 12 | I20: ='Program Budget'!J157 -> 0.25 | J20: =G20*H20*I20 -> 20800 | K20: =G20*1.04 -> 7210.6667 | L20: ='Program Budget'!N157 -> 12 | M20: ='Program Budget'!M157 -> 0.25 | N20: =K20*L20*M20 -> 21632 | O20: =K20*1.04 -> 7499.0933 | P20: ='Program Budget'!Q157 -> 12 | Q20: ='Program Budget'!P157 -> 0.25 | R20: =O20*P20*Q20 -> 22497.28 | S20: =O20*1.04 -> 7799.0571 | T20: ='Program Budget'!T157 -> 12 | U20: ='Program Budget'!S157 -> 0.25 | V20: =S20*T20*U20 -> 23397.171 | W20: =F20+J20+N20+R20+V20 -> 100326.45 | AE20: 180 | AF20: 50-01-2-020 | AG20: DIR-USN (Expat) Labor
A21: ='Program Budget'!D158 -> Human Resource Manager | B21: ='Program Budget'!F24 -> Month | C21: ='Program Budget'!H158 -> 2916.6667 | D21: ='Program Budget'!G158 -> 9 | E21: ='Program Budget'!E158 -> 0.25 | F21: =C21*D21*E21 -> 6562.5 | G21: =C21*1.04 -> 3033.3333 | H21: ='Program Budget'!K158 -> 12 | I21: ='Program Budget'!J158 -> 0.3 | J21: =G21*H21*I21 -> 10920 | K21: =G21*1.04 -> 3154.6667 | L21: ='Program Budget'!N158 -> 12 | M21: ='Program Budget'!M158 -> 0.25 | N21: =K21*L21*M21 -> 9464 | O21: =K21*1.04 -> 3280.8533 | P21: ='Program Budget'!Q158 -> 12 | Q21: ='Program Budget'!P158 -> 0.25 | R21: =O21*P21*Q21 -> 9842.56 | S21: =O21*1.04 -> 3412.0875 | T21: ='Program Budget'!T158 -> 10 | U21: ='Program Budget'!S158 -> 0.25 | V21: =S21*T21*U21 -> 8530.2187 | W21: =F21+J21+N21+R21+V21 -> 45319.279
A22: ='Program Budget'!D159 -> Contracts & Compliance Specialist | B22: ='Program Budget'!F25 -> Month | C22: ='Program Budget'!H159 -> 2916.6667 | D22: ='Program Budget'!G159 -> 6 | E22: ='Program Budget'!E159 -> 0.25 | F22: =C22*D22*E22 -> 4375 | G22: =C22*1.04 -> 3033.3333 | H22: ='Program Budget'!K159 -> 12 | I22: ='Program Budget'!J159 -> 0.25 | J22: =G22*H22*I22 -> 9100 | K22: =G22*1.04 -> 3154.6667 | L22: ='Program Budget'!N159 -> 12 | M22: ='Program Budget'!M159 -> 0.25 | N22: =K22*L22*M22 -> 9464 | O22: =K22*1.04 -> 3280.8533 | P22: ='Program Budget'!Q159 -> 12 | Q22: ='Program Budget'!P159 -> 0.25 | R22: =O22*P22*Q22 -> 9842.56 | S22: =O22*1.04 -> 3412.0875 | T22: ='Program Budget'!T159 -> 9 | U22: ='Program Budget'!S159 -> 0.25 | V22: =S22*T22*U22 -> 7677.1968 | W22: =F22+J22+N22+R22+V22 -> 40458.757 | AE22: 180 | AF22: 50-01-2-020 | AG22: DIR-USN (Expat) Labor
A23: ='Program Budget'!D160 -> Accountant | B23: ='Program Budget'!F26 -> Month | C23: ='Program Budget'!H160 -> 1666.6667 | D23: ='Program Budget'!G160 -> 7 | E23: ='Program Budget'!E160 -> 0.2 | F23: =C23*D23*E23 -> 2333.3333 | G23: =C23*1.04 -> 1733.3333 | H23: ='Program Budget'!K160 -> 12 | I23: ='Program Budget'!J160 -> 0.2 | J23: =G23*H23*I23 -> 4160 | K23: =G23*1.04 -> 1802.6667 | L23: ='Program Budget'!N160 -> 12 | M23: ='Program Budget'!M160 -> 0.2 | N23: =K23*L23*M23 -> 4326.4 | O23: =K23*1.04 -> 1874.7733 | P23: ='Program Budget'!Q160 -> 12 | Q23: ='Program Budget'!P160 -> 0.2 | R23: =O23*P23*Q23 -> 4499.456 | S23: =O23*1.04 -> 1949.7643 | T23: ='Program Budget'!T160 -> 10 | U23: ='Program Budget'!S160 -> 0.2 | V23: =S23*T23*U23 -> 3899.5285 | W23: =F23+J23+N23+R23+V23 -> 19218.718 | AE23: 180 | AF23: 50-01-2-020 | AG23: DIR-USN (Expat) Labor
A24: ='Program Budget'!D161 -> Administrative Assistant | B24: ='Program Budget'!F27 -> Month | C24: ='Program Budget'!H161 -> 833.33333 | D24: ='Program Budget'!G161 -> 7 | E24: ='Program Budget'!E161 -> 0.2 | F24: =C24*D24*E24 -> 1166.6667 | G24: =C24*1.04 -> 866.66667 | H24: ='Program Budget'!K161 -> 12 | I24: ='Program Budget'!J161 -> 0.2 | J24: =G24*H24*I24 -> 2080 | K24: =G24*1.04 -> 901.33333 | L24: ='Program Budget'!N161 -> 12 | M24: ='Program Budget'!M161 -> 0.2 | N24: =K24*L24*M24 -> 2163.2 | O24: =K24*1.04 -> 937.38667 | P24: ='Program Budget'!Q161 -> 12 | Q24: ='Program Budget'!P161 -> 0.2 | R24: =O24*P24*Q24 -> 2249.728 | S24: =O24*1.04 -> 974.88213 | T24: ='Program Budget'!T161 -> 10 | U24: ='Program Budget'!S161 -> 0.2 | V24: =S24*T24*U24 -> 1949.7643 | W24: =F24+J24+N24+R24+V24 -> 9609.3589 | AE24: 180 | AF24: 50-01-2-020 | AG24: DIR-USN (Expat) Labor
A25: ='Program Budget'!D162 -> Security Guards | B25: ='Program Budget'!F28 -> Month | C25: ='Program Budget'!H162 -> 666.66667 | D25: ='Program Budget'!G162 -> 8 | E25: ='Program Budget'!E162 -> 0.2 | F25: =C25*D25*E25 -> 1066.6667 | G25: =C25*1.04 -> 693.33333 | H25: ='Program Budget'!K162 -> 12 | I25: ='Program Budget'!J162 -> 0.25 | J25: =G25*H25*I25 -> 2080 | K25: =G25*1.04 -> 721.06667 | L25: ='Program Budget'!N162 -> 12 | M25: ='Program Budget'!M162 -> 0.25 | N25: =K25*L25*M25 -> 2163.2 | O25: =K25*1.04 -> 749.90933 | P25: ='Program Budget'!Q162 -> 12 | Q25: ='Program Budget'!P162 -> 0.25 | R25: =O25*P25*Q25 -> 2249.728 | S25: =O25*1.04 -> 779.90571 | T25: ='Program Budget'!T162 -> 10 | U25: ='Program Budget'!S162 -> 0.25 | V25: =S25*T25*U25 -> 1949.7643 | W25: =F25+J25+N25+R25+V25 -> 9509.3589 | AE25: 180 | AF25: 50-01-2-020 | AG25: DIR-USN (Expat) Labor
A26: ='Program Budget'!D163 -> Driver (2 Individuals) | B26: ='Program Budget'!F29 -> Month | C26: ='Program Budget'!H163 -> 1333.3333 | D26: ='Program Budget'!G163 -> 6 | E26: ='Program Budget'!E163 -> 0.2 | F26: =C26*D26*E26 -> 1600 | G26: =C26*1.04 -> 1386.6667 | H26: ='Program Budget'!K163 -> 12 | I26: ='Program Budget'!J163 -> 0.25 | J26: =G26*H26*I26 -> 4160 | K26: =G26*1.04 -> 1442.1333 | L26: ='Program Budget'!N163 -> 12 | M26: ='Program Budget'!M163 -> 0.25 | N26: =K26*L26*M26 -> 4326.4 | O26: =K26*1.04 -> 1499.8187 | P26: ='Program Budget'!Q163 -> 12 | Q26: ='Program Budget'!P163 -> 0.25 | R26: =O26*P26*Q26 -> 4499.456 | S26: =O26*1.04 -> 1559.8114 | T26: ='Program Budget'!T163 -> 9 | U26: ='Program Budget'!S163 -> 0.25 | V26: =S26*T26*U26 -> 3509.5757 | W26: =F26+J26+N26+R26+V26 -> 18095.432 | AE26: 180 | AF26: 50-01-2-020 | AG26: DIR-USN (Expat) Labor
A27: Total Local Salary Cost | F27: =SUM(F10:F26) -> 78729.167 | J27: =SUM(J10:J26) -> 253500 | N27: =SUM(N10:N26) -> 193606.4 | R27: =SUM(R10:R26) -> 130484.22 | V27: =SUM(V10:V26) -> 110527.26 | W27: =F27+J27+N27+R27+V27 -> 766847.05
A29: Subtotal: Salaries & Wages | F29: =F27+F8 -> 107729.17 | J29: =J27+J8 -> 291200 | N29: =N27+N8 -> 232814.4 | R29: =R27+R8 -> 171260.54 | V29: =V27+V8 -> 152934.63 | W29: =+F29+J29+N29+R29+V29 -> 955938.75
A30: Fringe
A31: USN/TCN Staff | B31: ='Program Budget'!F167 -> % | C31: =F8 -> 29000 | D31: 1 | E31: ='Program Budget'!H168 -> 0.2347 | F31: =C31*D31*E31 -> 6806.3 | G31: =J8 -> 37700 | H31: 1 | I31: =E31 -> 0.2347 | J31: =G31*H31*I31 -> 8848.19 | K31: =N8 -> 39208 | L31: 1 | M31: =I31 -> 0.2347 | N31: =K31*L31*M31 -> 9202.1176 | O31: =R8 -> 40776.32 | P31: 1 | Q31: =M31 -> 0.2347 | R31: =O31*P31*Q31 -> 9570.2023 | S31: =V8 -> 42407.373 | T31: 1 | U31: =Q31 -> 0.2347 | V31: =S31*T31*U31 -> 9953.0104 | W31: =F31+J31+N31+R31+V31 -> 44379.82 | AE31: 194 | AF31: 50-03-0-020 | AG31: DIR-Allocated USN Fringe
A32: CCN Staff | B32: ='Program Budget'!F168 -> % | C32: =F27 -> 78729.167 | D32: 1 | E32: ='Program Budget'!H167 -> 0.2692 | F32: =C32*D32*E32 -> 21193.892 | G32: =J27 -> 253500 | H32: 1 | I32: =E32 -> 0.2692 | J32: =G32*H32*I32 -> 68242.2 | K32: =N27 -> 193606.4 | L32: 1 | M32: =I32 -> 0.2692 | N32: =K32*L32*M32 -> 52118.843 | O32: =R27 -> 130484.22 | P32: 1 | Q32: =M32 -> 0.2692 | R32: =O32*P32*Q32 -> 35126.353 | S32: =V27 -> 110527.26 | T32: 1 | U32: =Q32 -> 0.2692 | V32: =S32*T32*U32 -> 29753.939 | W32: =F32+J32+N32+R32+V32 -> 206435.23 | AE32: 197 | AF32: 50-03-0-050 | AG32: DIR-CCN Fringe
A33: Total: Fringe Benefits | F33: =+SUM(F31:F32) -> 28000.192 | J33: =+SUM(J31:J32) -> 77090.39 | N33: =+SUM(N31:N32) -> 61320.96 | R33: =+SUM(R31:R32) -> 44696.555 | V33: =+SUM(V31:V32) -> 39706.949 | W33: =+F33+J33+N33+R33+V33 -> 250815.05
A34: Allowances | W34: =+F34+J34+N34+R34+V34 -> 0
A35: ='Program Budget'!D169 -> Cost of Living Adjustment for Ex-pat Chief of Party | B35: ='Program Budget'!F169 -> % | C35: =F8 -> 29000 | D35: 1 | E35: ='Program Budget'!H169 -> 0.15 | F35: =C35*D35*E35 -> 4350 | G35: =J8 -> 37700 | H35: 1 | I35: =E35 -> 0.15 | J35: =G35*H35*I35 -> 5655 | K35: =N8 -> 39208 | L35: 1 | M35: =I35 -> 0.15 | N35: =K35*L35*M35 -> 5881.2 | O35: =R8 -> 40776.32 | P35: 1 | Q35: =M35 -> 0.15 | R35: =O35*P35*Q35 -> 6116.448 | S35: =V8 -> 42407.373 | T35: 1 | U35: =Q35 -> 0.15 | V35: =S35*T35*U35 -> 6361.1059 | W35: =F35+J35+N35+R35+V35 -> 28363.754
A36: ='Program Budget'!D170 -> Post Hardship for Ex-pat Chief of Party | B36: ='Program Budget'!F170 -> % | C36: =F8 -> 29000 | D36: 1 | E36: ='Program Budget'!H170 -> 0.35 | F36: =C36*D36*E36 -> 10150 | G36: =J8 -> 37700 | H36: 1 | I36: =E36 -> 0.35 | J36: =G36*H36*I36 -> 13195 | K36: =N8 -> 39208 | L36: 1 | M36: =I36 -> 0.35 | N36: =K36*L36*M36 -> 13722.8 | O36: =R8 -> 40776.32 | P36: 1 | Q36: =M36 -> 0.35 | R36: =O36*P36*Q36 -> 14271.712 | S36: =V8 -> 42407.373 | T36: 1 | U36: =Q36 -> 0.35 | V36: =S36*T36*U36 -> 14842.58 | W36: =F36+J36+N36+R36+V36 -> 66182.092
A37: Total: Allowances | F37: =SUM(F35:F36) -> 14500 | J37: =SUM(J35:J36) -> 18850 | N37: =SUM(N35:N36) -> 19604 | R37: =SUM(R35:R36) -> 20388.16 | V37: =SUM(V35:V36) -> 21203.686 | W37: =F37+J37+N37+R37+V37 -> 94545.846
A39: Subtotal: Benefits | F39: =F37+F33 -> 42500.192 | J39: =J37+J33 -> 95940.39 | N39: =N37+N33 -> 80924.96 | R39: =R37+R33 -> 65084.715 | V39: =V37+V33 -> 60910.636 | W39: =+F39+J39+N39+R39+V39 -> 345360.89 | AE39: 287 | AF39: 51-04-2-050 | AG39: DIR-Int Travel Other
A40: Local Travel
A41: ='Program Budget'!D189 -> Local Transportation for Trainings | B41: ='Program Budget'!F189 -> Trip | C41: ='Program Budget'!H189 -> 100 | D41: ='Program Budget'!G189 -> 6 | E41: 1 | F41: =C41*D41*E41 -> 600 | G41: =C41*1.04 -> 104 | H41: ='Program Budget'!K189 -> 12 | I41: 1 | J41: =G41*H41*I41 -> 1248 | K41: =G41*1.04 -> 108.16 | L41: ='Program Budget'!N189 -> 12 | M41: 1 | N41: =K41*L41*M41 -> 1297.92 | O41: =K41*1.04 -> 112.4864 | P41: ='Program Budget'!Q189 -> 12 | Q41: 1 | R41: =O41*P41*Q41 -> 1349.8368 | S41: =O41*1.04 -> 116.98586 | T41: ='Program Budget'!T189 -> 9 | U41: 1 | V41: =S41*T41*U41 -> 1052.8727 | W41: =F41+J41+N41+R41+V41 -> 5548.6295 | AE41: 180 | AF41: 50-01-2-020 | AG41: DIR-USN (Expat) Labor
A42: ='Program Budget'!D191 -> Transport Stipends for Participants to attend Trainings | B42: ='Program Budget'!F191 -> Participant | C42: ='Program Budget'!H191 -> 10 | D42: ='Program Budget'!G191 -> 6000 | E42: 1 | F42: =C42*D42*E42 -> 60000 | G42: =C42*1.04 -> 10.4 | H42: ='Program Budget'!K191 -> 6000 | I42: 1 | J42: =G42*H42*I42 -> 62400 | K42: =G42*1.04 -> 10.816 | L42: ='Program Budget'!N191 -> 0 | M42: 1 | N42: =K42*L42*M42 -> 0 | O42: =K42*1.04 -> 11.24864 | P42: ='Program Budget'!Q191 -> 0 | Q42: 1 | R42: =O42*P42*Q42 -> 0 | S42: =O42*1.04 -> 11.698586 | T42: ='Program Budget'!T191 -> 0 | U42: 1 | V42: =S42*T42*U42 -> 0 | W42: =F42+J42+N42+R42+V42 -> 122400 | AE42: 180 | AF42: 50-01-2-020 | AG42: DIR-USN (Expat) Labor
A43: Vehicle Fuel
A44: ='Program Budget'!D188 -> Motorcycle and Vehicle Fuel Expense | B44: ='Program Budget'!F188 -> Month | C44: ='Program Budget'!H188 -> 170 | D44: ='Program Budget'!G188 -> 3 | E44: 1 | F44: =C44*D44*E44 -> 510 | G44: =C44*1.04 -> 176.8 | H44: ='Program Budget'!K188 -> 12 | I44: 1 | J44: =G44*H44*I44 -> 2121.6 | K44: =G44*1.04 -> 183.872 | L44: ='Program Budget'!N188 -> 12 | M44: 1 | N44: =K44*L44*M44 -> 2206.464 | O44: =K44*1.04 -> 191.22688 | P44: ='Program Budget'!Q188 -> 12 | Q44: 1 | R44: =O44*P44*Q44 -> 2294.7226 | S44: =O44*1.04 -> 198.87596 | T44: ='Program Budget'!T188 -> 7 | U44: 1 | V44: =S44*T44*U44 -> 1392.1317 | W44: =F44+J44+N44+R44+V44 -> 8524.9182 | AE44: 180 | AF44: 50-01-2-020 | AG44: DIR-USN (Expat) Labor
A45: Per Diem
A46: ='Program Budget'!D190 -> Lodging and M&IE for Trainings | B46: ='Program Budget'!F190 -> Day | C46: ='Program Budget'!H190 -> 78 | D46: ='Program Budget'!G190 -> 18 | E46: 1 | F46: =C46*D46*E46 -> 1404 | G46: =C46*1.04 -> 81.12 | H46: ='Program Budget'!K190 -> 36 | I46: 1 | J46: =G46*H46*I46 -> 2920.32 | K46: =G46*1.04 -> 84.3648 | L46: ='Program Budget'!N190 -> 36 | M46: 1 | N46: =K46*L46*M46 -> 3037.1328 | O46: =K46*1.04 -> 87.739392 | P46: ='Program Budget'!Q190 -> 36 | Q46: 1 | R46: =O46*P46*Q46 -> 3158.6181 | S46: =O46*1.04 -> 91.248968 | T46: ='Program Budget'!T190 -> 27 | U46: 1 | V46: =S46*T46*U46 -> 2463.7221 | W46: =F46+J46+N46+R46+V46 -> 12983.793 | AE46: 180 | AF46: 50-01-2-020 | AG46: DIR-USN (Expat) Labor
A48: Subtotal: Travel | F48: =SUM(F40:F46) -> 62514 | J48: =SUM(J40:J46) -> 68689.92 | N48: =SUM(N40:N46) -> 6541.5168 | R48: =SUM(R40:R46) -> 6803.1775 | V48: =SUM(V40:V46) -> 4908.7265 | W48: =+F48+J48+N48+R48+V48 -> 149457.34
A49: Professional Services
A50: ='Program Budget'!D174 -> Contract to 6th Grain for GIS Mapping and Remote Sensing Technologies | B50: ='Program Budget'!F174 -> Unit | C50: ='Program Budget'!H174 -> 300000 | D50: ='Program Budget'!G174 -> 0.5 | E50: 1 | F50: =C50*D50*E50 -> 150000 | G50: =C50 -> 300000 | H50: ='Program Budget'!K174 -> 0.5 | I50: 1 | J50: =G50*H50*I50 -> 150000 | K50: =G50 -> 300000 | L50: ='Program Budget'!N174 -> 0 | M50: 1 | N50: =K50*L50*M50 -> 0 | O50: =K50 -> 300000 | P50: ='Program Budget'!Q174 -> 0 | Q50: 1 | R50: =O50*P50*Q50 -> 0 | S50: =O50 -> 300000 | T50: ='Program Budget'!T174 -> 0 | U50: 1 | V50: =S50*T50*U50 -> 0 | W50: =F50+J50+N50+R50+V50 -> 300000
A51: ='Program Budget'!D175 -> Expert Technical Irrigation Hydrology Engineers - one for large scale infrastructure and one for on-farm irrigation | B51: ='Program Budget'!F175 -> Month | C51: ='Program Budget'!H175 -> 6000 | D51: ='Program Budget'!G175 -> 6 | E51: 1 | F51: =C51*D51*E51 -> 36000 | G51: =C51 -> 6000 | H51: ='Program Budget'!K175 -> 0 | I51: 1 | J51: =G51*H51*I51 -> 0 | K51: =G51 -> 6000 | L51: ='Program Budget'!N175 -> 0 | M51: 1 | N51: =K51*L51*M51 -> 0 | O51: =K51 -> 6000 | P51: ='Program Budget'!Q175 -> 0 | Q51: 1 | R51: =O51*P51*Q51 -> 0 | S51: =O51 -> 6000 | T51: ='Program Budget'!T175 -> 0 | U51: 1 | V51: =S51*T51*U51 -> 0 | W51: =F51+J51+N51+R51+V51 -> 36000
A52: ='Program Budget'!D176 -> Security Services, Risk Assessments, & Security Assessment | B52: Year | C52: 5000 | D52: 1 | E52: 1 | F52: =C52*D52*E52 -> 5000 | G52: =C52 -> 5000 | H52: 1 | I52: 1 | J52: =G52*H52*I52 -> 5000 | K52: =G52 -> 5000 | L52: 1 | M52: 1 | N52: =K52*L52*M52 -> 5000 | O52: =K52 -> 5000 | P52: 1 | Q52: 1 | R52: =O52*P52*Q52 -> 5000 | S52: =O52 -> 5000 | T52: 1 | U52: 1 | V52: =S52*T52*U52 -> 5000 | W52: =F52+J52+N52+R52+V52 -> 25000
A53: ='Program Budget'!D177 -> Short-Term Technical Advisors | B53: ='Program Budget'!F177 -> Month | C53: ='Program Budget'!H177 -> 550 | D53: ='Program Budget'!G177 -> 9 | E53: 1 | F53: =C53*D53*E53 -> 4950 | G53: =C53 -> 550 | H53: ='Program Budget'!K177 -> 12 | I53: 1 | J53: =G53*H53*I53 -> 6600 | K53: =G53 -> 550 | L53: ='Program Budget'!N177 -> 12 | M53: 1 | N53: =K53*L53*M53 -> 6600 | O53: =K53 -> 550 | P53: ='Program Budget'!Q177 -> 12 | Q53: 1 | R53: =O53*P53*Q53 -> 6600 | S53: =O53 -> 550 | T53: ='Program Budget'!T177 -> 9 | U53: 1 | V53: =S53*T53*U53 -> 4950 | W53: =F53+J53+N53+R53+V53 -> 29700
A54: ='Program Budget'!D178 -> Technical Advisor of Trade Promotion & Strategic Partnership & Investment | B54: ='Program Budget'!F178 -> Month | C54: =(150000/12) -> 12500 | D54: ='Program Budget'!G178 -> 0 | E54: 0 | F54: =C54*D54*E54 -> 0 | G54: =C54 -> 12500 | H54: ='Program Budget'!K178 -> 12 | I54: 0.05 | J54: =G54*H54*I54 -> 7500 | K54: =G54 -> 12500 | L54: ='Program Budget'!N178 -> 12 | M54: 0.05 | N54: =K54*L54*M54 -> 7500 | O54: =K54 -> 12500 | P54: ='Program Budget'!Q178 -> 12 | Q54: 0.05 | R54: =O54*P54*Q54 -> 7500 | S54: =O54 -> 12500 | T54: ='Program Budget'!T178 -> 9 | U54: 0.05 | V54: =S54*T54*U54 -> 5625 | W54: =F54+J54+N54+R54+V54 -> 28125
A56: Subtotal: Professional Services/Contractual | F56: =SUM(F50:F54) -> 195950 | J56: =SUM(J50:J54) -> 169100 | N56: =SUM(N50:N54) -> 19100 | R56: =SUM(R50:R54) -> 19100 | V56: =SUM(V50:V54) -> 15575 | W56: =SUM(W50:W54) -> 418825
A57: Equipment (>$5000/unit)
A58: None | F58: =C58*D58*E58 -> 0 | J58: =G58*H58*I58 -> 0 | N58: =K58*L58*M58 -> 0 | R58: =O58*P58*Q58 -> 0 | V58: =S58*T58*U58 -> 0 | W58: =F58+J58+N58+R58+V58 -> 0 | AE58: 298 | AF58: 51-05-1-003 | AG58: DIR-Furniture
A59: Subtotal: Equipment | F59: =SUM(F58:F58) -> 0 | J59: =SUM(J58:J58) -> 0 | N59: =SUM(N58:N58) -> 0 | R59: =SUM(R58:R58) -> 0 | V59: =SUM(V58:V58) -> 0 | W59: =+F59+J59+N59+R59+V59 -> 0
A60: Office
A61: None | F61: =C61*D61*E61 -> 0 | J61: =G61*H61*I61 -> 0 | N61: =K61*L61*M61 -> 0 | R61: =O61*P61*Q61 -> 0 | V61: =S61*T61*U61 -> 0 | W61: =F61+J61+N61+R61+V61 -> 0
A62: Subtotal: Office | F62: =SUM(F58:F58) -> 0 | J62: =SUM(J58:J58) -> 0 | N62: =SUM(N58:N58) -> 0 | R62: =SUM(R58:R58) -> 0 | V62: =SUM(V58:V58) -> 0 | W62: =+F62+J62+N62+R62+V62 -> 0 | AE62: 236 | AF62: 51-02-1-001 | AG62: DIR-Prof. Serv Labor
A63: Supplies | AE63: 236 | AF63: 51-02-1-001 | AG63: DIR-Prof. Serv Labor
A64: ='Program Budget'!D182 -> Seeds and Tools for Demonstration Plots Set-up and Maintenance | B64: ='Program Budget'!F182 -> Unit | C64: ='Program Budget'!H182 -> 3750 | D64: ='Program Budget'!G182 -> 4 | E64: 1 | F64: =C64*D64*E64 -> 15000 | G64: =C64 -> 3750 | H64: ='Program Budget'!K182 -> 4 | I64: 1 | J64: =G64*H64*I64 -> 15000 | K64: =G64 -> 3750 | L64: ='Program Budget'!N182 -> 0 | M64: 1 | N64: =K64*L64*M64 -> 0 | O64: =K64 -> 3750 | P64: ='Program Budget'!Q182 -> 0 | Q64: 1 | R64: =O64*P64*Q64 -> 0 | S64: =O64 -> 3750 | T64: ='Program Budget'!T182 -> 0 | U64: 1 | V64: =S64*T64*U64 -> 0 | W64: =F64+J64+N64+R64+V64 -> 30000
A65: ='Program Budget'!D183 -> Motorcycles for Extension Agents | B65: ='Program Budget'!F183 -> Unit | C65: ='Program Budget'!H183 -> 1100 | D65: ='Program Budget'!G183 -> 9 | E65: 1 | F65: =C65*D65*E65 -> 9900 | G65: =C65 -> 1100 | H65: ='Program Budget'!K183 -> 0 | I65: 1 | J65: =G65*H65*I65 -> 0 | K65: =G65 -> 1100 | L65: ='Program Budget'!N183 -> 0 | M65: 1 | N65: =K65*L65*M65 -> 0 | O65: =K65 -> 1100 | P65: ='Program Budget'!Q183 -> 0 | Q65: 1 | R65: =O65*P65*Q65 -> 0 | S65: =O65 -> 1100 | T65: ='Program Budget'!T183 -> 0 | U65: 1 | V65: =S65*T65*U65 -> 0 | W65: =F65+J65+N65+R65+V65 -> 9900
A66: ='Program Budget'!D184 -> Tablets for Rural Data Collection for Extension Agents | B66: ='Program Budget'!F184 -> Unit | C66: ='Program Budget'!H184 -> 600 | D66: ='Program Budget'!G184 -> 9 | E66: 1 | F66: =C66*D66*E66 -> 5400 | G66: =C66 -> 600 | H66: ='Program Budget'!K184 -> 0 | I66: 1 | J66: =G66*H66*I66 -> 0 | K66: =G66 -> 600 | L66: ='Program Budget'!N184 -> 0 | M66: 1 | N66: =K66*L66*M66 -> 0 | O66: =K66 -> 600 | P66: ='Program Budget'!Q184 -> 0 | Q66: 1 | R66: =O66*P66*Q66 -> 0 | S66: =O66 -> 600 | T66: ='Program Budget'!T184 -> 0 | U66: 1 | V66: =S66*T66*U66 -> 0 | W66: =F66+J66+N66+R66+V66 -> 5400
A68: Subtotal: Supplies | F68: =SUM(F64:F67) -> 30300 | J68: =SUM(J64:J67) -> 15000 | N68: =SUM(N64:N67) -> 0 | R68: =SUM(R64:R67) -> 0 | V68: =SUM(V64:V67) -> 0 | W68: =+F68+J68+N68+R68+V68 -> 45300
A69: Other Direct Cost
A70: Training
A71: ='Program Budget'!D195 -> Development of Technical Package (Design, Printing, & Translation) | B71: ='Program Budget'!F195 -> Unit | C71: ='Program Budget'!H195 -> 18000 | D71: ='Program Budget'!G195 -> 1 | E71: 1 | F71: =C71*D71*E71 -> 18000 | G71: =C71 -> 18000 | H71: ='Program Budget'!K195 -> 0 | I71: 1 | J71: =G71*H71*I71 -> 0 | K71: =G71 -> 18000 | L71: ='Program Budget'!N195 -> 0 | M71: 1 | N71: =K71*L71*M71 -> 0 | O71: =K71 -> 18000 | P71: ='Program Budget'!Q195 -> 0 | Q71: 1 | R71: =O71*P71*Q71 -> 0 | S71: =O71 -> 18000 | T71: ='Program Budget'!T195 -> 0 | U71: 1 | V71: =S71*T71*U71 -> 0 | W71: =F71+J71+N71+R71+V71 -> 18000
A72: ='Program Budget'!D196 -> Publish Report for On-farm Irrigation (Design, Printing, & Translation) | B72: ='Program Budget'!F196 -> Unit | C72: ='Program Budget'!H196 -> 18000 | D72: ='Program Budget'!G196 -> 0 | E72: 1 | F72: =C72*D72*E72 -> 0 | G72: =C72 -> 18000 | H72: ='Program Budget'!K196 -> 1 | I72: 1 | J72: =G72*H72*I72 -> 18000 | K72: =G72 -> 18000 | L72: ='Program Budget'!N196 -> 0 | M72: 1 | N72: =K72*L72*M72 -> 0 | O72: =K72 -> 18000 | P72: ='Program Budget'!Q196 -> 0 | Q72: 1 | R72: =O72*P72*Q72 -> 0 | S72: =O72 -> 18000 | T72: ='Program Budget'!T196 -> 0 | U72: 1 | V72: =S72*T72*U72 -> 0 | W72: =F72+J72+N72+R72+V72 -> 18000
A73: ='Program Budget'!D197 -> Publish Report for Large-Scale Water Infrastructure (Design, Printing, & Translation) | B73: ='Program Budget'!F197 -> Unit | C73: ='Program Budget'!H197 -> 18000 | D73: ='Program Budget'!G197 -> 0 | E73: 1 | F73: =C73*D73*E73 -> 0 | G73: =C73 -> 18000 | H73: ='Program Budget'!K197 -> 1 | I73: 1 | J73: =G73*H73*I73 -> 18000 | K73: =G73 -> 18000 | L73: ='Program Budget'!N197 -> 0 | M73: 1 | N73: =K73*L73*M73 -> 0 | O73: =K73 -> 18000 | P73: ='Program Budget'!Q197 -> 0 | Q73: 1 | R73: =O73*P73*Q73 -> 0 | S73: =O73 -> 18000 | T73: ='Program Budget'!T197 -> 0 | U73: 1 | V73: =S73*T73*U73 -> 0 | W73: =F73+J73+N73+R73+V73 -> 18000
A74: ='Program Budget'!D198 -> Demonstration Plots for Drip and Innovative Irrigation Solutions (2 drip, 2 aspersion/sprinklers and 2 valley pivot plots) | B74: ='Program Budget'!F198 -> Plot | C74: ='Program Budget'!H198 -> 20000 | D74: ='Program Budget'!G198 -> 3 | E74: 1 | F74: =C74*D74*E74 -> 60000 | G74: =C74 -> 20000 | H74: ='Program Budget'!K198 -> 3 | I74: 1 | J74: =G74*H74*I74 -> 60000 | K74: =G74 -> 20000 | L74: ='Program Budget'!N198 -> 0 | M74: 1 | N74: =K74*L74*M74 -> 0 | O74: =K74 -> 20000 | P74: ='Program Budget'!Q198 -> 0 | Q74: 1 | R74: =O74*P74*Q74 -> 0 | S74: =O74 -> 20000 | T74: ='Program Budget'!T198 -> 0 | U74: 1 | V74: =S74*T74*U74 -> 0 | W74: =F74+J74+N74+R74+V74 -> 120000
A76: Subtotal: Other Direct Cost | F76: =SUM(F70:F74) -> 78000 | J76: =SUM(J70:J74) -> 96000 | N76: =SUM(N70:N74) -> 0 | R76: =SUM(R70:R74) -> 0 | V76: =SUM(V70:V74) -> 0 | W76: =+F76+J76+N76+R76+V76 -> 174000 | AE76: 250 | AF76: 51-02-2-008 | AG76: DIR-Security
AE77: 317 | AF77: 51-08-1-002 | AG77: DIR-Office Make Ready
A78: Total Direct Cost | F78: =F29+F39+F48+F62+F68+F56+F76 -> 516993.36 | J78: =J29+J39+J48+J62+J68+J56+J76 -> 735930.31 | N78: =N29+N39+N48+N62+N68+N56+N76 -> 339380.88 | R78: =R29+R39+R48+R62+R68+R56+R76 -> 262248.44 | V78: =V29+V39+V48+V62+V68+V56+V76 -> 234329 | W78: =W29+W39+W48+W62+W68+W56+W76 -> 2088882 | AE78: 318 | AF78: 51-08-1-003 | AG78: DIR-Office Maintenance
A80: Indirect Costs
A81: ICR on Administration | B81: % | C81: 0 | D81: 1 | E81: 0.2828 | F81: =C81*D81*E81 -> 0 | G81: 0 | H81: 1 | I81: 0.2828 | J81: =G81*H81*I81 -> 0 | K81: 0 | L81: 1 | M81: 0.2828 | N81: =K81*L81*M81 -> 0 | O81: 0 | P81: 1 | Q81: 0.2828 | R81: =O81*P81*Q81 -> 0 | S81: 0 | T81: 1 | U81: 0.2828 | V81: =S81*T81*U81 -> 0 | W81: =F81+J81+N81+R81+V81 -> 0
A82: ICR on Activities | B82: % | C82: =F78 -> 516993.36 | D82: 1 | E82: 0.2828 | F82: =C82*D82*E82 -> 146205.72 | G82: =J78 -> 735930.31 | H82: 1 | I82: 0.2828 | J82: =G82*H82*I82 -> 208121.09 | K82: =N78 -> 339380.88 | L82: 1 | M82: 0.2828 | N82: =K82*L82*M82 -> 95976.912 | O82: =R78 -> 262248.44 | P82: 1 | Q82: 0.2828 | R82: =O82*P82*Q82 -> 74163.858 | S82: =V78 -> 234329 | T82: 1 | U82: 0.2828 | V82: =S82*T82*U82 -> 66268.24 | W82: =F82+J82+N82+R82+V82 -> 590735.82
A84: Subtotal Indirect Cost | F84: =SUM(F81:F83) -> 146205.72 | J84: =SUM(J81:J83) -> 208121.09 | N84: =SUM(N81:N83) -> 95976.912 | R84: =SUM(R81:R83) -> 74163.858 | V84: =SUM(V81:V83) -> 66268.24 | W84: =SUM(W81:W83) -> 590735.82
A86: Total Estimated Cost (Direct Cost + Indirect Cost) | F86: =F78+F84 -> 663199.08 | J86: =J78+J84 -> 944051.4 | N86: =N78+N84 -> 435357.79 | R86: =R78+R84 -> 336412.29 | V86: =V78+V84 -> 300597.24 | W86: =F86+J86+N86+R86+V86 -> 2679617.8
A87: Total Cost Share (for reference) | F87: =C87*D87*E87 -> 0 | J87: =G87*H87*I87 -> 0 | N87: =K87*L87*M87 -> 0 | R87: =O87*P87*Q87 -> 0 | V87: =S87*T87*U87 -> 0 | W87: =F87+J87+N87+R87+V87 -> 0
A88: Total Estimated Cost (Direct Cost + Indirect Cost+ Cost Share) | F88: =F86+F87 -> 663199.08 | J88: =J86+J87 -> 944051.4 | N88: =N86+N87 -> 435357.79 | R88: =R86+R87 -> 336412.29 | V88: =V86+V87 -> 300597.24 | W88: =F88+J88+N88+R88+V88 -> 2679617.8
A90: Anticipated Program Income (baked in costs and this is for reference)

Sheet Activity 2
A2: Item | B2: Type of Unit | C2: Year 1 | G2: Year 2 | K2: Year 3 | O2: Year 4 | S2: Year 5 | W2: Total
C3: Cost | D3: Quantity | E3: Percent Allocated | F3: Total | G3: Cost | H3: Quantity | I3: Percent Allocated | J3: Total | K3: Cost | L3: Quantity | M3: Percent Allocated | N3: Total | O3: Cost | P3: Quantity | Q3: Percent Allocated | R3: Total | S3: Cost | T3: Quantity | U3: Percent Allocated | V3: Total | AF3: Chart of Accounts
A4: Direct Costs | AE4: Line# | AF4: Account | AG4: Account Name
A5: Salaries
A6: USN/TCN Staff
A7: ='Program Budget'!D12 -> Key Personnel: Ex-pat Chief of Party | B7: ='Program Budget'!F13 -> Month | C7: ='Program Budget'!H12 -> 12083.333 | D7: ='Program Budget'!G12 -> 12 | E7: ='Program Budget'!E206 -> 0.2 | F7: =C7*D7*E7 -> 29000 | G7: =C7*1.04 -> 12566.667 | H7: ='Program Budget'!K12 -> 12 | I7: ='Program Budget'!J206 -> 0.2 | J7: =G7*H7*I7 -> 30160 | K7: =G7*1.04 -> 13069.333 | L7: ='Program Budget'!N12 -> 12 | M7: ='Program Budget'!M206 -> 0.2 | N7: =K7*L7*M7 -> 31366.4 | O7: =K7*1.04 -> 13592.107 | P7: ='Program Budget'!Q12 -> 12 | Q7: ='Program Budget'!P206 -> 0.2 | R7: =O7*P7*Q7 -> 32621.056 | S7: =O7*1.04 -> 14135.791 | T7: ='Program Budget'!T12 -> 12 | U7: ='Program Budget'!S206 -> 0.2 | V7: =S7*T7*U7 -> 33925.898 | W7: =F7+J7+N7+R7+V7 -> 157073.35 | AE7: 180 | AF7: 50-01-2-020 | AG7: DIR-USN (Expat) Labor
A8: Total: Expatriate Salaries & Wages | F8: =SUM(F7:F7) -> 29000 | J8: =SUM(J7:J7) -> 30160 | N8: =SUM(N7:N7) -> 31366.4 | R8: =SUM(R7:R7) -> 32621.056 | V8: =SUM(V7:V7) -> 33925.898 | W8: =+F8+J8+N8+R8+V8 -> 157073.35
A9: CCN Staff
A10: ='Program Budget'!D13 -> Deputy Chief of Party | B10: ='Program Budget'!F12 -> Month | C10: ='Program Budget'!H13 -> 7500 | D10: ='Program Budget'!G13 -> 6 | E10: ='Program Budget'!E207 -> 0.1 | F10: =C10*D10*E10 -> 4500 | G10: =C10*1.04 -> 7800 | H10: ='Program Budget'!K13 -> 12 | I10: ='Program Budget'!J207 -> 0.1 | J10: =G10*H10*I10 -> 9360 | K10: =G10*1.04 -> 8112 | L10: ='Program Budget'!N13 -> 12 | M10: ='Program Budget'!M207 -> 0.1 | N10: =K10*L10*M10 -> 9734.4 | O10: =K10*1.04 -> 8436.48 | P10: ='Program Budget'!Q13 -> 12 | Q10: ='Program Budget'!P207 -> 0.1 | R10: =O10*P10*Q10 -> 10123.776 | S10: =O10*1.04 -> 8773.9392 | T10: ='Program Budget'!T13 -> 6 | U10: ='Program Budget'!S207 -> 0.1 | V10: =S10*T10*U10 -> 5264.3635 | W10: =F10+J10+N10+R10+V10 -> 38982.54 | AE10: 180 | AF10: 50-01-2-020 | AG10: DIR-USN (Expat) Labor
A11: ='Program Budget'!D208 -> Technical Lead Component 1 | B11: ='Program Budget'!F208 -> Month | C11: ='Program Budget'!H208 -> 3333.3333 | D11: ='Program Budget'!G208 -> 6 | E11: ='Program Budget'!E208 -> 0 | F11: =C11*D11*E11 -> 0 | G11: =C11*1.04 -> 3466.6667 | H11: ='Program Budget'!K208 -> 12 | I11: ='Program Budget'!J208 -> 0 | J11: =G11*H11*I11 -> 0 | K11: =G11*1.04 -> 3605.3333 | L11: ='Program Budget'!N208 -> 12 | M11: ='Program Budget'!M208 -> 0 | N11: =K11*L11*M11 -> 0 | O11: =K11*1.04 -> 3749.5467 | P11: ='Program Budget'!Q208 -> 12 | Q11: ='Program Budget'!P208 -> 0 | R11: =O11*P11*Q11 -> 0 | S11: =O11*1.04 -> 3899.5285 | T11: ='Program Budget'!T208 -> 9 | U11: ='Program Budget'!S208 -> 0 | V11: =S11*T11*U11 -> 0 | W11: =F11+J11+N11+R11+V11 -> 0 | AE11: 180 | AF11: 50-01-2-020 | AG11: DIR-USN (Expat) Labor
A12: ='Program Budget'!D209 -> Technical Lead Component 2 | B12: ='Program Budget'!F209 -> Month | C12: ='Program Budget'!H209 -> 3333.3333 | D12: ='Program Budget'!G209 -> 6 | E12: ='Program Budget'!E209 -> 0.75 | F12: =C12*D12*E12 -> 15000 | G12: =C12*1.04 -> 3466.6667 | H12: ='Program Budget'!K209 -> 12 | I12: ='Program Budget'!J209 -> 1 | J12: =G12*H12*I12 -> 41600 | K12: =G12*1.04 -> 3605.3333 | L12: ='Program Budget'!N209 -> 12 | M12: ='Program Budget'!M209 -> 1 | N12: =K12*L12*M12 -> 43264 | O12: =K12*1.04 -> 3749.5467 | P12: ='Program Budget'!Q209 -> 12 | Q12: ='Program Budget'!P209 -> 1 | R12: =O12*P12*Q12 -> 44994.56 | S12: =O12*1.04 -> 3899.5285 | T12: ='Program Budget'!T209 -> 9 | U12: ='Program Budget'!S209 -> 1 | V12: =S12*T12*U12 -> 35095.757 | W12: =F12+J12+N12+R12+V12 -> 179954.32 | AE12: 180 | AF12: 50-01-2-020 | AG12: DIR-USN (Expat) Labor
A13: ='Program Budget'!D210 -> Technical Lead Component 3 | B13: ='Program Budget'!F210 -> Month | C13: ='Program Budget'!H210 -> 3333.3333 | D13: ='Program Budget'!G210 -> 6 | E13: ='Program Budget'!E210 -> 0 | F13: =C13*D13*E13 -> 0 | G13: =C13*1.04 -> 3466.6667 | H13: ='Program Budget'!K210 -> 12 | I13: ='Program Budget'!J210 -> 0 | J13: =G13*H13*I13 -> 0 | K13: =G13*1.04 -> 3605.3333 | L13: ='Program Budget'!N210 -> 12 | M13: ='Program Budget'!M210 -> 0 | N13: =K13*L13*M13 -> 0 | O13: =K13*1.04 -> 3749.5467 | P13: ='Program Budget'!Q210 -> 12 | Q13: ='Program Budget'!P210 -> 0 | R13: =O13*P13*Q13 -> 0 | S13: =O13*1.04 -> 3899.5285 | T13: ='Program Budget'!T210 -> 9 | U13: ='Program Budget'!S210 -> 0 | V13: =S13*T13*U13 -> 0 | W13: =F13+J13+N13+R13+V13 -> 0 | AE13: 180 | AF13: 50-01-2-020 | AG13: DIR-USN (Expat) Labor
A14: ='Program Budget'!D211 -> Specialist Component 2 | B14: ='Program Budget'!F211 -> Month | C14: ='Program Budget'!H211 -> 1666.6667 | D14: ='Program Budget'!G211 -> 6 | E14: ='Program Budget'!E211 -> 0.8 | F14: =C14*D14*E14 -> 8000 | G14: =C14*1.04 -> 1733.3333 | H14: ='Program Budget'!K211 -> 12 | I14: ='Program Budget'!J211 -> 1 | J14: =G14*H14*I14 -> 20800 | K14: =G14*1.04 -> 1802.6667 | L14: ='Program Budget'!N211 -> 12 | M14: ='Program Budget'!M211 -> 1 | N14: =K14*L14*M14 -> 21632 | O14: =K14*1.04 -> 1874.7733 | P14: ='Program Budget'!Q211 -> 12 | Q14: ='Program Budget'!P211 -> 1 | R14: =O14*P14*Q14 -> 22497.28 | S14: =O14*1.04 -> 1949.7643 | T14: ='Program Budget'!T211 -> 6 | U14: ='Program Budget'!S211 -> 1 | V14: =S14*T14*U14 -> 11698.586 | W14: =F14+J14+N14+R14+V14 -> 84627.866
A15: ='Program Budget'!D212 -> Specialist Component 3 | B15: ='Program Budget'!F212 -> Month | C15: ='Program Budget'!H212 -> 1666.6667 | D15: ='Program Budget'!G212 -> 6 | E15: ='Program Budget'!E212 -> 0 | F15: =C15*D15*E15 -> 0 | G15: =C15*1.04 -> 1733.3333 | H15: ='Program Budget'!K212 -> 12 | I15: ='Program Budget'!J212 -> 0 | J15: =G15*H15*I15 -> 0 | K15: =G15*1.04 -> 1802.6667 | L15: ='Program Budget'!N212 -> 12 | M15: ='Program Budget'!M212 -> 0 | N15: =K15*L15*M15 -> 0 | O15: =K15*1.04 -> 1874.7733 | P15: ='Program Budget'!Q212 -> 12 | Q15: ='Program Budget'!P212 -> 0 | R15: =O15*P15*Q15 -> 0 | S15: =O15*1.04 -> 1949.7643 | T15: ='Program Budget'!T212 -> 6 | U15: ='Program Budget'!S212 -> 0 | V15: =S15*T15*U15 -> 0 | W15: =F15+J15+N15+R15+V15 -> 0
A16: ='Program Budget'!D213 -> Specialist Component 4 | B16: ='Program Budget'!F213 -> Month | C16: ='Program Budget'!H213 -> 1666.6667 | D16: ='Program Budget'!G213 -> 6 | E16: ='Program Budget'!E213 -> 0 | F16: =C16*D16*E16 -> 0 | G16: =C16*1.04 -> 1733.3333 | H16: ='Program Budget'!K213 -> 12 | I16: ='Program Budget'!J213 -> 0 | J16: =G16*H16*I16 -> 0 | K16: =G16*1.04 -> 1802.6667 | L16: ='Program Budget'!N213 -> 12 | M16: ='Program Budget'!M213 -> 0 | N16: =K16*L16*M16 -> 0 | O16: =K16*1.04 -> 1874.7733 | P16: ='Program Budget'!Q213 -> 12 | Q16: ='Program Budget'!P213 -> 0 | R16: =O16*P16*Q16 -> 0 | S16: =O16*1.04 -> 1949.7643 | T16: ='Program Budget'!T213 -> 6 | U16: ='Program Budget'!S213 -> 0 | V16: =S16*T16*U16 -> 0 | W16: =F16+J16+N16+R16+V16 -> 0
A17: ='Program Budget'!D214 -> Extension Agents (20 Individuals) | B17: ='Program Budget'!F214 -> Month | C17: ='Program Budget'!H214 -> 23333.333 | D17: ='Program Budget'!G214 -> 3 | E17: ='Program Budget'!E214 -> 0.2 | F17: =C17*D17*E17 -> 14000 | G17: =C17*1.04 -> 24266.667 | H17: ='Program Budget'!K214 -> 12 | I17: ='Program Budget'!J214 -> 0.3 | J17: =G17*H17*I17 -> 87360 | K17: =G17*1.04 -> 25237.333 | L17: ='Program Budget'!N214 -> 6 | M17: ='Program Budget'!M214 -> 0.3 | N17: =K17*L17*M17 -> 45427.2 | O17: =K17*1.04 -> 26246.827 | P17: ='Program Budget'!Q214 -> 0 | Q17: ='Program Budget'!P214 -> 0 | R17: =O17*P17*Q17 -> 0 | S17: =O17*1.04 -> 27296.7 | T17: ='Program Budget'!T214 -> 0 | U17: ='Program Budget'!S214 -> 0 | V17: =S17*T17*U17 -> 0 | W17: =F17+J17+N17+R17+V17 -> 146787.2 | AE17: 180 | AF17: 50-01-2-020 | AG17: DIR-USN (Expat) Labor
A18: ='Program Budget'!D215 -> M&E Director | B18: ='Program Budget'!F215 -> Month | C18: ='Program Budget'!H215 -> 3750 | D18: ='Program Budget'!G215 -> 9 | E18: ='Program Budget'!E215 -> 0.2 | F18: =C18*D18*E18 -> 6750 | G18: =C18*1.04 -> 3900 | H18: ='Program Budget'!K215 -> 12 | I18: ='Program Budget'!J215 -> 0.2 | J18: =G18*H18*I18 -> 9360 | K18: =G18*1.04 -> 4056 | L18: ='Program Budget'!N215 -> 12 | M18: ='Program Budget'!M215 -> 0.2 | N18: =K18*L18*M18 -> 9734.4 | O18: =K18*1.04 -> 4218.24 | P18: ='Program Budget'!Q215 -> 12 | Q18: ='Program Budget'!P215 -> 0.2 | R18: =O18*P18*Q18 -> 10123.776 | S18: =O18*1.04 -> 4386.9696 | T18: ='Program Budget'!T215 -> 12 | U18: ='Program Budget'!S215 -> 0.2 | V18: =S18*T18*U18 -> 10528.727 | W18: =F18+J18+N18+R18+V18 -> 46496.903 | AE18: 180 | AF18: 50-01-2-020 | AG18: DIR-USN (Expat) Labor
A19: ='Program Budget'!D216 -> M&E Specialist | B19: ='Program Budget'!F216 -> Month | C19: ='Program Budget'!H216 -> 2083.3333 | D19: ='Program Budget'!G216 -> 6 | E19: ='Program Budget'!E216 -> 0.2 | F19: =C19*D19*E19 -> 2500 | G19: =C19*1.04 -> 2166.6667 | H19: ='Program Budget'!K216 -> 12 | I19: ='Program Budget'!J216 -> 0.2 | J19: =G19*H19*I19 -> 5200 | K19: =G19*1.04 -> 2253.3333 | L19: ='Program Budget'!N216 -> 12 | M19: ='Program Budget'!M216 -> 0.2 | N19: =K19*L19*M19 -> 5408 | O19: =K19*1.04 -> 2343.4667 | P19: ='Program Budget'!Q216 -> 12 | Q19: ='Program Budget'!P216 -> 0.2 | R19: =O19*P19*Q19 -> 5624.32 | S19: =O19*1.04 -> 2437.2053 | T19: ='Program Budget'!T216 -> 10 | U19: ='Program Budget'!S216 -> 0.2 | V19: =S19*T19*U19 -> 4874.4107 | W19: =F19+J19+N19+R19+V19 -> 23606.731 | AE19: 180 | AF19: 50-01-2-020 | AG19: DIR-USN (Expat) Labor
A20: ='Program Budget'!D217 -> F&A Director | B20: ='Program Budget'!F217 -> Month | C20: ='Program Budget'!H217 -> 6666.6667 | D20: ='Program Budget'!G217 -> 9 | E20: ='Program Budget'!E217 -> 0.2 | F20: =C20*D20*E20 -> 12000 | G20: =C20*1.04 -> 6933.3333 | H20: ='Program Budget'!K217 -> 12 | I20: ='Program Budget'!J217 -> 0.2 | J20: =G20*H20*I20 -> 16640 | K20: =G20*1.04 -> 7210.6667 | L20: ='Program Budget'!N217 -> 12 | M20: ='Program Budget'!M217 -> 0.2 | N20: =K20*L20*M20 -> 17305.6 | O20: =K20*1.04 -> 7499.0933 | P20: ='Program Budget'!Q217 -> 12 | Q20: ='Program Budget'!P217 -> 0.2 | R20: =O20*P20*Q20 -> 17997.824 | S20: =O20*1.04 -> 7799.0571 | T20: ='Program Budget'!T217 -> 12 | U20: ='Program Budget'!S217 -> 0.2 | V20: =S20*T20*U20 -> 18717.737 | W20: =F20+J20+N20+R20+V20 -> 82661.161 | AE20: 180 | AF20: 50-01-2-020 | AG20: DIR-USN (Expat) Labor
A21: ='Program Budget'!D218 -> Human Resource Manager | B21: ='Program Budget'!F218 -> Month | C21: ='Program Budget'!H218 -> 2916.6667 | D21: ='Program Budget'!G218 -> 9 | E21: ='Program Budget'!E218 -> 0.2 | F21: =C21*D21*E21 -> 5250 | G21: =C21*1.04 -> 3033.3333 | H21: ='Program Budget'!K218 -> 12 | I21: ='Program Budget'!J218 -> 0.2 | J21: =G21*H21*I21 -> 7280 | K21: =G21*1.04 -> 3154.6667 | L21: ='Program Budget'!N218 -> 12 | M21: ='Program Budget'!M218 -> 0.25 | N21: =K21*L21*M21 -> 9464 | O21: =K21*1.04 -> 3280.8533 | P21: ='Program Budget'!Q218 -> 12 | Q21: ='Program Budget'!P218 -> 0.25 | R21: =O21*P21*Q21 -> 9842.56 | S21: =O21*1.04 -> 3412.0875 | T21: ='Program Budget'!T218 -> 10 | U21: ='Program Budget'!S218 -> 0.25 | V21: =S21*T21*U21 -> 8530.2187 | W21: =F21+J21+N21+R21+V21 -> 40366.779
A22: ='Program Budget'!D219 -> Contracts & Compliance Specialist | B22: ='Program Budget'!F219 -> Month | C22: ='Program Budget'!H219 -> 2916.6667 | D22: ='Program Budget'!G219 -> 6 | E22: ='Program Budget'!E219 -> 0.25 | F22: =C22*D22*E22 -> 4375 | G22: =C22*1.04 -> 3033.3333 | H22: ='Program Budget'!K219 -> 12 | I22: ='Program Budget'!J219 -> 0.25 | J22: =G22*H22*I22 -> 9100 | K22: =G22*1.04 -> 3154.6667 | L22: ='Program Budget'!N219 -> 12 | M22: ='Program Budget'!M219 -> 0.25 | N22: =K22*L22*M22 -> 9464 | O22: =K22*1.04 -> 3280.8533 | P22: ='Program Budget'!Q219 -> 12 | Q22: ='Program Budget'!P219 -> 0.25 | R22: =O22*P22*Q22 -> 9842.56 | S22: =O22*1.04 -> 3412.0875 | T22: ='Program Budget'!T219 -> 9 | U22: ='Program Budget'!S219 -> 0.25 | V22: =S22*T22*U22 -> 7677.1968 | W22: =F22+J22+N22+R22+V22 -> 40458.757 | AE22: 180 | AF22: 50-01-2-020 | AG22: DIR-USN (Expat) Labor
A23: ='Program Budget'!D220 -> Accountant | B23: ='Program Budget'!F220 -> Month | C23: ='Program Budget'!H220 -> 1666.6667 | D23: ='Program Budget'!G220 -> 7 | E23: ='Program Budget'!E220 -> 0.2 | F23: =C23*D23*E23 -> 2333.3333 | G23: =C23*1.04 -> 1733.3333 | H23: ='Program Budget'!K220 -> 12 | I23: ='Program Budget'!J220 -> 0.2 | J23: =G23*H23*I23 -> 4160 | K23: =G23*1.04 -> 1802.6667 | L23: ='Program Budget'!N220 -> 12 | M23: ='Program Budget'!M220 -> 0.2 | N23: =K23*L23*M23 -> 4326.4 | O23: =K23*1.04 -> 1874.7733 | P23: ='Program Budget'!Q220 -> 12 | Q23: ='Program Budget'!P220 -> 0.2 | R23: =O23*P23*Q23 -> 4499.456 | S23: =O23*1.04 -> 1949.7643 | T23: ='Program Budget'!T220 -> 10 | U23: ='Program Budget'!S220 -> 0.2 | V23: =S23*T23*U23 -> 3899.5285 | W23: =F23+J23+N23+R23+V23 -> 19218.718 | AE23: 180 | AF23: 50-01-2-020 | AG23: DIR-USN (Expat) Labor
A24: ='Program Budget'!D221 -> Administrative Assistant | B24: ='Program Budget'!F221 -> Month | C24: ='Program Budget'!H221 -> 833.33333 | D24: ='Program Budget'!G221 -> 7 | E24: ='Program Budget'!E221 -> 0.2 | F24: =C24*D24*E24 -> 1166.6667 | G24: =C24*1.04 -> 866.66667 | H24: ='Program Budget'!K221 -> 12 | I24: ='Program Budget'!J221 -> 0.2 | J24: =G24*H24*I24 -> 2080 | K24: =G24*1.04 -> 901.33333 | L24: ='Program Budget'!N221 -> 12 | M24: ='Program Budget'!M221 -> 0.2 | N24: =K24*L24*M24 -> 2163.2 | O24: =K24*1.04 -> 937.38667 | P24: ='Program Budget'!Q221 -> 12 | Q24: ='Program Budget'!P221 -> 0.2 | R24: =O24*P24*Q24 -> 2249.728 | S24: =O24*1.04 -> 974.88213 | T24: ='Program Budget'!T221 -> 10 | U24: ='Program Budget'!S221 -> 0.2 | V24: =S24*T24*U24 -> 1949.7643 | W24: =F24+J24+N24+R24+V24 -> 9609.3589 | AE24: 180 | AF24: 50-01-2-020 | AG24: DIR-USN (Expat) Labor
A25: ='Program Budget'!D222 -> Security Guards | B25: ='Program Budget'!F222 -> Month | C25: ='Program Budget'!H222 -> 666.66667 | D25: ='Program Budget'!G222 -> 8 | E25: ='Program Budget'!E222 -> 0.2 | F25: =C25*D25*E25 -> 1066.6667 | G25: =C25*1.04 -> 693.33333 | H25: ='Program Budget'!K222 -> 12 | I25: ='Program Budget'!J222 -> 0.25 | J25: =G25*H25*I25 -> 2080 | K25: =G25*1.04 -> 721.06667 | L25: ='Program Budget'!N222 -> 12 | M25: ='Program Budget'!M222 -> 0.25 | N25: =K25*L25*M25 -> 2163.2 | O25: =K25*1.04 -> 749.90933 | P25: ='Program Budget'!Q222 -> 12 | Q25: ='Program Budget'!P222 -> 0.25 | R25: =O25*P25*Q25 -> 2249.728 | S25: =O25*1.04 -> 779.90571 | T25: ='Program Budget'!T222 -> 10 | U25: ='Program Budget'!S222 -> 0.25 | V25: =S25*T25*U25 -> 1949.7643 | W25: =F25+J25+N25+R25+V25 -> 9509.3589 | AE25: 180 | AF25: 50-01-2-020 | AG25: DIR-USN (Expat) Labor
A26: ='Program Budget'!D223 -> Driver (2 Individuals) | B26: ='Program Budget'!F223 -> Month | C26: ='Program Budget'!H223 -> 1333.3333 | D26: ='Program Budget'!G223 -> 6 | E26: ='Program Budget'!E223 -> 0.2 | F26: =C26*D26*E26 -> 1600 | G26: =C26*1.04 -> 1386.6667 | H26: ='Program Budget'!K223 -> 12 | I26: ='Program Budget'!J223 -> 0.2 | J26: =G26*H26*I26 -> 3328 | K26: =G26*1.04 -> 1442.1333 | L26: ='Program Budget'!N223 -> 12 | M26: ='Program Budget'!M223 -> 0.2 | N26: =K26*L26*M26 -> 3461.12 | O26: =K26*1.04 -> 1499.8187 | P26: ='Program Budget'!Q223 -> 12 | Q26: ='Program Budget'!P223 -> 0.2 | R26: =O26*P26*Q26 -> 3599.5648 | S26: =O26*1.04 -> 1559.8114 | T26: ='Program Budget'!T223 -> 9 | U26: ='Program Budget'!S223 -> 0.2 | V26: =S26*T26*U26 -> 2807.6605 | W26: =F26+J26+N26+R26+V26 -> 14796.345 | AE26: 180 | AF26: 50-01-2-020 | AG26: DIR-USN (Expat) Labor
A27: Total Local Salary Cost | F27: =SUM(F10:F26) -> 78541.667 | J27: =SUM(J10:J26) -> 218348 | N27: =SUM(N10:N26) -> 183547.52 | R27: =SUM(R10:R26) -> 143645.13 | V27: =SUM(V10:V26) -> 112993.71 | W27: =F27+J27+N27+R27+V27 -> 737076.03
A29: Subtotal: Salaries & Wages | F29: =F27+F8 -> 107541.67 | J29: =J27+J8 -> 248508 | N29: =N27+N8 -> 214913.92 | R29: =R27+R8 -> 176266.19 | V29: =V27+V8 -> 146919.61 | W29: =+F29+J29+N29+R29+V29 -> 894149.39
A30: Fringe
A31: USN/TCN Staff | B31: ='Program Budget'!F167 -> % | C31: =F8 -> 29000 | D31: 1 | E31: ='Program Budget'!H228 -> 0.2347 | F31: =C31*D31*E31 -> 6806.3 | G31: =J8 -> 30160 | H31: 1 | I31: =E31 -> 0.2347 | J31: =G31*H31*I31 -> 7078.552 | K31: =N8 -> 31366.4 | L31: 1 | M31: =I31 -> 0.2347 | N31: =K31*L31*M31 -> 7361.6941 | O31: =R8 -> 32621.056 | P31: 1 | Q31: =M31 -> 0.2347 | R31: =O31*P31*Q31 -> 7656.1618 | S31: =V8 -> 33925.898 | T31: 1 | U31: =Q31 -> 0.2347 | V31: =S31*T31*U31 -> 7962.4083 | W31: =F31+J31+N31+R31+V31 -> 36865.116 | AE31: 194 | AF31: 50-03-0-020 | AG31: DIR-Allocated USN Fringe
A32: CCN Staff | B32: ='Program Budget'!F168 -> % | C32: =F27 -> 78541.667 | D32: 1 | E32: ='Program Budget'!H227 -> 0.2692 | F32: =C32*D32*E32 -> 21143.417 | G32: =J27 -> 218348 | H32: 1 | I32: =E32 -> 0.2692 | J32: =G32*H32*I32 -> 58779.282 | K32: =N27 -> 183547.52 | L32: 1 | M32: =I32 -> 0.2692 | N32: =K32*L32*M32 -> 49410.992 | O32: =R27 -> 143645.13 | P32: 1 | Q32: =M32 -> 0.2692 | R32: =O32*P32*Q32 -> 38669.27 | S32: =V27 -> 112993.71 | T32: 1 | U32: =Q32 -> 0.2692 | V32: =S32*T32*U32 -> 30417.908 | W32: =F32+J32+N32+R32+V32 -> 198420.87 | AE32: 197 | AF32: 50-03-0-050 | AG32: DIR-CCN Fringe
A33: Total: Fringe Benefits | F33: =+SUM(F31:F32) -> 27949.717 | J33: =+SUM(J31:J32) -> 65857.834 | N33: =+SUM(N31:N32) -> 56772.686 | R33: =+SUM(R31:R32) -> 46325.432 | V33: =+SUM(V31:V32) -> 38380.316 | W33: =+F33+J33+N33+R33+V33 -> 235285.98
A34: Allowances | W34: =+F34+J34+N34+R34+V34 -> 0
A35: ='Program Budget'!D169 -> Cost of Living Adjustment for Ex-pat Chief of Party | B35: ='Program Budget'!F169 -> % | C35: =F8 -> 29000 | D35: 1 | E35: ='Program Budget'!H229 -> 0.15 | F35: =C35*D35*E35 -> 4350 | G35: =J8 -> 30160 | H35: 1 | I35: =E35 -> 0.15 | J35: =G35*H35*I35 -> 4524 | K35: =N8 -> 31366.4 | L35: 1 | M35: =I35 -> 0.15 | N35: =K35*L35*M35 -> 4704.96 | O35: =R8 -> 32621.056 | P35: 1 | Q35: =M35 -> 0.15 | R35: =O35*P35*Q35 -> 4893.1584 | S35: =V8 -> 33925.898 | T35: 1 | U35: =Q35 -> 0.15 | V35: =S35*T35*U35 -> 5088.8847 | W35: =F35+J35+N35+R35+V35 -> 23561.003
A36: ='Program Budget'!D170 -> Post Hardship for Ex-pat Chief of Party | B36: ='Program Budget'!F170 -> % | C36: =F8 -> 29000 | D36: 1 | E36: ='Program Budget'!H230 -> 0.35 | F36: =C36*D36*E36 -> 10150 | G36: =J8 -> 30160 | H36: 1 | I36: =E36 -> 0.35 | J36: =G36*H36*I36 -> 10556 | K36: =N8 -> 31366.4 | L36: 1 | M36: =I36 -> 0.35 | N36: =K36*L36*M36 -> 10978.24 | O36: =R8 -> 32621.056 | P36: 1 | Q36: =M36 -> 0.35 | R36: =O36*P36*Q36 -> 11417.37 | S36: =V8 -> 33925.898 | T36: 1 | U36: =Q36 -> 0.35 | V36: =S36*T36*U36 -> 11874.064 | W36: =F36+J36+N36+R36+V36 -> 54975.674
A37: Total: Allowances | F37: =SUM(F35:F36) -> 14500 | J37: =SUM(J35:J36) -> 15080 | N37: =SUM(N35:N36) -> 15683.2 | R37: =SUM(R35:R36) -> 16310.528 | V37: =SUM(V35:V36) -> 16962.949 | W37: =F37+J37+N37+R37+V37 -> 78536.677
A38: Subtotal: Benefits | F38: =F37+F33 -> 42449.717 | J38: =J37+J33 -> 80937.834 | N38: =N37+N33 -> 72455.886 | R38: =R37+R33 -> 62635.96 | V38: =V37+V33 -> 55343.265 | W38: =+F38+J38+N38+R38+V38 -> 313822.66 | AE38: 287 | AF38: 51-04-2-050 | AG38: DIR-Int Travel Other
A39: Local Travel
A40: ='Program Budget'!D250 -> Local Transportation for Trainings | B40: ='Program Budget'!F250 -> Trip | C40: ='Program Budget'!H250 -> 100 | D40: ='Program Budget'!G250 -> 6 | E40: 1 | F40: =C40*D40*E40 -> 600 | G40: =C40*1.04 -> 104 | H40: ='Program Budget'!K250 -> 12 | I40: 1 | J40: =G40*H40*I40 -> 1248 | K40: =G40*1.04 -> 108.16 | L40: ='Program Budget'!N250 -> 12 | M40: 1 | N40: =K40*L40*M40 -> 1297.92 | O40: =K40*1.04 -> 112.4864 | P40: ='Program Budget'!Q250 -> 12 | Q40: 1 | R40: =O40*P40*Q40 -> 1349.8368 | S40: =O40*1.04 -> 116.98586 | T40: ='Program Budget'!T250 -> 9 | U40: 1 | V40: =S40*T40*U40 -> 1052.8727 | W40: =F40+J40+N40+R40+V40 -> 5548.6295 | AE40: 180 | AF40: 50-01-2-020 | AG40: DIR-USN (Expat) Labor
A41: ='Program Budget'!D252 -> Transport Stipends for Participants to attend Farmer Field Schools | B41: ='Program Budget'!F252 -> Participant | C41: ='Program Budget'!H252 -> 10 | D41: ='Program Budget'!G252 -> 0 | E41: 1 | F41: =C41*D41*E41 -> 0 | G41: =C41*1.04 -> 10.4 | H41: ='Program Budget'!K252 -> 1000 | I41: 1 | J41: =G41*H41*I41 -> 10400 | K41: =G41*1.04 -> 10.816 | L41: ='Program Budget'!N252 -> 1000 | M41: 1 | N41: =K41*L41*M41 -> 10816 | O41: =K41*1.04 -> 11.24864 | P41: ='Program Budget'!Q252 -> 1000 | Q41: 1 | R41: =O41*P41*Q41 -> 11248.64 | S41: =O41*1.04 -> 11.698586 | T41: ='Program Budget'!T252 -> 0 | U41: 1 | V41: =S41*T41*U41 -> 0 | W41: =F41+J41+N41+R41+V41 -> 32464.64 | AE41: 180 | AF41: 50-01-2-020 | AG41: DIR-USN (Expat) Labor
A42: Vehicle Fuel
A43: ='Program Budget'!D249 -> Motorcycle and Vehicle Fuel Expense | B43: ='Program Budget'!F249 -> Month | C43: ='Program Budget'!H249 -> 170 | D43: ='Program Budget'!G249 -> 3 | E43: 1 | F43: =C43*D43*E43 -> 510 | G43: =C43*1.04 -> 176.8 | H43: ='Program Budget'!K249 -> 12 | I43: 1 | J43: =G43*H43*I43 -> 2121.6 | K43: =G43*1.04 -> 183.872 | L43: ='Program Budget'!N249 -> 12 | M43: 1 | N43: =K43*L43*M43 -> 2206.464 | O43: =K43*1.04 -> 191.22688 | P43: ='Program Budget'!Q249 -> 12 | Q43: 1 | R43: =O43*P43*Q43 -> 2294.7226 | S43: =O43*1.04 -> 198.87596 | T43: ='Program Budget'!T249 -> 7 | U43: 1 | V43: =S43*T43*U43 -> 1392.1317 | W43: =F43+J43+N43+R43+V43 -> 8524.9182 | AE43: 180 | AF43: 50-01-2-020 | AG43: DIR-USN (Expat) Labor
A44: Per Diem | F44: =C44*D44*E44 -> 0 | J44: =G44*H44*I44 -> 0 | N44: =K44*L44*M44 -> 0 | R44: =O44*P44*Q44 -> 0 | V44: =S44*T44*U44 -> 0 | W44: =F44+J44+N44+R44+V44 -> 0
A45: ='Program Budget'!D251 -> Lodging and M&IE for Trainings | B45: ='Program Budget'!F251 -> Day | C45: ='Program Budget'!H251 -> 78 | D45: ='Program Budget'!G251 -> 18 | E45: 1 | F45: =C45*D45*E45 -> 1404 | G45: =C45*1.04 -> 81.12 | H45: ='Program Budget'!K251 -> 36 | I45: 1 | J45: =G45*H45*I45 -> 2920.32 | K45: =G45*1.04 -> 84.3648 | L45: ='Program Budget'!N251 -> 36 | M45: 1 | N45: =K45*L45*M45 -> 3037.1328 | O45: =K45*1.04 -> 87.739392 | P45: ='Program Budget'!Q251 -> 36 | Q45: 1 | R45: =O45*P45*Q45 -> 3158.6181 | S45: =O45*1.04 -> 91.248968 | T45: ='Program Budget'!T251 -> 27 | U45: 1 | V45: =S45*T45*U45 -> 2463.7221 | W45: =F45+J45+N45+R45+V45 -> 12983.793 | AE45: 180 | AF45: 50-01-2-020 | AG45: DIR-USN (Expat) Labor
A47: Subtotal: Travel | F47: =SUM(F39:F46) -> 2514 | J47: =SUM(J39:J46) -> 16689.92 | N47: =SUM(N39:N46) -> 17357.517 | R47: =SUM(R39:R46) -> 18051.817 | V47: =SUM(V39:V46) -> 4908.7265 | W47: =+F47+J47+N47+R47+V47 -> 59521.981
A48: Professional Services
A49: ='Program Budget'!D234 -> Consultant to Design Materials for Outreach and Awareness Campaign including Translation | B49: ='Program Budget'!F234 -> Unit | C49: ='Program Budget'!H234 -> 30000 | D49: ='Program Budget'!G234 -> 1 | E49: 1 | F49: =C49*D49*E49 -> 30000 | G49: =C49 -> 30000 | H49: ='Program Budget'!K234 -> 0 | I49: 1 | J49: =G49*H49*I49 -> 0 | K49: =G49 -> 30000 | L49: ='Program Budget'!N234 -> 0 | M49: 1 | N49: =K49*L49*M49 -> 0 | O49: =K49 -> 30000 | P49: ='Program Budget'!Q234 -> 0 | Q49: 1 | R49: =O49*P49*Q49 -> 0 | S49: =O49 -> 30000 | T49: ='Program Budget'!T234 -> 0 | U49: 1 | V49: =S49*T49*U49 -> 0 | W49: =F49+J49+N49+R49+V49 -> 30000
A50: ='Program Budget'!D235 -> Contract for Dissemination of Outreach and Awareness Campaigns | B50: ='Program Budget'!F235 -> Year | C50: ='Program Budget'!H235 -> 60000 | D50: ='Program Budget'!G235 -> 0 | E50: 1 | F50: =C50*D50*E50 -> 0 | G50: =C50 -> 60000 | H50: ='Program Budget'!K235 -> 0 | I50: 1 | J50: =G50*H50*I50 -> 0 | K50: =G50 -> 60000 | L50: ='Program Budget'!N235 -> 1 | M50: 1 | N50: =K50*L50*M50 -> 60000 | O50: =K50 -> 60000 | P50: ='Program Budget'!Q235 -> 1 | Q50: 1 | R50: =O50*P50*Q50 -> 60000 | S50: =O50 -> 60000 | T50: ='Program Budget'!T235 -> 1 | U50: 1 | V50: =S50*T50*U50 -> 60000 | W50: =F50+J50+N50+R50+V50 -> 180000
A51: ='Program Budget'!D236 -> Contract Nurseries in Mauritania and Senegal | B51: ='Program Budget'!F236 -> Contract | C51: ='Program Budget'!H236 -> 10000 | D51: ='Program Budget'!G236 -> 5 | E51: 1 | F51: =C51*D51*E51 -> 50000 | G51: =C51 -> 10000 | H51: ='Program Budget'!K236 -> 0 | I51: 1 | J51: =G51*H51*I51 -> 0 | K51: =G51 -> 10000 | L51: ='Program Budget'!N236 -> 0 | M51: 1 | N51: =K51*L51*M51 -> 0 | O51: =K51 -> 10000 | P51: ='Program Budget'!Q236 -> 0 | Q51: 1 | R51: =O51*P51*Q51 -> 0 | S51: =O51 -> 10000 | T51: ='Program Budget'!T236 -> 0 | U51: 1 | V51: =S51*T51*U51 -> 0 | W51: =F51+J51+N51+R51+V51 -> 50000
A52: ='Program Budget'!D237 -> Consultant to Create Outreach and Sensitization Materials for Social Behavioral Change Activities | B52: ='Program Budget'!F237 -> Month | C52: ='Program Budget'!H237 -> 3000 | D52: ='Program Budget'!G237 -> 0 | E52: 1 | F52: =C52*D52*E52 -> 0 | G52: =C52 -> 3000 | H52: ='Program Budget'!K237 -> 2 | I52: 1 | J52: =G52*H52*I52 -> 6000 | K52: =G52 -> 3000 | L52: ='Program Budget'!N237 -> 2 | M52: 1 | N52: =K52*L52*M52 -> 6000 | O52: =K52 -> 3000 | P52: ='Program Budget'!Q237 -> 2 | Q52: 1 | R52: =O52*P52*Q52 -> 6000 | S52: =O52 -> 3000 | T52: ='Program Budget'!T237 -> 0 | U52: 1 | V52: =S52*T52*U52 -> 0 | W52: =F52+J52+N52+R52+V52 -> 18000
A53: ='Program Budget'!D238 -> Security Services, Risk Assessments, & Security Assessment | B53: ='Program Budget'!F238 -> Year | C53: ='Program Budget'!H238 -> 7000 | D53: ='Program Budget'!G238 -> 1 | E53: 1 | F53: =C53*D53*E53 -> 7000 | G53: =C53 -> 7000 | H53: ='Program Budget'!K238 -> 1 | I53: 1 | J53: =G53*H53*I53 -> 7000 | K53: =G53 -> 7000 | L53: ='Program Budget'!N238 -> 1 | M53: 1 | N53: =K53*L53*M53 -> 7000 | O53: =K53 -> 7000 | P53: ='Program Budget'!Q238 -> 1 | Q53: 1 | R53: =O53*P53*Q53 -> 7000 | S53: =O53 -> 7000 | T53: ='Program Budget'!T238 -> 1 | U53: 1 | V53: =S53*T53*U53 -> 7000 | W53: =F53+J53+N53+R53+V53 -> 35000
A54: ='Program Budget'!D239 -> Short-Term Technical Advisors | B54: ='Program Budget'!F239 -> Month | C54: ='Program Budget'!H239 -> 500 | D54: ='Program Budget'!G239 -> 9 | E54: 1 | F54: =C54*D54*E54 -> 4500 | G54: =C54 -> 500 | H54: ='Program Budget'!K239 -> 12 | I54: 1 | J54: =G54*H54*I54 -> 6000 | K54: =G54 -> 500 | L54: ='Program Budget'!N239 -> 12 | M54: 1 | N54: =K54*L54*M54 -> 6000 | O54: =K54 -> 500 | P54: ='Program Budget'!Q239 -> 12 | Q54: 1 | R54: =O54*P54*Q54 -> 6000 | S54: =O54 -> 500 | T54: ='Program Budget'!T239 -> 9 | U54: 1 | V54: =S54*T54*U54 -> 4500 | W54: =F54+J54+N54+R54+V54 -> 27000
A55: ='Program Budget'!D240 -> Technical Advisor of Trade Promotion & Strategic Partnership & Investment | B55: ='Program Budget'!F240 -> Month | C55: =(150000/12) -> 12500 | D55: ='Program Budget'!G240 -> 0 | E55: 0 | F55: =C55*D55*E55 -> 0 | G55: =C55 -> 12500 | H55: ='Program Budget'!K240 -> 12 | I55: 0.05 | J55: =G55*H55*I55 -> 7500 | K55: =G55 -> 12500 | L55: ='Program Budget'!N240 -> 12 | M55: 0.05 | N55: =K55*L55*M55 -> 7500 | O55: =K55 -> 12500 | P55: ='Program Budget'!Q240 -> 12 | Q55: 0.05 | R55: =O55*P55*Q55 -> 7500 | S55: =O55 -> 12500 | T55: ='Program Budget'!T240 -> 9 | U55: 0.05 | V55: =S55*T55*U55 -> 5625 | W55: =F55+J55+N55+R55+V55 -> 28125
A57: Subtotal: Professional Services/Contractual | F57: =SUM(F49:F56) -> 91500 | J57: =SUM(J49:J56) -> 26500 | N57: =SUM(N49:N56) -> 86500 | R57: =SUM(R49:R56) -> 86500 | V57: =SUM(V49:V56) -> 77125 | W57: =SUM(W49:W56) -> 368125
A58: Equipment (>$5000/unit)
A59: None | F59: =C59*D59*E59 -> 0 | J59: =G59*H59*I59 -> 0 | N59: =K59*L59*M59 -> 0 | R59: =O59*P59*Q59 -> 0 | V59: =S59*T59*U59 -> 0 | W59: =F59+J59+N59+R59+V59 -> 0 | AE59: 298 | AF59: 51-05-1-003 | AG59: DIR-Furniture
A60: Subtotal: Equipment | F60: =SUM(F59:F59) -> 0 | J60: =SUM(J59:J59) -> 0 | N60: =SUM(N59:N59) -> 0 | R60: =SUM(R59:R59) -> 0 | V60: =SUM(V59:V59) -> 0 | W60: =+F60+J60+N60+R60+V60 -> 0
A61: Office
A62: None | F62: =C62*D62*E62 -> 0 | J62: =G62*H62*I62 -> 0 | N62: =K62*L62*M62 -> 0 | R62: =O62*P62*Q62 -> 0 | V62: =S62*T62*U62 -> 0 | W62: =F62+J62+N62+R62+V62 -> 0 | AE62: 298 | AF62: 51-05-1-003 | AG62: DIR-Furniture
A63: Subtotal: Office | F63: =SUM(F59:F59) -> 0 | J63: =SUM(J59:J59) -> 0 | N63: =SUM(N59:N59) -> 0 | R63: =SUM(R59:R59) -> 0 | V63: =SUM(V59:V59) -> 0 | W63: =+F63+J63+N63+R63+V63 -> 0 | AE63: 236 | AF63: 51-02-1-001 | AG63: DIR-Prof. Serv Labor
A64: Supplies | AE64: 236 | AF64: 51-02-1-001 | AG64: DIR-Prof. Serv Labor
A65: ='Program Budget'!D244 -> Motorcycles for Extension Agent | B65: ='Program Budget'!F244 -> Unit | C65: ='Program Budget'!H244 -> 1100 | D65: ='Program Budget'!G244 -> 6 | E65: 1 | F65: =C65*D65*E65 -> 6600 | G65: =C65 -> 1100 | H65: ='Program Budget'!K244 -> 0 | I65: 1 | J65: =G65*H65*I65 -> 0 | K65: =G65 -> 1100 | L65: ='Program Budget'!N244 -> 0 | M65: 1 | N65: =K65*L65*M65 -> 0 | O65: =K65 -> 1100 | P65: ='Program Budget'!Q244 -> 0 | Q65: 1 | R65: =O65*P65*Q65 -> 0 | S65: =O65 -> 1100 | T65: ='Program Budget'!T244 -> 0 | U65: 1 | V65: =S65*T65*U65 -> 0 | W65: =F65+J65+N65+R65+V65 -> 6600
A66: ='Program Budget'!D245 -> Tablets for Rural Data Collection for Extension Agents | B66: ='Program Budget'!F245 -> Unit | C66: ='Program Budget'!H245 -> 600 | D66: ='Program Budget'!G245 -> 6 | E66: 1 | F66: =C66*D66*E66 -> 3600 | G66: =C66 -> 600 | H66: ='Program Budget'!K245 -> 0 | I66: 1 | J66: =G66*H66*I66 -> 0 | K66: =G66 -> 600 | L66: ='Program Budget'!N245 -> 0 | M66: 1 | N66: =K66*L66*M66 -> 0 | O66: =K66 -> 600 | P66: ='Program Budget'!Q245 -> 0 | Q66: 1 | R66: =O66*P66*Q66 -> 0 | S66: =O66 -> 600 | T66: ='Program Budget'!T245 -> 0 | U66: 1 | V66: =S66*T66*U66 -> 0 | W66: =F66+J66+N66+R66+V66 -> 3600
A68: Subtotal: Supplies | F68: =SUM(F65:F67) -> 10200 | J68: =SUM(J65:J67) -> 0 | N68: =SUM(N65:N67) -> 0 | R68: =SUM(R65:R67) -> 0 | V68: =SUM(V65:V67) -> 0 | W68: =SUM(W65:W67) -> 10200
A69: Other Direct Cost
A70: Training
A71: ='Program Budget'!D256 -> Farmer Field Schools | B71: ='Program Budget'!F256 -> Training | C71: ='Program Budget'!H256 -> 10000 | D71: ='Program Budget'!G256 -> 0 | E71: 1 | F71: =C71*D71*E71 -> 0 | G71: =C71 -> 10000 | H71: ='Program Budget'!K256 -> 6 | I71: 1 | J71: =G71*H71*I71 -> 60000 | K71: =G71 -> 10000 | L71: ='Program Budget'!N256 -> 6 | M71: 1 | N71: =K71*L71*M71 -> 60000 | O71: =K71 -> 10000 | P71: ='Program Budget'!Q256 -> 6 | Q71: 1 | R71: =O71*P71*Q71 -> 60000 | S71: =O71 -> 10000 | T71: ='Program Budget'!T256 -> 0 | U71: 1 | V71: =S71*T71*U71 -> 0 | W71: =F71+J71+N71+R71+V71 -> 180000
A73: Subtotal: Other Direct Cost | F73: =SUM(F70:F71) -> 0 | J73: =SUM(J70:J71) -> 60000 | N73: =SUM(N70:N71) -> 60000 | R73: =SUM(R70:R71) -> 60000 | V73: =SUM(V70:V71) -> 0 | W73: =+F73+J73+N73+R73+V73 -> 180000 | AE73: 250 | AF73: 51-02-2-008 | AG73: DIR-Security
AE74: 317 | AF74: 51-08-1-002 | AG74: DIR-Office Make Ready
A75: Total Direct Cost | F75: =F29+F38+F47+F63+F68+F57+F73 -> 254205.38 | J75: =J29+J38+J47+J63+J68+J57+J73 -> 432635.75 | N75: =N29+N38+N47+N63+N68+N57+N73 -> 451227.32 | R75: =R29+R38+R47+R63+R68+R57+R73 -> 403453.97 | V75: =V29+V38+V47+V63+V68+V57+V73 -> 284296.6 | W75: =W29+W38+W47+W63+W68+W57+W73 -> 1825819 | AE75: 318 | AF75: 51-08-1-003 | AG75: DIR-Office Maintenance
A77: Indirect Costs
A78: ICR on Administration | B78: % | C78: 0 | D78: 1 | E78: 0.2828 | F78: =C78*D78*E78 -> 0 | G78: 0 | H78: 1 | I78: 0.2828 | J78: =G78*H78*I78 -> 0 | K78: 0 | L78: 1 | M78: 0.2828 | N78: =K78*L78*M78 -> 0 | O78: 0 | P78: 1 | Q78: 0.2828 | R78: =O78*P78*Q78 -> 0 | S78: 0 | T78: 1 | U78: 0.2828 | V78: =S78*T78*U78 -> 0 | W78: =F78+J78+N78+R78+V78 -> 0
A79: ICR on Activities | B79: % | C79: =F75 -> 254205.38 | D79: 1 | E79: 0.2828 | F79: =C79*D79*E79 -> 71889.282 | G79: =J75 -> 432635.75 | H79: 1 | I79: 0.2828 | J79: =G79*H79*I79 -> 122349.39 | K79: =N75 -> 451227.32 | L79: 1 | M79: 0.2828 | N79: =K79*L79*M79 -> 127607.09 | O79: =R75 -> 403453.97 | P79: 1 | Q79: 0.2828 | R79: =O79*P79*Q79 -> 114096.78 | S79: =V75 -> 284296.6 | T79: 1 | U79: 0.2828 | V79: =S79*T79*U79 -> 80399.079 | W79: =F79+J79+N79+R79+V79 -> 516341.62
A81: Subtotal Indirect Cost | F81: =SUM(F78:F80) -> 71889.282 | J81: =SUM(J78:J80) -> 122349.39 | N81: =SUM(N78:N80) -> 127607.09 | R81: =SUM(R78:R80) -> 114096.78 | V81: =SUM(V78:V80) -> 80399.079 | W81: =SUM(W78:W80) -> 516341.62
A83: Total Estimated Cost (Direct Cost + Indirect Cost) | F83: =F75+F81 -> 326094.67 | J83: =J75+J81 -> 554985.14 | N83: =N75+N81 -> 578834.41 | R83: =R75+R81 -> 517550.75 | V83: =V75+V81 -> 364695.68 | W83: =F83+J83+N83+R83+V83 -> 2342160.7
A84: Total Cost Share (for reference) | F84: =C84*D84*E84 -> 0 | J84: =G84*H84*I84 -> 0 | N84: =K84*L84*M84 -> 0 | R84: =O84*P84*Q84 -> 0 | V84: =S84*T84*U84 -> 0 | W84: =F84+J84+N84+R84+V84 -> 0
A85: Total Estimated Cost (Direct Cost + Indirect Cost+ Cost Share) | F85: =F83+F84 -> 326094.67 | J85: =J83+J84 -> 554985.14 | N85: =N83+N84 -> 578834.41 | R85: =R83+R84 -> 517550.75 | V85: =V83+V84 -> 364695.68 | W85: =F85+J85+N85+R85+V85 -> 2342160.7
A87: Anticipated Program Income (baked in costs and this is for reference)

Sheet Activity 3
A2: Item | B2: Type of Unit | C2: Year 1 | G2: Year 2 | K2: Year 3 | O2: Year 4 | S2: Year 5 | W2: Total
C3: Cost | D3: Quantity | E3: Percent Allocated | F3: Total | G3: Cost | H3: Quantity | I3: Percent Allocated | J3: Total | K3: Cost | L3: Quantity | M3: Percent Allocated | N3: Total | O3: Cost | P3: Quantity | Q3: Percent Allocated | R3: Total | S3: Cost | T3: Quantity | U3: Percent Allocated | V3: Total | AF3: Chart of Accounts
A4: Direct Costs | AE4: Line# | AF4: Account | AG4: Account Name
A5: Salaries
A6: USN/TCN Staff
A7: ='Program Budget'!D12 -> Key Personnel: Ex-pat Chief of Party | B7: ='Program Budget'!F13 -> Month | C7: ='Program Budget'!H12 -> 12083.333 | D7: ='Program Budget'!G12 -> 12 | E7: ='Program Budget'!E264 -> 0.2 | F7: =C7*D7*E7 -> 29000 | G7: =C7*1.04 -> 12566.667 | H7: ='Program Budget'!K12 -> 12 | I7: ='Program Budget'!J264 -> 0.25 | J7: =G7*H7*I7 -> 37700 | K7: =G7*1.04 -> 13069.333 | L7: ='Program Budget'!N12 -> 12 | M7: ='Program Budget'!M264 -> 0.25 | N7: =K7*L7*M7 -> 39208 | O7: =K7*1.04 -> 13592.107 | P7: ='Program Budget'!Q12 -> 12 | Q7: ='Program Budget'!P264 -> 0.25 | R7: =O7*P7*Q7 -> 40776.32 | S7: =O7*1.04 -> 14135.791 | T7: ='Program Budget'!T12 -> 12 | U7: ='Program Budget'!S264 -> 0.25 | V7: =S7*T7*U7 -> 42407.373 | W7: =F7+J7+N7+R7+V7 -> 189091.69 | AE7: 180 | AF7: 50-01-2-020 | AG7: DIR-USN (Expat) Labor
A8: Total: Expatriate Salaries & Wages | F8: =SUM(F7:F7) -> 29000 | J8: =SUM(J7:J7) -> 37700 | N8: =SUM(N7:N7) -> 39208 | R8: =SUM(R7:R7) -> 40776.32 | V8: =SUM(V7:V7) -> 42407.373 | W8: =+F8+J8+N8+R8+V8 -> 189091.69
A9: CCN Staff
A10: ='Program Budget'!D13 -> Deputy Chief of Party | B10: ='Program Budget'!F12 -> Month | C10: ='Program Budget'!H13 -> 7500 | D10: ='Program Budget'!G13 -> 6 | E10: ='Program Budget'!E265 -> 0.1 | F10: =C10*D10*E10 -> 4500 | G10: =C10*1.04 -> 7800 | H10: ='Program Budget'!K13 -> 12 | I10: ='Program Budget'!J265 -> 0.1 | J10: =G10*H10*I10 -> 9360 | K10: =G10*1.04 -> 8112 | L10: ='Program Budget'!N13 -> 12 | M10: ='Program Budget'!M265 -> 0.1 | N10: =K10*L10*M10 -> 9734.4 | O10: =K10*1.04 -> 8436.48 | P10: ='Program Budget'!Q13 -> 12 | Q10: ='Program Budget'!P265 -> 0.1 | R10: =O10*P10*Q10 -> 10123.776 | S10: =O10*1.04 -> 8773.9392 | T10: ='Program Budget'!T13 -> 6 | U10: ='Program Budget'!S265 -> 0.1 | V10: =S10*T10*U10 -> 5264.3635 | W10: =F10+J10+N10+R10+V10 -> 38982.54 | AE10: 180 | AF10: 50-01-2-020 | AG10: DIR-USN (Expat) Labor
A11: ='Program Budget'!D266 -> Technical Lead Component 1 | B11: ='Program Budget'!F266 -> Month | C11: ='Program Budget'!H266 -> 3333.3333 | D11: ='Program Budget'!G266 -> 6 | E11: ='Program Budget'!E266 -> 0 | F11: =C11*D11*E11 -> 0 | G11: =C11*1.04 -> 3466.6667 | H11: ='Program Budget'!K266 -> 12 | I11: ='Program Budget'!J266 -> 0 | J11: =G11*H11*I11 -> 0 | K11: =G11*1.04 -> 3605.3333 | L11: ='Program Budget'!N266 -> 12 | M11: ='Program Budget'!M266 -> 0 | N11: =K11*L11*M11 -> 0 | O11: =K11*1.04 -> 3749.5467 | P11: ='Program Budget'!Q266 -> 12 | Q11: ='Program Budget'!P266 -> 0 | R11: =O11*P11*Q11 -> 0 | S11: =O11*1.04 -> 3899.5285 | T11: ='Program Budget'!T266 -> 9 | U11: ='Program Budget'!S266 -> 0 | V11: =S11*T11*U11 -> 0 | W11: =F11+J11+N11+R11+V11 -> 0 | AE11: 180 | AF11: 50-01-2-020 | AG11: DIR-USN (Expat) Labor
A12: ='Program Budget'!D267 -> Technical Lead Component 2 | B12: ='Program Budget'!F267 -> Month | C12: ='Program Budget'!H267 -> 3333.3333 | D12: ='Program Budget'!G267 -> 6 | E12: ='Program Budget'!E267 -> 0 | F12: =C12*D12*E12 -> 0 | G12: =C12*1.04 -> 3466.6667 | H12: ='Program Budget'!K267 -> 12 | I12: ='Program Budget'!J267 -> 0 | J12: =G12*H12*I12 -> 0 | K12: =G12*1.04 -> 3605.3333 | L12: ='Program Budget'!N267 -> 12 | M12: ='Program Budget'!M267 -> 0 | N12: =K12*L12*M12 -> 0 | O12: =K12*1.04 -> 3749.5467 | P12: ='Program Budget'!Q267 -> 12 | Q12: ='Program Budget'!P267 -> 0 | R12: =O12*P12*Q12 -> 0 | S12: =O12*1.04 -> 3899.5285 | T12: ='Program Budget'!T267 -> 9 | U12: ='Program Budget'!S267 -> 0 | V12: =S12*T12*U12 -> 0 | W12: =F12+J12+N12+R12+V12 -> 0 | AE12: 180 | AF12: 50-01-2-020 | AG12: DIR-USN (Expat) Labor
A13: ='Program Budget'!D268 -> Technical Lead Component 3 | B13: ='Program Budget'!F268 -> Month | C13: ='Program Budget'!H268 -> 3333.3333 | D13: ='Program Budget'!G268 -> 6 | E13: ='Program Budget'!E268 -> 0.75 | F13: =C13*D13*E13 -> 15000 | G13: =C13*1.04 -> 3466.6667 | H13: ='Program Budget'!K268 -> 12 | I13: ='Program Budget'!J268 -> 1 | J13: =G13*H13*I13 -> 41600 | K13: =G13*1.04 -> 3605.3333 | L13: ='Program Budget'!N268 -> 12 | M13: ='Program Budget'!M268 -> 1 | N13: =K13*L13*M13 -> 43264 | O13: =K13*1.04 -> 3749.5467 | P13: ='Program Budget'!Q268 -> 12 | Q13: ='Program Budget'!P268 -> 1 | R13: =O13*P13*Q13 -> 44994.56 | S13: =O13*1.04 -> 3899.5285 | T13: ='Program Budget'!T268 -> 9 | U13: ='Program Budget'!S268 -> 1 | V13: =S13*T13*U13 -> 35095.757 | W13: =F13+J13+N13+R13+V13 -> 179954.32 | AE13: 180 | AF13: 50-01-2-020 | AG13: DIR-USN (Expat) Labor
A14: ='Program Budget'!D269 -> Specialist Component 2 | B14: ='Program Budget'!F269 -> Month | C14: ='Program Budget'!H269 -> 1666.6667 | D14: ='Program Budget'!G269 -> 6 | E14: ='Program Budget'!E269 -> 0 | F14: =C14*D14*E14 -> 0 | G14: =C14*1.04 -> 1733.3333 | H14: ='Program Budget'!K269 -> 12 | I14: ='Program Budget'!J269 -> 0 | J14: =G14*H14*I14 -> 0 | K14: =G14*1.04 -> 1802.6667 | L14: ='Program Budget'!N269 -> 12 | M14: ='Program Budget'!M269 -> 0 | N14: =K14*L14*M14 -> 0 | O14: =K14*1.04 -> 1874.7733 | P14: ='Program Budget'!Q269 -> 12 | Q14: ='Program Budget'!P269 -> 0 | R14: =O14*P14*Q14 -> 0 | S14: =O14*1.04 -> 1949.7643 | T14: ='Program Budget'!T269 -> 6 | U14: ='Program Budget'!S269 -> 0 | V14: =S14*T14*U14 -> 0 | W14: =F14+J14+N14+R14+V14 -> 0
A15: ='Program Budget'!D270 -> Specialist Component 3 | B15: ='Program Budget'!F270 -> Month | C15: ='Program Budget'!H270 -> 1666.6667 | D15: ='Program Budget'!G270 -> 6 | E15: ='Program Budget'!E270 -> 0.8 | F15: =C15*D15*E15 -> 8000 | G15: =C15*1.04 -> 1733.3333 | H15: ='Program Budget'!K270 -> 12 | I15: ='Program Budget'!J270 -> 1 | J15: =G15*H15*I15 -> 20800 | K15: =G15*1.04 -> 1802.6667 | L15: ='Program Budget'!N270 -> 12 | M15: ='Program Budget'!M270 -> 1 | N15: =K15*L15*M15 -> 21632 | O15: =K15*1.04 -> 1874.7733 | P15: ='Program Budget'!Q270 -> 12 | Q15: ='Program Budget'!P270 -> 1 | R15: =O15*P15*Q15 -> 22497.28 | S15: =O15*1.04 -> 1949.7643 | T15: ='Program Budget'!T270 -> 6 | U15: ='Program Budget'!S270 -> 1 | V15: =S15*T15*U15 -> 11698.586 | W15: =F15+J15+N15+R15+V15 -> 84627.866
A16: ='Program Budget'!D271 -> Specialist Component 4 | B16: ='Program Budget'!F271 -> Month | C16: ='Program Budget'!H271 -> 1666.6667 | D16: ='Program Budget'!G271 -> 6 | E16: ='Program Budget'!E271 -> 0 | F16: =C16*D16*E16 -> 0 | G16: =C16*1.04 -> 1733.3333 | H16: ='Program Budget'!K271 -> 12 | I16: ='Program Budget'!J271 -> 0 | J16: =G16*H16*I16 -> 0 | K16: =G16*1.04 -> 1802.6667 | L16: ='Program Budget'!N271 -> 12 | M16: ='Program Budget'!M271 -> 0 | N16: =K16*L16*M16 -> 0 | O16: =K16*1.04 -> 1874.7733 | P16: ='Program Budget'!Q271 -> 12 | Q16: ='Program Budget'!P271 -> 0 | R16: =O16*P16*Q16 -> 0 | S16: =O16*1.04 -> 1949.7643 | T16: ='Program Budget'!T271 -> 6 | U16: ='Program Budget'!S271 -> 0 | V16: =S16*T16*U16 -> 0 | W16: =F16+J16+N16+R16+V16 -> 0
A17: ='Program Budget'!D272 -> Extension Agents (20 Individuals) | B17: ='Program Budget'!F272 -> Month | C17: ='Program Budget'!H272 -> 23333.333 | D17: ='Program Budget'!G272 -> 3 | E17: ='Program Budget'!E272 -> 0.2 | F17: =C17*D17*E17 -> 14000 | G17: =C17*1.04 -> 24266.667 | H17: ='Program Budget'!K272 -> 12 | I17: ='Program Budget'!J272 -> 0.2 | J17: =G17*H17*I17 -> 58240 | K17: =G17*1.04 -> 25237.333 | L17: ='Program Budget'!N272 -> 6 | M17: ='Program Budget'!M272 -> 0.2 | N17: =K17*L17*M17 -> 30284.8 | O17: =K17*1.04 -> 26246.827 | P17: ='Program Budget'!Q272 -> 0 | Q17: ='Program Budget'!P272 -> 0 | R17: =O17*P17*Q17 -> 0 | S17: =O17*1.04 -> 27296.7 | T17: ='Program Budget'!T272 -> 0 | U17: ='Program Budget'!S272 -> 0 | V17: =S17*T17*U17 -> 0 | W17: =F17+J17+N17+R17+V17 -> 102524.8 | AE17: 180 | AF17: 50-01-2-020 | AG17: DIR-USN (Expat) Labor
A18: ='Program Budget'!D273 -> M&E Director | B18: ='Program Budget'!F273 -> Month | C18: ='Program Budget'!H273 -> 3750 | D18: ='Program Budget'!G273 -> 9 | E18: ='Program Budget'!E273 -> 0.2 | F18: =C18*D18*E18 -> 6750 | G18: =C18*1.04 -> 3900 | H18: ='Program Budget'!K273 -> 12 | I18: ='Program Budget'!J273 -> 0.25 | J18: =G18*H18*I18 -> 11700 | K18: =G18*1.04 -> 4056 | L18: ='Program Budget'!N273 -> 12 | M18: ='Program Budget'!M273 -> 0.25 | N18: =K18*L18*M18 -> 12168 | O18: =K18*1.04 -> 4218.24 | P18: ='Program Budget'!Q273 -> 12 | Q18: ='Program Budget'!P273 -> 0.25 | R18: =O18*P18*Q18 -> 12654.72 | S18: =O18*1.04 -> 4386.9696 | T18: ='Program Budget'!T273 -> 12 | U18: ='Program Budget'!S273 -> 0.25 | V18: =S18*T18*U18 -> 13160.909 | W18: =F18+J18+N18+R18+V18 -> 56433.629 | AE18: 180 | AF18: 50-01-2-020 | AG18: DIR-USN (Expat) Labor
A19: ='Program Budget'!D274 -> M&E Specialist | B19: ='Program Budget'!F274 -> Month | C19: ='Program Budget'!H274 -> 2083.3333 | D19: ='Program Budget'!G274 -> 6 | E19: ='Program Budget'!E274 -> 0.2 | F19: =C19*D19*E19 -> 2500 | G19: =C19*1.04 -> 2166.6667 | H19: ='Program Budget'!K274 -> 12 | I19: ='Program Budget'!J274 -> 0.25 | J19: =G19*H19*I19 -> 6500 | K19: =G19*1.04 -> 2253.3333 | L19: ='Program Budget'!N274 -> 12 | M19: ='Program Budget'!M274 -> 0.25 | N19: =K19*L19*M19 -> 6760 | O19: =K19*1.04 -> 2343.4667 | P19: ='Program Budget'!Q274 -> 12 | Q19: ='Program Budget'!P274 -> 0.25 | R19: =O19*P19*Q19 -> 7030.4 | S19: =O19*1.04 -> 2437.2053 | T19: ='Program Budget'!T274 -> 10 | U19: ='Program Budget'!S274 -> 0.25 | V19: =S19*T19*U19 -> 6093.0133 | W19: =F19+J19+N19+R19+V19 -> 28883.413 | AE19: 180 | AF19: 50-01-2-020 | AG19: DIR-USN (Expat) Labor
A20: ='Program Budget'!D275 -> F&A Director | B20: ='Program Budget'!F275 -> Month | C20: ='Program Budget'!H275 -> 6666.6667 | D20: ='Program Budget'!G275 -> 9 | E20: ='Program Budget'!E275 -> 0.2 | F20: =C20*D20*E20 -> 12000 | G20: =C20*1.04 -> 6933.3333 | H20: ='Program Budget'!K275 -> 12 | I20: ='Program Budget'!J275 -> 0.2 | J20: =G20*H20*I20 -> 16640 | K20: =G20*1.04 -> 7210.6667 | L20: ='Program Budget'!N275 -> 12 | M20: ='Program Budget'!M275 -> 0.2 | N20: =K20*L20*M20 -> 17305.6 | O20: =K20*1.04 -> 7499.0933 | P20: ='Program Budget'!Q275 -> 12 | Q20: ='Program Budget'!P275 -> 0.2 | R20: =O20*P20*Q20 -> 17997.824 | S20: =O20*1.04 -> 7799.0571 | T20: ='Program Budget'!T275 -> 12 | U20: ='Program Budget'!S275 -> 0.2 | V20: =S20*T20*U20 -> 18717.737 | W20: =F20+J20+N20+R20+V20 -> 82661.161 | AE20: 180 | AF20: 50-01-2-020 | AG20: DIR-USN (Expat) Labor
A21: ='Program Budget'!D276 -> Human Resource Manager | B21: ='Program Budget'!F276 -> Month | C21: ='Program Budget'!H276 -> 2916.6667 | D21: ='Program Budget'!G276 -> 9 | E21: ='Program Budget'!E276 -> 0.2 | F21: =C21*D21*E21 -> 5250 | G21: =C21*1.04 -> 3033.3333 | H21: ='Program Budget'!K276 -> 12 | I21: ='Program Budget'!J276 -> 0.2 | J21: =G21*H21*I21 -> 7280 | K21: =G21*1.04 -> 3154.6667 | L21: ='Program Budget'!N276 -> 12 | M21: ='Program Budget'!M276 -> 0.25 | N21: =K21*L21*M21 -> 9464 | O21: =K21*1.04 -> 3280.8533 | P21: ='Program Budget'!Q276 -> 12 | Q21: ='Program Budget'!P276 -> 0.25 | R21: =O21*P21*Q21 -> 9842.56 | S21: =O21*1.04 -> 3412.0875 | T21: ='Program Budget'!T276 -> 10 | U21: ='Program Budget'!S276 -> 0.25 | V21: =S21*T21*U21 -> 8530.2187 | W21: =F21+J21+N21+R21+V21 -> 40366.779
A22: ='Program Budget'!D277 -> Contracts & Compliance Specialist | B22: ='Program Budget'!F277 -> Month | C22: ='Program Budget'!H277 -> 2916.6667 | D22: ='Program Budget'!G277 -> 6 | E22: ='Program Budget'!E277 -> 0.2 | F22: =C22*D22*E22 -> 3500 | G22: =C22*1.04 -> 3033.3333 | H22: ='Program Budget'!K277 -> 12 | I22: ='Program Budget'!J277 -> 0.2 | J22: =G22*H22*I22 -> 7280 | K22: =G22*1.04 -> 3154.6667 | L22: ='Program Budget'!N277 -> 12 | M22: ='Program Budget'!M277 -> 0.2 | N22: =K22*L22*M22 -> 7571.2 | O22: =K22*1.04 -> 3280.8533 | P22: ='Program Budget'!Q277 -> 12 | Q22: ='Program Budget'!P277 -> 0.2 | R22: =O22*P22*Q22 -> 7874.048 | S22: =O22*1.04 -> 3412.0875 | T22: ='Program Budget'!T277 -> 9 | U22: ='Program Budget'!S277 -> 0.2 | V22: =S22*T22*U22 -> 6141.7574 | W22: =F22+J22+N22+R22+V22 -> 32367.005 | AE22: 180 | AF22: 50-01-2-020 | AG22: DIR-USN (Expat) Labor
A23: ='Program Budget'!D278 -> Accountant | B23: ='Program Budget'!F278 -> Month | C23: ='Program Budget'!H278 -> 1666.6667 | D23: ='Program Budget'!G278 -> 7 | E23: ='Program Budget'!E278 -> 0.2 | F23: =C23*D23*E23 -> 2333.3333 | G23: =C23*1.04 -> 1733.3333 | H23: ='Program Budget'!K278 -> 12 | I23: ='Program Budget'!J278 -> 0.2 | J23: =G23*H23*I23 -> 4160 | K23: =G23*1.04 -> 1802.6667 | L23: ='Program Budget'!N278 -> 12 | M23: ='Program Budget'!M278 -> 0.2 | N23: =K23*L23*M23 -> 4326.4 | O23: =K23*1.04 -> 1874.7733 | P23: ='Program Budget'!Q278 -> 12 | Q23: ='Program Budget'!P278 -> 0.2 | R23: =O23*P23*Q23 -> 4499.456 | S23: =O23*1.04 -> 1949.7643 | T23: ='Program Budget'!T278 -> 10 | U23: ='Program Budget'!S278 -> 0.2 | V23: =S23*T23*U23 -> 3899.5285 | W23: =F23+J23+N23+R23+V23 -> 19218.718 | AE23: 180 | AF23: 50-01-2-020 | AG23: DIR-USN (Expat) Labor
A24: ='Program Budget'!D279 -> Administrative Assistant | B24: ='Program Budget'!F279 -> Month | C24: ='Program Budget'!H279 -> 833.33333 | D24: ='Program Budget'!G279 -> 7 | E24: ='Program Budget'!E279 -> 0.2 | F24: =C24*D24*E24 -> 1166.6667 | G24: =C24*1.04 -> 866.66667 | H24: ='Program Budget'!K279 -> 12 | I24: ='Program Budget'!J279 -> 0.2 | J24: =G24*H24*I24 -> 2080 | K24: =G24*1.04 -> 901.33333 | L24: ='Program Budget'!N279 -> 12 | M24: ='Program Budget'!M279 -> 0.2 | N24: =K24*L24*M24 -> 2163.2 | O24: =K24*1.04 -> 937.38667 | P24: ='Program Budget'!Q279 -> 12 | Q24: ='Program Budget'!P279 -> 0.2 | R24: =O24*P24*Q24 -> 2249.728 | S24: =O24*1.04 -> 974.88213 | T24: ='Program Budget'!T279 -> 10 | U24: ='Program Budget'!S279 -> 0.2 | V24: =S24*T24*U24 -> 1949.7643 | W24: =F24+J24+N24+R24+V24 -> 9609.3589 | AE24: 180 | AF24: 50-01-2-020 | AG24: DIR-USN (Expat) Labor
