Workbook
Name agentfee: #REF!
Name avrent: #REF!
Name Category: #REF!
Name coffee: #REF!
Name consairfare: #REF!
Name consground: #REF!
Name conslodg: #REF!
Name consmeals: #REF!
Name consmisc: #REF!
Name DL_Country: #REF!
Name DL_TotalDOL: #REF!
Name EQ_Country: #REF!
Name EQ_TotalDOL: #REF!
Name er: #REF!
Name ground: #REF!
Name guideprint: #REF!
Name inmuniz: #REF!
Name intairfare: #REF!
Name intcalls: #REF!
Name intcons: #REF!
Name intmisc: #REF!
Name livingq: #REF!
Name Local_transport_part: #REF!
Name localairfare: #REF!
Name localcons: #REF!
Name locallodg: #REF!
Name localmeals: #REF!
Name localmisc: #REF!
Name lunch: #REF!
Name mats: #REF!
Name ME_TotalDOL: #REF!
Name medex: #REF!
Name meetcost: #REF!+#REF!
Name mileage: #REF!
Name natcalls: #REF!
Name O1_Country: #REF!
Name O1_TotalDOL: #REF!
Name O2_Country: #REF!
Name O2_TotalDOL: #REF!
Name partairfare: #REF!
Name partground: #REF!
Name partlodg: #REF!
Name partmats: #REF!
Name partmeals: #REF!
Name partmisc: #REF!
Name partprint: #REF!
Name parttransp: #REF!
Name print: #REF!
Name regcons: #REF!
Name roomrent: #REF!
Name SU_Country: #REF!
Name SU_TotalDOL: #REF!
Name surveyor: #REF!
Name tdlunch: #REF!
Name TotalDOL: #REF!
Name TR_Country: #REF!
Name TR_TotalDOL: #REF!
Name travmisc: #REF!+#REF!+#REF!
Name usaidlodg: #REF!
Name usaidmeal: #REF!

Sheet Budget Summary
A3: Project Budget Summary
A4: Partners of the Americas
A5: ='POA General Budget'!D3 -> Leveling the Field for American Workers in U.S.-Mexico Trade
A6: 54 Months
A8: BUDGET SUMMARY CATEGORIES | B8: YEAR 1 | C8: YEAR 2 | D8: YEAR 3 | E8: YEAR 4 | F8: YEAR 5 | G8: TOTAL FEDERAL FUNDS REQUESTED
A10: 1. PERSONNEL | B10: =+'POA General Budget'!J24 -> 475499.97 | C10: =+'POA General Budget'!L24 -> 580649.97 | D10: =+'POA General Budget'!N24 -> 609682.47 | E10: =+'POA General Budget'!P24 -> 640166.59 | F10: =+'POA General Budget'!R24 -> 263157.09 | G10: =SUM(B10:F10) -> 2569156.1
A11: 2. FRINGE BENEFITS | B11: =+'POA General Budget'!J28 -> 172270.79 | C11: =+'POA General Budget'!L28 -> 214654.96 | D11: =+'POA General Budget'!N28 -> 225387.71 | E11: =+'POA General Budget'!P28 -> 236657.09 | F11: =+'POA General Budget'!R28 -> 93978.867 | G11: =SUM(B11:F11) -> 942949.42
A12: 3. TRAVEL | B12: =+'POA General Budget'!J77 -> 62289.573 | C12: =+'POA General Budget'!L77 -> 71787.781 | D12: =+'POA General Budget'!N77 -> 64240.73 | E12: =+'POA General Budget'!P77 -> 63348.573 | F12: =+'POA General Budget'!R77 -> 10261.051 | G12: =SUM(B12:F12) -> 271927.71
A13: 4. EQUIPMENT | B13: =+'POA General Budget'!J80 -> 0 | C13: =+'POA General Budget'!L80 -> 0 | D13: =+'POA General Budget'!N80 -> 0 | E13: =+'POA General Budget'!P80 -> 0 | F13: =+'POA General Budget'!R80 -> 0 | G13: =SUM(B13:F13) -> 0
A14: 5. SUPPLIES | B14: =+'POA General Budget'!J85 -> 10202 | C14: =+'POA General Budget'!L85 -> 1872 | D14: =+'POA General Budget'!N85 -> 1946.88 | E14: =+'POA General Budget'!P85 -> 2024.7552 | F14: =+'POA General Budget'!R85 -> 1052.8727 | G14: =SUM(B14:F14) -> 17098.508
A15: 6. CONTRACTUAL | B15: =+'POA General Budget'!J96 -> 415327.56 | C15: =+'POA General Budget'!L96 -> 1345025.8 | D15: =+'POA General Budget'!N96 -> 1211382.7 | E15: =+'POA General Budget'!P96 -> 856735.7 | F15: =+'POA General Budget'!R96 -> 45528.727 | G15: =SUM(B15:F15) -> 3874000.5
A16: 7. CONSTRUCTION | B16: =+'POA General Budget'!J99 -> 0 | C16: =+'POA General Budget'!L99 -> 0 | D16: =+'POA General Budget'!N99 -> 0 | E16: =+'POA General Budget'!P99 -> 0 | F16: =+'POA General Budget'!R99 -> 0 | G16: =SUM(B16:F16) -> 0
A17: 8. OTHER DIRECT COSTS | B17: =+'POA General Budget'!J158 -> 152676 | C17: =+'POA General Budget'!L158 -> 364098.64 | D17: =+'POA General Budget'!N158 -> 347427.13 | E17: =+'POA General Budget'!P158 -> 352225.46 | F17: =+'POA General Budget'!R158 -> 42603.909 | G17: =SUM(B17:F17) -> 1259031.1
A19: 9. TOTAL DIRECT COSTS (Lines 1-8) | B19: =SUM(B10:B17) -> 1288265.9 | C19: =SUM(C10:C17) -> 2578089.2 | D19: =SUM(D10:D17) -> 2460067.6 | E19: =SUM(E10:E17) -> 2151158.2 | F19: =SUM(F10:F17) -> 456582.51 | G19: =SUM(G10:G17) -> 8934163.4
A20: 10. INDIRECT COSTS | B20: =+'POA General Budget'!J165 -> 169933.68 | C20: =+'POA General Budget'!L165 -> 292026.51 | D20: =+'POA General Budget'!N165 -> 278014.54 | E20: =+'POA General Budget'!P165 -> 257374.48 | F20: =+'POA General Budget'!R165 -> 68487.377 | G20: =SUM(B20:F20) -> 1065836.6
A21: 11. TOTAL COSTS (Lines 9-10) | B21: =SUM(B19:B20) -> 1458199.6 | C21: =SUM(C19:C20) -> 2870115.7 | D21: =SUM(D19:D20) -> 2738082.2 | E21: =SUM(E19:E20) -> 2408532.7 | F21: =SUM(F19:F20) -> 525069.89 | G21: =SUM(G19:G20) -> 10000000

Sheet POA General Budget
D1: Project Line-Item Budget
D2: Partners of the Americas
D3: Leveling the Field for American Workers in U.S.-Mexico Trade
A4: Entity: | B4: P | D4: 54 Months
A5: Program-Dept.: | B5: 20200 | D5: Cost Assumptions
A6: Funder-Grant: | B6: DOL427 | D6: Inflation - Goods/Services | E6: 1.04
D7: Merit Based Increases for HO & Field Staff | E7: 1.05
A9: Activity Code | B9: Account Code | C9: Country Code | D9: BUDGET ITEM | E9: CATEGORY | F9: LOE | G9: UNIT | H9: # of Units | I9: RATE / UNIT | J9: Year 1 | K9: # of Units | L9: Year 2 | M9: # of Units | N9: Year 3 | O9: # of Units | P9: Year 4 | Q9: # of Units | R9: Year 5 | S9: TOTAL DOL | T9: TOTAL COST SHARING | U9: PROJECT GRAND TOTAL
D10: Personnel
D11: Key Personnel
A12: PERSNL-PD | B12: 70000 | C12: MEX | D12: Project Director: Ingrid Ceballos | E12: Salaries | F12: 1 | G12: Month | H12: 12 | I12: 10000 | J12: =H12*I12*F12 -> 120000 | K12: 12 | L12: =K12*$I12*$E$7*$F12 -> 126000 | M12: 12 | N12: =M12*$I12*$E$7*$F12*$E$7 -> 132300 | O12: 12 | P12: =O12*$I12*$E$7*$F12*$E$7*$E$7 -> 138915 | Q12: 6 | R12: =Q12*$I12*$E$7*$F12*$E$7*$E$7*$E$7 -> 72930.375 | S12: =SUM(J12+L12+N12+P12+R12) -> 590145.38 | T12: 0 | U12: =SUM(S12:T12) -> 590145.38
A13: PERSNL-M&E | B13: 70000 | C13: MEX | D13: M&E Officer: Luis Madrid | E13: Salaries | F13: 1 | G13: Month | H13: 11 | I13: =4500 -> 4500 | J13: =H13*I13*F13 -> 49500 | K13: 12 | L13: =K13*$I13*$E$7*$F13 -> 56700 | M13: 12 | N13: =M13*$I13*$E$7*$F13*$E$7 -> 59535 | O13: 12 | P13: =O13*$I13*$E$7*$F13*$E$7*$E$7 -> 62511.75 | Q13: 6 | R13: =Q13*$I13*$E$7*$F13*$E$7*$E$7*$E$7 -> 32818.669 | S13: =SUM(J13+L13+N13+P13+R13) -> 261065.42 | T13: 0 | U13: =SUM(S13:T13) -> 261065.42
A14: PERSNL-IRS | B14: 70000 | C14: MEX | D14: Industrial Relations Specialist: Darlene Rojas | E14: Salaries | F14: 1 | G14: Month | H14: 11 | I14: 7000 | J14: =H14*I14*F14 -> 77000 | K14: 12 | L14: =K14*$I14*$E$7*$F14 -> 88200 | M14: 12 | N14: =M14*$I14*$E$7*$F14*$E$7 -> 92610 | O14: 12 | P14: =O14*$I14*$E$7*$F14*$E$7*$E$7 -> 97240.5 | Q14: 2 | R14: =Q14*$I14*$E$7*$F14*$E$7*$E$7*$E$7 -> 17017.088 | S14: =SUM(J14+L14+N14+P14+R14) -> 372067.59 | T14: 0 | U14: =SUM(S14:T14) -> 372067.59
D15: Other Professional Personnel
A16: PERSNL-F&A | B16: 70000 | C16: MEX | D16: F&A Manager | E16: Salaries | F16: 1 | G16: Month | H16: 10 | I16: =5000 -> 5000 | J16: =H16*I16*F16 -> 50000 | K16: 12 | L16: =K16*$I16*$E$7*$F16 -> 63000 | M16: 12 | N16: =M16*$I16*$E$7*$F16*$E$7 -> 66150 | O16: 12 | P16: =O16*$I16*$E$7*$F16*$E$7*$E$7 -> 69457.5 | Q16: 6 | R16: =Q16*$I16*$E$7*$F16*$E$7*$E$7*$E$7 -> 36465.188 | S16: =SUM(J16+L16+N16+P16+R16) -> 285072.69 | T16: 0 | U16: =SUM(S16:T16) -> 285072.69
A17: PERSNL-OPS | B17: 70000 | C17: MEX | D17: Administration & Operations Specialist | E17: Salaries | F17: 1 | G17: Month | H17: 8 | I17: =4000 -> 4000 | J17: =H17*I17*F17 -> 32000 | K17: 12 | L17: =K17*$I17*$E$7*$F17 -> 50400 | M17: 12 | N17: =M17*$I17*$E$7*$F17*$E$7 -> 52920 | O17: 12 | P17: =O17*$I17*$E$7*$F17*$E$7*$E$7 -> 55566 | Q17: 2 | R17: =Q17*$I17*$E$7*$F17*$E$7*$E$7*$E$7 -> 9724.05 | S17: =SUM(J17+L17+N17+P17+R17) -> 200610.05 | T17: 0 | U17: =SUM(S17:T17) -> 200610.05
A18: PERSNL-TPS | B18: 70000 | C18: MEX | D18: Technology Project Specialist | E18: Salaries | F18: 1 | G18: Month | H18: 2 | I18: =4000 -> 4000 | J18: =H18*I18*F18 -> 8000 | K18: 12 | L18: =K18*$I18*$E$7*$F18 -> 50400 | M18: 12 | N18: =M18*$I18*$E$7*$F18*$E$7 -> 52920 | O18: 12 | P18: =O18*$I18*$E$7*$F18*$E$7*$E$7 -> 55566 | Q18: 2 | R18: =Q18*$I18*$E$7*$F18*$E$7*$E$7*$E$7 -> 9724.05 | S18: =SUM(J18+L18+N18+P18+R18) -> 176610.05 | T18: 0 | U18: =SUM(S18:T18) -> 176610.05
D19: Home Office Support
A20: PERSNL-PM | B20: 50000 | C20: USA | D20: Project Manager | E20: Salaries | F20: 0.3 | G20: Month | H20: 12 | I20: 12500 | J20: =H20*I20*F20 -> 45000 | K20: 12 | L20: =K20*$I20*$E$7*$F20 -> 47250 | M20: 12 | N20: =M20*$I20*$E$7*$F20*$E$7 -> 49612.5 | O20: 12 | P20: =(O20*I20*$E$7*$E$7*$E$7)*F20 -> 52093.125 | Q20: 6 | R20: =Q20*$I20*$E$7*$F20*$E$7*$E$7*$E$7 -> 27348.891 | S20: =SUM(J20+L20+N20+P20+R20) -> 221304.52 | T20: 0 | U20: =SUM(S20:T20) -> 221304.52
A21: PERSNL-PO | B21: 50000 | C21: USA | D21: Senior Program Officer | E21: Salaries | F21: 0.8 | G21: Month | H21: 12 | I21: 5833.33 | J21: =H21*I21*F21 -> 55999.968 | K21: 12 | L21: =K21*$I21*$E$7*$F21 -> 58799.966 | M21: 12 | N21: =M21*$I21*$E$7*$F21*$E$7 -> 61739.965 | O21: 12 | P21: =(O21*I21*$E$7*$E$7*$E$7)*F21 -> 64826.963 | Q21: 6 | R21: =Q21*$I21*$E$7*$F21*$E$7*$E$7*$E$7 -> 34034.156 | S21: =SUM(J21+L21+N21+P21+R21) -> 275401.02 | T21: 0 | U21: =SUM(S21:T21) -> 275401.02
A22: PERSNL | B22: 50000 | C22: USA | D22: Compliance & Contracts Director | E22: Salaries | F22: 0.1 | G22: Month | H22: 12 | I22: 9166.67 | J22: =H22*I22*F22 -> 11000.004 | K22: 12 | L22: =K22*$I22*$E$7*$F22 -> 11550.004 | M22: 12 | N22: =M22*$I22*$E$7*$F22*$E$7 -> 12127.504 | O22: 12 | P22: =(O22*I22*$E$7*$E$7*$E$7)*F22 -> 12733.88 | Q22: 6 | R22: =Q22*$I22*$E$7*$F22*$E$7*$E$7*$E$7 -> 6685.2868 | S22: =SUM(J22+L22+N22+P22+R22) -> 54096.679 | T22: 0 | U22: =SUM(S22:T22) -> 54096.679
A23: PERSNL | B23: 50000 | C23: USA | D23: Finance, HR, & Administration Support | E23: Salaries | F23: 0.3 | G23: Month | H23: 12 | I23: 7500 | J23: =H23*I23*F23 -> 27000 | K23: 12 | L23: =K23*$I23*$E$7*$F23 -> 28350 | M23: 12 | N23: =M23*$I23*$E$7*$F23*$E$7 -> 29767.5 | O23: 12 | P23: =(O23*I23*$E$7*$E$7*$E$7)*F23 -> 31255.875 | Q23: 6 | R23: =Q23*$I23*$E$7*$F23*$E$7*$E$7*$E$7 -> 16409.334 | S23: =SUM(J23+L23+N23+P23+R23) -> 132782.71 | T23: 0 | U23: =SUM(S23:T23) -> 132782.71
D24: Total Personnel | J24: =SUM(J12:J23) -> 475499.97 | L24: =SUM(L12:L23) -> 580649.97 | N24: =SUM(N12:N23) -> 609682.47 | P24: =SUM(P12:P23) -> 640166.59 | R24: =SUM(R12:R23) -> 263157.09 | S24: =SUM(S12:S23) -> 2569156.1 | T24: =SUM(T12:T23) -> 0 | U24: =SUM(S24:T24) -> 2569156.1
D25: Fringe Benefits
A26: FRINGE-MX | B26: 70015 | C26: MEX | D26: Fringe Benefits - MX | E26: Fringe Benefits | G26: Month | I26: 0.415 | J26: =SUM(J12:J18)*$I26 -> 139647.5 | L26: =SUM(L12:L18)*$I26 -> 180400.5 | N26: =SUM(N12:N18)*$I26 -> 189420.52 | P26: =SUM(P12:P18)*$I26 -> 198891.55 | R26: =SUM(R12:R18)*$I26 -> 74151.959 | S26: =SUM(J26+L26+N26+P26+R26) -> 782512.04 | T26: 0 | U26: =SUM(S26:T26) -> 782512.04
A27: FRINGE | B27: 50900 | C27: USA | D27: Fringe Benefits - HO | E27: Fringe Benefits | G27: Month | I27: 0.2347 | J27: =SUM(J20:J23)*$I$27 -> 32623.293 | L27: =SUM(L20:L23)*$I$27 -> 34254.458 | N27: =SUM(N20:N23)*$I$27 -> 35967.181 | P27: =SUM(P20:P23)*$I$27 -> 37765.54 | R27: =SUM(R20:R23)*$I$27 -> 19826.909 | S27: =SUM(J27+L27+N27+P27+R27) -> 160437.38 | T27: 0 | U27: =SUM(S27:T27) -> 160437.38
D28: Total Fringe Benefits | J28: =SUM(J26:J27) -> 172270.79 | L28: =SUM(L26:L27) -> 214654.96 | N28: =SUM(N26:N27) -> 225387.71 | P28: =SUM(P26:P27) -> 236657.09 | R28: =SUM(R26:R27) -> 93978.867 | S28: =SUM(S26:S27) -> 942949.42 | T28: =SUM(T26:T27) -> 0 | U28: =SUM(U26:U27) -> 942949.42
D29: Travel
D30: T1: Post-award Meeting with ILAB
A31: MX.T1.A | B31: 86040 | C31: USA | D31: Airfare - Mexico City-DC | E31: Travel | F31: 1 | G31: Trip | H31: 2 | I31: 700 | J31: =H31*$I31*$F31 -> 1400 | K31: 0 | L31: =+K31*$I31*$F31*$E$6 -> 0 | M31: 0 | N31: =+M31*$I31*$F31*$E$6*$E$6 -> 0 | O31: 0 | P31: =+O31*$I31*$F31*$E$6*$E$6*$E$6 -> 0 | Q31: 0 | R31: =+Q31*$I31*$F31*$E$6*$E$6*$E$6*$E$6 -> 0 | S31: =SUM(J31+L31+N31+P31+R31) -> 1400 | T31: 0 | U31: =SUM(S31:T31) -> 1400
A32: MX.T1.B | B32: 86030 (Lodging)/ 86050 (M&IE) | C32: USA | D32: Lodging and M&IE in DC | E32: Travel | F32: 1 | G32: Day | H32: =5*2 -> 10 | I32: =(92*0.9)+183 -> 265.8 | J32: =H32*$I32*$F32 -> 2658 | K32: 0 | L32: =+K32*$I32*$F32*$E$6 -> 0 | M32: 0 | N32: =+M32*$I32*$F32*$E$6*$E$6 -> 0 | O32: 0 | P32: =+O32*$I32*$F32*$E$6*$E$6*$E$6 -> 0 | Q32: 0 | R32: =+Q32*$I32*$F32*$E$6*$E$6*$E$6*$E$6 -> 0 | S32: =SUM(J32+L32+N32+P32+R32) -> 2658 | T32: 0 | U32: =SUM(S32:T32) -> 2658
A33: MX.T1.C | B33: 86000 | C33: USA | D33: Local transportation in DC | E33: Travel | F33: 1 | G33: Day | H33: =5*2 -> 10 | I33: 50 | J33: =H33*$I33*$F33 -> 500 | K33: 0 | L33: =+K33*$I33*$F33*$E$6 -> 0 | M33: 0 | N33: =+M33*$I33*$F33*$E$6*$E$6 -> 0 | O33: 0 | P33: =+O33*$I33*$F33*$E$6*$E$6*$E$6 -> 0 | Q33: 0 | R33: =+Q33*$I33*$F33*$E$6*$E$6*$E$6*$E$6 -> 0 | S33: =SUM(J33+L33+N33+P33+R33) -> 500 | T33: 0 | U33: =SUM(S33:T33) -> 500
A34: MX.T1.D | B34: 86050 | C34: USA | D34: U.S. Visa Fees | E34: Travel | F34: 1 | G34: Person | H34: 2 | I34: 185 | J34: =H34*$I34*$F34 -> 370 | K34: 0 | L34: =+K34*$I34*$F34*$E$6 -> 0 | M34: 0 | N34: =+M34*$I34*$F34*$E$6*$E$6 -> 0 | O34: 0 | P34: =+O34*$I34*$F34*$E$6*$E$6*$E$6 -> 0 | Q34: 0 | R34: =+Q34*$I34*$F34*$E$6*$E$6*$E$6*$E$6 -> 0 | S34: =SUM(J34+L34+N34+P34+R34) -> 370 | T34: 0 | U34: =SUM(S34:T34) -> 370
D35: T2: Field Personnel Annual Visits with ILAB
A36: MX.T2.A | B36: 86040 | C36: MEX | D36: Airfare - Mexico City-DC | E36: Travel | F36: 1 | G36: Trip | H36: 0 | I36: 700 | J36: =H36*$I36*$F36 -> 0 | K36: 2 | L36: =+K36*$I36*$F36*$E$6 -> 1456 | M36: 2 | N36: =+M36*$I36*$F36*$E$6*$E$6 -> 1514.24 | O36: 2 | P36: =+O36*$I36*$F36*$E$6*$E$6*$E$6 -> 1574.8096 | Q36: 2 | R36: =+Q36*$I36*$F36*$E$6*$E$6*$E$6*$E$6 -> 1637.802 | S36: =SUM(J36+L36+N36+P36+R36) -> 6182.8516 | T36: 0 | U36: =SUM(S36:T36) -> 6182.8516
A37: MX.T2.B | B37: 86030 (Lodging)/ 86050 (M&IE) | C37: MEX | D37: Lodging and M&IE in DC | E37: Travel | F37: 1 | G37: Day | H37: 0 | I37: =(92*0.9)+183 -> 265.8 | J37: =H37*$I37*$F37 -> 0 | K37: =5*2 -> 10 | L37: =+K37*$I37*$F37*$E$6 -> 2764.32 | M37: =5*2 -> 10 | N37: =+M37*$I37*$F37*$E$6*$E$6 -> 2874.8928 | O37: =5*2 -> 10 | P37: =+O37*$I37*$F37*$E$6*$E$6*$E$6 -> 2989.8885 | Q37: =5*2 -> 10 | R37: =+Q37*$I37*$F37*$E$6*$E$6*$E$6*$E$6 -> 3109.4841 | S37: =SUM(J37+L37+N37+P37+R37) -> 11738.585 | T37: 0 | U37: =SUM(S37:T37) -> 11738.585
A38: MX.T2.C | B38: 86000 | C38: MEX | D38: Local transportation in DC | E38: Travel | F38: 1 | G38: Day | H38: 0 | I38: 50 | J38: =H38*$I38*$F38 -> 0 | K38: =5*2 -> 10 | L38: =+K38*$I38*$F38*$E$6 -> 520 | M38: =5*2 -> 10 | N38: =+M38*$I38*$F38*$E$6*$E$6 -> 540.8 | O38: =5*2 -> 10 | P38: =+O38*$I38*$F38*$E$6*$E$6*$E$6 -> 562.432 | Q38: =5*2 -> 10 | R38: =+Q38*$I38*$F38*$E$6*$E$6*$E$6*$E$6 -> 584.92928 | S38: =SUM(J38+L38+N38+P38+R38) -> 2208.1613 | T38: 0 | U38: =SUM(S38:T38) -> 2208.1613
D39: T3: Program Management Visits to Field
A40: MX.T3.A | B40: 86040 | C40: MEX | D40: Airfare - DC - Mexico City | E40: Travel | F40: 1 | G40: Trip | H40: 2 | I40: 700 | J40: =H40*$I40*$F40 -> 1400 | K40: 2 | L40: =+K40*$I40*$F40*$E$6 -> 1456 | M40: 2 | N40: =+M40*$I40*$F40*$E$6*$E$6 -> 1514.24 | O40: 2 | P40: =+O40*$I40*$F40*$E$6*$E$6*$E$6 -> 1574.8096 | Q40: 2 | R40: =+Q40*$I40*$F40*$E$6*$E$6*$E$6*$E$6 -> 1637.802 | S40: =SUM(J40+L40+N40+P40+R40) -> 7582.8516 | T40: 0 | U40: =SUM(S40:T40) -> 7582.8516
A41: MX.T3.B | B41: 86030 (Lodging)/ 86050 (M&IE) | C41: MEX | D41: Lodging and M&IE in Mexico City | E41: Travel | F41: 1 | G41: Day | H41: =5*2 -> 10 | I41: =+Travel!B19+Travel!B20 -> 231.31892 | J41: =H41*$I41*$F41 -> 2313.1892 | K41: =5*2 -> 10 | L41: =+K41*$I41*$F41*$E$6 -> 2405.7168 | M41: =5*2 -> 10 | N41: =+M41*$I41*$F41*$E$6*$E$6 -> 2501.9454 | O41: =5*2 -> 10 | P41: =+O41*$I41*$F41*$E$6*$E$6*$E$6 -> 2602.0232 | Q41: =5*2 -> 10 | R41: =+Q41*$I41*$F41*$E$6*$E$6*$E$6*$E$6 -> 2706.1042 | S41: =SUM(J41+L41+N41+P41+R41) -> 12528.979 | T41: 0 | U41: =SUM(S41:T41) -> 12528.979
A42: MX.T3.C | B42: 86000 | C42: MEX | D42: Local transportation in Mexico City | E42: Travel | F42: 1 | G42: Day | H42: =5*2 -> 10 | I42: 50 | J42: =H42*$I42*$F42 -> 500 | K42: =5*2 -> 10 | L42: =+K42*$I42*$F42*$E$6 -> 520 | M42: =5*2 -> 10 | N42: =+M42*$I42*$F42*$E$6*$E$6 -> 540.8 | O42: =5*2 -> 10 | P42: =+O42*$I42*$F42*$E$6*$E$6*$E$6 -> 562.432 | Q42: =5*2 -> 10 | R42: =+Q42*$I42*$F42*$E$6*$E$6*$E$6*$E$6 -> 584.92928 | S42: =SUM(J42+L42+N42+P42+R42) -> 2708.1613 | T42: 0 | U42: =SUM(S42:T42) -> 2708.1613
D43: T4: Domestic Travel to Field
D44: Activity 6: Facilitate Constructive Dialogue between Employers and Local Labor Authorities
A45: MX.T4.6A | B45: 86040 | C45: MEX | D45: Airfare | E45: Travel | F45: 1 | G45: Trip | H45: 4 | I45: =+Travel!$D$11 -> 363.30878 | J45: =H45*$I45*$F45 -> 1453.2351 | K45: 4 | L45: =+K45*$I45*$F45*$E$6 -> 1511.3645 | M45: 4 | N45: =+M45*$I45*$F45*$E$6*$E$6 -> 1571.8191 | O45: 4 | P45: =+O45*$I45*$F45*$E$6*$E$6*$E$6 -> 1634.6919 | R45: =+Q45*$I45*$F45*$E$6*$E$6*$E$6*$E$6 -> 0 | S45: =SUM(J45+L45+N45+P45+R45) -> 6171.1107 | T45: 0 | U45: =SUM(S45:T45) -> 6171.1107
A46: MX.T4.6B | B46: 86030 (Lodging)/ 86050 (M&IE) | C46: MEX | D46: Lodging and M&IE | E46: Travel | F46: 1 | G46: Day | H46: =4*2 -> 8 | I46: =+Travel!$B$11+Travel!$C$12 -> 153.03504 | J46: =H46*$I46*$F46 -> 1224.2803 | K46: =4*2 -> 8 | L46: =+K46*$I46*$F46*$E$6 -> 1273.2515 | M46: =4*2 -> 8 | N46: =+M46*$I46*$F46*$E$6*$E$6 -> 1324.1816 | O46: =4*2 -> 8 | P46: =+O46*$I46*$F46*$E$6*$E$6*$E$6 -> 1377.1488 | R46: =+Q46*$I46*$F46*$E$6*$E$6*$E$6*$E$6 -> 0 | S46: =SUM(J46+L46+N46+P46+R46) -> 5198.8623 | T46: 0 | U46: =SUM(S46:T46) -> 5198.8623
A47: MX.T4.6C | B47: 86000 | C47: MEX | D47: Local transportation | E47: Travel | F47: 1 | G47: Day | H47: =4*2 -> 8 | I47: 50 | J47: =H47*$I47*$F47 -> 400 | K47: =4*2 -> 8 | L47: =+K47*$I47*$F47*$E$6 -> 416 | M47: =4*2 -> 8 | N47: =+M47*$I47*$F47*$E$6*$E$6 -> 432.64 | O47: =4*2 -> 8 | P47: =+O47*$I47*$F47*$E$6*$E$6*$E$6 -> 449.9456 | R47: =+Q47*$I47*$F47*$E$6*$E$6*$E$6*$E$6 -> 0 | S47: =SUM(J47+L47+N47+P47+R47) -> 1698.5856 | T47: 0 | U47: =SUM(S47:T47) -> 1698.5856
D48: Activity 7: Strengthen SMEs’ Knowledge of and Compliance with Labor Reforms and USMCA Commitments
A49: MX.T4.7A | B49: 86040 | C49: MEX | D49: Airfare | E49: Travel | F49: 1 | G49: Trip | H49: 3 | I49: =+Travel!$D$11 -> 363.30878 | J49: =H49*$I49*$F49 -> 1089.9264 | K49: 3 | L49: =+K49*$I49*$F49*$E$6 -> 1133.5234 | M49: 3 | N49: =+M49*$I49*$F49*$E$6*$E$6 -> 1178.8643 | O49: 3 | P49: =+O49*$I49*$F49*$E$6*$E$6*$E$6 -> 1226.0189 | R49: =+Q49*$I49*$F49*$E$6*$E$6*$E$6*$E$6 -> 0 | S49: =SUM(J49+L49+N49+P49+R49) -> 4628.333 | T49: 0 | U49: =SUM(S49:T49) -> 4628.333
A50: MX.T4.7B | B50: 86030 (Lodging)/ 86050 (M&IE) | C50: MEX | D50: Lodging and M&IE | E50: Travel | F50: 1 | G50: Day | H50: =3*2 -> 6 | I50: =+Travel!$B$11+Travel!$C$12 -> 153.03504 | J50: =H50*$I50*$F50 -> 918.21023 | K50: =3*2 -> 6 | L50: =+K50*$I50*$F50*$E$6 -> 954.93864 | M50: =3*2 -> 6 | N50: =+M50*$I50*$F50*$E$6*$E$6 -> 993.13619 | O50: =3*2 -> 6 | P50: =+O50*$I50*$F50*$E$6*$E$6*$E$6 -> 1032.8616 | R50: =+Q50*$I50*$F50*$E$6*$E$6*$E$6*$E$6 -> 0 | S50: =SUM(J50+L50+N50+P50+R50) -> 3899.1467 | T50: 0 | U50: =SUM(S50:T50) -> 3899.1467
A51: MX.T4.7C | B51: 86000 | C51: MEX | D51: Local transportation | E51: Travel | F51: 1 | G51: Day | H51: =3*2 -> 6 | I51: 50 | J51: =H51*$I51*$F51 -> 300 | K51: =3*2 -> 6 | L51: =+K51*$I51*$F51*$E$6 -> 312 | M51: =3*2 -> 6 | N51: =+M51*$I51*$F51*$E$6*$E$6 -> 324.48 | O51: =3*2 -> 6 | P51: =+O51*$I51*$F51*$E$6*$E$6*$E$6 -> 337.4592 | R51: =+Q51*$I51*$F51*$E$6*$E$6*$E$6*$E$6 -> 0 | S51: =SUM(J51+L51+N51+P51+R51) -> 1273.9392 | T51: 0 | U51: =SUM(S51:T51) -> 1273.9392
D52: Activity 8: Increase Transparency to Strengthen Collective Bargaining
A53: MX.T4.8A | B53: 86040 | C53: MEX | D53: Airfare | E53: Travel | F53: 1 | G53: Trip | H53: =4 -> 4 | I53: =+Travel!$D$11 -> 363.30878 | J53: =H53*$I53*$F53 -> 1453.2351 | K53: =4 -> 4 | L53: =+K53*$I53*$F53*$E$6 -> 1511.3645 | M53: =4 -> 4 | N53: =+M53*$I53*$F53*$E$6*$E$6 -> 1571.8191 | P53: =+O53*$I53*$F53*$E$6*$E$6*$E$6 -> 0 | R53: =+Q53*$I53*$F53*$E$6*$E$6*$E$6*$E$6 -> 0 | S53: =SUM(J53+L53+N53+P53+R53) -> 4536.4188 | T53: 0 | U53: =SUM(S53:T53) -> 4536.4188
A54: MX.T4.8B | B54: 86030 (Lodging)/ 86050 (M&IE) | C54: MEX | D54: Lodging and M&IE | E54: Travel | F54: 1 | G54: Day | H54: =4*2 -> 8 | I54: =+Travel!$B$11+Travel!$C$12 -> 153.03504 | J54: =H54*$I54*$F54 -> 1224.2803 | K54: =4*2 -> 8 | L54: =+K54*$I54*$F54*$E$6 -> 1273.2515 | M54: =4*2 -> 8 | N54: =+M54*$I54*$F54*$E$6*$E$6 -> 1324.1816 | P54: =+O54*$I54*$F54*$E$6*$E$6*$E$6 -> 0 | R54: =+Q54*$I54*$F54*$E$6*$E$6*$E$6*$E$6 -> 0 | S54: =SUM(J54+L54+N54+P54+R54) -> 3821.7134 | T54: 0 | U54: =SUM(S54:T54) -> 3821.7134
A55: MX.T4.8C | B55: 86000 | C55: MEX | D55: Local transportation | E55: Travel | F55: 1 | G55: Day | H55: =4*2 -> 8 | I55: 50 | J55: =H55*$I55*$F55 -> 400 | K55: =4*2 -> 8 | L55: =+K55*$I55*$F55*$E$6 -> 416 | M55: =4*2 -> 8 | N55: =+M55*$I55*$F55*$E$6*$E$6 -> 432.64 | P55: =+O55*$I55*$F55*$E$6*$E$6*$E$6 -> 0 | R55: =+Q55*$I55*$F55*$E$6*$E$6*$E$6*$E$6 -> 0 | S55: =SUM(J55+L55+N55+P55+R55) -> 1248.64 | T55: 0 | U55: =SUM(S55:T55) -> 1248.64
D56: Activity 9: Increase Union Capacity to Submit Effective Petitions under the RRM of the USMCA
A57: MX.T4.9A | B57: 86040 | C57: MEX | D57: Airfare | E57: Travel | F57: 1 | G57: Trip | H57: 4 | I57: =+Travel!$D$11 -> 363.30878 | J57: =H57*$I57*$F57 -> 1453.2351 | K57: 4 | L57: =+K57*$I57*$F57*$E$6 -> 1511.3645 | N57: =+M57*$I57*$F57*$E$6*$E$6 -> 0 | P57: =+O57*$I57*$F57*$E$6*$E$6*$E$6 -> 0 | R57: =+Q57*$I57*$F57*$E$6*$E$6*$E$6*$E$6 -> 0 | S57: =SUM(J57+L57+N57+P57+R57) -> 2964.5997 | T57: 0 | U57: =SUM(S57:T57) -> 2964.5997
A58: MX.T4.9B | B58: 86030 (Lodging)/ 86050 (M&IE) | C58: MEX | D58: Lodging and M&IE | E58: Travel | F58: 1 | G58: Day | H58: =4*2 -> 8 | I58: =+Travel!$B$11+Travel!$C$12 -> 153.03504 | J58: =H58*$I58*$F58 -> 1224.2803 | K58: =4*2 -> 8 | L58: =+K58*$I58*$F58*$E$6 -> 1273.2515 | N58: =+M58*$I58*$F58*$E$6*$E$6 -> 0 | P58: =+O58*$I58*$F58*$E$6*$E$6*$E$6 -> 0 | R58: =+Q58*$I58*$F58*$E$6*$E$6*$E$6*$E$6 -> 0 | S58: =SUM(J58+L58+N58+P58+R58) -> 2497.5318 | T58: 0 | U58: =SUM(S58:T58) -> 2497.5318
A59: MX.T4.9C | B59: 86000 | C59: MEX | D59: Local transportation | E59: Travel | F59: 1 | G59: Day | H59: =4*2 -> 8 | I59: 50 | J59: =H59*$I59*$F59 -> 400 | K59: =4*2 -> 8 | L59: =+K59*$I59*$F59*$E$6 -> 416 | N59: =+M59*$I59*$F59*$E$6*$E$6 -> 0 | P59: =+O59*$I59*$F59*$E$6*$E$6*$E$6 -> 0 | R59: =+Q59*$I59*$F59*$E$6*$E$6*$E$6*$E$6 -> 0 | S59: =SUM(J59+L59+N59+P59+R59) -> 816 | T59: 0 | U59: =SUM(S59:T59) -> 816
D60: Activity 10: Strengthen Collective Bargaining Capacity through U.S. Union Exchanges
A61: MX.T4.10A | B61: 86040 | C61: MEX | D61: Airfare | E61: Travel | F61: 1 | G61: Trip | H61: 0 | I61: =+Travel!B36 -> 795.89949 | J61: =H61*$I61*$F61 -> 0 | K61: =2*2 -> 4 | L61: =+K61*$I61*$F61 -> 3183.5979 | M61: =2*2 -> 4 | N61: =+M61*$I61*$F61*$E$6 -> 3310.9419 | O61: =2*2 -> 4 | P61: =+O61*$I61*$F61*$E$6*$E$6 -> 3443.3795 | R61: =+Q61*$I61*$F61*$E$6*$E$6*$E$6*$E$6 -> 0 | S61: =SUM(J61+L61+N61+P61+R61) -> 9937.9193 | T61: 0 | U61: =SUM(S61:T61) -> 9937.9193
A62: MX.T4.10B | B62: 86030 (Lodging)/ 86050 (M&IE) | C62: MEX | D62: Lodging and M&IE | E62: Travel | F62: 1 | G62: Day | H62: 0 | I62: =+Travel!B19+Travel!B20 -> 231.31892 | J62: =H62*$I62*$F62 -> 0 | K62: =2*2*3 -> 12 | L62: =+K62*$I62*$F62 -> 2775.827 | M62: =2*2*3 -> 12 | N62: =+M62*$I62*$F62*$E$6 -> 2886.8601 | O62: =2*2*3 -> 12 | P62: =+O62*$I62*$F62*$E$6*$E$6 -> 3002.3345 | R62: =+Q62*$I62*$F62*$E$6*$E$6*$E$6*$E$6 -> 0 | S62: =SUM(J62+L62+N62+P62+R62) -> 8665.0216 | T62: 0 | U62: =SUM(S62:T62) -> 8665.0216
A63: MX.T4.10C | B63: 86000 | C63: MEX | D63: Local transportation | E63: Travel | F63: 1 | G63: Day | H63: 0 | I63: 50 | J63: =H63*$I63*$F63 -> 0 | K63: =2*2*3 -> 12 | L63: =+K63*$I63*$F63 -> 600 | M63: =2*2*3 -> 12 | N63: =+M63*$I63*$F63*$E$6 -> 624 | O63: =2*2*3 -> 12 | P63: =+O63*$I63*$F63*$E$6*$E$6 -> 648.96 | R63: =+Q63*$I63*$F63*$E$6*$E$6*$E$6*$E$6 -> 0 | S63: =SUM(J63+L63+N63+P63+R63) -> 1872.96 | T63: 0 | U63: =SUM(S63:T63) -> 1872.96
D64: Activity 11: Build a New Generation of Union Leadership
A65: MX.T4.11A | B65: 86040 | C65: MEX | D65: Airfare | E65: Travel | F65: 1 | G65: Trip | H65: 0 | I65: =+Travel!$D$11 -> 363.30878 | J65: =H65*$I65*$F65 -> 0 | K65: 4 | L65: =+K65*$I65*$F65*$E$6 -> 1511.3645 | M65: 4 | N65: =+M65*$I65*$F65*$E$6*$E$6 -> 1571.8191 | O65: 4 | P65: =+O65*$I65*$F65*$E$6*$E$6*$E$6 -> 1634.6919 | R65: =+Q65*$I65*$F65*$E$6*$E$6*$E$6*$E$6 -> 0 | S65: =SUM(J65+L65+N65+P65+R65) -> 4717.8755 | T65: 0 | U65: =SUM(S65:T65) -> 4717.8755
A66: MX.T4.11B | B66: 86030 (Lodging)/ 86050 (M&IE) | C66: MEX | D66: Lodging and M&IE | E66: Travel | F66: 1 | G66: Day | H66: 0 | I66: =+Travel!$B$11+Travel!$C$12 -> 153.03504 | J66: =H66*$I66*$F66 -> 0 | K66: =4*2 -> 8 | L66: =+K66*$I66*$F66*$E$6 -> 1273.2515 | M66: =4*2 -> 8 | N66: =+M66*$I66*$F66*$E$6*$E$6 -> 1324.1816 | O66: =4*2 -> 8 | P66: =+O66*$I66*$F66*$E$6*$E$6*$E$6 -> 1377.1488 | R66: =+Q66*$I66*$F66*$E$6*$E$6*$E$6*$E$6 -> 0 | S66: =SUM(J66+L66+N66+P66+R66) -> 3974.5819 | T66: 0 | U66: =SUM(S66:T66) -> 3974.5819
A67: MX.T4.11C | B67: 86000 | C67: MEX | D67: Local transportation | E67: Travel | F67: 1 | G67: Day | H67: 0 | I67: 50 | J67: =H67*$I67*$F67 -> 0 | K67: =4*2 -> 8 | L67: =+K67*$I67*$F67*$E$6 -> 416 | M67: =4*2 -> 8 | N67: =+M67*$I67*$F67*$E$6*$E$6 -> 432.64 | O67: =4*2 -> 8 | P67: =+O67*$I67*$F67*$E$6*$E$6*$E$6 -> 449.9456 | R67: =+Q67*$I67*$F67*$E$6*$E$6*$E$6*$E$6 -> 0 | S67: =SUM(J67+L67+N67+P67+R67) -> 1298.5856 | T67: 0 | U67: =SUM(S67:T67) -> 1298.5856
D68: M&E - Collection of Reliable Data and Processing of Monitoring Data
A69: MX.T5.A | B69: 86040 | C69: MEX | D69: M&E - Airfare - Field verification and data collection visits | E69: M&E | F69: 1 | G69: Trip | H69: =H45*8 -> 32 | I69: =+Travel!$D$11 -> 363.30878 | J69: =H69*$I69*$F69 -> 11625.881 | K69: =K45*12 -> 48 | L69: =+K69*$I69*$F69*$E$6 -> 18136.374 | M69: =M45*10 -> 40 | N69: =+M69*$I69*$F69*$E$6*$E$6 -> 15718.191 | O69: =O45*10 -> 40 | P69: =+O69*$I69*$F69*$E$6*$E$6*$E$6 -> 16346.919 | R69: =+Q69*$I69*$F69*$E$6*$E$6*$E$6*$E$6 -> 0 | S69: =SUM(J69+L69+N69+P69+R69) -> 61827.366 | T69: 0 | U69: =SUM(S69:T69) -> 61827.366
A70: MX.T5.B | B70: 86030 (Lodging)/ 86050 (M&IE) | C70: MEX | D70: M&E - Lodging and M&IE - Field verification and data collection visits | E70: M&E | F70: 1 | G70: Day | H70: =H46*8 -> 64 | I70: =+Travel!$B$11+Travel!$C$12 -> 153.03504 | J70: =H70*$I70*$F70 -> 9794.2425 | K70: =K46*12 -> 96 | L70: =+K70*$I70*$F70*$E$6 -> 15279.018 | M70: =M46*10 -> 80 | N70: =+M70*$I70*$F70*$E$6*$E$6 -> 13241.816 | O70: =O46*10 -> 80 | P70: =+O70*$I70*$F70*$E$6*$E$6*$E$6 -> 13771.488 | R70: =+Q70*$I70*$F70*$E$6*$E$6*$E$6*$E$6 -> 0 | S70: =SUM(J70+L70+N70+P70+R70) -> 52086.565 | T70: 0 | U70: =SUM(S70:T70) -> 52086.565
A71: MX.T5.C | B71: 86000 | C71: MEX | D71: M&E - Local transportation | E71: M&E | F71: 1 | G71: Day | H71: =H47*8 -> 64 | I71: 50 | J71: =H71*$I71*$F71 -> 3200 | K71: =K47*12 -> 96 | L71: =+K71*$I71*$F71*$E$6 -> 4992 | M71: =M47*10 -> 80 | N71: =+M71*$I71*$F71*$E$6*$E$6 -> 4326.4 | O71: =O47*10 -> 80 | P71: =+O71*$I71*$F71*$E$6*$E$6*$E$6 -> 4499.456 | R71: =+Q71*$I71*$F71*$E$6*$E$6*$E$6*$E$6 -> 0 | S71: =SUM(J71+L71+N71+P71+R71) -> 17017.856 | T71: 0 | U71: =SUM(S71:T71) -> 17017.856
A72: MX.T5.D | B72: 82420 (Materials)/ 85300 (Printing) | C72: MEX | D72: M&E - Data collection materials and printing | E72: M&E | F72: 1 | G72: Unit | H72: =+H69 -> 32 | I72: 50 | J72: =H72*$I72*$F72 -> 1600 | K72: =+K69 -> 48 | L72: =+K72*$I72*$F72*$E$6 -> 2496 | M72: =+M69 -> 40 | N72: =+M72*$I72*$F72*$E$6*$E$6 -> 2163.2 | O72: =+O69 -> 40 | P72: =+O72*$I72*$F72*$E$6*$E$6*$E$6 -> 2249.728 | R72: =+Q72*$I72*$F72*$E$6*$E$6*$E$6*$E$6 -> 0 | S72: =SUM(J72+L72+N72+P72+R72) -> 8508.928 | T72: 0 | U72: =SUM(S72:T72) -> 8508.928
D73: M&E - Stakeholder Engagement and Strategy Validation
A74: MX.T5.E | B74: 86040 | C74: MEX | D74: M&E - Airfare | E74: Travel | F74: 1 | G74: Trip | H74: =((3+2)*4) -> 20 | I74: =+Travel!$D$11 -> 363.30878 | J74: =H74*$I74*$F74 -> 7266.1757 | L74: =+K74*$I74*$F74*$E$6 -> 0 | N74: =+M74*$I74*$F74*$E$6*$E$6 -> 0 | P74: =+O74*$I74*$F74*$E$6*$E$6*$E$6 -> 0 | R74: =+Q74*$I74*$F74*$E$6*$E$6*$E$6*$E$6 -> 0 | S74: =SUM(J74+L74+N74+P74+R74) -> 7266.1757 | T74: 0 | U74: =SUM(S74:T74) -> 7266.1757
A75: MX.T5.F | B75: 86030 (Lodging)/ 86050 (M&IE) | C75: MEX | D75: M&E - Lodging and M&IE - Field verification and data collection visits | E75: M&E | F75: 1 | G75: Day | H75: =((3+2)*4)*2 -> 40 | I75: =+Travel!$B$11+Travel!$C$12 -> 153.03504 | J75: =H75*$I75*$F75 -> 6121.4015 | L75: =+K75*$I75*$F75*$E$6 -> 0 | N75: =+M75*$I75*$F75*$E$6*$E$6 -> 0 | P75: =+O75*$I75*$F75*$E$6*$E$6*$E$6 -> 0 | R75: =+Q75*$I75*$F75*$E$6*$E$6*$E$6*$E$6 -> 0 | S75: =SUM(J75+L75+N75+P75+R75) -> 6121.4015 | T75: 0 | U75: =SUM(S75:T75) -> 6121.4015
A76: MX.T5.G | B76: 86000 | C76: MEX | D76: M&E - Local transportation | E76: M&E | F76: 1 | G76: Day | H76: =((3+2)*4)*2 -> 40 | I76: 50 | J76: =H76*$I76*$F76 -> 2000 | L76: =+K76*$I76*$F76*$E$6 -> 0 | N76: =+M76*$I76*$F76*$E$6*$E$6 -> 0 | P76: =+O76*$I76*$F76*$E$6*$E$6*$E$6 -> 0 | R76: =+Q76*$I76*$F76*$E$6*$E$6*$E$6*$E$6 -> 0 | S76: =SUM(J76+L76+N76+P76+R76) -> 2000 | T76: 0 | U76: =SUM(S76:T76) -> 2000
D77: Total Travel | J77: =SUM(J31:J76) -> 62289.573 | L77: =SUM(L31:L76) -> 71787.781 | N77: =SUM(N31:N76) -> 64240.73 | P77: =SUM(P31:P76) -> 63348.573 | R77: =SUM(R31:R76) -> 10261.051 | S77: =SUM(S31:S76) -> 271927.71 | T77: =SUM(T31:T76) -> 0 | U77: =SUM(U31:U76) -> 271927.71
D78: Equipment
A79: None | B79: None | C79: None | D79: None | E79: Equipment | G79: Unit | H79: 0 | I79: 0 | J79: =H79*$I79*$F79 -> 0 | K79: 0 | L79: =+K79*$I79*$F79*$E$6 -> 0 | M79: 0 | N79: =+M79*$I79*$F79*$E$6*$E$6 -> 0 | O79: 0 | P79: =+O79*$I79*$F79*$E$6*$E$6*$E$6 -> 0 | Q79: 0 | R79: =+Q79*$I79*$F79*$E$6*$E$6*$E$6*$E$6 -> 0 | S79: =SUM(J79+L79+N79+P79+R79) -> 0 | T79: 0 | U79: =SUM(S79:T79) -> 0
D80: Total Equipment | J80: =SUM(J79) -> 0 | L80: =SUM(L79) -> 0 | N80: =SUM(N79) -> 0 | P80: =SUM(P79) -> 0 | R80: =SUM(R79) -> 0 | S80: =SUM(S79) -> 0 | T80: =SUM(T79:T79) -> 0 | U80: =SUM(S80:T80) -> 0
D81: Supplies
A82: LAPTOP | B82: 82401 | C82: MEX/USA | D82: Laptop computers & software | E82: Supplies | F82: 1 | G82: Unit | H82: 8 | I82: 1100 | J82: =H82*$I82*$F82 -> 8800 | K82: 0 | L82: =+K82*$I82*$F82*$E$6 -> 0 | M82: 0 | N82: =+M82*$I82*$F82*$E$6*$E$6 -> 0 | O82: 0 | P82: =+O82*$I82*$F82*$E$6*$E$6*$E$6 -> 0 | Q82: 0 | R82: =+Q82*$I82*$F82*$E$6*$E$6*$E$6*$E$6 -> 0 | S82: =SUM(J82+L82+N82+P82+R82) -> 8800 | T82: 0 | U82: =SUM(S82:T82) -> 8800
A83: SUPPLIES | B83: 82401 | C83: MEX/USA | D83: Office supplies | E83: Supplies | F83: 1 | G83: Month | H83: 6 | I83: 150 | J83: =H83*$I83*$F83 -> 900 | K83: 12 | L83: =+K83*$I83*$F83*$E$6 -> 1872 | M83: 12 | N83: =+M83*$I83*$F83*$E$6*$E$6 -> 1946.88 | O83: 12 | P83: =+O83*$I83*$F83*$E$6*$E$6*$E$6 -> 2024.7552 | Q83: 6 | R83: =+Q83*$I83*$F83*$E$6*$E$6*$E$6*$E$6 -> 1052.8727 | S83: =SUM(J83+L83+N83+P83+R83) -> 7796.5079 | T83: 0 | U83: =SUM(S83:T83) -> 7796.5079
A84: PRINTER | B84: 82401 | C84: MEX/USA | D84: Printer | E84: Supplies | F84: 1 | G84: Unit | H84: 1 | I84: 502 | J84: =H84*$I84*$F84 -> 502 | L84: =+K84*$I84*$F84*$E$6 -> 0 | N84: =+M84*$I84*$F84*$E$6*$E$6 -> 0 | P84: =+O84*$I84*$F84*$E$6*$E$6*$E$6 -> 0 | R84: =+Q84*$I84*$F84*$E$6*$E$6*$E$6*$E$6 -> 0 | S84: =SUM(J84+L84+N84+P84+R84) -> 502 | T84: 0 | U84: =SUM(S84:T84) -> 502
D85: Total Supplies | J85: =SUM(J82:J84) -> 10202 | L85: =SUM(L82:L84) -> 1872 | N85: =SUM(N82:N84) -> 1946.88 | P85: =SUM(P82:P84) -> 2024.7552 | R85: =SUM(R82:R84) -> 1052.8727 | S85: =SUM(S82:S84) -> 17098.508 | T85: =SUM(T82:T84) -> 0 | U85: =SUM(U82:U84) -> 17098.508
D86: Contractual
D87: Subawards
A88: SUBFES | B88: 89050 | C88: MEX | D88: Friedrich-Ebert-Stiftung (FES) | E88: Subaward | F88: 1 | G88: Subaward | H88: 1 | I88: 0 | J88: =+'FES Sub Budget'!G67 -> 56712.321 | K88: 1 | L88: =+'FES Sub Budget'!I67 -> 246791.02 | M88: 1 | N88: =+'FES Sub Budget'!K67 -> 288227.19 | O88: 1 | P88: =+'FES Sub Budget'!M67 -> 207741.3 | Q88: 1 | R88: =+'FES Sub Budget'!O67 -> 0 | S88: =SUM(J88+L88+N88+P88+R88) -> 799471.83 | T88: 0 | U88: =SUM(S88:T88) -> 799471.83
A89: SUBITAM | B89: 89050 | C89: MEX | D89: Instituto Tecnológico Autónomo de México (ITAM) | E89: Subaward | F89: 1 | G89: Subaward | H89: 1 | I89: 0 | J89: =+'ITAM Sub Budget'!G113 -> 234615.24 | K89: 1 | L89: =+'ITAM Sub Budget'!I113 -> 936794.83 | M89: 1 | N89: =+'ITAM Sub Budget'!K113 -> 849217.92 | O89: 1 | P89: =+'ITAM Sub Budget'!M113 -> 608499.3 | Q89: 1 | R89: =+'ITAM Sub Budget'!O113 -> 0 | S89: =SUM(J89+L89+N89+P89+R89) -> 2629127.3 | T89: 0 | U89: =SUM(S89:T89) -> 2629127.3
D90: Contracts
A91: COMMCONT | B91: 81000 (Consultant)/ 81010 (Professional Fees) | C91: MEX | D91: Communications & Creation of Visual Assets Contract | E91: Contract | F91: 1 | G91: Contract | H91: 8 | I91: 3000 | J91: =H91*$I91*$F91 -> 24000 | K91: 12 | L91: =+K91*$I91*$F91*$E$6 -> 37440 | M91: 12 | N91: =+M91*$I91*$F91*$E$6*$E$6 -> 38937.6 | O91: 12 | P91: =+O91*$I91*$F91*$E$6*$E$6*$E$6 -> 40495.104 | Q91: 3 | R91: =+Q91*$I91*$F91*$E$6*$E$6*$E$6*$E$6 -> 10528.727 | S91: =SUM(J91+L91+N91+P91+R91) -> 151401.43 | T91: 0 | U91: =SUM(S91:T91) -> 151401.43
A92: ELECTCONT | B92: 81000 (Consultant)/ 81010 (Professional Fees) | C92: MEX | D92: Activity 9 - Contract on democratically elected unions and accompanying organizations | E92: Contract | F92: 1 | G92: Contract | H92: 5 | I92: 20000 | J92: =H92*$I92*$F92 -> 100000 | K92: 5 | L92: =+K92*$I92*$F92*$E$6 -> 104000 | N92: =+M92*$I92*$F92*$E$6*$E$6 -> 0 | P92: =+O92*$I92*$F92*$E$6*$E$6*$E$6 -> 0 | R92: =+Q92*$I92*$F92*$E$6*$E$6*$E$6*$E$6 -> 0 | S92: =SUM(J92+L92+N92+P92+R92) -> 204000 | T92: 0 | U92: =SUM(S92:T92) -> 204000
A93: DIGITALCON | B93: 81000 (Consultant)/ 81010 (Professional Fees) | C93: MEX | D93: Activity 7 - Contract to digitalize Compliance Checklist to Strengthen Compliance Across Priority Sectors and States | E93: Contract | F93: 1 | G93: Contract | I93: 20000 | J93: =H93*$I93*$F93 -> 0 | K93: 1 | L93: =+K93*$I93*$F93 -> 20000 | N93: =+M93*$I93*$F93*$E$6*$E$6 -> 0 | P93: =+O93*$I93*$F93*$E$6*$E$6*$E$6 -> 0 | R93: =+Q93*$I93*$F93*$E$6*$E$6*$E$6*$E$6 -> 0 | S93: =SUM(J93+L93+N93+P93+R93) -> 20000 | T93: 0 | U93: =SUM(S93:T93) -> 20000
A94: MIDLINE | B94: 81010 | C94: MEX | D94: M&E - Interim Performance Evaluation | E94: M&E | F94: 1 | G94: Evaluation | I94: 35000 | J94: =H94*$I94*$F94 -> 0 | L94: =+K94*$I94*$F94*$E$6 -> 0 | M94: 1 | N94: =+M94*$I94*$F94 -> 35000 | P94: =+O94*$I94*$F94*$E$6*$E$6*$E$6 -> 0 | R94: =+Q94*$I94*$F94*$E$6*$E$6*$E$6*$E$6 -> 0 | S94: =SUM(J94+L94+N94+P94+R94) -> 35000 | T94: 0 | U94: =SUM(S94:T94) -> 35000
A95: ENDLINE | B95: 81010 | C95: MEX | D95: M&E - Final Performance Evaluation | E95: M&E | F95: 1 | G95: Evaluation | I95: 35000 | J95: =H95*$I95*$F95 -> 0 | L95: =+K95*$I95*$F95*$E$6 -> 0 | N95: =+M95*$I95*$F95*$E$6*$E$6 -> 0 | P95: =+O95*$I95*$F95*$E$6*$E$6*$E$6 -> 0 | Q95: 1 | R95: =+Q95*$I95*$F95 -> 35000 | S95: =SUM(J95+L95+N95+P95+R95) -> 35000 | T95: 0 | U95: =SUM(S95:T95) -> 35000
D96: Total Contractual | J96: =SUM(J88:J95) -> 415327.56 | L96: =SUM(L88:L95) -> 1345025.8 | N96: =SUM(N88:N95) -> 1211382.7 | P96: =SUM(P88:P95) -> 856735.7 | R96: =SUM(R88:R95) -> 45528.727 | S96: =SUM(S88:S95) -> 3874000.5 | T96: =SUM(T88:T95) -> 0 | U96: =SUM(U88:U95) -> 3874000.5
D97: Construction
A98: None | B98: None | C98: None | D98: None | E98: Construction | G98: Unit | H98: 0 | I98: 0 | J98: =H98*$I98*$F98 -> 0 | K98: 0 | L98: =+K98*$I98*$F98*$E$6 -> 0 | M98: 0 | N98: =+M98*$I98*$F98*$E$6*$E$6 -> 0 | O98: 0 | P98: =+O98*$I98*$F98*$E$6*$E$6*$E$6 -> 0 | Q98: 0 | R98: =+Q98*$I98*$F98*$E$6*$E$6*$E$6*$E$6 -> 0 | S98: =SUM(J98+L98+N98+P98+R98) -> 0 | T98: 0 | U98: =SUM(S98:T98) -> 0
D99: Total Construction | J99: =SUM(J98) -> 0 | L99: =SUM(L98) -> 0 | N99: =SUM(N98) -> 0 | P99: =SUM(P98) -> 0 | R99: =SUM(R98) -> 0 | S99: =SUM(S98) -> 0 | T99: =SUM(T98:T98) -> 0 | U99: =SUM(S99:T99) -> 0
D100: Other Direct Costs
D101: Project Office
...

Sheet M&E Budget
A1: M&E Budget
A2: Partners of the Americas
A3: Leveling the Field for American Workers in U.S.-Mexico Trade
A4: 54 Months
A5: Cost Assumptions
A6: Inflation - Goods/Services | B6: 1.04
A7: Merit Based Increases for HO & Field Staff | B7: 1.05
A9: BUDGET ITEM | B9: CATEGORY | C9: LOE | D9: UNIT | E9: # of Units | F9: RATE / UNIT | G9: Year 1 | H9: # of Units | I9: Year 2 | J9: # of Units | K9: Year 3 | L9: # of Units | M9: Year 4 | N9: # of Units | O9: Year 5 | P9: TOTAL DOL | Q9: TOTAL COST SHARING | R9: PROJECT GRAND TOTAL
A10: Partners of the Americas Monitoring, Evaluation, and Collection of Reliable Data
A11: Travel
A12: M&E - Collection of Reliable Data and Processing of Monitoring Data
A13: M&E - Airfare - Field verification and data collection visits | B13: M&E | C13: 1 | D13: Trip | E13: =+'POA General Budget'!H69 -> 32 | F13: =+'POA General Budget'!I69 -> 363.30878 | G13: =+'POA General Budget'!J69 -> 11625.881 | H13: =+'POA General Budget'!K69 -> 48 | I13: =+'POA General Budget'!L69 -> 18136.374 | J13: =+'POA General Budget'!M69 -> 40 | K13: =+'POA General Budget'!N69 -> 15718.191 | L13: =+'POA General Budget'!O69 -> 40 | ... R13: =+'POA General Budget'!U69 -> 61827.366
A14: M&E - Lodging and M&IE - Field verification and data collection visits | B14: M&E | C14: 1 | D14: Day | E14: =+'POA General Budget'!H70 -> 64 | F14: =+'POA General Budget'!I70 -> 153.03504 | G14: =+'POA General Budget'!J70 -> 9794.2425 | H14: =+'POA General Budget'!K70 -> 96 | I14: =+'POA General Budget'!L70 -> 15279.018 | J14: =+'POA General Budget'!M70 -> 80 | K14: =+'POA General Budget'!N70 -> 13241.816 | L14: =+'POA General Budget'!O70 -> 80 | ... R14: =+'POA General Budget'!U70 -> 52086.565
A15: M&E - Local transportation | B15: M&E | C15: 1 | D15: Day | E15: =+'POA General Budget'!H71 -> 64 | F15: =+'POA General Budget'!I71 -> 50 | G15: =+'POA General Budget'!J71 -> 3200 | H15: =+'POA General Budget'!K71 -> 96 | I15: =+'POA General Budget'!L71 -> 4992 | J15: =+'POA General Budget'!M71 -> 80 | K15: =+'POA General Budget'!N71 -> 4326.4 | L15: =+'POA General Budget'!O71 -> 80 | ... R15: =+'POA General Budget'!U71 -> 17017.856
A16: M&E - Data collection materials and printing | B16: M&E | C16: 1 | D16: Unit | E16: =+'POA General Budget'!H72 -> 32 | F16: =+'POA General Budget'!I72 -> 50 | G16: =+'POA General Budget'!J72 -> 1600 | H16: =+'POA General Budget'!K72 -> 48 | I16: =+'POA General Budget'!L72 -> 2496 | J16: =+'POA General Budget'!M72 -> 40 | K16: =+'POA General Budget'!N72 -> 2163.2 | L16: =+'POA General Budget'!O72 -> 40 | ... R16: =+'POA General Budget'!U72 -> 8508.928
A17: M&E - Stakeholder Engagement and Strategy Validation | E17: =+'POA General Budget'!H73 -> 0 | F17: =+'POA General Budget'!I73 -> 0 | G17: =+'POA General Budget'!J73 -> 0 | H17: =+'POA General Budget'!K73 -> 0 | I17: =+'POA General Budget'!L73 -> 0 | J17: =+'POA General Budget'!M73 -> 0 | K17: =+'POA General Budget'!N73 -> 0 | L17: =+'POA General Budget'!O73 -> 0 | ... R17: =+'POA General Budget'!U73 -> 0
A18: M&E - Airfare | B18: Travel | C18: 1 | D18: Trip | E18: =+'POA General Budget'!H74 -> 20 | F18: =+'POA General Budget'!I74 -> 363.30878 | G18: =+'POA General Budget'!J74 -> 7266.1757 | H18: =+'POA General Budget'!K74 -> 0 | I18: =+'POA General Budget'!L74 -> 0 | J18: =+'POA General Budget'!M74 -> 0 | K18: =+'POA General Budget'!N74 -> 0 | L18: =+'POA General Budget'!O74 -> 0 | ... R18: =+'POA General Budget'!U74 -> 7266.1757
A19: M&E - Lodging and M&IE - Field verification and data collection visits | B19: M&E | C19: 1 | D19: Day | E19: =+'POA General Budget'!H75 -> 40 | F19: =+'POA General Budget'!I75 -> 153.03504 | G19: =+'POA General Budget'!J75 -> 6121.4015 | H19: =+'POA General Budget'!K75 -> 0 | I19: =+'POA General Budget'!L75 -> 0 | J19: =+'POA General Budget'!M75 -> 0 | K19: =+'POA General Budget'!N75 -> 0 | L19: =+'POA General Budget'!O75 -> 0 | ... R19: =+'POA General Budget'!U75 -> 6121.4015
A20: M&E - Local transportation | B20: M&E | C20: 1 | D20: Day | E20: =+'POA General Budget'!H76 -> 40 | F20: =+'POA General Budget'!I76 -> 50 | G20: =+'POA General Budget'!J76 -> 2000 | H20: =+'POA General Budget'!K76 -> 0 | I20: =+'POA General Budget'!L76 -> 0 | J20: =+'POA General Budget'!M76 -> 0 | K20: =+'POA General Budget'!N76 -> 0 | L20: =+'POA General Budget'!O76 -> 0 | ... R20: =+'POA General Budget'!U76 -> 2000
A21: Contracts
A22: Interim Performance Evaluation | B22: M&E | C22: 1 | D22: Evaluation | E22: =+'POA General Budget'!H94 -> 0 | F22: =+'POA General Budget'!I94 -> 35000 | G22: =+'POA General Budget'!J94 -> 0 | H22: =+'POA General Budget'!K94 -> 0 | I22: =+'POA General Budget'!L94 -> 0 | J22: =+'POA General Budget'!M94 -> 1 | K22: =+'POA General Budget'!N94 -> 35000 | L22: =+'POA General Budget'!O94 -> 0 | ... R22: =+'POA General Budget'!U94 -> 35000
A23: Final Performance Evaluation | B23: M&E | C23: 1 | D23: Evaluation | E23: =+'POA General Budget'!H95 -> 0 | F23: =+'POA General Budget'!I95 -> 35000 | G23: =+'POA General Budget'!J95 -> 0 | H23: =+'POA General Budget'!K95 -> 0 | I23: =+'POA General Budget'!L95 -> 0 | J23: =+'POA General Budget'!M95 -> 0 | K23: =+'POA General Budget'!N95 -> 0 | L23: =+'POA General Budget'!O95 -> 0 | ... R23: =+'POA General Budget'!U95 -> 35000
A24: Other Direct Costs
A25: Monitoring, Evaluation, and Collection of Reliable Data
A26: 4.1 On-going M&E Training
A27: On-going M&E training workshops | B27: M&E | C27: 1 | D27: Workshop | E27: =+'POA General Budget'!H147 -> 2 | F27: =+'POA General Budget'!I147 -> 240 | G27: =+'POA General Budget'!J147 -> 480 | H27: =+'POA General Budget'!K147 -> 8 | I27: =+'POA General Budget'!L147 -> 1996.8 | J27: =+'POA General Budget'!M147 -> 8 | K27: =+'POA General Budget'!N147 -> 2076.672 | L27: =+'POA General Budget'!O147 -> 8 | ... R27: =+'POA General Budget'!U147 -> 6713.2109
A28: 4.2 Development of Performance Monitoring Plan (PMP)
A29: Document translation | B29: M&E | C29: 1 | D29: Document | E29: =+'POA General Budget'!H149 -> 1 | F29: =+'POA General Budget'!I149 -> 3500 | G29: =+'POA General Budget'!J149 -> 3500 | H29: =+'POA General Budget'!K149 -> 0 | I29: =+'POA General Budget'!L149 -> 0 | J29: =+'POA General Budget'!M149 -> 0 | K29: =+'POA General Budget'!N149 -> 0 | L29: =+'POA General Budget'!O149 -> 0 | ... R29: =+'POA General Budget'!U149 -> 3500
A30: 4.3 Stakeholder Engagement and Strategy Validation
A31: Workshops with Stakeholders to validate project strategies | B31: M&E | C31: 1 | D31: Workshop | E31: =+'POA General Budget'!H151 -> 30 | F31: =+'POA General Budget'!I151 -> 1360 | G31: =+'POA General Budget'!J151 -> 40800 | H31: =+'POA General Budget'!K151 -> 0 | I31: =+'POA General Budget'!L151 -> 0 | J31: =+'POA General Budget'!M151 -> 0 | K31: =+'POA General Budget'!N151 -> 0 | L31: =+'POA General Budget'!O151 -> 0 | ... R31: =+'POA General Budget'!U151 -> 40800
A32: Printing materials | B32: M&E | C32: 1 | D32: Unit | E32: =+'POA General Budget'!H152 -> 40 | F32: =+'POA General Budget'!I152 -> 50 | G32: =+'POA General Budget'!J152 -> 2000 | H32: =+'POA General Budget'!K152 -> 0 | I32: =+'POA General Budget'!L152 -> 0 | J32: =+'POA General Budget'!M152 -> 0 | K32: =+'POA General Budget'!N152 -> 0 | L32: =+'POA General Budget'!O152 -> 0 | ... R32: =+'POA General Budget'!U152 -> 2000
A33: 4.4 Consultants
A34: M&E - Consultant fees for Database development | B34: M&E | C34: 1 | D34: Hour | E34: =+'POA General Budget'!H154 -> 360 | F34: =+'POA General Budget'!I154 -> 25 | G34: =+'POA General Budget'!J154 -> 9000 | H34: =+'POA General Budget'!K154 -> 480 | I34: =+'POA General Budget'!L154 -> 12480 | J34: =+'POA General Budget'!M154 -> 480 | K34: =+'POA General Budget'!N154 -> 12979.2 | L34: =+'POA General Budget'!O154 -> 480 | ... R34: =+'POA General Budget'!U154 -> 47957.568
A35: M&E - Consultant fees to draft written PMP | B35: M&E | C35: 1 | D35: Hour | E35: =+'POA General Budget'!H155 -> 180 | F35: =+'POA General Budget'!I155 -> 25 | G35: =+'POA General Budget'!J155 -> 4500 | H35: =+'POA General Budget'!K155 -> 0 | I35: =+'POA General Budget'!L155 -> 0 | J35: =+'POA General Budget'!M155 -> 0 | K35: =+'POA General Budget'!N155 -> 0 | L35: =+'POA General Budget'!O155 -> 0 | ... R35: =+'POA General Budget'!U155 -> 4500
A36: Subtotal Partners of the Americas Monitoring, Evaluation, and Collection of Reliable Data | G36: =SUM(G12:G35) -> 101887.7 | I36: =SUM(I12:I35) -> 55380.193 | K36: =SUM(K12:K35) -> 85505.479 | M36: =SUM(M12:M35) -> 52525.698 | O36: =SUM(O12:O35) -> 35000 | P36: =SUM(P12:P35) -> 330299.07 | Q36: =SUM(Q12:Q35) -> 0 | R36: =SUM(R12:R35) -> 330299.07
A37: FES Monitoring, Evaluation, and Collection of Reliable Data
A38: Travel
A39: M&E - Airfare - Field Verification & Data Collection Expenses | B39: Travel | C39: 1 | D39: Trip | E39: =+'FES Sub Budget'!E24 -> 0 | F39: =+'FES Sub Budget'!F24 -> 363.30878 | G39: =+'FES Sub Budget'!G24 -> 0 | H39: =+'FES Sub Budget'!H24 -> 14 | I39: =+'FES Sub Budget'!I24 -> 5086.323 | J39: =+'FES Sub Budget'!J24 -> 14 | K39: =+'FES Sub Budget'!K24 -> 5289.7759 | L39: =+'FES Sub Budget'!L24 -> 7 | ... R39: =+'FES Sub Budget'!R24 -> 13126.782
A40: M&E - Lodging and M&IE - Field Verification & Data Collection Expenses | B40: Travel | C40: 1 | D40: Day | E40: =+'FES Sub Budget'!E25 -> 0 | F40: =+'FES Sub Budget'!F25 -> 153.03504 | G40: =+'FES Sub Budget'!G25 -> 0 | H40: =+'FES Sub Budget'!H25 -> 14 | I40: =+'FES Sub Budget'!I25 -> 2142.4905 | J40: =+'FES Sub Budget'!J25 -> 14 | K40: =+'FES Sub Budget'!K25 -> 2228.1902 | L40: =+'FES Sub Budget'!L25 -> 7 | ... R40: =+'FES Sub Budget'!R25 -> 5529.3396
A41: M&E - Transportation - Field Verification & Data Collection Expenses | B41: Travel | C41: 1 | D41: Day | E41: =+'FES Sub Budget'!E26 -> 0 | F41: =+'FES Sub Budget'!F26 -> 50 | G41: =+'FES Sub Budget'!G26 -> 0 | H41: =+'FES Sub Budget'!H26 -> 14 | I41: =+'FES Sub Budget'!I26 -> 700 | J41: =+'FES Sub Budget'!J26 -> 14 | K41: =+'FES Sub Budget'!K26 -> 728 | L41: =+'FES Sub Budget'!L26 -> 7 | ... R41: =+'FES Sub Budget'!R26 -> 1806.56
A42: Subtotal FES Monitoring, Evaluation, and Collection of Reliable Data | G42: =SUM(G38:G41) -> 0 | I42: =SUM(I38:I41) -> 7928.8135 | K42: =SUM(K38:K41) -> 8245.9661 | M42: =SUM(M38:M41) -> 4287.9023 | O42: =SUM(O38:O41) -> 0 | P42: =SUM(P38:P41) -> 20462.682 | Q42: =SUM(Q38:Q41) -> 0 | R42: =SUM(R38:R41) -> 20462.682
A43: ITAM Monitoring, Evaluation, and Collection of Reliable Data
A44: Travel
A45: Travel Expenses for M&E Baja California
A46: Lodging | B46: Travel | C46: 1 | D46: Night | E46: =+'ITAM Sub Budget'!E42 -> 0 | F46: =+'ITAM Sub Budget'!F42 -> 182 | G46: =+'ITAM Sub Budget'!G42 -> 0 | H46: =+'ITAM Sub Budget'!H42 -> 0 | I46: =+'ITAM Sub Budget'!I42 -> 0 | J46: =+'ITAM Sub Budget'!J42 -> 4 | K46: =+'ITAM Sub Budget'!K42 -> 787.4048 | L46: =+'ITAM Sub Budget'!L42 -> 4 | ... R46: =+'ITAM Sub Budget'!R42 -> 1606.3058
A47: Per Diem | B47: Travel | C47: 1 | D47: Day | E47: =+'ITAM Sub Budget'!E43 -> 0 | F47: =+'ITAM Sub Budget'!F43 -> 116 | G47: =+'ITAM Sub Budget'!G43 -> 0 | H47: =+'ITAM Sub Budget'!H43 -> 0 | I47: =+'ITAM Sub Budget'!I43 -> 0 | J47: =+'ITAM Sub Budget'!J43 -> 4 | K47: =+'ITAM Sub Budget'!K43 -> 501.8624 | L47: =+'ITAM Sub Budget'!L43 -> 4 | ... R47: =+'ITAM Sub Budget'!R43 -> 1023.7993
A48: Local Transportation | B48: Travel | C48: 1 | D48: Day | E48: =+'ITAM Sub Budget'!E44 -> 0 | F48: =+'ITAM Sub Budget'!F44 -> 50 | G48: =+'ITAM Sub Budget'!G44 -> 0 | H48: =+'ITAM Sub Budget'!H44 -> 0 | I48: =+'ITAM Sub Budget'!I44 -> 0 | J48: =+'ITAM Sub Budget'!J44 -> 2 | K48: =+'ITAM Sub Budget'!K44 -> 108.16 | L48: =+'ITAM Sub Budget'!L44 -> 2 | ... R48: =+'ITAM Sub Budget'!R44 -> 220.6464
A49: Airfare | B49: Travel | C49: 1 | D49: Trip | E49: =+'ITAM Sub Budget'!E45 -> 0 | F49: =+'ITAM Sub Budget'!F45 -> 500 | G49: =+'ITAM Sub Budget'!G45 -> 0 | H49: =+'ITAM Sub Budget'!H45 -> 0 | I49: =+'ITAM Sub Budget'!I45 -> 0 | J49: =+'ITAM Sub Budget'!J45 -> 2 | K49: =+'ITAM Sub Budget'!K45 -> 1081.6 | L49: =+'ITAM Sub Budget'!L45 -> 2 | ... R49: =+'ITAM Sub Budget'!R45 -> 2206.464
A50: Travel Expenses for M&E Jalisco
A51: Lodging | B51: Travel | C51: 1 | D51: Night | E51: =+'ITAM Sub Budget'!E47 -> 0 | F51: =+'ITAM Sub Budget'!F47 -> 241 | G51: =+'ITAM Sub Budget'!G47 -> 0 | H51: =+'ITAM Sub Budget'!H47 -> 0 | I51: =+'ITAM Sub Budget'!I47 -> 0 | J51: =+'ITAM Sub Budget'!J47 -> 4 | K51: =+'ITAM Sub Budget'!K47 -> 1042.6624 | L51: =+'ITAM Sub Budget'!L47 -> 4 | ... R51: =+'ITAM Sub Budget'!R47 -> 2127.0313
A52: Per Diem | B52: Travel | C52: 1 | D52: Day | E52: =+'ITAM Sub Budget'!E48 -> 0 | F52: =+'ITAM Sub Budget'!F48 -> 121 | G52: =+'ITAM Sub Budget'!G48 -> 0 | H52: =+'ITAM Sub Budget'!H48 -> 0 | I52: =+'ITAM Sub Budget'!I48 -> 0 | J52: =+'ITAM Sub Budget'!J48 -> 4 | K52: =+'ITAM Sub Budget'!K48 -> 523.4944 | L52: =+'ITAM Sub Budget'!L48 -> 4 | ... R52: =+'ITAM Sub Budget'!R48 -> 1067.9286
A53: Local Transportation | B53: Travel | C53: 1 | D53: Day | E53: =+'ITAM Sub Budget'!E49 -> 0 | F53: =+'ITAM Sub Budget'!F49 -> 50 | G53: =+'ITAM Sub Budget'!G49 -> 0 | H53: =+'ITAM Sub Budget'!H49 -> 0 | I53: =+'ITAM Sub Budget'!I49 -> 0 | J53: =+'ITAM Sub Budget'!J49 -> 2 | K53: =+'ITAM Sub Budget'!K49 -> 108.16 | L53: =+'ITAM Sub Budget'!L49 -> 2 | ... R53: =+'ITAM Sub Budget'!R49 -> 220.6464
A54: Airfare | B54: Travel | C54: 1 | D54: Trip | E54: =+'ITAM Sub Budget'!E50 -> 0 | F54: =+'ITAM Sub Budget'!F50 -> 300 | G54: =+'ITAM Sub Budget'!G50 -> 0 | H54: =+'ITAM Sub Budget'!H50 -> 0 | I54: =+'ITAM Sub Budget'!I50 -> 0 | J54: =+'ITAM Sub Budget'!J50 -> 2 | K54: =+'ITAM Sub Budget'!K50 -> 648.96 | L54: =+'ITAM Sub Budget'!L50 -> 2 | ... R54: =+'ITAM Sub Budget'!R50 -> 1323.8784
A55: Travel Expenses for M&E Guanajuato
A56: Lodging | B56: Travel | C56: 1 | D56: Night | E56: =+'ITAM Sub Budget'!E52 -> 0 | F56: =+'ITAM Sub Budget'!F52 -> 141 | G56: =+'ITAM Sub Budget'!G52 -> 0 | H56: =+'ITAM Sub Budget'!H52 -> 0 | I56: =+'ITAM Sub Budget'!I52 -> 0 | J56: =+'ITAM Sub Budget'!J52 -> 4 | K56: =+'ITAM Sub Budget'!K52 -> 610.0224 | L56: =+'ITAM Sub Budget'!L52 -> 4 | ... R56: =+'ITAM Sub Budget'!R52 -> 1244.4457
A57: Per Diem | B57: Travel | C57: 1 | D57: Day | E57: =+'ITAM Sub Budget'!E53 -> 0 | F57: =+'ITAM Sub Budget'!F53 -> 110 | G57: =+'ITAM Sub Budget'!G53 -> 0 | H57: =+'ITAM Sub Budget'!H53 -> 0 | I57: =+'ITAM Sub Budget'!I53 -> 0 | J57: =+'ITAM Sub Budget'!J53 -> 4 | K57: =+'ITAM Sub Budget'!K53 -> 475.904 | L57: =+'ITAM Sub Budget'!L53 -> 4 | ... R57: =+'ITAM Sub Budget'!R53 -> 970.84416
A58: Local Transportation | B58: Travel | C58: 1 | D58: Day | E58: =+'ITAM Sub Budget'!E54 -> 0 | F58: =+'ITAM Sub Budget'!F54 -> 50 | G58: =+'ITAM Sub Budget'!G54 -> 0 | H58: =+'ITAM Sub Budget'!H54 -> 0 | I58: =+'ITAM Sub Budget'!I54 -> 0 | J58: =+'ITAM Sub Budget'!J54 -> 2 | K58: =+'ITAM Sub Budget'!K54 -> 108.16 | L58: =+'ITAM Sub Budget'!L54 -> 2 | ... R58: =+'ITAM Sub Budget'!R54 -> 220.6464
A59: Airfare | B59: Travel | C59: 1 | D59: Trip | E59: =+'ITAM Sub Budget'!E55 -> 0 | F59: =+'ITAM Sub Budget'!F55 -> 450 | G59: =+'ITAM Sub Budget'!G55 -> 0 | H59: =+'ITAM Sub Budget'!H55 -> 0 | I59: =+'ITAM Sub Budget'!I55 -> 0 | J59: =+'ITAM Sub Budget'!J55 -> 2 | K59: =+'ITAM Sub Budget'!K55 -> 973.44 | L59: =+'ITAM Sub Budget'!L55 -> 2 | ... R59: =+'ITAM Sub Budget'!R55 -> 1985.8176
A60: Travel Expenses for M&E Querétaro
A61: Lodging | B61: Travel | C61: 1 | D61: Night | E61: =+'ITAM Sub Budget'!E57 -> 0 | F61: =+'ITAM Sub Budget'!F57 -> 210 | G61: =+'ITAM Sub Budget'!G57 -> 0 | H61: =+'ITAM Sub Budget'!H57 -> 0 | I61: =+'ITAM Sub Budget'!I57 -> 0 | J61: =+'ITAM Sub Budget'!J57 -> 4 | K61: =+'ITAM Sub Budget'!K57 -> 908.544 | L61: =+'ITAM Sub Budget'!L57 -> 4 | ... R61: =+'ITAM Sub Budget'!R57 -> 1853.4298
A62: Per Diem | B62: Travel | C62: 1 | D62: Day | E62: =+'ITAM Sub Budget'!E58 -> 0 | F62: =+'ITAM Sub Budget'!F58 -> 123 | G62: =+'ITAM Sub Budget'!G58 -> 0 | H62: =+'ITAM Sub Budget'!H58 -> 0 | I62: =+'ITAM Sub Budget'!I58 -> 0 | J62: =+'ITAM Sub Budget'!J58 -> 4 | K62: =+'ITAM Sub Budget'!K58 -> 532.1472 | L62: =+'ITAM Sub Budget'!L58 -> 4 | ... R62: =+'ITAM Sub Budget'!R58 -> 1085.5803
A63: Local Transportation | B63: Travel | C63: 1 | D63: Day | E63: =+'ITAM Sub Budget'!E59 -> 0 | F63: =+'ITAM Sub Budget'!F59 -> 50 | G63: =+'ITAM Sub Budget'!G59 -> 0 | H63: =+'ITAM Sub Budget'!H59 -> 0 | I63: =+'ITAM Sub Budget'!I59 -> 0 | J63: =+'ITAM Sub Budget'!J59 -> 2 | K63: =+'ITAM Sub Budget'!K59 -> 108.16 | L63: =+'ITAM Sub Budget'!L59 -> 2 | ... R63: =+'ITAM Sub Budget'!R59 -> 220.6464
A64: Airfare | B64: Travel | C64: 1 | D64: Trip | E64: =+'ITAM Sub Budget'!E60 -> 0 | F64: =+'ITAM Sub Budget'!F60 -> 150 | G64: =+'ITAM Sub Budget'!G60 -> 0 | H64: =+'ITAM Sub Budget'!H60 -> 0 | I64: =+'ITAM Sub Budget'!I60 -> 0 | J64: =+'ITAM Sub Budget'!J60 -> 2 | K64: =+'ITAM Sub Budget'!K60 -> 324.48 | L64: =+'ITAM Sub Budget'!L60 -> 2 | ... R64: =+'ITAM Sub Budget'!R60 -> 661.9392
A65: Contractual
A66: Institutional Liaison Coordinator (M&E Activities) | B66: Contract | C66: 0.5 | D66: Month | E66: =+'ITAM Sub Budget'!E89 -> 0 | F66: =+'ITAM Sub Budget'!F89 -> 2800 | G66: =+'ITAM Sub Budget'!G89 -> 0 | H66: =+'ITAM Sub Budget'!H89 -> 6 | I66: =+'ITAM Sub Budget'!I89 -> 8736 | J66: =+'ITAM Sub Budget'!J89 -> 6 | K66: =+'ITAM Sub Budget'!K89 -> 9085.44 | L66: =+'ITAM Sub Budget'!L89 -> 6 | ... R66: =+'ITAM Sub Budget'!R89 -> 27270.298
A67: Senior Data Analyst (M&E Activities) | B67: Contract | C67: 0.6 | D67: Month | E67: =+'ITAM Sub Budget'!E90 -> 0 | F67: =+'ITAM Sub Budget'!F90 -> 2600 | G67: =+'ITAM Sub Budget'!G90 -> 0 | H67: =+'ITAM Sub Budget'!H90 -> 0 | I67: =+'ITAM Sub Budget'!I90 -> 0 | J67: =+'ITAM Sub Budget'!J90 -> 3 | K67: =+'ITAM Sub Budget'!K90 -> 5061.888 | L67: =+'ITAM Sub Budget'!L90 -> 3 | ... R67: =+'ITAM Sub Budget'!R90 -> 10326.252
A68: Junior Data Analyst (M&E Activities) | B68: Contract | C68: 1 | D68: Month | E68: =+'ITAM Sub Budget'!E91 -> 0 | F68: =+'ITAM Sub Budget'!F91 -> 1590 | G68: =+'ITAM Sub Budget'!G91 -> 0 | H68: =+'ITAM Sub Budget'!H91 -> 0 | I68: =+'ITAM Sub Budget'!I91 -> 0 | J68: =+'ITAM Sub Budget'!J91 -> 3 | K68: =+'ITAM Sub Budget'!K91 -> 5159.232 | L68: =+'ITAM Sub Budget'!L91 -> 3 | ... R68: =+'ITAM Sub Budget'!R91 -> 10524.833
A69: Senior Legal Analyst (M&E Activities) | B69: Contract | C69: 1 | D69: Month | E69: =+'ITAM Sub Budget'!E92 -> 0 | F69: =+'ITAM Sub Budget'!F92 -> 3070 | G69: =+'ITAM Sub Budget'!G92 -> 0 | H69: =+'ITAM Sub Budget'!H92 -> 6 | I69: =+'ITAM Sub Budget'!I92 -> 19156.8 | J69: =+'ITAM Sub Budget'!J92 -> 6 | K69: =+'ITAM Sub Budget'!K92 -> 19923.072 | L69: =+'ITAM Sub Budget'!L92 -> 6 | ... R69: =+'ITAM Sub Budget'!R92 -> 59799.867
A70: Subtotal ITAM Monitoring, Evaluation, and Collection of Reliable Data | G70: =SUM(G43:G69) -> 0 | I70: =SUM(I43:I69) -> 27892.8 | K70: =SUM(K43:K69) -> 48072.794 | M70: =SUM(M43:M69) -> 49995.705 | O70: =SUM(O43:O69) -> 0 | P70: =SUM(P43:P69) -> 125961.3 | Q70: =SUM(Q43:Q69) -> 0 | R70: =SUM(R43:R69) -> 125961.3
A72: Total Monitoring, Evaluation, and Collection of Reliable Data | G72: =SUM(G36,G42,G70) -> 101887.7 | I72: =SUM(I36,I42,I70) -> 91201.806 | K72: =SUM(K36,K42,K70) -> 141824.24 | M72: =SUM(M36,M42,M70) -> 106809.31 | O72: =SUM(O36,O42,O70) -> 35000 | P72: =SUM(P36,P42,P70) -> 476723.05 | Q72: =SUM(Q36,Q42,Q70) -> 0 | R72: =SUM(R36,R42,R70) -> 476723.05 | S72: =R72/'POA General Budget'!U160 -> 0.053359563

Sheet ITAM Sub Budget Summary
A3: Project Budget Summary
A4: Partners of the Americas
A5: Instituto Tecnológico Autónomo de México (ITAM) Sub-Recipient / Sub-receptor Instituto Tecnológico Autónomo de México (ITAM) (UEI: DP38M16THBJ6)
A6: 42 Months
A8: BUDGET SUMMARY CATEGORIES | B8: YEAR 1 | C8: YEAR 2 | D8: YEAR 3 | E8: YEAR 4 | F8: YEAR 5 | G8: TOTAL FEDERAL FUNDS REQUESTED
A10: 1. PERSONNEL | B10: =+'ITAM Sub Budget'!G14 -> 51600 | C10: =+'ITAM Sub Budget'!I14 -> 108360 | D10: =+'ITAM Sub Budget'!K14 -> 113778 | E10: =+'ITAM Sub Budget'!M14 -> 119466.9 | F10: =+'ITAM Sub Budget'!O14 -> 0 | G10: =SUM(B10:F10) -> 393204.9
A11: 2. FRINGE BENEFITS | B11: =+'ITAM Sub Budget'!G17 -> 14504.28 | C11: =+'ITAM Sub Budget'!I17 -> 30458.988 | D11: =+'ITAM Sub Budget'!K17 -> 31981.937 | E11: =+'ITAM Sub Budget'!M17 -> 33581.034 | F11: =+'ITAM Sub Budget'!O17 -> 0 | G11: =SUM(B11:F11) -> 110526.24
A12: 3. TRAVEL | B12: =+'ITAM Sub Budget'!G61 -> 4088 | C12: =+'ITAM Sub Budget'!I61 -> 8503.04 | D12: =+'ITAM Sub Budget'!K61 -> 8843.1616 | E12: =+'ITAM Sub Budget'!M61 -> 9196.8881 | F12: =+'ITAM Sub Budget'!O61 -> 0 | G12: =SUM(B12:F12) -> 30631.09
A13: 4. EQUIPMENT | B13: =+'ITAM Sub Budget'!G64 -> 0 | C13: =+'ITAM Sub Budget'!I64 -> 0 | D13: =+'ITAM Sub Budget'!K64 -> 0 | E13: =+'ITAM Sub Budget'!M64 -> 0 | F13: =+'ITAM Sub Budget'!O64 -> 0 | G13: =SUM(B13:F13) -> 0
A14: 5. SUPPLIES | B14: =+'ITAM Sub Budget'!G67 -> 0 | C14: =+'ITAM Sub Budget'!I67 -> 0 | D14: =+'ITAM Sub Budget'!K67 -> 0 | E14: =+'ITAM Sub Budget'!M67 -> 0 | F14: =+'ITAM Sub Budget'!O67 -> 0 | G14: =SUM(B14:F14) -> 0
A15: 6. CONTRACTUAL | B15: =+'ITAM Sub Budget'!G93 -> 131694.3 | C15: =+'ITAM Sub Budget'!I93 -> 680597.63 | D15: =+'ITAM Sub Budget'!K93 -> 592752.71 | E15: =+'ITAM Sub Budget'!M93 -> 378112.91 | F15: =+'ITAM Sub Budget'!O93 -> 0 | G15: =SUM(B15:F15) -> 1783157.6
A16: 7. CONSTRUCTION | B16: =+'ITAM Sub Budget'!G96 -> 0 | C16: =+'ITAM Sub Budget'!I96 -> 0 | D16: =+'ITAM Sub Budget'!K96 -> 0 | E16: =+'ITAM Sub Budget'!M96 -> 0 | F16: =+'ITAM Sub Budget'!O96 -> 0 | G16: =SUM(B16:F16) -> 0
A17: 8. OTHER DIRECT COSTS | B17: =+'ITAM Sub Budget'!G106 -> 11400 | C17: =+'ITAM Sub Budget'!I106 -> 23712 | D17: =+'ITAM Sub Budget'!K106 -> 24660.48 | E17: =+'ITAM Sub Budget'!M106 -> 12823.45 | F17: =+'ITAM Sub Budget'!O106 -> 0 | G17: =SUM(B17:F17) -> 72595.93
A19: 9. TOTAL DIRECT COSTS (Lines 1-8) | B19: =SUM(B10:B17) -> 213286.58 | C19: =SUM(C10:C17) -> 851631.66 | D19: =SUM(D10:D17) -> 772016.29 | E19: =SUM(E10:E17) -> 553181.18 | F19: =SUM(F10:F17) -> 0 | G19: =SUM(G10:G17) -> 2390115.7
A20: 10. DE MINIMIS RATE | B20: =+B19*0.1 -> 21328.658 | C20: =+C19*0.1 -> 85163.166 | D20: =+D19*0.1 -> 77201.629 | E20: =+E19*0.1 -> 55318.118 | F20: =+F19*0.1 -> 0 | G20: =SUM(B20:F20) -> 239011.57
A21: 11. TOTAL COSTS (Lines 9-10) | B21: =SUM(B19:B20) -> 234615.24 | C21: =SUM(C19:C20) -> 936794.83 | D21: =SUM(D19:D20) -> 849217.92 | E21: =SUM(E19:E20) -> 608499.3 | F21: =SUM(F19:F20) -> 0 | G21: =SUM(G19:G20) -> 2629127.3

Sheet ITAM Sub Budget
A1: Project Line-Item Budget
A2: Instituto Tecnológico Autónomo de México (ITAM) Sub-Recipient / Sub-receptor Instituto Tecnológico Autónomo de México (ITAM) (UEI: DP38M16THBJ6)
A3: 42 Months
A4: Cost Assumptions
A5: Inflation - Goods/Services | B5: 1.04
A6: Merit Based Increases for HO & Field Staff | B6: 1.05
A8: BUDGET ITEM | B8: CATEGORY | C8: LOE | D8: UNIT | E8: # of Units | F8: RATE / UNIT | G8: Year 1 | H8: # of Units | I8: Year 2 | J8: # of Units | K8: Year 3 | L8: # of Units | M8: Year 4 | N8: # of Units | O8: Year 5 | P8: TOTAL US$ | Q8: TOTAL COST SHARING | R8: PROJECT GRAND TOTAL
A9: Personnel
A10: Professional Personnel
A11: Technical Director | B11: Salaries | C11: 0.2 | D11: Month | E11: 6 | F11: 12000 | G11: =F11*$E11*$C11 -> 14400 | H11: 12 | I11: =H11*$F11*$C11*$B$6 -> 30240 | J11: 12 | K11: =J11*$F11*$C11*$B$6*$B$6 -> 31752 | L11: 12 | M11: =L11*$F11*$C11*$B$6*$B$6*$B$6 -> 33339.6 | O11: =N11*$F11*$B$6*$B$6*$B$6*$B$6*20% -> 0 | P11: =SUM(G11,I11,K11,M11,O11) -> 109731.6 | Q11: 0 | R11: =SUM(P11:Q11) -> 109731.6
A12: Project Manager | B12: Salaries | C12: 1 | D12: Month | E12: 6 | F12: 2900 | G12: =F12*$E12*C12 -> 17400 | H12: 12 | I12: =H12*$F12*$C12*$B$6 -> 36540 | J12: 12 | K12: =J12*$F12*$C12*$B$6*$B$6 -> 38367 | L12: 12 | M12: =L12*$F12*$C12*$B$6*$B$6*$B$6 -> 40285.35 | O12: =N12*$F12*$C12*$B$6*$B$6*$B$6*$B$6 -> 0 | P12: =SUM(G12,I12,K12,M12,O12) -> 132592.35 | Q12: 0 | R12: =SUM(P12:Q12) -> 132592.35
A13: Product Manager | B13: Salaries | C13: 1 | D13: Month | E13: 6 | F13: 3300 | G13: =F13*$E13*C13 -> 19800 | H13: 12 | I13: =H13*$F13*$C13*$B$6 -> 41580 | J13: 12 | K13: =J13*$F13*$C13*$B$6*$B$6 -> 43659 | L13: 12 | M13: =L13*$F13*$C13*$B$6*$B$6*$B$6 -> 45841.95 | O13: =N13*$F13*$C13*$B$6*$B$6*$B$6*$B$6 -> 0 | P13: =SUM(G13,I13,K13,M13,O13) -> 150880.95 | Q13: 0 | R13: =SUM(P13:Q13) -> 150880.95
A14: Total Personnel | G14: =SUM(G11:G13) -> 51600 | I14: =SUM(I11:I13) -> 108360 | K14: =SUM(K11:K13) -> 113778 | M14: =SUM(M11:M13) -> 119466.9 | O14: =SUM(O11:O13) -> 0 | P14: =SUM(P11:P13) -> 393204.9 | Q14: =SUM(Q11:Q13) -> 0 | R14: =SUM(R11:R13) -> 393204.9
A15: Fringe Benefits
A16: Fringe Benefits - Mexico | B16: Fringe Benefits | D16: Month | F16: 0.3899 | G16: =SUM(G12:G13)*F16 -> 14504.28 | H16: =+F16 -> 0.3899 | I16: =SUM(I12:I13)*H16 -> 30458.988 | J16: =+H16 -> 0.3899 | K16: =SUM(K12:K13)*J16 -> 31981.937 | L16: =+J16 -> 0.3899 | M16: =SUM(M12:M13)*L16 -> 33581.034 | N16: =+L16 -> 0.3899 | O16: =SUM(O11:O13)*N16 -> 0 | P16: =SUM(G16,I16,K16,M16,O16) -> 110526.24 | Q16: 0 | R16: =SUM(P16:Q16) -> 110526.24
A17: Total Fringe Benefits | G17: =SUM(G16:G16) -> 14504.28 | I17: =SUM(I16:I16) -> 30458.988 | K17: =SUM(K16:K16) -> 31981.937 | M17: =SUM(M16:M16) -> 33581.034 | O17: =SUM(O16:O16) -> 0 | P17: =SUM(P16:P16) -> 110526.24 | Q17: =SUM(Q16:Q16) -> 0 | R17: =SUM(R16:R16) -> 110526.24
A18: Travel
A19: Country travel
A20: Travel Expenses Baja California (Mexicali)
A21: Lodging | B21: Travel | C21: 1 | D21: Night | E21: 2 | F21: 182 | G21: =F21*$E21*C21 -> 364 | H21: =2*2 -> 4 | I21: =H21*$F21*$C21*$B$5 -> 757.12 | K21: =J21*$F21*$C21*$B$5*$B$5 -> 0 | M21: =L21*$F21*$C21*$B$5*$B$5*$B$5 -> 0 | N21: 0 | O21: =N21*$F21*$C21*$B$5*$B$5*$B$5*$B$5 -> 0 | P21: =SUM(G21,I21,K21,M21,O21) -> 1121.12 | Q21: 0 | R21: =SUM(P21:Q21) -> 1121.12
A22: Per Diem | B22: Travel | C22: 1 | D22: Day | E22: 2 | F22: 116 | G22: =F22*$E22*C22 -> 232 | H22: =2*2 -> 4 | I22: =H22*$F22*$C22*$B$5 -> 482.56 | K22: =J22*$F22*$C22*$B$5*$B$5 -> 0 | M22: =L22*$F22*$C22*$B$5*$B$5*$B$5 -> 0 | O22: =N22*$F22*$C22*$B$5*$B$5*$B$5*$B$5 -> 0 | P22: =SUM(G22,I22,K22,M22,O22) -> 714.56 | Q22: 0 | R22: =SUM(P22:Q22) -> 714.56
A23: Local Transportation | B23: Travel | C23: 1 | D23: Day | E23: 1 | F23: 50 | G23: =F23*$E23*C23 -> 50 | H23: =2*1 -> 2 | I23: =H23*$F23*$C23*$B$5 -> 104 | K23: =J23*$F23*$C23*$B$5*$B$5 -> 0 | M23: =L23*$F23*$C23*$B$5*$B$5*$B$5 -> 0 | N23: 0 | O23: =N23*$F23*$C23*$B$5*$B$5*$B$5*$B$5 -> 0 | P23: =SUM(G23,I23,K23,M23,O23) -> 154 | Q23: 0 | R23: =SUM(P23:Q23) -> 154
A24: Airfare | B24: Travel | C24: 1 | D24: Trip | E24: 1 | F24: 500 | G24: =F24*$E24*C24 -> 500 | H24: =1*2 -> 2 | I24: =H24*$F24*$C24*$B$5 -> 1040 | K24: =J24*$F24*$C24*$B$5*$B$5 -> 0 | M24: =L24*$F24*$C24*$B$5*$B$5*$B$5 -> 0 | N24: 0 | O24: =N24*$F24*$C24*$B$5*$B$5*$B$5*$B$5 -> 0 | P24: =SUM(G24,I24,K24,M24,O24) -> 1540 | Q24: 0 | R24: =SUM(P24:Q24) -> 1540
A25: Travel Expenses Jalisco (Guadalajara)
A26: Lodging | B26: Travel | C26: 1 | D26: Night | E26: 2 | F26: 241 | G26: =F26*$E26*C26 -> 482 | H26: =2*2 -> 4 | I26: =H26*$F26*$C26*$B$5 -> 1002.56 | K26: =J26*$F26*$C26*$B$5*$B$5 -> 0 | M26: =L26*$F26*$C26*$B$5*$B$5*$B$5 -> 0 | N26: 0 | O26: =N26*$F26*$C26*$B$5*$B$5*$B$5*$B$5 -> 0 | P26: =SUM(G26,I26,K26,M26,O26) -> 1484.56 | Q26: 0 | R26: =SUM(P26:Q26) -> 1484.56
A27: Per Diem | B27: Travel | C27: 1 | D27: Day | E27: 2 | F27: 121 | G27: =F27*$E27*C27 -> 242 | H27: =2*2 -> 4 | I27: =H27*$F27*$C27*$B$5 -> 503.36 | K27: =J27*$F27*$C27*$B$5*$B$5 -> 0 | M27: =L27*$F27*$C27*$B$5*$B$5*$B$5 -> 0 | O27: =N27*$F27*$C27*$B$5*$B$5*$B$5*$B$5 -> 0 | P27: =SUM(G27,I27,K27,M27,O27) -> 745.36 | Q27: 0 | R27: =SUM(P27:Q27) -> 745.36
A28: Local Transportation | B28: Travel | C28: 1 | D28: Day | E28: 1 | F28: 50 | G28: =F28*$E28*C28 -> 50 | H28: =2*1 -> 2 | I28: =H28*$F28*$C28*$B$5 -> 104 | K28: =J28*$F28*$C28*$B$5*$B$5 -> 0 | M28: =L28*$F28*$C28*$B$5*$B$5*$B$5 -> 0 | N28: 0 | O28: =N28*$F28*$C28*$B$5*$B$5*$B$5*$B$5 -> 0 | P28: =SUM(G28,I28,K28,M28,O28) -> 154 | Q28: 0 | R28: =SUM(P28:Q28) -> 154
A29: Airfare | B29: Travel | C29: 1 | D29: Trip | E29: 1 | F29: 300 | G29: =F29*$E29*C29 -> 300 | H29: =1*2 -> 2 | I29: =H29*$F29*$C29*$B$5 -> 624 | K29: =J29*$F29*$C29*$B$5*$B$5 -> 0 | M29: =L29*$F29*$C29*$B$5*$B$5*$B$5 -> 0 | N29: 0 | O29: =N29*$F29*$C29*$B$5*$B$5*$B$5*$B$5 -> 0 | P29: =SUM(G29,I29,K29,M29,O29) -> 924 | Q29: 0 | R29: =SUM(P29:Q29) -> 924
A30: Travel Expenses Guanajuato (Other)
A31: Lodging | B31: Travel | C31: 1 | D31: Night | E31: 2 | F31: 141 | G31: =F31*$E31*C31 -> 282 | H31: =2*2 -> 4 | I31: =H31*$F31*$C31*$B$5 -> 586.56 | K31: =J31*$F31*$C31*$B$5*$B$5 -> 0 | M31: =L31*$F31*$C31*$B$5*$B$5*$B$5 -> 0 | N31: 0 | O31: =N31*$F31*$C31*$B$5*$B$5*$B$5*$B$5 -> 0 | P31: =SUM(G31,I31,K31,M31,O31) -> 868.56 | Q31: 0 | R31: =SUM(P31:Q31) -> 868.56
A32: Per Diem | B32: Travel | C32: 1 | D32: Day | E32: 2 | F32: 110 | G32: =F32*$E32*C32 -> 220 | H32: =2*2 -> 4 | I32: =H32*$F32*$C32*$B$5 -> 457.6 | K32: =J32*$F32*$C32*$B$5*$B$5 -> 0 | M32: =L32*$F32*$C32*$B$5*$B$5*$B$5 -> 0 | O32: =N32*$F32*$C32*$B$5*$B$5*$B$5*$B$5 -> 0 | P32: =SUM(G32,I32,K32,M32,O32) -> 677.6 | Q32: 0 | R32: =SUM(P32:Q32) -> 677.6
A33: Local Transportation | B33: Travel | C33: 1 | D33: Day | E33: 1 | F33: 50 | G33: =F33*$E33*C33 -> 50 | H33: =2*1 -> 2 | I33: =H33*$F33*$C33*$B$5 -> 104 | K33: =J33*$F33*$C33*$B$5*$B$5 -> 0 | M33: =L33*$F33*$C33*$B$5*$B$5*$B$5 -> 0 | N33: 0 | O33: =N33*$F33*$C33*$B$5*$B$5*$B$5*$B$5 -> 0 | P33: =SUM(G33,I33,K33,M33,O33) -> 154 | Q33: 0 | R33: =SUM(P33:Q33) -> 154
A34: Airfare | B34: Travel | C34: 1 | D34: Trip | E34: 1 | F34: 450 | G34: =F34*$E34*C34 -> 450 | H34: =1*2 -> 2 | I34: =H34*$F34*$C34*$B$5 -> 936 | K34: =J34*$F34*$C34*$B$5*$B$5 -> 0 | M34: =L34*$F34*$C34*$B$5*$B$5*$B$5 -> 0 | N34: 0 | O34: =N34*$F34*$C34*$B$5*$B$5*$B$5*$B$5 -> 0 | P34: =SUM(G34,I34,K34,M34,O34) -> 1386 | Q34: 0 | R34: =SUM(P34:Q34) -> 1386
A35: Travel Expenses Querétaro
A36: Lodging | B36: Travel | C36: 1 | D36: Night | E36: 2 | F36: 210 | G36: =F36*$E36*C36 -> 420 | H36: =2*2 -> 4 | I36: =H36*$F36*$C36*$B$5 -> 873.6 | K36: =J36*$F36*$C36*$B$5*$B$5 -> 0 | M36: =L36*$F36*$C36*$B$5*$B$5*$B$5 -> 0 | N36: 0 | O36: =N36*$F36*$C36*$B$5*$B$5*$B$5*$B$5 -> 0 | P36: =SUM(G36,I36,K36,M36,O36) -> 1293.6 | Q36: 0 | R36: =SUM(P36:Q36) -> 1293.6
A37: Per Diem | B37: Travel | C37: 1 | D37: Day | E37: 2 | F37: 123 | G37: =F37*$E37*C37 -> 246 | H37: =2*2 -> 4 | I37: =H37*$F37*$C37*$B$5 -> 511.68 | K37: =J37*$F37*$C37*$B$5*$B$5 -> 0 | M37: =L37*$F37*$C37*$B$5*$B$5*$B$5 -> 0 | O37: =N37*$F37*$C37*$B$5*$B$5*$B$5*$B$5 -> 0 | P37: =SUM(G37,I37,K37,M37,O37) -> 757.68 | Q37: 0 | R37: =SUM(P37:Q37) -> 757.68
A38: Local Transportation | B38: Travel | C38: 1 | D38: Day | E38: 1 | F38: 50 | G38: =F38*$E38*C38 -> 50 | H38: =2*1 -> 2 | I38: =H38*$F38*$C38*$B$5 -> 104 | K38: =J38*$F38*$C38*$B$5*$B$5 -> 0 | M38: =L38*$F38*$C38*$B$5*$B$5*$B$5 -> 0 | N38: 0 | O38: =N38*$F38*$C38*$B$5*$B$5*$B$5*$B$5 -> 0 | P38: =SUM(G38,I38,K38,M38,O38) -> 154 | Q38: 0 | R38: =SUM(P38:Q38) -> 154
A39: Airfare | B39: Travel | C39: 1 | D39: Trip | E39: 1 | F39: 150 | G39: =F39*$E39*C39 -> 150 | H39: =1*2 -> 2 | I39: =H39*$F39*$C39*$B$5 -> 312 | K39: =J39*$F39*$C39*$B$5*$B$5 -> 0 | M39: =L39*$F39*$C39*$B$5*$B$5*$B$5 -> 0 | N39: 0 | O39: =N39*$F39*$C39*$B$5*$B$5*$B$5*$B$5 -> 0 | P39: =SUM(G39,I39,K39,M39,O39) -> 462 | Q39: 0 | R39: =SUM(P39:Q39) -> 462
A40: Monitoring, Evaluation, and Collection of Reliable Data
A41: Travel Expenses for M&E Baja California (Mexicali)
A42: Lodging | B42: Travel | C42: 1 | D42: Night | E42: 0 | F42: 182 | G42: =F42*$E42*C42 -> 0 | I42: =H42*$F42*$C42*$B$5 -> 0 | J42: =2*2 -> 4 | K42: =J42*$F42*$C42*$B$5*$B$5 -> 787.4048 | L42: =2*2 -> 4 | M42: =L42*$F42*$C42*$B$5*$B$5*$B$5 -> 818.90099 | N42: 0 | O42: =N42*$F42*$C42*$B$5*$B$5*$B$5*$B$5 -> 0 | P42: =SUM(G42,I42,K42,M42,O42) -> 1606.3058 | Q42: 0 | R42: =SUM(P42:Q42) -> 1606.3058
A43: Per Diem | B43: Travel | C43: 1 | D43: Day | E43: 0 | F43: 116 | G43: =F43*$E43*C43 -> 0 | I43: =H43*$F43*$C43*$B$5 -> 0 | J43: =2*2 -> 4 | K43: =J43*$F43*$C43*$B$5*$B$5 -> 501.8624 | L43: =2*2 -> 4 | M43: =L43*$F43*$C43*$B$5*$B$5*$B$5 -> 521.9369 | O43: =N43*$F43*$C43*$B$5*$B$5*$B$5*$B$5 -> 0 | P43: =SUM(G43,I43,K43,M43,O43) -> 1023.7993 | Q43: 0 | R43: =SUM(P43:Q43) -> 1023.7993
A44: Local Transportation | B44: Travel | C44: 1 | D44: Day | E44: 0 | F44: 50 | G44: =F44*$E44*C44 -> 0 | I44: =H44*$F44*$C44*$B$5 -> 0 | J44: =2*1 -> 2 | K44: =J44*$F44*$C44*$B$5*$B$5 -> 108.16 | L44: =2*1 -> 2 | M44: =L44*$F44*$C44*$B$5*$B$5*$B$5 -> 112.4864 | N44: 0 | O44: =N44*$F44*$C44*$B$5*$B$5*$B$5*$B$5 -> 0 | P44: =SUM(G44,I44,K44,M44,O44) -> 220.6464 | Q44: 0 | R44: =SUM(P44:Q44) -> 220.6464
A45: Airfare | B45: Travel | C45: 1 | D45: Trip | E45: 0 | F45: 500 | G45: =F45*$E45*C45 -> 0 | I45: =H45*$F45*$C45*$B$5 -> 0 | J45: =1*2 -> 2 | K45: =J45*$F45*$C45*$B$5*$B$5 -> 1081.6 | L45: =1*2 -> 2 | M45: =L45*$F45*$C45*$B$5*$B$5*$B$5 -> 1124.864 | N45: 0 | O45: =N45*$F45*$C45*$B$5*$B$5*$B$5*$B$5 -> 0 | P45: =SUM(G45,I45,K45,M45,O45) -> 2206.464 | Q45: 0 | R45: =SUM(P45:Q45) -> 2206.464
A46: Travel Expenses for M&E Jalisco (Guadalajara) | Q46: 0 | R46: =SUM(P46:Q46) -> 0
A47: Lodging | B47: Travel | C47: 1 | D47: Night | E47: 0 | F47: 241 | G47: =F47*$E47*C47 -> 0 | I47: =H47*$F47*$C47*$B$5 -> 0 | J47: =2*2 -> 4 | K47: =J47*$F47*$C47*$B$5*$B$5 -> 1042.6624 | L47: =2*2 -> 4 | M47: =L47*$F47*$C47*$B$5*$B$5*$B$5 -> 1084.3689 | N47: 0 | O47: =N47*$F47*$C47*$B$5*$B$5*$B$5*$B$5 -> 0 | P47: =SUM(G47,I47,K47,M47,O47) -> 2127.0313 | Q47: 0 | R47: =SUM(P47:Q47) -> 2127.0313
A48: Per Diem | B48: Travel | C48: 1 | D48: Day | E48: 0 | F48: 121 | G48: =F48*$E48*C48 -> 0 | I48: =H48*$F48*$C48*$B$5 -> 0 | J48: =2*2 -> 4 | K48: =J48*$F48*$C48*$B$5*$B$5 -> 523.4944 | L48: =2*2 -> 4 | M48: =L48*$F48*$C48*$B$5*$B$5*$B$5 -> 544.43418 | O48: =N48*$F48*$C48*$B$5*$B$5*$B$5*$B$5 -> 0 | P48: =SUM(G48,I48,K48,M48,O48) -> 1067.9286 | Q48: 0 | R48: =SUM(P48:Q48) -> 1067.9286
A49: Local Transportation | B49: Travel | C49: 1 | D49: Day | E49: 0 | F49: 50 | G49: =F49*$E49*C49 -> 0 | I49: =H49*$F49*$C49*$B$5 -> 0 | J49: =2*1 -> 2 | K49: =J49*$F49*$C49*$B$5*$B$5 -> 108.16 | L49: =2*1 -> 2 | M49: =L49*$F49*$C49*$B$5*$B$5*$B$5 -> 112.4864 | N49: 0 | O49: =N49*$F49*$C49*$B$5*$B$5*$B$5*$B$5 -> 0 | P49: =SUM(G49,I49,K49,M49,O49) -> 220.6464 | Q49: 0 | R49: =SUM(P49:Q49) -> 220.6464
A50: Airfare | B50: Travel | C50: 1 | D50: Trip | E50: 0 | F50: 300 | G50: =F50*$E50*C50 -> 0 | I50: =H50*$F50*$C50*$B$5 -> 0 | J50: =1*2 -> 2 | K50: =J50*$F50*$C50*$B$5*$B$5 -> 648.96 | L50: =1*2 -> 2 | M50: =L50*$F50*$C50*$B$5*$B$5*$B$5 -> 674.9184 | N50: 0 | O50: =N50*$F50*$C50*$B$5*$B$5*$B$5*$B$5 -> 0 | P50: =SUM(G50,I50,K50,M50,O50) -> 1323.8784 | Q50: 0 | R50: =SUM(P50:Q50) -> 1323.8784
A51: Travel Expenses for M&E Guanajuato (Other) | Q51: 0 | R51: =SUM(P51:Q51) -> 0
A52: Lodging | B52: Travel | C52: 1 | D52: Night | E52: 0 | F52: 141 | G52: =F52*$E52*C52 -> 0 | I52: =H52*$F52*$C52*$B$5 -> 0 | J52: =2*2 -> 4 | K52: =J52*$F52*$C52*$B$5*$B$5 -> 610.0224 | L52: =2*2 -> 4 | M52: =L52*$F52*$C52*$B$5*$B$5*$B$5 -> 634.4233 | N52: 0 | O52: =N52*$F52*$C52*$B$5*$B$5*$B$5*$B$5 -> 0 | P52: =SUM(G52,I52,K52,M52,O52) -> 1244.4457 | Q52: 0 | R52: =SUM(P52:Q52) -> 1244.4457
A53: Per Diem | B53: Travel | C53: 1 | D53: Day | E53: 0 | F53: 110 | G53: =F53*$E53*C53 -> 0 | I53: =H53*$F53*$C53*$B$5 -> 0 | J53: =2*2 -> 4 | K53: =J53*$F53*$C53*$B$5*$B$5 -> 475.904 | L53: =2*2 -> 4 | M53: =L53*$F53*$C53*$B$5*$B$5*$B$5 -> 494.94016 | O53: =N53*$F53*$C53*$B$5*$B$5*$B$5*$B$5 -> 0 | P53: =SUM(G53,I53,K53,M53,O53) -> 970.84416 | Q53: 0 | R53: =SUM(P53:Q53) -> 970.84416
A54: Local Transportation | B54: Travel | C54: 1 | D54: Day | E54: 0 | F54: 50 | G54: =F54*$E54*C54 -> 0 | I54: =H54*$F54*$C54*$B$5 -> 0 | J54: =2*1 -> 2 | K54: =J54*$F54*$C54*$B$5*$B$5 -> 108.16 | L54: =2*1 -> 2 | M54: =L54*$F54*$C54*$B$5*$B$5*$B$5 -> 112.4864 | N54: 0 | O54: =N54*$F54*$C54*$B$5*$B$5*$B$5*$B$5 -> 0 | P54: =SUM(G54,I54,K54,M54,O54) -> 220.6464 | Q54: 0 | R54: =SUM(P54:Q54) -> 220.6464
A55: Airfare | B55: Travel | C55: 1 | D55: Trip | E55: 0 | F55: 450 | G55: =F55*$E55*C55 -> 0 | I55: =H55*$F55*$C55*$B$5 -> 0 | J55: =1*2 -> 2 | K55: =J55*$F55*$C55*$B$5*$B$5 -> 973.44 | L55: =1*2 -> 2 | M55: =L55*$F55*$C55*$B$5*$B$5*$B$5 -> 1012.3776 | N55: 0 | O55: =N55*$F55*$C55*$B$5*$B$5*$B$5*$B$5 -> 0 | P55: =SUM(G55,I55,K55,M55,O55) -> 1985.8176 | Q55: 0 | R55: =SUM(P55:Q55) -> 1985.8176
A56: Travel Expenses for M&E Querétaro | Q56: 0 | R56: =SUM(P56:Q56) -> 0
A57: Lodging | B57: Travel | C57: 1 | D57: Night | E57: 0 | F57: 210 | G57: =F57*$E57*C57 -> 0 | I57: =H57*$F57*$C57*$B$5 -> 0 | J57: =2*2 -> 4 | K57: =J57*$F57*$C57*$B$5*$B$5 -> 908.544 | L57: =2*2 -> 4 | M57: =L57*$F57*$C57*$B$5*$B$5*$B$5 -> 944.88576 | N57: 0 | O57: =N57*$F57*$C57*$B$5*$B$5*$B$5*$B$5 -> 0 | P57: =SUM(G57,I57,K57,M57,O57) -> 1853.4298 | Q57: 0 | R57: =SUM(P57:Q57) -> 1853.4298
A58: Per Diem | B58: Travel | C58: 1 | D58: Day | E58: 0 | F58: 123 | G58: =F58*$E58*C58 -> 0 | I58: =H58*$F58*$C58*$B$5 -> 0 | J58: =2*2 -> 4 | K58: =J58*$F58*$C58*$B$5*$B$5 -> 532.1472 | L58: =2*2 -> 4 | M58: =L58*$F58*$C58*$B$5*$B$5*$B$5 -> 553.43309 | O58: =N58*$F58*$C58*$B$5*$B$5*$B$5*$B$5 -> 0 | P58: =SUM(G58,I58,K58,M58,O58) -> 1085.5803 | Q58: 0 | R58: =SUM(P58:Q58) -> 1085.5803
A59: Local Transportation | B59: Travel | C59: 1 | D59: Day | E59: 0 | F59: 50 | G59: =F59*$E59*C59 -> 0 | I59: =H59*$F59*$C59*$B$5 -> 0 | J59: =2*1 -> 2 | K59: =J59*$F59*$C59*$B$5*$B$5 -> 108.16 | L59: =2*1 -> 2 | M59: =L59*$F59*$C59*$B$5*$B$5*$B$5 -> 112.4864 | N59: 0 | O59: =N59*$F59*$C59*$B$5*$B$5*$B$5*$B$5 -> 0 | P59: =SUM(G59,I59,K59,M59,O59) -> 220.6464 | Q59: 0 | R59: =SUM(P59:Q59) -> 220.6464
A60: Airfare | B60: Travel | C60: 1 | D60: Trip | E60: 0 | F60: 150 | G60: =F60*$E60*C60 -> 0 | I60: =H60*$F60*$C60*$B$5 -> 0 | J60: =1*2 -> 2 | K60: =J60*$F60*$C60*$B$5*$B$5 -> 324.48 | L60: =1*2 -> 2 | M60: =L60*$F60*$C60*$B$5*$B$5*$B$5 -> 337.4592 | N60: 0 | O60: =N60*$F60*$C60*$B$5*$B$5*$B$5*$B$5 -> 0 | P60: =SUM(G60,I60,K60,M60,O60) -> 661.9392 | Q60: 0 | R60: =SUM(P60:Q60) -> 661.9392
A61: Total Travel | G61: =SUM(G20:G60) -> 4088 | I61: =SUM(I20:I60) -> 8503.04 | K61: =SUM(K20:K60) -> 8843.1616 | M61: =SUM(M20:M60) -> 9196.8881 | O61: =SUM(O20:O60) -> 0 | P61: =SUM(P20:P60) -> 30631.09 | Q61: =SUM(Q20:Q60) -> 0 | R61: =SUM(R20:R60) -> 30631.09
A62: Equipment
A63: None | E63: 0 | F63: 0 | G63: 0 | H63: 0 | I63: 0 | J63: 0 | K63: 0 | L63: 0 | M63: 0 | N63: 0 | O63: 0 | P63: =SUM(G63,I63,K63,M63,O63) -> 0 | Q63: 0 | R63: =SUM(P63:Q63) -> 0
A64: Total Equipment | G64: =SUM(G63) -> 0 | I64: =SUM(I63) -> 0 | K64: =SUM(K63) -> 0 | M64: =SUM(M63) -> 0 | O64: =SUM(O63) -> 0 | P64: =SUM(P63) -> 0 | Q64: =SUM(Q63) -> 0 | R64: =SUM(P64:Q64) -> 0
A65: Supplies
A66: None | E66: 0 | F66: 0 | G66: 0 | H66: 0 | I66: 0 | J66: 0 | K66: 0 | L66: 0 | M66: 0 | N66: 0 | O66: 0 | P66: =SUM(G66,I66,K66,M66,O66) -> 0 | Q66: 0 | R66: =SUM(P66:Q66) -> 0
A67: Total Supplies | G67: =SUM(G66:G66) -> 0 | I67: =SUM(I66:I66) -> 0 | K67: =SUM(K66:K66) -> 0 | M67: =SUM(M66:M66) -> 0 | O67: =SUM(O66:O66) -> 0 | P67: =SUM(P66:P66) -> 0 | Q67: =SUM(Q66:Q66) -> 0 | R67: =SUM(R66:R66) -> 0
A68: Contractual
A69: Contracts
A70: Institutional Liaison Coordinator | B70: Contract | C70: 0.5 | D70: Month | E70: 3 | F70: 2800 | G70: =F70*E70*C70 -> 4200 | H70: 6 | I70: =H70*$F70*$C70*$B$5 -> 8736 | J70: 6 | K70: =J70*$F70*$C70*$B$5*$B$5 -> 9085.44 | L70: 6 | M70: =L70*$F70*$C70*$B$5*$B$5*$B$5 -> 9448.8576 | N70: 0 | O70: =N70*$F70*$C70*$B$5*$B$5*$B$5*$B$5 -> 0 | P70: =SUM(G70,I70,K70,M70,O70) -> 31470.298 | Q70: 0 | R70: =SUM(P70:Q70) -> 31470.298
A71: Senior Software Architect | B71: Contract | C71: 0.85 | D71: Month | E71: 3 | F71: 6270 | G71: =F71*E71*C71 -> 15988.5 | H71: 12 | I71: =H71*$F71*$C71*$B$5 -> 66512.16 | J71: 12 | K71: =J71*$F71*$C71*$B$5*$B$5 -> 69172.646 | L71: 12 | M71: =L71*$F71*$C71*$B$5*$B$5*$B$5 -> 71939.552 | N71: 0 | O71: =N71*$F71*$C71*$B$5*$B$5*$B$5*$B$5 -> 0 | P71: =SUM(G71,I71,K71,M71,O71) -> 223612.86 | Q71: 0 | R71: =SUM(P71:Q71) -> 223612.86
A72: Senior Full-Stack Developer | B72: Contract | C72: 1 | D72: Month | E72: =3*2 -> 6 | F72: 2885 | G72: =F72*E72*C72 -> 17310 | H72: =12*5 -> 60 | I72: =H72*$F72*$C72*$B$5 -> 180024 | J72: =12*5 -> 60 | K72: =J72*$F72*$C72*$B$5*$B$5 -> 187224.96 | L72: =12*2 -> 24 | M72: =L72*$F72*$C72*$B$5*$B$5*$B$5 -> 77885.583 | N72: 0 | O72: =N72*$F72*$C72*$B$5*$B$5*$B$5*$B$5 -> 0 | P72: =SUM(G72,I72,K72,M72,O72) -> 462444.54 | Q72: 0 | R72: =SUM(P72:Q72) -> 462444.54
A73: Junior Full-Stack Developer | B73: Contract | C73: 1 | D73: Month | E73: 3 | F73: 1780 | G73: =F73*E73*C73 -> 5340 | H73: =12 -> 12 | I73: =H73*$F73*$C73*$B$5 -> 22214.4 | J73: =12 -> 12 | K73: =J73*$F73*$C73*$B$5*$B$5 -> 23102.976 | L73: 12 | M73: =L73*$F73*$C73*$B$5*$B$5*$B$5 -> 24027.095 | N73: 0 | O73: =N73*$F73*$C73*$B$5*$B$5*$B$5*$B$5 -> 0 | P73: =SUM(G73,I73,K73,M73,O73) -> 74684.471 | Q73: 0 | R73: =SUM(P73:Q73) -> 74684.471
A74: DevOps/Infrastructure | B74: Contract | C74: 0.85 | D74: Month | E74: 3 | F74: 2510 | G74: =F74*E74*C74 -> 6400.5 | H74: 12 | I74: =H74*$F74*$C74*$B$5 -> 26626.08 | J74: 12 | K74: =J74*$F74*$C74*$B$5*$B$5 -> 27691.123 | L74: 12 | M74: =L74*$F74*$C74*$B$5*$B$5*$B$5 -> 28798.768 | N74: 0 | O74: =N74*$F74*$C74*$B$5*$B$5*$B$5*$B$5 -> 0 | P74: =SUM(G74,I74,K74,M74,O74) -> 89516.471 | Q74: 0 | R74: =SUM(P74:Q74) -> 89516.471
A75: Product Manager | B75: Contract | C75: 0.6 | D75: Month | E75: 3 | F75: 3480 | G75: =F75*E75*C75 -> 6264 | H75: 12 | I75: =H75*$F75*$C75*$B$5 -> 26058.24 | J75: 12 | K75: =J75*$F75*$C75*$B$5*$B$5 -> 27100.57 | L75: 9 | M75: =L75*$F75*$C75*$B$5*$B$5*$B$5 -> 21138.444 | N75: 0 | O75: =N75*$F75*$C75*$B$5*$B$5*$B$5*$B$5 -> 0 | P75: =SUM(G75,I75,K75,M75,O75) -> 80561.254 | Q75: 0 | R75: =SUM(P75:Q75) -> 80561.254
A76: Product Analyst | B76: Contract | C76: 1 | D76: Month | E76: 3 | F76: 1780 | G76: =F76*E76*C76 -> 5340 | H76: =12*2 -> 24 | I76: =H76*$F76*$C76*$B$5 -> 44428.8 | J76: =12*2 -> 24 | K76: =J76*$F76*$C76*$B$5*$B$5 -> 46205.952 | L76: =9*2 -> 18 | M76: =L76*$F76*$C76*$B$5*$B$5*$B$5 -> 36040.643 | N76: 0 | O76: =N76*$F76*$C76*$B$5*$B$5*$B$5*$B$5 -> 0 | P76: =SUM(G76,I76,K76,M76,O76) -> 132015.39 | Q76: 0 | R76: =SUM(P76:Q76) -> 132015.39
A77: Senior Legal Analyst | B77: Contract | C77: 1 | D77: Month | E77: 3 | F77: 3070 | G77: =F77*E77*C77 -> 9210 | H77: =9*2 -> 18 | I77: =H77*$F77*$C77*$B$5 -> 57470.4 | J77: =9*2 -> 18 | K77: =J77*$F77*$C77*$B$5*$B$5 -> 59769.216 | L77: 6 | M77: =L77*$F77*$C77*$B$5*$B$5*$B$5 -> 20719.995 | N77: 0 | O77: =N77*$F77*$C77*$B$5*$B$5*$B$5*$B$5 -> 0 | P77: =SUM(G77,I77,K77,M77,O77) -> 147169.61 | Q77: 0 | R77: =SUM(P77:Q77) -> 147169.61
A78: Support & Training Coordinator | B78: Contract | C78: 0.95 | D78: Month | E78: 3 | F78: 1075 | G78: =F78*E78*C78 -> 3063.75 | H78: 12 | I78: =H78*$F78*$C78*$B$5 -> 12745.2 | J78: 12 | K78: =J78*$F78*$C78*$B$5*$B$5 -> 13255.008 | L78: 12 | M78: =L78*$F78*$C78*$B$5*$B$5*$B$5 -> 13785.208 | N78: 0 | O78: =N78*$F78*$C78*$B$5*$B$5*$B$5*$B$5 -> 0 | P78: =SUM(G78,I78,K78,M78,O78) -> 42849.166 | Q78: 0 | R78: =SUM(P78:Q78) -> 42849.166
A79: Support & Training Assistant | B79: Contract | C79: 0.9 | D79: Month | E79: =3*2 -> 6 | F79: 920 | G79: =F79*E79*C79 -> 4968 | H79: =12*4 -> 48 | I79: =H79*$F79*$C79*$B$5 -> 41333.76 | J79: =12*4 -> 48 | K79: =J79*$F79*$C79*$B$5*$B$5 -> 42987.11 | L79: =12*3 -> 36 | M79: =L79*$F79*$C79*$B$5*$B$5*$B$5 -> 33529.946 | N79: 0 | O79: =N79*$F79*$C79*$B$5*$B$5*$B$5*$B$5 -> 0 | P79: =SUM(G79,I79,K79,M79,O79) -> 122818.82 | Q79: 0 | R79: =SUM(P79:Q79) -> 122818.82
A80: Senior Data Analyst | B80: Contract | C80: 0.6 | D80: Month | E80: 3 | F80: 2600 | G80: =F80*E80*C80 -> 4680 | H80: 6 | I80: =H80*$F80*$C80*$B$5 -> 9734.4 | J80: 3 | K80: =J80*$F80*$C80*$B$5*$B$5 -> 5061.888 | L80: 0 | M80: =L80*$F80*$C80*$B$5*$B$5*$B$5 -> 0 | N80: 0 | O80: =N80*$F80*$C80*$B$5*$B$5*$B$5*$B$5 -> 0 | P80: =SUM(G80,I80,K80,M80,O80) -> 19476.288 | Q80: 0 | R80: =SUM(P80:Q80) -> 19476.288
A81: Junior Data Analyst | B81: Contract | C81: 1 | D81: Month | E81: 3 | F81: 1590 | G81: =F81*E81*C81 -> 4770 | H81: 6 | I81: =H81*$F81*$C81*$B$5 -> 9921.6 | J81: 3 | K81: =J81*$F81*$C81*$B$5*$B$5 -> 5159.232 | L81: 0 | M81: =L81*$F81*$C81*$B$5*$B$5*$B$5 -> 0 | N81: 0 | O81: =N81*$F81*$C81*$B$5*$B$5*$B$5*$B$5 -> 0 | P81: =SUM(G81,I81,K81,M81,O81) -> 19850.832 | Q81: 0 | R81: =SUM(P81:Q81) -> 19850.832
A82: Data Entry Specialist | B82: Contract | C82: 1 | D82: Month | E82: =3*7 -> 21 | F82: 810 | G82: =F82*E82*C82 -> 17010 | H82: =3*7 -> 21 | I82: =H82*$F82*$C82*$B$5 -> 17690.4 | J82: 0 | K82: =J82*$F82*$C82*$B$5*$B$5 -> 0 | L82: 0 | M82: =L82*$F82*$C82*$B$5*$B$5*$B$5 -> 0 | N82: 0 | O82: =N82*$F82*$C82*$B$5*$B$5*$B$5*$B$5 -> 0 | P82: =SUM(G82,I82,K82,M82,O82) -> 34700.4 | Q82: 0 | R82: =SUM(P82:Q82) -> 34700.4
A83: Senior Technical Instructor | B83: Contract | C83: 0.28 | D83: Month | E83: 3 | F83: 2600 | G83: =F83*E83*C83 -> 2184 | H83: 12 | I83: =H83*$F83*$C83*$B$5 -> 9085.44 | J83: 0 | K83: =J83*$F83*$C83*$B$5*$B$5 -> 0 | L83: 0 | M83: =L83*$F83*$C83*$B$5*$B$5*$B$5 -> 0 | N83: 0 | O83: =N83*$F83*$C83*$B$5*$B$5*$B$5*$B$5 -> 0 | P83: =SUM(G83,I83,K83,M83,O83) -> 11269.44 | Q83: 0 | R83: =SUM(P83:Q83) -> 11269.44
A84: Technical Instructor Coordinator | B84: Contract | C84: 1 | D84: Month | E84: 3 | F84: 2430 | G84: =F84*E84*C84 -> 7290 | H84: 12 | I84: =H84*$F84*$C84*$B$5 -> 30326.4 | J84: 2 | K84: =J84*$F84*$C84*$B$5*$B$5 -> 5256.576 | L84: 0 | M84: =L84*$F84*$C84*$B$5*$B$5*$B$5 -> 0 | N84: 0 | O84: =N84*$F84*$C84*$B$5*$B$5*$B$5*$B$5 -> 0 | P84: =SUM(G84,I84,K84,M84,O84) -> 42872.976 | Q84: 0 | R84: =SUM(P84:Q84) -> 42872.976
A85: Junior Technical Instructor | B85: Contract | C85: 1 | D85: Month | E85: =3*2 -> 6 | F85: 2035 | G85: =F85*E85*C85 -> 12210 | H85: =12*2 -> 24 | I85: =H85*$F85*$C85*$B$5 -> 50793.6 | J85: =2*2 -> 4 | K85: =J85*$F85*$C85*$B$5*$B$5 -> 8804.224 | L85: 0 | M85: =L85*$F85*$C85*$B$5*$B$5*$B$5 -> 0 | N85: 0 | O85: =N85*$F85*$C85*$B$5*$B$5*$B$5*$B$5 -> 0 | P85: =SUM(G85,I85,K85,M85,O85) -> 71807.824 | Q85: 0 | R85: =SUM(P85:Q85) -> 71807.824
A86: Materials Designer | B86: Contract | C86: 0.83 | D86: Month | E86: 3 | F86: 2195 | G86: =F86*E86*C86 -> 5465.55 | H86: 12 | I86: =H86*$F86*$C86*$B$5 -> 22736.688 | J86: 12 | K86: =J86*$F86*$C86*$B$5*$B$5 -> 23646.156 | L86: 0 | M86: =L86*$F86*$C86*$B$5*$B$5*$B$5 -> 0 | N86: 0 | O86: =N86*$F86*$C86*$B$5*$B$5*$B$5*$B$5 -> 0 | P86: =SUM(G86,I86,K86,M86,O86) -> 51848.394 | Q86: 0 | R86: =SUM(P86:Q86) -> 51848.394
A87: Moodle Expert | B87: Contract | C87: 0.52 | D87: Month | E87: 0 | F87: 3760 | G87: =F87*E87*C87 -> 0 | H87: 8 | I87: =H87*$F87*$C87*$B$5 -> 16267.264 | J87: 0 | K87: =J87*$F87*$C87*$B$5*$B$5 -> 0 | L87: 0 | M87: =L87*$F87*$C87*$B$5*$B$5*$B$5 -> 0 | N87: 0 | O87: =N87*$F87*$C87*$B$5*$B$5*$B$5*$B$5 -> 0 | P87: =SUM(G87,I87,K87,M87,O87) -> 16267.264 | Q87: 0 | R87: =SUM(P87:Q87) -> 16267.264
A88: Contractual for M&E | Q88: 0 | R88: =SUM(P88:Q88) -> 0
A89: Institutional Liaison Coordinator (M&E Activities) | B89: Contract | C89: 0.5 | D89: Month | E89: 0 | F89: 2800 | G89: =F89*E89*C89 -> 0 | H89: 6 | I89: =H89*$F89*$C89*$B$5 -> 8736 | J89: 6 | K89: =J89*$F89*$C89*$B$5*$B$5 -> 9085.44 | L89: 6 | M89: =L89*$F89*$C89*$B$5*$B$5*$B$5 -> 9448.8576 | N89: 0 | O89: =N89*$F89*$C89*$B$5*$B$5*$B$5*$B$5 -> 0 | P89: =SUM(G89,I89,K89,M89,O89) -> 27270.298 | Q89: 0 | R89: =SUM(P89:Q89) -> 27270.298
A90: Senior Data Analyst (M&E Activities) | B90: Contract | C90: 0.6 | D90: Month | E90: 0 | F90: 2600 | G90: =F90*E90*C90 -> 0 | H90: 0 | I90: =H90*$F90*$C90*$B$5 -> 0 | J90: 3 | K90: =J90*$F90*$C90*$B$5*$B$5 -> 5061.888 | L90: 3 | M90: =L90*$F90*$C90*$B$5*$B$5*$B$5 -> 5264.3635 | N90: 0 | O90: =N90*$F90*$C90*$B$5*$B$5*$B$5*$B$5 -> 0 | P90: =SUM(G90,I90,K90,M90,O90) -> 10326.252 | Q90: 0 | R90: =SUM(P90:Q90) -> 10326.252
A91: Junior Data Analyst (M&E Activities) | B91: Contract | C91: 1 | D91: Month | E91: 0 | F91: 1590 | G91: =F91*E91*C91 -> 0 | H91: 0 | I91: =H91*$F91*$C91*$B$5 -> 0 | J91: 3 | K91: =J91*$F91*$C91*$B$5*$B$5 -> 5159.232 | L91: 3 | M91: =L91*$F91*$C91*$B$5*$B$5*$B$5 -> 5365.6013 | N91: 0 | O91: =N91*$F91*$C91*$B$5*$B$5*$B$5*$B$5 -> 0 | P91: =SUM(G91,I91,K91,M91,O91) -> 10524.833 | Q91: 0 | R91: =SUM(P91:Q91) -> 10524.833
A92: Senior Legal Analyst (M&E Activities) | B92: Contract | C92: 1 | D92: Month | E92: 0 | F92: 3070 | G92: =F92*E92*C92 -> 0 | H92: =3*2 -> 6 | I92: =H92*$F92*$C92*$B$5 -> 19156.8 | J92: =3*2 -> 6 | K92: =J92*$F92*$C92*$B$5*$B$5 -> 19923.072 | L92: 6 | M92: =L92*$F92*$C92*$B$5*$B$5*$B$5 -> 20719.995 | N92: 0 | O92: =N92*$F92*$C92*$B$5*$B$5*$B$5*$B$5 -> 0 | P92: =SUM(G92,I92,K92,M92,O92) -> 59799.867 | Q92: 0 | R92: =SUM(P92:Q92) -> 59799.867
A93: Total Contractual | G93: =SUM(G70:G92) -> 131694.3 | I93: =SUM(I70:I92) -> 680597.63 | K93: =SUM(K70:K92) -> 592752.71 | M93: =SUM(M70:M92) -> 378112.91 | O93: =SUM(O70:O92) -> 0 | P93: =SUM(P70:P92) -> 1783157.6 | Q93: =SUM(Q70:Q92) -> 0 | R93: =SUM(R70:R92) -> 1783157.6
A94: Construction
A95: Construction | E95: 0 | F95: 0 | G95: 0 | H95: 0 | I95: 0 | J95: 0 | K95: 0 | L95: 0 | M95: 0 | N95: 0 | O95: 0 | P95: =SUM(G95,I95,K95,M95,O95) -> 0 | Q95: 0 | R95: =SUM(P95:Q95) -> 0
A96: Total Construction | G96: =SUM(G95) -> 0 | I96: =SUM(I95) -> 0 | K96: =SUM(K95) -> 0 | M96: =SUM(M95) -> 0 | O96: =SUM(O95) -> 0 | P96: =SUM(P95) -> 0 | Q96: =SUM(Q95) -> 0 | R96: =SUM(P96:Q96) -> 0
A97: Other Direct Costs
A98: Project Office
A99: Infrastructure & Cloud Services | B99: Supplies | C99: 1 | D99: Month | E99: 6 | F99: 860 | G99: =F99*E99*C99 -> 5160 | H99: 12 | I99: =H99*$F99*$C99*$B$5 -> 10732.8 | J99: 12 | K99: =J99*$F99*$C99*$B$5*$B$5 -> 11162.112 | L99: 6 | M99: =L99*$F99*$C99*$B$5*$B$5*$B$5 -> 5804.2982 | O99: =N99*$F99*$C99*$B$5*$B$5*$B$5*$B$5 -> 0 | P99: =SUM(G99,I99,K99,M99,O99) -> 32859.21 | Q99: 0 | R99: =SUM(P99:Q99) -> 32859.21
A100: Development & Testing Tools | B100: Supplies | C100: 1 | D100: Month | E100: 6 | F100: 340 | G100: =F100*E100*C100 -> 2040 | H100: 12 | I100: =H100*$F100*$C100*$B$5 -> 4243.2 | J100: 12 | K100: =J100*$F100*$C100*$B$5*$B$5 -> 4412.928 | L100: 6 | M100: =L100*$F100*$C100*$B$5*$B$5*$B$5 -> 2294.7226 | O100: =N100*$F100*$C100*$B$5*$B$5*$B$5*$B$5 -> 0 | P100: =SUM(G100,I100,K100,M100,O100) -> 12990.851 | Q100: 0 | R100: =SUM(P100:Q100) -> 12990.851
A101: Productivity & Collaboration Tools | B101: Supplies | C101: 1 | D101: Month | E101: 6 | F101: 270 | G101: =F101*E101*C101 -> 1620 | H101: 12 | I101: =H101*$F101*$C101*$B$5 -> 3369.6 | J101: 12 | K101: =J101*$F101*$C101*$B$5*$B$5 -> 3504.384 | L101: 6 | M101: =L101*$F101*$C101*$B$5*$B$5*$B$5 -> 1822.2797 | O101: =N101*$F101*$C101*$B$5*$B$5*$B$5*$B$5 -> 0 | P101: =SUM(G101,I101,K101,M101,O101) -> 10316.264 | Q101: 0 | R101: =SUM(P101:Q101) -> 10316.264
...

Sheet FES Sub Budget Summary
A3: Project Budget Summary
A4: Partners of the Americas
A5: Friedrich-Ebert-Stiftung (FES) Sub-Recipient / Sub-receptor Friedrich-Ebert-Stiftung (FES)
A6: 37 Months
A8: BUDGET SUMMARY CATEGORIES | B8: YEAR 1 | C8: YEAR 2 | D8: YEAR 3 | E8: YEAR 4 | F8: YEAR 5 | G8: TOTAL FEDERAL FUNDS REQUESTED
A10: 1. PERSONNEL | B10: =+'FES Sub Budget'!G14 -> 31380 | C10: =+'FES Sub Budget'!I14 -> 91476 | D10: =+'FES Sub Budget'!K14 -> 96049.8 | E10: =+'FES Sub Budget'!M14 -> 54130.545 | F10: =+'FES Sub Budget'!O14 -> 0 | G10: =SUM(B10:F10) -> 273036.34
A11: 2. FRINGE BENEFITS | B11: =+'FES Sub Budget'!G17 -> 12235.062 | C11: =+'FES Sub Budget'!I17 -> 35666.492 | D11: =+'FES Sub Budget'!K17 -> 37449.817 | E11: =+'FES Sub Budget'!M17 -> 21105.499 | F11: =+'FES Sub Budget'!O17 -> 0 | G11: =SUM(B11:F11) -> 106456.87
A12: 3. TRAVEL | B12: =+'FES Sub Budget'!G27 -> 0 | C12: =+'FES Sub Budget'!I27 -> 23316.391 | D12: =+'FES Sub Budget'!K27 -> 24249.046 | E12: =+'FES Sub Budget'!M27 -> 10945.184 | F12: =+'FES Sub Budget'!O27 -> 0 | G12: =SUM(B12:F12) -> 58510.621
A13: 4. EQUIPMENT | B13: =+'FES Sub Budget'!G30 -> 0 | C13: =+'FES Sub Budget'!I30 -> 0 | D13: =+'FES Sub Budget'!K30 -> 0 | E13: =+'FES Sub Budget'!M30 -> 0 | F13: =+'FES Sub Budget'!O30 -> 0 | G13: =SUM(B13:F13) -> 0
A14: 5. SUPPLIES | B14: =+'FES Sub Budget'!G34 -> 4200 | C14: =+'FES Sub Budget'!I34 -> 1872 | D14: =+'FES Sub Budget'!K34 -> 1946.88 | E14: =+'FES Sub Budget'!M34 -> 1181.1072 | F14: =+'FES Sub Budget'!O34 -> 0 | G14: =SUM(B14:F14) -> 9199.9872
A15: 6. CONTRACTUAL | B15: =+'FES Sub Budget'!G38 -> 0 | C15: =+'FES Sub Budget'!I38 -> 39000 | D15: =+'FES Sub Budget'!K38 -> 43680 | E15: =+'FES Sub Budget'!M38 -> 25958.4 | F15: =+'FES Sub Budget'!O38 -> 0 | G15: =SUM(B15:F15) -> 108638.4
A16: 7. CONSTRUCTION | B16: =+'FES Sub Budget'!G41 -> 0 | C16: =+'FES Sub Budget'!I41 -> 0 | D16: =+'FES Sub Budget'!K41 -> 0 | E16: =+'FES Sub Budget'!M41 -> 0 | F16: =+'FES Sub Budget'!O41 -> 0 | G16: =SUM(B16:F16) -> 0
A17: 8. OTHER DIRECT COSTS | B17: =+'FES Sub Budget'!G61 -> 1500 | C17: =+'FES Sub Budget'!I61 -> 23270 | D17: =+'FES Sub Budget'!K61 -> 47256.8 | E17: =+'FES Sub Budget'!M61 -> 67323.872 | F17: =+'FES Sub Budget'!O61 -> 0 | G17: =SUM(B17:F17) -> 139350.67
A19: 9. TOTAL DIRECT COSTS (Lines 1-8) | B19: =SUM(B10:B17) -> 49315.062 | C19: =SUM(C10:C17) -> 214600.88 | D19: =SUM(D10:D17) -> 250632.34 | E19: =SUM(E10:E17) -> 180644.61 | F19: =SUM(F10:F17) -> 0 | G19: =SUM(G10:G17) -> 695192.9
A20: 10. DE MINIMIS RATE | B20: =+B19*0.15 -> 7397.2593 | C20: =+C19*0.15 -> 32190.132 | D20: =+D19*0.15 -> 37594.852 | E20: =+E19*0.15 -> 27096.691 | F20: =+F19*0.15 -> 0 | G20: =SUM(B20:F20) -> 104278.93
A21: 11. TOTAL COSTS (Lines 9-10) | B21: =SUM(B19:B20) -> 56712.321 | C21: =SUM(C19:C20) -> 246791.02 | D21: =SUM(D19:D20) -> 288227.19 | E21: =SUM(E19:E20) -> 207741.3 | F21: =SUM(F19:F20) -> 0 | G21: =SUM(G19:G20) -> 799471.83

Sheet FES Sub Budget
A1: Project Line-Item Budget
A2: Friedrich-Ebert-Stiftung (FES) Sub-Recipient / Sub-receptor Friedrich-Ebert-Stiftung (FES)
A3: 37 Months
A4: Cost Assumptions
A5: Inflation - Goods/Services | B5: 1.04
A6: Merit Based Increases for HO & Field Staff | B6: 1.05
A8: BUDGET ITEM | B8: CATEGORY | C8: LOE | D8: UNIT | E8: # of Units | F8: RATE / UNIT | G8: Year 1 | H8: # of Units | I8: Year 2 | J8: # of Units | K8: Year 3 | L8: # of Units | M8: Year 4 | N8: # of Units | O8: Year 5 | P8: TOTAL US$ | Q8: TOTAL COST SHARING | R8: PROJECT GRAND TOTAL
A9: Personnel
A10: Professional Personnel
A11: Project Coordinator | B11: Salaries | C11: 1 | D11: Month | E11: 6 | F11: 3200 | G11: =F11*$E11*$C11 -> 19200 | H11: 12 | I11: =H11*$F11*$C11*$B$6 -> 40320 | J11: 12 | K11: =J11*$F11*$C11*$B$6*$B$6 -> 42336 | L11: 7 | M11: =L11*$F11*$C11*$B$6*$B$6*$B$6 -> 25930.8 | O11: =N11*$F11*$C11*$B$6*$B$6*$B$6*$B$6 -> 0 | P11: =SUM(G11,I11,K11,M11,O11) -> 127786.8 | Q11: 0 | R11: =SUM(P11:Q11) -> 127786.8
A12: Project Specialist and M&E | B12: Salaries | C12: 1 | D12: Month | E12: 3 | F12: 2400 | G12: =F12*$E12*C12 -> 7200 | H12: 12 | I12: =H12*$F12*$C12*$B$6 -> 30240 | J12: 12 | K12: =J12*$F12*$C12*$B$6*$B$6 -> 31752 | L12: 6 | M12: =L12*$F12*$C12*$B$6*$B$6*$B$6 -> 16669.8 | O12: =N12*$F12*$C12*$B$6*$B$6*$B$6*$B$6 -> 0 | P12: =SUM(G12,I12,K12,M12,O12) -> 85861.8 | Q12: 0 | R12: =SUM(P12:Q12) -> 85861.8
A13: F&A Officer | B13: Salaries | C13: 1 | D13: Month | E13: 3 | F13: 1660 | G13: =F13*$E13*C13 -> 4980 | H13: 12 | I13: =H13*$F13*$C13*$B$6 -> 20916 | J13: 12 | K13: =J13*$F13*$C13*$B$6*$B$6 -> 21961.8 | L13: 6 | M13: =L13*$F13*$C13*$B$6*$B$6*$B$6 -> 11529.945 | O13: =N13*$F13*$C13*$B$6*$B$6*$B$6*$B$6 -> 0 | P13: =SUM(G13,I13,K13,M13,O13) -> 59387.745 | Q13: 0 | R13: =SUM(P13:Q13) -> 59387.745
A14: Total Personnel | G14: =SUM(G11:G13) -> 31380 | I14: =SUM(I11:I13) -> 91476 | K14: =SUM(K11:K13) -> 96049.8 | M14: =SUM(M11:M13) -> 54130.545 | O14: =SUM(O11:O13) -> 0 | P14: =SUM(P11:P13) -> 273036.35 | Q14: =SUM(Q11:Q13) -> 0 | R14: =SUM(R11:R13) -> 273036.35
A15: Fringe Benefits
A16: Fringe Benefits - Mexico | B16: Fringe Benefits | D16: Month | F16: 0.3899 | G16: =G14*F16 -> 12235.062 | H16: =+F16 -> 0.3899 | I16: =I14*H16 -> 35666.492 | J16: =+H16 -> 0.3899 | K16: =K14*J16 -> 37449.817 | L16: =+J16 -> 0.3899 | M16: =M14*L16 -> 21105.499 | N16: =+L16 -> 0.3899 | O16: =O14*N16 -> 0 | P16: =SUM(G16,I16,K16,M16,O16) -> 106456.87 | Q16: 0 | R16: =SUM(P16:Q16) -> 106456.87
A17: Total Fringe Benefits | G17: =SUM(G16:G16) -> 12235.062 | I17: =SUM(I16:I16) -> 35666.492 | K17: =SUM(K16:K16) -> 37449.817 | M17: =SUM(M16:M16) -> 21105.499 | O17: =SUM(O16:O16) -> 0 | P17: =SUM(P16:P16) -> 106456.87 | Q17: =SUM(Q16:Q16) -> 0 | R17: =SUM(R16:R16) -> 106456.87
A18: Travel
A19: Activity 11 — Escuela de Liderazgo Sindical: Annual Leadership Training for a New Generation of Union Leaders
A20: Airfare | B20: Travel | C20: 1 | D20: Trip | E20: 0 | F20: =+Travel!$D$11 -> 363.30878 | G20: =F20*E20*C20 -> 0 | H20: 20 | I20: =H20*$F20*$C20 -> 7266.1757 | J20: 20 | K20: =J20*$F20*$C20*$B$5 -> 7556.8227 | L20: 8 | M20: =L20*$F20*$C20*$B$5*$B$5 -> 3143.6382 | O20: =N20*$F20*$C20*$B$5*$B$5*$B$5*$B$5 -> 0 | P20: =SUM(G20,I20,K20,M20,O20) -> 17966.637 | Q20: 0 | R20: =SUM(P20:Q20) -> 17966.637
A21: Lodging and M&IE | B21: Travel | C21: 1 | D21: Day | E21: 0 | F21: =+Travel!$B$11+Travel!$C$12 -> 153.03504 | G21: =F21*E21*C21 -> 0 | H21: =2*20 -> 40 | I21: =H21*$F21*$C21 -> 6121.4015 | J21: =2*20 -> 40 | K21: =J21*$F21*$C21*$B$5 -> 6366.2576 | L21: 16 | M21: =L21*$F21*$C21*$B$5*$B$5 -> 2648.3632 | O21: =N21*$F21*$C21*$B$5*$B$5*$B$5*$B$5 -> 0 | P21: =SUM(G21,I21,K21,M21,O21) -> 15136.022 | Q21: 0 | R21: =SUM(P21:Q21) -> 15136.022
A22: Local transportation | B22: Travel | C22: 1 | D22: Day | E22: 0 | F22: 50 | G22: =F22*E22*C22 -> 0 | H22: =2*20 -> 40 | I22: =H22*$F22*$C22 -> 2000 | J22: =2*20 -> 40 | K22: =J22*$F22*$C22*$B$5 -> 2080 | L22: 16 | M22: =L22*$F22*$C22*$B$5*$B$5 -> 865.28 | O22: =N22*$F22*$C22*$B$5*$B$5*$B$5*$B$5 -> 0 | P22: =SUM(G22,I22,K22,M22,O22) -> 4945.28 | Q22: 0 | R22: =SUM(P22:Q22) -> 4945.28
A23: Monitoring, Evaluation, and Collection of Reliable Data
A24: M&E - Airfare - Field Verification & Data Collection Expenses | B24: Travel | C24: 1 | D24: Trip | E24: 0 | F24: =+Travel!$D$11 -> 363.30878 | G24: =F24*E24*C24 -> 0 | H24: =((2*2)+(4*2)+(2*1)) -> 14 | I24: =H24*$F24*$C24 -> 5086.323 | J24: =((2*2)+(4*2)+(2*1)) -> 14 | K24: =J24*$F24*$C24*$B$5 -> 5289.7759 | L24: 7 | M24: =L24*$F24*$C24*$B$5*$B$5 -> 2750.6835 | O24: =N24*$F24*$C24*$B$5*$B$5*$B$5*$B$5 -> 0 | P24: =SUM(G24,I24,K24,M24,O24) -> 13126.782 | Q24: 0 | R24: =SUM(P24:Q24) -> 13126.782
A25: M&E - Lodging and M&IE - Field Verification & Data Collection Expenses | B25: Travel | C25: 1 | D25: Day | E25: 0 | F25: =+Travel!$B$11+Travel!$C$12 -> 153.03504 | G25: =F25*E25*C25 -> 0 | H25: =((2*2)+(4*2)+(2*1)) -> 14 | I25: =H25*$F25*$C25 -> 2142.4905 | J25: =((2*2)+(4*2)+(2*1)) -> 14 | K25: =J25*$F25*$C25*$B$5 -> 2228.1902 | L25: 7 | M25: =L25*$F25*$C25*$B$5*$B$5 -> 1158.6589 | O25: =N25*$F25*$C25*$B$5*$B$5*$B$5*$B$5 -> 0 | P25: =SUM(G25,I25,K25,M25,O25) -> 5529.3396 | Q25: 0 | R25: =SUM(P25:Q25) -> 5529.3396
A26: M&E - Transportation - Field Verification & Data Collection Expenses | B26: Travel | C26: 1 | D26: Day | E26: 0 | F26: 50 | G26: =F26*E26*C26 -> 0 | H26: =((2*2)+(4*2)+(2*1)) -> 14 | I26: =H26*$F26*$C26 -> 700 | J26: =((2*2)+(4*2)+(2*1)) -> 14 | K26: =J26*$F26*$C26*$B$5 -> 728 | L26: 7 | M26: =L26*$F26*$C26*$B$5*$B$5 -> 378.56 | O26: =N26*$F26*$C26*$B$5*$B$5*$B$5*$B$5 -> 0 | P26: =SUM(G26,I26,K26,M26,O26) -> 1806.56 | Q26: 0 | R26: =SUM(P26:Q26) -> 1806.56
A27: Total Travel | G27: =SUM(G19:G26) -> 0 | I27: =SUM(I19:I26) -> 23316.391 | K27: =SUM(K19:K26) -> 24249.046 | M27: =SUM(M19:M26) -> 10945.184 | O27: =SUM(O19:O26) -> 0 | P27: =SUM(P19:P26) -> 58510.621 | Q27: =SUM(Q19:Q26) -> 0 | R27: =SUM(R19:R26) -> 58510.621
A28: Equipment
A29: None | E29: 0 | F29: 0 | G29: 0 | H29: 0 | I29: 0 | J29: 0 | K29: 0 | L29: 0 | M29: 0 | N29: 0 | O29: 0 | P29: =SUM(G29,I29,K29,M29,O29) -> 0 | Q29: 0 | R29: =SUM(P29:Q29) -> 0
A30: Total Equipment | G30: =SUM(G29) -> 0 | I30: =SUM(I29) -> 0 | K30: =SUM(K29) -> 0 | M30: =SUM(M29) -> 0 | O30: =SUM(O29) -> 0 | P30: =SUM(P29) -> 0 | Q30: =SUM(Q29) -> 0 | R30: =SUM(P30:Q30) -> 0
A31: Supplies
A32: Office supplies | B32: Supplies | C32: 1 | D32: Month | E32: 6 | F32: 150 | G32: =F32*E32*C32 -> 900 | H32: 12 | I32: =H32*$F32*$C32*$B$5 -> 1872 | J32: 12 | K32: =J32*$F32*$C32*$B$5*$B$5 -> 1946.88 | L32: 7 | M32: =L32*$F32*$C32*$B$5*$B$5*$B$5 -> 1181.1072 | O32: =N32*$F32*$C32*$B$5*$B$5*$B$5*$B$5 -> 0 | P32: =SUM(G32,I32,K32,M32,O32) -> 5899.9872 | Q32: 0 | R32: =SUM(P32:Q32) -> 5899.9872
A33: Computers | B33: Supplies | C33: 1 | D33: Month | E33: 3 | F33: 1100 | G33: =F33*E33*C33 -> 3300 | H33: 0 | I33: =H33*$F33*$C33*$B$5 -> 0 | J33: 0 | K33: =J33*$F33*$C33*$B$5*$B$5 -> 0 | L33: 0 | M33: =L33*$F33*$C33*$B$5*$B$5*$B$5 -> 0 | O33: =N33*$F33*$C33*$B$5*$B$5*$B$5*$B$5 -> 0 | P33: =SUM(G33,I33,K33,M33,O33) -> 3300 | Q33: 0 | R33: =SUM(P33:Q33) -> 3300
A34: Total Supplies | G34: =SUM(G32:G33) -> 4200 | I34: =SUM(I32:I33) -> 1872 | K34: =SUM(K32:K33) -> 1946.88 | M34: =SUM(M32:M33) -> 1181.1072 | O34: =SUM(O32:O33) -> 0 | P34: =SUM(P32:P33) -> 9199.9872 | Q34: =SUM(Q32:Q33) -> 0 | R34: =SUM(R32:R33) -> 9199.9872
A35: Contractual
A36: Activity 9 - Contract to deliver workshops to strengthen the capacity of unions to submit effective petitions under the Rapid Response Mechanism | B36: Contract | C36: 1 | D36: Contract | E36: 0 | F36: 1500 | G36: 0 | H36: 2 | I36: =H36*$F36*$C36 -> 3000 | J36: 4 | K36: =J36*$F36*$C36*$B$5 -> 6240 | L36: 4 | M36: =L36*$F36*$C36*$B$5*$B$5 -> 6489.6 | O36: 0 | P36: =SUM(G36,I36,K36,M36,O36) -> 15729.6 | Q36: 0 | R36: =SUM(P36:Q36) -> 15729.6
A37: Activity 11 — Escuela de Liderazgo Sindical: Consultants | B37: Contract | C37: 1 | D37: Contract | E37: 0 | F37: 3000 | G37: 0 | H37: 12 | I37: =H37*$F37*$C37 -> 36000 | J37: 12 | K37: =J37*$F37*$C37*$B$5 -> 37440 | L37: 6 | M37: =L37*$F37*$C37*$B$5*$B$5 -> 19468.8 | O37: 0 | P37: =SUM(G37,I37,K37,M37,O37) -> 92908.8 | Q37: 0 | R37: =SUM(P37:Q37) -> 92908.8
A38: Total Contractual | G38: =SUM(G36:G37) -> 0 | I38: =SUM(I36:I37) -> 39000 | K38: =SUM(K36:K37) -> 43680 | M38: =SUM(M36:M37) -> 25958.4 | O38: =SUM(O36:O37) -> 0 | P38: =SUM(P36:P37) -> 108638.4 | Q38: =SUM(Q36:Q37) -> 0 | R38: =SUM(R36:R37) -> 108638.4
A39: Construction
A40: None | E40: 0 | F40: 0 | G40: 0 | H40: 0 | I40: 0 | J40: 0 | K40: 0 | L40: 0 | M40: 0 | N40: 0 | O40: 0 | P40: =SUM(G40,I40,K40,M40,O40) -> 0 | Q40: 0 | R40: =SUM(P40:Q40) -> 0
A41: Total Construction | G41: =SUM(G40) -> 0 | I41: =SUM(I40) -> 0 | K41: =SUM(K40) -> 0 | M41: =SUM(M40) -> 0 | O41: =SUM(O40) -> 0 | P41: =SUM(P40) -> 0 | Q41: =SUM(Q40) -> 0 | R41: =SUM(P41:Q41) -> 0
A42: Other Direct Costs
A43: Project Office
A44: Banking and cash handling fees | B44: Office Expenses | C44: 1 | D44: Month | E44: 6 | F44: 50 | G44: =F44*E44*C44 -> 300 | H44: 12 | I44: =H44*$F44*$C44*$B$5 -> 624 | J44: 12 | K44: =J44*$F44*$C44*$B$5*$B$5 -> 648.96 | L44: 7 | M44: =L44*$F44*$C44*$B$5*$B$5*$B$5 -> 393.7024 | O44: =N44*$F44*$C44*$B$5*$B$5*$B$5*$B$5 -> 0 | P44: =SUM(G44,I44,K44,M44,O44) -> 1966.6624 | Q44: 0 | R44: =SUM(P44:Q44) -> 1966.6624
A45: Licenses & Subscriptions (Microsoft 365, Azure, GoDaddy, VozLaboral) | B45: Office Expenses | C45: 1 | D45: Month | E45: 6 | F45: 200 | G45: =F45*E45*C45 -> 1200 | H45: 12 | I45: =H45*$F45*$C45*$B$5 -> 2496 | J45: 12 | K45: =J45*$F45*$C45*$B$5*$B$5 -> 2595.84 | L45: 7 | M45: =L45*$F45*$C45*$B$5*$B$5*$B$5 -> 1574.8096 | O45: =N45*$F45*$C45*$B$5*$B$5*$B$5*$B$5 -> 0 | P45: =SUM(G45,I45,K45,M45,O45) -> 7866.6496 | Q45: 0 | R45: =SUM(P45:Q45) -> 7866.6496
A46: Subtotal Project Office | G46: =SUM(G44:G45) -> 1500 | I46: =SUM(I44:I45) -> 3120 | K46: =SUM(K44:K45) -> 3244.8 | M46: =SUM(M44:M45) -> 1968.512 | O46: =SUM(O44:O45) -> 0 | P46: =SUM(P44:P45) -> 9833.312 | Q46: =SUM(Q44:Q45) -> 0 | R46: =SUM(R44:R45) -> 9833.312
A47: Outcome 3: Workers' and Workers' Organizations Capacity Improved to Effectively Negotiate Meaningful Improvements in Wages and Working Conditions
A48: Activity 8: Increase Transparency to Strengthen Collective Bargaining
A49: Meetings to promote CONDATOS | B49: Outcome3 | C49: 1 | D49: Activity | E49: 0 | F49: ='Expenses - Unit Costs'!$K$4 -> 360 | G49: =F49*E49*C49 -> 0 | H49: 10 | I49: =H49*$F49*$C49 -> 3600 | J49: 5 | K49: =J49*$F49*$C49*$B$5 -> 1872 | L49: 5 | M49: =L49*$F49*$C49*$B$5*$B$5 -> 1946.88 | O49: =N49*$F49*$C49*$B$5*$B$5*$B$5*$B$5 -> 0 | P49: =SUM(G49,I49,K49,M49,O49) -> 7418.88 | Q49: 0 | R49: =SUM(P49:Q49) -> 7418.88
A50: Ads campaign to promote CONDATOS | B50: Outcome3 | C50: 1 | D50: Ads | E50: 0 | F50: 1800 | G50: =F50*E50*C50 -> 0 | H50: 0 | I50: =H50*$F50*$C50*$B$5 -> 0 | J50: 12 | K50: =J50*$F50*$C50 -> 21600 | L50: 7 | M50: =L50*$F50*$C50*$B$5 -> 13104 | O50: =N50*$F50*$C50*$B$5*$B$5*$B$5*$B$5 -> 0 | P50: =SUM(G50,I50,K50,M50,O50) -> 34704 | Q50: 0 | R50: =SUM(P50:Q50) -> 34704
A51: Presentations of CONDATOS with democratically elected unions | B51: Outcome3 | C51: 1 | D51: Presentations | E51: 0 | F51: ='Expenses - Unit Costs'!$K$5 -> 5940 | G51: =F51*E51*C51 -> 0 | H51: 0 | I51: =H51*$F51*$C51*$B$5 -> 0 | J51: 0 | K51: =J51*$F51*$C51*$B$5*$B$5 -> 0 | L51: 5 | M51: =L51*$F51*$C51 -> 29700 | O51: =N51*$F51*$C51*$B$5*$B$5*$B$5*$B$5 -> 0 | P51: =SUM(G51,I51,K51,M51,O51) -> 29700 | Q51: 0 | R51: =SUM(P51:Q51) -> 29700
A52: Activity 9: Increase Union Capacity to Submit Effective Petitions under the RRM of the USMCA
A53: Workshops designed to strengthen the capacity of unions to submit effective petitions under the Rapid Response Mechanism | B53: Outcome3 | C53: 1 | D53: Workshop | E53: 0 | F53: ='Expenses - Unit Costs'!$K$12 -> 1600 | G53: 0 | H53: 2 | I53: =H53*$F53*$C53 -> 3200 | J53: 4 | K53: =J53*$F53*$C53*$B$5 -> 6656 | L53: 4 | M53: =L53*$F53*$C53*$B$5*$B$5 -> 6922.24 | P53: =SUM(G53,I53,K53,M53,O53) -> 16778.24 | Q53: 0 | R53: =SUM(P53:Q53) -> 16778.24
A54: Activity 11: Build a New Generation of Union Leadership
A55: Miscellaneous expenses for union leaders training | B55: Outcome 3 | C55: 1 | D55: Materials | F55: 1500 | G55: =F55*E55*C55 -> 0 | H55: 1 | I55: =H55*$F55*$C55 -> 1500 | J55: 1 | K55: =J55*$F55*$C55*$B$5 -> 1560 | L55: 1 | M55: =L55*$F55*$C55*$B$5*$B$5 -> 1622.4 | O55: =N55*$F55*$C55*$B$5*$B$5*$B$5*$B$5 -> 0 | P55: =SUM(G55,I55,K55,M55,O55) -> 4682.4 | Q55: 0 | R55: =SUM(P55:Q55) -> 4682.4
A56: Educational materials for participants | B56: Outcome 3 | C56: 1 | D56: Materials | F56: 35 | G56: =F56*E56*C56 -> 0 | H56: 40 | I56: =H56*$F56*$C56 -> 1400 | J56: 40 | K56: =J56*$F56*$C56*$B$5 -> 1456 | L56: 20 | M56: =L56*$F56*$C56*$B$5*$B$5 -> 757.12 | O56: =N56*$F56*$C56*$B$5*$B$5*$B$5*$B$5 -> 0 | P56: =SUM(G56,I56,K56,M56,O56) -> 3613.12 | Q56: 0 | R56: =SUM(P56:Q56) -> 3613.12
A57: Equipment for trainings for union leaders | B57: Outcome 3 | C57: 1 | D57: Materials | F57: 2280 | G57: =F57*E57*C57 -> 0 | H57: 1 | I57: =H57*$F57*$C57 -> 2280 | J57: 1 | K57: =J57*$F57*$C57*$B$5 -> 2371.2 | L57: 1 | M57: =L57*$F57*$C57*$B$5*$B$5 -> 2466.048 | O57: =N57*$F57*$C57*$B$5*$B$5*$B$5*$B$5 -> 0 | P57: =SUM(G57,I57,K57,M57,O57) -> 7117.248 | Q57: 0 | R57: =SUM(P57:Q57) -> 7117.248
A58: Venue and coffee break for participants | B58: Outcome 3 | C58: 1 | D58: Meeting | F58: =190*43 -> 8170 | G58: =F58*E58*C58 -> 0 | H58: 1 | I58: =H58*$F58*$C58 -> 8170 | J58: 1 | K58: =J58*$F58*$C58*$B$5 -> 8496.8 | L58: 1 | M58: =L58*$F58*$C58*$B$5*$B$5 -> 8836.672 | O58: =N58*$F58*$C58*$B$5*$B$5*$B$5*$B$5 -> 0 | P58: =SUM(G58,I58,K58,M58,O58) -> 25503.472 | Q58: 0 | R58: =SUM(P58:Q58) -> 25503.472
A59: Subtotal Outcome 3 | G59: =SUM(G48:G58) -> 0 | I59: =SUM(I48:I58) -> 20150 | K59: =SUM(K48:K58) -> 44012 | M59: =SUM(M48:M58) -> 65355.36 | O59: =SUM(O48:O58) -> 0 | P59: =SUM(P48:P58) -> 129517.36 | Q59: =SUM(Q48:Q58) -> 0 | R59: =SUM(R48:R58) -> 129517.36
A61: Total Other Direct Costs | G61: =SUM(G44:G59)/2 -> 1500 | I61: =SUM(I44:I59)/2 -> 23270 | K61: =SUM(K44:K59)/2 -> 47256.8 | M61: =SUM(M44:M59)/2 -> 67323.872 | O61: =SUM(O44:O59)/2 -> 0 | P61: =SUM(P44:P59)/2 -> 139350.67 | Q61: =SUM(Q44:Q59)/2 -> 0 | R61: =SUM(R44:R59)/2 -> 139350.67
A63: Total Direct Costs | G63: =SUM(G14+G17+G27+G34++G61+G38+G30+G41) -> 49315.062 | I63: =SUM(I14+I17+I27+I34++I61+I38+I30+I41) -> 214600.88 | K63: =SUM(K14+K17+K27+K34++K61+K38+K30+K41) -> 250632.34 | M63: =SUM(M14+M17+M27+M34++M61+M38+M30+M41) -> 180644.61 | O63: =SUM(O14+O17+O27+O34++O61+O38+O30+O41) -> 0 | P63: =SUM(P14+P17+P27+P34++P61+P38+P30+P41) -> 695192.9 | Q63: =SUM(Q14+Q17+Q27+Q34++Q61+Q38+Q30+Q41) -> 0 | R63: =SUM(R14+R17+R27+R34++R61+R38+R30+R41) -> 695192.9
A65: De minimis rate | B65: Indirect Charges | F65: 0.15 | G65: =(G63)*$F$65 -> 7397.2593 | I65: =(I63)*$F$65 -> 32190.132 | K65: =(K63)*$F$65 -> 37594.852 | M65: =(M63)*$F$65 -> 27096.691 | O65: =(O63)*$F$65 -> 0 | P65: =SUM(G65,I65,K65,M65,O65) -> 104278.93 | Q65: 0 | R65: =SUM(P65:Q65) -> 104278.93
A67: TOTAL PROGRAM COSTS | G67: =G63+G65 -> 56712.321 | I67: =I63+I65 -> 246791.02 | K67: =K63+K65 -> 288227.19 | M67: =M63+M65 -> 207741.3 | O67: =O63+O65 -> 0 | P67: =P63+P65 -> 799471.83 | Q67: =Q63+Q65 -> 0 | R67: =SUM(P67:Q67) -> 799471.83

Sheet Travel
A1: TC | B1: 18.5
A4: Domestic travel
B5: Lodging | C5: Per Diem | D5: Airfare (round) | E5: Ground transportation (round) | F5: Max lodging
A6: CDMX
A7: QRO | B7: =AVERAGE(2100,1750,1662,788,1746)/$B$1 -> 86.983784 | C7: =123 -> 123 | D7: =AVERAGE(10117,11683)/$B$1 -> 589.18919 | E7: 50 | F7: 210
A8: BC | B8: =AVERAGE(2343,2933,2273,1562,1889,2014)/$B$1 -> 117.24324 | C8: =101 -> 101 | D8: =AVERAGE(4274,4439,4532,4536,4547)/$B$1 -> 241.38378 | E8: 50 | F8: 193
A9: GTO | B9: =AVERAGE(2075,601,1984,777,1283,2355,2455)/$B$1 -> 89.034749 | C9: =110 -> 110 | D9: =AVERAGE(7356,7820,10470,10682)/$B$1 -> 490.91892 | E9: 50 | F9: 141
A10: JAL | B10: =AVERAGE(1203,2371,906,858,2371,2434)/$B$1 -> 91.378378 | C10: =121 -> 121 | D10: =AVERAGE(1543,2444,2879,2883)/$B$1 -> 131.74324 | E10: 50 | F10: 241
A11: Average | B11: =AVERAGE(B6:B10) -> 96.160039 | C11: =AVERAGE(C6:C10) -> 113.75 | D11: =AVERAGE(D6:D10) -> 363.30878 | E11: =AVERAGE(E6:E10) -> 50 | F11: =AVERAGE(F6:F10) -> 196.25
A12: 0.5 | C12: =+C11*0.5 -> 56.875
A16: International travel
A18: CDMX-DC | B18: =AVERAGE(14811,19251)/$B$1 -> 920.59459
A19: CDMX lodging | B19: =AVERAGE(3680,1721,1092,2233)/$B$1 -> 117.91892
A20: CDMX M&IE | B20: =126*0.9 -> 113.4
A21: DC lodging | B21: 183
A22: DC M&IE | B22: =92*0.9 -> 82.8
A27: International travel - labor experts
A28: Colombia-CDMX | B28: =AVERAGE(9986,10307,11289) -> 10527.333
A29: Paraguay-CDMX | B29: =AVERAGE(14336,14605,16704) -> 15215
A30: Uruguay-CDMX | B30: =AVERAGE(16220,17106,18138,20211,21372) -> 18609.4
A31: Argentina-CDMX | B31: =AVERAGE(17095,18998) -> 18046.5
A32: Chile-CDMX | B32: =AVERAGE(11637,12408,13044,13990) -> 12769.75
A33: Brazil-CDMX | B33: =AVERAGE(9364,9410,13836) -> 10870
A34: DC-CDMX | B34: 17031
A35: Average | B35: =AVERAGE(B28:B34) -> 14724.14
A36: Average USD | B36: =+B35/$B$1 -> 795.89949

Sheet Expenses - Unit Costs
A1: Unit cost
A3: Category | B3: Activity | C3: Unit | D3: # of persons | E3: Coffee break | F3: Lunch | G3: Printing materials | H3: Other logistic material | I3: Back | J3: Venue (A/V Equipment, Materials, etc.) | K3: Total
A4: Activity 1.1 - TRACE: Targeted Response and Coordination for Enforcement – ITAM | B4: State and Local Coordination Meetings to Launch and Monitor the Enforcement Information System | C4: Meeting | D4: 15 | E4: 5 | F4: 14 | G4: 5 | K4: =(SUM(E4:H4)*D4)+SUM(I4:J4) -> 360
A5: Activity 1.2 - Strengthening SINACOL as a National Data Platform | B5: National CONACENTROS Meetings to Promote Open Data Adoption | C5: Meeting | D5: 60 | E5: 5 | F5: 14 | G5: 5 | I5: 500 | J5: 4000 | K5: =(SUM(E5:H5)*D5)+SUM(I5:J5) -> 5940
A6: Activity 1.3 - Strengthening Collective Conciliation During the Pre-Strike (Bargaining) Period through Collective platform (Developed in partnership with ITAM) | B6: Coordination Meetings with State Labor Courts and Conciliation Centers | C6: Meeting | D6: 15 | E6: 5 | F6: 14 | G6: 5 | K6: =(SUM(E6:H6)*D6)+SUM(I6:J6) -> 360
A7: Activity 1.4 - Training Modules for State Labor Authorities | B7: Graduation Ceremonies for State Labor Authorities | C7: Ceremony | D7: 50 | E7: 5 | F7: 14 | G7: 10 | J7: 2500 | K7: =(SUM(E7:H7)*D7)+SUM(I7:J7) -> 3950
A8: Activity 2.1 - Improved Dialogue between Employers and Local Labor Authorities | B8: Summits to Strengthen Dialogue between Employers and Local Labor Authorities | C8: Summit | D8: 100 | E8: 5 | F8: 14 | G8: 10 | I8: 500 | J8: 4000 | K8: =(SUM(E8:H8)*D8)+SUM(I8:J8) -> 7400
A9: Activity 2.2 - Strengthen SMEs’ Knowledge of and Compliance with Labor Reforms and USMCA Commitments | B9: Workshops to Strengthen SMEs’ Knowledge of Labor Rights and Trade Commitments | C9: Training | D9: 30 | E9: 5 | F9: 14 | G9: 5 | J9: 1500 | K9: =(SUM(E9:H9)*D9)+SUM(I9:J9) -> 2220
A10: Activity 2.3 - Meetings to pilot Labor Rights Compliance Checklist to Strengthen Compliance Across Priority Sectors and States | B10: Meetings to pilot Labor Rights Compliance Checklist to Strengthen Compliance Across Priority Sectors and States | C10: Meetings | D10: 10 | E10: 5 | F10: 14 | G10: 5 | K10: =(SUM(E10:H10)*D10)+SUM(I10:J10) -> 240
A11: Activity 3.1 - CONDATOS: A Co-Developed Digital Platform to Benchmark Collective Bargaining Agreements, Expand Transparency, and Strengthen Workers’ Negotiating Power | B11: Meetings with democratically elected unions | C11: Meeting | D11: 10 | E11: 5 | F11: 14 | G11: 5 | K11: =(SUM(E11:H11)*D11)+SUM(I11:J11) -> 240
A12: Activity 3.1 - CONDATOS: A Co-Developed Digital Platform to Benchmark Collective Bargaining Agreements, Expand Transparency, and Strengthen Workers’ Negotiating Power | B12: Presentations with democratically elected unions | C12: Workshop | D12: 25 | E12: 5 | F12: 14 | G12: 5 | J12: 1000 | K12: =(SUM(E12:H12)*D12)+SUM(I12:J12) -> 1600
A13: Activity 3.2 - Strengthening Union Capacity to Submit Effective Petitions Under the Rapid Response Mechanism | B13: Workshop expenses to ensure outreach and consultation with stakeholders | C13: Workshop | D13: 10 | E13: 5 | F13: 14 | G13: 5 | K13: =(SUM(E13:H13)*D13)+SUM(I13:J13) -> 240
A14: Activity 3.2 - Strengthening Union Capacity to Submit Effective Petitions Under the Rapid Response Mechanism | B14: Printing and dissemination of developed tool | C14: Materials | D14: 700 | G14: 10 | K14: =(SUM(E14:H14)*D14)+SUM(I14:J14) -> 7000
A15: Activity 3.3 - Building Union-to-Union Exchanges to Strengthen Collective Bargaining Capacity | B15: International workshops to Strengthen Collective Bargaining Capacity | C15: Workshop | D15: 100 | E15: 5 | F15: 14 | G15: 10 | H15: 30 | I15: 500 | J15: 4000 | K15: =(SUM(E15:H15)*D15)+SUM(I15:J15) -> 10400
A16: Activity 3.3 - Building Union-to-Union Exchanges to Strengthen Collective Bargaining Capacity | B16: Printing materials | C16: Materials | D16: 50 | G16: 10 | K16: =(SUM(E16:H16)*D16)+SUM(I16:J16) -> 500
A17: 4.5 Stakeholder Engagement and Strategy Validation | B17: Workshops with Stakeholders to validate project strategies | C17: Meeting | D17: 15 | E17: 5 | F17: 14 | G17: 5 | J17: 1000 | K17: =(SUM(E17:H17)*D17)+SUM(I17:J17) -> 1360
