Workbook

Sheet Budget Summary
A1: PARTNERS OF THE AMERICAS
A2: SUMMARY BUDGET FOR MEXICO MIGRATION MESSAGING EXTENSION
B3: Year 1 | E3: Year 2 (Oct 2024 - Sept 2025) | H3: Year 3 (Oct 2025 - Sept 2026) | K3: Year 4 (Oct 2026 - Apr 2027) | N3: Total
A4: BUDGET SUMMARY CATEGORIES | B4: Grant | C4: Cost Share | D4: Total | E4: Grant | F4: Cost Share | G4: Total | H4: Grant | I4: Cost Share | J4: Total | K4: Grant | L4: Cost Share | M4: Total | N4: Grant | O4: Cost Share | P4: Total
A5: A. Personnel | B5: =+'Line Item Budget'!K20 -> 80210 | C5: =+'Line Item Budget'!L20 -> 0 | D5: =B5+C5 -> 80210 | E5: =+'Line Item Budget'!S20 -> 99954.4 | F5: =+'Line Item Budget'!T20 -> 0 | G5: =E5+F5 -> 99954.4 | H5: =+'Line Item Budget'!AA20 -> 114905.7 | I5: =+'Line Item Budget'!AB20 -> 0 | J5: =H5+I5 -> 114905.7 | K5: =+'Line Item Budget'!AI20 -> 59635.107 | L5: =+'Line Item Budget'!AJ20 -> 0 | M5: =K5+L5 -> 59635.107 | N5: =+B5+E5+H5+K5 -> 354705.21 | O5: =+C5+F5+I5+L5 -> 0 | P5: =+N5+O5 -> 354705.21
A6: B. Fringe Benefits | B6: =+'Line Item Budget'!K26 -> 27988.691 | C6: =+'Line Item Budget'!L26 -> 0 | D6: =B6+C6 -> 27988.691 | E6: =+'Line Item Budget'!S26 -> 32989.238 | F6: =+'Line Item Budget'!T26 -> 0 | G6: =E6+F6 -> 32989.238 | H6: =+'Line Item Budget'!AA26 -> 53739.035 | I6: =+'Line Item Budget'!AB26 -> 0 | J6: =H6+I6 -> 53739.035 | K6: =+'Line Item Budget'!AI26 -> 27864.962 | L6: =+'Line Item Budget'!AJ26 -> 0 | M6: =K6+L6 -> 27864.962 | N6: =+B6+E6+H6+K6 -> 142581.93 | O6: =+C6+F6+I6+L6 -> 0 | P6: =+N6+O6 -> 142581.93
A7: C. Travel | B7: =+'Line Item Budget'!K38 -> 7135 | C7: =+'Line Item Budget'!L38 -> 0 | D7: =B7+C7 -> 7135 | E7: =+'Line Item Budget'!S38 -> 7420.4 | F7: =+'Line Item Budget'!T38 -> 0 | G7: =E7+F7 -> 7420.4 | H7: =+'Line Item Budget'!AA38 -> 2573 | I7: =+'Line Item Budget'!AB38 -> 0 | J7: =H7+I7 -> 2573 | K7: =+'Line Item Budget'!AI38 -> 1175.2 | L7: =+'Line Item Budget'!AJ38 -> 0 | M7: =K7+L7 -> 1175.2 | N7: =+B7+E7+H7+K7 -> 18303.6 | O7: =+C7+F7+I7+L7 -> 0 | P7: =+N7+O7 -> 18303.6
A8: D. Equipment
A9: E. Supplies | B9: =+'Line Item Budget'!K44 -> 3600 | C9: =+'Line Item Budget'!L44 -> 0 | D9: =B9+C9 -> 3600 | E9: =+'Line Item Budget'!S44 -> 3046 | F9: =+'Line Item Budget'!T44 -> 0 | G9: =E9+F9 -> 3046 | H9: =+'Line Item Budget'!AA44 -> 374.4 | I9: =+'Line Item Budget'!AB44 -> 0 | J9: =H9+I9 -> 374.4 | K9: =+'Line Item Budget'!AI44 -> 193.8 | L9: =+'Line Item Budget'!AJ44 -> 0 | M9: =K9+L9 -> 193.8 | N9: =+B9+E9+H9+K9 -> 7214.2 | O9: =+C9+F9+I9+L9 -> 0 | P9: =+N9+O9 -> 7214.2
A10: F. Contractual and Subawards | B10: =+'Line Item Budget'!K61 -> 115900 | C10: =+'Line Item Budget'!L61 -> 0 | D10: =B10+C10 -> 115900 | E10: =+'Line Item Budget'!S61 -> 324287.42 | F10: =+'Line Item Budget'!T61 -> 0 | G10: =E10+F10 -> 324287.42 | H10: =+'Line Item Budget'!AA61 -> 535208.17 | I10: =+'Line Item Budget'!AB61 -> 0 | J10: =H10+I10 -> 535208.17 | K10: =+'Line Item Budget'!AI61 -> 46687.417 | L10: =+'Line Item Budget'!AJ61 -> 0 | M10: =K10+L10 -> 46687.417 | N10: =+B10+E10+H10+K10 -> 1022083 | O10: =+C10+F10+I10+L10 -> 0 | P10: =+N10+O10 -> 1022083
A11: G. Construction
A12: H. Other Direct Costs | B12: =+'Line Item Budget'!K86 -> 39031 | C12: =+'Line Item Budget'!L86 -> 0 | D12: =B12+C12 -> 39031 | E12: =+'Line Item Budget'!S86 -> 251211.64 | F12: =+'Line Item Budget'!T86 -> 0 | G12: =E12+F12 -> 251211.64 | H12: =+'Line Item Budget'!AA86 -> 48315.04 | I12: =+'Line Item Budget'!AB86 -> 0 | J12: =H12+I12 -> 48315.04 | K12: =+'Line Item Budget'!AI86 -> 23728.089 | L12: =+'Line Item Budget'!AJ86 -> 0 | M12: =K12+L12 -> 23728.089 | N12: =+B12+E12+H12+K12 -> 362285.77 | O12: =+C12+F12+I12+L12 -> 0 | P12: =+N12+O12 -> 362285.77
A13: I. Total Direct Costs | B13: =SUM(B5:B12) -> 273864.69 | C13: =SUM(C5:C12) -> 0 | D13: =B13+C13 -> 273864.69 | E13: =SUM(E5:E12) -> 718909.09 | F13: =SUM(F5:F12) -> 0 | G13: =E13+F13 -> 718909.09 | H13: =SUM(H5:H12) -> 755115.34 | I13: =SUM(I5:I12) -> 0 | J13: =H13+I13 -> 755115.34 | K13: =SUM(K5:K12) -> 159284.57 | L13: =SUM(L5:L12) -> 0 | M13: =K13+L13 -> 159284.57 | N13: =+B13+E13+H13+K13 -> 1907173.7 | O13: =+C13+F13+I13+L13 -> 0 | P13: =+N13+O13 -> 1907173.7
A14: J. Indirect Costs | B14: =+'Line Item Budget'!K89 -> 77448.935 | C14: =+'Line Item Budget'!L89 -> 0 | D14: =B14+C14 -> 77448.935 | E14: =+'Line Item Budget'!S89 -> 203307.49 | F14: =+'Line Item Budget'!T89 -> 0 | G14: =E14+F14 -> 203307.49 | H14: =+'Line Item Budget'!AA89 -> 213546.62 | I14: =+'Line Item Budget'!AB89 -> 0 | J14: =H14+I14 -> 213546.62 | K14: =+'Line Item Budget'!AI89 -> 45048.128 | L14: =+'Line Item Budget'!AJ89 -> 0 | M14: =K14+L14 -> 45048.128 | N14: =+B14+E14+H14+K14 -> 539351.17 | O14: =+C14+F14+I14+L14 -> 0 | P14: =+N14+O14 -> 539351.17
A15: K. Total Costs | B15: =+B13+B14 -> 351313.63 | C15: =+C13+C14 -> 0 | D15: =D13+D14 -> 351313.63 | E15: =+E13+E14 -> 922216.59 | F15: =+F13+F14 -> 0 | G15: =G13+G14 -> 922216.59 | H15: =+H13+H14 -> 968661.96 | I15: =+I13+I14 -> 0 | J15: =J13+J14 -> 968661.96 | K15: =+K13+K14 -> 204332.7 | L15: =+L13+L14 -> 0 | M15: =M13+M14 -> 204332.7 | N15: =N14+N13 -> 2446524.9 | O15: =+C15+F15+I15+L15 -> 0 | P15: =+N15+O15 -> 2446524.9

Sheet Line Item Budget
D1: PARTNERS OF THE AMERICAS - Mexico Migration Messaging Project (MMMP) - Cost Extension
A2: Entity: | B2: P | D2: Merit and Cost of Living Increases - 5% | E2: 1.05
A3: Program/Dept.: | B3: 20200 | D3: Inflation - 4% | E3: 1.04 | O3: Change in calculation component | R3: Green Text is Budget 01 | T3: Black Text is Budget 02 | V3: Purple Text has Budget 01 + 02
A4: Funder-Grant: | B4: DOS453
A5: Budget Code | B5: Account Code | C5: Country Code | D5: All costs in US$ | E5: Year 1 (Oct 2023 - Sept 2024) | M5: Year 2 (October 2024 - September 2025) | U5: Year 3 (October 2025 - September 2026) | AC5: Year 4 (October 2026 - April 2027) | AK5: Total
D6: Budget Line Items | E6: No. | F6: Unit Type | G6: Freq. | H6: % | I6: Rate | J6: Total | K6: Federal | L6: Cost Share | M6: No. | N6: Unit Type | O6: Freq. | P6: % | Q6: Rate | R6: Total | S6: Federal | T6: Cost Share | U6: No. | V6: Unit Type | W6: Freq. | X6: % | Y6: Rate | Z6: Total | AA6: Federal | AB6: Cost Share | AC6: No. | AD6: Unit Type | AE6: Freq. | AF6: % | AG6: Rate | AH6: Total | AI6: Federal | AJ6: Cost Share | AK6: Federal | AL6: Cost Share | AM6: Grand Total
D7: A. Personnel
D8: A.1 Field Staff Salaries
A9: PERSNL-CDM | B9: 70000 | C9: MEX | D9: A.1.1 Country Director Mexico | E9: 1 | F9: Month | G9: 12 | H9: 0.05 | I9: 13450 | J9: =E9*I9*G9*H9 -> 8070 | K9: =J9 -> 8070 | L9: =J9-K9 -> 0 | M9: 1 | N9: Month | O9: 12 | P9: 0.05 | Q9: =+I9*1.04 -> 13988 | R9: =M9*Q9*O9*P9 -> 8392.8 | S9: =R9 -> 8392.8 | T9: =R9-S9 -> 0 | AK9: =K9+S9+AA9+AI9 -> 16462.8 | AL9: =L9+T9+AB9+AJ9 -> 0 | AM9: =+AK9+AL9 -> 16462.8
A10: PERSNL-PD | B10: 70000 | C10: MEX | D10: A.1.2 Program Director/Coordinator | E10: 1 | F10: Month | G10: 12 | H10: 0.1 | I10: 8650 | J10: =E10*I10*G10*H10 -> 10380 | K10: =J10 -> 10380 | L10: =J10-K10 -> 0 | M10: 1 | N10: Month | O10: 12 | P10: 0.1 | Q10: =I10*$E$3 -> 8996 | R10: =M10*Q10*O10*P10 -> 10795.2 | S10: =R10 -> 10795.2 | T10: =R10-S10 -> 0 | U10: 1 | V10: Month | W10: 12 | X10: 1 | Y10: 4830 | Z10: =U10*Y10*W10*X10 -> 57960 | AA10: =Z10 -> 57960 | AB10: =Z10-AA10 -> 0 | AC10: 1 | AD10: Month | AE10: 7 | AF10: 1 | AG10: =Y10*$E$2 -> 5071.5 | AH10: =AC10*AG10*AE10*AF10 -> 35500.5 | AI10: =AH10 -> 35500.5 | AJ10: =AH10-AI10 -> 0 | AK10: =K10+S10+AA10+AI10 -> 114635.7 | AL10: =L10+T10+AB10+AJ10 -> 0 | AM10: =+AK10+AL10 -> 114635.7
A11: PERSNL-SCS | B11: 70000 | C11: MEX | D11: A.1.3 Senior Communications Specialist | E11: 1 | F11: Month | G11: 12 | H11: 0.3 | I11: 4100 | J11: =E11*I11*G11*H11 -> 14760 | K11: =J11 -> 14760 | L11: =J11-K11 -> 0 | M11: 1 | N11: Month | O11: 12 | P11: 0.3 | Q11: =+I11*1.04 -> 4264 | R11: =M11*Q11*O11*P11 -> 15350.4 | S11: =R11 -> 15350.4 | T11: =R11-S11 -> 0 | AK11: =K11+S11+AA11+AI11 -> 30110.4 | AL11: =L11+T11+AB11+AJ11 -> 0 | AM11: =+AK11+AL11 -> 30110.4
A12: PERSNL-COM | B12: 70000 | C12: MEX | D12: A.1.4 Communications Specialist | E12: 1 | F12: Month | G12: 12 | H12: 0.3 | I12: 3000 | J12: =E12*I12*G12*H12 -> 10800 | K12: =J12 -> 10800 | L12: =J12-K12 -> 0 | M12: 1 | N12: Month | O12: 12 | P12: 0.3 | Q12: =I12*E3 -> 3120 | R12: =M12*Q12*O12*P12 -> 11232 | S12: =R12 -> 11232 | T12: =R12-S12 -> 0 | U12: 1 | V12: Month | W12: 12 | X12: 0.75 | Y12: =2300*$E$2 -> 2415 | Z12: =U12*Y12*W12*X12 -> 21735 | AA12: =Z12 -> 21735 | AB12: =Z12-AA12 -> 0 | AC12: 1 | AD12: Month | AE12: 3 | AF12: 0.75 | AG12: =Y12*$E$2 -> 2535.75 | AH12: =AC12*AG12*AE12*AF12 -> 5705.4375 | AI12: =AH12 -> 5705.4375 | AJ12: =AH12-AI12 -> 0 | AK12: =K12+S12+AA12+AI12 -> 49472.438 | AL12: =L12+T12+AB12+AJ12 -> 0 | AM12: =+AK12+AL12 -> 49472.438
A13: PERSNL-SMA | B13: 70000 | C13: MEX | D13: A.1.5 Social Media Analyst | E13: 1 | F13: Month | G13: 12 | H13: 0.3 | I13: 2100 | J13: =E13*I13*G13*H13 -> 7560 | K13: =J13 -> 7560 | L13: =J13-K13 -> 0 | M13: 1 | N13: Month | O13: 12 | P13: 0.3 | Q13: =+I13*1.04 -> 2184 | R13: =M13*Q13*O13*P13 -> 7862.4 | S13: =R13 -> 7862.4 | T13: =R13-S13 -> 0 | AK13: =K13+S13+AA13+AI13 -> 15422.4 | AL13: =L13+T13+AB13+AJ13 -> 0 | AM13: =+AK13+AL13 -> 15422.4
A14: PERSNL-M&E | B14: 70000 | C14: MEX | D14: A.1.6 Monitoring, Evaluation, and Learning Officer | E14: 1 | F14: Month | G14: 12 | H14: 0.25 | I14: 3100 | J14: =E14*I14*G14*H14 -> 9300 | K14: =J14 -> 9300 | L14: =J14-K14 -> 0 | M14: 1 | N14: Month | O14: 12 | P14: 0.25 | Q14: =+I14*1.04 -> 3224 | R14: =M14*Q14*O14*P14 -> 9672 | S14: =R14 -> 9672 | T14: =R14-S14 -> 0 | AK14: =K14+S14+AA14+AI14 -> 18972 | AL14: =L14+T14+AB14+AJ14 -> 0 | AM14: =+AK14+AL14 -> 18972
A15: PERSNL-F&A | B15: 70000 | C15: MEX | D15: A.1.7 Finance & Administration Director | E15: 1 | F15: Month | G15: 12 | H15: 0.05 | I15: 5500 | J15: =E15*I15*G15*H15 -> 3300 | K15: =J15 -> 3300 | L15: =J15-K15 -> 0 | M15: 1 | N15: Month | O15: 12 | P15: 0.05 | Q15: =+I15*1.04 -> 5720 | R15: =M15*Q15*O15*P15 -> 3432 | S15: =R15 -> 3432 | T15: =R15-S15 -> 0 | AK15: =K15+S15+AA15+AI15 -> 6732 | AL15: =L15+T15+AB15+AJ15 -> 0 | AM15: =+AK15+AL15 -> 6732
A16: PERSNL-F&A | B16: 70000 | C16: MEX | D16: A.1.8 Finance & Administration Officer | E16: 1 | F16: Month | G16: 12 | H16: 0.2 | I16: 2100 | J16: =E16*I16*G16*H16 -> 5040 | K16: =J16 -> 5040 | L16: =J16-K16 -> 0 | M16: 1 | N16: Month | O16: 12 | P16: 0.2 | Q16: =I16*1.04 -> 2184 | R16: =M16*Q16*O16*P16 -> 5241.6 | S16: =R16 -> 5241.6 | T16: =R16-S16 -> 0 | U16: 1 | V16: Month | W16: 12 | X16: 0.5 | Y16: =1833*$E$2 -> 1924.65 | Z16: =U16*Y16*W16*X16 -> 11547.9 | AA16: =Z16 -> 11547.9 | AB16: =Z16-AA16 -> 0 | AC16: 1 | AD16: Month | AE16: 6 | AF16: 0.5 | AG16: =Y16*$E$2 -> 2020.8825 | AH16: =AC16*AG16*AE16*AF16 -> 6062.6475 | AI16: =AH16 -> 6062.6475 | AJ16: =AH16-AI16 -> 0 | AK16: =K16+S16+AA16+AI16 -> 27892.147 | AL16: =L16+T16+AB16+AJ16 -> 0 | AM16: =+AK16+AL16 -> 27892.147
D17: A.2 HQ Staff Salaries
A18: PERSNL | B18: 50000 | C18: USA | D18: A.2.1 Program Manager (HQ) | E18: 1 | F18: Month | G18: 12 | H18: 0.2 | I18: =55000/12 -> 4583.3333 | J18: =E18*I18*G18*H18 -> 11000 | K18: =J18 -> 11000 | L18: =J18-K18 -> 0 | M18: 1 | N18: Month | O18: 12 | P18: 0.2 | Q18: =I18*1.04 -> 4766.6667 | R18: =M18*Q18*O18*P18 -> 11440 | S18: =R18 -> 11440 | T18: =R18-S18 -> 0 | U18: 1 | V18: Month | W18: 12 | X18: 0.05 | Y18: =10000*$E$2 -> 10500 | Z18: =U18*Y18*W18*X18 -> 6300 | AA18: =Z18 -> 6300 | AB18: =Z18-AA18 -> 0 | AC18: 1 | AD18: Month | AE18: 7 | AF18: 0.05 | AG18: =Y18*$E$2 -> 11025 | AH18: =AC18*AG18*AE18*AF18 -> 3858.75 | AI18: =AH18 -> 3858.75 | AJ18: =AH18-AI18 -> 0 | AK18: =K18+S18+AA18+AI18 -> 32598.75 | AL18: =L18+T18+AB18+AJ18 -> 0 | AM18: =+AK18+AL18 -> 32598.75
A19: PERSNL-PO | B19: 50000 | C19: USA | D19: A.2.2. Program Officer (HQ) | E19: 0 | F19: Month | G19: 0 | J19: =E19*I19*G19*H19 -> 0 | K19: =J19 -> 0 | L19: =J19-K19 -> 0 | M19: 1 | N19: Month | O19: 12 | P19: 0.25 | Q19: 5512 | R19: =M19*Q19*O19*P19 -> 16536 | S19: =R19 -> 16536 | T19: =R19-S19 -> 0 | U19: 1 | V19: Month | W19: 12 | X19: 0.25 | Y19: =Q19*$E$2 -> 5787.6 | Z19: =U19*Y19*W19*X19 -> 17362.8 | AA19: =Z19 -> 17362.8 | AB19: =Z19-AA19 -> 0 | AC19: 1 | AD19: Month | AE19: 7 | AF19: 0.2 | AG19: =Y19*$E$2 -> 6076.98 | AH19: =AC19*AG19*AE19*AF19 -> 8507.772 | AI19: =AH19 -> 8507.772 | AJ19: =AH19-AI19 -> 0 | AK19: =K19+S19+AA19+AI19 -> 42406.572 | AL19: =L19+T19+AB19+AJ19 -> 0 | AM19: =+AK19+AL19 -> 42406.572
D20: Subtotal Personnel | J20: =SUM(J9:J19) -> 80210 | K20: =SUM(K9:K19) -> 80210 | L20: =SUM(L9:L19) -> 0 | R20: =SUM(R9:R19) -> 99954.4 | S20: =SUM(S9:S19) -> 99954.4 | T20: =SUM(T9:T19) -> 0 | Z20: =SUM(Z9:Z19) -> 114905.7 | AA20: =SUM(AA9:AA19) -> 114905.7 | AB20: =SUM(AB9:AB19) -> 0 | AH20: =SUM(AH9:AH19) -> 59635.107 | AI20: =SUM(AI9:AI19) -> 59635.107 | AJ20: =SUM(AJ9:AJ19) -> 0 | AK20: =SUM(AK9:AK19) -> 354705.21 | AL20: =SUM(AL9:AL19) -> 0 | AM20: =SUM(AM9:AM19) -> 354705.21
D21: B. Fringe Benefits
D22: B.1 HQ Fringe Benefits
A23: FRINGE | B23: 50900 | C23: USA | D23: B.1.1 U.S.-Based Personnel Fringe Benefits | F23: % | H23: 0.2347 | J23: =$H23*SUM(J18:J19) -> 2581.7 | K23: =J23 -> 2581.7 | L23: 0 | N23: % | P23: 0.2347 | R23: =P23*SUM(R18:R19) -> 6565.9672 | S23: =R23 -> 6565.9672 | T23: 0 | V23: % | X23: 0.2347 | Z23: =X23*SUM(Z18:Z19) -> 5553.6592 | AA23: =Z23 -> 5553.6592 | AB23: 0 | AD23: % | AF23: 0.2347 | AH23: =AF23*SUM(AH18:AH19) -> 2902.4227 | AI23: =AH23 -> 2902.4227 | AJ23: 0 | AK23: =K23+S23+AA23+AI23 -> 17603.749 | AL23: =L23+T23+AB23+AJ23 -> 0 | AM23: =+AK23+AL23 -> 17603.749
D24: B.2 Field Fringe Benefits
A25: FRINGE-MX | B25: 70015 | C25: MEX | D25: B.2.1 Mexico Field Staff Fringe Benefits | F25: % | H25: 0.3671 | J25: =$H25*SUM(J9:J16) -> 25406.991 | K25: =J25 -> 25406.991 | L25: 0 | N25: % | P25: =H25 -> 0.3671 | R25: =P25*SUM(R9:R16) -> 26423.271 | S25: =R25 -> 26423.271 | T25: 0 | V25: % | X25: 0.5281 | Z25: =X25*SUM(Z10:Z16) -> 48185.375 | AA25: =Z25 -> 48185.375 | AB25: 0 | AD25: % | AF25: 0.5281 | AH25: =AF25*SUM(AH10:AH16) -> 24962.54 | AI25: =AH25 -> 24962.54 | AJ25: 0 | AK25: =K25+S25+AA25+AI25 -> 124978.18 | AL25: =L25+T25+AB25+AJ25 -> 0 | AM25: =+AK25+AL25 -> 124978.18
D26: Subtotal Fringe Benefits | J26: =SUM(J23:J25) -> 27988.691 | K26: =SUM(K23:K25) -> 27988.691 | L26: =SUM(L23:L25) -> 0 | R26: =SUM(R23:R25) -> 32989.238 | S26: =SUM(S23:S25) -> 32989.238 | T26: =SUM(T23:T25) -> 0 | Z26: =SUM(Z23:Z25) -> 53739.035 | AA26: =SUM(AA23:AA25) -> 53739.035 | AB26: =SUM(AB23:AB25) -> 0 | AH26: =SUM(AH23:AH25) -> 27864.962 | AI26: =SUM(AI23:AI25) -> 27864.962 | AJ26: =SUM(AJ23:AJ25) -> 0 | AK26: =SUM(AK23:AK25) -> 142581.93 | AL26: =SUM(AL23:AL25) -> 0 | AM26: =SUM(AM23:AM25) -> 142581.93
D27: C. Travel
D28: C.1 HQ Staff International Travel
A29: STFTRAVEL | B29: 86040 | C29: USA | D29: C.1.1 International Airfare (DC-MX) | E29: 1 | F29: Flight | G29: 1 | H29: 1 | I29: 700 | J29: =E29*I29*G29 -> 700 | K29: =J29 -> 700 | L29: =J29-K29 -> 0 | M29: 1 | N29: Flight | O29: 1 | P29: 1 | Q29: =+I29*1.04 -> 728 | R29: =M29*Q29*O29*P29 -> 728 | S29: =R29 -> 728 | T29: =R29-S29 -> 0 | AK29: =K29+S29+AA29+AI29 -> 1428 | AL29: =L29+T29+AB29+AJ29 -> 0 | AM29: =+AK29+AL29 -> 1428
A30: GROUNDTRAN | B30: 86000 | C30: USA | D30: C.1.2 Ground Transportation | E30: 1 | F30: Trip | G30: 1 | H30: 1 | I30: 100 | J30: =E30*I30*G30 -> 100 | K30: =J30 -> 100 | L30: =J30-K30 -> 0 | M30: 1 | N30: Trip | O30: 1 | P30: 1 | Q30: =+I30*1.04 -> 104 | R30: =M30*Q30*O30*P30 -> 104 | S30: =R30 -> 104 | T30: =R30-S30 -> 0 | AK30: =K30+S30+AA30+AI30 -> 204 | AL30: =L30+T30+AB30+AJ30 -> 0 | AM30: =+AK30+AL30 -> 204
A31: LODGING | B31: 86030 | C31: USA | D31: C.1.3 Lodging | E31: 1 | F31: Night | G31: 4 | H31: 1 | I31: 120 | J31: =E31*I31*G31 -> 480 | K31: =J31 -> 480 | L31: =J31-K31 -> 0 | M31: 1 | N31: Night | O31: 4 | P31: 1 | Q31: =+I31*1.04 -> 124.8 | R31: =M31*Q31*O31*P31 -> 499.2 | S31: =R31 -> 499.2 | T31: =R31-S31 -> 0 | AK31: =K31+S31+AA31+AI31 -> 979.2 | AL31: =L31+T31+AB31+AJ31 -> 0 | AM31: =+AK31+AL31 -> 979.2
A32: STFCN DIEM | B32: 86050 | C32: USA | D32: C.1.4 M&IE | E32: 1 | F32: Day | G32: 5 | H32: 1 | I32: 95 | J32: =E32*I32*G32 -> 475 | K32: =J32 -> 475 | L32: =J32-K32 -> 0 | M32: 1 | N32: Day | O32: 5 | P32: 1 | Q32: =+I32*1.04 -> 98.8 | R32: =M32*Q32*O32*P32 -> 494 | S32: =R32 -> 494 | T32: =R32-S32 -> 0 | AK32: =K32+S32+AA32+AI32 -> 969 | AL32: =L32+T32+AB32+AJ32 -> 0 | AM32: =+AK32+AL32 -> 969
D33: C.2 Local Staff In-Country Travel to Target Geographic Regions
A34: LSDOMAIR | B34: 86030 | C34: MEX | D34: C.2.1 Domestic Airfare | E34: 2 | F34: Flight | G34: 1 | H34: 1 | I34: 200 | J34: =E34*I34*G34 -> 400 | K34: =J34 -> 400 | L34: =J34-K34 -> 0 | M34: 2 | N34: Flight | O34: 1 | P34: 1 | Q34: =+I34*1.04 -> 208 | R34: =M34*Q34*O34*P34 -> 416 | S34: =R34 -> 416 | T34: =R34-S34 -> 0 | U34: 2 | V34: Flight | W34: 1 | X34: 1 | Y34: 208 | Z34: =+Y34*W34*U34*X34 -> 416 | AA34: =Z34 -> 416 | AB34: =Z34-AA34 -> 0 | AC34: 1 | AD34: Flight | AE34: 1 | AF34: 1 | AG34: =Y34*$E$3 -> 216.32 | AH34: =+AG34*AE34*AC34*$H34 -> 216.32 | AI34: =AH34 -> 216.32 | AJ34: =AH34-AI34 -> 0 | AK34: =K34+S34+AA34+AI34 -> 1448.32 | AL34: =L34+T34+AB34+AJ34 -> 0 | AM34: =+AK34+AL34 -> 1448.32
A35: LSLODGING | B35: 86050 | C35: MEX | D35: C.2.2 Lodging | E35: 6 | F35: Night | G35: 3 | H35: 1 | I35: 100 | J35: =E35*I35*G35 -> 1800 | K35: =J35 -> 1800 | L35: =J35-K35 -> 0 | M35: 6 | N35: Night | O35: 3 | P35: 1 | Q35: =+I35*1.04 -> 104 | R35: =M35*Q35*O35*P35 -> 1872 | S35: =R35 -> 1872 | T35: =R35-S35 -> 0 | U35: 2 | V35: Night | W35: 3 | X35: 1 | Y35: 130 | Z35: =+Y35*W35*U35*X35 -> 780 | AA35: =Z35 -> 780 | AB35: =Z35-AA35 -> 0 | AC35: 1 | AD35: Night | AE35: 3 | AF35: 1 | AG35: =Y35*$E$3 -> 135.2 | AH35: =+AG35*AE35*AC35*$H35 -> 405.6 | AI35: =AH35 -> 405.6 | AJ35: =AH35-AI35 -> 0 | AK35: =K35+S35+AA35+AI35 -> 4857.6 | AL35: =L35+T35+AB35+AJ35 -> 0 | AM35: =+AK35+AL35 -> 4857.6
A36: LSM&IE | B36: 86000 | C36: MEX | D36: C.2.3 M&IE | E36: 6 | F36: Day | G36: 4 | H36: 1 | I36: 70 | J36: =E36*I36*G36 -> 1680 | K36: =J36 -> 1680 | L36: =J36-K36 -> 0 | M36: 6 | N36: Day | O36: 4 | P36: 1 | Q36: =+I36*1.04 -> 72.8 | R36: =M36*Q36*O36*P36 -> 1747.2 | S36: =R36 -> 1747.2 | T36: =R36-S36 -> 0 | U36: 2 | V36: Day | W36: 4 | X36: 1 | Y36: 55 | Z36: 441 | AA36: =Z36 -> 441 | AB36: =Z36-AA36 -> 0 | AC36: 1 | AD36: Day | AE36: 4 | AF36: 1 | AG36: =Y36*$E$3 -> 57.2 | AH36: =+AG36*AE36*AC36*$H36 -> 228.8 | AI36: =AH36 -> 228.8 | AJ36: =AH36-AI36 -> 0 | AK36: =K36+S36+AA36+AI36 -> 4097 | AL36: =L36+T36+AB36+AJ36 -> 0 | AM36: =+AK36+AL36 -> 4097
A37: LSTRANS | B37: 86040 | C37: MEX | D37: C.2.4 Ground Transportation | E37: 1 | F37: Month | G37: 10 | H37: 1 | I37: 150 | J37: =E37*I37*G37 -> 1500 | K37: =J37 -> 1500 | L37: =J37-K37 -> 0 | M37: 1 | N37: Month | O37: 10 | P37: 1 | Q37: =+I37*1.04 -> 156 | R37: =M37*Q37*O37*P37 -> 1560 | S37: =R37 -> 1560 | T37: =R37-S37 -> 0 | U37: 1 | V37: Month | W37: 12 | X37: 1 | Y37: 78 | Z37: =+Y37*W37*U37*X37 -> 936 | AA37: =Z37 -> 936 | AB37: =Z37-AA37 -> 0 | AC37: 1 | AD37: Month | AE37: 4 | AF37: 1 | AG37: =Y37*$E$3 -> 81.12 | AH37: =+AG37*AE37*AC37*$H37 -> 324.48 | AI37: =AH37 -> 324.48 | AJ37: =AH37-AI37 -> 0 | AK37: =K37+S37+AA37+AI37 -> 4320.48 | AL37: =L37+T37+AB37+AJ37 -> 0 | AM37: =+AK37+AL37 -> 4320.48
D38: Subtotal Travel | J38: =SUM(J29:J37) -> 7135 | K38: =SUM(K29:K37) -> 7135 | L38: =SUM(L29:L37) -> 0 | R38: =SUM(R29:R37) -> 7420.4 | S38: =SUM(S29:S37) -> 7420.4 | T38: =SUM(T29:T37) -> 0 | Z38: =SUM(Z29:Z37) -> 2573 | AA38: =SUM(AA29:AA37) -> 2573 | AB38: =SUM(AB29:AB37) -> 0 | AH38: =SUM(AH29:AH37) -> 1175.2 | AI38: =SUM(AI29:AI37) -> 1175.2 | AJ38: =SUM(AJ29:AJ37) -> 0 | AK38: =SUM(AK29:AK37) -> 18303.6 | AL38: =SUM(AL29:AL37) -> 0 | AM38: =SUM(AM29:AM37) -> 18303.6
D39: D. Equipment
D40: E. Supplies
A41: SUPPLIES | B41: 82401 | C41: MEX | D41: E.1 Office Supplies | E41: 1 | F41: Month | G41: 12 | H41: 1 | I41: 50 | J41: =E41*I41*G41*H41 -> 600 | K41: =J41 -> 600 | L41: =J41-K41 -> 0 | M41: 1 | N41: Month | O41: 12 | P41: 1 | Q41: =I41*$E$3 -> 52 | R41: =M41*Q41*O41*P41 -> 624 | S41: =R41 -> 624 | T41: =R41-S41 -> 0 | U41: 1 | V41: Month | W41: 12 | X41: 1 | Y41: 31.2 | Z41: =U41*Y41*W41*X41 -> 374.4 | AA41: =Z41 -> 374.4 | AB41: =Z41-AA41 -> 0 | AC41: 1 | AD41: Month | AE41: 6 | AF41: 1 | AG41: 32.3 | AH41: =AC41*AG41*AE41*AF41 -> 193.8 | AI41: =AH41 -> 193.8 | AJ41: =AH41-AI41 -> 0 | AK41: =K41+S41+AA41+AI41 -> 1792.2 | AL41: =L41+T41+AB41+AJ41 -> 0 | AM41: =+AK41+AL41 -> 1792.2
A42: LAPTOP | B42: 82401 | C42: MEX | D42: E.2 Laptop Computers & Software | E42: 1 | F42: Unit | G42: 3 | H42: 1 | I42: 1000 | J42: =E42*I42*G42*H42 -> 3000 | K42: =J42 -> 3000 | L42: =J42-K42 -> 0 | M42: 1 | N42: Unit | O42: 1 | P42: 1 | Q42: 1200 | R42: 1222 | S42: =R42 -> 1222 | T42: =R42-S42 -> 0 | U42: 0 | V42: Unit | W42: 0 | X42: 0 | Z42: =U42*Y42*W42*X42 -> 0 | AA42: =Z42 -> 0 | AB42: =Z42-AA42 -> 0 | AC42: 0 | AD42: Unit | AE42: 0 | AF42: 0 | AH42: =AC42*AG42*AE42*$H42 -> 0 | AI42: =AH42 -> 0 | AJ42: =AH42-AI42 -> 0 | AK42: =K42+S42+AA42+AI42 -> 4222 | AL42: =L42+T42+AB42+AJ42 -> 0 | AM42: =+AK42+AL42 -> 4222
A43: PHOTO | B43: 82420 | C43: MEX | D43: E.3 Photography Supplies | E43: 0 | F43: Lumpsum | G43: 0 | H43: 1 | J43: =E43*I43*G43*H43 -> 0 | K43: =J43 -> 0 | L43: =J43-K43 -> 0 | M43: 1 | N43: Lumpsum | O43: 1 | P43: 1 | Q43: 1200 | R43: =M43*Q43*O43*P43 -> 1200 | S43: =R43 -> 1200 | T43: =R43-S43 -> 0 | U43: 0 | V43: Lumpsum | W43: 0 | X43: 0 | Z43: =U43*Y43*W43*X43 -> 0 | AA43: =Z43 -> 0 | AB43: =Z43-AA43 -> 0 | AC43: 0 | AD43: Lumpsum | AE43: 0 | AF43: 0 | AG43: =Y43 -> 0 | AH43: =AC43*AG43*AE43*AF43 -> 0 | AI43: =AH43 -> 0 | AJ43: =AH43-AI43 -> 0 | AK43: =K43+S43+AA43+AI43 -> 1200 | AL43: =L43+T43+AB43+AJ43 -> 0 | AM43: =+AK43+AL43 -> 1200
D44: Subtotal Supplies | J44: =SUM(J41:J42) -> 3600 | K44: =SUM(K41:K42) -> 3600 | L44: =SUM(L41:L42) -> 0 | R44: =SUM(R41:R43) -> 3046 | S44: =SUM(S41:S43) -> 3046 | T44: =SUM(T41:T42) -> 0 | Z44: =SUM(Z41:Z43) -> 374.4 | AA44: =SUM(AA41:AA43) -> 374.4 | AB44: =SUM(AB41:AB42) -> 0 | AH44: =SUM(AH41:AH43) -> 193.8 | AI44: =SUM(AI41:AI43) -> 193.8 | AJ44: =SUM(AJ41:AJ42) -> 0 | AK44: =SUM(AK41:AK43) -> 7214.2 | AL44: =SUM(AL41:AL43) -> 0 | AM44: =SUM(AM41:AM43) -> 7214.2
D45: F. Contractual
D46: F.1 Consultants
A47: CONSULTSM | B47: 81000 | C47: MEX | D47: F.1.1 Social Media Influencer Consultants | E47: 4 | F47: Month | G47: 6 | H47: 1 | I47: 1825 | J47: =E47*I47*G47 -> 43800 | K47: =J47 -> 43800 | L47: =J47-K47 -> 0 | M47: 4 | N47: Month | O47: 6 | P47: 1 | Q47: 1825 | R47: =M47*Q47*O47*P47 -> 43800 | S47: =R47 -> 43800 | T47: =R47-S47 -> 0 | U47: 1 | V47: Month | W47: 12 | X47: 1 | Y47: 4000 | Z47: =U47*Y47*W47*X47 -> 48000 | AA47: =Z47 -> 48000 | AB47: =Z47-AA47 -> 0 | AC47: 1 | AD47: Month | AE47: 5 | AF47: 1 | AG47: 4000 | AH47: =AC47*AG47*AE47*AF47 -> 20000 | AI47: =AH47 -> 20000 | AJ47: =AH47-AI47 -> 0 | AK47: =K47+S47+AA47+AI47 -> 155600 | AL47: =L47+T47+AB47+AJ47 -> 0 | AM47: =+AK47+AL47 -> 155600
A48: TECHADPP | B48: 81000 | C48: MEX | D48: F.1.2 Technical Advisor on Public Policy | E48: 1 | F48: Month | G48: 5 | H48: 1 | I48: 3500 | J48: =E48*I48*G48 -> 17500 | K48: =J48 -> 17500 | L48: =J48-K48 -> 0 | M48: 1 | N48: Month | O48: 5 | P48: 1 | Q48: 3500 | R48: =M48*Q48*O48*P48 -> 17500 | S48: =R48 -> 17500 | T48: =R48-S48 -> 0 | AK48: =K48+S48+AA48+AI48 -> 35000 | AL48: =L48+T48+AB48+AJ48 -> 0 | AM48: =+AK48+AL48 -> 35000
A49: CONSULTDC | B49: 81000 | C49: MEX | D49: F.1.3 Consultant for Participatory Research for Data Collection | E49: 1 | F49: Month | G49: 2 | H49: 1 | I49: 3000 | J49: =E49*I49*G49 -> 6000 | K49: =J49 -> 6000 | L49: =J49-K49 -> 0 | M49: 1 | N49: Month | O49: 2 | P49: 1 | Q49: 3000 | R49: =M49*Q49*O49*P49 -> 6000 | S49: =R49 -> 6000 | T49: =R49-S49 -> 0 | AK49: =K49+S49+AA49+AI49 -> 12000 | AL49: =L49+T49+AB49+AJ49 -> 0 | AM49: =+AK49+AL49 -> 12000
A50: CONSULTGDS | B50: 81000 | C50: MEX | D50: F.1.4 Consultant for Graphic Design Services | E50: 0 | F50: Contract | G50: 0 | H50: 1 | I50: 12000 | J50: =E50*I50*G50 -> 0 | K50: =J50 -> 0 | L50: =J50-K50 -> 0 | M50: 1 | N50: Contract | O50: 1 | P50: 0.45 | Q50: 12000 | R50: =M50*Q50*O50*P50 -> 5400 | S50: =R50 -> 5400 | T50: =R50-S50 -> 0 | U50: 1 | V50: Contract | W50: 1 | X50: 0.45 | Y50: 12000 | Z50: =U50*Y50*W50*X50 -> 5400 | AA50: =Z50 -> 5400 | AB50: =Z50-AA50 -> 0 | AC50: 1 | AD50: Contract | AE50: 1 | AF50: 0.1 | AG50: 12000 | AH50: =AC50*AG50*AE50*AF50 -> 1200 | AI50: =AH50 -> 1200 | AJ50: =AH50-AI50 -> 0 | AK50: =K50+S50+AA50+AI50 -> 12000 | AL50: =L50+T50+AB50+AJ50 -> 0 | AM50: =+AK50+AL50 -> 12000
D51: F.2 Contracts
A52: IMMERSIVE | B52: 81010 | C52: MEX | D52: F.2.1 Contract for Live Portrait and Immersive Experience | E52: 1 | F52: Contract | G52: 1 | H52: 1 | I52: 25000 | J52: =E52*I52*G52 -> 25000 | K52: =J52 -> 25000 | L52: =J52-K52 -> 0 | M52: 1 | N52: Contract | O52: 1 | P52: 0.25 | Q52: 28000 | R52: =M52*Q52*O52*P52 -> 7000 | S52: =R52 -> 7000 | T52: =R52-S52 -> 0 | U52: 1 | V52: Contract | W52: 1 | X52: 0.5 | Y52: 28000 | Z52: =U52*Y52*W52*X52 -> 14000 | AA52: =Z52 -> 14000 | AB52: =Z52-AA52 -> 0 | AC52: 1 | AD52: Contract | AE52: 1 | AF52: 0.25 | AG52: 28000 | AH52: =AC52*AG52*AE52*AF52 -> 7000 | AI52: =AH52 -> 7000 | AJ52: =AH52-AI52 -> 0 | AK52: =K52+S52+AA52+AI52 -> 53000 | AL52: =L52+T52+AB52+AJ52 -> 0 | AM52: =+AK52+AL52 -> 53000
A53: FILMPROD | B53: 81010 | C53: MEX | D53: F.2.2 Contract to Film & Produce Soap Opera | E53: 1 | F53: Contract | G53: 1 | H53: 1 | I53: 20000 | J53: =E53*I53*G53 -> 20000 | K53: =J53 -> 20000 | L53: =J53-K53 -> 0 | M53: 0 | N53: Contract | O53: 0 | P53: 0 | Q53: 20000 | R53: =M53*Q53*O53*P53 -> 0 | S53: =R53 -> 0 | T53: =R53-S53 -> 0 | AK53: =K53+S53+AA53+AI53 -> 20000 | AL53: =L53+T53+AB53+AJ53 -> 0 | AM53: =+AK53+AL53 -> 20000
A54: SECURITY | B54: 86110 | C54: MEX | D54: F.2.3 Security Advisors | E54: 1 | F54: Month | G54: 12 | H54: 1 | I54: 300 | J54: =E54*I54*G54 -> 3600 | K54: =J54 -> 3600 | L54: =J54-K54 -> 0 | M54: 1 | N54: Month | O54: 12 | P54: 1 | Q54: 300 | R54: =M54*Q54*O54*P54 -> 3600 | S54: =R54 -> 3600 | T54: =R54-S54 -> 0 | AK54: =K54+S54+AA54+AI54 -> 7200 | AL54: =L54+T54+AB54+AJ54 -> 0 | AM54: =+AK54+AL54 -> 7200
A55: CONTRANS | B55: 81021 | C55: MEX | D55: F.2.4 Contract for Translation Services | E55: 0 | F55: Year | G55: 0 | H55: 1 | I55: 20000 | J55: =E55*I55*G55 -> 0 | K55: =J55 -> 0 | L55: =J55-K55 -> 0 | M55: 1 | N55: Contract | O55: 1 | P55: =1/3 -> 0.33333333 | Q55: 20000 | R55: =M55*Q55*O55*P55 -> 6666.6667 | S55: =R55 -> 6666.6667 | T55: =R55-S55 -> 0 | U55: 1 | V55: Contract | W55: 1 | X55: =1/3 -> 0.33333333 | Y55: 20000 | Z55: =U55*Y55*W55*X55 -> 6666.6667 | AA55: =Z55 -> 6666.6667 | AB55: =Z55-AA55 -> 0 | AC55: 1 | AD55: Contract | AE55: 1 | AF55: =1/3 -> 0.33333333 | AG55: 20000 | AH55: =AC55*AG55*AE55*AF55 -> 6666.6667 | AI55: =AH55 -> 6666.6667 | AJ55: =AH55-AI55 -> 0 | AK55: =K55+S55+AA55+AI55 -> 20000 | AL55: =L55+T55+AB55+AJ55 -> 0 | AM55: =+AK55+AL55 -> 20000
A56: CONEXVIDEO | B56: 81010 | C56: MEX | D56: F.2.5 Contract for Production of Explainer Videos | E56: 0 | F56: Contract | G56: 0 | H56: 1 | I56: 40000 | J56: =E56*I56*G56 -> 0 | K56: =J56 -> 0 | L56: =J56-K56 -> 0 | M56: 0 | N56: Contract | O56: 0 | P56: 0 | Q56: 40000 | R56: =M56*Q56*O56*P56 -> 0 | S56: =R56 -> 0 | T56: =R56-S56 -> 0 | U56: 1 | V56: Contract | W56: 1 | X56: 1 | Y56: =Q56 -> 40000 | Z56: =U56*Y56*W56*X56 -> 40000 | AA56: =Z56 -> 40000 | AB56: =Z56-AA56 -> 0 | AC56: 0 | AD56: Contract | AE56: 0 | AF56: 0 | AG56: 40000 | AH56: =AC56*AG56*AE56*AF56 -> 0 | AI56: =AH56 -> 0 | AJ56: =AH56-AI56 -> 0 | AK56: =K56+S56+AA56+AI56 -> 40000 | AL56: =L56+T56+AB56+AJ56 -> 0 | AM56: =+AK56+AL56 -> 40000
A57: CONMARKET | B57: 90450 | C57: MEX | D57: F.2.6 Contract for Transit Marketing Campaign | E57: 0 | F57: Contract | G57: 0 | H57: 1 | I57: 400000 | J57: =E57*I57*G57 -> 0 | K57: =J57 -> 0 | L57: =J57-K57 -> 0 | M57: 0 | N57: Contract | O57: 0 | P57: 0 | Q57: 400000 | R57: =M57*Q57*O57*P57 -> 0 | S57: =R57 -> 0 | T57: =R57-S57 -> 0 | U57: 1 | V57: Contract | W57: 1 | X57: 1 | Y57: 400000 | Z57: =U57*Y57*W57*X57 -> 400000 | AA57: =Z57 -> 400000 | AB57: =Z57-AA57 -> 0 | AC57: 0 | AD57: Contract | AE57: 0 | AF57: 0 | AG57: 400000 | AH57: =AC57*AG57*AE57*AF57 -> 0 | AI57: =AH57 -> 0 | AJ57: =AH57-AI57 -> 0 | AK57: =K57+S57+AA57+AI57 -> 400000 | AL57: =L57+T57+AB57+AJ57 -> 0 | AM57: =+AK57+AL57 -> 400000
A58: CONPRINT | B58: 85300 | C58: MEX | D58: F.2.7 Contract for Printing Services | E58: 0 | F58: Contract | G58: 0 | H58: 1 | I58: 37283 | J58: =E58*I58*G58 -> 0 | K58: =J58 -> 0 | L58: =J58-K58 -> 0 | M58: 1 | N58: Contract | O58: 1 | P58: 0.25 | Q58: 37283 | R58: =M58*Q58*O58*P58 -> 9320.75 | S58: =R58 -> 9320.75 | T58: =R58-S58 -> 0 | U58: 1 | V58: Contract | W58: 1 | X58: 0.5 | Y58: =Q58 -> 37283 | Z58: =U58*Y58*W58*X58 -> 18641.5 | AA58: =Z58 -> 18641.5 | AB58: =Z58-AA58 -> 0 | AC58: 1 | AD58: Contract | AE58: 1 | AF58: 0.25 | AG58: =Y58 -> 37283 | AH58: =AC58*AG58*AE58*AF58 -> 9320.75 | AI58: =AH58 -> 9320.75 | AJ58: =AH58-AI58 -> 0 | AK58: =K58+S58+AA58+AI58 -> 37283 | AL58: =L58+T58+AB58+AJ58 -> 0 | AM58: =+AK58+AL58 -> 37283
A59: CONSHELTER | B59: 81010 | C59: MEX | D59: F.2.8 Contract for Shelter Coordination and Monitoring | E59: 0 | F59: Contract | G59: 0 | H59: 1 | I59: 5000 | J59: =E59*I59*G59 -> 0 | K59: =J59 -> 0 | L59: =J59-K59 -> 0 | M59: 0 | N59: Contract | O59: 0 | P59: 0 | Q59: 5000 | R59: =M59*Q59*O59*P59 -> 0 | S59: =R59 -> 0 | T59: =R59-S59 -> 0 | U59: 1 | V59: Contract | W59: 1 | X59: 0.5 | Y59: 5000 | Z59: =U59*Y59*W59*X59 -> 2500 | AA59: =Z59 -> 2500 | AB59: =Z59-AA59 -> 0 | AC59: 1 | AD59: Contract | AE59: 1 | AF59: 0.5 | AG59: 5000 | AH59: =AC59*AG59*AE59*AF59 -> 2500 | AI59: =AH59 -> 2500 | AJ59: =AH59-AI59 -> 0 | AK59: =K59+S59+AA59+AI59 -> 5000 | AL59: =L59+T59+AB59+AJ59 -> 0 | AM59: =+AK59+AL59 -> 5000
A60: CONDISSEM | B60: 81010 | C60: MEX | D60: F.2.9 Contract Dissemination Research and Response | E60: 0 | F60: Contract | G60: 0 | H60: 1 | I60: 225000 | J60: =E60*I60*G60 -> 0 | K60: =J60 -> 0 | L60: =J60-K60 -> 0 | M60: 1 | N60: Contract | O60: 1 | P60: 1 | Q60: 225000 | R60: =M60*Q60*O60*P60 -> 225000 | S60: =R60 -> 225000 | T60: =R60-S60 -> 0 | U60: 0 | V60: Contract | W60: 0 | X60: 1 | Y60: =Q60*$E$3 -> 234000 | Z60: =U60*Y60*W60*X60 -> 0 | AA60: =Z60 -> 0 | AB60: =Z60-AA60 -> 0 | AC60: 0 | AD60: Contract | AE60: 0 | AF60: 1 | AG60: =Y60*$E$3 -> 243360 | AH60: =AC60*AG60*AE60*AF60 -> 0 | AI60: =AH60 -> 0 | AJ60: =AH60-AI60 -> 0 | AK60: =K60+S60+AA60+AI60 -> 225000 | AL60: =L60+T60+AB60+AJ60 -> 0 | AM60: =+AK60+AL60 -> 225000
D61: Subtotal Contractual | J61: =SUM(J47:J60) -> 115900 | K61: =SUM(K47:K60) -> 115900 | L61: =SUM(L47:L60) -> 0 | R61: =SUM(R47:R60) -> 324287.42 | S61: =SUM(S47:S60) -> 324287.42 | T61: =SUM(T47:T57) -> 0 | Z61: =SUM(Z47:Z60) -> 535208.17 | AA61: =SUM(AA47:AA60) -> 535208.17 | AB61: =SUM(AB47:AB57) -> 0 | AH61: =SUM(AH47:AH60) -> 46687.417 | AI61: =SUM(AI47:AI60) -> 46687.417 | AJ61: =SUM(AJ47:AJ57) -> 0 | AK61: =SUM(AK47:AK60) -> 1022083 | AL61: =SUM(AL47:AL59) -> 0 | AM61: =SUM(AM47:AM60) -> 1022083
D62: G. Other Direct Costs
D63: G.1 Office Costs
A64: RENT & UT | B64: 85180 | C64: MEX | D64: G.1.1 Office Space & Utilities | E64: 1 | F64: Month | G64: 12 | H64: 1 | I64: 350 | J64: =E64*I64*G64*H64 -> 4200 | K64: =J64 -> 4200 | L64: =J64-K64 -> 0 | M64: 1 | N64: Month | O64: 12 | P64: 1 | Q64: =I64*$E$3 -> 364 | R64: =M64*Q64*O64*P64 -> 4368 | S64: =R64 -> 4368 | T64: =R64-S64 -> 0 | U64: 1 | V64: Month | W64: 12 | X64: 1 | Y64: 620 | Z64: =U64*W64*Y64*X64 -> 7440 | AA64: =Z64 -> 7440 | AB64: =Z64-AA64 -> 0 | AC64: 1 | AD64: Month | AE64: 4 | AF64: 1 | AG64: =Y64*$E$3 -> 644.8 | AH64: =AC64*AG64*AE64*AF64 -> 2579.2 | AI64: =AH64 -> 2579.2 | AJ64: =AH64-AI64 -> 0 | AK64: =K64+S64+AA64+AI64 -> 18587.2 | AL64: =L64+T64+AB64+AJ64 -> 0 | AM64: =+AK64+AL64 -> 18587.2
A65: BANK FEES | B65: 90900 | C65: MEX | D65: G.1.2 Banking and Cash Handling Fees | E65: 1 | F65: Month | G65: 12 | H65: 1 | I65: 35 | J65: =E65*I65*G65*H65 -> 420 | K65: =J65 -> 420 | L65: =J65-K65 -> 0 | M65: 1 | N65: Month | O65: 12 | P65: 1 | Q65: =I65*$E$3 -> 36.4 | R65: =M65*Q65*O65*P65 -> 436.8 | S65: =R65 -> 436.8 | T65: =R65-S65 -> 0 | U65: 1 | V65: Month | W65: 12 | X65: 1 | Y65: 21.84 | Z65: =U65*W65*Y65*X65 -> 262.08 | AA65: =Z65 -> 262.08 | AB65: =Z65-AA65 -> 0 | AC65: 1 | AD65: Month | AE65: 7 | AF65: 1 | AG65: =Y65*$E$3 -> 22.7136 | AH65: =AC65*AG65*AE65*AF65 -> 158.9952 | AI65: =AH65 -> 158.9952 | AJ65: =AH65-AI65 -> 0 | AK65: =K65+S65+AA65+AI65 -> 1277.8752 | AL65: =L65+T65+AB65+AJ65 -> 0 | AM65: =+AK65+AL65 -> 1277.8752
A66: PAYROLL | B66: 81030 | C66: MEX | D66: G.1.3 Payroll Processing | E66: 1 | F66: Month | G66: 12 | H66: 1 | I66: 50 | J66: =E66*I66*G66*H66 -> 600 | K66: =J66 -> 600 | L66: =J66-K66 -> 0 | M66: 1 | N66: Month | O66: 12 | P66: 1 | Q66: =I66*$E$3 -> 52 | R66: =M66*Q66*O66*P66 -> 624 | S66: =R66 -> 624 | T66: =R66-S66 -> 0 | U66: 1 | V66: Month | W66: 12 | X66: 1 | Y66: 41.6 | Z66: =U66*W66*Y66*X66 -> 499.2 | AA66: =Z66 -> 499.2 | AB66: =Z66-AA66 -> 0 | AC66: 1 | AD66: Month | AE66: 7 | AF66: 1 | AG66: =Y66*$E$3 -> 43.264 | AH66: =AC66*AG66*AE66*AF66 -> 302.848 | AI66: =AH66 -> 302.848 | AJ66: =AH66-AI66 -> 0 | AK66: =K66+S66+AA66+AI66 -> 2026.048 | AL66: =L66+T66+AB66+AJ66 -> 0 | AM66: =+AK66+AL66 -> 2026.048
A67: COMM | B67: 82030 | C67: MEX | D67: G.1.4 Communications Costs (Phone, Data, Internet, etc.) | E67: 1 | F67: Month | G67: 12 | H67: 1 | I67: 150 | J67: =E67*I67*G67*H67 -> 1800 | K67: =J67 -> 1800 | L67: =J67-K67 -> 0 | M67: 1 | N67: Month | O67: 12 | P67: 1 | Q67: =I67*$E$3 -> 156 | R67: =M67*Q67*O67*P67 -> 1872 | S67: =R67 -> 1872 | T67: =R67-S67 -> 0 | U67: 1 | V67: Month | W67: 12 | X67: 1 | Y67: 124.8 | Z67: =U67*W67*Y67*X67 -> 1497.6 | AA67: =Z67 -> 1497.6 | AB67: =Z67-AA67 -> 0 | AC67: 1 | AD67: Month | AE67: 7 | AF67: 0.8 | AG67: =Y67*$E$3 -> 129.792 | AH67: =AC67*AG67*AE67*AF67 -> 726.8352 | AI67: =AH67 -> 726.8352 | AJ67: =AH67-AI67 -> 0 | AK67: =K67+S67+AA67+AI67 -> 5896.4352 | AL67: =L67+T67+AB67+AJ67 -> 0 | AM67: =+AK67+AL67 -> 5896.4352
A68: SUBSCRIPT | B68: 89400 | C68: MEX | D68: G.1.5 HR, Platform Subscriptions (Timekeeping and Expense Reporting) | E68: 1 | F68: Month | G68: 12 | H68: 1 | I68: 120 | J68: =E68*I68*G68*H68 -> 1440 | K68: =J68 -> 1440 | L68: =J68-K68 -> 0 | M68: 1 | N68: Month | O68: 12 | P68: 1 | Q68: =I68*$E$3 -> 124.8 | R68: =M68*Q68*O68*P68 -> 1497.6 | S68: =R68 -> 1497.6 | T68: =R68-S68 -> 0 | U68: 1 | V68: Month | W68: 12 | X68: 1 | Y68: 93.6 | Z68: =U68*W68*Y68*X68 -> 1123.2 | AA68: =Z68 -> 1123.2 | AB68: =Z68-AA68 -> 0 | AC68: 1 | AD68: Month | AE68: 7 | AF68: 1 | AG68: =Y68*$E$3 -> 97.344 | AH68: =AC68*AG68*AE68*AF68 -> 681.408 | AI68: =AH68 -> 681.408 | AJ68: =AH68-AI68 -> 0 | AK68: =K68+S68+AA68+AI68 -> 4742.208 | AL68: =L68+T68+AB68+AJ68 -> 0 | AM68: =+AK68+AL68 -> 4742.208
A69: MEETING | B69: 87010 | C69: MEX | D69: G.1.6 Meeting Expenses | E69: 1 | F69: Month | G69: 12 | H69: 1 | I69: 50 | J69: =E69*I69*G69*H69 -> 600 | K69: =J69 -> 600 | L69: =J69-K69 -> 0 | M69: 1 | N69: Month | O69: 12 | P69: 1 | Q69: =I69*$E$3 -> 52 | R69: =M69*Q69*O69*P69 -> 624 | S69: =R69 -> 624 | T69: =R69-S69 -> 0 | AK69: =K69+S69+AA69+AI69 -> 1224 | AL69: =L69+T69+AB69+AJ69 -> 0 | AM69: =+AK69+AL69 -> 1224
A70: RECRUIT | B70: 90450 | C70: MEX | D70: G.1.7 Procurement Advertising | E70: 1 | F70: Year | G70: 1 | H70: 1 | I70: 400 | J70: =E70*I70*G70*H70 -> 400 | K70: =J70 -> 400 | L70: =J70-K70 -> 0 | M70: 1 | N70: Year | O70: 1 | P70: 1 | Q70: =I70*$E$3 -> 416 | R70: =M70*Q70*O70*P70 -> 416 | S70: =R70 -> 416 | T70: =R70-S70 -> 0 | AK70: =K70+S70+AA70+AI70 -> 816 | AL70: =L70+T70+AB70+AJ70 -> 0 | AM70: =+AK70+AL70 -> 816
A71: LEGAL | B71: 90100 | C71: MEX | D71: G.1.8 Legal Fees | E71: 1 | F71: Year | G71: 1 | H71: 1 | I71: 250 | J71: =E71*I71*G71*H71 -> 250 | K71: =J71 -> 250 | L71: =J71-K71 -> 0 | M71: 1 | N71: Year | O71: 1 | P71: 1 | Q71: =I71*$E$3 -> 260 | R71: =M71*Q71*O71*P71 -> 260 | S71: =R71 -> 260 | T71: =R71-S71 -> 0 | U71: 1 | V71: Year | W71: 1 | X71: 1 | Y71: =Q71*$E$3 -> 270.4 | Z71: =U71*W71*Y71*X71 -> 270.4 | AA71: =Z71 -> 270.4 | AB71: =Z71-AA71 -> 0 | AC71: 1 | AD71: Year | AE71: 1 | AF71: 1 | AG71: =Y71*$E$3 -> 281.216 | AH71: =AC71*AG71*AE71*AF71 -> 281.216 | AI71: =AH71 -> 281.216 | AJ71: =AH71-AI71 -> 0 | AK71: =K71+S71+AA71+AI71 -> 1061.616 | AL71: =L71+T71+AB71+AJ71 -> 0 | AM71: =+AK71+AL71 -> 1061.616
A72: AUDIT | B72: 82100 | C72: MEX | D72: G.1.9 Audit Fees | E72: 1 | F72: Year | G72: 1 | H72: 1 | I72: 100 | J72: =E72*I72*G72*H72 -> 100 | K72: =J72 -> 100 | L72: =J72-K72 -> 0 | M72: 1 | N72: Year | O72: 1 | P72: 1 | Q72: =I72*$E$3 -> 104 | R72: =M72*Q72*O72*P72 -> 104 | S72: =R72 -> 104 | T72: =R72-S72 -> 0 | U72: 1 | V72: Year | W72: 1 | X72: 1 | Y72: =Q72*$E$3 -> 108.16 | Z72: =U72*W72*Y72*X72 -> 108.16 | AA72: =Z72 -> 108.16 | AB72: =Z72-AA72 -> 0 | AC72: 1 | AD72: Year | AE72: 1 | AF72: 1 | AG72: =Y72*$E$3 -> 112.4864 | AH72: =AC72*AG72*AE72*AF72 -> 112.4864 | AI72: =AH72 -> 112.4864 | AJ72: =AH72-AI72 -> 0 | AK72: =K72+S72+AA72+AI72 -> 424.6464 | AL72: =L72+T72+AB72+AJ72 -> 0 | AM72: =+AK72+AL72 -> 424.6464
A73: POSTAGE | B73: 82350 | C73: MEX | D73: G.1.10 Postage/Shipping | E73: 0 | F73: Month | G73: 0 | H73: 1 | I73: 30 | J73: =E73*I73*G73*H73 -> 0 | K73: =J73 -> 0 | L73: =J73-K73 -> 0 | M73: 1 | N73: Month | O73: 12 | P73: 1 | Q73: 30 | R73: =M73*Q73*O73*P73 -> 360 | S73: =R73 -> 360 | T73: =R73-S73 -> 0 | U73: 1 | V73: Month | W73: 12 | X73: 1 | Y73: =Q73*$E$3 -> 31.2 | Z73: =U73*W73*Y73*X73 -> 374.4 | AA73: =Z73 -> 374.4 | AB73: =Z73-AA73 -> 0 | AC73: 1 | AD73: Month | AE73: 7 | AF73: 1 | AG73: 32.5 | AH73: =AC73*AG73*AE73*AF73 -> 227.5 | AI73: =AH73 -> 227.5 | AJ73: =AH73-AI73 -> 0 | AK73: =K73+S73+AA73+AI73 -> 961.9 | AL73: =L73+T73+AB73+AJ73 -> 0 | AM73: =+AK73+AL73 -> 961.9
D74: G.2 Activities Costs
A75: TRANS | B75: 81021 | C75: MEX | D75: G.2.1 Translation Costs | E75: 1 | F75: Year | G75: 1 | H75: 1 | I75: 15000 | J75: =E75*I75*G75*H75 -> 15000 | K75: =J75 -> 15000 | L75: =J75-K75 -> 0 | M75: 1 | N75: Year | O75: 1 | P75: 1 | Q75: =I75*$E$3 -> 15600 | R75: =M75*Q75*O75*P75 -> 15600 | S75: =R75 -> 15600 | T75: =R75-S75 -> 0 | AK75: =K75+S75+AA75+AI75 -> 30600 | AL75: =L75+T75+AB75+AJ75 -> 0 | AM75: =+AK75+AL75 -> 30600
A76: SOCIALADS | B76: 90450 | C76: MEX | D76: G.2.2 Social Media Ads/Boosts | E76: 1 | F76: Ad | G76: 24 | H76: 1 | I76: 250 | J76: =E76*I76*G76*H76 -> 6000 | K76: =J76 -> 6000 | L76: =J76-K76 -> 0 | M76: 1 | N76: Ad | O76: 42 | P76: 1 | Q76: 255.7 | R76: =M76*Q76*O76*P76 -> 10739.4 | S76: =R76 -> 10739.4 | T76: =R76-S76 -> 0 | U76: 1 | V76: Ad | W76: 35 | X76: 1 | Y76: 260 | Z76: =U76*Y76*W76*X76 -> 9100 | AA76: =Z76 -> 9100 | AB76: =Z76-AA76 -> 0 | AC76: 1 | AD76: Ad | AE76: 25 | AF76: 1 | AG76: =Y76*$E$3 -> 270.4 | AH76: =AC76*AG76*AE76*$H76*AF76 -> 6760 | AI76: =AH76 -> 6760 | AJ76: =AH76-AI76 -> 0 | AK76: =K76+S76+AA76+AI76 -> 32599.4 | AL76: =L76+T76+AB76+AJ76 -> 0 | AM76: =+AK76+AL76 -> 32599.4
A77: WEBSITE | B77: 81035 | C77: MEX | D77: G.2.3 Website Development Fees | E77: 1 | F77: Lumpsum | G77: 1 | H77: 1 | I77: 7000 | J77: =E77*I77*G77*H77 -> 7000 | K77: =J77 -> 7000 | L77: =J77-K77 -> 0 | M77: 1 | N77: Lumpsum | O77: 0 | P77: 0 | Q77: 7000 | R77: =M77*Q77*O77*P77 -> 0 | S77: =R77 -> 0 | T77: =R77-S77 -> 0 | U77: 1 | V77: Lumpsum | W77: 1 | X77: 1 | Y77: 7000 | Z77: =U77*Y77*W77*X77 -> 7000 | AA77: =Z77 -> 7000 | AB77: =Z77-AA77 -> 0 | AC77: 0 | AD77: Lumpsum | AE77: 0 | AF77: 0 | AG77: 7000 | AH77: =AC77*AG77*AE77*$H77*AF77 -> 0 | AI77: =AH77 -> 0 | AJ77: =AH77-AI77 -> 0 | AK77: =K77+S77+AA77+AI77 -> 14000 | AL77: =L77+T77+AB77+AJ77 -> 0 | AM77: =+AK77+AL77 -> 14000
A78: HOSTMAINT | B78: 81035 | C78: MEX | D78: G.2.4 Website Hosting and Maintenance Fees | E78: 1 | F78: Year | G78: 1 | H78: 1 | I78: 800 | J78: =E78*I78*G78*H78 -> 800 | K78: =J78 -> 800 | L78: =J78-K78 -> 0 | M78: 1 | N78: Year | O78: 1 | P78: 1 | Q78: =I78*$E$3 -> 832 | R78: =M78*Q78*O78*P78 -> 832 | S78: =R78 -> 832 | T78: =R78-S78 -> 0 | U78: 1 | V78: Year | W78: 1 | X78: 1 | Y78: 1040 | Z78: =U78*Y78*W78*X78 -> 1040 | AA78: =Z78 -> 1040 | AB78: =Z78-AA78 -> 0 | AC78: 1 | AD78: Year | AE78: 1 | AF78: 1 | AG78: =Y78*$E$3 -> 1081.6 | AH78: =AC78*AG78*AE78*$H78*AF78 -> 1081.6 | AI78: =AH78 -> 1081.6 | AJ78: =AH78-AI78 -> 0 | AK78: =K78+S78+AA78+AI78 -> 3753.6 | AL78: =L78+T78+AB78+AJ78 -> 0 | AM78: =+AK78+AL78 -> 3753.6
A79: AIAPPPROMO | B79: 87000 | C79: MEX | D79: G.2.5 AI App Promotion, Training, and Events | E79: 0 | F79: Event | G79: 0 | H79: 1 | I79: 2000 | J79: =E79*I79*G79*H79 -> 0 | K79: =J79 -> 0 | L79: =J79-K79 -> 0 | M79: 1 | N79: Event | O79: 3 | P79: 1 | Q79: 2000 | R79: =M79*Q79*O79*P79 -> 6000 | S79: =R79 -> 6000 | T79: =R79-S79 -> 0 | U79: 1 | V79: Event | W79: 2 | X79: 1 | Y79: 2000 | Z79: =U79*Y79*W79*X79 -> 4000 | AA79: =Z79 -> 4000 | AB79: =Z79-AA79 -> 0 | AC79: 0 | AD79: Event | AE79: 0 | AF79: 1 | AG79: 2000 | AH79: =AC79*AG79*AE79*$H79*AF79 -> 0 | AI79: =AH79 -> 0 | AJ79: =AH79-AI79 -> 0 | AK79: =K79+S79+AA79+AI79 -> 10000 | AL79: =L79+T79+AB79+AJ79 -> 0 | AM79: =+AK79+AL79 -> 10000
A80: EVENTSIOM | B80: 87000 | C80: MEX | D80: G.2.6 Events in Partnership with IOM | E80: 0 | F80: Event | G80: 0 | H80: 1 | I80: 5000 | J80: =E80*I80*G80*H80 -> 0 | K80: =J80 -> 0 | L80: =J80-K80 -> 0 | M80: 1 | N80: Event | O80: 2 | P80: 1 | Q80: 5000 | R80: =M80*Q80*O80*P80 -> 10000 | S80: =R80 -> 10000 | T80: =R80-S80 -> 0 | U80: 1 | V80: Event | W80: 3 | X80: 1 | Y80: =Q80*$E$3 -> 5200 | Z80: =U80*Y80*W80*X80 -> 15600 | AA80: =Z80 -> 15600 | AB80: =Z80-AA80 -> 0 | AC80: 1 | AD80: Event | AE80: 2 | AF80: 1 | AG80: =Y80*$E$3 -> 5408 | AH80: =AC80*AG80*AE80*$H80*AF80 -> 10816 | AI80: =AH80 -> 10816 | AJ80: =AH80-AI80 -> 0 | AK80: =K80+S80+AA80+AI80 -> 36416 | AL80: =L80+T80+AB80+AJ80 -> 0 | AM80: =+AK80+AL80 -> 36416
A81: REGIONADS | B81: 90450 | C81: MEX | D81: G.2.7 Social Media Ads/Boosts (Regional Advertising Initiative) | E81: 0 | F81: Ad | G81: 0 | H81: 1 | I81: 250 | J81: =E81*I81*G81*H81 -> 0 | K81: =J81 -> 0 | L81: =J81-K81 -> 0 | M81: 1 | N81: Ad | O81: 784 | P81: 1 | Q81: 250 | R81: 196000 | S81: =R81 -> 196000 | T81: =R81-S81 -> 0 | U81: 0 | V81: Ad | W81: 0 | X81: 0 | Y81: 250 | Z81: =U81*Y81*W81*X81 -> 0 | AA81: =Z81 -> 0 | AB81: =Z81-AA81 -> 0 | AC81: 1 | AD81: Ad | AE81: 0 | AF81: 1 | AG81: =Y81*$E$3 -> 260 | AH81: =AC81*AG81*AE81*$H81*AF81 -> 0 | AI81: =AH81 -> 0 | AJ81: =AH81-AI81 -> 0 | AK81: =K81+S81+AA81+AI81 -> 196000 | AL81: =L81+T81+AB81+AJ81 -> 0 | AM81: =+AK81+AL81 -> 196000
D82: G.3 M&E
A83: M&EMATL | B83: 82420 | C83: MEX | D83: G.3.1 M&E Materials | E83: 1 | F83: Year | G83: 1 | H83: 1 | I83: 300 | J83: =E83*I83*G83*H83 -> 300 | K83: =J83 -> 300 | L83: =J83-K83 -> 0 | M83: 1 | N83: Year | O83: 1 | P83: 1 | Q83: =300*1.04 -> 312 | R83: =M83*Q83*O83*P83 -> 312 | S83: =R83 -> 312 | T83: =R83-S83 -> 0 | AK83: =K83+S83+AA83+AI83 -> 612 | AL83: =L83+T83+AB83+AJ83 -> 0 | AM83: =+AK83+AL83 -> 612
A84: M&ETRAIN | B84: 87010 | C84: MEX | D84: G.3.2 M&E Training and Coordination Meetings | E84: 1 | F84: Meetings | G84: 1 | H84: 1 | I84: 121 | J84: =E84*I84*G84*H84 -> 121 | K84: =J84 -> 121 | L84: =J84-K84 -> 0 | M84: 1 | N84: Meetings | O84: 1 | P84: 1 | Q84: =121*1.04 -> 125.84 | R84: =M84*Q84*O84*P84 -> 125.84 | S84: =R84 -> 125.84 | T84: =R84-S84 -> 0 | AK84: =K84+S84+AA84+AI84 -> 246.84 | AL84: =L84+T84+AB84+AJ84 -> 0 | AM84: =+AK84+AL84 -> 246.84
A85: EVAL | B85: 81010 | C85: MEX | D85: G.3.3 External Project Evaluation support costs | E85: 1 | F85: Lumpsum | G85: 0 | H85: 1 | I85: 1000 | J85: =E85*I85*G85*H85 -> 0 | K85: =J85 -> 0 | L85: =J85-K85 -> 0 | M85: 1 | N85: Lumpsum | O85: 1 | P85: 1 | Q85: =1000*1.04 -> 1040 | R85: =M85*Q85*O85*P85 -> 1040 | S85: =R85 -> 1040 | T85: =R85-S85 -> 0 | AK85: =K85+S85+AA85+AI85 -> 1040 | AL85: =L85+T85+AB85+AJ85 -> 0 | AM85: =+AK85+AL85 -> 1040
D86: Subtotal Other Direct Costs | J86: =SUM(J63:J85) -> 39031 | K86: =SUM(K63:K85) -> 39031 | L86: =SUM(L63:L85) -> 0 | R86: =SUM(R63:R85) -> 251211.64 | S86: =SUM(S63:S85) -> 251211.64 | T86: =SUM(T63:T85) -> 0 | Z86: =SUM(Z63:Z85) -> 48315.04 | AA86: =SUM(AA63:AA85) -> 48315.04 | AB86: =SUM(AB63:AB85) -> 0 | AH86: =SUM(AH63:AH85) -> 23728.089 | AI86: =SUM(AI63:AI85) -> 23728.089 | AJ86: =SUM(AJ63:AJ85) -> 0 | AK86: =SUM(AK63:AK85) -> 362285.77 | AL86: =SUM(AL63:AL85) -> 0 | AM86: =SUM(AM63:AM85) -> 362285.77
D87: H. Total Direct Costs | J87: =J20+J26+J38+J44+J61+J86 -> 273864.69 | K87: =K20+K26+K38+K44+K61+K86 -> 273864.69 | L87: =L20+L26+L38+L44+L61+L86 -> 0 | R87: =R20+R26+R38+R44+R61+R86 -> 718909.09 | S87: =S20+S26+S38+S44+S61+S86 -> 718909.09 | T87: =T20+T26+T38+T44+T61+T86 -> 0 | Z87: =Z20+Z26+Z38+Z44+Z61+Z86 -> 755115.34 | AA87: =AA20+AA26+AA38+AA44+AA61+AA86 -> 755115.34 | AB87: =AB20+AB26+AB38+AB44+AB61+AB86 -> 0 | AH87: =AH20+AH26+AH38+AH44+AH61+AH86 -> 159284.57 | AI87: =AI20+AI26+AI38+AI44+AI61+AI86 -> 159284.57 | AJ87: =AJ20+AJ26+AJ38+AJ44+AJ61+AJ86 -> 0 | AK87: =K87+S87+AA87+AI87 -> 1907173.7 | AL87: =L87+T87+AB87+AJ87 -> 0 | AM87: =+AK87+AL87 -> 1907173.7
D88: I. Indirect Cost
A89: IDC | B89: 94050 | C89: USA | D89: I.1 Indirect Cost (28.28% NICRA rate) | F89: 0.2828 | J89: =J87*F89 -> 77448.935 | K89: =J89 -> 77448.935 | L89: =J89-K89 -> 0 | N89: 0.2828 | R89: =R87*$N$89 -> 203307.49 | S89: =R89 -> 203307.49 | T89: =R89-S89 -> 0 | V89: 0.2828 | Z89: =Z87*$N$89 -> 213546.62 | AA89: =Z89 -> 213546.62 | AB89: =Z89-AA89 -> 0 | AD89: 0.2828 | AH89: =AH87*$N$89+2.45 -> 45048.128 | AI89: =AH89 -> 45048.128 | AJ89: =AH89-AI89 -> 0 | AK89: =K89+S89+AA89+AI89 -> 539351.17 | AL89: =L89+T89+AB89+AJ89 -> 0 | AM89: =+AK89+AL89 -> 539351.17
D90: I.2 Total Indirect Cost | J90: =J89 -> 77448.935 | K90: =K89 -> 77448.935 | L90: =L89 -> 0 | R90: =R89 -> 203307.49 | S90: =S89 -> 203307.49 | T90: =T89 -> 0 | Z90: =Z89 -> 213546.62 | AA90: =AA89 -> 213546.62 | AB90: =AB89 -> 0 | AH90: =AH89 -> 45048.128 | AI90: =AI89 -> 45048.128 | AJ90: =AJ89 -> 0 | AK90: =K90+S90+AA90+AI90 -> 539351.17 | AL90: =L90+T90+AB90+AJ90 -> 0 | AM90: =+AK90+AL90 -> 539351.17
D91: J. GRAND TOTAL | J91: =J87+J90 -> 351313.63 | K91: =K87+K90 -> 351313.63 | L91: =L87+L90 -> 0 | R91: =R87+R90 -> 922216.59 | S91: =S87+S90 -> 922216.59 | T91: =T87+T90 -> 0 | Z91: =Z87+Z90 -> 968661.96 | AA91: =AA87+AA90 -> 968661.96 | AB91: =AB87+AB90 -> 0 | AH91: =AH87+AH90 -> 204332.7 | AI91: =AI87+AI90 -> 204332.7 | AJ91: =AJ87+AJ90 -> 0 | AK91: =K91+S91+AA91+AI91 -> 2446524.9 | AL91: =L91+T91+AB91+AJ91 -> 0 | AM91: =+AK91+AL91 -> 2446524.9
AL94: Extra | AM94: 1805524.7
AL95: Original | AM95: 640999.73
AL96: Total | AM96: =SUM(AM94:AM95) -> 2446524.5 | AO96: =+AM96-AM91 -> -0.41907104

Sheet Color Coded Merged Budget
A1: PARTNERS OF THE AMERICAS - Mexico Migration Messaging Project (MMMP) - Cost Extension
A2: Merit and Cost of Living Increases - 5% | B2: 1.05
A3: Inflation - 4% | B3: 1.04 | L3: Budget 01 | M3: Budget 02 | N3: Budget 01+02
A5: All costs in US$ | B5: Year 1 (Oct 2023 - Sept 2024) | J5: Year 2 (October 2024 - September 2025) | R5: Year 3 (October 2025 - September 2026) | Z5: Year 4 (October 2026 - April 2027) | AH5: Total
A6: Budget Line Items | B6: No. | C6: Unit Type | D6: Freq. | E6: % | F6: Rate | G6: Total | H6: Federal | I6: Cost Share | J6: No. | K6: Unit Type | L6: Freq. | M6: % | N6: Rate | O6: Total | P6: Federal | Q6: Cost Share | R6: No. | S6: Unit Type | T6: Freq. | U6: % | V6: Rate | W6: Total | X6: Federal | Y6: Cost Share | Z6: No. | AA6: Unit Type | AB6: Freq. | AC6: % | AD6: Rate | AE6: Total | AF6: Federal | AG6: Cost Share | AH6: Federal | AI6: Cost Share | AJ6: Grand Total
A7: A. Personnel
A8: A.1 Field Staff Salaries
A9: A.1.1 Country Director Mexico | B9: 1 | C9: Month | D9: 12 | E9: 0.05 | F9: 13450 | G9: =B9*F9*D9*E9 -> 8070 | H9: =G9 -> 8070 | I9: =G9-H9 -> 0 | J9: 1 | K9: Month | L9: 12 | M9: 0.05 | N9: =+F9*1.04 -> 13988 | O9: =J9*N9*L9*M9 -> 8392.8 | P9: =O9 -> 8392.8 | Q9: =O9-P9 -> 0 | AH9: =H9+P9+X9+AF9 -> 16462.8 | AI9: =I9+Q9+Y9+AG9 -> 0 | AJ9: =+AH9+AI9 -> 16462.8
A10: A.1.2 Program Director/Coordinator | B10: 1 | C10: Month | D10: 12 | E10: 0.1 | F10: 8650 | G10: =B10*F10*D10*E10 -> 10380 | H10: =G10 -> 10380 | I10: =G10-H10 -> 0 | J10: 1 | K10: Month | L10: 12 | M10: 0.1 | N10: =F10*$B$3 -> 8996 | O10: =J10*N10*L10*M10 -> 10795.2 | P10: =O10 -> 10795.2 | Q10: =O10-P10 -> 0 | R10: 1 | S10: Month | T10: 12 | U10: 1 | V10: 4830 | W10: =R10*V10*T10*U10 -> 57960 | X10: =W10 -> 57960 | Y10: =W10-X10 -> 0 | Z10: 1 | AA10: Month | AB10: 7 | AC10: 1 | AD10: =V10*$B$2 -> 5071.5 | AE10: =Z10*AD10*AB10*AC10 -> 35500.5 | AF10: =AE10 -> 35500.5 | AG10: =AE10-AF10 -> 0 | AH10: =H10+P10+X10+AF10 -> 114635.7 | AI10: =I10+Q10+Y10+AG10 -> 0 | AJ10: =+AH10+AI10 -> 114635.7
A11: A.1.3 Senior Communications Specialist | B11: 1 | C11: Month | D11: 12 | E11: 0.3 | F11: 4100 | G11: =B11*F11*D11*E11 -> 14760 | H11: =G11 -> 14760 | I11: =G11-H11 -> 0 | J11: 1 | K11: Month | L11: 12 | M11: 0.3 | N11: =+F11*1.04 -> 4264 | O11: =J11*N11*L11*M11 -> 15350.4 | P11: =O11 -> 15350.4 | Q11: =O11-P11 -> 0 | AH11: =H11+P11+X11+AF11 -> 30110.4 | AI11: =I11+Q11+Y11+AG11 -> 0 | AJ11: =+AH11+AI11 -> 30110.4
A12: A.1.4 Communications Specialist | B12: 1 | C12: Month | D12: 12 | E12: 0.3 | F12: 3000 | G12: =B12*F12*D12*E12 -> 10800 | H12: =G12 -> 10800 | I12: =G12-H12 -> 0 | J12: 1 | K12: Month | L12: 12 | M12: 0.3 | N12: =F12*B3 -> 3120 | O12: =J12*N12*L12*M12 -> 11232 | P12: =O12 -> 11232 | Q12: =O12-P12 -> 0 | R12: 1 | S12: Month | T12: 12 | U12: 0.75 | V12: =2300*$B$2 -> 2415 | W12: =R12*V12*T12*U12 -> 21735 | X12: =W12 -> 21735 | Y12: =W12-X12 -> 0 | Z12: 1 | AA12: Month | AB12: 3 | AC12: 0.75 | AD12: =V12*$B$2 -> 2535.75 | AE12: =Z12*AD12*AB12*AC12 -> 5705.4375 | AF12: =AE12 -> 5705.4375 | AG12: =AE12-AF12 -> 0 | AH12: =H12+P12+X12+AF12 -> 49472.438 | AI12: =I12+Q12+Y12+AG12 -> 0 | AJ12: =+AH12+AI12 -> 49472.438
A13: A.1.5 Social Media Analyst | B13: 1 | C13: Month | D13: 12 | E13: 0.3 | F13: 2100 | G13: =B13*F13*D13*E13 -> 7560 | H13: =G13 -> 7560 | I13: =G13-H13 -> 0 | J13: 1 | K13: Month | L13: 12 | M13: 0.3 | N13: =+F13*1.04 -> 2184 | O13: =J13*N13*L13*M13 -> 7862.4 | P13: =O13 -> 7862.4 | Q13: =O13-P13 -> 0 | AH13: =H13+P13+X13+AF13 -> 15422.4 | AI13: =I13+Q13+Y13+AG13 -> 0 | AJ13: =+AH13+AI13 -> 15422.4
A14: A.1.6 Monitoring, Evaluation, and Learning Officer | B14: 1 | C14: Month | D14: 12 | E14: 0.25 | F14: 3100 | G14: =B14*F14*D14*E14 -> 9300 | H14: =G14 -> 9300 | I14: =G14-H14 -> 0 | J14: 1 | K14: Month | L14: 12 | M14: 0.25 | N14: =+F14*1.04 -> 3224 | O14: =J14*N14*L14*M14 -> 9672 | P14: =O14 -> 9672 | Q14: =O14-P14 -> 0 | AH14: =H14+P14+X14+AF14 -> 18972 | AI14: =I14+Q14+Y14+AG14 -> 0 | AJ14: =+AH14+AI14 -> 18972
A15: A.1.7 Finance & Administration Director | B15: 1 | C15: Month | D15: 12 | E15: 0.05 | F15: 5500 | G15: =B15*F15*D15*E15 -> 3300 | H15: =G15 -> 3300 | I15: =G15-H15 -> 0 | J15: 1 | K15: Month | L15: 12 | M15: 0.05 | N15: =+F15*1.04 -> 5720 | O15: =J15*N15*L15*M15 -> 3432 | P15: =O15 -> 3432 | Q15: =O15-P15 -> 0 | AH15: =H15+P15+X15+AF15 -> 6732 | AI15: =I15+Q15+Y15+AG15 -> 0 | AJ15: =+AH15+AI15 -> 6732
A16: A.1.8 Finance & Administration Officer | B16: 1 | C16: Month | D16: 12 | E16: 0.2 | F16: 2100 | G16: =B16*F16*D16*E16 -> 5040 | H16: =G16 -> 5040 | I16: =G16-H16 -> 0 | J16: 1 | K16: Month | L16: 12 | M16: 0.2 | N16: =F16*1.04 -> 2184 | O16: =J16*N16*L16*M16 -> 5241.6 | P16: =O16 -> 5241.6 | Q16: =O16-P16 -> 0 | R16: 1 | S16: Month | T16: 12 | U16: 0.5 | V16: =1833*$B$2 -> 1924.65 | W16: =R16*V16*T16*U16 -> 11547.9 | X16: =W16 -> 11547.9 | Y16: =W16-X16 -> 0 | Z16: 1 | AA16: Month | AB16: 6 | AC16: 0.5 | AD16: =V16*$B$2 -> 2020.8825 | AE16: =Z16*AD16*AB16*AC16 -> 6062.6475 | AF16: =AE16 -> 6062.6475 | AG16: =AE16-AF16 -> 0 | AH16: =H16+P16+X16+AF16 -> 27892.147 | AI16: =I16+Q16+Y16+AG16 -> 0 | AJ16: =+AH16+AI16 -> 27892.147
A17: A.2 HQ Staff Salaries
A18: A.2.1 Program Manager (HQ) | B18: 1 | C18: Month | D18: 12 | E18: 0.2 | F18: =55000/12 -> 4583.3333 | G18: =B18*F18*D18*E18 -> 11000 | H18: =G18 -> 11000 | I18: =G18-H18 -> 0 | J18: 1 | K18: Month | L18: 12 | M18: 0.2 | N18: =F18*1.04 -> 4766.6667 | O18: =J18*N18*L18*M18 -> 11440 | P18: =O18 -> 11440 | Q18: =O18-P18 -> 0 | R18: 1 | S18: Month | T18: 12 | U18: 0.05 | V18: =10000*$B$2 -> 10500 | W18: =R18*V18*T18*U18 -> 6300 | X18: =W18 -> 6300 | Y18: =W18-X18 -> 0 | Z18: 1 | AA18: Month | AB18: 7 | AC18: 0.05 | AD18: =V18*$B$2 -> 11025 | AE18: =Z18*AD18*AB18*AC18 -> 3858.75 | AF18: =AE18 -> 3858.75 | AG18: =AE18-AF18 -> 0 | AH18: =H18+P18+X18+AF18 -> 32598.75 | AI18: =I18+Q18+Y18+AG18 -> 0 | AJ18: =+AH18+AI18 -> 32598.75
A19: A.2.2. Program Officer (HQ) | B19: 0 | G19: =B19*F19*D19*E19 -> 0 | H19: =G19 -> 0 | I19: =G19-H19 -> 0 | J19: 1 | K19: Month | L19: 12 | M19: 0.25 | N19: 5512 | O19: =J19*N19*L19*M19 -> 16536 | P19: =O19 -> 16536 | Q19: =O19-P19 -> 0 | R19: 1 | S19: Month | T19: 12 | U19: 0.25 | V19: =N19*$B$2 -> 5787.6 | W19: =R19*V19*T19*U19 -> 17362.8 | X19: =W19 -> 17362.8 | Y19: =W19-X19 -> 0 | Z19: 1 | AA19: Month | AB19: 7 | AC19: 0.2 | AD19: =V19*$B$2 -> 6076.98 | AE19: =Z19*AD19*AB19*AC19 -> 8507.772 | AF19: =AE19 -> 8507.772 | AG19: =AE19-AF19 -> 0 | AH19: =H19+P19+X19+AF19 -> 42406.572 | AI19: =I19+Q19+Y19+AG19 -> 0 | AJ19: =+AH19+AI19 -> 42406.572
A20: Subtotal Personnel | G20: =SUM(G9:G19) -> 80210 | H20: =SUM(H9:H19) -> 80210 | I20: =SUM(I9:I19) -> 0 | O20: =SUM(O9:O19) -> 99954.4 | P20: =SUM(P9:P19) -> 99954.4 | Q20: =SUM(Q9:Q19) -> 0 | W20: =SUM(W9:W19) -> 114905.7 | X20: =SUM(X9:X19) -> 114905.7 | Y20: =SUM(Y9:Y19) -> 0 | AE20: =SUM(AE9:AE19) -> 59635.107 | AF20: =SUM(AF9:AF19) -> 59635.107 | AG20: =SUM(AG9:AG19) -> 0 | AH20: =SUM(AH9:AH19) -> 354705.21 | AI20: =SUM(AI9:AI19) -> 0 | AJ20: =SUM(AJ9:AJ19) -> 354705.21
A21: B. Fringe Benefits
A22: B.1 HQ Fringe Benefits
A23: B.1.1 U.S.-Based Personnel Fringe Benefits | C23: % | E23: 0.2347 | G23: =$E23*SUM(G18:G19) -> 2581.7 | H23: =G23 -> 2581.7 | I23: 0 | K23: % | M23: 0.2347 | O23: =M23*SUM(O18:O19) -> 6565.9672 | P23: =O23 -> 6565.9672 | Q23: 0 | S23: % | U23: 0.2347 | W23: =U23*SUM(W18:W19) -> 5553.6592 | X23: =W23 -> 5553.6592 | Y23: 0 | AA23: % | AC23: 0.2347 | AE23: =AC23*SUM(AE18:AE19) -> 2902.4227 | AF23: =AE23 -> 2902.4227 | AG23: 0 | AH23: =H23+P23+X23+AF23 -> 17603.749 | AI23: =I23+Q23+Y23+AG23 -> 0 | AJ23: =+AH23+AI23 -> 17603.749
A24: B.2 Field Fringe Benefits
A25: B.2.1 Mexico Field Staff Fringe Benefits | C25: % | E25: 0.3671 | G25: =$E25*SUM(G9:G16) -> 25406.991 | H25: =G25 -> 25406.991 | I25: 0 | K25: % | M25: =E25 -> 0.3671 | O25: =M25*SUM(O9:O16) -> 26423.271 | P25: =O25 -> 26423.271 | Q25: 0 | S25: % | U25: 0.5281 | W25: =U25*SUM(W10:W16) -> 48185.375 | X25: =W25 -> 48185.375 | Y25: 0 | AA25: % | AC25: 0.5281 | AE25: =AC25*SUM(AE10:AE16) -> 24962.54 | AF25: =AE25 -> 24962.54 | AG25: 0 | AH25: =H25+P25+X25+AF25 -> 124978.18 | AI25: =I25+Q25+Y25+AG25 -> 0 | AJ25: =+AH25+AI25 -> 124978.18
A26: Subtotal Fringe Benefits | G26: =SUM(G23:G25) -> 27988.691 | H26: =SUM(H23:H25) -> 27988.691 | I26: =SUM(I23:I25) -> 0 | O26: =SUM(O23:O25) -> 32989.238 | P26: =SUM(P23:P25) -> 32989.238 | Q26: =SUM(Q23:Q25) -> 0 | W26: =SUM(W23:W25) -> 53739.035 | X26: =SUM(X23:X25) -> 53739.035 | Y26: =SUM(Y23:Y25) -> 0 | AE26: =SUM(AE23:AE25) -> 27864.962 | AF26: =SUM(AF23:AF25) -> 27864.962 | AG26: =SUM(AG23:AG25) -> 0 | AH26: =SUM(AH23:AH25) -> 142581.93 | AI26: =SUM(AI23:AI25) -> 0 | AJ26: =SUM(AJ23:AJ25) -> 142581.93
A27: C. Travel
A28: C.1 HQ Staff International Travel
A29: C.1.1 International Airfare (DC-MX) | B29: 1 | C29: Flight | D29: 1 | E29: 1 | F29: 700 | G29: =B29*F29*D29 -> 700 | H29: =G29 -> 700 | I29: =G29-H29 -> 0 | J29: 1 | K29: Flight | L29: 1 | M29: 1 | N29: =+F29*1.04 -> 728 | O29: =J29*N29*L29*M29 -> 728 | P29: =O29 -> 728 | Q29: =O29-P29 -> 0 | AH29: =H29+P29+X29+AF29 -> 1428 | AI29: =I29+Q29+Y29+AG29 -> 0 | AJ29: =+AH29+AI29 -> 1428
A30: C.1.2 Ground Transportation | B30: 1 | C30: Trip | D30: 1 | E30: 1 | F30: 100 | G30: =B30*F30*D30 -> 100 | H30: =G30 -> 100 | I30: =G30-H30 -> 0 | J30: 1 | K30: Trip | L30: 1 | M30: 1 | N30: =+F30*1.04 -> 104 | O30: =J30*N30*L30*M30 -> 104 | P30: =O30 -> 104 | Q30: =O30-P30 -> 0 | AH30: =H30+P30+X30+AF30 -> 204 | AI30: =I30+Q30+Y30+AG30 -> 0 | AJ30: =+AH30+AI30 -> 204
A31: C.1.3 Lodging | B31: 1 | C31: Night | D31: 4 | E31: 1 | F31: 120 | G31: =B31*F31*D31 -> 480 | H31: =G31 -> 480 | I31: =G31-H31 -> 0 | J31: 1 | K31: Night | L31: 4 | M31: 1 | N31: =+F31*1.04 -> 124.8 | O31: =J31*N31*L31*M31 -> 499.2 | P31: =O31 -> 499.2 | Q31: =O31-P31 -> 0 | AH31: =H31+P31+X31+AF31 -> 979.2 | AI31: =I31+Q31+Y31+AG31 -> 0 | AJ31: =+AH31+AI31 -> 979.2
A32: C.1.4 M&IE | B32: 1 | C32: Day | D32: 5 | E32: 1 | F32: 95 | G32: =B32*F32*D32 -> 475 | H32: =G32 -> 475 | I32: =G32-H32 -> 0 | J32: 1 | K32: Day | L32: 5 | M32: 1 | N32: =+F32*1.04 -> 98.8 | O32: =J32*N32*L32*M32 -> 494 | P32: =O32 -> 494 | Q32: =O32-P32 -> 0 | AH32: =H32+P32+X32+AF32 -> 969 | AI32: =I32+Q32+Y32+AG32 -> 0 | AJ32: =+AH32+AI32 -> 969
A33: C.2 Local Staff In-Country Travel to Target Geographic Regions
A34: C.2.1 Domestic Airfare | B34: 2 | C34: Flight | D34: 1 | E34: 1 | F34: 200 | G34: =B34*F34*D34 -> 400 | H34: =G34 -> 400 | I34: =G34-H34 -> 0 | J34: 2 | K34: Flight | L34: 1 | M34: 1 | N34: =+F34*1.04 -> 208 | O34: =J34*N34*L34*M34 -> 416 | P34: =O34 -> 416 | Q34: =O34-P34 -> 0 | R34: 2 | S34: Flight | T34: 1 | U34: 1 | V34: 208 | W34: =+V34*T34*R34*U34 -> 416 | X34: =W34 -> 416 | Y34: =W34-X34 -> 0 | Z34: 1 | AA34: Flight | AB34: 1 | AC34: 1 | AD34: =V34*$B$3 -> 216.32 | AE34: =+AD34*AB34*Z34*$E34 -> 216.32 | AF34: =AE34 -> 216.32 | AG34: =AE34-AF34 -> 0 | AH34: =H34+P34+X34+AF34 -> 1448.32 | AI34: =I34+Q34+Y34+AG34 -> 0 | AJ34: =+AH34+AI34 -> 1448.32
A35: C.2.2 Lodging | B35: 6 | C35: Night | D35: 3 | E35: 1 | F35: 100 | G35: =B35*F35*D35 -> 1800 | H35: =G35 -> 1800 | I35: =G35-H35 -> 0 | J35: 6 | K35: Night | L35: 3 | M35: 1 | N35: =+F35*1.04 -> 104 | O35: =J35*N35*L35*M35 -> 1872 | P35: =O35 -> 1872 | Q35: =O35-P35 -> 0 | R35: 2 | S35: Night | T35: 3 | U35: 1 | V35: 130 | W35: =+V35*T35*R35*U35 -> 780 | X35: =W35 -> 780 | Y35: =W35-X35 -> 0 | Z35: 1 | AA35: Night | AB35: 3 | AC35: 1 | AD35: =V35*$B$3 -> 135.2 | AE35: =+AD35*AB35*Z35*$E35 -> 405.6 | AF35: =AE35 -> 405.6 | AG35: =AE35-AF35 -> 0 | AH35: =H35+P35+X35+AF35 -> 4857.6 | AI35: =I35+Q35+Y35+AG35 -> 0 | AJ35: =+AH35+AI35 -> 4857.6
A36: C.2.3 M&IE | B36: 6 | C36: Day | D36: 4 | E36: 1 | F36: 70 | G36: =B36*F36*D36 -> 1680 | H36: =G36 -> 1680 | I36: =G36-H36 -> 0 | J36: 6 | K36: Day | L36: 4 | M36: 1 | N36: =+F36*1.04 -> 72.8 | O36: =J36*N36*L36*M36 -> 1747.2 | P36: =O36 -> 1747.2 | Q36: =O36-P36 -> 0 | R36: 2 | S36: Day | T36: 4 | U36: 1 | V36: 55 | W36: 441 | X36: =W36 -> 441 | Y36: =W36-X36 -> 0 | Z36: 1 | AA36: Day | AB36: 4 | AC36: 1 | AD36: =V36*$B$3 -> 57.2 | AE36: =+AD36*AB36*Z36*$E36 -> 228.8 | AF36: =AE36 -> 228.8 | AG36: =AE36-AF36 -> 0 | AH36: =H36+P36+X36+AF36 -> 4097 | AI36: =I36+Q36+Y36+AG36 -> 0 | AJ36: =+AH36+AI36 -> 4097
A37: C.2.4 Ground Transportation | B37: 1 | C37: Month | D37: 10 | E37: 1 | F37: 150 | G37: =B37*F37*D37 -> 1500 | H37: =G37 -> 1500 | I37: =G37-H37 -> 0 | J37: 1 | K37: Month | L37: 10 | M37: 1 | N37: =+F37*1.04 -> 156 | O37: =J37*N37*L37*M37 -> 1560 | P37: =O37 -> 1560 | Q37: =O37-P37 -> 0 | R37: 1 | S37: Month | T37: 12 | U37: 1 | V37: 78 | W37: =+V37*T37*R37*U37 -> 936 | X37: =W37 -> 936 | Y37: =W37-X37 -> 0 | Z37: 1 | AA37: Month | AB37: 4 | AC37: 1 | AD37: =V37*$B$3 -> 81.12 | AE37: =+AD37*AB37*Z37*$E37 -> 324.48 | AF37: =AE37 -> 324.48 | AG37: =AE37-AF37 -> 0 | AH37: =H37+P37+X37+AF37 -> 4320.48 | AI37: =I37+Q37+Y37+AG37 -> 0 | AJ37: =+AH37+AI37 -> 4320.48
A38: Subtotal Travel | G38: =SUM(G29:G37) -> 7135 | H38: =SUM(H29:H37) -> 7135 | I38: =SUM(I29:I37) -> 0 | O38: =SUM(O29:O37) -> 7420.4 | P38: =SUM(P29:P37) -> 7420.4 | Q38: =SUM(Q29:Q37) -> 0 | W38: =SUM(W29:W37) -> 2573 | X38: =SUM(X29:X37) -> 2573 | Y38: =SUM(Y29:Y37) -> 0 | AE38: =SUM(AE29:AE37) -> 1175.2 | AF38: =SUM(AF29:AF37) -> 1175.2 | AG38: =SUM(AG29:AG37) -> 0 | AH38: =SUM(AH29:AH37) -> 18303.6 | AI38: =SUM(AI29:AI37) -> 0 | AJ38: =SUM(AJ29:AJ37) -> 18303.6
A39: D. Equipment
A40: E. Supplies
A41: E.1 Office Supplies | B41: 1 | C41: Month | D41: 12 | E41: 1 | F41: 50 | G41: =B41*F41*D41*E41 -> 600 | H41: =G41 -> 600 | I41: =G41-H41 -> 0 | J41: 1 | K41: Month | L41: 12 | M41: 1 | N41: =F41*$B$3 -> 52 | O41: =J41*N41*L41*M41 -> 624 | P41: =O41 -> 624 | Q41: =O41-P41 -> 0 | R41: 1 | S41: Month | T41: 12 | U41: 1 | V41: 31.2 | W41: =R41*V41*T41*U41 -> 374.4 | X41: =W41 -> 374.4 | Y41: =W41-X41 -> 0 | Z41: 1 | AA41: Month | AB41: 6 | AC41: 1 | AD41: =V41*$B$3 -> 32.448 | AE41: =Z41*AD41*AB41*AC41 -> 194.688 | AF41: =AE41 -> 194.688 | AG41: =AE41-AF41 -> 0 | AH41: =H41+P41+X41+AF41 -> 1793.088 | AI41: =I41+Q41+Y41+AG41 -> 0 | AJ41: =+AH41+AI41 -> 1793.088
A42: E.2 Laptop Computers & Software | B42: 1 | C42: Unit | D42: 3 | E42: 1 | F42: 1000 | G42: =B42*F42*D42*E42 -> 3000 | H42: =G42 -> 3000 | I42: =G42-H42 -> 0 | J42: 1 | K42: Unit | L42: 1 | M42: 1 | N42: 1200 | O42: 1222 | P42: =O42 -> 1222 | Q42: =O42-P42 -> 0 | R42: 0 | S42: Unit | T42: 0 | U42: 0 | W42: =R42*V42*T42*U42 -> 0 | X42: =W42 -> 0 | Y42: =W42-X42 -> 0 | Z42: 0 | AA42: Unit | AB42: 0 | AC42: 0 | AE42: =Z42*AD42*AB42*$E42 -> 0 | AF42: =AE42 -> 0 | AG42: =AE42-AF42 -> 0 | AH42: =H42+P42+X42+AF42 -> 4222 | AI42: =I42+Q42+Y42+AG42 -> 0 | AJ42: =+AH42+AI42 -> 4222
A43: E.3 Photography Supplies | B43: 0 | C43: Lumpsum | D43: 0 | E43: 1 | G43: =B43*F43*D43*E43 -> 0 | H43: =G43 -> 0 | I43: =G43-H43 -> 0 | J43: 1 | K43: Lumpsum | L43: 1 | M43: 1 | N43: 1200 | O43: =J43*N43*L43*M43 -> 1200 | P43: =O43 -> 1200 | Q43: =O43-P43 -> 0 | R43: 0 | S43: Lumpsum | T43: 0 | U43: 0 | W43: =R43*V43*T43*U43 -> 0 | X43: =W43 -> 0 | Y43: =W43-X43 -> 0 | Z43: 0 | AA43: Lumpsum | AB43: 0 | AC43: 0 | AD43: =V43 -> 0 | AE43: =Z43*AD43*AB43*AC43 -> 0 | AF43: =AE43 -> 0 | AG43: =AE43-AF43 -> 0 | AH43: =H43+P43+X43+AF43 -> 1200 | AI43: =I43+Q43+Y43+AG43 -> 0 | AJ43: =+AH43+AI43 -> 1200
A44: Subtotal Supplies | G44: =SUM(G41:G42) -> 3600 | H44: =SUM(H41:H42) -> 3600 | I44: =SUM(I41:I42) -> 0 | O44: =SUM(O41:O43) -> 3046 | P44: =SUM(P41:P43) -> 3046 | Q44: =SUM(Q41:Q42) -> 0 | W44: =SUM(W41:W43) -> 374.4 | X44: =SUM(X41:X43) -> 374.4 | Y44: =SUM(Y41:Y42) -> 0 | AE44: =SUM(AE41:AE43) -> 194.688 | AF44: =SUM(AF41:AF43) -> 194.688 | AG44: =SUM(AG41:AG42) -> 0 | AH44: =SUM(AH41:AH43) -> 7215.088 | AI44: =SUM(AI41:AI43) -> 0 | AJ44: =SUM(AJ41:AJ43) -> 7215.088
A45: F. Contractual
A46: F.1 Consultants
A47: F.1.1 Social Media Influencer Consultants | B47: 4 | C47: Month | D47: 6 | E47: 1 | F47: 1825 | G47: =B47*F47*D47 -> 43800 | H47: =G47 -> 43800 | I47: =G47-H47 -> 0 | J47: 4 | K47: Month | L47: 6 | M47: 1 | N47: 1825 | O47: =J47*N47*L47*M47 -> 43800 | P47: =O47 -> 43800 | Q47: =O47-P47 -> 0 | R47: 1 | S47: Month | T47: 12 | U47: 1 | V47: 4000 | W47: =R47*V47*T47*U47 -> 48000 | X47: =W47 -> 48000 | Y47: =W47-X47 -> 0 | Z47: 1 | AA47: Month | AB47: 5 | AC47: 1 | AD47: 4000 | AE47: =Z47*AD47*AB47*AC47 -> 20000 | AF47: =AE47 -> 20000 | AG47: =AE47-AF47 -> 0 | AH47: =H47+P47+X47+AF47 -> 155600 | AI47: =I47+Q47+Y47+AG47 -> 0 | AJ47: =+AH47+AI47 -> 155600
A48: F.1.2 Technical Advisor on Public Policy | B48: 1 | C48: Month | D48: 5 | E48: 1 | F48: 3500 | G48: =B48*F48*D48 -> 17500 | H48: =G48 -> 17500 | I48: =G48-H48 -> 0 | J48: 1 | K48: Month | L48: 5 | M48: 1 | N48: 3500 | O48: =J48*N48*L48*M48 -> 17500 | P48: =O48 -> 17500 | Q48: =O48-P48 -> 0 | AH48: =H48+P48+X48+AF48 -> 35000 | AI48: =I48+Q48+Y48+AG48 -> 0 | AJ48: =+AH48+AI48 -> 35000
A49: F.1.3 Consultant for Participatory Research for Data Collection | B49: 1 | C49: Month | D49: 2 | E49: 1 | F49: 3000 | G49: =B49*F49*D49 -> 6000 | H49: =G49 -> 6000 | I49: =G49-H49 -> 0 | J49: 1 | K49: Month | L49: 2 | M49: 1 | N49: 3000 | O49: =J49*N49*L49*M49 -> 6000 | P49: =O49 -> 6000 | Q49: =O49-P49 -> 0 | AH49: =H49+P49+X49+AF49 -> 12000 | AI49: =I49+Q49+Y49+AG49 -> 0 | AJ49: =+AH49+AI49 -> 12000
A50: F.1.4 Consultant for Graphic Design Services | B50: 0 | C50: Contract | D50: 0 | E50: 1 | F50: 12000 | G50: =B50*F50*D50 -> 0 | H50: =G50 -> 0 | I50: =G50-H50 -> 0 | J50: 1 | K50: Contract | L50: 1 | M50: 0.45 | N50: 12000 | O50: =J50*N50*L50*M50 -> 5400 | P50: =O50 -> 5400 | Q50: =O50-P50 -> 0 | R50: 1 | S50: Contract | T50: 1 | U50: 0.45 | V50: 12000 | W50: =R50*V50*T50*U50 -> 5400 | X50: =W50 -> 5400 | Y50: =W50-X50 -> 0 | Z50: 1 | AA50: Contract | AB50: 1 | AC50: 0.1 | AD50: 12000 | AE50: =Z50*AD50*AB50*AC50 -> 1200 | AF50: =AE50 -> 1200 | AG50: =AE50-AF50 -> 0 | AH50: =H50+P50+X50+AF50 -> 12000 | AI50: =I50+Q50+Y50+AG50 -> 0 | AJ50: =+AH50+AI50 -> 12000
A51: F.2 Contracts
A52: F.2.1 Contract for Live Portrait and Immersive Experience | B52: 1 | C52: Contract | D52: 1 | E52: 1 | F52: 25000 | G52: =B52*F52*D52 -> 25000 | H52: =G52 -> 25000 | I52: =G52-H52 -> 0 | J52: 1 | K52: Contract | L52: 1 | M52: 0.25 | N52: 28000 | O52: =J52*N52*L52*M52 -> 7000 | P52: =O52 -> 7000 | Q52: =O52-P52 -> 0 | R52: 1 | S52: Contract | T52: 1 | U52: 0.5 | V52: 28000 | W52: =R52*V52*T52*U52 -> 14000 | X52: =W52 -> 14000 | Y52: =W52-X52 -> 0 | Z52: 1 | AA52: Contract | AB52: 1 | AC52: 0.25 | AD52: 28000 | AE52: =Z52*AD52*AB52*AC52 -> 7000 | AF52: =AE52 -> 7000 | AG52: =AE52-AF52 -> 0 | AH52: =H52+P52+X52+AF52 -> 53000 | AI52: =I52+Q52+Y52+AG52 -> 0 | AJ52: =+AH52+AI52 -> 53000
A53: F.2.2 Contract to Film & Produce Soap Opera | B53: 1 | C53: Contract | D53: 1 | E53: 1 | F53: 20000 | G53: =B53*F53*D53 -> 20000 | H53: =G53 -> 20000 | I53: =G53-H53 -> 0 | J53: 0 | K53: Contract | L53: 0 | M53: 0 | N53: 20000 | O53: =J53*N53*L53*M53 -> 0 | P53: =O53 -> 0 | Q53: =O53-P53 -> 0 | AH53: =H53+P53+X53+AF53 -> 20000 | AI53: =I53+Q53+Y53+AG53 -> 0 | AJ53: =+AH53+AI53 -> 20000
A54: F.2.3 Security Advisors | B54: 1 | C54: Month | D54: 12 | E54: 1 | F54: 300 | G54: =B54*F54*D54 -> 3600 | H54: =G54 -> 3600 | I54: =G54-H54 -> 0 | J54: 1 | K54: Month | L54: 12 | M54: 1 | N54: 300 | O54: =J54*N54*L54*M54 -> 3600 | P54: =O54 -> 3600 | Q54: =O54-P54 -> 0 | AH54: =H54+P54+X54+AF54 -> 7200 | AI54: =I54+Q54+Y54+AG54 -> 0 | AJ54: =+AH54+AI54 -> 7200
A55: F.2.4 Contract for Translation Services | B55: 0 | C55: Year | D55: 0 | E55: 1 | F55: 20000 | G55: =B55*F55*D55 -> 0 | H55: =G55 -> 0 | I55: =G55-H55 -> 0 | J55: 1 | K55: Contract | L55: 1 | M55: =1/3 -> 0.33333333 | N55: 20000 | O55: =J55*N55*L55*M55 -> 6666.6667 | P55: =O55 -> 6666.6667 | Q55: =O55-P55 -> 0 | R55: 1 | S55: Contract | T55: 1 | U55: =1/3 -> 0.33333333 | V55: 20000 | W55: =R55*V55*T55*U55 -> 6666.6667 | X55: =W55 -> 6666.6667 | Y55: =W55-X55 -> 0 | Z55: 1 | AA55: Contract | AB55: 1 | AC55: =1/3 -> 0.33333333 | AD55: 20000 | AE55: =Z55*AD55*AB55*AC55 -> 6666.6667 | AF55: =AE55 -> 6666.6667 | AG55: =AE55-AF55 -> 0 | AH55: =H55+P55+X55+AF55 -> 20000 | AI55: =I55+Q55+Y55+AG55 -> 0 | AJ55: =+AH55+AI55 -> 20000
A56: F.2.5 Contract for Production of Explainer Videos | B56: 0 | C56: Contract | D56: 0 | E56: 1 | F56: 40000 | G56: =B56*F56*D56 -> 0 | H56: =G56 -> 0 | I56: =G56-H56 -> 0 | J56: 0 | K56: Contract | L56: 0 | M56: 0 | N56: 40000 | O56: =J56*N56*L56*M56 -> 0 | P56: =O56 -> 0 | Q56: =O56-P56 -> 0 | R56: 1 | S56: Contract | T56: 1 | U56: 1 | V56: =N56 -> 40000 | W56: =R56*V56*T56*U56 -> 40000 | X56: =W56 -> 40000 | Y56: =W56-X56 -> 0 | Z56: 0 | AA56: Contract | AB56: 0 | AC56: 0 | AD56: 40000 | AE56: =Z56*AD56*AB56*AC56 -> 0 | AF56: =AE56 -> 0 | AG56: =AE56-AF56 -> 0 | AH56: =H56+P56+X56+AF56 -> 40000 | AI56: =I56+Q56+Y56+AG56 -> 0 | AJ56: =+AH56+AI56 -> 40000
A57: F.2.6 Contract for Transit Marketing Campaign | B57: 0 | C57: Contract | D57: 0 | E57: 1 | F57: 400000 | G57: =B57*F57*D57 -> 0 | H57: =G57 -> 0 | I57: =G57-H57 -> 0 | J57: 0 | K57: Contract | L57: 0 | M57: 0 | N57: 400000 | O57: =J57*N57*L57*M57 -> 0 | P57: =O57 -> 0 | Q57: =O57-P57 -> 0 | R57: 1 | S57: Contract | T57: 1 | U57: 1 | V57: 400000 | W57: =R57*V57*T57*U57 -> 400000 | X57: =W57 -> 400000 | Y57: =W57-X57 -> 0 | Z57: 0 | AA57: Contract | AB57: 0 | AC57: 0 | AD57: 400000 | AE57: =Z57*AD57*AB57*AC57 -> 0 | AF57: =AE57 -> 0 | AG57: =AE57-AF57 -> 0 | AH57: =H57+P57+X57+AF57 -> 400000 | AI57: =I57+Q57+Y57+AG57 -> 0 | AJ57: =+AH57+AI57 -> 400000
A58: F.2.7 Contract for Printing Services | B58: 0 | C58: Contract | D58: 0 | E58: 1 | F58: 37283 | G58: =B58*F58*D58 -> 0 | H58: =G58 -> 0 | I58: =G58-H58 -> 0 | J58: 1 | K58: Contract | L58: 1 | M58: 0.25 | N58: 37283 | O58: =J58*N58*L58*M58 -> 9320.75 | P58: =O58 -> 9320.75 | Q58: =O58-P58 -> 0 | R58: 1 | S58: Contract | T58: 1 | U58: 0.5 | V58: =N58 -> 37283 | W58: =R58*V58*T58*U58 -> 18641.5 | X58: =W58 -> 18641.5 | Y58: =W58-X58 -> 0 | Z58: 1 | AA58: Contract | AB58: 1 | AC58: 0.25 | AD58: =V58 -> 37283 | AE58: =Z58*AD58*AB58*AC58 -> 9320.75 | AF58: =AE58 -> 9320.75 | AG58: =AE58-AF58 -> 0 | AH58: =H58+P58+X58+AF58 -> 37283 | AI58: =I58+Q58+Y58+AG58 -> 0 | AJ58: =+AH58+AI58 -> 37283
A59: F.2.8 Contract for Shelter Coordination and Monitoring | B59: 0 | C59: Contract | D59: 0 | E59: 1 | F59: 5000 | G59: =B59*F59*D59 -> 0 | H59: =G59 -> 0 | I59: =G59-H59 -> 0 | J59: 0 | K59: Contract | L59: 0 | M59: 0 | N59: 5000 | O59: =J59*N59*L59*M59 -> 0 | P59: =O59 -> 0 | Q59: =O59-P59 -> 0 | R59: 1 | S59: Contract | T59: 1 | U59: 0.5 | V59: 5000 | W59: =R59*V59*T59*U59 -> 2500 | X59: =W59 -> 2500 | Y59: =W59-X59 -> 0 | Z59: 1 | AA59: Contract | AB59: 1 | AC59: 0.5 | AD59: 5000 | AE59: =Z59*AD59*AB59*AC59 -> 2500 | AF59: =AE59 -> 2500 | AG59: =AE59-AF59 -> 0 | AH59: =H59+P59+X59+AF59 -> 5000 | AI59: =I59+Q59+Y59+AG59 -> 0 | AJ59: =+AH59+AI59 -> 5000
A60: F.2.9 Contract Dissemination Research and Response | B60: 0 | C60: Contract | D60: 0 | E60: 1 | F60: 225000 | G60: =B60*F60*D60 -> 0 | H60: =G60 -> 0 | I60: =G60-H60 -> 0 | J60: 1 | K60: Contract | L60: 1 | M60: 1 | N60: 225000 | O60: =J60*N60*L60*M60 -> 225000 | P60: =O60 -> 225000 | Q60: =O60-P60 -> 0 | R60: 0 | S60: Contract | T60: 0 | U60: 1 | V60: =N60*$B$3 -> 234000 | W60: =R60*V60*T60*U60 -> 0 | X60: =W60 -> 0 | Y60: =W60-X60 -> 0 | Z60: 0 | AA60: Contract | AB60: 0 | AC60: 1 | AD60: =V60*$B$3 -> 243360 | AE60: =Z60*AD60*AB60*AC60 -> 0 | AF60: =AE60 -> 0 | AG60: =AE60-AF60 -> 0 | AH60: =H60+P60+X60+AF60 -> 225000 | AI60: =I60+Q60+Y60+AG60 -> 0 | AJ60: =+AH60+AI60 -> 225000
A61: Subtotal Contractual | G61: =SUM(G47:G60) -> 115900 | H61: =SUM(H47:H60) -> 115900 | I61: =SUM(I47:I60) -> 0 | O61: =SUM(O47:O60) -> 324287.42 | P61: =SUM(P47:P60) -> 324287.42 | Q61: =SUM(Q47:Q57) -> 0 | W61: =SUM(W47:W60) -> 535208.17 | X61: =SUM(X47:X60) -> 535208.17 | Y61: =SUM(Y47:Y57) -> 0 | AE61: =SUM(AE47:AE60) -> 46687.417 | AF61: =SUM(AF47:AF60) -> 46687.417 | AG61: =SUM(AG47:AG57) -> 0 | AH61: =SUM(AH47:AH60) -> 1022083 | AI61: =SUM(AI47:AI59) -> 0 | AJ61: =SUM(AJ47:AJ60) -> 1022083
A62: G. Other Direct Costs
A63: G.1 Office Costs
A64: G.1.1 Office Space & Utilities | B64: 1 | C64: Month | D64: 12 | E64: 1 | F64: 350 | G64: =B64*F64*D64*E64 -> 4200 | H64: =G64 -> 4200 | I64: =G64-H64 -> 0 | J64: 1 | K64: Month | L64: 12 | M64: 1 | N64: =F64*$B$3 -> 364 | O64: =J64*N64*L64*M64 -> 4368 | P64: =O64 -> 4368 | Q64: =O64-P64 -> 0 | R64: 1 | S64: Month | T64: 12 | U64: 1 | V64: 620 | W64: =R64*T64*V64*U64 -> 7440 | X64: =W64 -> 7440 | Y64: =W64-X64 -> 0 | Z64: 1 | AA64: Month | AB64: 4 | AC64: 1 | AD64: =V64*$B$3 -> 644.8 | AE64: =Z64*AD64*AB64*AC64 -> 2579.2 | AF64: =AE64 -> 2579.2 | AG64: =AE64-AF64 -> 0 | AH64: =H64+P64+X64+AF64 -> 18587.2 | AI64: =I64+Q64+Y64+AG64 -> 0 | AJ64: =+AH64+AI64 -> 18587.2
A65: G.1.2 Banking and Cash Handling Fees | B65: 1 | C65: Month | D65: 12 | E65: 1 | F65: 35 | G65: =B65*F65*D65*E65 -> 420 | H65: =G65 -> 420 | I65: =G65-H65 -> 0 | J65: 1 | K65: Month | L65: 12 | M65: 1 | N65: =F65*$B$3 -> 36.4 | O65: =J65*N65*L65*M65 -> 436.8 | P65: =O65 -> 436.8 | Q65: =O65-P65 -> 0 | R65: 1 | S65: Month | T65: 12 | U65: 1 | V65: 21.84 | W65: =R65*T65*V65*U65 -> 262.08 | X65: =W65 -> 262.08 | Y65: =W65-X65 -> 0 | Z65: 1 | AA65: Month | AB65: 7 | AC65: 1 | AD65: =V65*$B$3 -> 22.7136 | AE65: =Z65*AD65*AB65*AC65 -> 158.9952 | AF65: =AE65 -> 158.9952 | AG65: =AE65-AF65 -> 0 | AH65: =H65+P65+X65+AF65 -> 1277.8752 | AI65: =I65+Q65+Y65+AG65 -> 0 | AJ65: =+AH65+AI65 -> 1277.8752
A66: G.1.3 Payroll Processing | B66: 1 | C66: Month | D66: 12 | E66: 1 | F66: 50 | G66: =B66*F66*D66*E66 -> 600 | H66: =G66 -> 600 | I66: =G66-H66 -> 0 | J66: 1 | K66: Month | L66: 12 | M66: 1 | N66: =F66*$B$3 -> 52 | O66: =J66*N66*L66*M66 -> 624 | P66: =O66 -> 624 | Q66: =O66-P66 -> 0 | R66: 1 | S66: Month | T66: 12 | U66: 1 | V66: 41.6 | W66: =R66*T66*V66*U66 -> 499.2 | X66: =W66 -> 499.2 | Y66: =W66-X66 -> 0 | Z66: 1 | AA66: Month | AB66: 7 | AC66: 1 | AD66: =V66*$B$3 -> 43.264 | AE66: =Z66*AD66*AB66*AC66 -> 302.848 | AF66: =AE66 -> 302.848 | AG66: =AE66-AF66 -> 0 | AH66: =H66+P66+X66+AF66 -> 2026.048 | AI66: =I66+Q66+Y66+AG66 -> 0 | AJ66: =+AH66+AI66 -> 2026.048
A67: G.1.4 Communications Costs (Phone, Data, Internet, etc.) | B67: 1 | C67: Month | D67: 12 | E67: 1 | F67: 150 | G67: =B67*F67*D67*E67 -> 1800 | H67: =G67 -> 1800 | I67: =G67-H67 -> 0 | J67: 1 | K67: Month | L67: 12 | M67: 1 | N67: =F67*$B$3 -> 156 | O67: =J67*N67*L67*M67 -> 1872 | P67: =O67 -> 1872 | Q67: =O67-P67 -> 0 | R67: 1 | S67: Month | T67: 12 | U67: 1 | V67: 124.8 | W67: =R67*T67*V67*U67 -> 1497.6 | X67: =W67 -> 1497.6 | Y67: =W67-X67 -> 0 | Z67: 1 | AA67: Month | AB67: 7 | AC67: 0.8 | AD67: =V67*$B$3 -> 129.792 | AE67: =Z67*AD67*AB67*AC67 -> 726.8352 | AF67: =AE67 -> 726.8352 | AG67: =AE67-AF67 -> 0 | AH67: =H67+P67+X67+AF67 -> 5896.4352 | AI67: =I67+Q67+Y67+AG67 -> 0 | AJ67: =+AH67+AI67 -> 5896.4352
A68: G.1.5 HR, Platform Subscriptions (Timekeeping and Expense Reporting) | B68: 1 | C68: Month | D68: 12 | E68: 1 | F68: 120 | G68: =B68*F68*D68*E68 -> 1440 | H68: =G68 -> 1440 | I68: =G68-H68 -> 0 | J68: 1 | K68: Month | L68: 12 | M68: 1 | N68: =F68*$B$3 -> 124.8 | O68: =J68*N68*L68*M68 -> 1497.6 | P68: =O68 -> 1497.6 | Q68: =O68-P68 -> 0 | R68: 1 | S68: Month | T68: 12 | U68: 1 | V68: 93.6 | W68: =R68*T68*V68*U68 -> 1123.2 | X68: =W68 -> 1123.2 | Y68: =W68-X68 -> 0 | Z68: 1 | AA68: Month | AB68: 7 | AC68: 1 | AD68: =V68*$B$3 -> 97.344 | AE68: =Z68*AD68*AB68*AC68 -> 681.408 | AF68: =AE68 -> 681.408 | AG68: =AE68-AF68 -> 0 | AH68: =H68+P68+X68+AF68 -> 4742.208 | AI68: =I68+Q68+Y68+AG68 -> 0 | AJ68: =+AH68+AI68 -> 4742.208
A69: G.1.6 Meeting Expenses | B69: 1 | C69: Month | D69: 12 | E69: 1 | F69: 50 | G69: =B69*F69*D69*E69 -> 600 | H69: =G69 -> 600 | I69: =G69-H69 -> 0 | J69: 1 | K69: Month | L69: 12 | M69: 1 | N69: =F69*$B$3 -> 52 | O69: =J69*N69*L69*M69 -> 624 | P69: =O69 -> 624 | Q69: =O69-P69 -> 0 | AH69: =H69+P69+X69+AF69 -> 1224 | AI69: =I69+Q69+Y69+AG69 -> 0 | AJ69: =+AH69+AI69 -> 1224
A70: G.1.7 Procurement Advertising | B70: 1 | C70: Year | D70: 1 | E70: 1 | F70: 400 | G70: =B70*F70*D70*E70 -> 400 | H70: =G70 -> 400 | I70: =G70-H70 -> 0 | J70: 1 | K70: Year | L70: 1 | M70: 1 | N70: =F70*$B$3 -> 416 | O70: =J70*N70*L70*M70 -> 416 | P70: =O70 -> 416 | Q70: =O70-P70 -> 0 | AH70: =H70+P70+X70+AF70 -> 816 | AI70: =I70+Q70+Y70+AG70 -> 0 | AJ70: =+AH70+AI70 -> 816
A71: G.1.8 Legal Fees | B71: 1 | C71: Year | D71: 1 | E71: 1 | F71: 250 | G71: =B71*F71*D71*E71 -> 250 | H71: =G71 -> 250 | I71: =G71-H71 -> 0 | J71: 1 | K71: Year | L71: 1 | M71: 1 | N71: =F71*$B$3 -> 260 | O71: =J71*N71*L71*M71 -> 260 | P71: =O71 -> 260 | Q71: =O71-P71 -> 0 | R71: 1 | S71: Year | T71: 1 | U71: 1 | V71: =N71*$B$3 -> 270.4 | W71: =R71*T71*V71*U71 -> 270.4 | X71: =W71 -> 270.4 | Y71: =W71-X71 -> 0 | Z71: 1 | AA71: Year | AB71: 1 | AC71: 1 | AD71: =V71*$B$3 -> 281.216 | AE71: =Z71*AD71*AB71*AC71 -> 281.216 | AF71: =AE71 -> 281.216 | AG71: =AE71-AF71 -> 0 | AH71: =H71+P71+X71+AF71 -> 1061.616 | AI71: =I71+Q71+Y71+AG71 -> 0 | AJ71: =+AH71+AI71 -> 1061.616
A72: G.1.9 Audit Fees | B72: 1 | C72: Year | D72: 1 | E72: 1 | F72: 100 | G72: =B72*F72*D72*E72 -> 100 | H72: =G72 -> 100 | I72: =G72-H72 -> 0 | J72: 1 | K72: Year | L72: 1 | M72: 1 | N72: =F72*$B$3 -> 104 | O72: =J72*N72*L72*M72 -> 104 | P72: =O72 -> 104 | Q72: =O72-P72 -> 0 | R72: 1 | S72: Year | T72: 1 | U72: 1 | V72: =N72*$B$3 -> 108.16 | W72: =R72*T72*V72*U72 -> 108.16 | X72: =W72 -> 108.16 | Y72: =W72-X72 -> 0 | Z72: 1 | AA72: Year | AB72: 1 | AC72: 1 | AD72: =V72*$B$3 -> 112.4864 | AE72: =Z72*AD72*AB72*AC72 -> 112.4864 | AF72: =AE72 -> 112.4864 | AG72: =AE72-AF72 -> 0 | AH72: =H72+P72+X72+AF72 -> 424.6464 | AI72: =I72+Q72+Y72+AG72 -> 0 | AJ72: =+AH72+AI72 -> 424.6464
A73: G.1.10 Postage/Shipping | B73: 0 | C73: Month | D73: 0 | E73: 1 | F73: 30 | G73: =B73*F73*D73*E73 -> 0 | H73: =G73 -> 0 | I73: =G73-H73 -> 0 | J73: 1 | K73: Month | L73: 12 | M73: 1 | N73: 30 | O73: =J73*N73*L73*M73 -> 360 | P73: =O73 -> 360 | Q73: =O73-P73 -> 0 | R73: 1 | S73: Month | T73: 12 | U73: 1 | V73: =N73*$B$3 -> 31.2 | W73: =R73*T73*V73*U73 -> 374.4 | X73: =W73 -> 374.4 | Y73: =W73-X73 -> 0 | Z73: 1 | AA73: Month | AB73: 7 | AC73: 1 | AD73: =V73*$B$3 -> 32.448 | AE73: =Z73*AD73*AB73*AC73 -> 227.136 | AF73: =AE73 -> 227.136 | AG73: =AE73-AF73 -> 0 | AH73: =H73+P73+X73+AF73 -> 961.536 | AI73: =I73+Q73+Y73+AG73 -> 0 | AJ73: =+AH73+AI73 -> 961.536
A74: G.2 Activities Costs
A75: G.2.1 Translation Costs | B75: 1 | C75: Year | D75: 1 | E75: 1 | F75: 15000 | G75: =B75*F75*D75*E75 -> 15000 | H75: =G75 -> 15000 | I75: =G75-H75 -> 0 | J75: 1 | K75: Year | L75: 1 | M75: 1 | N75: =F75*$B$3 -> 15600 | O75: =J75*N75*L75*M75 -> 15600 | P75: =O75 -> 15600 | Q75: =O75-P75 -> 0 | AH75: =H75+P75+X75+AF75 -> 30600 | AI75: =I75+Q75+Y75+AG75 -> 0 | AJ75: =+AH75+AI75 -> 30600
A76: G.2.2 Social Media Ads/Boosts | B76: 1 | C76: Ad | D76: 24 | E76: 1 | F76: 250 | G76: =B76*F76*D76*E76 -> 6000 | H76: =G76 -> 6000 | I76: =G76-H76 -> 0 | J76: 1 | K76: Ad | L76: 42 | M76: 1 | N76: 255.7 | O76: =J76*N76*L76*M76 -> 10739.4 | P76: =O76 -> 10739.4 | Q76: =O76-P76 -> 0 | R76: 1 | S76: Ad | T76: 35 | U76: 1 | V76: 260 | W76: =R76*V76*T76*U76 -> 9100 | X76: =W76 -> 9100 | Y76: =W76-X76 -> 0 | Z76: 1 | AA76: Ad | AB76: 25 | AC76: 1 | AD76: =V76*$B$3 -> 270.4 | AE76: =Z76*AD76*AB76*$E76*AC76 -> 6760 | AF76: =AE76 -> 6760 | AG76: =AE76-AF76 -> 0 | AH76: =H76+P76+X76+AF76 -> 32599.4 | AI76: =I76+Q76+Y76+AG76 -> 0 | AJ76: =+AH76+AI76 -> 32599.4
A77: G.2.3 Website Development Fees | B77: 1 | C77: Lumpsum | D77: 1 | E77: 1 | F77: 7000 | G77: =B77*F77*D77*E77 -> 7000 | H77: =G77 -> 7000 | I77: =G77-H77 -> 0 | J77: 1 | K77: Lumpsum | L77: 0 | M77: 0 | N77: 7000 | O77: =J77*N77*L77*M77 -> 0 | P77: =O77 -> 0 | Q77: =O77-P77 -> 0 | R77: 1 | S77: Lumpsum | T77: 1 | U77: 1 | V77: 7000 | W77: =R77*V77*T77*U77 -> 7000 | X77: =W77 -> 7000 | Y77: =W77-X77 -> 0 | Z77: 0 | AA77: Lumpsum | AB77: 0 | AC77: 0 | AD77: 7000 | AE77: =Z77*AD77*AB77*$E77*AC77 -> 0 | AF77: =AE77 -> 0 | AG77: =AE77-AF77 -> 0 | AH77: =H77+P77+X77+AF77 -> 14000 | AI77: =I77+Q77+Y77+AG77 -> 0 | AJ77: =+AH77+AI77 -> 14000
A78: G.2.4 Website Hosting and Maintenance Fees | B78: 1 | C78: Year | D78: 1 | E78: 1 | F78: 800 | G78: =B78*F78*D78*E78 -> 800 | H78: =G78 -> 800 | I78: =G78-H78 -> 0 | J78: 1 | K78: Year | L78: 1 | M78: 1 | N78: =F78*$B$3 -> 832 | O78: =J78*N78*L78*M78 -> 832 | P78: =O78 -> 832 | Q78: =O78-P78 -> 0 | R78: 1 | S78: Year | T78: 1 | U78: 1 | V78: 1040 | W78: =R78*V78*T78*U78 -> 1040 | X78: =W78 -> 1040 | Y78: =W78-X78 -> 0 | Z78: 1 | AA78: Year | AB78: 1 | AC78: 1 | AD78: =V78*$B$3 -> 1081.6 | AE78: =Z78*AD78*AB78*$E78*AC78 -> 1081.6 | AF78: =AE78 -> 1081.6 | AG78: =AE78-AF78 -> 0 | AH78: =H78+P78+X78+AF78 -> 3753.6 | AI78: =I78+Q78+Y78+AG78 -> 0 | AJ78: =+AH78+AI78 -> 3753.6
A79: G.2.5 AI App Promotion, Training, and Events | B79: 0 | C79: Event | D79: 0 | E79: 1 | F79: 2000 | G79: =B79*F79*D79*E79 -> 0 | H79: =G79 -> 0 | I79: =G79-H79 -> 0 | J79: 1 | K79: Event | L79: 3 | M79: 1 | N79: 2000 | O79: =J79*N79*L79*M79 -> 6000 | P79: =O79 -> 6000 | Q79: =O79-P79 -> 0 | R79: 1 | S79: Event | T79: 2 | U79: 1 | V79: 2000 | W79: =R79*V79*T79*U79 -> 4000 | X79: =W79 -> 4000 | Y79: =W79-X79 -> 0 | Z79: 0 | AA79: Event | AB79: 0 | AC79: 1 | AD79: 2000 | AE79: =Z79*AD79*AB79*$E79*AC79 -> 0 | AF79: =AE79 -> 0 | AG79: =AE79-AF79 -> 0 | AH79: =H79+P79+X79+AF79 -> 10000 | AI79: =I79+Q79+Y79+AG79 -> 0 | AJ79: =+AH79+AI79 -> 10000
A80: G.2.6 Events in Partnership with IOM | B80: 0 | C80: Event | D80: 0 | E80: 1 | F80: 5000 | G80: =B80*F80*D80*E80 -> 0 | H80: =G80 -> 0 | I80: =G80-H80 -> 0 | J80: 1 | K80: Event | L80: 2 | M80: 1 | N80: 5000 | O80: =J80*N80*L80*M80 -> 10000 | P80: =O80 -> 10000 | Q80: =O80-P80 -> 0 | R80: 1 | S80: Event | T80: 3 | U80: 1 | V80: =N80*$B$3 -> 5200 | W80: =R80*V80*T80*U80 -> 15600 | X80: =W80 -> 15600 | Y80: =W80-X80 -> 0 | Z80: 1 | AA80: Event | AB80: 2 | AC80: 1 | AD80: =V80*$B$3 -> 5408 | AE80: =Z80*AD80*AB80*$E80*AC80 -> 10816 | AF80: =AE80 -> 10816 | AG80: =AE80-AF80 -> 0 | AH80: =H80+P80+X80+AF80 -> 36416 | AI80: =I80+Q80+Y80+AG80 -> 0 | AJ80: =+AH80+AI80 -> 36416
A81: G.2.7 Social Media Ads/Boosts (Regional Advertising Initiative) | B81: 0 | C81: Ad | D81: 0 | E81: 1 | F81: 250 | G81: =B81*F81*D81*E81 -> 0 | H81: =G81 -> 0 | I81: =G81-H81 -> 0 | J81: 1 | K81: Ad | L81: 784 | M81: 1 | N81: 250 | O81: 196000 | P81: =O81 -> 196000 | Q81: =O81-P81 -> 0 | R81: 0 | S81: Ad | T81: 0 | U81: 0 | V81: 250 | W81: =R81*V81*T81*U81 -> 0 | X81: =W81 -> 0 | Y81: =W81-X81 -> 0 | Z81: 1 | AA81: Ad | AB81: 0 | AC81: 1 | AD81: =V81*$B$3 -> 260 | AE81: =Z81*AD81*AB81*$E81*AC81 -> 0 | AF81: =AE81 -> 0 | AG81: =AE81-AF81 -> 0 | AH81: =H81+P81+X81+AF81 -> 196000 | AI81: =I81+Q81+Y81+AG81 -> 0 | AJ81: =+AH81+AI81 -> 196000
A82: G.3 M&E
A83: G.3.1 M&E Materials | B83: 1 | C83: Year | D83: 1 | E83: 1 | F83: 300 | G83: =B83*F83*D83*E83 -> 300 | H83: =G83 -> 300 | I83: =G83-H83 -> 0 | J83: 1 | K83: Year | L83: 1 | M83: 1 | N83: =300*1.04 -> 312 | O83: =J83*N83*L83*M83 -> 312 | P83: =O83 -> 312 | Q83: =O83-P83 -> 0 | AH83: =H83+P83+X83+AF83 -> 612 | AI83: =I83+Q83+Y83+AG83 -> 0 | AJ83: =+AH83+AI83 -> 612
A84: G.3.2 M&E Training and Coordination Meetings | B84: 1 | C84: Meetings | D84: 1 | E84: 1 | F84: 121 | G84: =B84*F84*D84*E84 -> 121 | H84: =G84 -> 121 | I84: =G84-H84 -> 0 | J84: 1 | K84: Meetings | L84: 1 | M84: 1 | N84: =121*1.04 -> 125.84 | O84: =J84*N84*L84*M84 -> 125.84 | P84: =O84 -> 125.84 | Q84: =O84-P84 -> 0 | AH84: =H84+P84+X84+AF84 -> 246.84 | AI84: =I84+Q84+Y84+AG84 -> 0 | AJ84: =+AH84+AI84 -> 246.84
A85: G.3.3 External Project Evaluation support costs | B85: 1 | C85: Lumpsum | D85: 0 | E85: 1 | F85: 1000 | G85: =B85*F85*D85*E85 -> 0 | H85: =G85 -> 0 | I85: =G85-H85 -> 0 | J85: 1 | K85: Lumpsum | L85: 1 | M85: 1 | N85: =1000*1.04 -> 1040 | O85: =J85*N85*L85*M85 -> 1040 | P85: =O85 -> 1040 | Q85: =O85-P85 -> 0 | AH85: =H85+P85+X85+AF85 -> 1040 | AI85: =I85+Q85+Y85+AG85 -> 0 | AJ85: =+AH85+AI85 -> 1040
A86: Subtotal Other Direct Costs | G86: =SUM(G63:G85) -> 39031 | H86: =SUM(H63:H85) -> 39031 | I86: =SUM(I63:I85) -> 0 | O86: =SUM(O63:O85) -> 251211.64 | P86: =SUM(P63:P85) -> 251211.64 | Q86: =SUM(Q63:Q85) -> 0 | W86: =SUM(W63:W85) -> 48315.04 | X86: =SUM(X63:X85) -> 48315.04 | Y86: =SUM(Y63:Y85) -> 0 | AE86: =SUM(AE63:AE85) -> 23727.725 | AF86: =SUM(AF63:AF85) -> 23727.725 | AG86: =SUM(AG63:AG85) -> 0 | AH86: =SUM(AH63:AH85) -> 362285.4 | AI86: =SUM(AI63:AI85) -> 0 | AJ86: =SUM(AJ63:AJ85) -> 362285.4
A87: H. Total Direct Costs | G87: =G20+G26+G38+G44+G61+G86 -> 273864.69 | H87: =H20+H26+H38+H44+H61+H86 -> 273864.69 | I87: =I20+I26+I38+I44+I61+I86 -> 0 | O87: =O20+O26+O38+O44+O61+O86 -> 718909.09 | P87: =P20+P26+P38+P44+P61+P86 -> 718909.09 | Q87: =Q20+Q26+Q38+Q44+Q61+Q86 -> 0 | W87: =W20+W26+W38+W44+W61+W86 -> 755115.34 | X87: =X20+X26+X38+X44+X61+X86 -> 755115.34 | Y87: =Y20+Y26+Y38+Y44+Y61+Y86 -> 0 | AE87: =AE20+AE26+AE38+AE44+AE61+AE86 -> 159285.1 | AF87: =AF20+AF26+AF38+AF44+AF61+AF86 -> 159285.1 | AG87: =AG20+AG26+AG38+AG44+AG61+AG86 -> 0 | AH87: =H87+P87+X87+AF87 -> 1907174.2 | AI87: =I87+Q87+Y87+AG87 -> 0 | AJ87: =+AH87+AI87 -> 1907174.2
A88: I. Indirect Cost
A89: I.1 Indirect Cost (28.28% NICRA rate) | C89: 0.2828 | G89: =G87*C89 -> 77448.935 | H89: =G89 -> 77448.935 | I89: =G89-H89 -> 0 | K89: 0.2828 | O89: =O87*$K$89 -> 203307.49 | P89: =O89 -> 203307.49 | Q89: =O89-P89 -> 0 | S89: 0.2828 | W89: =W87*$K$89 -> 213546.62 | X89: =W89 -> 213546.62 | Y89: =W89-X89 -> 0 | AA89: 0.2828 | AE89: =AE87*$K$89 -> 45045.826 | AF89: =AE89 -> 45045.826 | AG89: =AE89-AF89 -> 0 | AH89: =H89+P89+X89+AF89 -> 539348.87 | AI89: =I89+Q89+Y89+AG89 -> 0 | AJ89: =+AH89+AI89 -> 539348.87
A90: I.2 Total Indirect Cost | G90: =G89 -> 77448.935 | H90: =H89 -> 77448.935 | I90: =I89 -> 0 | O90: =O89 -> 203307.49 | P90: =P89 -> 203307.49 | Q90: =Q89 -> 0 | W90: =W89 -> 213546.62 | X90: =X89 -> 213546.62 | Y90: =Y89 -> 0 | AE90: =AE89 -> 45045.826 | AF90: =AF89 -> 45045.826 | AG90: =AG89 -> 0 | AH90: =H90+P90+X90+AF90 -> 539348.87 | AI90: =I90+Q90+Y90+AG90 -> 0 | AJ90: =+AH90+AI90 -> 539348.87
A91: J. GRAND TOTAL | G91: =G87+G90 -> 351313.63 | H91: =H87+H90 -> 351313.63 | I91: =I87+I90 -> 0 | O91: =O87+O90 -> 922216.59 | P91: =P87+P90 -> 922216.59 | Q91: =Q87+Q90 -> 0 | W91: =W87+W90 -> 968661.96 | X91: =X87+X90 -> 968661.96 | Y91: =Y87+Y90 -> 0 | AE91: =AE87+AE90 -> 204330.92 | AF91: =AF87+AF90 -> 204330.92 | AG91: =AG87+AG90 -> 0 | AH91: =H91+P91+X91+AF91 -> 2446523.1 | AI91: =I91+Q91+Y91+AG91 -> 0 | AJ91: =+AH91+AI91 -> 2446523.1
AI94: Extra | AJ94: 1805524.7
AI95: Original | AJ95: 640999.73
AI96: Total | AJ96: =SUM(AJ94:AJ95) -> 2446524.5 | AL96: =+AJ96-AJ91 -> 1.3587418
