Workbook

Sheet APP
A1: PLAN ANUAL DE ADQUISICIONES
A2: Preparado por: | B2: Dirección de Contratos y Cumplimiento C4D
A3: Cooperante: | B3: Departamento de Agricultura de Estados Unidos-USDA. | O3: Pendiente revisión HO
A4: Acuerdo No.: | B4: Nº OGSM: FCC-514-2020/002-00. | O4: Para revisar.
A5: Periodo: | B5: Enero 1, 2024 a Diciembre 31, 2024 | O5: En convocatoria
A6: *TRM: | B6: 4000
A8: No. | B8: Sage Activity | C8: Budget Item | D8: Actividad | E8: Área encargada | F8: Descripción Ítem | G8: Cantidad | H8: Costo estimado COP | I8: Costo estimado USD* | J8: Tipo de proceso | K8: Tipo de Adquisición | L8: Método de Adquisición | M8: Aprobación previa de USDA o waiver requerido? | N8: Duración estimada del contrato | O8: Fecha límite para el envío de los TDR | P8: Fecha límite para suscribir Purchase Requisition Form (PRF) | Q8: Responsable de la PRF | R8: Fecha estimada firma de contrato | S8: Día y mes en el que deben ser recibidos los bienes/servicios | T8: Expected delivery location/procurement region
A9: 1 | B9: DIGITALPAR | C9: Digital Training Parthnership | D9: 3 | E9: Dirección alianzas e inversiones | F9: Herramienta digital - Diseñar, construir, pilotear, e implementar una(s) herramienta(s) digital(es) para la gestión de las fincas de los productores, la gestión de las asociaciones y un market place para el uso de vendedores, compradores y transportadores de cacao y productos complementarios. | H9: =+I9*$B$6 -> 424000000 | I9: 106000 | J9: Contratación consultoría persona jurídica | K9: Technical - Workplan | L9: Competitive proposal | M9: Prior approval needed | N9: 12 meses | O9: 45627 | P9: 45292 | Q9: Área de contratos y donaciones | R9: 45352
A10: 2 | B10: NEWPARTNER | C10: Other new parthership | D10: 3 | E10: Dirección técnica | F10: Tecnología inteligencia artificial - Diseñar una tecnología de inteligencia artificial para determinar cuál es el perfil de sabor de grano de cacao a partir de dispositivo móvil. | H10: =+I10*$B$6 -> 467824000 | I10: 116956 | J10: Contratación consultoría persona jurídica | K10: Technical - Workplan | L10: Competitive proposal | M10: Prior approval needed | N10: 12 meses | O10: 45474 | P10: =+O10 -> 45474 | Q10: Área de contratos y donaciones | R10: 45536
A11: 3 | B11: NEWPARTNER | C11: FCIA Parthership | D11: 3 | E11: Dirección alianzas e inversiones | F11: Find chocolate Partnership - Ruedas de negocios. | H11: =+I11*$B$6 -> 0 | I11: 0 | J11: Contratación consultoría persona jurídica | K11: Technical - Workplan | M11: Prior approval needed | N11: TBD | O11: TBD | P11: TBD | Q11: Área de contratos y donaciones | R11: TBD
A12: 4 | B12: CACAOSAFE | C12: Cacao Food Safety, Traceability, and Risk Managment | D12: 3 | E12: Dirección alianzas e inversiones | F12: Inocuidad alimentaria / Cadmio (componente 4) - Analizar los niveles de cadmio a nivel de suelos y grano seco, de plomo a nivel de grano seco, y de análisis de suelo de elementos menores y elementos mayores para una muestra representativa a nivel de asociación para un grupo de asociaciones seleccionadas del proyecto C4D. | H12: =+I12*$B$6 -> 368000000 | I12: 92000 | J12: Contratación consultoría persona jurídica | K12: Technical - Workplan | L12: Competitive proposal | M12: Prior approval needed | N12: 6 meses | O12: 45627 | P12: 45292 | Q12: Área de contratos y donaciones | R12: 45352
A13: 5 | B13: CACAOSAFE | C13: Cacao Food Safety, Traceability, and Risk Managment | D13: 3 | E13: Dirección alianzas e inversiones | F13: Equipo E-Max - Adquisición del equipo de fluorescencia de rayos X monocromática (MXRF), E-max, de Z-spec o equivalente. | H13: =+I13*$B$6 -> 224000000 | I13: 56000 | J13: Adquisición de bienes | K13: Technical - Workplan | L13: Competitive proposal | M13: Prior approval needed | N13: TBD | O13: TBD | P13: =+O13 -> TBD | Q13: Área de contratos y donaciones | R13: TBD
A14: 6 | B14: CACAOSAFE | C14: Cacao Food Safety, Traceability, and Risk Managment | D14: 3 | E14: Dirección técnica | F14: Adquisición de insumos para carmenta. | H14: =+I14*$B$6 -> 144000000 | I14: 36000 | J14: Adquisición de bienes | K14: Technical - Workplan | L14: Competitive proposal | M14: Prior approval needed | N14: 2 meses | O14: 45474 | P14: =+O14 -> 45474 | Q14: Área de contratos y donaciones | R14: 45536 | S14: 45352
A15: 7 | B15: DIGITALPAR | C15: Fertilizer for Farmers Digital Training Partnership | D15: 3 | E15: Dirección técnica | F15: Implementar 28 Biofabricas de Biopreparados, para promover en 2.500 familias cacaocultoras las diferentes opciones tecnológicas en la elaboración de productos amigables con el medio ambiente, como un método alternativo sostenible. | H15: =+I15*$B$6 -> 680000000 | I15: 170000 | J15: Adquisición de bienes | K15: Technical - Workplan | L15: Competitive proposal | M15: Both prior approval & wavier needed | N15: 3 meses | O15: 45261 | P15: 45292 | Q15: Área de contratos y donaciones | R15: 45352 | S15: 45352
A16: 8 | B16: DIGITALPAR | C16: Fertilizer for Farmers Digital Training Partnership | D16: 3 | E16: Dirección técnica | F16: Realización de capacitaciones Biofábricas. | H16: =+I16*$B$6 -> 240000000 | I16: =230000-170000 -> 60000 | J16: Adquisición de servicios | K16: Technical - Workplan | L16: Competitive proposal | M16: Prior approval needed | N16: 3 meses | O16: 45292 | P16: =+O16 -> 45292 | Q16: Área de contratos y donaciones | R16: 45383 | S16: 45352
A17: 9 | B17: CARBONPAR | C17: New Carbon Partnership | D17: 3 | E17: Dirección técnica | F17: Consultor individual para implementación del PDD. | H17: =+I17*$B$6 -> 80000000 | I17: 20000 | J17: Contratación consultoría persona natural | K17: Technical - Workplan | L17: Competitive proposal | M17: Prior approval needed | N17: 6 meses | O17: 45323 | P17: =+O17 -> 45323 | Q17: Área de contratos y donaciones | R17: 45383
A18: 10 | B18: COMCROPS | C18: Complementary Crops Food Security, traceability, and Risk Managment | D18: 3 | E18: Dirección técnica | F18: Proceso para seleccionar a las organizaciones beneficiarias de los centros de reproducción de gallinas. Proceso interno | H18: =+I18*$B$6 -> 0 | I18: 0 | J18: N/A | K18: Technical - Workplan | M18: Prior approval needed | N18: N/A | O18: N/A | P18: =+O18 -> N/A | Q18: Área de contratos y donaciones | R18: N/A
A19: 11 | B19: COMCROPS | C19: Complementary Crops Food Security, traceability, and Risk Managment | D19: 3 | E19: Dirección técnica | F19: Proceso para seleccionar a las organizaciones beneficiarias de los pilotos de ají. Proceso interno. | H19: =+I19*$B$6 -> 0 | I19: 0 | J19: N/A | K19: Technical - Workplan | M19: Prior approval needed | N19: N/A | O19: N/A | P19: =+O19 -> N/A | Q19: Área de contratos y donaciones | R19: N/A
A20: 12 | B20: COMCROPS | C20: Complementary Crops Food Security, traceability, and Risk Managment | D20: 3 | E20: Dirección técnica | F20: Implementación de centros de reproducción de gallinas para seguridad alimentaria de las familias productoras. | H20: =+I20*$B$6 -> 219600000 | I20: 54900 | J20: Contratación consultoría perdona jurídica | K20: Technical - Workplan | L20: Competitive proposal | M20: Prior approval needed | N20: 4 meses | O20: 45352 | P20: =+O20 -> 45352 | Q20: Área de contratos y donaciones | R20: 45444
A21: 13 | B21: COMCROPS | C21: Complementary Crops Food Security, traceability, and Risk Managment | D21: 3 | E21: Dirección técnica | F21: Implementación piloto ají. | H21: =+I21*$B$6 -> 80000000 | I21: 20000 | J21: Adquisición de bienes y servicios | K21: Technical - Workplan | L21: Competitive proposal | M21: Prior approval needed | N21: 4 meses | O21: 45474 | P21: =+O21 -> 45474 | Q21: Área de contratos y donaciones | R21: 45536
A22: 14 | C22: Suplies for extension Agents | D22: 3 | E22: Dirección técnica | F22: Adquisición de prendas de visibilidad. | H22: =+I22*$B$6 -> 99000000 | I22: 24750 | J22: Adquisición de bienes | K22: Operational | L22: Competitive proposal | M22: Prior approval needed | N22: BPA | O22: 45292 | P22: =+O22 -> 45292 | Q22: Área de contratos y donaciones | R22: 45352
A23: 15 | C23: Cacaograma, Platanograma y yucagrama and Related Supplies (Include prinitng) | D23: 3 | E23: Dirección técnica | F23: Adquisición de cacaogramas y planes de manejo de finca. | H23: =+I23*$B$6 -> 22000000 | I23: 5500 | J23: Adquisición de bienes | K23: Operational | L23: Small purchase | M23: Prior approval needed | N23: 2 meses | O23: 45292 | P23: =+O23 -> 45292 | Q23: Área de contratos y donaciones | R23: 45352
A24: 16 | C24: Nutresa Support for private | D24: 3 | E24: Dirección técnica | F24: Agrreement Nutresa + agreement Luker. Compra de Material vegetal convenios Luker y Nutresa. 4 procesos | H24: =+I24*$B$6 -> 330000000 | I24: 82500 | J24: Pendiente definir | K24: Technical - Workplan | L24: Competitive proposal | M24: Prior approval needed | N24: TBD | O24: TBD | P24: =+O24 -> TBD | Q24: Área de contratos y donaciones | R24: durante el año, validar con Felipe
A25: 17 | C25: Small group - training for producers on Cacao and Complementary crops | D25: 3 | E25: Dirección técnica | F25: Capacitación (como Manuel Mejía) Se propone en Yariguies en tandas. | H25: =+I25*$B$6 -> 48000000 | I25: 12000 | J25: Adquisición de servicios | K25: Technical - Workplan | L25: Competitive proposal | M25: Prior approval needed | N25: TBD | O25: TBD | P25: =+O25 -> TBD | Q25: Área de contratos y donaciones | R25: TDB
A26: 18 | B26: SUBAGROSAV | C26: Subrecipient Agrosavia | D26: 4 | E26: Dirección alianzas e inversiones | F26: Biorremediador (componente 3) - Implementar una prueba piloto para determinar los valores de inmovilización de cadmio en dos viveros de cacao y/o dos plantaciones, mediante la aplicación del biopreparado de bacterias tolerantes a cadmio o un producto similar. | H26: =+I26*$B$6 -> 209592000 | I26: 52398 | J26: Contratación consultoría persona jurídica | K26: Technical - Workplan | L26: Competitive proposal | M26: Prior approval needed | N26: 12 meses | O26: 45261 | P26: =+O26 -> 45261 | Q26: Área de contratos y donaciones | R26: 45352
A27: 19 | B27: ACCELPART | C27: Incubator/Accelerator partherships | D27: 5 | E27: Dirección fortalecimiento cadena de valor | F27: Consultoría para aceleración de emprendimientos - Desarrollar un proceso para aceleración de ideas de negocio o emprendimientos. | H27: =+I27*$B$6 -> 160000000 | I27: 40000 | J27: Contratación consultoría persona jurídica | K27: Technical - Workplan | L27: Competitive proposal | M27: Prior approval needed | N27: 4-6 meses | O27: 45280 | P27: =+O27 -> 45280 | Q27: Área de contratos y donaciones | R27: 45352
A28: 20 | B28: YOUTHORGS | C28: Organizations/networks/youth Incubators | D28: 6 | E28: Dirección fortalecimiento cadena de valor | F28: Desarrollar un proceso de innovación abierta que promueva una amplia participación de jóvenes en la ideación y propuesta de soluciones a los retos de las cadenas de valor de cacao y sus cultivos complementarios (plátano, ají, yuca, mango y limón Tahití) y que, a través de un proceso competitivo, permita seleccionar las ideas de negocio o emprendimientos prometedores que puedan ser aceleradas y/o escaladas. | H28: =+I28*$B$6 -> 232000000 | I28: 58000 | J28: Contratación consultoría persona jurídica | K28: Technical - Workplan | L28: Competitive proposal | M28: Prior approval needed | N28: 5 meses | O28: 45261 | P28: =+O28 -> 45261 | Q28: Área de contratos y donaciones | R28: 45352
A29: 21 | B29: STUDYTRIP | C29: Colombia Student Stipends for Local 6 Month Research trip | D29: 6 | E29: Dirección fortalecimiento cadena de valor | F29: Formación de jóvenes en cultivos complementarios IES - Servicio integral de alojamiento, hospedaje y capacitación para la formación de jóvenes en cultivos complementarios. | H29: =+I29*$B$6 -> 149848000 | I29: 37462 | J29: Adquisición de servicios | K29: Technical - Workplan | L29: Competitive proposal | M29: Prior approval needed | N29: 7 meses | O29: 45352 | P29: =+O29 -> 45352 | Q29: Área de contratos y donaciones | R29: 45474
A30: 22 | B30: COMPRORFA6 | C30: Communication & Promotional Fees for Grant RFAs | D30: 6 | E30: Dirección fortalecimiento cadena de valor | F30: Por definir: evento de presentación de ganadores. | H30: =+I30*$B$6 -> 12000000 | I30: 3000 | J30: Adquisición de servicios | K30: Operational | L30: Small purchase | M30: Prior approval needed | N30: 1 mes | O30: 45505 | P30: =+O30 -> 45505 | Q30: Área de contratos y donaciones | R30: 45536
A31: 23 | B31: RCPEVENTS | C31: RCP Events/Conference | D31: 7 | E31: Dirección fortalecimiento cadena de valor | F31: Logística para evento - Convenio con FEDECACAO | H31: =+I31*$B$6 -> 208000000 | I31: 52000 | J31: Adquisición de servicios | K31: Operational | L31: Competitive proposal | M31: Prior approval needed | N31: 1 mes | O31: 45323 | P31: =+O31 -> 45323 | Q31: Área de contratos y donaciones | R31: 45413
A32: Total: | H32: =SUM(H9:H31) -> 4397864000 | I32: =SUM(I9:I31) -> 1099466 | S32: =SUM(S9:S31) -> 136056
A35: Reviewed and Approved by: | E35: Date:
A38: Signature:

Sheet Grants
A2: No. | B2: Sage Activity | C2: Budget Item | D2: Actividad | E2: Área encargada | F2: Descripción Ítem | G2: Cantidad | H2: Costo estimado COP | I2: Costo estimado USD* | J2: Tipo de proceso | K2: Tipo de Adquisición | L2: Método de Adquisición | M2: Aprobación previa de USDA o waiver requerido? | N2: Fecha límite para el envío de los TDR | O2: Fecha límite para suscribir Purchase Requisition Form (PRF) | P2: Responsable de la PRF | Q2: Fecha estimada firma de grants | R2: Instrumento propuesto
A3: 1 | C3: Grant found - Activity 3 | D3: 3 | E3: Dirección técnica | F3: Grants actividad 3 | H3: =+I3*APP!$B$6 -> 892000000 | I3: 223000 | J3: Grants | K3: Technical - Workplan | L3: Competitive proposal | M3: Prior approval needed | N3: 45413 | O3: 45413 | P3: Área de contratos y donaciones | Q3: 45536 | R3: APS
A4: 2 | C4: Grant found - Activity 4 | D4: 4 | E4: Dirección técnica | F4: Grants actividad 4 | H4: =+I4*APP!$B$6 -> 280000000 | I4: =70000 -> 70000 | J4: Grants | K4: Technical - Workplan | L4: Competitive proposal | M4: Prior approval needed | N4: 45413 | O4: 45413 | P4: Área de contratos y donaciones | Q4: 45536
A5: 3 | C5: Grant found - Activity 5 | D5: 5 | E5: Dirección fortalecimiento cadena de valor | F5: Grants actividad 5 - Financiación de ideas de negocio de acuerdo con el proceso de aceleración | H5: =+I5*APP!$B$6 -> 229400000 | I5: 57350 | J5: Grants | K5: Technical - Workplan | L5: Competitive proposal | M5: Prior approval needed | N5: 45413 | O5: 45413 | P5: Área de contratos y donaciones | Q5: 45536 | R5: RFA
A6: 4 | B6: AGRIBGRANT | C6: Youth Agribusiness Impact Investing Grants | D6: 6 | E6: Dirección fortalecimiento cadena de valor | F6: Grants actividad 6 | H6: =+I6*APP!$B$6 -> 440000000 | I6: 110000 | J6: Grants | K6: Technical - Workplan | L6: Competitive proposal | M6: Prior approval needed | N6: 45413 | O6: 45413 | P6: Área de contratos y donaciones | Q6: 45536 | R6: RFA
A7: 5 | B7: VCHAINGRANT | C7: Niche Cacao & Underutilize Value Chain Market Research Grant | D7: 6 | E7: Dirección fortalecimiento cadena de valor | F7: Grants actividad 6 | H7: =+I7*APP!$B$6 -> 760000000 | I7: 190000 | J7: Grants | K7: Technical - Workplan | L7: Competitive proposal | M7: Prior approval needed | N7: 45413 | O7: 45413 | P7: Área de contratos y donaciones | Q7: 45536 | R7: RFA
A8: 6 | C8: OTHER GRANTS ACT6 | D8: 6 | E8: Dirección fortalecimiento cadena de valor | F8: Grants actividad 6 | H8: =+I8*APP!$B$6 -> 1146000000 | I8: 286500 | J8: Grants | K8: Technical - Workplan | L8: Competitive proposal | M8: Prior approval needed | N8: 45413 | O8: 45413 | P8: Área de contratos y donaciones | Q8: 45536 | R8: RFA
A9: TOTAL | H9: =SUM(H3:H8) -> 3747400000 | I9: =SUM(I3:I8) -> 936850

Sheet Listas
A1: Micro-purchase
A2: Small purchase
A3: Competitive proposal
A4: Non-competitive (sole source)
A7: Both prior approval & wavier needed
A8: Neither needed
A9: Prior approval needed
A10: Wavier needed
A12: Technical - Workplan
A13: Operational
