Workbook
Name \A: #REF!
Name \A: #REF!
Name \P: #REF!
Name \P: #REF!
Name \S: #REF!
Name \S: #REF!
Name _______sho1: '[3]Detailed Budget-SAVE'!#REF!
Name _______sho1: '[3]Detailed Budget-SAVE'!#REF!
Name __2DAI_1: #N/A
Name __3FEE: #N/A
Name __AFP1: #N/A
Name __AFP2: #N/A
Name __AFP3: #N/A
Name __AFP4: #N/A
Name __AMP1: #N/A
Name __AMP2: #N/A
Name __AMP3: #N/A
Name __AMP4: #N/A
Name __DAI4: #N/A
Name __EES1: #N/A
Name __EES2: #N/A
Name __EES3: #N/A
Name __EES4: #N/A
Name __EXT1: #N/A
Name __EXT2: #N/A
Name __EXT3: #N/A
Name __EXT4: #N/A
Name __FCP1: #N/A
Name __FCP2: #N/A
Name __FCP3: #N/A
Name __FCP4: #N/A
Name __FRI1: #N/A
Name __FRI4: #N/A
Name __HRA1: #N/A
Name __HRA2: #N/A
Name __HRA3: #N/A
Name __HRA4: #N/A
Name __inf1: #REF!
Name __LT4: [4]Parameters!$B$40
Name __ODC1: #N/A
Name __ODC2: #N/A
Name __POL1: #N/A
Name __POL2: #N/A
Name __POL3: #N/A
Name __POL4: #N/A
Name __TOT1: #N/A
Name __TOT2: #N/A
Name __TRV1: #N/A
Name __TRV2: #N/A
Name _060: #REF!
Name _1_1: #REF!
Name _13th_and_14th_month: [5]Parameters!$D$62
Name _2_1034: #REF!
Name _2DAI_1: #N/A
Name _3_1440: #REF!
Name _3FEE: #N/A
Name _4_2: #REF!
Name _5_3: #REF!
Name _AFP1: #N/A
Name _AFP2: #N/A

Sheet USDA Budget Summary
A1: Attachment 9
A2: Proposed Budget Summary
A4: Program (FFPr or MGD): | B4: FFPr
A5: Country of Operation: | B5: Tunisia
A6: Implementing Organization: | B6: Partners of the Americas Inc.
A7: Fiscal Year: | B7: 2024
A8: Agreement Number: | B8: USDA-FAS-10.606-0700-24(480)
A10: Total Amount of Federal Funds Requested
A11: Funding Source (FAS for MGD) (CCC for FFPr) | B11: Funding Year | C11: Commodity Cost | D11: Freight Cost | E11: Administrative Costs (cash portion) | F11: Total Federal Funding Obligated
B12: 2024 | C12: 19350000 | D12: 4000000 | E12: 1500000 | F12: =E12+D12+C12 -> 24850000
A14: Project Operating Budget
A15: Expense Type | B15: Monetization Proceeds (FFPr Only) | C15: FAS or CCC Funds (CCC is Admin Only) | D15: Cost Share | E15: Total w/out Cost Share | F15: Total w/Cost Share
A16: Administration
A17: Salaries/Personnel | B17: ='Program Budget'!V37-C17 -> 520668.29 | C17: 577000 | D17: ='Program Budget'!W37 -> 0 | E17: =B17+C17 -> 1097668.3 | F17: =B17+C17+D17 -> 1097668.3
A18: Benefits | B18: ='Program Budget'!V43-C18 -> 112887.37 | C18: 244128 | D18: ='Program Budget'!W43 -> 0 | E18: =B18+C18 -> 357015.37 | F18: =B18+C18+D18 -> 357015.37
A19: Travel | B19: ='Program Budget'!V60-C19 -> 297871 | C19: 20789.12 | D19: ='Program Budget'!W60 -> 0 | E19: =B19+C19 -> 318660.12 | F19: =B19+C19+D19 -> 318660.12
A20: Professional Services/Contractual | B20: ='Program Budget'!V86-C20 -> 1215333.8 | C20: 293800 | D20: ='Program Budget'!W86 -> 0 | E20: =B20+C20 -> 1509133.8 | F20: =B20+C20+D20 -> 1509133.8
A21: Equipment | B21: ='Program Budget'!V91-C21 -> 180000 | C21: 0 | D21: ='Program Budget'!W91 -> 0 | E21: =B21+C21 -> 180000 | F21: =B21+C21+D21 -> 180000
A22: Office | B22: ='Program Budget'!V110-C22 -> 438775.84 | C22: 12000 | D22: ='Program Budget'!W110 -> 0 | E22: =B22+C22 -> 450775.84 | F22: =B22+C22+D22 -> 450775.84
A23: Supplies | B23: ='Program Budget'!V125-C23 -> 64091.97 | C23: 18600 | D23: ='Program Budget'!W125 -> 0 | E23: =B23+C23 -> 82691.97 | F23: =B23+C23+D23 -> 82691.97
A24: Other | B24: ='Program Budget'!V135-C24 -> 57728.88 | C24: 3000 | D24: 0 | E24: =B24+C24 -> 60728.88 | F24: =B24+C24+D24 -> 60728.88
A25: Total Administration | B25: =SUM(B17:B24) -> 2887357.2 | C25: =SUM(C17:C24) -> 1169317.1 | D25: =SUM(D17:D24) -> 0 | E25: =SUM(E17:E24) -> 4056674.3 | F25: =SUM(F17:F24) -> 4056674.3
A27: Activities
A28: Activity 1: Increase Use of Climate Smart Agriculture and Water Management | B28: ='Program Budget'!V211 -> 3860925.1 | C28: 0 | D28: ='Program Budget'!W211 -> 96476 | E28: =B28+C28 -> 3860925.1 | F28: =B28+C28+D28 -> 3957401.1
A29: Activity 2: Increase Productivity of the Oasis Agricultural System | B29: ='Program Budget'!V282 -> 2395689.3 | C29: 0 | D29: ='Program Budget'!W282 -> 165000 | E29: =B29+C29 -> 2395689.3 | F29: =B29+C29+D29 -> 2560689.3
A30: Activity 3: Increase Use of Sustainable Oasis Agricultural System Business Models | B30: ='Program Budget'!V379 -> 2938971.9 | C30: 0 | D30: =ROUND('Program Budget'!W379,0) -> 43750 | E30: =B30+C30 -> 2938971.9 | F30: =B30+C30+D30 -> 2982721.9
A31: Total Activities | B31: =SUM(B28:B30) -> 9195586.4 | C31: =SUM(C28:C30) -> 0 | D31: =SUM(D28:D30) -> 305226 | E31: =SUM(E28:E30) -> 9195586.4 | F31: =SUM(F28:F30) -> 9500812.4
A33: Commodity and Food Purchases (N/A to FFPr)
A34: Commodity Procurement | B34: 0 | C34: 0 | D34: 0 | E34: =B34+C34 -> 0 | F34: =B34+C34+D34 -> 0
A35: Food Vouchers (N/A to MGD)
A36: Cash Transfers (N/A to MGD)
A37: Total Commodity Procurement | B37: =SUM(B34:B36) -> 0 | C37: =SUM(C34:C36) -> 0 | D37: =SUM(D34:D36) -> 0 | E37: =SUM(E34:E36) -> 0 | F37: =SUM(F34:F36) -> 0
A39: ITSH (N/A to FFPr)
A40: Salaries | B40: 0 | C40: 0 | D40: 0 | E40: =B40+C40 -> 0 | F40: =B40+C40+D40 -> 0
A41: Benefits | B41: 0 | C41: 0 | D41: 0 | E41: =B41+C41 -> 0 | F41: =B41+C41+D41 -> 0
A42: Transportation | B42: 0 | C42: 0 | D42: 0 | E42: =B42+C42 -> 0 | F42: =B42+C42+D42 -> 0
A43: Professional Services | B43: 0 | C43: 0 | D43: =0 -> 0 | E43: =B43+C43 -> 0 | F43: =B43+C43+D43 -> 0
A44: Warehouse | B44: 0 | C44: 0 | D44: 0 | E44: =B44+C44 -> 0 | F44: =B44+C44+D44 -> 0
A45: Supplies | B45: 0 | C45: 0 | D45: 0 | E45: =B45+C45 -> 0 | F45: =B45+C45+D45 -> 0
A46: Other | B46: 0 | C46: 0 | D46: 0 | E46: =B46+C46 -> 0 | F46: =B46+C46+D46 -> 0
A47: Total ITSH | B47: =SUM(B40:B46) -> 0 | C47: 0 | D47: =SUM(D40:D46) -> 0 | E47: =SUM(E40:E46) -> 0 | F47: =SUM(F40:F46) -> 0
A49: Total Direct Costs | B49: =B25+B31+B47+B37 -> 12082944 | C49: =C25+C31+C47+C37 -> 1169317.1 | D49: =D25+D31+D47+D37 -> 305226 | E49: =E37+E31+E25+E47 -> 13252261 | F49: =F37+F31+F25+F47 -> 13557487
A51: Indirect Costs
A52: ICR on Administration | B52: =((B25*0.2828)) -> 816544.61 | C52: =((C25*0.2828)) -> 330682.88 | E52: =B52+C52 -> 1147227.5
A53: ICR on Activities | B53: =((B31*0.2828)) -> 2600511.8 | C53: =C31*0.2828 -> 0 | E53: =B53+C53 -> 2600511.8
A54: ICR on Commodity and Food Purchases (N/A to FFPr) | B54: =B37*0.2828 -> 0 | C54: =C37*0.2828 -> 0 | E54: =B54+C54 -> 0
A55: ICR on ITSH (N/A to FFPr) | B55: =B47*0.2828 -> 0 | C55: =C47*0.2828 -> 0 | E55: =B55+C55 -> 0
A56: Total Indirect Costs | B56: =(SUM(B52:B55)) -> 3417056.4 | C56: =(SUM(C52:C55)) -> 330682.88 | E56: =(SUM(E52:E55)) -> 3747739.3
A58: Anticipated Program Income | F58: 342285.93
A60: Grand Total Costs | B60: =(B56+B49) -> 15500000 | C60: =(C56+C49) -> 1500000 | D60: =(D56+D49) -> 305226 | E60: =(E56+E49) -> 17000000 | F60: =(F49+E56) -> 17305226
A62: Total Amount of Federal Award (Total Federal Funds Requested Plus Cost Share): | F62: =F12+D60 -> 25155226

Sheet Detailed Budget
A2: Item | B2: Type of Unit | C2: Year 1 | G2: Year 2 | K2: Year 3 | O2: Year 4 | S2: Year 5 | W2: Total
C3: Cost | D3: Quantity | E3: Percent Allocated | F3: Total | G3: Cost | H3: Quantity | I3: Percent Allocated | J3: Total | K3: Cost | L3: Quantity | M3: Percent Allocated | N3: Total | O3: Cost | P3: Quantity | Q3: Percent Allocated | R3: Total | S3: Cost | T3: Quantity | U3: Percent Allocated | V3: Total
A4: Direct Costs
A5: Salaries
A6: USN/TCN Staff
A7: None | F7: =C7*D7*E7 -> 0 | J7: =G7*H7*I7 -> 0 | N7: =K7*L7*M7 -> 0 | R7: =O7*P7*Q7 -> 0 | V7: =S7*T7*U7 -> 0 | W7: =F7+J7+N7+R7+V7 -> 0
A8: Total: Expatriate Salaries & Wages | F8: =SUM(F7:F7) -> 0 | J8: =SUM(J7:J7) -> 0 | N8: =SUM(N7:N7) -> 0 | R8: =SUM(R7:R7) -> 0 | V8: =SUM(V7:V7) -> 0 | W8: =+F8+J8+N8+R8+V8 -> 0
A9: CNN Staff
A10: ='Program Budget'!D12 -> Key Personnel: Chief of Party - Ms. Rym Ayari | B10: ='Program Budget'!F12 -> Month | C10: ='Program Budget'!H12 -> 13000 | D10: ='Program Budget'!G12 -> 12 | E10: =Admin!E10+'Activity 1'!E10+'Activity 2'!E10+'Activity 3'!E10 -> 1 | F10: =C10*D10*E10 -> 156000 | G10: =C10*1.05 -> 13650 | H10: ='Program Budget'!K12 -> 12 | I10: =Admin!I10+'Activity 1'!I10+'Activity 2'!I10+'Activity 3'!I10 -> 1 | J10: =G10*H10*I10 -> 163800 | K10: =G10*1.05 -> 14332.5 | L10: ='Program Budget'!N12 -> 12 | M10: =Admin!M10+'Activity 1'!M10+'Activity 2'!M10+'Activity 3'!M10 -> 1 | N10: =K10*L10*M10 -> 171990 | O10: =K10*1.05 -> 15049.125 | P10: ='Program Budget'!Q12 -> 12 | Q10: =Admin!Q10+'Activity 1'!Q10+'Activity 2'!Q10+'Activity 3'!Q10 -> 1 | R10: =O10*P10*Q10 -> 180589.5 | S10: =O10*1.05 -> 15801.581 | T10: ='Program Budget'!T12 -> 12 | U10: =Admin!U10+'Activity 1'!U10+'Activity 2'!U10+'Activity 3'!U10 -> 1 | V10: =S10*T10*U10 -> 189618.98 | W10: =F10+J10+N10+R10+V10 -> 861998.47
A11: ='Program Budget'!D13 -> Key Personnel: Technical Director | B11: ='Program Budget'!F13 -> Month | C11: ='Program Budget'!H13 -> 3916.6667 | D11: ='Program Budget'!G13 -> 9 | E11: =Admin!E11+'Activity 1'!E11+'Activity 2'!E11+'Activity 3'!E11 -> 1 | F11: =C11*D11*E11 -> 35250 | G11: =C11*1.05 -> 4112.5 | H11: ='Program Budget'!K13 -> 12 | I11: =Admin!I11+'Activity 1'!I11+'Activity 2'!I11+'Activity 3'!I11 -> 1 | J11: =G11*H11*I11 -> 49350 | K11: =G11*1.05 -> 4318.125 | L11: ='Program Budget'!N13 -> 12 | M11: =Admin!M11+'Activity 1'!M11+'Activity 2'!M11+'Activity 3'!M11 -> 1 | N11: =K11*L11*M11 -> 51817.5 | O11: =K11*1.05 -> 4534.0312 | P11: ='Program Budget'!Q13 -> 12 | Q11: =Admin!Q11+'Activity 1'!Q11+'Activity 2'!Q11+'Activity 3'!Q11 -> 1 | R11: =O11*P11*Q11 -> 54408.375 | S11: =O11*1.05 -> 4760.7328 | T11: ='Program Budget'!T13 -> 9 | U11: =Admin!U11+'Activity 1'!U11+'Activity 2'!U11+'Activity 3'!U11 -> 1 | V11: =S11*T11*U11 -> 42846.595 | W11: =F11+J11+N11+R11+V11 -> 233672.47
A12: ='Program Budget'!D14 -> Technical Lead Component 1 | B12: ='Program Budget'!F14 -> Month | C12: ='Program Budget'!H14 -> 2500 | D12: ='Program Budget'!G14 -> 6 | E12: =Admin!E12+'Activity 1'!E12+'Activity 2'!E12+'Activity 3'!E12 -> 1 | F12: =C12*D12*E12 -> 15000 | G12: =C12*1.05 -> 2625 | H12: ='Program Budget'!K14 -> 12 | I12: =Admin!I12+'Activity 1'!I12+'Activity 2'!I12+'Activity 3'!I12 -> 1 | J12: =G12*H12*I12 -> 31500 | K12: =G12*1.05 -> 2756.25 | L12: ='Program Budget'!N14 -> 12 | M12: =Admin!M12+'Activity 1'!M12+'Activity 2'!M12+'Activity 3'!M12 -> 1 | N12: =K12*L12*M12 -> 33075 | O12: =K12*1.05 -> 2894.0625 | P12: ='Program Budget'!Q14 -> 12 | Q12: =Admin!Q12+'Activity 1'!Q12+'Activity 2'!Q12+'Activity 3'!Q12 -> 1 | R12: =O12*P12*Q12 -> 34728.75 | S12: =O12*1.05 -> 3038.7656 | T12: ='Program Budget'!T14 -> 9 | U12: =Admin!U12+'Activity 1'!U12+'Activity 2'!U12+'Activity 3'!U12 -> 1 | V12: =S12*T12*U12 -> 27348.891 | W12: =F12+J12+N12+R12+V12 -> 141652.64
A13: ='Program Budget'!D15 -> Technical Lead Component 2 | B13: ='Program Budget'!F15 -> Month | C13: ='Program Budget'!H15 -> 2500 | D13: ='Program Budget'!G15 -> 6 | E13: =Admin!E13+'Activity 1'!E13+'Activity 2'!E13+'Activity 3'!E13 -> 1 | F13: =C13*D13*E13 -> 15000 | G13: =C13*1.05 -> 2625 | H13: ='Program Budget'!K15 -> 12 | I13: =Admin!I13+'Activity 1'!I13+'Activity 2'!I13+'Activity 3'!I13 -> 1 | J13: =G13*H13*I13 -> 31500 | K13: =G13*1.05 -> 2756.25 | L13: ='Program Budget'!N15 -> 12 | M13: =Admin!M13+'Activity 1'!M13+'Activity 2'!M13+'Activity 3'!M13 -> 1 | N13: =K13*L13*M13 -> 33075 | O13: =K13*1.05 -> 2894.0625 | P13: ='Program Budget'!Q15 -> 12 | Q13: =Admin!Q13+'Activity 1'!Q13+'Activity 2'!Q13+'Activity 3'!Q13 -> 1 | R13: =O13*P13*Q13 -> 34728.75 | S13: =O13*1.05 -> 3038.7656 | T13: ='Program Budget'!T15 -> 9 | U13: =Admin!U13+'Activity 1'!U13+'Activity 2'!U13+'Activity 3'!U13 -> 1 | V13: =S13*T13*U13 -> 27348.891 | W13: =F13+J13+N13+R13+V13 -> 141652.64
A14: ='Program Budget'!D16 -> Technical Lead Component 3 | B14: ='Program Budget'!F16 -> Month | C14: ='Program Budget'!H16 -> 2500 | D14: ='Program Budget'!G16 -> 6 | E14: =Admin!E14+'Activity 1'!E14+'Activity 2'!E14+'Activity 3'!E14 -> 1 | F14: =C14*D14*E14 -> 15000 | G14: =C14*1.05 -> 2625 | H14: ='Program Budget'!K16 -> 12 | I14: =Admin!I14+'Activity 1'!I14+'Activity 2'!I14+'Activity 3'!I14 -> 1 | J14: =G14*H14*I14 -> 31500 | K14: =G14*1.05 -> 2756.25 | L14: ='Program Budget'!N16 -> 12 | M14: =Admin!M14+'Activity 1'!M14+'Activity 2'!M14+'Activity 3'!M14 -> 1 | N14: =K14*L14*M14 -> 33075 | O14: =K14*1.05 -> 2894.0625 | P14: ='Program Budget'!Q16 -> 12 | Q14: =Admin!Q14+'Activity 1'!Q14+'Activity 2'!Q14+'Activity 3'!Q14 -> 1 | R14: =O14*P14*Q14 -> 34728.75 | S14: =O14*1.05 -> 3038.7656 | T14: ='Program Budget'!T16 -> 9 | U14: =Admin!U14+'Activity 1'!U14+'Activity 2'!U14+'Activity 3'!U14 -> 1 | V14: =S14*T14*U14 -> 27348.891 | W14: =F14+J14+N14+R14+V14 -> 141652.64
A15: ='Program Budget'!D17 -> Technical Specialist Component 1 | B15: ='Program Budget'!F17 -> Month | C15: ='Program Budget'!H17 -> 1833.3333 | D15: ='Program Budget'!G17 -> 6 | E15: =Admin!E15+'Activity 1'!E15+'Activity 2'!E15+'Activity 3'!E15 -> 1 | F15: =C15*D15*E15 -> 11000 | G15: =C15*1.05 -> 1925 | H15: ='Program Budget'!K17 -> 12 | I15: =Admin!I15+'Activity 1'!I15+'Activity 2'!I15+'Activity 3'!I15 -> 1 | J15: =G15*H15*I15 -> 23100 | K15: =G15*1.05 -> 2021.25 | L15: ='Program Budget'!N17 -> 12 | M15: =Admin!M15+'Activity 1'!M15+'Activity 2'!M15+'Activity 3'!M15 -> 1 | N15: =K15*L15*M15 -> 24255 | O15: =K15*1.05 -> 2122.3125 | P15: ='Program Budget'!Q17 -> 12 | Q15: =Admin!Q15+'Activity 1'!Q15+'Activity 2'!Q15+'Activity 3'!Q15 -> 1 | R15: =O15*P15*Q15 -> 25467.75 | S15: =O15*1.05 -> 2228.4281 | T15: ='Program Budget'!T17 -> 6 | U15: =Admin!U15+'Activity 1'!U15+'Activity 2'!U15+'Activity 3'!U15 -> 1 | V15: =S15*T15*U15 -> 13370.569 | W15: =F15+J15+N15+R15+V15 -> 97193.319
A16: ='Program Budget'!D18 -> Technical Specialist Component 2 | B16: ='Program Budget'!F18 -> Month | C16: ='Program Budget'!H18 -> 1833.3333 | D16: ='Program Budget'!G18 -> 6 | E16: =Admin!E16+'Activity 1'!E16+'Activity 2'!E16+'Activity 3'!E16 -> 1 | F16: =C16*D16*E16 -> 11000 | G16: =C16*1.05 -> 1925 | H16: ='Program Budget'!K18 -> 12 | I16: =Admin!I16+'Activity 1'!I16+'Activity 2'!I16+'Activity 3'!I16 -> 1 | J16: =G16*H16*I16 -> 23100 | K16: =G16*1.05 -> 2021.25 | L16: ='Program Budget'!N18 -> 12 | M16: =Admin!M16+'Activity 1'!M16+'Activity 2'!M16+'Activity 3'!M16 -> 1 | N16: =K16*L16*M16 -> 24255 | O16: =K16*1.05 -> 2122.3125 | P16: ='Program Budget'!Q18 -> 12 | Q16: =Admin!Q16+'Activity 1'!Q16+'Activity 2'!Q16+'Activity 3'!Q16 -> 1 | R16: =O16*P16*Q16 -> 25467.75 | S16: =O16*1.05 -> 2228.4281 | T16: ='Program Budget'!T18 -> 6 | U16: =Admin!U16+'Activity 1'!U16+'Activity 2'!U16+'Activity 3'!U16 -> 1 | V16: =S16*T16*U16 -> 13370.569 | W16: =F16+J16+N16+R16+V16 -> 97193.319
A17: ='Program Budget'!D19 -> Technical Specialist Component 3 | B17: ='Program Budget'!F19 -> Month | C17: ='Program Budget'!H19 -> 1833.3333 | D17: ='Program Budget'!G19 -> 6 | E17: =Admin!E17+'Activity 1'!E17+'Activity 2'!E17+'Activity 3'!E17 -> 1 | F17: =C17*D17*E17 -> 11000 | G17: =C17*1.05 -> 1925 | H17: ='Program Budget'!K19 -> 12 | I17: =Admin!I17+'Activity 1'!I17+'Activity 2'!I17+'Activity 3'!I17 -> 1 | J17: =G17*H17*I17 -> 23100 | K17: =G17*1.05 -> 2021.25 | L17: ='Program Budget'!N19 -> 12 | M17: =Admin!M17+'Activity 1'!M17+'Activity 2'!M17+'Activity 3'!M17 -> 1 | N17: =K17*L17*M17 -> 24255 | O17: =K17*1.05 -> 2122.3125 | P17: ='Program Budget'!Q19 -> 12 | Q17: =Admin!Q17+'Activity 1'!Q17+'Activity 2'!Q17+'Activity 3'!Q17 -> 1 | R17: =O17*P17*Q17 -> 25467.75 | S17: =O17*1.05 -> 2228.4281 | T17: ='Program Budget'!T19 -> 6 | U17: =Admin!U17+'Activity 1'!U17+'Activity 2'!U17+'Activity 3'!U17 -> 1 | V17: =S17*T17*U17 -> 13370.569 | W17: =F17+J17+N17+R17+V17 -> 97193.319
A18: ='Program Budget'!D20 -> Capacity Building Specialist (2) | B18: ='Program Budget'!F20 -> Month | C18: ='Program Budget'!H20 -> 3333.3333 | D18: ='Program Budget'!G20 -> 4 | E18: =Admin!E18+'Activity 1'!E18+'Activity 2'!E18+'Activity 3'!E18 -> 1 | F18: =C18*D18*E18 -> 13333.333 | G18: =C18*1.05 -> 3500 | H18: ='Program Budget'!K20 -> 12 | I18: =Admin!I18+'Activity 1'!I18+'Activity 2'!I18+'Activity 3'!I18 -> 1 | J18: =G18*H18*I18 -> 42000 | K18: =G18*1.05 -> 3675 | L18: ='Program Budget'!N20 -> 12 | M18: =Admin!M18+'Activity 1'!M18+'Activity 2'!M18+'Activity 3'!M18 -> 1 | N18: =K18*L18*M18 -> 44100 | O18: =K18*1.05 -> 3858.75 | P18: ='Program Budget'!Q20 -> 12 | Q18: =Admin!Q18+'Activity 1'!Q18+'Activity 2'!Q18+'Activity 3'!Q18 -> 1 | R18: =O18*P18*Q18 -> 46305 | S18: =O18*1.05 -> 4051.6875 | T18: ='Program Budget'!T20 -> 5 | U18: =Admin!U18+'Activity 1'!U18+'Activity 2'!U18+'Activity 3'!U18 -> 1 | V18: =S18*T18*U18 -> 20258.438 | W18: =F18+J18+N18+R18+V18 -> 165996.77
A19: ='Program Budget'!D21 -> Sociocultural and Gender Specialist | B19: ='Program Budget'!F21 -> Month | C19: ='Program Budget'!H21 -> 1833.3333 | D19: ='Program Budget'!G21 -> 7 | E19: =Admin!E19+'Activity 1'!E19+'Activity 2'!E19+'Activity 3'!E19 -> 1 | F19: =C19*D19*E19 -> 12833.333 | G19: =C19*1.05 -> 1925 | H19: ='Program Budget'!K21 -> 12 | I19: =Admin!I19+'Activity 1'!I19+'Activity 2'!I19+'Activity 3'!I19 -> 1 | J19: =G19*H19*I19 -> 23100 | K19: =G19*1.05 -> 2021.25 | L19: ='Program Budget'!N21 -> 12 | M19: =Admin!M19+'Activity 1'!M19+'Activity 2'!M19+'Activity 3'!M19 -> 1 | N19: =K19*L19*M19 -> 24255 | O19: =K19*1.05 -> 2122.3125 | P19: ='Program Budget'!Q21 -> 12 | Q19: =Admin!Q19+'Activity 1'!Q19+'Activity 2'!Q19+'Activity 3'!Q19 -> 1 | R19: =O19*P19*Q19 -> 25467.75 | S19: =O19*1.05 -> 2228.4281 | T19: ='Program Budget'!T21 -> 9 | U19: =Admin!U19+'Activity 1'!U19+'Activity 2'!U19+'Activity 3'!U19 -> 1 | V19: =S19*T19*U19 -> 20055.853 | W19: =F19+J19+N19+R19+V19 -> 105711.94
A20: ='Program Budget'!D22 -> Sociocultural and Gender Officers (3) | B20: ='Program Budget'!F22 -> Month | C20: ='Program Budget'!H22 -> 3750 | D20: ='Program Budget'!G22 -> 7 | E20: =Admin!E20+'Activity 1'!E20+'Activity 2'!E20+'Activity 3'!E20 -> 1 | F20: =C20*D20*E20 -> 26250 | G20: =C20*1.05 -> 3937.5 | H20: ='Program Budget'!K22 -> 12 | I20: =Admin!I20+'Activity 1'!I20+'Activity 2'!I20+'Activity 3'!I20 -> 1 | J20: =G20*H20*I20 -> 47250 | K20: =G20*1.05 -> 4134.375 | L20: ='Program Budget'!N22 -> 12 | M20: =Admin!M20+'Activity 1'!M20+'Activity 2'!M20+'Activity 3'!M20 -> 1 | N20: =K20*L20*M20 -> 49612.5 | O20: =K20*1.05 -> 4341.0938 | P20: ='Program Budget'!Q22 -> 12 | Q20: =Admin!Q20+'Activity 1'!Q20+'Activity 2'!Q20+'Activity 3'!Q20 -> 1 | R20: =O20*P20*Q20 -> 52093.125 | S20: =O20*1.05 -> 4558.1484 | T20: ='Program Budget'!T22 -> 9 | U20: =Admin!U20+'Activity 1'!U20+'Activity 2'!U20+'Activity 3'!U20 -> 1 | V20: =S20*T20*U20 -> 41023.336 | W20: =F20+J20+N20+R20+V20 -> 216228.96
A21: ='Program Budget'!D23 -> Communications Specialists | B21: ='Program Budget'!F23 -> Month | C21: ='Program Budget'!H23 -> 1500 | D21: ='Program Budget'!G23 -> 7 | E21: =Admin!E21+'Activity 1'!E21+'Activity 2'!E21+'Activity 3'!E21 -> 1 | F21: =C21*D21*E21 -> 10500 | G21: =C21*1.05 -> 1575 | H21: ='Program Budget'!K23 -> 12 | I21: =Admin!I21+'Activity 1'!I21+'Activity 2'!I21+'Activity 3'!I21 -> 1 | J21: =G21*H21*I21 -> 18900 | K21: =G21*1.05 -> 1653.75 | L21: ='Program Budget'!N23 -> 12 | M21: =Admin!M21+'Activity 1'!M21+'Activity 2'!M21+'Activity 3'!M21 -> 1 | N21: =K21*L21*M21 -> 19845 | O21: =K21*1.05 -> 1736.4375 | P21: ='Program Budget'!Q23 -> 12 | Q21: =Admin!Q21+'Activity 1'!Q21+'Activity 2'!Q21+'Activity 3'!Q21 -> 1 | R21: =O21*P21*Q21 -> 20837.25 | S21: =O21*1.05 -> 1823.2594 | T21: ='Program Budget'!T23 -> 10 | U21: =Admin!U21+'Activity 1'!U21+'Activity 2'!U21+'Activity 3'!U21 -> 1 | V21: =S21*T21*U21 -> 18232.594 | W21: =F21+J21+N21+R21+V21 -> 88314.844
... A30: ='Program Budget'!D32 -> Driver (3 Individuals) | B30: ='Program Budget'!F32 -> Month | C30: ='Program Budget'!H32 -> 2250 | D30: ='Program Budget'!G32 -> 3 | E30: =Admin!E30+'Activity 1'!E30+'Activity 2'!E30+'Activity 3'!E30 -> 1 | F30: =C30*D30*E30 -> 6750 | G30: =C30*1.05 -> 2362.5 | H30: ='Program Budget'!K32 -> 12 | I30: =Admin!I30+'Activity 1'!I30+'Activity 2'!I30+'Activity 3'!I30 -> 1 | J30: =G30*H30*I30 -> 28350 | K30: =G30*1.05 -> 2480.625 | L30: ='Program Budget'!N32 -> 12 | M30: =Admin!M30+'Activity 1'!M30+'Activity 2'!M30+'Activity 3'!M30 -> 1 | N30: =K30*L30*M30 -> 29767.5 | O30: =K30*1.05 -> 2604.6562 | P30: ='Program Budget'!Q32 -> 12 | Q30: =Admin!Q30+'Activity 1'!Q30+'Activity 2'!Q30+'Activity 3'!Q30 -> 1 | R30: =O30*P30*Q30 -> 31255.875 | S30: =O30*1.05 -> 2734.8891 | T30: ='Program Budget'!T32 -> 9 | U30: =Admin!U30+'Activity 1'!U30+'Activity 2'!U30+'Activity 3'!U30 -> 1 | V30: =S30*T30*U30 -> 24614.002 | W30: =F30+J30+N30+R30+V30 -> 120737.38
A31: Total Local Salary Cost | F31: =SUM(F10:F30) -> 522583.33 | J31: =SUM(J10:J30) -> 775950 | N31: =SUM(N10:N30) -> 814747.5 | R31: =SUM(R10:R30) -> 855484.88 | V31: =SUM(V10:V30) -> 747435.05 | W31: =F31+J31+N31+R31+V31 -> 3716200.8
A32: HQ Staff
A33: ='Program Budget'!D34 -> Senior Program Director | B33: ='Program Budget'!F34 -> Month | C33: ='Program Budget'!H34 -> 11250 | D33: ='Program Budget'!G34 -> 12 | E33: ='Program Budget'!E34 -> 0.2 | F33: =C33*D33*E33 -> 27000 | G33: =C33*1.05 -> 11812.5 | H33: ='Program Budget'!K34 -> 12 | I33: ='Program Budget'!J34 -> 0.2 | J33: =G33*H33*I33 -> 28350 | K33: =G33*1.05 -> 12403.125 | L33: ='Program Budget'!N34 -> 12 | M33: ='Program Budget'!M34 -> 0.2 | N33: =K33*L33*M33 -> 29767.5 | O33: =K33*1.05 -> 13023.281 | P33: ='Program Budget'!Q34 -> 12 | Q33: ='Program Budget'!P34 -> 0.2 | R33: =O33*P33*Q33 -> 31255.875 | S33: =O33*1.05 -> 13674.445 | T33: ='Program Budget'!T34 -> 12 | U33: ='Program Budget'!S34 -> 0.2 | V33: =S33*T33*U33 -> 32818.669 | W33: =F33+J33+N33+R33+V33 -> 149192.04
A34: ='Program Budget'!D35 -> Associate Director | B34: ='Program Budget'!F35 -> Month | C34: ='Program Budget'!H35 -> 7500 | D34: ='Program Budget'!G35 -> 12 | E34: ='Program Budget'!E35 -> 1 | F34: =C34*D34*E34 -> 90000 | G34: =C34*1.05 -> 7875 | H34: ='Program Budget'!K35 -> 12 | I34: ='Program Budget'!J35 -> 1 | J34: =G34*H34*I34 -> 94500 | K34: =G34*1.05 -> 8268.75 | L34: ='Program Budget'!N35 -> 12 | M34: ='Program Budget'!M35 -> 1 | N34: =K34*L34*M34 -> 99225 | O34: =K34*1.05 -> 8682.1875 | P34: ='Program Budget'!Q35 -> 12 | Q34: ='Program Budget'!P35 -> 1 | R34: =O34*P34*Q34 -> 104186.25 | S34: =O34*1.05 -> 9116.2969 | T34: ='Program Budget'!T35 -> 12 | U34: ='Program Budget'!S35 -> 1 | V34: =S34*T34*U34 -> 109395.56 | W34: =F34+J34+N34+R34+V34 -> 497306.81
A35: Total HQ Staff | F35: =SUM(F33:F34) -> 117000 | J35: =SUM(J33:J34) -> 122850 | N35: =SUM(N33:N34) -> 128992.5 | R35: =SUM(R33:R34) -> 135442.12 | V35: =SUM(V33:V34) -> 142214.23 | W35: =+F35+J35+N35+R35+V35 -> 646498.86
A37: Subtotal: Salaries & Wages | F37: =F35+F31+F8 -> 639583.33 | J37: =J35+J31+J8 -> 898800 | N37: =N35+N31+N8 -> 943740 | R37: =R35+R31+R8 -> 990927 | V37: =V35+V31+V8 -> 889649.28 | W37: =+F37+J37+N37+R37+V37 -> 4362699.6
A38: Fringe
A39: USN/TCN Staff | F39: =C39*D39*E39 -> 0 | J39: =G39*H39*I39 -> 0 | N39: =K39*L39*M39 -> 0 | R39: =O39*P39*Q39 -> 0 | V39: =S39*T39*U39 -> 0 | W39: =F39+J39+N39+R39+V39 -> 0
A40: CCN Staff | B40: ='Program Budget'!F41 -> % | C40: =F31 -> 522583.33 | D40: 1 | E40: ='Program Budget'!H40 -> 0.455 | F40: =C40*D40*E40 -> 237775.42 | G40: =J31 -> 775950 | H40: 1 | I40: =E40 -> 0.455 | J40: =G40*H40*I40 -> 353057.25 | K40: =N31 -> 814747.5 | L40: 1 | M40: =I40 -> 0.455 | N40: =K40*L40*M40 -> 370710.11 | O40: =R31 -> 855484.88 | P40: 1 | Q40: =M40 -> 0.455 | R40: =O40*P40*Q40 -> 389245.62 | S40: =V31 -> 747435.05 | T40: 1 | U40: =Q40 -> 0.455 | V40: =S40*T40*U40 -> 340082.95 | W40: =F40+J40+N40+R40+V40 -> 1690871.3
A41: HQ Staff | B41: ='Program Budget'!F41 -> % | C41: =F35 -> 117000 | D41: 1 | E41: ='Program Budget'!H41 -> 0.2347 | F41: =C41*D41*E41 -> 27459.9 | G41: =J35 -> 122850 | H41: 1 | I41: =E41 -> 0.2347 | J41: =G41*H41*I41 -> 28832.895 | K41: =N35 -> 128992.5 | L41: 1 | M41: =I41 -> 0.2347 | N41: =K41*L41*M41 -> 30274.54 | O41: =R35 -> 135442.12 | P41: 1 | Q41: =M41 -> 0.2347 | R41: =O41*P41*Q41 -> 31788.267 | S41: =V35 -> 142214.23 | T41: 1 | U41: =Q41 -> 0.2347 | V41: =S41*T41*U41 -> 33377.68 | W41: =F41+J41+N41+R41+V41 -> 151733.28
A42: Total: Fringe Benefits | F42: =+SUM(F39:F41) -> 265235.32 | J42: =+SUM(J39:J41) -> 381890.15 | N42: =+SUM(N39:N41) -> 400984.65 | R42: =+SUM(R39:R41) -> 421033.88 | V42: =+SUM(V39:V41) -> 373460.63 | W42: =+F42+J42+N42+R42+V42 -> 1842604.6
A43: Allowances
A44: USN/TCN Staff
A45: None | F45: =C45*D45*E45 -> 0 | J45: =G45*H45*I45 -> 0 | N45: =K45*L45*M45 -> 0 | R45: =O45*P45*Q45 -> 0 | V45: =S45*T45*U45 -> 0 | W45: =F45+J45+N45+R45+V45 -> 0
A46: Total: Allowances | F46: =SUM(F44:F45) -> 0 | J46: =SUM(J44:J45) -> 0 | N46: =SUM(N44:N45) -> 0 | R46: =SUM(R44:R45) -> 0 | V46: =SUM(V44:V45) -> 0 | W46: =F46+J46+N46+R46+V46 -> 0
A48: Subtotal: Benefits | F48: =F46+F42 -> 265235.32 | J48: =J46+J42 -> 381890.15 | N48: =N46+N42 -> 400984.65 | R48: =R46+R42 -> 421033.88 | V48: =V46+V42 -> 373460.63 | W48: =+F48+J48+N48+R48+V48 -> 1842604.6
A49: International Travel
A50: ='Program Budget'!D47 -> Airfare - DC-Tunisia - HQ Project Management Trip | B50: ='Program Budget'!F47 -> Trip | C50: ='Program Budget'!H47 -> 1400 | D50: ='Program Budget'!G47 -> 5 | E50: 1 | F50: =C50*D50*E50 -> 7000 | G50: =C50*1.07 -> 1498 | H50: ='Program Budget'!K47 -> 5 | I50: 1 | J50: =G50*H50*I50 -> 7490 | K50: =G50*1.07 -> 1602.86 | L50: ='Program Budget'!N47 -> 5 | M50: 1 | N50: =K50*L50*M50 -> 8014.3 | O50: =K50*1.07 -> 1715.0602 | P50: ='Program Budget'!Q47 -> 5 | Q50: 1 | R50: =O50*P50*Q50 -> 8575.301 | S50: =O50*1.07 -> 1835.1144 | T50: ='Program Budget'!T47 -> 5 | U50: 1 | V50: =S50*T50*U50 -> 9175.5721 | W50: =F50+J50+N50+R50+V50 -> 40255.173
A51: ='Program Budget'!D52 -> Airfare - Roundtrip - Tunisia to USA | B51: ='Program Budget'!F52 -> Trip | C51: ='Program Budget'!H52 -> 1400 | D51: ='Program Budget'!G52 -> 4 | E51: 1 | F51: =C51*D51*E51 -> 5600 | G51: =C51*1.07 -> 1498 | H51: ='Program Budget'!K52 -> 4 | I51: 1 | J51: =G51*H51*I51 -> 5992 | K51: =G51*1.07 -> 1602.86 | L51: ='Program Budget'!N52 -> 4 | M51: 1 | N51: =K51*L51*M51 -> 6411.44 | O51: =K51*1.07 -> 1715.0602 | P51: ='Program Budget'!Q52 -> 4 | Q51: 1 | R51: =O51*P51*Q51 -> 6860.2408 | S51: =O51*1.07 -> 1835.1144 | T51: ='Program Budget'!T52 -> 4 | U51: 1 | V51: =S51*T51*U51 -> 7340.4577 | W51: =F51+J51+N51+R51+V51 -> 32204.138
A52: ='Program Budget'!D339 -> Airfare and Local Transport for Two-Way Trade (US to Tunisia) to - 50% of Cost | B52: ='Program Budget'!F339 -> Trip | C52: ='Program Budget'!H339 -> 775 | D52: ='Program Budget'!G339 -> 0 | E52: 0 | F52: =C52*D52*E52 -> 0 | G52: =C52*1.07 -> 829.25 | H52: ='Program Budget'!K339 -> 0 | I52: 0 | J52: =G52*H52*I52 -> 0 | K52: =G52*1.07 -> 887.2975 | L52: ='Program Budget'!N339 -> 10 | M52: 1 | N52: =K52*L52*M52 -> 8872.975 | O52: =K52*1.07 -> 949.40833 | P52: ='Program Budget'!Q339 -> 0 | Q52: 0 | R52: =O52*P52*Q52 -> 0 | S52: =O52*1.07 -> 1015.8669 | T52: ='Program Budget'!T339 -> 0 | U52: 0 | V52: =S52*T52*U52 -> 0 | W52: =F52+J52+N52+R52+V52 -> 8872.975
A53: ='Program Budget'!D340 -> Airfare and Local Transport for Two-Way Trade (Tunisia to US) | B53: ='Program Budget'!F340 -> Trip | C53: ='Program Budget'!H340 -> 1550 | D53: ='Program Budget'!G340 -> 0 | E53: 0 | F53: =C53*D53*E53 -> 0 | G53: =C53*1.07 -> 1658.5 | H53: ='Program Budget'!K340 -> 0 | I53: 0 | J53: =G53*H53*I53 -> 0 | K53: =G53*1.07 -> 1774.595 | L53: ='Program Budget'!N340 -> 10 | M53: 1 | N53: =K53*L53*M53 -> 17745.95 | O53: =K53*1.07 -> 1898.8167 | P53: ='Program Budget'!Q340 -> 0 | Q53: 0 | R53: =O53*P53*Q53 -> 0 | S53: =O53*1.07 -> 2031.7338 | T53: ='Program Budget'!T340 -> 0 | U53: 0 | V53: =S53*T53*U53 -> 0 | W53: =F53+J53+N53+R53+V53 -> 17745.95
A54: ='Program Budget'!D344 -> Airfare and Local Transport for International Food Shows (Tunisia to Dubai) | B54: ='Program Budget'!F344 -> Trip | C54: ='Program Budget'!H344 -> 750 | D54: ='Program Budget'!G344 -> 0 | E54: 0 | F54: =C54*D54*E54 -> 0 | G54: =C54*1.07 -> 802.5 | H54: ='Program Budget'!K344 -> 5 | I54: 1 | J54: =G54*H54*I54 -> 4012.5 | K54: =G54*1.07 -> 858.675 | L54: ='Program Budget'!N344 -> 5 | M54: 1 | N54: =K54*L54*M54 -> 4293.375 | O54: =K54*1.07 -> 918.78225 | P54: ='Program Budget'!Q344 -> 0 | Q54: 0 | R54: =O54*P54*Q54 -> 0 | S54: =O54*1.07 -> 983.09701 | T54: ='Program Budget'!T344 -> 0 | U54: 0 | V54: =S54*T54*U54 -> 0 | W54: =F54+J54+N54+R54+V54 -> 8305.875
A55: ='Program Budget'!D345 -> Airfare and Local Transport for International Food Shows (Tunisia to US) | B55: ='Program Budget'!F345 -> Trip | C55: ='Program Budget'!H345 -> 1550 | D55: ='Program Budget'!G345 -> 0 | E55: 0 | F55: =C55*D55*E55 -> 0 | G55: =C55*1.07 -> 1658.5 | H55: ='Program Budget'!K345 -> 0 | I55: 0 | J55: =G55*H55*I55 -> 0 | K55: =G55*1.07 -> 1774.595 | L55: ='Program Budget'!N345 -> 5 | M55: 1 | N55: =K55*L55*M55 -> 8872.975 | O55: =K55*1.07 -> 1898.8167 | P55: ='Program Budget'!Q345 -> 5 | Q55: 1 | R55: =O55*P55*Q55 -> 9494.0833 | S55: =O55*1.07 -> 2031.7338 | T55: ='Program Budget'!T345 -> 0 | U55: 0 | V55: =S55*T55*U55 -> 0 | W55: =F55+J55+N55+R55+V55 -> 18367.058
A56: Local Travel
A57: ='Program Budget'!D49 -> Ground Transportation – HQ Project Management Trip | B57: ='Program Budget'!F49 -> Trip | C57: ='Program Budget'!H49 -> 150 | D57: ='Program Budget'!G49 -> 5 | E57: 1 | F57: =C57*D57*E57 -> 750 | G57: =C57*1.07 -> 160.5 | H57: ='Program Budget'!K49 -> 5 | I57: 1 | J57: =G57*H57*I57 -> 802.5 | K57: =G57*1.07 -> 171.735 | L57: ='Program Budget'!N49 -> 5 | M57: 1 | N57: =K57*L57*M57 -> 858.675 | O57: =K57*1.07 -> 183.75645 | P57: ='Program Budget'!Q49 -> 5 | Q57: 1 | R57: =O57*P57*Q57 -> 918.78225 | S57: =O57*1.07 -> 196.6194 | T57: ='Program Budget'!T49 -> 5 | U57: 1 | V57: =S57*T57*U57 -> 983.09701 | W57: =F57+J57+N57+R57+V57 -> 4313.0543
A58: ='Program Budget'!D54 -> Ground Transportation for Tunisia Staff Travel | B58: ='Program Budget'!F58 -> Trip | C58: ='Program Budget'!H54 -> 150 | D58: ='Program Budget'!G54 -> 4 | E58: 1 | F58: =C58*D58*E58 -> 600 | G58: =C58*1.07 -> 160.5 | H58: ='Program Budget'!K54 -> 4 | I58: 1 | J58: =G58*H58*I58 -> 642 | K58: =G58*1.07 -> 171.735 | L58: ='Program Budget'!N54 -> 4 | M58: 1 | N58: =K58*L58*M58 -> 686.94 | O58: =K58*1.07 -> 183.75645 | P58: ='Program Budget'!Q54 -> 4 | Q58: 1 | R58: =O58*P58*Q58 -> 735.0258 | S58: =O58*1.07 -> 196.6194 | T58: ='Program Budget'!T54 -> 4 | U58: 1 | V58: =S58*T58*U58 -> 786.47761 | W58: =F58+J58+N58+R58+V58 -> 3450.4434
A59: ='Program Budget'!D58 -> Local Transportation (Car Rental, Taxis) – Training, M&E, & Data Collection | B59: ='Program Budget'!F58 -> Trip | C59: ='Program Budget'!H58 -> 100 | D59: ='Program Budget'!G58 -> 36 | E59: 1 | F59: =C59*D59*E59 -> 3600 | G59: =C59*1.07 -> 107 | H59: ='Program Budget'!K58 -> 36 | I59: 1 | J59: =G59*H59*I59 -> 3852 | K59: =G59*1.07 -> 114.49 | L59: ='Program Budget'!N58 -> 36 | M59: 1 | N59: =K59*L59*M59 -> 4121.64 | O59: =K59*1.07 -> 122.5043 | P59: ='Program Budget'!Q58 -> 36 | Q59: 1 | R59: =O59*P59*Q59 -> 4410.1548 | S59: =O59*1.07 -> 131.0796 | T59: ='Program Budget'!T58 -> 36 | U59: 1 | V59: =S59*T59*U59 -> 4718.8656 | W59: =F59+J59+N59+R59+V59 -> 20702.66
A60: Local Transportation (Car Rental, Taxis) - Activity 1 | B60: ='Program Budget'!F183 -> Month | C60: ='Program Budget'!H183 -> 50 | D60: ='Program Budget'!G183 -> 3 | E60: 1 | F60: =C60*D60*E60 -> 150 | G60: =C60*1.07 -> 53.5 | H60: ='Program Budget'!K183 -> 12 | I60: 1 | J60: =G60*H60*I60 -> 642 | K60: =G60*1.07 -> 57.245 | L60: ='Program Budget'!N183 -> 12 | M60: 1 | N60: =K60*L60*M60 -> 686.94 | O60: =K60*1.07 -> 61.25215 | P60: ='Program Budget'!Q183 -> 12 | Q60: 1 | R60: =O60*P60*Q60 -> 735.0258 | S60: =O60*1.07 -> 65.539801 | T60: ='Program Budget'!T183 -> 9 | U60: 1 | V60: =S60*T60*U60 -> 589.8582 | W60: =F60+J60+N60+R60+V60 -> 2803.824
A61: ='Program Budget'!D184 -> Local Transportation for Staff for Communication Materials Development | B61: ='Program Budget'!F184 -> Trip | C61: ='Program Budget'!H184 -> 300 | D61: ='Program Budget'!G184 -> 3 | E61: 1 | F61: =C61*D61*E61 -> 900 | G61: =C61*1.07 -> 321 | H61: ='Program Budget'!K184 -> 3 | I61: 1 | J61: =G61*H61*I61 -> 963 | K61: =G61*1.07 -> 343.47 | L61: ='Program Budget'!N184 -> 0 | M61: 0 | N61: =K61*L61*M61 -> 0 | O61: =K61*1.07 -> 367.5129 | P61: ='Program Budget'!Q184 -> 0 | Q61: 0 | R61: =O61*P61*Q61 -> 0 | S61: =O61*1.07 -> 393.2388 | T61: ='Program Budget'!T184 -> 0 | U61: 0 | V61: =S61*T61*U61 -> 0 | W61: =F61+J61+N61+R61+V61 -> 1863
A62: ='Program Budget'!D186 -> Local Transportation for Staff to Attend Local Agriculture Events | B62: ='Program Budget'!F186 -> Trip | C62: ='Program Budget'!H186 -> 200 | D62: ='Program Budget'!G186 -> 0 | E62: 0 | F62: =C62*D62*E62 -> 0 | G62: =C62*1.07 -> 214 | H62: ='Program Budget'!K186 -> 6 | I62: 1 | J62: =G62*H62*I62 -> 1284 | K62: =G62*1.07 -> 228.98 | L62: ='Program Budget'!N186 -> 6 | M62: 1 | N62: =K62*L62*M62 -> 1373.88 | O62: =K62*1.07 -> 245.0086 | P62: ='Program Budget'!Q186 -> 6 | Q62: 1 | R62: =O62*P62*Q62 -> 1470.0516 | S62: =O62*1.07 -> 262.1592 | T62: ='Program Budget'!T186 -> 6 | U62: 1 | V62: =S62*T62*U62 -> 1572.9552 | W62: =F62+J62+N62+R62+V62 -> 5700.8868
A63: ='Program Budget'!D188 -> Local Transportation for Leaders of Northern Tunisian Cooperatives to Attend Trainings | B63: ='Program Budget'!F188 -> Trip | C63: ='Program Budget'!H188 -> 200 | D63: ='Program Budget'!G188 -> 0 | E63: 0 | F63: =C63*D63*E63 -> 0 | G63: =C63*1.07 -> 214 | H63: ='Program Budget'!K188 -> 2 | I63: 1 | J63: =G63*H63*I63 -> 428 | K63: =G63*1.07 -> 228.98 | L63: ='Program Budget'!N188 -> 2 | M63: 1 | N63: =K63*L63*M63 -> 457.96 | O63: =K63*1.07 -> 245.0086 | P63: ='Program Budget'!Q188 -> 0 | Q63: 0 | R63: =O63*P63*Q63 -> 0 | S63: =O63*1.07 -> 262.1592 | T63: ='Program Budget'!T188 -> 0 | U63: 0 | V63: =S63*T63*U63 -> 0 | W63: =F63+J63+N63+R63+V63 -> 885.96
A64: ='Program Budget'!D190 -> Transport Stipends for Participants to Attend Farmer Field School | B64: ='Program Budget'!F190 -> Participant | C64: ='Program Budget'!H190 -> 10 | D64: ='Program Budget'!G190 -> 500 | E64: 1 | F64: =C64*D64*E64 -> 5000 | G64: =C64*1.07 -> 10.7 | H64: ='Program Budget'!K190 -> 1000 | I64: 1 | J64: =G64*H64*I64 -> 10700 | K64: =G64*1.07 -> 11.449 | L64: ='Program Budget'!N190 -> 500 | M64: 1 | N64: =K64*L64*M64 -> 5724.5 | O64: =K64*1.07 -> 12.25043 | P64: ='Program Budget'!Q190 -> 0 | Q64: 0 | R64: =O64*P64*Q64 -> 0 | S64: =O64*1.07 -> 13.10796 | T64: ='Program Budget'!T190 -> 0 | U64: 0 | V64: =S64*T64*U64 -> 0 | W64: =F64+J64+N64+R64+V64 -> 21424.5
A65: ='Program Budget'!D256 -> Local Transportation (Car Rental, Taxis) | B65: ='Program Budget'!F256 -> Month | C65: ='Program Budget'!H256 -> 50 | D65: ='Program Budget'!G256 -> 3 | E65: 1 | F65: =C65*D65*E65 -> 150 | G65: =C65*1.07 -> 53.5 | H65: ='Program Budget'!K256 -> 12 | I65: 1 | J65: =G65*H65*I65 -> 642 | K65: =G65*1.07 -> 57.245 | L65: ='Program Budget'!N256 -> 12 | M65: 1 | N65: =K65*L65*M65 -> 686.94 | O65: =K65*1.07 -> 61.25215 | P65: ='Program Budget'!Q256 -> 12 | Q65: 1 | R65: =O65*P65*Q65 -> 735.0258 | S65: =O65*1.07 -> 65.539801 | T65: ='Program Budget'!T256 -> 9 | U65: 1 | V65: =S65*T65*U65 -> 589.8582 | W65: =F65+J65+N65+R65+V65 -> 2803.824
A66: ='Program Budget'!D257 -> Local Transportation for Stakeholder Workshop | B66: ='Program Budget'!F257 -> Trip | C66: ='Program Budget'!H257 -> 100 | D66: ='Program Budget'!G257 -> 3 | E66: 1 | F66: =C66*D66*E66 -> 300 | G66: =C66*1.07 -> 107 | H66: ='Program Budget'!K257 -> 0 | I66: 0 | J66: =G66*H66*I66 -> 0 | K66: =G66*1.07 -> 114.49 | L66: ='Program Budget'!N257 -> 0 | M66: 0 | N66: =K66*L66*M66 -> 0 | O66: =K66*1.07 -> 122.5043 | P66: ='Program Budget'!Q257 -> 0 | Q66: 0 | R66: =O66*P66*Q66 -> 0 | S66: =O66*1.07 -> 131.0796 | T66: ='Program Budget'!T257 -> 0 | U66: 0 | V66: =S66*T66*U66 -> 0 | W66: =F66+J66+N66+R66+V66 -> 300
A67: ='Program Budget'!D259 -> Local Transportation for Technical Package Design | B67: ='Program Budget'!F259 -> Trip | C67: ='Program Budget'!H259 -> 100 | D67: ='Program Budget'!G259 -> 8 | E67: 1 | F67: =C67*D67*E67 -> 800 | G67: =C67*1.07 -> 107 | H67: ='Program Budget'!K259 -> 0 | I67: 0 | J67: =G67*H67*I67 -> 0 | K67: =G67*1.07 -> 114.49 | L67: ='Program Budget'!N259 -> 0 | M67: 0 | N67: =K67*L67*M67 -> 0 | O67: =K67*1.07 -> 122.5043 | P67: ='Program Budget'!Q259 -> 0 | Q67: 0 | R67: =O67*P67*Q67 -> 0 | S67: =O67*1.07 -> 131.0796 | T67: ='Program Budget'!T259 -> 0 | U67: 0 | V67: =S67*T67*U67 -> 0 | W67: =F67+J67+N67+R67+V67 -> 800
A68: Local Transportation (Car Rental, Taxis) - Activity 3 | B68: ='Program Budget'!F260 -> Day | C68: ='Program Budget'!H332 -> 75 | D68: ='Program Budget'!G332 -> 3 | E68: 1 | F68: =C68*D68*E68 -> 225 | G68: =C68*1.07 -> 80.25 | H68: ='Program Budget'!K332 -> 12 | I68: 1 | J68: =G68*H68*I68 -> 963 | K68: =G68*1.07 -> 85.8675 | L68: ='Program Budget'!N332 -> 12 | M68: 1 | N68: =K68*L68*M68 -> 1030.41 | O68: =K68*1.07 -> 91.878225 | P68: ='Program Budget'!Q332 -> 12 | Q68: 1 | R68: =O68*P68*Q68 -> 1102.5387 | S68: =O68*1.07 -> 98.309701 | T68: ='Program Budget'!T332 -> 7 | U68: 1 | V68: =S68*T68*U68 -> 688.16791 | W68: =F68+J68+N68+R68+V68 -> 4009.1166
A69: ='Program Budget'!D261 -> Transport Stipends for Producers Organization Leaders to Attend PASPs Trainings | B69: ='Program Budget'!F261 -> Participant | C69: ='Program Budget'!H261+'Program Budget'!H333 -> 14 | D69: ='Program Budget'!G261 -> 0 | E69: 0 | F69: =C69*D69*E69 -> 0 | G69: =C69*1.07 -> 14.98 | H69: ='Program Budget'!K261 -> 36 | I69: 1 | J69: =G69*H69*I69 -> 539.28 | K69: =G69*1.07 -> 16.0286 | L69: ='Program Budget'!N261 -> 38 | M69: 1 | N69: =K69*L69*M69 -> 609.0868 | O69: =K69*1.07 -> 17.150602 | P69: ='Program Budget'!Q261 -> 36 | Q69: 1 | R69: =O69*P69*Q69 -> 617.42167 | S69: =O69*1.07 -> 18.351144 | T69: ='Program Budget'!T261 -> 0 | U69: 0 | V69: =S69*T69*U69 -> 0 | W69: =F69+J69+N69+R69+V69 -> 1765.7885
A70: ='Program Budget'!D334 -> Transport Stipends for Producers Organization to Attend Market Access Training | B70: ='Program Budget'!F334 -> Participant | C70: ='Program Budget'!H334 -> 10 | D70: ='Program Budget'!G334 -> 0 | E70: 0 | F70: =C70*D70*E70 -> 0 | G70: =C70*1.07 -> 10.7 | H70: ='Program Budget'!K334 -> 200 | I70: 1 | J70: =G70*H70*I70 -> 2140 | K70: =G70*1.07 -> 11.449 | L70: ='Program Budget'!N334 -> 0 | M70: 0 | N70: =K70*L70*M70 -> 0 | O70: =K70*1.07 -> 12.25043 | P70: ='Program Budget'!Q334 -> 0 | Q70: 0 | R70: =O70*P70*Q70 -> 0 | S70: =O70*1.07 -> 13.10796 | T70: ='Program Budget'!T334 -> 0 | U70: 1 | V70: =S70*T70*U70 -> 0 | W70: =F70+J70+N70+R70+V70 -> 2140
A71: ='Program Budget'!D335 -> Transportation for US Consultant to Provide Technical Assistance on Farmer Certification | B71: ='Program Budget'!F335 -> Trip | C71: ='Program Budget'!H335 -> 1550 | D71: ='Program Budget'!G335 -> 0 | E71: 0 | F71: =C71*D71*E71 -> 0 | G71: =C71*1.07 -> 1658.5 | H71: ='Program Budget'!K335 -> 0 | I71: 0 | J71: =G71*H71*I71 -> 0 | K71: =G71*1.07 -> 1774.595 | L71: ='Program Budget'!N335 -> 1 | M71: 1 | N71: =K71*L71*M71 -> 1774.595 | O71: =K71*1.07 -> 1898.8167 | P71: ='Program Budget'!Q335 -> 0 | Q71: 0 | R71: =O71*P71*Q71 -> 0 | S71: =O71*1.07 -> 2031.7338 | T71: ='Program Budget'!T335 -> 0 | U71: 1 | V71: =S71*T71*U71 -> 0 | W71: =F71+J71+N71+R71+V71 -> 1774.595
A72: ='Program Budget'!D337 -> Local Transportation Stipend for Financial Literacy Trainings | B72: ='Program Budget'!F337 -> Trip | C72: ='Program Budget'!H337 -> 10 | D72: ='Program Budget'!G337 -> 0 | E72: 0 | F72: =C72*D72*E72 -> 0 | G72: =C72*1.07 -> 10.7 | H72: ='Program Budget'!K337 -> 160 | I72: 1 | J72: =G72*H72*I72 -> 1712 | K72: =G72*1.07 -> 11.449 | L72: ='Program Budget'!N337 -> 160 | M72: 1 | N72: =K72*L72*M72 -> 1831.84 | O72: =K72*1.07 -> 12.25043 | P72: ='Program Budget'!Q337 -> 0 | Q72: 0 | R72: =O72*P72*Q72 -> 0 | S72: =O72*1.07 -> 13.10796 | T72: ='Program Budget'!T337 -> 0 | U72: 1 | V72: =S72*T72*U72 -> 0 | W72: =F72+J72+N72+R72+V72 -> 3543.84
A73: Vehicle Fuel
A74: Vehicle Fuel Expense - Admin, Act. 1-2 | B74: ='Program Budget'!F182 -> Month | C74: =Admin!C56+'Activity 1'!C50+'Activity 2'!C48 -> 800 | D74: ='Activity 1'!D50 -> 3 | E74: 1 | F74: =C74*D74*E74 -> 2400 | G74: =C74*1.07 -> 856 | H74: ='Activity 1'!H50 -> 12 | I74: 1 | J74: =G74*H74*I74 -> 10272 | K74: =G74*1.07 -> 915.92 | L74: ='Program Budget'!N182 -> 12 | M74: 1 | N74: =K74*L74*M74 -> 10991.04 | O74: =K74*1.07 -> 980.0344 | P74: ='Program Budget'!Q182 -> 12 | Q74: 1 | R74: =O74*P74*Q74 -> 11760.413 | S74: =O74*1.07 -> 1048.6368 | T74: ='Program Budget'!T182 -> 9 | U74: 1 | V74: =S74*T74*U74 -> 9437.7313 | W74: =F74+J74+N74+R74+V74 -> 44861.184
A75: Vehicle Fuel Expense - Act. 3 | B75: ='Activity 3'!B55 -> Month | C75: ='Activity 3'!C55 -> 325 | D75: ='Program Budget'!G331 -> 3 | E75: 1 | F75: =C75*D75*E75 -> 975 | G75: =C75*1.07 -> 347.75 | H75: ='Program Budget'!K331 -> 12 | I75: 1 | J75: =G75*H75*I75 -> 4173 | K75: =G75*1.07 -> 372.0925 | L75: ='Program Budget'!N331 -> 12 | M75: 1 | N75: =K75*L75*M75 -> 4465.11 | O75: =K75*1.07 -> 398.13898 | P75: ='Program Budget'!Q331 -> 12 | Q75: 1 | R75: =O75*P75*Q75 -> 4777.6677 | S75: =O75*1.07 -> 426.0087 | T75: ='Program Budget'!T331 -> 7 | U75: 1 | V75: =S75*T75*U75 -> 2982.0609 | W75: =F75+J75+N75+R75+V75 -> 17372.839
A76: Per Diem & Lodging
A77: ='Program Budget'!D48 -> Lodging and M&IE - HQ Project Management Trip | B77: ='Program Budget'!F48 -> Day | C77: ='Program Budget'!H48 -> 212 | D77: ='Program Budget'!G48 -> 35 | E77: 1 | F77: =C77*D77*E77 -> 7420 | G77: =C77*1.07 -> 226.84 | H77: ='Program Budget'!K48 -> 35 | I77: 1 | J77: =G77*H77*I77 -> 7939.4 | K77: =G77*1.07 -> 242.7188 | L77: ='Program Budget'!N48 -> 35 | M77: 1 | N77: =K77*L77*M77 -> 8495.158 | O77: =K77*1.07 -> 259.70912 | P77: ='Program Budget'!Q48 -> 35 | Q77: 1 | R77: =O77*P77*Q77 -> 9089.8191 | S77: =O77*1.07 -> 277.88875 | T77: ='Program Budget'!T48 -> 35 | U77: 1 | V77: =S77*T77*U77 -> 9726.1064 | W77: =F77+J77+N77+R77+V77 -> 42670.483
A78: ='Program Budget'!D50 -> Other Travel Related Expenses – HQ Project Management Trip | B78: ='Program Budget'!F50 -> Trip | C78: ='Program Budget'!H50 -> 50 | D78: ='Program Budget'!G50 -> 5 | E78: 1 | F78: =C78*D78*E78 -> 250 | G78: =C78*1.07 -> 53.5 | H78: ='Program Budget'!K50 -> 5 | I78: 1 | J78: =G78*H78*I78 -> 267.5 | K78: =G78*1.07 -> 57.245 | L78: ='Program Budget'!N50 -> 5 | M78: 1 | N78: =K78*L78*M78 -> 286.225 | O78: =K78*1.07 -> 61.25215 | P78: ='Program Budget'!Q50 -> 5 | Q78: 1 | R78: =O78*P78*Q78 -> 306.26075 | S78: =O78*1.07 -> 65.539801 | T78: ='Program Budget'!T50 -> 5 | U78: 1 | V78: =S78*T78*U78 -> 327.699 | W78: =F78+J78+N78+R78+V78 -> 1437.6848
A79: ='Program Budget'!D53 -> Lodging and M&IE for Tunisia Staff Travel | B79: ='Program Budget'!F53 -> Day | C79: ='Program Budget'!H53 -> 251 | D79: ='Program Budget'!G53 -> 28 | E79: 1 | F79: =C79*D79*E79 -> 7028 | G79: =C79*1.07 -> 268.57 | H79: ='Program Budget'!K53 -> 28 | I79: 1 | J79: =G79*H79*I79 -> 7519.96 | K79: =G79*1.07 -> 287.3699 | L79: ='Program Budget'!N53 -> 28 | M79: 1 | N79: =K79*L79*M79 -> 8046.3572 | O79: =K79*1.07 -> 307.48579 | P79: ='Program Budget'!Q53 -> 28 | Q79: 1 | R79: =O79*P79*Q79 -> 8609.6022 | S79: =O79*1.07 -> 329.0098 | T79: ='Program Budget'!T53 -> 28 | U79: 1 | V79: =S79*T79*U79 -> 9212.2744 | W79: =F79+J79+N79+R79+V79 -> 40416.194
A80: ='Program Budget'!D55 -> Other Travel Related Expenses for Tunisia Staff Travel | B80: ='Program Budget'!F55 -> Trip | C80: ='Program Budget'!H55 -> 50 | D80: ='Program Budget'!G55 -> 4 | E80: 1 | F80: =C80*D80*E80 -> 200 | G80: =C80*1.07 -> 53.5 | H80: ='Program Budget'!K55 -> 4 | I80: 1 | J80: =G80*H80*I80 -> 214 | K80: =G80*1.07 -> 57.245 | L80: ='Program Budget'!N55 -> 4 | M80: 1 | N80: =K80*L80*M80 -> 228.98 | O80: =K80*1.07 -> 61.25215 | P80: ='Program Budget'!Q55 -> 4 | Q80: 1 | R80: =O80*P80*Q80 -> 245.0086 | S80: =O80*1.07 -> 65.539801 | T80: ='Program Budget'!T55 -> 4 | U80: 1 | V80: =S80*T80*U80 -> 262.1592 | W80: =F80+J80+N80+R80+V80 -> 1150.1478
A81: ='Program Budget'!D59 -> Lodging and M&IE - Training, M&E, & Data Collection | B81: ='Program Budget'!F59 -> Day | C81: ='Program Budget'!H59 -> 129 | D81: ='Program Budget'!G59 -> 144 | E81: 1 | F81: =C81*D81*E81 -> 18576 | G81: =C81*1.07 -> 138.03 | H81: ='Program Budget'!K59 -> 144 | I81: 1 | J81: =G81*H81*I81 -> 19876.32 | K81: =G81*1.07 -> 147.6921 | L81: ='Program Budget'!N59 -> 144 | M81: 1 | N81: =K81*L81*M81 -> 21267.662 | O81: =K81*1.07 -> 158.03055 | P81: ='Program Budget'!Q59 -> 144 | Q81: 1 | R81: =O81*P81*Q81 -> 22756.399 | S81: =O81*1.07 -> 169.09269 | T81: ='Program Budget'!T59 -> 144 | U81: 1 | V81: =S81*T81*U81 -> 24349.347 | W81: =F81+J81+N81+R81+V81 -> 106825.73
A82: ='Program Budget'!D185 -> Lodging and M&IE for Staff for Communication Materials Development | B82: ='Program Budget'!F185 -> Day | C82: ='Program Budget'!H185 -> 129 | D82: ='Program Budget'!G185 -> 9 | E82: 1 | F82: =C82*D82*E82 -> 1161 | G82: =C82*1.07 -> 138.03 | H82: ='Program Budget'!K185 -> 9 | I82: 1 | J82: =G82*H82*I82 -> 1242.27 | K82: =G82*1.07 -> 147.6921 | L82: ='Program Budget'!N185 -> 0 | M82: 0 | N82: =K82*L82*M82 -> 0 | O82: =K82*1.07 -> 158.03055 | P82: ='Program Budget'!Q185 -> 0 | Q82: 0 | R82: =O82*P82*Q82 -> 0 | S82: =O82*1.07 -> 169.09269 | T82: ='Program Budget'!T185 -> 0 | U82: 0 | V82: =S82*T82*U82 -> 0 | W82: =F82+J82+N82+R82+V82 -> 2403.27
A83: ='Program Budget'!D187 -> Lodging and M&IE for Staff to Attend Local Agriculture Events | B83: ='Program Budget'!F187 -> Day | C83: ='Program Budget'!H187 -> 129 | D83: ='Program Budget'!G187 -> 0 | E83: 0 | F83: =C83*D83*E83 -> 0 | G83: =C83*1.07 -> 138.03 | H83: ='Program Budget'!K187 -> 18 | I83: 1 | J83: =G83*H83*I83 -> 2484.54 | K83: =G83*1.07 -> 147.6921 | L83: ='Program Budget'!N187 -> 18 | M83: 1 | N83: =K83*L83*M83 -> 2658.4578 | O83: =K83*1.07 -> 158.03055 | P83: ='Program Budget'!Q187 -> 18 | Q83: 1 | R83: =O83*P83*Q83 -> 2844.5498 | S83: =O83*1.07 -> 169.09269 | T83: ='Program Budget'!T187 -> 18 | U83: 1 | V83: =S83*T83*U83 -> 3043.6683 | W83: =F83+J83+N83+R83+V83 -> 11031.216
A84: ='Program Budget'!D189 -> Lodging and M&IE for Staff Leaders of Northern Tunisian Cooperatives to Attend Trainings | B84: ='Program Budget'!F189 -> Day | C84: ='Program Budget'!H189 -> 129 | D84: ='Program Budget'!G189 -> 0 | E84: 0 | F84: =C84*D84*E84 -> 0 | G84: =C84*1.07 -> 138.03 | H84: ='Program Budget'!K189 -> 6 | I84: 1 | J84: =G84*H84*I84 -> 828.18 | K84: =G84*1.07 -> 147.6921 | L84: ='Program Budget'!N189 -> 6 | M84: 1 | N84: =K84*L84*M84 -> 886.1526 | O84: =K84*1.07 -> 158.03055 | P84: ='Program Budget'!Q189 -> 0 | Q84: 0 | R84: =O84*P84*Q84 -> 0 | S84: =O84*1.07 -> 169.09269 | T84: ='Program Budget'!T189 -> 0 | U84: 0 | V84: =S84*T84*U84 -> 0 | W84: =F84+J84+N84+R84+V84 -> 1714.3326
A85: ='Program Budget'!D258 -> Lodging and M&IE for Stakeholder Workshop | B85: ='Program Budget'!F258 -> Day | C85: ='Program Budget'!H258 -> 129 | D85: ='Program Budget'!G258 -> 6 | E85: 1 | F85: =C85*D85*E85 -> 774 | G85: =C85*1.07 -> 138.03 | H85: ='Program Budget'!K258 -> 0 | I85: 0 | J85: =G85*H85*I85 -> 0 | K85: =G85*1.07 -> 147.6921 | L85: ='Program Budget'!N258 -> 0 | M85: 0 | N85: =K85*L85*M85 -> 0 | O85: =K85*1.07 -> 158.03055 | P85: ='Program Budget'!Q258 -> 0 | Q85: 0 | R85: =O85*P85*Q85 -> 0 | S85: =O85*1.07 -> 169.09269 | T85: ='Program Budget'!T258 -> 0 | U85: 0 | V85: =S85*T85*U85 -> 0 | W85: =F85+J85+N85+R85+V85 -> 774
A86: ='Program Budget'!D260 -> Lodging and M&IE for Technical Package Design | B86: ='Program Budget'!F260 -> Day | C86: ='Program Budget'!H260 -> 129 | D86: ='Program Budget'!G260 -> 16 | E86: 1 | F86: =C86*D86*E86 -> 2064 | G86: =C86*1.07 -> 138.03 | H86: ='Program Budget'!K260 -> 0 | I86: 0 | J86: =G86*H86*I86 -> 0 | K86: =G86*1.07 -> 147.6921 | L86: ='Program Budget'!N260 -> 0 | M86: 0 | N86: =K86*L86*M86 -> 0 | O86: =K86*1.07 -> 158.03055 | P86: ='Program Budget'!Q260 -> 0 | Q86: 0 | R86: =O86*P86*Q86 -> 0 | S86: =O86*1.07 -> 169.09269 | T86: ='Program Budget'!T260 -> 0 | U86: 0 | V86: =S86*T86*U86 -> 0 | W86: =F86+J86+N86+R86+V86 -> 2064
A87: ='Program Budget'!D336 -> Lodging and M&IE for US Consultant to Provide Technical Assistance on Farmer Certification | B87: ='Program Budget'!F336 -> Day | C87: ='Program Budget'!H336 -> 212 | D87: ='Program Budget'!G336 -> 0 | E87: 0 | F87: =C87*D87*E87 -> 0 | G87: =C87*1.07 -> 226.84 | H87: ='Program Budget'!K336 -> 0 | I87: 0 | J87: =G87*H87*I87 -> 0 | K87: =G87*1.07 -> 242.7188 | L87: ='Program Budget'!N336 -> 15 | M87: 1 | N87: =K87*L87*M87 -> 3640.782 | O87: =K87*1.07 -> 259.70912 | P87: ='Program Budget'!Q336 -> 0 | Q87: 0 | R87: =O87*P87*Q87 -> 0 | S87: =O87*1.07 -> 277.88875 | T87: ='Program Budget'!T336 -> 0 | U87: 0 | V87: =S87*T87*U87 -> 0 | W87: =F87+J87+N87+R87+V87 -> 3640.782
A88: ='Program Budget'!D341 -> Lodging and M&IE for Two-Way Trade Travel (Tunisia to US) | B88: ='Program Budget'!F341 -> Day | C88: ='Program Budget'!H341 -> 219 | D88: ='Program Budget'!G341 -> 0 | E88: 0 | F88: =C88*D88*E88 -> 0 | G88: =C88*1.07 -> 234.33 | H88: ='Program Budget'!K341 -> 0 | I88: 0 | J88: =G88*H88*I88 -> 0 | K88: =G88*1.07 -> 250.7331 | L88: ='Program Budget'!N341 -> 70 | M88: 1 | N88: =K88*L88*M88 -> 17551.317 | O88: =K88*1.07 -> 268.28442 | P88: ='Program Budget'!Q341 -> 0 | Q88: 0 | R88: =O88*P88*Q88 -> 0 | S88: =O88*1.07 -> 287.06433 | T88: ='Program Budget'!T341 -> 0 | U88: 0 | V88: =S88*T88*U88 -> 0 | W88: =F88+J88+N88+R88+V88 -> 17551.317
A89: ='Program Budget'!D342 -> Lodging and M&IE for Two-Way Trade (US to Tunisia) | B89: ='Program Budget'!F342 -> Day | C89: ='Program Budget'!H342 -> 212 | D89: ='Program Budget'!G342 -> 0 | E89: 0 | F89: =C89*D89*E89 -> 0 | G89: =C89*1.07 -> 226.84 | H89: ='Program Budget'!K342 -> 0 | I89: 0 | J89: =G89*H89*I89 -> 0 | K89: =G89*1.07 -> 242.7188 | L89: ='Program Budget'!N342 -> 70 | M89: 1 | N89: =K89*L89*M89 -> 16990.316 | O89: =K89*1.07 -> 259.70912 | P89: ='Program Budget'!Q342 -> 0 | Q89: 0 | R89: =O89*P89*Q89 -> 0 | S89: =O89*1.07 -> 277.88875 | T89: ='Program Budget'!T342 -> 0 | U89: 0 | V89: =S89*T89*U89 -> 0 | W89: =F89+J89+N89+R89+V89 -> 16990.316
A90: ='Program Budget'!D346 -> Lodging and M&IE for International Food Shows (Dubai) | B90: ='Program Budget'!F346 -> Day | C90: ='Program Budget'!H346 -> 236 | D90: ='Program Budget'!G346 -> 0 | E90: 0 | F90: =C90*D90*E90 -> 0 | G90: =C90*1.07 -> 252.52 | H90: ='Program Budget'!K346 -> 35 | I90: 1 | J90: =G90*H90*I90 -> 8838.2 | K90: =G90*1.07 -> 270.1964 | L90: ='Program Budget'!N346 -> 35 | M90: 1 | N90: =K90*L90*M90 -> 9456.874 | O90: =K90*1.07 -> 289.11015 | P90: ='Program Budget'!Q346 -> 0 | Q90: 0 | R90: =O90*P90*Q90 -> 0 | S90: =O90*1.07 -> 309.34786 | T90: ='Program Budget'!T346 -> 0 | U90: 0 | V90: =S90*T90*U90 -> 0 | W90: =F90+J90+N90+R90+V90 -> 18295.074
A91: ='Program Budget'!D347 -> Lodging and M&IE for International Food Shows (USA) | B91: ='Program Budget'!F347 -> Day | C91: ='Program Budget'!H347 -> 321 | D91: ='Program Budget'!G347 -> 0 | E91: 0 | F91: =C91*D91*E91 -> 0 | G91: =C91*1.07 -> 343.47 | H91: ='Program Budget'!K347 -> 0 | I91: 0 | J91: =G91*H91*I91 -> 0 | K91: =G91*1.07 -> 367.5129 | L91: ='Program Budget'!N347 -> 35 | M91: 1 | N91: =K91*L91*M91 -> 12862.952 | O91: =K91*1.07 -> 393.2388 | P91: ='Program Budget'!Q347 -> 35 | Q91: 1 | R91: =O91*P91*Q91 -> 13763.358 | S91: =O91*1.07 -> 420.76552 | T91: ='Program Budget'!T347 -> 0 | U91: 0 | V91: =S91*T91*U91 -> 0 | W91: =F91+J91+N91+R91+V91 -> 26626.31
A93: Subtotal: Travel | F93: =SUM(F50:F92) -> 65923 | J93: =SUM(J50:J92) -> 106459.65 | N93: =SUM(N50:N92) -> 191881.81 | R93: =SUM(R50:R92) -> 109806.73 | V93: =SUM(V50:V92) -> 85786.356 | W93: =SUM(W50:W92) -> 559857.54
A94: Professional Services
A95: ='Program Budget'!D63 -> Monetization Agent Fee | B95: ='Program Budget'!F63 -> % | C95: =15157714 -> 15157714 | D95: ='Program Budget'!G63 -> 1 | E95: 0.0167 | F95: =C95*D95*E95 -> 253133.82 | G95: 0 | H95: 0 | I95: 0 | J95: =G95*H95*I95 -> 0 | K95: =G95 -> 0 | L95: ='Program Budget'!N63 -> 0 | M95: 0 | N95: =K95*L95*M95 -> 0 | O95: =K95 -> 0 | P95: ='Program Budget'!Q674 -> 0 | Q95: 0 | R95: =O95*P95*Q95 -> 0 | S95: =O95 -> 0 | T95: ='Program Budget'!T63 -> 0 | U95: 0 | V95: =S95*T95*U95 -> 0 | W95: =F95+J95+N95+R95+V95 -> 253133.82
A96: ='Program Budget'!D64 -> Monetization Impact Assessment | B96: ='Program Budget'!F64 -> Unit | C96: ='Program Budget'!H64 -> 60000 | D96: ='Program Budget'!G64 -> 0 | E96: 0 | F96: =C96*D96*E96 -> 0 | G96: =C96 -> 60000 | H96: ='Program Budget'!K64 -> 1 | I96: 1 | J96: =G96*H96*I96 -> 60000 | K96: =G96 -> 60000 | L96: ='Program Budget'!N64 -> 0 | M96: 0 | N96: =K96*L96*M96 -> 0 | O96: =K96 -> 60000 | P96: ='Program Budget'!Q64 -> 0 | Q96: 0 | R96: =O96*P96*Q96 -> 0 | S96: =O96 -> 60000 | T96: ='Program Budget'!T64 -> 0 | U96: 0 | V96: =S96*T96*U96 -> 0 | W96: =F96+J96+N96+R96+V96 -> 60000
A97: ='Program Budget'!D65 -> Local Program Audit Costs | B97: ='Program Budget'!F65 -> Year | C97: ='Program Budget'!H65 -> 1500 | D97: ='Program Budget'!G65 -> 1 | E97: 1 | F97: =C97*D97*E97 -> 1500 | G97: =C97 -> 1500 | H97: ='Program Budget'!K65 -> 1 | I97: 1 | J97: =G97*H97*I97 -> 1500 | K97: =G97 -> 1500 | L97: ='Program Budget'!N65 -> 1 | M97: 1 | N97: =K97*L97*M97 -> 1500 | O97: =K97 -> 1500 | P97: ='Program Budget'!Q65 -> 1 | Q97: 1 | R97: =O97*P97*Q97 -> 1500 | S97: =O97 -> 1500 | T97: ='Program Budget'!T65 -> 1 | U97: 1 | V97: =S97*T97*U97 -> 1500 | W97: =F97+J97+N97+R97+V97 -> 7500
A98: ='Program Budget'!D66 -> Legal & Registration Fees | B98: ='Program Budget'!F66 -> Year | C98: ='Program Budget'!H66 -> 4500 | D98: ='Program Budget'!G66 -> 1 | E98: 1 | F98: =C98*D98*E98 -> 4500 | G98: =C98 -> 4500 | H98: ='Program Budget'!K66 -> 1 | I98: 1 | J98: =G98*H98*I98 -> 4500 | K98: =G98 -> 4500 | L98: ='Program Budget'!N66 -> 1 | M98: 1 | N98: =K98*L98*M98 -> 4500 | O98: =K98 -> 4500 | P98: ='Program Budget'!Q66 -> 1 | Q98: 1 | R98: =O98*P98*Q98 -> 4500 | S98: =O98 -> 4500 | T98: ='Program Budget'!T66 -> 1 | U98: 1 | V98: =S98*T98*U98 -> 4500 | W98: =F98+J98+N98+R98+V98 -> 22500
A99: ='Program Budget'!D67 -> Security Services, Risk Assessments, & Security Assessment | B99: ='Program Budget'!F67 -> Year | C99: ='Program Budget'!H67+'Program Budget'!H173+'Program Budget'!H247+'Program Budget'!H321 -> 15500 | D99: ='Program Budget'!G67 -> 1 | E99: 1 | F99: =C99*D99*E99 -> 15500 | G99: =C99 -> 15500 | H99: ='Program Budget'!K67 -> 1 | I99: 1 | J99: =G99*H99*I99 -> 15500 | K99: =G99 -> 15500 | L99: ='Program Budget'!N67 -> 1 | M99: 1 | N99: =K99*L99*M99 -> 15500 | O99: =K99 -> 15500 | P99: ='Program Budget'!Q67 -> 1 | Q99: 1 | R99: =O99*P99*Q99 -> 15500 | S99: =O99 -> 15500 | T99: ='Program Budget'!T67 -> 1 | U99: 1 | V99: =S99*T99*U99 -> 15500 | W99: =F99+J99+N99+R99+V99 -> 77500
A100: ='Program Budget'!D68 -> Short-Term Technical Advisors | B100: ='Program Budget'!F68 -> Month | C100: ='Program Budget'!H68 -> 3500 | D100: ='Program Budget'!G68 -> 9 | E100: 1 | F100: =C100*D100*E100 -> 31500 | G100: =C100 -> 3500 | H100: ='Program Budget'!K68 -> 12 | I100: 1 | J100: =G100*H100*I100 -> 42000 | K100: =G100 -> 3500 | L100: ='Program Budget'!N68 -> 12 | M100: 1 | N100: =K100*L100*M100 -> 42000 | O100: =K100 -> 3500 | P100: ='Program Budget'!Q68 -> 12 | Q100: 1 | R100: =O100*P100*Q100 -> 42000 | S100: =O100 -> 3500 | T100: ='Program Budget'!T68 -> 9 | U100: 1 | V100: =S100*T100*U100 -> 31500 | W100: =F100+J100+N100+R100+V100 -> 189000
A101: ='Program Budget'!D69 -> Start-up Consultant | B101: ='Program Budget'!F69 -> Day | C101: ='Program Budget'!H69 -> 520 | D101: ='Program Budget'!G69 -> 50 | E101: 1 | F101: =C101*D101*E101 -> 26000 | G101: =C101 -> 520 | H101: ='Program Budget'!K69 -> 0 | I101: 0 | J101: =G101*H101*I101 -> 0 | K101: =G101 -> 520 | L101: ='Program Budget'!N69 -> 0 | M101: 0 | N101: =K101*L101*M101 -> 0 | O101: =K101 -> 520 | P101: ='Program Budget'!Q69 -> 0 | Q101: 0 | R101: =O101*P101*Q101 -> 0 | S101: =O101 -> 520 | T101: ='Program Budget'!T69 -> 0 | U101: 0 | V101: =S101*T101*U101 -> 0 | W101: =F101+J101+N101+R101+V101 -> 26000
A102: ='Program Budget'!D168 -> Contract for Development of Materials for Communications Campaign (includes budget for videos, social media reels, etc.) | B102: ='Program Budget'!F168 -> Year | C102: ='Program Budget'!H168 -> 100000 | D102: ='Program Budget'!G168 -> 0.5 | E102: 1 | F102: =C102*D102*E102 -> 50000 | G102: =C102 -> 100000 | H102: ='Program Budget'!K168 -> 0.5 | I102: 1 | J102: =G102*H102*I102 -> 50000 | K102: =G102 -> 100000 | L102: ='Program Budget'!N168 -> 0 | M102: 0 | N102: =K102*L102*M102 -> 0 | O102: =K102 -> 100000 | P102: ='Program Budget'!Q168 -> 0 | Q102: 0 | R102: =O102*P102*Q102 -> 0 | S102: =O102 -> 100000 | T102: ='Program Budget'!T168 -> 0 | U102: 0 | V102: =S102*T102*U102 -> 0 | W102: =F102+J102+N102+R102+V102 -> 100000
A103: ='Program Budget'!D169 -> Contract for Communications Campaign Dissemination | B103: ='Program Budget'!F169 -> Year | C103: ='Program Budget'!H169 -> 25000 | D103: ='Program Budget'!G169 -> 0 | E103: 0 | F103: =C103*D103*E103 -> 0 | G103: =C103 -> 25000 | H103: ='Program Budget'!K169 -> 1 | I103: 1 | J103: =G103*H103*I103 -> 25000 | K103: =G103 -> 25000 | L103: ='Program Budget'!N169 -> 1 | M103: 1 | N103: =K103*L103*M103 -> 25000 | O103: =K103 -> 25000 | P103: ='Program Budget'!Q169 -> 1 | Q103: 1 | R103: =O103*P103*Q103 -> 25000 | S103: =O103 -> 25000 | T103: ='Program Budget'!T169 -> 1 | U103: 1 | V103: =S103*T103*U103 -> 25000 | W103: =F103+J103+N103+R103+V103 -> 100000
A104: ='Program Budget'!D170 -> Contract for Private Agriculture Service Providers (PASPs) to Manage Model Farms and Training for Farmer Field Days | B104: ='Program Budget'!F170 -> Day | C104: ='Program Budget'!H170 -> 700 | D104: ='Program Budget'!G170 -> 8 | E104: 1 | F104: =C104*D104*E104 -> 5600 | G104: =C104 -> 700 | H104: ='Program Budget'!K170 -> 16 | I104: 1 | J104: =G104*H104*I104 -> 11200 | K104: =G104 -> 700 | L104: ='Program Budget'!N170 -> 8 | M104: 1 | N104: =K104*L104*M104 -> 5600 | O104: =K104 -> 700 | P104: ='Program Budget'!Q170 -> 0 | Q104: 0 | R104: =O104*P104*Q104 -> 0 | S104: =O104 -> 700 | T104: ='Program Budget'!T170 -> 0 | U104: 0 | V104: =S104*T104*U104 -> 0 | W104: =F104+J104+N104+R104+V104 -> 22400
A105: ='Program Budget'!D171 -> Consultant for Producer Organization Capacity Building | B105: ='Program Budget'!F171 -> Month | C105: ='Program Budget'!H171 -> 4500 | D105: ='Program Budget'!G171 -> 0 | E105: 0 | F105: =C105*D105*E105 -> 0 | G105: =C105 -> 4500 | H105: ='Program Budget'!K171 -> 3 | I105: 1 | J105: =G105*H105*I105 -> 13500 | K105: =G105 -> 4500 | L105: ='Program Budget'!N171 -> 3 | M105: 1 | N105: =K105*L105*M105 -> 13500 | O105: =K105 -> 4500 | P105: ='Program Budget'!Q171 -> 0 | Q105: 0 | R105: =O105*P105*Q105 -> 0 | S105: =O105 -> 4500 | T105: ='Program Budget'!T171 -> 0 | U105: 0 | V105: =S105*T105*U105 -> 0 | W105: =F105+J105+N105+R105+V105 -> 27000
A106: ='Program Budget'!D172 -> Consultant (Financial & Legal) to Advise on Grant Mechanism and Blended Finance Structure | B106: ='Program Budget'!F172 -> Day | C106: ='Program Budget'!H172 -> 625 | D106: ='Program Budget'!G172 -> 20 | E106: 1 | F106: =C106*D106*E106 -> 12500 | G106: =C106 -> 625 | H106: ='Program Budget'!K172 -> 0 | I106: 0 | J106: =G106*H106*I106 -> 0 | K106: =G106 -> 625 | L106: ='Program Budget'!N172 -> 0 | M106: 0 | N106: =K106*L106*M106 -> 0 | O106: =K106 -> 625 | P106: ='Program Budget'!Q172 -> 0 | Q106: 0 | R106: =O106*P106*Q106 -> 0 | S106: =O106 -> 625 | T106: ='Program Budget'!T172 -> 0 | U106: 0 | V106: =S106*T106*U106 -> 0 | W106: =F106+J106+N106+R106+V106 -> 12500
A107: ='Program Budget'!D244 -> Contract for Private Agriculture Service Providers (PASPs) to Train on Technical Assistance Business Models | B107: ='Program Budget'!F244 -> Region | C107: ='Program Budget'!H244 -> 25000 | D107: ='Program Budget'!G244 -> 4 | E107: 1 | F107: =C107*D107*E107 -> 100000 | G107: =(C107/2) -> 12500 | H107: ='Program Budget'!K244 -> 4 | I107: 1 | J107: =G107*H107*I107 -> 50000 | K107: =G107 -> 12500 | L107: ='Program Budget'!N244 -> 4 | M107: 1 | N107: =K107*L107*M107 -> 50000 | O107: =K107 -> 12500 | P107: ='Program Budget'!Q244 -> 4 | Q107: 1 | R107: =O107*P107*Q107 -> 50000 | S107: =O107 -> 12500 | T107: ='Program Budget'!T244 -> 0 | U107: 0 | V107: =S107*T107*U107 -> 0 | W107: =F107+J107+N107+R107+V107 -> 250000
A108: ='Program Budget'!D245 -> Contract for Private Agriculture Service Providers (PASPs) to Support Capacity-Building Efforts for Producer Organizations | B108: ='Program Budget'!F245 -> Day | C108: ='Program Budget'!H245 -> 350 | D108: ='Program Budget'!G245 -> 0 | E108: 0 | F108: =C108*D108*E108 -> 0 | G108: =C108 -> 350 | H108: ='Program Budget'!K245 -> 4 | I108: 1 | J108: =G108*H108*I108 -> 1400 | K108: =G108 -> 350 | L108: ='Program Budget'!N245 -> 4 | M108: 1 | N108: =K108*L108*M108 -> 1400 | O108: =K108 -> 350 | P108: ='Program Budget'!Q245 -> 4 | Q108: 1 | R108: =O108*P108*Q108 -> 1400 | S108: =O108 -> 350 | T108: ='Program Budget'!T245 -> 0 | U108: 0 | V108: =S108*T108*U108 -> 0 | W108: =F108+J108+N108+R108+V108 -> 4200
A109: ='Program Budget'!D246 -> Contract for Women-Led Enterprise Development Technical Assistance | B109: ='Program Budget'!F246 -> Unit | C109: ='Program Budget'!H246 -> 5000 | D109: ='Program Budget'!G246 -> 0 | E109: 0 | F109: =C109*D109*E109 -> 0 | G109: =C109 -> 5000 | H109: ='Program Budget'!K246 -> 12 | I109: 1 | J109: =G109*H109*I109 -> 60000 | K109: =G109 -> 5000 | L109: ='Program Budget'!N246 -> 13 | M109: 1 | N109: =K109*L109*M109 -> 65000 | O109: =K109 -> 5000 | P109: ='Program Budget'!Q246 -> 0 | Q109: 0 | R109: =O109*P109*Q109 -> 0 | S109: =O109 -> 5000 | T109: ='Program Budget'!T246 -> 0 | U109: 0 | V109: =S109*T109*U109 -> 0 | W109: =F109+J109+N109+R109+V109 -> 125000
A110: ='Program Budget'!D315 -> Subrecipient: 6th Grain | B110: ='Program Budget'!F315 -> Subrecipient | C110: ='Program Budget'!I315 -> 189531.67 | D110: ='Program Budget'!G315 -> 1 | E110: 1 | F110: =C110*D110*E110 -> 189531.67 | G110: ='Program Budget'!L315 -> 176568.93 | H110: ='Program Budget'!K315 -> 1 | I110: 1 | J110: =G110*H110*I110 -> 176568.93 | K110: ='Program Budget'!O315 -> 135632.78 | L110: ='Program Budget'!N315 -> 1 | M110: 1 | N110: =K110*L110*M110 -> 135632.78 | O110: ='Program Budget'!R315 -> 0 | P110: ='Program Budget'!Q315 -> 0 | Q110: 0 | R110: =O110*P110*Q110 -> 0 | S110: ='Program Budget'!U315 -> 0 | T110: ='Program Budget'!T315 -> 0 | U110: 0 | V110: =S110*T110*U110 -> 0 | W110: =F110+J110+N110+R110+V110 -> 501733.38
A111: ='Program Budget'!D316 -> Contract for Private Agriculture Service Providers (PASPs) to Train Producer Organizations to Leverage Economies of Scale | B111: ='Program Budget'!F316 -> Day | C111: ='Program Budget'!H316 -> 350 | D111: ='Program Budget'!G316 -> 0 | E111: 0 | F111: =C111*D111*E111 -> 0 | G111: =C111 -> 350 | H111: ='Program Budget'!K316 -> 4 | I111: 1 | J111: =G111*H111*I111 -> 1400 | K111: =G111 -> 350 | L111: ='Program Budget'!N316 -> 4 | M111: 1 | N111: =K111*L111*M111 -> 1400 | O111: =K111 -> 350 | P111: ='Program Budget'!Q316 -> 4 | Q111: 1 | R111: =O111*P111*Q111 -> 1400 | S111: =O111 -> 350 | T111: ='Program Budget'!T316 -> 0 | U111: 0 | V111: =S111*T111*U111 -> 0 | W111: =F111+J111+N111+R111+V111 -> 4200
A112: ='Program Budget'!D317 -> Contract for Organization to Provide Farmers Organic Certifications | B112: ='Program Budget'!F317 -> Certification | C112: ='Program Budget'!H317 -> 100 | D112: ='Program Budget'!G317 -> 0 | E112: 0 | F112: =C112*D112*E112 -> 0 | G112: =C112 -> 100 | H112: ='Program Budget'!K317 -> 0 | I112: 0 | J112: =G112*H112*I112 -> 0 | K112: =G112 -> 100 | L112: ='Program Budget'!N317 -> 1000 | M112: 1 | N112: =K112*L112*M112 -> 100000 | O112: =K112 -> 100 | P112: ='Program Budget'!Q317 -> 0 | Q112: 0 | R112: =O112*P112*Q112 -> 0 | S112: =O112 -> 100 | T112: ='Program Budget'!T317 -> 0 | U112: 0 | V112: =S112*T112*U112 -> 0 | W112: =F112+J112+N112+R112+V112 -> 100000
...

Sheet Sheet1

Sheet Admin
A2: Item | B2: Type of Unit | C2: Year 1 | G2: Year 2 | K2: Year 3 | O2: Year 4 | S2: Year 5 | W2: Total
C3: Cost | D3: Quantity | E3: Percent Allocated | F3: Total | G3: Cost | H3: Quantity | I3: Percent Allocated | J3: Total | K3: Cost | L3: Quantity | M3: Percent Allocated | N3: Total | O3: Cost | P3: Quantity | Q3: Percent Allocated | R3: Total | S3: Cost | T3: Quantity | U3: Percent Allocated | V3: Total | AF3: Chart of Accounts
A4: Direct Costs | AE4: Line# | AF4: Account | AG4: Account Name
A5: Salaries
A6: USN/TCN Staff
A7: None | F7: =C7*D7*E7 -> 0 | J7: =G7*H7*I7 -> 0 | N7: =K7*L7*M7 -> 0 | R7: =O7*P7*Q7 -> 0 | V7: =S7*T7*U7 -> 0 | W7: =F7+J7+N7+R7+V7 -> 0
A8: Total: Expatriate Salaries & Wages | F8: =SUM(F7:F7) -> 0 | J8: =SUM(J7:J7) -> 0 | N8: =SUM(N7:N7) -> 0 | R8: =SUM(R7:R7) -> 0 | V8: =SUM(V7:V7) -> 0 | W8: =+F8+J8+N8+R8+V8 -> 0
A9: CNN Staff
A10: ='Program Budget'!D12 -> Key Personnel: Chief of Party - Ms. Rym Ayari | B10: ='Program Budget'!F12 -> Month | C10: ='Program Budget'!H12 -> 13000 | D10: ='Program Budget'!G12 -> 12 | E10: ='Program Budget'!E12 -> 0.3 | F10: =C10*D10*E10 -> 46800 | G10: =C10*1.05 -> 13650 | H10: ='Program Budget'!K12 -> 12 | I10: ='Program Budget'!J12 -> 0.1 | J10: =G10*H10*I10 -> 16380 | K10: =G10*1.05 -> 14332.5 | L10: ='Program Budget'!N12 -> 12 | M10: ='Program Budget'!M12 -> 0.1 | N10: =K10*L10*M10 -> 17199 | O10: =K10*1.05 -> 15049.125 | P10: ='Program Budget'!Q12 -> 12 | Q10: ='Program Budget'!P12 -> 0.1 | R10: =O10*P10*Q10 -> 18058.95 | S10: =O10*1.05 -> 15801.581 | T10: ='Program Budget'!T12 -> 12 | U10: ='Program Budget'!S12 -> 0.1 | V10: =S10*T10*U10 -> 18961.898 | W10: =F10+J10+N10+R10+V10 -> 117399.85 | AE10: 180 | AF10: 50-01-2-020 | AG10: DIR-USN (Expat) Labor
A11: ='Program Budget'!D13 -> Key Personnel: Technical Director | B11: ='Program Budget'!F13 -> Month | C11: ='Program Budget'!H13 -> 3916.6667 | D11: ='Program Budget'!G13 -> 9 | E11: ='Program Budget'!E13 -> 0.3 | F11: =C11*D11*E11 -> 10575 | G11: =C11*1.05 -> 4112.5 | H11: ='Program Budget'!K13 -> 12 | I11: ='Program Budget'!J13 -> 0 | J11: =G11*H11*I11 -> 0 | K11: =G11*1.05 -> 4318.125 | L11: ='Program Budget'!N13 -> 12 | M11: ='Program Budget'!M13 -> 0 | N11: =K11*L11*M11 -> 0 | O11: =K11*1.05 -> 4534.0312 | P11: ='Program Budget'!Q13 -> 12 | Q11: ='Program Budget'!P13 -> 0 | R11: =O11*P11*Q11 -> 0 | S11: =O11*1.05 -> 4760.7328 | T11: ='Program Budget'!T13 -> 9 | U11: ='Program Budget'!S13 -> 0 | V11: =S11*T11*U11 -> 0 | W11: =F11+J11+N11+R11+V11 -> 10575 | AE11: 180 | AF11: 50-01-2-020 | AG11: DIR-USN (Expat) Labor
A12: ='Program Budget'!D14 -> Technical Lead Component 1 | B12: ='Program Budget'!F14 -> Month | C12: ='Program Budget'!H14 -> 2500 | D12: ='Program Budget'!G14 -> 6 | E12: ='Program Budget'!E14 -> 0.2 | F12: =C12*D12*E12 -> 3000 | G12: =C12*1.05 -> 2625 | H12: ='Program Budget'!K14 -> 12 | I12: ='Program Budget'!J14 -> 0 | J12: =G12*H12*I12 -> 0 | K12: =G12*1.05 -> 2756.25 | L12: ='Program Budget'!N14 -> 12 | M12: ='Program Budget'!M14 -> 0 | N12: =K12*L12*M12 -> 0 | O12: =K12*1.05 -> 2894.0625 | P12: ='Program Budget'!Q14 -> 12 | Q12: ='Program Budget'!P14 -> 0 | R12: =O12*P12*Q12 -> 0 | S12: =O12*1.05 -> 3038.7656 | T12: ='Program Budget'!T14 -> 9 | U12: ='Program Budget'!S14 -> 0 | V12: =S12*T12*U12 -> 0 | W12: =F12+J12+N12+R12+V12 -> 3000 | AE12: 180 | AF12: 50-01-2-020 | AG12: DIR-USN (Expat) Labor
A13: ='Program Budget'!D15 -> Technical Lead Component 2 | B13: ='Program Budget'!F15 -> Month | C13: ='Program Budget'!H15 -> 2500 | D13: ='Program Budget'!G15 -> 6 | E13: ='Program Budget'!E15 -> 0.2 | F13: =C13*D13*E13 -> 3000 | G13: =C13*1.05 -> 2625 | H13: ='Program Budget'!K15 -> 12 | I13: ='Program Budget'!J15 -> 0 | J13: =G13*H13*I13 -> 0 | K13: =G13*1.05 -> 2756.25 | L13: ='Program Budget'!N15 -> 12 | M13: ='Program Budget'!M15 -> 0 | N13: =K13*L13*M13 -> 0 | O13: =K13*1.05 -> 2894.0625 | P13: ='Program Budget'!Q15 -> 12 | Q13: ='Program Budget'!P15 -> 0 | R13: =O13*P13*Q13 -> 0 | S13: =O13*1.05 -> 3038.7656 | T13: ='Program Budget'!T15 -> 9 | U13: ='Program Budget'!S15 -> 0 | V13: =S13*T13*U13 -> 0 | W13: =F13+J13+N13+R13+V13 -> 3000 | AE13: 180 | AF13: 50-01-2-020 | AG13: DIR-USN (Expat) Labor
A14: ='Program Budget'!D16 -> Technical Lead Component 3 | B14: ='Program Budget'!F16 -> Month | C14: ='Program Budget'!H16 -> 2500 | D14: ='Program Budget'!G16 -> 6 | E14: ='Program Budget'!E16 -> 0.2 | F14: =C14*D14*E14 -> 3000 | G14: =C14*1.05 -> 2625 | H14: ='Program Budget'!K16 -> 12 | I14: ='Program Budget'!J16 -> 0 | J14: =G14*H14*I14 -> 0 | K14: =G14*1.05 -> 2756.25 | L14: ='Program Budget'!N16 -> 12 | M14: ='Program Budget'!M16 -> 0 | N14: =K14*L14*M14 -> 0 | O14: =K14*1.05 -> 2894.0625 | P14: ='Program Budget'!Q16 -> 12 | Q14: ='Program Budget'!P16 -> 0 | R14: =O14*P14*Q14 -> 0 | S14: =O14*1.05 -> 3038.7656 | T14: ='Program Budget'!T16 -> 9 | U14: ='Program Budget'!S16 -> 0 | V14: =S14*T14*U14 -> 0 | W14: =F14+J14+N14+R14+V14 -> 3000 | AE14: 180 | AF14: 50-01-2-020 | AG14: DIR-USN (Expat) Labor
A15: ='Program Budget'!D17 -> Technical Specialist Component 1 | B15: ='Program Budget'!F17 -> Month | C15: ='Program Budget'!H17 -> 1833.3333 | D15: ='Program Budget'!G17 -> 6 | E15: ='Program Budget'!E17 -> 0.2 | F15: =C15*D15*E15 -> 2200 | G15: =C15*1.05 -> 1925 | H15: ='Program Budget'!K17 -> 12 | I15: ='Program Budget'!J17 -> 0 | J15: =G15*H15*I15 -> 0 | K15: =G15*1.05 -> 2021.25 | L15: ='Program Budget'!N17 -> 12 | M15: ='Program Budget'!M17 -> 0 | N15: =K15*L15*M15 -> 0 | O15: =K15*1.05 -> 2122.3125 | P15: ='Program Budget'!Q17 -> 12 | Q15: ='Program Budget'!P17 -> 0 | R15: =O15*P15*Q15 -> 0 | S15: =O15*1.05 -> 2228.4281 | T15: ='Program Budget'!T17 -> 6 | U15: ='Program Budget'!S17 -> 0 | V15: =S15*T15*U15 -> 0 | W15: =F15+J15+N15+R15+V15 -> 2200
A16: ='Program Budget'!D18 -> Technical Specialist Component 2 | B16: ='Program Budget'!F18 -> Month | C16: ='Program Budget'!H18 -> 1833.3333 | D16: ='Program Budget'!G18 -> 6 | E16: ='Program Budget'!E18 -> 0.2 | F16: =C16*D16*E16 -> 2200 | G16: =C16*1.05 -> 1925 | H16: ='Program Budget'!K18 -> 12 | I16: ='Program Budget'!J18 -> 0 | J16: =G16*H16*I16 -> 0 | K16: =G16*1.05 -> 2021.25 | L16: ='Program Budget'!N18 -> 12 | M16: ='Program Budget'!M18 -> 0 | N16: =K16*L16*M16 -> 0 | O16: =K16*1.05 -> 2122.3125 | P16: ='Program Budget'!Q18 -> 12 | Q16: ='Program Budget'!P18 -> 0 | R16: =O16*P16*Q16 -> 0 | S16: =O16*1.05 -> 2228.4281 | T16: ='Program Budget'!T18 -> 6 | U16: ='Program Budget'!S18 -> 0 | V16: =S16*T16*U16 -> 0 | W16: =F16+J16+N16+R16+V16 -> 2200
A17: ='Program Budget'!D19 -> Technical Specialist Component 3 | B17: ='Program Budget'!F19 -> Month | C17: ='Program Budget'!H19 -> 1833.3333 | D17: ='Program Budget'!G19 -> 6 | E17: ='Program Budget'!E19 -> 0.2 | F17: =C17*D17*E17 -> 2200 | G17: =C17*1.05 -> 1925 | H17: ='Program Budget'!K19 -> 12 | I17: ='Program Budget'!J19 -> 0 | J17: =G17*H17*I17 -> 0 | K17: =G17*1.05 -> 2021.25 | L17: ='Program Budget'!N19 -> 12 | M17: ='Program Budget'!M19 -> 0 | N17: =K17*L17*M17 -> 0 | O17: =K17*1.05 -> 2122.3125 | P17: ='Program Budget'!Q19 -> 12 | Q17: ='Program Budget'!P19 -> 0 | R17: =O17*P17*Q17 -> 0 | S17: =O17*1.05 -> 2228.4281 | T17: ='Program Budget'!T19 -> 6 | U17: ='Program Budget'!S19 -> 0 | V17: =S17*T17*U17 -> 0 | W17: =F17+J17+N17+R17+V17 -> 2200 | AE17: 180 | AF17: 50-01-2-020 | AG17: DIR-USN (Expat) Labor
A18: ='Program Budget'!D20 -> Capacity Building Specialist (2) | B18: ='Program Budget'!F20 -> Month | C18: ='Program Budget'!H20 -> 3333.3333 | D18: ='Program Budget'!G20 -> 4 | E18: ='Program Budget'!E20 -> 0.2 | F18: =C18*D18*E18 -> 2666.6667 | G18: =C18*1.05 -> 3500 | H18: ='Program Budget'!K20 -> 12 | I18: ='Program Budget'!J20 -> 0 | J18: =G18*H18*I18 -> 0 | K18: =G18*1.05 -> 3675 | L18: ='Program Budget'!N20 -> 12 | M18: ='Program Budget'!M20 -> 0 | N18: =K18*L18*M18 -> 0 | O18: =K18*1.05 -> 3858.75 | P18: ='Program Budget'!Q20 -> 12 | Q18: ='Program Budget'!P20 -> 0 | R18: =O18*P18*Q18 -> 0 | S18: =O18*1.05 -> 4051.6875 | T18: ='Program Budget'!T20 -> 5 | U18: ='Program Budget'!S20 -> 0 | V18: =S18*T18*U18 -> 0 | W18: =F18+J18+N18+R18+V18 -> 2666.6667 | AE18: 180 | AF18: 50-01-2-020 | AG18: DIR-USN (Expat) Labor
A19: ='Program Budget'!D21 -> Sociocultural and Gender Specialist | B19: ='Program Budget'!F21 -> Month | C19: ='Program Budget'!H21 -> 1833.3333 | D19: ='Program Budget'!G21 -> 7 | E19: ='Program Budget'!E21 -> 0.25 | F19: =C19*D19*E19 -> 3208.3333 | G19: =C19*1.05 -> 1925 | H19: ='Program Budget'!K21 -> 12 | I19: ='Program Budget'!J21 -> 0 | J19: =G19*H19*I19 -> 0 | K19: =G19*1.05 -> 2021.25 | L19: ='Program Budget'!N21 -> 12 | M19: ='Program Budget'!M21 -> 0 | N19: =K19*L19*M19 -> 0 | O19: =K19*1.05 -> 2122.3125 | P19: ='Program Budget'!Q21 -> 12 | Q19: ='Program Budget'!P21 -> 0 | R19: =O19*P19*Q19 -> 0 | S19: =O19*1.05 -> 2228.4281 | T19: ='Program Budget'!T21 -> 9 | U19: ='Program Budget'!S21 -> 0 | V19: =S19*T19*U19 -> 0 | W19: =F19+J19+N19+R19+V19 -> 3208.3333
A20: ='Program Budget'!D22 -> Sociocultural and Gender Officers (3) | B20: ='Program Budget'!F22 -> Month | C20: ='Program Budget'!H22 -> 3750 | D20: ='Program Budget'!G22 -> 7 | E20: ='Program Budget'!E22 -> 0.25 | F20: =C20*D20*E20 -> 6562.5 | G20: =C20*1.05 -> 3937.5 | H20: ='Program Budget'!K22 -> 12 | I20: ='Program Budget'!J22 -> 0 | J20: =G20*H20*I20 -> 0 | K20: =G20*1.05 -> 4134.375 | L20: ='Program Budget'!N22 -> 12 | M20: ='Program Budget'!M22 -> 0 | N20: =K20*L20*M20 -> 0 | O20: =K20*1.05 -> 4341.0938 | P20: ='Program Budget'!Q22 -> 12 | Q20: ='Program Budget'!P22 -> 0 | R20: =O20*P20*Q20 -> 0 | S20: =O20*1.05 -> 4558.1484 | T20: ='Program Budget'!T22 -> 9 | U20: ='Program Budget'!S22 -> 0 | V20: =S20*T20*U20 -> 0 | W20: =F20+J20+N20+R20+V20 -> 6562.5
A21: ='Program Budget'!D23 -> Communications Specialists | B21: ='Program Budget'!F23 -> Month | C21: ='Program Budget'!H23 -> 1500 | D21: ='Program Budget'!G23 -> 7 | E21: ='Program Budget'!E23 -> 0.25 | F21: =C21*D21*E21 -> 2625 | G21: =C21*1.05 -> 1575 | H21: ='Program Budget'!K23 -> 12 | I21: ='Program Budget'!J23 -> 0.1 | J21: =G21*H21*I21 -> 1890 | K21: =G21*1.05 -> 1653.75 | L21: ='Program Budget'!N23 -> 12 | M21: ='Program Budget'!M23 -> 0.1 | N21: =K21*L21*M21 -> 1984.5 | O21: =K21*1.05 -> 1736.4375 | P21: ='Program Budget'!Q23 -> 12 | Q21: ='Program Budget'!P23 -> 0.1 | R21: =O21*P21*Q21 -> 2083.725 | S21: =O21*1.05 -> 1823.2594 | T21: ='Program Budget'!T23 -> 10 | U21: ='Program Budget'!S23 -> 0.1 | V21: =S21*T21*U21 -> 1823.2594 | W21: =F21+J21+N21+R21+V21 -> 10406.484
A22: ='Program Budget'!D24 -> M&E Director | B22: ='Program Budget'!F24 -> Month | C22: ='Program Budget'!H24 -> 3916.6667 | D22: ='Program Budget'!G24 -> 9 | E22: ='Program Budget'!E24 -> 0.25 | F22: =C22*D22*E22 -> 8812.5 | G22: =C22*1.05 -> 4112.5 | H22: ='Program Budget'!K24 -> 12 | I22: ='Program Budget'!J24 -> 0.1 | J22: =G22*H22*I22 -> 4935 | K22: =G22*1.05 -> 4318.125 | L22: ='Program Budget'!N24 -> 12 | M22: ='Program Budget'!M24 -> 0.1 | N22: =K22*L22*M22 -> 5181.75 | O22: =K22*1.05 -> 4534.0312 | P22: ='Program Budget'!Q24 -> 12 | Q22: ='Program Budget'!P24 -> 0.1 | R22: =O22*P22*Q22 -> 5440.8375 | S22: =O22*1.05 -> 4760.7328 | T22: ='Program Budget'!T24 -> 12 | U22: ='Program Budget'!S24 -> 0.1 | V22: =S22*T22*U22 -> 5712.8794 | W22: =F22+J22+N22+R22+V22 -> 30082.967 | AE22: 180 | AF22: 50-01-2-020 | AG22: DIR-USN (Expat) Labor
A23: ='Program Budget'!D25 -> M&E Specialist | B23: ='Program Budget'!F25 -> Month | C23: ='Program Budget'!H25 -> 1833.3333 | D23: ='Program Budget'!G25 -> 8 | E23: ='Program Budget'!E25 -> 0.25 | F23: =C23*D23*E23 -> 3666.6667 | G23: =C23*1.05 -> 1925 | H23: ='Program Budget'!K25 -> 12 | I23: ='Program Budget'!J25 -> 0.1 | J23: =G23*H23*I23 -> 2310 | K23: =G23*1.05 -> 2021.25 | L23: ='Program Budget'!N25 -> 12 | M23: ='Program Budget'!M25 -> 0.1 | N23: =K23*L23*M23 -> 2425.5 | O23: =K23*1.05 -> 2122.3125 | P23: ='Program Budget'!Q25 -> 12 | Q23: ='Program Budget'!P25 -> 0.1 | R23: =O23*P23*Q23 -> 2546.775 | S23: =O23*1.05 -> 2228.4281 | T23: ='Program Budget'!T25 -> 10 | U23: ='Program Budget'!S25 -> 0.1 | V23: =S23*T23*U23 -> 2228.4281 | W23: =F23+J23+N23+R23+V23 -> 13177.37 | AE23: 180 | AF23: 50-01-2-020 | AG23: DIR-USN (Expat) Labor
A24: ='Program Budget'!D26 -> Key Personnel: Finance Director | B24: ='Program Budget'!F26 -> Month | C24: ='Program Budget'!H26 -> 3916.6667 | D24: ='Program Budget'!G26 -> 11 | E24: ='Program Budget'!E26 -> 0.25 | F24: =C24*D24*E24 -> 10770.833 | G24: =C24*1.05 -> 4112.5 | H24: ='Program Budget'!K26 -> 12 | I24: ='Program Budget'!J26 -> 0.25 | J24: =G24*H24*I24 -> 12337.5 | K24: =G24*1.05 -> 4318.125 | L24: ='Program Budget'!N26 -> 12 | M24: ='Program Budget'!M26 -> 0.25 | N24: =K24*L24*M24 -> 12954.375 | O24: =K24*1.05 -> 4534.0312 | P24: ='Program Budget'!Q26 -> 12 | Q24: ='Program Budget'!P26 -> 0.25 | R24: =O24*P24*Q24 -> 13602.094 | S24: =O24*1.05 -> 4760.7328 | T24: ='Program Budget'!T26 -> 12 | U24: ='Program Budget'!S26 -> 0.25 | V24: =S24*T24*U24 -> 14282.198 | W24: =F24+J24+N24+R24+V24 -> 63947.001 | AE24: 180 | AF24: 50-01-2-020 | AG24: DIR-USN (Expat) Labor
A25: ='Program Budget'!D27 -> Contracts & Compliance Specialist | B25: ='Program Budget'!F27 -> Month | C25: ='Program Budget'!H27 -> 1833.3333 | D25: ='Program Budget'!G27 -> 9 | E25: ='Program Budget'!E27 -> 0.25 | F25: =C25*D25*E25 -> 4125 | G25: =C25*1.05 -> 1925 | H25: ='Program Budget'!K27 -> 12 | I25: ='Program Budget'!J27 -> 0.25 | J25: =G25*H25*I25 -> 5775 | K25: =G25*1.05 -> 2021.25 | L25: ='Program Budget'!N27 -> 12 | M25: ='Program Budget'!M27 -> 0.25 | N25: =K25*L25*M25 -> 6063.75 | O25: =K25*1.05 -> 2122.3125 | P25: ='Program Budget'!Q27 -> 12 | Q25: ='Program Budget'!P27 -> 0.25 | R25: =O25*P25*Q25 -> 6366.9375 | S25: =O25*1.05 -> 2228.4281 | T25: ='Program Budget'!T27 -> 12 | U25: ='Program Budget'!S27 -> 0.25 | V25: =S25*T25*U25 -> 6685.2844 | W25: =F25+J25+N25+R25+V25 -> 29015.972
A26: ='Program Budget'!D28 -> Grants & Procurement Officer (2) | B26: ='Program Budget'!F28 -> Month | C26: ='Program Budget'!H28 -> 2500 | D26: ='Program Budget'!G28 -> 9 | E26: ='Program Budget'!E28 -> 0.25 | F26: =C26*D26*E26 -> 5625 | G26: =C26*1.05 -> 2625 | H26: ='Program Budget'!K28 -> 12 | I26: ='Program Budget'!J28 -> 0.25 | J26: =G26*H26*I26 -> 7875 | K26: =G26*1.05 -> 2756.25 | L26: ='Program Budget'!N28 -> 12 | M26: ='Program Budget'!M28 -> 0.25 | N26: =K26*L26*M26 -> 8268.75 | O26: =K26*1.05 -> 2894.0625 | P26: ='Program Budget'!Q28 -> 12 | Q26: ='Program Budget'!P28 -> 0.25 | R26: =O26*P26*Q26 -> 8682.1875 | S26: =O26*1.05 -> 3038.7656 | T26: ='Program Budget'!T28 -> 12 | U26: ='Program Budget'!S28 -> 0.25 | V26: =S26*T26*U26 -> 9116.2969 | W26: =F26+J26+N26+R26+V26 -> 39567.234 | AE26: 180 | AF26: 50-01-2-020 | AG26: DIR-USN (Expat) Labor
A27: ='Program Budget'!D29 -> Accountant | B27: ='Program Budget'!F29 -> Month | C27: ='Program Budget'!H29 -> 1666.6667 | D27: ='Program Budget'!G29 -> 10 | E27: ='Program Budget'!E29 -> 0.25 | F27: =C27*D27*E27 -> 4166.6667 | G27: =C27*1.05 -> 1750 | H27: ='Program Budget'!K29 -> 12 | I27: ='Program Budget'!J29 -> 0.25 | J27: =G27*H27*I27 -> 5250 | K27: =G27*1.05 -> 1837.5 | L27: ='Program Budget'!N29 -> 12 | M27: ='Program Budget'!M29 -> 0.25 | N27: =K27*L27*M27 -> 5512.5 | O27: =K27*1.05 -> 1929.375 | P27: ='Program Budget'!Q29 -> 12 | Q27: ='Program Budget'!P29 -> 0.25 | R27: =O27*P27*Q27 -> 5788.125 | S27: =O27*1.05 -> 2025.8438 | T27: ='Program Budget'!T29 -> 11 | U27: ='Program Budget'!S29 -> 0.25 | V27: =S27*T27*U27 -> 5571.0703 | W27: =F27+J27+N27+R27+V27 -> 26288.362 | AE27: 180 | AF27: 50-01-2-020 | AG27: DIR-USN (Expat) Labor
A28: ='Program Budget'!D30 -> Administrative Officer | B28: ='Program Budget'!F30 -> Month | C28: ='Program Budget'!H30 -> 833.33333 | D28: ='Program Budget'!G30 -> 9 | E28: ='Program Budget'!E30 -> 0.25 | F28: =C28*D28*E28 -> 1875 | G28: =C28*1.05 -> 875 | H28: ='Program Budget'!K30 -> 12 | I28: ='Program Budget'!J30 -> 0.25 | J28: =G28*H28*I28 -> 2625 | K28: =G28*1.05 -> 918.75 | L28: ='Program Budget'!N30 -> 12 | M28: ='Program Budget'!M30 -> 0.25 | N28: =K28*L28*M28 -> 2756.25 | O28: =K28*1.05 -> 964.6875 | P28: ='Program Budget'!Q30 -> 12 | Q28: ='Program Budget'!P30 -> 0.25 | R28: =O28*P28*Q28 -> 2894.0625 | S28: =O28*1.05 -> 1012.9219 | T28: ='Program Budget'!T30 -> 10 | U28: ='Program Budget'!S30 -> 0.25 | V28: =S28*T28*U28 -> 2532.3047 | W28: =F28+J28+N28+R28+V28 -> 12682.617 | AE28: 180 | AF28: 50-01-2-020 | AG28: DIR-USN (Expat) Labor
A29: ='Program Budget'!D31 -> Human Resources Manager | B29: ='Program Budget'!F31 -> Month | C29: ='Program Budget'!H31 -> 2500 | D29: ='Program Budget'!G31 -> 11 | E29: ='Program Budget'!E31 -> 0.25 | F29: =C29*D29*E29 -> 6875 | G29: =C29*1.05 -> 2625 | H29: ='Program Budget'!K31 -> 12 | I29: ='Program Budget'!J31 -> 0.25 | J29: =G29*H29*I29 -> 7875 | K29: =G29*1.05 -> 2756.25 | L29: ='Program Budget'!N31 -> 12 | M29: ='Program Budget'!M31 -> 0.25 | N29: =K29*L29*M29 -> 8268.75 | O29: =K29*1.05 -> 2894.0625 | P29: ='Program Budget'!Q31 -> 12 | Q29: ='Program Budget'!P31 -> 0.25 | R29: =O29*P29*Q29 -> 8682.1875 | S29: =O29*1.05 -> 3038.7656 | T29: ='Program Budget'!T31 -> 12 | U29: ='Program Budget'!S31 -> 0.25 | V29: =S29*T29*U29 -> 9116.2969 | W29: =F29+J29+N29+R29+V29 -> 40817.234 | AE29: 180 | AF29: 50-01-2-020 | AG29: DIR-USN (Expat) Labor
A30: ='Program Budget'!D32 -> Driver (3 Individuals) | B30: ='Program Budget'!F32 -> Month | C30: ='Program Budget'!H32 -> 2250 | D30: ='Program Budget'!G32 -> 3 | E30: ='Program Budget'!E32 -> 0.1 | F30: =C30*D30*E30 -> 675 | G30: =C30*1.05 -> 2362.5 | H30: ='Program Budget'!K32 -> 12 | I30: ='Program Budget'!J32 -> 0.25 | J30: =G30*H30*I30 -> 7087.5 | K30: =G30*1.05 -> 2480.625 | L30: ='Program Budget'!N32 -> 12 | M30: ='Program Budget'!M32 -> 0.25 | N30: =K30*L30*M30 -> 7441.875 | O30: =K30*1.05 -> 2604.6562 | P30: ='Program Budget'!Q32 -> 12 | Q30: ='Program Budget'!P32 -> 0.25 | R30: =O30*P30*Q30 -> 7813.9688 | S30: =O30*1.05 -> 2734.8891 | T30: ='Program Budget'!T32 -> 9 | U30: ='Program Budget'!S32 -> 0.25 | V30: =S30*T30*U30 -> 6153.5004 | W30: =F30+J30+N30+R30+V30 -> 29171.844 | AE30: 180 | AF30: 50-01-2-020 | AG30: DIR-USN (Expat) Labor
A31: Total Local Salary Cost | F31: =SUM(F10:F30) -> 134629.17 | J31: =SUM(J10:J30) -> 74340 | N31: =SUM(N10:N30) -> 78057 | R31: =SUM(R10:R30) -> 81959.85 | V31: =SUM(V10:V30) -> 82183.416 | W31: =SUM(W10:W30) -> 451169.43
A32: HQ Staff
A33: ='Program Budget'!D34 -> Senior Program Director | B33: ='Program Budget'!F34 -> Month | C33: ='Program Budget'!H34 -> 11250 | D33: ='Program Budget'!G34 -> 12 | E33: ='Program Budget'!E34 -> 0.2 | F33: =C33*D33*E33 -> 27000 | G33: =C33*1.05 -> 11812.5 | H33: ='Program Budget'!K34 -> 12 | I33: ='Program Budget'!J34 -> 0.2 | J33: =G33*H33*I33 -> 28350 | K33: =G33*1.05 -> 12403.125 | L33: ='Program Budget'!N34 -> 12 | M33: ='Program Budget'!M34 -> 0.2 | N33: =K33*L33*M33 -> 29767.5 | O33: =K33*1.05 -> 13023.281 | P33: ='Program Budget'!Q34 -> 12 | Q33: ='Program Budget'!P34 -> 0.2 | R33: =O33*P33*Q33 -> 31255.875 | S33: =O33*1.05 -> 13674.445 | T33: ='Program Budget'!T34 -> 12 | U33: ='Program Budget'!S34 -> 0.2 | V33: =S33*T33*U33 -> 32818.669 | W33: =F33+J33+N33+R33+V33 -> 149192.04 | AE33: 180 | AF33: 50-01-2-020 | AG33: DIR-USN (Expat) Labor
A34: ='Program Budget'!D35 -> Associate Director | B34: ='Program Budget'!F35 -> Month | C34: ='Program Budget'!H35 -> 7500 | D34: ='Program Budget'!G35 -> 12 | E34: ='Program Budget'!E35 -> 1 | F34: =C34*D34*E34 -> 90000 | G34: =C34*1.05 -> 7875 | H34: ='Program Budget'!K35 -> 12 | I34: ='Program Budget'!J35 -> 1 | J34: =G34*H34*I34 -> 94500 | K34: =G34*1.05 -> 8268.75 | L34: ='Program Budget'!N35 -> 12 | M34: ='Program Budget'!M35 -> 1 | N34: =K34*L34*M34 -> 99225 | O34: =K34*1.05 -> 8682.1875 | P34: ='Program Budget'!Q35 -> 12 | Q34: ='Program Budget'!P35 -> 1 | R34: =O34*P34*Q34 -> 104186.25 | S34: =O34*1.05 -> 9116.2969 | T34: ='Program Budget'!T35 -> 12 | U34: ='Program Budget'!S35 -> 1 | V34: =S34*T34*U34 -> 109395.56 | W34: =F34+J34+N34+R34+V34 -> 497306.81 | AE34: 180 | AF34: 50-01-2-020 | AG34: DIR-USN (Expat) Labor
A35: Total HQ Staff | F35: =SUM(F33:F34) -> 117000 | J35: =SUM(J33:J34) -> 122850 | N35: =SUM(N33:N34) -> 128992.5 | R35: =SUM(R33:R34) -> 135442.12 | V35: =SUM(V33:V34) -> 142214.23 | W35: =+F35+J35+N35+R35+V35 -> 646498.86
A37: Subtotal: Salaries & Wages | F37: =F35+F31+F8 -> 251629.17 | J37: =J35+J31+J8 -> 197190 | N37: =N35+N31+N8 -> 207049.5 | R37: =R35+R31+R8 -> 217401.98 | V37: =V35+V31+V8 -> 224397.65 | W37: =+F37+J37+N37+R37+V37 -> 1097668.3
A38: Fringe
A39: USN/TCN Staff | F39: =C39*D39*E39 -> 0 | J39: =G39*H39*I39 -> 0 | N39: =K39*L39*M39 -> 0 | R39: =O39*P39*Q39 -> 0 | V39: =S39*T39*U39 -> 0 | W39: =F39+J39+N39+R39+V39 -> 0 | AE39: 194 | AF39: 50-03-0-020 | AG39: DIR-Allocated USN Fringe
A40: CCN Staff | B40: ='Program Budget'!F41 -> % | C40: =F31 -> 134629.17 | D40: 1 | E40: ='Program Budget'!H40 -> 0.455 | F40: =C40*D40*E40 -> 61256.271 | G40: =J31 -> 74340 | H40: 1 | I40: =E40 -> 0.455 | J40: =G40*H40*I40 -> 33824.7 | K40: =N31 -> 78057 | L40: 1 | M40: =I40 -> 0.455 | N40: =K40*L40*M40 -> 35515.935 | O40: =R31 -> 81959.85 | P40: 1 | Q40: =M40 -> 0.455 | R40: =O40*P40*Q40 -> 37291.732 | S40: =V31 -> 82183.416 | T40: 1 | U40: =Q40 -> 0.455 | V40: =S40*T40*U40 -> 37393.454 | W40: =F40+J40+N40+R40+V40 -> 205282.09 | AE40: 197 | AF40: 50-03-0-050 | AG40: DIR-CCN Fringe
A41: HQ Staff | B41: ='Program Budget'!#REF! -> #REF! | C41: =F35 -> 117000 | D41: 1 | E41: ='Program Budget'!H41 -> 0.2347 | F41: =C41*D41*E41 -> 27459.9 | G41: =J35 -> 122850 | H41: 1 | I41: =E41 -> 0.2347 | J41: =G41*H41*I41 -> 28832.895 | K41: =N35 -> 128992.5 | L41: 1 | M41: =I41 -> 0.2347 | N41: =K41*L41*M41 -> 30274.54 | O41: =R35 -> 135442.12 | P41: 1 | Q41: =M41 -> 0.2347 | R41: =O41*P41*Q41 -> 31788.267 | S41: =V35 -> 142214.23 | T41: 1 | U41: =Q41 -> 0.2347 | V41: =S41*T41*U41 -> 33377.68 | W41: =F41+J41+N41+R41+V41 -> 151733.28 | AE41: 193 | AF41: 50-03-0-010 | AG41: DIR-Allocated HQ Fringe
A42: Total: Fringe Benefits | F42: =+SUM(F39:F41) -> 88716.171 | J42: =+SUM(J39:J41) -> 62657.595 | N42: =+SUM(N39:N41) -> 65790.475 | R42: =+SUM(R39:R41) -> 69079.998 | V42: =+SUM(V39:V41) -> 70771.135 | W42: =+F42+J42+N42+R42+V42 -> 357015.37
A43: Allowances
A44: None | F44: =C44*D44*E44 -> 0 | J44: =G44*H44*I44 -> 0 | N44: =K44*L44*M44 -> 0 | R44: =O44*P44*Q44 -> 0 | V44: =S44*T44*U44 -> 0 | W44: =F44+J44+N44+R44+V44 -> 0
A45: Total: Allowances | F45: =SUM(F44:F44) -> 0 | J45: =SUM(J44:J44) -> 0 | N45: =SUM(N44:N44) -> 0 | R45: =SUM(R44:R44) -> 0 | V45: =SUM(V44:V44) -> 0 | W45: =F45+J45+N45+R45+V45 -> 0
A47: Subtotal: Benefits | F47: =F45+F42 -> 88716.171 | J47: =J45+J42 -> 62657.595 | N47: =N45+N42 -> 65790.475 | R47: =R45+R42 -> 69079.998 | V47: =V45+V42 -> 70771.135 | W47: =+F47+J47+N47+R47+V47 -> 357015.37 | AE47: 287 | AF47: 51-04-2-050 | AG47: DIR-Int Travel Other
A48: International Travel
A49: ='Program Budget'!D47 -> Airfare - DC-Tunisia - HQ Project Management Trip | B49: ='Program Budget'!F47 -> Trip | C49: ='Program Budget'!H47 -> 1400 | D49: ='Program Budget'!G47 -> 5 | E49: 1 | F49: =C49*D49*E49 -> 7000 | G49: =C49*1.07 -> 1498 | H49: ='Program Budget'!K47 -> 5 | I49: 1 | J49: =G49*H49*I49 -> 7490 | K49: =G49*1.07 -> 1602.86 | L49: ='Program Budget'!N47 -> 5 | M49: 1 | N49: =K49*L49*M49 -> 8014.3 | O49: =K49*1.07 -> 1715.0602 | P49: ='Program Budget'!Q47 -> 5 | Q49: 1 | R49: =O49*P49*Q49 -> 8575.301 | S49: =O49*1.07 -> 1835.1144 | T49: ='Program Budget'!T47 -> 5 | U49: 1 | V49: =S49*T49*U49 -> 9175.5721 | W49: =F49+J49+N49+R49+V49 -> 40255.173 | AE49: 180 | AF49: 50-01-2-020 | AG49: DIR-USN (Expat) Labor
A50: ='Program Budget'!D52 -> Airfare - Roundtrip - Tunisia to USA | B50: ='Program Budget'!F52 -> Trip | C50: ='Program Budget'!H52 -> 1400 | D50: ='Program Budget'!G52 -> 4 | E50: 1 | F50: =C50*D50*E50 -> 5600 | G50: =C50*1.07 -> 1498 | H50: ='Program Budget'!K52 -> 4 | I50: 1 | J50: =G50*H50*I50 -> 5992 | K50: =G50*1.07 -> 1602.86 | L50: ='Program Budget'!N52 -> 4 | M50: 1 | N50: =K50*L50*M50 -> 6411.44 | O50: =K50*1.07 -> 1715.0602 | P50: ='Program Budget'!Q52 -> 4 | Q50: 1 | R50: =O50*P50*Q50 -> 6860.2408 | S50: =O50*1.07 -> 1835.1144 | T50: ='Program Budget'!T52 -> 4 | U50: 1 | V50: =S50*T50*U50 -> 7340.4577 | W50: =F50+J50+N50+R50+V50 -> 32204.138 | AE50: 180 | AF50: 50-01-2-020 | AG50: DIR-USN (Expat) Labor
A51: Local Travel
A52: ='Program Budget'!D49 -> Ground Transportation – HQ Project Management Trip | B52: ='Program Budget'!F49 -> Trip | C52: ='Program Budget'!H49 -> 150 | D52: ='Program Budget'!G49 -> 5 | E52: 1 | F52: =C52*D52*E52 -> 750 | G52: =C52*1.07 -> 160.5 | H52: ='Program Budget'!K49 -> 5 | I52: 1 | J52: =G52*H52*I52 -> 802.5 | K52: =G52*1.07 -> 171.735 | L52: ='Program Budget'!N49 -> 5 | M52: 1 | N52: =K52*L52*M52 -> 858.675 | O52: =K52*1.07 -> 183.75645 | P52: ='Program Budget'!Q49 -> 5 | Q52: 1 | R52: =O52*P52*Q52 -> 918.78225 | S52: =O52*1.07 -> 196.6194 | T52: ='Program Budget'!T49 -> 5 | U52: 1 | V52: =S52*T52*U52 -> 983.09701 | W52: =F52+J52+N52+R52+V52 -> 4313.0543 | AE52: 180 | AF52: 50-01-2-020 | AG52: DIR-USN (Expat) Labor
A53: ='Program Budget'!D54 -> Ground Transportation for Tunisia Staff Travel | B53: ='Program Budget'!F58 -> Trip | C53: ='Program Budget'!H54 -> 150 | D53: ='Program Budget'!G54 -> 4 | E53: 1 | F53: =C53*D53*E53 -> 600 | G53: =C53*1.07 -> 160.5 | H53: ='Program Budget'!K54 -> 4 | I53: 1 | J53: =G53*H53*I53 -> 642 | K53: =G53*1.07 -> 171.735 | L53: ='Program Budget'!N54 -> 4 | M53: 1 | N53: =K53*L53*M53 -> 686.94 | O53: =K53*1.07 -> 183.75645 | P53: ='Program Budget'!Q54 -> 4 | Q53: 1 | R53: =O53*P53*Q53 -> 735.0258 | S53: =O53*1.07 -> 196.6194 | T53: ='Program Budget'!T54 -> 4 | U53: 1 | V53: =S53*T53*U53 -> 786.47761 | W53: =F53+J53+N53+R53+V53 -> 3450.4434 | AE53: 180 | AF53: 50-01-2-020 | AG53: DIR-USN (Expat) Labor
A54: ='Program Budget'!D58 -> Local Transportation (Car Rental, Taxis) – Training, M&E, & Data Collection | B54: ='Program Budget'!F58 -> Trip | C54: ='Program Budget'!H58 -> 100 | D54: ='Program Budget'!G58 -> 36 | E54: 1 | F54: =C54*D54*E54 -> 3600 | G54: =C54*1.07 -> 107 | H54: ='Program Budget'!K58 -> 36 | I54: 1 | J54: =G54*H54*I54 -> 3852 | K54: =G54*1.07 -> 114.49 | L54: ='Program Budget'!N58 -> 36 | M54: 1 | N54: =K54*L54*M54 -> 4121.64 | O54: =K54*1.07 -> 122.5043 | P54: ='Program Budget'!Q58 -> 36 | Q54: 1 | R54: =O54*P54*Q54 -> 4410.1548 | S54: =O54*1.07 -> 131.0796 | T54: ='Program Budget'!T58 -> 36 | U54: 1 | V54: =S54*T54*U54 -> 4718.8656 | W54: =F54+J54+N54+R54+V54 -> 20702.66 | AE54: 180 | AF54: 50-01-2-020 | AG54: DIR-USN (Expat) Labor
A55: Vehicle Fuel
A56: ='Program Budget'!D57 -> Vehicle Fuel Expense (for Field Office Vehicles) | B56: ='Program Budget'!F57 -> Month | C56: ='Program Budget'!H57 -> 450 | D56: ='Program Budget'!G57 -> 3 | E56: 1 | F56: =C56*D56*E56 -> 1350 | G56: =C56*1.07 -> 481.5 | H56: ='Program Budget'!K57 -> 12 | I56: 1 | J56: =G56*H56*I56 -> 5778 | K56: =G56*1.07 -> 515.205 | L56: ='Program Budget'!N57 -> 12 | M56: 1 | N56: =K56*L56*M56 -> 6182.46 | O56: =K56*1.07 -> 551.26935 | P56: ='Program Budget'!Q57 -> 12 | Q56: 1 | R56: =O56*P56*Q56 -> 6615.2322 | S56: =O56*1.07 -> 589.8582 | T56: ='Program Budget'!T57 -> 9 | U56: 1 | V56: =S56*T56*U56 -> 5308.7238 | W56: =F56+J56+N56+R56+V56 -> 25234.416 | AE56: 180 | AF56: 50-01-2-020 | AG56: DIR-USN (Expat) Labor
A57: Per Diem & Lodging
A58: ='Program Budget'!D48 -> Lodging and M&IE - HQ Project Management Trip | B58: ='Program Budget'!F48 -> Day | C58: ='Program Budget'!H48 -> 212 | D58: ='Program Budget'!G48 -> 35 | E58: 1 | F58: =C58*D58*E58 -> 7420 | G58: =C58*1.07 -> 226.84 | H58: ='Program Budget'!K48 -> 35 | I58: 1 | J58: =G58*H58*I58 -> 7939.4 | K58: =G58*1.07 -> 242.7188 | L58: ='Program Budget'!N48 -> 35 | M58: 1 | N58: =K58*L58*M58 -> 8495.158 | O58: =K58*1.07 -> 259.70912 | P58: ='Program Budget'!Q48 -> 35 | Q58: 1 | R58: =O58*P58*Q58 -> 9089.8191 | S58: =O58*1.07 -> 277.88875 | T58: ='Program Budget'!T48 -> 35 | U58: 1 | V58: =S58*T58*U58 -> 9726.1064 | W58: =F58+J58+N58+R58+V58 -> 42670.483 | AE58: 180 | AF58: 50-01-2-020 | AG58: DIR-USN (Expat) Labor
A59: ='Program Budget'!D50 -> Other Travel Related Expenses – HQ Project Management Trip | B59: ='Program Budget'!F50 -> Trip | C59: ='Program Budget'!H50 -> 50 | D59: ='Program Budget'!G50 -> 5 | E59: 1 | F59: =C59*D59*E59 -> 250 | G59: =C59*1.07 -> 53.5 | H59: ='Program Budget'!K50 -> 5 | I59: 1 | J59: =G59*H59*I59 -> 267.5 | K59: =G59*1.07 -> 57.245 | L59: ='Program Budget'!N50 -> 5 | M59: 1 | N59: =K59*L59*M59 -> 286.225 | O59: =K59*1.07 -> 61.25215 | P59: ='Program Budget'!Q50 -> 5 | Q59: 1 | R59: =O59*P59*Q59 -> 306.26075 | S59: =O59*1.07 -> 65.539801 | T59: ='Program Budget'!T50 -> 5 | U59: 1 | V59: =S59*T59*U59 -> 327.699 | W59: =F59+J59+N59+R59+V59 -> 1437.6848 | AE59: 180 | AF59: 50-01-2-020 | AG59: DIR-USN (Expat) Labor
A60: ='Program Budget'!D53 -> Lodging and M&IE for Tunisia Staff Travel | B60: ='Program Budget'!F53 -> Day | C60: ='Program Budget'!H53 -> 251 | D60: ='Program Budget'!G53 -> 28 | E60: 1 | F60: =C60*D60*E60 -> 7028 | G60: =C60*1.07 -> 268.57 | H60: ='Program Budget'!K53 -> 28 | I60: 1 | J60: =G60*H60*I60 -> 7519.96 | K60: =G60*1.07 -> 287.3699 | L60: ='Program Budget'!N53 -> 28 | M60: 1 | N60: =K60*L60*M60 -> 8046.3572 | O60: =K60*1.07 -> 307.48579 | P60: ='Program Budget'!Q53 -> 28 | Q60: 1 | R60: =O60*P60*Q60 -> 8609.6022 | S60: =O60*1.07 -> 329.0098 | T60: ='Program Budget'!T53 -> 28 | U60: 1 | V60: =S60*T60*U60 -> 9212.2744 | W60: =F60+J60+N60+R60+V60 -> 40416.194 | AE60: 180 | AF60: 50-01-2-020 | AG60: DIR-USN (Expat) Labor
A61: ='Program Budget'!D55 -> Other Travel Related Expenses for Tunisia Staff Travel | B61: ='Program Budget'!F55 -> Trip | C61: ='Program Budget'!H55 -> 50 | D61: ='Program Budget'!G55 -> 4 | E61: 1 | F61: =C61*D61*E61 -> 200 | G61: =C61*1.07 -> 53.5 | H61: ='Program Budget'!K55 -> 4 | I61: 1 | J61: =G61*H61*I61 -> 214 | K61: =G61*1.07 -> 57.245 | L61: ='Program Budget'!N55 -> 4 | M61: 1 | N61: =K61*L61*M61 -> 228.98 | O61: =K61*1.07 -> 61.25215 | P61: ='Program Budget'!Q55 -> 4 | Q61: 1 | R61: =O61*P61*Q61 -> 245.0086 | S61: =O61*1.07 -> 65.539801 | T61: ='Program Budget'!T55 -> 4 | U61: 1 | V61: =S61*T61*U61 -> 262.1592 | W61: =F61+J61+N61+R61+V61 -> 1150.1478 | AE61: 180 | AF61: 50-01-2-020 | AG61: DIR-USN (Expat) Labor
A62: ='Program Budget'!D59 -> Lodging and M&IE - Training, M&E, & Data Collection | B62: ='Program Budget'!F59 -> Day | C62: ='Program Budget'!H59 -> 129 | D62: ='Program Budget'!G59 -> 144 | E62: 1 | F62: =C62*D62*E62 -> 18576 | G62: =C62*1.07 -> 138.03 | H62: ='Program Budget'!K59 -> 144 | I62: 1 | J62: =G62*H62*I62 -> 19876.32 | K62: =G62*1.07 -> 147.6921 | L62: ='Program Budget'!N59 -> 144 | M62: 1 | N62: =K62*L62*M62 -> 21267.662 | O62: =K62*1.07 -> 158.03055 | P62: ='Program Budget'!Q59 -> 144 | Q62: 1 | R62: =O62*P62*Q62 -> 22756.399 | S62: =O62*1.07 -> 169.09269 | T62: ='Program Budget'!T59 -> 144 | U62: 1 | V62: =S62*T62*U62 -> 24349.347 | W62: =F62+J62+N62+R62+V62 -> 106825.73 | AE62: 180 | AF62: 50-01-2-020 | AG62: DIR-USN (Expat) Labor
A64: Subtotal: Travel | F64: =SUM(F48:F63) -> 52374 | J64: =SUM(J48:J63) -> 60373.68 | N64: =SUM(N48:N63) -> 64599.838 | R64: =SUM(R48:R63) -> 69121.826 | V64: =SUM(V48:V63) -> 72190.779 | W64: =+F64+J64+N64+R64+V64 -> 318660.12
A65: Professional Services
A66: ='Program Budget'!D63 -> Monetization Agent Fee | B66: ='Program Budget'!F63 -> % | C66: =15157714 -> 15157714 | D66: 1 | E66: 0.0167 | F66: =C66*D66*E66 -> 253133.82 | G66: 0 | H66: 0 | I66: 0 | J66: =G66*H66*I66 -> 0 | K66: =G66 -> 0 | L66: ='Program Budget'!N63 -> 0 | M66: 0 | N66: =K66*L66*M66 -> 0 | O66: =K66 -> 0 | P66: ='Program Budget'!Q63 -> 0 | Q66: 0 | R66: =O66*P66*Q66 -> 0 | S66: =O66 -> 0 | T66: ='Program Budget'!T63 -> 0 | U66: 0 | V66: =S66*T66*U66 -> 0 | W66: =F66+J66+N66+R66+V66 -> 253133.82
A67: ='Program Budget'!D64 -> Monetization Impact Assessment | B67: ='Program Budget'!F64 -> Unit | C67: ='Program Budget'!H64 -> 60000 | D67: ='Program Budget'!G64 -> 0 | E67: 1 | F67: =C67*D67*E67 -> 0 | G67: =C67 -> 60000 | H67: ='Program Budget'!K64 -> 1 | I67: 1 | J67: =G67*H67*I67 -> 60000 | K67: =G67 -> 60000 | L67: ='Program Budget'!N64 -> 0 | M67: 0 | N67: =K67*L67*M67 -> 0 | O67: =K67 -> 60000 | P67: ='Program Budget'!Q64 -> 0 | Q67: 0 | R67: =O67*P67*Q67 -> 0 | S67: =O67 -> 60000 | T67: ='Program Budget'!T64 -> 0 | U67: 0 | V67: =S67*T67*U67 -> 0 | W67: =F67+J67+N67+R67+V67 -> 60000
A68: ='Program Budget'!D65 -> Local Program Audit Costs | B68: ='Program Budget'!F65 -> Year | C68: ='Program Budget'!H65 -> 1500 | D68: ='Program Budget'!G65 -> 1 | E68: 1 | F68: =C68*D68*E68 -> 1500 | G68: =C68 -> 1500 | H68: ='Program Budget'!K65 -> 1 | I68: 1 | J68: =G68*H68*I68 -> 1500 | K68: =G68 -> 1500 | L68: ='Program Budget'!N65 -> 1 | M68: 1 | N68: =K68*L68*M68 -> 1500 | O68: =K68 -> 1500 | P68: ='Program Budget'!Q65 -> 1 | Q68: 1 | R68: =O68*P68*Q68 -> 1500 | S68: =O68 -> 1500 | T68: ='Program Budget'!T65 -> 1 | U68: 1 | V68: =S68*T68*U68 -> 1500 | W68: =F68+J68+N68+R68+V68 -> 7500
A69: ='Program Budget'!D66 -> Legal & Registration Fees | B69: ='Program Budget'!F66 -> Year | C69: ='Program Budget'!H66 -> 4500 | D69: ='Program Budget'!G66 -> 1 | E69: 1 | F69: =C69*D69*E69 -> 4500 | G69: =C69 -> 4500 | H69: ='Program Budget'!K66 -> 1 | I69: 1 | J69: =G69*H69*I69 -> 4500 | K69: =G69 -> 4500 | L69: ='Program Budget'!N66 -> 1 | M69: 1 | N69: =K69*L69*M69 -> 4500 | O69: =K69 -> 4500 | P69: ='Program Budget'!Q66 -> 1 | Q69: 1 | R69: =O69*P69*Q69 -> 4500 | S69: =O69 -> 4500 | T69: ='Program Budget'!T66 -> 1 | U69: 1 | V69: =S69*T69*U69 -> 4500 | W69: =F69+J69+N69+R69+V69 -> 22500
A70: ='Program Budget'!D67 -> Security Services, Risk Assessments, & Security Assessment | B70: ='Program Budget'!F67 -> Year | C70: ='Program Budget'!H67 -> 500 | D70: ='Program Budget'!G67 -> 1 | E70: 1 | F70: =C70*D70*E70 -> 500 | G70: =C70 -> 500 | H70: ='Program Budget'!K67 -> 1 | I70: 1 | J70: =G70*H70*I70 -> 500 | K70: =G70 -> 500 | L70: ='Program Budget'!N67 -> 1 | M70: 1 | N70: =K70*L70*M70 -> 500 | O70: =K70 -> 500 | P70: ='Program Budget'!Q67 -> 1 | Q70: 1 | R70: =O70*P70*Q70 -> 500 | S70: =O70 -> 500 | T70: ='Program Budget'!T67 -> 1 | U70: 1 | V70: =S70*T70*U70 -> 500 | W70: =F70+J70+N70+R70+V70 -> 2500
A71: ='Program Budget'!D68 -> Short-Term Technical Advisors | B71: ='Program Budget'!F68 -> Month | C71: ='Program Budget'!H68 -> 3500 | D71: ='Program Budget'!G68 -> 9 | E71: 1 | F71: =C71*D71*E71 -> 31500 | G71: =C71 -> 3500 | H71: ='Program Budget'!K68 -> 12 | I71: 1 | J71: =G71*H71*I71 -> 42000 | K71: =G71 -> 3500 | L71: ='Program Budget'!N68 -> 12 | M71: 1 | N71: =K71*L71*M71 -> 42000 | O71: =K71 -> 3500 | P71: ='Program Budget'!Q68 -> 12 | Q71: 1 | R71: =O71*P71*Q71 -> 42000 | S71: =O71 -> 3500 | T71: ='Program Budget'!T68 -> 9 | U71: 1 | V71: =S71*T71*U71 -> 31500 | W71: =F71+J71+N71+R71+V71 -> 189000 | AE71: 670 | AF71: 61-01-1-003 | AG71: DIR_Sub-AW (No Fee)
A72: ='Program Budget'!D69 -> Start-up Consultant | B72: ='Program Budget'!F69 -> Day | C72: ='Program Budget'!H69 -> 520 | D72: ='Program Budget'!G69 -> 50 | E72: 1 | F72: =C72*D72*E72 -> 26000 | G72: =C72 -> 520 | H72: ='Program Budget'!K69 -> 0 | I72: 0 | J72: =G72*H72*I72 -> 0 | K72: =G72 -> 520 | L72: ='Program Budget'!N69 -> 0 | M72: 0 | N72: =K72*L72*M72 -> 0 | O72: =K72 -> 520 | P72: ='Program Budget'!Q69 -> 0 | Q72: 0 | R72: =O72*P72*Q72 -> 0 | S72: =O72 -> 520 | T72: ='Program Budget'!T69 -> 0 | U72: 0 | V72: =S72*T72*U72 -> 0 | W72: =F72+J72+N72+R72+V72 -> 26000 | AE72: 670 | AF72: 61-01-1-003 | AG72: DIR_Sub-AW (No Fee)
A73: ='Program Budget'!D71 -> Evaluations
A74: ='Program Budget'!D72 -> Baseline Evaluation | B74: ='Program Budget'!F72 -> Unit | C74: ='Program Budget'!H72 -> 150000 | D74: ='Program Budget'!G72 -> 1 | E74: 1 | F74: =C74*D74*E74 -> 150000 | G74: =C74 -> 150000 | H74: ='Program Budget'!K72 -> 0 | I74: 0 | J74: =G74*H74*I74 -> 0 | K74: =G74 -> 150000 | L74: ='Program Budget'!N72 -> 0 | M74: 0 | N74: =K74*L74*M74 -> 0 | O74: =K74 -> 150000 | P74: ='Program Budget'!Q72 -> 0 | Q74: 0 | R74: =O74*P74*Q74 -> 0 | S74: =O74 -> 150000 | T74: ='Program Budget'!T72 -> 0 | U74: 0 | V74: =S74*T74*U74 -> 0 | W74: =F74+J74+N74+R74+V74 -> 150000
A75: ='Program Budget'!D73 -> Midterm Evaluation | B75: ='Program Budget'!F73 -> Unit | C75: ='Program Budget'!H73 -> 170000 | D75: ='Program Budget'!G73 -> 0 | E75: 0 | F75: =C75*D75*E75 -> 0 | G75: =C75 -> 170000 | H75: ='Program Budget'!K73 -> 0 | I75: 0 | J75: =G75*H75*I75 -> 0 | K75: =G75 -> 170000 | L75: ='Program Budget'!N73 -> 1 | M75: 1 | N75: =K75*L75*M75 -> 170000 | O75: =K75 -> 170000 | P75: ='Program Budget'!Q73 -> 0 | Q75: 0 | R75: =O75*P75*Q75 -> 0 | S75: =O75 -> 170000 | T75: ='Program Budget'!T73 -> 0 | U75: 0 | V75: =S75*T75*U75 -> 0 | W75: =F75+J75+N75+R75+V75 -> 170000
A76: ='Program Budget'!D74 -> Final Evaluation | B76: ='Program Budget'!F74 -> Unit | C76: ='Program Budget'!H74 -> 180000 | D76: ='Program Budget'!G74 -> 0 | E76: 0 | F76: =C76*D76*E76 -> 0 | G76: =C76 -> 180000 | H76: ='Program Budget'!K74 -> 0 | I76: 0 | J76: =G76*H76*I76 -> 0 | K76: =G76 -> 180000 | L76: ='Program Budget'!N74 -> 0 | M76: 0 | N76: =K76*L76*M76 -> 0 | O76: =K76 -> 180000 | P76: ='Program Budget'!Q74 -> 0 | Q76: 0 | R76: =O76*P76*Q76 -> 0 | S76: =O76 -> 180000 | T76: ='Program Budget'!T74 -> 1 | U76: 1 | V76: =S76*T76*U76 -> 180000 | W76: =F76+J76+N76+R76+V76 -> 180000
A77: ='Program Budget'!D75 -> Special Studies on Carbon Assessment and Living Incomes | B77: ='Program Budget'!F75 -> Unit | C77: ='Program Budget'!H75 -> 280000 | D77: ='Program Budget'!G75 -> 0 | E77: 0 | F77: =C77*D77*E77 -> 0 | G77: =C77 -> 280000 | H77: ='Program Budget'!K75 -> 0.5 | I77: 1 | J77: =G77*H77*I77 -> 140000 | K77: =G77 -> 280000 | L77: ='Program Budget'!N75 -> 0.5 | M77: 1 | N77: =K77*L77*M77 -> 140000 | O77: =K77 -> 280000 | P77: ='Program Budget'!Q75 -> 0 | Q77: 0 | R77: =O77*P77*Q77 -> 0 | S77: =O77 -> 280000 | T77: ='Program Budget'!T75 -> 0 | U77: 0 | V77: =S77*T77*U77 -> 0 | W77: =F77+J77+N77+R77+V77 -> 280000
A78: ='Program Budget'!D76 -> Conduct Rapid Complementary Cost-Benefit Analysis | B78: ='Program Budget'!F76 -> Unit | C78: ='Program Budget'!H76 -> 45000 | D78: ='Program Budget'!G76 -> 1 | E78: 1 | F78: =C78*D78*E78 -> 45000 | G78: =C78 -> 45000 | H78: ='Program Budget'!K76 -> 0 | I78: 0 | J78: =G78*H78*I78 -> 0 | K78: =G78 -> 45000 | L78: ='Program Budget'!N76 -> 0 | M78: 0 | N78: =K78*L78*M78 -> 0 | O78: =K78 -> 45000 | P78: ='Program Budget'!Q76 -> 0 | Q78: 0 | R78: =O78*P78*Q78 -> 0 | S78: =O78 -> 45000 | T78: ='Program Budget'!T76 -> 0 | U78: 0 | V78: =S78*T78*U78 -> 0 | W78: =F78+J78+N78+R78+V78 -> 45000
A79: ='Program Budget'!D77 -> Monitoring Guidelines Development
A80: ='Program Budget'!D78 -> Monitoring Guidelines Creation, Translation & Printing | B80: ='Program Budget'!F78 -> Document | C80: ='Program Budget'!H78 -> 8000 | D80: ='Program Budget'!G78 -> 1 | E80: 1 | F80: =C80*D80*E80 -> 8000 | G80: =C80 -> 8000 | H80: ='Program Budget'!K78 -> 0 | I80: 0 | J80: =G80*H80*I80 -> 0 | K80: =G80 -> 8000 | L80: ='Program Budget'!N78 -> 0 | M80: 0 | N80: =K80*L80*M80 -> 0 | O80: =K80 -> 8000 | P80: ='Program Budget'!Q78 -> 0 | Q80: 0 | R80: =O80*P80*Q80 -> 0 | S80: =O80 -> 8000 | T80: ='Program Budget'!T78 -> 0 | U80: 0 | V80: =S80*T80*U80 -> 0 | W80: =F80+J80+N80+R80+V80 -> 8000
A81: ='Program Budget'!D79 -> Monitoring Guidelines Revision, Translation & Printing | B81: ='Program Budget'!F79 -> Year | C81: ='Program Budget'!H79 -> 2000 | D81: ='Program Budget'!G79 -> 0 | E81: 0 | F81: =C81*D81*E81 -> 0 | G81: =C81 -> 2000 | H81: ='Program Budget'!K79 -> 1 | I81: 1 | J81: =G81*H81*I81 -> 2000 | K81: =G81 -> 2000 | L81: ='Program Budget'!N79 -> 1 | M81: 1 | N81: =K81*L81*M81 -> 2000 | O81: =K81 -> 2000 | P81: ='Program Budget'!Q79 -> 1 | Q81: 1 | R81: =O81*P81*Q81 -> 2000 | S81: =O81 -> 2000 | T81: ='Program Budget'!T79 -> 1 | U81: 1 | V81: =S81*T81*U81 -> 2000 | W81: =F81+J81+N81+R81+V81 -> 8000
A82: ='Program Budget'!D80 -> Monitoring Guidelines Staff Training on Indicators and Data Collection/Analysis | B82: ='Program Budget'!F80 -> Workshop | C82: ='Program Budget'!H80 -> 6000 | D82: ='Program Budget'!G80 -> 1 | E82: 1 | F82: =C82*D82*E82 -> 6000 | G82: =C82 -> 6000 | H82: ='Program Budget'!K80 -> 1 | I82: 1 | J82: =G82*H82*I82 -> 6000 | K82: =G82 -> 6000 | L82: ='Program Budget'!N80 -> 1 | M82: 1 | N82: =K82*L82*M82 -> 6000 | O82: =K82 -> 6000 | P82: ='Program Budget'!Q80 -> 1 | Q82: 1 | R82: =O82*P82*Q82 -> 6000 | S82: =O82 -> 6000 | T82: ='Program Budget'!T80 -> 1 | U82: 1 | V82: =S82*T82*U82 -> 6000 | W82: =F82+J82+N82+R82+V82 -> 30000
A83: ='Program Budget'!D81 -> M&E Database
A84: ='Program Budget'!D82 -> M&E Database Trainings | B84: ='Program Budget'!F82 -> Year | C84: ='Program Budget'!H82 -> 500 | D84: ='Program Budget'!G82 -> 1 | E84: 1 | F84: =C84*D84*E84 -> 500 | G84: =C84 -> 500 | H84: ='Program Budget'!K82 -> 1 | I84: 1 | J84: =G84*H84*I84 -> 500 | K84: =G84 -> 500 | L84: ='Program Budget'!N82 -> 1 | M84: 1 | N84: =K84*L84*M84 -> 500 | O84: =K84 -> 500 | P84: ='Program Budget'!Q82 -> 1 | Q84: 1 | R84: =O84*P84*Q84 -> 500 | S84: =O84 -> 500 | T84: ='Program Budget'!T82 -> 1 | U84: 1 | V84: =S84*T84*U84 -> 500 | W84: =F84+J84+N84+R84+V84 -> 2500
A85: ='Program Budget'!D83 -> M&E Database Platform Subscription and Customization | B85: ='Program Budget'!F83 -> Year | C85: ='Program Budget'!H83 -> 15000 | D85: ='Program Budget'!G83 -> 1 | E85: 1 | F85: =C85*D85*E85 -> 15000 | G85: =C85 -> 15000 | H85: ='Program Budget'!K83 -> 1 | I85: 1 | J85: =G85*H85*I85 -> 15000 | K85: =G85 -> 15000 | L85: ='Program Budget'!N83 -> 1 | M85: 1 | N85: =K85*L85*M85 -> 15000 | O85: =K85 -> 15000 | P85: ='Program Budget'!Q83 -> 1 | Q85: 1 | R85: =O85*P85*Q85 -> 15000 | S85: =O85 -> 15000 | T85: ='Program Budget'!T83 -> 1 | U85: 1 | V85: =S85*T85*U85 -> 15000 | W85: =F85+J85+N85+R85+V85 -> 75000
AE86: 319 | AF86: 51-08-1-004 | AG86: DIR-Office Utilities
A87: Subtotal: Professional Services/Contractual | F87: =SUM(F66:F86) -> 541633.82 | J87: =SUM(J66:J86) -> 272000 | N87: =SUM(N66:N86) -> 382000 | R87: =SUM(R66:R86) -> 72000 | V87: =SUM(V66:V86) -> 241500 | W87: =+F87+J87+N87+R87+V87 -> 1509133.8
A88: Equipment (>$5000/unit)
A89: ='Program Budget'!D89 -> Vehicles for Field Office | B89: ='Program Budget'!F89 -> Unit | C89: ='Program Budget'!H89 -> 60000 | D89: ='Program Budget'!G89 -> 3 | E89: 1 | F89: =C89*D89*E89 -> 180000 | G89: =C89 -> 60000 | H89: ='Program Budget'!K89 -> 0 | I89: 0 | J89: =G89*H89*I89 -> 0 | K89: =G89 -> 60000 | L89: ='Program Budget'!N89 -> 0 | M89: 0 | N89: =K89*L89*M89 -> 0 | O89: =K89 -> 60000 | P89: ='Program Budget'!Q89 -> 0 | Q89: 0 | R89: =O89*P89*Q89 -> 0 | S89: =O89 -> 60000 | T89: ='Program Budget'!T89 -> 0 | U89: 0 | V89: =S89*T89*U89 -> 0 | W89: =F89+J89+N89+R89+V89 -> 180000
AE90: 297 | AF90: 51-05-1-002 | AG90: DIR-Office Equipment
A91: Subtotal: Equipment | F91: =SUM(F89:F90) -> 180000 | J91: =SUM(J89:J90) -> 0 | N91: =SUM(N89:N90) -> 0 | R91: =SUM(R89:R90) -> 0 | V91: =SUM(V89:V90) -> 0 | W91: =+F91+J91+N91+R91+V91 -> 180000
A92: Office
A93: ='Program Budget'!D95 -> Communications Costs (Internet, Phone, Data) (Tunis) | B93: ='Program Budget'!F95 -> Month | C93: ='Program Budget'!H95 -> 350 | D93: ='Program Budget'!G95 -> 3 | E93: 1 | F93: =C93*D93*E93 -> 1050 | G93: =C93*1.07 -> 374.5 | H93: ='Program Budget'!K95 -> 12 | I93: 1 | J93: =G93*H93*I93 -> 4494 | K93: =G93*1.07 -> 400.715 | L93: ='Program Budget'!N95 -> 12 | M93: 1 | N93: =K93*L93*M93 -> 4808.58 | O93: =K93*1.07 -> 428.76505 | P93: ='Program Budget'!Q95 -> 12 | Q93: 1 | R93: =O93*P93*Q93 -> 5145.1806 | S93: =O93*1.07 -> 458.7786 | T93: ='Program Budget'!T95 -> 6 | U93: 1 | V93: =S93*T93*U93 -> 2752.6716 | W93: =F93+J93+N93+R93+V93 -> 18250.432
A94: ='Program Budget'!D96 -> Office Rent, Utilities & Cleaning (Tunis) (Furnished) (Coworking Space, rental price includes all costs) | B94: ='Program Budget'!F96 -> Month | C94: ='Program Budget'!H96 -> 3500 | D94: ='Program Budget'!G96 -> 3 | E94: 1 | F94: =C94*D94*E94 -> 10500 | G94: =C94*1.07 -> 3745 | H94: ='Program Budget'!K96 -> 12 | I94: 1 | J94: =G94*H94*I94 -> 44940 | K94: =G94*1.07 -> 4007.15 | L94: ='Program Budget'!N96 -> 12 | M94: 1 | N94: =K94*L94*M94 -> 48085.8 | O94: =K94*1.07 -> 4287.6505 | P94: ='Program Budget'!Q96 -> 12 | Q94: 1 | R94: =O94*P94*Q94 -> 51451.806 | S94: =O94*1.07 -> 4587.786 | T94: ='Program Budget'!T96 -> 6 | U94: 1 | V94: =S94*T94*U94 -> 27526.716 | W94: =F94+J94+N94+R94+V94 -> 182504.32
A95: ='Program Budget'!D98 -> Communications Costs (Internet, Phone, Data) (Tozeur) | B95: ='Program Budget'!F98 -> Month | C95: ='Program Budget'!H98 -> 500 | D95: ='Program Budget'!G98 -> 3 | E95: 1 | F95: =C95*D95*E95 -> 1500 | G95: =C95*1.07 -> 535 | H95: ='Program Budget'!K98 -> 12 | I95: 1 | J95: =G95*H95*I95 -> 6420 | K95: =G95*1.07 -> 572.45 | L95: ='Program Budget'!N98 -> 12 | M95: 1 | N95: =K95*L95*M95 -> 6869.4 | O95: =K95*1.07 -> 612.5215 | P95: ='Program Budget'!Q98 -> 12 | Q95: 1 | R95: =O95*P95*Q95 -> 7350.258 | S95: =O95*1.07 -> 655.39801 | T95: ='Program Budget'!T98 -> 6 | U95: 1 | V95: =S95*T95*U95 -> 3932.388 | W95: =F95+J95+N95+R95+V95 -> 26072.046
A96: ='Program Budget'!D99 -> Office Rent (Tozeur) (Unfurnished) | B96: ='Program Budget'!F99 -> Month | C96: ='Program Budget'!H99 -> 825 | D96: ='Program Budget'!G99 -> 3 | E96: 1 | F96: =C96*D96*E96 -> 2475 | G96: =C96*1.07 -> 882.75 | H96: ='Program Budget'!K99 -> 12 | I96: 1 | J96: =G96*H96*I96 -> 10593 | K96: =G96*1.07 -> 944.5425 | L96: ='Program Budget'!N99 -> 12 | M96: 1 | N96: =K96*L96*M96 -> 11334.51 | O96: =K96*1.07 -> 1010.6605 | P96: ='Program Budget'!Q99 -> 12 | Q96: 1 | R96: =O96*P96*Q96 -> 12127.926 | S96: =O96*1.07 -> 1081.4067 | T96: ='Program Budget'!T99 -> 6 | U96: 1 | V96: =S96*T96*U96 -> 6488.4402 | W96: =F96+J96+N96+R96+V96 -> 43018.876
A97: ='Program Budget'!D100 -> Office Utilities (Tozeur) | B97: ='Program Budget'!F100 -> Month | C97: ='Program Budget'!H100 -> 100 | D97: ='Program Budget'!G100 -> 3 | E97: 1 | F97: =C97*D97*E97 -> 300 | G97: =C97*1.07 -> 107 | H97: ='Program Budget'!K100 -> 12 | I97: 1 | J97: =G97*H97*I97 -> 1284 | K97: =G97*1.07 -> 114.49 | L97: ='Program Budget'!N100 -> 12 | M97: 1 | N97: =K97*L97*M97 -> 1373.88 | O97: =K97*1.07 -> 122.5043 | P97: ='Program Budget'!Q100 -> 12 | Q97: 1 | R97: =O97*P97*Q97 -> 1470.0516 | S97: =O97*1.07 -> 131.0796 | T97: ='Program Budget'!T100 -> 6 | U97: 1 | V97: =S97*T97*U97 -> 786.47761 | W97: =F97+J97+N97+R97+V97 -> 5214.4092
A98: ='Program Budget'!D101 -> Office Cleaning (Tozeur) | B98: ='Program Budget'!F101 -> Month | C98: ='Program Budget'!H101 -> 75 | D98: ='Program Budget'!G101 -> 3 | E98: 1 | F98: =C98*D98*E98 -> 225 | G98: =C98*1.07 -> 80.25 | H98: ='Program Budget'!K101 -> 12 | I98: 1 | J98: =G98*H98*I98 -> 963 | K98: =G98*1.07 -> 85.8675 | L98: ='Program Budget'!N101 -> 12 | M98: 1 | N98: =K98*L98*M98 -> 1030.41 | O98: =K98*1.07 -> 91.878225 | P98: ='Program Budget'!Q101 -> 12 | Q98: 1 | R98: =O98*P98*Q98 -> 1102.5387 | S98: =O98*1.07 -> 98.309701 | T98: ='Program Budget'!T101 -> 6 | U98: 1 | V98: =S98*T98*U98 -> 589.8582 | W98: =F98+J98+N98+R98+V98 -> 3910.8069
A99: ='Program Budget'!D103 -> Banking and Cash Handling Fees | B99: ='Program Budget'!F103 -> Month | C99: ='Program Budget'!H103 -> 150 | D99: ='Program Budget'!G103 -> 9 | E99: 1 | F99: =C99*D99*E99 -> 1350 | G99: =C99*1.07 -> 160.5 | H99: ='Program Budget'!K103 -> 12 | I99: 1 | J99: =G99*H99*I99 -> 1926 | K99: =G99*1.07 -> 171.735 | L99: ='Program Budget'!N103 -> 12 | M99: 1 | N99: =K99*L99*M99 -> 2060.82 | O99: =K99*1.07 -> 183.75645 | P99: ='Program Budget'!Q103 -> 12 | Q99: 1 | R99: =O99*P99*Q99 -> 2205.0774 | S99: =O99*1.07 -> 196.6194 | T99: ='Program Budget'!T103 -> 6 | U99: 1 | V99: =S99*T99*U99 -> 1179.7164 | W99: =F99+J99+N99+R99+V99 -> 8721.6138
A100: ='Program Budget'!D104 -> Courier fees/Services/Postage | B100: ='Program Budget'!F104 -> Month | C100: ='Program Budget'!H104 -> 30 | D100: ='Program Budget'!G104 -> 9 | E100: 1 | F100: =C100*D100*E100 -> 270 | G100: =C100*1.07 -> 32.1 | H100: ='Program Budget'!K104 -> 12 | I100: 1 | J100: =G100*H100*I100 -> 385.2 | K100: =G100*1.07 -> 34.347 | L100: ='Program Budget'!N104 -> 12 | M100: 1 | N100: =K100*L100*M100 -> 412.164 | O100: =K100*1.07 -> 36.75129 | P100: ='Program Budget'!Q104 -> 12 | Q100: 1 | R100: =O100*P100*Q100 -> 441.01548 | S100: =O100*1.07 -> 39.32388 | T100: ='Program Budget'!T104 -> 6 | U100: 1 | V100: =S100*T100*U100 -> 235.94328 | W100: =F100+J100+N100+R100+V100 -> 1744.3228
A101: ='Program Budget'!D105 -> Recruitment/Procurement Advertising | B101: ='Program Budget'!F105 -> Year | C101: ='Program Budget'!H105 -> 2400 | D101: ='Program Budget'!G105 -> 1 | E101: 1 | F101: =C101*D101*E101 -> 2400 | G101: =C101*1.07 -> 2568 | H101: ='Program Budget'!K105 -> 1 | I101: 1 | J101: =G101*H101*I101 -> 2568 | K101: =G101*1.07 -> 2747.76 | L101: ='Program Budget'!N105 -> 1 | M101: 1 | N101: =K101*L101*M101 -> 2747.76 | O101: =K101*1.07 -> 2940.1032 | P101: ='Program Budget'!Q105 -> 1 | Q101: 1 | R101: =O101*P101*Q101 -> 2940.1032 | S101: =O101*1.07 -> 3145.9104 | T101: ='Program Budget'!T105 -> 1 | U101: 1 | V101: =S101*T101*U101 -> 3145.9104 | W101: =F101+J101+N101+R101+V101 -> 13801.774
A102: ='Program Budget'!D106 -> Meeting Expenses - Room Rental and A/V Equipment (for Small Meeting, Rooms Space Rented per Hour) | B102: ='Program Budget'!F106 -> Hours | C102: ='Program Budget'!H106 -> 10 | D102: ='Program Budget'!G106 -> 225 | E102: 1 | F102: =C102*D102*E102 -> 2250 | G102: =C102*1.07 -> 10.7 | H102: ='Program Budget'!K106 -> 300 | I102: 1 | J102: =G102*H102*I102 -> 3210 | K102: =G102*1.07 -> 11.449 | L102: ='Program Budget'!N106 -> 300 | M102: 1 | N102: =K102*L102*M102 -> 3434.7 | O102: =K102*1.07 -> 12.25043 | P102: ='Program Budget'!Q106 -> 300 | Q102: 1 | R102: =O102*P102*Q102 -> 3675.129 | S102: =O102*1.07 -> 13.10796 | T102: ='Program Budget'!T106 -> 150 | U102: 1 | V102: =S102*T102*U102 -> 1966.194 | W102: =F102+J102+N102+R102+V102 -> 14536.023
A103: ='Program Budget'!D107 -> Payroll Processing and Local Accounting Books Preparation | B103: ='Program Budget'!F107 -> Year | C103: ='Program Budget'!H107 -> 10660 | D103: ='Program Budget'!G107 -> 1 | E103: 1 | F103: =C103*D103*E103 -> 10660 | G103: =C103*1.07 -> 11406.2 | H103: ='Program Budget'!K107 -> 1 | I103: 1 | J103: =G103*H103*I103 -> 11406.2 | K103: =G103*1.07 -> 12204.634 | L103: ='Program Budget'!N107 -> 1 | M103: 1 | N103: =K103*L103*M103 -> 12204.634 | O103: =K103*1.07 -> 13058.958 | P103: ='Program Budget'!Q107 -> 1 | Q103: 1 | R103: =O103*P103*Q103 -> 13058.958 | S103: =O103*1.07 -> 13973.085 | T103: ='Program Budget'!T107 -> 1 | U103: 1 | V103: =S103*T103*U103 -> 13973.085 | W103: =F103+J103+N103+R103+V103 -> 61302.878
A104: ='Program Budget'!D108 -> Licenses & Subscriptions (Microsoft 365, Replicon, PandaDoc, TripLog, HR Platform) | B104: ='Program Budget'!F108 -> Month | C104: ='Program Budget'!H108 -> 1155 | D104: ='Program Budget'!G108 -> 9 | E104: 1 | F104: =C104*D104*E104 -> 10395 | G104: =C104*1.07 -> 1235.85 | H104: ='Program Budget'!K108 -> 12 | I104: 1 | J104: =G104*H104*I104 -> 14830.2 | K104: =G104*1.07 -> 1322.3595 | L104: ='Program Budget'!N108 -> 12 | M104: 1 | N104: =K104*L104*M104 -> 15868.314 | O104: =K104*1.07 -> 1414.9247 | P104: ='Program Budget'!Q108 -> 12 | Q104: 1 | R104: =O104*P104*Q104 -> 16979.096 | S104: =O104*1.07 -> 1513.9694 | T104: ='Program Budget'!T108 -> 9 | U104: 1 | V104: =S104*T104*U104 -> 13625.725 | W104: =F104+J104+N104+R104+V104 -> 71698.335
...

Sheet Activity 1
A2: Item | B2: Type of Unit | C2: Year 1 | G2: Year 2 | K2: Year 3 | O2: Year 4 | S2: Year 5 | W2: Total
C3: Cost | D3: Quantity | E3: Percent Allocated | F3: Total | G3: Cost | H3: Quantity | I3: Percent Allocated | J3: Total | K3: Cost | L3: Quantity | M3: Percent Allocated | N3: Total | O3: Cost | P3: Quantity | Q3: Percent Allocated | R3: Total | S3: Cost | T3: Quantity | U3: Percent Allocated | V3: Total | AF3: Chart of Accounts
A4: Direct Costs | AE4: Line# | AF4: Account | AG4: Account Name
A5: Salaries
A6: USN/TCN Staff
A7: None | F7: =C7*D7*E7 -> 0 | J7: =G7*H7*I7 -> 0 | N7: =K7*L7*M7 -> 0 | R7: =O7*P7*Q7 -> 0 | V7: =S7*T7*U7 -> 0 | W7: =F7+J7+N7+R7+V7 -> 0
A8: Total: Expatriate Salaries & Wages | F8: =SUM(F7:F7) -> 0 | J8: =SUM(J7:J7) -> 0 | N8: =SUM(N7:N7) -> 0 | R8: =SUM(R7:R7) -> 0 | V8: =SUM(V7:V7) -> 0 | W8: =+F8+J8+N8+R8+V8 -> 0
A9: CCN Staff
A10: ='Program Budget'!D12 -> Key Personnel: Chief of Party - Ms. Rym Ayari | B10: ='Program Budget'!F140 -> Month | C10: ='Program Budget'!H12 -> 13000 | D10: ='Program Budget'!G12 -> 12 | E10: ='Program Budget'!E140 -> 0.25 | F10: =C10*D10*E10 -> 39000 | G10: =C10*1.05 -> 13650 | H10: ='Program Budget'!K12 -> 12 | I10: ='Program Budget'!J140 -> 0.3 | J10: =G10*H10*I10 -> 49140 | K10: =G10*1.05 -> 14332.5 | L10: ='Program Budget'!N12 -> 12 | M10: ='Program Budget'!M140 -> 0.3 | N10: =K10*L10*M10 -> 51597 | O10: =K10*1.05 -> 15049.125 | P10: ='Program Budget'!Q12 -> 12 | Q10: ='Program Budget'!P140 -> 0.3 | R10: =O10*P10*Q10 -> 54176.85 | S10: =O10*1.05 -> 15801.581 | T10: ='Program Budget'!T12 -> 12 | U10: ='Program Budget'!S140 -> 0.3 | V10: =S10*T10*U10 -> 56885.692 | W10: =F10+J10+N10+R10+V10 -> 250799.54
A11: ='Program Budget'!D13 -> Key Personnel: Technical Director | B11: ='Program Budget'!F141 -> Month | C11: ='Program Budget'!H13 -> 3916.6667 | D11: ='Program Budget'!G13 -> 9 | E11: ='Program Budget'!E141 -> 0.25 | F11: =C11*D11*E11 -> 8812.5 | G11: =C11*1.05 -> 4112.5 | H11: ='Program Budget'!K13 -> 12 | I11: ='Program Budget'!J141 -> 0.35 | J11: =G11*H11*I11 -> 17272.5 | K11: =G11*1.05 -> 4318.125 | L11: ='Program Budget'!N13 -> 12 | M11: ='Program Budget'!M141 -> 0.35 | N11: =K11*L11*M11 -> 18136.125 | O11: =K11*1.05 -> 4534.0312 | P11: ='Program Budget'!Q13 -> 12 | Q11: ='Program Budget'!P141 -> 0.35 | R11: =O11*P11*Q11 -> 19042.931 | S11: =O11*1.05 -> 4760.7328 | T11: ='Program Budget'!T13 -> 9 | U11: ='Program Budget'!S141 -> 0.35 | V11: =S11*T11*U11 -> 14996.308 | W11: =F11+J11+N11+R11+V11 -> 78260.365 | AE11: 180 | AF11: 50-01-2-020 | AG11: DIR-USN (Expat) Labor
A12: ='Program Budget'!D14 -> Technical Lead Component 1 | B12: ='Program Budget'!F142 -> Month | C12: ='Program Budget'!H14 -> 2500 | D12: ='Program Budget'!G14 -> 6 | E12: ='Program Budget'!E142 -> 0.8 | F12: =C12*D12*E12 -> 12000 | G12: =C12*1.05 -> 2625 | H12: ='Program Budget'!K14 -> 12 | I12: ='Program Budget'!J142 -> 1 | J12: =G12*H12*I12 -> 31500 | K12: =G12*1.05 -> 2756.25 | L12: ='Program Budget'!N14 -> 12 | M12: ='Program Budget'!M142 -> 1 | N12: =K12*L12*M12 -> 33075 | O12: =K12*1.05 -> 2894.0625 | P12: ='Program Budget'!Q14 -> 12 | Q12: ='Program Budget'!P142 -> 1 | R12: =O12*P12*Q12 -> 34728.75 | S12: =O12*1.05 -> 3038.7656 | T12: ='Program Budget'!T14 -> 9 | U12: ='Program Budget'!S142 -> 1 | V12: =S12*T12*U12 -> 27348.891 | W12: =F12+J12+N12+R12+V12 -> 138652.64 | AE12: 180 | AF12: 50-01-2-020 | AG12: DIR-USN (Expat) Labor
A13: ='Program Budget'!D15 -> Technical Lead Component 2 | B13: ='Program Budget'!F143 -> Month | C13: ='Program Budget'!H15 -> 2500 | D13: ='Program Budget'!G15 -> 6 | E13: ='Program Budget'!E143 -> 0 | F13: =C13*D13*E13 -> 0 | G13: =C13*1.05 -> 2625 | H13: ='Program Budget'!K15 -> 12 | I13: ='Program Budget'!J143 -> 0 | J13: =G13*H13*I13 -> 0 | K13: =G13*1.05 -> 2756.25 | L13: ='Program Budget'!N15 -> 12 | M13: ='Program Budget'!M143 -> 0 | N13: =K13*L13*M13 -> 0 | O13: =K13*1.05 -> 2894.0625 | P13: ='Program Budget'!Q15 -> 12 | Q13: ='Program Budget'!P143 -> 0 | R13: =O13*P13*Q13 -> 0 | S13: =O13*1.05 -> 3038.7656 | T13: ='Program Budget'!T15 -> 9 | U13: ='Program Budget'!S143 -> 0 | V13: =S13*T13*U13 -> 0 | W13: =F13+J13+N13+R13+V13 -> 0 | AE13: 180 | AF13: 50-01-2-020 | AG13: DIR-USN (Expat) Labor
A14: ='Program Budget'!D16 -> Technical Lead Component 3 | B14: ='Program Budget'!F144 -> Month | C14: ='Program Budget'!H16 -> 2500 | D14: ='Program Budget'!G16 -> 6 | E14: ='Program Budget'!E144 -> 0 | F14: =C14*D14*E14 -> 0 | G14: =C14*1.05 -> 2625 | H14: ='Program Budget'!K16 -> 12 | I14: ='Program Budget'!J144 -> 0 | J14: =G14*H14*I14 -> 0 | K14: =G14*1.05 -> 2756.25 | L14: ='Program Budget'!N16 -> 12 | M14: ='Program Budget'!M144 -> 0 | N14: =K14*L14*M14 -> 0 | O14: =K14*1.05 -> 2894.0625 | P14: ='Program Budget'!Q16 -> 12 | Q14: ='Program Budget'!P144 -> 0 | R14: =O14*P14*Q14 -> 0 | S14: =O14*1.05 -> 3038.7656 | T14: ='Program Budget'!T16 -> 9 | U14: ='Program Budget'!S144 -> 0 | V14: =S14*T14*U14 -> 0 | W14: =F14+J14+N14+R14+V14 -> 0 | AE14: 180 | AF14: 50-01-2-020 | AG14: DIR-USN (Expat) Labor
A15: ='Program Budget'!D17 -> Technical Specialist Component 1 | B15: ='Program Budget'!F145 -> Month | C15: ='Program Budget'!H17 -> 1833.3333 | D15: ='Program Budget'!G17 -> 6 | E15: ='Program Budget'!E145 -> 0.8 | F15: =C15*D15*E15 -> 8800 | G15: =C15*1.05 -> 1925 | H15: ='Program Budget'!K17 -> 12 | I15: ='Program Budget'!J145 -> 1 | J15: =G15*H15*I15 -> 23100 | K15: =G15*1.05 -> 2021.25 | L15: ='Program Budget'!N17 -> 12 | M15: ='Program Budget'!M145 -> 1 | N15: =K15*L15*M15 -> 24255 | O15: =K15*1.05 -> 2122.3125 | P15: ='Program Budget'!Q17 -> 12 | Q15: ='Program Budget'!P145 -> 1 | R15: =O15*P15*Q15 -> 25467.75 | S15: =O15*1.05 -> 2228.4281 | T15: ='Program Budget'!T17 -> 6 | U15: ='Program Budget'!S145 -> 1 | V15: =S15*T15*U15 -> 13370.569 | W15: =F15+J15+N15+R15+V15 -> 94993.319
A16: ='Program Budget'!D18 -> Technical Specialist Component 2 | B16: ='Program Budget'!F146 -> Month | C16: ='Program Budget'!H18 -> 1833.3333 | D16: ='Program Budget'!G18 -> 6 | E16: ='Program Budget'!E146 -> 0 | F16: =C16*D16*E16 -> 0 | G16: =C16*1.05 -> 1925 | H16: ='Program Budget'!K18 -> 12 | I16: ='Program Budget'!J146 -> 0 | J16: =G16*H16*I16 -> 0 | K16: =G16*1.05 -> 2021.25 | L16: ='Program Budget'!N18 -> 12 | M16: ='Program Budget'!M146 -> 0 | N16: =K16*L16*M16 -> 0 | O16: =K16*1.05 -> 2122.3125 | P16: ='Program Budget'!Q18 -> 12 | Q16: ='Program Budget'!P146 -> 0 | R16: =O16*P16*Q16 -> 0 | S16: =O16*1.05 -> 2228.4281 | T16: ='Program Budget'!T18 -> 6 | U16: ='Program Budget'!S146 -> 0 | V16: =S16*T16*U16 -> 0 | W16: =F16+J16+N16+R16+V16 -> 0
A17: ='Program Budget'!D19 -> Technical Specialist Component 3 | B17: ='Program Budget'!F147 -> Month | C17: ='Program Budget'!H19 -> 1833.3333 | D17: ='Program Budget'!G19 -> 6 | E17: ='Program Budget'!E147 -> 0 | F17: =C17*D17*E17 -> 0 | G17: =C17*1.05 -> 1925 | H17: ='Program Budget'!K19 -> 12 | I17: ='Program Budget'!J147 -> 0 | J17: =G17*H17*I17 -> 0 | K17: =G17*1.05 -> 2021.25 | L17: ='Program Budget'!N19 -> 12 | M17: ='Program Budget'!M147 -> 0 | N17: =K17*L17*M17 -> 0 | O17: =K17*1.05 -> 2122.3125 | P17: ='Program Budget'!Q19 -> 12 | Q17: ='Program Budget'!P147 -> 0 | R17: =O17*P17*Q17 -> 0 | S17: =O17*1.05 -> 2228.4281 | T17: ='Program Budget'!T19 -> 6 | U17: ='Program Budget'!S147 -> 0 | V17: =S17*T17*U17 -> 0 | W17: =F17+J17+N17+R17+V17 -> 0
A18: ='Program Budget'!D20 -> Capacity Building Specialist (2) | B18: ='Program Budget'!F148 -> Month | C18: ='Program Budget'!H20 -> 3333.3333 | D18: ='Program Budget'!G20 -> 4 | E18: ='Program Budget'!E148 -> 0 | F18: =C18*D18*E18 -> 0 | G18: =C18*1.05 -> 3500 | H18: ='Program Budget'!K20 -> 12 | I18: ='Program Budget'!J148 -> 0 | J18: =G18*H18*I18 -> 0 | K18: =G18*1.05 -> 3675 | L18: ='Program Budget'!N20 -> 12 | M18: ='Program Budget'!M148 -> 0 | N18: =K18*L18*M18 -> 0 | O18: =K18*1.05 -> 3858.75 | P18: ='Program Budget'!Q20 -> 12 | Q18: ='Program Budget'!P148 -> 0 | R18: =O18*P18*Q18 -> 0 | S18: =O18*1.05 -> 4051.6875 | T18: ='Program Budget'!T20 -> 5 | U18: ='Program Budget'!S148 -> 0 | V18: =S18*T18*U18 -> 0 | W18: =F18+J18+N18+R18+V18 -> 0
A19: ='Program Budget'!D21 -> Sociocultural and Gender Specialist | B19: ='Program Budget'!F149 -> Month | C19: ='Program Budget'!H21 -> 1833.3333 | D19: ='Program Budget'!G21 -> 7 | E19: ='Program Budget'!E149 -> 0.25 | F19: =C19*D19*E19 -> 3208.3333 | G19: =C19*1.05 -> 1925 | H19: ='Program Budget'!K21 -> 12 | I19: ='Program Budget'!J149 -> 0.35 | J19: =G19*H19*I19 -> 8085 | K19: =G19*1.05 -> 2021.25 | L19: ='Program Budget'!N21 -> 12 | M19: ='Program Budget'!M149 -> 0.3 | N19: =K19*L19*M19 -> 7276.5 | O19: =K19*1.05 -> 2122.3125 | P19: ='Program Budget'!Q21 -> 12 | Q19: ='Program Budget'!P149 -> 0.3 | R19: =O19*P19*Q19 -> 7640.325 | S19: =O19*1.05 -> 2228.4281 | T19: ='Program Budget'!T21 -> 9 | U19: ='Program Budget'!S149 -> 0.3 | V19: =S19*T19*U19 -> 6016.7559 | W19: =F19+J19+N19+R19+V19 -> 32226.914
A20: ='Program Budget'!D22 -> Sociocultural and Gender Officers (3) | B20: ='Program Budget'!F150 -> Month | C20: ='Program Budget'!H22 -> 3750 | D20: ='Program Budget'!G22 -> 7 | E20: ='Program Budget'!E150 -> 0.25 | F20: =C20*D20*E20 -> 6562.5 | G20: =C20*1.05 -> 3937.5 | H20: ='Program Budget'!K22 -> 12 | I20: ='Program Budget'!J150 -> 0.35 | J20: =G20*H20*I20 -> 16537.5 | K20: =G20*1.05 -> 4134.375 | L20: ='Program Budget'!N22 -> 12 | M20: ='Program Budget'!M150 -> 0.3 | N20: =K20*L20*M20 -> 14883.75 | O20: =K20*1.05 -> 4341.0938 | P20: ='Program Budget'!Q22 -> 12 | Q20: ='Program Budget'!P150 -> 0.3 | R20: =O20*P20*Q20 -> 15627.938 | S20: =O20*1.05 -> 4558.1484 | T20: ='Program Budget'!T22 -> 9 | U20: ='Program Budget'!S150 -> 0.3 | V20: =S20*T20*U20 -> 12307.001 | W20: =F20+J20+N20+R20+V20 -> 65918.688
A21: ='Program Budget'!D23 -> Communications Specialists | B21: ='Program Budget'!F151 -> Month | C21: ='Program Budget'!H23 -> 1500 | D21: ='Program Budget'!G23 -> 7 | E21: ='Program Budget'!E151 -> 0.25 | F21: =C21*D21*E21 -> 2625 | G21: =C21*1.05 -> 1575 | H21: ='Program Budget'!K23 -> 12 | I21: ='Program Budget'!J151 -> 0.3 | J21: =G21*H21*I21 -> 5670 | K21: =G21*1.05 -> 1653.75 | L21: ='Program Budget'!N23 -> 12 | M21: ='Program Budget'!M151 -> 0.3 | N21: =K21*L21*M21 -> 5953.5 | O21: =K21*1.05 -> 1736.4375 | P21: ='Program Budget'!Q23 -> 12 | Q21: ='Program Budget'!P151 -> 0.3 | R21: =O21*P21*Q21 -> 6251.175 | S21: =O21*1.05 -> 1823.2594 | T21: ='Program Budget'!T23 -> 10 | U21: ='Program Budget'!S151 -> 0.3 | V21: =S21*T21*U21 -> 5469.7781 | W21: =F21+J21+N21+R21+V21 -> 25969.453
A22: ='Program Budget'!D24 -> M&E Director | B22: ='Program Budget'!F152 -> Month | C22: ='Program Budget'!H24 -> 3916.6667 | D22: ='Program Budget'!G24 -> 9 | E22: ='Program Budget'!E152 -> 0.25 | F22: =C22*D22*E22 -> 8812.5 | G22: =C22*1.05 -> 4112.5 | H22: ='Program Budget'!K24 -> 12 | I22: ='Program Budget'!J152 -> 0.3 | J22: =G22*H22*I22 -> 14805 | K22: =G22*1.05 -> 4318.125 | L22: ='Program Budget'!N24 -> 12 | M22: ='Program Budget'!M152 -> 0.3 | N22: =K22*L22*M22 -> 15545.25 | O22: =K22*1.05 -> 4534.0312 | P22: ='Program Budget'!Q24 -> 12 | Q22: ='Program Budget'!P152 -> 0.3 | R22: =O22*P22*Q22 -> 16322.512 | S22: =O22*1.05 -> 4760.7328 | T22: ='Program Budget'!T24 -> 12 | U22: ='Program Budget'!S152 -> 0.3 | V22: =S22*T22*U22 -> 17138.638 | W22: =F22+J22+N22+R22+V22 -> 72623.901 | AE22: 180 | AF22: 50-01-2-020 | AG22: DIR-USN (Expat) Labor
A23: ='Program Budget'!D25 -> M&E Specialist | B23: ='Program Budget'!F153 -> Month | C23: ='Program Budget'!H25 -> 1833.3333 | D23: ='Program Budget'!G25 -> 8 | E23: ='Program Budget'!E153 -> 0.25 | F23: =C23*D23*E23 -> 3666.6667 | G23: =C23*1.05 -> 1925 | H23: ='Program Budget'!K25 -> 12 | I23: ='Program Budget'!J153 -> 0.3 | J23: =G23*H23*I23 -> 6930 | K23: =G23*1.05 -> 2021.25 | L23: ='Program Budget'!N25 -> 12 | M23: ='Program Budget'!M153 -> 0.3 | N23: =K23*L23*M23 -> 7276.5 | O23: =K23*1.05 -> 2122.3125 | P23: ='Program Budget'!Q25 -> 12 | Q23: ='Program Budget'!P153 -> 0.3 | R23: =O23*P23*Q23 -> 7640.325 | S23: =O23*1.05 -> 2228.4281 | T23: ='Program Budget'!T25 -> 10 | U23: ='Program Budget'!S153 -> 0.3 | V23: =S23*T23*U23 -> 6685.2844 | W23: =F23+J23+N23+R23+V23 -> 32198.776 | AE23: 180 | AF23: 50-01-2-020 | AG23: DIR-USN (Expat) Labor
A24: ='Program Budget'!D26 -> Key Personnel: Finance Director | B24: ='Program Budget'!F154 -> Month | C24: ='Program Budget'!H26 -> 3916.6667 | D24: ='Program Budget'!G26 -> 11 | E24: ='Program Budget'!E154 -> 0.25 | F24: =C24*D24*E24 -> 10770.833 | G24: =C24*1.05 -> 4112.5 | H24: ='Program Budget'!K26 -> 12 | I24: ='Program Budget'!J154 -> 0.25 | J24: =G24*H24*I24 -> 12337.5 | K24: =G24*1.05 -> 4318.125 | L24: ='Program Budget'!N26 -> 12 | M24: ='Program Budget'!M154 -> 0.25 | N24: =K24*L24*M24 -> 12954.375 | O24: =K24*1.05 -> 4534.0312 | P24: ='Program Budget'!Q26 -> 12 | Q24: ='Program Budget'!P154 -> 0.25 | R24: =O24*P24*Q24 -> 13602.094 | S24: =O24*1.05 -> 4760.7328 | T24: ='Program Budget'!T26 -> 12 | U24: ='Program Budget'!S154 -> 0.25 | V24: =S24*T24*U24 -> 14282.198 | W24: =F24+J24+N24+R24+V24 -> 63947.001 | AE24: 180 | AF24: 50-01-2-020 | AG24: DIR-USN (Expat) Labor
A25: ='Program Budget'!D27 -> Contracts & Compliance Specialist | B25: ='Program Budget'!F155 -> Month | C25: ='Program Budget'!H27 -> 1833.3333 | D25: ='Program Budget'!G27 -> 9 | E25: ='Program Budget'!E155 -> 0.25 | F25: =C25*D25*E25 -> 4125 | G25: =C25*1.05 -> 1925 | H25: ='Program Budget'!K27 -> 12 | I25: ='Program Budget'!J155 -> 0.25 | J25: =G25*H25*I25 -> 5775 | K25: =G25*1.05 -> 2021.25 | L25: ='Program Budget'!N27 -> 12 | M25: ='Program Budget'!M155 -> 0.25 | N25: =K25*L25*M25 -> 6063.75 | O25: =K25*1.05 -> 2122.3125 | P25: ='Program Budget'!Q27 -> 12 | Q25: ='Program Budget'!P155 -> 0.25 | R25: =O25*P25*Q25 -> 6366.9375 | S25: =O25*1.05 -> 2228.4281 | T25: ='Program Budget'!T27 -> 12 | U25: ='Program Budget'!S155 -> 0.25 | V25: =S25*T25*U25 -> 6685.2844 | W25: =F25+J25+N25+R25+V25 -> 29015.972 | AE25: 180 | AF25: 50-01-2-020 | AG25: DIR-USN (Expat) Labor
A26: ='Program Budget'!D28 -> Grants & Procurement Officer (2) | B26: ='Program Budget'!F156 -> Month | C26: ='Program Budget'!H28 -> 2500 | D26: ='Program Budget'!G28 -> 9 | E26: ='Program Budget'!E156 -> 0.25 | F26: =C26*D26*E26 -> 5625 | G26: =C26*1.05 -> 2625 | H26: ='Program Budget'!K28 -> 12 | I26: ='Program Budget'!J156 -> 0.25 | J26: =G26*H26*I26 -> 7875 | K26: =G26*1.05 -> 2756.25 | L26: ='Program Budget'!N28 -> 12 | M26: ='Program Budget'!M156 -> 0.25 | N26: =K26*L26*M26 -> 8268.75 | O26: =K26*1.05 -> 2894.0625 | P26: ='Program Budget'!Q28 -> 12 | Q26: ='Program Budget'!P156 -> 0.25 | R26: =O26*P26*Q26 -> 8682.1875 | S26: =O26*1.05 -> 3038.7656 | T26: ='Program Budget'!T28 -> 12 | U26: ='Program Budget'!S156 -> 0.25 | V26: =S26*T26*U26 -> 9116.2969 | W26: =F26+J26+N26+R26+V26 -> 39567.234
A27: ='Program Budget'!D29 -> Accountant | B27: ='Program Budget'!F157 -> Month | C27: ='Program Budget'!H29 -> 1666.6667 | D27: ='Program Budget'!G29 -> 10 | E27: ='Program Budget'!E157 -> 0.25 | F27: =C27*D27*E27 -> 4166.6667 | G27: =C27*1.05 -> 1750 | H27: ='Program Budget'!K29 -> 12 | I27: ='Program Budget'!J157 -> 0.25 | J27: =G27*H27*I27 -> 5250 | K27: =G27*1.05 -> 1837.5 | L27: ='Program Budget'!N29 -> 12 | M27: ='Program Budget'!M157 -> 0.25 | N27: =K27*L27*M27 -> 5512.5 | O27: =K27*1.05 -> 1929.375 | P27: ='Program Budget'!Q29 -> 12 | Q27: ='Program Budget'!P157 -> 0.25 | R27: =O27*P27*Q27 -> 5788.125 | S27: =O27*1.05 -> 2025.8438 | T27: ='Program Budget'!T29 -> 11 | U27: ='Program Budget'!S157 -> 0.25 | V27: =S27*T27*U27 -> 5571.0703 | W27: =F27+J27+N27+R27+V27 -> 26288.362 | AE27: 180 | AF27: 50-01-2-020 | AG27: DIR-USN (Expat) Labor
A28: ='Program Budget'!D30 -> Administrative Officer | B28: ='Program Budget'!F158 -> Month | C28: ='Program Budget'!H30 -> 833.33333 | D28: ='Program Budget'!G30 -> 9 | E28: ='Program Budget'!E158 -> 0.25 | F28: =C28*D28*E28 -> 1875 | G28: =C28*1.05 -> 875 | H28: ='Program Budget'!K30 -> 12 | I28: ='Program Budget'!J158 -> 0.25 | J28: =G28*H28*I28 -> 2625 | K28: =G28*1.05 -> 918.75 | L28: ='Program Budget'!N30 -> 12 | M28: ='Program Budget'!M158 -> 0.25 | N28: =K28*L28*M28 -> 2756.25 | O28: =K28*1.05 -> 964.6875 | P28: ='Program Budget'!Q30 -> 12 | Q28: ='Program Budget'!P158 -> 0.25 | R28: =O28*P28*Q28 -> 2894.0625 | S28: =O28*1.05 -> 1012.9219 | T28: ='Program Budget'!T30 -> 10 | U28: ='Program Budget'!S158 -> 0.25 | V28: =S28*T28*U28 -> 2532.3047 | W28: =F28+J28+N28+R28+V28 -> 12682.617 | AE28: 180 | AF28: 50-01-2-020 | AG28: DIR-USN (Expat) Labor
A29: ='Program Budget'!D31 -> Human Resources Manager | B29: ='Program Budget'!F159 -> Month | C29: ='Program Budget'!H31 -> 2500 | D29: ='Program Budget'!G31 -> 11 | E29: ='Program Budget'!E159 -> 0.25 | F29: =C29*D29*E29 -> 6875 | G29: =C29*1.05 -> 2625 | H29: ='Program Budget'!K31 -> 12 | I29: ='Program Budget'!J159 -> 0.25 | J29: =G29*H29*I29 -> 7875 | K29: =G29*1.05 -> 2756.25 | L29: ='Program Budget'!N31 -> 12 | M29: ='Program Budget'!M159 -> 0.25 | N29: =K29*L29*M29 -> 8268.75 | O29: =K29*1.05 -> 2894.0625 | P29: ='Program Budget'!Q31 -> 12 | Q29: ='Program Budget'!P159 -> 0.25 | R29: =O29*P29*Q29 -> 8682.1875 | S29: =O29*1.05 -> 3038.7656 | T29: ='Program Budget'!T31 -> 12 | U29: ='Program Budget'!S159 -> 0.25 | V29: =S29*T29*U29 -> 9116.2969 | W29: =F29+J29+N29+R29+V29 -> 40817.234 | AE29: 180 | AF29: 50-01-2-020 | AG29: DIR-USN (Expat) Labor
A30: ='Program Budget'!D32 -> Driver (3 Individuals) | B30: ='Program Budget'!F160 -> Month | C30: ='Program Budget'!H32 -> 2250 | D30: ='Program Budget'!G32 -> 3 | E30: ='Program Budget'!E160 -> 0.3 | F30: =C30*D30*E30 -> 2025 | G30: =C30*1.05 -> 2362.5 | H30: ='Program Budget'!K32 -> 12 | I30: ='Program Budget'!J160 -> 0.25 | J30: =G30*H30*I30 -> 7087.5 | K30: =G30*1.05 -> 2480.625 | L30: ='Program Budget'!N32 -> 12 | M30: ='Program Budget'!M160 -> 0.25 | N30: =K30*L30*M30 -> 7441.875 | O30: =K30*1.05 -> 2604.6562 | P30: ='Program Budget'!Q32 -> 12 | Q30: ='Program Budget'!P160 -> 0.25 | R30: =O30*P30*Q30 -> 7813.9688 | S30: =O30*1.05 -> 2734.8891 | T30: ='Program Budget'!T32 -> 9 | U30: ='Program Budget'!S160 -> 0.25 | V30: =S30*T30*U30 -> 6153.5004 | W30: =F30+J30+N30+R30+V30 -> 30521.844 | AE30: 180 | AF30: 50-01-2-020 | AG30: DIR-USN (Expat) Labor
A31: Total Local Salary Cost | F31: =SUM(F10:F30) -> 128950 | J31: =SUM(J10:J30) -> 221865 | N31: =SUM(N10:N30) -> 229264.88 | R31: =SUM(R10:R30) -> 240728.12 | V31: =SUM(V10:V30) -> 213675.87 | W31: =SUM(W10:W30) -> 1034483.9
A33: Subtotal: Salaries & Wages | F33: =F31+F8 -> 128950 | J33: =J31+J8 -> 221865 | N33: =N31+N8 -> 229264.88 | R33: =R31+R8 -> 240728.12 | V33: =V31+V8 -> 213675.87 | W33: =+F33+J33+N33+R33+V33 -> 1034483.9
A34: Fringe
A35: USN/TCN Staff | F35: =C35*D35*E35 -> 0 | J35: =G35*H35*I35 -> 0 | N35: =K35*L35*M35 -> 0 | R35: =O35*P35*Q35 -> 0 | V35: =S35*T35*U35 -> 0 | W35: =F35+J35+N35+R35+V35 -> 0 | AE35: 194 | AF35: 50-03-0-020 | AG35: DIR-Allocated USN Fringe
A36: CCN Staff | B36: ='Program Budget'!F164 -> % | C36: =F31 -> 128950 | D36: 1 | E36: ='Program Budget'!H164 -> 0.455 | F36: =C36*D36*E36 -> 58672.25 | G36: =J31 -> 221865 | H36: 1 | I36: =E36 -> 0.455 | J36: =G36*H36*I36 -> 100948.57 | K36: =N31 -> 229264.88 | L36: 1 | M36: =I36 -> 0.455 | N36: =K36*L36*M36 -> 104315.52 | O36: =R31 -> 240728.12 | P36: 1 | Q36: =M36 -> 0.455 | R36: =O36*P36*Q36 -> 109531.29 | S36: =V31 -> 213675.87 | T36: 1 | U36: =Q36 -> 0.455 | V36: =S36*T36*U36 -> 97222.521 | W36: =F36+J36+N36+R36+V36 -> 470690.16 | AE36: 197 | AF36: 50-03-0-050 | AG36: DIR-CCN Fringe
A37: Total: Fringe Benefits | F37: =+SUM(F35:F36) -> 58672.25 | J37: =+SUM(J35:J36) -> 100948.57 | N37: =+SUM(N35:N36) -> 104315.52 | R37: =+SUM(R35:R36) -> 109531.29 | V37: =+SUM(V35:V36) -> 97222.521 | W37: =+F37+J37+N37+R37+V37 -> 470690.16
A38: Allowances | W38: =+F38+J38+N38+R38+V38 -> 0
A39: None | F39: =C39*D39*E39 -> 0 | J39: =G39*H39*I39 -> 0 | N39: =K39*L39*M39 -> 0 | R39: =O39*P39*Q39 -> 0 | V39: =S39*T39*U39 -> 0 | W39: =F39+J39+N39+R39+V39 -> 0
A40: Total: Allowances | F40: =SUM(F39:F39) -> 0 | J40: =SUM(J39:J39) -> 0 | N40: =SUM(N39:N39) -> 0 | R40: =SUM(R39:R39) -> 0 | V40: =SUM(V39:V39) -> 0 | W40: =F40+J40+N40+R40+V40 -> 0
A42: Subtotal: Benefits | F42: =F40+F37 -> 58672.25 | J42: =J40+J37 -> 100948.57 | N42: =N40+N37 -> 104315.52 | R42: =R40+R37 -> 109531.29 | V42: =V40+V37 -> 97222.521 | W42: =+F42+J42+N42+R42+V42 -> 470690.16 | AE42: 287 | AF42: 51-04-2-050 | AG42: DIR-Int Travel Other
A43: Local Travel
A44: ='Program Budget'!D183 -> Local Transportation (Car Rental, Taxis) | B44: ='Program Budget'!F183 -> Month | C44: ='Program Budget'!H183 -> 50 | D44: ='Program Budget'!G183 -> 3 | E44: 1 | F44: =C44*D44*E44 -> 150 | G44: =C44*1.07 -> 53.5 | H44: ='Program Budget'!K183 -> 12 | I44: 1 | J44: =G44*H44*I44 -> 642 | K44: =G44*1.07 -> 57.245 | L44: ='Program Budget'!N183 -> 12 | M44: 1 | N44: =K44*L44*M44 -> 686.94 | O44: =K44*1.07 -> 61.25215 | P44: ='Program Budget'!Q183 -> 12 | Q44: 1 | R44: =O44*P44*Q44 -> 735.0258 | S44: =O44*1.07 -> 65.539801 | T44: ='Program Budget'!T183 -> 9 | U44: 1 | V44: =S44*T44*U44 -> 589.8582 | W44: =F44+J44+N44+R44+V44 -> 2803.824 | AE44: 180 | AF44: 50-01-2-020 | AG44: DIR-USN (Expat) Labor
A45: ='Program Budget'!D184 -> Local Transportation for Staff for Communication Materials Development | B45: ='Program Budget'!F184 -> Trip | C45: ='Program Budget'!H184 -> 300 | D45: ='Program Budget'!G184 -> 3 | E45: 1 | F45: =C45*D45*E45 -> 900 | G45: =C45*1.07 -> 321 | H45: ='Program Budget'!K184 -> 3 | I45: 1 | J45: =G45*H45*I45 -> 963 | K45: =G45*1.07 -> 343.47 | L45: ='Program Budget'!N184 -> 0 | M45: 0 | N45: =K45*L45*M45 -> 0 | O45: =K45*1.07 -> 367.5129 | P45: ='Program Budget'!Q184 -> 0 | Q45: 0 | R45: =O45*P45*Q45 -> 0 | S45: =O45*1.07 -> 393.2388 | T45: ='Program Budget'!T184 -> 0 | U45: 0 | V45: =S45*T45*U45 -> 0 | W45: =F45+J45+N45+R45+V45 -> 1863 | AE45: 180 | AF45: 50-01-2-020 | AG45: DIR-USN (Expat) Labor
A46: ='Program Budget'!D186 -> Local Transportation for Staff to Attend Local Agriculture Events | B46: ='Program Budget'!F186 -> Trip | C46: ='Program Budget'!H186 -> 200 | D46: ='Program Budget'!G186 -> 0 | E46: 0 | F46: =C46*D46*E46 -> 0 | G46: =C46*1.07 -> 214 | H46: ='Program Budget'!K186 -> 6 | I46: 1 | J46: =G46*H46*I46 -> 1284 | K46: =G46*1.07 -> 228.98 | L46: ='Program Budget'!N186 -> 6 | M46: 1 | N46: =K46*L46*M46 -> 1373.88 | O46: =K46*1.07 -> 245.0086 | P46: ='Program Budget'!Q186 -> 6 | Q46: 1 | R46: =O46*P46*Q46 -> 1470.0516 | S46: =O46*1.07 -> 262.1592 | T46: ='Program Budget'!T186 -> 6 | U46: 1 | V46: =S46*T46*U46 -> 1572.9552 | W46: =F46+J46+N46+R46+V46 -> 5700.8868 | AE46: 180 | AF46: 50-01-2-020 | AG46: DIR-USN (Expat) Labor
A47: ='Program Budget'!D188 -> Local Transportation for Leaders of Northern Tunisian Cooperatives to Attend Trainings | B47: ='Program Budget'!F188 -> Trip | C47: ='Program Budget'!H188 -> 200 | D47: ='Program Budget'!G188 -> 0 | E47: 0 | F47: =C47*D47*E47 -> 0 | G47: =C47*1.07 -> 214 | H47: ='Program Budget'!K188 -> 2 | I47: 1 | J47: =G47*H47*I47 -> 428 | K47: =G47*1.07 -> 228.98 | L47: ='Program Budget'!N188 -> 2 | M47: 1 | N47: =K47*L47*M47 -> 457.96 | O47: =K47*1.07 -> 245.0086 | P47: ='Program Budget'!Q188 -> 0 | Q47: 0 | R47: =O47*P47*Q47 -> 0 | S47: =O47*1.07 -> 262.1592 | T47: ='Program Budget'!T188 -> 0 | U47: 0 | V47: =S47*T47*U47 -> 0 | W47: =F47+J47+N47+R47+V47 -> 885.96 | AE47: 180 | AF47: 50-01-2-020 | AG47: DIR-USN (Expat) Labor
A48: ='Program Budget'!D190 -> Transport Stipends for Participants to Attend Farmer Field School | B48: ='Program Budget'!F190 -> Participant | C48: ='Program Budget'!H190 -> 10 | D48: ='Program Budget'!G190 -> 500 | E48: 1 | F48: =C48*D48*E48 -> 5000 | G48: =C48*1.07 -> 10.7 | H48: ='Program Budget'!K190 -> 1000 | I48: 1 | J48: =G48*H48*I48 -> 10700 | K48: =G48*1.07 -> 11.449 | L48: ='Program Budget'!N190 -> 500 | M48: 1 | N48: =K48*L48*M48 -> 5724.5 | O48: =K48*1.07 -> 12.25043 | P48: ='Program Budget'!Q190 -> 0 | Q48: 0 | R48: =O48*P48*Q48 -> 0 | S48: =O48*1.07 -> 13.10796 | T48: ='Program Budget'!T190 -> 0 | U48: 0 | V48: =S48*T48*U48 -> 0 | W48: =F48+J48+N48+R48+V48 -> 21424.5 | AE48: 180 | AF48: 50-01-2-020 | AG48: DIR-USN (Expat) Labor
A49: Vehicle Fuel
A50: ='Program Budget'!D182 -> Vehicle Fuel Expense (for Field Office Vehicles) | B50: ='Program Budget'!F182 -> Month | C50: ='Program Budget'!H182 -> 250 | D50: ='Program Budget'!G182 -> 3 | E50: 1 | F50: =C50*D50*E50 -> 750 | G50: =C50*1.07 -> 267.5 | H50: ='Program Budget'!K182 -> 12 | I50: 1 | J50: =G50*H50*I50 -> 3210 | K50: =G50*1.07 -> 286.225 | L50: ='Program Budget'!N182 -> 12 | M50: 1 | N50: =K50*L50*M50 -> 3434.7 | O50: =K50*1.07 -> 306.26075 | P50: ='Program Budget'!Q182 -> 12 | Q50: 1 | R50: =O50*P50*Q50 -> 3675.129 | S50: =O50*1.07 -> 327.699 | T50: ='Program Budget'!T182 -> 9 | U50: 1 | V50: =S50*T50*U50 -> 2949.291 | W50: =F50+J50+N50+R50+V50 -> 14019.12 | AE50: 180 | AF50: 50-01-2-020 | AG50: DIR-USN (Expat) Labor
A51: Per Diem & Lodging
A52: ='Program Budget'!D185 -> Lodging and M&IE for Staff for Communication Materials Development | B52: ='Program Budget'!F185 -> Day | C52: ='Program Budget'!H185 -> 129 | D52: ='Program Budget'!G185 -> 9 | E52: 1 | F52: =C52*D52*E52 -> 1161 | G52: =C52*1.07 -> 138.03 | H52: ='Program Budget'!K185 -> 9 | I52: 1 | J52: =G52*H52*I52 -> 1242.27 | K52: =G52*1.07 -> 147.6921 | L52: ='Program Budget'!N185 -> 0 | M52: 0 | N52: =K52*L52*M52 -> 0 | O52: =K52*1.07 -> 158.03055 | P52: ='Program Budget'!Q185 -> 0 | Q52: 0 | R52: =O52*P52*Q52 -> 0 | S52: =O52*1.07 -> 169.09269 | T52: ='Program Budget'!T185 -> 0 | U52: 0 | V52: =S52*T52*U52 -> 0 | W52: =F52+J52+N52+R52+V52 -> 2403.27 | AE52: 180 | AF52: 50-01-2-020 | AG52: DIR-USN (Expat) Labor
A53: ='Program Budget'!D187 -> Lodging and M&IE for Staff to Attend Local Agriculture Events | B53: ='Program Budget'!F187 -> Day | C53: ='Program Budget'!H187 -> 129 | D53: ='Program Budget'!G187 -> 0 | E53: 0 | F53: =C53*D53*E53 -> 0 | G53: =C53*1.07 -> 138.03 | H53: ='Program Budget'!K187 -> 18 | I53: 1 | J53: =G53*H53*I53 -> 2484.54 | K53: =G53*1.07 -> 147.6921 | L53: ='Program Budget'!N187 -> 18 | M53: 1 | N53: =K53*L53*M53 -> 2658.4578 | O53: =K53*1.07 -> 158.03055 | P53: ='Program Budget'!Q187 -> 18 | Q53: 1 | R53: =O53*P53*Q53 -> 2844.5498 | S53: =O53*1.07 -> 169.09269 | T53: ='Program Budget'!T187 -> 18 | U53: 1 | V53: =S53*T53*U53 -> 3043.6683 | W53: =F53+J53+N53+R53+V53 -> 11031.216 | AE53: 180 | AF53: 50-01-2-020 | AG53: DIR-USN (Expat) Labor
A54: ='Program Budget'!D189 -> Lodging and M&IE for Staff Leaders of Northern Tunisian Cooperatives to Attend Trainings | B54: ='Program Budget'!F189 -> Day | C54: ='Program Budget'!H189 -> 129 | D54: ='Program Budget'!G189 -> 0 | E54: 0 | F54: =C54*D54*E54 -> 0 | G54: =C54*1.07 -> 138.03 | H54: ='Program Budget'!K189 -> 6 | I54: 1 | J54: =G54*H54*I54 -> 828.18 | K54: =G54*1.07 -> 147.6921 | L54: ='Program Budget'!N189 -> 6 | M54: 1 | N54: =K54*L54*M54 -> 886.1526 | O54: =K54*1.07 -> 158.03055 | P54: ='Program Budget'!Q189 -> 0 | Q54: 0 | R54: =O54*P54*Q54 -> 0 | S54: =O54*1.07 -> 169.09269 | T54: ='Program Budget'!T189 -> 0 | U54: 0 | V54: =S54*T54*U54 -> 0 | W54: =F54+J54+N54+R54+V54 -> 1714.3326 | AE54: 180 | AF54: 50-01-2-020 | AG54: DIR-USN (Expat) Labor
A56: Subtotal: Travel | F56: =SUM(F43:F55) -> 7961 | J56: =SUM(J43:J55) -> 21781.99 | N56: =SUM(N43:N55) -> 15222.59 | R56: =SUM(R43:R55) -> 8724.7562 | V56: =SUM(V43:V55) -> 8155.7728 | W56: =+F56+J56+N56+R56+V56 -> 61846.109
A57: Professional Services
A58: ='Program Budget'!D168 -> Contract for Development of Materials for Communications Campaign (includes budget for videos, social media reels, etc.) | B58: ='Program Budget'!F168 -> Year | C58: ='Program Budget'!H168 -> 100000 | D58: ='Program Budget'!G168 -> 0.5 | E58: 1 | F58: =C58*D58*E58 -> 50000 | G58: =C58 -> 100000 | H58: ='Program Budget'!K168 -> 0.5 | I58: 1 | J58: =G58*H58*I58 -> 50000 | K58: =G58 -> 100000 | L58: ='Program Budget'!N168 -> 0 | M58: 0 | N58: =K58*L58*M58 -> 0 | O58: =K58 -> 100000 | P58: ='Program Budget'!Q168 -> 0 | Q58: 0 | R58: =O58*P58*Q58 -> 0 | S58: =O58 -> 100000 | T58: ='Program Budget'!T168 -> 0 | U58: 0 | V58: =S58*T58*U58 -> 0 | W58: =F58+J58+N58+R58+V58 -> 100000
A59: ='Program Budget'!D169 -> Contract for Communications Campaign Dissemination | B59: ='Program Budget'!F169 -> Year | C59: ='Program Budget'!H169 -> 25000 | D59: ='Program Budget'!G169 -> 0 | E59: 0 | F59: =C59*D59*E59 -> 0 | G59: =C59 -> 25000 | H59: ='Program Budget'!K169 -> 1 | I59: 1 | J59: =G59*H59*I59 -> 25000 | K59: =G59 -> 25000 | L59: ='Program Budget'!N169 -> 1 | M59: 1 | N59: =K59*L59*M59 -> 25000 | O59: =K59 -> 25000 | P59: ='Program Budget'!Q169 -> 1 | Q59: 1 | R59: =O59*P59*Q59 -> 25000 | S59: =O59 -> 25000 | T59: ='Program Budget'!T169 -> 1 | U59: 1 | V59: =S59*T59*U59 -> 25000 | W59: =F59+J59+N59+R59+V59 -> 100000
A60: ='Program Budget'!D170 -> Contract for Private Agriculture Service Providers (PASPs) to Manage Model Farms and Training for Farmer Field Days | B60: ='Program Budget'!F170 -> Day | C60: ='Program Budget'!H170 -> 700 | D60: ='Program Budget'!G170 -> 8 | E60: 1 | F60: =C60*D60*E60 -> 5600 | G60: =C60 -> 700 | H60: ='Program Budget'!K170 -> 16 | I60: 1 | J60: =G60*H60*I60 -> 11200 | K60: =G60 -> 700 | L60: ='Program Budget'!N170 -> 8 | M60: 1 | N60: =K60*L60*M60 -> 5600 | O60: =K60 -> 700 | P60: ='Program Budget'!Q170 -> 0 | Q60: 0 | R60: =O60*P60*Q60 -> 0 | S60: =O60 -> 700 | T60: ='Program Budget'!T170 -> 0 | U60: 0 | V60: =S60*T60*U60 -> 0 | W60: =F60+J60+N60+R60+V60 -> 22400
A61: ='Program Budget'!D171 -> Consultant for Producer Organization Capacity Building | B61: ='Program Budget'!F171 -> Month | C61: ='Program Budget'!H171 -> 4500 | D61: ='Program Budget'!G171 -> 0 | E61: 0 | F61: =C61*D61*E61 -> 0 | G61: =C61 -> 4500 | H61: ='Program Budget'!K171 -> 3 | I61: 1 | J61: =G61*H61*I61 -> 13500 | K61: =G61 -> 4500 | L61: ='Program Budget'!N171 -> 3 | M61: 1 | N61: =K61*L61*M61 -> 13500 | O61: =K61 -> 4500 | P61: ='Program Budget'!Q171 -> 0 | Q61: 0 | R61: =O61*P61*Q61 -> 0 | S61: =O61 -> 4500 | T61: ='Program Budget'!T171 -> 0 | U61: 0 | V61: =S61*T61*U61 -> 0 | W61: =F61+J61+N61+R61+V61 -> 27000
A62: ='Program Budget'!D172 -> Consultant (Financial & Legal) to Advise on Grant Mechanism and Blended Finance Structure | B62: ='Program Budget'!F172 -> Day | C62: ='Program Budget'!H172 -> 625 | D62: ='Program Budget'!G172 -> 20 | E62: 1 | F62: =C62*D62*E62 -> 12500 | G62: =C62 -> 625 | H62: ='Program Budget'!K172 -> 0 | I62: 0 | J62: =G62*H62*I62 -> 0 | K62: =G62 -> 625 | L62: ='Program Budget'!N172 -> 0 | M62: 0 | N62: =K62*L62*M62 -> 0 | O62: =K62 -> 625 | P62: ='Program Budget'!Q172 -> 0 | Q62: 0 | R62: =O62*P62*Q62 -> 0 | S62: =O62 -> 625 | T62: ='Program Budget'!T172 -> 0 | U62: 0 | V62: =S62*T62*U62 -> 0 | W62: =F62+J62+N62+R62+V62 -> 12500
A63: ='Program Budget'!D173 -> Security Services, Risk Assessments, & Security Assessment | B63: ='Program Budget'!F173 -> Year | C63: ='Program Budget'!H173 -> 5000 | D63: ='Program Budget'!G173 -> 1 | E63: 1 | F63: =C63*D63*E63 -> 5000 | G63: =C63 -> 5000 | H63: ='Program Budget'!K173 -> 1 | I63: 1 | J63: =G63*H63*I63 -> 5000 | K63: =G63 -> 5000 | L63: ='Program Budget'!N173 -> 1 | M63: 1 | N63: =K63*L63*M63 -> 5000 | O63: =K63 -> 5000 | P63: ='Program Budget'!Q173 -> 1 | Q63: 1 | R63: =O63*P63*Q63 -> 5000 | S63: =O63 -> 5000 | T63: ='Program Budget'!T173 -> 1 | U63: 1 | V63: =S63*T63*U63 -> 5000 | W63: =F63+J63+N63+R63+V63 -> 25000
A65: Subtotal: Professional Services/Contractual | F65: =SUM(F58:F64) -> 73100 | J65: =SUM(J58:J64) -> 104700 | N65: =SUM(N58:N64) -> 49100 | R65: =SUM(R58:R64) -> 30000 | V65: =SUM(V58:V64) -> 30000 | W65: =+F65+J65+N65+R65+V65 -> 286900
A66: Equipment (>$5000/unit)
A67: None | F67: =C67*D67*E67 -> 0 | J67: =G67*H67*I67 -> 0 | N67: =K67*L67*M67 -> 0 | R67: =O67*P67*Q67 -> 0 | V67: =S67*T67*U67 -> 0 | W67: =F67+J67+N67+R67+V67 -> 0 | AE67: 298 | AF67: 51-05-1-003 | AG67: DIR-Furniture
A68: Subtotal: Equipment | F68: =SUM(F67:F67) -> 0 | J68: =SUM(J67:J67) -> 0 | N68: =SUM(N67:N67) -> 0 | R68: =SUM(R67:R67) -> 0 | V68: =SUM(V67:V67) -> 0 | W68: =+F68+J68+N68+R68+V68 -> 0
A69: Office
A70: None | F70: =C70*D70*E70 -> 0 | J70: =G70*H70*I70 -> 0 | N70: =K70*L70*M70 -> 0 | R70: =O70*P70*Q70 -> 0 | V70: =S70*T70*U70 -> 0 | W70: =F70+J70+N70+R70+V70 -> 0
A71: Subtotal: Office | F71: =SUM(F67:F67) -> 0 | J71: =SUM(J67:J67) -> 0 | N71: =SUM(N67:N67) -> 0 | R71: =SUM(R67:R67) -> 0 | V71: =SUM(V67:V67) -> 0 | W71: =+F71+J71+N71+R71+V71 -> 0 | AE71: 236 | AF71: 51-02-1-001 | AG71: DIR-Prof. Serv Labor
A72: Supplies | AE72: 236 | AF72: 51-02-1-001 | AG72: DIR-Prof. Serv Labor
A73: ='Program Budget'!D177 -> Inputs for Model Farms (Demonstration Plots) Set-up and Maintenance | B73: ='Program Budget'!F177 -> Unit | C73: ='Program Budget'!H177 -> 8000 | D73: ='Program Budget'!G177 -> 2 | E73: 1 | F73: =C73*D73*E73 -> 16000 | G73: =C73 -> 8000 | H73: ='Program Budget'!K177 -> 2 | I73: 1 | J73: =G73*H73*I73 -> 16000 | K73: =G73 -> 8000 | L73: ='Program Budget'!N177 -> 0 | M73: 0 | N73: =K73*L73*M73 -> 0 | O73: =K73 -> 8000 | P73: ='Program Budget'!Q177 -> 0 | Q73: 0 | R73: =O73*P73*Q73 -> 0 | S73: =O73 -> 8000 | T73: ='Program Budget'!T177 -> 0 | U73: 0 | V73: =S73*T73*U73 -> 0 | W73: =F73+J73+N73+R73+V73 -> 32000
A74: ='Program Budget'!D178 -> Communication Costs for Publication of RFPs/RFAs | B74: ='Program Budget'!F178 -> Unit | C74: ='Program Budget'!H178 -> 500 | D74: ='Program Budget'!G178 -> 1 | E74: 1 | F74: =C74*D74*E74 -> 500 | G74: =C74 -> 500 | H74: ='Program Budget'!K178 -> 1 | I74: 1 | J74: =G74*H74*I74 -> 500 | K74: =G74 -> 500 | L74: ='Program Budget'!N178 -> 1 | M74: 1 | N74: =K74*L74*M74 -> 500 | O74: =K74 -> 500 | P74: ='Program Budget'!Q178 -> 1 | Q74: 1 | R74: =O74*P74*Q74 -> 500 | S74: =O74 -> 500 | T74: ='Program Budget'!T178 -> 0 | U74: 0 | V74: =S74*T74*U74 -> 0 | W74: =F74+J74+N74+R74+V74 -> 2000
A76: Subtotal: Supplies | F76: =SUM(F73:F75) -> 16500 | J76: =SUM(J73:J75) -> 16500 | N76: =SUM(N73:N75) -> 500 | R76: =SUM(R73:R75) -> 500 | V76: =SUM(V73:V75) -> 0 | W76: =+F76+J76+N76+R76+V76 -> 34000
A77: Other Direct Cost
A78: Grants
A79: ='Program Budget'!D195 -> Climate Smart Agriculture Adaptations Grants | B79: ='Program Budget'!F195 -> Grant | C79: ='Program Budget'!H195 -> 1425 | D79: ='Program Budget'!G195 -> 0 | E79: 0 | F79: =C79*D79*E79 -> 0 | G79: =C79 -> 1425 | H79: ='Program Budget'!K195 -> 400 | I79: 1 | J79: =G79*H79*I79 -> 570000 | K79: =G79 -> 1425 | L79: ='Program Budget'!N195 -> 533 | M79: 1 | N79: =K79*L79*M79 -> 759525 | O79: =K79 -> 1425 | P79: ='Program Budget'!Q195 -> 400 | Q79: 1 | R79: =O79*P79*Q79 -> 570000 | S79: =O79 -> 1425 | T79: ='Program Budget'!T195 -> 0 | U79: 0 | V79: =S79*T79*U79 -> 0 | W79: =F79+J79+N79+R79+V79 -> 1899525
A80: Training
A81: ='Program Budget'!D197 -> Farmer Field School Trainings (Materials, Food, & Refreshments) | B81: ='Program Budget'!F197 -> Day | C81: ='Program Budget'!H197 -> 900 | D81: ='Program Budget'!G197 -> 8 | E81: 1 | F81: =C81*D81*E81 -> 7200 | G81: =C81 -> 900 | H81: ='Program Budget'!K197 -> 16 | I81: 1 | J81: =G81*H81*I81 -> 14400 | K81: =G81 -> 900 | L81: ='Program Budget'!N197 -> 8 | M81: 1 | N81: =K81*L81*M81 -> 7200 | O81: =K81 -> 900 | P81: ='Program Budget'!Q197 -> 0 | Q81: 0 | R81: =O81*P81*Q81 -> 0 | S81: =O81 -> 900 | T81: ='Program Budget'!T197 -> 0 | U81: 0 | V81: =S81*T81*U81 -> 0 | W81: =F81+J81+N81+R81+V81 -> 28800
A82: ='Program Budget'!D198 -> Trainings for Producer Organizations to Boost Climate Smart Agriculture Adoption - 3 Days | B82: ='Program Budget'!F198 -> Training | C82: ='Program Budget'!H198 -> 1890 | D82: ='Program Budget'!G198 -> 0 | E82: 0 | F82: =C82*D82*E82 -> 0 | G82: =C82 -> 1890 | H82: ='Program Budget'!K198 -> 2 | I82: 1 | J82: =G82*H82*I82 -> 3780 | K82: =G82 -> 1890 | L82: ='Program Budget'!N198 -> 2 | M82: 1 | N82: =K82*L82*M82 -> 3780 | O82: =K82 -> 1890 | P82: ='Program Budget'!Q198 -> 0 | Q82: 0 | R82: =O82*P82*Q82 -> 0 | S82: =O82 -> 1890 | T82: ='Program Budget'!T198 -> 0 | U82: 0 | V82: =S82*T82*U82 -> 0 | W82: =F82+J82+N82+R82+V82 -> 7560
A83: ='Program Budget'!D199 -> Workshop with Stakeholders on Grants Mechanism | B83: ='Program Budget'!F199 -> Workshop | C83: ='Program Budget'!H199 -> 1060 | D83: ='Program Budget'!G199 -> 2 | E83: 1 | F83: =C83*D83*E83 -> 2120 | G83: =C83 -> 1060 | H83: ='Program Budget'!K199 -> 0 | I83: 0 | J83: =G83*H83*I83 -> 0 | K83: =G83 -> 1060 | L83: ='Program Budget'!N199 -> 0 | M83: 0 | N83: =K83*L83*M83 -> 0 | O83: =K83 -> 1060 | P83: ='Program Budget'!Q199 -> 0 | Q83: 0 | R83: =O83*P83*Q83 -> 0 | S83: =O83 -> 1060 | T83: ='Program Budget'!T199 -> 0 | U83: 0 | V83: =S83*T83*U83 -> 0 | W83: =F83+J83+N83+R83+V83 -> 2120
A84: Registration and Events
A85: ='Program Budget'!D201 -> Registration for Agricultural Events and Booths | B85: ='Program Budget'!F201 -> Event | C85: ='Program Budget'!H201 -> 2500 | D85: ='Program Budget'!G201 -> 0 | E85: 0 | F85: =C85*D85*E85 -> 0 | G85: =C85 -> 2500 | H85: ='Program Budget'!K201 -> 2 | I85: 1 | J85: =G85*H85*I85 -> 5000 | K85: =G85 -> 2500 | L85: ='Program Budget'!N201 -> 2 | M85: 1 | N85: =K85*L85*M85 -> 5000 | O85: =K85 -> 2500 | P85: ='Program Budget'!Q201 -> 2 | Q85: 1 | R85: =O85*P85*Q85 -> 5000 | S85: =O85 -> 2500 | T85: ='Program Budget'!T201 -> 2 | U85: 1 | V85: =S85*T85*U85 -> 5000 | W85: =F85+J85+N85+R85+V85 -> 20000
A86: ='Program Budget'!D202 -> Printing Materials to Distribute at Local Agriculture Events | B86: ='Program Budget'!F202 -> Unit | C86: ='Program Budget'!H202 -> 15000 | D86: ='Program Budget'!G202 -> 0 | E86: 0 | F86: =C86*D86*E86 -> 0 | G86: =C86 -> 15000 | H86: ='Program Budget'!K202 -> 1 | I86: 1 | J86: =G86*H86*I86 -> 15000 | K86: =G86 -> 15000 | L86: ='Program Budget'!N202 -> 0 | M86: 0 | N86: =K86*L86*M86 -> 0 | O86: =K86 -> 15000 | P86: ='Program Budget'!Q202 -> 0 | Q86: 0 | R86: =O86*P86*Q86 -> 0 | S86: =O86 -> 15000 | T86: ='Program Budget'!T202 -> 0 | U86: 0 | V86: =S86*T86*U86 -> 0 | W86: =F86+J86+N86+R86+V86 -> 15000
A88: Subtotal: Other Direct Cost | F88: =SUM(F77:F87) -> 9320 | J88: =SUM(J77:J87) -> 608180 | N88: =SUM(N77:N87) -> 775505 | R88: =SUM(R77:R87) -> 575000 | V88: =SUM(V77:V87) -> 5000 | W88: =+F88+J88+N88+R88+V88 -> 1973005 | AE88: 250 | AF88: 51-02-2-008 | AG88: DIR-Security
AE89: 317 | AF89: 51-08-1-002 | AG89: DIR-Office Make Ready
A90: Total Direct Cost | F90: =F33+F42+F56+F71+F76+F65+F88+F68 -> 294503.25 | J90: =J33+J42+J56+J71+J76+J65+J88+J68 -> 1073975.6 | N90: =N33+N42+N56+N71+N76+N65+N88+N68 -> 1173908 | R90: =R33+R42+R56+R71+R76+R65+R88+R68 -> 964484.17 | V90: =V33+V42+V56+V71+V76+V65+V88+V68 -> 354054.16 | W90: =W33+W42+W56+W71+W76+W65+W88 -> 3860925.1 | AE90: 318 | AF90: 51-08-1-003 | AG90: DIR-Office Maintenance
A92: Indirect Costs
A93: ICR on Administration | B93: % | C93: 0 | D93: 0 | E93: 0.2828 | F93: =C93*D93*E93 -> 0 | G93: 0 | H93: 0 | I93: 0.2828 | J93: =G93*H93*I93 -> 0 | K93: 0 | L93: 0 | M93: 0.2828 | N93: =K93*L93*M93 -> 0 | O93: 0 | P93: 0 | Q93: 0.2828 | R93: =O93*P93*Q93 -> 0 | S93: 0 | T93: 0 | U93: 0.2828 | V93: =S93*T93*U93 -> 0 | W93: =F93+J93+N93+R93+V93 -> 0
A94: ICR on Activities | B94: % | C94: =F90 -> 294503.25 | D94: 1 | E94: 0.2828 | F94: =C94*D94*E94 -> 83285.519 | G94: =J90 -> 1073975.6 | H94: 1 | I94: 0.2828 | J94: =G94*H94*I94 -> 303720.29 | K94: =N90 -> 1173908 | L94: 1 | M94: 0.2828 | N94: =K94*L94*M94 -> 331981.18 | O94: =R90 -> 964484.17 | P94: 1 | Q94: 0.2828 | R94: =O94*P94*Q94 -> 272756.12 | S94: =V90 -> 354054.16 | T94: 1 | U94: 0.2828 | V94: =S94*T94*U94 -> 100126.52 | W94: =F94+J94+N94+R94+V94 -> 1091869.6
A96: Subtotal Indirect Cost | F96: =SUM(F93:F95) -> 83285.519 | J96: =SUM(J93:J95) -> 303720.29 | N96: =SUM(N93:N95) -> 331981.18 | R96: =SUM(R93:R95) -> 272756.12 | V96: =SUM(V93:V95) -> 100126.52 | W96: =SUM(W93:W95) -> 1091869.6
A98: Total Estimated Cost (Direct Cost + Indirect Cost) | F98: =F90+F96 -> 377788.77 | J98: =J90+J96 -> 1377695.9 | N98: =N90+N96 -> 1505889.2 | R98: =R90+R96 -> 1237240.3 | V98: =V90+V96 -> 454180.68 | W98: =F98+J98+N98+R98+V98 -> 4952794.8
A99: ='Program Budget'!D206 -> Cost Share for Climate Smart Agriculture Adaptations Grants | B99: ='Program Budget'!F206 -> Unit | C99: ='Program Budget'!H206 -> 71.25 | D99: ='Program Budget'!G206 -> 0 | E99: 0 | F99: =C99*D99*E99 -> 0 | G99: =C99 -> 71.25 | H99: ='Program Budget'!K206 -> 400 | I99: 1 | J99: =G99*H99*I99 -> 28500 | K99: =G99 -> 71.25 | L99: ='Program Budget'!N206 -> 533 | M99: 1 | N99: =K99*L99*M99 -> 37976.25 | O99: =K99 -> 71.25 | P99: ='Program Budget'!Q206 -> 400 | Q99: 1 | R99: =O99*P99*Q99 -> 28500 | S99: =O99 -> 71.25 | T99: ='Program Budget'!T206 -> 0 | U99: 0 | V99: =S99*T99*U99 -> 0 | W99: =F99+J99+N99+R99+V99 -> 94976.25
A100: ='Program Budget'!D207 -> Donated Materials and Time from APIA for Events | B100: ='Program Budget'!F207 -> Event | C100: ='Program Budget'!H207 -> 249.95 | D100: ='Program Budget'!G207 -> 1 | E100: 1 | F100: =C100*D100*E100 -> 249.95 | G100: =C100 -> 249.95 | H100: ='Program Budget'!K207 -> 1 | I100: 1 | J100: =G100*H100*I100 -> 249.95 | K100: =G100 -> 249.95 | L100: ='Program Budget'!N207 -> 1 | M100: 1 | N100: =K100*L100*M100 -> 249.95 | O100: =K100 -> 249.95 | P100: ='Program Budget'!Q207 -> 1 | Q100: 1 | R100: =O100*P100*Q100 -> 249.95 | S100: =O100 -> 249.95 | T100: ='Program Budget'!T207 -> 1 | U100: 1 | V100: =S100*T100*U100 -> 249.95 | W100: =F100+J100+N100+R100+V100 -> 1249.75
A101: ='Program Budget'!D208 -> Venue Space for Grant Mechanism Design Meeting | B101: ='Program Budget'!F208 -> Day | C101: ='Program Budget'!H208 -> 125 | D101: ='Program Budget'!G208 -> 2 | E101: 1 | F101: =C101*D101*E101 -> 250 | G101: =C101 -> 125 | H101: ='Program Budget'!K208 -> 0 | I101: 0 | J101: =G101*H101*I101 -> 0 | K101: =G101 -> 125 | L101: ='Program Budget'!N208 -> 0 | M101: 0 | N101: =K101*L101*M101 -> 0 | O101: =K101 -> 125 | P101: ='Program Budget'!Q208 -> 0 | Q101: 0 | R101: =O101*P101*Q101 -> 0 | S101: =O101 -> 125 | T101: ='Program Budget'!T208 -> 0 | U101: 0 | V101: =S101*T101*U101 -> 0 | W101: =F101+J101+N101+R101+V101 -> 250
A102: Total Estimated Cost (Direct Cost + Indirect Cost+ Cost Share) | F102: =F98+F99 -> 377788.77 | J102: =J98+J99 -> 1406195.9 | N102: =N98+N99 -> 1543865.4 | R102: =R98+R99 -> 1265740.3 | V102: =V98+V99 -> 454180.68 | W102: =F102+J102+N102+R102+V102 -> 5047771
A104: Anticipated Program Income (baked in costs and this is for reference)

Sheet Activity 2
A2: Item | B2: Type of Unit | C2: Year 1 | G2: Year 2 | K2: Year 3 | O2: Year 4 | S2: Year 5 | W2: Total
C3: Cost | D3: Quantity | E3: Percent Allocated | F3: Total | G3: Cost | H3: Quantity | I3: Percent Allocated | J3: Total | K3: Cost | L3: Quantity | M3: Percent Allocated | N3: Total | O3: Cost | P3: Quantity | Q3: Percent Allocated | R3: Total | S3: Cost | T3: Quantity | U3: Percent Allocated | V3: Total | AF3: Chart of Accounts
A4: Direct Costs | AE4: Line# | AF4: Account | AG4: Account Name
A5: Salaries
A6: USN/TCN Staff
A7: None | F7: =C7*D7*E7 -> 0 | J7: =G7*H7*I7 -> 0 | N7: =K7*L7*M7 -> 0 | R7: =O7*P7*Q7 -> 0 | V7: =S7*T7*U7 -> 0 | W7: =F7+J7+N7+R7+V7 -> 0
A8: Total: Expatriate Salaries & Wages | F8: =SUM(F7:F7) -> 0 | J8: =SUM(J7:J7) -> 0 | N8: =SUM(N7:N7) -> 0 | R8: =SUM(R7:R7) -> 0 | V8: =SUM(V7:V7) -> 0 | W8: =+F8+J8+N8+R8+V8 -> 0
A9: CCN Staff
A10: ='Program Budget'!D12 -> Key Personnel: Chief of Party - Ms. Rym Ayari | B10: ='Program Budget'!F216 -> Month | C10: ='Program Budget'!H12 -> 13000 | D10: ='Program Budget'!G12 -> 12 | E10: ='Program Budget'!E216 -> 0.25 | F10: =C10*D10*E10 -> 39000 | G10: =C10*1.05 -> 13650 | H10: ='Program Budget'!K12 -> 12 | I10: ='Program Budget'!J216 -> 0.3 | J10: =G10*H10*I10 -> 49140 | K10: =G10*1.05 -> 14332.5 | L10: ='Program Budget'!N12 -> 12 | M10: ='Program Budget'!M216 -> 0.3 | N10: =K10*L10*M10 -> 51597 | O10: =K10*1.05 -> 15049.125 | P10: ='Program Budget'!Q12 -> 12 | Q10: ='Program Budget'!P216 -> 0.3 | R10: =O10*P10*Q10 -> 54176.85 | S10: =O10*1.05 -> 15801.581 | T10: ='Program Budget'!T12 -> 12 | U10: ='Program Budget'!S216 -> 0.3 | V10: =S10*T10*U10 -> 56885.692 | W10: =F10+J10+N10+R10+V10 -> 250799.54
A11: ='Program Budget'!D13 -> Key Personnel: Technical Director | B11: ='Program Budget'!F217 -> Month | C11: ='Program Budget'!H13 -> 3916.6667 | D11: ='Program Budget'!G13 -> 9 | E11: ='Program Budget'!E217 -> 0.25 | F11: =C11*D11*E11 -> 8812.5 | G11: =C11*1.05 -> 4112.5 | H11: ='Program Budget'!K13 -> 12 | I11: ='Program Budget'!J217 -> 0.35 | J11: =G11*H11*I11 -> 17272.5 | K11: =G11*1.05 -> 4318.125 | L11: ='Program Budget'!N13 -> 12 | M11: ='Program Budget'!M217 -> 0.32 | N11: =K11*L11*M11 -> 16581.6 | O11: =K11*1.05 -> 4534.0312 | P11: ='Program Budget'!Q13 -> 12 | Q11: ='Program Budget'!P217 -> 0.32 | R11: =O11*P11*Q11 -> 17410.68 | S11: =O11*1.05 -> 4760.7328 | T11: ='Program Budget'!T13 -> 9 | U11: ='Program Budget'!S217 -> 0.32 | V11: =S11*T11*U11 -> 13710.91 | W11: =F11+J11+N11+R11+V11 -> 73788.19 | AE11: 180 | AF11: 50-01-2-020 | AG11: DIR-USN (Expat) Labor
A12: ='Program Budget'!D14 -> Technical Lead Component 1 | B12: ='Program Budget'!F218 -> Month | C12: ='Program Budget'!H14 -> 2500 | D12: ='Program Budget'!G14 -> 6 | E12: ='Program Budget'!E218 -> 0 | F12: =C12*D12*E12 -> 0 | G12: =C12*1.05 -> 2625 | H12: ='Program Budget'!K14 -> 12 | I12: ='Program Budget'!J218 -> 0 | J12: =G12*H12*I12 -> 0 | K12: =G12*1.05 -> 2756.25 | L12: ='Program Budget'!N14 -> 12 | M12: ='Program Budget'!M218 -> 0 | N12: =K12*L12*M12 -> 0 | O12: =K12*1.05 -> 2894.0625 | P12: ='Program Budget'!Q14 -> 12 | Q12: ='Program Budget'!P218 -> 0 | R12: =O12*P12*Q12 -> 0 | S12: =O12*1.05 -> 3038.7656 | T12: ='Program Budget'!T14 -> 9 | U12: ='Program Budget'!S218 -> 0 | V12: =S12*T12*U12 -> 0 | W12: =F12+J12+N12+R12+V12 -> 0 | AE12: 180 | AF12: 50-01-2-020 | AG12: DIR-USN (Expat) Labor
A13: ='Program Budget'!D15 -> Technical Lead Component 2 | B13: ='Program Budget'!F219 -> Month | C13: ='Program Budget'!H15 -> 2500 | D13: ='Program Budget'!G15 -> 6 | E13: ='Program Budget'!E219 -> 0.8 | F13: =C13*D13*E13 -> 12000 | G13: =C13*1.05 -> 2625 | H13: ='Program Budget'!K15 -> 12 | I13: ='Program Budget'!J219 -> 1 | J13: =G13*H13*I13 -> 31500 | K13: =G13*1.05 -> 2756.25 | L13: ='Program Budget'!N15 -> 12 | M13: ='Program Budget'!M219 -> 1 | N13: =K13*L13*M13 -> 33075 | O13: =K13*1.05 -> 2894.0625 | P13: ='Program Budget'!Q15 -> 12 | Q13: ='Program Budget'!P219 -> 1 | R13: =O13*P13*Q13 -> 34728.75 | S13: =O13*1.05 -> 3038.7656 | T13: ='Program Budget'!T15 -> 9 | U13: ='Program Budget'!S219 -> 1 | V13: =S13*T13*U13 -> 27348.891 | W13: =F13+J13+N13+R13+V13 -> 138652.64 | AE13: 180 | AF13: 50-01-2-020 | AG13: DIR-USN (Expat) Labor
A14: ='Program Budget'!D16 -> Technical Lead Component 3 | B14: ='Program Budget'!F220 -> Month | C14: ='Program Budget'!H16 -> 2500 | D14: ='Program Budget'!G16 -> 6 | E14: ='Program Budget'!E220 -> 0 | F14: =C14*D14*E14 -> 0 | G14: =C14*1.05 -> 2625 | H14: ='Program Budget'!K16 -> 12 | I14: ='Program Budget'!J220 -> 0 | J14: =G14*H14*I14 -> 0 | K14: =G14*1.05 -> 2756.25 | L14: ='Program Budget'!N16 -> 12 | M14: ='Program Budget'!M220 -> 0 | N14: =K14*L14*M14 -> 0 | O14: =K14*1.05 -> 2894.0625 | P14: ='Program Budget'!Q16 -> 12 | Q14: ='Program Budget'!P220 -> 0 | R14: =O14*P14*Q14 -> 0 | S14: =O14*1.05 -> 3038.7656 | T14: ='Program Budget'!T16 -> 9 | U14: ='Program Budget'!S220 -> 0 | V14: =S14*T14*U14 -> 0 | W14: =F14+J14+N14+R14+V14 -> 0
A15: ='Program Budget'!D17 -> Technical Specialist Component 1 | B15: ='Program Budget'!F221 -> Month | C15: ='Program Budget'!H17 -> 1833.3333 | D15: ='Program Budget'!G17 -> 6 | E15: ='Program Budget'!E221 -> 0 | F15: =C15*D15*E15 -> 0 | G15: =C15*1.05 -> 1925 | H15: ='Program Budget'!K17 -> 12 | I15: ='Program Budget'!J221 -> 0 | J15: =G15*H15*I15 -> 0 | K15: =G15*1.05 -> 2021.25 | L15: ='Program Budget'!N17 -> 12 | M15: ='Program Budget'!M221 -> 0 | N15: =K15*L15*M15 -> 0 | O15: =K15*1.05 -> 2122.3125 | P15: ='Program Budget'!Q17 -> 12 | Q15: ='Program Budget'!P221 -> 0 | R15: =O15*P15*Q15 -> 0 | S15: =O15*1.05 -> 2228.4281 | T15: ='Program Budget'!T17 -> 6 | U15: ='Program Budget'!S221 -> 0 | V15: =S15*T15*U15 -> 0 | W15: =F15+J15+N15+R15+V15 -> 0
A16: ='Program Budget'!D18 -> Technical Specialist Component 2 | B16: ='Program Budget'!F222 -> Month | C16: ='Program Budget'!H18 -> 1833.3333 | D16: ='Program Budget'!G18 -> 6 | E16: ='Program Budget'!E222 -> 0.8 | F16: =C16*D16*E16 -> 8800 | G16: =C16*1.05 -> 1925 | H16: ='Program Budget'!K18 -> 12 | I16: ='Program Budget'!J222 -> 1 | J16: =G16*H16*I16 -> 23100 | K16: =G16*1.05 -> 2021.25 | L16: ='Program Budget'!N18 -> 12 | M16: ='Program Budget'!M222 -> 1 | N16: =K16*L16*M16 -> 24255 | O16: =K16*1.05 -> 2122.3125 | P16: ='Program Budget'!Q18 -> 12 | Q16: ='Program Budget'!P222 -> 1 | R16: =O16*P16*Q16 -> 25467.75 | S16: =O16*1.05 -> 2228.4281 | T16: ='Program Budget'!T18 -> 6 | U16: ='Program Budget'!S222 -> 1 | V16: =S16*T16*U16 -> 13370.569 | W16: =F16+J16+N16+R16+V16 -> 94993.319 | AE16: 180 | AF16: 50-01-2-020 | AG16: DIR-USN (Expat) Labor
A17: ='Program Budget'!D19 -> Technical Specialist Component 3 | B17: ='Program Budget'!F223 -> Month | C17: ='Program Budget'!H19 -> 1833.3333 | D17: ='Program Budget'!G19 -> 6 | E17: ='Program Budget'!E223 -> 0 | F17: =C17*D17*E17 -> 0 | G17: =C17*1.05 -> 1925 | H17: ='Program Budget'!K19 -> 12 | I17: ='Program Budget'!J223 -> 0 | J17: =G17*H17*I17 -> 0 | K17: =G17*1.05 -> 2021.25 | L17: ='Program Budget'!N19 -> 12 | M17: ='Program Budget'!M223 -> 0 | N17: =K17*L17*M17 -> 0 | O17: =K17*1.05 -> 2122.3125 | P17: ='Program Budget'!Q19 -> 12 | Q17: ='Program Budget'!P223 -> 0 | R17: =O17*P17*Q17 -> 0 | S17: =O17*1.05 -> 2228.4281 | T17: ='Program Budget'!T19 -> 6 | U17: ='Program Budget'!S223 -> 0 | V17: =S17*T17*U17 -> 0 | W17: =F17+J17+N17+R17+V17 -> 0
A18: ='Program Budget'!D20 -> Capacity Building Specialist (2) | B18: ='Program Budget'!F224 -> Month | C18: ='Program Budget'!H20 -> 3333.3333 | D18: ='Program Budget'!G20 -> 4 | E18: ='Program Budget'!E224 -> 0 | F18: =C18*D18*E18 -> 0 | G18: =C18*1.05 -> 3500 | H18: ='Program Budget'!K20 -> 12 | I18: ='Program Budget'!J224 -> 0 | J18: =G18*H18*I18 -> 0 | K18: =G18*1.05 -> 3675 | L18: ='Program Budget'!N20 -> 12 | M18: ='Program Budget'!M224 -> 0 | N18: =K18*L18*M18 -> 0 | O18: =K18*1.05 -> 3858.75 | P18: ='Program Budget'!Q20 -> 12 | Q18: ='Program Budget'!P224 -> 0 | R18: =O18*P18*Q18 -> 0 | S18: =O18*1.05 -> 4051.6875 | T18: ='Program Budget'!T20 -> 5 | U18: ='Program Budget'!S224 -> 0 | V18: =S18*T18*U18 -> 0 | W18: =F18+J18+N18+R18+V18 -> 0
A19: ='Program Budget'!D21 -> Sociocultural and Gender Specialist | B19: ='Program Budget'!F225 -> Month | C19: ='Program Budget'!H21 -> 1833.3333 | D19: ='Program Budget'!G21 -> 7 | E19: ='Program Budget'!E225 -> 0.25 | F19: =C19*D19*E19 -> 3208.3333 | G19: =C19*1.05 -> 1925 | H19: ='Program Budget'!K21 -> 12 | I19: ='Program Budget'!J225 -> 0.35 | J19: =G19*H19*I19 -> 8085 | K19: =G19*1.05 -> 2021.25 | L19: ='Program Budget'!N21 -> 12 | M19: ='Program Budget'!M225 -> 0.35 | N19: =K19*L19*M19 -> 8489.25 | O19: =K19*1.05 -> 2122.3125 | P19: ='Program Budget'!Q21 -> 12 | Q19: ='Program Budget'!P225 -> 0.35 | R19: =O19*P19*Q19 -> 8913.7125 | S19: =O19*1.05 -> 2228.4281 | T19: ='Program Budget'!T21 -> 9 | U19: ='Program Budget'!S225 -> 0.35 | V19: =S19*T19*U19 -> 7019.5486 | W19: =F19+J19+N19+R19+V19 -> 35715.844
A20: ='Program Budget'!D22 -> Sociocultural and Gender Officers (3) | B20: ='Program Budget'!F226 -> Month | C20: ='Program Budget'!H22 -> 3750 | D20: ='Program Budget'!G22 -> 7 | E20: ='Program Budget'!E226 -> 0.25 | F20: =C20*D20*E20 -> 6562.5 | G20: =C20*1.05 -> 3937.5 | H20: ='Program Budget'!K22 -> 12 | I20: ='Program Budget'!J226 -> 0.35 | J20: =G20*H20*I20 -> 16537.5 | K20: =G20*1.05 -> 4134.375 | L20: ='Program Budget'!N22 -> 12 | M20: ='Program Budget'!M226 -> 0.35 | N20: =K20*L20*M20 -> 17364.375 | O20: =K20*1.05 -> 4341.0938 | P20: ='Program Budget'!Q22 -> 12 | Q20: ='Program Budget'!P226 -> 0.35 | R20: =O20*P20*Q20 -> 18232.594 | S20: =O20*1.05 -> 4558.1484 | T20: ='Program Budget'!T22 -> 9 | U20: ='Program Budget'!S226 -> 0.35 | V20: =S20*T20*U20 -> 14358.168 | W20: =F20+J20+N20+R20+V20 -> 73055.136
A21: ='Program Budget'!D23 -> Communications Specialists | B21: ='Program Budget'!F227 -> Month | C21: ='Program Budget'!H23 -> 1500 | D21: ='Program Budget'!G23 -> 7 | E21: ='Program Budget'!E227 -> 0.25 | F21: =C21*D21*E21 -> 2625 | G21: =C21*1.05 -> 1575 | H21: ='Program Budget'!K23 -> 12 | I21: ='Program Budget'!J227 -> 0.3 | J21: =G21*H21*I21 -> 5670 | K21: =G21*1.05 -> 1653.75 | L21: ='Program Budget'!N23 -> 12 | M21: ='Program Budget'!M227 -> 0.3 | N21: =K21*L21*M21 -> 5953.5 | O21: =K21*1.05 -> 1736.4375 | P21: ='Program Budget'!Q23 -> 12 | Q21: ='Program Budget'!P227 -> 0.3 | R21: =O21*P21*Q21 -> 6251.175 | S21: =O21*1.05 -> 1823.2594 | T21: ='Program Budget'!T23 -> 10 | U21: ='Program Budget'!S227 -> 0.3 | V21: =S21*T21*U21 -> 5469.7781 | W21: =F21+J21+N21+R21+V21 -> 25969.453 | AE21: 180 | AF21: 50-01-2-020 | AG21: DIR-USN (Expat) Labor
A22: ='Program Budget'!D24 -> M&E Director | B22: ='Program Budget'!F228 -> Month | C22: ='Program Budget'!H24 -> 3916.6667 | D22: ='Program Budget'!G24 -> 9 | E22: ='Program Budget'!E228 -> 0.25 | F22: =C22*D22*E22 -> 8812.5 | G22: =C22*1.05 -> 4112.5 | H22: ='Program Budget'!K24 -> 12 | I22: ='Program Budget'!J228 -> 0.3 | J22: =G22*H22*I22 -> 14805 | K22: =G22*1.05 -> 4318.125 | L22: ='Program Budget'!N24 -> 12 | M22: ='Program Budget'!M228 -> 0.3 | N22: =K22*L22*M22 -> 15545.25 | O22: =K22*1.05 -> 4534.0312 | P22: ='Program Budget'!Q24 -> 12 | Q22: ='Program Budget'!P228 -> 0.3 | R22: =O22*P22*Q22 -> 16322.512 | S22: =O22*1.05 -> 4760.7328 | T22: ='Program Budget'!T24 -> 12 | U22: ='Program Budget'!S228 -> 0.3 | V22: =S22*T22*U22 -> 17138.638 | W22: =F22+J22+N22+R22+V22 -> 72623.901 | AE22: 180 | AF22: 50-01-2-020 | AG22: DIR-USN (Expat) Labor
A23: ='Program Budget'!D25 -> M&E Specialist | B23: ='Program Budget'!F229 -> Month | C23: ='Program Budget'!H25 -> 1833.3333 | D23: ='Program Budget'!G25 -> 8 | E23: ='Program Budget'!E229 -> 0.25 | F23: =C23*D23*E23 -> 3666.6667 | G23: =C23*1.05 -> 1925 | H23: ='Program Budget'!K25 -> 12 | I23: ='Program Budget'!J229 -> 0.3 | J23: =G23*H23*I23 -> 6930 | K23: =G23*1.05 -> 2021.25 | L23: ='Program Budget'!N25 -> 12 | M23: ='Program Budget'!M229 -> 0.3 | N23: =K23*L23*M23 -> 7276.5 | O23: =K23*1.05 -> 2122.3125 | P23: ='Program Budget'!Q25 -> 12 | Q23: ='Program Budget'!P229 -> 0.3 | R23: =O23*P23*Q23 -> 7640.325 | S23: =O23*1.05 -> 2228.4281 | T23: ='Program Budget'!T25 -> 10 | U23: ='Program Budget'!S229 -> 0.3 | V23: =S23*T23*U23 -> 6685.2844 | W23: =F23+J23+N23+R23+V23 -> 32198.776 | AE23: 180 | AF23: 50-01-2-020 | AG23: DIR-USN (Expat) Labor
A24: ='Program Budget'!D26 -> Key Personnel: Finance Director | B24: ='Program Budget'!F230 -> Month | C24: ='Program Budget'!H26 -> 3916.6667 | D24: ='Program Budget'!G26 -> 11 | E24: ='Program Budget'!E230 -> 0.25 | F24: =C24*D24*E24 -> 10770.833 | G24: =C24*1.05 -> 4112.5 | H24: ='Program Budget'!K26 -> 12 | I24: ='Program Budget'!J230 -> 0.25 | J24: =G24*H24*I24 -> 12337.5 | K24: =G24*1.05 -> 4318.125 | L24: ='Program Budget'!N26 -> 12 | M24: ='Program Budget'!M230 -> 0.25 | N24: =K24*L24*M24 -> 12954.375 | O24: =K24*1.05 -> 4534.0312 | P24: ='Program Budget'!Q26 -> 12 | Q24: ='Program Budget'!P230 -> 0.25 | R24: =O24*P24*Q24 -> 13602.094 | S24: =O24*1.05 -> 4760.7328 | T24: ='Program Budget'!T26 -> 12 | U24: ='Program Budget'!S230 -> 0.25 | V24: =S24*T24*U24 -> 14282.198 | W24: =F24+J24+N24+R24+V24 -> 63947.001 | AE24: 180 | AF24: 50-01-2-020 | AG24: DIR-USN (Expat) Labor
A25: ='Program Budget'!D27 -> Contracts & Compliance Specialist | B25: ='Program Budget'!F231 -> Month | C25: ='Program Budget'!H27 -> 1833.3333 | D25: ='Program Budget'!G27 -> 9 | E25: ='Program Budget'!E231 -> 0.25 | F25: =C25*D25*E25 -> 4125 | G25: =C25*1.05 -> 1925 | H25: ='Program Budget'!K27 -> 12 | I25: ='Program Budget'!J231 -> 0.25 | J25: =G25*H25*I25 -> 5775 | K25: =G25*1.05 -> 2021.25 | L25: ='Program Budget'!N27 -> 12 | M25: ='Program Budget'!M231 -> 0.25 | N25: =K25*L25*M25 -> 6063.75 | O25: =K25*1.05 -> 2122.3125 | P25: ='Program Budget'!Q27 -> 12 | Q25: ='Program Budget'!P231 -> 0.25 | R25: =O25*P25*Q25 -> 6366.9375 | S25: =O25*1.05 -> 2228.4281 | T25: ='Program Budget'!T27 -> 12 | U25: ='Program Budget'!S231 -> 0.25 | V25: =S25*T25*U25 -> 6685.2844 | W25: =F25+J25+N25+R25+V25 -> 29015.972
A26: ='Program Budget'!D28 -> Grants & Procurement Officer (2) | B26: ='Program Budget'!F232 -> Month | C26: ='Program Budget'!H28 -> 2500 | D26: ='Program Budget'!G28 -> 9 | E26: ='Program Budget'!E232 -> 0.25 | F26: =C26*D26*E26 -> 5625 | G26: =C26*1.05 -> 2625 | H26: ='Program Budget'!K28 -> 12 | I26: ='Program Budget'!J232 -> 0.25 | J26: =G26*H26*I26 -> 7875 | K26: =G26*1.05 -> 2756.25 | L26: ='Program Budget'!N28 -> 12 | M26: ='Program Budget'!M232 -> 0.25 | N26: =K26*L26*M26 -> 8268.75 | O26: =K26*1.05 -> 2894.0625 | P26: ='Program Budget'!Q28 -> 12 | Q26: ='Program Budget'!P232 -> 0.25 | R26: =O26*P26*Q26 -> 8682.1875 | S26: =O26*1.05 -> 3038.7656 | T26: ='Program Budget'!T28 -> 12 | U26: ='Program Budget'!S232 -> 0.25 | V26: =S26*T26*U26 -> 9116.2969 | W26: =F26+J26+N26+R26+V26 -> 39567.234 | AE26: 180 | AF26: 50-01-2-020 | AG26: DIR-USN (Expat) Labor
A27: ='Program Budget'!D29 -> Accountant | B27: ='Program Budget'!F233 -> Month | C27: ='Program Budget'!H29 -> 1666.6667 | D27: ='Program Budget'!G29 -> 10 | E27: ='Program Budget'!E233 -> 0.25 | F27: =C27*D27*E27 -> 4166.6667 | G27: =C27*1.05 -> 1750 | H27: ='Program Budget'!K29 -> 12 | I27: ='Program Budget'!J233 -> 0.25 | J27: =G27*H27*I27 -> 5250 | K27: =G27*1.05 -> 1837.5 | L27: ='Program Budget'!N29 -> 12 | M27: ='Program Budget'!M233 -> 0.25 | N27: =K27*L27*M27 -> 5512.5 | O27: =K27*1.05 -> 1929.375 | P27: ='Program Budget'!Q29 -> 12 | Q27: ='Program Budget'!P233 -> 0.25 | R27: =O27*P27*Q27 -> 5788.125 | S27: =O27*1.05 -> 2025.8438 | T27: ='Program Budget'!T29 -> 11 | U27: ='Program Budget'!S233 -> 0.25 | V27: =S27*T27*U27 -> 5571.0703 | W27: =F27+J27+N27+R27+V27 -> 26288.362 | AE27: 180 | AF27: 50-01-2-020 | AG27: DIR-USN (Expat) Labor
A28: ='Program Budget'!D30 -> Administrative Officer | B28: ='Program Budget'!F234 -> Month | C28: ='Program Budget'!H30 -> 833.33333 | D28: ='Program Budget'!G30 -> 9 | E28: ='Program Budget'!E234 -> 0.25 | F28: =C28*D28*E28 -> 1875 | G28: =C28*1.05 -> 875 | H28: ='Program Budget'!K30 -> 12 | I28: ='Program Budget'!J234 -> 0.25 | J28: =G28*H28*I28 -> 2625 | K28: =G28*1.05 -> 918.75 | L28: ='Program Budget'!N30 -> 12 | M28: ='Program Budget'!M234 -> 0.25 | N28: =K28*L28*M28 -> 2756.25 | O28: =K28*1.05 -> 964.6875 | P28: ='Program Budget'!Q30 -> 12 | Q28: ='Program Budget'!P234 -> 0.25 | R28: =O28*P28*Q28 -> 2894.0625 | S28: =O28*1.05 -> 1012.9219 | T28: ='Program Budget'!T30 -> 10 | U28: ='Program Budget'!S234 -> 0.25 | V28: =S28*T28*U28 -> 2532.3047 | W28: =F28+J28+N28+R28+V28 -> 12682.617 | AE28: 180 | AF28: 50-01-2-020 | AG28: DIR-USN (Expat) Labor
A29: ='Program Budget'!D31 -> Human Resources Manager | B29: ='Program Budget'!F235 -> Month | C29: ='Program Budget'!H31 -> 2500 | D29: ='Program Budget'!G31 -> 11 | E29: ='Program Budget'!E235 -> 0.25 | F29: =C29*D29*E29 -> 6875 | G29: =C29*1.05 -> 2625 | H29: ='Program Budget'!K31 -> 12 | I29: ='Program Budget'!J235 -> 0.25 | J29: =G29*H29*I29 -> 7875 | K29: =G29*1.05 -> 2756.25 | L29: ='Program Budget'!N31 -> 12 | M29: ='Program Budget'!M235 -> 0.25 | N29: =K29*L29*M29 -> 8268.75 | O29: =K29*1.05 -> 2894.0625 | P29: ='Program Budget'!Q31 -> 12 | Q29: ='Program Budget'!P235 -> 0.25 | R29: =O29*P29*Q29 -> 8682.1875 | S29: =O29*1.05 -> 3038.7656 | T29: ='Program Budget'!T31 -> 12 | U29: ='Program Budget'!S235 -> 0.25 | V29: =S29*T29*U29 -> 9116.2969 | W29: =F29+J29+N29+R29+V29 -> 40817.234 | AE29: 180 | AF29: 50-01-2-020 | AG29: DIR-USN (Expat) Labor
A30: ='Program Budget'!D32 -> Driver (3 Individuals) | B30: ='Program Budget'!F236 -> Month | C30: ='Program Budget'!H32 -> 2250 | D30: ='Program Budget'!G32 -> 3 | E30: ='Program Budget'!E236 -> 0.3 | F30: =C30*D30*E30 -> 2025 | G30: =C30*1.05 -> 2362.5 | H30: ='Program Budget'!K32 -> 12 | I30: ='Program Budget'!J236 -> 0.25 | J30: =G30*H30*I30 -> 7087.5 | K30: =G30*1.05 -> 2480.625 | L30: ='Program Budget'!N32 -> 12 | M30: ='Program Budget'!M236 -> 0.25 | N30: =K30*L30*M30 -> 7441.875 | O30: =K30*1.05 -> 2604.6562 | P30: ='Program Budget'!Q32 -> 12 | Q30: ='Program Budget'!P236 -> 0.25 | R30: =O30*P30*Q30 -> 7813.9688 | S30: =O30*1.05 -> 2734.8891 | T30: ='Program Budget'!T32 -> 9 | U30: ='Program Budget'!S236 -> 0.25 | V30: =S30*T30*U30 -> 6153.5004 | W30: =F30+J30+N30+R30+V30 -> 30521.844 | AE30: 180 | AF30: 50-01-2-020 | AG30: DIR-USN (Expat) Labor
A31: Total Local Salary Cost | F31: =SUM(F10:F30) -> 128950 | J31: =SUM(J10:J30) -> 221865 | N31: =SUM(N10:N30) -> 231403.73 | R31: =SUM(R10:R30) -> 242973.91 | V31: =SUM(V10:V30) -> 215444.43 | W31: =SUM(W10:W30) -> 1040637.1
A33: Subtotal: Salaries & Wages | F33: =F31+F8 -> 128950 | J33: =J31+J8 -> 221865 | N33: =N31+N8 -> 231403.73 | R33: =R31+R8 -> 242973.91 | V33: =V31+V8 -> 215444.43 | W33: =+F33+J33+N33+R33+V33 -> 1040637.1
A34: Fringe
A35: USN/TCN Staff | F35: =C35*D35*E35 -> 0 | J35: =G35*H35*I35 -> 0 | N35: =K35*L35*M35 -> 0 | R35: =O35*P35*Q35 -> 0 | V35: =S35*T35*U35 -> 0 | W35: =F35+J35+N35+R35+V35 -> 0 | AE35: 194 | AF35: 50-03-0-020 | AG35: DIR-Allocated USN Fringe
A36: CCN Staff | B36: ='Program Budget'!F240 -> % | C36: =F31 -> 128950 | D36: 1 | E36: ='Program Budget'!H240 -> 0.455 | F36: =C36*D36*E36 -> 58672.25 | G36: =J31 -> 221865 | H36: 1 | I36: =E36 -> 0.455 | J36: =G36*H36*I36 -> 100948.57 | K36: =N31 -> 231403.73 | L36: 1 | M36: =I36 -> 0.455 | N36: =K36*L36*M36 -> 105288.69 | O36: =R31 -> 242973.91 | P36: 1 | Q36: =M36 -> 0.455 | R36: =O36*P36*Q36 -> 110553.13 | S36: =V31 -> 215444.43 | T36: 1 | U36: =Q36 -> 0.455 | V36: =S36*T36*U36 -> 98027.216 | W36: =F36+J36+N36+R36+V36 -> 473489.87 | AE36: 197 | AF36: 50-03-0-050 | AG36: DIR-CCN Fringe
A37: Total: Fringe Benefits | F37: =+SUM(F35:F36) -> 58672.25 | J37: =+SUM(J35:J36) -> 100948.57 | N37: =+SUM(N35:N36) -> 105288.69 | R37: =+SUM(R35:R36) -> 110553.13 | V37: =+SUM(V35:V36) -> 98027.216 | W37: =+F37+J37+N37+R37+V37 -> 473489.87
A38: Allowances | W38: =+F38+J38+N38+R38+V38 -> 0
A39: None | F39: =C39*D39*E39 -> 0 | J39: =G39*H39*I39 -> 0 | N39: =K39*L39*M39 -> 0 | R39: =O39*P39*Q39 -> 0 | V39: =S39*T39*U39 -> 0 | W39: =F39+J39+N39+R39+V39 -> 0
A40: Total: Allowances | F40: =SUM(F39:F39) -> 0 | J40: =SUM(J39:J39) -> 0 | N40: =SUM(N39:N39) -> 0 | R40: =SUM(R39:R39) -> 0 | V40: =SUM(V39:V39) -> 0 | W40: =F40+J40+N40+R40+V40 -> 0
A41: Subtotal: Benefits | F41: =F40+F37 -> 58672.25 | J41: =J40+J37 -> 100948.57 | N41: =N40+N37 -> 105288.69 | R41: =R40+R37 -> 110553.13 | V41: =V40+V37 -> 98027.216 | W41: =+F41+J41+N41+R41+V41 -> 473489.87 | AE41: 287 | AF41: 51-04-2-050 | AG41: DIR-Int Travel Other
A42: Local Travel
A43: ='Program Budget'!D256 -> Local Transportation (Car Rental, Taxis) | B43: ='Program Budget'!F256 -> Month | C43: ='Program Budget'!H256 -> 50 | D43: ='Program Budget'!G256 -> 3 | E43: 1 | F43: =C43*D43*E43 -> 150 | G43: =C43*1.07 -> 53.5 | H43: ='Program Budget'!K256 -> 12 | I43: 1 | J43: =G43*H43*I43 -> 642 | K43: =G43*1.07 -> 57.245 | L43: ='Program Budget'!N256 -> 12 | M43: 1 | N43: =K43*L43*M43 -> 686.94 | O43: =K43*1.07 -> 61.25215 | P43: ='Program Budget'!Q256 -> 12 | Q43: 1 | R43: =O43*P43*Q43 -> 735.0258 | S43: =O43*1.07 -> 65.539801 | T43: ='Program Budget'!T256 -> 9 | U43: 1 | V43: =S43*T43*U43 -> 589.8582 | W43: =F43+J43+N43+R43+V43 -> 2803.824 | AE43: 180 | AF43: 50-01-2-020 | AG43: DIR-USN (Expat) Labor
A44: ='Program Budget'!D257 -> Local Transportation for Stakeholder Workshop | B44: ='Program Budget'!F257 -> Trip | C44: ='Program Budget'!H257 -> 100 | D44: ='Program Budget'!G257 -> 3 | E44: 1 | F44: =C44*D44*E44 -> 300 | G44: =C44*1.07 -> 107 | H44: ='Program Budget'!K257 -> 0 | I44: 0 | J44: =G44*H44*I44 -> 0 | K44: =G44*1.07 -> 114.49 | L44: ='Program Budget'!N257 -> 0 | M44: 0 | N44: =K44*L44*M44 -> 0 | O44: =K44*1.07 -> 122.5043 | P44: ='Program Budget'!Q257 -> 0 | Q44: 0 | R44: =O44*P44*Q44 -> 0 | S44: =O44*1.07 -> 131.0796 | T44: ='Program Budget'!T257 -> 0 | U44: 0 | V44: =S44*T44*U44 -> 0 | W44: =F44+J44+N44+R44+V44 -> 300 | AE44: 180 | AF44: 50-01-2-020 | AG44: DIR-USN (Expat) Labor
A45: ='Program Budget'!D259 -> Local Transportation for Technical Package Design | B45: ='Program Budget'!F259 -> Trip | C45: ='Program Budget'!H259 -> 100 | D45: ='Program Budget'!G259 -> 8 | E45: 1 | F45: =C45*D45*E45 -> 800 | G45: =C45*1.07 -> 107 | H45: ='Program Budget'!K259 -> 0 | I45: 0 | J45: =G45*H45*I45 -> 0 | K45: =G45*1.07 -> 114.49 | L45: ='Program Budget'!N259 -> 0 | M45: 0 | N45: =K45*L45*M45 -> 0 | O45: =K45*1.07 -> 122.5043 | P45: ='Program Budget'!Q259 -> 0 | Q45: 0 | R45: =O45*P45*Q45 -> 0 | S45: =O45*1.07 -> 131.0796 | T45: ='Program Budget'!T259 -> 0 | U45: 0 | V45: =S45*T45*U45 -> 0 | W45: =F45+J45+N45+R45+V45 -> 800 | AE45: 180 | AF45: 50-01-2-020 | AG45: DIR-USN (Expat) Labor
A46: ='Program Budget'!D261 -> Transport Stipends for Producers Organization Leaders to Attend PASPs Trainings | B46: ='Program Budget'!F261 -> Participant | C46: ='Program Budget'!H261 -> 7 | D46: ='Program Budget'!G261 -> 0 | E46: 0 | F46: =C46*D46*E46 -> 0 | G46: =C46*1.07 -> 7.49 | H46: ='Program Budget'!K261 -> 36 | I46: 1 | J46: =G46*H46*I46 -> 269.64 | K46: =G46*1.07 -> 8.0143 | L46: ='Program Budget'!N261 -> 38 | M46: 1 | N46: =K46*L46*M46 -> 304.5434 | O46: =K46*1.07 -> 8.575301 | P46: ='Program Budget'!Q261 -> 36 | Q46: 1 | R46: =O46*P46*Q46 -> 308.71084 | S46: =O46*1.07 -> 9.1755721 | T46: ='Program Budget'!T261 -> 0 | U46: 0 | V46: =S46*T46*U46 -> 0 | W46: =F46+J46+N46+R46+V46 -> 882.89424 | AE46: 180 | AF46: 50-01-2-020 | AG46: DIR-USN (Expat) Labor
A47: Vehicle Fuel
A48: ='Program Budget'!D255 -> Vehicle Fuel Expense (for Field Office Vehicles) | B48: ='Program Budget'!F255 -> Month | C48: ='Program Budget'!H255 -> 100 | D48: ='Program Budget'!G255 -> 3 | E48: 1 | F48: =C48*D48*E48 -> 300 | G48: =C48*1.07 -> 107 | H48: ='Program Budget'!K255 -> 12 | I48: 1 | J48: =G48*H48*I48 -> 1284 | K48: =G48*1.07 -> 114.49 | L48: ='Program Budget'!N255 -> 12 | M48: 1 | N48: =K48*L48*M48 -> 1373.88 | O48: =K48*1.07 -> 122.5043 | P48: ='Program Budget'!Q255 -> 12 | Q48: 1 | R48: =O48*P48*Q48 -> 1470.0516 | S48: =O48*1.07 -> 131.0796 | T48: ='Program Budget'!T255 -> 9 | U48: 1 | V48: =S48*T48*U48 -> 1179.7164 | W48: =F48+J48+N48+R48+V48 -> 5607.648 | AE48: 180 | AF48: 50-01-2-020 | AG48: DIR-USN (Expat) Labor
A49: Per Diem & Lodging | F49: =C49*D49*E49 -> 0 | J49: =G49*H49*I49 -> 0 | N49: =K49*L49*M49 -> 0 | R49: =O49*P49*Q49 -> 0
A50: ='Program Budget'!D258 -> Lodging and M&IE for Stakeholder Workshop | B50: ='Program Budget'!F258 -> Day | C50: ='Program Budget'!H258 -> 129 | D50: ='Program Budget'!G258 -> 6 | E50: 1 | F50: =C50*D50*E50 -> 774 | G50: =C50*1.07 -> 138.03 | H50: ='Program Budget'!K258 -> 0 | I50: 1 | J50: =G50*H50*I50 -> 0 | K50: =G50*1.07 -> 147.6921 | L50: ='Program Budget'!N258 -> 0 | M50: 1 | N50: =K50*L50*M50 -> 0 | O50: =K50*1.07 -> 158.03055 | P50: ='Program Budget'!Q258 -> 0 | Q50: 1 | R50: =O50*P50*Q50 -> 0 | S50: =O50*1.07 -> 169.09269 | T50: ='Program Budget'!T258 -> 0 | U50: 1 | V50: =S50*T50*U50 -> 0 | W50: =F50+J50+N50+R50+V50 -> 774 | AE50: 180 | AF50: 50-01-2-020 | AG50: DIR-USN (Expat) Labor
A51: ='Program Budget'!D260 -> Lodging and M&IE for Technical Package Design | B51: ='Program Budget'!F260 -> Day | C51: ='Program Budget'!H260 -> 129 | D51: ='Program Budget'!G260 -> 16 | E51: 1 | F51: =C51*D51*E51 -> 2064 | G51: =C51*1.07 -> 138.03 | H51: ='Program Budget'!K260 -> 0 | I51: 1 | J51: =G51*H51*I51 -> 0 | K51: =G51*1.07 -> 147.6921 | L51: ='Program Budget'!N260 -> 0 | M51: 1 | N51: =K51*L51*M51 -> 0 | O51: =K51*1.07 -> 158.03055 | P51: ='Program Budget'!Q260 -> 0 | Q51: 1 | R51: =O51*P51*Q51 -> 0 | S51: =O51*1.07 -> 169.09269 | T51: ='Program Budget'!T260 -> 0 | U51: 1 | V51: =S51*T51*U51 -> 0 | W51: =F51+J51+N51+R51+V51 -> 2064 | AE51: 180 | AF51: 50-01-2-020 | AG51: DIR-USN (Expat) Labor
A53: Subtotal: Travel | F53: =SUM(F42:F52) -> 4388 | J53: =SUM(J42:J52) -> 2195.64 | N53: =SUM(N42:N52) -> 2365.3634 | R53: =SUM(R42:R52) -> 2513.7882 | V53: =SUM(V42:V52) -> 1769.5746 | W53: =+F53+J53+N53+R53+V53 -> 13232.366
A54: Professional Services
A55: ='Program Budget'!D244 -> Contract for Private Agriculture Service Providers (PASPs) to Train on Technical Assistance Business Models | B55: ='Program Budget'!F244 -> Region | C55: ='Program Budget'!H244 -> 25000 | D55: ='Program Budget'!G244 -> 4 | E55: 1 | F55: =C55*D55*E55 -> 100000 | G55: =(C55/2) -> 12500 | H55: ='Program Budget'!K244 -> 4 | I55: 1 | J55: =G55*H55*I55 -> 50000 | K55: =G55 -> 12500 | L55: ='Program Budget'!N244 -> 4 | M55: 1 | N55: =K55*L55*M55 -> 50000 | O55: =K55 -> 12500 | P55: ='Program Budget'!Q244 -> 4 | Q55: 1 | R55: =O55*P55*Q55 -> 50000 | S55: =O55 -> 12500 | T55: ='Program Budget'!T244 -> 0 | U55: 0 | V55: =S55*T55*U55 -> 0 | W55: =F55+J55+N55+R55+V55 -> 250000
A56: ='Program Budget'!D245 -> Contract for Private Agriculture Service Providers (PASPs) to Support Capacity-Building Efforts for Producer Organizations | B56: ='Program Budget'!F245 -> Day | C56: ='Program Budget'!H245 -> 350 | D56: ='Program Budget'!G245 -> 0 | E56: 0 | F56: =C56*D56*E56 -> 0 | G56: =C56 -> 350 | H56: ='Program Budget'!K245 -> 4 | I56: 1 | J56: =G56*H56*I56 -> 1400 | K56: =G56 -> 350 | L56: ='Program Budget'!N245 -> 4 | M56: 1 | N56: =K56*L56*M56 -> 1400 | O56: =K56 -> 350 | P56: ='Program Budget'!Q245 -> 4 | Q56: 1 | R56: =O56*P56*Q56 -> 1400 | S56: =O56 -> 350 | T56: ='Program Budget'!T245 -> 0 | U56: 0 | V56: =S56*T56*U56 -> 0 | W56: =F56+J56+N56+R56+V56 -> 4200
A57: ='Program Budget'!D246 -> Contract for Women-Led Enterprise Development Technical Assistance | B57: ='Program Budget'!F246 -> Unit | C57: ='Program Budget'!H246 -> 5000 | D57: ='Program Budget'!G246 -> 0 | E57: 0 | F57: =C57*D57*E57 -> 0 | G57: =C57 -> 5000 | H57: ='Program Budget'!K246 -> 12 | I57: 1 | J57: =G57*H57*I57 -> 60000 | K57: =G57 -> 5000 | L57: ='Program Budget'!N246 -> 13 | M57: 1 | N57: =K57*L57*M57 -> 65000 | O57: =K57 -> 5000 | P57: ='Program Budget'!Q246 -> 0 | Q57: 0 | R57: =O57*P57*Q57 -> 0 | S57: =O57 -> 5000 | T57: ='Program Budget'!T246 -> 0 | U57: 0 | V57: =S57*T57*U57 -> 0 | W57: =F57+J57+N57+R57+V57 -> 125000
A58: ='Program Budget'!D247 -> Security Services, Risk Assessments, & Security Assessment | B58: ='Program Budget'!F247 -> Year | C58: ='Program Budget'!H247 -> 5000 | D58: ='Program Budget'!G247 -> 1 | E58: 1 | F58: =C58*D58*E58 -> 5000 | G58: =C58 -> 5000 | H58: ='Program Budget'!K247 -> 1 | I58: 1 | J58: =G58*H58*I58 -> 5000 | K58: =G58 -> 5000 | L58: ='Program Budget'!N247 -> 1 | M58: 1 | N58: =K58*L58*M58 -> 5000 | O58: =K58 -> 5000 | P58: ='Program Budget'!Q247 -> 1 | Q58: 1 | R58: =O58*P58*Q58 -> 5000 | S58: =O58 -> 5000 | T58: ='Program Budget'!T247 -> 1 | U58: 1 | V58: =S58*T58*U58 -> 5000 | W58: =F58+J58+N58+R58+V58 -> 25000
A60: Subtotal: Professional Services/Contractual | F60: =SUM(F55:F59) -> 105000 | J60: =SUM(J55:J59) -> 116400 | N60: =SUM(N55:N59) -> 121400 | R60: =SUM(R55:R59) -> 56400 | V60: =SUM(V55:V59) -> 5000 | W60: =SUM(W55:W59) -> 404200
A61: Equipment (>$5000/unit)
A62: None | F62: =C62*D62*E62 -> 0 | J62: =G62*H62*I62 -> 0 | N62: =K62*L62*M62 -> 0 | R62: =O62*P62*Q62 -> 0 | V62: =S62*T62*U62 -> 0 | W62: =F62+J62+N62+R62+V62 -> 0 | AE62: 298 | AF62: 51-05-1-003 | AG62: DIR-Furniture
A63: Subtotal: Equipment | F63: =SUM(F62:F62) -> 0 | J63: =SUM(J62:J62) -> 0 | N63: =SUM(N62:N62) -> 0 | R63: =SUM(R62:R62) -> 0 | V63: =SUM(V62:V62) -> 0 | W63: =+F63+J63+N63+R63+V63 -> 0
A64: Office
A65: None | F65: =C65*D65*E65 -> 0 | J65: =G65*H65*I65 -> 0 | N65: =K65*L65*M65 -> 0 | R65: =O65*P65*Q65 -> 0 | V65: =S65*T65*U65 -> 0 | W65: =F65+J65+N65+R65+V65 -> 0 | AE65: 298 | AF65: 51-05-1-003 | AG65: DIR-Furniture
A66: Subtotal: Office | F66: =SUM(F62:F62) -> 0 | J66: =SUM(J62:J62) -> 0 | N66: =SUM(N62:N62) -> 0 | R66: =SUM(R62:R62) -> 0 | V66: =SUM(V62:V62) -> 0 | W66: =+F66+J66+N66+R66+V66 -> 0 | AE66: 236 | AF66: 51-02-1-001 | AG66: DIR-Prof. Serv Labor
A67: Supplies | AE67: 236 | AF67: 51-02-1-001 | AG67: DIR-Prof. Serv Labor
A68: ='Program Budget'!D251 -> Communication Costs for Publication of RFPs/RFAs | B68: ='Program Budget'!F251 -> Unit | C68: ='Program Budget'!H251 -> 500 | D68: ='Program Budget'!G251 -> 1 | E68: 1 | F68: =C68*D68*E68 -> 500 | G68: =C68 -> 500 | H68: ='Program Budget'!K251 -> 3 | I68: 1 | J68: =G68*H68*I68 -> 1500 | K68: =G68 -> 500 | L68: ='Program Budget'!N251 -> 1 | M68: 1 | N68: =K68*L68*M68 -> 500 | O68: =K68 -> 500 | P68: ='Program Budget'!Q251 -> 0 | Q68: 0 | R68: =O68*P68*Q68 -> 0 | S68: =O68 -> 500 | T68: ='Program Budget'!T251 -> 0 | U68: 0 | V68: =S68*T68*U68 -> 0 | W68: =F68+J68+N68+R68+V68 -> 2500
A70: Subtotal: Supplies | F70: =SUM(F68:F69) -> 500 | J70: =SUM(J68:J69) -> 1500 | N70: =SUM(N68:N69) -> 500 | R70: =SUM(R68:R69) -> 0 | V70: =SUM(V68:V69) -> 0 | W70: =SUM(W68:W69) -> 2500
A71: Other Direct Cost
A72: Trainings & Meetings
A73: ='Program Budget'!D266 -> Workshop with Stakeholders on Complementary Crop Feedback (Venue, Materials, Food, & Refreshments) | B73: ='Program Budget'!F266 -> Workshop | C73: ='Program Budget'!H266 -> 850 | D73: ='Program Budget'!G266 -> 1 | E73: 1 | F73: =C73*D73*E73 -> 850 | G73: =C73 -> 850 | H73: ='Program Budget'!K266 -> 0 | I73: 0 | J73: =G73*H73*I73 -> 0 | K73: =G73 -> 850 | L73: ='Program Budget'!N266 -> 0 | M73: 0 | N73: =K73*L73*M73 -> 0 | O73: =K73 -> 850 | P73: ='Program Budget'!Q266 -> 0 | Q73: 0 | R73: =O73*P73*Q73 -> 0 | S73: =O73 -> 850 | T73: ='Program Budget'!T266 -> 0 | U73: 0 | V73: =S73*T73*U73 -> 0 | W73: =F73+J73+N73+R73+V73 -> 850
A74: ='Program Budget'!D267 -> Development of Technical Package (Technical Review, Printing, & Translation) | B74: ='Program Budget'!F267 -> Package | C74: ='Program Budget'!H267 -> 5000 | D74: ='Program Budget'!G267 -> 4 | E74: 1 | F74: =C74*D74*E74 -> 20000 | G74: =C74 -> 5000 | H74: ='Program Budget'!K267 -> 0 | I74: 0 | J74: =G74*H74*I74 -> 0 | K74: =G74 -> 5000 | L74: ='Program Budget'!N267 -> 0 | M74: 0 | N74: =K74*L74*M74 -> 0 | O74: =K74 -> 5000 | P74: ='Program Budget'!Q267 -> 0 | Q74: 0 | R74: =O74*P74*Q74 -> 0 | S74: =O74 -> 5000 | T74: ='Program Budget'!T267 -> 0 | U74: 0 | V74: =S74*T74*U74 -> 0 | W74: =F74+J74+N74+R74+V74 -> 20000
A75: ='Program Budget'!D268 -> Train PASPs in Cost-Efficient Date and Complementary Oasis Production (Venue, Materials, Food, & Refreshments) | B75: ='Program Budget'!F268 -> Training | C75: ='Program Budget'!H268 -> 730 | D75: ='Program Budget'!G268 -> 2 | E75: 1 | F75: =C75*D75*E75 -> 1460 | G75: =C75 -> 730 | H75: ='Program Budget'!K268 -> 0 | I75: 0 | J75: =G75*H75*I75 -> 0 | K75: =G75 -> 730 | L75: ='Program Budget'!N268 -> 0 | M75: 0 | N75: =K75*L75*M75 -> 0 | O75: =K75 -> 730 | P75: ='Program Budget'!Q268 -> 0 | Q75: 0 | R75: =O75*P75*Q75 -> 0 | S75: =O75 -> 730 | T75: ='Program Budget'!T268 -> 0 | U75: 0 | V75: =S75*T75*U75 -> 0 | W75: =F75+J75+N75+R75+V75 -> 1460
A76: ='Program Budget'!D269 -> PASPs Trainings to Support Capacity-Building Efforts for Producer Organizations (Materials, Food, & Refreshments) | B76: ='Program Budget'!F269 -> Day | C76: ='Program Budget'!H269 -> 330 | D76: ='Program Budget'!G269 -> 0 | E76: 0 | F76: =C76*D76*E76 -> 0 | G76: =C76 -> 330 | H76: ='Program Budget'!K269 -> 4 | I76: 1 | J76: =G76*H76*I76 -> 1320 | K76: =G76 -> 330 | L76: ='Program Budget'!N269 -> 4 | M76: 1 | N76: =K76*L76*M76 -> 1320 | O76: =K76 -> 330 | P76: ='Program Budget'!Q269 -> 4 | Q76: 1 | R76: =O76*P76*Q76 -> 1320 | S76: =O76 -> 330 | T76: ='Program Budget'!T269 -> 0 | U76: 0 | V76: =S76*T76*U76 -> 0 | W76: =F76+J76+N76+R76+V76 -> 3960
A77: ='Program Budget'!D270 -> Training on Best Practices with US Grains Council for Alfalfa Processers (Materials, Food, & Refreshments) | B77: ='Program Budget'!F270 -> Training | C77: ='Program Budget'!H270 -> 380 | D77: ='Program Budget'!G270 -> 0 | E77: 0 | F77: =C77*D77*E77 -> 0 | G77: =C77 -> 380 | H77: ='Program Budget'!K270 -> 2 | I77: 1 | J77: =G77*H77*I77 -> 760 | K77: =G77 -> 380 | L77: ='Program Budget'!N270 -> 0 | M77: 0 | N77: =K77*L77*M77 -> 0 | O77: =K77 -> 380 | P77: ='Program Budget'!Q270 -> 0 | Q77: 0 | R77: =O77*P77*Q77 -> 0 | S77: =O77 -> 380 | T77: ='Program Budget'!T270 -> 0 | U77: 0 | V77: =S77*T77*U77 -> 0 | W77: =F77+J77+N77+R77+V77 -> 760
A78: ='Program Budget'!D271 -> Meeting Expenses with Producer Organizations and Stakeholders | B78: ='Program Budget'!F271 -> Meeting | C78: ='Program Budget'!H271 -> 75 | D78: ='Program Budget'!G271 -> 4 | E78: 1 | F78: =C78*D78*E78 -> 300 | G78: =C78 -> 75 | H78: ='Program Budget'!K271 -> 8 | I78: 1 | J78: =G78*H78*I78 -> 600 | K78: =G78 -> 75 | L78: ='Program Budget'!N271 -> 8 | M78: 1 | N78: =K78*L78*M78 -> 600 | O78: =K78 -> 75 | P78: ='Program Budget'!Q271 -> 4 | Q78: 1 | R78: =O78*P78*Q78 -> 300 | S78: =O78 -> 75 | T78: ='Program Budget'!T271 -> 4 | U78: 1 | V78: =S78*T78*U78 -> 300 | W78: =F78+J78+N78+R78+V78 -> 2100
A79: Grants
A80: ='Program Budget'!D273 -> Cold Storage Grants | B80: ='Program Budget'!F273 -> Grant | C80: ='Program Budget'!H273 -> 3750 | D80: ='Program Budget'!G273 -> 0 | E80: 0 | F80: =C80*D80*E80 -> 0 | G80: =C80 -> 3750 | H80: ='Program Budget'!K273 -> 60 | I80: 1 | J80: =G80*H80*I80 -> 225000 | K80: =G80 -> 3750 | L80: ='Program Budget'!N273 -> 0 | M80: 0 | N80: =K80*L80*M80 -> 0 | O80: =K80 -> 3750 | P80: ='Program Budget'!Q273 -> 0 | Q80: 0 | R80: =O80*P80*Q80 -> 0 | S80: =O80 -> 3750 | T80: ='Program Budget'!T273 -> 0 | U80: 0 | V80: =S80*T80*U80 -> 0 | W80: =F80+J80+N80+R80+V80 -> 225000
A81: ='Program Budget'!D274 -> Grants for Alfalfa Processers | B81: ='Program Budget'!F274 -> Grant | C81: ='Program Budget'!H274 -> 5000 | D81: ='Program Budget'!G274 -> 0 | E81: 0 | F81: =C81*D81*E81 -> 0 | G81: =C81 -> 5000 | H81: ='Program Budget'!K274 -> 4 | I81: 1 | J81: =G81*H81*I81 -> 20000 | K81: =G81 -> 5000 | L81: ='Program Budget'!N274 -> 0 | M81: 0 | N81: =K81*L81*M81 -> 0 | O81: =K81 -> 5000 | P81: ='Program Budget'!Q274 -> 0 | Q81: 0 | R81: =O81*P81*Q81 -> 0 | S81: =O81 -> 5000 | T81: ='Program Budget'!T274 -> 0 | U81: 0 | V81: =S81*T81*U81 -> 0 | W81: =F81+J81+N81+R81+V81 -> 20000
A82: ='Program Budget'!D275 -> Women-Led Enterprise Development Grants | B82: ='Program Budget'!F275 -> Grant | C82: ='Program Budget'!H275 -> 7500 | D82: ='Program Budget'!G275 -> 0 | E82: 0 | F82: =C82*D82*E82 -> 0 | G82: =C82 -> 7500 | H82: ='Program Budget'!K275 -> 12 | I82: 1 | J82: =G82*H82*I82 -> 90000 | K82: =G82 -> 7500 | L82: ='Program Budget'!N275 -> 13 | M82: 1 | N82: =K82*L82*M82 -> 97500 | O82: =K82 -> 7500 | P82: ='Program Budget'!Q275 -> 0 | Q82: 0 | R82: =O82*P82*Q82 -> 0 | S82: =O82 -> 7500 | T82: ='Program Budget'!T275 -> 0 | U82: 0 | V82: =S82*T82*U82 -> 0 | W82: =F82+J82+N82+R82+V82 -> 187500
A84: Subtotal: Other Direct Cost | F84: =SUM(F72:F83) -> 22610 | J84: =SUM(J72:J83) -> 337680 | N84: =SUM(N72:N83) -> 99420 | R84: =SUM(R72:R83) -> 1620 | V84: =SUM(V72:V83) -> 300 | W84: =+F84+J84+N84+R84+V84 -> 461630 | AE84: 250 | AF84: 51-02-2-008 | AG84: DIR-Security
AE85: 317 | AF85: 51-08-1-002 | AG85: DIR-Office Make Ready
A86: Total Direct Cost | F86: =F33+F41+F53+F66+F70+F60+F84 -> 320120.25 | J86: =J33+J41+J53+J66+J70+J60+J84 -> 780589.22 | N86: =N33+N41+N53+N66+N70+N60+N84 -> 560377.78 | R86: =R33+R41+R53+R66+R70+R60+R84 -> 414060.83 | V86: =V33+V41+V53+V66+V70+V60+V84 -> 320541.22 | W86: =W33+W41+W53+W66+W70+W60+W84 -> 2395689.3 | AE86: 318 | AF86: 51-08-1-003 | AG86: DIR-Office Maintenance
A88: Indirect Costs
A89: ICR on Administration | B89: % | C89: 0 | D89: 0 | E89: 0.2828 | F89: =C89*D89*E89 -> 0 | G89: 0 | H89: 0 | I89: 0.2828 | J89: =G89*H89*I89 -> 0 | K89: 0 | L89: 0 | M89: 0.2828 | N89: =K89*L89*M89 -> 0 | O89: 0 | P89: 0 | Q89: 0.2828 | R89: =O89*P89*Q89 -> 0 | S89: 0 | T89: 0 | U89: 0.2828 | V89: =S89*T89*U89 -> 0 | W89: =F89+J89+N89+R89+V89 -> 0
A90: ICR on Activities | B90: % | C90: =F86 -> 320120.25 | D90: 1 | E90: 0.2828 | F90: =C90*D90*E90 -> 90530.007 | G90: =J86 -> 780589.22 | H90: 1 | I90: 0.2828 | J90: =G90*H90*I90 -> 220750.63 | K90: =N86 -> 560377.78 | L90: 1 | M90: 0.2828 | N90: =K90*L90*M90 -> 158474.84 | O90: =R86 -> 414060.83 | P90: 1 | Q90: 0.2828 | R90: =O90*P90*Q90 -> 117096.4 | S90: =V86 -> 320541.22 | T90: 1 | U90: 0.2828 | V90: =S90*T90*U90 -> 90649.058 | W90: =F90+J90+N90+R90+V90 -> 677500.93
A92: Subtotal Indirect Cost | F92: =SUM(F89:F91) -> 90530.007 | J92: =SUM(J89:J91) -> 220750.63 | N92: =SUM(N89:N91) -> 158474.84 | R92: =SUM(R89:R91) -> 117096.4 | V92: =SUM(V89:V91) -> 90649.058 | W92: =SUM(W89:W91) -> 677500.93
A94: Total Estimated Cost (Direct Cost + Indirect Cost) | F94: =F86+F92 -> 410650.26 | J94: =J86+J92 -> 1001339.8 | N94: =N86+N92 -> 718852.62 | R94: =R86+R92 -> 531157.23 | V94: =V86+V92 -> 411190.28 | W94: =F94+J94+N94+R94+V94 -> 3073190.2
A95: ='Program Budget'!D279 -> Cost Share for Co-Investment of Cold Storage Grants | B95: ='Program Budget'!F279 -> Grant | C95: ='Program Budget'!H279 -> 2750 | D95: ='Program Budget'!G279 -> 0 | E95: 0 | F95: =C95*D95*E95 -> 0 | G95: =C95 -> 2750 | H95: ='Program Budget'!K279 -> 60 | I95: 1 | J95: =G95*H95*I95 -> 165000 | K95: =G95 -> 2750 | L95: ='Program Budget'!N279 -> 0 | M95: 0 | N95: =K95*L95*M95 -> 0 | O95: =K95 -> 2750 | P95: ='Program Budget'!Q279 -> 0 | Q95: 0 | R95: =O95*P95*Q95 -> 0 | S95: =O95 -> 2750 | T95: ='Program Budget'!T279 -> 0 | U95: 0 | V95: =S95*T95*U95 -> 0 | W95: =F95+J95+N95+R95+V95 -> 165000
A96: Total Estimated Cost (Direct Cost + Indirect Cost+ Cost Share) | F96: =F94+F95 -> 410650.26 | J96: =J94+J95 -> 1166339.8 | N96: =N94+N95 -> 718852.62 | R96: =R94+R95 -> 531157.23 | V96: =V94+V95 -> 411190.28 | W96: =F96+J96+N96+R96+V96 -> 3238190.2
A98: Anticipated Program Income (baked in costs and this is for reference)

Sheet Activity 3
A2: Item | B2: Type of Unit | C2: Year 1 | G2: Year 2 | K2: Year 3 | O2: Year 4 | S2: Year 5 | W2: Total
C3: Cost | D3: Quantity | E3: Percent Allocated | F3: Total | G3: Cost | H3: Quantity | I3: Percent Allocated | J3: Total | K3: Cost | L3: Quantity | M3: Percent Allocated | N3: Total | O3: Cost | P3: Quantity | Q3: Percent Allocated | R3: Total | S3: Cost | T3: Quantity | U3: Percent Allocated | V3: Total | AF3: Chart of Accounts
A4: Direct Costs | AE4: Line# | AF4: Account | AG4: Account Name
A5: Salaries
A6: USN/TCN Staff
A7: None | F7: =C7*D7*E7 -> 0 | J7: =G7*H7*I7 -> 0 | N7: =K7*L7*M7 -> 0 | R7: =O7*P7*Q7 -> 0 | V7: =S7*T7*U7 -> 0 | W7: =F7+J7+N7+R7+V7 -> 0
A8: Total: Expatriate Salaries & Wages | F8: =SUM(F7:F7) -> 0 | J8: =SUM(J7:J7) -> 0 | N8: =SUM(N7:N7) -> 0 | R8: =SUM(R7:R7) -> 0 | V8: =SUM(V7:V7) -> 0 | W8: =+F8+J8+N8+R8+V8 -> 0
A9: CCN Staff
A10: ='Program Budget'!D12 -> Key Personnel: Chief of Party - Ms. Rym Ayari | B10: ='Program Budget'!F287 -> Month | C10: ='Program Budget'!H12 -> 13000 | D10: ='Program Budget'!G12 -> 12 | E10: ='Program Budget'!E287 -> 0.2 | F10: =C10*D10*E10 -> 31200 | G10: =C10*1.05 -> 13650 | H10: ='Program Budget'!K12 -> 12 | I10: ='Program Budget'!J287 -> 0.3 | J10: =G10*H10*I10 -> 49140 | K10: =G10*1.05 -> 14332.5 | L10: ='Program Budget'!N12 -> 12 | M10: ='Program Budget'!M287 -> 0.3 | N10: =K10*L10*M10 -> 51597 | O10: =K10*1.05 -> 15049.125 | P10: ='Program Budget'!Q12 -> 12 | Q10: ='Program Budget'!P287 -> 0.3 | R10: =O10*P10*Q10 -> 54176.85 | S10: =O10*1.05 -> 15801.581 | T10: ='Program Budget'!T12 -> 12 | U10: ='Program Budget'!S287 -> 0.3 | V10: =S10*T10*U10 -> 56885.692 | W10: =F10+J10+N10+R10+V10 -> 242999.54
