Workbook
Name __pd1: [1]Rates!$J$24
Name __pd6: [1]Rates!$J$30
Name __tix1: [1]Rates!$J$40
Name __tix2: [1]Rates!$J$41
Name __tix6: [1]Rates!$J$47
Name ANPDH: '[2]Salary & PR Tax'!#REF!
Name Board: '[3]Schedule E - Other'!$F$102
Name CEE_Consult: #REF!
Name CENIDH: #REF!
Name Consultants: #REF!
Name Equipment: '[4]Schedule D - Equipment'!$E$26
Name fg: #REF!
Name Housing: '[2]Salary & PR Tax'!#REF!
Name inf: [5]Assumptions!$C$75
Name Inflation: '[6]Detail-1'!$J$2
Name Interns: #REF!
Name jenn: #REF!
Name Local_Hire: #REF!
Name Local_Hires: #REF!
Name Merit: '[6]Detail-1'!$J$1
Name padf01: '[7]Level of Effort'!$C$14
Name padf02: '[7]Level of Effort'!$C$15
Name padf03: '[7]Level of Effort'!$C$16
Name padf04: '[7]Level of Effort'!$C$17
Name padf05: [7]Rates!$J$23
Name postdif01: [7]Rates!$J$34
Name postdif02: [7]Rates!$J$65
Name Print_Titles_MI: #REF!
Name sdf: #REF!
Name Travel_Regional: #REF!
Name Travel_WDC: #REF!

Sheet Summary Budget
A1: Partners of the Americas F2F Caribbean Basin Program Budget
A2: USAID NOFO #7200AA23RFA00006
A4: Line Items | B4: Year 1 | E4: Year 2 | H4: Year 3 | K4: Year 4 | N4: Year 5 | Q4: Total | R4: Total | S4: Grand
B5: USAID | C5: Leverage | D5: Total | E5: USAID | F5: Leverage | G5: Total | H5: USAID | I5: Leverage | J5: Total | K5: USAID | L5: Leverage | M5: Total | N5: USAID | O5: Leverage | P5: Total | Q5: USAID | R5: Leverage | S5: Total
A7: Salaries & Wages | B7: ='Detailed Budget'!I25 -> 534480 | C7: ='Detailed Budget'!J25 -> 511560 | D7: =SUM(B7:C7) -> 1046040 | E7: ='Detailed Budget'!O25 -> 614246.68 | F7: ='Detailed Budget'!P25 -> 589860 | G7: =SUM(E7:F7) -> 1204106.7 | H7: ='Detailed Budget'!U25 -> 632674.08 | I7: ='Detailed Budget'!V25 -> 582030 | J7: =SUM(H7:I7) -> 1214704.1 | K7: ='Detailed Budget'!AA25 -> 651654.3 | L7: ='Detailed Budget'!AB25 -> 574200 | M7: =SUM(K7:L7) -> 1225854.3 | N7: ='Detailed Budget'!AG25 -> 522138.54 | O7: ='Detailed Budget'!AH25 -> 477630 | P7: =SUM(N7:O7) -> 999768.54 | Q7: ='Detailed Budget'!AJ25 -> 2955193.6 | R7: ='Detailed Budget'!AK25 -> 2735280 | S7: ='Detailed Budget'!AL25 -> 5690473.6
A9: Fringe Benefits | B9: ='Detailed Budget'!I31 -> 128190.95 | C9: ='Detailed Budget'!J31 -> 0 | D9: ='Detailed Budget'!K31 -> 128190.95 | E9: ='Detailed Budget'!O31 -> 148739.99 | F9: ='Detailed Budget'!P31 -> 0 | G9: ='Detailed Budget'!Q31 -> 148739.99 | H9: ='Detailed Budget'!U31 -> 153202.19 | I9: ='Detailed Budget'!V31 -> 0 | J9: ='Detailed Budget'!W31 -> 153202.19 | K9: ='Detailed Budget'!AA31 -> 157798.25 | L9: ='Detailed Budget'!AB31 -> 0 | M9: ='Detailed Budget'!AC31 -> 157798.25 | N9: ='Detailed Budget'!AG31 -> 125392.85 | O9: ='Detailed Budget'!AH31 -> 0 | P9: ='Detailed Budget'!AI31 -> 125392.85 | Q9: ='Detailed Budget'!AJ31 -> 713324.22 | R9: ='Detailed Budget'!AK31 -> 0 | S9: ='Detailed Budget'!AL31 -> 713324.22
A11: Travel & Transportation | B11: ='Detailed Budget'!I80 -> 290955.13 | C11: ='Detailed Budget'!J80 -> 0 | D11: ='Detailed Budget'!K80 -> 290955.13 | E11: ='Detailed Budget'!O80 -> 324939.93 | F11: ='Detailed Budget'!P80 -> 0 | G11: ='Detailed Budget'!Q80 -> 324939.93 | H11: ='Detailed Budget'!U80 -> 340648.15 | I11: ='Detailed Budget'!V80 -> 0 | J11: ='Detailed Budget'!W80 -> 340648.15 | K11: ='Detailed Budget'!AA80 -> 332162.34 | L11: ='Detailed Budget'!AB80 -> 0 | M11: ='Detailed Budget'!AC80 -> 332162.34 | N11: ='Detailed Budget'!AG80 -> 294477.26 | O11: ='Detailed Budget'!AH80 -> 0 | P11: ='Detailed Budget'!AI80 -> 294477.26 | Q11: ='Detailed Budget'!AJ80 -> 1583182.8 | R11: ='Detailed Budget'!AK80 -> 0 | S11: ='Detailed Budget'!AL80 -> 1583182.8
A13: Equipment | B13: ='Detailed Budget'!I86 -> 43000 | C13: ='Detailed Budget'!J86 -> 0 | D13: ='Detailed Budget'!K86 -> 43000 | E13: ='Detailed Budget'!O86 -> 0 | F13: ='Detailed Budget'!P86 -> 0 | G13: ='Detailed Budget'!Q86 -> 0 | H13: ='Detailed Budget'!U86 -> 0 | I13: ='Detailed Budget'!V86 -> 0 | J13: ='Detailed Budget'!W86 -> 0 | K13: ='Detailed Budget'!AA86 -> 0 | L13: ='Detailed Budget'!AB86 -> 0 | M13: ='Detailed Budget'!AC86 -> 0 | N13: ='Detailed Budget'!AG86 -> 0 | O13: ='Detailed Budget'!AH86 -> 0 | P13: ='Detailed Budget'!AI86 -> 0 | Q13: ='Detailed Budget'!AJ86 -> 43000 | R13: ='Detailed Budget'!AK86 -> 0 | S13: ='Detailed Budget'!AL86 -> 43000
A15: Supplies | B15: ='Detailed Budget'!I99 -> 26514.3 | C15: ='Detailed Budget'!J99 -> 0 | D15: ='Detailed Budget'!K99 -> 26514.3 | E15: ='Detailed Budget'!O99 -> 2762.4 | F15: ='Detailed Budget'!P99 -> 0 | G15: ='Detailed Budget'!Q99 -> 2762.4 | H15: ='Detailed Budget'!U99 -> 2805.648 | I15: ='Detailed Budget'!V99 -> 0 | J15: ='Detailed Budget'!W99 -> 2805.648 | K15: ='Detailed Budget'!AA99 -> 2849.761 | L15: ='Detailed Budget'!AB99 -> 0 | M15: ='Detailed Budget'!AC99 -> 2849.761 | N15: ='Detailed Budget'!AG99 -> 2744.7562 | O15: ='Detailed Budget'!AH99 -> 0 | P15: ='Detailed Budget'!AI99 -> 2744.7562 | Q15: ='Detailed Budget'!AJ99 -> 37676.865 | R15: ='Detailed Budget'!AK99 -> 0 | S15: ='Detailed Budget'!AL99 -> 37676.865
A17: Contractual | B17: ='Detailed Budget'!I106 -> 9000 | C17: ='Detailed Budget'!J106 -> 0 | D17: ='Detailed Budget'!K106 -> 9000 | E17: ='Detailed Budget'!O106 -> 5000 | F17: ='Detailed Budget'!P106 -> 0 | G17: ='Detailed Budget'!Q106 -> 5000 | H17: ='Detailed Budget'!U106 -> 7000 | I17: ='Detailed Budget'!V106 -> 0 | J17: ='Detailed Budget'!W106 -> 7000 | K17: ='Detailed Budget'!AA106 -> 3000 | L17: ='Detailed Budget'!AB106 -> 0 | M17: ='Detailed Budget'!AC106 -> 3000 | N17: ='Detailed Budget'!AG106 -> 1000 | O17: ='Detailed Budget'!AH106 -> 0 | P17: ='Detailed Budget'!AI106 -> 1000 | Q17: ='Detailed Budget'!AJ106 -> 25000 | R17: ='Detailed Budget'!AK106 -> 0 | S17: ='Detailed Budget'!AL106 -> 25000
A19: Other Direct Costs | B19: ='Detailed Budget'!I122 -> 105761.26 | C19: ='Detailed Budget'!J122 -> 0 | D19: ='Detailed Budget'!K122 -> 105761.26 | E19: ='Detailed Budget'!O122 -> 90213.961 | F19: ='Detailed Budget'!P122 -> 0 | G19: ='Detailed Budget'!Q122 -> 90213.961 | H19: ='Detailed Budget'!U122 -> 115945.88 | I19: ='Detailed Budget'!V122 -> 0 | J19: ='Detailed Budget'!W122 -> 115945.88 | K19: ='Detailed Budget'!AA122 -> 93858.605 | L19: ='Detailed Budget'!AB122 -> 0 | M19: ='Detailed Budget'!AC122 -> 93858.605 | N19: ='Detailed Budget'!AG122 -> 83428.102 | O19: ='Detailed Budget'!AH122 -> 0 | P19: ='Detailed Budget'!AI122 -> 83428.102 | Q19: ='Detailed Budget'!AJ122 -> 489207.81 | R19: ='Detailed Budget'!AK122 -> 0 | S19: ='Detailed Budget'!AL122 -> 489207.81
A21: Total Direct Costs | B21: ='Detailed Budget'!I124 -> 1137901.6 | C21: ='Detailed Budget'!J124 -> 511560 | D21: ='Detailed Budget'!K124 -> 1649461.6 | E21: ='Detailed Budget'!O124 -> 1185903 | F21: ='Detailed Budget'!P124 -> 589860 | G21: ='Detailed Budget'!Q124 -> 1775763 | H21: ='Detailed Budget'!U124 -> 1252275.9 | I21: ='Detailed Budget'!V124 -> 582030 | J21: ='Detailed Budget'!W124 -> 1834305.9 | K21: ='Detailed Budget'!AA124 -> 1241323.3 | L21: ='Detailed Budget'!AB124 -> 574200 | M21: ='Detailed Budget'!AC124 -> 1815523.3 | N21: ='Detailed Budget'!AG124 -> 1029181.5 | O21: ='Detailed Budget'!AH124 -> 477630 | P21: ='Detailed Budget'!AI124 -> 1506811.5 | Q21: ='Detailed Budget'!AJ124 -> 5846585.3 | R21: ='Detailed Budget'!AK124 -> 2735280 | S21: ='Detailed Budget'!AL124 -> 8581865.3
A22: Indirect Costs | B22: ='Detailed Budget'!I125 -> 321798.58 | C22: ='Detailed Budget'!J125 -> 0 | D22: ='Detailed Budget'!K125 -> 321798.58 | E22: ='Detailed Budget'!O125 -> 335373.36 | F22: ='Detailed Budget'!P125 -> 0 | G22: ='Detailed Budget'!Q125 -> 335373.36 | H22: ='Detailed Budget'!U125 -> 354143.64 | I22: ='Detailed Budget'!V125 -> 0 | J22: ='Detailed Budget'!W125 -> 354143.64 | K22: ='Detailed Budget'!AA125 -> 351046.22 | L22: ='Detailed Budget'!AB125 -> 0 | M22: ='Detailed Budget'!AC125 -> 351046.22 | N22: ='Detailed Budget'!AG125 -> 291052.53 | O22: ='Detailed Budget'!AH125 -> 0 | P22: ='Detailed Budget'!AI125 -> 291052.53 | Q22: ='Detailed Budget'!AJ125 -> 1653414.3 | R22: ='Detailed Budget'!AK125 -> 0 | S22: ='Detailed Budget'!AL125 -> 1653414.3
A23: Buy-in | B23: ='Detailed Budget'!I126 -> 0 | C23: ='Detailed Budget'!J126 -> 0 | D23: ='Detailed Budget'!K126 -> 0 | E23: ='Detailed Budget'!O126 -> 0 | F23: ='Detailed Budget'!P126 -> 0 | G23: ='Detailed Budget'!Q126 -> 0 | H23: ='Detailed Budget'!U126 -> 1000000 | I23: ='Detailed Budget'!V126 -> 0 | J23: ='Detailed Budget'!W126 -> 0 | K23: ='Detailed Budget'!AA126 -> 0 | L23: ='Detailed Budget'!AB126 -> 0 | M23: ='Detailed Budget'!AC126 -> 0 | N23: ='Detailed Budget'!AG126 -> 0 | O23: ='Detailed Budget'!AH126 -> 0 | P23: ='Detailed Budget'!AI126 -> 0 | Q23: ='Detailed Budget'!AJ126 -> 1000000 | R23: ='Detailed Budget'!AK126 -> 0 | S23: ='Detailed Budget'!AL126 -> 1000000
A24: Total | B24: ='Detailed Budget'!I127 -> 1459700.2 | C24: ='Detailed Budget'!J127 -> 511560 | D24: ='Detailed Budget'!K127 -> 1971260.2 | E24: ='Detailed Budget'!O127 -> 1521276.3 | F24: ='Detailed Budget'!P127 -> 589860 | G24: ='Detailed Budget'!Q127 -> 2111136.3 | H24: ='Detailed Budget'!U127 -> 2606419.6 | I24: ='Detailed Budget'!V127 -> 582030 | J24: ='Detailed Budget'!W127 -> 2188449.6 | K24: ='Detailed Budget'!AA127 -> 1592369.5 | L24: ='Detailed Budget'!AB127 -> 574200 | M24: ='Detailed Budget'!AC127 -> 2166569.5 | N24: ='Detailed Budget'!AG127 -> 1320234 | O24: ='Detailed Budget'!AH127 -> 477630 | P24: ='Detailed Budget'!AI127 -> 1797864 | Q24: ='Detailed Budget'!AJ127 -> 8499999.7 | R24: ='Detailed Budget'!AK127 -> 2735280 | S24: ='Detailed Budget'!AL127 -> 11235280
Q25: =Q24-8500000 -> -0.34737351

Sheet Detailed Budget
A1: Entity: | B1: P | D1: Partners of the Americas F2F Caribbean Basin Program Budget
A2: Program-Dept.: | B2: 30100 | D2: USAID NOFO #7200AA23RFA00006
A3: Funder-Grant: | B3: USAID650
A4: Budget (Activity) Code | B4: Account Code | C4: Country Code | D4: Line Items | I4: Year 1 | O4: Year 2 | R4: Year 3 | AA4: Year 4 | AG4: Year 5 | AJ4: Total | AK4: Total | AL4: Grand
E5: Unit | F5: Cost | G5: Duration | H5: Type | I5: USAID | J5: Leverage | K5: Total | L5: Unit | M5: Cost | N5: Duration | O5: USAID | P5: Leverage | Q5: Total | R5: Unit | S5: Cost | T5: Duration | U5: USAID | V5: Leverage | W5: Total | X5: Unit | Y5: Cost | Z5: Duration | AA5: USAID | AB5: Leverage | AC5: Total | AD5: Unit | AE5: Cost | AF5: Duration | AG5: USAID | AH5: Leverage | AI5: Total | AJ5: USAID | AK5: Leverage | AL5: Total
D7: Personnel
D8: Headquarters | E8: LOE
A9: PERSNL | B9: 50000 | C9: USA | D9: Senior Director | E9: 0.05 | F9: =120000/12 -> 10000 | G9: 12 | H9: /months | I9: =G9*F9*E9 -> 6000 | J9: 0 | K9: =SUM(I9:J9) -> 6000 | L9: =E9 -> 0.05 | M9: =F9*1.03 -> 10300 | N9: 12 | O9: =L9*M9*N9 -> 6180 | P9: 0 | Q9: =SUM(O9:P9) -> 6180 | R9: =E9 -> 0.05 | S9: =M9*1.03 -> 10609 | T9: 12 | U9: =R9*S9*T9 -> 6365.4 | V9: 0 | W9: =SUM(U9:V9) -> 6365.4 | X9: =R9 -> 0.05 | Y9: =S9*1.03 -> 10927.27 | Z9: 12 | AA9: =X9*Y9*Z9 -> 6556.362 | AB9: 0 | AC9: =SUM(AA9:AB9) -> 6556.362 | AD9: =X9 -> 0.05 | AE9: =Y9*1.03 -> 11255.088 | AF9: 12 | AG9: =AD9*AE9*AF9 -> 6753.0529 | AH9: 0 | AI9: =SUM(AG9:AH9) -> 6753.0529 | AJ9: =I9+O9+U9+AA9+AG9 -> 31854.815 | AK9: =J9+P9+V9+AB9+AH9 -> 0 | AL9: =SUM(AJ9:AK9) -> 31854.815
A10: PERSNL | B10: 50000 | C10: USA | D10: Program Director* | E10: 0.75 | F10: =92000/12 -> 7666.6667 | G10: 12 | H10: /months | I10: =G10*F10*E10 -> 69000 | J10: 0 | K10: =SUM(I10:J10) -> 69000 | L10: =E10 -> 0.75 | M10: =F10*1.03 -> 7896.6667 | N10: 12 | O10: =L10*M10*N10 -> 71070 | P10: 0 | Q10: =SUM(O10:P10) -> 71070 | R10: =E10 -> 0.75 | S10: =M10*1.03 -> 8133.5667 | T10: 12 | U10: =R10*S10*T10 -> 73202.1 | V10: 0 | W10: =SUM(U10:V10) -> 73202.1 | X10: =R10 -> 0.75 | Y10: =S10*1.03 -> 8377.5737 | Z10: 12 | AA10: =X10*Y10*Z10 -> 75398.163 | AB10: 0 | AC10: =SUM(AA10:AB10) -> 75398.163 | AD10: =X10 -> 0.75 | AE10: =Y10*1.03 -> 8628.9009 | AF10: 12 | AG10: =AD10*AE10*AF10 -> 77660.108 | AH10: 0 | AI10: =SUM(AG10:AH10) -> 77660.108 | AJ10: =I10+O10+U10+AA10+AG10 -> 366330.37 | AK10: =J10+P10+V10+AB10+AH10 -> 0 | AL10: =SUM(AJ10:AK10) -> 366330.37
A11: PERSNL | B11: 50000 | C11: USA | D11: Program Manager | E11: 0.8 | F11: =80000/12 -> 6666.6667 | G11: 9 | H11: /months | I11: =G11*F11*E11 -> 48000 | J11: 0 | K11: =SUM(I11:J11) -> 48000 | L11: =E11 -> 0.8 | M11: =F11*1.03 -> 6866.6667 | N11: 12 | O11: =L11*M11*N11 -> 65920 | P11: 0 | Q11: =SUM(O11:P11) -> 65920 | R11: =L11 -> 0.8 | S11: =M11*1.03 -> 7072.6667 | T11: 12 | U11: =R11*S11*T11 -> 67897.6 | V11: 0 | W11: =SUM(U11:V11) -> 67897.6 | X11: =R11 -> 0.8 | Y11: =S11*1.03 -> 7284.8467 | Z11: 12 | AA11: =X11*Y11*Z11 -> 69934.528 | AB11: 0 | AC11: =SUM(AA11:AB11) -> 69934.528 | AD11: =X11 -> 0.8 | AE11: =Y11*1.03 -> 7503.3921 | AF11: 10 | AG11: =AD11*AE11*AF11 -> 60027.137 | AH11: 0 | AI11: =SUM(AG11:AH11) -> 60027.137 | AJ11: =I11+O11+U11+AA11+AG11 -> 311779.26 | AK11: =J11+P11+V11+AB11+AH11 -> 0 | AL11: =SUM(AJ11:AK11) -> 311779.26
A12: PERSNL | B12: 50000 | C12: USA | D12: Technical & M&E Officer | E12: 0.9 | F12: 4820 | G12: 10 | H12: /months | I12: =G12*F12*E12 -> 43380 | J12: 0 | K12: =SUM(I12:J12) -> 43380 | L12: =E12 -> 0.9 | M12: =F12*1.03 -> 4964.6 | N12: 12 | O12: =L12*M12*N12 -> 53617.68 | P12: 0 | Q12: =SUM(O12:P12) -> 53617.68 | R12: =L12 -> 0.9 | S12: =M12*1.03 -> 5113.538 | T12: 12 | U12: =R12*S12*T12 -> 55226.21 | V12: 0 | W12: =SUM(U12:V12) -> 55226.21 | X12: =R12 -> 0.9 | Y12: =S12*1.03 -> 5266.9441 | Z12: 12 | AA12: =X12*Y12*Z12 -> 56882.997 | AB12: 0 | AC12: =SUM(AA12:AB12) -> 56882.997 | AD12: =X12 -> 0.9 | AE12: =Y12*1.03 -> 5424.9525 | AF12: 10 | AG12: =AD12*AE12*AF12 -> 48824.572 | AH12: 0 | AI12: =SUM(AG12:AH12) -> 48824.572 | AJ12: =I12+O12+U12+AA12+AG12 -> 257931.46 | AK12: =J12+P12+V12+AB12+AH12 -> 0 | AL12: =SUM(AJ12:AK12) -> 257931.46
A13: PERSNL | B13: 50000 | C13: USA | D13: Recruiter | E13: 0.9 | F13: =51000/12 -> 4250 | G13: 10 | H13: /months | I13: =G13*F13*E13 -> 38250 | J13: 0 | K13: =SUM(I13:J13) -> 38250 | L13: =E13 -> 0.9 | M13: =F13*1.03 -> 4377.5 | N13: 12 | O13: =L13*M13*N13 -> 47277 | P13: 0 | Q13: =SUM(O13:P13) -> 47277 | R13: =L13 -> 0.9 | S13: =M13*1.03 -> 4508.825 | T13: 12 | U13: =R13*S13*T13 -> 48695.31 | V13: 0 | W13: =SUM(U13:V13) -> 48695.31 | X13: =R13 -> 0.9 | Y13: =S13*1.03 -> 4644.0898 | Z13: 12 | AA13: =X13*Y13*Z13 -> 50156.169 | AB13: 0 | AC13: =SUM(AA13:AB13) -> 50156.169 | AD13: =X13 -> 0.9 | AE13: =Y13*1.03 -> 4783.4124 | AF13: 8 | AG13: =AD13*AE13*AF13 -> 34440.57 | AH13: 0 | AI13: =SUM(AG13:AH13) -> 34440.57 | AJ13: =I13+O13+U13+AA13+AG13 -> 218819.05 | AK13: =J13+P13+V13+AB13+AH13 -> 0 | AL13: =SUM(AJ13:AK13) -> 218819.05
D14: Subtotal HQ Personnel | I14: =SUM(I9:I13) -> 204630 | J14: =SUM(J9:J13) -> 0 | K14: =SUM(K9:K13) -> 204630 | O14: =SUM(O9:O13) -> 244064.68 | P14: =SUM(P9:P13) -> 0 | Q14: =SUM(Q9:Q13) -> 244064.68 | U14: =SUM(U9:U13) -> 251386.62 | V14: =SUM(V9:V13) -> 0 | W14: =SUM(W9:W13) -> 251386.62 | AA14: =SUM(AA9:AA13) -> 258928.22 | AB14: =SUM(AB9:AB13) -> 0 | AC14: =SUM(AC9:AC13) -> 258928.22 | AG14: =SUM(AG9:AG13) -> 227705.44 | AH14: =SUM(AH9:AH13) -> 0 | AI14: =SUM(AI9:AI13) -> 227705.44 | AJ14: =SUM(AJ9:AJ13) -> 1186715 | AK14: =SUM(AK9:AK13) -> 0 | AL14: =SUM(AL9:AL13) -> 1186715
D15: *Key Personnel
D16: Field Personnel | E16: LOE
A17: PERSNL-GTM | B17: 70000 | C17: GTM | D17: Guatemala | E17: 1 | G17: 1 | H17: /year | I17: ='Guatemala '!I14 -> 94150 | J17: 0 | K17: =SUM(I17:J17) -> 94150 | O17: ='Guatemala '!N14 -> 108150 | P17: 0 | Q17: =SUM(O17:P17) -> 108150 | U17: ='Guatemala '!S14 -> 111394.5 | V17: 0 | W17: =SUM(U17:V17) -> 111394.5 | AA17: ='Guatemala '!X14 -> 114736.34 | AB17: 0 | AC17: =SUM(AA17:AB17) -> 114736.34 | AG17: ='Guatemala '!AC14 -> 84413.161 | AH17: 0 | AI17: =SUM(AG17:AH17) -> 84413.161 | AJ17: =I17+O17+U17+AA17+AG17 -> 512844 | AK17: =J17+P17+V17+AB17+AH17 -> 0 | AL17: =SUM(AJ17:AK17) -> 512844
A18: PERSNL-DOM | B18: 70000 | C18: DOM | D18: Dominican Republic | E18: 1 | G18: 1 | H18: /year | I18: ='Dominican Republic'!I14 -> 84700 | J18: 0 | K18: =SUM(I18:J18) -> 84700 | O18: ='Dominican Republic'!N14 -> 100116 | P18: 0 | Q18: =SUM(O18:P18) -> 100116 | U18: ='Dominican Republic'!S14 -> 103119.48 | V18: 0 | W18: =SUM(U18:V18) -> 103119.48 | AA18: ='Dominican Republic'!X14 -> 106213.06 | AB18: 0 | AC18: =SUM(AA18:AB18) -> 106213.06 | AG18: ='Dominican Republic'!AC14 -> 77322.455 | AH18: 0 | AI18: =SUM(AG18:AH18) -> 77322.455 | AJ18: =I18+O18+U18+AA18+AG18 -> 471471 | AK18: =J18+P18+V18+AB18+AH18 -> 0 | AL18: =SUM(AJ18:AK18) -> 471471
A19: PERSNL-GUY | B19: 70000 | C19: GUY | D19: Guyana | E19: 1 | G19: 1 | H19: /year | I19: =Guyana!I13 -> 68350 | J19: 0 | K19: =SUM(I19:J19) -> 68350 | O19: =Guyana!N13 -> 73542 | P19: 0 | Q19: =SUM(O19:P19) -> 73542 | U19: =Guyana!S13 -> 75748.26 | V19: 0 | W19: =SUM(U19:V19) -> 75748.26 | AA19: =Guyana!X13 -> 78020.708 | AB19: 0 | AC19: =SUM(AA19:AB19) -> 78020.708 | AG19: =Guyana!AC13 -> 60270.997 | AH19: 0 | AI19: =SUM(AG19:AH19) -> 60270.997 | AJ19: =I19+O19+U19+AA19+AG19 -> 355931.96 | AK19: =J19+P19+V19+AB19+AH19 -> 0 | AL19: =SUM(AJ19:AK19) -> 355931.96
A20: PERSNL-JAM | B20: 70000 | C20: JAM | D20: Jamaica | E20: 1 | G20: 1 | H20: /year | I20: =Jamaica!I13 -> 82650 | J20: 0 | K20: =SUM(I20:J20) -> 82650 | O20: =Jamaica!N13 -> 88374 | P20: 0 | Q20: =SUM(O20:P20) -> 88374 | U20: =Jamaica!S13 -> 91025.22 | V20: 0 | W20: =SUM(U20:V20) -> 91025.22 | AA20: =Jamaica!X13 -> 93755.977 | AB20: 0 | AC20: =SUM(AA20:AB20) -> 93755.977 | AG20: =Jamaica!AC13 -> 72426.492 | AH20: 0 | AI20: =SUM(AG20:AH20) -> 72426.492 | AJ20: =I20+O20+U20+AA20+AG20 -> 428231.69 | AK20: =J20+P20+V20+AB20+AH20 -> 0 | AL20: =SUM(AJ20:AK20) -> 428231.69
D21: Subtotal Field Personnel | I21: =SUM(I17:I20) -> 329850 | J21: =SUM(J17:J20) -> 0 | K21: =SUM(K17:K20) -> 329850 | O21: =SUM(O17:O20) -> 370182 | P21: =SUM(P17:P20) -> 0 | Q21: =SUM(Q17:Q20) -> 370182 | U21: =SUM(U17:U20) -> 381287.46 | V21: =SUM(V17:V20) -> 0 | W21: =SUM(W17:W20) -> 381287.46 | AA21: =SUM(AA17:AA20) -> 392726.08 | AB21: =SUM(AB17:AB20) -> 0 | AC21: =SUM(AC17:AC20) -> 392726.08 | AG21: =SUM(AG17:AG20) -> 294433.1 | AH21: =SUM(AH17:AH20) -> 0 | AI21: =SUM(AI17:AI20) -> 294433.1 | AJ21: =I21+O21+U21+AA21+AG21 -> 1768478.6 | AK21: =J21+P21+V21+AB21+AH21 -> 0 | AL21: =SUM(AJ21:AK21) -> 1768478.6
D23: F2F Volunteers | E23: =Leverage!F2 -> 980 | F23: 522 | G23: 1 | H23: /day | I23: 0 | J23: =F23*E23*G23 -> 511560 | K23: =SUM(I23:J23) -> 511560 | L23: =Leverage!F3 -> 1130 | M23: =F23 -> 522 | N23: 1 | O23: 0 | P23: =M23*L23*N23 -> 589860 | Q23: =SUM(O23:P23) -> 589860 | R23: =Leverage!F4 -> 1115 | S23: =F23 -> 522 | T23: 1 | U23: 0 | V23: =S23*R23*T23 -> 582030 | W23: =SUM(U23:V23) -> 582030 | X23: =Leverage!F5 -> 1100 | Y23: =F23 -> 522 | Z23: 1 | AA23: 0 | AB23: =Y23*X23*Z23 -> 574200 | AC23: =SUM(AA23:AB23) -> 574200 | AD23: =Leverage!F6 -> 915 | AE23: =F23 -> 522 | AF23: 1 | AG23: 0 | AH23: =AE23*AD23*AF23 -> 477630 | AI23: =SUM(AG23:AH23) -> 477630 | AJ23: =I23+O23+U23+AA23+AG23 -> 0 | AK23: =J23+P23+V23+AB23+AH23 -> 2735280 | AL23: =SUM(AJ23:AK23) -> 2735280
D25: Personnel Total | I25: =I21+I14+I23 -> 534480 | J25: =SUM(J23:J23) -> 511560 | K25: =K21+K14+K23 -> 1046040 | O25: =O21+O14+O23 -> 614246.68 | P25: =SUM(P23:P23) -> 589860 | Q25: =Q21+Q14+Q23 -> 1204106.7 | U25: =U21+U14+U23 -> 632674.08 | V25: =SUM(V23:V23) -> 582030 | W25: =W21+W14+W23 -> 1214704.1 | AA25: =AA21+AA14+AA23 -> 651654.3 | AB25: =SUM(AB23:AB23) -> 574200 | AC25: =AC21+AC14+AC23 -> 1225854.3 | AG25: =AG21+AG14+AG23 -> 522138.54 | AH25: =SUM(AH23:AH23) -> 477630 | AI25: =AI21+AI14+AI23 -> 999768.54 | AJ25: =AJ21+AJ14+AJ23 -> 2955193.6 | AK25: =SUM(AK23:AK23) -> 2735280 | AL25: =AL21+AL14+AL23 -> 5690473.6
D27: Fringe Benefits
A28: FRINGE | B28: 50900 | C28: USA | D28: Fringe Benefits - Headquarters | E28: 0.2347 | I28: =I14*E28 -> 48026.661 | J28: 0 | K28: =SUM(I28:J28) -> 48026.661 | O28: =O14*$E$28 -> 57281.98 | P28: 0 | Q28: =SUM(O28:P28) -> 57281.98 | U28: =U14*$E$28 -> 59000.44 | V28: 0 | W28: =SUM(U28:V28) -> 59000.44 | AA28: =AA14*$E$28 -> 60770.453 | AB28: 0 | AC28: =SUM(AA28:AB28) -> 60770.453 | AG28: =AG14*$E$28 -> 53442.467 | AH28: 0 | AI28: =SUM(AG28:AH28) -> 53442.467 | AJ28: =I28+O28+U28+AA28+AG28 -> 278522 | AK28: =J28+P28+V28+AB28+AH28 -> 0 | AL28: =SUM(AJ28:AK28) -> 278522
A29: VARIOUS SEE TAB | B29: 70015 | C29: VARIOUS SEE TAB | D29: Fringe Benefits - Field | I29: ='Guatemala '!I16+'Dominican Republic'!I16+Guyana!I15+Jamaica!I15 -> 80164.285 | J29: 0 | K29: =SUM(I29:J29) -> 80164.285 | O29: ='Guatemala '!N16+'Dominican Republic'!N16+Guyana!N15+Jamaica!N15 -> 91458.005 | P29: 0 | Q29: =SUM(O29:P29) -> 91458.005 | U29: ='Guatemala '!T16+'Dominican Republic'!T16+Guyana!T15+Jamaica!T15 -> 94201.746 | V29: 0 | W29: =SUM(U29:V29) -> 94201.746 | AA29: ='Guatemala '!X16+'Dominican Republic'!X16+Guyana!X15+Jamaica!X15 -> 97027.798 | AB29: 0 | AC29: =SUM(AA29:AB29) -> 97027.798 | AG29: ='Guatemala '!AC16+'Dominican Republic'!AC16+Guyana!AC15+Jamaica!AC15 -> 71950.385 | AH29: 0 | AI29: =SUM(AG29:AH29) -> 71950.385 | AJ29: =I29+O29+U29+AA29+AG29 -> 434802.22 | AK29: =J29+P29+V29+AB29+AH29 -> 0 | AL29: =SUM(AJ29:AK29) -> 434802.22
D31: Fringe Benefits Total | I31: =SUM(I28:I30) -> 128190.95 | J31: =SUM(J28:J30) -> 0 | K31: =SUM(K28:K30) -> 128190.95 | O31: =SUM(O28:O30) -> 148739.99 | P31: =SUM(P28:P30) -> 0 | Q31: =SUM(Q28:Q30) -> 148739.99 | U31: =SUM(U28:U30) -> 153202.19 | V31: =SUM(V28:V30) -> 0 | W31: =SUM(W28:W30) -> 153202.19 | AA31: =SUM(AA28:AA30) -> 157798.25 | AB31: =SUM(AB28:AB30) -> 0 | AC31: =SUM(AC28:AC30) -> 157798.25 | AG31: =SUM(AG28:AG30) -> 125392.85 | AH31: =SUM(AH28:AH30) -> 0 | AI31: =SUM(AI28:AI30) -> 125392.85 | AJ31: =SUM(AJ28:AJ30) -> 713324.22 | AK31: =SUM(AK28:AK30) -> 0 | AL31: =SUM(AL28:AL30) -> 713324.22
D33: Travel
D35: Volunteer Travel - International Airfare
A36: VFLYGTM | B36: 86040 | C36: GTM | D36: Guatemala | E36: ='Guatemala '!E26 -> 16 | F36: ='Guatemala '!F26 -> 650 | G36: 1 | H36: /RT | I36: =G36*F36*E36 -> 10400 | J36: 0 | K36: =SUM(I36:J36) -> 10400 | L36: ='Guatemala '!K26 -> 22 | M36: =F36*1.02 -> 663 | N36: 1 | O36: =L36*M36*N36 -> 14586 | P36: 0 | Q36: =SUM(O36:P36) -> 14586 | R36: ='Guatemala '!P26 -> 22 | S36: =M36*1.02 -> 676.26 | T36: 1 | U36: =R36*S36*T36 -> 14877.72 | V36: 0 | W36: =SUM(U36:V36) -> 14877.72 | X36: ='Guatemala '!U26 -> 22 | Y36: =S36*1.02 -> 689.7852 | Z36: 1 | AA36: =X36*Y36*Z36 -> 15175.274 | AB36: 0 | AC36: =SUM(AA36:AB36) -> 15175.274 | AD36: ='Guatemala '!Z26 -> 16 | AE36: =Y36*1.02 -> 703.5809 | AF36: 1 | AG36: =AD36*AE36*AF36 -> 11257.294 | AH36: 0 | AI36: =SUM(AG36:AH36) -> 11257.294 | AJ36: =I36+O36+U36+AA36+AG36 -> 66296.289 | AK36: =J36+P36+V36+AB36+AH36 -> 0 | AL36: =SUM(AJ36:AK36) -> 66296.289
A37: VFLYDOM | B37: 86040 | C37: DOM | D37: Dominican Republic | E37: ='Dominican Republic'!E26 -> 16 | F37: ='Dominican Republic'!F26 -> 750 | G37: 1 | H37: /RT | I37: =G37*F37*E37 -> 12000 | J37: 0 | K37: =SUM(I37:J37) -> 12000 | L37: ='Dominican Republic'!K26 -> 22 | M37: =F37*1.02 -> 765 | N37: 1 | O37: =L37*M37*N37 -> 16830 | P37: 0 | Q37: =SUM(O37:P37) -> 16830 | R37: ='Dominican Republic'!P26 -> 22 | S37: =M37*1.02 -> 780.3 | T37: 1 | U37: =R37*S37*T37 -> 17166.6 | V37: 0 | W37: =SUM(U37:V37) -> 17166.6 | X37: ='Dominican Republic'!U26 -> 22 | Y37: =S37*1.02 -> 795.906 | Z37: 1 | AA37: =X37*Y37*Z37 -> 17509.932 | AB37: 0 | AC37: =SUM(AA37:AB37) -> 17509.932 | AD37: ='Dominican Republic'!Z26 -> 16 | AE37: =Y37*1.02 -> 811.82412 | AF37: 1 | AG37: =AD37*AE37*AF37 -> 12989.186 | AH37: 0 | AI37: =SUM(AG37:AH37) -> 12989.186 | AJ37: =I37+O37+U37+AA37+AG37 -> 76495.718 | AK37: =J37+P37+V37+AB37+AH37 -> 0 | AL37: =SUM(AJ37:AK37) -> 76495.718
A38: VFLYGUY | B38: 86040 | C38: GUY | D38: Guyana | E38: =Guyana!E25 -> 14 | F38: =Guyana!F25 -> 850 | G38: 1 | H38: /RT | I38: =G38*F38*E38 -> 11900 | J38: 0 | K38: =SUM(I38:J38) -> 11900 | L38: =Guyana!K25 -> 13 | M38: =F38*1.02 -> 867 | N38: 1 | O38: =L38*M38*N38 -> 11271 | P38: 0 | Q38: =SUM(O38:P38) -> 11271 | R38: =Guyana!P25 -> 13 | S38: =M38*1.02 -> 884.34 | T38: 1 | U38: =R38*S38*T38 -> 11496.42 | V38: 0 | W38: =SUM(U38:V38) -> 11496.42 | X38: =Guyana!U25 -> 12 | Y38: =S38*1.02 -> 902.0268 | Z38: 1 | AA38: =X38*Y38*Z38 -> 10824.322 | AB38: 0 | AC38: =SUM(AA38:AB38) -> 10824.322 | AD38: =Guyana!Z25 -> 12 | AE38: =Y38*1.02 -> 920.06734 | AF38: 1 | AG38: =AD38*AE38*AF38 -> 11040.808 | AH38: 0 | AI38: =SUM(AG38:AH38) -> 11040.808 | AJ38: =I38+O38+U38+AA38+AG38 -> 56532.55 | AK38: =J38+P38+V38+AB38+AH38 -> 0 | AL38: =SUM(AJ38:AK38) -> 56532.55
A39: VFLYJAM | B39: 86040 | C39: JAM | D39: Jamaica | E39: =Jamaica!E25 -> 14 | F39: =Jamaica!F25 -> 800 | G39: 1 | H39: /RT | I39: =G39*F39*E39 -> 11200 | J39: 0 | K39: =SUM(I39:J39) -> 11200 | L39: =Jamaica!K25 -> 13 | M39: =F39*1.02 -> 816 | N39: 1 | O39: =L39*M39*N39 -> 10608 | P39: 0 | Q39: =SUM(O39:P39) -> 10608 | R39: =Jamaica!P25 -> 12 | S39: =M39*1.02 -> 832.32 | T39: 1 | U39: =R39*S39*T39 -> 9987.84 | V39: 0 | W39: =SUM(U39:V39) -> 9987.84 | X39: =Jamaica!U25 -> 12 | Y39: =S39*1.02 -> 848.9664 | Z39: 1 | AA39: =X39*Y39*Z39 -> 10187.597 | AB39: 0 | AC39: =SUM(AA39:AB39) -> 10187.597 | AD39: =Jamaica!Z25 -> 13 | AE39: =Y39*1.02 -> 865.94573 | AF39: 1 | AG39: =AD39*AE39*AF39 -> 11257.294 | AH39: 0 | AI39: =SUM(AG39:AH39) -> 11257.294 | AJ39: =I39+O39+U39+AA39+AG39 -> 53240.731 | AK39: =J39+P39+V39+AB39+AH39 -> 0 | AL39: =SUM(AJ39:AK39) -> 53240.731
A40: VOLTRAVEL | B40: 86040 | C40: FLX | D40: Flexible (Additional Countries) | E40: ='Volunteer Travel'!C12 -> 3 | F40: ='Volunteer Travel'!B31 -> 887 | G40: 1 | H40: /RT | I40: =G40*F40*E40 -> 2661 | J40: 0 | K40: =SUM(I40:J40) -> 2661 | L40: ='Volunteer Travel'!D12 -> 3 | M40: =F40*1.02 -> 904.74 | N40: 1 | O40: =L40*M40*N40 -> 2714.22 | P40: 0 | Q40: =SUM(O40:P40) -> 2714.22 | R40: ='Volunteer Travel'!E12 -> 4 | S40: =M40*1.02 -> 922.8348 | T40: 1 | U40: =R40*S40*T40 -> 3691.3392 | V40: 0 | W40: =SUM(U40:V40) -> 3691.3392 | X40: ='Volunteer Travel'!F12 -> 4 | Y40: =S40*1.02 -> 941.2915 | Z40: 1 | AA40: =X40*Y40*Z40 -> 3765.166 | AB40: 0 | AC40: =SUM(AA40:AB40) -> 3765.166 | AD40: ='Volunteer Travel'!G12 -> 4 | AE40: =Y40*1.02 -> 960.11733 | AF40: 1 | AG40: =AD40*AE40*AF40 -> 3840.4693 | AH40: 0 | AI40: =SUM(AG40:AH40) -> 3840.4693 | AJ40: =I40+O40+U40+AA40+AG40 -> 16672.194 | AK40: =J40+P40+V40+AB40+AH40 -> 0 | AL40: =SUM(AJ40:AK40) -> 16672.194
D41: Total Volunteer Airfare | E41: =SUM(E36:E40) -> 63 | I41: =SUM(I36:I40) -> 48161 | J41: =SUM(J36:J40) -> 0 | K41: =SUM(K36:K40) -> 48161 | L41: =SUM(L36:L40) -> 73 | O41: =SUM(O36:O40) -> 56009.22 | P41: =SUM(P36:P40) -> 0 | Q41: =SUM(Q36:Q40) -> 56009.22 | R41: =SUM(R36:R40) -> 73 | U41: =SUM(U36:U40) -> 57219.919 | V41: =SUM(V36:V40) -> 0 | W41: =SUM(W36:W40) -> 57219.919 | X41: =SUM(X36:X40) -> 72 | AA41: =SUM(AA36:AA40) -> 57462.291 | AB41: =SUM(AB36:AB40) -> 0 | AC41: =SUM(AC36:AC40) -> 57462.291 | AD41: =SUM(AD36:AD40) -> 61 | AG41: =SUM(AG36:AG40) -> 50385.052 | AH41: =SUM(AH36:AH40) -> 0 | AI41: =SUM(AI36:AI40) -> 50385.052 | AJ41: =SUM(AJ36:AJ40) -> 269237.48 | AK41: =SUM(AK36:AK40) -> 0 | AL41: =SUM(AL36:AL40) -> 269237.48
D43: Volunteer Travel-Related Costs (Traditional & Paired)
A44: VARIOUS SEE TAB | B44: 86000 (Transport)/ 86030 (Lodging)/ 86050 (M&IE) | C44: GTM | D44: Guatemala - Volunteer Travel Related Costs | E44: 1 | F44: =SUM('Guatemala '!I27:I35) -> 34108.665 | G44: 1 | H44: /year | I44: =G44*F44*E44 -> 34108.665 | J44: 0 | K44: =SUM(I44:J44) -> 34108.665 | L44: 1 | M44: =SUM('Guatemala '!O27:O35) -> 46333.839 | N44: 1 | O44: =L44*M44*N44 -> 46333.839 | P44: 0 | Q44: =SUM(O44:P44) -> 46333.839 | R44: 1 | S44: =SUM('Guatemala '!T27:T35) -> 47260.516 | T44: 1 | U44: =R44*S44*T44 -> 47260.516 | V44: 0 | W44: =SUM(U44:V44) -> 47260.516 | X44: 1 | Y44: =SUM('Guatemala '!Y27:Y35) -> 48205.726 | Z44: 1 | AA44: =X44*Y44*Z44 -> 48205.726 | AB44: 0 | AC44: =SUM(AA44:AB44) -> 48205.726 | AD44: 1 | AE44: =SUM('Guatemala '!AD27:AD35) -> 36008.548 | AF44: 1 | AG44: =AD44*AE44*AF44 -> 36008.548 | AH44: 0 | AI44: =SUM(AG44:AH44) -> 36008.548 | AJ44: =I44+O44+U44+AA44+AG44 -> 211917.29 | AK44: =J44+P44+V44+AB44+AH44 -> 0 | AL44: =SUM(AJ44:AK44) -> 211917.29
A45: VARIOUS SEE TAB | B45: 86000 (Transport)/ 86030 (Lodging)/ 86050 (M&IE) | C45: DOM | D45: Dominican Republic - Volunteer Travel Related Costs | E45: 1 | F45: =SUM('Dominican Republic'!I27:I35) -> 39000.27 | G45: 1 | H45: /year | I45: =G45*F45*E45 -> 39000.27 | J45: 0 | K45: =SUM(I45:J45) -> 39000.27 | L45: 1 | M45: =SUM('Dominican Republic'!O27:O35) -> 53251.074 | N45: 1 | O45: =L45*M45*N45 -> 53251.074 | P45: 0 | Q45: =SUM(O45:P45) -> 53251.074 | R45: 1 | S45: =SUM('Dominican Republic'!S27:S35) -> 54316.095 | T45: 1 | U45: =R45*S45*T45 -> 54316.095 | V45: 0 | W45: =SUM(U45:V45) -> 54316.095 | X45: 1 | Y45: =SUM('Dominican Republic'!Y27:Y35) -> 55402.417 | Z45: 1 | AA45: =X45*Y45*Z45 -> 55402.417 | AB45: 0 | AC45: =SUM(AA45:AB45) -> 55402.417 | AD45: 1 | AE45: =SUM('Dominican Republic'!AD27:AD35) -> 41337.797 | AF45: 1 | AG45: =AD45*AE45*AF45 -> 41337.797 | AH45: 0 | AI45: =SUM(AG45:AH45) -> 41337.797 | AJ45: =I45+O45+U45+AA45+AG45 -> 243307.65 | AK45: =J45+P45+V45+AB45+AH45 -> 0 | AL45: =SUM(AJ45:AK45) -> 243307.65
A46: VARIOUS SEE TAB | B46: 86000 (Transport)/ 86030 (Lodging)/ 86050 (M&IE) | C46: GUY | D46: Guyana - Volunteer Travel Related Costs | E46: 1 | F46: =SUM(Guyana!I26:I34) -> 37219.024 | G46: 1 | H46: /year | I46: =G46*F46*E46 -> 37219.024 | J46: 0 | K46: =SUM(I46:J46) -> 37219.024 | L46: 1 | M46: =SUM(Guyana!N26:N34) -> 36276.316 | N46: 1 | O46: =L46*M46*N46 -> 36276.316 | P46: 0 | Q46: =SUM(O46:P46) -> 36276.316 | R46: 1 | S46: =SUM(Guyana!S26:S34) -> 37001.843 | T46: 1 | U46: =R46*S46*T46 -> 37001.843 | V46: 0 | W46: =SUM(U46:V46) -> 37001.843 | X46: 1 | Y46: =SUM(Guyana!Y26:Y34) -> 35053.903 | Z46: 1 | AA46: =X46*Y46*Z46 -> 35053.903 | AB46: 0 | AC46: =SUM(AA46:AB46) -> 35053.903 | AD46: 1 | AE46: =SUM(Guyana!AD26:AD34) -> 34803.597 | AF46: 1 | AG46: =AD46*AE46*AF46 -> 34803.597 | AH46: 0 | AI46: =SUM(AG46:AH46) -> 34803.597 | AJ46: =I46+O46+U46+AA46+AG46 -> 180354.68 | AK46: =J46+P46+V46+AB46+AH46 -> 0 | AL46: =SUM(AJ46:AK46) -> 180354.68
A47: VARIOUS SEE TAB | B47: 86000 (Transport)/ 86030 (Lodging)/ 86050 (M&IE) | C47: JAM | D47: Jamaica - Volunteer Travel Related Costs | E47: 1 | F47: =SUM(Jamaica!I26:I34) -> 37878.62 | G47: 1 | H47: /year | I47: =G47*F47*E47 -> 37878.62 | J47: 0 | K47: =SUM(I47:J47) -> 37878.62 | L47: 1 | M47: =SUM(Jamaica!N26:N34) -> 36891.697 | N47: 1 | O47: =L47*M47*N47 -> 36891.697 | P47: 0 | Q47: =SUM(O47:P47) -> 36891.697 | R47: 1 | S47: =SUM(Jamaica!S26:S34) -> 34944.05 | T47: 1 | U47: =R47*S47*T47 -> 34944.05 | V47: 0 | W47: =SUM(U47:V47) -> 34944.05 | X47: 1 | Y47: =SUM(Jamaica!Y26:Y34) -> 35642.931 | Z47: 1 | AA47: =X47*Y47*Z47 -> 35642.931 | AB47: 0 | AC47: =SUM(AA47:AB47) -> 35642.931 | AD47: 1 | AE47: =SUM(Jamaica!AD26:AD34) -> 38207.063 | AF47: 1 | AG47: =AD47*AE47*AF47 -> 38207.063 | AH47: 0 | AI47: =SUM(AG47:AH47) -> 38207.063 | AJ47: =I47+O47+U47+AA47+AG47 -> 183564.36 | AK47: =J47+P47+V47+AB47+AH47 -> 0 | AL47: =SUM(AJ47:AK47) -> 183564.36
A48: VOLTRVCTS | B48: 86000 (Transport)/ 86030 (Lodging)/ 86050 (M&IE) | C48: FLX | D48: Flexible - Volunteer Travel Related Costs | E48: 1 | F48: ='Volunteer Travel'!B34*'Detailed Budget'!E40 -> 5571 | G48: 1 | H48: /year | I48: =G48*F48*E48 -> 5571 | J48: 0 | K48: =SUM(I48:J48) -> 5571 | L48: 1 | M48: ='Volunteer Travel'!C34*'Detailed Budget'!L40 -> 5739 | N48: 1 | O48: =L48*M48*N48 -> 5739 | P48: 0 | Q48: =SUM(O48:P48) -> 5739 | R48: 1 | S48: ='Volunteer Travel'!D34*'Detailed Budget'!R40 -> 7880 | T48: 1 | U48: =R48*S48*T48 -> 7880 | V48: 0 | W48: =SUM(U48:V48) -> 7880 | X48: 1 | Y48: ='Volunteer Travel'!F34*'Detailed Budget'!X40 -> 8116 | Z48: 1 | AA48: =X48*Y48*Z48 -> 8116 | AB48: 0 | AC48: =SUM(AA48:AB48) -> 8116 | AD48: 1 | AE48: ='Volunteer Travel'!G34*'Detailed Budget'!AD40 -> 8360 | AF48: 1 | AG48: =AD48*AE48*AF48 -> 8360 | AH48: 0 | AI48: =SUM(AG48:AH48) -> 8360 | AJ48: =I48+O48+U48+AA48+AG48 -> 35666 | AK48: =J48+P48+V48+AB48+AH48 -> 0 | AL48: =SUM(AJ48:AK48) -> 35666
D49: Total Volunteer Travel-Related | I49: =SUM(I44:I48) -> 153777.58 | J49: =SUM(J44:J48) -> 0 | K49: =SUM(K44:K48) -> 153777.58 | O49: =SUM(O44:O48) -> 178491.93 | P49: =SUM(P44:P48) -> 0 | Q49: =SUM(Q44:Q48) -> 178491.93 | U49: =SUM(U44:U48) -> 181402.5 | V49: =SUM(V44:V48) -> 0 | W49: =SUM(W44:W48) -> 181402.5 | AA49: =SUM(AA44:AA48) -> 182420.98 | AB49: =SUM(AB44:AB48) -> 0 | AC49: =SUM(AC44:AC48) -> 182420.98 | AG49: =SUM(AG44:AG48) -> 158717.01 | AH49: =SUM(AH44:AH48) -> 0 | AI49: =SUM(AI44:AI48) -> 158717.01 | AJ49: =SUM(AJ44:AJ48) -> 854809.99 | AK49: =SUM(AK44:AK48) -> 0 | AL49: =SUM(AL44:AL48) -> 854809.99
D51: Subtotal Volunteer Travel | I51: =I49+I41 -> 201938.58 | J51: =J49+J41 -> 0 | K51: =K49+K41 -> 201938.58 | O51: =O49+O41 -> 234501.15 | P51: =P49+P41 -> 0 | Q51: =SUM(O51:P51) -> 234501.15 | U51: =U49+U41 -> 238622.42 | V51: =V49+V41 -> 0 | W51: =SUM(U51:V51) -> 238622.42 | AA51: =AA49+AA41 -> 239883.27 | AB51: =AB49+AB41 -> 0 | AC51: =SUM(AA51:AB51) -> 239883.27 | AG51: =AG49+AG41 -> 209102.06 | AH51: =AH49+AH41 -> 0 | AI51: =SUM(AG51:AH51) -> 209102.06 | AJ51: =AJ49+AJ41 -> 1124047.5 | AK51: =AK49+AK41 -> 0 | AL51: =AL49+AL41 -> 1124047.5
AK52: =J52+P52+V52+AB52+AH52 -> 0 | AL52: =SUM(AJ52:AK52) -> 0
D53: Staff Travel - International Airfare
A54: STFTRAVEL | B54: 86040 | C54: USA | D54: Guatemala | E54: 1 | F54: ='HQ Travel'!B3 -> 650 | G54: 1 | H54: /RT | I54: =G54*F54*E54 -> 650 | J54: 0 | K54: =SUM(I54:J54) -> 650 | L54: 1 | M54: =F54*1.02 -> 663 | N54: 1 | O54: =L54*M54*N54 -> 663 | P54: 0 | Q54: =SUM(O54:P54) -> 663 | R54: 1 | S54: =M54*1.02 -> 676.26 | T54: 1 | U54: =R54*S54*T54 -> 676.26 | V54: 0 | W54: =SUM(U54:V54) -> 676.26 | X54: 1 | Y54: =S54*1.02 -> 689.7852 | Z54: 1 | AA54: =X54*Y54*Z54 -> 689.7852 | AB54: 0 | AC54: =SUM(AA54:AB54) -> 689.7852 | AD54: 1 | AE54: =Y54*1.02 -> 703.5809 | AF54: 1 | AG54: =AD54*AE54*AF54 -> 703.5809 | AH54: 0 | AI54: =SUM(AG54:AH54) -> 703.5809 | AJ54: =I54+O54+U54+AA54+AG54 -> 3382.6261 | AK54: =J54+P54+V54+AB54+AH54 -> 0 | AL54: =SUM(AJ54:AK54) -> 3382.6261
A55: STFTRAVEL | B55: 86040 | C55: USA | D55: Dominican Republic | E55: 1 | F55: ='HQ Travel'!B4 -> 750 | G55: 1 | H55: /RT | I55: =G55*F55*E55 -> 750 | J55: 0 | K55: =SUM(I55:J55) -> 750 | L55: 1 | M55: =F55*1.02 -> 765 | N55: 1 | O55: =L55*M55*N55 -> 765 | P55: 0 | Q55: =SUM(O55:P55) -> 765 | R55: 1 | S55: =M55*1.02 -> 780.3 | T55: 1 | U55: =R55*S55*T55 -> 780.3 | V55: 0 | W55: =SUM(U55:V55) -> 780.3 | X55: 1 | Y55: =S55*1.02 -> 795.906 | Z55: 1 | AA55: =X55*Y55*Z55 -> 795.906 | AB55: 0 | AC55: =SUM(AA55:AB55) -> 795.906 | AD55: 1 | AE55: =Y55*1.02 -> 811.82412 | AF55: 1 | AG55: =AD55*AE55*AF55 -> 811.82412 | AH55: 0 | AI55: =SUM(AG55:AH55) -> 811.82412 | AJ55: =I55+O55+U55+AA55+AG55 -> 3903.0301 | AK55: =J55+P55+V55+AB55+AH55 -> 0 | AL55: =SUM(AJ55:AK55) -> 3903.0301
A56: STFTRAVEL | B56: 86040 | C56: USA | D56: Guyana | E56: 1 | F56: ='HQ Travel'!B5 -> 850 | G56: 1 | H56: /RT | I56: =G56*F56*E56 -> 850 | J56: 0 | K56: =SUM(I56:J56) -> 850 | L56: 1 | M56: =F56*1.02 -> 867 | N56: 1 | O56: =L56*M56*N56 -> 867 | P56: 0 | Q56: =SUM(O56:P56) -> 867 | R56: 1 | S56: =M56*1.02 -> 884.34 | T56: 1 | U56: =R56*S56*T56 -> 884.34 | V56: 0 | W56: =SUM(U56:V56) -> 884.34 | X56: 1 | Y56: =S56*1.02 -> 902.0268 | Z56: 1 | AA56: =X56*Y56*Z56 -> 902.0268 | AB56: 0 | AC56: =SUM(AA56:AB56) -> 902.0268 | AD56: 1 | AE56: =Y56*1.02 -> 920.06734 | AF56: 1 | AG56: =AD56*AE56*AF56 -> 920.06734 | AH56: 0 | AI56: =SUM(AG56:AH56) -> 920.06734 | AJ56: =I56+O56+U56+AA56+AG56 -> 4423.4341 | AK56: =J56+P56+V56+AB56+AH56 -> 0 | AL56: =SUM(AJ56:AK56) -> 4423.4341
A57: STFTRAVEL | B57: 86040 | C57: USA | D57: Jamaica | E57: 1 | F57: ='HQ Travel'!B6 -> 800 | G57: 1 | H57: /RT | I57: =G57*F57*E57 -> 800 | J57: 0 | K57: =SUM(I57:J57) -> 800 | L57: 1 | M57: =F57*1.02 -> 816 | N57: 1 | O57: =L57*M57*N57 -> 816 | P57: 0 | Q57: =SUM(O57:P57) -> 816 | R57: 1 | S57: =M57*1.02 -> 832.32 | T57: 1 | U57: =R57*S57*T57 -> 832.32 | V57: 0 | W57: =SUM(U57:V57) -> 832.32 | X57: 1 | Y57: =S57*1.02 -> 848.9664 | Z57: 1 | AA57: =X57*Y57*Z57 -> 848.9664 | AB57: 0 | AC57: =SUM(AA57:AB57) -> 848.9664 | AD57: 1 | AE57: =Y57*1.02 -> 865.94573 | AF57: 1 | AG57: =AD57*AE57*AF57 -> 865.94573 | AH57: 0 | AI57: =SUM(AG57:AH57) -> 865.94573 | AJ57: =I57+O57+U57+AA57+AG57 -> 4163.2321 | AK57: =J57+P57+V57+AB57+AH57 -> 0 | AL57: =SUM(AJ57:AK57) -> 4163.2321
D58: Total Staff Intl Airfare | E58: =SUM(E54:E57) -> 4 | I58: =SUM(I54:I57) -> 3050 | J58: =SUM(J54:J57) -> 0 | K58: =SUM(K54:K57) -> 3050 | L58: =SUM(L54:L57) -> 4 | O58: =SUM(O54:O57) -> 3111 | P58: =SUM(P54:P57) -> 0 | Q58: =SUM(Q54:Q57) -> 3111 | R58: =SUM(R54:R57) -> 4 | U58: =SUM(U54:U57) -> 3173.22 | V58: =SUM(V54:V57) -> 0 | W58: =SUM(W54:W57) -> 3173.22 | X58: =SUM(X54:X57) -> 4 | AA58: =SUM(AA54:AA57) -> 3236.6844 | AB58: =SUM(AB54:AB57) -> 0 | AC58: =SUM(AC54:AC57) -> 3236.6844 | AD58: =SUM(AD54:AD57) -> 4 | AG58: =SUM(AG54:AG57) -> 3301.4181 | AH58: =SUM(AH54:AH57) -> 0 | AI58: =SUM(AI54:AI57) -> 3301.4181 | AJ58: =I58+O58+U58+AA58+AG58 -> 15872.322 | AK58: =J58+P58+V58+AB58+AH58 -> 0 | AL58: =SUM(AJ58:AK58) -> 15872.322
D60: Staff International Travel-Related Costs
A61: STFTRVCTS | B61: 86050 | C61: USA | D61: Meals and Incidentals | E61: =E58 -> 4 | F61: ='HQ Travel'!D7 -> 93.7125 | G61: 7 | H61: /day | I61: =G61*F61*E61 -> 2623.95 | J61: 0 | K61: =SUM(I61:J61) -> 2623.95 | L61: =L58 -> 4 | M61: =F61*1.02 -> 95.58675 | N61: 7 | O61: =L61*M61*N61 -> 2676.429 | P61: 0 | Q61: =SUM(O61:P61) -> 2676.429 | R61: =R58 -> 4 | S61: =M61*1.02 -> 97.498485 | T61: 7 | U61: =R61*S61*T61 -> 2729.9576 | V61: 0 | W61: =SUM(U61:V61) -> 2729.9576 | X61: =X58 -> 4 | Y61: =S61*1.02 -> 99.448455 | Z61: 7 | AA61: =X61*Y61*Z61 -> 2784.5567 | AB61: 0 | AC61: =SUM(AA61:AB61) -> 2784.5567 | AD61: =AD58 -> 4 | AE61: =Y61*1.02 -> 101.43742 | AF61: 7 | AG61: =AD61*AE61*AF61 -> 2840.2479 | AH61: 0 | AI61: =SUM(AG61:AH61) -> 2840.2479 | AJ61: =I61+O61+U61+AA61+AG61 -> 13655.141 | AK61: =J61+P61+V61+AB61+AH61 -> 0 | AL61: =SUM(AJ61:AK61) -> 13655.141
A62: STFTRVCTS | B62: 86030 | C62: USA | D62: Lodging | E62: =E61 -> 4 | F62: ='HQ Travel'!C7 -> 99.23375 | G62: 6 | H62: /day | I62: =G62*F62*E62 -> 2381.61 | J62: 0 | K62: =SUM(I62:J62) -> 2381.61 | L62: =L58 -> 4 | M62: =F62*1.02 -> 101.21842 | N62: 6 | O62: =L62*M62*N62 -> 2429.2422 | P62: 0 | Q62: =SUM(O62:P62) -> 2429.2422 | R62: =R58 -> 4 | S62: =M62*1.02 -> 103.24279 | T62: 6 | U62: =R62*S62*T62 -> 2477.827 | V62: 0 | W62: =SUM(U62:V62) -> 2477.827 | X62: =X58 -> 4 | Y62: =S62*1.02 -> 105.30765 | Z62: 6 | AA62: =X62*Y62*Z62 -> 2527.3836 | AB62: 0 | AC62: =SUM(AA62:AB62) -> 2527.3836 | AD62: =AD58 -> 4 | AE62: =Y62*1.02 -> 107.4138 | AF62: 6 | AG62: =AD62*AE62*AF62 -> 2577.9313 | AH62: 0 | AI62: =SUM(AG62:AH62) -> 2577.9313 | AJ62: =I62+O62+U62+AA62+AG62 -> 12393.994 | AK62: =J62+P62+V62+AB62+AH62 -> 0 | AL62: =SUM(AJ62:AK62) -> 12393.994
A63: STFTRVCTS | B63: 86000 (Transport)/ 86060 (baggage, etc.) | C63: USA | D63: Other Travel Related Expenses (baggage, transportation, etc.) | E63: =E61 -> 4 | F63: 100 | G63: 1 | H63: /trip | I63: =G63*F63*E63 -> 400 | J63: 0 | K63: =SUM(I63:J63) -> 400 | L63: =L58 -> 4 | M63: =F63*1.02 -> 102 | N63: 1 | O63: =L63*M63*N63 -> 408 | P63: 0 | Q63: =SUM(O63:P63) -> 408 | R63: =R58 -> 4 | S63: =M63*1.02 -> 104.04 | T63: 1 | U63: =R63*S63*T63 -> 416.16 | V63: 0 | W63: =SUM(U63:V63) -> 416.16 | X63: =X58 -> 4 | Y63: =S63*1.02 -> 106.1208 | Z63: 1 | AA63: =X63*Y63*Z63 -> 424.4832 | AB63: 0 | AC63: =SUM(AA63:AB63) -> 424.4832 | AD63: =AD58 -> 4 | AE63: =Y63*1.02 -> 108.24322 | AF63: 1 | AG63: =AD63*AE63*AF63 -> 432.97286 | AH63: 0 | AI63: =SUM(AG63:AH63) -> 432.97286 | AJ63: =I63+O63+U63+AA63+AG63 -> 2081.6161 | AK63: =J63+P63+V63+AB63+AH63 -> 0 | AL63: =SUM(AJ63:AK63) -> 2081.6161
D64: Total Staff Intl TRE | E64: =SUM(E61:E63) -> 12 | I64: =SUM(I61:I63) -> 5405.56 | J64: =SUM(J61:J63) -> 0 | K64: =SUM(K61:K63) -> 5405.56 | L64: =SUM(L61:L63) -> 12 | O64: =SUM(O61:O63) -> 5513.6712 | P64: =SUM(P61:P63) -> 0 | Q64: =SUM(Q61:Q63) -> 5513.6712 | R64: =SUM(R61:R63) -> 12 | U64: =SUM(U61:U63) -> 5623.9446 | V64: =SUM(V61:V63) -> 0 | W64: =SUM(W61:W63) -> 5623.9446 | X64: =SUM(X61:X63) -> 12 | AA64: =SUM(AA61:AA63) -> 5736.4235 | AB64: =SUM(AB61:AB63) -> 0 | AC64: =SUM(AC61:AC63) -> 5736.4235 | AD64: =SUM(AD61:AD63) -> 12 | AG64: =SUM(AG61:AG63) -> 5851.152 | AH64: =SUM(AH61:AH63) -> 0 | AI64: =SUM(AI61:AI63) -> 5851.152 | AJ64: =SUM(AJ61:AJ63) -> 28130.751 | AK64: =SUM(AK61:AK63) -> 0 | AL64: =SUM(AL61:AL63) -> 28130.751
D66: Staff Travel - US Travel
A67: STFTRAV-US | B67: 86040 | C67: USA | D67: Workshop / US Trips Airfare | E67: 1 | F67: ='HQ Travel'!H10 -> 350 | G67: 1 | H67: /RT | I67: =G67*F67*E67 -> 350 | J67: 0 | K67: =SUM(I67:J67) -> 350 | L67: 1 | M67: =F67*1.02 -> 357 | N67: 1 | O67: =L67*M67*N67 -> 357 | P67: 0 | Q67: =SUM(O67:P67) -> 357 | R67: 1 | S67: =M67*1.02 -> 364.14 | T67: 1 | U67: =R67*S67*T67 -> 364.14 | V67: 0 | W67: =SUM(U67:V67) -> 364.14 | X67: 1 | Y67: =S67*1.02 -> 371.4228 | Z67: 1 | AA67: =X67*Y67*Z67 -> 371.4228 | AB67: 0 | AC67: =SUM(AA67:AB67) -> 371.4228 | AD67: 1 | AE67: =Y67*1.02 -> 378.85126 | AF67: 1 | AG67: =AD67*AE67*AF67 -> 378.85126 | AH67: 0 | AI67: =SUM(AG67:AH67) -> 378.85126 | AJ67: =I67+O67+U67+AA67+AG67 -> 1821.4141 | AK67: =J67+P67+V67+AB67+AH67 -> 0 | AL67: =SUM(AJ67:AK67) -> 1821.4141
A68: STFTRAV-US | B68: 86050 | C68: USA | D68: Meals and incidentals | E68: =E67 -> 1 | F68: ='HQ Travel'!J10 -> 59 | G68: 5 | H68: /day | I68: =G68*F68*E68 -> 295 | J68: 0 | K68: =SUM(I68:J68) -> 295 | L68: =L67 -> 1 | M68: =F68*1.02 -> 60.18 | N68: 5 | O68: =L68*M68*N68 -> 300.9 | P68: 0 | Q68: =SUM(O68:P68) -> 300.9 | R68: =R67 -> 1 | S68: =M68*1.02 -> 61.3836 | T68: 5 | U68: =R68*S68*T68 -> 306.918 | V68: 0 | W68: =SUM(U68:V68) -> 306.918 | X68: =X67 -> 1 | Y68: =S68*1.02 -> 62.611272 | Z68: 5 | AA68: =X68*Y68*Z68 -> 313.05636 | AB68: 0 | AC68: =SUM(AA68:AB68) -> 313.05636 | AD68: =AD67 -> 1 | AE68: =Y68*1.02 -> 63.863497 | AF68: 5 | AG68: =AD68*AE68*AF68 -> 319.31749 | AH68: 0 | AI68: =SUM(AG68:AH68) -> 319.31749 | AJ68: =I68+O68+U68+AA68+AG68 -> 1535.1918 | AK68: =J68+P68+V68+AB68+AH68 -> 0 | AL68: =SUM(AJ68:AK68) -> 1535.1918
A69: STFTRAV-US | B69: 86030 | C69: USA | D69: Lodging | E69: =E67 -> 1 | F69: ='HQ Travel'!I10 -> 98 | G69: 5 | H69: /day | I69: =G69*F69*E69 -> 490 | J69: 0 | K69: =SUM(I69:J69) -> 490 | L69: =L67 -> 1 | M69: =F69*1.02 -> 99.96 | N69: 5 | O69: =L69*M69*N69 -> 499.8 | P69: 0 | Q69: =SUM(O69:P69) -> 499.8 | R69: =R67 -> 1 | S69: =M69*1.02 -> 101.9592 | T69: 5 | U69: =R69*S69*T69 -> 509.796 | V69: 0 | W69: =SUM(U69:V69) -> 509.796 | X69: =X67 -> 1 | Y69: =S69*1.02 -> 103.99838 | Z69: 5 | AA69: =X69*Y69*Z69 -> 519.99192 | AB69: 0 | AC69: =SUM(AA69:AB69) -> 519.99192 | AD69: =AD67 -> 1 | AE69: =Y69*1.02 -> 106.07835 | AF69: 5 | AG69: =AD69*AE69*AF69 -> 530.39176 | AH69: 0 | AI69: =SUM(AG69:AH69) -> 530.39176 | AJ69: =I69+O69+U69+AA69+AG69 -> 2549.9797 | AK69: =J69+P69+V69+AB69+AH69 -> 0 | AL69: =SUM(AJ69:AK69) -> 2549.9797
A70: STFTRAV-US | B70: 86000 (Transport)/ 86060 (baggage, etc.) | C70: USA | D70: Other Travel Related Expenses (baggage, transportation, etc.) | E70: =E67 -> 1 | F70: ='HQ Travel'!K10 -> 100 | G70: 1 | H70: /trip | I70: =G70*F70*E70 -> 100 | J70: 0 | K70: =SUM(I70:J70) -> 100 | L70: =L67 -> 1 | M70: =F70*1.02 -> 102 | N70: 1 | O70: =L70*M70*N70 -> 102 | P70: 0 | Q70: =SUM(O70:P70) -> 102 | R70: =R67 -> 1 | S70: =M70*1.02 -> 104.04 | T70: 1 | U70: =R70*S70*T70 -> 104.04 | V70: 0 | W70: =SUM(U70:V70) -> 104.04 | X70: =X67 -> 1 | Y70: =S70*1.02 -> 106.1208 | Z70: 1 | AA70: =X70*Y70*Z70 -> 106.1208 | AB70: 0 | AC70: =SUM(AA70:AB70) -> 106.1208 | AD70: =AD67 -> 1 | AE70: =Y70*1.02 -> 108.24322 | AF70: 1 | AG70: =AD70*AE70*AF70 -> 108.24322 | AH70: 0 | AI70: =SUM(AG70:AH70) -> 108.24322 | AJ70: =I70+O70+U70+AA70+AG70 -> 520.40402 | AK70: =J70+P70+V70+AB70+AH70 -> 0 | AL70: =SUM(AJ70:AK70) -> 520.40402
D71: Total Staff Travel US | I71: =SUM(I67:I70) -> 1235 | J71: =SUM(J67:J70) -> 0 | K71: =SUM(K67:K70) -> 1235 | L71: =SUM(L67:L70) -> 4 | O71: =SUM(O67:O70) -> 1259.7 | P71: =SUM(P67:P70) -> 0 | Q71: =SUM(Q67:Q70) -> 1259.7 | R71: =SUM(R67:R70) -> 4 | U71: =SUM(U67:U70) -> 1284.894 | V71: =SUM(V67:V70) -> 0 | W71: =SUM(W67:W70) -> 1284.894 | X71: =SUM(X67:X70) -> 4 | AA71: =SUM(AA67:AA70) -> 1310.5919 | AB71: =SUM(AB67:AB70) -> 0 | AC71: =SUM(AC67:AC70) -> 1310.5919 | AD71: =SUM(AD67:AD70) -> 4 | AG71: =SUM(AG67:AG70) -> 1336.8037 | AH71: =SUM(AH67:AH70) -> 0 | AI71: =SUM(AI67:AI70) -> 1336.8037 | AJ71: =SUM(AJ67:AJ70) -> 6426.9896 | AK71: =J71+P71+V71+AB71+AH71 -> 0 | AL71: =SUM(AJ71:AK71) -> 6426.9896
D73: Field Staff Travel-Related Costs
A74: VARIOUS SEE TAB | B74: 86050 | C74: VARIOUS SEE TAB | D74: Meals and Incidentals | E74: 1 | F74: =SUM('Guatemala '!I39+'Dominican Republic'!I39+Guyana!I38+Jamaica!I38) -> 29917.5 | G74: 1 | H74: /day | I74: =G74*F74*E74 -> 29917.5 | J74: 0 | K74: =SUM(I74:J74) -> 29917.5 | L74: 1 | M74: =SUM('Guatemala '!N9+'Dominican Republic'!N39+Guyana!N38+Jamaica!N38) -> 25719.3 | N74: 1 | O74: =L74*M74*N74 -> 25719.3 | P74: 0 | Q74: =SUM(O74:P74) -> 25719.3 | R74: 1 | S74: =SUM('Guatemala '!S9+'Dominican Republic'!S39+Guyana!S38+Jamaica!S38) -> 29022.478 | T74: 1 | U74: =R74*S74*T74 -> 29022.478 | V74: 0 | W74: =SUM(U74:V74) -> 29022.478 | X74: 1 | Y74: =SUM('Guatemala '!X9+'Dominican Republic'!X39+Guyana!X38+Jamaica!X38) -> 26057.962 | Z74: 1 | AA74: =X74*Y74*Z74 -> 26057.962 | AB74: 0 | AC74: =SUM(AA74:AB74) -> 26057.962 | AD74: 1 | AE74: =SUM('Guatemala '!AD9+'Dominican Republic'!AD39+Guyana!AD38+Jamaica!AD38) -> 24020.252 | AF74: 1 | AG74: =AD74*AE74*AF74 -> 24020.252 | AH74: 0 | AI74: =SUM(AG74:AH74) -> 24020.252 | AJ74: =I74+O74+U74+AA74+AG74 -> 134737.49 | AK74: =J74+P74+V74+AB74+AH74 -> 0 | AL74: =SUM(AJ74:AK74) -> 134737.49 | AM74: ='Guatemala '!AF39+Guyana!AF38+'Dominican Republic'!AF39+Jamaica!AF38 -> 166038.18 | AN74: =AM74-AL74 -> 31300.692
A75: VARIOUS SEE TAB | B75: 86030 | C75: VARIOUS SEE TAB | D75: Lodging | E75: 1 | F75: =SUM('Guatemala '!I38+'Dominican Republic'!I38+Guyana!I37+Jamaica!I37) -> 39838.491 | G75: 1 | H75: /day | I75: =G75*F75*E75 -> 39838.491 | J75: 0 | K75: =SUM(I75:J75) -> 39838.491 | L75: 1 | M75: =SUM('Guatemala '!N38+'Dominican Republic'!N38+Guyana!N37+Jamaica!N37) -> 44446.414 | N75: 1 | O75: =L75*M75*N75 -> 44446.414 | P75: 0 | Q75: =SUM(O75:P75) -> 44446.414 | R75: 1 | S75: =SUM('Guatemala '!S38+'Dominican Republic'!S38+Guyana!S37+Jamaica!S37) -> 50031.678 | T75: 1 | U75: =R75*S75*T75 -> 50031.678 | V75: 0 | W75: =SUM(U75:V75) -> 50031.678 | X75: 1 | Y75: =SUM('Guatemala '!X38+'Dominican Republic'!X38+Guyana!X37+Jamaica!X37) -> 45265.906 | Z75: 1 | AA75: =X75*Y75*Z75 -> 45265.906 | AB75: 0 | AC75: =SUM(AA75:AB75) -> 45265.906 | AD75: 1 | AE75: =SUM('Guatemala '!AD38+'Dominican Republic'!AD38+Guyana!AD37+Jamaica!AD37) -> 40849.834 | AF75: 1 | AG75: =AD75*AE75*AF75 -> 40849.834 | AH75: 0 | AI75: =SUM(AG75:AH75) -> 40849.834 | AJ75: =I75+O75+U75+AA75+AG75 -> 220432.32 | AK75: =J75+P75+V75+AB75+AH75 -> 0 | AL75: =SUM(AJ75:AK75) -> 220432.32 | AN75: =AN74/4 -> 7825.173
A76: VARIOUS SEE TAB | B76: 86000 (Transport)/ 86060 (baggage, etc.) | C76: VARIOUS SEE TAB | D76: Other Travel Related Expenses (baggage, transportation, etc.) | E76: =E74 -> 1 | F76: =SUM('Guatemala '!I40+'Dominican Republic'!I40+Guyana!I39+Jamaica!I39) -> 9570 | G76: 1 | H76: /trip | I76: =G76*F76*E76 -> 9570 | J76: 0 | K76: =SUM(I76:J76) -> 9570 | L76: =L74 -> 1 | M76: =SUM('Guatemala '!N40+'Dominican Republic'!N40+Guyana!N39+Jamaica!N39) -> 10388.7 | N76: 1 | O76: =L76*M76*N76 -> 10388.7 | P76: 0 | Q76: =SUM(O76:P76) -> 10388.7 | R76: =R74 -> 1 | S76: =SUM('Guatemala '!S40+'Dominican Republic'!S40+Guyana!S39+Jamaica!S39) -> 12889.516 | T76: 1 | U76: =R76*S76*T76 -> 12889.516 | V76: 0 | W76: =SUM(U76:V76) -> 12889.516 | X76: =X74 -> 1 | Y76: =SUM('Guatemala '!X40+'Dominican Republic'!X40+Guyana!X39+Jamaica!X39) -> 10671.508 | Z76: 1 | AA76: =X76*Y76*Z76 -> 10671.508 | AB76: 0 | AC76: =SUM(AA76:AB76) -> 10671.508 | AD76: =AD74 -> 1 | AE76: =SUM('Guatemala '!AD40+'Dominican Republic'!AD40+Guyana!AD39+Jamaica!AD39) -> 10015.745 | AF76: 1 | AG76: =AD76*AE76*AF76 -> 10015.745 | AH76: 0 | AI76: =SUM(AG76:AH76) -> 10015.745 | AJ76: =I76+O76+U76+AA76+AG76 -> 53535.468 | AK76: =J76+P76+V76+AB76+AH76 -> 0 | AL76: =SUM(AJ76:AK76) -> 53535.468
D77: Total Field Staff Travel | I77: =SUM(I74:I76) -> 79325.991 | J77: =SUM(J73:J76) -> 0 | K77: =SUM(K73:K76) -> 79325.991 | L77: =SUM(L73:L76) -> 3 | O77: =SUM(O74:O76) -> 80554.414 | P77: =SUM(P73:P76) -> 0 | Q77: =SUM(Q73:Q76) -> 80554.414 | R77: =SUM(R73:R76) -> 3 | U77: =SUM(U74:U76) -> 91943.672 | V77: =SUM(V73:V76) -> 0 | W77: =SUM(W73:W76) -> 91943.672 | X77: =SUM(X73:X76) -> 3 | AA77: =SUM(AA74:AA76) -> 81995.376 | AB77: =SUM(AB73:AB76) -> 0 | AC77: =SUM(AC73:AC76) -> 81995.376 | AD77: =SUM(AD73:AD76) -> 3 | AG77: =SUM(AG74:AG76) -> 74885.831 | AH77: =SUM(AH73:AH76) -> 0 | AI77: =SUM(AI74:AI76) -> 74885.831 | AJ77: =SUM(AJ74:AJ76) -> 408705.28 | AK77: =J77+P77+V77+AB77+AH77 -> 0 | AL77: =SUM(AJ77:AK77) -> 408705.28
D78: Subtotal Staff Travel | I78: =I71+I64+I58+I77 -> 89016.551 | J78: =J71+J64+J58+J77 -> 0 | K78: =K71+K64+K58+K77 -> 89016.551 | O78: =O71+O64+O58+O77 -> 90438.786 | P78: =P71+P64+P58+P77 -> 0 | Q78: =Q71+Q64+Q58+Q77 -> 90438.786 | U78: =U71+U64+U58+U77 -> 102025.73 | V78: =V71+V64+V58+V77 -> 0 | W78: =W71+W64+W58+W77 -> 102025.73 | AA78: =AA71+AA64+AA58+AA77 -> 92279.076 | AB78: =AB71+AB64+AB58+AB77 -> 0 | AC78: =AC71+AC64+AC58+AC77 -> 92279.076 | AG78: =AG71+AG64+AG58+AG77 -> 85375.204 | AH78: =AH71+AH64+AH58+AH77 -> 0 | AI78: =AI71+AI64+AI58+AI77 -> 85375.204 | AJ78: =AJ71+AJ64+AJ58+AJ77 -> 459135.35 | AK78: =AK71+AK64+AK58+AK77 -> 0 | AL78: =AL71+AL64+AL58+AL77 -> 459135.35
D80: Travel Total | I80: =I78+I51 -> 290955.13 | J80: =J78+J51 -> 0 | K80: =K78+K51 -> 290955.13 | O80: =O78+O51 -> 324939.93 | P80: =P78+P51 -> 0 | Q80: =Q78+Q51 -> 324939.93 | U80: =U78+U51 -> 340648.15 | V80: =V78+V51 -> 0 | W80: =W78+W51 -> 340648.15 | AA80: =AA78+AA51 -> 332162.34 | AB80: =AB78+AB51 -> 0 | AC80: =AC78+AC51 -> 332162.34 | AG80: =AG78+AG51 -> 294477.26 | AH80: =AH78+AH51 -> 0 | AI80: =AI78+AI51 -> 294477.26 | AJ80: =AJ78+AJ51 -> 1583182.8 | AK80: =AK78+AK51 -> 0 | AL80: =SUM(AJ80:AK80) -> 1583182.8
D82: Equipment
A84: EQUIPDOM | B84: 85200 | C84: DOM | D84: Field Office Equipment | E84: 1 | F84: ='Dominican Republic'!F43 -> 43000 | H84: /vehicle | I84: =F84*E84 -> 43000 | J84: 0 | K84: =SUM(I84:J84) -> 43000 | L84: 1 | M84: ='Guatemala '!N43+'Dominican Republic'!N43+Guyana!N42+Jamaica!N42 -> 0 | O84: =L84*M84 -> 0 | P84: 0 | Q84: =SUM(O84:P84) -> 0 | R84: 1 | S84: ='Guatemala '!T43+'Dominican Republic'!T43+Guyana!T42+Jamaica!T42 -> 0 | U84: =S84*R84 -> 0 | V84: 0 | W84: =SUM(U84:V84) -> 0 | X84: 1 | Y84: ='Guatemala '!Z43+'Dominican Republic'!Z43+Guyana!Z42+Jamaica!Z42 -> 0 | AA84: =X84*Y84 -> 0 | AB84: 0 | AC84: =SUM(AA84:AB84) -> 0 | AD84: 1 | AE84: ='Guatemala '!AC43+'Dominican Republic'!AC43+Guyana!AC42+Jamaica!AC42 -> 0 | AG84: =AE84*AD84 -> 0 | AH84: 0 | AI84: =SUM(AG84:AH84) -> 0 | AJ84: =I84+O84+U84+AA84+AG84 -> 43000 | AK84: =J84+P84+V84+AB84+AH84 -> 0 | AL84: =SUM(AJ84:AK84) -> 43000
D86: Equipment Total | I86: =SUM(I84:I85) -> 43000 | J86: =SUM(J84:J85) -> 0 | K86: =SUM(K84:K85) -> 43000 | O86: =SUM(O84:O85) -> 0 | P86: =SUM(P84:P85) -> 0 | Q86: =SUM(Q84:Q85) -> 0 | U86: =SUM(U84:U85) -> 0 | V86: =SUM(V84:V85) -> 0 | W86: =SUM(W84:W85) -> 0 | AA86: =SUM(AA84:AA85) -> 0 | AB86: =SUM(AB84:AB85) -> 0 | AC86: =SUM(AC84:AC85) -> 0 | AG86: =SUM(AG84:AG85) -> 0 | AH86: =SUM(AH84:AH85) -> 0 | AI86: =SUM(AI84:AI85) -> 0 | AJ86: =SUM(AJ84:AJ85) -> 43000 | AK86: =SUM(AK84:AK85) -> 0 | AL86: =SUM(AJ86:AK86) -> 43000
D88: Supplies
D90: HQ Office Supplies
A91: SUPPLIES | B91: 82401 | C91: USA | D91: Laptop, Bag, Accessories | E91: ='HQ Expenses'!C5 -> 3 | F91: =SUM('HQ Expenses'!B5) -> 1105 | G91: 1 | H91: /unit | I91: =F91*E91 -> 3315 | J91: 0 | K91: =SUM(I91:J91) -> 3315 | L91: 0 | M91: =F91 -> 1105 | N91: 1 | O91: =L91*M91 -> 0 | P91: 0 | Q91: =SUM(O91:P91) -> 0 | R91: =O91*P91*Q91 -> 0 | S91: =F91 -> 1105 | T91: 1 | U91: =S91*R91 -> 0 | V91: 0 | W91: =SUM(U91:V91) -> 0 | X91: =U91*V91*W91 -> 0 | Y91: =F91 -> 1105 | Z91: 1 | AA91: =Y91*X91 -> 0 | AB91: 0 | AC91: =SUM(AA91:AB91) -> 0 | AD91: =AA91*AB91*AC91 -> 0 | AE91: =F91 -> 1105 | AF91: 1 | AG91: =AE91*AD91 -> 0 | AH91: 0 | AI91: =SUM(AG91:AH91) -> 0 | AJ91: =I91+O91+U91+AA91+AG91 -> 3315 | AK91: =J91+P91+V91+AB91+AH91 -> 0 | AL91: =SUM(AJ91:AK91) -> 3315
A92: SUPPLIES | B92: 82401 | C92: USA | D92: Camera, Accessories, Memory Card, S&H | E92: ='HQ Expenses'!C6 -> 1 | F92: ='HQ Expenses'!B32 -> 581.3 | G92: 1 | H92: /unit | I92: =F92*E92 -> 581.3 | J92: 0 | K92: =SUM(I92:J92) -> 581.3 | L92: 0 | M92: =F92 -> 581.3 | N92: 1 | O92: =L92*M92 -> 0 | P92: 0 | Q92: =SUM(O92:P92) -> 0 | R92: =O92*P92*Q92 -> 0 | S92: =F92 -> 581.3 | T92: 1 | U92: =S92*R92 -> 0 | V92: 0 | W92: =SUM(U92:V92) -> 0 | X92: =U92*V92*W92 -> 0 | Y92: =F92 -> 581.3 | Z92: 1 | AA92: =Y92*X92 -> 0 | AB92: 0 | AC92: =SUM(AA92:AB92) -> 0 | AD92: =AA92*AB92*AC92 -> 0 | AE92: =F92 -> 581.3 | AF92: 1 | AG92: =AE92*AD92 -> 0 | AH92: 0 | AI92: =SUM(AG92:AH92) -> 0 | AJ92: =I92+O92+U92+AA92+AG92 -> 581.3 | AK92: =J92+P92+V92+AB92+AH92 -> 0 | AL92: =SUM(AJ92:AK92) -> 581.3
A93: SUPPLIES | B93: 82401 | C93: USA | D93: General Office Supplies for HQ | E93: 1 | F93: 50 | G93: 12 | H93: /month | I93: =F93*E93*G93 -> 600 | J93: 0 | K93: =SUM(I93:J93) -> 600 | L93: 1 | M93: =F93 -> 50 | N93: 12 | O93: =L93*M93*N93 -> 600 | P93: 0 | Q93: =SUM(O93:P93) -> 600 | R93: 1 | S93: =F93 -> 50 | T93: 12 | U93: =S93*R93*T93 -> 600 | V93: 0 | W93: =SUM(U93:V93) -> 600 | X93: 1 | Y93: =F93 -> 50 | Z93: 12 | AA93: =Y93*X93*Z93 -> 600 | AB93: 0 | AC93: =SUM(AA93:AB93) -> 600 | AD93: 1 | AE93: =F93 -> 50 | AF93: 9 | AG93: =AE93*AD93*AF93 -> 450 | AH93: 0 | AI93: =SUM(AG93:AH93) -> 450 | AJ93: =I93+O93+U93+AA93+AG93 -> 2850 | AK93: =J93+P93+V93+AB93+AH93 -> 0 | AL93: =SUM(AJ93:AK93) -> 2850
D94: Total HQ Office Supplies | I94: =SUM(I91:I93) -> 4496.3 | J94: =SUM(J91:J93) -> 0 | K94: =SUM(K91:K93) -> 4496.3 | O94: =SUM(O91:O93) -> 600 | P94: =SUM(P91:P93) -> 0 | Q94: =SUM(Q91:Q93) -> 600 | U94: =SUM(U91:U93) -> 600 | V94: =SUM(V91:V93) -> 0 | W94: =SUM(W91:W93) -> 600 | AA94: =SUM(AA91:AA93) -> 600 | AB94: =SUM(AB91:AB93) -> 0 | AC94: =SUM(AC91:AC93) -> 600 | AG94: =SUM(AG91:AG93) -> 450 | AH94: =SUM(AH91:AH93) -> 0 | AI94: =SUM(AI91:AI93) -> 450 | AJ94: =I94+O94+U94+AA94+AG94 -> 6746.3 | AK94: =J94+P94+V94+AB94+AH94 -> 0 | AL94: =SUM(AJ94:AK94) -> 6746.3
A96: VARIOUS SEE TAB | B96: 82401 | C96: VARIOUS SEE TAB | D96: Field Office Supplies | E96: 1 | F96: ='Guatemala '!I23+'Dominican Republic'!I23+Guyana!I22+Jamaica!I22 -> 22018 | G96: 1 | H96: /year | I96: =F96*E96*G96 -> 22018 | J96: 0 | K96: =SUM(I96:J96) -> 22018 | L96: 1 | M96: ='Guatemala '!N23+'Dominican Republic'!N23+Guyana!N22+Jamaica!N22 -> 2162.4 | N96: 1 | O96: =L96*M96*N96 -> 2162.4 | P96: 0 | Q96: =SUM(O96:P96) -> 2162.4 | R96: 1 | S96: ='Guatemala '!T23+'Dominican Republic'!T23+Guyana!T22+Jamaica!T22 -> 2205.648 | T96: 1 | U96: =S96*R96*T96 -> 2205.648 | V96: 0 | W96: =SUM(U96:V96) -> 2205.648 | X96: 1 | Y96: ='Guatemala '!X23+'Dominican Republic'!X23+Guyana!X22+Jamaica!X22 -> 2249.761 | Z96: 1 | AA96: =Y96*X96*Z96 -> 2249.761 | AB96: 0 | AC96: =SUM(AA96:AB96) -> 2249.761 | AD96: 1 | AE96: ='Guatemala '!AC23+'Dominican Republic'!AC23+Guyana!AC22+Jamaica!AC22 -> 2294.7562 | AF96: 1 | AG96: =AE96*AD96*AF96 -> 2294.7562 | AH96: 0 | AI96: =SUM(AG96:AH96) -> 2294.7562 | AJ96: =I96+O96+U96+AA96+AG96 -> 30930.565 | AK96: =J96+P96+V96+AB96+AH96 -> 0 | AL96: =SUM(AJ96:AK96) -> 30930.565
D97: Total Field Office Supplies | I97: =SUM(I96:I96) -> 22018 | J97: =SUM(J96:J96) -> 0 | K97: =SUM(K96:K96) -> 22018 | O97: =SUM(O96:O96) -> 2162.4 | P97: =SUM(P96:P96) -> 0 | Q97: =SUM(Q96:Q96) -> 2162.4 | U97: =SUM(U96:U96) -> 2205.648 | V97: =SUM(V96:V96) -> 0 | W97: =SUM(W96:W96) -> 2205.648 | AA97: =SUM(AA96:AA96) -> 2249.761 | AB97: =SUM(AB96:AB96) -> 0 | AC97: =SUM(AC96:AC96) -> 2249.761 | AG97: =SUM(AG96:AG96) -> 2294.7562 | AH97: =SUM(AH96:AH96) -> 0 | AI97: =SUM(AI96:AI96) -> 2294.7562 | AJ97: =SUM(AJ96:AJ96) -> 30930.565 | AK97: =SUM(AK96:AK96) -> 0 | AL97: =SUM(AL96:AL96) -> 30930.565
D99: Supplies Total | I99: =I97+I94 -> 26514.3 | J99: =J97+J94 -> 0 | K99: =K97+K94 -> 26514.3 | O99: =O97+O94 -> 2762.4 | P99: =P97+P94 -> 0 | Q99: =Q97+Q94 -> 2762.4 | U99: =U97+U94 -> 2805.648 | V99: =V97+V94 -> 0 | W99: =W97+W94 -> 2805.648 | AA99: =AA97+AA94 -> 2849.761 | AB99: =AB97+AB94 -> 0 | AC99: =AC97+AC94 -> 2849.761 | AG99: =AG97+AG94 -> 2744.7562 | AH99: =AH97+AH94 -> 0 | AI99: =AI97+AI94 -> 2744.7562 | AJ99: =AG99+AA99+U99+O99+I99 -> 37676.865 | AK99: =AH99+AB99+V99+P99+J99 -> 0 | AL99: =AI99+AC99+W99+Q99+K99 -> 37676.865
D101: Contractual
A103: M&EDATA | B103: 81010 | C103: USA | D103: M&E Database | E103: 1 | F103: =Contractual!D11 -> 5000 | G103: 1 | H103: /unit | I103: =F103*E103*G103 -> 5000 | J103: 0 | K103: =SUM(I103:J103) -> 5000 | L103: 1 | M103: =Contractual!H11 -> 1000 | N103: 1 | O103: =M103*L103*N103 -> 1000 | P103: 0 | Q103: =SUM(O103:P103) -> 1000 | R103: 1 | S103: =Contractual!L11 -> 3000 | T103: 1 | U103: =R103*S103*T103 -> 3000 | V103: 0 | W103: =SUM(U103:V103) -> 3000 | X103: 1 | Y103: =Contractual!P11 -> 3000 | Z103: 1 | AA103: =Y103*X103*Z103 -> 3000 | AB103: 0 | AC103: =SUM(AA103:AB103) -> 3000 | AD103: 1 | AE103: =Contractual!T11 -> 1000 | AF103: 1 | AG103: =AE103*AD103*AF103 -> 1000 | AH103: 0 | AI103: =SUM(AG103:AH103) -> 1000 | AJ103: =I103+O103+U103+AA103+AG103 -> 13000 | AK103: =J103+P103+V103+AB103+AH103 -> 0 | AL103: =SUM(AJ103:AK103) -> 13000
A104: GRANT | B104: 89050 | C104: USA | D104: IICA | E104: 1 | F104: =Contractual!D13 -> 4000 | H104: /unit | I104: =F104*E104 -> 4000 | J104: 0 | K104: =SUM(I104:J104) -> 4000 | L104: 1 | M104: =F104 -> 4000 | N104: 1 | O104: =M104*L104 -> 4000 | P104: 0 | Q104: =SUM(O104:P104) -> 4000 | R104: 1 | S104: =F104 -> 4000 | T104: 1 | U104: =R104*S104 -> 4000 | V104: 0 | W104: =SUM(U104:V104) -> 4000 | X104: 0 | Y104: =F104 -> 4000 | Z104: 1 | AA104: =Y104*X104 -> 0 | AB104: 0 | AC104: =SUM(AA104:AB104) -> 0 | AD104: 0 | AE104: =F104 -> 4000 | AF104: 1 | AG104: =AE104*AD104 -> 0 | AH104: 0 | AI104: =SUM(AG104:AH104) -> 0 | AJ104: =I104+O104+U104+AA104+AG104 -> 12000 | AK104: =J104+P104+V104+AB104+AH104 -> 0 | AL104: =SUM(AJ104:AK104) -> 12000
D106: Contractual Total | I106: =SUM(I103:I104) -> 9000 | J106: =SUM(J103:J104) -> 0 | K106: =SUM(K103:K104) -> 9000 | O106: =SUM(O103:O104) -> 5000 | P106: =SUM(P103:P104) -> 0 | Q106: =SUM(Q103:Q104) -> 5000 | U106: =SUM(U103:U104) -> 7000 | V106: =SUM(V103:V104) -> 0 | W106: =SUM(W103:W104) -> 7000 | AA106: =SUM(AA103:AA104) -> 3000 | AB106: =SUM(AB103:AB104) -> 0 | AC106: =SUM(AC103:AC104) -> 3000 | AG106: =SUM(AG103:AG104) -> 1000 | AH106: =SUM(AH103:AH104) -> 0 | AI106: =SUM(AI103:AI104) -> 1000 | AJ106: =AG106+AA106+U106+O106+I106 -> 25000 | AK106: =SUM(AK103:AK104) -> 0 | AL106: =AI106+AC106+W106+Q106+K106 -> 25000
D108: Other Direct Costs
A110: MEETING | B110: 87010 | C110: USA | D110: Meeting/Events - HQ | E110: 1 | F110: 1000 | G110: 1 | H110: /year | I110: =G110*F110*E110 -> 1000 | J110: 0 | K110: =SUM(I110:J110) -> 1000 | L110: 1 | M110: =F110*1.02 -> 1020 | N110: 1 | O110: =L110*M110*N110 -> 1020 | P110: 0 | Q110: =SUM(O110:P110) -> 1020 | R110: 1 | S110: =M110*1.02 -> 1040.4 | T110: 1 | U110: =T110*S110*R110 -> 1040.4 | V110: 0 | W110: =SUM(U110:V110) -> 1040.4 | X110: 1 | Y110: =S110*1.02 -> 1061.208 | Z110: 1 | AA110: =Z110*Y110*X110 -> 1061.208 | AB110: 0 | AC110: =SUM(AA110:AB110) -> 1061.208 | AD110: 1 | AE110: =Y110*1.02 -> 1082.4322 | AF110: 1 | AG110: =AF110*AE110*AD110 -> 1082.4322 | AH110: 0 | AI110: =SUM(AG110:AH110) -> 1082.4322 | AJ110: =I110+O110+U110+AA110+AG110 -> 5204.0402 | AK110: =J110+P110+V110+AB110+AH110 -> 0 | AL110: =SUM(AJ110:AK110) -> 5204.0402
A111: PUBLICAT | B111: 85300 | C111: USA | D111: Publications - HQ | E111: 1 | F111: 499.5 | G111: 1 | H111: /year | I111: =G111*F111*E111 -> 499.5 | J111: 0 | K111: =SUM(I111:J111) -> 499.5 | L111: 1 | M111: =F111*1.02 -> 509.49 | N111: 1 | O111: =L111*M111*N111 -> 509.49 | P111: 0 | Q111: =SUM(O111:P111) -> 509.49 | R111: 1 | S111: =M111*1.02 -> 519.6798 | T111: 1 | U111: =T111*S111*R111 -> 519.6798 | V111: 0 | W111: =SUM(U111:V111) -> 519.6798 | X111: 1 | Y111: =S111*1.02 -> 530.0734 | Z111: 1 | AA111: =Z111*Y111*X111 -> 530.0734 | AB111: 0 | AC111: =SUM(AA111:AB111) -> 530.0734 | AD111: 1 | AE111: =Y111*1.02 -> 540.67486 | AF111: 1 | AG111: =AF111*AE111*AD111 -> 540.67486 | AH111: 0 | AI111: =SUM(AG111:AH111) -> 540.67486 | AJ111: =I111+O111+U111+AA111+AG111 -> 2599.4181 | AK111: =J111+P111+V111+AB111+AH111 -> 0 | AL111: =SUM(AJ111:AK111) -> 2599.4181
A112: TRAIN | B112: 87000 | C112: USA | D112: Trainings - HQ | E112: 4 | F112: 799.5 | G112: 1 | H112: /year | I112: =G112*F112*E112 -> 3198 | J112: 0 | K112: =SUM(I112:J112) -> 3198 | L112: 0 | M112: =F112*1.02 -> 815.49 | N112: 1 | O112: =L112*M112*N112 -> 0 | P112: 0 | Q112: =SUM(O112:P112) -> 0 | R112: 3 | S112: =M112*1.02 -> 831.7998 | T112: 1 | U112: =T112*S112*R112 -> 2495.3994 | V112: 0 | W112: =SUM(U112:V112) -> 2495.3994 | X112: 0 | Y112: =S112*1.02 -> 848.4358 | Z112: 1 | AA112: =Z112*Y112*X112 -> 0 | AB112: 0 | AC112: =SUM(AA112:AB112) -> 0 | AD112: 0 | AE112: =Y112*1.02 -> 865.40451 | AF112: 1 | AG112: =AF112*AE112*AD112 -> 0 | AH112: 0 | AI112: =SUM(AG112:AH112) -> 0 | AJ112: =I112+O112+U112+AA112+AG112 -> 5693.3994 | AK112: =J112+P112+V112+AB112+AH112 -> 0 | AL112: =SUM(AJ112:AK112) -> 5693.3994
A113: COMM | B113: 82030 | C113: USA | D113: Communications, Licenses & Subscriptions - HQ | E113: 1 | F113: ='HQ Expenses'!D15 -> 9164 | G113: 1 | H113: /year | I113: =G113*F113*E113 -> 9164 | J113: 0 | K113: =SUM(I113:J113) -> 9164 | L113: 1 | M113: =F113*1.02 -> 9347.28 | N113: 1 | O113: =L113*M113*N113 -> 9347.28 | P113: 0 | Q113: =SUM(O113:P113) -> 9347.28 | R113: 1 | S113: =M113*1.02 -> 9534.2256 | T113: 1 | U113: =T113*S113*R113 -> 9534.2256 | V113: 0 | W113: =SUM(U113:V113) -> 9534.2256 | X113: 1 | Y113: =S113*1.02 -> 9724.9101 | Z113: 1 | AA113: =Z113*Y113*X113 -> 9724.9101 | AB113: 0 | AC113: =SUM(AA113:AB113) -> 9724.9101 | AD113: 1 | AE113: =Y113*1.02 -> 9919.4083 | AF113: 1 | AG113: =AF113*AE113*AD113 -> 9919.4083 | AH113: 0 | AI113: =SUM(AG113:AH113) -> 9919.4083 | AJ113: =I113+O113+U113+AA113+AG113 -> 47689.824 | AK113: =J113+P113+V113+AB113+AH113 -> 0 | AL113: =SUM(AJ113:AK113) -> 47689.824
A114: WORKSHOP | B114: 87000 | C114: USA | D114: F2F Regional Workshop | E114: 1 | F114: 20600 | G114: 1 | H114: /year | I114: =G114*F114*E114 -> 20600 | J114: 0 | K114: =SUM(I114:J114) -> 20600 | L114: 0 | M114: =F114*1.02 -> 21012 | N114: 1 | O114: =L114*M114*N114 -> 0 | P114: 0 | Q114: =SUM(O114:P114) -> 0 | R114: 1 | S114: =M114*1.02 -> 21432.24 | T114: 1 | U114: =T114*S114*R114 -> 21432.24 | V114: 0 | W114: =SUM(U114:V114) -> 21432.24 | X114: 0 | Y114: =S114*1.02 -> 21860.885 | Z114: 1 | AA114: =Z114*Y114*X114 -> 0 | AB114: 0 | AC114: =SUM(AA114:AB114) -> 0 | AD114: 1 | AE114: =Y114*1.02 -> 22298.102 | AF114: 1 | AG114: =AF114*AE114*AD114 -> 22298.102 | AH114: 0 | AI114: =SUM(AG114:AH114) -> 22298.102 | AJ114: =I114+O114+U114+AA114+AG114 -> 64330.342 | AK114: =J114+P114+V114+AB114+AH114 -> 0 | AL114: =SUM(AJ114:AK114) -> 64330.342
A115: VARIOUS SEE TAB | B115: 87010 | C115: VARIOUS SEE TAB | D115: Field Office Meetings and Events | E115: 1 | F115: ='Guatemala '!I47+'Dominican Republic'!I47+Guyana!I46+Jamaica!J46 -> 3080 | G115: 1 | H115: /year | I115: =G115*F115*E115 -> 3080 | J115: 0 | K115: =SUM(I115:J115) -> 3080 | L115: 1 | M115: ='Guatemala '!N47+'Dominican Republic'!N47+Guyana!N46+Jamaica!N46 -> 3427.2 | N115: 1 | O115: =L115*M115*N115 -> 3427.2 | P115: 0 | Q115: =SUM(O115:P115) -> 3427.2 | R115: 1 | S115: ='Guatemala '!S47+'Dominican Republic'!S47+Guyana!S46+Jamaica!S46 -> 3495.744 | T115: 1 | U115: =T115*S115*R115 -> 3495.744 | V115: 0 | W115: =SUM(U115:V115) -> 3495.744 | X115: 1 | Y115: ='Guatemala '!X47+'Dominican Republic'!X47+Guyana!X46+Jamaica!X46 -> 3565.6589 | Z115: 1 | AA115: =Z115*Y115*X115 -> 3565.6589 | AB115: 0 | AC115: =SUM(AA115:AB115) -> 3565.6589 | AD115: 1 | AE115: ='Guatemala '!AD47+'Dominican Republic'!AD47+Guyana!AD46+Jamaica!AD46 -> 2727.729 | AF115: 1 | AG115: =AF115*AE115*AD115 -> 2727.729 | AH115: 0 | AI115: =SUM(AG115:AH115) -> 2727.729 | AJ115: =I115+O115+U115+AA115+AG115 -> 16296.332 | AK115: =J115+P115+V115+AB115+AH115 -> 0 | AL115: =SUM(AJ115:AK115) -> 16296.332
A116: VARIOUS SEE TAB | B116: 85105 | C116: VARIOUS SEE TAB | D116: Field Office Transportation | E116: 1 | F116: ='Guatemala '!I48+'Dominican Republic'!I48+Guyana!I47+Jamaica!J47 -> 7078.5 | G116: 1 | H116: /year | I116: =G116*F116*E116 -> 7078.5 | J116: 0 | K116: =SUM(I116:J116) -> 7078.5 | L116: 1 | M116: ='Guatemala '!N48+'Dominican Republic'!N48+Guyana!N47+Jamaica!N47 -> 7876.44 | N116: 1 | O116: =L116*M116*N116 -> 7876.44 | P116: 0 | Q116: =SUM(O116:P116) -> 7876.44 | R116: 1 | S116: ='Guatemala '!S48+'Dominican Republic'!S48+Guyana!S47+Jamaica!S47 -> 8033.9688 | T116: 1 | U116: =T116*S116*R116 -> 8033.9688 | V116: 0 | W116: =SUM(U116:V116) -> 8033.9688 | X116: 1 | Y116: ='Guatemala '!X48+'Dominican Republic'!X48+Guyana!X47+Jamaica!X47 -> 8194.6482 | Z116: 1 | AA116: =Z116*Y116*X116 -> 8194.6482 | AB116: 0 | AC116: =SUM(AA116:AB116) -> 8194.6482 | AD116: 1 | AE116: ='Guatemala '!AD48+'Dominican Republic'!AD48+Guyana!AD47+Jamaica!AD47 -> 6268.9059 | AF116: 1 | AG116: =AF116*AE116*AD116 -> 6268.9059 | AH116: 0 | AI116: =SUM(AG116:AH116) -> 6268.9059 | AJ116: =I116+O116+U116+AA116+AG116 -> 37452.463 | AK116: =J116+P116+V116+AB116+AH116 -> 0 | AL116: =SUM(AJ116:AK116) -> 37452.463
A117: VARIOUS SEE TAB | B117: 90900 | C117: VARIOUS SEE TAB | D117: Field Office Bank Fees | E117: 1 | F117: ='Guatemala '!I49+'Dominican Republic'!I49+Guyana!I48+Jamaica!J48 -> 2630.43 | G117: 1 | H117: /year | I117: =G117*F117*E117 -> 2630.43 | J117: 0 | K117: =SUM(I117:J117) -> 2630.43 | L117: 1 | M117: ='Guatemala '!N49+'Dominican Republic'!N49+Guyana!N48+Jamaica!N48 -> 2926.9512 | N117: 1 | O117: =L117*M117*N117 -> 2926.9512 | P117: 0 | Q117: =SUM(O117:P117) -> 2926.9512 | R117: 1 | S117: ='Guatemala '!S49+'Dominican Republic'!S49+Guyana!S48+Jamaica!S48 -> 2985.4902 | T117: 1 | U117: =T117*S117*R117 -> 2985.4902 | V117: 0 | W117: =SUM(U117:V117) -> 2985.4902 | X117: 1 | Y117: ='Guatemala '!X49+'Dominican Republic'!X49+Guyana!X48+Jamaica!X48 -> 3045.2 | Z117: 1 | AA117: =Z117*Y117*X117 -> 3045.2 | AB117: 0 | AC117: =SUM(AA117:AB117) -> 3045.2 | AD117: 1 | AE117: ='Guatemala '!AD49+'Dominican Republic'!AD49+Guyana!AD48+Jamaica!AD48 -> 2329.578 | AF117: 1 | AG117: =AF117*AE117*AD117 -> 2329.578 | AH117: 0 | AI117: =SUM(AG117:AH117) -> 2329.578 | AJ117: =I117+O117+U117+AA117+AG117 -> 13917.649 | AK117: =J117+P117+V117+AB117+AH117 -> 0 | AL117: =SUM(AJ117:AK117) -> 13917.649
A118: VARIOUS SEE TAB | B118: 82030 | C118: VARIOUS SEE TAB | D118: Field Office Communications | E118: 1 | F118: ='Guatemala '!I50+'Dominican Republic'!I50+Guyana!I49+Jamaica!J49 -> 4400 | G118: 1 | H118: /year | I118: =G118*F118*E118 -> 4400 | J118: 0 | K118: =SUM(I118:J118) -> 4400 | L118: 1 | M118: ='Guatemala '!N50+'Dominican Republic'!N50+Guyana!N49+Jamaica!N49 -> 4896 | N118: 1 | O118: =L118*M118*N118 -> 4896 | P118: 0 | Q118: =SUM(O118:P118) -> 4896 | R118: 1 | S118: ='Guatemala '!S50+'Dominican Republic'!S50+Guyana!S49+Jamaica!S49 -> 4993.92 | T118: 1 | U118: =T118*S118*R118 -> 4993.92 | V118: 0 | W118: =SUM(U118:V118) -> 4993.92 | X118: 1 | Y118: ='Guatemala '!X50+'Dominican Republic'!X50+Guyana!X49+Jamaica!X49 -> 5093.7984 | Z118: 1 | AA118: =Z118*Y118*X118 -> 5093.7984 | AB118: 0 | AC118: =SUM(AA118:AB118) -> 5093.7984 | AD118: 1 | AE118: ='Guatemala '!AD50+'Dominican Republic'!AD50+Guyana!AD49+Jamaica!AD49 -> 3896.7558 | AF118: 1 | AG118: =AF118*AE118*AD118 -> 3896.7558 | AH118: 0 | AI118: =SUM(AG118:AH118) -> 3896.7558 | AJ118: =I118+O118+U118+AA118+AG118 -> 23280.474 | AK118: =J118+P118+V118+AB118+AH118 -> 0 | AL118: =SUM(AJ118:AK118) -> 23280.474
A119: VARIOUS SEE TAB | B119: 85180 | C119: VARIOUS SEE TAB | D119: Field Office Rent & Utilities | E119: 1 | F119: ='Guatemala '!I51+'Dominican Republic'!I51+Guyana!I50+Jamaica!J50 -> 45925 | G119: 1 | H119: /year | I119: =G119*F119*E119 -> 45925 | J119: 0 | K119: =SUM(I119:J119) -> 45925 | L119: 1 | M119: ='Guatemala '!N51+'Dominican Republic'!N51+Guyana!N50+Jamaica!N50 -> 51102 | N119: 1 | O119: =L119*M119*N119 -> 51102 | P119: 0 | Q119: =SUM(O119:P119) -> 51102 | R119: 1 | S119: ='Guatemala '!S51+'Dominican Republic'!S51+Guyana!S50+Jamaica!S50 -> 52124.04 | T119: 1 | U119: =T119*S119*R119 -> 52124.04 | V119: 0 | W119: =SUM(U119:V119) -> 52124.04 | X119: 1 | Y119: ='Guatemala '!X51+'Dominican Republic'!X51+Guyana!X50+Jamaica!X50 -> 53166.521 | Z119: 1 | AA119: =Z119*Y119*X119 -> 53166.521 | AB119: 0 | AC119: =SUM(AA119:AB119) -> 53166.521 | AD119: 1 | AE119: ='Guatemala '!AD51+'Dominican Republic'!AD51+Guyana!AD50+Jamaica!AD50 -> 27114.926 | AF119: 1 | AG119: =AF119*AE119*AD119 -> 27114.926 | AH119: 0 | AI119: =SUM(AG119:AH119) -> 27114.926 | AJ119: =I119+O119+U119+AA119+AG119 -> 229432.49 | AK119: =J119+P119+V119+AB119+AH119 -> 0 | AL119: =SUM(AJ119:AK119) -> 229432.49
A120: VARIOUS SEE TAB | B120: 81030 | C120: VARIOUS SEE TAB | D120: Field Office Payroll | E120: 1 | F120: ='Guatemala '!I52+'Dominican Republic'!I52+Guyana!I51+Jamaica!J51 -> 8185.8333 | G120: 1 | H120: /year | I120: =G120*F120*E120 -> 8185.8333 | J120: 0 | K120: =SUM(I120:J120) -> 8185.8333 | L120: 1 | M120: ='Guatemala '!N52+'Dominican Republic'!N52+Guyana!N51+Jamaica!N51 -> 9108.6 | N120: 1 | O120: =L120*M120*N120 -> 9108.6 | P120: 0 | Q120: =SUM(O120:P120) -> 9108.6 | R120: 1 | S120: ='Guatemala '!S52+'Dominican Republic'!S52+Guyana!S51+Jamaica!S51 -> 9290.772 | T120: 1 | U120: =T120*S120*R120 -> 9290.772 | V120: 0 | W120: =SUM(U120:V120) -> 9290.772 | X120: 1 | Y120: ='Guatemala '!X52+'Dominican Republic'!X52+Guyana!X51+Jamaica!X51 -> 9476.5874 | Z120: 1 | AA120: =Z120*Y120*X120 -> 9476.5874 | AB120: 0 | AC120: =SUM(AA120:AB120) -> 9476.5874 | AD120: 1 | AE120: ='Guatemala '!AD52+'Dominican Republic'!AD52+Guyana!AD51+Jamaica!AD51 -> 7249.5894 | AF120: 1 | AG120: =AF120*AE120*AD120 -> 7249.5894 | AH120: 0 | AI120: =SUM(AG120:AH120) -> 7249.5894 | AJ120: =I120+O120+U120+AA120+AG120 -> 43311.382 | AK120: =J120+P120+V120+AB120+AH120 -> 0 | AL120: =SUM(AJ120:AK120) -> 43311.382
D122: Other Direct Costs Total | I122: =SUM(I110:I120) -> 105761.26 | J122: =SUM(J110:J120) -> 0 | K122: =SUM(K110:K120) -> 105761.26 | O122: =SUM(O110:O120) -> 90213.961 | P122: =SUM(P110:P120) -> 0 | Q122: =SUM(Q110:Q120) -> 90213.961 | U122: =SUM(U110:U120) -> 115945.88 | V122: =SUM(V110:V120) -> 0 | W122: =SUM(W110:W120) -> 115945.88 | AA122: =SUM(AA110:AA120) -> 93858.605 | AB122: =SUM(AB110:AB120) -> 0 | AC122: =SUM(AC110:AC120) -> 93858.605 | AG122: =SUM(AG110:AG120) -> 83428.102 | AH122: =SUM(AH110:AH120) -> 0 | AI122: =SUM(AI110:AI120) -> 83428.102 | AJ122: =AG122+AA122+U122+O122+I122 -> 489207.81 | AK122: =AH122+AB122+V122+P122+J122 -> 0 | AL122: =AI122+AC122+W122+Q122+K122 -> 489207.81
D124: Total Direct Costs | I124: =I122+I106+I99+I86+I80+I31+I25 -> 1137901.6 | J124: =J122+J106+J99+J86+J80+J31+J25 -> 511560 | K124: =SUM(I124:J124) -> 1649461.6 | O124: =O122+O106+O99+O86+O80+O31+O25 -> 1185903 | P124: =P122+P106+P99+P86+P80+P31+P25 -> 589860 | Q124: =SUM(O124:P124) -> 1775763 | U124: =U122+U106+U99+U86+U80+U31+U25 -> 1252275.9 | V124: =V122+V106+V99+V86+V80+V31+V25 -> 582030 | W124: =W122+W106+W99+W86+W80+W31+W25 -> 1834305.9 | AA124: =AA122+AA106+AA99+AA86+AA80+AA31+AA25 -> 1241323.3 | AB124: =AB122+AB106+AB99+AB86+AB80+AB31+AB25 -> 574200 | AC124: =AC122+AC106+AC99+AC86+AC80+AC31+AC25 -> 1815523.3 | AG124: =AG122+AG106+AG99+AG86+AG80+AG31+AG25 -> 1029181.5 | AH124: =AH122+AH106+AH99+AH86+AH80+AH31+AH25 -> 477630 | AI124: =AI122+AI106+AI99+AI86+AI80+AI31+AI25 -> 1506811.5 | AJ124: =AG124+AA124+U124+O124+I124 -> 5846585.3 | AK124: =AH124+AB124+V124+P124+J124 -> 2735280 | AL124: =SUM(AJ124:AK124) -> 8581865.3
A125: IDC | B125: 94050 | C125: USA | D125: Indirect Costs | E125: 0.2828 | I125: =I124*$E125 -> 321798.58 | J125: 0 | K125: =SUM(I125:J125) -> 321798.58 | O125: =O124*$E125 -> 335373.36 | P125: 0 | Q125: =SUM(O125:P125) -> 335373.36 | U125: =U124*$E125 -> 354143.64 | V125: 0 | W125: =SUM(U125:V125) -> 354143.64 | AA125: =AA124*$E125 -> 351046.22 | AB125: 0 | AC125: =SUM(AA125:AB125) -> 351046.22 | AG125: =AG124*$E125 -> 291052.53 | AH125: 0 | AI125: =SUM(AG125:AH125) -> 291052.53 | AJ125: =AG125+AA125+U125+O125+I125 -> 1653414.3 | AK125: =AH125+AB125+V125+P125+J125 -> 0 | AL125: =SUM(AJ125:AK125) -> 1653414.3
A126: BUY-IN | C126: USA | D126: Buy-in | U126: 1000000 | AJ126: =AG126+AA126+U126+O126+I126 -> 1000000 | AL126: =SUM(AJ126:AK126) -> 1000000
D127: Total | I127: =SUM(I124:I125) -> 1459700.2 | J127: =SUM(J124:J125) -> 511560 | K127: =SUM(K124:K125) -> 1971260.2 | O127: =SUM(O124:O125) -> 1521276.3 | P127: =SUM(P124:P125) -> 589860 | Q127: =SUM(Q124:Q125) -> 2111136.3 | U127: =SUM(U124:U126) -> 2606419.6 | V127: =SUM(V124:V125) -> 582030 | W127: =SUM(W124:W125) -> 2188449.6 | AA127: =SUM(AA124:AA125) -> 1592369.5 | AB127: =SUM(AB124:AB125) -> 574200 | AC127: =SUM(AC124:AC125) -> 2166569.5 | AG127: =SUM(AG124:AG125) -> 1320234 | AH127: =SUM(AH124:AH125) -> 477630 | AI127: =SUM(AI124:AI125) -> 1797864 | AJ127: =AG127+AA127+U127+O127+I127 -> 8499999.7 | AK127: =AH127+AB127+V127+P127+J127 -> 2735280 | AL127: =SUM(AJ127:AK127) -> 11235280

Sheet Guatemala 
A1: Entity: | B1: P | D1: Partners of the Americas F2F Caribbean Basin Program Budget
A2: Program-Dept.: | B2: 30100 | D2: USAID NOFO #7200AA23RFA00006
A3: Funder-Grant: | B3: USAID650
A4: Budget (Activity) Code | B4: Account Code | C4: Country Code | D4: Guatemala | I4: Year 1 | K4: Year 2 | P4: Year 3 | U4: Year 4 | Z4: Year 5 | AE4: Total | AF4: Grand
E5: Units | F5: Cost | G5: Duration | H5: Type | I5: USAID | J5: Total | K5: Units | L5: Cost | M5: Duration | N5: USAID | O5: Total | P5: Units | Q5: Cost | R5: Duration | S5: USAID | T5: Total | U5: Units | V5: Cost | W5: Duration | X5: USAID | Y5: Total | Z5: Units | AA5: Cost | AB5: Duration | AC5: USAID | AD5: Total | AE5: USAID | AF5: Total
D7: Key Personnel
A8: PERSNL-GTM | B8: 70000 | C8: GTM | D8: Country Director* | E8: 1 | F8: 5400 | G8: 12 | H8: /months | I8: =G8*F8*E8 -> 64800 | J8: =SUM(I8:I8) -> 64800 | K8: 1 | L8: =F8*1.03 -> 5562 | M8: 12 | N8: =M8*L8*K8 -> 66744 | O8: =SUM(N8:N8) -> 66744 | P8: 1 | Q8: =L8*1.03 -> 5728.86 | R8: 12 | S8: =R8*Q8*P8 -> 68746.32 | T8: =SUM(S8:S8) -> 68746.32 | U8: 1 | V8: =Q8*1.03 -> 5900.7258 | W8: 12 | X8: =W8*V8*U8 -> 70808.71 | Y8: =SUM(X8:X8) -> 70808.71 | Z8: 1 | AA8: =V8*1.03 -> 6077.7476 | AB8: 9 | AC8: =AB8*AA8*Z8 -> 54699.728 | AD8: =SUM(AC8:AC8) -> 54699.728 | AE8: =I8+N8+S8+X8+AC8 -> 325798.76 | AF8: =SUM(AE8:AE8) -> 325798.76
D10: Other Personnel
A11: PERSNL-GTM | B11: 70000 | C11: GTM | D11: Field Officer 1 | E11: 1 | F11: 1250 | G11: 10 | H11: /months | I11: =G11*F11*E11 -> 12500 | J11: =SUM(I11:I11) -> 12500 | K11: =E11 -> 1 | L11: =F11*1.03 -> 1287.5 | M11: 12 | N11: =M11*L11*K11 -> 15450 | O11: =SUM(N11:N11) -> 15450 | P11: =E11 -> 1 | Q11: =L11*1.03 -> 1326.125 | R11: 12 | S11: =R11*Q11*P11 -> 15913.5 | T11: =SUM(S11:S11) -> 15913.5 | U11: =E11 -> 1 | V11: =Q11*1.03 -> 1365.9088 | W11: 12 | X11: =W11*V11*U11 -> 16390.905 | Y11: =SUM(X11:X11) -> 16390.905 | Z11: =E11 -> 1 | AA11: =V11*1.03 -> 1406.886 | AB11: 9 | AC11: =AB11*AA11*Z11 -> 12661.974 | AD11: =SUM(AC11:AC11) -> 12661.974 | AE11: =I11+N11+S11+X11+AC11 -> 72916.379 | AF11: =SUM(AE11:AE11) -> 72916.379 | AG11: =K11+P11+U11+Z11+AE11 -> 72920.379 | AH11: =SUM(AG11:AG11) -> 72920.379 | AI11: =M11+R11+W11+AB11+AG11 -> 72965.379
A12: PERSNL-GTM | B12: 70000 | C12: GTM | D12: Field Officer 2 | E12: 1 | F12: 1250 | G12: 6 | H12: /months | I12: =G12*F12*E12 -> 7500 | J12: =SUM(I12:I12) -> 7500 | K12: =E12 -> 1 | L12: =F12*1.03 -> 1287.5 | M12: 12 | N12: =M12*L12*K12 -> 15450 | O12: =SUM(N12:N12) -> 15450 | P12: =E12 -> 1 | Q12: =L12*1.03 -> 1326.125 | R12: 12 | S12: =R12*Q12*P12 -> 15913.5 | T12: =SUM(S12:S12) -> 15913.5 | U12: =E12 -> 1 | V12: =Q12*1.03 -> 1365.9088 | W12: 12 | X12: =W12*V12*U12 -> 16390.905 | Y12: =SUM(X12:X12) -> 16390.905 | Z12: =E12 -> 1 | AA12: =V12*1.03 -> 1406.886 | AB12: 6 | AC12: =AB12*AA12*Z12 -> 8441.3161 | AD12: =SUM(AC12:AC12) -> 8441.3161 | AE12: =I12+N12+S12+X12+AC12 -> 63695.721 | AF12: =SUM(AE12:AE12) -> 63695.721 | AG12: =K12+P12+U12+Z12+AE12 -> 63699.721 | AH12: =SUM(AG12:AG12) -> 63699.721 | AI12: =M12+R12+W12+AB12+AG12 -> 63741.721
A13: PERSNL-GTM | B13: 70000 | C13: GTM | D13: Administrative Assistant | E13: 1 | F13: 850 | G13: 11 | H13: /months | I13: =G13*F13*E13 -> 9350 | J13: =SUM(I13:I13) -> 9350 | K13: 1 | L13: =F13*1.03 -> 875.5 | M13: 12 | N13: =M13*L13*K13 -> 10506 | O13: =SUM(N13:N13) -> 10506 | P13: 1 | Q13: =L13*1.03 -> 901.765 | R13: 12 | S13: =R13*Q13*P13 -> 10821.18 | T13: =SUM(S13:S13) -> 10821.18 | U13: 1 | V13: =Q13*1.03 -> 928.81795 | W13: 12 | X13: =W13*V13*U13 -> 11145.815 | Y13: =SUM(X13:X13) -> 11145.815 | Z13: 1 | AA13: =V13*1.03 -> 956.68249 | AB13: 9 | AC13: =AB13*AA13*Z13 -> 8610.1424 | AD13: =SUM(AC13:AC13) -> 8610.1424 | AE13: =I13+N13+S13+X13+AC13 -> 50433.138 | AF13: =SUM(AE13:AE13) -> 50433.138 | AG13: =K13+P13+U13+Z13+AE13 -> 50437.138 | AH13: =SUM(AG13:AG13) -> 50437.138 | AI13: =M13+R13+W13+AB13+AG13 -> 50482.138
D14: Subtotal Field Salaries | I14: =SUM(I8:I13) -> 94150 | J14: =SUM(J8:J13) -> 94150 | N14: =SUM(N8:N13) -> 108150 | O14: =SUM(O8:O13) -> 108150 | S14: =SUM(S8:S13) -> 111394.5 | T14: =SUM(T8:T13) -> 111394.5 | X14: =SUM(X8:X13) -> 114736.34 | Y14: =SUM(Y8:Y13) -> 114736.34 | AC14: =SUM(AC8:AC13) -> 84413.161 | AD14: =SUM(AD8:AD13) -> 84413.161 | AE14: =I14+N14+S14+X14+AC14 -> 512844 | AF14: =SUM(AE14:AE14) -> 512844
A16: FRINGE-GTM | B16: 70015 | C16: GTM | D16: Benefits | E16: 0.3566 | F16: =I14 -> 94150 | I16: =F16*E16 -> 33573.89 | J16: =SUM(I16:I16) -> 33573.89 | L16: =N14 -> 108150 | N16: =L16*E16 -> 38566.29 | O16: =SUM(N16:N16) -> 38566.29 | Q16: =S14 -> 111394.5 | S16: =Q16*E16 -> 39723.279 | T16: =SUM(S16:S16) -> 39723.279 | V16: =X14 -> 114736.34 | X16: =V16*E16 -> 40914.977 | Y16: =SUM(X16:X16) -> 40914.977 | AA16: =AC14 -> 84413.161 | AC16: =AA16*E16 -> 30101.733 | AD16: =SUM(AC16:AC16) -> 30101.733 | AE16: =I16+N16+S16+X16+AC16 -> 182880.17 | AF16: =SUM(AE16:AE16) -> 182880.17
D18: Supplies
A19: SUPPLY-GTM | B19: 82401 | C19: GTM | D19: Laptops | E19: ='FO Expenses'!C12 -> 4 | F19: ='FO Expenses'!B12 -> 1100 | G19: 1 | H19: /year | I19: =E19*F19*G19 -> 4400 | J19: =SUM(I19:I19) -> 4400 | K19: 0 | L19: =F19*1.02 -> 1122 | M19: 1 | N19: =M19*L19*K19 -> 0 | O19: =SUM(N19:N19) -> 0 | P19: 0 | Q19: =L19*1.02 -> 1144.44 | R19: 1 | S19: =R19*Q19*P19 -> 0 | T19: =SUM(S19:S19) -> 0 | U19: 0 | V19: =Q19*1.02 -> 1167.3288 | W19: 1 | X19: =W19*V19*U19 -> 0 | Y19: =SUM(X19:X19) -> 0 | Z19: 0 | AA19: =V19*1.02 -> 1190.6754 | AB19: 1 | AC19: =AB19*AA19*Z19 -> 0 | AD19: =SUM(AC19:AC19) -> 0 | AE19: =I19+N19+S19+X19+AC19 -> 4400 | AF19: =SUM(AE19:AE19) -> 4400
A20: SUPPLY-GTM | B20: 82401 | C20: GTM | D20: Tablet | E20: ='FO Expenses'!C13 -> 2 | F20: ='FO Expenses'!B13 -> 260 | G20: 1 | H20: /year | I20: =E20*F20*G20 -> 520 | J20: =SUM(I20:I20) -> 520 | K20: 0 | L20: =F20*1.02 -> 265.2 | M20: 1 | N20: =M20*L20*K20 -> 0 | O20: =SUM(N20:N20) -> 0 | P20: 0 | Q20: =L20*1.02 -> 270.504 | R20: 1 | S20: =R20*Q20*P20 -> 0 | T20: =SUM(S20:S20) -> 0 | U20: 0 | V20: =Q20*1.02 -> 275.91408 | W20: 1 | X20: =W20*V20*U20 -> 0 | Y20: =SUM(X20:X20) -> 0 | Z20: 0 | AA20: =V20*1.02 -> 281.43236 | AB20: 1 | AC20: =AB20*AA20*Z20 -> 0 | AD20: =SUM(AC20:AC20) -> 0 | AE20: =I20+N20+S20+X20+AC20 -> 520 | AF20: =SUM(AE20:AE20) -> 520
A21: SUPPLY-GTM | B21: 82401 | C21: GTM | D21: Projector | E21: ='FO Expenses'!C14 -> 1 | F21: ='FO Expenses'!B14 -> 650 | G21: 1 | H21: /year | I21: =E21*F21*G21 -> 650 | J21: =SUM(I21:I21) -> 650 | K21: 0 | L21: =F21*1.02 -> 663 | M21: 1 | N21: =M21*L21*K21 -> 0 | O21: =SUM(N21:N21) -> 0 | P21: 0 | Q21: =L21*1.02 -> 676.26 | R21: 1 | S21: =R21*Q21*P21 -> 0 | T21: =SUM(S21:S21) -> 0 | U21: 0 | V21: =Q21*1.02 -> 689.7852 | W21: 1 | X21: =W21*V21*U21 -> 0 | Y21: =SUM(X21:X21) -> 0 | Z21: 0 | AA21: =V21*1.02 -> 703.5809 | AB21: 1 | AC21: =AB21*AA21*Z21 -> 0 | AD21: =SUM(AC21:AC21) -> 0 | AE21: =I21+N21+S21+X21+AC21 -> 650 | AF21: =SUM(AE21:AE21) -> 650
A22: SUPPLY-GTM | B22: 82401 | C22: GTM | D22: Miscellaneous Supplies | E22: ='FO Expenses'!C15 -> 1 | F22: =SUM('FO Expenses'!D15) -> 530 | G22: 1 | H22: /year | I22: =E22*F22*G22 -> 530 | J22: =SUM(I22:I22) -> 530 | K22: 1 | L22: =F22*1.02 -> 540.6 | M22: 1 | N22: =M22*L22*K22 -> 540.6 | O22: =SUM(N22:N22) -> 540.6 | P22: 1 | Q22: =L22*1.02 -> 551.412 | R22: 1 | S22: =R22*Q22*P22 -> 551.412 | T22: =SUM(S22:S22) -> 551.412 | U22: 1 | V22: =Q22*1.02 -> 562.44024 | W22: 1 | X22: =W22*V22*U22 -> 562.44024 | Y22: =SUM(X22:X22) -> 562.44024 | Z22: 1 | AA22: =V22*1.02 -> 573.68904 | AB22: 1 | AC22: =AB22*AA22*Z22 -> 573.68904 | AD22: =SUM(AC22:AC22) -> 573.68904 | AE22: =I22+N22+S22+X22+AC22 -> 2758.1413 | AF22: =SUM(AE22:AE22) -> 2758.1413
D23: Subtotal Supplies | I23: =SUM(I19:I22) -> 6100 | J23: =SUM(J19:J22) -> 6100 | N23: =SUM(N19:N22) -> 540.6 | O23: =SUM(O19:O22) -> 540.6 | S23: =SUM(S19:S22) -> 551.412 | T23: =SUM(T19:T22) -> 551.412 | X23: =SUM(X19:X22) -> 562.44024 | Y23: =SUM(Y19:Y22) -> 562.44024 | AC23: =SUM(AC19:AC22) -> 573.68904 | AD23: =SUM(AD19:AD22) -> 573.68904 | AE23: =I23+N23+S23+X23+AC23 -> 8328.1413 | AF23: =SUM(AE23:AE23) -> 8328.1413
D25: Volunteer Travel Related Costs (Traditional)
A26: VFLYGTM | B26: 86040 | C26: GTM | D26: Roundtrip Airfare | E26: ='Volunteer Travel'!C4 -> 16 | F26: ='Volunteer Travel'!B19 -> 650 | G26: 1 | H26: /trip | I26: =E26*F26*G26 -> 10400 | J26: =F26*G26*E26 -> 10400 | K26: ='Volunteer Travel'!D4 -> 22 | L26: =F26*1.02 -> 663 | M26: =G26 -> 1 | N26: =L26*M26*K26 -> 14586 | O26: =L26*M26*K26 -> 14586 | P26: ='Volunteer Travel'!E4 -> 22 | Q26: =L26*1.02 -> 676.26 | R26: =M26 -> 1 | S26: =Q26*R26*P26 -> 14877.72 | T26: =Q26*R26*P26 -> 14877.72 | U26: ='Volunteer Travel'!F4 -> 22 | V26: =Q26*1.02 -> 689.7852 | W26: =R26 -> 1 | X26: =V26*W26*U26 -> 15175.274 | Y26: =V26*W26*U26 -> 15175.274 | Z26: ='Volunteer Travel'!G4 -> 16 | AA26: =V26*1.02 -> 703.5809 | AB26: =W26 -> 1 | AC26: =AA26*AB26*Z26 -> 11257.294 | AD26: =AA26*AB26*Z26 -> 11257.294 | AE26: =SUM(AD26,Y26,T26,O26,J26) -> 66296.289 | AF26: =SUM(AE26:AE26) -> 66296.289 | AG26: =AF26*0.7 -> 46407.402 | AH26: =AG26/3 -> 15469.134 | AI26: =AH26/12 -> 1289.0945
A27: VTRADGTM | B27: 86030 | C27: GTM | D27: Lodging | E27: =E26 -> 16 | F27: ='Volunteer Travel'!C19 -> 85 | G27: 14 | H27: /night | I27: =E27*F27*G27 -> 19040 | J27: =F27*G27*E27 -> 19040 | K27: =K26 -> 22 | L27: =F27*1.02 -> 86.7 | M27: =G27 -> 14 | N27: =L27*M27*K27 -> 26703.6 | O27: =L27*M27*K27 -> 26703.6 | P27: =P26 -> 22 | Q27: =L27*1.02 -> 88.434 | R27: =M27 -> 14 | S27: =Q27*R27*P27 -> 27237.672 | T27: =Q27*R27*P27 -> 27237.672 | U27: =U26 -> 22 | V27: =Q27*1.02 -> 90.20268 | W27: =R27 -> 14 | X27: =V27*W27*U27 -> 27782.425 | Y27: =V27*W27*U27 -> 27782.425 | Z27: =Z26 -> 16 | AA27: =V27*1.02 -> 92.006734 | AB27: =W27 -> 14 | AC27: =AA27*AB27*Z27 -> 20609.508 | AD27: =AA27*AB27*Z27 -> 20609.508 | AE27: =SUM(AD27,Y27,T27,O27,J27) -> 121373.21 | AF27: =SUM(AE27:AE27) -> 121373.21 | AG27: =AF27*0.7 -> 84961.244 | AH27: =AG27/3 -> 28320.415 | AI27: =AH27/12 -> 2360.0346
A28: VTRADGTM | B28: 86050 | C28: GTM | D28: Meals and Incidentals | E28: =E26 -> 16 | F28: ='Volunteer Travel'!D19 -> 42.5 | G28: 15 | H28: /day | I28: =E28*F28*G28 -> 10200 | J28: =F28*G28*E28 -> 10200 | K28: =K26 -> 22 | L28: =F28*1.02 -> 43.35 | M28: =G28 -> 15 | N28: =L28*M28*K28 -> 14305.5 | O28: =L28*M28*K28 -> 14305.5 | P28: =P26 -> 22 | Q28: =L28*1.02 -> 44.217 | R28: =M28 -> 15 | S28: =Q28*R28*P28 -> 14591.61 | T28: =Q28*R28*P28 -> 14591.61 | U28: =U26 -> 22 | V28: =Q28*1.02 -> 45.10134 | W28: =R28 -> 15 | X28: =V28*W28*U28 -> 14883.442 | Y28: =V28*W28*U28 -> 14883.442 | Z28: =Z26 -> 16 | AA28: =V28*1.02 -> 46.003367 | AB28: =W28 -> 15 | AC28: =AA28*AB28*Z28 -> 11040.808 | AD28: =AA28*AB28*Z28 -> 11040.808 | AE28: =SUM(AD28,Y28,T28,O28,J28) -> 65021.36 | AF28: =SUM(AE28:AE28) -> 65021.36 | AG28: =AF28*0.7 -> 45514.952 | AH28: =AG28/3 -> 15171.651 | AI28: =AH28/12 -> 1264.3042
A29: VTRADGTM | B29: 86050 | C29: GTM | D29: Health Related | E29: =E26 -> 16 | F29: ='Volunteer Travel'!E19 -> 75 | G29: 1 | H29: /trip | I29: =E29*F29*G29 -> 1200 | J29: =F29*G29*E29 -> 1200 | K29: =K27 -> 22 | L29: =F29*1.02 -> 76.5 | M29: =G29 -> 1 | N29: =L29*M29*K29 -> 1683 | O29: =L29*M29*K29 -> 1683 | P29: =P27 -> 22 | Q29: =L29*1.02 -> 78.03 | R29: =M29 -> 1 | S29: =Q29*R29*P29 -> 1716.66 | T29: =Q29*R29*P29 -> 1716.66 | U29: =U27 -> 22 | V29: =Q29*1.02 -> 79.5906 | W29: =R29 -> 1 | X29: =V29*W29*U29 -> 1750.9932 | Y29: =V29*W29*U29 -> 1750.9932 | Z29: =Z27 -> 16 | AA29: =V29*1.02 -> 81.182412 | AB29: =W29 -> 1 | AC29: =AA29*AB29*Z29 -> 1298.9186 | AD29: =AA29*AB29*Z29 -> 1298.9186 | AE29: =SUM(AD29,Y29,T29,O29,J29) -> 7649.5718 | AF29: =SUM(AE29:AE29) -> 7649.5718
A30: VTRADGTM | B30: 86050 | C30: GTM | D30: Other Travel Related Costs | E30: =E26 -> 16 | F30: ='Volunteer Travel'!F19 -> 124 | G30: 1 | H30: /trip | I30: =E30*F30*G30 -> 1984 | J30: =F30*G30*E30 -> 1984 | K30: =K26 -> 22 | L30: =F30*1.02 -> 126.48 | M30: 1 | N30: =L30*M30*K30 -> 2782.56 | O30: =L30*M30*K30 -> 2782.56 | P30: =P26 -> 22 | Q30: =L30*1.02 -> 129.0096 | R30: 1 | S30: =Q30*R30*P30 -> 2838.2112 | T30: =Q30*R30*P30 -> 2838.2112 | U30: =U26 -> 22 | V30: =Q30*1.02 -> 131.58979 | W30: 1 | X30: =V30*W30*U30 -> 2894.9754 | Y30: =V30*W30*U30 -> 2894.9754 | Z30: =Z26 -> 16 | AA30: =V30*1.02 -> 134.22159 | AB30: 1 | AC30: =AA30*AB30*Z30 -> 2147.5454 | AD30: =AA30*AB30*Z30 -> 2147.5454 | AE30: =SUM(AD30,Y30,T30,O30,J30) -> 12647.292 | AF30: =SUM(AE30:AE30) -> 12647.292 | AG30: =AF30*0.7 -> 8853.1044 | AH30: =AG30/3 -> 2951.0348 | AI30: =AH30/12 -> 245.91957
D32: Volunteer Travel Related Costs (Paired)
A33: VPAIRGTM | B33: 86030 | C33: GTM | D33: Lodging | E33: ='Volunteer Travel'!C5 -> 2 | F33: ='Volunteer Travel'!G19 -> 59.5 | G33: 6 | H33: /night | I33: =E33*F33*G33 -> 714 | J33: =E33*F33*G33 -> 714 | K33: ='Volunteer Travel'!D5 -> 1 | L33: =F33*1.02 -> 60.69 | M33: =G33 -> 6 | N33: =M33*K33*L33 -> 364.14 | O33: =K33*L33*M33 -> 364.14 | P33: ='Volunteer Travel'!D5 -> 1 | Q33: =L33*1.02 -> 61.9038 | R33: =M33 -> 6 | S33: =R33*P33*Q33 -> 371.4228 | T33: =P33*Q33*R33 -> 371.4228 | U33: ='Volunteer Travel'!F5 -> 1 | V33: =Q33*1.02 -> 63.141876 | W33: =R33 -> 6 | X33: =W33*U33*V33 -> 378.85126 | Y33: =U33*V33*W33 -> 378.85126 | Z33: ='Volunteer Travel'!G5 -> 1 | AA33: =V33*1.02 -> 64.404714 | AB33: =W33 -> 6 | AC33: =AB33*Z33*AA33 -> 386.42828 | AD33: =Z33*AA33*AB33 -> 386.42828 | AE33: =SUM(AD33,Y33,T33,O33,J33) -> 2214.8423 | AF33: =SUM(AE33:AE33) -> 2214.8423 | AG33: =AF33*0.7 -> 1550.3896 | AH33: =AG33/3 -> 516.79655 | AI33: =AH33/12 -> 43.066379
A34: VPAIRGTM | B34: 86050 | C34: GTM | D34: Meals and Incidentals | E34: =E33 -> 2 | F34: ='Volunteer Travel'!G20 -> 65.0475 | G34: 7 | H34: /day | I34: =E34*F34*G34 -> 910.665 | J34: =E34*F34*G34 -> 910.665 | K34: =K33 -> 1 | L34: =F34*1.02 -> 66.34845 | M34: =G34 -> 7 | N34: =M34*K34*L34 -> 464.43915 | O34: =K34*L34*M34 -> 464.43915 | P34: =P33 -> 1 | Q34: =L34*1.02 -> 67.675419 | R34: =M34 -> 7 | S34: =R34*P34*Q34 -> 473.72793 | T34: =P34*Q34*R34 -> 473.72793 | U34: =U33 -> 1 | V34: =Q34*1.02 -> 69.028927 | W34: =R34 -> 7 | X34: =W34*U34*V34 -> 483.20249 | Y34: =U34*V34*W34 -> 483.20249 | Z34: =Z33 -> 1 | AA34: =V34*1.02 -> 70.409506 | AB34: =W34 -> 7 | AC34: =AB34*Z34*AA34 -> 492.86654 | AD34: =Z34*AA34*AB34 -> 492.86654 | AE34: =SUM(AD34,Y34,T34,O34,J34) -> 2824.9011 | AF34: =SUM(AE34:AE34) -> 2824.9011 | AG34: =AF34*0.7 -> 1977.4308 | AH34: =AG34/3 -> 659.14359 | AI34: =AH34/12 -> 54.928633
A35: VPAIRGTM | B35: 86050 | C35: GTM | D35: Other Travel Related Costs | E35: =E33 -> 2 | F35: ='Volunteer Travel'!I19 -> 30 | G35: 1 | H35: /trip | I35: =E35*F35*G35 -> 60 | J35: =E35*F35*G35 -> 60 | K35: =K33 -> 1 | L35: =F35*1.02 -> 30.6 | M35: =G35 -> 1 | N35: =M35*K35*L35 -> 30.6 | O35: =K35*L35*M35 -> 30.6 | P35: =P33 -> 1 | Q35: =L35*1.02 -> 31.212 | R35: =M35 -> 1 | S35: =R35*P35*Q35 -> 31.212 | T35: =P35*Q35*R35 -> 31.212 | U35: =U33 -> 1 | V35: =Q35*1.02 -> 31.83624 | W35: =R35 -> 1 | X35: =W35*U35*V35 -> 31.83624 | Y35: =U35*V35*W35 -> 31.83624 | Z35: =Z33 -> 1 | AA35: =V35*1.02 -> 32.472965 | AB35: =W35 -> 1 | AC35: =AB35*Z35*AA35 -> 32.472965 | AD35: =Z35*AA35*AB35 -> 32.472965 | AE35: =SUM(AD35,Y35,T35,O35,J35) -> 186.1212 | AF35: =SUM(AE35:AE35) -> 186.1212 | AG35: =AF35*0.7 -> 130.28484 | AH35: =AG35/3 -> 43.428281 | AI35: =AH35/12 -> 3.6190234
AG36: =AF30-AG30 -> 3794.1876 | AH36: =AG36/2 -> 1897.0938 | AI36: =AH36/9 -> 210.7882
D37: Local Travel Related Costs
A38: LOTRVL-GTM | B38: 86030 | C38: GTM | D38: Lodging | E38: 1 | F38: ='Field Travel'!B15 -> 59.5 | G38: ='Volunteer Travel'!K5 -> 150 | H38: /night | I38: =E38*F38*G38 -> 8925 | J38: =F38*G38 -> 8925 | K38: 1 | L38: =F38*1.02 -> 60.69 | M38: ='Volunteer Travel'!L5 -> 180 | N38: =L38*M38 -> 10924.2 | O38: =L38*M38 -> 10924.2 | P38: 1 | Q38: =L38*1.02 -> 61.9038 | R38: ='Volunteer Travel'!M5 -> 198 | S38: =Q38*R38 -> 12256.952 | T38: =Q38*R38 -> 12256.952 | U38: 1 | V38: =Q38*1.02 -> 63.141876 | W38: ='Volunteer Travel'!N5 -> 180 | X38: =V38*W38 -> 11365.538 | Y38: =V38*W38 -> 11365.538 | Z38: 1 | AA38: =V38*1.02 -> 64.404714 | AB38: ='Volunteer Travel'!O5 -> 144 | AC38: =AA38*AB38 -> 9274.2787 | AD38: =AA38*AB38 -> 9274.2787 | AE38: =SUM(AD38,Y38,T38,O38,J38) -> 52745.969 | AF38: =SUM(AE38:AE38) -> 52745.969 | AG38: =AF38*0.7 -> 36922.178 | AH38: =AG38/3 -> 12307.393 | AI38: =AH38/12 -> 1025.6161
A39: LOTRVL-GTM | B39: 86050 | C39: GTM | D39: Meals and Incidentals | E39: 1 | F39: ='Field Travel'!C15 -> 42.5 | G39: =G38 -> 150 | H39: /day | I39: =E39*F39*G39 -> 6375 | J39: =F39*G39 -> 6375 | K39: 1 | L39: =F39*1.02 -> 43.35 | M39: =M38 -> 180 | N39: =L39*M39 -> 7803 | O39: =L39*M39 -> 7803 | P39: 1 | Q39: =L39*1.02 -> 44.217 | R39: =R38 -> 198 | S39: =Q39*R39 -> 8754.966 | T39: =Q39*R39 -> 8754.966 | U39: 1 | V39: =Q39*1.02 -> 45.10134 | W39: =W38 -> 180 | X39: =V39*W39 -> 8118.2412 | Y39: =V39*W39 -> 8118.2412 | Z39: 1 | AA39: =V39*1.02 -> 46.003367 | AB39: =AB38 -> 144 | AC39: =AA39*AB39 -> 6624.4848 | AD39: =AA39*AB39 -> 6624.4848 | AE39: =SUM(AD39,Y39,T39,O39,J39) -> 37675.692 | AF39: =SUM(AE39:AE39) -> 37675.692 | AG39: =AF39*0.7 -> 26372.984 | AH39: =AG39/3 -> 8790.9948 | AI39: =AH39/12 -> 732.5829
A40: LOTRVL-GTM | B40: 86000 | C40: GTM | D40: Local Transportation Costs (fuel) | E40: 1 | F40: ='Field Travel'!D15 -> 56 | G40: =E26+E33+'Field Travel'!L15 -> 39 | H40: /trip | I40: =E40*F40*G40 -> 2184 | J40: =F40*G40 -> 2184 | K40: 1 | L40: =F40*1.02 -> 57.12 | M40: =K26+K33+'Field Travel'!L16 -> 44 | N40: =L40*M40 -> 2513.28 | O40: =L40*M40 -> 2513.28 | P40: 1 | Q40: =L40*1.02 -> 58.2624 | R40: =P26+P33+'Field Travel'!L17 -> 53 | S40: =Q40*R40 -> 3087.9072 | T40: =Q40*R40 -> 3087.9072 | U40: 1 | V40: =Q40*1.02 -> 59.427648 | W40: =U26+U33+'Field Travel'!L18 -> 44 | X40: =V40*W40 -> 2614.8165 | Y40: =V40*W40 -> 2614.8165 | Z40: 1 | AA40: =V40*1.02 -> 60.616201 | AB40: =Z26+Z33+'Field Travel'!L19 -> 38 | AC40: =AA40*AB40 -> 2303.4156 | AD40: =AA40*AB40 -> 2303.4156 | AE40: =SUM(AD40,Y40,T40,O40,J40) -> 12703.419 | AF40: =SUM(AE40:AE40) -> 12703.419 | AG40: =AF40*0.7 -> 8892.3935 | AH40: =AG40/3 -> 2964.1312 | AI40: =AH40/12 -> 247.01093
D42: Equipment | AI42: =AH36/10 -> 189.70938
A43: NONE | B43: NONE | C43: NONE | D43: Vehicles | E43: 1 | F43: 0 | G43: 1 | H43: /year | I43: =E43*F43*G43 -> 0 | J43: =SUM(I43:I43) -> 0 | K43: 0 | L43: 0 | M43: 0 | N43: =M43*L43*K43 -> 0 | O43: =SUM(N43:N43) -> 0 | P43: 0 | Q43: 0 | R43: 0 | S43: =R43*Q43*P43 -> 0 | T43: =SUM(S43:S43) -> 0 | U43: 0 | V43: 0 | W43: 0 | X43: =W43*V43*U43 -> 0 | Y43: =SUM(X43:X43) -> 0 | Z43: 0 | AA43: 0 | AB43: 0 | AC43: =AB43*AA43*Z43 -> 0 | AD43: =SUM(AC43:AC43) -> 0 | AE43: =I43+N43+S43+X43+AC43 -> 0 | AF43: =SUM(AE43:AE43) -> 0
D44: Subtotal Equipment | I44: =SUM(I42:I43) -> 0 | J44: =SUM(J42:J43) -> 0 | N44: =SUM(N42:N43) -> 0 | O44: =SUM(O42:O43) -> 0 | S44: =SUM(S42:S43) -> 0 | T44: =SUM(T42:T43) -> 0 | X44: =SUM(X42:X43) -> 0 | Y44: =SUM(Y42:Y43) -> 0 | AC44: =SUM(AC42:AC43) -> 0 | AD44: =SUM(AD42:AD43) -> 0 | AE44: =I44+N44+S44+X44+AC44 -> 0 | AF44: =SUM(AE44:AE44) -> 0
D46: Other Expenses
A47: MEETGTM | B47: 87010 | C47: GTM | D47: Meetings and Events | E47: 1 | F47: ='FO Expenses'!L12 -> 65 | G47: 11 | H47: /months | I47: =G47*F47*E47 -> 715 | J47: =SUM(I47:I47) -> 715 | K47: 1 | L47: =F47*1.02 -> 66.3 | M47: 12 | N47: =M47*L47*K47 -> 795.6 | O47: =SUM(N47:N47) -> 795.6 | P47: 1 | Q47: =L47*1.02 -> 67.626 | R47: 12 | S47: =R47*Q47*P47 -> 811.512 | T47: =SUM(S47:S47) -> 811.512 | U47: 1 | V47: =Q47*1.02 -> 68.97852 | W47: 12 | X47: =W47*V47*U47 -> 827.74224 | Y47: =SUM(X47:X47) -> 827.74224 | Z47: 1 | AA47: =V47*1.02 -> 70.35809 | AB47: 9 | AC47: =AB47*AA47*Z47 -> 633.22281 | AD47: =SUM(AC47:AC47) -> 633.22281 | AE47: =I47+N47+S47+X47+AC47 -> 3783.0771 | AF47: =SUM(AE47:AE47) -> 3783.0771
A48: TRANSGTM | B48: 85105 | C48: GTM | D48: Transportation | E48: 1 | F48: ='FO Expenses'!L13 -> 155 | G48: 11 | H48: /months | I48: =G48*F48*E48 -> 1705 | J48: =SUM(I48:I48) -> 1705 | K48: 1 | L48: =F48*1.02 -> 158.1 | M48: 12 | N48: =M48*L48*K48 -> 1897.2 | O48: =SUM(N48:N48) -> 1897.2 | P48: 1 | Q48: =L48*1.02 -> 161.262 | R48: 12 | S48: =R48*Q48*P48 -> 1935.144 | T48: =SUM(S48:S48) -> 1935.144 | U48: 1 | V48: =Q48*1.02 -> 164.48724 | W48: 12 | X48: =W48*V48*U48 -> 1973.8469 | Y48: =SUM(X48:X48) -> 1973.8469 | Z48: 1 | AA48: =V48*1.02 -> 167.77698 | AB48: 9 | AC48: =AB48*AA48*Z48 -> 1509.9929 | AD48: =SUM(AC48:AC48) -> 1509.9929 | AE48: =I48+N48+S48+X48+AC48 -> 9021.1837 | AF48: =SUM(AE48:AE48) -> 9021.1837
A49: BANKGTM | B49: 90900 | C49: GTM | D49: Bank Fees | E49: 1 | F49: ='FO Expenses'!L14 -> 60.13 | G49: 11 | H49: /months | I49: =G49*F49*E49 -> 661.43 | J49: =SUM(I49:I49) -> 661.43 | K49: 1 | L49: =F49*1.02 -> 61.3326 | M49: 12 | N49: =M49*L49*K49 -> 735.9912 | O49: =SUM(N49:N49) -> 735.9912 | P49: 1 | Q49: =L49*1.02 -> 62.559252 | R49: 12 | S49: =R49*Q49*P49 -> 750.71102 | T49: =SUM(S49:S49) -> 750.71102 | U49: 1 | V49: =Q49*1.02 -> 63.810437 | W49: 12 | X49: =W49*V49*U49 -> 765.72524 | Y49: =SUM(X49:X49) -> 765.72524 | Z49: 1 | AA49: =V49*1.02 -> 65.086646 | AB49: 9 | AC49: =AB49*AA49*Z49 -> 585.77981 | AD49: =SUM(AC49:AC49) -> 585.77981 | AE49: =I49+N49+S49+X49+AC49 -> 3499.6373 | AF49: =SUM(AE49:AE49) -> 3499.6373
A50: COMMGTM | B50: 82030 | C50: GTM | D50: Communications | E50: 1 | F50: =SUM('FO Expenses'!L16:L16) -> 100 | G50: 11 | H50: /months | I50: =G50*F50*E50 -> 1100 | J50: =SUM(I50:I50) -> 1100 | K50: 1 | L50: =F50*1.02 -> 102 | M50: 12 | N50: =M50*L50*K50 -> 1224 | O50: =SUM(N50:N50) -> 1224 | P50: 1 | Q50: =L50*1.02 -> 104.04 | R50: 12 | S50: =R50*Q50*P50 -> 1248.48 | T50: =SUM(S50:S50) -> 1248.48 | U50: 1 | V50: =Q50*1.02 -> 106.1208 | W50: 12 | X50: =W50*V50*U50 -> 1273.4496 | Y50: =SUM(X50:X50) -> 1273.4496 | Z50: 1 | AA50: =V50*1.02 -> 108.24322 | AB50: 9 | AC50: =AB50*AA50*Z50 -> 974.18894 | AD50: =SUM(AC50:AC50) -> 974.18894 | AE50: =I50+N50+S50+X50+AC50 -> 5820.1185 | AF50: =SUM(AE50:AE50) -> 5820.1185
A51: RENT&UTGTM | B51: 85180 | C51: GTM | D51: Office Rent & Utilities | E51: 1 | F51: =SUM('FO Expenses'!G9:G9) -> 900 | G51: 11 | H51: /months | I51: =G51*F51*E51 -> 9900 | J51: =SUM(I51:I51) -> 9900 | K51: 1 | L51: =F51*1.02 -> 918 | M51: 12 | N51: =M51*L51*K51 -> 11016 | O51: =SUM(N51:N51) -> 11016 | P51: 1 | Q51: =L51*1.02 -> 936.36 | R51: 12 | S51: =R51*Q51*P51 -> 11236.32 | T51: =SUM(S51:S51) -> 11236.32 | U51: 1 | V51: =Q51*1.02 -> 955.0872 | W51: 12 | X51: =W51*V51*U51 -> 11461.046 | Y51: =SUM(X51:X51) -> 11461.046 | Z51: 1 | AA51: =V51*1.02 -> 974.18894 | AB51: 6 | AC51: =AB51*AA51*Z51 -> 5845.1337 | AD51: =SUM(AC51:AC51) -> 5845.1337 | AE51: =I51+N51+S51+X51+AC51 -> 49458.5 | AF51: =SUM(AE51:AE51) -> 49458.5
A52: PAYROLLGTM | B52: 81030 | C52: GTM | D52: Payroll Company | E52: 1 | F52: ='FO Expenses'!L15 -> 233.75 | G52: 11 | H52: /months | I52: =G52*F52*E52 -> 2571.25 | J52: =SUM(I52:I52) -> 2571.25 | K52: 1 | L52: =F52*1.02 -> 238.425 | M52: 12 | N52: =M52*L52*K52 -> 2861.1 | O52: =SUM(N52:N52) -> 2861.1 | P52: 1 | Q52: =L52*1.02 -> 243.1935 | R52: 12 | S52: =R52*Q52*P52 -> 2918.322 | T52: =SUM(S52:S52) -> 2918.322 | U52: 1 | V52: =Q52*1.02 -> 248.05737 | W52: 12 | X52: =W52*V52*U52 -> 2976.6884 | Y52: =SUM(X52:X52) -> 2976.6884 | Z52: 1 | AA52: =V52*1.02 -> 253.01852 | AB52: 9 | AC52: =AB52*AA52*Z52 -> 2277.1667 | AD52: =SUM(AC52:AC52) -> 2277.1667 | AE52: =I52+N52+S52+X52+AC52 -> 13604.527 | AF52: =SUM(AE52:AE52) -> 13604.527
D53: Subtotal Office Expenses | I53: =SUM(I47:I52) -> 16652.68 | J53: =SUM(J47:J52) -> 16652.68 | N53: =SUM(N47:N52) -> 18529.891 | O53: =SUM(O47:O52) -> 18529.891 | S53: =SUM(S47:S52) -> 18900.489 | T53: =SUM(T47:T52) -> 18900.489 | X53: =SUM(X47:X52) -> 19278.499 | Y53: =SUM(Y47:Y52) -> 19278.499 | AC53: =SUM(AC47:AC52) -> 11825.485 | AD53: =SUM(AD47:AD52) -> 11825.485 | AE53: =I53+N53+S53+X53+AC53 -> 85187.044 | AF53: =SUM(AE53:AE53) -> 85187.044
D55: Total | I55: =I53+I16+I19+I44+I14+I30 -> 150760.57 | J55: =J53+J16+J19+J44+J14+J30 -> 150760.57 | N55: =N53+N16+N19+N44+N14+N30 -> 168028.74 | O55: =O53+O16+O19+O44+O14+O30 -> 168028.74 | S55: =S53+S16+S19+S44+S14+S30 -> 172856.48 | T55: =T53+T16+T19+T44+T14+T30 -> 172856.48 | X55: =X53+X16+X19+X44+X14+X30 -> 177824.79 | Y55: =Y53+Y16+Y19+Y44+Y14+Y30 -> 177824.79 | AC55: =AC53+AC16+AC19+AC44+AC14+AC30 -> 128487.92 | AD55: =AD53+AD16+AD19+AD44+AD14+AD30 -> 128487.92 | AE55: =AE53+AE16+AE19+AE44+AE14+AE30 -> 797958.5 | AF55: =AF53+AF16+AF19+AF44+AF14+AF30 -> 797958.5

Sheet Guyana
A1: Entity: | B1: P | D1: Partners of the Americas F2F Caribbean Basin Program Budget
A2: Program-Dept.: | B2: 30100 | D2: USAID NOFO #7200AA23RFA00006
A3: Funder-Grant: | B3: USAID650
A4: Budget (Activity) Code | B4: Account Code | C4: Country Code | D4: Guyana | I4: Year 1 | K4: Year 2 | P4: Year 3 | U4: Year 4 | Z4: Year 5 | AE4: Total | AF4: Grand
E5: Units | F5: Cost | G5: Duration | H5: Type | I5: USAID | J5: Total | K5: Units | L5: Cost | M5: Duration | N5: USAID | O5: Total | P5: Units | Q5: Cost | R5: Duration | S5: USAID | T5: Total | U5: Units | V5: Cost | W5: Duration | X5: USAID | Y5: Total | Z5: Units | AA5: Cost | AB5: Duration | AC5: USAID | AD5: Total | AE5: USAID | AF5: Total
D7: Key Personnel
A8: PERSNL-GUY | B8: 70000 | C8: GUY | D8: Country Director* | E8: 1 | F8: 4000 | G8: 12 | H8: /months | I8: =G8*F8*E8 -> 48000 | J8: =SUM(I8:I8) -> 48000 | K8: 1 | L8: =F8*1.03 -> 4120 | M8: 12 | N8: =M8*L8*K8 -> 49440 | O8: =SUM(N8:N8) -> 49440 | P8: 1 | Q8: =L8*1.03 -> 4243.6 | R8: 12 | S8: =R8*Q8*P8 -> 50923.2 | T8: =SUM(S8:S8) -> 50923.2 | U8: 1 | V8: =Q8*1.03 -> 4370.908 | W8: 12 | X8: =W8*V8*U8 -> 52450.896 | Y8: =SUM(X8:X8) -> 52450.896 | Z8: 1 | AA8: =V8*1.03 -> 4502.0352 | AB8: 9 | AC8: =AB8*AA8*Z8 -> 40518.317 | AD8: =SUM(AC8:AC8) -> 40518.317 | AE8: =I8+N8+S8+X8+AC8 -> 241332.41 | AF8: =SUM(AE8:AE8) -> 241332.41
D10: Other Personnel
A11: PERSNL-GUY | B11: 70000 | C11: GUY | D11: Field Officer | E11: 1 | F11: 1100 | G11: 10 | H11: /months | I11: =G11*F11*E11 -> 11000 | J11: =SUM(I11:I11) -> 11000 | K11: =E11 -> 1 | L11: =F11*1.03 -> 1133 | M11: 12 | N11: =M11*L11*K11 -> 13596 | O11: =SUM(N11:N11) -> 13596 | P11: =E11 -> 1 | Q11: =L11*1.03 -> 1166.99 | R11: 12 | S11: =R11*Q11*P11 -> 14003.88 | T11: =SUM(S11:S11) -> 14003.88 | U11: =E11 -> 1 | V11: =Q11*1.03 -> 1201.9997 | W11: 12 | X11: =W11*V11*U11 -> 14423.996 | Y11: =SUM(X11:X11) -> 14423.996 | Z11: =E11 -> 1 | AA11: =V11*1.03 -> 1238.0597 | AB11: 9 | AC11: =AB11*AA11*Z11 -> 11142.537 | AD11: =SUM(AC11:AC11) -> 11142.537 | AE11: =I11+N11+S11+X11+AC11 -> 64166.414 | AF11: =SUM(AE11:AE11) -> 64166.414 | AG11: =K11+P11+U11+Z11+AE11 -> 64170.414 | AH11: =SUM(AG11:AG11) -> 64170.414 | AI11: =M11+R11+W11+AB11+AG11 -> 64215.414
A12: PERSNL-GUY | B12: 70000 | C12: GUY | D12: Administrative Assistant | E12: 1 | F12: 850 | G12: 11 | H12: /months | I12: =G12*F12*E12 -> 9350 | J12: =SUM(I12:I12) -> 9350 | K12: 1 | L12: =F12*1.03 -> 875.5 | M12: 12 | N12: =M12*L12*K12 -> 10506 | O12: =SUM(N12:N12) -> 10506 | P12: 1 | Q12: =L12*1.03 -> 901.765 | R12: 12 | S12: =R12*Q12*P12 -> 10821.18 | T12: =SUM(S12:S12) -> 10821.18 | U12: 1 | V12: =Q12*1.03 -> 928.81795 | W12: 12 | X12: =W12*V12*U12 -> 11145.815 | Y12: =SUM(X12:X12) -> 11145.815 | Z12: 1 | AA12: =V12*1.03 -> 956.68249 | AB12: 9 | AC12: =AB12*AA12*Z12 -> 8610.1424 | AD12: =SUM(AC12:AC12) -> 8610.1424 | AE12: =I12+N12+S12+X12+AC12 -> 50433.138 | AF12: =SUM(AE12:AE12) -> 50433.138 | AG12: =K12+P12+U12+Z12+AE12 -> 50437.138 | AH12: =SUM(AG12:AG12) -> 50437.138 | AI12: =M12+R12+W12+AB12+AG12 -> 50482.138
D13: Subtotal Field Salaries | I13: =SUM(I8:I12) -> 68350 | J13: =SUM(J8:J12) -> 68350 | N13: =SUM(N8:N12) -> 73542 | O13: =SUM(O8:O12) -> 73542 | S13: =SUM(S8:S12) -> 75748.26 | T13: =SUM(T8:T12) -> 75748.26 | X13: =SUM(X8:X12) -> 78020.708 | Y13: =SUM(Y8:Y12) -> 78020.708 | AC13: =SUM(AC8:AC12) -> 60270.997 | AD13: =SUM(AD8:AD12) -> 60270.997 | AE13: =I13+N13+S13+X13+AC13 -> 355931.96 | AF13: =SUM(AE13:AE13) -> 355931.96
A15: FRINGE-GUY | B15: 70015 | C15: GUY | D15: Benefits | E15: 0.1032 | F15: =I13 -> 68350 | I15: =F15*E15 -> 7053.72 | J15: =SUM(I15:I15) -> 7053.72 | L15: =N13 -> 73542 | N15: =L15*E15 -> 7589.5344 | O15: =SUM(N15:N15) -> 7589.5344 | Q15: =S13 -> 75748.26 | S15: =Q15*E15 -> 7817.2204 | T15: =SUM(S15:S15) -> 7817.2204 | V15: =X13 -> 78020.708 | X15: =V15*E15 -> 8051.737 | Y15: =SUM(X15:X15) -> 8051.737 | AA15: =AC13 -> 60270.997 | AC15: =AA15*E15 -> 6219.9669 | AD15: =SUM(AC15:AC15) -> 6219.9669 | AE15: =I15+N15+S15+X15+AC15 -> 36732.179 | AF15: =SUM(AE15:AE15) -> 36732.179
D17: Supplies
A18: SUPPLY-GUY | B18: 82401 | C18: GUY | D18: Laptops | E18: ='FO Expenses'!C19 -> 3 | F18: ='FO Expenses'!B19 -> 1100 | G18: 1 | H18: /year | I18: =E18*F18*G18 -> 3300 | J18: =SUM(I18:I18) -> 3300 | K18: 0 | L18: =F18*1.02 -> 1122 | M18: 1 | N18: =M18*L18*K18 -> 0 | O18: =SUM(N18:N18) -> 0 | P18: 0 | Q18: =L18*1.02 -> 1144.44 | R18: 1 | S18: =R18*Q18*P18 -> 0 | T18: =SUM(S18:S18) -> 0 | U18: 0 | V18: =Q18*1.02 -> 1167.3288 | W18: 1 | X18: =W18*V18*U18 -> 0 | Y18: =SUM(X18:X18) -> 0 | Z18: 0 | AA18: =V18*1.02 -> 1190.6754 | AB18: 1 | AC18: =AB18*AA18*Z18 -> 0 | AD18: =SUM(AC18:AC18) -> 0 | AE18: =I18+N18+S18+X18+AC18 -> 3300 | AF18: =SUM(AE18:AE18) -> 3300
A19: SUPPLY-GUY | B19: 82401 | C19: GUY | D19: Tablet | E19: ='FO Expenses'!C20 -> 2 | F19: ='FO Expenses'!B20 -> 190 | G19: 1 | H19: /year | I19: =E19*F19*G19 -> 380 | J19: =SUM(I19:I19) -> 380 | K19: 0 | L19: =F19*1.02 -> 193.8 | M19: 1 | N19: =M19*L19*K19 -> 0 | O19: =SUM(N19:N19) -> 0 | P19: 0 | Q19: =L19*1.02 -> 197.676 | R19: 1 | S19: =R19*Q19*P19 -> 0 | T19: =SUM(S19:S19) -> 0 | U19: 0 | V19: =Q19*1.02 -> 201.62952 | W19: 1 | X19: =W19*V19*U19 -> 0 | Y19: =SUM(X19:X19) -> 0 | Z19: 0 | AA19: =V19*1.02 -> 205.66211 | AB19: 1 | AC19: =AB19*AA19*Z19 -> 0 | AD19: =SUM(AC19:AC19) -> 0 | AE19: =I19+N19+S19+X19+AC19 -> 380 | AF19: =SUM(AE19:AE19) -> 380
A20: SUPPLY-GUY | B20: 82401 | C20: GUY | D20: Projector | E20: ='FO Expenses'!C21 -> 1 | F20: ='FO Expenses'!B21 -> 650 | G20: 1 | H20: /year | I20: =E20*F20*G20 -> 650 | J20: =SUM(I20:I20) -> 650 | K20: 0 | L20: =F20*1.02 -> 663 | M20: 1 | N20: =M20*L20*K20 -> 0 | O20: =SUM(N20:N20) -> 0 | P20: 0 | Q20: =L20*1.02 -> 676.26 | R20: 1 | S20: =R20*Q20*P20 -> 0 | T20: =SUM(S20:S20) -> 0 | U20: 0 | V20: =Q20*1.02 -> 689.7852 | W20: 1 | X20: =W20*V20*U20 -> 0 | Y20: =SUM(X20:X20) -> 0 | Z20: 0 | AA20: =V20*1.02 -> 703.5809 | AB20: 1 | AC20: =AB20*AA20*Z20 -> 0 | AD20: =SUM(AC20:AC20) -> 0 | AE20: =I20+N20+S20+X20+AC20 -> 650 | AF20: =SUM(AE20:AE20) -> 650
A21: SUPPLY-GUY | B21: 82401 | C21: GUY | D21: Miscellaneous Supplies | E21: =1 -> 1 | F21: ='FO Expenses'!B22 -> 530 | G21: 1 | H21: /year | I21: =E21*F21*G21 -> 530 | J21: =SUM(I21:I21) -> 530 | K21: 1 | L21: =F21*1.02 -> 540.6 | M21: 1 | N21: =M21*L21*K21 -> 540.6 | O21: =SUM(N21:N21) -> 540.6 | P21: 1 | Q21: =L21*1.02 -> 551.412 | R21: 1 | S21: =R21*Q21*P21 -> 551.412 | T21: =SUM(S21:S21) -> 551.412 | U21: 1 | V21: =Q21*1.02 -> 562.44024 | W21: 1 | X21: =W21*V21*U21 -> 562.44024 | Y21: =SUM(X21:X21) -> 562.44024 | Z21: 1 | AA21: =V21*1.02 -> 573.68904 | AB21: 1 | AC21: =AB21*AA21*Z21 -> 573.68904 | AD21: =SUM(AC21:AC21) -> 573.68904 | AE21: =I21+N21+S21+X21+AC21 -> 2758.1413 | AF21: =SUM(AE21:AE21) -> 2758.1413
D22: Subtotal Supplies | I22: =SUM(I18:I21) -> 4860 | J22: =SUM(J18:J21) -> 4860 | N22: =SUM(N18:N21) -> 540.6 | O22: =SUM(O18:O21) -> 540.6 | S22: =SUM(S18:S21) -> 551.412 | T22: =SUM(T18:T21) -> 551.412 | X22: =SUM(X18:X21) -> 562.44024 | Y22: =SUM(Y18:Y21) -> 562.44024 | AC22: =SUM(AC18:AC21) -> 573.68904 | AD22: =SUM(AD18:AD21) -> 573.68904 | AE22: =I22+N22+S22+X22+AC22 -> 7088.1413 | AF22: =SUM(AE22:AE22) -> 7088.1413
D24: Volunteer Travel Related Costs (Traditional)
A25: VFLYGUY | B25: 86040 | C25: GUY | D25: Roundtrip Airfare | E25: ='Volunteer Travel'!C8 -> 14 | F25: ='Volunteer Travel'!B21 -> 850 | G25: 1 | H25: /trip | I25: =E25*F25*G25 -> 11900 | J25: =F25*G25*E25 -> 11900 | K25: ='Volunteer Travel'!D8 -> 13 | L25: =F25*1.02 -> 867 | M25: =G25 -> 1 | N25: =L25*M25*K25 -> 11271 | O25: =L25*M25*K25 -> 11271 | P25: ='Volunteer Travel'!E8 -> 13 | Q25: =L25*1.02 -> 884.34 | R25: =M25 -> 1 | S25: =Q25*R25*P25 -> 11496.42 | T25: =Q25*R25*P25 -> 11496.42 | U25: ='Volunteer Travel'!F8 -> 12 | V25: =Q25*1.02 -> 902.0268 | W25: =R25 -> 1 | X25: =V25*W25*U25 -> 10824.322 | Y25: =V25*W25*U25 -> 10824.322 | Z25: ='Volunteer Travel'!G8 -> 12 | AA25: =V25*1.02 -> 920.06734 | AB25: =W25 -> 1 | AC25: =AA25*AB25*Z25 -> 11040.808 | AD25: =AA25*AB25*Z25 -> 11040.808 | AE25: =SUM(AD25,Y25,T25,O25,J25) -> 56532.55 | AF25: =SUM(AE25:AE25) -> 56532.55 | AG25: =AF25*0.7 -> 39572.785 | AH25: =AG25/3 -> 13190.928 | AI25: =AH25/12 -> 1099.244
A26: VTRADGUY | B26: 86030 | C26: GUY | D26: Lodging | E26: =E25 -> 14 | F26: ='Volunteer Travel'!C21 -> 102.96 | G26: 14 | H26: /night | I26: =E26*F26*G26 -> 20180.16 | J26: =F26*G26*E26 -> 20180.16 | K26: =K25 -> 13 | L26: =F26*1.02 -> 105.0192 | M26: =G26 -> 14 | N26: =L26*M26*K26 -> 19113.494 | O26: =L26*M26*K26 -> 19113.494 | P26: =P25 -> 13 | Q26: =L26*1.02 -> 107.11958 | R26: =M26 -> 14 | S26: =Q26*R26*P26 -> 19495.764 | T26: =Q26*R26*P26 -> 19495.764 | U26: =U25 -> 12 | V26: =Q26*1.02 -> 109.26198 | W26: =R26 -> 14 | X26: =V26*W26 -> 1529.6677 | Y26: =V26*W26*U26 -> 18356.012 | Z26: =Z25 -> 12 | AA26: =V26*1.02 -> 111.44722 | AB26: =W26 -> 14 | AC26: =AA26*AB26*Z26 -> 18723.132 | AD26: =AA26*AB26*Z26 -> 18723.132 | AE26: =SUM(AD26,Y26,T26,O26,J26) -> 95868.563 | AF26: =SUM(AE26:AE26) -> 95868.563 | AG26: =AF26*0.7 -> 67107.994 | AH26: =AG26/3 -> 22369.331 | AI26: =AH26/12 -> 1864.1109
A27: VTRADGUY | B27: 86050 | C27: GUY | D27: Meals and Incidentals | E27: =E25 -> 14 | F27: ='Volunteer Travel'!D21 -> 59.5 | G27: 15 | H27: /day | I27: =E27*F27*G27 -> 12495 | J27: =F27*G27*E27 -> 12495 | K27: =K25 -> 13 | L27: =F27*1.02 -> 60.69 | M27: =G27 -> 15 | N27: =L27*M27*K27 -> 11834.55 | O27: =L27*M27*K27 -> 11834.55 | P27: =P25 -> 13 | Q27: =L27*1.02 -> 61.9038 | R27: =M27 -> 15 | S27: =Q27*R27*P27 -> 12071.241 | T27: =Q27*R27*P27 -> 12071.241 | U27: =U25 -> 12 | V27: =Q27*1.02 -> 63.141876 | W27: =R27 -> 15 | X27: =V27*W27 -> 947.12814 | Y27: =V27*W27*U27 -> 11365.538 | Z27: =Z25 -> 12 | AA27: =V27*1.02 -> 64.404714 | AB27: =W27 -> 15 | AC27: =AA27*AB27*Z27 -> 11592.848 | AD27: =AA27*AB27*Z27 -> 11592.848 | AE27: =SUM(AD27,Y27,T27,O27,J27) -> 59359.177 | AF27: =SUM(AE27:AE27) -> 59359.177 | AG27: =AF27*0.7 -> 41551.424 | AH27: =AG27/3 -> 13850.475 | AI27: =AH27/12 -> 1154.2062
A28: VTRADGUY | B28: 86050 | C28: GUY | D28: Health Related | E28: =E25 -> 14 | F28: ='Volunteer Travel'!E21 -> 75 | G28: 1 | H28: /trip | I28: =E28*F28*G28 -> 1050 | J28: =F28*G28*E28 -> 1050 | K28: =K26 -> 13 | L28: =F28*1.02 -> 76.5 | M28: =G28 -> 1 | N28: =L28*M28*K28 -> 994.5 | O28: =L28*M28*K28 -> 994.5 | P28: =P26 -> 13 | Q28: =L28*1.02 -> 78.03 | R28: =M28 -> 1 | S28: =Q28*R28*P28 -> 1014.39 | T28: =Q28*R28*P28 -> 1014.39 | U28: =U26 -> 12 | V28: =Q28*1.02 -> 79.5906 | W28: =R28 -> 1 | X28: =V28*W28 -> 79.5906 | Y28: =V28*W28*U28 -> 955.0872 | Z28: =Z26 -> 12 | AA28: =V28*1.02 -> 81.182412 | AB28: =W28 -> 1 | AC28: =AA28*AB28*Z28 -> 974.18894 | AD28: =AA28*AB28*Z28 -> 974.18894 | AE28: =SUM(AD28,Y28,T28,O28,J28) -> 4988.1661 | AF28: =SUM(AE28:AE28) -> 4988.1661
A29: VTRADGUY | B29: 86050 | C29: GUY | D29: Other Travel Related Costs | E29: =E25 -> 14 | F29: ='Volunteer Travel'!F21 -> 124 | G29: 1 | H29: /trip | I29: =E29*F29*G29 -> 1736 | J29: =F29*G29*E29 -> 1736 | K29: =K25 -> 13 | L29: =F29*1.02 -> 126.48 | M29: 1 | N29: =L29*M29*K29 -> 1644.24 | O29: =L29*M29*K29 -> 1644.24 | P29: =P25 -> 13 | Q29: =L29*1.02 -> 129.0096 | R29: 1 | S29: =Q29*R29*P29 -> 1677.1248 | T29: =Q29*R29*P29 -> 1677.1248 | U29: =U25 -> 12 | V29: =Q29*1.02 -> 131.58979 | W29: 1 | X29: =V29*W29 -> 131.58979 | Y29: =V29*W29*U29 -> 1579.0775 | Z29: =Z25 -> 12 | AA29: =V29*1.02 -> 134.22159 | AB29: 1 | AC29: =AA29*AB29*Z29 -> 1610.6591 | AD29: =AA29*AB29*Z29 -> 1610.6591 | AE29: =SUM(AD29,Y29,T29,O29,J29) -> 8247.1014 | AF29: =SUM(AE29:AE29) -> 8247.1014 | AG29: =AF29*0.7 -> 5772.971 | AH29: =AG29/3 -> 1924.3237 | AI29: =AH29/12 -> 160.3603
D31: Volunteer Travel Related Costs (Paired)
A32: VPAIRGUY | B32: 86030 | C32: GUY | D32: Lodging | E32: ='Volunteer Travel'!C9 -> 2 | F32: ='Volunteer Travel'!G21 -> 72.072 | G32: 6 | H32: /night | I32: =E32*F32*G32 -> 864.864 | J32: =F32*G32*E32 -> 864.864 | K32: ='Volunteer Travel'!D9 -> 3 | L32: =F32*1.02 -> 73.51344 | M32: =G32 -> 6 | N32: =K32*L32*M32 -> 1323.2419 | O32: =K32*L32*M32 -> 1323.2419 | P32: ='Volunteer Travel'!E9 -> 3 | Q32: =L32*1.02 -> 74.983709 | R32: =M32 -> 6 | S32: =P32*Q32*R32 -> 1349.7068 | T32: =P32*Q32*R32 -> 1349.7068 | U32: ='Volunteer Travel'!F9 -> 3 | V32: =Q32*1.02 -> 76.483383 | W32: =R32 -> 6 | X32: =U32*V32*W32 -> 1376.7009 | Y32: =U32*V32*W32 -> 1376.7009 | Z32: ='Volunteer Travel'!G9 -> 2 | AA32: =V32*1.02 -> 78.013051 | AB32: =W32 -> 6 | AC32: =Z32*AA32*AB32 -> 936.15661 | AD32: =Z32*AA32*AB32 -> 936.15661 | AE32: =SUM(AD32,Y32,T32,O32,J32) -> 5850.6702 | AF32: =SUM(AE32:AE32) -> 5850.6702 | AG32: =AF32*0.7 -> 4095.4691 | AH32: =AG32/3 -> 1365.1564 | AI32: =AH32/12 -> 113.76303
A33: VPAIRGUY | B33: 86050 | C33: GUY | D33: Meals and Incidentals | E33: =E32 -> 2 | F33: ='Volunteer Travel'!H21 -> 59.5 | G33: 7 | H33: /day | I33: =E33*F33*G33 -> 833 | J33: =F33*G33*E33 -> 833 | K33: =K32 -> 3 | L33: =F33*1.02 -> 60.69 | M33: =G33 -> 7 | N33: =K33*L33*M33 -> 1274.49 | O33: =K33*L33*M33 -> 1274.49 | P33: =P32 -> 3 | Q33: =L33*1.02 -> 61.9038 | R33: =M33 -> 7 | S33: =P33*Q33*R33 -> 1299.9798 | T33: =P33*Q33*R33 -> 1299.9798 | U33: =U32 -> 3 | V33: =Q33*1.02 -> 63.141876 | W33: =R33 -> 7 | X33: =U33*V33*W33 -> 1325.9794 | Y33: =U33*V33*W33 -> 1325.9794 | Z33: =Z32 -> 2 | AA33: =V33*1.02 -> 64.404714 | AB33: =W33 -> 7 | AC33: =Z33*AA33*AB33 -> 901.66599 | AD33: =Z33*AA33*AB33 -> 901.66599 | AE33: =SUM(AD33,Y33,T33,O33,J33) -> 5635.1152 | AF33: =SUM(AE33:AE33) -> 5635.1152 | AG33: =AF33*0.7 -> 3944.5806 | AH33: =AG33/3 -> 1314.8602 | AI33: =AH33/12 -> 109.57168
A34: VPAIRGUY | B34: 86050 | C34: GUY | D34: Other Travel Related Costs | E34: =E32 -> 2 | F34: ='Volunteer Travel'!I21 -> 30 | G34: 1 | H34: /trip | I34: =E34*F34*G34 -> 60 | J34: =F34*G34*E34 -> 60 | K34: =K32 -> 3 | L34: =F34*1.02 -> 30.6 | M34: =G34 -> 1 | N34: =K34*L34*M34 -> 91.8 | O34: =K34*L34*M34 -> 91.8 | P34: =P32 -> 3 | Q34: =L34*1.02 -> 31.212 | R34: =M34 -> 1 | S34: =P34*Q34*R34 -> 93.636 | T34: =P34*Q34*R34 -> 93.636 | U34: =U32 -> 3 | V34: =Q34*1.02 -> 31.83624 | W34: =R34 -> 1 | X34: =U34*V34*W34 -> 95.50872 | Y34: =U34*V34*W34 -> 95.50872 | Z34: =Z32 -> 2 | AA34: =V34*1.02 -> 32.472965 | AB34: =W34 -> 1 | AC34: =Z34*AA34*AB34 -> 64.94593 | AD34: =Z34*AA34*AB34 -> 64.94593 | AE34: =SUM(AD34,Y34,T34,O34,J34) -> 405.89065 | AF34: =SUM(AE34:AE34) -> 405.89065 | AG34: =AF34*0.7 -> 284.12345 | AH34: =AG34/3 -> 94.707818 | AI34: =AH34/12 -> 7.8923182
AG35: =AF29-AG29 -> 2474.1304 | AH35: =AG35/2 -> 1237.0652 | AI35: =AH35/9 -> 137.45169
D36: Local Travel Related Costs
A37: LOTRVL-GUY | B37: 86030 | C37: GUY | D37: Lodging | E37: 1 | F37: ='Field Travel'!B17 -> 72.072 | G37: ='Volunteer Travel'!K7 -> 138 | H37: /night | I37: =E37*F37*G37 -> 9945.936 | J37: =F37*G37 -> 9945.936 | K37: 1 | L37: =F37*1.02 -> 73.51344 | M37: ='Volunteer Travel'!L7 -> 138 | N37: =L37*M37 -> 10144.855 | O37: =L37*M37 -> 10144.855 | P37: 1 | Q37: =L37*1.02 -> 74.983709 | R37: ='Volunteer Travel'!M7 -> 156 | S37: =Q37*R37 -> 11697.459 | T37: =Q37*R37 -> 11697.459 | U37: 1 | V37: =Q37*1.02 -> 76.483383 | W37: ='Volunteer Travel'!N7 -> 132 | X37: =V37*W37 -> 10095.807 | Y37: =V37*W37 -> 10095.807 | Z37: 1 | AA37: =V37*1.02 -> 78.013051 | AB37: ='Volunteer Travel'!O7 -> 126 | AC37: =AA37*AB37 -> 9829.6444 | AD37: =AA37*AB37 -> 9829.6444 | AE37: =SUM(AD37,Y37,T37,O37,J37) -> 51713.7 | AF37: =SUM(AE37:AE37) -> 51713.7 | AG37: =AF37*0.7 -> 36199.59 | AH37: =AG37/3 -> 12066.53 | AI37: =AH37/12 -> 1005.5442
A38: LOTRVL-GUY | B38: 86050 | C38: GUY | D38: Meals and Incidentals | E38: 1 | F38: ='Field Travel'!C17 -> 59.5 | G38: =G37 -> 138 | H38: /day | I38: =E38*F38*G38 -> 8211 | J38: =F38*G38 -> 8211 | K38: 1 | L38: =F38*1.02 -> 60.69 | M38: =M37 -> 138 | N38: =L38*M38 -> 8375.22 | O38: =L38*M38 -> 8375.22 | P38: 1 | Q38: =L38*1.02 -> 61.9038 | R38: =R37 -> 156 | S38: =Q38*R38 -> 9656.9928 | T38: =Q38*R38 -> 9656.9928 | U38: 1 | V38: =Q38*1.02 -> 63.141876 | W38: =W37 -> 132 | X38: =V38*W38 -> 8334.7276 | Y38: =V38*W38 -> 8334.7276 | Z38: 1 | AA38: =V38*1.02 -> 64.404714 | AB38: =AB37 -> 126 | AC38: =AA38*AB38 -> 8114.9939 | AD38: =AA38*AB38 -> 8114.9939 | AE38: =SUM(AD38,Y38,T38,O38,J38) -> 42692.934 | AF38: =SUM(AE38:AE38) -> 42692.934 | AG38: =AF38*0.7 -> 29885.054 | AH38: =AG38/3 -> 9961.6847 | AI38: =AH38/12 -> 830.14039
A39: LOTRVL-GUY | B39: 86000 | C39: GUY | D39: Local Transportation Costs (fuel) | E39: 1 | F39: ='Field Travel'!D17 -> 65 | G39: =E25+E32+'Field Travel'!U15 -> 37 | H39: /trip | I39: =E39*F39*G39 -> 2405 | J39: =F39*G39 -> 2405 | K39: 1 | L39: =F39*1.02 -> 66.3 | M39: =K25+K32+'Field Travel'!U16 -> 37 | N39: =L39*M39 -> 2453.1 | O39: =L39*M39 -> 2453.1 | P39: 1 | Q39: =L39*1.02 -> 67.626 | R39: =P25+P32+'Field Travel'!U17 -> 46 | S39: =Q39*R39 -> 3110.796 | T39: =Q39*R39 -> 3110.796 | U39: 1 | V39: =Q39*1.02 -> 68.97852 | W39: =U25+U32+'Field Travel'!U18 -> 36 | X39: =V39*W39 -> 2483.2267 | Y39: =V39*W39 -> 2483.2267 | Z39: 1 | AA39: =V39*1.02 -> 70.35809 | AB39: =Z25+Z32+'Field Travel'!U19 -> 35 | AC39: =AA39*AB39 -> 2462.5332 | AD39: =AA39*AB39 -> 2462.5332 | AE39: =SUM(AD39,Y39,T39,O39,J39) -> 12914.656 | AF39: =SUM(AE39:AE39) -> 12914.656 | AG39: =AF39*0.7 -> 9040.2591 | AH39: =AG39/3 -> 3013.4197 | AI39: =AH39/12 -> 251.11831
D41: Equipment | AI41: =AH35/10 -> 123.70652
A42: NONE | B42: NONE | C42: NONE | D42: Vehicles | E42: 0 | F42: 0 | G42: 1 | H42: /year | I42: =E42*F42*G42 -> 0 | J42: =SUM(I42:I42) -> 0 | K42: 1 | M42: 1 | N42: =M42*L42*K42 -> 0 | O42: =SUM(N42:N42) -> 0 | S42: =R42*Q42*P42 -> 0 | T42: =SUM(S42:S42) -> 0 | X42: =W42*V42*U42 -> 0 | Y42: =SUM(X42:X42) -> 0 | AC42: =AB42*AA42*Z42 -> 0 | AD42: =SUM(AC42:AC42) -> 0 | AE42: =I42+N42+S42+X42+AC42 -> 0 | AF42: =SUM(AE42:AE42) -> 0
D43: Subtotal Equipment | I43: =SUM(I41:I42) -> 0 | J43: =SUM(J41:J42) -> 0 | N43: =SUM(N41:N42) -> 0 | O43: =SUM(O41:O42) -> 0 | S43: =SUM(S41:S42) -> 0 | T43: =SUM(T41:T42) -> 0 | X43: =SUM(X41:X42) -> 0 | Y43: =SUM(Y41:Y42) -> 0 | AC43: =SUM(AC41:AC42) -> 0 | AD43: =SUM(AD41:AD42) -> 0 | AE43: =I43+N43+S43+X43+AC43 -> 0 | AF43: =SUM(AE43:AE43) -> 0
D45: Field Office Expenses
A46: MEETGUY | B46: 87010 | C46: GUY | D46: Meetings and Events | E46: 1 | F46: ='FO Expenses'!L19 -> 75 | G46: 11 | H46: /months | I46: =G46*F46*E46 -> 825 | J46: =SUM(I46:I46) -> 825 | K46: 1 | L46: =F46*1.02 -> 76.5 | M46: 12 | N46: =M46*L46*K46 -> 918 | O46: =SUM(N46:N46) -> 918 | P46: 1 | Q46: =L46*1.02 -> 78.03 | R46: 12 | S46: =R46*Q46*P46 -> 936.36 | T46: =SUM(S46:S46) -> 936.36 | U46: 1 | V46: =Q46*1.02 -> 79.5906 | W46: 12 | X46: =W46*V46*U46 -> 955.0872 | Y46: =SUM(X46:X46) -> 955.0872 | Z46: 1 | AA46: =V46*1.02 -> 81.182412 | AB46: 9 | AC46: =AB46*AA46*Z46 -> 730.64171 | AD46: =SUM(AC46:AC46) -> 730.64171 | AE46: =I46+N46+S46+X46+AC46 -> 4365.0889 | AF46: =SUM(AE46:AE46) -> 4365.0889
A47: TRANSGY | B47: 85105 | C47: GUY | D47: Transportation | E47: 1 | F47: ='FO Expenses'!L20 -> 165 | G47: 11 | H47: /months | I47: =G47*F47*E47 -> 1815 | J47: =SUM(I47:I47) -> 1815 | K47: 1 | L47: =F47*1.02 -> 168.3 | M47: 12 | N47: =M47*L47*K47 -> 2019.6 | O47: =SUM(N47:N47) -> 2019.6 | P47: 1 | Q47: =L47*1.02 -> 171.666 | R47: 12 | S47: =R47*Q47*P47 -> 2059.992 | T47: =SUM(S47:S47) -> 2059.992 | U47: 1 | V47: =Q47*1.02 -> 175.09932 | W47: 12 | X47: =W47*V47*U47 -> 2101.1918 | Y47: =SUM(X47:X47) -> 2101.1918 | Z47: 1 | AA47: =V47*1.02 -> 178.60131 | AB47: 9 | AC47: =AB47*AA47*Z47 -> 1607.4118 | AD47: =SUM(AC47:AC47) -> 1607.4118 | AE47: =I47+N47+S47+X47+AC47 -> 9603.1956 | AF47: =SUM(AE47:AE47) -> 9603.1956
A48: BANKGUY | B48: 90900 | C48: GUY | D48: Bank Fees | E48: 1 | F48: ='FO Expenses'!L21 -> 60 | G48: 11 | H48: /months | I48: =G48*F48*E48 -> 660 | J48: =SUM(I48:I48) -> 660 | K48: 1 | L48: =F48*1.02 -> 61.2 | M48: 12 | N48: =M48*L48*K48 -> 734.4 | O48: =SUM(N48:N48) -> 734.4 | P48: 1 | Q48: =L48*1.02 -> 62.424 | R48: 12 | S48: =R48*Q48*P48 -> 749.088 | T48: =SUM(S48:S48) -> 749.088 | U48: 1 | V48: =Q48*1.02 -> 63.67248 | W48: 12 | X48: =W48*V48*U48 -> 764.06976 | Y48: =SUM(X48:X48) -> 764.06976 | Z48: 1 | AA48: =V48*1.02 -> 64.94593 | AB48: 9 | AC48: =AB48*AA48*Z48 -> 584.51337 | AD48: =SUM(AC48:AC48) -> 584.51337 | AE48: =I48+N48+S48+X48+AC48 -> 3492.0711 | AF48: =SUM(AE48:AE48) -> 3492.0711
A49: COMMGUY | B49: 82030 | C49: GUY | D49: Communications | E49: 1 | F49: ='FO Expenses'!L23 -> 100 | G49: 11 | H49: /months | I49: =G49*F49*E49 -> 1100 | J49: =SUM(I49:I49) -> 1100 | K49: 1 | L49: =F49*1.02 -> 102 | M49: 12 | N49: =M49*L49*K49 -> 1224 | O49: =SUM(N49:N49) -> 1224 | P49: 1 | Q49: =L49*1.02 -> 104.04 | R49: 12 | S49: =R49*Q49*P49 -> 1248.48 | T49: =SUM(S49:S49) -> 1248.48 | U49: 1 | V49: =Q49*1.02 -> 106.1208 | W49: 12 | X49: =W49*V49*U49 -> 1273.4496 | Y49: =SUM(X49:X49) -> 1273.4496 | Z49: 1 | AA49: =V49*1.02 -> 108.24322 | AB49: 9 | AC49: =AB49*AA49*Z49 -> 974.18894 | AD49: =SUM(AC49:AC49) -> 974.18894 | AE49: =I49+N49+S49+X49+AC49 -> 5820.1185 | AF49: =SUM(AE49:AE49) -> 5820.1185
A50: RENT&UTGUY | B50: 85180 | C50: GUY | D50: Office Rent & Utilities | E50: 1 | F50: ='FO Expenses'!G14 -> 1025 | G50: 11 | H50: /months | I50: =G50*F50*E50 -> 11275 | J50: =SUM(I50:I50) -> 11275 | K50: 1 | L50: =F50*1.02 -> 1045.5 | M50: 12 | N50: =M50*L50*K50 -> 12546 | O50: =SUM(N50:N50) -> 12546 | P50: 1 | Q50: =L50*1.02 -> 1066.41 | R50: 12 | S50: =R50*Q50*P50 -> 12796.92 | T50: =SUM(S50:S50) -> 12796.92 | U50: 1 | V50: =Q50*1.02 -> 1087.7382 | W50: 12 | X50: =W50*V50*U50 -> 13052.858 | Y50: =SUM(X50:X50) -> 13052.858 | Z50: 1 | AA50: =V50*1.02 -> 1109.493 | AB50: 6 | AC50: =AB50*AA50*Z50 -> 6656.9578 | AD50: =SUM(AC50:AC50) -> 6656.9578 | AE50: =I50+N50+S50+X50+AC50 -> 56327.736 | AF50: =SUM(AE50:AE50) -> 56327.736
A51: PAYROLLGUY | B51: 81030 | C51: GUY | D51: Payroll Company | E51: 1 | F51: ='FO Expenses'!L22 -> 150 | G51: 11 | H51: /months | I51: =G51*F51*E51 -> 1650 | J51: =SUM(I51:I51) -> 1650 | K51: 1 | L51: =F51*1.02 -> 153 | M51: 12 | N51: =M51*L51*K51 -> 1836 | O51: =SUM(N51:N51) -> 1836 | P51: 1 | Q51: =L51*1.02 -> 156.06 | R51: 12 | S51: =R51*Q51*P51 -> 1872.72 | T51: =SUM(S51:S51) -> 1872.72 | U51: 1 | V51: =Q51*1.02 -> 159.1812 | W51: 12 | X51: =W51*V51*U51 -> 1910.1744 | Y51: =SUM(X51:X51) -> 1910.1744 | Z51: 1 | AA51: =V51*1.02 -> 162.36482 | AB51: 9 | AC51: =AB51*AA51*Z51 -> 1461.2834 | AD51: =SUM(AC51:AC51) -> 1461.2834 | AE51: =I51+N51+S51+X51+AC51 -> 8730.1778 | AF51: =SUM(AE51:AE51) -> 8730.1778
D52: Subtotal Office Expenses | I52: =SUM(I46:I51) -> 17325 | J52: =SUM(J46:J51) -> 17325 | N52: =SUM(N46:N51) -> 19278 | O52: =SUM(O46:O51) -> 19278 | S52: =SUM(S46:S51) -> 19663.56 | T52: =SUM(T46:T51) -> 19663.56 | X52: =SUM(X46:X51) -> 20056.831 | Y52: =SUM(Y46:Y51) -> 20056.831 | AC52: =SUM(AC46:AC51) -> 12014.997 | AD52: =SUM(AD46:AD51) -> 12014.997 | AE52: =I52+N52+S52+X52+AC52 -> 88338.388 | AF52: =SUM(AE52:AE52) -> 88338.388
D54: Total | I54: =I52+I15+I18+I43+I13+I29 -> 97764.72 | J54: =J52+J15+J18+J43+J13+J29 -> 97764.72 | N54: =N52+N15+N18+N43+N13+N29 -> 102053.77 | O54: =O52+O15+O18+O43+O13+O29 -> 102053.77 | S54: =S52+S15+S18+S43+S13+S29 -> 104906.17 | T54: =T52+T15+T18+T43+T13+T29 -> 104906.17 | X54: =X52+X15+X18+X43+X13+X29 -> 106260.87 | Y54: =Y52+Y15+Y18+Y43+Y13+Y29 -> 107708.35 | AC54: =AC52+AC15+AC18+AC43+AC13+AC29 -> 80116.62 | AD54: =AD52+AD15+AD18+AD43+AD13+AD29 -> 80116.62 | AE54: =AE52+AE15+AE18+AE43+AE13+AE29 -> 492549.63 | AF54: =AF52+AF15+AF18+AF43+AF13+AF29 -> 492549.63

Sheet Dominican Republic
A1: Entity: | B1: P | D1: Partners of the Americas F2F Caribbean Basin Program Budget
A2: Program-Dept.: | B2: 30100 | D2: USAID NOFO #7200AA23RFA00006
A3: Funder-Grant: | B3: USAID650
A4: Budget (Activity) Code | B4: Account Code | C4: Country Code | D4: Dominican Republic | I4: Year 1 | K4: Year 2 | P4: Year 3 | U4: Year 4 | Z4: Year 5 | AE4: Total | AF4: Grand
E5: Units | F5: Cost | G5: Duration | H5: Type | I5: USAID | J5: Total | K5: Units | L5: Cost | M5: Duration | N5: USAID | O5: Total | P5: Units | Q5: Cost | R5: Duration | S5: USAID | T5: Total | U5: Units | V5: Cost | W5: Duration | X5: USAID | Y5: Total | Z5: Units | AA5: Cost | AB5: Duration | AC5: USAID | AD5: Total | AE5: USAID | AF5: Total
D7: Key Personnel
A8: PERSNL-DOM | B8: 70000 | C8: DOM | D8: Country Director* | E8: 1 | F8: 4000 | G8: 12 | H8: /months | I8: =G8*F8*E8 -> 48000 | J8: =SUM(I8:I8) -> 48000 | K8: 1 | L8: =F8*1.03 -> 4120 | M8: 12 | N8: =M8*L8*K8 -> 49440 | O8: =SUM(N8:N8) -> 49440 | P8: 1 | Q8: =L8*1.03 -> 4243.6 | R8: 12 | S8: =R8*Q8*P8 -> 50923.2 | T8: =SUM(S8:S8) -> 50923.2 | U8: 1 | V8: =Q8*1.03 -> 4370.908 | W8: 12 | X8: =W8*V8*U8 -> 52450.896 | Y8: =SUM(X8:X8) -> 52450.896 | Z8: 1 | AA8: =V8*1.03 -> 4502.0352 | AB8: 9 | AC8: =AB8*AA8*Z8 -> 40518.317 | AD8: =SUM(AC8:AC8) -> 40518.317 | AE8: =I8+N8+S8+X8+AC8 -> 241332.41 | AF8: =SUM(AE8:AE8) -> 241332.41
D10: Other Personnel
A11: PERSNL-DOM | B11: 70000 | C11: DOM | D11: Field Officer 1 | E11: 1 | F11: 1400 | G11: 10 | H11: /months | I11: =G11*F11*E11 -> 14000 | J11: =SUM(I11:I11) -> 14000 | K11: =E11 -> 1 | L11: =F11*1.03 -> 1442 | M11: 12 | N11: =M11*L11*K11 -> 17304 | O11: =SUM(N11:N11) -> 17304 | P11: =E11 -> 1 | Q11: =L11*1.03 -> 1485.26 | R11: 12 | S11: =R11*Q11*P11 -> 17823.12 | T11: =SUM(S11:S11) -> 17823.12 | U11: =E11 -> 1 | V11: =Q11*1.03 -> 1529.8178 | W11: 12 | X11: =W11*V11*U11 -> 18357.814 | Y11: =SUM(X11:X11) -> 18357.814 | Z11: =E11 -> 1 | AA11: =V11*1.03 -> 1575.7123 | AB11: 9 | AC11: =AB11*AA11*Z11 -> 14181.411 | AD11: =SUM(AC11:AC11) -> 14181.411 | AE11: =I11+N11+S11+X11+AC11 -> 81666.345 | AF11: =SUM(AE11:AE11) -> 81666.345 | AG11: =K11+P11+U11+Z11+AE11 -> 81670.345 | AH11: =SUM(AG11:AG11) -> 81670.345 | AI11: =M11+R11+W11+AB11+AG11 -> 81715.345
A12: PERSNL-DOM | B12: 70000 | C12: DOM | D12: Field Officer 2 | E12: 1 | F12: 1400 | G12: 6 | H12: /months | I12: =G12*F12*E12 -> 8400 | J12: =SUM(I12:I12) -> 8400 | K12: =E12 -> 1 | L12: =F12*1.03 -> 1442 | M12: 12 | N12: =M12*L12*K12 -> 17304 | O12: =SUM(N12:N12) -> 17304 | P12: =E12 -> 1 | Q12: =L12*1.03 -> 1485.26 | R12: 12 | S12: =R12*Q12*P12 -> 17823.12 | T12: =SUM(S12:S12) -> 17823.12 | U12: =E12 -> 1 | V12: =Q12*1.03 -> 1529.8178 | W12: 12 | X12: =W12*V12*U12 -> 18357.814 | Y12: =SUM(X12:X12) -> 18357.814 | Z12: =E12 -> 1 | AA12: =V12*1.03 -> 1575.7123 | AB12: 6 | AC12: =AB12*AA12*Z12 -> 9454.274 | AD12: =SUM(AC12:AC12) -> 9454.274 | AE12: =I12+N12+S12+X12+AC12 -> 71339.208 | AF12: =SUM(AE12:AE12) -> 71339.208 | AG12: =K12+P12+U12+Z12+AE12 -> 71343.208 | AH12: =SUM(AG12:AG12) -> 71343.208 | AI12: =M12+R12+W12+AB12+AG12 -> 71385.208
A13: PERSNL-DOM | B13: 70000 | C13: DOM | D13: Administrative Assistant | E13: 1 | F13: 1300 | G13: 11 | H13: /months | I13: =G13*F13*E13 -> 14300 | J13: =SUM(I13:I13) -> 14300 | K13: 1 | L13: =F13*1.03 -> 1339 | M13: 12 | N13: =M13*L13*K13 -> 16068 | O13: =SUM(N13:N13) -> 16068 | P13: 1 | Q13: =L13*1.03 -> 1379.17 | R13: 12 | S13: =R13*Q13*P13 -> 16550.04 | T13: =SUM(S13:S13) -> 16550.04 | U13: 1 | V13: =Q13*1.03 -> 1420.5451 | W13: 12 | X13: =W13*V13*U13 -> 17046.541 | Y13: =SUM(X13:X13) -> 17046.541 | Z13: 1 | AA13: =V13*1.03 -> 1463.1615 | AB13: 9 | AC13: =AB13*AA13*Z13 -> 13168.453 | AD13: =SUM(AC13:AC13) -> 13168.453 | AE13: =I13+N13+S13+X13+AC13 -> 77133.034 | AF13: =SUM(AE13:AE13) -> 77133.034 | AG13: =K13+P13+U13+Z13+AE13 -> 77137.034 | AH13: =SUM(AG13:AG13) -> 77137.034 | AI13: =M13+R13+W13+AB13+AG13 -> 77182.034
D14: Subtotal Field Salaries | I14: =SUM(I8:I13) -> 84700 | J14: =SUM(J8:J13) -> 84700 | N14: =SUM(N8:N13) -> 100116 | O14: =SUM(O8:O13) -> 100116 | S14: =SUM(S8:S13) -> 103119.48 | T14: =SUM(T8:T13) -> 103119.48 | X14: =SUM(X8:X13) -> 106213.06 | Y14: =SUM(Y8:Y13) -> 106213.06 | AC14: =SUM(AC8:AC13) -> 77322.455 | AD14: =SUM(AD8:AD13) -> 77322.455 | AE14: =I14+N14+S14+X14+AC14 -> 471471 | AF14: =SUM(AE14:AE14) -> 471471
A16: FRINGE-DOM | B16: 70015 | C16: DOM | D16: Benefits | E16: 0.317 | F16: =I14 -> 84700 | I16: =F16*E16 -> 26849.9 | J16: =SUM(I16:I16) -> 26849.9 | L16: =N14 -> 100116 | N16: =L16*E16 -> 31736.772 | O16: =SUM(N16:N16) -> 31736.772 | Q16: =S14 -> 103119.48 | S16: =Q16*E16 -> 32688.875 | T16: =SUM(S16:S16) -> 32688.875 | V16: =X14 -> 106213.06 | X16: =V16*E16 -> 33669.541 | Y16: =SUM(X16:X16) -> 33669.541 | AA16: =AC14 -> 77322.455 | AC16: =AA16*E16 -> 24511.218 | AD16: =SUM(AC16:AC16) -> 24511.218 | AE16: =I16+N16+S16+X16+AC16 -> 149456.31 | AF16: =SUM(AE16:AE16) -> 149456.31
D18: Supplies
A19: SUPPLY-DOM | B19: 82401 | C19: DOM | D19: Laptops | E19: ='FO Expenses'!C5 -> 4 | F19: ='FO Expenses'!B5 -> 1100 | G19: 1 | H19: /year | I19: =E19*F19*G19 -> 4400 | J19: =SUM(I19:I19) -> 4400 | K19: 0 | L19: =F19*1.02 -> 1122 | M19: 1 | N19: =M19*L19*K19 -> 0 | O19: =SUM(N19:N19) -> 0 | P19: 0 | Q19: =L19*1.02 -> 1144.44 | R19: 1 | S19: =R19*Q19*P19 -> 0 | T19: =SUM(S19:S19) -> 0 | U19: 0 | V19: =Q19*1.02 -> 1167.3288 | W19: 1 | X19: =W19*V19*U19 -> 0 | Y19: =SUM(X19:X19) -> 0 | Z19: 0 | AA19: =V19*1.02 -> 1190.6754 | AB19: 1 | AC19: =AB19*AA19*Z19 -> 0 | AD19: =SUM(AC19:AC19) -> 0 | AE19: =I19+N19+S19+X19+AC19 -> 4400 | AF19: =SUM(AE19:AE19) -> 4400
A20: SUPPLY-DOM | B20: 82401 | C20: DOM | D20: Tablet | E20: ='FO Expenses'!C6 -> 2 | F20: ='FO Expenses'!B6 -> 160 | G20: 1 | H20: /year | I20: =E20*F20*G20 -> 320 | J20: =SUM(I20:I20) -> 320 | K20: 0 | L20: =F20*1.02 -> 163.2 | M20: 1 | N20: =M20*L20*K20 -> 0 | O20: =SUM(N20:N20) -> 0 | P20: 0 | Q20: =L20*1.02 -> 166.464 | R20: 1 | S20: =R20*Q20*P20 -> 0 | T20: =SUM(S20:S20) -> 0 | U20: 0 | V20: =Q20*1.02 -> 169.79328 | W20: 1 | X20: =W20*V20*U20 -> 0 | Y20: =SUM(X20:X20) -> 0 | Z20: 0 | AA20: =V20*1.02 -> 173.18915 | AB20: 1 | AC20: =AB20*AA20*Z20 -> 0 | AD20: =SUM(AC20:AC20) -> 0 | AE20: =I20+N20+S20+X20+AC20 -> 320 | AF20: =SUM(AE20:AE20) -> 320
A21: SUPPLY-DOM | B21: 82401 | C21: DOM | D21: Projector | E21: ='FO Expenses'!C7 -> 1 | F21: ='FO Expenses'!B7 -> 650 | G21: 1 | H21: /year | I21: =E21*F21*G21 -> 650 | J21: =SUM(I21:I21) -> 650 | K21: 0 | L21: =F21*1.02 -> 663 | M21: 1 | N21: =M21*L21*K21 -> 0 | O21: =SUM(N21:N21) -> 0 | P21: 0 | Q21: =L21*1.02 -> 676.26 | R21: 1 | S21: =R21*Q21*P21 -> 0 | T21: =SUM(S21:S21) -> 0 | U21: 0 | V21: =Q21*1.02 -> 689.7852 | W21: 1 | X21: =W21*V21*U21 -> 0 | Y21: =SUM(X21:X21) -> 0 | Z21: 0 | AA21: =V21*1.02 -> 703.5809 | AB21: 1 | AC21: =AB21*AA21*Z21 -> 0 | AD21: =SUM(AC21:AC21) -> 0 | AE21: =I21+N21+S21+X21+AC21 -> 650 | AF21: =SUM(AE21:AE21) -> 650
A22: SUPPLY-DOM | B22: 82401 | C22: DOM | D22: Miscellaneous Supplies | E22: ='FO Expenses'!C8 -> 1 | F22: ='FO Expenses'!B8 -> 530 | G22: 1 | H22: /year | I22: =E22*F22*G22 -> 530 | J22: =SUM(I22:I22) -> 530 | K22: 1 | L22: =F22*1.02 -> 540.6 | M22: 1 | N22: =M22*L22*K22 -> 540.6 | O22: =SUM(N22:N22) -> 540.6 | P22: 1 | Q22: =L22*1.02 -> 551.412 | R22: 1 | S22: =R22*Q22*P22 -> 551.412 | T22: =SUM(S22:S22) -> 551.412 | U22: 1 | V22: =Q22*1.02 -> 562.44024 | W22: 1 | X22: =W22*V22*U22 -> 562.44024 | Y22: =SUM(X22:X22) -> 562.44024 | Z22: 1 | AA22: =V22*1.02 -> 573.68904 | AB22: 1 | AC22: =AB22*AA22*Z22 -> 573.68904 | AD22: =SUM(AC22:AC22) -> 573.68904 | AE22: =I22+N22+S22+X22+AC22 -> 2758.1413 | AF22: =SUM(AE22:AE22) -> 2758.1413
D23: Subtotal Supplies | I23: =SUM(I19:I22) -> 5900 | J23: =SUM(J19:J22) -> 5900 | N23: =SUM(N19:N22) -> 540.6 | O23: =SUM(O19:O22) -> 540.6 | S23: =SUM(S19:S22) -> 551.412 | T23: =SUM(T19:T22) -> 551.412 | X23: =SUM(X19:X22) -> 562.44024 | Y23: =SUM(Y19:Y22) -> 562.44024 | AC23: =SUM(AC19:AC22) -> 573.68904 | AD23: =SUM(AD19:AD22) -> 573.68904 | AE23: =I23+N23+S23+X23+AC23 -> 8128.1413 | AF23: =SUM(AE23:AE23) -> 8128.1413
D25: Volunteer Travel Related Costs (Traditional)
A26: VFLYJDOM | B26: 86040 | C26: DOM | D26: Roundtrip Airfare | E26: ='Volunteer Travel'!C6 -> 16 | F26: ='Volunteer Travel'!B20 -> 750 | G26: 1 | H26: /trip | I26: =E26*F26*G26 -> 12000 | J26: =F26*G26*E26 -> 12000 | K26: ='Volunteer Travel'!D6 -> 22 | L26: =F26*1.02 -> 765 | M26: =G26 -> 1 | N26: =L26*M26*K26 -> 16830 | O26: =L26*M26*K26 -> 16830 | P26: ='Volunteer Travel'!E6 -> 22 | Q26: =L26*1.02 -> 780.3 | R26: =M26 -> 1 | S26: =Q26*R26*P26 -> 17166.6 | T26: =Q26*R26*P26 -> 17166.6 | U26: ='Volunteer Travel'!F6 -> 22 | V26: =Q26*1.02 -> 795.906 | W26: =R26 -> 1 | X26: =V26*W26*U26 -> 17509.932 | Y26: =V26*W26*U26 -> 17509.932 | Z26: ='Volunteer Travel'!G6 -> 16 | AA26: =V26*1.02 -> 811.82412 | AB26: =W26 -> 1 | AC26: =AA26*AB26*Z26 -> 12989.186 | AD26: =AA26*AB26*Z26 -> 12989.186 | AE26: =SUM(AD26,Y26,T26,O26,J26) -> 76495.718 | AF26: =SUM(AE26:AE26) -> 76495.718 | AG26: =AF26*0.7 -> 53547.003 | AH26: =AG26/3 -> 17849.001 | AI26: =AH26/12 -> 1487.4167
A27: VTRADDOM | B27: 86030 | C27: DOM | D27: Lodging | E27: =E26 -> 16 | F27: ='Volunteer Travel'!C20 -> 92.925 | G27: 14 | H27: /night | I27: =E27*F27*G27 -> 20815.2 | J27: =F27*G27*E27 -> 20815.2 | K27: =K26 -> 22 | L27: =F27*1.02 -> 94.7835 | M27: =G27 -> 14 | N27: =L27*M27*K27 -> 29193.318 | O27: =L27*M27*K27 -> 29193.318 | P27: =P26 -> 22 | Q27: =L27*1.02 -> 96.67917 | R27: =M27 -> 14 | S27: =Q27*R27*P27 -> 29777.184 | T27: =Q27*R27*P27 -> 29777.184 | U27: =U26 -> 22 | V27: =Q27*1.02 -> 98.612753 | W27: =R27 -> 14 | X27: =V27*W27*U27 -> 30372.728 | Y27: =V27*W27*U27 -> 30372.728 | Z27: =Z26 -> 16 | AA27: =V27*1.02 -> 100.58501 | AB27: =W27 -> 14 | AC27: =AA27*AB27*Z27 -> 22531.042 | AD27: =AA27*AB27*Z27 -> 22531.042 | AE27: =SUM(AD27,Y27,T27,O27,J27) -> 132689.47 | AF27: =SUM(AE27:AE27) -> 132689.47 | AG27: =AF27*0.7 -> 92882.631 | AH27: =AG27/3 -> 30960.877 | AI27: =AH27/12 -> 2580.0731
A28: VTRADDOM | B28: 86050 | C28: DOM | D28: Meals and Incidentals | E28: =E26 -> 16 | F28: ='Volunteer Travel'!D20 -> 55.75 | G28: 15 | H28: /day | I28: =E28*F28*G28 -> 13380 | J28: =F28*G28*E28 -> 13380 | K28: =K26 -> 22 | L28: =F28*1.02 -> 56.865 | M28: =G28 -> 15 | N28: =L28*M28*K28 -> 18765.45 | O28: =L28*M28*K28 -> 18765.45 | P28: =P26 -> 22 | Q28: =L28*1.02 -> 58.0023 | R28: =M28 -> 15 | S28: =Q28*R28*P28 -> 19140.759 | T28: =Q28*R28*P28 -> 19140.759 | U28: =U26 -> 22 | V28: =Q28*1.02 -> 59.162346 | W28: =R28 -> 15 | X28: =V28*W28*U28 -> 19523.574 | Y28: =V28*W28*U28 -> 19523.574 | Z28: =Z26 -> 16 | AA28: =V28*1.02 -> 60.345593 | AB28: =W28 -> 15 | AC28: =AA28*AB28*Z28 -> 14482.942 | AD28: =AA28*AB28*Z28 -> 14482.942 | AE28: =SUM(AD28,Y28,T28,O28,J28) -> 85292.725 | AF28: =SUM(AE28:AE28) -> 85292.725 | AG28: =AF28*0.7 -> 59704.908 | AH28: =AG28/3 -> 19901.636 | AI28: =AH28/12 -> 1658.4697
A29: VTRADDOM | B29: 86050 | C29: DOM | D29: Health Related | E29: =E26 -> 16 | F29: ='Volunteer Travel'!E20 -> 75 | G29: 1 | H29: /trip | I29: =E29*F29*G29 -> 1200 | J29: =F29*G29*E29 -> 1200 | K29: =K27 -> 22 | L29: =F29*1.02 -> 76.5 | M29: =G29 -> 1 | N29: =L29*M29*K29 -> 1683 | O29: =L29*M29*K29 -> 1683 | P29: =P27 -> 22 | Q29: =L29*1.02 -> 78.03 | R29: =M29 -> 1 | S29: =Q29*R29*P29 -> 1716.66 | T29: =Q29*R29*P29 -> 1716.66 | U29: =U27 -> 22 | V29: =Q29*1.02 -> 79.5906 | W29: =R29 -> 1 | X29: =V29*W29*U29 -> 1750.9932 | Y29: =V29*W29*U29 -> 1750.9932 | Z29: =Z27 -> 16 | AA29: =V29*1.02 -> 81.182412 | AB29: =W29 -> 1 | AC29: =AA29*AB29*Z29 -> 1298.9186 | AD29: =AA29*AB29*Z29 -> 1298.9186 | AE29: =SUM(AD29,Y29,T29,O29,J29) -> 7649.5718 | AF29: =SUM(AE29:AE29) -> 7649.5718
A30: VTRADDOM | B30: 86050 | C30: DOM | D30: Other Travel Related Costs | E30: =E26 -> 16 | F30: ='Volunteer Travel'!F20 -> 124 | G30: 1 | H30: /trip | I30: =E30*F30*G30 -> 1984 | J30: =F30*G30*E30 -> 1984 | K30: =K26 -> 22 | L30: =F30*1.02 -> 126.48 | M30: 1 | N30: =L30*M30*K30 -> 2782.56 | O30: =L30*M30*K30 -> 2782.56 | P30: =P26 -> 22 | Q30: =L30*1.02 -> 129.0096 | R30: 1 | S30: =Q30*R30*P30 -> 2838.2112 | T30: =Q30*R30*P30 -> 2838.2112 | U30: =U26 -> 22 | V30: =Q30*1.02 -> 131.58979 | W30: 1 | X30: =V30*W30*U30 -> 2894.9754 | Y30: =V30*W30*U30 -> 2894.9754 | Z30: =Z26 -> 16 | AA30: =V30*1.02 -> 134.22159 | AB30: 1 | AC30: =AA30*AB30*Z30 -> 2147.5454 | AD30: =AA30*AB30*Z30 -> 2147.5454 | AE30: =SUM(AD30,Y30,T30,O30,J30) -> 12647.292 | AF30: =SUM(AE30:AE30) -> 12647.292 | AG30: =AF30*0.7 -> 8853.1044 | AH30: =AG30/3 -> 2951.0348 | AI30: =AH30/12 -> 245.91957
D32: Volunteer Travel Related Costs (Paired)
A33: VPAIRDOM | B33: 86030 | C33: DOM | D33: Lodging | E33: ='Volunteer Travel'!C7 -> 2 | F33: ='Volunteer Travel'!G20 -> 65.0475 | G33: 6 | H33: /night | I33: =E33*F33*G33 -> 780.57 | J33: =E33*F33*G33 -> 780.57 | K33: ='Volunteer Travel'!E7 -> 1 | L33: =F33*1.02 -> 66.34845 | M33: =G33 -> 6 | N33: =K33*L33*M33 -> 398.0907 | O33: =K33*L33*M33 -> 398.0907 | P33: ='Volunteer Travel'!E7 -> 1 | Q33: =L33*1.02 -> 67.675419 | R33: =M33 -> 6 | S33: =P33*Q33*R33 -> 406.05251 | T33: =P33*Q33*R33 -> 406.05251 | U33: ='Volunteer Travel'!F7 -> 1 | V33: =Q33*1.02 -> 69.028927 | W33: =R33 -> 6 | X33: =U33*V33*W33 -> 414.17356 | Y33: =U33*V33*W33 -> 414.17356 | Z33: ='Volunteer Travel'!G7 -> 1 | AA33: =V33*1.02 -> 70.409506 | AB33: =W33 -> 6 | AC33: =Z33*AA33*AB33 -> 422.45704 | AD33: =Z33*AA33*AB33 -> 422.45704 | AE33: =SUM(AD33,Y33,T33,O33,J33) -> 2421.3438 | AF33: =SUM(AE33:AE33) -> 2421.3438 | AG33: =AF33*0.7 -> 1694.9407 | AH33: =AG33/3 -> 564.98022 | AI33: =AH33/12 -> 47.081685
A34: VPAIRDOM | B34: 86050 | C34: DOM | D34: Meals and Incidentals | E34: =E33 -> 2 | F34: ='Volunteer Travel'!H20 -> 55.75 | G34: 7 | H34: /day | I34: =E34*F34*G34 -> 780.5 | J34: =E34*F34*G34 -> 780.5 | K34: =K33 -> 1 | L34: =F34*1.02 -> 56.865 | M34: =G34 -> 7 | N34: =K34*L34*M34 -> 398.055 | O34: =K34*L34*M34 -> 398.055 | P34: =P33 -> 1 | Q34: =L34*1.02 -> 58.0023 | R34: =M34 -> 7 | S34: =P34*Q34*R34 -> 406.0161 | T34: =P34*Q34*R34 -> 406.0161 | U34: =U33 -> 1 | V34: =Q34*1.02 -> 59.162346 | W34: =R34 -> 7 | X34: =U34*V34*W34 -> 414.13642 | Y34: =U34*V34*W34 -> 414.13642 | Z34: =Z33 -> 1 | AA34: =V34*1.02 -> 60.345593 | AB34: =W34 -> 7 | AC34: =Z34*AA34*AB34 -> 422.41915 | AD34: =Z34*AA34*AB34 -> 422.41915 | AE34: =SUM(AD34,Y34,T34,O34,J34) -> 2421.1267 | AF34: =SUM(AE34:AE34) -> 2421.1267 | AG34: =AF34*0.7 -> 1694.7887 | AH34: =AG34/3 -> 564.92956 | AI34: =AH34/12 -> 47.077463
A35: VPAIRDOM | B35: 86050 | C35: DOM | D35: Other Travel Related Costs | E35: =E33 -> 2 | F35: ='Volunteer Travel'!I20 -> 30 | G35: 1 | H35: /trip | I35: =E35*F35*G35 -> 60 | J35: =E35*F35*G35 -> 60 | K35: =K33 -> 1 | L35: =F35*1.02 -> 30.6 | M35: =G35 -> 1 | N35: =K35*L35*M35 -> 30.6 | O35: =K35*L35*M35 -> 30.6 | P35: =P33 -> 1 | Q35: =L35*1.02 -> 31.212 | R35: =M35 -> 1 | S35: =P35*Q35*R35 -> 31.212 | T35: =P35*Q35*R35 -> 31.212 | U35: =U33 -> 1 | V35: =Q35*1.02 -> 31.83624 | W35: =R35 -> 1 | X35: =U35*V35*W35 -> 31.83624 | Y35: =U35*V35*W35 -> 31.83624 | Z35: =Z33 -> 1 | AA35: =V35*1.02 -> 32.472965 | AB35: =W35 -> 1 | AC35: =Z35*AA35*AB35 -> 32.472965 | AD35: =Z35*AA35*AB35 -> 32.472965 | AE35: =SUM(AD35,Y35,T35,O35,J35) -> 186.1212 | AF35: =SUM(AE35:AE35) -> 186.1212 | AG35: =AF35*0.7 -> 130.28484 | AH35: =AG35/3 -> 43.428281 | AI35: =AH35/12 -> 3.6190234
AG36: =AF30-AG30 -> 3794.1876 | AH36: =AG36/2 -> 1897.0938 | AI36: =AH36/9 -> 210.7882
D37: Local Travel Related Costs
A38: LOTRVL-DOM | B38: 86030 | C38: DOM | D38: Lodging | E38: 1 | F38: ='Field Travel'!B16 -> 65.0475 | G38: ='Volunteer Travel'!K6 -> 150 | H38: /night | I38: =E38*F38*G38 -> 9757.125 | J38: =F38*G38 -> 9757.125 | K38: 1 | L38: =F38*1.02 -> 66.34845 | M38: ='Volunteer Travel'!L6 -> 180 | N38: =L38*M38 -> 11942.721 | O38: =L38*M38 -> 11942.721 | P38: 1 | Q38: =L38*1.02 -> 67.675419 | R38: ='Volunteer Travel'!M6 -> 198 | S38: =Q38*R38 -> 13399.733 | T38: =Q38*R38 -> 13399.733 | U38: 1 | V38: =Q38*1.02 -> 69.028927 | W38: ='Volunteer Travel'!N6 -> 180 | X38: =V38*W38 -> 12425.207 | Y38: =V38*W38 -> 12425.207 | Z38: 1 | AA38: =V38*1.02 -> 70.409506 | AB38: ='Volunteer Travel'!O6 -> 144 | AC38: =AA38*AB38 -> 10138.969 | AD38: =AA38*AB38 -> 10138.969 | AE38: =SUM(AD38,Y38,T38,O38,J38) -> 57663.755 | AF38: =SUM(AE38:AE38) -> 57663.755 | AG38: =AF38*0.7 -> 40364.628 | AH38: =AG38/3 -> 13454.876 | AI38: =AH38/12 -> 1121.2397
A39: LOTRVL-DOM | B39: 86050 | C39: DOM | D39: Meals and Incidentals | E39: 1 | F39: ='Field Travel'!C16 -> 55.75 | G39: =G38 -> 150 | H39: /day | I39: =E39*F39*G39 -> 8362.5 | J39: =F39*G39 -> 8362.5 | K39: 1 | L39: =F39*1.02 -> 56.865 | M39: =M38 -> 180 | N39: =L39*M39 -> 10235.7 | O39: =L39*M39 -> 10235.7 | P39: 1 | Q39: =L39*1.02 -> 58.0023 | R39: =R38 -> 198 | S39: =Q39*R39 -> 11484.455 | T39: =Q39*R39 -> 11484.455 | U39: 1 | V39: =Q39*1.02 -> 59.162346 | W39: =W38 -> 180 | X39: =V39*W39 -> 10649.222 | Y39: =V39*W39 -> 10649.222 | Z39: 1 | AA39: =V39*1.02 -> 60.345593 | AB39: =AB38 -> 144 | AC39: =AA39*AB39 -> 8689.7654 | AD39: =AA39*AB39 -> 8689.7654 | AE39: =SUM(AD39,Y39,T39,O39,J39) -> 49421.643 | AF39: =SUM(AE39:AE39) -> 49421.643 | AG39: =AF39*0.7 -> 34595.15 | AH39: =AG39/3 -> 11531.717 | AI39: =AH39/12 -> 960.97639
A40: LOTRVL-DOM | B40: 86000 | C40: DOM | D40: Local Transportation Costs (fuel) | E40: 1 | F40: ='Field Travel'!D16 -> 67 | G40: =E26+E33+'Field Travel'!L24 -> 39 | H40: /trip | I40: =E40*F40*G40 -> 2613 | J40: =F40*G40 -> 2613 | K40: 1 | L40: =F40*1.02 -> 68.34 | M40: =K26+K33+'Field Travel'!L25 -> 44 | N40: =L40*M40 -> 3006.96 | O40: =L40*M40 -> 3006.96 | P40: 1 | Q40: =L40*1.02 -> 69.7068 | R40: =P26+P33+'Field Travel'!L26 -> 53 | S40: =Q40*R40 -> 3694.4604 | T40: =Q40*R40 -> 3694.4604 | U40: 1 | V40: =Q40*1.02 -> 71.100936 | W40: =U26+U33+'Field Travel'!L27 -> 44 | X40: =V40*W40 -> 3128.4412 | Y40: =V40*W40 -> 3128.4412 | Z40: 1 | AA40: =V40*1.02 -> 72.522955 | AB40: =Z26+Z33+'Field Travel'!L28 -> 38 | AC40: =AA40*AB40 -> 2755.8723 | AD40: =AA40*AB40 -> 2755.8723 | AE40: =SUM(AD40,Y40,T40,O40,J40) -> 15198.734 | AF40: =SUM(AE40:AE40) -> 15198.734 | AG40: =AF40*0.7 -> 10639.114 | AH40: =AG40/3 -> 3546.3712 | AI40: =AH40/12 -> 295.53094
D42: Equipment | AI42: =AH36/10 -> 189.70938
A43: EQUIPDOM | B43: 85200 | C43: DOM | D43: Vehicles | E43: 1 | F43: 43000 | G43: 1 | H43: /year | I43: =E43*F43*G43 -> 43000 | J43: =SUM(I43:I43) -> 43000 | N43: =M43*L43*K43 -> 0 | O43: =SUM(N43:N43) -> 0 | S43: =R43*Q43*P43 -> 0 | T43: =SUM(S43:S43) -> 0 | X43: =W43*V43*U43 -> 0 | Y43: =SUM(X43:X43) -> 0 | AC43: =AB43*AA43*Z43 -> 0 | AD43: =SUM(AC43:AC43) -> 0 | AE43: =I43+N43+S43+X43+AC43 -> 43000 | AF43: =SUM(AE43:AE43) -> 43000
D44: Subtotal Equipment | I44: =SUM(I42:I43) -> 43000 | J44: =SUM(J42:J43) -> 43000 | N44: =SUM(N42:N43) -> 0 | O44: =SUM(O42:O43) -> 0 | S44: =SUM(S42:S43) -> 0 | T44: =SUM(T42:T43) -> 0 | X44: =SUM(X42:X43) -> 0 | Y44: =SUM(Y42:Y43) -> 0 | AC44: =SUM(AC42:AC43) -> 0 | AD44: =SUM(AD42:AD43) -> 0 | AE44: =I44+N44+S44+X44+AC44 -> 43000 | AF44: =SUM(AE44:AE44) -> 43000
D46: Field Office Expenses
A47: MEETDOM | B47: 87010 | C47: DOM | D47: Meetings and Events | E47: 1 | F47: ='FO Expenses'!L5 -> 65 | G47: 11 | H47: /months | I47: =G47*F47*E47 -> 715 | J47: =SUM(I47:I47) -> 715 | K47: 1 | L47: =F47*1.02 -> 66.3 | M47: 12 | N47: =M47*L47*K47 -> 795.6 | O47: =SUM(N47:N47) -> 795.6 | P47: 1 | Q47: =L47*1.02 -> 67.626 | R47: 12 | S47: =R47*Q47*P47 -> 811.512 | T47: =SUM(S47:S47) -> 811.512 | U47: 1 | V47: =Q47*1.02 -> 68.97852 | W47: 12 | X47: =W47*V47*U47 -> 827.74224 | Y47: =SUM(X47:X47) -> 827.74224 | Z47: 1 | AA47: =V47*1.02 -> 70.35809 | AB47: 9 | AC47: =AB47*AA47*Z47 -> 633.22281 | AD47: =SUM(AC47:AC47) -> 633.22281 | AE47: =I47+N47+S47+X47+AC47 -> 3783.0771 | AF47: =SUM(AE47:AE47) -> 3783.0771
A48: TRANSDOM | B48: 85105 | C48: DOM | D48: Transportation | E48: 1 | F48: ='FO Expenses'!L6 -> 167 | G48: 11 | H48: /months | I48: =G48*F48*E48 -> 1837 | J48: =SUM(I48:I48) -> 1837 | K48: 1 | L48: =F48*1.02 -> 170.34 | M48: 12 | N48: =M48*L48*K48 -> 2044.08 | O48: =SUM(N48:N48) -> 2044.08 | P48: 1 | Q48: =L48*1.02 -> 173.7468 | R48: 12 | S48: =R48*Q48*P48 -> 2084.9616 | T48: =SUM(S48:S48) -> 2084.9616 | U48: 1 | V48: =Q48*1.02 -> 177.22174 | W48: 12 | X48: =W48*V48*U48 -> 2126.6608 | Y48: =SUM(X48:X48) -> 2126.6608 | Z48: 1 | AA48: =V48*1.02 -> 180.76617 | AB48: 9 | AC48: =AB48*AA48*Z48 -> 1626.8955 | AD48: =SUM(AC48:AC48) -> 1626.8955 | AE48: =I48+N48+S48+X48+AC48 -> 9719.598 | AF48: =SUM(AE48:AE48) -> 9719.598
A49: BANKDOM | B49: 90900 | C49: DOM | D49: Bank Fees | E49: 1 | F49: ='FO Expenses'!L7 -> 71 | G49: 11 | H49: /months | I49: =G49*F49*E49 -> 781 | J49: =SUM(I49:I49) -> 781 | K49: 1 | L49: =F49*1.02 -> 72.42 | M49: 12 | N49: =M49*L49*K49 -> 869.04 | O49: =SUM(N49:N49) -> 869.04 | P49: 1 | Q49: =L49*1.02 -> 73.8684 | R49: 12 | S49: =R49*Q49*P49 -> 886.4208 | T49: =SUM(S49:S49) -> 886.4208 | U49: 1 | V49: =Q49*1.02 -> 75.345768 | W49: 12 | X49: =W49*V49*U49 -> 904.14922 | Y49: =SUM(X49:X49) -> 904.14922 | Z49: 1 | AA49: =V49*1.02 -> 76.852683 | AB49: 9 | AC49: =AB49*AA49*Z49 -> 691.67415 | AD49: =SUM(AC49:AC49) -> 691.67415 | AE49: =I49+N49+S49+X49+AC49 -> 4132.2842 | AF49: =SUM(AE49:AE49) -> 4132.2842
A50: COMMDOM | B50: 82030 | C50: DOM | D50: Communications | E50: 1 | F50: ='FO Expenses'!L9 -> 100 | G50: 11 | H50: /months | I50: =G50*F50*E50 -> 1100 | J50: =SUM(I50:I50) -> 1100 | K50: 1 | L50: =F50*1.02 -> 102 | M50: 12 | N50: =M50*L50*K50 -> 1224 | O50: =SUM(N50:N50) -> 1224 | P50: 1 | Q50: =L50*1.02 -> 104.04 | R50: 12 | S50: =R50*Q50*P50 -> 1248.48 | T50: =SUM(S50:S50) -> 1248.48 | U50: 1 | V50: =Q50*1.02 -> 106.1208 | W50: 12 | X50: =W50*V50*U50 -> 1273.4496 | Y50: =SUM(X50:X50) -> 1273.4496 | Z50: 1 | AA50: =V50*1.02 -> 108.24322 | AB50: 9 | AC50: =AB50*AA50*Z50 -> 974.18894 | AD50: =SUM(AC50:AC50) -> 974.18894 | AE50: =I50+N50+S50+X50+AC50 -> 5820.1185 | AF50: =SUM(AE50:AE50) -> 5820.1185
A51: RENT&UTDOM | B51: 85180 | C51: DOM | D51: Office Rent & Utilities | E51: 1 | F51: ='FO Expenses'!G5 -> 850 | G51: 11 | H51: /months | I51: =G51*F51*E51 -> 9350 | J51: =SUM(I51:I51) -> 9350 | K51: 1 | L51: =F51*1.02 -> 867 | M51: 12 | N51: =M51*L51*K51 -> 10404 | O51: =SUM(N51:N51) -> 10404 | P51: 1 | Q51: =L51*1.02 -> 884.34 | R51: 12 | S51: =R51*Q51*P51 -> 10612.08 | T51: =SUM(S51:S51) -> 10612.08 | U51: 1 | V51: =Q51*1.02 -> 902.0268 | W51: 12 | X51: =W51*V51*U51 -> 10824.322 | Y51: =SUM(X51:X51) -> 10824.322 | Z51: 1 | AA51: =V51*1.02 -> 920.06734 | AB51: 6 | AC51: =AB51*AA51*Z51 -> 5520.404 | AD51: =SUM(AC51:AC51) -> 5520.404 | AE51: =I51+N51+S51+X51+AC51 -> 46710.806 | AF51: =SUM(AE51:AE51) -> 46710.806
A52: PAYROLLDOM | B52: 81030 | C52: DOM | D52: Payroll Company | E52: 1 | F52: ='FO Expenses'!L8 -> 160.41667 | G52: 11 | H52: /months | I52: =G52*F52*E52 -> 1764.5833 | J52: =SUM(I52:I52) -> 1764.5833 | K52: 1 | L52: =F52*1.02 -> 163.625 | M52: 12 | N52: =M52*L52*K52 -> 1963.5 | O52: =SUM(N52:N52) -> 1963.5 | P52: 1 | Q52: =L52*1.02 -> 166.8975 | R52: 12 | S52: =R52*Q52*P52 -> 2002.77 | T52: =SUM(S52:S52) -> 2002.77 | U52: 1 | V52: =Q52*1.02 -> 170.23545 | W52: 12 | X52: =W52*V52*U52 -> 2042.8254 | Y52: =SUM(X52:X52) -> 2042.8254 | Z52: 1 | AA52: =V52*1.02 -> 173.64016 | AB52: 9 | AC52: =AB52*AA52*Z52 -> 1562.7614 | AD52: =SUM(AC52:AC52) -> 1562.7614 | AE52: =I52+N52+S52+X52+AC52 -> 9336.4402 | AF52: =SUM(AE52:AE52) -> 9336.4402
D53: Subtotal Office Expenses | I53: =SUM(I47:I52) -> 15547.583 | J53: =SUM(J47:J52) -> 15547.583 | N53: =SUM(N47:N52) -> 17300.22 | O53: =SUM(O47:O52) -> 17300.22 | S53: =SUM(S47:S52) -> 17646.224 | T53: =SUM(T47:T52) -> 17646.224 | X53: =SUM(X47:X52) -> 17999.149 | Y53: =SUM(Y47:Y52) -> 17999.149 | AC53: =SUM(AC47:AC52) -> 11009.147 | AD53: =SUM(AD47:AD52) -> 11009.147 | AE53: =I53+N53+S53+X53+AC53 -> 79502.324 | AF53: =SUM(AE53:AE53) -> 79502.324
D55: Total | I55: =I53+I16+I19+I44+I14+I30 -> 176481.48 | J55: =J53+J16+J19+J44+J14+J30 -> 176481.48 | N55: =N53+N16+N19+N44+N14+N30 -> 151935.55 | O55: =O53+O16+O19+O44+O14+O30 -> 151935.55 | S55: =S53+S16+S19+S44+S14+S30 -> 156292.79 | T55: =T53+T16+T19+T44+T14+T30 -> 156292.79 | X55: =X53+X16+X19+X44+X14+X30 -> 160776.73 | Y55: =Y53+Y16+Y19+Y44+Y14+Y30 -> 160776.73 | AC55: =AC53+AC16+AC19+AC44+AC14+AC30 -> 114990.37 | AD55: =AD53+AD16+AD19+AD44+AD14+AD30 -> 114990.37 | AE55: =AE53+AE16+AE19+AE44+AE14+AE30 -> 760476.92 | AF55: =AF53+AF16+AF19+AF44+AF14+AF30 -> 760476.92
F58: 900
O61: =SUM(AE55+'Dominican Republic'!AD55+Guyana!AD54+Jamaica!AD54) -> 1055610.6

Sheet Jamaica
A1: Entity: | B1: P | D1: Partners of the Americas F2F Caribbean Basin Program Budget
A2: Program-Dept.: | B2: 30100 | D2: USAID NOFO #7200AA23RFA00006
A3: Funder-Grant: | B3: USAID650
A4: Budget (Activity) Code | B4: Account Code | C4: Country Code | D4: Jamaica | I4: Year 1 | K4: Year 2 | P4: Year 3 | U4: Year 4 | Z4: Year 5 | AE4: Total | AF4: Grand
E5: Units | F5: Cost | G5: Duration | H5: Type | I5: USAID | J5: Total | K5: Units | L5: Cost | M5: Duration | N5: USAID | O5: Total | P5: Units | Q5: Cost | R5: Duration | S5: USAID | T5: Total | U5: Units | V5: Cost | W5: Duration | X5: USAID | Y5: Total | Z5: Units | AA5: Cost | AB5: Duration | AC5: USAID | AD5: Total | AE5: USAID | AF5: Total
D7: Key Personnel
A8: PERSNL-JAM | B8: 70000 | C8: JAM | D8: Country Director* | E8: 1 | F8: 5100 | G8: 12 | H8: /months | I8: =G8*F8*E8 -> 61200 | J8: =SUM(I8:I8) -> 61200 | K8: 1 | L8: =F8*1.03 -> 5253 | M8: 12 | N8: =M8*L8*K8 -> 63036 | O8: =SUM(N8:N8) -> 63036 | P8: 1 | Q8: =L8*1.03 -> 5410.59 | R8: 12 | S8: =R8*Q8*P8 -> 64927.08 | T8: =SUM(S8:S8) -> 64927.08 | U8: 1 | V8: =Q8*1.03 -> 5572.9077 | W8: 12 | X8: =W8*V8*U8 -> 66874.892 | Y8: =SUM(X8:X8) -> 66874.892 | Z8: 1 | AA8: =V8*1.03 -> 5740.0949 | AB8: 9 | AC8: =AB8*AA8*Z8 -> 51660.854 | AD8: =SUM(AC8:AC8) -> 51660.854 | AE8: =I8+N8+S8+X8+AC8 -> 307698.83 | AF8: =SUM(AE8:AE8) -> 307698.83
D10: Other Personnel
A11: PERSNL-JAM | B11: 70000 | C11: JAM | D11: Field Officer | E11: 1 | F11: 1100 | G11: 10 | H11: /months | I11: =G11*F11*E11 -> 11000 | J11: =SUM(I11:I11) -> 11000 | K11: =E11 -> 1 | L11: =F11*1.03 -> 1133 | M11: 12 | N11: =M11*L11*K11 -> 13596 | O11: =SUM(N11:N11) -> 13596 | P11: =E11 -> 1 | Q11: =L11*1.03 -> 1166.99 | R11: 12 | S11: =R11*Q11*P11 -> 14003.88 | T11: =SUM(S11:S11) -> 14003.88 | U11: =E11 -> 1 | V11: =Q11*1.03 -> 1201.9997 | W11: 12 | X11: =W11*V11*U11 -> 14423.996 | Y11: =SUM(X11:X11) -> 14423.996 | Z11: =E11 -> 1 | AA11: =V11*1.03 -> 1238.0597 | AB11: 9 | AC11: =AB11*AA11*Z11 -> 11142.537 | AD11: =SUM(AC11:AC11) -> 11142.537 | AE11: =I11+N11+S11+X11+AC11 -> 64166.414 | AF11: =SUM(AE11:AE11) -> 64166.414 | AG11: =K11+P11+U11+Z11+AE11 -> 64170.414 | AH11: =SUM(AG11:AG11) -> 64170.414 | AI11: =M11+R11+W11+AB11+AG11 -> 64215.414
A12: PERSNL-JAM | B12: 70000 | C12: JAM | D12: Administrative Assistant | E12: 1 | F12: 950 | G12: 11 | H12: /months | I12: =G12*F12*E12 -> 10450 | J12: =SUM(I12:I12) -> 10450 | K12: 1 | L12: =F12*1.03 -> 978.5 | M12: 12 | N12: =M12*L12*K12 -> 11742 | O12: =SUM(N12:N12) -> 11742 | P12: 1 | Q12: =L12*1.03 -> 1007.855 | R12: 12 | S12: =R12*Q12*P12 -> 12094.26 | T12: =SUM(S12:S12) -> 12094.26 | U12: 1 | V12: =Q12*1.03 -> 1038.0907 | W12: 12 | X12: =W12*V12*U12 -> 12457.088 | Y12: =SUM(X12:X12) -> 12457.088 | Z12: 1 | AA12: =V12*1.03 -> 1069.2334 | AB12: 9 | AC12: =AB12*AA12*Z12 -> 9623.1003 | AD12: =SUM(AC12:AC12) -> 9623.1003 | AE12: =I12+N12+S12+X12+AC12 -> 56366.448 | AF12: =SUM(AE12:AE12) -> 56366.448 | AG12: =K12+P12+U12+Z12+AE12 -> 56370.448 | AH12: =SUM(AG12:AG12) -> 56370.448 | AI12: =M12+R12+W12+AB12+AG12 -> 56415.448
D13: Subtotal Field Salaries | I13: =SUM(I8:I12) -> 82650 | J13: =SUM(J8:J12) -> 82650 | N13: =SUM(N8:N12) -> 88374 | O13: =SUM(O8:O12) -> 88374 | S13: =SUM(S8:S12) -> 91025.22 | T13: =SUM(T8:T12) -> 91025.22 | X13: =SUM(X8:X12) -> 93755.977 | Y13: =SUM(Y8:Y12) -> 93755.977 | AC13: =SUM(AC8:AC12) -> 72426.492 | AD13: =SUM(AD8:AD12) -> 72426.492 | AE13: =I13+N13+S13+X13+AC13 -> 428231.69 | AF13: =SUM(AE13:AE13) -> 428231.69
A15: FRINGE-JAM | B15: 70015 | C15: JAM | D15: Benefits | E15: 0.1535 | F15: =I13 -> 82650 | I15: =F15*E15 -> 12686.775 | J15: =SUM(I15:I15) -> 12686.775 | L15: =N13 -> 88374 | N15: =L15*E15 -> 13565.409 | O15: =SUM(N15:N15) -> 13565.409 | Q15: =S13 -> 91025.22 | S15: =Q15*E15 -> 13972.371 | T15: =SUM(S15:S15) -> 13972.371 | V15: =X13 -> 93755.977 | X15: =V15*E15 -> 14391.542 | Y15: =SUM(X15:X15) -> 14391.542 | AA15: =AC13 -> 72426.492 | AC15: =AA15*E15 -> 11117.467 | AD15: =SUM(AC15:AC15) -> 11117.467 | AE15: =I15+N15+S15+X15+AC15 -> 65733.564 | AF15: =SUM(AE15:AE15) -> 65733.564
D17: Supplies
A18: SUPPLY-JAM | B18: 82401 | C18: JAM | D18: Laptops | E18: ='FO Expenses'!C26 -> 3 | F18: ='FO Expenses'!B26 -> 1100 | G18: 1 | H18: /year | I18: =E18*F18*G18 -> 3300 | J18: =SUM(I18:I18) -> 3300 | K18: 0 | L18: =F18*1.02 -> 1122 | M18: 1 | N18: =M18*L18*K18 -> 0 | O18: =SUM(N18:N18) -> 0 | P18: 0 | Q18: =L18*1.02 -> 1144.44 | R18: 1 | S18: =R18*Q18*P18 -> 0 | T18: =SUM(S18:S18) -> 0 | U18: 0 | V18: =Q18*1.02 -> 1167.3288 | W18: 1 | X18: =W18*V18*U18 -> 0 | Y18: =SUM(X18:X18) -> 0 | Z18: 0 | AA18: =V18*1.02 -> 1190.6754 | AB18: 1 | AC18: =AB18*AA18*Z18 -> 0 | AD18: =SUM(AC18:AC18) -> 0 | AE18: =I18+N18+S18+X18+AC18 -> 3300 | AF18: =SUM(AE18:AE18) -> 3300
A19: SUPPLY-JAM | B19: 82401 | C19: JAM | D19: Tablet | E19: ='FO Expenses'!C27 -> 2 | F19: ='FO Expenses'!B27 -> 370 | G19: 1 | H19: /year | I19: =E19*F19*G19 -> 740 | J19: =SUM(I19:I19) -> 740 | K19: 0 | L19: =F19*1.02 -> 377.4 | M19: 1 | N19: =M19*L19*K19 -> 0 | O19: =SUM(N19:N19) -> 0 | P19: 0 | Q19: =L19*1.02 -> 384.948 | R19: 1 | S19: =R19*Q19*P19 -> 0 | T19: =SUM(S19:S19) -> 0 | U19: 0 | V19: =Q19*1.02 -> 392.64696 | W19: 1 | X19: =W19*V19*U19 -> 0 | Y19: =SUM(X19:X19) -> 0 | Z19: 0 | AA19: =V19*1.02 -> 400.4999 | AB19: 1 | AC19: =AB19*AA19*Z19 -> 0 | AD19: =SUM(AC19:AC19) -> 0 | AE19: =I19+N19+S19+X19+AC19 -> 740 | AF19: =SUM(AE19:AE19) -> 740
A20: SUPPLY-JAM | B20: 82401 | C20: JAM | D20: Projector | E20: ='FO Expenses'!C28 -> 1 | F20: ='FO Expenses'!B28 -> 588 | G20: 1 | H20: /year | I20: =E20*F20*G20 -> 588 | J20: =SUM(I20:I20) -> 588 | K20: 0 | L20: =F20*1.02 -> 599.76 | M20: 1 | N20: =M20*L20*K20 -> 0 | O20: =SUM(N20:N20) -> 0 | P20: 0 | Q20: =L20*1.02 -> 611.7552 | R20: 1 | S20: =R20*Q20*P20 -> 0 | T20: =SUM(S20:S20) -> 0 | U20: 0 | V20: =Q20*1.02 -> 623.9903 | W20: 1 | X20: =W20*V20*U20 -> 0 | Y20: =SUM(X20:X20) -> 0 | Z20: 0 | AA20: =V20*1.02 -> 636.47011 | AB20: 1 | AC20: =AB20*AA20*Z20 -> 0 | AD20: =SUM(AC20:AC20) -> 0 | AE20: =I20+N20+S20+X20+AC20 -> 588 | AF20: =SUM(AE20:AE20) -> 588
A21: SUPPLY-JAM | B21: 82401 | C21: JAM | D21: Miscellaneous Supplies | E21: 1 | F21: ='FO Expenses'!B29 -> 530 | G21: 1 | H21: /year | I21: =E21*F21*G21 -> 530 | J21: =SUM(I21:I21) -> 530 | K21: 1 | L21: =F21*1.02 -> 540.6 | M21: 1 | N21: =M21*L21*K21 -> 540.6 | O21: =SUM(N21:N21) -> 540.6 | P21: 1 | Q21: =L21*1.02 -> 551.412 | R21: 1 | S21: =R21*Q21*P21 -> 551.412 | T21: =SUM(S21:S21) -> 551.412 | U21: 1 | V21: =Q21*1.02 -> 562.44024 | W21: 1 | X21: =W21*V21*U21 -> 562.44024 | Y21: =SUM(X21:X21) -> 562.44024 | Z21: 1 | AA21: =V21*1.02 -> 573.68904 | AB21: 1 | AC21: =AB21*AA21*Z21 -> 573.68904 | AD21: =SUM(AC21:AC21) -> 573.68904 | AE21: =I21+N21+S21+X21+AC21 -> 2758.1413 | AF21: =SUM(AE21:AE21) -> 2758.1413
D22: Subtotal Supplies | I22: =SUM(I18:I21) -> 5158 | J22: =SUM(J18:J21) -> 5158 | N22: =SUM(N18:N21) -> 540.6 | O22: =SUM(O18:O21) -> 540.6 | S22: =SUM(S18:S21) -> 551.412 | T22: =SUM(T18:T21) -> 551.412 | X22: =SUM(X18:X21) -> 562.44024 | Y22: =SUM(Y18:Y21) -> 562.44024 | AC22: =SUM(AC18:AC21) -> 573.68904 | AD22: =SUM(AD18:AD21) -> 573.68904 | AE22: =I22+N22+S22+X22+AC22 -> 7386.1413 | AF22: =SUM(AE22:AE22) -> 7386.1413
D24: Volunteer Travel Related Costs (Traditional)
A25: VFLYJAM | B25: 86040 | C25: JAM | D25: Roundtrip Airfare | E25: ='Volunteer Travel'!C10 -> 14 | F25: ='Volunteer Travel'!B22 -> 800 | G25: 1 | H25: /trip | I25: =E25*F25*G25 -> 11200 | J25: =F25*G25*E25 -> 11200 | K25: ='Volunteer Travel'!D10 -> 13 | L25: =F25*1.02 -> 816 | M25: =G25 -> 1 | N25: =L25*M25*K25 -> 10608 | O25: =L25*M25*K25 -> 10608 | P25: ='Volunteer Travel'!E10 -> 12 | Q25: =L25*1.02 -> 832.32 | R25: =M25 -> 1 | S25: =Q25*R25*P25 -> 9987.84 | T25: =Q25*R25*P25 -> 9987.84 | U25: ='Volunteer Travel'!F10 -> 12 | V25: =Q25*1.02 -> 848.9664 | W25: =R25 -> 1 | X25: =V25*W25*U25 -> 10187.597 | Y25: =V25*W25*U25 -> 10187.597 | Z25: ='Volunteer Travel'!G10 -> 13 | AA25: =V25*1.02 -> 865.94573 | AB25: =W25 -> 1 | AC25: =AA25*AB25*Z25 -> 11257.294 | AD25: =AA25*AB25*Z25 -> 11257.294 | AE25: =SUM(AD25,Y25,T25,O25,J25) -> 53240.731 | AF25: =SUM(AE25:AE25) -> 53240.731 | AG25: =AF25*0.7 -> 37268.512 | AH25: =AG25/3 -> 12422.837 | AI25: =AH25/12 -> 1035.2364
A26: VTRADJAM | B26: 86030 | C26: JAM | D26: Lodging | E26: =E25 -> 14 | F26: ='Volunteer Travel'!C22 -> 116.05 | G26: 14 | H26: /night | I26: =E26*F26*G26 -> 22745.8 | J26: =F26*G26*E26 -> 22745.8 | K26: =K25 -> 13 | L26: =F26*1.02 -> 118.371 | M26: =G26 -> 14 | N26: =L26*M26*K26 -> 21543.522 | O26: =L26*M26*K26 -> 21543.522 | P26: =P25 -> 12 | Q26: =L26*1.02 -> 120.73842 | R26: =M26 -> 14 | S26: =Q26*R26*P26 -> 20284.055 | T26: =Q26*R26*P26 -> 20284.055 | U26: =U25 -> 12 | V26: =Q26*1.02 -> 123.15319 | W26: =R26 -> 14 | X26: =V26*W26 -> 1724.1446 | Y26: =V26*W26*U26 -> 20689.736 | Z26: =Z25 -> 13 | AA26: =V26*1.02 -> 125.61625 | AB26: =W26 -> 14 | AC26: =AA26*AB26*Z26 -> 22862.158 | AD26: =AA26*AB26*Z26 -> 22862.158 | AE26: =SUM(AD26,Y26,T26,O26,J26) -> 108125.27 | AF26: =SUM(AE26:AE26) -> 108125.27 | AG26: =AF26*0.7 -> 75687.689 | AH26: =AG26/3 -> 25229.23 | AI26: =AH26/12 -> 2102.4358
A27: VTRADJAM | B27: 86050 | C27: JAM | D27: Meals and Incidentals | E27: =E25 -> 14 | F27: ='Volunteer Travel'!D22 -> 50.5 | G27: 15 | H27: /day | I27: =E27*F27*G27 -> 10605 | J27: =F27*G27*E27 -> 10605 | K27: =K25 -> 13 | L27: =F27*1.02 -> 51.51 | M27: =G27 -> 15 | N27: =L27*M27*K27 -> 10044.45 | O27: =L27*M27*K27 -> 10044.45 | P27: =P25 -> 12 | Q27: =L27*1.02 -> 52.5402 | R27: =M27 -> 15 | S27: =Q27*R27*P27 -> 9457.236 | T27: =Q27*R27*P27 -> 9457.236 | U27: =U25 -> 12 | V27: =Q27*1.02 -> 53.591004 | W27: =R27 -> 15 | X27: =V27*W27 -> 803.86506 | Y27: =V27*W27*U27 -> 9646.3807 | Z27: =Z25 -> 13 | AA27: =V27*1.02 -> 54.662824 | AB27: =W27 -> 15 | AC27: =AA27*AB27*Z27 -> 10659.251 | AD27: =AA27*AB27*Z27 -> 10659.251 | AE27: =SUM(AD27,Y27,T27,O27,J27) -> 50412.317 | AF27: =SUM(AE27:AE27) -> 50412.317 | AG27: =AF27*0.7 -> 35288.622 | AH27: =AG27/3 -> 11762.874 | AI27: =AH27/12 -> 980.23951
A28: VTRADJAM | B28: 86050 | C28: JAM | D28: Health Related | E28: =E25 -> 14 | F28: ='Volunteer Travel'!E22 -> 75 | G28: 1 | H28: /trip | I28: =E28*F28*G28 -> 1050 | J28: =F28*G28*E28 -> 1050 | K28: =K26 -> 13 | L28: =F28*1.02 -> 76.5 | M28: =G28 -> 1 | N28: =L28*M28*K28 -> 994.5 | O28: =L28*M28*K28 -> 994.5 | P28: =P26 -> 12 | Q28: =L28*1.02 -> 78.03 | R28: =M28 -> 1 | S28: =Q28*R28*P28 -> 936.36 | T28: =Q28*R28*P28 -> 936.36 | U28: =U26 -> 12 | V28: =Q28*1.02 -> 79.5906 | W28: =R28 -> 1 | X28: =V28*W28 -> 79.5906 | Y28: =V28*W28*U28 -> 955.0872 | Z28: =Z26 -> 13 | AA28: =V28*1.02 -> 81.182412 | AB28: =W28 -> 1 | AC28: =AA28*AB28*Z28 -> 1055.3714 | AD28: =AA28*AB28*Z28 -> 1055.3714 | AE28: =SUM(AD28,Y28,T28,O28,J28) -> 4991.3186 | AF28: =SUM(AE28:AE28) -> 4991.3186
A29: VTRADJAM | B29: 86050 | C29: JAM | D29: Other Travel Related Costs | E29: =E25 -> 14 | F29: ='Volunteer Travel'!F22 -> 124 | G29: 1 | H29: /trip | I29: =E29*F29*G29 -> 1736 | J29: =F29*G29*E29 -> 1736 | K29: =K25 -> 13 | L29: =F29*1.02 -> 126.48 | M29: 1 | N29: =L29*M29*K29 -> 1644.24 | O29: =L29*M29*K29 -> 1644.24 | P29: =P25 -> 12 | Q29: =L29*1.02 -> 129.0096 | R29: 1 | S29: =Q29*R29*P29 -> 1548.1152 | T29: =Q29*R29*P29 -> 1548.1152 | U29: =U25 -> 12 | V29: =Q29*1.02 -> 131.58979 | W29: 1 | X29: =V29*W29 -> 131.58979 | Y29: =V29*W29*U29 -> 1579.0775 | Z29: =Z25 -> 13 | AA29: =V29*1.02 -> 134.22159 | AB29: 1 | AC29: =AA29*AB29*Z29 -> 1744.8806 | AD29: =AA29*AB29*Z29 -> 1744.8806 | AE29: =SUM(AD29,Y29,T29,O29,J29) -> 8252.3133 | AF29: =SUM(AE29:AE29) -> 8252.3133 | AG29: =AF29*0.7 -> 5776.6193 | AH29: =AG29/3 -> 1925.5398 | AI29: =AH29/12 -> 160.46165
D31: Volunteer Travel Related Costs (Paired)
A32: VPAIRJAM | B32: 86030 | C32: JAM | D32: Lodging | E32: ='Volunteer Travel'!C11 -> 2 | F32: ='Volunteer Travel'!G22 -> 81.235 | G32: 6 | H32: /night | I32: =E32*F32*G32 -> 974.82 | J32: =F32*G32*E32 -> 974.82 | K32: ='Volunteer Travel'!D11 -> 3 | L32: =F32*1.02 -> 82.8597 | M32: =G32 -> 6 | N32: =M32*K32*L32 -> 1491.4746 | O32: =K32*L32*M32 -> 1491.4746 | P32: ='Volunteer Travel'!E11 -> 3 | Q32: =L32*1.02 -> 84.516894 | R32: =M32 -> 6 | S32: =R32*P32*Q32 -> 1521.3041 | T32: =P32*Q32*R32 -> 1521.3041 | U32: ='Volunteer Travel'!F11 -> 3 | V32: =Q32*1.02 -> 86.207232 | W32: =R32 -> 6 | X32: =W32*U32*V32 -> 1551.7302 | Y32: =U32*V32*W32 -> 1551.7302 | Z32: ='Volunteer Travel'!G11 -> 2 | AA32: =V32*1.02 -> 87.931377 | AB32: =W32 -> 6 | AC32: =AB32*Z32*AA32 -> 1055.1765 | AD32: =Z32*AA32*AB32 -> 1055.1765 | AE32: =SUM(AD32,Y32,T32,O32,J32) -> 6594.5054 | AF32: =SUM(AE32:AE32) -> 6594.5054 | AG32: =AF32*0.7 -> 4616.1538 | AH32: =AG32/3 -> 1538.7179 | AI32: =AH32/12 -> 128.22649
A33: VPAIRJAM | B33: 86050 | C33: JAM | D33: Meals and Incidentals | E33: =E32 -> 2 | F33: ='Volunteer Travel'!H22 -> 50.5 | G33: 7 | H33: /day | I33: =E33*F33*G33 -> 707 | J33: =F33*G33*E33 -> 707 | K33: =K32 -> 3 | L33: =F33*1.02 -> 51.51 | M33: =G33 -> 7 | N33: =M33*K33*L33 -> 1081.71 | O33: =K33*L33*M33 -> 1081.71 | P33: =P32 -> 3 | Q33: =L33*1.02 -> 52.5402 | R33: =M33 -> 7 | S33: =R33*P33*Q33 -> 1103.3442 | T33: =P33*Q33*R33 -> 1103.3442 | U33: =U32 -> 3 | V33: =Q33*1.02 -> 53.591004 | W33: =R33 -> 7 | X33: =W33*U33*V33 -> 1125.4111 | Y33: =U33*V33*W33 -> 1125.4111 | Z33: =Z32 -> 2 | AA33: =V33*1.02 -> 54.662824 | AB33: =W33 -> 7 | AC33: =AB33*Z33*AA33 -> 765.27954 | AD33: =Z33*AA33*AB33 -> 765.27954 | AE33: =SUM(AD33,Y33,T33,O33,J33) -> 4782.7448 | AF33: =SUM(AE33:AE33) -> 4782.7448 | AG33: =AF33*0.7 -> 3347.9214 | AH33: =AG33/3 -> 1115.9738 | AI33: =AH33/12 -> 92.997816
A34: VPAIRJAM | B34: 86050 | C34: JAM | D34: Other Travel Related Costs | E34: =E32 -> 2 | F34: ='Volunteer Travel'!I22 -> 30 | G34: 1 | H34: /trip | I34: =E34*F34*G34 -> 60 | J34: =F34*G34*E34 -> 60 | K34: =K32 -> 3 | L34: =F34*1.02 -> 30.6 | M34: =G34 -> 1 | N34: =M34*K34*L34 -> 91.8 | O34: =K34*L34*M34 -> 91.8 | P34: =P32 -> 3 | Q34: =L34*1.02 -> 31.212 | R34: =M34 -> 1 | S34: =R34*P34*Q34 -> 93.636 | T34: =P34*Q34*R34 -> 93.636 | U34: =U32 -> 3 | V34: =Q34*1.02 -> 31.83624 | W34: =R34 -> 1 | X34: =W34*U34*V34 -> 95.50872 | Y34: =U34*V34*W34 -> 95.50872 | Z34: =Z32 -> 2 | AA34: =V34*1.02 -> 32.472965 | AB34: =W34 -> 1 | AC34: =AB34*Z34*AA34 -> 64.94593 | AD34: =Z34*AA34*AB34 -> 64.94593 | AE34: =SUM(AD34,Y34,T34,O34,J34) -> 405.89065 | AF34: =SUM(AE34:AE34) -> 405.89065 | AG34: =AF34*0.7 -> 284.12345 | AH34: =AG34/3 -> 94.707818 | AI34: =AH34/12 -> 7.8923182
AG35: =AF29-AG29 -> 2475.694 | AH35: =AG35/2 -> 1237.847 | AI35: =AH35/9 -> 137.53856
D36: Local Travel Related Costs
A37: LOTRVL-JAM | B37: 86030 | C37: JAM | D37: Lodging | E37: 1 | F37: ='Field Travel'!B18 -> 81.235 | G37: ='Volunteer Travel'!K8 -> 138 | H37: /night | I37: =E37*F37*G37 -> 11210.43 | J37: =F37*G37 -> 11210.43 | K37: 1 | L37: =F37*1.02 -> 82.8597 | M37: ='Volunteer Travel'!L8 -> 138 | N37: =L37*M37 -> 11434.639 | O37: =L37*M37 -> 11434.639 | P37: 1 | Q37: =L37*1.02 -> 84.516894 | R37: ='Volunteer Travel'!M8 -> 150 | S37: =Q37*R37 -> 12677.534 | T37: =Q37*R37 -> 12677.534 | U37: 1 | V37: =Q37*1.02 -> 86.207232 | W37: ='Volunteer Travel'!N8 -> 132 | X37: =V37*W37 -> 11379.355 | Y37: =V37*W37 -> 11379.355 | Z37: 1 | AA37: =V37*1.02 -> 87.931377 | AB37: ='Volunteer Travel'!O8 -> 132 | AC37: =AA37*AB37 -> 11606.942 | AD37: =AA37*AB37 -> 11606.942 | AE37: =SUM(AD37,Y37,T37,O37,J37) -> 58308.899 | AF37: =SUM(AE37:AE37) -> 58308.899 | AG37: =AF37*0.7 -> 40816.229 | AH37: =AG37/3 -> 13605.41 | AI37: =AH37/12 -> 1133.7841
A38: LOTRVL-JAM | B38: 86050 | C38: JAM | D38: Meals and Incidentals | E38: 1 | F38: ='Field Travel'!C18 -> 50.5 | G38: =G37 -> 138 | H38: /day | I38: =E38*F38*G38 -> 6969 | J38: =F38*G38 -> 6969 | K38: 1 | L38: =F38*1.02 -> 51.51 | M38: =M37 -> 138 | N38: =L38*M38 -> 7108.38 | O38: =L38*M38 -> 7108.38 | P38: 1 | Q38: =L38*1.02 -> 52.5402 | R38: =R37 -> 150 | S38: =Q38*R38 -> 7881.03 | T38: =Q38*R38 -> 7881.03 | U38: 1 | V38: =Q38*1.02 -> 53.591004 | W38: =W37 -> 132 | X38: =V38*W38 -> 7074.0125 | Y38: =V38*W38 -> 7074.0125 | Z38: 1 | AA38: =V38*1.02 -> 54.662824 | AB38: =AB37 -> 132 | AC38: =AA38*AB38 -> 7215.4928 | AD38: =AA38*AB38 -> 7215.4928 | AE38: =SUM(AD38,Y38,T38,O38,J38) -> 36247.915 | AF38: =SUM(AE38:AE38) -> 36247.915 | AG38: =AF38*0.7 -> 25373.541 | AH38: =AG38/3 -> 8457.8469 | AI38: =AH38/12 -> 704.82058
A39: LOTRVL-JAM | B39: 86000 | C39: JAM | D39: Local Transportation Costs (fuel) | E39: 1 | F39: ='Field Travel'!D18 -> 64 | G39: =E25+E32+'Field Travel'!U24 -> 37 | H39: /trip | I39: =E39*F39*G39 -> 2368 | J39: =F39*G39 -> 2368 | K39: 1 | L39: =F39*1.02 -> 65.28 | M39: =K25+K32+'Field Travel'!U25 -> 37 | N39: =L39*M39 -> 2415.36 | O39: =L39*M39 -> 2415.36 | P39: 1 | Q39: =L39*1.02 -> 66.5856 | R39: =P25+P32+'Field Travel'!U26 -> 45 | S39: =Q39*R39 -> 2996.352 | T39: =Q39*R39 -> 2996.352 | U39: 1 | V39: =Q39*1.02 -> 67.917312 | W39: =U25+U32+'Field Travel'!U27 -> 36 | X39: =V39*W39 -> 2445.0232 | Y39: =V39*W39 -> 2445.0232 | Z39: 1 | AA39: =V39*1.02 -> 69.275658 | AB39: =Z25+Z32+'Field Travel'!U28 -> 36 | AC39: =AA39*AB39 -> 2493.9237 | AD39: =AA39*AB39 -> 2493.9237 | AE39: =SUM(AD39,Y39,T39,O39,J39) -> 12718.659 | AF39: =SUM(AE39:AE39) -> 12718.659 | AG39: =AF39*0.7 -> 8903.0613 | AH39: =AG39/3 -> 2967.6871 | AI39: =AH39/12 -> 247.30726
D41: Equipment | AI41: =AH35/10 -> 123.7847
A42: NONE | B42: NONE | C42: NONE | D42: Vehicles | E42: 0 | F42: 0 | G42: 1 | H42: /year | I42: =E42*F42*G42 -> 0 | J42: =SUM(I42:I42) -> 0 | N42: =M42*L42*K42 -> 0 | O42: =SUM(N42:N42) -> 0 | S42: =R42*Q42*P42 -> 0 | T42: =SUM(S42:S42) -> 0 | X42: =W42*V42*U42 -> 0 | Y42: =SUM(X42:X42) -> 0 | AC42: =AB42*AA42*Z42 -> 0 | AD42: =SUM(AC42:AC42) -> 0 | AE42: =I42+N42+S42+X42+AC42 -> 0 | AF42: =SUM(AE42:AE42) -> 0
D43: Subtotal Equipment | I43: =SUM(I41:I42) -> 0 | J43: =SUM(J41:J42) -> 0 | N43: =SUM(N41:N42) -> 0 | O43: =SUM(O41:O42) -> 0 | S43: =SUM(S41:S42) -> 0 | T43: =SUM(T41:T42) -> 0 | X43: =SUM(X41:X42) -> 0 | Y43: =SUM(Y41:Y42) -> 0 | AC43: =SUM(AC41:AC42) -> 0 | AD43: =SUM(AD41:AD42) -> 0 | AE43: =I43+N43+S43+X43+AC43 -> 0 | AF43: =SUM(AE43:AE43) -> 0
D45: Field Office Expenses
A46: MEETJAM | B46: 87010 | C46: JAM | D46: Meetings and Events | E46: 1 | F46: ='FO Expenses'!L26 -> 75 | G46: 11 | H46: /months | I46: =G46*F46*E46 -> 825 | J46: =SUM(I46:I46) -> 825 | K46: 1 | L46: =F46*1.02 -> 76.5 | M46: 12 | N46: =M46*L46*K46 -> 918 | O46: =SUM(N46:N46) -> 918 | P46: 1 | Q46: =L46*1.02 -> 78.03 | R46: 12 | S46: =R46*Q46*P46 -> 936.36 | T46: =SUM(S46:S46) -> 936.36 | U46: 1 | V46: =Q46*1.02 -> 79.5906 | W46: 12 | X46: =W46*V46*U46 -> 955.0872 | Y46: =SUM(X46:X46) -> 955.0872 | Z46: 1 | AA46: =V46*1.02 -> 81.182412 | AB46: 9 | AC46: =AB46*AA46*Z46 -> 730.64171 | AD46: =SUM(AC46:AC46) -> 730.64171 | AE46: =I46+N46+S46+X46+AC46 -> 4365.0889 | AF46: =SUM(AE46:AE46) -> 4365.0889
A47: TRANSJAM | B47: 85105 | C47: JAM | D47: Transportation | E47: 1 | F47: ='FO Expenses'!L27 -> 156.5 | G47: 11 | H47: /months | I47: =G47*F47*E47 -> 1721.5 | J47: =SUM(I47:I47) -> 1721.5 | K47: 1 | L47: =F47*1.02 -> 159.63 | M47: 12 | N47: =M47*L47*K47 -> 1915.56 | O47: =SUM(N47:N47) -> 1915.56 | P47: 1 | Q47: =L47*1.02 -> 162.8226 | R47: 12 | S47: =R47*Q47*P47 -> 1953.8712 | T47: =SUM(S47:S47) -> 1953.8712 | U47: 1 | V47: =Q47*1.02 -> 166.07905 | W47: 12 | X47: =W47*V47*U47 -> 1992.9486 | Y47: =SUM(X47:X47) -> 1992.9486 | Z47: 1 | AA47: =V47*1.02 -> 169.40063 | AB47: 9 | AC47: =AB47*AA47*Z47 -> 1524.6057 | AD47: =SUM(AC47:AC47) -> 1524.6057 | AE47: =I47+N47+S47+X47+AC47 -> 9108.4855 | AF47: =SUM(AE47:AE47) -> 9108.4855
A48: BANKJAM | B48: 90900 | C48: JAM | D48: Bank Fees | E48: 1 | F48: ='FO Expenses'!L28 -> 48 | G48: 11 | H48: /months | I48: =G48*F48*E48 -> 528 | J48: =SUM(I48:I48) -> 528 | K48: 1 | L48: =F48*1.02 -> 48.96 | M48: 12 | N48: =M48*L48*K48 -> 587.52 | O48: =SUM(N48:N48) -> 587.52 | P48: 1 | Q48: =L48*1.02 -> 49.9392 | R48: 12 | S48: =R48*Q48*P48 -> 599.2704 | T48: =SUM(S48:S48) -> 599.2704 | U48: 1 | V48: =Q48*1.02 -> 50.937984 | W48: 12 | X48: =W48*V48*U48 -> 611.25581 | Y48: =SUM(X48:X48) -> 611.25581 | Z48: 1 | AA48: =V48*1.02 -> 51.956744 | AB48: 9 | AC48: =AB48*AA48*Z48 -> 467.61069 | AD48: =SUM(AC48:AC48) -> 467.61069 | AE48: =I48+N48+S48+X48+AC48 -> 2793.6569 | AF48: =SUM(AE48:AE48) -> 2793.6569
A49: COMMJAM | B49: 82030 | C49: JAM | D49: Communications | E49: 1 | F49: ='FO Expenses'!L30 -> 100 | G49: 11 | H49: /months | I49: =G49*F49*E49 -> 1100 | J49: =SUM(I49:I49) -> 1100 | K49: 1 | L49: =F49*1.02 -> 102 | M49: 12 | N49: =M49*L49*K49 -> 1224 | O49: =SUM(N49:N49) -> 1224 | P49: 1 | Q49: =L49*1.02 -> 104.04 | R49: 12 | S49: =R49*Q49*P49 -> 1248.48 | T49: =SUM(S49:S49) -> 1248.48 | U49: 1 | V49: =Q49*1.02 -> 106.1208 | W49: 12 | X49: =W49*V49*U49 -> 1273.4496 | Y49: =SUM(X49:X49) -> 1273.4496 | Z49: 1 | AA49: =V49*1.02 -> 108.24322 | AB49: 9 | AC49: =AB49*AA49*Z49 -> 974.18894 | AD49: =SUM(AC49:AC49) -> 974.18894 | AE49: =I49+N49+S49+X49+AC49 -> 5820.1185 | AF49: =SUM(AE49:AE49) -> 5820.1185
A50: RENT&UTJAM | B50: 85180 | C50: JAM | D50: Office Rent & Utilities | E50: 1 | F50: ='FO Expenses'!G18 -> 1400 | G50: 11 | H50: /months | I50: =G50*F50*E50 -> 15400 | J50: =SUM(I50:I50) -> 15400 | K50: 1 | L50: =F50*1.02 -> 1428 | M50: 12 | N50: =M50*L50*K50 -> 17136 | O50: =SUM(N50:N50) -> 17136 | P50: 1 | Q50: =L50*1.02 -> 1456.56 | R50: 12 | S50: =R50*Q50*P50 -> 17478.72 | T50: =SUM(S50:S50) -> 17478.72 | U50: 1 | V50: =Q50*1.02 -> 1485.6912 | W50: 12 | X50: =W50*V50*U50 -> 17828.294 | Y50: =SUM(X50:X50) -> 17828.294 | Z50: 1 | AA50: =V50*1.02 -> 1515.405 | AB50: 6 | AC50: =AB50*AA50*Z50 -> 9092.4301 | AD50: =SUM(AC50:AC50) -> 9092.4301 | AE50: =I50+N50+S50+X50+AC50 -> 76935.445 | AF50: =SUM(AE50:AE50) -> 76935.445
A51: PAYROLLJAM | B51: 81030 | C51: JAM | D51: Payroll Company | E51: 1 | F51: ='FO Expenses'!L29 -> 200 | G51: 11 | H51: /months | I51: =G51*F51*E51 -> 2200 | J51: =SUM(I51:I51) -> 2200 | K51: 1 | L51: =F51*1.02 -> 204 | M51: 12 | N51: =M51*L51*K51 -> 2448 | O51: =SUM(N51:N51) -> 2448 | P51: 1 | Q51: =L51*1.02 -> 208.08 | R51: 12 | S51: =R51*Q51*P51 -> 2496.96 | T51: =SUM(S51:S51) -> 2496.96 | U51: 1 | V51: =Q51*1.02 -> 212.2416 | W51: 12 | X51: =W51*V51*U51 -> 2546.8992 | Y51: =SUM(X51:X51) -> 2546.8992 | Z51: 1 | AA51: =V51*1.02 -> 216.48643 | AB51: 9 | AC51: =AB51*AA51*Z51 -> 1948.3779 | AD51: =SUM(AC51:AC51) -> 1948.3779 | AE51: =I51+N51+S51+X51+AC51 -> 11640.237 | AF51: =SUM(AE51:AE51) -> 11640.237
D52: Subtotal Office Expenses | I52: =SUM(I46:I51) -> 21774.5 | J52: =SUM(J46:J51) -> 21774.5 | N52: =SUM(N46:N51) -> 24229.08 | O52: =SUM(O46:O51) -> 24229.08 | S52: =SUM(S46:S51) -> 24713.662 | T52: =SUM(T46:T51) -> 24713.662 | X52: =SUM(X46:X51) -> 25207.935 | Y52: =SUM(Y46:Y51) -> 25207.935 | AC52: =SUM(AC46:AC51) -> 14737.855 | AD52: =SUM(AD46:AD51) -> 14737.855 | AE52: =I52+N52+S52+X52+AC52 -> 110663.03 | AF52: =SUM(AE52:AE52) -> 110663.03
D54: Total | I54: =I52+I15+I18+I43+I13+I29 -> 122147.27 | J54: =J52+J15+J18+J43+J13+J29 -> 122147.27 | N54: =N52+N15+N18+N43+N13+N29 -> 127812.73 | O54: =O52+O15+O18+O43+O13+O29 -> 127812.73 | S54: =S52+S15+S18+S43+S13+S29 -> 131259.37 | T54: =T52+T15+T18+T43+T13+T29 -> 131259.37 | X54: =X52+X15+X18+X43+X13+X29 -> 133487.04 | Y54: =Y52+Y15+Y18+Y43+Y13+Y29 -> 134934.53 | AC54: =AC52+AC15+AC18+AC43+AC13+AC29 -> 100026.69 | AD54: =AD52+AD15+AD18+AD43+AD13+AD29 -> 100026.69 | AE54: =AE52+AE15+AE18+AE43+AE13+AE29 -> 616180.6 | AF54: =AF52+AF15+AF18+AF43+AF13+AF29 -> 616180.6

Sheet Volunteer Travel
A2: Volunteer Assignments by Fiscal Year & Assignment Type
C3: FY24 | D3: FY25 | E3: FY26 | F3: FY27 | G3: FY28 | H3: Totals | J3: Field Visit - Days per fiscal year
A4: Guatemala | B4: Traditional | C4: 16 | D4: 22 | E4: 22 | F4: 22 | G4: 16 | H4: =SUM(C4:G4) -> 98 | J4: Country | K4: FY24 | L4: FY25 | M4: FY26 | N4: FY27 | O4: FY28
B5: Paired | C5: 2 | D5: 1 | E5: 1 | F5: 1 | G5: 1 | H5: =SUM(C5:G5) -> 6 | J5: Guatemala | K5: =(SUM($C4:$C5)*6)+42 -> 150 | L5: =(SUM(D4:D5)*6)+42 -> 180 | M5: =(SUM(E4:E5)*6)+60 -> 198 | N5: =(SUM(F4:F5)*6)+42 -> 180 | O5: =(SUM(G4:G5)*6)+42 -> 144
A6: DR | B6: Traditional | C6: 16 | D6: 22 | E6: 22 | F6: 22 | G6: 16 | H6: =SUM(C6:G6) -> 98 | J6: DR | K6: =(SUM(C6:C7)*6)+42 -> 150 | L6: =(SUM(D6:D7)*6)+42 -> 180 | M6: =(SUM(E6:E7)*6)+60 -> 198 | N6: =(SUM(F6:F7)*6)+42 -> 180 | O6: =(SUM(G6:G7)*6)+42 -> 144
B7: Paired | C7: 2 | D7: 1 | E7: 1 | F7: 1 | G7: 1 | H7: =SUM(C7:G7) -> 6 | J7: Guyana | K7: =(SUM(C8:C9)*6)+42 -> 138 | L7: =(SUM(D8:D9)*6)+42 -> 138 | M7: =(SUM(E8:E9)*6)+60 -> 156 | N7: =(SUM(F8:F9)*6)+42 -> 132 | O7: =(SUM(G8:G9)*6)+42 -> 126
A8: Guyana | B8: Traditional | C8: 14 | D8: 13 | E8: 13 | F8: 12 | G8: 12 | H8: =SUM(C8:G8) -> 64 | J8: Jamaica | K8: =(SUM(C10:C11)*6)+42 -> 138 | L8: =(SUM(D10:D11)*6)+42 -> 138 | M8: =(SUM(E10:E11)*6)+60 -> 150 | N8: =(SUM(F10:F11)*6)+42 -> 132 | O8: =(SUM(G10:G11)*6)+42 -> 132
B9: Paired | C9: 2 | D9: 3 | E9: 3 | F9: 3 | G9: 2 | H9: =SUM(C9:G9) -> 13
A10: Jamaica | B10: Traditional | C10: 14 | D10: 13 | E10: 12 | F10: 12 | G10: 13 | H10: =SUM(C10:G10) -> 64
B11: Paired | C11: 2 | D11: 3 | E11: 3 | F11: 3 | G11: 2 | H11: =SUM(C11:G11) -> 13
A12: Flex (Additional countries) | C12: 3 | D12: 3 | E12: 4 | F12: 4 | G12: 4 | H12: =SUM(C12:G12) -> 18
A13: Total Traditional | C13: =SUM(C4,C6,C8,C10) -> 60 | D13: =SUM(D4,D6,D8,D10) -> 70 | E13: =SUM(E4,E6,E8,E10) -> 69 | F13: =SUM(F4,F6,F8,F10) -> 68 | G13: =SUM(G4,G6,G8,G10) -> 57 | H13: =SUM(C13:G13) -> 324
A14: Total Paired | C14: =SUM(C5,C7,C9,C11) -> 8 | D14: =SUM(D5,D7,D9,D11) -> 8 | E14: =SUM(E5,E7,E9,E11) -> 8 | F14: =SUM(F5,F7,F9,F11) -> 8 | G14: =SUM(G5,G7,G9,G11) -> 6 | H14: =SUM(C14:G14) -> 38
A15: Assignment Total | C15: =C14+C13+C12 -> 71 | D15: =D14+D13+D12 -> 81 | E15: =E14+E13+E12 -> 81 | F15: =F14+F13+F12 -> 80 | G15: =G14+G13+G12 -> 67 | H15: =H14+H13+H12 -> 380 | I15: =H14/H15 -> 0.1
B17: Traditional | G17: Paired
A18: Country | B18: Flights | C18: Lodging | D18: Per Diem | E18: Health | F18: Other | G18: Lodging | H18: Per Diem | I18: Other | K18: Country | L18: Flights
A19: Guatemala | B19: 650 | C19: 85 | D19: 42.5 | E19: 75 | F19: 124 | G19: 59.5 | H19: 42.5 | I19: 30 | K19: Guatemala | L19: 650
A20: DR | B20: 750 | C20: 92.925 | D20: 55.75 | E20: 75 | F20: 124 | G20: 65.0475 | H20: 55.75 | I20: 30 | K20: DR | L20: 750
A21: Guyana | B21: 850 | C21: 102.96 | D21: 59.5 | E21: 75 | F21: 124 | G21: 72.072 | H21: 59.5 | I21: 30 | K21: Guyana | L21: 850
A22: Jamaica | B22: 800 | C22: 116.05 | D22: 50.5 | E22: 75 | F22: 124 | G22: 81.235 | H22: 50.5 | I22: 30 | K22: Jamaica | L22: 800
B25: Flex Assignments
A26: Country | B26: Flights | C26: Lodging | D26: Per Diem | F26: Health | G26: Other
A27: Barbados | B27: 850 | C27: 52.5 | D27: 68 | F27: 75 | G27: 124
A28: Dominica | B28: 1070 | C28: 55 | D28: 58 | F28: 75 | G28: 124
A29: St. Vincent | B29: 978 | C29: 68.5 | D29: 35 | F29: 75 | G29: 124
A30: Grenada | B30: 650 | C30: 63 | D30: 58 | F30: 75 | G30: 124
A31: Average | B31: 887 | C31: 59.75 | D31: 54.75 | F31: 75 | G31: 124
B32: FY24 | C32: FY25 | D32: FY26 | F32: FY27 | G32: FY28
A33: # of Assignments | B33: =C12 -> 3 | C33: =D12 -> 3 | D33: =E12 -> 4 | F33: =F12 -> 4 | G33: =G12 -> 4
A34: 15-day Assignment Average | B34: =ROUND((C31*14)+(D31*15)+(F31+G31),0) -> 1857 | C34: =ROUND(B34*1.03,0) -> 1913 | D34: =ROUND(C34*1.03,0) -> 1970 | F34: =ROUND(D34*1.03,0) -> 2029 | G34: =ROUND(F34*1.03,0) -> 2090
D35: =D33*D34 -> 7880
A38: Flex Assignments | B38: FY24 | G38: FY25 | L38: FY26 | Q38: FY27 | V38: FY28
B39: Units | C39: Cost | D39: Duration | E39: Type | F39: Total | G39: Units | H39: Cost | I39: Duration | J39: Type | K39: Total | L39: Units | M39: Cost | N39: Duration | O39: Type | P39: Total | Q39: Units | R39: Cost | S39: Duration | T39: Type | U39: Total | V39: Units | W39: Cost | X39: Duration | Y39: Type | Z39: Total
A40: Lodging | B40: 42 | C40: 59.75 | D40: 1 | E40: Trip | F40: 2510 | G40: 42 | H40: 62 | I40: 1 | J40: Trip | K40: 2604 | L40: 56 | M40: =H40*1.03 -> 63.86 | N40: 1 | O40: Trip | P40: =L40*M40 -> 3576.16 | Q40: 56 | R40: =65.287786 -> 65.287786 | S40: 1 | T40: Trip | U40: =Q40*R40 -> 3656.116 | V40: 56 | W40: 67.24642 | X40: 1 | Y40: Trip | Z40: =V40*W40 -> 3765.7995
A41: Meals and Incidentals | B41: 45 | C41: 54.75 | D41: 1 | E41: Trip | F41: 2464 | G41: 45 | H41: 56 | I41: 1 | J41: Trip | K41: 2520 | L41: 60 | M41: =H41*1.03 -> 57.68 | N41: 1 | O41: Trip | P41: =L41*M41 -> 3460.8 | Q41: 60 | R41: =59.824151 -> 59.824151 | S41: 1 | T41: Trip | U41: =Q41*R41 -> 3589.4491 | V41: 60 | W41: 61.618876 | X41: 1 | Y41: Trip | Z41: =V41*W41 -> 3697.1325
A42: Health Related | B42: 3 | C42: 75 | D42: 1 | E42: Trip | F42: 225 | G42: 3 | H42: 77 | I42: 1 | J42: Trip | K42: 231 | L42: 4 | M42: =ROUND(H42*1.03,0) -> 79 | N42: 1 | O42: Trip | P42: =L42*M42 -> 316 | Q42: 4 | R42: =ROUND(81.954525,0) -> 82 | S42: 1 | T42: Trip | U42: =Q42*R42 -> 328 | V42: 4 | W42: 84.413161 | X42: 1 | Y42: Trip | Z42: =V42*W42 -> 337.65264
A43: Other Travel Related Costs | B43: 3 | C43: 124 | D43: 1 | E43: Trip | F43: 372 | G43: 3 | H43: 128 | I43: 1 | J43: Trip | K43: 384 | L43: 4 | M43: =H43*1.03 -> 131.84 | N43: 1 | O43: Trip | P43: =L43*M43 -> 527.36 | Q43: 4 | R43: =135.498148 -> 135.49815 | S43: 1 | T43: Trip | U43: =Q43*R43 -> 541.99259 | V43: 4 | W43: =139.56309244 -> 139.56309 | X43: 1 | Y43: Trip | Z43: =V43*W43 -> 558.25237
A44: Total | F44: 5571 | K44: 5739 | P44: =SUM(P40:P43) -> 7880.32 | U44: =SUM(U40:U43) -> 8115.5577 | Z44: =SUM(Z40:Z43) -> 8358.837

Sheet Field Travel
A3: Field Visit - Days per fiscal year | I3: Average Field Staff Travel-Related Costs per Volunteer Assignments
A4: Country | B4: FY24 | C4: FY25 | D4: FY26 | E4: FY27 | F4: FY28
A5: Guatemala | B5: ='Volunteer Travel'!K5 -> 150 | C5: ='Volunteer Travel'!L5 -> 180 | D5: ='Volunteer Travel'!M5 -> 198 | E5: ='Volunteer Travel'!N5 -> 180 | F5: ='Volunteer Travel'!O5 -> 144 | I5: Daily Rates | K5: Per Trip Rates | L5: FY24
A6: DR | B6: ='Volunteer Travel'!K6 -> 150 | C6: ='Volunteer Travel'!L6 -> 180 | D6: ='Volunteer Travel'!M6 -> 198 | E6: ='Volunteer Travel'!N6 -> 180 | F6: ='Volunteer Travel'!O6 -> 144 | H6: Country | I6: Lodging | J6: Per Diem | K6: Other Related Costs
A7: Guyana | B7: ='Volunteer Travel'!K7 -> 138 | C7: ='Volunteer Travel'!L7 -> 138 | D7: ='Volunteer Travel'!M7 -> 156 | E7: ='Volunteer Travel'!N7 -> 132 | F7: ='Volunteer Travel'!O7 -> 126 | H7: Guatemala | I7: 59.5 | J7: 42.5 | K7: 56 | L7: =SUM(O15*I7)+(O15*J7)+(K7*(I15+L15)) -> 17484
A8: Jamaica | B8: ='Volunteer Travel'!K8 -> 138 | C8: ='Volunteer Travel'!L8 -> 138 | D8: ='Volunteer Travel'!M8 -> 150 | E8: ='Volunteer Travel'!N8 -> 132 | F8: ='Volunteer Travel'!O8 -> 132 | H8: DR | I8: 65.0475 | J8: 55.75 | K8: 67 | L8: =SUM(O24*I8)+(O24*J8)+(K8*(I24+L24)) -> 20732.625
H9: Guyana | I9: 72.072 | J9: 59.5 | K9: 65 | L9: =SUM($I9*X15)+($J9*X15)+($K9*(R15+U15)) -> 20561.936
H10: Jamaica | I10: 81.235 | J10: 50.5 | K10: 64 | L10: =SUM($I10*X24)+($J10*X24)+($K10*(R24+U24)) -> 20547.43
I12: Field Staff Travel Days - Guatemala | R12: Field Staff Travel Days - Guyana
B13: Field Staff | I13: Volunteer Assignments | L13: Data Collection & Follow-up | O13: Total Travel Days | R13: Volunteer Assignments | U13: Data Collection & Follow-up | X13: Total Travel Days
A14: Country | B14: Lodging | C14: Per Diem | D14: Transport (Fuel) | I14: Trips | J14: Days per trip | K14: Total Days | L14: Trips | M14: Days per trip | N14: Total Days | R14: Trips | S14: Days per trip | T14: Total Days | U14: Trips | V14: Days per trip | W14: Total Days
A15: Guatemala | B15: 59.5 | C15: 42.5 | D15: 56 | H15: FY24 | I15: 18 | J15: 6 | K15: =I15*J15 -> 108 | L15: 21 | M15: 2 | N15: =L15*M15 -> 42 | O15: =N15+K15 -> 150 | Q15: FY24 | R15: 16 | S15: 6 | T15: =R15*S15 -> 96 | U15: 21 | V15: 2 | W15: =U15*V15 -> 42 | X15: =W15+T15 -> 138
A16: DR | B16: 65.0475 | C16: 55.75 | D16: 67 | H16: FY25 | I16: 23 | J16: 6 | K16: =I16*J16 -> 138 | L16: 21 | M16: 2 | N16: =L16*M16 -> 42 | O16: =N16+K16 -> 180 | Q16: FY25 | R16: 16 | S16: 6 | T16: =R16*S16 -> 96 | U16: 21 | V16: 2 | W16: =U16*V16 -> 42 | X16: =W16+T16 -> 138
A17: Guyana | B17: 72.072 | C17: 59.5 | D17: 65 | H17: FY26 | I17: 23 | J17: 6 | K17: =I17*J17 -> 138 | L17: 30 | M17: 2 | N17: =L17*M17 -> 60 | O17: =N17+K17 -> 198 | Q17: FY26 | R17: 16 | S17: 6 | T17: =R17*S17 -> 96 | U17: 30 | V17: 2 | W17: =U17*V17 -> 60 | X17: =W17+T17 -> 156
A18: Jamaica | B18: 81.235 | C18: 50.5 | D18: 64 | H18: 1FY27 | I18: 23 | J18: 6 | K18: =I18*J18 -> 138 | L18: 21 | M18: 2 | N18: =L18*M18 -> 42 | O18: =N18+K18 -> 180 | Q18: 1FY27 | R18: 15 | S18: 6 | T18: =R18*S18 -> 90 | U18: 21 | V18: 2 | W18: =U18*V18 -> 42 | X18: =W18+T18 -> 132
H19: FY28 | I19: 17 | J19: 6 | K19: =I19*J19 -> 102 | L19: 21 | M19: 2 | N19: =M19*L19 -> 42 | O19: =N19+K19 -> 144 | Q19: FY28 | R19: 14 | S19: 6 | T19: =R19*S19 -> 84 | U19: 21 | V19: 2 | W19: =V19*U19 -> 42 | X19: =W19+T19 -> 126
I21: Field Staff Travel Days - DR | R21: Field Staff Travel Days - Jamaica
I22: Volunteer Assignments | L22: Data Collection & Follow-up | O22: Total Travel Days | R22: Volunteer Assignments | U22: Data Collection & Follow-up | X22: Total Travel Days
I23: Trips | J23: Days per trip | K23: Total Days | L23: Trips | M23: Days per trip | N23: Total Days | R23: Trips | S23: Days per trip | T23: Total Days | U23: Trips | V23: Days per trip | W23: Total Days
H24: FY24 | I24: 18 | J24: 6 | K24: =I24*J24 -> 108 | L24: 21 | M24: 2 | N24: =L24*M24 -> 42 | O24: =N24+K24 -> 150 | Q24: FY24 | R24: 16 | S24: 6 | T24: =R24*S24 -> 96 | U24: 21 | V24: 2 | W24: =U24*V24 -> 42 | X24: =W24+T24 -> 138
H25: FY25 | I25: 23 | J25: 6 | K25: =I25*J25 -> 138 | L25: 21 | M25: 2 | N25: =L25*M25 -> 42 | O25: =N25+K25 -> 180 | Q25: FY25 | R25: 16 | S25: 6 | T25: =R25*S25 -> 96 | U25: 21 | V25: 2 | W25: =U25*V25 -> 42 | X25: =W25+T25 -> 138
H26: FY26 | I26: 23 | J26: 6 | K26: =I26*J26 -> 138 | L26: 30 | M26: 2 | N26: =L26*M26 -> 60 | O26: =N26+K26 -> 198 | Q26: FY26 | R26: 15 | S26: 6 | T26: =R26*S26 -> 90 | U26: 30 | V26: 2 | W26: =U26*V26 -> 60 | X26: =W26+T26 -> 150
H27: 1FY27 | I27: 23 | J27: 6 | K27: =I27*J27 -> 138 | L27: 21 | M27: 2 | N27: =L27*M27 -> 42 | O27: =N27+K27 -> 180 | Q27: 1FY27 | R27: 15 | S27: 6 | T27: =R27*S27 -> 90 | U27: 21 | V27: 2 | W27: =U27*V27 -> 42 | X27: =W27+T27 -> 132
H28: FY28 | I28: 17 | J28: 6 | K28: =I28*J28 -> 102 | L28: 21 | M28: 2 | N28: =M28*L28 -> 42 | O28: =N28+K28 -> 144 | Q28: FY28 | R28: 15 | S28: 6 | T28: =R28*S28 -> 90 | U28: 21 | V28: 2 | W28: =V28*U28 -> 42 | X28: =W28+T28 -> 132

Sheet HQ Travel
B1: HQ Staff Travel - INTL | H1: HQ Staff Travel - USA | M1: Regional Workshops | N1: Regional Meetings
A2: Country | B2: Flights | C2: Lodging | D2: Per Diem | E2: Other | G2: State/City | H2: Flights | I2: Lodging | J2: Per Diem | K2: Other | M2: Dominican Republic rate as base (15 people) | N2: Rate | O2: Unit | P2: Total
A3: Guatemala | B3: 650 | C3: 85 | D3: 76.5 | E3: 124 | G3: San Francisco | H3: 258 | I3: 165 | J3: 63.2 | K3: 100 | M3: Meeting space (table rental, snacks, and coffee breaks) | N3: 2210 | O3: 1 | P3: =N3*O3 -> 2210
A4: DR | B4: 750 | C4: 92.925 | D4: 100.35 | E4: 124 | G4: Des Moines | H4: 348 | I4: 55.5 | J4: 51.2 | K4: 100 | M4: Hotel Rooms (15) | N4: 65 | O4: =12*5 -> 60 | P4: =O4*N4 -> 3900
A5: Guyana | B5: 850 | C5: 102.96 | D5: 107.1 | E5: 124 | G5: Indianapolis | H5: 260 | I5: 63 | J5: 57.6 | K5: 100 | M5: Flights (12) | N5: 750 | O5: 12 | P5: =O5*N5 -> 9000
A6: Jamaica | B6: 800 | C6: 116.05 | D6: 90.9 | E6: 124 | G6: Fort Lauderdale | H6: 148 | I6: 110 | J6: 62.1 | K6: 100 | M6: Taxis (airport pick-up & drop-off) | N6: 10 | O6: 15 | P6: =O6*N6 -> 150
A7: Average | C7: =AVERAGE(C3:C6) -> 99.23375 | D7: =AVERAGE(D3:D6) -> 93.7125 | E7: =AVERAGE(E3:E6) -> 124 | G7: Average | H7: 253.5 | I7: 98.375 | J7: 58.525 | K7: 100 | M7: 18-seater Van for Host Visits | N7: 300 | O7: 1 | P7: =O7*N7 -> 300
G8: Booking Fee | H8: 65 | M8: Per Diems | N8: 56 | O8: =6*15 -> 90 | P8: =O8*N8 -> 5040
B9: Guyana | C9: Jamaica | D9: DR | E9: Guatemala | G9: Contingency | H9: =(H7+H8)*0.1 -> 31.85 | M9: Total | P9: =SUM(P3:P8) -> 20600
A10: DC | B10: 597 | C10: 468 | D10: 581 | E10: 706 | G10: Total | H10: =ROUND(H9+H7+H8,0) -> 350 | I10: =ROUND(I9+I7+I8,0) -> 98 | J10: =ROUND(J9+J7+J8,0) -> 59 | K10: =ROUND(K9+K7+K8,0) -> 100
A11: Madison, WI | B11: 765 | C11: 1196 | D11: 744 | E11: 617
A12: Miami, FL | B12: 594 | C12: 372 | D12: 368 | E12: 322
A13: Seattle, WA | B13: 874 | C13: 612 | D13: 774 | E13: 457
A14: Average | B14: =AVERAGE(B10:B13) -> 707.5 | C14: =AVERAGE(C10:C13) -> 662 | D14: =AVERAGE(D10:D13) -> 616.75 | E14: =AVERAGE(E10:E13) -> 525.5
A15: Booking Fee | B15: 65 | C15: 65 | D15: 65 | E15: 65
A16: Contingency | B16: =(B14+B15)*0.1 -> 77.25 | C16: =(C14+C15)*0.1 -> 72.7 | D16: =(D14+D15)*0.1 -> 68.175 | E16: =(E14+E15)*0.1 -> 59.05
A17: Total | B17: =B16+B14+B15 -> 849.75 | C17: =C16+C14+C15 -> 799.7 | D17: =D16+D14+D15 -> 749.925 | E17: =E16+E14+E15 -> 649.55

Sheet HQ Expenses
A1: Headquarters
B2: Rate | C2: Unit | D2: Total
A4: Supplies
A5: Laptop, Bag, Accessories, Shipping and Handling | B5: =B26 -> 1105 | C5: 3 | D5: =B5*C5 -> 3315
A6: Camera, Accessories, Memory Card, S&H | B6: =B32 -> 581.3 | C6: 1 | D6: =B6*C6 -> 581.3
A7: Total HQ | D7: =SUM(D5:D6) -> 3896.3
A9: Communications
A10: Linkedin Recruiter Lite (Annuall Fee) | B10: 170 | C10: 12 | D10: =B10*C10 -> 2040
A11: Formstack (Create Forms for Volunteers - Annual Fee) | B11: 500 | C11: 1 | D11: =B11*C11 -> 500
A12: Microsoft 365 Licenses (POA Policy) | B12: 200 | C12: 12 | D12: =B12*C12 -> 2400
A13: PandaDoc (Digital signing platform - quarterly fee) | B13: 480 | C13: 4 | D13: =B13*C13 -> 1920
A14: IT/Comm Reimbursement (POA Policy) | B14: 192 | C14: 12 | D14: =B14*C14 -> 2304
A15: Total Field | D15: =SUM(D10:D14) -> 9164
A17: Total: | D17: =D15+D7 -> 13060.3
A20: Detailed Quotes for Supplies
A21: Item Detail | B21: Price
A23: Laptop
A24: HP Spectre x360 | B24: 1050
A25: Laptop Sleeve | B25: 55
B26: =SUM(B24:B25) -> 1105
A28: Digital Camera
A29: Canon - PowerShot SX730 HS 20.3-Megapixel Digital Camera | B29: 500
A30: Camera Bag | B30: 50.3
A31: SanDisk 256GB Ultra microSDXC UHS-I Memory Card | B31: 31
B32: =SUM(B29:B31) -> 581.3

Sheet FO Expenses
A1: Field Office Supplies | F1: Field Office Rent | K1: Other Field Office Costs
B2: Rate | C2: Unit | D2: Total | G2: Rate | H2: Unit | I2: Total | L2: Rate | M2: Unit | N2: Total
A4: DOM | F4: DOM | K4: DOM
A5: Laptop (and bag) | B5: 1100 | C5: 4 | D5: =C5*B5 -> 4400 | F5: Rent | G5: 850 | H5: 56 | I5: =G5*H5 -> 47600 | K5: Meetings & Events | L5: 65 | M5: 56 | N5: =M5*L5 -> 3640
A6: Tablet | B6: 160 | C6: 2 | D6: =C6*B6 -> 320 | I6: =SUM(I5:I5) -> 47600 | K6: Transportation | L6: 167 | M6: 56 | N6: =M6*L6 -> 9352
A7: Projector | B7: 650 | C7: 1 | D7: =C7*B7 -> 650 | K7: Bank Fees | L7: 71 | M7: 56 | N7: =M7*L7 -> 3976
A8: Supplies | B8: 530 | C8: 1 | D8: =C8*B8 -> 530 | F8: GUA | K8: Payroll Company | L8: =1925/12 -> 160.41667 | M8: 56 | N8: =M8*L8 -> 8983.3333
D9: =SUM(D5:D8) -> 5900 | F9: Rent | G9: 900 | H9: 56 | I9: =G9*H9 -> 50400 | K9: Cell phone stipend | L9: =25*4 -> 100 | M9: 56 | N9: =M9*L9 -> 5600
I10: =SUM(I9:I9) -> 50400 | N10: =SUM(N5:N9) -> 31551.333
A11: GUA | K11: GUA
A12: Laptop (and bag) | B12: 1100 | C12: 4 | D12: =C12*B12 -> 4400 | K12: Meetings & Events | L12: 65 | M12: 56 | N12: =M12*L12 -> 3640
A13: Tablet | B13: 260 | C13: 2 | D13: =C13*B13 -> 520 | F13: GUY | K13: Transportation | L13: 155 | M13: 56 | N13: =M13*L13 -> 8680
A14: Projector | B14: 650 | C14: 1 | D14: =C14*B14 -> 650 | F14: Rent | G14: 1025 | H14: 56 | I14: =G14*H14 -> 57400 | K14: Bank Fees | L14: 60.13 | M14: 56 | N14: =M14*L14 -> 3367.28
A15: Supplies | B15: 530 | C15: 1 | D15: =C15*B15 -> 530 | I15: =SUM(I14:I14) -> 57400 | K15: Payroll Company | L15: =2805/12 -> 233.75 | M15: 56 | N15: =M15*L15 -> 13090
D16: =SUM(D12:D15) -> 6100 | K16: Cell phone stipend | L16: =25*4 -> 100 | M16: 56 | N16: =M16*L16 -> 5600
F17: JAM | N17: =SUM(N12:N16) -> 34377.28
A18: GUY | F18: Rent | G18: 1400 | H18: 56 | I18: =G18*H18 -> 78400 | K18: GUY
A19: Laptop (and bag) | B19: 1100 | C19: 3 | D19: =C19*B19 -> 3300 | I19: =SUM(I18:I18) -> 78400 | K19: Meetings & Events | L19: 75 | M19: 56 | N19: =M19*L19 -> 4200
A20: Tablet | B20: 190 | C20: 2 | D20: =C20*B20 -> 380 | K20: Transportation | L20: 165 | M20: 56 | N20: =M20*L20 -> 9240
A21: Projector | B21: 650 | C21: 1 | D21: =C21*B21 -> 650 | F21: TOTAL | I21: =SUM(I6,I10,I15,I19) -> 233800 | K21: Bank Fees | L21: 60 | M21: 56 | N21: =M21*L21 -> 3360
A22: Supplies | B22: 530 | C22: 1 | D22: =C22*B22 -> 530 | K22: Payroll Company | L22: =1800/12 -> 150 | M22: 56 | N22: =M22*L22 -> 8400
D23: =SUM(D19:D22) -> 4860 | K23: Cell phone stipend | L23: =25*4 -> 100 | M23: 56 | N23: =M23*L23 -> 5600
N24: =SUM(N19:N23) -> 30800
A25: JAM | K25: JAM
A26: Laptop (and bag) | B26: 1100 | C26: 3 | D26: =C26*B26 -> 3300 | K26: Meetings & Events | L26: 75 | M26: 56 | N26: =M26*L26 -> 4200
A27: Tablet | B27: 370 | C27: 2 | D27: =C27*B27 -> 740 | K27: Transportation | L27: 156.5 | M27: 56 | N27: =M27*L27 -> 8764
A28: Projector | B28: 588 | C28: 1 | D28: =C28*B28 -> 588 | K28: Bank Fees | L28: 48 | M28: 56 | N28: =M28*L28 -> 2688
A29: Supplies | B29: 530 | C29: 1 | D29: =C29*B29 -> 530 | K29: Payroll Company | L29: =2400/12 -> 200 | M29: 56 | N29: =M29*L29 -> 11200
D30: =SUM(D26:D29) -> 5158 | K30: Cell phone stipend | L30: =25*4 -> 100 | M30: 56 | N30: =M30*L30 -> 5600
A31: TOTAL | D31: =D30+D23+D16+D9 -> 22018 | N31: =SUM(N26:N30) -> 32452
K32: TOTAL | N32: =SUM(N31,N24,N17,N10) -> 129180.61

Sheet Contractual
A1: Partners of the Americas F2F Caribbean Basin Program Budget
A2: USAID NOFO #7200AA23RFA00006
A4: Contractual | B4: Year 1 | F4: Year 2 | J4: Year 3 | N4: Year 4 | R4: Year 5 | V4: Total | W4: Grand
B5: Rate | C5: Unit | D5: USAID | E5: Total | F5: Rate | G5: Unit | H5: USAID | I5: Total | J5: Rate | K5: Unit | L5: USAID | M5: Total | N5: Rate | O5: Unit | P5: USAID | Q5: Total | R5: Rate | S5: Unit | T5: USAID | U5: Total | V5: USAID | W5: Total
A7: M&E
A8: Database Development | B8: 5000 | C8: 1 | D8: =B8*C8 -> 5000 | E8: =SUM(D8:D8) -> 5000 | G8: 0 | H8: =F8*G8 -> 0 | I8: =SUM(H8:H8) -> 0 | K8: 0 | L8: =J8*K8 -> 0 | M8: =SUM(L8:L8) -> 0 | O8: 0 | P8: =N8*O8 -> 0 | Q8: =SUM(P8:P8) -> 0 | S8: 0 | T8: =R8*S8 -> 0 | U8: =SUM(T8:T8) -> 0 | V8: =D8+H8+L8+P8+T8 -> 5000 | W8: =SUM(V8:V8) -> 5000
A9: Yearly Maintenance | B9: 1000 | C9: 0 | D9: =B9*C9 -> 0 | E9: =SUM(D9:D9) -> 0 | F9: =B9 -> 1000 | G9: 1 | H9: =F9*G9 -> 1000 | I9: =SUM(H9:H9) -> 1000 | J9: =F9 -> 1000 | K9: 1 | L9: =J9*K9 -> 1000 | M9: =SUM(L9:L9) -> 1000 | N9: =J9 -> 1000 | O9: 1 | P9: =N9*O9 -> 1000 | Q9: =SUM(P9:P9) -> 1000 | R9: =N9 -> 1000 | S9: 1 | T9: =R9*S9 -> 1000 | U9: =SUM(T9:T9) -> 1000 | V9: =D9+H9+L9+P9+T9 -> 4000 | W9: =SUM(V9:V9) -> 4000
A10: Other ICT | B10: 2000 | C10: 0 | D10: =B10*C10 -> 0 | E10: =SUM(D10:D10) -> 0 | F10: =B10 -> 2000 | G10: 0 | H10: =F10*G10 -> 0 | I10: =SUM(H10:H10) -> 0 | J10: =F10 -> 2000 | K10: 1 | L10: =J10*K10 -> 2000 | M10: =SUM(L10:L10) -> 2000 | N10: =J10 -> 2000 | O10: 1 | P10: =N10*O10 -> 2000 | Q10: =SUM(P10:P10) -> 2000 | R10: =N10 -> 2000 | S10: 0 | T10: =R10*S10 -> 0 | U10: =SUM(T10:T10) -> 0 | V10: =D10+H10+L10+P10+T10 -> 4000 | W10: =SUM(V10:V10) -> 4000
A11: Subtotal | D11: =SUM(D8:D10) -> 5000 | E11: =SUM(E8:E10) -> 5000 | H11: =SUM(H8:H10) -> 1000 | I11: =SUM(I8:I10) -> 1000 | L11: =SUM(L8:L10) -> 3000 | M11: =SUM(M8:M10) -> 3000 | P11: =SUM(P8:P10) -> 3000 | Q11: =SUM(Q8:Q10) -> 3000 | T11: =SUM(T8:T10) -> 1000 | U11: =SUM(U8:U10) -> 1000 | V11: =D11+H11+L11+P11+T11 -> 13000 | W11: =SUM(V11:V11) -> 13000
A12: IICA
A13: Program Implementation Support | B13: 4000 | C13: 1 | D13: =B13*C13 -> 4000 | E13: =SUM(D13:D13) -> 4000 | F13: 5000 | G13: 1 | H13: =F13*G13 -> 5000 | I13: =SUM(H13:H13) -> 5000 | J13: 5000 | K13: 1 | L13: =J13*K13 -> 5000 | M13: =SUM(L13:L13) -> 5000 | N13: 5000 | O13: 0 | P13: =N13*O13 -> 0 | Q13: =SUM(P13:P13) -> 0 | R13: 5000 | S13: 0 | T13: =R13*S13 -> 0 | U13: =SUM(T13:T13) -> 0 | V13: =D13+H13+L13+P13+T13 -> 14000 | W13: =SUM(V13:V13) -> 14000
A15: Total: | D15: =D11+D13 -> 9000 | E15: =E11+E13 -> 9000 | H15: =H11+H13 -> 6000 | I15: =I11+I13 -> 6000 | L15: =L11+L13 -> 8000 | M15: =M11+M13 -> 8000 | P15: =P11+P13 -> 3000 | Q15: =Q11+Q13 -> 3000 | T15: =T11+T13 -> 1000 | U15: =U11+U13 -> 1000 | V15: =D15+H15+L15+P15+T15 -> 27000 | W15: =SUM(V15:V15) -> 27000

Sheet Leverage
A1: Leverage Formula Summaries | B1: Traditional | C1: Total Days | D1: Paired | E1: Total Days | F1: Grand Total Days | G1: Leverage Total | H1: Avg Days Per Assignment Type
A2: FY24 | B2: ='Volunteer Travel'!C13 -> 60 | C2: =B2*H3 -> 900 | D2: ='Volunteer Travel'!C14 -> 8 | E2: =D2*I3 -> 80 | F2: =C2+E2 -> 980 | G2: =F2*A11 -> 511560 | H2: Traditional | I2: Paired
A3: FY25 | B3: ='Volunteer Travel'!D13 -> 70 | C3: =B3*H3 -> 1050 | D3: ='Volunteer Travel'!D14 -> 8 | E3: =D3*I3 -> 80 | F3: =C3+E3 -> 1130 | G3: =F3*A11 -> 589860 | H3: 15 | I3: 10
A4: FY26 | B4: ='Volunteer Travel'!E13 -> 69 | C4: =B4*H3 -> 1035 | D4: ='Volunteer Travel'!E14 -> 8 | E4: =D4*I3 -> 80 | F4: =C4+E4 -> 1115 | G4: =F4*A11 -> 582030
A5: FY27 | B5: ='Volunteer Travel'!F13 -> 68 | C5: =B5*H3 -> 1020 | D5: ='Volunteer Travel'!F14 -> 8 | E5: =D5*I3 -> 80 | F5: =C5+E5 -> 1100 | G5: =F5*A11 -> 574200
A6: FY28 | B6: ='Volunteer Travel'!G13 -> 57 | C6: =B6*H3 -> 855 | D6: ='Volunteer Travel'!G14 -> 6 | E6: =D6*I3 -> 60 | F6: =C6+E6 -> 915 | G6: =F6*A11 -> 477630
A7: Total | B7: =SUM(B2:B6) -> 324 | C7: =SUM(C2:C6) -> 4860 | D7: =SUM(D2:D6) -> 38 | E7: =SUM(E2:E6) -> 380 | F7: =SUM(F2:F6) -> 5240 | G7: =SUM(G2:G6) -> 2735280
A8: LOP Total
A10: Leverage value per assignment day
A11: 522
