Workbook
Name inf: #REF!
Name TRM: 'Activity 2 Sub Budget'!$B$1
Name TRM: 'Agrosavia Sub Budget'!$B$1

Sheet Project Funds Snapshots
B2: FFPR Program Budget Summary Sheet
C3: Total USDA Project | D3: Direct $ | E3: Direct % | F3: Indirect Costs $
B5: OVERALL PROJECT BUDGET | C5: =C6+C7 -> 25487876 | D5: ='Program Budget'!W534-'Activity 2 Sub Budget'!P46-'CIAT Sub Budget'!P71-'CIAT Sub Budget'!P116-'CIAT Sub Budget'!P152-'Agrosavia Sub Budget'!P43 -> 18689315 | E5: =D5/$C$5 -> 0.73326294 | F5: ='Program Budget'!W536+'Activity 2 Sub Budget'!P46+'CIAT Sub Budget'!P71+'CIAT Sub Budget'!P116+'CIAT Sub Budget'!P152+'Agrosavia Sub Budget'!P43 -> 4820633
B6: USDA | C6: ='USDA Budget Summary'!B65+'USDA Budget Summary'!C65 -> 23509948
B7: Cost Share | C7: ='USDA Budget Summary'!D65 -> 1977928 | D7: ='USDA Budget Summary'!D36 -> 1977928.1 | E7: =D7/$C$5 -> 0.077602703 | F7: 0
C9: Total USDA Project | D9: Direct $ | E9: Direct % | F9: Indirect Costs $ | G9: Cost Share $ | H9: % of Direct Funds by Partner | K9: =C9 -> Total USDA Project
B11: BUDGET BY PARTNER | J11: TOTAL | K11: =SUM(K12:K16)*-1 -> 25487876
B12: Prime | C12: =C5-SUM(C13:C16) -> 21850530 | D12: =C12-F12-G12 -> 15455142 | E12: =D12/SUM($C$12:$C$16) -> 0.60637229 | F12: ='Indirect Calculations'!I72 -> 4572464.1 | G12: ='USDA Budget Summary'!D65-SUM(G13:G16) -> 1822924 | H12: =(G12+D12)/SUM($C$12:$C$16) -> 0.67789351 | J12: POA | K12: =-C12 -> -21850530
B13: Sub 1 - CIAT | C13: ='CIAT Sub Budget'!P156+G13 -> 1776970.4 | D13: ='CIAT Sub Budget'!P69+'CIAT Sub Budget'!P114+'CIAT Sub Budget'!P150 -> 1474514.9 | E13: =D13/SUM($C$12:$C$16) -> 0.057851619 | F13: ='CIAT Sub Budget'!P71+'CIAT Sub Budget'!P116+'CIAT Sub Budget'!P152 -> 147451.49 | G13: ='Program Budget'!X160+'Program Budget'!X260 -> 155004 | H13: =(G13+D13)/SUM($C$12:$C$16) -> 0.063933098 | J13: CIAT | K13: =-C13 -> -1776970.4
B14: Sub 2 - TBD | C14: ='Activity 2 Sub Budget'!P50 -> 1000773.2 | D14: ='Activity 2 Sub Budget'!P44 -> 909793.81 | E14: =D14/SUM($C$12:$C$16) -> 0.03569516 | F14: ='Activity 2 Sub Budget'!P46 -> 90979.381 | G14: ='Activity 2 Sub Budget'!Q50 -> 0 | H14: =(G14+D14)/SUM($C$12:$C$16) -> 0.03569516 | J14: TBD | K14: =-C14 -> -1000773.2
B15: Sub 3 - Agrosavia | C15: ='Agrosavia Sub Budget'!P47 -> 334340.21 | D15: ='Agrosavia Sub Budget'!P41 -> 324602.14 | E15: =D15/SUM($C$12:$C$16) -> 0.012735551 | F15: ='Agrosavia Sub Budget'!P43 -> 9738.0643 | G15: ='Agrosavia Sub Budget'!Q47 -> 0 | H15: =(G15+D15)/SUM($C$12:$C$16) -> 0.012735551 | J15: Agrosavia | K15: =-C15 -> -334340.21
B16: Monetization Agent | C16: ='Program Budget'!Y66 -> 525262.5 | D16: ='Program Budget'!Y66 -> 525262.5 | E16: =D16/SUM($C$12:$C$16) -> 0.020608328 | F16: 0 | G16: 0 | H16: =(G16+D16)/SUM($C$12:$C$16) -> 0.020608328 | J16: Monetization | K16: =-C16 -> -525262.5
C18: Total USDA Project | D18: Direct $ | E18: Direct % | F18: Indirect Costs $ | G18: Cost Share $ | H18: % of Direct Funds by Activity | K18: =C18 -> Total USDA Project
B20: BUDGET BY ACTIVITY | K20: =SUM(K21:K29)*-1 -> 25487876
B21: Admin | C21: ='USDA Budget Summary'!F25+'USDA Budget Summary'!E57 -> 6605294.3 | D21: ='USDA Budget Summary'!E25-'CIAT Sub Budget'!P71 -> 5040229.9 | E21: =D21/SUM($C$21:$C$29) -> 0.1977501 | F21: ='USDA Budget Summary'!E57+'CIAT Sub Budget'!P71 -> 1565064.4 | G21: ='USDA Budget Summary'!D25 -> 0 | H21: =(G21+D21)/SUM($C$21:$C$29) -> 0.1977501 | J21: =B21 -> Admin | K21: =C21*-1 -> -6605294.3
B22: Activity 1 | C22: ='USDA Budget Summary'!F28+('USDA Budget Summary'!E28*0.2869) -> 303709.1 | D22: ='USDA Budget Summary'!B28 -> 154064.11 | E22: =D22/SUM($C$21:$C$29) -> 0.0060446038 | F22: =D22*0.2869 -> 44200.994 | G22: ='Program Budget'!X163 -> 105444 | H22: =(G22+D22)/SUM($C$21:$C$29) -> 0.01018163 | J22: =B22 -> Activity 1 | K22: =C22*-1 -> -303709.1
B23: Activity 2 | C23: ='USDA Budget Summary'!F29+('USDA Budget Summary'!E29*0.2869) -> 2142038.8 | D23: ='USDA Budget Summary'!B29-'Activity 2 Sub Budget'!P46 -> 1493538.2 | E23: =D23/SUM($C$21:$C$29) -> 0.058597988 | F23: =('USDA Budget Summary'!B29*0.2869)+'Activity 2 Sub Budget'!P46 -> 545577.49 | G23: ='Program Budget'!X206 -> 102923.08 | H23: =(G23+D23)/SUM($C$21:$C$29) -> 0.062636107 | J23: =B23 -> Activity 2 | K23: =C23*-1 -> -2142038.8
B24: Activity 3 | C24: ='USDA Budget Summary'!F30+('USDA Budget Summary'!E30*0.2869) -> 5815755.9 | D24: ='USDA Budget Summary'!B30-'CIAT Sub Budget'!P116-'CIAT Sub Budget'!P152 -> 4344411.4 | E24: =D24/SUM($C$21:$C$29) -> 0.17045012 | F24: =('USDA Budget Summary'!B30*0.2869)+'CIAT Sub Budget'!P116+'CIAT Sub Budget'!P152 -> 1317144.5 | G24: ='Program Budget'!X265 -> 154200 | H24: =(G24+D24)/SUM($C$21:$C$29) -> 0.17650005 | J24: =B24 -> Activity 3 | K24: =C24*-1 -> -5815755.9
B25: Activity 4 | C25: ='USDA Budget Summary'!F31+('USDA Budget Summary'!E31*0.2869) -> 2209425.6 | D25: ='USDA Budget Summary'!B31-'Agrosavia Sub Budget'!P43 -> 1698961.6 | E25: =D25/SUM($C$21:$C$29) -> 0.066657638 | F25: ='USDA Budget Summary'!B31*0.2869+'Agrosavia Sub Budget'!P43 -> 499964 | G25: ='USDA Budget Summary'!D31 -> 10500 | H25: =(G25+D25)/SUM($C$21:$C$29) -> 0.067069598 | J25: =B25 -> Activity 4 | K25: =C25*-1 -> -2209425.6
B26: Activity 5 | C26: ='USDA Budget Summary'!F32+('USDA Budget Summary'!E32*0.2869) -> 1440644.1 | D26: ='USDA Budget Summary'!B32 -> 618622.73 | E26: =D26/SUM($C$21:$C$29) -> 0.024271255 | F26: =D26*0.2869 -> 177482.86 | G26: ='Program Budget'!X367 -> 644538.46 | H26: =(G26+D26)/SUM($C$21:$C$29) -> 0.049559296 | J26: =B26 -> Activity 5 | K26: =C26*-1 -> -1440644.1
B27: Activity 6 | C27: ='USDA Budget Summary'!F33+('USDA Budget Summary'!E33*0.2869) -> 2135277.4 | D27: ='USDA Budget Summary'!B33 -> 1146739.4 | E27: =D27/SUM($C$21:$C$29) -> 0.044991565 | F27: =D27*0.2869 -> 328999.54 | G27: ='Program Budget'!X433 -> 659538.46 | H27: =(G27+D27)/SUM($C$21:$C$29) -> 0.070868122 | J27: =B27 -> Activity 6 | K27: =C27*-1 -> -2135277.4
B28: Activity 7 | C28: ='USDA Budget Summary'!F34+('USDA Budget Summary'!E34*0.2869) -> 1052406.8 | D28: ='USDA Budget Summary'!B34 -> 813122.07 | E28: =D28/SUM($C$21:$C$29) -> 0.031902308 | F28: =D28*0.2869 -> 233284.72 | G28: ='Program Budget'!X479 -> 6000 | H28: =(G28+D28)/SUM($C$21:$C$29) -> 0.032137714 | J28: =B28 -> Activity 7 | K28: =C28*-1 -> -1052406.8
B29: Activity 8 | C29: ='USDA Budget Summary'!F35+(('USDA Budget Summary'!E35-3000000)*0.2869) -> 3783323.9 | D29: ='USDA Budget Summary'!B35 -> 3379625.3 | E29: =D29/SUM($C$21:$C$29) -> 0.13259737 | F29: =(D29-3000000)*0.2869 -> 108914.5 | G29: ='Program Budget'!X526 -> 294784.07 | H29: =(G29+D29)/SUM($C$21:$C$29) -> 0.14416303 | J29: =B29 -> Activity 8 | K29: =C29*-1 -> -3783323.9
C31: Total USDA Project | D31: Direct $ | E31: Direct % | F31: Indirect Costs $ | G31: Cost Share $ | H31: % of Direct Funds by Activity
B32: DIRECT COST DETAILS BY ACTIVITY & PARTNER
B33: =CONCATENATE(B21," - ",B12) -> Admin - Prime | C33: ='USDA Budget Summary'!E25+'USDA Budget Summary'!E57-C34-C35 -> 5062667 | D33: ='USDA Budget Summary'!E25-D34-D35-F34-F35 -> 3590090.4 | E33: =D33/SUM($C$33:$C$46) -> 0.14085483 | F33: ='Indirect Calculations'!I46 -> 1472576.7 | G33: ='USDA Budget Summary'!D25 -> 0 | H33: =(G33+D33)/SUM($C$33:$C$46) -> 0.14085483
B34: Admin - Sub 1 - CIAT | C34: ='CIAT Sub Budget'!P73 -> 1017364.7 | D34: ='CIAT Sub Budget'!P69 -> 924877.04 | E34: =D34/SUM($C$33:$C$46) -> 0.036286941 | F34: ='CIAT Sub Budget'!P71 -> 92487.704 | G34: 0 | H34: =(G34+D34)/SUM($C$33:$C$46) -> 0.036286941
B35: =CONCATENATE(B21," - ",B16) -> Admin - Monetization Agent | C35: ='Program Budget'!Y66 -> 525262.5 | D35: ='Program Budget'!Y66 -> 525262.5 | E35: =D35/SUM($C$33:$C$46) -> 0.020608328 | F35: 0 | G35: 0 | H35: =(G35+D35)/SUM($C$33:$C$46) -> 0.020608328
B36: =CONCATENATE(B22," - ",B12) -> Activity 1 - Prime | C36: =('USDA Budget Summary'!F28+('USDA Budget Summary'!B28*0.2869)) -> 303709.1 | D36: ='USDA Budget Summary'!B28 -> 154064.11 | E36: =D36/SUM($C$33:$C$46) -> 0.0060446038 | F36: ='USDA Budget Summary'!B28*0.2869 -> 44200.994 | G36: ='Program Budget'!X163 -> 105444 | H36: =(G36+D36)/SUM($C$33:$C$46) -> 0.01018163
B37: =CONCATENATE(B23," - ",B12) -> Activity 2 - Prime | C37: ='USDA Budget Summary'!F29+('USDA Budget Summary'!B29*0.2869)-C38 -> 1141265.6 | D37: ='USDA Budget Summary'!B29-D38-F38 -> 583744.42 | E37: =D37/SUM($C$33:$C$46) -> 0.022902827 | F37: ='USDA Budget Summary'!B29*0.2869 -> 454598.1 | G37: ='Program Budget'!X206 -> 102923.08 | H37: =(G37+D37)/SUM($C$33:$C$46) -> 0.026940946
B38: Activity 2 - Sub 1 - TBD | C38: ='Activity 2 Sub Budget'!P48 -> 1000773.2 | D38: ='Activity 2 Sub Budget'!P44 -> 909793.81 | E38: =D38/SUM($C$33:$C$46) -> 0.03569516 | F38: ='Activity 2 Sub Budget'!P46 -> 90979.381 | G38: ='Activity 2 Sub Budget'!Q48 -> 0 | H38: =(G38+D38)/SUM($C$33:$C$46) -> 0.03569516
B39: =CONCATENATE(B24," - ",B12) -> Activity 3 - Prime | C39: =('USDA Budget Summary'!F30+('USDA Budget Summary'!B30*0.2869))-C40 -> 5151154.3 | D39: ='USDA Budget Summary'!B30-'Project Funds Snapshots'!D40-'Project Funds Snapshots'!F40 -> 3794773.6 | E39: =D39/SUM($C$33:$C$46) -> 0.14888544 | F39: ='USDA Budget Summary'!B30*0.2869 -> 1262180.7 | G39: ='Program Budget'!X265-G40 -> 94200 | H39: =(G39+D39)/SUM($C$33:$C$46) -> 0.15258131
B40: Activity 3 - Sub 1 - CIAT | C40: ='CIAT Sub Budget'!P118+'CIAT Sub Budget'!P154+'Program Budget'!X260 -> 664601.62 | D40: ='CIAT Sub Budget'!P150+'CIAT Sub Budget'!P114 -> 549637.84 | E40: =D40/SUM($C$33:$C$46) -> 0.021564678 | F40: ='CIAT Sub Budget'!P116+'CIAT Sub Budget'!P152 -> 54963.784 | G40: ='Program Budget'!X260 -> 60000 | H40: =(G40+D40)/SUM($C$33:$C$46) -> 0.023918738
B41: =CONCATENATE(B25," - ",B12) -> Activity 4 - Prime | C41: ='USDA Budget Summary'!F31+('USDA Budget Summary'!B31*0.2869)-C42 -> 1875085.4 | D41: ='USDA Budget Summary'!B31-D42-F42 -> 1374359.5 | E41: =D41/SUM($C$33:$C$46) -> 0.053922087 | F41: ='USDA Budget Summary'!B31*0.2869 -> 490225.93 | G41: ='Program Budget'!X313 -> 10500 | H41: =(G41+D41)/SUM($C$33:$C$46) -> 0.054334047
B42: Activity 4 - Sub 1 - Agrosavia | C42: ='Agrosavia Sub Budget'!P45 -> 334340.21 | D42: ='Agrosavia Sub Budget'!P41 -> 324602.14 | E42: =D42/SUM($C$33:$C$46) -> 0.012735551 | F42: ='Agrosavia Sub Budget'!P43 -> 9738.0643 | G42: ='Agrosavia Sub Budget'!Q45 -> 0 | H42: =(G42+D42)/SUM($C$33:$C$46) -> 0.012735551
B43: =CONCATENATE(B26," - ",B12) -> Activity 5 - Prime | C43: ='USDA Budget Summary'!F32+('USDA Budget Summary'!B32*0.2869) -> 1440644.1 | D43: ='USDA Budget Summary'!B32 -> 618622.73 | E43: =D43/SUM($C$33:$C$46) -> 0.024271255 | F43: =D43*0.2869 -> 177482.86 | G43: ='Program Budget'!X367 -> 644538.46 | H43: =(G43+D43)/SUM($C$33:$C$46) -> 0.049559296
B44: =CONCATENATE(B27," - ",B12) -> Activity 6 - Prime | C44: ='USDA Budget Summary'!F33+('USDA Budget Summary'!B33*0.2869) -> 2135277.4 | D44: ='USDA Budget Summary'!B33 -> 1146739.4 | E44: =D44/SUM($C$33:$C$46) -> 0.044991565 | F44: =D44*0.2869 -> 328999.54 | G44: ='Program Budget'!X433 -> 659538.46 | H44: =(G44+D44)/SUM($C$33:$C$46) -> 0.070868122
B45: =CONCATENATE(B28," - ",B12) -> Activity 7 - Prime | C45: ='USDA Budget Summary'!F34+('USDA Budget Summary'!B34*0.2869) -> 1052406.8 | D45: ='USDA Budget Summary'!B34 -> 813122.07 | E45: =D45/SUM($C$33:$C$46) -> 0.031902308 | F45: =D45*0.2869 -> 233284.72 | G45: ='Program Budget'!X479 -> 6000 | H45: =(G45+D45)/SUM($C$33:$C$46) -> 0.032137714
B46: =CONCATENATE(B29," - ",B12) -> Activity 8 - Prime | C46: ='USDA Budget Summary'!F35+(('USDA Budget Summary'!B35-3000000)*0.2869) -> 3783323.9 | D46: ='USDA Budget Summary'!B35 -> 3379625.3 | E46: =D46/SUM($C$33:$C$46) -> 0.13259737 | F46: =(D46-3000000)*0.2869 -> 108914.5 | G46: ='Program Budget'!X526 -> 294784.07 | H46: =(G46+D46)/SUM($C$33:$C$46) -> 0.14416303
C48: Total USDA Project | D48: Direct $ | E48: Direct % | F48: Indirect Costs $ | G48: Cost Share $ | H48: % of Direct Funds by Activity | L48: Column Labels
A49: Category | B49: BUDGET BY CROP | C49: Total USDA Project | D49: Direct $ | E49: Direct % | F49: Indirect Costs $ | G49: Cost Share $ | H49: % of Direct Funds by Activity | I49: Crop | L49: Cacao | M49: Complementary | N49: Grand Total
A50: Admin | B50: Admin - Cacao | C50: =C21-C51 -> 3302647.1 | D50: =C50-F50 -> 2520114.9 | E50: =D50/SUM($C$51:$C$67) -> 0.11359427 | F50: =(('USDA Budget Summary'!E25*0.2869)*0.5)+('CIAT Sub Budget'!P71*0.5) -> 782532.19 | G50: ='USDA Budget Summary'!D24 -> 0 | H50: =(G50+D50)/SUM($C$51:$C$67) -> 0.11359427 | I50: Cacao | K50: Sum of Total USDA Project | L50: 12952230 | M50: 12535647 | N50: 25487876
A51: Admin | B51: Admin - Complementary Crops | C51: ='Program Budget'!AB32+'Program Budget'!AB44+'Program Budget'!AB61+'Program Budget'!AB84+'Program Budget'!AB89+'Program Budget'!AB102+'Program Budget'!AB113+'Program Budget'!AB125+(('Program Budget'!AB32+'Program Budget'!AB44+'Program Budget'!AB61+'Program Budget'!AB84+'Program Budget'!AB89+'Program Budget'!AB102+'Program Budget'!AB113+'Program Budget'!AB125)*0.2869) -> 3302647.1 | D51: =C51-F51 -> 2520114.9 | E51: =D51/SUM($C$51:$C$67) -> 0.11359427 | F51: =(('USDA Budget Summary'!E25*0.2869)*0.5)+('CIAT Sub Budget'!P71*0.5) -> 782532.19 | G51: ='USDA Budget Summary'!D25 -> 0 | H51: =(G51+D51)/SUM($C$51:$C$67) -> 0.11359427 | I51: Complementary
A52: Activity 1 | B52: Activity 1 - Cacao | C52: ='Program Budget'!AA163+('Program Budget'!AA163*0.2869)+G52 -> 151854.55 | D52: ='Program Budget'!AA163 -> 77032.056 | E52: =D52/SUM($C$51:$C$67) -> 0.0034722227 | F52: ='Program Budget'!AA163*0.2869 -> 22100.497 | G52: ='Program Budget'!X163*0.5 -> 52722 | H52: =(G52+D52)/SUM($C$51:$C$67) -> 0.0058486688 | I52: Cacao
A53: Activity 1 | B53: Activity 1 - Complementary Crops | C53: ='Program Budget'!AB163+('Program Budget'!AB163*0.2869)+G53 -> 151854.55 | D53: =C53-G53-F53 -> 77032.056 | E53: =D53/SUM($C$51:$C$67) -> 0.0034722227 | F53: ='Program Budget'!AB163*0.2869 -> 22100.497 | G53: ='Program Budget'!X163*0.5 -> 52722 | H53: =(G53+D53)/SUM($C$51:$C$67) -> 0.0058486688 | I53: Complementary
A54: Activity 2 | B54: Activity 2 - Cacao | C54: ='Program Budget'!AA206+('Program Budget'!AA206*0.2869)+G54 -> 1071019.4 | D54: =C54-F54-G54 -> 746769.12 | E54: =D54/SUM($C$51:$C$67) -> 0.033660645 | F54: ='Program Budget'!AA206*0.2869+('Activity 2 Sub Budget'!P46*0.5) -> 272788.74 | G54: ='Program Budget'!X206*0.5 -> 51461.538 | H54: =(G54+D54)/SUM($C$51:$C$67) -> 0.035980276 | I54: Cacao
A55: Activity 2 | B55: Activity 2 - Complementary Crops | C55: ='Program Budget'!AB206+('Program Budget'!AB206*0.2869)+G55 -> 1071019.4 | D55: =C55-F55-G55 -> 746769.12 | E55: =D55/SUM($C$51:$C$67) -> 0.033660645 | F55: ='Program Budget'!AB206*0.2869+('Activity 2 Sub Budget'!P46*0.5) -> 272788.74 | G55: ='Program Budget'!X206*0.5 -> 51461.538 | H55: =(G55+D55)/SUM($C$51:$C$67) -> 0.035980276 | I55: Complementary
A56: Activity 3 | B56: Activity 3 - Cacao | C56: ='Program Budget'!AA265+('Program Budget'!AA265*0.2869)+'Program Budget'!AD265 -> 3027373.2 | D56: =C56-G56-F56 -> 2270238.8 | E56: =D56/SUM($C$51:$C$67) -> 0.1023311 | F56: ='Program Budget'!AA265*0.2869+'CIAT Sub Budget'!P152+('CIAT Sub Budget'!P116*0.5) -> 706134.39 | G56: ='Program Budget'!AD265 -> 51000 | H56: =(G56+D56)/SUM($C$51:$C$67) -> 0.10462992 | I56: Cacao
A57: Activity 3 | B57: Activity 3 - Complementary Crops | C57: ='Program Budget'!AB265+('Program Budget'!AB265*0.2869)+'Program Budget'!AE265 -> 2788382.8 | D57: =C57-G57-F57 -> 2074172.7 | E57: =D57/SUM($C$51:$C$67) -> 0.093493409 | F57: ='Program Budget'!AB265*0.2869+'CIAT Sub Budget'!P116*0.5 -> 611010.14 | G57: ='Program Budget'!AE265 -> 103200 | H57: =(G57+D57)/SUM($C$51:$C$67) -> 0.098145152 | I57: Complementary
A58: Activity 4 | B58: Activity 4 - Cacao | C58: ='Program Budget'!AA313+('Program Budget'!AA313*0.2869)+G58 -> 1104712.8 | D58: ='Program Budget'!AA313-('Agrosavia Sub Budget'!P43*0.5) -> 849480.8 | E58: =D58/SUM($C$51:$C$67) -> 0.038290378 | F58: ='Program Budget'!AA313*0.2869+('Agrosavia Sub Budget'!P43*0.5) -> 249982 | G58: ='Program Budget'!X313*0.5 -> 5250 | H58: =(G58+D58)/SUM($C$51:$C$67) -> 0.038527022 | I58: Cacao
A59: Activity 4 | B59: Activity 4 - Complementary Crops | C59: ='Program Budget'!AB313+('Program Budget'!AB313*0.2869)+G59 -> 1104712.8 | D59: ='Program Budget'!AB313-('Agrosavia Sub Budget'!P43*0.5) -> 849480.8 | E59: =D59/SUM($C$51:$C$67) -> 0.038290378 | F59: ='Program Budget'!AB313*0.2869+('Agrosavia Sub Budget'!P43*0.5) -> 249982 | G59: ='Program Budget'!X313*0.5 -> 5250 | H59: =(G59+D59)/SUM($C$51:$C$67) -> 0.038527022 | I59: Complementary
A60: Activity 5 | B60: Activity 5 - Cacao | C60: ='Program Budget'!AA367+('Program Budget'!AA367*0.2869)+G60 -> 720322.03 | D60: ='Program Budget'!AA367 -> 309311.37 | E60: =D60/SUM($C$51:$C$67) -> 0.013942221 | F60: =D60*0.2869 -> 88741.431 | G60: ='Program Budget'!X367*0.5 -> 322269.23 | H60: =(G60+D60)/SUM($C$51:$C$67) -> 0.028468519 | I60: Cacao
A61: Activity 5 | B61: Activity 5 - Complementary Crops | C61: ='Program Budget'!AB367+('Program Budget'!AB367*0.2869)+G61 -> 720322.03 | D61: ='Program Budget'!AB367 -> 309311.37 | E61: =D61/SUM($C$51:$C$67) -> 0.013942221 | F61: =D61*0.2869 -> 88741.431 | G61: ='Program Budget'!X367*0.5 -> 322269.23 | H61: =(G61+D61)/SUM($C$51:$C$67) -> 0.028468519 | I61: Complementary
A62: Activity 6 | B62: Activity 6 - Cacao | C62: ='Program Budget'!AA433+('Program Budget'!AA433*0.2869)+G62 -> 1067638.7 | D62: ='Program Budget'!AA433 -> 573369.71 | E62: =D62/SUM($C$51:$C$67) -> 0.025844661 | F62: =D62*0.2869 -> 164499.77 | G62: ='Program Budget'!X433*0.5 -> 329769.23 | H62: =(G62+D62)/SUM($C$51:$C$67) -> 0.040709021 | I62: Cacao
A63: Activity 6 | B63: Activity 6 - Complementary Crops | C63: ='Program Budget'!AB433+('Program Budget'!AB433*0.2869)+'Project Funds Snapshots'!G63 -> 1067638.7 | D63: ='Program Budget'!AB433 -> 573369.71 | E63: =D63/SUM($C$51:$C$67) -> 0.025844661 | F63: =D63*0.2869 -> 164499.77 | G63: ='Program Budget'!X433*0.5 -> 329769.23 | H63: =(G63+D63)/SUM($C$51:$C$67) -> 0.040709021 | I63: Complementary
A64: Activity 7 | B64: Activity 7 - Cacao | C64: ='Program Budget'!AA479+('Program Budget'!AA479*0.2869)+G64 -> 526203.39 | D64: ='Program Budget'!W479*0.5 -> 406561.03 | E64: =D64/SUM($C$51:$C$67) -> 0.018325753 | F64: =D64*0.2869 -> 116642.36 | G64: ='Program Budget'!X479*0.5 -> 3000 | H64: =(G64+D64)/SUM($C$51:$C$67) -> 0.018460979 | I64: Cacao
A65: Activity 7 | B65: Activity 7 - Complementary Crops | C65: =('Program Budget'!AB479)+(('Program Budget'!AB479)*0.2869)+G65 -> 526203.39 | D65: ='Program Budget'!W479*0.5 -> 406561.03 | E65: =D65/SUM($C$51:$C$67) -> 0.018325753 | F65: =D65*0.2869 -> 116642.36 | G65: ='Program Budget'!X479*0.5 -> 3000 | H65: =(G65+D65)/SUM($C$51:$C$67) -> 0.018460979 | I65: Complementary
A66: Activity 8 | B66: Activity 8 - Cacao | C66: ='Program Budget'!AA526+(('Program Budget'!AA526-1500000)*0.2869)+G66 -> 1891661.9 | D66: ='Program Budget'!AA526 -> 1689812.7 | E66: =D66/SUM($C$51:$C$67) -> 0.076168368 | F66: =(D66-1500000)*0.2869 -> 54457.251 | G66: ='Program Budget'!X526*0.5 -> 147392.03 | H66: =(G66+D66)/SUM($C$51:$C$67) -> 0.082812069 | I66: Cacao
A67: Activity 8 | B67: Activity 8 - Complementary Crops | C67: ='Program Budget'!AB526+(('Program Budget'!AB526-1500000)*0.2869)+G67 -> 1891661.9 | D67: ='Program Budget'!AB526 -> 1689812.7 | E67: =D67/SUM($C$51:$C$67) -> 0.076168368 | F67: =(D66-1500000)*0.2869 -> 54457.251 | G67: ='Program Budget'!X526*0.5 -> 147392.03 | H67: =(G67+D67)/SUM($C$51:$C$67) -> 0.082812069 | I67: Complementary
K68: Row Labels | L68: Sum of Total USDA Project
K69: Activity 1 | L69: 303709.1
K70: Cacao | L70: 151854.55
K71: Complementary | L71: 151854.55
K72: Activity 2 | L72: 2142038.8
K73: Cacao | L73: 1071019.4
K74: Complementary | L74: 1071019.4
K75: Activity 3 | L75: 5815937.4
K76: Cacao | L76: 3116260
K77: Complementary | L77: 2699677.4
K78: Activity 4 | L78: 2209425.6
K79: Cacao | L79: 1104712.8
K80: Complementary | L80: 1104712.8
... K96: Grand Total | L96: 25487876

Sheet USDA Budget Summary
A1: ATTACHMENT C -1
A2: Proposed Budget Summary
A4: Program (FFPr or MGD): | B4: FFPr
A5: Country of Operation: | B5: Colombia
A6: Implementing Organization: | B6: Partners of the Americas Inc.
A7: Fiscal Year: | B7: 2020
A8: Agreement Number: | B8: USDA-FAS-10.606-0700-20-(514)
A10: Total Amount of Federal Funds Requested
A11: Funding Source (FAS for MGD) (CCC for FFPr) | B11: Funding Year | C11: Commodity Cost | D11: Freight Cost | E11: Administrative Costs (cash portion) | F11: Total Federal Funding Obligated
B12: 2020 | C12: 21924000 | D12: 9591750 | E12: 2280000 | F12: =E12+D12+C12 -> 33795750
A14: Project Operating Budget
A15: Expense Type | B15: Monetization Proceeds (FFPr Only) | C15: FAS or CCC Funds (CCC is Admin Only) | D15: Cost Share | E15: Total w/out Cost Share | F15: Total w/Cost Share
A16: Administration
A17: Salaries/Personnel | B17: ='Program Budget'!W32-C17 -> 843769.36 | C17: 430000 | D17: ='Program Budget'!X32 -> 0 | E17: =B17+C17 -> 1273769.4 | F17: =B17+C17+D17 -> 1273769.4
A18: Benefits | B18: ='Program Budget'!W44-C18 -> 499261.89 | C18: 225648 | D18: ='Program Budget'!X44 -> 0 | E18: =B18+C18 -> 724909.89 | F18: =B18+C18+D18 -> 724909.89
A19: Travel | B19: ='Program Budget'!W61-C19 -> 116709.46 | C19: 39104 | D19: ='Program Budget'!X61 -> 0 | E19: =B19+C19 -> 155813.46 | F19: =B19+C19+D19 -> 155813.46
A20: Professional Services/Contractual | B20: ='Program Budget'!W84-C20 -> 1619480 | C20: 862147.25 | D20: ='Program Budget'!X84 -> 0 | E20: =B20+C20 -> 2481627.2 | F20: =B20+C20+D20 -> 2481627.2
A21: Equipment | B21: ='Program Budget'!W89-C21 -> 0 | C21: 100000 | D21: ='Program Budget'!X89 -> 0 | E21: =B21+C21 -> 100000 | F21: =B21+C21+D21 -> 100000
A22: Office | B22: ='Program Budget'!W102-C22 -> 168021.71 | C22: 53944 | D22: ='Program Budget'!X102 -> 0 | E22: =B22+C22 -> 221965.71 | F22: =B22+C22+D22 -> 221965.71
A23: Supplies | B23: ='Program Budget'!W113-C23 -> 45495.646 | C23: 41096 | D23: ='Program Budget'!X113 -> 0 | E23: =B23+C23 -> 86591.646 | F23: =B23+C23+D23 -> 86591.646
A24: Other | B24: ='Program Budget'!W125-C24 -> 68280.29 | C24: ='Program Budget'!M125 -> 19760 | D24: 0 | E24: =B24+C24 -> 88040.29 | F24: =B24+C24+D24 -> 88040.29
A25: Total Administration | B25: =SUM(B17:B24) -> 3361018.4 | C25: =SUM(C17:C24) -> 1771699.2 | D25: =SUM(D17:D24) -> 0 | E25: =SUM(E17:E24) -> 5132717.6 | F25: =SUM(F17:F24) -> 5132717.6
A27: Activities
A28: Activity 1: Value Chain Development (Value Chain Analysis, Carbon Assessment, and Living Incomes) | B28: ='Program Budget'!W163 -> 154064.11 | C28: 0 | D28: ='Program Budget'!X163 -> 105444 | E28: =B28+C28 -> 154064.11 | F28: =B28+C28+D28 -> 259508.11 | G28: =B28/$B$36 -> 0.011160212
A29: Activity 2: Producer Organization Development & Commercialization | B29: ='Program Budget'!W206 -> 1584517.6 | C29: 0 | D29: ='Program Budget'!X206 -> 102923.08 | E29: =B29+C29 -> 1584517.6 | F29: =B29+C29+D29 -> 1687440.7 | G29: =B29/$B$36 -> 0.11478048
A30: Activity 3: Agriculture Extension and Production Support | B30: ='Program Budget'!W265 -> 4399375.2 | C30: 0 | D30: =ROUND('Program Budget'!X265,0) -> 154200 | E30: =B30+C30 -> 4399375.2 | F30: =B30+C30+D30 -> 4553575.2 | G30: =B30/$B$36 -> 0.31868524
A31: Activity 4: Post-Harvest Aggregation & Processing | B31: ='Program Budget'!W313 -> 1708699.7 | C31: 0 | D31: ='Program Budget'!X313 -> 10500 | E31: =B31+C31 -> 1708699.7 | F31: =B31+C31+D31 -> 1719199.7 | G31: =B31/$B$36 -> 0.12377607
A32: Activity 5: Ensure Financial Service/ Capital Access for Actors in the Value Chains | B32: ='Program Budget'!W367 -> 618622.73 | C32: 0 | D32: ='Program Budget'!X367 -> 644538.46 | E32: =B32+C32 -> 618622.73 | F32: =B32+C32+D32 -> 1263161.2 | G32: =B32/$B$36 -> 0.044812257
A33: Activity 6: Innovation and Job Creation Through Youth Engagement | B33: ='Program Budget'!W433 -> 1146739.4 | C33: 0 | D33: ='Program Budget'!X433 -> 659538.46 | E33: =B33+C33 -> 1146739.4 | F33: =B33+C33+D33 -> 1806277.9 | G33: =B33/$B$36 -> 0.08306837
A34: Activity 7: Establishment of Regional Community of Practice | B34: ='Program Budget'!W479 -> 813122.07 | C34: 0 | D34: ='Program Budget'!X479 -> 6000 | E34: =B34+C34 -> 813122.07 | F34: =B34+C34+D34 -> 819122.07 | G34: =B34/$B$36 -> 0.058901546
A35: Activity 8: Financial Services: Endowment Establishment, Fundraising and Management | B35: ='Program Budget'!W526 -> 3379625.3 | C35: 0 | D35: ='Program Budget'!X526 -> 294784.07 | E35: =B35+C35 -> 3379625.3 | F35: =B35+C35+D35 -> 3674409.4 | G35: =B35/$B$36 -> 0.24481583
A36: Total Activities | B36: =SUM(B28:B35) -> 13804766 | C36: =SUM(C28:C35) -> 0 | D36: =SUM(D28:D35) -> 1977928.1 | E36: =SUM(E28:E35) -> 13804766 | F36: =SUM(F28:F35) -> 15782694 | G36: =B36/$B$36 -> 1
A38: Commodity and Food Purchases (N/A to FFPr)
A39: Commodity Procurement | B39: 0 | C39: 0 | D39: 0 | E39: =B39+C39 -> 0 | F39: =B39+C39+D39 -> 0
A40: Food Vouchers (N/A to MGD)
A41: Cash Transfers (N/A to MGD)
A42: Total Commodity Procurement | B42: =SUM(B39:B41) -> 0 | C42: =SUM(C39:C41) -> 0 | D42: =SUM(D39:D41) -> 0 | E42: =SUM(E39:E41) -> 0 | F42: =SUM(F39:F41) -> 0
A44: ITSH (N/A to FFPr)
A45: Salaries | B45: 0 | C45: 0 | D45: 0 | E45: =B45+C45 -> 0 | F45: =B45+C45+D45 -> 0
A46: Benefits | B46: 0 | C46: 0 | D46: 0 | E46: =B46+C46 -> 0 | F46: =B46+C46+D46 -> 0
A47: Transportation | B47: 0 | C47: 0 | D47: 0 | E47: =B47+C47 -> 0 | F47: =B47+C47+D47 -> 0
A48: Professional Services | B48: 0 | C48: 0 | D48: =0 -> 0 | E48: =B48+C48 -> 0 | F48: =B48+C48+D48 -> 0
A49: Warehouse | B49: 0 | C49: 0 | D49: 0 | E49: =B49+C49 -> 0 | F49: =B49+C49+D49 -> 0
A50: Supplies | B50: 0 | C50: 0 | D50: 0 | E50: =B50+C50 -> 0 | F50: =B50+C50+D50 -> 0
A51: Other | B51: 0 | C51: 0 | D51: 0 | E51: =B51+C51 -> 0 | F51: =B51+C51+D51 -> 0
A52: Total ITSH | B52: =SUM(B45:B51) -> 0 | C52: 0 | D52: =SUM(D45:D51) -> 0 | E52: =SUM(E45:E51) -> 0 | F52: =SUM(F45:F51) -> 0
A54: Total Direct Costs | B54: =B25+B36+B52+B42 -> 17165784 | C54: =C25+C36+C52+C42 -> 1771699.2 | D54: =D25+D36+D52+D42 -> 1977928.1 | E54: =E42+E36+E25+E52 -> 18937484 | F54: =F42+F36+F25+F52 -> 20915412
A56: Indirect Costs
A57: ICR on Administration | B57: =(B25*0.2869) -> 964276.17 | C57: =C25*0.2869 -> 508300.51 | E57: =B57+C57 -> 1472576.7
A58: ICR on Activities | B58: =(B36-'Program Budget'!M517)*0.2869 -> 3099887.4 | C58: =C36*0.2869 -> 0 | E58: =B58+C58 -> 3099887.4
A59: ICR on Commodity and Food Purchases (N/A to FFPr) | B59: =B42*0.2869 -> 0 | C59: =C42*0.2869 -> 0 | E59: =B59+C59 -> 0
A60: ICR on ITSH (N/A to FFPr) | B60: =B52*0.2869 -> 0 | C60: =C52*0.2869 -> 0 | E60: =B60+C60 -> 0
A61: Total Indirect Costs | B61: =ROUND(SUM(B57:B60),0) -> 4064164 | C61: =ROUND(SUM(C57:C60),0) -> 508301 | E61: =ROUND(SUM(E57:E60),0) -> 4572464
A63: Anticipated Program Income
A65: Grand Total Costs | B65: =ROUNDDOWN(B61+B54,0) -> 21229948 | C65: =ROUND(C61+C54,0) -> 2280000 | D65: =ROUND(D61+D54,0) -> 1977928 | E65: =ROUND(E61+E54,0) -> 23509948 | F65: =ROUND(F54+E61,0) -> 25487876
E66: =E65*10% -> 2350994.8
A67: Total Amount of Federal Award (Total Federal Funds Requested Plus Cost Share): | F67: =F12+D65 -> 35773678

Sheet Indirect Calculations
B1: Partners of the Americas – FY 2020 FFPr Colombia
B2: NOFO: USDA-FAS-10.606-0700-20-(514)
B3: Duration: 5 Years
B4: Country: Colombia
B5: Summary of Indirect Cost Rates Applied
B7: BUDGET ITEM | C7: RATE/ UNIT | D7: YEAR 1 | E7: YEAR 2 | F7: YEAR 3 | G7: YEAR 4 | H7: YEAR 5 | I7: TOTAL USDA
B8: Administration Salaries/Personnel
B9: CCN Colombia National Staff (LOE)
B10: Key Personnel: Expat Chief of Party | C10: =141500/12 -> 11791.667 | D10: =#REF!*C10*#REF! -> #REF! | E10: =#REF!*C10*#REF!*#REF! -> #REF! | F10: =#REF!*C10*#REF!*#REF!*#REF! -> #REF! | G10: =#REF!*C10*#REF!*#REF!*#REF!*#REF! -> #REF! | H10: =#REF!*C10*#REF!*#REF!*#REF!*#REF!*#REF! -> #REF! | I10: =SUM(G10,F10,E10,D10,H10) -> #REF!
B11: Key Personnel: Deputy Chief of Party | C11: =110000/12 -> 9166.6667 | D11: =#REF!*C11*#REF! -> #REF! | E11: =#REF!*C11*#REF!*#REF! -> #REF! | F11: =#REF!*C11*#REF!*#REF!*#REF! -> #REF! | G11: =#REF!*C11*#REF!*#REF!*#REF!*#REF! -> #REF! | H11: =#REF!*C11*#REF!*#REF!*#REF!*#REF!*#REF! -> #REF! | I11: =SUM(G11,F11,E11,D11,H11) -> #REF!
B12: F&A Director | C12: =39000/12 -> 3250 | D12: =#REF!*C12*#REF! -> #REF! | E12: =#REF!*C12*#REF!*#REF! -> #REF! | F12: =#REF!*C12*#REF!*#REF!*#REF! -> #REF! | G12: =#REF!*C12*#REF!*#REF!*#REF!*#REF! -> #REF! | H12: =#REF!*C12*#REF!*#REF!*#REF!*#REF!*#REF! -> #REF! | I12: =SUM(G12,F12,E12,D12,H12) -> #REF!
B13: M&E Director | C13: =39000/12 -> 3250 | D13: =#REF!*C13*#REF! -> #REF! | E13: =#REF!*C13*#REF!*#REF! -> #REF! | F13: =#REF!*C13*#REF!*#REF!*#REF! -> #REF! | G13: =#REF!*C13*#REF!*#REF!*#REF!*#REF! -> #REF! | H13: =#REF!*C13*#REF!*#REF!*#REF!*#REF!*#REF! -> #REF! | I13: =SUM(G13,F13,E13,D13,H13) -> #REF!
B14: M&E Specialists | C14: =22000/12 -> 1833.3333 | D14: =#REF!*C14*#REF! -> #REF! | E14: =#REF!*C14*#REF!*#REF! -> #REF! | F14: =#REF!*C14*#REF!*#REF!*#REF! -> #REF! | G14: =#REF!*C14*#REF!*#REF!*#REF!*#REF! -> #REF! | H14: =#REF!*C14*#REF!*#REF!*#REF!*#REF!*#REF! -> #REF! | I14: =SUM(G14,F14,E14,D14,H14) -> #REF!
B15: M&E Specialists | C15: =22000/12 -> 1833.3333 | D15: =#REF!*C15*#REF! -> #REF! | E15: =#REF!*C15*#REF!*#REF! -> #REF! | F15: =#REF!*C15*#REF!*#REF!*#REF! -> #REF! | G15: =#REF!*C15*#REF!*#REF!*#REF!*#REF! -> #REF! | H15: =#REF!*C15*#REF!*#REF!*#REF!*#REF!*#REF! -> #REF! | I15: =SUM(G15,F15,E15,D15,H15) -> #REF!
B16: Activity Lead RCP Manager | C16: =22000/12 -> 1833.3333 | D16: =#REF!*C16*#REF! -> #REF! | E16: =#REF!*C16*#REF!*#REF! -> #REF! | F16: =#REF!*C16*#REF!*#REF!*#REF! -> #REF! | G16: =#REF!*C16*#REF!*#REF!*#REF!*#REF! -> #REF! | H16: =#REF!*C16*#REF!*#REF!*#REF!*#REF!*#REF! -> #REF! | I16: =SUM(G16,F16,E16,D16,H16) -> #REF!
B17: Activity Lead RCP Manager | C17: =18000/12 -> 1500 | D17: =#REF!*C17*#REF! -> #REF! | E17: =#REF!*C17*#REF!*#REF! -> #REF! | F17: =#REF!*C17*#REF!*#REF!*#REF! -> #REF! | G17: =#REF!*C17*#REF!*#REF!*#REF!*#REF! -> #REF! | H17: =#REF!*C17*#REF!*#REF!*#REF!*#REF!*#REF! -> #REF! | I17: =SUM(G17,F17,E17,D17,H17) -> #REF!
B18: Activity Lead Agribusiness Specialist | C18: =22000/12 -> 1833.3333 | D18: =#REF!*C18*#REF! -> #REF! | E18: =#REF!*C18*#REF!*#REF! -> #REF! | F18: =#REF!*C18*#REF!*#REF!*#REF! -> #REF! | G18: =#REF!*C18*#REF!*#REF!*#REF!*#REF! -> #REF! | H18: =#REF!*C18*#REF!*#REF!*#REF!*#REF!*#REF! -> #REF! | I18: =SUM(G18,F18,E18,D18,H18) -> #REF!
B19: Activity Lead Agribusiness Specialist | C19: =22000/12 -> 1833.3333 | D19: =#REF!*C19*#REF! -> #REF! | E19: =#REF!*C19*#REF!*#REF! -> #REF! | F19: =#REF!*C19*#REF!*#REF!*#REF! -> #REF! | G19: =#REF!*C19*#REF!*#REF!*#REF!*#REF! -> #REF! | H19: =#REF!*C19*#REF!*#REF!*#REF!*#REF!*#REF! -> #REF! | I19: =SUM(G19,F19,E19,D19,H19) -> #REF!
B20: Activity Lead Agribusiness Specialist | C20: =18000/12 -> 1500 | D20: =#REF!*C20*#REF! -> #REF! | E20: =#REF!*C20*#REF!*#REF! -> #REF! | F20: =#REF!*C20*#REF!*#REF!*#REF! -> #REF! | G20: =#REF!*C20*#REF!*#REF!*#REF!*#REF! -> #REF! | H20: =#REF!*C20*#REF!*#REF!*#REF!*#REF!*#REF! -> #REF! | I20: =SUM(G20,F20,E20,D20,H20) -> #REF!
B21: Activity Lead Agribusiness Specialist | C21: =18000/12 -> 1500 | D21: =#REF!*C21*#REF! -> #REF! | E21: =#REF!*C21*#REF!*#REF! -> #REF! | F21: =#REF!*C21*#REF!*#REF!*#REF! -> #REF! | G21: =#REF!*C21*#REF!*#REF!*#REF!*#REF! -> #REF! | H21: =#REF!*C21*#REF!*#REF!*#REF!*#REF!*#REF! -> #REF! | I21: =SUM(G21,F21,E21,D21,H21) -> #REF!
B22: Compliance Officer | C22: =22000/12 -> 1833.3333 | D22: =#REF!*C22*#REF! -> #REF! | E22: =#REF!*C22*#REF!*#REF! -> #REF! | F22: =#REF!*C22*#REF!*#REF!*#REF! -> #REF! | G22: =#REF!*C22*#REF!*#REF!*#REF!*#REF! -> #REF! | H22: =#REF!*C22*#REF!*#REF!*#REF!*#REF!*#REF! -> #REF! | I22: =SUM(G22,F22,E22,D22,H22) -> #REF!
B23: Accountant | C23: =18000/12 -> 1500 | D23: =#REF!*C23*#REF! -> #REF! | E23: =#REF!*C23*#REF!*#REF! -> #REF! | F23: =#REF!*C23*#REF!*#REF!*#REF! -> #REF! | G23: =#REF!*C23*#REF!*#REF!*#REF!*#REF! -> #REF! | H23: =#REF!*C23*#REF!*#REF!*#REF!*#REF!*#REF! -> #REF! | I23: =SUM(G23,F23,E23,D23,H23) -> #REF!
B24: Administrative Assistant | C24: =15000/12 -> 1250 | D24: =#REF!*C24*#REF! -> #REF! | E24: =#REF!*C24*#REF!*#REF! -> #REF! | F24: =#REF!*C24*#REF!*#REF!*#REF! -> #REF! | G24: =#REF!*C24*#REF!*#REF!*#REF!*#REF! -> #REF! | H24: =#REF!*C24*#REF!*#REF!*#REF!*#REF!*#REF! -> #REF! | I24: =SUM(G24,F24,E24,D24,H24) -> #REF!
B26: Home Office Support (LOE)
B27: HQ Senior Program Officer | C27: =55000/12 -> 4583.3333 | D27: =#REF!*C27*#REF! -> #REF! | E27: =#REF!*C27*#REF!*#REF! -> #REF! | F27: =#REF!*C27*#REF!*#REF!*#REF! -> #REF! | G27: =#REF!*C27*#REF!*#REF!*#REF!*#REF! -> #REF! | H27: =#REF!*C27*#REF!*#REF!*#REF!*#REF!*#REF! -> #REF! | I27: =SUM(G27,F27,E27,D27,H27) -> #REF!
B29: Total Personnel | D29: ='Program Budget'!J32 -> 188172.22 | E29: ='Program Budget'!M32 -> 268458.67 | F29: ='Program Budget'!P32 -> 279197.01 | G29: ='Program Budget'!S32 -> 267080.21 | H29: ='Program Budget'!V32 -> 270861.25 | I29: =SUM(D29:H29) -> 1273769.4
B30: Administration Fringe Benefits
B31: Total Fringe Benefits | D31: ='Program Budget'!J44 -> 112358.33 | E31: ='Program Budget'!M44 -> 144568.98 | F31: ='Program Budget'!P44 -> 150026.26 | G31: ='Program Budget'!S44 -> 143150 | H31: ='Program Budget'!V44 -> 174806.32 | I31: =SUM(D31:H31) -> 724909.89
B32: Administration Travel
B33: Total Travel | D33: ='Program Budget'!J61 -> 20120 | E33: ='Program Budget'!M61 -> 32458.8 | F33: ='Program Budget'!P61 -> 33639.732 | G33: ='Program Budget'!S61 -> 34864.379 | H33: ='Program Budget'!V61 -> 34730.553 | I33: =SUM(D33:H33) -> 155813.46
B34: Administration Professional Services/Contractual
B35: Total Professional Services/Contractual | D35: ='Program Budget'!J84 -> 1570061.2 | E35: ='Program Budget'!M84 -> 385066.02 | F35: ='Program Budget'!P84 -> 245500 | G35: ='Program Budget'!S84 -> 60500 | H35: ='Program Budget'!V84 -> 220500 | I35: =SUM(D35:H35) -> 2481627.2
B36: Administration Equipment
B37: Total Equipment | D37: ='Program Budget'!J89 -> 100000 | E37: ='Program Budget'!M89 -> 0 | F37: ='Program Budget'!P89 -> 0 | G37: ='Program Budget'!S89 -> 0 | H37: ='Program Budget'!V89 -> 0 | I37: =SUM(D37:H37) -> 100000
B38: Administration Office Expenses
B39: Total Office Expenses | D39: ='Program Budget'!J102 -> 13910.8 | E39: ='Program Budget'!M102 -> 56400.032 | F39: ='Program Budget'!P102 -> 58656.033 | G39: ='Program Budget'!S102 -> 61002.275 | H39: ='Program Budget'!V102 -> 31996.568 | I39: =SUM(D39:H39) -> 221965.71
B40: Administration Office Supplies
B41: Total Office Supplies | D41: ='Program Budget'!J113 -> 72798.63 | E41: ='Program Budget'!M113 -> 3744 | F41: ='Program Budget'!P113 -> 3893.76 | G41: ='Program Budget'!S113 -> 4049.5104 | H41: ='Program Budget'!V113 -> 2105.7454 | I41: =SUM(D41:H41) -> 86591.646
B42: Administration Other
B43: Total Other | D43: ='Program Budget'!J125 -> 13525 | E43: ='Program Budget'!M125 -> 19760 | F43: ='Program Budget'!P125 -> 19926.4 | G43: ='Program Budget'!S125 -> 20099.456 | H43: ='Program Budget'!V125 -> 14729.434 | I43: =SUM(D43:H43) -> 88040.29
B44: Total Administration Direct Costs | D44: =SUM(D29:D43) -> 2090946.2 | E44: =SUM(E29:E43) -> 910456.5 | F44: =SUM(F29:F43) -> 790839.2 | G44: =SUM(G29:G43) -> 590745.83 | H44: =SUM(H29:H43) -> 749729.88 | I44: =SUM(I29:I43) -> 5132717.6
B46: Total Indirect Costs (NICRA) on Administration | C46: 0.2869 | D46: =D44*$C$46 -> 599892.47 | E46: =E44*$C$46 -> 261209.97 | F46: =F44*$C$46 -> 226891.77 | G46: =G44*$C$46 -> 169484.98 | H46: =H44*$C$46 -> 215097.5 | I46: =SUM(H46+G46,F46,E46,D46) -> 1472576.7
B48: TOTAL ADMINISTRATION INDIRECT COSTS | D48: =D46 -> 599892.47 | E48: =E46 -> 261209.97 | F48: =F46 -> 226891.77 | G48: =G46 -> 169484.98 | H48: =H46 -> 215097.5 | I48: =I46 -> 1472576.7
B50: ='USDA Budget Summary'!A28 -> Activity 1: Value Chain Development (Value Chain Analysis, Carbon Assessment, and Living Incomes)
B51: Total Activity 1 | D51: ='Program Budget'!J163 -> 118015 | E51: ='Program Budget'!M163 -> 36049.11 | F51: ='Program Budget'!P163 -> 0 | G51: ='Program Budget'!S163 -> 0 | H51: ='Program Budget'!V163 -> 0 | I51: =SUM(D51:H51) -> 154064.11
B52: ='USDA Budget Summary'!A29 -> Activity 2: Producer Organization Development & Commercialization
B53: Total Activity 2 | D53: ='Program Budget'!J206 -> 227437.92 | E53: ='Program Budget'!M206 -> 352581.64 | F53: ='Program Budget'!P206 -> 359812.34 | G53: ='Program Budget'!S206 -> 372714.85 | H53: ='Program Budget'!V206 -> 271970.87 | I53: =SUM(D53:H53) -> 1584517.6
B54: ='USDA Budget Summary'!A30 -> Activity 3: Agriculture Extension and Production Support
B55: Total Activity 3 | D55: ='Program Budget'!J265 -> 448988.92 | E55: ='Program Budget'!M265 -> 1226785.7 | F55: ='Program Budget'!P265 -> 1174652.8 | G55: ='Program Budget'!S265 -> 840537 | H55: ='Program Budget'!V265 -> 708410.77 | I55: =SUM(D55:H55) -> 4399375.2
B56: ='USDA Budget Summary'!A31 -> Activity 4: Post-Harvest Aggregation & Processing
B57: Total Activity 4 | D57: ='Program Budget'!J313 -> 169506.75 | E57: ='Program Budget'!M313 -> 456486.67 | F57: ='Program Budget'!P313 -> 508797.8 | G57: ='Program Budget'!S313 -> 301601.4 | H57: ='Program Budget'!V313 -> 272307.04 | I57: =SUM(D57:H57) -> 1708699.7
B58: ='USDA Budget Summary'!A32 -> Activity 5: Ensure Financial Service/ Capital Access for Actors in the Value Chains
B59: Total Activity 5 | D59: ='Program Budget'!J367 -> 63483.978 | E59: ='Program Budget'!M367 -> 192068.14 | F59: ='Program Budget'!P367 -> 195410.86 | G59: ='Program Budget'!S367 -> 105122.43 | H59: ='Program Budget'!V367 -> 62537.333 | I59: =SUM(D59:H59) -> 618622.73
B60: ='USDA Budget Summary'!A33 -> Activity 6: Innovation and Job Creation Through Youth Engagement
B61: Total Activity 6 | D61: ='Program Budget'!J433 -> 0 | E61: ='Program Budget'!M433 -> 403287.98 | F61: ='Program Budget'!P433 -> 437686 | G61: ='Program Budget'!S433 -> 214795.23 | H61: ='Program Budget'!V433 -> 90970.202 | I61: =SUM(D61:H61) -> 1146739.4
B62: ='USDA Budget Summary'!A34 -> Activity 7: Establishment of Regional Community of Practice
B63: Total Activity 7 | D63: ='Program Budget'!J479 -> 88278.325 | E63: ='Program Budget'!M479 -> 117620.75 | F63: ='Program Budget'!P479 -> 252657.21 | G63: ='Program Budget'!S479 -> 140690.61 | H63: ='Program Budget'!V479 -> 213875.17 | I63: =SUM(D63:H63) -> 813122.07
B64: ='USDA Budget Summary'!A35 -> Activity 8: Financial Services: Endowment Establishment, Fundraising and Management
B65: Total Activity 8 | D65: ='Program Budget'!J526 -> 11125 | E65: ='Program Budget'!M526 -> 3044523.2 | F65: ='Program Budget'!P526 -> 45874.142 | G65: ='Program Budget'!S526 -> 137266.78 | H65: ='Program Budget'!V526 -> 140836.17 | I65: =SUM(D65:H65) -> 3379625.3
B66: Total Activities Direct Costs | D66: =SUM(D51:D65) -> 1126835.9 | E66: =SUM(E51:E65) -> 5829403.2 | F66: =SUM(F51:F65) -> 2974891.2 | G66: =SUM(G51:G65) -> 2112728.3 | H66: =SUM(H51:H65) -> 1760907.6 | I66: =SUM(I51:I65) -> 13804766
B68: Total Indirect Costs (NICRA) on Activities | C68: 0.2869 | D68: =D66*$C$68 -> 323289.22 | E68: =(E66-3000000)*$C$68 -> 811755.78 | F68: =F66*$C$68 -> 853496.27 | G68: =G66*$C$68 -> 606141.75 | H68: =H66*$C$68 -> 505204.38 | I68: =SUM(H68+G68,F68,E68,D68) -> 3099887.4 | J68: NICRA less the $3M Philanthropy Fund
B70: TOTAL ACTIVITIES INDIRECT COSTS | D70: =D68 -> 323289.22 | E70: =E68 -> 811755.78 | F70: =F68 -> 853496.27 | G70: =G68 -> 606141.75 | H70: =H68 -> 505204.38 | I70: =I68 -> 3099887.4
B72: TOTAL INDIRECT COSTS | D72: =D70+D48 -> 923181.68 | E72: =E70+E48 -> 1072965.8 | F72: =F70+F48 -> 1080388 | G72: =G70+G48 -> 775626.72 | H72: =H70+H48 -> 720301.88 | I72: =I70+I48 -> 4572464.1

Sheet Program Budget
E1: Partners of the Americas – FY 2020 FFPr Colombia
E2: NOFO: USDA-FAS-10.606-0700-20-(514)
E3: Duration: 5 Years
E4: Country: Colombia
E5: Budget Assumptions:
A6: Entity: | B6: P | E6: Inflation - US Based Goods/Services | F6: 1.03
A7: Program-Dept.: | B7: FTF | E7: Inflation - Locally Purchased Goods/Services | F7: 1.04
A8: Funder-Grant: | B8: USDA700 | E8: Merit Based Increases for HQ & Field Staff | F8: 1.04
A10: Activity (Budget Code) | B10: Account Code | C10: Country Code (USA or COL2) | D10: Subcontract Code | E10: BUDGET ITEM | F10: Level of Effort (LOE) Year 1 | G10: UNIT | H10: # of Units | I10: RATE/ UNIT | J10: YEAR 1 | K10: Level of Effort (LOE) Year 2 | L10: # of Units | M10: YEAR 2 | N10: Level of Effort (LOE) Year 3 | O10: # of Units | P10: YEAR 3 | Q10: Level of Effort (LOE) Year 4 | R10: # of Units | S10: YEAR 4 | T10: Level of Effort (LOE) Year 5 | U10: # of Units | V10: YEAR 5 | W10: TOTAL USDA | X10: TOTAL COST SHARE | Y10: PROJECT GRAND TOTAL | AA10: Cacao Focus | AB10: Complementary Crop Focus
E11: Salaries/Personnel (Administration)
E12: CCN Colombia National Field Staff (LOE) | AA12: Cacao Focus | AB12: Complementary Crop Focus
A13: PERSNL | B13: 50000 | C13: USA | D13: 0 | E13: Key Personnel: Chief of Party | F13: ='LOE Breakdown by Year'!D11 -> 0.15 | G13: Month | H13: 12 | I13: =150000/12 -> 12500 | J13: =H13*I13*F13 -> 22500 | K13: ='LOE Breakdown by Year'!D35 -> 0.1 | L13: 12 | M13: =L13*I13*$F$8*$K13 -> 15600 | N13: ='LOE Breakdown by Year'!D59 -> 0.1 | O13: 12 | P13: =O13*I13*$N13*$F$8*$F$8 -> 16224 | Q13: ='LOE Breakdown by Year'!D83 -> 0.1 | R13: 12 | S13: =R13*I13*$Q13*$F$8*$F$8*$F$8 -> 16872.96 | T13: ='LOE Breakdown by Year'!D107 -> 0.1 | U13: 12 | V13: =U13*I13*$T13*$F$8*$F$8*$F$8*$F$8 -> 17547.878 | W13: =SUM(S13,P13,M13,J13,V13) -> 88744.838 | X13: 0 | Y13: =SUM(W13:X13) -> 88744.838 | AA13: 0.5 | AB13: 0.5
A14: PERSNL | B14: 70000 | C14: COL2 | D14: 0 | E14: Key Personnel: Technical Director | F14: ='LOE Breakdown by Year'!D12 -> 0.1 | G14: Month | H14: 8 | I14: =70000/12 -> 5833.3333 | J14: =H14*I14*F14 -> 4666.6667 | K14: ='LOE Breakdown by Year'!D36 -> 0.1 | L14: 12 | M14: =L14*I14*$F$8*$K14 -> 7280 | N14: ='LOE Breakdown by Year'!D60 -> 0.1 | O14: 12 | P14: =O14*I14*$N14*$F$8*$F$8 -> 7571.2 | Q14: ='LOE Breakdown by Year'!D84 -> 0.1 | R14: 12 | S14: =R14*I14*$Q14*$F$8*$F$8*$F$8 -> 7874.048 | T14: ='LOE Breakdown by Year'!D108 -> 0.1 | U14: 12 | V14: =U14*I14*$T14*$F$8*$F$8*$F$8*$F$8 -> 8189.0099 | W14: =SUM(S14,P14,M14,J14,V14) -> 35580.925 | X14: 0 | Y14: =SUM(W14:X14) -> 35580.925 | AA14: 0.5 | AB14: 0.5
A15: PERSNL | B15: 70000 | C15: COL2 | D15: 0 | E15: F&A Director | F15: ='LOE Breakdown by Year'!D13 -> 1 | G15: Month | H15: 8 | I15: =46000/12 -> 3833.3333 | J15: =H15*I15*F15 -> 30666.667 | K15: ='LOE Breakdown by Year'!D37 -> 0.95 | L15: 12 | M15: =L15*I15*$F$8*$K15 -> 45448 | N15: ='LOE Breakdown by Year'!D61 -> 0.95 | O15: 12 | P15: =O15*I15*$N15*$F$8*$F$8 -> 47265.92 | Q15: ='LOE Breakdown by Year'!D85 -> 0.5 | R15: 12 | S15: =R15*I15*$Q15*$F$8*$F$8*$F$8 -> 25871.872 | T15: ='LOE Breakdown by Year'!D109 -> 0.75 | U15: 12 | V15: =U15*I15*$T15*$F$8*$F$8*$F$8*$F$8 -> 40360.12 | W15: =SUM(S15,P15,M15,J15,V15) -> 189612.58 | X15: 0 | Y15: =SUM(W15:X15) -> 189612.58 | AA15: 0.5 | AB15: 0.5
A16: PERSNL | B16: 70000 | C16: COL2 | D16: 0 | E16: M&E Director | F16: ='LOE Breakdown by Year'!D14 -> 0.25 | G16: Month | H16: 8 | I16: =46000/12 -> 3833.3333 | J16: =H16*I16*F16 -> 7666.6667 | K16: ='LOE Breakdown by Year'!D38 -> 0.25 | L16: 12 | M16: =L16*I16*$F$8*$K16 -> 11960 | N16: ='LOE Breakdown by Year'!D62 -> 0.25 | O16: 12 | P16: =O16*I16*$N16*$F$8*$F$8 -> 12438.4 | Q16: ='LOE Breakdown by Year'!D86 -> 0.25 | R16: 12 | S16: =R16*I16*$Q16*$F$8*$F$8*$F$8 -> 12935.936 | T16: ='LOE Breakdown by Year'!D110 -> 0.25 | U16: 12 | V16: =U16*I16*$T16*$F$8*$F$8*$F$8*$F$8 -> 13453.373 | W16: =SUM(S16,P16,M16,J16,V16) -> 58454.376 | X16: 0 | Y16: =SUM(W16:X16) -> 58454.376 | AA16: 0.5 | AB16: 0.5
A17: PERSNL | B17: 70000 | C17: COL2 | D17: 0 | E17: M&E Mid-level Specialist | F17: ='LOE Breakdown by Year'!D15 -> 0.25 | G17: Month | H17: 7 | I17: =32000/12 -> 2666.6667 | J17: =H17*I17*F17 -> 4666.6667 | K17: ='LOE Breakdown by Year'!D39 -> 0.25 | L17: 12 | M17: =L17*I17*$F$8*$K17 -> 8320 | N17: ='LOE Breakdown by Year'!D63 -> 0.25 | O17: 12 | P17: =O17*I17*$N17*$F$8*$F$8 -> 8652.8 | Q17: ='LOE Breakdown by Year'!D87 -> 0.25 | R17: 12 | S17: =R17*I17*$Q17*$F$8*$F$8*$F$8 -> 8998.912 | T17: ='LOE Breakdown by Year'!D111 -> 0.25 | U17: 9 | V17: =U17*I17*$T17*$F$8*$F$8*$F$8*$F$8 -> 7019.1514 | W17: =SUM(S17,P17,M17,J17,V17) -> 37657.53 | X17: 0 | Y17: =SUM(W17:X17) -> 37657.53 | AA17: 0.5 | AB17: 0.5
A18: PERSNL | B18: 70000 | C18: COL2 | D18: 0 | E18: M&E Specialist | F18: ='LOE Breakdown by Year'!D16 -> 0.25 | G18: Month | H18: 3 | I18: =26000/12 -> 2166.6667 | J18: =H18*I18*F18 -> 1625 | K18: ='LOE Breakdown by Year'!D40 -> 0.25 | L18: 12 | M18: =L18*I18*$F$8*$K18 -> 6760 | N18: ='LOE Breakdown by Year'!D64 -> 0.25 | O18: 12 | P18: =O18*I18*$N18*$F$8*$F$8 -> 7030.4 | Q18: ='LOE Breakdown by Year'!D88 -> 0.25 | R18: 12 | S18: =R18*I18*$Q18*$F$8*$F$8*$F$8 -> 7311.616 | T18: ='LOE Breakdown by Year'!D112 -> 0.25 | U18: 9 | V18: =U18*I18*$T18*$F$8*$F$8*$F$8*$F$8 -> 5703.0605 | W18: =SUM(S18,P18,M18,J18,V18) -> 28430.076 | X18: 0 | Y18: =SUM(W18:X18) -> 28430.076 | AA18: 0.5 | AB18: 0.5
A19: PERSNL | B19: 70000 | C19: COL2 | D19: 0 | E19: Partnerships and Investment Director | F19: ='LOE Breakdown by Year'!D17 -> 0.05 | G19: Month | H19: 8 | I19: =46000/12 -> 3833.3333 | J19: =H19*I19*F19 -> 1533.3333 | K19: ='LOE Breakdown by Year'!D41 -> 0.1 | L19: 12 | M19: =L19*I19*$F$8*$K19 -> 4784 | N19: ='LOE Breakdown by Year'!D65 -> 0.1 | O19: 12 | P19: =O19*I19*$N19*$F$8*$F$8 -> 4975.36 | Q19: ='LOE Breakdown by Year'!D89 -> 0.1 | R19: 12 | S19: =R19*I19*$Q19*$F$8*$F$8*$F$8 -> 5174.3744 | T19: ='LOE Breakdown by Year'!D113 -> 0.1 | U19: 9 | V19: =U19*I19*$T19*$F$8*$F$8*$F$8*$F$8 -> 4036.012 | W19: =SUM(S19,P19,M19,J19,V19) -> 20503.08 | X19: 0 | Y19: =SUM(W19:X19) -> 20503.08 | AA19: 0.5 | AB19: 0.5
A20: PERSNL | B20: 70000 | C20: COL2 | D20: 0 | E20: Extension Agents (15) | F20: ='LOE Breakdown by Year'!D18 -> 0 | G20: Month | H20: 3 | I20: =(21000/12)*15 -> 26250 | J20: =H20*I20*F20 -> 0 | K20: ='LOE Breakdown by Year'!D42 -> 0 | L20: 12 | M20: =L20*I20*$F$8*$K20 -> 0 | N20: ='LOE Breakdown by Year'!D66 -> 0 | O20: 12 | P20: =O20*I20*$N20*$F$8*$F$8 -> 0 | Q20: ='LOE Breakdown by Year'!D90 -> 0 | R20: 12 | S20: =R20*I20*$Q20*$F$8*$F$8*$F$8 -> 0 | T20: ='LOE Breakdown by Year'!D114 -> 0 | U20: 9 | V20: =U20*I20*$T20*$F$8*$F$8*$F$8*$F$8 -> 0 | W20: =SUM(S20,P20,M20,J20,V20) -> 0 | X20: 0 | Y20: =SUM(W20:X20) -> 0 | AA20: 0.5 | AB20: 0.5
A21: PERSNL | B21: 70000 | C21: COL2 | D21: 0 | E21: Activity Lead Agribusiness Senior Specialist (Cacao) | F21: ='LOE Breakdown by Year'!D19 -> 0.1 | G21: Month | H21: 3 | I21: =34000/12 -> 2833.3333 | J21: =H21*I21*F21 -> 850 | K21: ='LOE Breakdown by Year'!D43 -> 0.1 | L21: 12 | M21: =L21*I21*$F$8*$K21 -> 3536 | N21: ='LOE Breakdown by Year'!D67 -> 0.1 | O21: 12 | P21: =O21*I21*$N21*$F$8*$F$8 -> 3677.44 | Q21: ='LOE Breakdown by Year'!D91 -> 0.1 | R21: 12 | S21: =R21*I21*$Q21*$F$8*$F$8*$F$8 -> 3824.5376 | T21: ='LOE Breakdown by Year'!D115 -> 0.1 | U21: 9 | V21: =U21*I21*$T21*$F$8*$F$8*$F$8*$F$8 -> 2983.1393 | W21: =SUM(S21,P21,M21,J21,V21) -> 14871.117 | X21: 0 | Y21: =SUM(W21:X21) -> 14871.117 | AA21: 1 | AB21: 0
A22: PERSNL | B22: 70000 | C22: COL2 | D22: 0 | E22: Activity Lead Agribusiness Senior Specialist (Complementary Crop) | F22: ='LOE Breakdown by Year'!D20 -> 0.1 | G22: Month | H22: 3 | I22: =34000/12 -> 2833.3333 | J22: =H22*I22*F22 -> 850 | K22: ='LOE Breakdown by Year'!D44 -> 0.1 | L22: 12 | M22: =L22*I22*$F$8*$K22 -> 3536 | N22: ='LOE Breakdown by Year'!D68 -> 0.1 | O22: 12 | P22: =O22*I22*$N22*$F$8*$F$8 -> 3677.44 | Q22: ='LOE Breakdown by Year'!D92 -> 0.1 | R22: 12 | S22: =R22*I22*$Q22*$F$8*$F$8*$F$8 -> 3824.5376 | T22: ='LOE Breakdown by Year'!D116 -> 0.1 | U22: 9 | V22: =U22*I22*$T22*$F$8*$F$8*$F$8*$F$8 -> 2983.1393 | W22: =SUM(S22,P22,M22,J22,V22) -> 14871.117 | X22: 0 | Y22: =SUM(W22:X22) -> 14871.117 | AA22: 0 | AB22: 1
A23: PERSNL | B23: 70000 | C23: COL2 | D23: 0 | E23: Food Safety Mid-Specialist | F23: ='LOE Breakdown by Year'!D21 -> 0.1 | G23: Month | H23: 3 | I23: =32000/12 -> 2666.6667 | J23: =H23*I23*F23 -> 800 | K23: ='LOE Breakdown by Year'!D45 -> 0.1 | L23: 12 | M23: =L23*I23*$F$8*$K23 -> 3328 | N23: ='LOE Breakdown by Year'!D69 -> 0.1 | O23: 12 | P23: =O23*I23*$N23*$F$8*$F$8 -> 3461.12 | Q23: ='LOE Breakdown by Year'!D93 -> 0.1 | R23: 12 | S23: =R23*I23*$Q23*$F$8*$F$8*$F$8 -> 3599.5648 | T23: ='LOE Breakdown by Year'!D117 -> 0.1 | U23: 9 | V23: =U23*I23*$T23*$F$8*$F$8*$F$8*$F$8 -> 2807.6605 | W23: =SUM(S23,P23,M23,J23,V23) -> 13996.345 | X23: 0 | Y23: =SUM(W23:X23) -> 13996.345 | AA23: 0.5 | AB23: 0.5
A24: PERSNL | B24: 70000 | C24: COL2 | D24: 0 | E24: Compliance Director | F24: ='LOE Breakdown by Year'!D22 -> 0.33333333 | G24: Month | H24: 8 | I24: =82000/12 -> 6833.3333 | J24: =H24*I24*F24 -> 18222.222 | K24: ='LOE Breakdown by Year'!D46 -> 0.33333333 | L24: 12 | M24: =L24*I24*$F$8*$K24 -> 28426.667 | N24: ='LOE Breakdown by Year'!D70 -> 0.33333333 | O24: 12 | P24: =O24*I24*$N24*$F$8*$F$8 -> 29563.733 | Q24: ='LOE Breakdown by Year'!D94 -> 0.33333333 | R24: 12 | S24: =R24*I24*$Q24*$F$8*$F$8*$F$8 -> 30746.283 | T24: ='LOE Breakdown by Year'!D118 -> 0.33333333 | U24: 12 | V24: =U24*I24*$T24*$F$8*$F$8*$F$8*$F$8 -> 31976.134 | W24: =SUM(S24,P24,M24,J24,V24) -> 138935.04 | X24: 0 | Y24: =SUM(W24:X24) -> 138935.04 | AA24: 0.5 | AB24: 0.5
A25: PERSNL | B25: 70000 | C25: COL2 | D25: 0 | E25: Accountant | F25: ='LOE Breakdown by Year'!D23 -> 1 | G25: Month | H25: 3 | I25: =21000/12 -> 1750 | J25: =H25*I25*F25 -> 5250 | K25: ='LOE Breakdown by Year'!D47 -> 1 | L25: 12 | M25: =L25*I25*$F$8*$K25 -> 21840 | N25: ='LOE Breakdown by Year'!D71 -> 1 | O25: 12 | P25: =O25*I25*$N25*$F$8*$F$8 -> 22713.6 | Q25: ='LOE Breakdown by Year'!D95 -> 1 | R25: 12 | S25: =R25*I25*$Q25*$F$8*$F$8*$F$8 -> 23622.144 | T25: ='LOE Breakdown by Year'!D119 -> 1 | U25: 9 | V25: =U25*I25*$T25*$F$8*$F$8*$F$8*$F$8 -> 18425.272 | W25: =SUM(S25,P25,M25,J25,V25) -> 91851.016 | X25: 0 | Y25: =SUM(W25:X25) -> 91851.016 | AA25: 0.5 | AB25: 0.5
A26: PERSNL | B26: 70000 | C26: COL2 | D26: 0 | E26: Administrative Assistant | F26: ='LOE Breakdown by Year'!D24 -> 0.5 | G26: Month | H26: 3 | I26: =15000/12 -> 1250 | J26: =H26*I26*F26 -> 1875 | K26: ='LOE Breakdown by Year'!D48 -> 0.5 | L26: 12 | M26: =L26*I26*$F$8*$K26 -> 7800 | N26: ='LOE Breakdown by Year'!D72 -> 0.5 | O26: 12 | P26: =O26*I26*$N26*$F$8*$F$8 -> 8112 | Q26: ='LOE Breakdown by Year'!D96 -> 0.5 | R26: 12 | S26: =R26*I26*$Q26*$F$8*$F$8*$F$8 -> 8436.48 | T26: ='LOE Breakdown by Year'!D120 -> 0.5 | U26: 9 | V26: =U26*I26*$T26*$F$8*$F$8*$F$8*$F$8 -> 6580.4544 | W26: =SUM(S26,P26,M26,J26,V26) -> 32803.934 | X26: 0 | Y26: =SUM(W26:X26) -> 32803.934 | AA26: 0.5 | AB26: 0.5
A27: PERSNL | B27: 70000 | C27: COL2 | D27: 0 | E27: Driver | F27: ='LOE Breakdown by Year'!D25 -> 1 | G27: Month | H27: 3 | I27: =12000/12 -> 1000 | J27: =H27*I27*F27 -> 3000 | K27: ='LOE Breakdown by Year'!D49 -> 1 | L27: 12 | M27: =L27*I27*$F$8*$K27 -> 12480 | N27: ='LOE Breakdown by Year'!D73 -> 1 | O27: 12 | P27: =O27*I27*$N27*$F$8*$F$8 -> 12979.2 | Q27: ='LOE Breakdown by Year'!D97 -> 1 | R27: 12 | S27: =R27*I27*$Q27*$F$8*$F$8*$F$8 -> 13498.368 | T27: ='LOE Breakdown by Year'!D121 -> 1 | U27: 9 | V27: =U27*I27*$T27*$F$8*$F$8*$F$8*$F$8 -> 10528.727 | W27: =SUM(S27,P27,M27,J27,V27) -> 52486.295 | X27: 0 | Y27: =SUM(W27:X27) -> 52486.295 | AA27: 0.5 | AB27: 0.5
E28: Headquarters (HQ) Support (LOE)
A29: PERSNL | B29: 50000 | C29: USA | D29: 0 | E29: Senior Director | F29: 0.2 | G29: Month | H29: 12 | I29: =120000/12 -> 10000 | J29: =H29*I29*F29 -> 24000 | K29: 0.2 | L29: 12 | M29: =L29*I29*$F$8*$K29 -> 24960 | N29: 0.2 | O29: 12 | P29: =O29*I29*$N29*$F$8*$F$8 -> 25958.4 | Q29: 0.2 | R29: 12 | S29: =R29*I29*$Q29*$F$8*$F$8*$F$8 -> 26996.736 | T29: 0.2 | U29: 12 | V29: =U29*I29*$T29*$F$8*$F$8*$F$8*$F$8 -> 28076.605 | W29: =SUM(S29,P29,M29,J29,V29) -> 129991.74 | X29: 0 | Y29: =SUM(W29:X29) -> 129991.74 | AA29: 0.5 | AB29: 0.5
A30: PERSNL | B30: 50000 | C30: USA | D30: 0 | E30: HQ Senior Program Officer | F30: ='LOE Breakdown by Year'!D28 -> 1 | G30: Month | H30: 12 | I30: =60000/12 -> 5000 | J30: =H30*I30*F30 -> 60000 | K30: ='LOE Breakdown by Year'!D52 -> 1 | L30: 12 | M30: =L30*I30*$F$8*$K30 -> 62400 | N30: ='LOE Breakdown by Year'!D76 -> 1 | O30: 12 | P30: =O30*I30*$N30*$F$8*$F$8 -> 64896 | Q30: ='LOE Breakdown by Year'!D100 -> 1 | R30: 12 | S30: =R30*I30*$Q30*$F$8*$F$8*$F$8 -> 67491.84 | T30: ='LOE Breakdown by Year'!D124 -> 1 | U30: 12 | V30: =U30*I30*$T30*$F$8*$F$8*$F$8*$F$8 -> 70191.514 | W30: =SUM(S30,P30,M30,J30,V30) -> 324979.35 | X30: 0 | Y30: =SUM(W30:X30) -> 324979.35 | AA30: 0.5 | AB30: 0.5
E32: Total Personnel | J32: =SUM(J13:J30) -> 188172.22 | M32: =SUM(M13:M30) -> 268458.67 | P32: =SUM(P13:P30) -> 279197.01 | S32: =SUM(S13:S30) -> 267080.21 | V32: =SUM(V13:V30) -> 270861.25 | W32: =SUM(W13:W30) -> 1273769.4 | X32: =SUM(X13:X30) -> 0 | Y32: =SUM(Y13:Y30) -> 1273769.4 | AA32: =SUMPRODUCT(Y13:Y27,AA13:AA27)+SUMPRODUCT(Y29:Y30,AA29:AA30) -> 636884.68 | AB32: =+SUMPRODUCT(Y13:Y27,AB13:AB27)+SUMPRODUCT(Y29:Y30,AB29:AB30) -> 636884.68
E34: Fringe Benefits
A35: FRINGE | B35: 70015 | C35: COL2 | D35: 0 | E35: Fringe Benefits CCN - Colombia (above $2,600 monthly) | G35: % | I35: 0.53864 | J35: =(J14+J15+J16+J24+J19+J17+J21+J22+J23)*$I$35 -> 37662.906 | M35: =(M14+M15+M16+M24+M19+M17+M21+M22+M23)*$I$35 -> 62815.479 | P35: =(P14+P15+P16+P24+P19+P17+P21+P22+P23)*$I$35 -> 65328.098 | S35: =(S14+S15+S16+S24+S19+S17+S21+S22+S23)*$I$35 -> 55399.159 | V35: =(V14+V15+V16+V24+V19+V17+V21+V22+V23)*$I$35 -> 61301.401 | W35: =SUM(S35,P35,M35,J35,V35) -> 282507.04 | X35: 0 | Y35: =SUM(W35:X35) -> 282507.04 | AA35: 0.5 | AB35: 0.5
A36: FRINGE | B36: 70015 | C36: COL2 | D36: 0 | E36: Fringe Benefits CCN - Colombia (below $2,600 monthly) | G36: % | I36: 0.40364 | J36: =(J18+J20+J25+J26+J27)*$I$36 -> 4742.77 | M36: =(M18+M20+M25+M26+M27)*$I$36 -> 19729.923 | P36: =(P18+P20+P25+P26+P27)*$I$36 -> 20519.12 | S36: =(S18+S20+S25+S26+S27)*$I$36 -> 21339.885 | V36: =(V18+V20+V25+V26+V27)*$I$36 -> 16645.11 | W36: =SUM(S36,P36,M36,J36,V36) -> 82976.809 | X36: 0 | Y36: =SUM(W36:X36) -> 82976.809 | AA36: 0.5 | AB36: 0.5
A37: FRINGE | B37: 50900 | C37: USA | D37: 0 | E37: Fringe Benefits - HQ (21.81%) | G37: % | I37: 0.2181 | J37: =(J30+J29)*$I$37 -> 18320.4 | M37: =(M30+M29)*$I$37 -> 19053.216 | P37: =(P30+P29)*$I$37 -> 19815.345 | S37: =(S30+S29)*$I$37 -> 20607.958 | V37: =(V30+V29)*$I$37 -> 21432.277 | W37: =SUM(S37,P37,M37,J37,V37) -> 99229.196 | X37: 0 | Y37: =SUM(W37:X37) -> 99229.196 | AA37: 0.5 | AB37: 0.5
A38: POST DIFF | B38: 50202 | C38: COL2 | D38: 0 | E38: Post (Hardship) Differential for Chief of Party | G38: % | I38: 0.1 | J38: =J13*$I$38 -> 2250 | M38: =M13*$I$38 -> 1560 | P38: =P13*$I$38 -> 1622.4 | S38: =S13*$I$38 -> 1687.296 | V38: =V13*$I$38 -> 1754.7878 | W38: =SUM(S38,P38,M38,J38,V38) -> 8874.4838 | X38: - | Y38: =SUM(W38:X38) -> 8874.4838 | AA38: 0.5 | AB38: 0.5
A39: FRINGE | B39: 50900 | C39: USA | D39: 0 | E39: Fringe Benefits Package for Chief of Party | G39: % | I39: 0.5681 | J39: =J13*$I$39 -> 12782.25 | M39: =M13*$I$39 -> 8862.36 | P39: =P13*$I$39 -> 9216.8544 | S39: =S13*$I$39 -> 9585.5286 | V39: =V13*$I$39 -> 9968.9497 | W39: =SUM(S39,P39,M39,J39,V39) -> 50415.943 | X39: - | Y39: =SUM(W39:X39) -> 50415.943 | AA39: 0.5 | AB39: 0.5
A40: HOUSE. ALL | B40: 50203 | C40: COL2 | D40: 0 | E40: Housing Allowance for Chief of Party | G40: Month | H40: 4 | I40: 2500 | J40: =H40*I40 -> 10000 | L40: 12 | M40: =I40*L40*$F$6 -> 30900 | O40: 12 | P40: =I40*O40*$F$6*$F$6 -> 31827 | R40: 12 | S40: =I40*R40*$F$6*$F$6*$F$6 -> 32781.81 | U40: 12 | V40: =U40*I40*$F$6*$F$6*$F$6*$F$6 -> 33765.264 | W40: =SUM(S40,P40,M40,J40,V40) -> 139274.07 | X40: - | Y40: =SUM(W40:X40) -> 139274.07 | AA40: 0.5 | AB40: 0.5
A41: REALLOC | B41: 50205 | C41: COL2 | D41: 0 | E41: Reallocation & Demobilization Allowance for Chief of Party | G41: Year | H41: 1 | I41: 25000 | J41: =H41*I41 -> 25000 | L41: 0 | M41: =I41*L41*$F$6 -> 0 | O41: 0 | P41: =I41*O41*$F$6*$F$6 -> 0 | R41: 0 | S41: =I41*R41*$F$6*$F$6*$F$6 -> 0 | U41: 1 | V41: =U41*I41*$F$6*$F$6*$F$6*$F$6 -> 28137.72 | W41: =SUM(S41,P41,M41,J41,V41) -> 53137.72 | X41: - | Y41: =SUM(W41:X41) -> 53137.72 | AA41: 0.5 | AB41: 0.5
A42: R&RTRIP | B42: 50206 | C42: COL2 | D42: 0 | E42: Annual Home of Record for Chief of Party | G42: Year | H42: 2 | I42: 800 | J42: =H42*I42 -> 1600 | L42: 2 | M42: =I42*L42*$F$6 -> 1648 | O42: 2 | P42: =I42*O42*$F$6*$F$6 -> 1697.44 | R42: 2 | S42: =I42*R42*$F$6*$F$6*$F$6 -> 1748.3632 | U42: 2 | V42: =U42*I42*$F$6*$F$6*$F$6*$F$6 -> 1800.8141 | W42: =SUM(S42,P42,M42,J42,V42) -> 8494.6173 | X42: - | Y42: =SUM(W42:X42) -> 8494.6173 | AA42: 0.5 | AB42: 0.5
E44: Total Fringe Benefits | J44: =SUM(J35:J43) -> 112358.33 | M44: =SUM(M35:M43) -> 144568.98 | P44: =SUM(P35:P43) -> 150026.26 | S44: =SUM(S35:S43) -> 143150 | V44: =SUM(V35:V43) -> 174806.32 | W44: =SUM(W35:W43) -> 724909.89 | X44: =SUM(X35:X43) -> 0 | Y44: =SUM(Y35:Y43) -> 724909.89 | AA44: =SUMPRODUCT(Y35:Y42,AA35:AA42) -> 362454.94 | AB44: =SUMPRODUCT(Y35:Y42,AB35:AB42) -> 362454.94
E46: Travel
E47: HQ Staff Travel - International
A48: STFTRAVEL | B48: 86040 | C48: USA | D48: 0 | E48: Airfare - DC-Colombia - HQ Project Management Trip | G48: Trip | H48: 1 | I48: 800 | J48: =H48*I48 -> 800 | L48: 3 | M48: =I48*L48*$F$6 -> 2472 | O48: 3 | P48: =I48*O48*$F$6*$F$6 -> 2546.16 | R48: 3 | S48: =I48*R48*$F$6*$F$6*$F$6 -> 2622.5448 | U48: 3 | V48: =U48*I48*$F$6*$F$6*$F$6*$F$6 -> 2701.2211 | W48: =SUM(S48,P48,M48,J48,V48) -> 11141.926 | X48: - | Y48: =SUM(W48:X48) -> 11141.926 | AA48: 0.5 | AB48: 0.5
A49: STFTRVCTS | B49: 86030 (Lodging)/ 86050 (M&IE) | C49: USA | D49: 0 | E49: Lodging and M&IE - HQ Project Management Trip | G49: Day | H49: =H48*5 -> 5 | I49: 100 | J49: =H49*I49 -> 500 | L49: =L48*5 -> 15 | M49: =I49*L49*$F$6 -> 1545 | O49: =O48*5 -> 15 | P49: =I49*O49*$F$6*$F$6 -> 1591.35 | R49: =R48*5 -> 15 | S49: =I49*R49*$F$6*$F$6*$F$6 -> 1639.0905 | U49: =U48*5 -> 15 | V49: =U49*I49*$F$6*$F$6*$F$6*$F$6 -> 1688.2632 | W49: =SUM(S49,P49,M49,J49,V49) -> 6963.7037 | X49: - | Y49: =SUM(W49:X49) -> 6963.7037 | AA49: 0.5 | AB49: 0.5
A50: STFTRVCTS | B50: 86000 | C50: USA | D50: 0 | E50: Local Transportation – HQ Project Management Trip | G50: Trip | H50: =H48 -> 1 | I50: 100 | J50: =H50*I50 -> 100 | L50: =L48 -> 3 | M50: =I50*L50*$F$6 -> 309 | O50: =O48 -> 3 | P50: =I50*O50*$F$6*$F$6 -> 318.27 | R50: =R48 -> 3 | S50: =I50*R50*$F$6*$F$6*$F$6 -> 327.8181 | U50: =U48 -> 3 | V50: =U50*I50*$F$6*$F$6*$F$6*$F$6 -> 337.65264 | W50: =SUM(S50,P50,M50,J50,V50) -> 1392.7407 | X50: - | Y50: =SUM(W50:X50) -> 1392.7407 | AA50: 0.5 | AB50: 0.5
A51: STFTRVCTS | B51: 86050 | C51: USA | D51: 0 | E51: Other Travel Related Expenses – HQ Project Management Trip | G51: Trip | H51: =H48 -> 1 | I51: 25 | J51: =H51*I51 -> 25 | L51: =L48 -> 3 | M51: =I51*L51*$F$6 -> 77.25 | O51: =O48 -> 3 | P51: =I51*O51*$F$6*$F$6 -> 79.5675 | R51: =R48 -> 3 | S51: =I51*R51*$F$6*$F$6*$F$6 -> 81.954525 | U51: =U48 -> 3 | V51: =U51*I51*$F$6*$F$6*$F$6*$F$6 -> 84.413161 | W51: =SUM(S51,P51,M51,J51,V51) -> 348.18519 | X51: - | Y51: =SUM(W51:X51) -> 348.18519 | AA51: 0.5 | AB51: 0.5
E52: Colombia Staff Travel - International
A53: INTLTRVLCO | B53: 86040 | C53: COL2 | D53: 0 | E53: Airfare - Roundtrip - Colombia to USA | G53: Trip | H53: 1 | I53: 800 | J53: =H53*I53 -> 800 | L53: 3 | M53: =I53*L53*$F$6 -> 2472 | O53: 3 | P53: =I53*O53*$F$6*$F$6 -> 2546.16 | R53: 3 | S53: =I53*R53*$F$6*$F$6*$F$6 -> 2622.5448 | U53: 3 | V53: =U53*I53*$F$6*$F$6*$F$6*$F$6 -> 2701.2211 | W53: =SUM(S53,P53,M53,J53,V53) -> 11141.926 | X53: - | Y53: =SUM(W53:X53) -> 11141.926 | AA53: 0.5 | AB53: 0.5
A54: INTLTRVLCO | B54: 86030 (Lodging)/ 86050 (M&IE) | C54: COL2 | D54: 0 | E54: Lodging and M&IE for Colombia Staff Travel | G54: Day | H54: =10*H53 -> 10 | I54: 150 | J54: =H54*I54 -> 1500 | L54: =10*L53 -> 30 | M54: =I54*L54*$F$6 -> 4635 | O54: =10*O53 -> 30 | P54: =I54*O54*$F$6*$F$6 -> 4774.05 | R54: =10*R53 -> 30 | S54: =I54*R54*$F$6*$F$6*$F$6 -> 4917.2715 | U54: =10*U53 -> 30 | V54: =U54*I54*$F$6*$F$6*$F$6*$F$6 -> 5064.7896 | W54: =SUM(S54,P54,M54,J54,V54) -> 20891.111 | X54: - | Y54: =SUM(W54:X54) -> 20891.111 | AA54: 0.5 | AB54: 0.5
A55: INTLTRVLCO | B55: 86000 | C55: COL2 | D55: 0 | E55: Local Transportation for Colombia Staff Travel | G55: Trip | H55: =H53 -> 1 | I55: 50 | J55: =H55*I55 -> 50 | L55: =L53 -> 3 | M55: =I55*L55*$F$6 -> 154.5 | O55: =O53 -> 3 | P55: =I55*O55*$F$6*$F$6 -> 159.135 | R55: =R53 -> 3 | S55: =I55*R55*$F$6*$F$6*$F$6 -> 163.90905 | U55: =U53 -> 3 | V55: =U55*I55*$F$6*$F$6*$F$6*$F$6 -> 168.82632 | W55: =SUM(S55,P55,M55,J55,V55) -> 696.37037 | X55: - | Y55: =SUM(W55:X55) -> 696.37037 | AA55: 0.5 | AB55: 0.5
A56: INTLTRVLCO | B56: 86050 | C56: COL2 | D56: 0 | E56: Other Travel Related Expenses for Colombia Staff Travel | G56: Trip | H56: =H53 -> 1 | I56: 25 | J56: =H56*I56 -> 25 | L56: =L53 -> 3 | M56: =I56*L56*$F$6 -> 77.25 | O56: =O53 -> 3 | P56: =I56*O56*$F$6*$F$6 -> 79.5675 | R56: =R53 -> 3 | S56: =I56*R56*$F$6*$F$6*$F$6 -> 81.954525 | U56: =U53 -> 3 | V56: =U56*I56*$F$6*$F$6*$F$6*$F$6 -> 84.413161 | W56: =SUM(S56,P56,M56,J56,V56) -> 348.18519 | X56: - | Y56: =SUM(W56:X56) -> 348.18519 | AA56: 0.5 | AB56: 0.5
E57: Colombia Local Staff Travel - Domestic
A58: LOCAL TRVL | B58: 86000 | C58: COL2 | D58: 0 | E58: Vehicle/Motorcycle Fuel Expense | G58: Month | H58: 3 | I58: 400 | J58: =H58*I58 -> 1200 | L58: 12 | M58: =L58*I58*$F$7 -> 4992 | O58: 12 | P58: =O58*I58*$F$7*$F$7 -> 5191.68 | R58: 12 | S58: =R58*I58*$F$7*$F$7*$F$7 -> 5399.3472 | U58: 9 | V58: =U58*I58*$F$7*$F$7*$F$7*$F$7 -> 4211.4908 | W58: =SUM(S58,P58,M58,J58,V58) -> 20994.518 | X58: - | Y58: =SUM(W58:X58) -> 20994.518 | AA58: 0.5 | AB58: 0.5
A59: LOCAL TRVL | B59: 86000 | C59: COL2 | D59: 0 | E59: Local Transportation – Training, M&E, & Data Collection | G59: Trip | H59: =12*3 -> 36 | I59: 100 | J59: =H59*I59 -> 3600 | L59: =12*3 -> 36 | M59: =I59*L59*$F$7 -> 3744 | O59: =12*3 -> 36 | P59: =I59*O59*$F$7*$F$7 -> 3893.76 | R59: =12*3 -> 36 | S59: =I59*R59*$F$7*$F$7*$F$7 -> 4049.5104 | U59: =12*3 -> 36 | V59: =I59*U59*$F$7*$F$7*$F$7*$F$7 -> 4211.4908 | W59: =SUM(S59,P59,M59,J59,V59) -> 19498.761 | X59: - | Y59: =SUM(W59:X59) -> 19498.761 | AA59: 0.5 | AB59: 0.5
A60: LOCAL TRVL | B60: 86030 (Lodging)/ 86050 (M&IE) | C60: COL2 | D60: 0 | E60: Lodging and M&IE - Training, M&E, & Data Collection | G60: Day | H60: =4*H59 -> 144 | I60: 80 | J60: =H60*I60 -> 11520 | L60: =4*L59 -> 144 | M60: =I60*L60*$F$7 -> 11980.8 | O60: =4*O59 -> 144 | P60: =I60*O60*$F$7*$F$7 -> 12460.032 | R60: =4*R59 -> 144 | S60: =I60*R60*$F$7*$F$7*$F$7 -> 12958.433 | U60: =4*U59 -> 144 | V60: =I60*U60*$F$7*$F$7*$F$7*$F$7 -> 13476.771 | W60: =SUM(S60,P60,M60,J60,V60) -> 62396.036 | X60: - | Y60: =SUM(W60:X60) -> 62396.036 | AA60: 0.5 | AB60: 0.5
E61: Total Travel | J61: =SUM(J47:J60) -> 20120 | M61: =SUM(M47:M60) -> 32458.8 | P61: =SUM(P47:P60) -> 33639.732 | S61: =SUM(S47:S60) -> 34864.379 | V61: =SUM(V47:V60) -> 34730.553 | W61: =SUM(W47:W60) -> 155813.46 | X61: =SUM(X47:X60) -> 0 | Y61: =SUM(Y47:Y60) -> 155813.46 | AA61: =SUMPRODUCT(Y48:Y60,AA48:AA60) -> 77906.732 | AB61: =SUMPRODUCT(Y48:Y60,AB48:AB60) -> 77906.732
E63: Professional Services/Contractual
A64: AUDIT | B64: 82100 | C64: COL2 | D64: 0 | E64: Audit Costs - (Auditoria Fiscal & Program Specific Audits) | G64: Year | H64: 1 | I64: 5000 | J64: =H64*I64 -> 5000 | L64: 1 | M64: =L64*I64 -> 5000 | O64: 1 | P64: =O64*I64 -> 5000 | R64: 1 | S64: =R64*I64 -> 5000 | U64: 1 | V64: 5000 | W64: =SUM(S64,P64,M64,J64,V64) -> 25000 | X64: 0 | Y64: =W64+X64 -> 25000 | AA64: 0.5 | AB64: 0.5
A65: LEGAL | B65: 81010 | C65: COL2 | D65: 0 | E65: Legal Fees | G65: Year | H65: 1 | I65: 1500 | J65: =H65*I65 -> 1500 | L65: 1 | M65: =L65*I65 -> 1500 | O65: 1 | P65: =O65*I65 -> 1500 | R65: 1 | S65: =R65*I65 -> 1500 | U65: 1 | V65: =U65*I65 -> 1500 | W65: =SUM(S65,P65,M65,J65,V65) -> 7500 | X65: 0 | Y65: =W65+X65 -> 7500 | AA65: 0.5 | AB65: 0.5
A66: MONETIZE | B66: 81010 | C66: USA | D66: 0 | E66: Monetization Agent Fee | G66: % | I66: 0.025 | J66: =I66*21010500 -> 525262.5 | L66: 0 | M66: =L66*I66 -> 0 | O66: 0 | P66: =O66*I66 -> 0 | R66: 0 | S66: =R66*I66 -> 0 | U66: 0 | V66: =U66*I66 -> 0 | W66: =SUM(S66,P66,M66,J66,V66) -> 525262.5 | X66: 0 | Y66: =W66+X66 -> 525262.5 | AA66: 0.5 | AB66: 0.5
A67: MONEASSMT | B67: 81010 | C67: COL2 | D67: 0 | E67: Post Monetization Assessment | G67: Unit | H67: 0 | I67: 100000 | J67: =H67*I67 -> 0 | L67: 1 | M67: =L67*I67 -> 100000 | O67: 0 | P67: =O67*I67 -> 0 | R67: 0 | S67: =R67*I67 -> 0 | U67: 0 | V67: =U67*I67 -> 0 | W67: =SUM(S67,P67,M67,J67,V67) -> 100000 | X67: 0 | Y67: =W67+X67 -> 100000 | AA67: 0.5 | AB67: 0.5
A68: CONSULT | B68: 81000 | C68: COL2 | D68: 0 | E68: HQ Consultants & Advisory Support Services | G68: Month | H68: 5 | I68: 2500 | J68: =H68*I68 -> 12500 | L68: 12 | M68: =L68*I68 -> 30000 | O68: 12 | P68: =O68*I68 -> 30000 | R68: 12 | S68: =R68*I68 -> 30000 | U68: 6 | V68: =U68*I68 -> 15000 | W68: =SUM(S68,P68,M68,J68,V68) -> 117500 | X68: 0 | Y68: =W68+X68 -> 117500 | AA68: 0.5 | AB68: 0.5
E69: Monitoring, Evaluation, and Collection of Reliable Data
E70: Evaluations
A71: BASELINE | B71: 81010 | C71: COL2 | D71: 0 | E71: Baseline Evaluation | G71: Unit | H71: 1 | I71: =165000 -> 165000 | J71: =H71*I71 -> 165000 | L71: 0 | M71: =L71*I71 -> 0 | O71: 0 | P71: =O71*I71 -> 0 | R71: 0 | S71: =R71*I71 -> 0 | U71: 0 | V71: =U71*I71 -> 0 | W71: =SUM(S71,P71,M71,J71,V71) -> 165000 | X71: 0 | Y71: =W71+X71 -> 165000 | AA71: 0.5 | AB71: 0.5
A72: MIDTERM | B72: 81010 | C72: COL2 | D72: 0 | E72: Midterm Evaluation | G72: Unit | H72: 0 | I72: =185000 -> 185000 | J72: 0 | L72: 0 | M72: =L72*I72 -> 0 | O72: 1 | P72: =O72*I72 -> 185000 | R72: 0 | S72: =R72*I72 -> 0 | U72: 0 | V72: =U72*I72 -> 0 | W72: =SUM(S72,P72,M72,J72,V72) -> 185000 | X72: 0 | Y72: =W72+X72 -> 185000 | AA72: 0.5 | AB72: 0.5
A73: ENDLINE | B73: 81010 | C73: COL2 | D73: 0 | E73: Final Evaluation | G73: Unit | H73: 0 | I73: =175000 -> 175000 | J73: 0 | L73: 0 | M73: =L73*I73 -> 0 | O73: 0 | P73: =O73*I73 -> 0 | R73: 0 | S73: =R73*I73 -> 0 | U73: 1 | V73: =U73*I73 -> 175000 | W73: =SUM(S73,P73,M73,J73,V73) -> 175000 | X73: 0 | Y73: =W73+X73 -> 175000 | AA73: 0.5 | AB73: 0.5
A74: VALUECHAIN | B74: 81010 | C74: COL2 | D74: CIAT | E74: CIAT Subaward: Value Chain Analysis, Carbon Assessment, and Living Incomes | G74: Subrecipient | H74: 1 | J74: ='CIAT Sub Budget'!G73 -> 792798.72 | L74: 1 | M74: ='CIAT Sub Budget'!I73 -> 224566.02 | O74: 1 | P74: ='CIAT Sub Budget'!K73 -> 0 | R74: 1 | S74: ='CIAT Sub Budget'!M73 -> 0 | U74: 1 | V74: ='CIAT Sub Budget'!O73 -> 0 | W74: =SUM(S74,P74,M74,J74,V74) -> 1017364.7 | X74: ='CIAT Sub Budget'!Q73 -> 0 | Y74: =SUM(W74:X74) -> 1017364.7 | AA74: 0.5 | AB74: 0.5
E75: Monitoring Guidelines Development
A76: M&ETRAIN | B76: 81021 (Translation)/ 85300 (Printing) | C76: COL2 | D76: 0 | E76: Monitoring Guidelines Creation, Translation & Printing | G76: Document | H76: 1 | I76: 8000 | J76: =H76*I76 -> 8000 | L76: 0 | M76: =L76*I76 -> 0 | O76: 0 | P76: =O76*I76 -> 0 | R76: 0 | S76: =R76*I76 -> 0 | U76: 0 | V76: =U76*L76 -> 0 | W76: =SUM(S76,P76,M76,J76,V76) -> 8000 | X76: - | Y76: =SUM(W76:X76) -> 8000 | AA76: 0.5 | AB76: 0.5
A77: M&ETRAIN | B77: 87000 | C77: COL2 | D77: 0 | E77: Monitoring Guidelines Staff Training Workshop | G77: Workshop | H77: 1 | I77: 3000 | J77: =H77*I77 -> 3000 | L77: 0 | M77: =L77*I77 -> 0 | O77: 0 | P77: =O77*I77 -> 0 | R77: 0 | S77: =R77*I77 -> 0 | U77: 0 | V77: =U77*L77 -> 0 | W77: =SUM(S77,P77,M77,J77,V77) -> 3000 | X77: - | Y77: =SUM(W77:X77) -> 3000 | AA77: 0.5 | AB77: 0.5
E78: M&E Database
A79: M&EDATA | B79: 81000 | C79: USA | D79: 0 | E79: M&E Software Setup | G79: Year | H79: 1 | I79: 28000 | J79: =H79*I79 -> 28000 | L79: 0 | M79: =L79*I79 -> 0 | O79: 0 | P79: =O79*I79 -> 0 | R79: 0 | S79: =R79*I79 -> 0 | U79: 0 | V79: =U79*I79 -> 0 | W79: =SUM(S79,P79,M79,J79,V79) -> 28000 | X79: - | Y79: =SUM(W79:X79) -> 28000 | AA79: 0.5 | AB79: 0.5
A80: M&EDATA | B80: 89400 | C80: USA | D80: 0 | E80: M&E Software Fee | G80: Year | H80: 1 | I80: 24000 | J80: =H80*I80 -> 24000 | L80: 1 | M80: =L80*I80 -> 24000 | O80: 1 | P80: =O80*I80 -> 24000 | R80: 1 | S80: =R80*I80 -> 24000 | U80: 1 | V80: =U80*I80 -> 24000 | W80: =SUM(S80,P80,M80,J80,V80) -> 120000 | Y80: =SUM(W80:X80) -> 120000 | AA80: 0.5 | AB80: 0.5
A81: M&EDATA | B81: 87000 | C81: USA | D81: 0 | E81: M&E Software Training | G81: Year | H81: 1 | I81: 5000 | J81: =H81*I81 -> 5000 | M81: =L81*I81 -> 0 | P81: =O81*I81 -> 0 | S81: =R81*I81 -> 0 | V81: =U81*I81 -> 0 | W81: =SUM(S81,P81,M81,J81,V81) -> 5000 | X81: - | Y81: =SUM(W81:X81) -> 5000 | Z81: M&E Percentage of Total Budget | AA81: 0.5 | AB81: 0.5
E82: Monitoring, Evaluation, and Collection of Reliable Data Subtotal | J82: =SUM(J70:J81) -> 1025798.7 | M82: =SUM(M70:M81) -> 248566.02 | P82: =SUM(P70:P81) -> 209000 | S82: =SUM(S70:S81) -> 24000 | V82: =SUM(V70:V81) -> 199000 | W82: =SUM(W70:W81) -> 1706364.7 | X82: =SUM(X70:X81) -> 0 | Y82: =SUM(Y70:Y81) -> 1706364.7 | Z82: =W82/W538 -> 0.072580542
E84: Total Professional Services/Contractual | J84: =SUM(J64:J81) -> 1570061.2 | M84: =SUM(M64:M81) -> 385066.02 | P84: =SUM(P64:P81) -> 245500 | S84: =SUM(S64:S81) -> 60500 | V84: =SUM(V64:V81) -> 220500 | W84: =SUM(W64:W81) -> 2481627.2 | X84: =SUM(X64:X81) -> 0 | Y84: =SUM(W84:X84) -> 2481627.2 | AA84: =SUMPRODUCT(Y64:Y81,AA64:AA81) -> 1240813.6 | AB84: =SUMPRODUCT(Y64:Y81,AB64:AB81) -> 1240813.6
E86: Equipment
A87: VEHICLE | B87: 85200 | C87: COL2 | D87: 0 | E87: Vehicles for Field Office | G87: Unit | H87: 2 | I87: 50000 | J87: =H87*I87 -> 100000 | L87: 0 | M87: =L87*I87 -> 0 | O87: 0 | P87: =O87*I87 -> 0 | R87: 0 | S87: =R87*I87 -> 0 | U87: 0 | V87: =U87*L87 -> 0 | W87: =SUM(S87,P87,M87,J87,V87) -> 100000 | X87: 0 | Y87: =W87+X87 -> 100000 | AA87: 0.5 | AB87: 0.5
E89: Total Equipment | J89: =SUM(J87:J87) -> 100000 | M89: =SUM(M87:M87) -> 0 | P89: =SUM(P87:P87) -> 0 | S89: =SUM(S87:S87) -> 0 | V89: =SUM(V87:V87) -> 0 | W89: =SUM(W87:W88) -> 100000 | X89: =SUM(X87:X87) -> 0 | Y89: =SUM(W89:X89) -> 100000 | AA89: =Y89*AA87 -> 50000 | AB89: =Y89*AB87 -> 50000
E91: Office Expenses
E92: Office in Bogota
A93: COMM | B93: 82350 | C93: COL2/USA | D93: 0 | E93: Courier fees/services/Postage | G93: Month | H93: 3 | I93: 30 | J93: =H93*I93 -> 90 | L93: 12 | M93: =L93*I93*$F$7 -> 374.4 | O93: 12 | P93: =O93*I93*$F$7*$F$7 -> 389.376 | R93: 12 | S93: =R93*I93*$F$7*$F$7*$F$7 -> 404.95104 | U93: 6 | V93: =U93*I93*$F$7*$F$7*$F$7*$F$7 -> 210.57454 | W93: =SUM(S93,P93,M93,J93,V93) -> 1469.3016 | X93: 0 | Y93: =W93+X93 -> 1469.3016 | AA93: 0.5 | AB93: 0.5
A94: COMM | B94: 82030 | C94: COL2/USA | D94: 0 | E94: Email/Internet | G94: Month | H94: 3 | I94: 150 | J94: =H94*I94 -> 450 | L94: 12 | M94: =L94*I94*$F$7 -> 1872 | O94: 12 | P94: =O94*I94*$F$7*$F$7 -> 1946.88 | R94: 12 | S94: =R94*I94*$F$7*$F$7*$F$7 -> 2024.7552 | U94: 6 | V94: =U94*I94*$F$7*$F$7*$F$7*$F$7 -> 1052.8727 | W94: =SUM(S94,P94,M94,J94,V94) -> 7346.5079 | X94: 0 | Y94: =W94+X94 -> 7346.5079 | AA94: 0.5 | AB94: 0.5
A95: COMM | B95: 82350 | C95: COL2/USA | D95: 0 | E95: Courier fees/services/Postage | G95: Month | H95: 3 | I95: 250 | J95: =H95*I95 -> 750 | L95: 12 | M95: =L95*I95*$F$7 -> 3120 | O95: 12 | P95: =O95*I95*$F$7*$F$7 -> 3244.8 | R95: 12 | S95: =R95*I95*$F$7*$F$7*$F$7 -> 3374.592 | U95: 6 | V95: =U95*I95*$F$7*$F$7*$F$7*$F$7 -> 1754.7878 | W95: =SUM(S95,P95,M95,J95,V95) -> 12244.18 | X95: 0 | Y95: =W95+X95 -> 12244.18 | AA95: 0.5 | AB95: 0.5
A96: ADVERTISIN | B96: 90450 | C96: COL2/USA | D96: 0 | E96: Recruitment/Procurement Advertising | G96: Year | H96: 1 | I96: 470.8 | J96: =H96*I96 -> 470.8 | L96: 1 | M96: =L96*I96*$F$7 -> 489.632 | O96: 1 | P96: =O96*I96*$F$7*$F$7 -> 509.21728 | R96: 1 | S96: =R96*I96*$F$7*$F$7*$F$7 -> 529.58597 | U96: 1 | V96: =U96*I96*$F$7*$F$7*$F$7*$F$7 -> 550.76941 | W96: =SUM(S96,P96,M96,J96,V96) -> 2550.0047 | X96: 0 | Y96: =W96+X96 -> 2550.0047 | AA96: 0.5 | AB96: 0.5
A97: RENT & UT | B97: 85180 | C97: COL2 | D97: 0 | E97: Office Rent, Utilities & Security (Bogota) | G97: Month | H97: 3 | I97: 3000 | J97: =H97*I97 -> 9000 | L97: 12 | M97: =L97*I97*$F$7 -> 37440 | O97: 12 | P97: =O97*I97*$F$7*$F$7 -> 38937.6 | R97: 12 | S97: =R97*I97*$F$7*$F$7*$F$7 -> 40495.104 | U97: 6 | V97: =U97*I97*$F$7*$F$7*$F$7*$F$7 -> 21057.454 | W97: =SUM(S97,P97,M97,J97,V97) -> 146930.16 | X97: 0 | Y97: =W97+X97 -> 146930.16 | AA97: 0.5 | AB97: 0.5
A98: BANK FEES | B98: 90900 | C98: COL2/USA | D98: 0 | E98: Banking and Cash Handling Fees | G98: Month | H98: 3 | I98: 200 | J98: =H98*I98 -> 600 | L98: 12 | M98: =L98*I98*$F$7 -> 2496 | O98: 12 | P98: =O98*I98*$F$7*$F$7 -> 2595.84 | R98: 12 | S98: =R98*I98*$F$7*$F$7*$F$7 -> 2699.6736 | U98: 6 | V98: =U98*I98*$F$7*$F$7*$F$7*$F$7 -> 1403.8303 | W98: =SUM(S98,P98,M98,J98,V98) -> 9795.3439 | X98: 0 | Y98: =W98+X98 -> 9795.3439 | AA98: 0.5 | AB98: 0.5
A99: MEETING | B99: 87010 | C99: COL2/USA | D99: 0 | E99: Office Meeting Expenses and Communications | G99: Month | H99: 3 | I99: 250 | J99: =H99*I99 -> 750 | L99: 12 | M99: =L99*I99*$F$7 -> 3120 | O99: 12 | P99: =O99*I99*$F$7*$F$7 -> 3244.8 | R99: 12 | S99: =R99*I99*$F$7*$F$7*$F$7 -> 3374.592 | U99: 6 | V99: =U99*I99*$F$7*$F$7*$F$7*$F$7 -> 1754.7878 | W99: =SUM(S99,P99,M99,J99,V99) -> 12244.18 | X99: 0 | Y99: =W99+X99 -> 12244.18 | AA99: 0.5 | AB99: 0.5
A100: SUBSCRIPT | B100: 89400 | C100: COL2/USA | D100: 0 | E100: Licenses & Subscriptions | G100: Month | H100: 3 | I100: 600 | J100: =H100*I100 -> 1800 | L100: 12 | M100: =L100*I100*$F$7 -> 7488 | O100: 12 | P100: =O100*I100*$F$7*$F$7 -> 7787.52 | R100: 12 | S100: =R100*I100*$F$7*$F$7*$F$7 -> 8099.0208 | U100: 6 | V100: =U100*I100*$F$7*$F$7*$F$7*$F$7 -> 4211.4908 | W100: =SUM(S100,P100,M100,J100,V100) -> 29386.032 | X100: 0 | Y100: =W100+X100 -> 29386.032 | AA100: 0.5 | AB100: 0.5
E102: Total Office Expenses | J102: =SUM(J93:J100) -> 13910.8 | M102: =SUM(M93:M100) -> 56400.032 | P102: =SUM(P93:P100) -> 58656.033 | S102: =SUM(S93:S100) -> 61002.275 | V102: =SUM(V93:V100) -> 31996.568 | W102: =SUM(W93:W101) -> 221965.71 | X102: =SUM(X93:X100) -> 0 | Y102: =SUM(W102:X102) -> 221965.71 | AA102: =SUMPRODUCT(Y93:Y100,AA93:AA100) -> 110982.85 | AB102: =SUMPRODUCT(Y93:Y100,AB93:AB100) -> 110982.85
E104: Office Supplies
A105: MOTORCYCLE | B105: 82401 | C105: COL2 | D105: 0 | E105: Motorcycles for Field Office | G105: Unit | H105: 15 | I105: 1100 | J105: =H105*I105 -> 16500 | L105: 0 | M105: =L105*I105 -> 0 | O105: 0 | P105: =O105*I105 -> 0 | R105: 0 | S105: =R105*I105 -> 0 | U105: 0 | V105: =U105*L105 -> 0 | W105: =SUM(S105,P105,M105,J105,V105) -> 16500 | X105: 0 | Y105: =W105+X105 -> 16500 | AA105: 0.5 | AB105: 0.5
A106: SUPPLIES | B106: 82401 | C106: COL2/USA | D106: 0 | E106: Desktop/Laptop Computers | G106: Unit | H106: 29 | I106: =Supplies!B12 -> 1114.97 | J106: =H106*I106 -> 32334.13 | L106: 0 | M106: =L106*I106 -> 0 | O106: 0 | P106: =O106*I106 -> 0 | R106: 0 | S106: =R106*I106 -> 0 | U106: 0 | V106: =U106*L106 -> 0 | W106: =SUM(S106,P106,M106,J106,V106) -> 32334.13 | X106: 0 | Y106: =W106+X106 -> 32334.13 | AA106: 0.5 | AB106: 0.5
A107: SUPPLIES | B107: 82401 | C107: COL2/USA | D107: 0 | E107: Tablets for Rural Data Collection | G107: Unit | H107: 15 | I107: =Supplies!B5 -> 850 | J107: =H107*I107 -> 12750 | L107: 0 | M107: =L107*I107 -> 0 | O107: 0 | P107: =O107*I107 -> 0 | R107: 0 | S107: =R107*I107 -> 0 | U107: 0 | V107: =U107*L107 -> 0 | W107: =SUM(S107,P107,M107,J107,V107) -> 12750 | X107: 0 | Y107: =W107+X107 -> 12750 | AA107: 0.5 | AB107: 0.5
A108: SUPPLIES | B108: 82401 | C108: COL2/USA | D108: 0 | E108: All in One: Printer, Photocopier & Scanner | G108: Unit | H108: 2 | I108: =Supplies!B22 -> 840 | J108: =H108*I108 -> 1680 | L108: 0 | M108: =L108*I108 -> 0 | O108: 0 | P108: =O108*I108 -> 0 | R108: 0 | S108: =R108*I108 -> 0 | U108: 0 | V108: =U108*L108 -> 0 | W108: =SUM(S108,P108,M108,J108,V108) -> 1680 | X108: 0 | Y108: =W108+X108 -> 1680 | AA108: 0.5 | AB108: 0.5
A109: SUPPLIES | B109: 82401 | C109: COL2/USA | D109: 0 | E109: Projector | G109: Unit | H109: 1 | I109: =Supplies!B17 -> 634.5 | J109: =H109*I109 -> 634.5 | L109: 0 | M109: =L109*I109 -> 0 | O109: 0 | P109: =O109*I109 -> 0 | R109: 0 | S109: =R109*I109 -> 0 | U109: 0 | V109: =U109*L109 -> 0 | W109: =SUM(S109,P109,M109,J109,V109) -> 634.5 | X109: 0 | Y109: =W109+X109 -> 634.5 | AA109: 0.5 | AB109: 0.5
A110: SUPPLIES | B110: 82401 | C110: COL2/USA | D110: 0 | E110: Office Furniture (Includes Desk, Chairs, Table, Shelves, Filing Cabinet, Safes, & A/C Unit) | G110: Unit | H110: 1 | I110: 8000 | J110: =H110*I110 -> 8000 | L110: 0 | M110: =L110*I110 -> 0 | O110: 0 | P110: =O110*I110 -> 0 | R110: 0 | S110: =R110*I110 -> 0 | U110: 0 | V110: =U110*L110 -> 0 | W110: =SUM(S110,P110,M110,J110,V110) -> 8000 | X110: 0 | Y110: =W110+X110 -> 8000 | AA110: 0.5 | AB110: 0.5
A111: SUPPLIES | B111: 82401 | C111: COL2/USA | D111: 0 | E111: Office Supplies & Personal Protective Equipment | G111: Month | H111: 3 | I111: 300 | J111: =H111*I111 -> 900 | L111: 12 | M111: =L111*I111*$F$7 -> 3744 | O111: 12 | P111: =O111*I111*$F$7*$F$7 -> 3893.76 | R111: 12 | S111: =R111*I111*$F$7*$F$7*$F$7 -> 4049.5104 | U111: 6 | V111: =U111*I111*$F$7*$F$7*$F$7*$F$7 -> 2105.7454 | W111: =SUM(S111,P111,M111,J111,V111) -> 14693.016 | X111: 0 | Y111: =W111+X111 -> 14693.016 | AA111: 0.5 | AB111: 0.5
E113: Total Office Supplies | J113: =SUM(J105:J112) -> 72798.63 | M113: =SUM(M105:M112) -> 3744 | P113: =SUM(P105:P112) -> 3893.76 | S113: =SUM(S105:S112) -> 4049.5104 | V113: =SUM(V105:V112) -> 2105.7454 | W113: =SUM(W105:W112) -> 86591.646 | X113: =SUM(X105:X112) -> 0 | Y113: =SUM(Y105:Y112) -> 86591.646 | AA113: =SUMPRODUCT(Y105:Y111,AA105:AA111) -> 43295.823 | AB113: =SUMPRODUCT(Y105:Y111,AB105:AB111) -> 43295.823
...

Sheet Partners by Activity
C1: Admin | D1: Activity 1. Value Chain Development (VC Study, Living Income, Carbon) | E1: Activity 2. Producer Organization Development & Commercialization | F1: Activity 3. Agriculture Extension and Production Support | G1: Activity 4. Post-Harvest Aggregation & Processing . Seedstock/Nurseries | H1: Activity 5. Ensure Financial Service/ Capital Access for Actors in the Value Chains | I1: Activity 6. Innovation and Job Creation Through Youth Engagement | J1: Activity 7. Establishment of Regional Community of Practice | K1: Activity 8. Financial Services: Endowment Establishment, Fundraising and Management
A2: In-Country Partners | B2: Partners of the Americas | C2: ● | D2: ● | E2: ● | F2: ● | G2: ● | H2: ● | I2: ● | J2: ● | K2: ● | L2: Prime Awardee with Regional Expertise
B3: CIAT | D3: ● | F3: ● | J3: ○ | L3: Major in-country research institution
B4: Agrosavia | G4: ● | J4: ○ | L4: Major in-country research institution
B5: Activity 2 partnership | E5: ● | J5: ○
B6: Fedecacao | D6: ○ | E6: ○ | F6: ○ | H6: ○ | I6: ○ | J6: ○ | L6: Colombian university with regional and research expertise
B7: Red Nacional Cacaotera | D7: ○ | E7: ○ | F7: ○ | H7: ○ | I7: ○ | J7: ○
B8: Sena | E8: ○ | H8: ○ | I8: ○ | J8: ○
B9: Office of the Vice President of Colombia | H9: ○ | I9: ○ | J9: ○ | K9: ○
B10: Nacional de Chocolates | D10: ○ | F10: ○ | I10: ○ | J10: ○ | K10: ○ | L10: Major in-country purchaser of Colombian cacao
B11: Luker Chocolates | D11: ○ | F11: ○ | G11: ○ | I11: ○ | J11: ○ | K11: ○ | L11: Major in-country purchaser of Colombian cacao
B12: Cacao Hunters | D12: ○ | F12: ○ | G12: ○ | I12: ○ | J12: ○ | K12: ○
B13: Other Colombian cacao companies | D13: ○ | F13: ○ | G13: ○ | I13: ○ | J13: ○ | K13: ○
B14: Other Colombian Complementary crops companies | D14: ○ | G14: ○ | I14: ○ | J14: ○ | L14: Colombian exporters of tropical fruit (pulp, juice concentrate, frozen) including soursop, guava, mango, papaya, and passion fruit, etc
B15: Digital training partnerships | F15: ● | J15: ○
B16: Carbon Partnerships | D16: ○ | F16: ● | J16: ○
B17: Food Safety, Traceability and Risk Management partnerships | F17: ● | J17: ○
B18: Other Extension-Producer support partnerships (Agromovil) | F18: ●
B19: Post harvest and aggregation partnerships | G19: ● | J19: ○
B20: Incubator/Accelerator partnerships | H20: ● | J20: ○
B21: ANDEAN* | I21: ○ | J21: ○ | K21: ○ | L21: Major in-country network for impact investors
B22: The National Fruit and Vegetable Association (ASOHOFRUCOL) | D22: ○ | E22: ○ | F22: ○ | G22: ○ | J22: ○ | L22: In-country association for commercialization of Colombian fruits and vegetables, administers the National Fund for Fruit and Vegetable Development
B23: Finanfuturo | G23: ○ | H23: ○ | J23: ○ | K23: ○ | L23: Impact investment arm of Citi Bank working in Cacao/illicit crop substitution
B24: Acumen, Alter-eco Foundation, InterAmerican Foundation & others | H24: ○ | J24: ○ | K24: ○ | L24: International Impact Investment firm with Bogota office
A25: Grants | B25: Multiple grant recipients | F25: ● | G25: ● | H25: ● | I25: ● | J25: ●
A26: International Partners | B26: World Cocoa Foundation | J26: ○ | K26: ○ | L26: Major international cacao sector development support organization
B27: American Retailer Chains | E27: ○ | G27: ○ | J27: ○ | L27: Global trader of tropical fruits sourced from Latin America, based in U.S. with offices across the region
L28: US-based market chain that sources from Latin America
L29: US-based market chain that sources from Latin America
A30: International Research Partners | B30: CATIE | J30: ○ | L30: Major International Agriculture Research Institution
B31: USDA ARS Tropical Crops and Germplasm Research (PR) | J31: ○ | L31: Major US Tropical Agriculture Research Institution
B32: Regional University Center of the Atlantic Coast (CURLA) | J32: ○ | L32: Major International Agriculture Research Institution
B33: Peruvian Amazon Research Institute | J33: ○ | L33: Tropical and Amazonian agriculture research station with cacao expertise
B34: Instituto Nacional de Investigaciones Agropecuarias (INIAP) | J34: ○ | L34: Major Ecuadorian agriculture research institution with cacao expertise
A36: ● | B36: Receives funding from C4D
A37: ○ | B37: Does not receive funding
S52: RACI for Activity 1 (Summarized Sample)
S53: Partners of the Americas | T53: CIAT | U53: USDA | V53: Fedecacao | W53: Red Cacaotera | X53: Sector Privado
R54: Questionnaire brainstorm | S54: A | T54: R | U54: A | V54: I | W54: I | X54: I
R55: Questionnaire Design/Validat | S55: A | T55: R | U55: I | V55: I | W55: I | X55: I
R56: Questionnaire Digitalization | S56: C | T56: R | U56: I | V56: I | W56: I | X56: I
R57: Data Capture | S57: C | T57: R | U57: I | V57: I | W57: I | X57: I
R58: Data Cleanup | S58: I | T58: R | U58: I | V58: I | W58: I | X58: I
R59: Data Aggregation | S59: I | T59: R | U59: I | V59: I | W59: I | X59: I
R60: Data Analysis | S60: A | T60: R | U60: I | V60: I | W60: I | X60: I
R61: Data Reporting | S61: A | T61: R | U61: I | V61: I | W61: I | X61: I
R63: Responsible | S63: R | T63: The people who actually do the work
R64: Accountable | S64: A | T64: The approver. Person who signs off on the work
R65: Consulted | S65: C | T65: SME consulted and can contribute to create content
R66: Informed | S66: I | T66: Group informed when a deliverable is complete

Sheet Personnel & LOE Summary
B1: Partners of the Americas – FY 2020 FFPr Colombia
B2: NOFO: USDA-FAS-10.606-0700-20-(514)
B3: Duration: 5 Years
B4: Country: Colombia
B5: Level of Effort (LOE) Breakdown by Activity
C7: Months in Year 1 | D7: Year 1 LOE | E7: Total Salary Amount Year 1 | F7: Months in Year 2 | G7: Year 2 LOE | H7: Total Salary Amount Year 2 | I7: Months in Year 3 | J7: Year 3 LOE | K7: Total Salary Amount Year 3 | L7: Months in Year 4 | M7: Year 4 LOE | N7: Total Salary Amount Year 4 | O7: Months in Year 5 | P7: Year 5 LOE | Q7: Total Salary Amount Year 5 | R7: Total Amount LOP
C8: LOE | D8: LOE | E8: LOE | F8: LOE | G8: LOE | H8: LOE | I8: LOE | J8: LOE | K8: LOE | L8: LOE | M8: LOE | N8: LOE | O8: LOE | P8: LOE | Q8: LOE | R8: LOE
B9: Personnel (Administration)
B10: Colombia National Staff
B11: ='Program Budget'!E13 -> Key Personnel: Chief of Party | C11: ='Program Budget'!H13 -> 12 | D11: ='Program Budget'!F13+'Program Budget'!F130+'Program Budget'!F168+'Program Budget'!F211+'Program Budget'!F270+'Program Budget'!F318+'Program Budget'!F372+'Program Budget'!F438+'Program Budget'!F484 -> 1 | E11: ='Program Budget'!J13+'Program Budget'!J130+'Program Budget'!J168+'Program Budget'!J211+'Program Budget'!J270+'Program Budget'!J318+'Program Budget'!J372+'Program Budget'!J438+'Program Budget'!J484 -> 150000 | F11: ='Program Budget'!L13 -> 12 | G11: ='Program Budget'!K13+'Program Budget'!K130+'Program Budget'!K168+'Program Budget'!K211+'Program Budget'!K270+'Program Budget'!K318+'Program Budget'!K372+'Program Budget'!K438+'Program Budget'!K484 -> 1 | H11: ='Program Budget'!M13+'Program Budget'!M130+'Program Budget'!M168+'Program Budget'!M211+'Program Budget'!M270+'Program Budget'!M318+'Program Budget'!M372+'Program Budget'!M438+'Program Budget'!M484 -> 156000 | I11: ='Program Budget'!O13 -> 12 | J11: ='Program Budget'!N13+'Program Budget'!N130+'Program Budget'!N168+'Program Budget'!N211+'Program Budget'!N270+'Program Budget'!N318+'Program Budget'!N372+'Program Budget'!N438+'Program Budget'!N484 -> 1 | K11: ='Program Budget'!P13+'Program Budget'!P130+'Program Budget'!P168+'Program Budget'!P211+'Program Budget'!P270+'Program Budget'!P318+'Program Budget'!P372+'Program Budget'!P438+'Program Budget'!P484 -> 162240 | L11: ='Program Budget'!R13 -> 12 | M11: ='Program Budget'!Q13+'Program Budget'!Q130+'Program Budget'!Q168+'Program Budget'!Q211+'Program Budget'!Q270+'Program Budget'!Q318+'Program Budget'!Q372+'Program Budget'!Q438+'Program Budget'!Q484 -> 1 | N11: ='Program Budget'!S13+'Program Budget'!S130+'Program Budget'!S168+'Program Budget'!S211+'Program Budget'!S270+'Program Budget'!S318+'Program Budget'!S372+'Program Budget'!S438+'Program Budget'!S484 -> 168729.6 | O11: ='Program Budget'!U13 -> 12 | P11: ='Program Budget'!T13+'Program Budget'!T130+'Program Budget'!T168+'Program Budget'!T211+'Program Budget'!T270+'Program Budget'!T318+'Program Budget'!T372+'Program Budget'!T438+'Program Budget'!T484 -> 1 | Q11: ='Program Budget'!V13+'Program Budget'!V130+'Program Budget'!V168+'Program Budget'!V211+'Program Budget'!V270+'Program Budget'!V318+'Program Budget'!V372+'Program Budget'!V438+'Program Budget'!V484 -> 175478.78 | R11: =E11+H11+K11+N11+Q11 -> 812448.38
B12: ='Program Budget'!E14 -> Key Personnel: Technical Director | C12: ='Program Budget'!H14 -> 8 | D12: ='Program Budget'!F14+'Program Budget'!F131+'Program Budget'!F169+'Program Budget'!F212+'Program Budget'!F271+'Program Budget'!F319+'Program Budget'!F373+'Program Budget'!F439+'Program Budget'!F485 -> 1 | E12: ='Program Budget'!J14+'Program Budget'!J131+'Program Budget'!J169+'Program Budget'!J212+'Program Budget'!J271+'Program Budget'!J319+'Program Budget'!J373+'Program Budget'!J439+'Program Budget'!J485 -> 46666.667 | F12: ='Program Budget'!L14 -> 12 | G12: ='Program Budget'!K14+'Program Budget'!K131+'Program Budget'!K169+'Program Budget'!K212+'Program Budget'!K271+'Program Budget'!K319+'Program Budget'!K373+'Program Budget'!K439+'Program Budget'!K485 -> 1 | H12: ='Program Budget'!M14+'Program Budget'!M131+'Program Budget'!M169+'Program Budget'!M212+'Program Budget'!M271+'Program Budget'!M319+'Program Budget'!M373+'Program Budget'!M439+'Program Budget'!M485 -> 72800 | I12: ='Program Budget'!O14 -> 12 | J12: ='Program Budget'!N14+'Program Budget'!N131+'Program Budget'!N169+'Program Budget'!N212+'Program Budget'!N271+'Program Budget'!N319+'Program Budget'!N373+'Program Budget'!N439+'Program Budget'!N485 -> 1 | K12: ='Program Budget'!P14+'Program Budget'!P131+'Program Budget'!P169+'Program Budget'!P212+'Program Budget'!P271+'Program Budget'!P319+'Program Budget'!P373+'Program Budget'!P439+'Program Budget'!P485 -> 75712 | L12: ='Program Budget'!R14 -> 12 | M12: ='Program Budget'!Q14+'Program Budget'!Q131+'Program Budget'!Q169+'Program Budget'!Q212+'Program Budget'!Q271+'Program Budget'!Q319+'Program Budget'!Q373+'Program Budget'!Q439+'Program Budget'!Q485 -> 1 | N12: ='Program Budget'!S14+'Program Budget'!S131+'Program Budget'!S169+'Program Budget'!S212+'Program Budget'!S271+'Program Budget'!S319+'Program Budget'!S373+'Program Budget'!S439+'Program Budget'!S485 -> 78740.48 | O12: ='Program Budget'!U14 -> 12 | P12: ='Program Budget'!T14+'Program Budget'!T131+'Program Budget'!T169+'Program Budget'!T212+'Program Budget'!T271+'Program Budget'!T319+'Program Budget'!T373+'Program Budget'!T439+'Program Budget'!T485 -> 1 | Q12: ='Program Budget'!V14+'Program Budget'!V131+'Program Budget'!V169+'Program Budget'!V212+'Program Budget'!V271+'Program Budget'!V319+'Program Budget'!V373+'Program Budget'!V439+'Program Budget'!V485 -> 81890.099 | R12: =E12+H12+K12+N12+Q12 -> 355809.25
B13: ='Program Budget'!E15 -> F&A Director | C13: ='Program Budget'!H15 -> 8 | D13: ='Program Budget'!F15+'Program Budget'!F132+'Program Budget'!F170+'Program Budget'!F213+'Program Budget'!F272+'Program Budget'!F320+'Program Budget'!F374+'Program Budget'!F440+'Program Budget'!F486 -> 1 | E13: ='Program Budget'!J15+'Program Budget'!J132+'Program Budget'!J170+'Program Budget'!J213+'Program Budget'!J272+'Program Budget'!J320+'Program Budget'!J374+'Program Budget'!J440+'Program Budget'!J486 -> 30666.667 | F13: ='Program Budget'!L15 -> 12 | G13: ='Program Budget'!K15+'Program Budget'!K132+'Program Budget'!K170+'Program Budget'!K213+'Program Budget'!K272+'Program Budget'!K320+'Program Budget'!K374+'Program Budget'!K440+'Program Budget'!K486 -> 1 | H13: ='Program Budget'!M15+'Program Budget'!M132+'Program Budget'!M170+'Program Budget'!M213+'Program Budget'!M272+'Program Budget'!M320+'Program Budget'!M374+'Program Budget'!M440+'Program Budget'!M486 -> 47840 | I13: ='Program Budget'!O15 -> 12 | J13: ='Program Budget'!N15+'Program Budget'!N132+'Program Budget'!N170+'Program Budget'!N213+'Program Budget'!N272+'Program Budget'!N320+'Program Budget'!N374+'Program Budget'!N440+'Program Budget'!N486 -> 1 | K13: ='Program Budget'!P15+'Program Budget'!P132+'Program Budget'!P170+'Program Budget'!P213+'Program Budget'!P272+'Program Budget'!P320+'Program Budget'!P374+'Program Budget'!P440+'Program Budget'!P486 -> 49753.6 | L13: ='Program Budget'!R15 -> 12 | M13: ='Program Budget'!Q15+'Program Budget'!Q132+'Program Budget'!Q170+'Program Budget'!Q213+'Program Budget'!Q272+'Program Budget'!Q320+'Program Budget'!Q374+'Program Budget'!Q440+'Program Budget'!Q486 -> 1 | N13: ='Program Budget'!S15+'Program Budget'!S132+'Program Budget'!S170+'Program Budget'!S213+'Program Budget'!S272+'Program Budget'!S320+'Program Budget'!S374+'Program Budget'!S440+'Program Budget'!S486 -> 51743.744 | O13: ='Program Budget'!U15 -> 12 | P13: ='Program Budget'!T15+'Program Budget'!T132+'Program Budget'!T170+'Program Budget'!T213+'Program Budget'!T272+'Program Budget'!T320+'Program Budget'!T374+'Program Budget'!T440+'Program Budget'!T486 -> 1 | Q13: ='Program Budget'!V15+'Program Budget'!V132+'Program Budget'!V170+'Program Budget'!V213+'Program Budget'!V272+'Program Budget'!V320+'Program Budget'!V374+'Program Budget'!V440+'Program Budget'!V486 -> 53813.494 | R13: =E13+H13+K13+N13+Q13 -> 233817.5
B14: ='Program Budget'!E16 -> M&E Director | C14: ='Program Budget'!H16 -> 8 | D14: ='Program Budget'!F16+'Program Budget'!F133+'Program Budget'!F171+'Program Budget'!F214+'Program Budget'!F273+'Program Budget'!F321+'Program Budget'!F375+'Program Budget'!F441+'Program Budget'!F487 -> 1 | E14: ='Program Budget'!J16+'Program Budget'!J133+'Program Budget'!J171+'Program Budget'!J214+'Program Budget'!J273+'Program Budget'!J321+'Program Budget'!J375+'Program Budget'!J441+'Program Budget'!J487 -> 30666.667 | F14: ='Program Budget'!L16 -> 12 | G14: ='Program Budget'!K16+'Program Budget'!K133+'Program Budget'!K171+'Program Budget'!K214+'Program Budget'!K273+'Program Budget'!K321+'Program Budget'!K375+'Program Budget'!K441+'Program Budget'!K487 -> 1 | H14: ='Program Budget'!M16+'Program Budget'!M133+'Program Budget'!M171+'Program Budget'!M214+'Program Budget'!M273+'Program Budget'!M321+'Program Budget'!M375+'Program Budget'!M441+'Program Budget'!M487 -> 47840 | I14: ='Program Budget'!O16 -> 12 | J14: ='Program Budget'!N16+'Program Budget'!N133+'Program Budget'!N171+'Program Budget'!N214+'Program Budget'!N273+'Program Budget'!N321+'Program Budget'!N375+'Program Budget'!N441+'Program Budget'!N487 -> 1 | K14: ='Program Budget'!P16+'Program Budget'!P133+'Program Budget'!P171+'Program Budget'!P214+'Program Budget'!P273+'Program Budget'!P321+'Program Budget'!P375+'Program Budget'!P441+'Program Budget'!P487 -> 49753.6 | L14: ='Program Budget'!R16 -> 12 | M14: ='Program Budget'!Q16+'Program Budget'!Q133+'Program Budget'!Q171+'Program Budget'!Q214+'Program Budget'!Q273+'Program Budget'!Q321+'Program Budget'!Q375+'Program Budget'!Q441+'Program Budget'!Q487 -> 1 | N14: ='Program Budget'!S16+'Program Budget'!S133+'Program Budget'!S171+'Program Budget'!S214+'Program Budget'!S273+'Program Budget'!S321+'Program Budget'!S375+'Program Budget'!S441+'Program Budget'!S487 -> 51743.744 | O14: ='Program Budget'!U16 -> 12 | P14: ='Program Budget'!T16+'Program Budget'!T133+'Program Budget'!T171+'Program Budget'!T214+'Program Budget'!T273+'Program Budget'!T321+'Program Budget'!T375+'Program Budget'!T441+'Program Budget'!T487 -> 1 | Q14: ='Program Budget'!V16+'Program Budget'!V133+'Program Budget'!V171+'Program Budget'!V214+'Program Budget'!V273+'Program Budget'!V321+'Program Budget'!V375+'Program Budget'!V441+'Program Budget'!V487 -> 53813.494 | R14: =E14+H14+K14+N14+Q14 -> 233817.5
B15: ='Program Budget'!E17 -> M&E Mid-level Specialist | C15: ='Program Budget'!H17 -> 7 | D15: ='Program Budget'!F17+'Program Budget'!F134+'Program Budget'!F172+'Program Budget'!F215+'Program Budget'!F274+'Program Budget'!F322+'Program Budget'!F376+'Program Budget'!F442+'Program Budget'!F488 -> 1 | E15: ='Program Budget'!J17+'Program Budget'!J134+'Program Budget'!J172+'Program Budget'!J215+'Program Budget'!J274+'Program Budget'!J322+'Program Budget'!J376+'Program Budget'!J442+'Program Budget'!J488 -> 18666.667 | F15: ='Program Budget'!L17 -> 12 | G15: ='Program Budget'!K17+'Program Budget'!K134+'Program Budget'!K172+'Program Budget'!K215+'Program Budget'!K274+'Program Budget'!K322+'Program Budget'!K376+'Program Budget'!K442+'Program Budget'!K488 -> 1 | H15: ='Program Budget'!M17+'Program Budget'!M134+'Program Budget'!M172+'Program Budget'!M215+'Program Budget'!M274+'Program Budget'!M322+'Program Budget'!M376+'Program Budget'!M442+'Program Budget'!M488 -> 33280 | I15: ='Program Budget'!O17 -> 12 | J15: ='Program Budget'!N17+'Program Budget'!N134+'Program Budget'!N172+'Program Budget'!N215+'Program Budget'!N274+'Program Budget'!N322+'Program Budget'!N376+'Program Budget'!N442+'Program Budget'!N488 -> 1 | K15: ='Program Budget'!P17+'Program Budget'!P134+'Program Budget'!P172+'Program Budget'!P215+'Program Budget'!P274+'Program Budget'!P322+'Program Budget'!P376+'Program Budget'!P442+'Program Budget'!P488 -> 34611.2 | L15: ='Program Budget'!R17 -> 12 | M15: ='Program Budget'!Q17+'Program Budget'!Q134+'Program Budget'!Q172+'Program Budget'!Q215+'Program Budget'!Q274+'Program Budget'!Q322+'Program Budget'!Q376+'Program Budget'!Q442+'Program Budget'!Q488 -> 1 | N15: ='Program Budget'!S17+'Program Budget'!S134+'Program Budget'!S172+'Program Budget'!S215+'Program Budget'!S274+'Program Budget'!S322+'Program Budget'!S376+'Program Budget'!S442+'Program Budget'!S488 -> 35995.648 | O15: ='Program Budget'!U17 -> 9 | P15: ='Program Budget'!T17+'Program Budget'!T134+'Program Budget'!T172+'Program Budget'!T215+'Program Budget'!T274+'Program Budget'!T322+'Program Budget'!T376+'Program Budget'!T442+'Program Budget'!T488 -> 1 | Q15: ='Program Budget'!V17+'Program Budget'!V134+'Program Budget'!V172+'Program Budget'!V215+'Program Budget'!V274+'Program Budget'!V322+'Program Budget'!V376+'Program Budget'!V442+'Program Budget'!V488 -> 28076.605 | R15: =E15+H15+K15+N15+Q15 -> 150630.12
B16: ='Program Budget'!E18 -> M&E Specialist | C16: ='Program Budget'!H18 -> 3 | D16: ='Program Budget'!F18+'Program Budget'!F135+'Program Budget'!F173+'Program Budget'!F216+'Program Budget'!F275+'Program Budget'!F323+'Program Budget'!F377+'Program Budget'!F443+'Program Budget'!F489 -> 1 | E16: ='Program Budget'!J18+'Program Budget'!J135+'Program Budget'!J173+'Program Budget'!J216+'Program Budget'!J275+'Program Budget'!J323+'Program Budget'!J377+'Program Budget'!J443+'Program Budget'!J489 -> 6500 | F16: ='Program Budget'!L18 -> 12 | G16: ='Program Budget'!K18+'Program Budget'!K135+'Program Budget'!K173+'Program Budget'!K216+'Program Budget'!K275+'Program Budget'!K323+'Program Budget'!K377+'Program Budget'!K443+'Program Budget'!K489 -> 1 | H16: ='Program Budget'!M18+'Program Budget'!M135+'Program Budget'!M173+'Program Budget'!M216+'Program Budget'!M275+'Program Budget'!M323+'Program Budget'!M377+'Program Budget'!M443+'Program Budget'!M489 -> 27040 | I16: ='Program Budget'!O18 -> 12 | J16: ='Program Budget'!N18+'Program Budget'!N135+'Program Budget'!N173+'Program Budget'!N216+'Program Budget'!N275+'Program Budget'!N323+'Program Budget'!N377+'Program Budget'!N443+'Program Budget'!N489 -> 1 | K16: ='Program Budget'!P18+'Program Budget'!P135+'Program Budget'!P173+'Program Budget'!P216+'Program Budget'!P275+'Program Budget'!P323+'Program Budget'!P377+'Program Budget'!P443+'Program Budget'!P489 -> 28121.6 | L16: ='Program Budget'!R18 -> 12 | M16: ='Program Budget'!Q18+'Program Budget'!Q135+'Program Budget'!Q173+'Program Budget'!Q216+'Program Budget'!Q275+'Program Budget'!Q323+'Program Budget'!Q377+'Program Budget'!Q443+'Program Budget'!Q489 -> 1 | N16: ='Program Budget'!S18+'Program Budget'!S135+'Program Budget'!S173+'Program Budget'!S216+'Program Budget'!S275+'Program Budget'!S323+'Program Budget'!S377+'Program Budget'!S443+'Program Budget'!S489 -> 29246.464 | O16: ='Program Budget'!U18 -> 9 | P16: ='Program Budget'!T18+'Program Budget'!T135+'Program Budget'!T173+'Program Budget'!T216+'Program Budget'!T275+'Program Budget'!T323+'Program Budget'!T377+'Program Budget'!T443+'Program Budget'!T489 -> 1 | Q16: ='Program Budget'!V18+'Program Budget'!V135+'Program Budget'!V173+'Program Budget'!V216+'Program Budget'!V275+'Program Budget'!V323+'Program Budget'!V377+'Program Budget'!V443+'Program Budget'!V489 -> 22812.242 | R16: =E16+H16+K16+N16+Q16 -> 113720.31
B17: ='Program Budget'!E19 -> Partnerships and Investment Director | C17: ='Program Budget'!H19 -> 8 | D17: ='Program Budget'!F19+'Program Budget'!F136+'Program Budget'!F174+'Program Budget'!F217+'Program Budget'!F276+'Program Budget'!F324+'Program Budget'!F378+'Program Budget'!F444+'Program Budget'!F490 -> 1 | E17: ='Program Budget'!J19+'Program Budget'!J136+'Program Budget'!J174+'Program Budget'!J217+'Program Budget'!J276+'Program Budget'!J324+'Program Budget'!J378+'Program Budget'!J444+'Program Budget'!J490 -> 30666.667 | F17: ='Program Budget'!L19 -> 12 | G17: ='Program Budget'!K19+'Program Budget'!K136+'Program Budget'!K174+'Program Budget'!K217+'Program Budget'!K276+'Program Budget'!K324+'Program Budget'!K378+'Program Budget'!K444+'Program Budget'!K490 -> 1 | H17: ='Program Budget'!M19+'Program Budget'!M136+'Program Budget'!M174+'Program Budget'!M217+'Program Budget'!M276+'Program Budget'!M324+'Program Budget'!M378+'Program Budget'!M444+'Program Budget'!M490 -> 47840 | I17: ='Program Budget'!O19 -> 12 | J17: ='Program Budget'!N19+'Program Budget'!N136+'Program Budget'!N174+'Program Budget'!N217+'Program Budget'!N276+'Program Budget'!N324+'Program Budget'!N378+'Program Budget'!N444+'Program Budget'!N490 -> 1 | K17: ='Program Budget'!P19+'Program Budget'!P136+'Program Budget'!P174+'Program Budget'!P217+'Program Budget'!P276+'Program Budget'!P324+'Program Budget'!P378+'Program Budget'!P444+'Program Budget'!P490 -> 49753.6 | L17: ='Program Budget'!R19 -> 12 | M17: ='Program Budget'!Q19+'Program Budget'!Q136+'Program Budget'!Q174+'Program Budget'!Q217+'Program Budget'!Q276+'Program Budget'!Q324+'Program Budget'!Q378+'Program Budget'!Q444+'Program Budget'!Q490 -> 1 | N17: ='Program Budget'!S19+'Program Budget'!S136+'Program Budget'!S174+'Program Budget'!S217+'Program Budget'!S276+'Program Budget'!S324+'Program Budget'!S378+'Program Budget'!S444+'Program Budget'!S490 -> 51743.744 | O17: ='Program Budget'!U19 -> 9 | P17: ='Program Budget'!T19+'Program Budget'!T136+'Program Budget'!T174+'Program Budget'!T217+'Program Budget'!T276+'Program Budget'!T324+'Program Budget'!T378+'Program Budget'!T444+'Program Budget'!T490 -> 1 | Q17: ='Program Budget'!V19+'Program Budget'!V136+'Program Budget'!V174+'Program Budget'!V217+'Program Budget'!V276+'Program Budget'!V324+'Program Budget'!V378+'Program Budget'!V444+'Program Budget'!V490 -> 40360.12 | R17: =E17+H17+K17+N17+Q17 -> 220364.13
B18: ='Program Budget'!E20 -> Extension Agents (15) | C18: ='Program Budget'!H20 -> 3 | D18: ='Program Budget'!F20+'Program Budget'!F137+'Program Budget'!F175+'Program Budget'!F218+'Program Budget'!F277+'Program Budget'!F325+'Program Budget'!F379+'Program Budget'!F445+'Program Budget'!F491 -> 1 | E18: ='Program Budget'!J20+'Program Budget'!J137+'Program Budget'!J175+'Program Budget'!J218+'Program Budget'!J277+'Program Budget'!J325+'Program Budget'!J379+'Program Budget'!J445+'Program Budget'!J491 -> 78750 | F18: ='Program Budget'!L20 -> 12 | G18: ='Program Budget'!K20+'Program Budget'!K137+'Program Budget'!K175+'Program Budget'!K218+'Program Budget'!K277+'Program Budget'!K325+'Program Budget'!K379+'Program Budget'!K445+'Program Budget'!K491 -> 1 | H18: ='Program Budget'!M20+'Program Budget'!M137+'Program Budget'!M175+'Program Budget'!M218+'Program Budget'!M277+'Program Budget'!M325+'Program Budget'!M379+'Program Budget'!M445+'Program Budget'!M491 -> 327600 | I18: ='Program Budget'!O20 -> 12 | J18: ='Program Budget'!N20+'Program Budget'!N137+'Program Budget'!N175+'Program Budget'!N218+'Program Budget'!N277+'Program Budget'!N325+'Program Budget'!N379+'Program Budget'!N445+'Program Budget'!N491 -> 1 | K18: ='Program Budget'!P20+'Program Budget'!P137+'Program Budget'!P175+'Program Budget'!P218+'Program Budget'!P277+'Program Budget'!P325+'Program Budget'!P379+'Program Budget'!P445+'Program Budget'!P491 -> 340704 | L18: ='Program Budget'!R20 -> 12 | M18: ='Program Budget'!Q20+'Program Budget'!Q137+'Program Budget'!Q175+'Program Budget'!Q218+'Program Budget'!Q277+'Program Budget'!Q325+'Program Budget'!Q379+'Program Budget'!Q445+'Program Budget'!Q491 -> 1 | N18: ='Program Budget'!S20+'Program Budget'!S137+'Program Budget'!S175+'Program Budget'!S218+'Program Budget'!S277+'Program Budget'!S325+'Program Budget'!S379+'Program Budget'!S445+'Program Budget'!S491 -> 354332.16 | O18: ='Program Budget'!U20 -> 9 | P18: ='Program Budget'!T20+'Program Budget'!T137+'Program Budget'!T175+'Program Budget'!T218+'Program Budget'!T277+'Program Budget'!T325+'Program Budget'!T379+'Program Budget'!T445+'Program Budget'!T491 -> 1 | Q18: ='Program Budget'!V20+'Program Budget'!V137+'Program Budget'!V175+'Program Budget'!V218+'Program Budget'!V277+'Program Budget'!V325+'Program Budget'!V379+'Program Budget'!V445+'Program Budget'!V491 -> 276379.08 | R18: =E18+H18+K18+N18+Q18 -> 1377765.2
B19: ='Program Budget'!E21 -> Activity Lead Agribusiness Senior Specialist (Cacao) | C19: ='Program Budget'!H21 -> 3 | D19: ='Program Budget'!F21+'Program Budget'!F138+'Program Budget'!F176+'Program Budget'!F219+'Program Budget'!F278+'Program Budget'!F326+'Program Budget'!F380+'Program Budget'!F446+'Program Budget'!F492 -> 1 | E19: ='Program Budget'!J21+'Program Budget'!J138+'Program Budget'!J176+'Program Budget'!J219+'Program Budget'!J278+'Program Budget'!J326+'Program Budget'!J380+'Program Budget'!J446+'Program Budget'!J492 -> 8500 | F19: ='Program Budget'!L21 -> 12 | G19: ='Program Budget'!K21+'Program Budget'!K138+'Program Budget'!K176+'Program Budget'!K219+'Program Budget'!K278+'Program Budget'!K326+'Program Budget'!K380+'Program Budget'!K446+'Program Budget'!K492 -> 1 | H19: ='Program Budget'!M21+'Program Budget'!M138+'Program Budget'!M176+'Program Budget'!M219+'Program Budget'!M278+'Program Budget'!M326+'Program Budget'!M380+'Program Budget'!M446+'Program Budget'!M492 -> 35360 | I19: ='Program Budget'!O21 -> 12 | J19: ='Program Budget'!N21+'Program Budget'!N138+'Program Budget'!N176+'Program Budget'!N219+'Program Budget'!N278+'Program Budget'!N326+'Program Budget'!N380+'Program Budget'!N446+'Program Budget'!N492 -> 1 | K19: ='Program Budget'!P21+'Program Budget'!P138+'Program Budget'!P176+'Program Budget'!P219+'Program Budget'!P278+'Program Budget'!P326+'Program Budget'!P380+'Program Budget'!P446+'Program Budget'!P492 -> 36774.4 | L19: ='Program Budget'!R21 -> 12 | M19: ='Program Budget'!Q21+'Program Budget'!Q138+'Program Budget'!Q176+'Program Budget'!Q219+'Program Budget'!Q278+'Program Budget'!Q326+'Program Budget'!Q380+'Program Budget'!Q446+'Program Budget'!Q492 -> 1 | N19: ='Program Budget'!S21+'Program Budget'!S138+'Program Budget'!S176+'Program Budget'!S219+'Program Budget'!S278+'Program Budget'!S326+'Program Budget'!S380+'Program Budget'!S446+'Program Budget'!S492 -> 38245.376 | O19: ='Program Budget'!U21 -> 9 | P19: ='Program Budget'!T21+'Program Budget'!T138+'Program Budget'!T176+'Program Budget'!T219+'Program Budget'!T278+'Program Budget'!T326+'Program Budget'!T380+'Program Budget'!T446+'Program Budget'!T492 -> 1 | Q19: ='Program Budget'!V21+'Program Budget'!V138+'Program Budget'!V176+'Program Budget'!V219+'Program Budget'!V278+'Program Budget'!V326+'Program Budget'!V380+'Program Budget'!V446+'Program Budget'!V492 -> 29831.393 | R19: =E19+H19+K19+N19+Q19 -> 148711.17
B20: ='Program Budget'!E22 -> Activity Lead Agribusiness Senior Specialist (Complementary Crop) | C20: ='Program Budget'!H22 -> 3 | D20: ='Program Budget'!F22+'Program Budget'!F139+'Program Budget'!F177+'Program Budget'!F220+'Program Budget'!F279+'Program Budget'!F327+'Program Budget'!F381+'Program Budget'!F447+'Program Budget'!F493 -> 1 | E20: ='Program Budget'!J22+'Program Budget'!J139+'Program Budget'!J177+'Program Budget'!J220+'Program Budget'!J279+'Program Budget'!J327+'Program Budget'!J381+'Program Budget'!J447+'Program Budget'!J493 -> 8500 | F20: ='Program Budget'!L22 -> 12 | G20: ='Program Budget'!K22+'Program Budget'!K139+'Program Budget'!K177+'Program Budget'!K220+'Program Budget'!K279+'Program Budget'!K327+'Program Budget'!K381+'Program Budget'!K447+'Program Budget'!K493 -> 1 | H20: ='Program Budget'!M22+'Program Budget'!M139+'Program Budget'!M177+'Program Budget'!M220+'Program Budget'!M279+'Program Budget'!M327+'Program Budget'!M381+'Program Budget'!M447+'Program Budget'!M493 -> 35360 | I20: ='Program Budget'!O22 -> 12 | J20: ='Program Budget'!N22+'Program Budget'!N139+'Program Budget'!N177+'Program Budget'!N220+'Program Budget'!N279+'Program Budget'!N327+'Program Budget'!N381+'Program Budget'!N447+'Program Budget'!N493 -> 1 | K20: ='Program Budget'!P22+'Program Budget'!P139+'Program Budget'!P177+'Program Budget'!P220+'Program Budget'!P279+'Program Budget'!P327+'Program Budget'!P381+'Program Budget'!P447+'Program Budget'!P493 -> 36774.4 | L20: ='Program Budget'!R22 -> 12 | M20: ='Program Budget'!Q22+'Program Budget'!Q139+'Program Budget'!Q177+'Program Budget'!Q220+'Program Budget'!Q279+'Program Budget'!Q327+'Program Budget'!Q381+'Program Budget'!Q447+'Program Budget'!Q493 -> 1 | N20: ='Program Budget'!S22+'Program Budget'!S139+'Program Budget'!S177+'Program Budget'!S220+'Program Budget'!S279+'Program Budget'!S327+'Program Budget'!S381+'Program Budget'!S447+'Program Budget'!S493 -> 38245.376 | O20: ='Program Budget'!U22 -> 9 | P20: ='Program Budget'!T22+'Program Budget'!T139+'Program Budget'!T177+'Program Budget'!T220+'Program Budget'!T279+'Program Budget'!T327+'Program Budget'!T381+'Program Budget'!T447+'Program Budget'!T493 -> 1 | Q20: ='Program Budget'!V22+'Program Budget'!V139+'Program Budget'!V177+'Program Budget'!V220+'Program Budget'!V279+'Program Budget'!V327+'Program Budget'!V381+'Program Budget'!V447+'Program Budget'!V493 -> 29831.393 | R20: =E20+H20+K20+N20+Q20 -> 148711.17
B21: ='Program Budget'!E23 -> Food Safety Mid-Specialist | C21: ='Program Budget'!H23 -> 3 | D21: ='Program Budget'!F23+'Program Budget'!F140+'Program Budget'!F178+'Program Budget'!F221+'Program Budget'!F280+'Program Budget'!F328+'Program Budget'!F382+'Program Budget'!F448+'Program Budget'!F494 -> 1 | E21: ='Program Budget'!J23+'Program Budget'!J140+'Program Budget'!J178+'Program Budget'!J221+'Program Budget'!J280+'Program Budget'!J328+'Program Budget'!J382+'Program Budget'!J448+'Program Budget'!J494 -> 8000 | F21: ='Program Budget'!L23 -> 12 | G21: ='Program Budget'!K23+'Program Budget'!K140+'Program Budget'!K178+'Program Budget'!K221+'Program Budget'!K280+'Program Budget'!K328+'Program Budget'!K382+'Program Budget'!K448+'Program Budget'!K494 -> 1 | H21: ='Program Budget'!M23+'Program Budget'!M140+'Program Budget'!M178+'Program Budget'!M221+'Program Budget'!M280+'Program Budget'!M328+'Program Budget'!M382+'Program Budget'!M448+'Program Budget'!M494 -> 33280 | I21: ='Program Budget'!O23 -> 12 | J21: ='Program Budget'!N23+'Program Budget'!N140+'Program Budget'!N178+'Program Budget'!N221+'Program Budget'!N280+'Program Budget'!N328+'Program Budget'!N382+'Program Budget'!N448+'Program Budget'!N494 -> 1 | K21: ='Program Budget'!P23+'Program Budget'!P140+'Program Budget'!P178+'Program Budget'!P221+'Program Budget'!P280+'Program Budget'!P328+'Program Budget'!P382+'Program Budget'!P448+'Program Budget'!P494 -> 34611.2 | L21: ='Program Budget'!R23 -> 12 | M21: ='Program Budget'!Q23+'Program Budget'!Q140+'Program Budget'!Q178+'Program Budget'!Q221+'Program Budget'!Q280+'Program Budget'!Q328+'Program Budget'!Q382+'Program Budget'!Q448+'Program Budget'!Q494 -> 1 | N21: ='Program Budget'!S23+'Program Budget'!S140+'Program Budget'!S178+'Program Budget'!S221+'Program Budget'!S280+'Program Budget'!S328+'Program Budget'!S382+'Program Budget'!S448+'Program Budget'!S494 -> 35995.648 | O21: ='Program Budget'!U23 -> 9 | P21: ='Program Budget'!T23+'Program Budget'!T140+'Program Budget'!T178+'Program Budget'!T221+'Program Budget'!T280+'Program Budget'!T328+'Program Budget'!T382+'Program Budget'!T448+'Program Budget'!T494 -> 1 | Q21: ='Program Budget'!V23+'Program Budget'!V140+'Program Budget'!V178+'Program Budget'!V221+'Program Budget'!V280+'Program Budget'!V328+'Program Budget'!V382+'Program Budget'!V448+'Program Budget'!V494 -> 28076.605 | R21: =E21+H21+K21+N21+Q21 -> 139963.45
B22: ='Program Budget'!E24 -> Compliance Director | C22: ='Program Budget'!H24 -> 8 | D22: ='Program Budget'!F24+'Program Budget'!F141+'Program Budget'!F179+'Program Budget'!F222+'Program Budget'!F281+'Program Budget'!F329+'Program Budget'!F383+'Program Budget'!F449+'Program Budget'!F495 -> 0.33333333 | E22: ='Program Budget'!J24+'Program Budget'!J141+'Program Budget'!J179+'Program Budget'!J222+'Program Budget'!J281+'Program Budget'!J329+'Program Budget'!J383+'Program Budget'!J449+'Program Budget'!J495 -> 18222.222 | F22: ='Program Budget'!L24 -> 12 | G22: ='Program Budget'!K24+'Program Budget'!K141+'Program Budget'!K179+'Program Budget'!K222+'Program Budget'!K281+'Program Budget'!K329+'Program Budget'!K383+'Program Budget'!K449+'Program Budget'!K495 -> 0.33333333 | H22: ='Program Budget'!M24+'Program Budget'!M141+'Program Budget'!M179+'Program Budget'!M222+'Program Budget'!M281+'Program Budget'!M329+'Program Budget'!M383+'Program Budget'!M449+'Program Budget'!M495 -> 28426.667 | I22: ='Program Budget'!O24 -> 12 | J22: ='Program Budget'!N24+'Program Budget'!N141+'Program Budget'!N179+'Program Budget'!N222+'Program Budget'!N281+'Program Budget'!N329+'Program Budget'!N383+'Program Budget'!N449+'Program Budget'!N495 -> 0.33333333 | K22: ='Program Budget'!P24+'Program Budget'!P141+'Program Budget'!P179+'Program Budget'!P222+'Program Budget'!P281+'Program Budget'!P329+'Program Budget'!P383+'Program Budget'!P449+'Program Budget'!P495 -> 29563.733 | L22: ='Program Budget'!R24 -> 12 | M22: ='Program Budget'!Q24+'Program Budget'!Q141+'Program Budget'!Q179+'Program Budget'!Q222+'Program Budget'!Q281+'Program Budget'!Q329+'Program Budget'!Q383+'Program Budget'!Q449+'Program Budget'!Q495 -> 0.33333333 | N22: ='Program Budget'!S24+'Program Budget'!S141+'Program Budget'!S179+'Program Budget'!S222+'Program Budget'!S281+'Program Budget'!S329+'Program Budget'!S383+'Program Budget'!S449+'Program Budget'!S495 -> 30746.283 | O22: ='Program Budget'!U24 -> 12 | P22: ='Program Budget'!T24+'Program Budget'!T141+'Program Budget'!T179+'Program Budget'!T222+'Program Budget'!T281+'Program Budget'!T329+'Program Budget'!T383+'Program Budget'!T449+'Program Budget'!T495 -> 0.33333333 | Q22: ='Program Budget'!V24+'Program Budget'!V141+'Program Budget'!V179+'Program Budget'!V222+'Program Budget'!V281+'Program Budget'!V329+'Program Budget'!V383+'Program Budget'!V449+'Program Budget'!V495 -> 31976.134 | R22: =E22+H22+K22+N22+Q22 -> 138935.04
B23: ='Program Budget'!E25 -> Accountant | C23: ='Program Budget'!H25 -> 3 | D23: ='Program Budget'!F25+'Program Budget'!F142+'Program Budget'!F180+'Program Budget'!F223+'Program Budget'!F282+'Program Budget'!F330+'Program Budget'!F384+'Program Budget'!F450+'Program Budget'!F496 -> 1 | E23: ='Program Budget'!J25 -> 5250 | F23: ='Program Budget'!L25 -> 12 | G23: ='Program Budget'!K25+'Program Budget'!K142+'Program Budget'!K180+'Program Budget'!K223+'Program Budget'!K282+'Program Budget'!K330+'Program Budget'!K384+'Program Budget'!K450+'Program Budget'!K496 -> 1 | H23: ='Program Budget'!M25 -> 21840 | I23: ='Program Budget'!O25 -> 12 | J23: ='Program Budget'!N25+'Program Budget'!N142+'Program Budget'!N180+'Program Budget'!N223+'Program Budget'!N282+'Program Budget'!N330+'Program Budget'!N384+'Program Budget'!N450+'Program Budget'!N496 -> 1 | K23: ='Program Budget'!P25 -> 22713.6 | L23: ='Program Budget'!R25 -> 12 | M23: ='Program Budget'!Q25+'Program Budget'!Q142+'Program Budget'!Q180+'Program Budget'!Q223+'Program Budget'!Q282+'Program Budget'!Q330+'Program Budget'!Q384+'Program Budget'!Q450+'Program Budget'!Q496 -> 1 | N23: ='Program Budget'!S25 -> 23622.144 | O23: ='Program Budget'!U25 -> 9 | P23: ='Program Budget'!T25+'Program Budget'!T142+'Program Budget'!T180+'Program Budget'!T223+'Program Budget'!T282+'Program Budget'!T330+'Program Budget'!T384+'Program Budget'!T450+'Program Budget'!T496 -> 1 | Q23: ='Program Budget'!V25 -> 18425.272 | R23: =E23+H23+K23+N23+Q23 -> 91851.016
B24: ='Program Budget'!E26 -> Administrative Assistant | C24: ='Program Budget'!H26 -> 3 | D24: ='Program Budget'!F26+'Program Budget'!F143+'Program Budget'!F181+'Program Budget'!F224+'Program Budget'!F283+'Program Budget'!F331+'Program Budget'!F385+'Program Budget'!F451+'Program Budget'!F497 -> 1 | E24: ='Program Budget'!J26 -> 1875 | F24: ='Program Budget'!L26 -> 12 | G24: ='Program Budget'!K26+'Program Budget'!K143+'Program Budget'!K181+'Program Budget'!K224+'Program Budget'!K283+'Program Budget'!K331+'Program Budget'!K385+'Program Budget'!K451+'Program Budget'!K497 -> 1 | H24: ='Program Budget'!M26 -> 7800 | I24: ='Program Budget'!O26 -> 12 | J24: ='Program Budget'!N26+'Program Budget'!N143+'Program Budget'!N181+'Program Budget'!N224+'Program Budget'!N283+'Program Budget'!N331+'Program Budget'!N385+'Program Budget'!N451+'Program Budget'!N497 -> 1 | K24: ='Program Budget'!P26 -> 8112 | L24: ='Program Budget'!R26 -> 12 | M24: ='Program Budget'!Q26+'Program Budget'!Q143+'Program Budget'!Q181+'Program Budget'!Q224+'Program Budget'!Q283+'Program Budget'!Q331+'Program Budget'!Q385+'Program Budget'!Q451+'Program Budget'!Q497 -> 1 | N24: ='Program Budget'!S26 -> 8436.48 | O24: ='Program Budget'!U26 -> 9 | P24: ='Program Budget'!T26+'Program Budget'!T143+'Program Budget'!T181+'Program Budget'!T224+'Program Budget'!T283+'Program Budget'!T331+'Program Budget'!T385+'Program Budget'!T451+'Program Budget'!T497 -> 1 | Q24: ='Program Budget'!V26 -> 6580.4544 | R24: =E24+H24+K24+N24+Q24 -> 32803.934
B25: ='Program Budget'!E27 -> Driver | C25: ='Program Budget'!H27 -> 3 | D25: ='Program Budget'!F27+'Program Budget'!F144+'Program Budget'!F182+'Program Budget'!F225+'Program Budget'!F284+'Program Budget'!F332+'Program Budget'!F386+'Program Budget'!F452+'Program Budget'!F498 -> 1 | E25: ='Program Budget'!J27 -> 3000 | F25: ='Program Budget'!L27 -> 12 | G25: ='Program Budget'!K27+'Program Budget'!K144+'Program Budget'!K182+'Program Budget'!K225+'Program Budget'!K284+'Program Budget'!K332+'Program Budget'!K386+'Program Budget'!K452+'Program Budget'!K498 -> 1 | H25: ='Program Budget'!M27 -> 12480 | I25: ='Program Budget'!O27 -> 12 | J25: ='Program Budget'!N27+'Program Budget'!N144+'Program Budget'!N182+'Program Budget'!N225+'Program Budget'!N284+'Program Budget'!N332+'Program Budget'!N386+'Program Budget'!N452+'Program Budget'!N498 -> 1 | K25: ='Program Budget'!P27 -> 12979.2 | L25: ='Program Budget'!R27 -> 12 | M25: ='Program Budget'!Q27+'Program Budget'!Q144+'Program Budget'!Q182+'Program Budget'!Q225+'Program Budget'!Q284+'Program Budget'!Q332+'Program Budget'!Q386+'Program Budget'!Q452+'Program Budget'!Q498 -> 1 | N25: ='Program Budget'!S27 -> 13498.368 | O25: ='Program Budget'!U27 -> 9 | P25: ='Program Budget'!T27+'Program Budget'!T144+'Program Budget'!T182+'Program Budget'!T225+'Program Budget'!T284+'Program Budget'!T332+'Program Budget'!T386+'Program Budget'!T452+'Program Budget'!T498 -> 1 | Q25: ='Program Budget'!V27 -> 10528.727 | R25: =E25+H25+K25+N25+Q25 -> 52486.295
B26: Home Office Support
B27: ='Program Budget'!E29 -> Senior Director | C27: ='Program Budget'!H29 -> 12 | D27: ='Program Budget'!F29 -> 0.2 | E27: ='Program Budget'!J29 -> 24000 | F27: ='Program Budget'!L29 -> 12 | G27: 0.2 | H27: ='Program Budget'!M29 -> 24960 | I27: ='Program Budget'!O29 -> 12 | J27: 0.2 | K27: ='Program Budget'!P29 -> 25958.4 | L27: ='Program Budget'!R29 -> 12 | M27: 0.2 | N27: ='Program Budget'!S29 -> 26996.736 | O27: ='Program Budget'!U29 -> 12 | P27: 0.2 | Q27: ='Program Budget'!V29 -> 28076.605 | R27: =E27+H27+K27+N27+Q27 -> 129991.74
B28: ='Program Budget'!E30 -> HQ Senior Program Officer | C28: ='Program Budget'!H30 -> 12 | D28: ='Program Budget'!F30 -> 1 | E28: ='Program Budget'!J30 -> 60000 | F28: ='Program Budget'!L30 -> 12 | G28: ='Program Budget'!K30 -> 1 | H28: ='Program Budget'!M30 -> 62400 | I28: ='Program Budget'!O30 -> 12 | J28: ='Program Budget'!N30 -> 1 | K28: ='Program Budget'!P30 -> 64896 | L28: ='Program Budget'!R30 -> 12 | M28: ='Program Budget'!Q30 -> 1 | N28: ='Program Budget'!S30 -> 67491.84 | O28: ='Program Budget'!U30 -> 12 | P28: ='Program Budget'!T30 -> 1 | Q28: ='Program Budget'!V30 -> 70191.514 | R28: =E28+H28+K28+N28+Q28 -> 324979.35
B29: Total Personnel | E29: =SUM(E11:E28) -> 529930.56 | H29: =SUM(H11:H28) -> 1022146.7 | K29: =SUM(K11:K28) -> 1063032.5 | N29: =SUM(N11:N28) -> 1105553.8 | Q29: =SUM(Q11:Q28) -> 986142.02 | R29: =SUM(R11:R28) -> 4706805.6

Sheet LOE Breakdown by Year
B1: Partners of the Americas – FY 2020 FFPr Colombia
B2: NOFO: USDA-FAS-10.606-0700-20-(514)
B3: Duration: 5 Years
B4: Country: Colombia
B5: Level of Effort (LOE) Breakdown by Activity
D7: Administration | E7: ='USDA Budget Summary'!A28 -> Activity 1: Value Chain Development (Value Chain Analysis, Carbon Assessment, and Living Incomes) | F7: ='USDA Budget Summary'!A29 -> Activity 2: Producer Organization Development & Commercialization | G7: ='USDA Budget Summary'!A30 -> Activity 3: Agriculture Extension and Production Support | H7: ='USDA Budget Summary'!A31 -> Activity 4: Post-Harvest Aggregation & Processing | I7: ='USDA Budget Summary'!A32 -> Activity 5: Ensure Financial Service/ Capital Access for Actors in the Value Chains | J7: ='USDA Budget Summary'!A33 -> Activity 6: Innovation and Job Creation Through Youth Engagement | K7: ='USDA Budget Summary'!A34 -> Activity 7: Establishment of Regional Community of Practice | L7: ='USDA Budget Summary'!A35 -> Activity 8: Financial Services: Endowment Establishment, Fundraising and Management | M7: Total LOE
B8: Year 1 | D8: LOE | E8: LOE | F8: LOE | G8: LOE | H8: LOE | I8: LOE | J8: LOE | K8: LOE | L8: LOE | M8: LOE
B9: Personnel (Administration)
B10: Colombia National Staff
B11: ='Program Budget'!E13 -> Key Personnel: Chief of Party | D11: 0.15 | E11: 0.25 | F11: 0.15 | G11: 0.1 | H11: 0.1 | I11: 0.15 | K11: 0.1 | M11: =SUM(D11:L11) -> 1
B12: ='Program Budget'!E14 -> Key Personnel: Technical Director | D12: 0.1 | E12: 0.25 | F12: 0.25 | G12: 0.2 | H12: 0.2 | M12: =SUM(D12:L12) -> 1
B13: ='Program Budget'!E15 -> F&A Director | D13: 1 | M13: =SUM(D13:L13) -> 1
B14: ='Program Budget'!E16 -> M&E Director | D14: 0.25 | E14: 0.25 | F14: 0.2 | G14: 0.15 | H14: 0.15 | M14: =SUM(D14:L14) -> 1
B15: ='Program Budget'!E17 -> M&E Mid-level Specialist | D15: 0.25 | E15: 0.25 | F15: 0.2 | G15: 0.15 | H15: 0.15 | M15: =SUM(D15:L15) -> 1
B16: ='Program Budget'!E18 -> M&E Specialist | D16: 0.25 | E16: 0.25 | F16: 0.2 | G16: 0.15 | H16: 0.15 | M16: =SUM(D16:L16) -> 1
B17: ='Program Budget'!E19 -> Partnerships and Investment Director | D17: 0.05 | H17: 0.4 | I17: 0.55 | M17: =SUM(D17:L17) -> 1
B18: ='Program Budget'!E20 -> Extension Agents (15) | D18: 0 | G18: 0.8 | H18: 0.2 | M18: =SUM(D18:L18) -> 1
B19: ='Program Budget'!E21 -> Activity Lead Agribusiness Senior Specialist (Cacao) | D19: 0.1 | E19: 0.3 | F19: 0.1 | G19: 0.3 | H19: 0.2 | M19: =SUM(D19:L19) -> 1
B20: ='Program Budget'!E22 -> Activity Lead Agribusiness Senior Specialist (Complementary Crop) | D20: 0.1 | E20: 0.3 | F20: 0.1 | G20: 0.3 | H20: 0.2 | M20: =SUM(D20:L20) -> 1
B21: ='Program Budget'!E23 -> Food Safety Mid-Specialist | D21: 0.1 | E21: 0.1 | F21: 0.25 | G21: 0.1 | H21: 0.45 | M21: =SUM(D21:L21) -> 1
B22: ='Program Budget'!E24 -> Compliance Director | D22: =1/3 -> 0.33333333 | M22: =SUM(D22:L22) -> 0.33333333
B23: ='Program Budget'!E25 -> Accountant | D23: 1 | M23: =SUM(D23:L23) -> 1
B24: ='Program Budget'!E26 -> Administrative Assistant | D24: 0.5 | K24: 0.5 | M24: =SUM(D24:L24) -> 1
B25: ='Program Budget'!E27 -> Driver | D25: 1 | M25: =SUM(D25:L25) -> 1
B26: Home Office Support
B27: ='Program Budget'!E29 -> Senior Director | D27: 0.2 | M27: =SUM(D27:L27) -> 0.2
B28: ='Program Budget'!E30 -> HQ Senior Program Officer | D28: 1 | M28: =SUM(D28:L28) -> 1
B29: Total Personnel
D31: Administration | E31: ='USDA Budget Summary'!A28 -> Activity 1: Value Chain Development (Value Chain Analysis, Carbon Assessment, and Living Incomes) | F31: ='USDA Budget Summary'!A29 -> Activity 2: Producer Organization Development & Commercialization | G31: ='USDA Budget Summary'!A30 -> Activity 3: Agriculture Extension and Production Support | H31: ='USDA Budget Summary'!A31 -> Activity 4: Post-Harvest Aggregation & Processing | I31: ='USDA Budget Summary'!A32 -> Activity 5: Ensure Financial Service/ Capital Access for Actors in the Value Chains | J31: ='USDA Budget Summary'!A33 -> Activity 6: Innovation and Job Creation Through Youth Engagement | K31: ='USDA Budget Summary'!A34 -> Activity 7: Establishment of Regional Community of Practice | L31: ='USDA Budget Summary'!A35 -> Activity 8: Financial Services: Endowment Establishment, Fundraising and Management | M31: Total LOE
B32: Year 2 | D32: LOE | E32: LOE | F32: LOE | G32: LOE | H32: LOE | I32: LOE | J32: LOE | K32: LOE | L32: LOE | M32: LOE
B33: Personnel (Administration)
B34: Colombia National Staff
B35: ='Program Budget'!E13 -> Key Personnel: Chief of Party | D35: 0.1 | E35: 0.05 | F35: 0.15 | G35: 0.1 | H35: 0.1 | I35: 0.2 | J35: 0.1 | K35: 0.1 | L35: 0.1 | M35: =SUM(D35:L35) -> 1
B36: ='Program Budget'!E14 -> Key Personnel: Technical Director | D36: 0.1 | E36: 0.1 | F36: 0.25 | G36: 0.2 | H36: 0.2 | J36: 0.15 | M36: =SUM(D36:L36) -> 1
B37: ='Program Budget'!E15 -> F&A Director | D37: 0.95 | H37: 0.05 | M37: =SUM(D37:L37) -> 1
B38: ='Program Budget'!E16 -> M&E Director | D38: 0.25 | F38: 0.2 | G38: 0.2 | H38: 0.2 | J38: 0.15 | M38: =SUM(D38:L38) -> 1
B39: ='Program Budget'!E17 -> M&E Mid-level Specialist | D39: 0.25 | F39: 0.2 | G39: 0.2 | H39: 0.2 | J39: 0.15 | M39: =SUM(D39:L39) -> 1
B40: ='Program Budget'!E18 -> M&E Specialist | D40: 0.25 | F40: 0.2 | G40: 0.2 | H40: 0.2 | J40: 0.15 | M40: =SUM(D40:L40) -> 1
B41: ='Program Budget'!E19 -> Partnerships and Investment Director | D41: 0.1 | H41: 0.3 | I41: 0.4 | J41: 0.1 | L41: 0.1 | M41: =SUM(D41:L41) -> 1
B42: ='Program Budget'!E20 -> Extension Agents (15) | D42: 0 | G42: 0.8 | H42: 0.2 | M42: =SUM(D42:L42) -> 1
B43: ='Program Budget'!E21 -> Activity Lead Agribusiness Senior Specialist (Cacao) | D43: 0.1 | E43: 0.05 | F43: 0.1 | G43: 0.35 | H43: 0.25 | J43: 0.15 | M43: =SUM(D43:L43) -> 1
B44: ='Program Budget'!E22 -> Activity Lead Agribusiness Senior Specialist (Complementary Crop) | D44: 0.1 | E44: 0.05 | F44: 0.1 | G44: 0.35 | H44: 0.25 | J44: 0.15 | M44: =SUM(D44:L44) -> 1
B45: ='Program Budget'!E23 -> Food Safety Mid-Specialist | D45: 0.1 | F45: 0.25 | G45: 0.1 | H45: 0.45 | J45: 0.1 | M45: =SUM(D45:L45) -> 1
B46: ='Program Budget'!E24 -> Compliance Director | D46: =1/3 -> 0.33333333 | M46: =SUM(D46:L46) -> 0.33333333
B47: ='Program Budget'!E25 -> Accountant | D47: 1 | M47: =SUM(D47:L47) -> 1
B48: ='Program Budget'!E26 -> Administrative Assistant | D48: 0.5 | K48: 0.5 | M48: =SUM(D48:L48) -> 1
B49: ='Program Budget'!E27 -> Driver | D49: 1 | M49: =SUM(D49:L49) -> 1
B50: Home Office Support
B51: ='Program Budget'!E29 -> Senior Director | D51: 0.2 | M51: =SUM(D51:L51) -> 0.2
B52: ='Program Budget'!E30 -> HQ Senior Program Officer | D52: 1 | M52: =SUM(D52:L52) -> 1
B53: Total Personnel
D55: Administration | E55: ='USDA Budget Summary'!A28 -> Activity 1: Value Chain Development (Value Chain Analysis, Carbon Assessment, and Living Incomes) | F55: ='USDA Budget Summary'!A29 -> Activity 2: Producer Organization Development & Commercialization | G55: ='USDA Budget Summary'!A30 -> Activity 3: Agriculture Extension and Production Support | H55: ='USDA Budget Summary'!A31 -> Activity 4: Post-Harvest Aggregation & Processing | I55: ='USDA Budget Summary'!A32 -> Activity 5: Ensure Financial Service/ Capital Access for Actors in the Value Chains | J55: ='USDA Budget Summary'!A33 -> Activity 6: Innovation and Job Creation Through Youth Engagement | K55: ='USDA Budget Summary'!A34 -> Activity 7: Establishment of Regional Community of Practice | L55: ='USDA Budget Summary'!A35 -> Activity 8: Financial Services: Endowment Establishment, Fundraising and Management | M55: Total LOE
B56: Year 3 | D56: LOE | E56: LOE | F56: LOE | G56: LOE | H56: LOE | I56: LOE | J56: LOE | K56: LOE | L56: LOE | M56: LOE
B57: Personnel (Administration)
B58: Colombia National Staff
B59: ='Program Budget'!E13 -> Key Personnel: Chief of Party | D59: 0.1 | F59: 0.15 | G59: 0.1 | H59: 0.1 | I59: 0.2 | J59: 0.1 | K59: 0.15 | L59: 0.1 | M59: =SUM(D59:L59) -> 1
B60: ='Program Budget'!E14 -> Key Personnel: Technical Director | D60: 0.1 | F60: 0.25 | G60: 0.2 | H60: 0.25 | J60: 0.2 | M60: =SUM(D60:L60) -> 1
B61: ='Program Budget'!E15 -> F&A Director | D61: 0.95 | H61: 0.05 | M61: =SUM(D61:L61) -> 1
B62: ='Program Budget'!E16 -> M&E Director | D62: 0.25 | F62: 0.2 | G62: 0.2 | H62: 0.2 | J62: 0.15 | M62: =SUM(D62:L62) -> 1
B63: ='Program Budget'!E17 -> M&E Mid-level Specialist | D63: 0.25 | F63: 0.2 | G63: 0.2 | H63: 0.2 | J63: 0.15 | M63: =SUM(D63:L63) -> 1
B64: ='Program Budget'!E18 -> M&E Specialist | D64: 0.25 | F64: 0.2 | G64: 0.2 | H64: 0.2 | J64: 0.15 | M64: =SUM(D64:L64) -> 1
B65: ='Program Budget'!E19 -> Partnerships and Investment Director | D65: 0.1 | H65: 0.3 | I65: 0.4 | J65: 0.1 | L65: 0.1 | M65: =SUM(D65:L65) -> 1
B66: ='Program Budget'!E20 -> Extension Agents (15) | D66: 0 | G66: 0.8 | H66: 0.2 | M66: =SUM(D66:L66) -> 1
B67: ='Program Budget'!E21 -> Activity Lead Agribusiness Senior Specialist (Cacao) | D67: 0.1 | F67: 0.1 | G67: 0.35 | H67: 0.25 | J67: 0.2 | M67: =SUM(D67:L67) -> 1
B68: ='Program Budget'!E22 -> Activity Lead Agribusiness Senior Specialist (Complementary Crop) | D68: 0.1 | F68: 0.1 | G68: 0.35 | H68: 0.25 | J68: 0.2 | M68: =SUM(D68:L68) -> 1
B69: ='Program Budget'!E23 -> Food Safety Mid-Specialist | D69: 0.1 | F69: 0.2 | G69: 0.1 | H69: 0.4 | J69: 0.2 | M69: =SUM(D69:L69) -> 1
B70: ='Program Budget'!E24 -> Compliance Director | D70: =1/3 -> 0.33333333 | M70: =SUM(D70:L70) -> 0.33333333
B71: ='Program Budget'!E25 -> Accountant | D71: 1 | M71: =SUM(D71:L71) -> 1
B72: ='Program Budget'!E26 -> Administrative Assistant | D72: 0.5 | K72: 0.5 | M72: =SUM(D72:L72) -> 1
B73: ='Program Budget'!E27 -> Driver | D73: 1 | M73: =SUM(D73:L73) -> 1
B74: Home Office Support
B75: ='Program Budget'!E29 -> Senior Director | D75: 0.2 | M75: =SUM(D75:L75) -> 0.2
B76: ='Program Budget'!E30 -> HQ Senior Program Officer | D76: 1 | M76: =SUM(D76:L76) -> 1
B77: Total Personnel
D79: Administration | E79: ='USDA Budget Summary'!A28 -> Activity 1: Value Chain Development (Value Chain Analysis, Carbon Assessment, and Living Incomes) | F79: ='USDA Budget Summary'!A29 -> Activity 2: Producer Organization Development & Commercialization | G79: ='USDA Budget Summary'!A30 -> Activity 3: Agriculture Extension and Production Support | H79: ='USDA Budget Summary'!A31 -> Activity 4: Post-Harvest Aggregation & Processing | I79: ='USDA Budget Summary'!A32 -> Activity 5: Ensure Financial Service/ Capital Access for Actors in the Value Chains | J79: ='USDA Budget Summary'!A33 -> Activity 6: Innovation and Job Creation Through Youth Engagement | K79: ='USDA Budget Summary'!A34 -> Activity 7: Establishment of Regional Community of Practice | L79: ='USDA Budget Summary'!A35 -> Activity 8: Financial Services: Endowment Establishment, Fundraising and Management | M79: Total LOE
B80: Year 4 | D80: LOE | E80: LOE | F80: LOE | G80: LOE | H80: LOE | I80: LOE | J80: LOE | K80: LOE | L80: LOE | M80: LOE
B81: Personnel (Administration)
B82: Colombia National Staff
B83: ='Program Budget'!E13 -> Key Personnel: Chief of Party | D83: 0.1 | F83: 0.15 | G83: 0.1 | H83: 0.1 | I83: 0.15 | J83: 0.05 | K83: 0.1 | L83: 0.25 | M83: =SUM(D83:L83) -> 1
B84: ='Program Budget'!E14 -> Key Personnel: Technical Director | D84: 0.1 | F84: 0.25 | G84: 0.2 | H84: 0.25 | J84: 0.2 | L84: 0 | M84: =SUM(D84:L84) -> 1
B85: ='Program Budget'!E15 -> F&A Director | D85: 0.5 | H85: 0.05 | J85: 0.25 | L85: 0.2 | M85: =SUM(D85:L85) -> 1
B86: ='Program Budget'!E16 -> M&E Director | D86: 0.25 | F86: 0.2 | G86: 0.15 | H86: 0.2 | J86: 0.15 | L86: 0.05 | M86: =SUM(D86:L86) -> 1
B87: ='Program Budget'!E17 -> M&E Mid-level Specialist | D87: 0.25 | F87: 0.2 | G87: 0.15 | H87: 0.2 | J87: 0.2 | L87: 0 | M87: =SUM(D87:L87) -> 1
B88: ='Program Budget'!E18 -> M&E Specialist | D88: 0.25 | F88: 0.2 | G88: 0.15 | H88: 0.2 | J88: 0.2 | L88: 0 | M88: =SUM(D88:L88) -> 1
B89: ='Program Budget'!E19 -> Partnerships and Investment Director | D89: 0.1 | H89: 0.1 | I89: 0.25 | J89: 0.1 | L89: 0.45 | M89: =SUM(D89:L89) -> 1
B90: ='Program Budget'!E20 -> Extension Agents (15) | D90: 0 | G90: 0.8 | H90: 0.2 | M90: =SUM(D90:L90) -> 1
B91: ='Program Budget'!E21 -> Activity Lead Agribusiness Senior Specialist (Cacao) | D91: 0.1 | F91: 0.1 | G91: 0.35 | H91: 0.25 | J91: 0.2 | M91: =SUM(D91:L91) -> 1
B92: ='Program Budget'!E22 -> Activity Lead Agribusiness Senior Specialist (Complementary Crop) | D92: 0.1 | F92: 0.1 | G92: 0.35 | H92: 0.25 | J92: 0.2 | M92: =SUM(D92:L92) -> 1
B93: ='Program Budget'!E23 -> Food Safety Mid-Specialist | D93: 0.1 | F93: 0.25 | G93: 0.1 | H93: 0.35 | J93: 0.2 | M93: =SUM(D93:L93) -> 1
B94: ='Program Budget'!E24 -> Compliance Director | D94: =1/3 -> 0.33333333 | M94: =SUM(D94:L94) -> 0.33333333
B95: ='Program Budget'!E25 -> Accountant | D95: 1 | M95: =SUM(D95:L95) -> 1
B96: ='Program Budget'!E26 -> Administrative Assistant | D96: 0.5 | K96: 0.5 | M96: =SUM(D96:L96) -> 1
B97: ='Program Budget'!E27 -> Driver | D97: 1 | M97: =SUM(D97:L97) -> 1
B98: Home Office Support
B99: ='Program Budget'!E29 -> Senior Director | D99: 0.2 | M99: =SUM(D99:L99) -> 0.2
B100: ='Program Budget'!E30 -> HQ Senior Program Officer | D100: 1 | M100: =SUM(D100:L100) -> 1
B101: Total Personnel
D103: Administration | E103: ='USDA Budget Summary'!A28 -> Activity 1: Value Chain Development (Value Chain Analysis, Carbon Assessment, and Living Incomes) | F103: ='USDA Budget Summary'!A29 -> Activity 2: Producer Organization Development & Commercialization | G103: ='USDA Budget Summary'!A30 -> Activity 3: Agriculture Extension and Production Support | H103: ='USDA Budget Summary'!A31 -> Activity 4: Post-Harvest Aggregation & Processing | I103: ='USDA Budget Summary'!A32 -> Activity 5: Ensure Financial Service/ Capital Access for Actors in the Value Chains | J103: ='USDA Budget Summary'!A33 -> Activity 6: Innovation and Job Creation Through Youth Engagement | K103: ='USDA Budget Summary'!A34 -> Activity 7: Establishment of Regional Community of Practice | L103: ='USDA Budget Summary'!A35 -> Activity 8: Financial Services: Endowment Establishment, Fundraising and Management | M103: Total LOE
B104: Year 5 | D104: LOE | E104: LOE | F104: LOE | G104: LOE | H104: LOE | I104: LOE | J104: LOE | K104: LOE | L104: LOE | M104: LOE
B105: Personnel (Administration)
...

Sheet Activity 2 Sub Budget
A1: Name of Project: FY 2020 FFPr Colombia - Partners of the Americas
A2: Name of Subawardee: To be determined
A3: Subaward Budget for Activity 2
A4: Budget Assumptions:
A5: Merit Based Increases for HQ & Field Staff | B5: 1.03
A7: BUDGET ITEM | B7: Level of Effort (LOE) | C7: CATEGORY | D7: UNIT | E7: # of Units | F7: RATE/ UNIT | G7: YEAR 1 | H7: # of Units | I7: YEAR 2 | J7: # of Units | K7: YEAR 3 | L7: # of Units | M7: YEAR 4 | N7: # of Units | O7: YEAR 5 | P7: TOTAL SUBAWARD | Q7: TOTAL COST SHARE | R7: PROJECT GRAND TOTAL
A8: ='USDA Budget Summary'!A29 -> Activity 2: Producer Organization Development & Commercialization
A9: Personnel Costs for Activity 2
A10: Field Personnel
A11: Field Coordinator for Continuous Advice of Associations in Uraba y Bajo Cauca | B11: 1 | C11: Salaries | D11: Month | E11: 6 | F11: 815 | G11: =E11*F11 -> 4890 | H11: 12 | I11: =(H11*F11*B11*$B$5) -> 10073.4 | J11: 12 | K11: =(J11*F11*B11*$B$5*$B$5) -> 10375.602 | L11: 12 | M11: =(L11*F11*B11*$B$5*$B$5*$B$5) -> 10686.87 | N11: 6 | O11: =(N11*F11*$B$5*$B$5*$B$5*$B$5) -> 5503.7381 | P11: =SUM(G11+I11+K11+M11+O11) -> 41529.61 | Q11: 0 | R11: =SUM(P11:Q11) -> 41529.61
A12: Field Coordinator for Continuous Advice of Associations in Caldas | B12: 1 | C12: Salaries | D12: Month | E12: 6 | F12: 815 | G12: =E12*F12 -> 4890 | H12: 12 | I12: =(H12*F12*B12*$B$5) -> 10073.4 | J12: 12 | K12: =(J12*F12*B12*$B$5*$B$5) -> 10375.602 | L12: 12 | M12: =(L12*F12*B12*$B$5*$B$5*$B$5) -> 10686.87 | N12: 6 | O12: =(N12*F12*$B$5*$B$5*$B$5*$B$5) -> 5503.7381 | P12: =SUM(G12+I12+K12+M12+O12) -> 41529.61 | Q12: 0 | R12: =SUM(P12:Q12) -> 41529.61
A13: Field Coordinator for Continuous Advice of Associations in Tolima | B13: 1 | C13: Salaries | D13: Month | E13: 6 | F13: 815 | G13: =E13*F13 -> 4890 | H13: 12 | I13: =(H13*F13*B13*$B$5) -> 10073.4 | J13: 12 | K13: =(J13*F13*B13*$B$5*$B$5) -> 10375.602 | L13: 12 | M13: =(L13*F13*B13*$B$5*$B$5*$B$5) -> 10686.87 | N13: 6 | O13: =(N13*F13*$B$5*$B$5*$B$5*$B$5) -> 5503.7381 | P13: =SUM(G13+I13+K13+M13+O13) -> 41529.61 | Q13: 0 | R13: =SUM(P13:Q13) -> 41529.61
A14: Field Coordinator for Continuous Advice of Associations in Sierra Nevada (Magdalena) | B14: 1 | C14: Salaries | D14: Month | E14: 6 | F14: 815 | G14: =E14*F14 -> 4890 | H14: 12 | I14: =(H14*F14*B14*$B$5) -> 10073.4 | J14: 12 | K14: =(J14*F14*B14*$B$5*$B$5) -> 10375.602 | L14: 12 | M14: =(L14*F14*B14*$B$5*$B$5*$B$5) -> 10686.87 | N14: 6 | O14: =(N14*F14*$B$5*$B$5*$B$5*$B$5) -> 5503.7381 | P14: =SUM(G14+I14+K14+M14+O14) -> 41529.61 | Q14: 0 | R14: =SUM(P14:Q14) -> 41529.61
A15: HQ Personnel
A16: Project Manager | B16: 1 | C16: Salaries | D16: Month | E16: 6 | F16: 1000 | G16: =E16*F16 -> 6000 | H16: 12 | I16: =(H16*F16*B16*$B$5) -> 12360 | J16: 12 | K16: =(J16*F16*B16*$B$5*$B$5) -> 12730.8 | L16: 12 | M16: =(L16*F16*B16*$B$5*$B$5*$B$5) -> 13112.724 | N16: 6 | O16: =(N16*F16*$B$5*$B$5*$B$5*$B$5) -> 6753.0529 | P16: =SUM(G16+I16+K16+M16+O16) -> 50956.577 | Q16: 0 | R16: =SUM(P16:Q16) -> 50956.577
A17: Social Organization Expert | B17: 1 | C17: Salaries | D17: Month | E17: 6 | F17: 1500 | G17: =E17*F17 -> 9000 | H17: 12 | I17: =(H17*F17*B17*$B$5) -> 18540 | J17: 12 | K17: =(J17*F17*B17*$B$5*$B$5) -> 19096.2 | L17: 12 | M17: =(L17*F17*B17*$B$5*$B$5*$B$5) -> 19669.086 | N17: 6 | O17: =(N17*F17*$B$5*$B$5*$B$5*$B$5) -> 10129.579 | P17: =SUM(G17+I17+K17+M17+O17) -> 76434.865 | Q17: 0 | R17: =SUM(P17:Q17) -> 76434.865
A18: Entrepreneur Expert | B18: 1 | C18: Salaries | D18: Month | E18: 6 | F18: 1500 | G18: =E18*F18 -> 9000 | H18: 12 | I18: =(H18*F18*B18*$B$5) -> 18540 | J18: 12 | K18: =(J18*F18*B18*$B$5*$B$5) -> 19096.2 | L18: 12 | M18: =(L18*F18*B18*$B$5*$B$5*$B$5) -> 19669.086 | N18: 6 | O18: =(N18*F18*$B$5*$B$5*$B$5*$B$5) -> 10129.579 | P18: =SUM(G18+I18+K18+M18+O18) -> 76434.865 | Q18: 0 | R18: =SUM(P18:Q18) -> 76434.865
A19: Assistant/Logistics Coordinator | B19: 1 | C19: Salaries | D19: Month | E19: 6 | F19: 700 | G19: =E19*F19 -> 4200 | H19: 12 | I19: =(H19*F19*B19*$B$5) -> 8652 | J19: 12 | K19: =(J19*F19*B19*$B$5*$B$5) -> 8911.56 | L19: 12 | M19: =(L19*F19*B19*$B$5*$B$5*$B$5) -> 9178.9068 | N19: 6 | O19: =(N19*F19*$B$5*$B$5*$B$5*$B$5) -> 4727.137 | P19: =SUM(G19+I19+K19+M19+O19) -> 35669.604 | Q19: 0 | R19: =SUM(P19:Q19) -> 35669.604
A20: Total Personnel Costs for Activity 2 | G20: =SUM(G11:G19) -> 47760 | I20: =SUM(I11:I19) -> 98385.6 | K20: =SUM(K11:K19) -> 101337.17 | M20: =SUM(M11:M19) -> 104377.28 | O20: =SUM(O11:O19) -> 53754.301 | P20: =SUM(P11:P19) -> 405614.35 | Q20: =SUM(Q11:Q19) -> 0 | R20: =SUM(R11:R19) -> 405614.35
A22: Fringe Benefit Costs for Activity 2
A23: Fringe Benefits for Field Personnel | B23: 0.52 | C23: Fringe | D23: % | F23: 0.52 | G23: =(G11+G14+G12+G13)*$F$23 -> 10171.2 | I23: =(I11+I14+I12+I13)*$F$23 -> 20952.672 | K23: =(K11+K14+K12+K13)*$F$23 -> 21581.252 | M23: =(M11+M14+M12+M13)*$F$23 -> 22228.69 | O23: =(O11+O14+O12+O13)*$F$23 -> 11447.775 | P23: =SUM(G23+I23+K23+M23+O23) -> 86381.589 | Q23: - | R23: =SUM(P23:Q23) -> 86381.589
A24: Fringe Benefits CCN for HQ Personnel | B24: 0.52 | C24: Fringe | D24: % | F24: 0.52 | G24: =(G16+G17+G18+G19)*$F$24 -> 14664 | I24: =(I16+I17+I18+I19)*$F$24 -> 30207.84 | K24: =(K16+K17+K18+K19)*$F$24 -> 31114.075 | M24: =(M16+M17+M18+M19)*$F$24 -> 32047.497 | O24: =(O16+O17+O18+O19)*$F$24 -> 16504.461 | P24: =SUM(G24+I24+K24+M24+O24) -> 124537.87 | Q24: - | R24: =SUM(P24:Q24) -> 124537.87
A25: Fringe Benefit Costs for Activity 2 | G25: =SUM(G23:G24) -> 24835.2 | I25: =SUM(I23:I24) -> 51160.512 | K25: =SUM(K23:K24) -> 52695.327 | M25: =SUM(M23:M24) -> 54276.187 | O25: =SUM(O23:O24) -> 27952.236 | P25: =SUM(P23:P24) -> 210919.46 | Q25: =SUM(Q23:Q24) -> 0 | R25: =SUM(R23:R24) -> 210919.46
A27: Travel Costs for Activity 2
A28: Ground Transportation for Visits to Associations | C28: Travel | D28: Month | E28: 6 | F28: 300 | G28: =E28*F28 -> 1800 | H28: 12 | I28: =H28*F28 -> 3600 | J28: 12 | K28: =J28*F28 -> 3600 | L28: 12 | M28: =L28*F28 -> 3600 | N28: 6 | O28: =N28*F28 -> 1800 | P28: =G28+I28+K28+M28+O28 -> 14400 | Q28: - | R28: =SUM(P28:Q28) -> 14400
A29: Travel for Formation in the Field
A30: Airfare for Formation in the Field | C30: Travel | D30: Trip | E30: =17*2 -> 34 | F30: 250 | G30: =E30*F30 -> 8500 | H30: =17*2 -> 34 | I30: =H30*F30 -> 8500 | J30: =17*2 -> 34 | K30: =J30*F30 -> 8500 | L30: =17*2 -> 34 | M30: =L30*F30 -> 8500 | N30: =17*2 -> 34 | O30: =N30*F30 -> 8500 | P30: =G30+I30+K30+M30+O30 -> 42500 | Q30: - | R30: =SUM(P30:Q30) -> 42500
A31: Lodging for Formation in the Field | C31: Travel | D31: Day | E31: =E30*3*2 -> 204 | F31: 75 | G31: =E31*F31 -> 15300 | H31: =H30*3*2 -> 204 | I31: =H31*F31 -> 15300 | J31: =J30*3*2 -> 204 | K31: =J31*F31 -> 15300 | L31: =L30*3*2 -> 204 | M31: =L31*F31 -> 15300 | N31: =N30*3*2 -> 204 | O31: =N31*F31 -> 15300 | P31: =G31+I31+K31+M31+O31 -> 76500 | Q31: - | R31: =SUM(P31:Q31) -> 76500
A32: M&IE for Formation in the Field | C32: Travel | D32: Day | E32: =E30*3*2 -> 204 | F32: 98 | G32: =E32*F32 -> 19992 | H32: =H30*3*2 -> 204 | I32: =H32*F32 -> 19992 | J32: =J30*3*2 -> 204 | K32: =J32*F32 -> 19992 | L32: =L30*3*2 -> 204 | M32: =L32*F32 -> 19992 | N32: =N30*3*2 -> 204 | O32: =N32*F32 -> 19992 | P32: =G32+I32+K32+M32+O32 -> 99960 | Q32: - | R32: =SUM(P32:Q32) -> 99960
A33: Ground Transportation for Formation in the Field | C33: Travel | D33: Month | E33: 6 | F33: 300 | G33: =E33*F33 -> 1800 | H33: 8 | I33: =H33*F33 -> 2400 | J33: 8 | K33: =J33*F33 -> 2400 | L33: 8 | M33: =L33*F33 -> 2400 | N33: 6 | O33: =N33*F33 -> 1800 | P33: =G33+I33+K33+M33+O33 -> 10800 | Q33: - | R33: =SUM(P33:Q33) -> 10800
A34: Total Travel Costs for Activity 2 | G34: =SUM(G28:G33) -> 47392 | I34: =SUM(I28:I33) -> 49792 | K34: =SUM(K28:K33) -> 49792 | M34: =SUM(M28:M33) -> 49792 | O34: =SUM(O28:O33) -> 47392 | P34: =SUM(P28:P33) -> 244160 | Q34: =SUM(Q28:Q33) -> 0 | R34: =SUM(R28:R33) -> 244160
A36: Supplies for Activity 2
A37: Laptops & Software | C37: Supplies | D37: Unit | E37: 6 | F37: 1100 | G37: =E37*F37 -> 6600 | H37: 0 | I37: =H37*F37 -> 0 | J37: 0 | K37: =J37*F37 -> 0 | L37: 0 | M37: =L37*F37 -> 0 | N37: 0 | O37: =N37*F37 -> 0 | P37: =G37+I37+K37+M37+O37 -> 6600 | Q37: 0 | R37: =SUM(P37:Q37) -> 6600
A38: Total Supplies for Activity 2 | G38: =SUM(G37:G37) -> 6600 | I38: =SUM(I37:I37) -> 0 | K38: =SUM(K37:K37) -> 0 | M38: =SUM(M37:M37) -> 0 | O38: =SUM(O37:O37) -> 0 | P38: =SUM(P37:P37) -> 6600 | Q38: =SUM(Q37:Q37) -> 0 | R38: =SUM(R37:R37) -> 6600
A40: Other for Activity 2
A41: Training for 17 Associations for 850 Participants (2 X year each Association) | C41: Training | D41: Unit | E41: 17 | F41: 500 | G41: =E41*F41 -> 8500 | H41: 17 | I41: =H41*F41 -> 8500 | J41: 17 | K41: =J41*F41 -> 8500 | L41: 17 | M41: =L41*F41 -> 8500 | N41: 17 | O41: =N41*F41 -> 8500 | P41: =G41+I41+K41+M41+O41 -> 42500 | Q41: 0 | R41: =SUM(P41:Q41) -> 42500
A42: Total Other for Activity 2 | G42: =SUM(G41:G41) -> 8500 | I42: =SUM(I41:I41) -> 8500 | K42: =SUM(K41:K41) -> 8500 | M42: =SUM(M41:M41) -> 8500 | O42: =SUM(O41:O41) -> 8500 | P42: =SUM(P41:P41) -> 42500 | Q42: =SUM(Q41:Q41) -> 0 | R42: =SUM(R41:R41) -> 42500
A44: Subtotal Direct Costs Activity 2 | G44: =G38+G42+G34+G25+G20 -> 135087.2 | I44: =I38+I42+I34+I25+I20 -> 207838.11 | K44: =K38+K42+K34+K25+K20 -> 212324.5 | M44: =M38+M42+M34+M25+M20 -> 216945.47 | O44: =O38+O42+O34+O25+O20 -> 137598.54 | P44: =P38+P42+P34+P25+P20 -> 909793.81 | Q44: =Q38+Q42+Q34+Q25+Q20 -> 0 | R44: =R38+R42+R34+R25+R20 -> 909793.81
A46: Total Indirect Costs for Activity 2 | C46: Indirect Charges | F46: 0.1 | G46: =$F$46*G44 -> 13508.72 | I46: =$F$46*I44 -> 20783.811 | K46: =$F$46*K44 -> 21232.45 | M46: =$F$46*M44 -> 21694.547 | O46: =$F$46*O44 -> 13759.854 | P46: =O46+M46+K46+I46+G46 -> 90979.381 | Q46: 0 | R46: =SUM(P46:Q46) -> 90979.381
A48: Total Activity 2 | G48: =G46+G44 -> 148595.92 | I48: =I46+I44 -> 228621.92 | K48: =K46+K44 -> 233556.94 | M48: =M46+M44 -> 238640.02 | O48: =O46+O44 -> 151358.39 | P48: =P46+P44 -> 1000773.2 | Q48: =Q46+Q44 -> 0 | R48: =R46+R44 -> 1000773.2
A50: Grant Total of Subaward | G50: =G48 -> 148595.92 | I50: =I48 -> 228621.92 | K50: =K48 -> 233556.94 | M50: =M48 -> 238640.02 | O50: =O48 -> 151358.39 | P50: =P48 -> 1000773.2 | Q50: =Q48 -> 0 | R50: =R48 -> 1000773.2

Sheet CIAT Sub Budget
A1: Name of Project: FY 2020 FFPr Colombia - Partners of the Americas
A2: Name of Subawardee: Alliance Bioversity International CIAT
A3: Subaward Budget for Activity 1 & 3
A4: Budget Assumptions:
A5: Merit Based Increases for HQ Staff (International) | B5: 1.01
A6: Merit Based Increases for Field Staff (National) | B6: 1.04
A8: BUDGET ITEM | B8: Level of Effort (LOE) | C8: CATEGORY | D8: UNIT | E8: # of Units | F8: RATE/ UNIT | G8: YEAR 1 | H8: # of Units | I8: YEAR 2 | J8: # of Units | K8: YEAR 3 | L8: # of Units | M8: YEAR 4 | N8: # of Units | O8: YEAR 5 | P8: TOTAL SUBAWARD | Q8: TOTAL COST SHARE | R8: PROJECT GRAND TOTAL
A9: ='USDA Budget Summary'!A28 -> Activity 1: Value Chain Development (Value Chain Analysis, Carbon Assessment, and Living Incomes)
A10: Personnel Costs for Activity 1
A11: Field Personnel (National Staff)
A12: Communications Assistant | B12: 1 | C12: Salaries | D12: Month | E12: 2 | F12: 2083 | G12: =E12*F12*B12 -> 4166 | H12: 1 | I12: =H12*F12*$B$6*B12 -> 2166.32 | J12: 0 | K12: =F12*J12*B12*$B$6*$B$6 -> 0 | L12: 0 | M12: =F12*L12*B12*$B$6*$B$6*$B$6 -> 0 | N12: 0 | O12: =N12*F12*B12*$B$6*$B$6*$B$6*$B$6 -> 0 | P12: =SUM(G12+I12+K12+M12+O12) -> 6332.32 | Q12: 0 | R12: =SUM(P12:Q12) -> 6332.32
A13: Value Chain and Business Models Expert #1 | B13: 0.5 | C13: Salaries | D13: Month | E13: 6 | F13: 3608 | G13: =E13*F13*B13 -> 10824 | H13: 3 | I13: =H13*F13*$B$6*B13 -> 5628.48 | J13: 0 | K13: =F13*J13*B13*$B$6*$B$6 -> 0 | L13: 0 | M13: =F13*L13*B13*$B$6*$B$6*$B$6 -> 0 | N13: 0 | O13: =N13*F13*B13*$B$6*$B$6*$B$6*$B$6 -> 0 | P13: =SUM(G13+I13+K13+M13+O13) -> 16452.48 | Q13: 0 | R13: =SUM(P13:Q13) -> 16452.48
A14: Value Chain and Business Models Expert #2 | B14: 1 | C14: Salaries | D14: Month | E14: 6 | F14: 2816 | G14: =E14*F14*B14 -> 16896 | H14: 3 | I14: =H14*F14*$B$6*B14 -> 8785.92 | J14: 0 | K14: =F14*J14*B14*$B$6*$B$6 -> 0 | L14: 0 | M14: =F14*L14*B14*$B$6*$B$6*$B$6 -> 0 | N14: 0 | O14: =N14*F14*B14*$B$6*$B$6*$B$6*$B$6 -> 0 | P14: =SUM(G14+I14+K14+M14+O14) -> 25681.92 | Q14: 0 | R14: =SUM(P14:Q14) -> 25681.92
A15: Research Assistant - Value Chain and Socioeconomics #1 | B15: 1 | C15: Salaries | D15: Month | E15: 6 | F15: 1470 | G15: =E15*F15*B15 -> 8820 | H15: 3 | I15: =H15*F15*$B$6*B15 -> 4586.4 | J15: 0 | K15: =F15*J15*B15*$B$6*$B$6 -> 0 | L15: 0 | M15: =F15*L15*B15*$B$6*$B$6*$B$6 -> 0 | N15: 0 | O15: =N15*F15*B15*$B$6*$B$6*$B$6*$B$6 -> 0 | P15: =SUM(G15+I15+K15+M15+O15) -> 13406.4 | Q15: 0 | R15: =SUM(P15:Q15) -> 13406.4
A16: Research Assistant - Value Chain and Socioeconomics #2 | B16: 1 | C16: Salaries | D16: Month | E16: 6 | F16: 1641 | G16: =E16*F16*B16 -> 9846 | H16: 3 | I16: =H16*F16*$B$6*B16 -> 5119.92 | J16: 0 | K16: =F16*J16*B16*$B$6*$B$6 -> 0 | L16: 0 | M16: =F16*L16*B16*$B$6*$B$6*$B$6 -> 0 | N16: 0 | O16: =N16*F16*B16*$B$6*$B$6*$B$6*$B$6 -> 0 | P16: =SUM(G16+I16+K16+M16+O16) -> 14965.92 | Q16: 0 | R16: =SUM(P16:Q16) -> 14965.92
A17: Research Assistant - Value Chain and Socioeconomics #3 | B17: 1 | C17: Salaries | D17: Month | E17: 6 | F17: 1470 | G17: =E17*F17*B17 -> 8820 | H17: 3 | I17: =H17*F17*$B$6*B17 -> 4586.4 | J17: 0 | K17: =F17*J17*B17*$B$6*$B$6 -> 0 | L17: 0 | M17: =F17*L17*B17*$B$6*$B$6*$B$6 -> 0 | N17: 0 | O17: =N17*F17*B17*$B$6*$B$6*$B$6*$B$6 -> 0 | P17: =SUM(G17+I17+K17+M17+O17) -> 13406.4 | Q17: 0 | R17: =SUM(P17:Q17) -> 13406.4
A18: Research Assistant - Value Chain and Agronomic Analysis | B18: 1 | C18: Salaries | D18: Month | E18: 6 | F18: 1641 | G18: =E18*F18*B18 -> 9846 | H18: 3 | I18: =H18*F18*$B$6*B18 -> 5119.92 | J18: 0 | K18: =F18*J18*B18*$B$6*$B$6 -> 0 | L18: 0 | M18: =F18*L18*B18*$B$6*$B$6*$B$6 -> 0 | N18: 0 | O18: =N18*F18*B18*$B$6*$B$6*$B$6*$B$6 -> 0 | P18: =SUM(G18+I18+K18+M18+O18) -> 14965.92 | Q18: 0 | R18: =SUM(P18:Q18) -> 14965.92
A19: Research Assistant - Suitability Analysis | B19: 1 | C19: Salaries | D19: Month | E19: 6 | F19: 1641 | G19: =E19*F19*B19 -> 9846 | H19: 0 | I19: =H19*F19*$B$6*B19 -> 0 | J19: 0 | K19: =F19*J19*B19*$B$6*$B$6 -> 0 | L19: 0 | M19: =F19*L19*B19*$B$6*$B$6*$B$6 -> 0 | N19: 0 | O19: =N19*F19*B19*$B$6*$B$6*$B$6*$B$6 -> 0 | P19: =SUM(G19+I19+K19+M19+O19) -> 9846 | Q19: 0 | R19: =SUM(P19:Q19) -> 9846
A20: Agronomist | B20: 0.4 | C20: Salaries | D20: Month | E20: 4 | F20: 4175 | G20: =E20*F20*B20 -> 6680 | H20: 2 | I20: =H20*F20*$B$6*B20 -> 3473.6 | J20: 0 | K20: =F20*J20*B20*$B$6*$B$6 -> 0 | L20: 0 | M20: =F20*L20*B20*$B$6*$B$6*$B$6 -> 0 | N20: 0 | O20: =N20*F20*B20*$B$6*$B$6*$B$6*$B$6 -> 0 | P20: =SUM(G20+I20+K20+M20+O20) -> 10153.6 | Q20: 0 | R20: =SUM(P20:Q20) -> 10153.6
A21: Research Assistant (Agronomist) | B21: 0.25 | C21: Salaries | D21: Month | E21: 4 | F21: 1629 | G21: =E21*F21*B21 -> 1629 | H21: 2 | I21: =H21*F21*$B$6*B21 -> 847.08 | J21: 0 | K21: =F21*J21*B21*$B$6*$B$6 -> 0 | L21: 0 | M21: =F21*L21*B21*$B$6*$B$6*$B$6 -> 0 | N21: 0 | O21: =N21*F21*B21*$B$6*$B$6*$B$6*$B$6 -> 0 | P21: =SUM(G21+I21+K21+M21+O21) -> 2476.08 | Q21: 0 | R21: =SUM(P21:Q21) -> 2476.08
A22: Research Assistant (Carbon Modelling) | B22: 0.25 | C22: Salaries | D22: Month | E22: 4 | F22: 2263 | G22: =E22*F22*B22 -> 2263 | H22: 2 | I22: =H22*F22*$B$6*B22 -> 1176.76 | J22: 0 | K22: =F22*J22*B22*$B$6*$B$6 -> 0 | L22: 0 | M22: =F22*L22*B22*$B$6*$B$6*$B$6 -> 0 | N22: 0 | O22: =N22*F22*B22*$B$6*$B$6*$B$6*$B$6 -> 0 | P22: =SUM(G22+I22+K22+M22+O22) -> 3439.76 | Q22: 0 | R22: =SUM(P22:Q22) -> 3439.76
A23: Research Assistant (Living Income & Econ. Assessment of Carbon Balance) #1 | B23: 1 | C23: Salaries | D23: Month | E23: 6 | F23: 2263 | G23: =E23*F23*B23 -> 13578 | H23: 3 | I23: =H23*F23*$B$6*B23 -> 7060.56 | J23: 0 | K23: =F23*J23*B23*$B$6*$B$6 -> 0 | L23: 0 | M23: =F23*L23*B23*$B$6*$B$6*$B$6 -> 0 | N23: 0 | O23: =N23*F23*B23*$B$6*$B$6*$B$6*$B$6 -> 0 | P23: =SUM(G23+I23+K23+M23+O23) -> 20638.56 | Q23: 0 | R23: =SUM(P23:Q23) -> 20638.56
... A29: Regional Finance Manager for the Americas | B29: 0.3 | C29: Salaries | D29: Month | E29: 6 | F29: 6882 | G29: =E29*F29*B29 -> 12387.6 | H29: 3 | I29: =H29*F29*$B$6*B29 -> 6441.552 | J29: 0 | K29: =F29*J29*B29*$B$6*$B$6 -> 0 | L29: 0 | M29: =F29*L29*B29*$B$6*$B$6*$B$6 -> 0 | N29: 0 | O29: =N29*F29*B29*$B$6*$B$6*$B$6*$B$6 -> 0 | P29: =SUM(G29+I29+K29+M29+O29) -> 18829.152 | Q29: 0 | R29: =SUM(P29:Q29) -> 18829.152
A30: HQ Personnel (International Staff)
A31: Theme Leader - Food Environment, Value Chains & Markets | B31: 0.3 | C31: Salaries | D31: Month | E31: 6 | F31: 14774 | G31: =E31*F31*B31 -> 26593.2 | H31: 3 | I31: =H31*F31*$B$5*B31 -> 13429.566 | J31: 0 | K31: =F31*J31*B31*$B$5*$B$5 -> 0 | L31: 0 | M31: =F31*L31*B31*$B$5*$B$5*$B$5 -> 0 | N31: 0 | O31: =N31*F31*B31*$B$5*$B$5*$B$5*$B$5 -> 0 | P31: =SUM(G31+I31+K31+M31+O31) -> 40022.766 | Q31: 0 | R31: =SUM(P31:Q31) -> 40022.766
A32: Soil Scientist and Coordinator | B32: 0.1 | C32: Salaries | D32: Month | E32: 4 | F32: 9390 | G32: =E32*F32*B32 -> 3756 | H32: 2 | I32: =H32*F32*$B$5*B32 -> 1896.78 | J32: 0 | K32: =F32*J32*B32*$B$5*$B$5 -> 0 | L32: 0 | M32: =F32*L32*B32*$B$5*$B$5*$B$5 -> 0 | N32: 0 | O32: =N32*F32*B32*$B$5*$B$5*$B$5*$B$5 -> 0 | P32: =SUM(G32+I32+K32+M32+O32) -> 5652.78 | Q32: 0 | R32: =SUM(P32:Q32) -> 5652.78
A33: Senior Agronomist | B33: 0.2 | C33: Salaries | D33: Month | E33: 4 | F33: 20822 | G33: =E33*F33*B33 -> 16657.6 | H33: 2 | I33: =H33*F33*$B$5*B33 -> 8412.088 | J33: 0 | K33: =F33*J33*B33*$B$5*$B$5 -> 0 | L33: 0 | M33: =F33*L33*B33*$B$5*$B$5*$B$5 -> 0 | N33: 0 | O33: =N33*F33*B33*$B$5*$B$5*$B$5*$B$5 -> 0 | P33: =SUM(G33+I33+K33+M33+O33) -> 25069.688 | Q33: 0 | R33: =SUM(P33:Q33) -> 25069.688
A34: Agricultural Economist | B34: 0.5 | C34: Salaries | D34: Month | E34: 6 | F34: 13325 | G34: =E34*F34*B34 -> 39975 | H34: 3 | I34: =H34*F34*$B$5*B34 -> 20187.375 | J34: 0 | K34: =F34*J34*B34*$B$5*$B$5 -> 0 | L34: 0 | M34: =F34*L34*B34*$B$5*$B$5*$B$5 -> 0 | N34: 0 | O34: =N34*F34*B34*$B$5*$B$5*$B$5*$B$5 -> 0 | P34: =SUM(G34+I34+K34+M34+O34) -> 60162.375 | Q34: 0 | R34: =SUM(P34:Q34) -> 60162.375
A35: Total Personnel Costs for Activity 1 | G35: =SUM(G12:G34) -> 246876.11 | I35: =SUM(I12:I34) -> 121950.93 | K35: =SUM(K12:K34) -> 0 | M35: =SUM(M12:M34) -> 0 | O35: =SUM(O12:O34) -> 0 | P35: =SUM(P12:P34) -> 368827.04 | Q35: =SUM(Q12:Q34) -> 0 | R35: =SUM(R12:R34) -> 368827.04
A37: Travel Costs for Activity 1
A38: Ground Transportation | C38: Travel | D38: Month | E38: 6 | F38: 1250 | G38: =E38*F38 -> 7500 | H38: 3 | I38: =H38*F38 -> 3750 | J38: 0 | K38: =J38*$F38 -> 0 | L38: 0 | M38: =L38*F38 -> 0 | N38: 0 | O38: =N38*F38 -> 0 | P38: =G38+I38+K38+M38+O38 -> 11250 | Q38: - | R38: =SUM(P38:Q38) -> 11250
A39: T1: Travel for National Trips for Value Chain Assessment
A40: Local Transportation for National Trips for Value Chain Assessment | C40: Travel | D40: Trip | E40: =7*2 -> 14 | F40: 700 | G40: =E40*F40 -> 9800 | H40: =7*1 -> 7 | I40: =H40*F40 -> 4900 | J40: 0 | K40: =J40*$F40 -> 0 | L40: 0 | M40: =L40*F40 -> 0 | N40: 0 | O40: =N40*F40 -> 0 | P40: =G40+I40+K40+M40+O40 -> 14700 | Q40: - | R40: =SUM(P40:Q40) -> 14700
A41: Lodging & M&IE for National Trips for Value Chain Assessment | C41: Travel | D41: Day | E41: =7*2*5 -> 70 | F41: 90 | G41: =E41*F41 -> 6300 | H41: =7*1*5 -> 35 | I41: =H41*F41 -> 3150 | J41: 0 | K41: =J41*$F41 -> 0 | L41: 0 | M41: =L41*F41 -> 0 | N41: 0 | O41: =N41*F41 -> 0 | P41: =G41+I41+K41+M41+O41 -> 9450 | Q41: - | R41: =SUM(P41:Q41) -> 9450
A42: T2: Travel for Quantification of Carbon Sequestration at Landscape Level
A43: Local Transportation for Quantification of Carbon Sequestration at Landscape Level | C43: Travel | D43: Trip | E43: 5 | F43: 700 | G43: =E43*F43 -> 3500 | H43: 2 | I43: =H43*F43 -> 1400 | J43: 0 | K43: =J43*$F43 -> 0 | L43: 0 | M43: =L43*F43 -> 0 | N43: 0 | O43: =N43*F43 -> 0 | P43: =G43+I43+K43+M43+O43 -> 4900 | Q43: - | R43: =SUM(P43:Q43) -> 4900
A44: Lodging & M&IE for Quantification of Carbon Sequestration at Landscape Level | C44: Travel | D44: Day | E44: =5*3 -> 15 | F44: 190 | G44: =E44*F44 -> 2850 | H44: =5*2 -> 10 | I44: =H44*F44 -> 1900 | J44: 0 | K44: =J44*$F44 -> 0 | L44: 0 | M44: =L44*F44 -> 0 | N44: 0 | O44: =N44*F44 -> 0 | P44: =G44+I44+K44+M44+O44 -> 4750 | Q44: - | R44: =SUM(P44:Q44) -> 4750
A45: T3: Travel for Living Income and Economic Assessment of Carbon Balance
A46: Local Transportation for National Trips for Living Income and Economic Assessment of Carbon Balance | C46: Travel | D46: Trip | E46: 12 | F46: 400 | G46: =E46*F46 -> 4800 | H46: 6 | I46: =H46*F46 -> 2400 | J46: 0 | K46: =J46*$F46 -> 0 | L46: 0 | M46: =L46*F46 -> 0 | N46: 0 | O46: =N46*F46 -> 0 | P46: =G46+I46+K46+M46+O46 -> 7200 | Q46: - | R46: =SUM(P46:Q46) -> 7200
A47: Lodging & M&IE for Living Income and Economic Assessment of Carbon Balance | C47: Travel | D47: Day | E47: =12*5 -> 60 | F47: 190 | G47: =E47*F47 -> 11400 | H47: =6*5 -> 30 | I47: =H47*F47 -> 5700 | J47: 0 | K47: =J47*$F47 -> 0 | L47: 0 | M47: =L47*F47 -> 0 | N47: 0 | O47: =N47*F47 -> 0 | P47: =G47+I47+K47+M47+O47 -> 17100 | Q47: - | R47: =SUM(P47:Q47) -> 17100
A48: Total Travel Costs for Activity 1 | G48: =SUM(G38:G47) -> 46150 | I48: =SUM(I38:I47) -> 23200 | K48: =SUM(K38:K47) -> 0 | M48: =SUM(M38:M47) -> 0 | O48: =SUM(O38:O47) -> 0 | P48: =SUM(P38:P47) -> 69350 | Q48: =SUM(Q38:Q47) -> 0 | R48: =SUM(R38:R47) -> 69350
A50: Professional Services/Contractual for Activity 1
A51: Consultant - Carbon Market Expert | C51: Contractual | D51: Month | E51: 3 | F51: 2000 | G51: =E51*F51 -> 6000 | H51: 0 | I51: =H51*F51 -> 0 | J51: 0 | K51: =J51*$F51 -> 0 | L51: 0 | M51: =L51*F51 -> 0 | N51: 0 | O51: =N51*F51 -> 0 | P51: =G51+I51+K51+M51+O51 -> 6000 | Q51: - | R51: =SUM(P51:Q51) -> 6000
A52: Consultant - Graphic Design for Special Study | C52: Contractual | D52: Month | E52: 0 | F52: 2000 | G52: =E52*F52 -> 0 | H52: 6 | I52: =H52*F52 -> 12000 | J52: 0 | K52: =J52*$F52 -> 0 | L52: 0 | M52: =L52*F52 -> 0 | N52: 0 | O52: =N52*F52 -> 0 | P52: =G52+I52+K52+M52+O52 -> 12000 | Q52: - | R52: =SUM(P52:Q52) -> 12000
A53: Contracts for Data Collection & Enumerators | C53: Contractual | D53: Unit | E53: 1 | F53: 280000 | G53: =E53*F53 -> 280000 | H53: 0 | I53: =H53*F53 -> 0 | J53: 0 | K53: =J53*$F53 -> 0 | L53: 0 | M53: =L53*F53 -> 0 | N53: 0 | O53: =N53*F53 -> 0 | P53: =G53+I53+K53+M53+O53 -> 280000 | Q53: - | R53: =SUM(P53:Q53) -> 280000
A54: Total Professional Services/Contractual for Activity 1 | G54: =SUM(G51:G53) -> 286000 | I54: =SUM(I51:I53) -> 12000 | K54: =SUM(K51:K53) -> 0 | M54: =SUM(M51:M53) -> 0 | O54: =SUM(O51:O53) -> 0 | P54: =SUM(P51:P53) -> 298000 | Q54: =SUM(Q51:Q53) -> 0 | R54: =SUM(R51:R53) -> 298000
A56: Office Expenses for Activity 1
A57: Office & Program Supplies | C57: Office Ex. | D57: Unit | E57: 3 | F57: 300 | G57: =E57*F57 -> 900 | H57: 2 | I57: =H57*F57 -> 600 | J57: 0 | K57: =J57*F57 -> 0 | L57: 0 | M57: =L57*F57 -> 0 | N57: 0 | O57: =N57*F57 -> 0 | P57: =G57+I57+K57+M57+O57 -> 1500 | Q57: - | R57: =SUM(P57:Q57) -> 1500
A58: Research Support Service | C58: Office Ex. | D58: Unit | E58: 1 | F58: 60000 | G58: =E58*F58 -> 60000 | H58: 1 | I58: 20000 | J58: 0 | K58: =J58*F58 -> 0 | L58: 0 | M58: =L58*F58 -> 0 | N58: 0 | O58: =N58*F58 -> 0 | P58: =G58+I58+K58+M58+O58 -> 80000 | Q58: - | R58: =SUM(P58:Q58) -> 80000
A59: Information Technology | C59: Office Ex. | D59: Unit | E59: 1 | F59: 30000 | G59: 30000 | H59: 1 | I59: 10000 | J59: 0 | K59: =J59*F59 -> 0 | L59: 0 | M59: =L59*F59 -> 0 | N59: 0 | O59: =N59*F59 -> 0 | P59: =G59+I59+K59+M59+O59 -> 40000 | Q59: - | R59: =SUM(P59:Q59) -> 40000
A60: Facilities and Public Area | C60: Office Ex. | D60: Unit | E60: 1 | F60: 25000 | G60: =E60*F60 -> 25000 | H60: 1 | I60: 8000 | J60: 0 | K60: =J60*F60 -> 0 | L60: 0 | M60: =L60*F60 -> 0 | N60: 0 | O60: =N60*F60 -> 0 | P60: =G60+I60+K60+M60+O60 -> 33000 | Q60: - | R60: =SUM(P60:Q60) -> 33000
A61: Total Office Expenses Costs for Activity 1 | G61: =SUM(G57:G60) -> 115900 | I61: =SUM(I57:I60) -> 38600 | K61: =SUM(K57:K60) -> 0 | M61: =SUM(M57:M60) -> 0 | O61: =SUM(O57:O60) -> 0 | P61: =SUM(P57:P60) -> 154500 | Q61: =SUM(Q57:Q60) -> 0 | R61: =SUM(R57:R60) -> 154500
A63: Other for Activity 1
A64: Validation Stakeholder Workshops | C64: Other | D64: Training | E64: 4 | F64: 3000 | G64: =E64*F64 -> 12000 | H64: 2 | I64: =H64*F64 -> 6000 | J64: 0 | K64: =J64*$F64 -> 0 | L64: 0 | M64: =L64*F64 -> 0 | N64: 0 | O64: =N64*F64 -> 0 | P64: =G64+I64+K64+M64+O64 -> 18000 | Q64: - | R64: =SUM(P64:Q64) -> 18000
A65: Analysis with All Actors on Specific Options | C65: Other | D65: Event | E65: 15 | F65: 600 | G65: =E65*F65 -> 9000 | H65: 0 | I65: =H65*F65 -> 0 | J65: 0 | K65: =J65*$F65 -> 0 | L65: 0 | M65: =L65*F65 -> 0 | N65: 0 | O65: =N65*F65 -> 0 | P65: =G65+I65+K65+M65+O65 -> 9000 | Q65: - | R65: =SUM(P65:Q65) -> 9000
A66: Focus Groups | C66: Other | D66: Training | E66: 16 | F66: 300 | G66: =E66*F66 -> 4800 | H66: 8 | I66: =H66*F66 -> 2400 | J66: 0 | K66: =J66*$F66 -> 0 | L66: 0 | M66: =L66*F66 -> 0 | N66: 0 | O66: =N66*F66 -> 0 | P66: =G66+I66+K66+M66+O66 -> 7200 | Q66: - | R66: =SUM(P66:Q66) -> 7200
A67: Total Other Costs for Activity 1 | G67: =SUM(G64:G66) -> 25800 | I67: =SUM(I64:I66) -> 8400 | K67: =SUM(K64:K66) -> 0 | M67: =SUM(M64:M66) -> 0 | O67: =SUM(O64:O66) -> 0 | P67: =SUM(P64:P66) -> 34200 | Q67: =SUM(Q64:Q66) -> 0 | R67: =SUM(R64:R66) -> 34200
A69: Subtotal Direct Costs Activity 1 | G69: =G67+G61+G48+G35+G54 -> 720726.11 | I69: =I67+I61+I48+I35+I54 -> 204150.93 | K69: =K67+K61+K48+K35+K54 -> 0 | M69: =M67+M61+M48+M35+M54 -> 0 | O69: =O67+O61+O48+O35+O54 -> 0 | P69: =P67+P61+P48+P35+P54 -> 924877.04 | Q69: =Q67+Q61+Q48+Q35+Q54 -> 0 | R69: =R67+R61+R48+R35+R54 -> 924877.04
A71: Total Indirect Costs De Minimis for Activity 1 | C71: Indirect Charges | F71: 0.1 | G71: =G69*$F$71 -> 72072.611 | I71: =I69*$F$71 -> 20415.093 | K71: =K69*$F$71 -> 0 | M71: =M69*$F$71 -> 0 | O71: =O69*$F$71 -> 0 | P71: =O71+M71+K71+I71+G71 -> 92487.704 | Q71: 0 | R71: =SUM(P71:Q71) -> 92487.704
A73: Total Activity 1 | G73: =G71+G69 -> 792798.72 | I73: =I71+I69 -> 224566.02 | K73: =K71+K69 -> 0 | M73: =M71+M69 -> 0 | O73: =O71+O69 -> 0 | P73: =P71+P69 -> 1017364.7 | Q73: =Q71+Q69 -> 0 | R73: =R71+R69 -> 1017364.7
A75: ='USDA Budget Summary'!A30 -> Activity 3: Agriculture Extension and Production Support
A76: CIAT - Digital Extension tools/GIS continuation from Cacao For Peace
A77: Personnel Costs for Activity 3
A78: Field Personnel (National Staff)
A79: Agronomist | B79: 1 | C79: Salaries | D79: Month | E79: 0 | F79: 4175 | G79: =E79*F79*B79 -> 0 | H79: 1 | I79: =H79*F79*$B$6*B79 -> 4342 | J79: 0 | K79: =F79*J79*B79*$B$6*$B$6 -> 0 | L79: 0 | M79: =F79*L79*B79*$B$6*$B$6*$B$6 -> 0 | N79: 0 | O79: =N79*F79*B79*$B$6*$B$6*$B$6*$B$6 -> 0 | P79: =SUM(G79+I79+K79+M79+O79) -> 4342 | Q79: 0 | R79: =SUM(P79:Q79) -> 4342
A80: Research Assistant (GIS) | B80: 0.4 | C80: Salaries | D80: Month | E80: 0 | F80: 1877 | G80: =E80*F80*B80 -> 0 | H80: 12 | I80: =H80*F80*$B$6*B80 -> 9369.984 | J80: 12 | K80: =F80*J80*B80*$B$6*$B$6 -> 9744.7834 | L80: 9 | M80: =F80*L80*B80*$B$6*$B$6*$B$6 -> 7600.931 | N80: 0 | O80: =N80*F80*B80*$B$6*$B$6*$B$6*$B$6 -> 0 | P80: =SUM(G80+I80+K80+M80+O80) -> 26715.698 | Q80: 0 | R80: =SUM(P80:Q80) -> 26715.698
A81: Associate Researcher (Economist) | B81: 0.8 | C81: Salaries | D81: Month | E81: 0 | F81: 1475 | G81: =E81*F81*B81 -> 0 | H81: 12 | I81: =H81*F81*$B$6*B81 -> 14726.4 | J81: 12 | K81: =F81*J81*B81*$B$6*$B$6 -> 15315.456 | L81: 0 | M81: =F81*L81*B81*$B$6*$B$6*$B$6 -> 0 | N81: 0 | O81: =N81*F81*B81*$B$6*$B$6*$B$6*$B$6 -> 0 | P81: =SUM(G81+I81+K81+M81+O81) -> 30041.856 | Q81: 0 | R81: =SUM(P81:Q81) -> 30041.856
A82: Administrative Assistant | B82: 0.115 | C82: Salaries | D82: Month | E82: 0 | F82: 2131 | G82: =E82*F82*B82 -> 0 | H82: 12 | I82: =H82*F82*$B$6*B82 -> 3058.4112 | J82: 12 | K82: =F82*J82*B82*$B$6*$B$6 -> 3180.7476 | L82: 9 | M82: =F82*L82*B82*$B$6*$B$6*$B$6 -> 2480.9832 | N82: 0 | O82: =N82*F82*B82*$B$6*$B$6*$B$6*$B$6 -> 0 | P82: =SUM(G82+I82+K82+M82+O82) -> 8720.142 | Q82: 0 | R82: =SUM(P82:Q82) -> 8720.142
A83: Project Financial Analysis and Support | B83: 0.08 | C83: Salaries | D83: Month | E83: 0 | F83: 4282 | G83: =E83*F83*B83 -> 0 | H83: 12 | I83: =H83*F83*$B$6*B83 -> 4275.1488 | J83: 12 | K83: =F83*J83*B83*$B$6*$B$6 -> 4446.1548 | L83: 5 | M83: =F83*L83*B83*$B$6*$B$6*$B$6 -> 1926.6671 | N83: 0 | O83: =N83*F83*B83*$B$6*$B$6*$B$6*$B$6 -> 0 | P83: =SUM(G83+I83+K83+M83+O83) -> 10647.971 | Q83: 0 | R83: =SUM(P83:Q83) -> 10647.971
A84: International Staff | I84: =H84*F84*$B$6*B84 -> 0
A85: Agricultural Economist | B85: 0.1 | C85: Salaries | D85: Month | E85: 0 | F85: 13325 | G85: =E85*F85*B85 -> 0 | H85: 6 | I85: =H85*F85*$B$6*B85 -> 8314.8 | J85: 6 | K85: =F85*J85*B85*$B$5*$B$5 -> 8155.6995 | L85: 0 | M85: =F85*L85*B85*$B$5*$B$5*$B$5 -> 0 | N85: 0 | O85: =N85*F85*B85*$B$5*$B$5*$B$5*$B$5 -> 0 | P85: =SUM(G85+I85+K85+M85+O85) -> 16470.5 | Q85: 0 | R85: =SUM(P85:Q85) -> 16470.5
A86: Soil Scientist and Coordinator | B86: 0.2 | C86: Salaries | D86: Month | E86: 0 | F86: 9390 | G86: =E86*F86*B86 -> 0 | H86: 12 | I86: =H86*F86*$B$6*B86 -> 23437.44 | J86: 12 | K86: =F86*J86*B86*$B$5*$B$5 -> 22988.974 | L86: 9 | M86: =F86*L86*B86*$B$5*$B$5*$B$5 -> 17414.148 | N86: 0 | O86: =N86*F86*B86*$B$5*$B$5*$B$5*$B$5 -> 0 | P86: =SUM(G86+I86+K86+M86+O86) -> 63840.561 | Q86: 0 | R86: =SUM(P86:Q86) -> 63840.561
A87: Total Personnel Costs for Activity 3 | G87: =SUM(G79:G86) -> 0 | I87: =SUM(I79:I86) -> 67524.184 | K87: =SUM(K79:K86) -> 63831.815 | M87: =SUM(M79:M86) -> 29422.729 | O87: =SUM(O79:O86) -> 0 | P87: =SUM(P79:P86) -> 160778.73 | Q87: =SUM(Q79:Q86) -> 0 | R87: =SUM(R79:R86) -> 160778.73
A89: Travel Costs for Activity 3
A90: T1: Travel for Digital Extension/ GIS to Optimize Cacao Production
A91: Local Transportation for Digital Extension/ GIS to Optimize Cacao Production | C91: Travel | D91: Trip | E91: 0 | F91: 800 | G91: =E91*F91 -> 0 | H91: 3 | I91: =H91*F91 -> 2400 | J91: 8 | K91: =J91*$F91 -> 6400 | L91: 6 | M91: =L91*F91 -> 4800 | N91: 0 | O91: =N91*F91 -> 0 | P91: =G91+I91+K91+M91+O91 -> 13600 | Q91: - | R91: =SUM(P91:Q91) -> 13600
A92: Lodging & M&IE for Digital Extension/ GIS to Optimize Cacao Production | C92: Travel | D92: Day | E92: 0 | F92: 190 | G92: =E92*F92 -> 0 | H92: =3*5 -> 15 | I92: =H92*F92 -> 2850 | J92: =5*8 -> 40 | K92: =J92*$F92 -> 7600 | L92: =5*6 -> 30 | M92: =L92*F92 -> 5700 | N92: 0 | O92: =N92*F92 -> 0 | P92: =G92+I92+K92+M92+O92 -> 16150 | Q92: - | R92: =SUM(P92:Q92) -> 16150
A93: Total Travel Costs for Activity 3 | G93: =SUM(G91:G92) -> 0 | I93: =SUM(I91:I92) -> 5250 | K93: =SUM(K91:K92) -> 14000 | M93: =SUM(M91:M92) -> 10500 | O93: =SUM(O91:O92) -> 0 | P93: =SUM(P91:P92) -> 29750 | Q93: =SUM(Q91:Q92) -> 0 | R93: =SUM(R91:R92) -> 29750
A95: Professional Services/Contractual for Activity 3
A96: Consultant - Field Extensionist | C96: Contractual | D96: Month | E96: 0 | F96: 2700 | G96: =E96*F96 -> 0 | H96: 4 | I96: =H96*F96 -> 10800 | J96: 3 | K96: =J96*$F96 -> 8100 | L96: 0 | M96: =L96*F96 -> 0 | N96: 0 | O96: =N96*F96 -> 0 | P96: =G96+I96+K96+M96+O96 -> 18900 | Q96: - | R96: =SUM(P96:Q96) -> 18900
A97: Total Professional Services/Contractual for Activity 3 | G97: =SUM(G96) -> 0 | I97: =SUM(I96) -> 10800 | K97: =SUM(K96) -> 8100 | M97: =SUM(M96) -> 0 | O97: =SUM(O96) -> 0 | P97: =SUM(P96) -> 18900 | Q97: =SUM(Q96) -> 0 | R97: =SUM(R96) -> 18900
A99: Office Expenses for Activity 3
A100: Office & Program Supplies | C100: Office Ex. | D100: Unit | E100: 0 | F100: 535 | G100: =E100*F100 -> 0 | H100: 1 | I100: =H100*F100 -> 535 | J100: 1 | K100: =J100*F100 -> 535 | L100: 1 | M100: =L100*F100 -> 535 | N100: 0 | O100: =N100*F100 -> 0 | P100: =G100+I100+K100+M100+O100 -> 1605 | Q100: - | R100: =SUM(P100:Q100) -> 1605
A101: Research Support Service | C101: Office Ex. | D101: Unit | E101: 0 | F101: 3674 | G101: =E101*F101 -> 0 | H101: 1 | I101: 3674 | J101: 1 | K101: 7348 | L101: 1 | M101: 2265 | N101: 0 | O101: =N101*F101 -> 0 | P101: =G101+I101+K101+M101+O101 -> 13287 | Q101: - | R101: =SUM(P101:Q101) -> 13287
A102: Information Technology | C102: Office Ex. | D102: Unit | E102: 0 | F102: 1429 | G102: =E102*F102 -> 0 | H102: 1 | I102: 1429 | J102: 1 | K102: 2635 | L102: 1 | M102: 953 | N102: 0 | O102: =N102*F102 -> 0 | P102: =G102+I102+K102+M102+O102 -> 5017 | Q102: - | R102: =SUM(P102:Q102) -> 5017
A103: Facilities and Public Area | C103: Office Ex. | D103: Unit | E103: 0 | F103: 1236 | G103: =E103*F103 -> 0 | H103: 1 | I103: 1236 | J103: 1 | K103: 2275 | L103: 1 | M103: 823 | N103: 0 | O103: =N103*F103 -> 0 | P103: =G103+I103+K103+M103+O103 -> 4334 | Q103: - | R103: =SUM(P103:Q103) -> 4334
A104: Total Office Expenses Costs for Activity 3 | G104: =SUM(G100:G103) -> 0 | I104: =SUM(I100:I103) -> 6874 | K104: =SUM(K100:K103) -> 12793 | M104: =SUM(M100:M103) -> 4576 | O104: =SUM(O100:O103) -> 0 | P104: =SUM(P100:P103) -> 24243 | Q104: =SUM(Q100:Q103) -> 0 | R104: =SUM(R100:R103) -> 24243
A106: Supplies for Activity 3
A107: Soils Samples | C107: Supplies | D107: Unit | E107: 0 | F107: 65 | G107: =E107*F107 -> 0 | H107: 60 | I107: =H107*F107 -> 3900 | J107: 0 | K107: =J107*F107 -> 0 | L107: 0 | M107: =L107*F107 -> 0 | N107: 0 | O107: =N107*F107 -> 0 | P107: =G107+I107+K107+M107+O107 -> 3900 | Q107: - | R107: =SUM(P107:Q107) -> 3900
A108: Total Supplies for Activity 3 | G108: =SUM(G107:G107) -> 0 | I108: =SUM(I107:I107) -> 3900 | K108: =SUM(K107:K107) -> 0 | M108: =SUM(M107:M107) -> 0 | O108: =SUM(O107:O107) -> 0 | P108: =SUM(P107:P107) -> 3900 | Q108: =SUM(Q107:Q107) -> 0 | R108: =SUM(R107:R107) -> 3900
A110: Other for Activity 3
A111: Training for Farmers/Technicians - Extension and GIS | C111: Other | D111: Training | E111: 0 | F111: 5000 | G111: =E111*F111 -> 0 | H111: 1 | I111: =H111*F111 -> 5000 | J111: 1 | K111: =J111*$F111 -> 5000 | L111: 0 | M111: =L111*F111 -> 0 | N111: 0 | O111: =N111*F111 -> 0 | P111: =G111+I111+K111+M111+O111 -> 10000 | Q111: - | R111: =SUM(P111:Q111) -> 10000
A112: Total Other Costs for Activity 3 | G112: =SUM(G111:G111) -> 0 | I112: =SUM(I111:I111) -> 5000 | K112: =SUM(K111:K111) -> 5000 | M112: =SUM(M111:M111) -> 0 | O112: =SUM(O111:O111) -> 0 | P112: =SUM(P111:P111) -> 10000 | Q112: =SUM(Q111:Q111) -> 0 | R112: =SUM(R111:R111) -> 10000
A114: Subtotal Direct Costs Activity 3 | G114: =G112+G108+G104+G93+G87+G97 -> 0 | I114: =I112+I108+I104+I93+I87+I97 -> 99348.184 | K114: =K112+K108+K104+K93+K87+K97 -> 103724.81 | M114: =M112+M108+M104+M93+M87+M97 -> 44498.729 | O114: =O112+O108+O104+O93+O87+O97 -> 0 | P114: =P112+P108+P104+P93+P87+P97 -> 247571.73 | Q114: =Q112+Q108+Q104+Q93+Q87+Q97 -> 0 | R114: =R112+R108+R104+R93+R87+R97 -> 247571.73
A116: Total Indirect Costs De Minimis for Activity 3 | C116: Indirect Charges | F116: 0.1 | G116: =G114*$F$116 -> 0 | I116: =I114*$F$116 -> 9934.8184 | K116: =K114*$F$116 -> 10372.481 | M116: =M114*$F$116 -> 4449.8729 | O116: =O114*$F$116 -> 0 | P116: =O116+M116+K116+I116+G116 -> 24757.173 | Q116: 0 | R116: =SUM(P116:Q116) -> 24757.173
A118: Total Activity 3 | G118: =G116+G114 -> 0 | I118: =I116+I114 -> 109283 | K118: =K116+K114 -> 114097.3 | M118: =M116+M114 -> 48948.602 | O118: =O116+O114 -> 0 | P118: =P116+P114 -> 272328.9 | Q118: =Q116+Q114 -> 0 | R118: =R116+R114 -> 272328.9
A120: =A75 -> Activity 3: Agriculture Extension and Production Support
A121: CIAT - Food Safety – (Evaluation, management and messaging for local and international markets, governments and NGOs)
A122: Personnel Costs for Activity 3
A123: Field Personnel (National Staff)
...

Sheet Agrosavia Sub Budget
A1: Name of Project: FY 2020 FFPr Colombia - Partners of the Americas
A2: Name of Subawardee: Agrosavia
A3: Subaward Budget for Activity 4
A4: Budget Assumptions:
A5: Merit Based Increases for HQ & Field Staff | B5: 1.03
A7: BUDGET ITEM | B7: Level of Effort (LOE) | C7: CATEGORY | D7: UNIT | E7: # of Units | F7: RATE/ UNIT | G7: YEAR 1 | H7: # of Units | I7: YEAR 2 | J7: # of Units | K7: YEAR 3 | L7: # of Units | M7: YEAR 4 | N7: # of Units | O7: YEAR 5 | P7: TOTAL SUBAWARD | Q7: TOTAL COST SHARE | R7: PROJECT GRAND TOTAL
A8: ='USDA Budget Summary'!A31 -> Activity 4: Post-Harvest Aggregation & Processing
A9: Personnel Costs for Activity 4
A10: Field Personnel
A11: Research Assistant | B11: 0.5 | C11: Salaries | D11: Month | E11: 2 | F11: 970 | G11: =F11*E11*B11 -> 970 | H11: 12 | I11: =(H11*F11*B11*$B$5) -> 5994.6 | J11: 12 | K11: =(J11*F11*B11*$B$5*$B$5) -> 6174.438 | L11: 2 | M11: =(L11*F11*B11*$B$5*$B$5*$B$5) -> 1059.9452 | N11: 0 | O11: =(N11*F11*$B$5*$B$5*$B$5*$B$5) -> 0 | P11: =SUM(G11+I11+K11+M11+O11) -> 14198.983 | Q11: 0 | R11: =SUM(P11:Q11) -> 14198.983
A12: Post-Harvest Researcher | B12: 0.5 | C12: Salaries | D12: Month | E12: 2 | F12: 2525 | G12: =F12*E12*B12 -> 2525 | H12: 12 | I12: =(H12*F12*B12*$B$5) -> 15604.5 | J12: 12 | K12: =(J12*F12*B12*$B$5*$B$5) -> 16072.635 | L12: 2 | M12: =(L12*F12*B12*$B$5*$B$5*$B$5) -> 2759.1357 | N12: 0 | O12: =(N12*F12*$B$5*$B$5*$B$5*$B$5) -> 0 | P12: =SUM(G12+I12+K12+M12+O12) -> 36961.271 | R12: =SUM(P12:Q12) -> 36961.271
A13: Agricultural Engineer | B13: 0.5 | C13: Salaries | D13: Month | E13: 2 | F13: 3500 | G13: =F13*E13*B13 -> 3500 | H13: 12 | I13: =(H13*F13*B13*$B$5) -> 21630 | J13: 12 | K13: =(J13*F13*B13*$B$5*$B$5) -> 22278.9 | L13: 2 | M13: =(L13*F13*B13*$B$5*$B$5*$B$5) -> 3824.5445 | N13: 0 | O13: =(N13*F13*$B$5*$B$5*$B$5*$B$5) -> 0 | P13: =SUM(G13+I13+K13+M13+O13) -> 51233.444 | R13: =SUM(P13:Q13) -> 51233.444
A14: Agricultural Economist | B14: 0.5 | C14: Salaries | D14: Month | E14: 2 | F14: 3500 | G14: =F14*E14*B14 -> 3500 | H14: 12 | I14: =(H14*F14*B14*$B$5) -> 21630 | J14: 12 | K14: =(J14*F14*B14*$B$5*$B$5) -> 22278.9 | L14: 2 | M14: =(L14*F14*B14*$B$5*$B$5*$B$5) -> 3824.5445 | N14: 0 | O14: =(N14*F14*$B$5*$B$5*$B$5*$B$5) -> 0 | P14: =SUM(G14+I14+K14+M14+O14) -> 51233.444 | R14: =SUM(P14:Q14) -> 51233.444
A15: Total Personnel Costs for Activity 4 | G15: =SUM(G11:G14) -> 10495 | I15: =SUM(I11:I14) -> 64859.1 | K15: =SUM(K11:K14) -> 66804.873 | M15: =SUM(M11:M14) -> 11468.17 | O15: =SUM(O11:O14) -> 0 | P15: =SUM(P11:P14) -> 153627.14 | Q15: =SUM(Q11:Q14) -> 0 | R15: =SUM(R11:R14) -> 153627.14
A17: Travel Costs for Activity 4
A18: Local Transportation | C18: Travel | D18: Month | E18: 6 | F18: 200 | G18: =E18*F18 -> 1200 | H18: 12 | I18: =H18*F18 -> 2400 | J18: 12 | K18: =J18*F18 -> 2400 | L18: 2 | M18: =L18*F18 -> 400 | N18: 0 | O18: =N18*F18 -> 0 | P18: =G18+I18+K18+M18+O18 -> 6400 | Q18: - | R18: =SUM(P18:Q18) -> 6400
A19: Travel for Post-Harvest Activities
A20: Airfare for Post-Harvest Activities | C20: Travel | D20: Trip | E20: 7 | F20: 150 | G20: =E20*F20 -> 1050 | H20: =2*4 -> 8 | I20: =H20*F20 -> 1200 | J20: =2*4 -> 8 | K20: =J20*F20 -> 1200 | L20: 1 | M20: =L20*F20 -> 150 | N20: 0 | O20: =N20*F20 -> 0 | P20: =G20+I20+K20+M20+O20 -> 3600 | Q20: - | R20: =SUM(P20:Q20) -> 3600
A21: Lodging for Post-Harvest Activities | C21: Travel | D21: Day | E21: =5*E20 -> 35 | F21: 78.125 | G21: =E21*F21 -> 2734.375 | H21: =5*H20 -> 40 | I21: =H21*F21 -> 3125 | J21: =5*J20 -> 40 | K21: =J21*F21 -> 3125 | L21: =L20*5 -> 5 | M21: =L21*F21 -> 390.625 | N21: 0 | O21: =N21*F21 -> 0 | P21: =G21+I21+K21+M21+O21 -> 9375 | Q21: - | R21: =SUM(P21:Q21) -> 9375
A22: Ground Transportation for Post-Harvest Activities | C22: Travel | D22: Day | E22: =5*E20 -> 35 | F22: 62.5 | G22: =E22*F22 -> 2187.5 | H22: =5*H20 -> 40 | I22: =H22*F22 -> 2500 | J22: =5*J20 -> 40 | K22: =J22*F22 -> 2500 | L22: =L20*5 -> 5 | M22: =L22*F22 -> 312.5 | N22: 0 | O22: =N22*F22 -> 0 | P22: =G22+I22+K22+M22+O22 -> 7500 | Q22: - | R22: =SUM(P22:Q22) -> 7500
A23: M&IE for Post-Harvest Activities | C23: Travel | D23: Day | E23: =5*E20 -> 35 | F23: 35 | G23: =E23*F23 -> 1225 | H23: =5*H20 -> 40 | I23: =H23*F23 -> 1400 | J23: =5*J20 -> 40 | K23: =J23*F23 -> 1400 | L23: =5*L20 -> 5 | M23: =L23*F23 -> 175 | N23: 0 | O23: =N23*F23 -> 0 | P23: =G23+I23+K23+M23+O23 -> 4200 | Q23: - | R23: =SUM(P23:Q23) -> 4200
A24: Total Travel Costs for Activity 4 | G24: =SUM(G18:G23) -> 8396.875 | I24: =SUM(I18:I23) -> 10625 | K24: =SUM(K18:K23) -> 10625 | M24: =SUM(M18:M23) -> 1428.125 | O24: =SUM(O18:O23) -> 0 | P24: =SUM(P18:P23) -> 31075 | Q24: =SUM(Q18:Q23) -> 0 | R24: =SUM(R18:R23) -> 31075
A26: Equipment for Activity 4
A27: Post Harvest Construction and Equipment | C27: Equipment | D27: Unit | E27: 1 | F27: 0 | G27: 38000 | H27: 1 | I27: 65000 | J27: 0 | K27: =J27*F27 -> 0 | L27: 0 | M27: =L27*F27 -> 0 | N27: 0 | O27: =N27*F27 -> 0 | P27: =G27+I27+K27+M27+O27 -> 103000 | Q27: 0 | R27: =SUM(P27:Q27) -> 103000
A28: Total Equipment for Activity 4 | F28: =SUM(C22:C27) -> 0 | G28: =SUM(G27) -> 38000 | I28: =SUM(I27) -> 65000 | K28: =SUM(K27) -> 0 | M28: =SUM(M27) -> 0 | O28: =SUM(O27) -> 0 | P28: =SUM(P27) -> 103000 | Q28: =SUM(Q27) -> 0 | R28: =SUM(R27) -> 103000
A30: Supplies for Activity 4
A31: Laptops & Software | C31: Supplies | D31: Unit | E31: 2 | F31: 1000 | G31: =E31*F31 -> 2000 | H31: 0 | I31: =H31*F31 -> 0 | J31: 0 | K31: =J31*F31 -> 0 | L31: 0 | M31: =L31*F31 -> 0 | N31: 0 | O31: =N31*F31 -> 0 | P31: =G31+I31+K31+M31+O31 -> 2000 | Q31: 0 | R31: =SUM(P31:Q31) -> 2000
A32: Office Supplies/Stationary/Printing Materials | C32: Supplies | D32: Month | E32: 2 | F32: 200 | G32: =E32*F32 -> 400 | H32: 12 | I32: =H32*F32 -> 2400 | J32: 12 | K32: =J32*F32 -> 2400 | L32: 2 | M32: =L32*F32 -> 400 | N32: 0 | O32: =N32*F32 -> 0 | P32: =G32+I32+K32+M32+O32 -> 5600 | Q32: 0 | R32: =SUM(P32:Q32) -> 5600
A33: Courier fees | C33: Supplies | D33: Month | E33: 2 | F33: 45 | G33: =E33*F33 -> 90 | H33: 12 | I33: =H33*F33 -> 540 | J33: 12 | K33: =J33*F33 -> 540 | L33: 2 | M33: =L33*F33 -> 90 | N33: 0 | O33: =N33*F33 -> 0 | P33: =G33+I33+K33+M33+O33 -> 1260 | Q33: 0 | R33: =SUM(P33:Q33) -> 1260
A34: Other Inputs for Post Harvest and Complementary Crops Value Adding Process | C34: Supplies | D34: Unit | E34: 1 | F34: 0 | G34: 1500 | H34: 1 | I34: 25500 | J34: 0 | K34: =J34*F34 -> 0 | L34: 0 | M34: =L34*F34 -> 0 | N34: 0 | O34: =N34*F34 -> 0 | P34: =G34+I34+K34+M34+O34 -> 27000 | Q34: 0 | R34: =SUM(P34:Q34) -> 27000
A35: Total Supplies for Activity 4 | G35: =SUM(G31:G34) -> 3990 | I35: =SUM(I31:I34) -> 28440 | K35: =SUM(K31:K34) -> 2940 | M35: =SUM(M31:M34) -> 490 | O35: =SUM(O31:O34) -> 0 | P35: =SUM(P31:P34) -> 35860 | Q35: =SUM(Q31:Q34) -> 0 | R35: =SUM(R31:R34) -> 35860
A37: Office Expenses for Activity 4
A38: Banking and Cash Handling Fees | C38: Office Expenses | D38: Month | E38: 0 | F38: 40 | G38: =E38*F38 -> 0 | H38: 12 | I38: =H38*F38 -> 480 | J38: 12 | K38: =J38*F38 -> 480 | L38: 2 | M38: =L38*F38 -> 80 | N38: 0 | O38: =N38*F38 -> 0 | P38: =G38+I38+K38+M38+O38 -> 1040 | Q38: 0 | R38: =SUM(P38:Q38) -> 1040
A39: Total Office Expenses for Activity 4 | G39: =SUM(G38:G38) -> 0 | I39: =SUM(I38:I38) -> 480 | K39: =SUM(K38:K38) -> 480 | M39: =SUM(M38:M38) -> 80 | O39: =SUM(O38:O38) -> 0 | P39: =SUM(P38:P38) -> 1040 | Q39: =SUM(Q38:Q38) -> 0 | R39: =SUM(R38:R38) -> 1040
A41: Subtotal Direct Costs Activity 4 | G41: =G39+G35+G24+G15+G28 -> 60881.875 | I41: =I39+I35+I24+I15+I28 -> 169404.1 | K41: =K39+K35+K24+K15+K28 -> 80849.873 | M41: =M39+M35+M24+M15+M28 -> 13466.295 | O41: =O39+O35+O24+O15+O28 -> 0 | P41: =P39+P35+P24+P15+P28 -> 324602.14 | Q41: =Q39+Q35+Q24+Q15+Q28 -> 0 | R41: =R39+R35+R24+R15+R28 -> 324602.14
A43: Total Indirect Costs for Activity 4 | C43: Indirect Charges | F43: 0.03 | G43: =$F$43*G41 -> 1826.4562 | I43: =$F$43*I41 -> 5082.123 | K43: =$F$43*K41 -> 2425.4962 | M43: =$F$43*M41 -> 403.98885 | O43: =$F$43*O41 -> 0 | P43: =O43+M43+K43+I43+G43 -> 9738.0643 | Q43: 0 | R43: =SUM(P43:Q43) -> 9738.0643
A45: Total Activity 4 | G45: =G43+G41 -> 62708.331 | I45: =I43+I41 -> 174486.22 | K45: =K43+K41 -> 83275.369 | M45: =M43+M41 -> 13870.284 | O45: =O43+O41 -> 0 | P45: =P43+P41 -> 334340.21 | Q45: =Q43+Q41 -> 0 | R45: =R43+R41 -> 334340.21
A47: Grant Total of Agrosavia Subaward | G47: =G45 -> 62708.331 | I47: =I45 -> 174486.22 | K47: =K45 -> 83275.369 | M47: =M45 -> 13870.284 | O47: =O45 -> 0 | P47: =P45 -> 334340.21 | Q47: =Q45 -> 0 | R47: =R45 -> 334340.21

Sheet Supplies
A1: Detailed Quotes for Supplies
A3: Item Detail | B3: Price
A4: Tablet
A5: Microsoft Surface Pro 4 256 GB i7e with Surface Pen & Cover | B5: 850
B6: =SUM(B5) -> 850
A8: Laptop
A9: Dell XPS 15 | B9: 1049.99
A10: Laptop Bag, Accessories | B10: 44.99
A11: Mouse | B11: 19.99
B12: =SUM(B9:B11) -> 1114.97
A14: LCD Projector
A15: BenQ MH535FHD 1080P Projector with Ceiling Mount | B15: 583
A16: Extra Bulb, stand and accessories | B16: 51.5
B17: =SUM(B15:B16) -> 634.5
A19: Color Laser Printer & Scanner
A20: Dell Color Smart Multifunction Printer S2825cdn Color Laser | B20: 390
A21: Toners & Accessories | B21: 450
B22: =SUM(B19:B21) -> 840

Sheet Education Worksheet 
A1: EpL Beneficiaries | H1: Totals
A2: Year | B2: Year 1 | C2: Year 2 | E2: Year 3 | G2: Year 4
A3: Frequency | B3: 3x/week | C3: 3x/week | D3: 2x/week | E3: 3x/week | F3: 2x/week | G3: 2x/week
A4: Choluteca | B4: 75 | C4: 125 | D4: 75 | E4: 75 | F4: 125 | G4: 75 | H4: =B4+C4+E4 -> 275 | I4: =H4+H5+H6 -> 850 | J4: Total Number of Child Beneficiaries
A5: Valle | B5: 75 | C5: 125 | D5: 75 | E5: 100 | F5: 125 | G5: 100 | H5: =B5+C5+E5 -> 300
A6: SPS Area | B6: 75 | C6: 100 | D6: 75 | E6: 100 | F6: 100 | G6: 100 | H6: =B6+C6+E6 -> 275
A8: EpE Beneficiaries | H8: Totals | J8: =I4+I11 -> 1750
A9: Year | B9: Year 1 | C9: Year 2 | E9: Year 3 | G9: Year 4
A10: Frequency | C10: 5x/week | E10: 5x/week | G10: 5x/week
A11: Choluteca | C11: 75 | E11: 100 | G11: 125 | H11: =C11+E11+G11 -> 300 | I11: =H11+H12+H13 -> 900
A12: Valle | C12: 75 | E12: 100 | G12: 125 | H12: =C12+E12+G12 -> 300
A13: SPS Area | C13: 75 | E13: 100 | G13: 125 | H13: =C13+E13+G13 -> 300
A15: EpL Classes | H15: Total Classes | J15: # of Participants per Class | K15: If Blue and Green Use Same Trainers
A16: Year | B16: Year 1 | C16: Year 2 | E16: Year 3 | G16: Year 4 | J16: Class
A17: Frequency | B17: 3x/week | C17: 3x/week | D17: 2x/week | E17: 3x/week | F17: 2x/week | G17: 2x/week | J17: 25
A18: Choluteca | B18: =B4/J17 -> 3 | C18: =C4/J17 -> 5 | D18: =D4/J17 -> 3 | E18: =E4/J17 -> 3 | F18: =F4/J17 -> 5 | G18: =G4/J17 -> 3 | H18: =B18+C18+E18 -> 11 | I18: =H18+H19+H20 -> 34 | J18: Total Number of Classes/Trainers | K18: =B21+C21 -> 23 | L18: Minium Number of Trainers Needed
A19: Valle | B19: =B5/J17 -> 3 | C19: =C5/J17 -> 5 | D19: =D5/J17 -> 3 | E19: =E5/J17 -> 4 | F19: =F5/J17 -> 5 | G19: =G5/J17 -> 4 | H19: =B19+C19+E19 -> 12
A20: SPS Area | B20: =B6/J17 -> 3 | C20: =C6/J17 -> 4 | D20: =D6/J17 -> 3 | E20: =E6/J17 -> 4 | F20: =F6/J17 -> 4 | G20: =G6/J17 -> 4 | H20: =B20+C20+E20 -> 11
B21: =SUM(B18:B20) -> 9 | C21: =SUM(C18:C20) -> 14 | D21: =SUM(D18:D20) -> 9 | E21: =SUM(E18:E20) -> 11 | F21: =SUM(F18:F20) -> 14 | G21: =SUM(G18:G20) -> 11
J22: =I18+I26 -> 70 | L22: =K18+K28 -> 38
A23: EpE Classes | H23: Totals
A24: Year | B24: Year 1 | C24: Year 2 | E24: Year 3 | G24: Year 4
A25: Frequency | C25: 5x/week | E25: 5x/week | G25: 5x/week | K25: If Each Group Has Same Trainer
A26: Choluteca | C26: =C11/J17 -> 3 | E26: =E11/J17 -> 4 | G26: =G11/J17 -> 5 | H26: =C26+E26+G26 -> 12 | I26: =H26+H27+H28 -> 36
A27: Valle | C27: =C12/J17 -> 3 | E27: =E12/J17 -> 4 | G27: =G12/J17 -> 5 | H27: =C27+E27+G27 -> 12
A28: SPS Area | C28: =C13/J17 -> 3 | E28: =E13/J17 -> 4 | G28: =G13/J17 -> 5 | H28: =C28+E28+G28 -> 12 | K28: 15
C29: =SUM(C26:D28) -> 9 | E29: =SUM(E26:F28) -> 12 | G29: =SUM(G26:G28) -> 15
A32: EpLs Frequency | H32: Total | J32: TOTAL EpL HOURS (By Number of Classes)
B33: Number of Weeks | D33: Frequency (week) | F33: Hours per Session | H33: Training Hours | J33: Year 1 | K33: Year 2 | M33: Year 3 | O33: Year 4
B34: Year 1 | C34: Year 2 | D34: Year 1 | E34: Year 2 | F34: Year 1 | G34: Year 2 | H34: Year 1 | I34: Year 2 | J34: Year 1 | K34: Year 1 | L34: Year 2 | M34: Year 1 | N34: Year 2 | O34: Year 2
A35: EpLs | B35: 30 | C35: 30 | D35: 3 | E35: 2 | F35: 2 | G35: 2 | H35: =B35*D35*F35 -> 180 | I35: =C35*E35*G35 -> 120 | J35: =B21*H35 -> 1620 | K35: =C21*H35 -> 2520 | L35: =D21*I35 -> 1080 | M35: =E21*H35 -> 1980 | N35: =F21*I35 -> 1680 | O35: =G21*I35 -> 1320
G36: EpL Program Total | H36: =H35+I35 -> 300
A38: EpEs Frequency | H38: Total | J38: By Number of Classes
B39: Number of Weeks | D39: Frequency (week) | F39: Hours per Session | H39: Training Hours | J39: Year 1 | K39: Year 2 | M39: Year 3 | O39: Year 4
B40: Year 1 | D40: Year 1 | F40: Year 1 | H40: Year 1 | J40: Year 1 | K40: Year 1 | M40: Year 1 | O40: Year 2
A41: EpLs | B41: 32 | D41: 5 | F41: 4 | H41: =B41*D41*F41 -> 640 | K41: =H41*C29 -> 5760 | M41: =E29*H41 -> 7680 | O41: =G29*H41 -> 9600
G42: EpL Program Total | H42: =H41+I41 -> 640
A43: EpL Facilitator Stipend
C44: Hours | D44: Cost Per Hour | E44: TOTAL
A45: First Year | B45: Faciliator Cost per EpL | C45: =H35 -> 180 | D45: 8 | E45: =C45*D45 -> 1440
A46: Second Year | B46: Faciliator Cost per EpL | C46: =I35 -> 120 | D46: 8 | E46: =C46*D46 -> 960
A48: EpL Snack Costs Per Session
C49: Number of Classes | D49: Cost Per Class | E49: TOTAL
A50: First Year | B50: Snack Cost per EpL | C50: =B35*D35 -> 90 | D50: 10 | E50: =C50*D50 -> 900
A51: Second Year | B51: Snack Cost per EpL | C51: =C35*E35 -> 60 | D51: 10 | E51: =C51*D51 -> 600
A53: EpE Facilitator Stipend
C54: Hours | D54: Cost Per Hour | E54: TOTAL
A55: First Year | B55: Faciliator Cost per EpE | C55: =H41 -> 640 | D55: 8 | E55: =C55*D55 -> 5120
A57: EpE Snack Costs Per Session
C58: Number of Classes | D58: Cost Per Class | E58: TOTAL
A59: First Year | B59: Snack Cost per EpL | C59: =B41*D41 -> 160 | D59: 10 | E59: =C59*D59 -> 1600
