Workbook
Name Category: #N/A
Name Category: #N/A
Name Category: #N/A
Name Category: 'Project Budget'!$G$15:$G$181
Name DL_Country: #N/A
Name DL_Country: #N/A
Name DL_Country: #N/A
Name DL_Country: 'Project Budget'!#REF!
Name DL_TotalDOL: #N/A
Name DL_TotalDOL: #N/A
Name DL_TotalDOL: #N/A
Name DL_TotalDOL: 'Project Budget'!$T$14:$T$31
Name EQ_Country: #N/A
Name EQ_Country: #N/A
Name EQ_Country: #N/A
Name EQ_Country: 'Project Budget'!#REF!
Name EQ_TotalDOL: #N/A
Name EQ_TotalDOL: #N/A
Name EQ_TotalDOL: #N/A
Name EQ_TotalDOL: 'Project Budget'!#REF!
Name inf: #N/A
Name inf: #N/A
Name inf: #N/A
Name inf: #REF!
Name JEA_Country: #N/A
Name JEA_Country: #N/A
Name JEA_Country: #N/A
Name JEA_Country: #REF!
Name JEA_Year1: #N/A
Name JEA_Year1: #N/A
Name JEA_Year1: #N/A
Name JEA_Year1: #REF!
Name ME_Country: #N/A
Name ME_Country: #N/A
Name ME_Country: #N/A
Name ME_Country: 'Project Budget'!#REF!
Name ME_TotalDOL: #N/A
Name ME_TotalDOL: #N/A
Name ME_TotalDOL: #N/A
Name ME_TotalDOL: 'Project Budget'!$T$156:$T$167
Name O1_Country: #N/A
Name O1_Country: #N/A
Name O1_Country: #N/A
Name O1_Country: 'Project Budget'!#REF!
Name O1_TotalDOL: #N/A
Name O1_TotalDOL: #N/A
Name O1_TotalDOL: #N/A
Name O1_TotalDOL: 'Project Budget'!$T$75:$T$75
Name O2_Country: #N/A
Name O2_Country: #N/A
Name O2_Country: #N/A
Name O2_Country: 'Project Budget'!#REF!
Name O2_TotalDOL: #N/A
Name O2_TotalDOL: #N/A
Name O2_TotalDOL: #N/A
Name O2_TotalDOL: 'Project Budget'!#REF!
Name SU_Country: #N/A
Name SU_Country: #N/A
Name SU_Country: #N/A
Name SU_Country: 'Project Budget'!#REF!

Sheet Budget Summary
B1: Mexico Awareness Raising Project
B2: FOA-ILAB-20-10
B3: Partners of the Americas
B4: BUDGET ITEM | C4: TOTAL DOL | D4: TOTAL COST SHARING | E4: PROJECT GRAND TOTAL
B5: Direct Labor | C5: ='Project Budget'!T33 -> 2303880.4 | D5: ='Project Budget'!U33 -> 0 | E5: =SUM(C5:D5) -> 2303880.4
B6: Travel | C6: ='Project Budget'!T53 -> 204415.3 | D6: ='Project Budget'!U53 -> 0 | E6: =SUM(C6:D6) -> 204415.3
B7: Equipment | C7: 0 | D7: 0 | E7: =SUM(C7:D7) -> 0
B8: Supplies and Office Expenses | C8: ='Project Budget'!T71 -> 259904.78 | D8: ='Project Budget'!U71 -> 0 | E8: =SUM(C8:D8) -> 259904.78
B9: Outcome 1 | C9: ='Project Budget'!T129 -> 3659294.1 | D9: ='Project Budget'!U129 -> 0 | E9: =SUM(C9:D9) -> 3659294.1
B10: Outcome 2 | C10: ='Project Budget'!T152 -> 1019816.1 | D10: ='Project Budget'!U152 -> 0 | E10: =SUM(C10:D10) -> 1019816.1
B11: Monitoring, Evaluation, and Collection of Reliable Data | C11: ='Project Budget'!T177 -> 323301.23 | D11: ='Project Budget'!U177 -> 0 | E11: =SUM(C11:D11) -> 323301.23
B12: Total Direct Costs | C12: =SUM(C5:C11) -> 7770611.9 | D12: =SUM(D5:D11) -> 0 | E12: =SUM(E5:E11) -> 7770611.9
B13: Indirect Costs (NICRA) | C13: ='Project Budget'!T181 -> 2229388.6 | D13: ='Project Budget'!U181 -> 0 | E13: =SUM(C13:D13) -> 2229388.6
B14: TOTAL COSTS | C14: =C13+C12 -> 10000000 | D14: =D13+D12 -> 0 | E14: =E13+E12 -> 10000000
B16: ADMINISTRATIVE COSTS (Direct Labor, Equipment, Supplies, Indirect Costs) | C16: =C5+C7+C8+C13 -> 4793173.7
B17: PROGRAM COSTS (Travel, Contractual, Other Direct Costs) | C17: =C6+C9+C10+C11 -> 5206826.8

Sheet Project Budget
F1: Equal Access to Quality Jobs for Women and Girls in Agriculture (EQUAL)
F2: FOA-ILAB-19-02
F3: Partners of the Americas
A4: Entity: | B4: P | F4: Partners of the Americas
A5: Program-Dept.: | B5: 20200 | F5: NOFO: FOA-ILAB-20-10
A6: Funder-Grant: | B6: DOL423 | F6: Country: Mexico
F7: Budget Assumptions:
F8: Inflation - US Based Goods/Services | G8: 1.03
F9: Inflation - Locally Purchased Goods/Services | G9: 1.04
F10: Merit Based Increases for HQ & Field Staff | G10: 1.035
A12: Sage Activity | B12: Sage Object Code/ Line Item | C12: Country Code (DC=0 or MX) | D12: Office Code (DC=0 or MX) | E12: Subcontract Code | F12: BUDGET ITEM | G12: CATEGORY | H12: UNIT | I12: # of Units | J12: RATE / UNIT | K12: YEAR 1 | L12: # of Units | M12: YEAR 2 | N12: # of Units | O12: YEAR 3 | P12: # of Units | Q12: YEAR 4 | R12: # of Units | S12: YEAR 5 | T12: TOTAL DOL | U12: TOTAL COST SHARING | V12: PROJECT GRAND TOTAL
F13: Direct Labor
F14: Key Personnel
A15: PERSNL-PD | B15: 70000 | C15: MEX | D15: MEX | E15: 0 | F15: Project Director (100%) | G15: Salaries | H15: Month | I15: 12 | J15: 12916 | K15: =I15*J15 -> 154992 | L15: 12 | M15: =L15*J15*$G$10 -> 160416.72 | N15: 12 | O15: =(J15*3*$G$10*$G$10)+(N15*7000*$G$10*$G$10) -> 131490.73 | P15: 12 | Q15: =P15*7000*1.015*$G$10*$G$10*$G$10 -> 94529.286 | R15: 6 | S15: =R15*7000*$G$10*$G$10*$G$10*$G$10 -> 48195.966 | T15: =SUM(K15+M15+O15+Q15+S15) -> 589624.7 | U15: 0 | V15: =SUM(T15:U15) -> 589624.7
A16: PERSNL-M&E | B16: 70000 | C16: MEX | D16: MEX | E16: 0 | F16: Monitoring and Evaluation (M&E) Officer (100%) | G16: Salaries | H16: Month | I16: 12 | J16: 4200 | K16: =I16*J16 -> 50400 | L16: 12 | M16: =L16*J16*$G$10 -> 52164 | N16: 12 | O16: =N16*J16*$G$10*$G$10 -> 53989.74 | P16: 12 | Q16: =P16*J16*1.015*$G$10*$G$10*$G$10 -> 56717.572 | R16: 6 | S16: =J16*R16*$G$10*$G$10*$G$10*$G$10 -> 28917.58 | T16: =SUM(K16+M16+O16+Q16+S16) -> 242188.89 | U16: 0 | V16: =SUM(T16:U16) -> 242188.89
F18: Other Professional Personnel
A19: PERSNL-CBS | B19: 70000 | C19: MEX | D19: MEX | E19: 0 | F19: Capacity Building Specialist (100%) | G19: Salaries | H19: Month | I19: 11 | J19: 3600 | K19: =I19*J19 -> 39600 | L19: 12 | M19: =L19*J19*$G$10 -> 44712 | N19: 12 | O19: =N19*J19*$G$10*$G$10 -> 46276.92 | P19: 12 | Q19: =P19*J19*1.015*$G$10*$G$10*$G$10 -> 48615.061 | R19: 5 | S19: =J19*R19*$G$10*$G$10*$G$10*$G$10 -> 20655.414 | T19: =SUM(K19+M19+O19+Q19+S19) -> 199859.4 | U19: 0 | V19: =SUM(T19:U19) -> 199859.4
A20: PERSNL-COM | B20: 70000 | C20: MEX | D20: MEX | E20: 0 | F20: Communications Specialist (100%) | G20: Salaries | H20: Month | I20: 11 | J20: 2800 | K20: =I20*J20 -> 30800 | L20: 12 | M20: =L20*J20*$G$10 -> 34776 | N20: 12 | O20: =N20*J20*$G$10*$G$10 -> 35993.16 | P20: 12 | Q20: =P20*J20*1.015*$G$10*$G$10*$G$10 -> 37811.714 | R20: 5 | S20: =J20*R20*$G$10*$G$10*$G$10*$G$10 -> 16065.322 | T20: =SUM(K20+M20+O20+Q20+S20) -> 155446.2 | U20: 0 | V20: =SUM(T20:U20) -> 155446.2
A21: PERSNL-F&A | B21: 70000 | C21: MEX | D21: MEX | E21: 0 | F21: Finance and Administration Manager (100%) | G21: Salaries | H21: Month | I21: 11 | J21: 3200 | K21: =I21*J21 -> 35200 | L21: 12 | M21: =L21*J21*$G$10 -> 39744 | N21: 12 | O21: =N21*J21*$G$10*$G$10 -> 41135.04 | P21: 12 | Q21: =P21*J21*1.015*$G$10*$G$10*$G$10 -> 43213.388 | R21: 6 | S21: =J21*R21*$G$10*$G$10*$G$10*$G$10 -> 22032.442 | T21: =SUM(K21+M21+O21+Q21+S21) -> 181324.87 | U21: 0 | V21: =SUM(T21:U21) -> 181324.87
F23: Home Office Support
A24: PERSNL-PM | B24: Timesheets | C24: 0 | D24: 0 | E24: 0 | F24: Project Manager (20%) | G24: Salaries | H24: Month | I24: 12 | J24: =9832*0.2 -> 1966.4 | K24: =I24*J24 -> 23596.8 | L24: 12 | M24: =L24*J24*$G$10 -> 24422.688 | N24: 12 | O24: =N24*J24*$G$10*$G$10 -> 25277.482 | P24: 12 | Q24: =P24*J24*1.015*$G$10*$G$10*$G$10 -> 26554.627 | R24: 6 | S24: =J24*R24*$G$10*$G$10*$G$10*$G$10 -> 13538.935 | T24: =SUM(K24+M24+O24+Q24+S24) -> 113390.53 | U24: 0 | V24: =SUM(T24:U24) -> 113390.53
A25: PERSNL-PO | B25: Timesheets | C25: 0 | D25: 0 | E25: 0 | F25: Program Officer (50%) | G25: Salaries | H25: Month | I25: 12 | J25: =5500*0.5 -> 2750 | K25: =I25*J25 -> 33000 | L25: 12 | M25: =L25*J25*$G$10 -> 34155 | N25: 12 | O25: =N25*J25*$G$10*$G$10 -> 35350.425 | P25: 12 | Q25: =P25*J25*1.015*$G$10*$G$10*$G$10 -> 37136.505 | R25: 6 | S25: =J25*R25*$G$10*$G$10*$G$10*$G$10 -> 18934.13 | T25: =SUM(K25+M25+O25+Q25+S25) -> 158576.06 | U25: 0 | V25: =SUM(T25:U25) -> 158576.06
F27: Subtotal | K27: =SUM(K15:K25) -> 367588.8 | M27: =SUM(M15:M25) -> 390390.41 | O27: =SUM(O15:O25) -> 369513.49 | Q27: =SUM(Q15:Q25) -> 344578.15 | S27: =SUM(S15:S25) -> 168339.79 | T27: =SUM(K27+M27+O27+Q27+S27) -> 1640410.6 | U27: 0 | V27: =SUM(T27:U27) -> 1640410.6
F29: Fringe Benefits
A30: FRINGE-MX | B30: 70015 | C30: MEX | D30: MEX | E30: 0 | F30: Fringe benefits - Mexico Staff | G30: Fringe Benefits | J30: 0.5084 | K30: =SUM(K16,K19,K20,K21)*J30 -> 79310.4 | M30: =SUM(M16,M19,M20,M21)*J30 -> 87137.726 | O30: =SUM(O15,O16,O19,O20,O21)*J30 -> 157037.43 | Q30: =SUM(Q15,Q16,Q19,Q20,Q21)*J30 -> 142802.96 | S30: =SUM(S15,S16,S19,S20,S21)*J30 -> 69074.642 | T30: =SUM(K30+M30+O30+Q30+S30) -> 535363.16 | U30: 0 | V30: =SUM(T30:U30) -> 535363.16
A31: FRINGE | B31: Timesheets | C31: 0 | D31: 0 | E31: 0 | F31: Fringe benefits - Home Office Support | G31: Fringe Benefits | J31: 0.2181 | K31: =SUM(K15,K24:K25)*$J$31 -> 46147.517 | M31: =SUM(M15,M24:M25)*$J$31 -> 47762.68 | O31: =SUM(O24:O25)*$J$31 -> 13222.947 | Q31: =SUM(Q24:Q25)*$J$31 -> 13891.036 | S31: =SUM(S24:S25)*$J$31 -> 7082.3755 | T31: =SUM(K31+M31+O31+Q31+S31) -> 128106.56 | U31: 0 | V31: =SUM(T31:U31) -> 128106.56
F33: Subtotal Direct Labor | K33: =SUM(K27:K31) -> 493046.72 | M33: =SUM(M27:M31) -> 525290.81 | O33: =SUM(O27:O31) -> 539773.87 | Q33: =SUM(Q27:Q31) -> 501272.15 | S33: =SUM(S27:S31) -> 244496.81 | T33: =K33+M33+O33+Q33+S33 -> 2303880.4 | U33: =SUM(U27:U31) -> 0 | V33: =SUM(T33:U33) -> 2303880.4
F34: Travel
F35: T1: Post-award Meeting with ILAB
A36: MX.T1.A | B36: 86040 | C36: MEX | D36: MEX | E36: 0 | F36: Airfare - Mexico-DC | G36: Travel | H36: Trip | I36: 2 | J36: 750 | K36: =I36*J36 -> 1500 | L36: 0 | M36: =L36*J36 -> 0 | N36: 0 | O36: =N36*J36 -> 0 | P36: 0 | Q36: =P36*J36 -> 0 | R36: 0 | S36: =R36*J36 -> 0 | T36: =K36+M36+O36+Q36+S36 -> 1500 | U36: - | V36: =SUM(T36:U36) -> 1500
A37: MX.T1.B | B37: 86030 (Lodging)/ 86050 (M&IE) | C37: MEX | D37: MEX | E37: 0 | F37: Lodging and M&IE in DC | G37: Travel | H37: Day | I37: =5*2 -> 10 | J37: =68.4+210 -> 278.4 | K37: =I37*J37 -> 2784 | L37: 0 | M37: =L37*J37 -> 0 | N37: 0 | O37: =N37*J37 -> 0 | P37: 0 | Q37: =P37*J37 -> 0 | R37: 0 | S37: =R37*J37 -> 0 | T37: =K37+M37+O37+Q37+S37 -> 2784 | U37: - | V37: =SUM(T37:U37) -> 2784
A38: MX.T1.C | B38: 86000 | C38: MEX | D38: MEX | E38: 0 | F38: Local transportation in DC | G38: Travel | H38: Day | I38: 5 | J38: 30 | K38: =I38*J38 -> 150 | L38: 0 | M38: =L38*J38 -> 0 | N38: 0 | O38: =N38*J38 -> 0 | P38: 0 | Q38: =P38*J38 -> 0 | R38: 0 | S38: =R38*J38 -> 0 | T38: =K38+M38+O38+Q38+S38 -> 150 | U38: - | V38: =SUM(T38:U38) -> 150
A39: MX.T1.D | B39: 86050 | C39: MEX | D39: MEX | E39: 0 | F39: U.S. Visa Fees | G39: Travel | H39: Trip | I39: 2 | J39: 160 | K39: =I39*J39 -> 320 | L39: 0 | M39: =L39*J39 -> 0 | N39: 0 | O39: =N39*J39 -> 0 | P39: 0 | Q39: =P39*J39 -> 0 | R39: 0 | S39: =R39*J39 -> 0 | T39: =K39+M39+O39+Q39+S39 -> 320 | U39: - | V39: =SUM(T39:U39) -> 320
F40: T2: Field Personnel Annual Visits with ILAB
A41: MX.T2.A | B41: 86040 | C41: MEX | D41: MEX | E41: 0 | F41: Airfare - Mexico-DC | G41: Travel | H41: Trip | I41: 0 | J41: 750 | K41: =I41*J41 -> 0 | L41: 1 | M41: =L41*J41*$G$9 -> 780 | N41: 2 | O41: =N41*J41*$G$9*$G$9 -> 1622.4 | P41: 1 | Q41: =P41*J41*$G$9*$G$9*$G$9 -> 843.648 | R41: 1 | S41: =R41*J41*$G$9*$G$9*$G$9*$G$9 -> 877.39392 | T41: =K41+M41+O41+Q41+S41 -> 4123.4419 | U41: - | V41: =SUM(T41:U41) -> 4123.4419
A42: MX.T2.B | B42: 86030 (Lodging)/ 86050 (M&IE) | C42: MEX | D42: MEX | E42: 0 | F42: Lodging and M&IE in DC | G42: Travel | H42: Day | I42: 0 | J42: =68.4+210 -> 278.4 | K42: =I42*J42 -> 0 | L42: 8 | M42: =L42*J42*$G$9 -> 2316.288 | N42: 16 | O42: =N42*J42*$G$9*$G$9 -> 4817.879 | P42: 8 | Q42: =P42*J42*$G$9*$G$9*$G$9 -> 2505.2971 | R42: 8 | S42: =R42*J42*$G$9*$G$9*$G$9*$G$9 -> 2605.509 | T42: =K42+M42+O42+Q42+S42 -> 12244.973 | U42: - | V42: =SUM(T42:U42) -> 12244.973
A43: MX.T2.C | B43: 86000 | C43: MEX | D43: MEX | E43: 0 | F43: Local transportation in DC | G43: Travel | H43: Day | I43: 0 | J43: 30 | K43: =I43*J43 -> 0 | L43: 8 | M43: =L43*J43*$G$9 -> 249.6 | N43: 8 | O43: =N43*J43*$G$9*$G$9 -> 259.584 | P43: 8 | Q43: =P43*J43*$G$9*$G$9*$G$9 -> 269.96736 | R43: 8 | S43: =R43*J43*$G$9*$G$9*$G$9*$G$9 -> 280.76605 | T43: =K43+M43+O43+Q43+S43 -> 1059.9174 | U43: - | V43: =SUM(T43:U43) -> 1059.9174
F44: T3: Project Management Travel to Field
A45: MX.T3.A | B45: 86040 | C45: 0 | D45: 0 | E45: 0 | F45: Airfare - DC-Mexico | G45: Travel | H45: Trip | I45: 1 | J45: 750 | K45: =I45*J45 -> 750 | L45: 2 | M45: =L45*J45*$G$9 -> 1560 | N45: 2 | O45: =N45*J45*$G$9*$G$9 -> 1622.4 | P45: 2 | Q45: =P45*J45*$G$9*$G$9*$G$9 -> 1687.296 | R45: 1 | S45: =R45*J45*$G$9*$G$9*$G$9*$G$9 -> 877.39392 | T45: =K45+M45+O45+Q45+S45 -> 6497.0899 | U45: - | V45: =SUM(T45:U45) -> 6497.0899
A46: MX.T3.B | B46: 86030 (Lodging)/ 86050 (M&IE) | C46: 0 | D46: 0 | E46: 0 | F46: Lodging and M&IE | G46: Travel | H46: Day | I46: 5 | J46: =106.2+210 -> 316.2 | K46: =I46*J46 -> 1581 | L46: 10 | M46: =L46*J46*$G$9 -> 3288.48 | N46: 10 | O46: =N46*J46*$G$9*$G$9 -> 3420.0192 | P46: 10 | Q46: =P46*J46*$G$9*$G$9*$G$9 -> 3556.82 | R46: 5 | S46: =R46*J46*$G$9*$G$9*$G$9*$G$9 -> 1849.5464 | T46: =K46+M46+O46+Q46+S46 -> 13695.866 | U46: - | V46: =SUM(T46:U46) -> 13695.866
A47: MX.T3.C | B47: 86000 | C47: 0 | D47: 0 | E47: 0 | F47: Local transportation | G47: Travel | H47: Day | I47: 5 | J47: 60 | K47: =I47*J47 -> 300 | L47: 10 | M47: =L47*J47*$G$9 -> 624 | N47: 10 | O47: =N47*J47*$G$9*$G$9 -> 648.96 | P47: 10 | Q47: =P47*J47*$G$9*$G$9*$G$9 -> 674.9184 | R47: 5 | S47: =R47*J47*$G$9*$G$9*$G$9*$G$9 -> 350.95757 | T47: =K47+M47+O47+Q47+S47 -> 2598.836 | U47: - | V47: =SUM(T47:U47) -> 2598.836
F48: T.4 Field-based Travel for Non-M&E Activities
A49: MX.T4.A | B49: 86030 (Lodging)/ 86050 (M&IE) | C49: MEX | D49: MEX | E49: 0 | F49: Lodging and M&IE | G49: Travel | H49: Month | I49: 8 | J49: =110*16 -> 1760 | K49: =I49*J49/2 -> 7040 | L49: 12 | M49: =L49*J49*$G$9 -> 21964.8 | N49: 12 | O49: =N49*J49*$G$9*$G$9 -> 22843.392 | P49: 12 | Q49: =P49*J49*$G$9*$G$9*$G$9 -> 23757.128 | R49: 3 | S49: =R49*J49*$G$9*$G$9*$G$9*$G$9/2 -> 3088.4266 | T49: =K49+M49+O49+Q49+S49 -> 78693.746 | U49: 0 | V49: =SUM(T49:U49) -> 78693.746
A50: MX.T4.B | B50: 86000 | C50: MEX | D50: MEX | E50: 0 | F50: Local transportation (ground transportation) | G50: Travel | H50: Month | I50: 8 | J50: =100*4 -> 400 | K50: =I50*J50 -> 3200 | L50: 12 | M50: =L50*J50*$G$9 -> 4992 | N50: 12 | O50: =N50*J50*$G$9*$G$9 -> 5191.68 | P50: 12 | Q50: =P50*J50*$G$9*$G$9*$G$9 -> 5399.3472 | R50: 3 | S50: =R50*J50*$G$9*$G$9*$G$9*$G$9 -> 1403.8303 | T50: =K50+M50+O50+Q50+S50 -> 20186.857 | U50: 0 | V50: =SUM(T50:U50) -> 20186.857
A51: MX.T4.C | B51: 86040 | C51: MEX | D51: MEX | E51: 0 | F51: Local transportation (airfare) | G51: Travel | H51: Month | I51: 8 | J51: =300*4 -> 1200 | K51: =I51*J51 -> 9600 | L51: 12 | M51: =L51*J51*$G$9 -> 14976 | N51: 12 | O51: =N51*J51*$G$9*$G$9 -> 15575.04 | P51: 12 | Q51: =P51*J51*$G$9*$G$9*$G$9 -> 16198.042 | R51: 3 | S51: =R51*J51*$G$9*$G$9*$G$9*$G$9 -> 4211.4908 | T51: =K51+M51+O51+Q51+S51 -> 60560.572 | U51: 0 | V51: =SUM(T51:U51) -> 60560.572
F53: Subtotal Travel | K53: =SUM(K36:K51) -> 27225 | M53: =SUM(M36:M51) -> 50751.168 | O53: =SUM(O36:O51) -> 56001.354 | Q53: =SUM(Q36:Q51) -> 54892.463 | S53: =SUM(S36:S51) -> 15545.315 | T53: =K53+M53+O53+Q53+S53 -> 204415.3 | U53: =SUM(U36:U50) -> 0 | V53: =SUM(T53:U53) -> 204415.3
F54: Supplies and Office Expenses
F55: Project Office
A56: LAPTOP | B56: 82401 | C56: MEX/0 | D56: MEX/0 | E56: 0 | F56: Laptop computers & software | G56: Equipment | H56: Unit | I56: 5 | J56: 900 | K56: =I56*J56 -> 4500 | L56: 0 | M56: =L56*J56*$G$9 -> 0 | N56: 0 | O56: =N56*J56*$G$9*$G$9 -> 0 | P56: 0 | Q56: =P56*J56*$G$9*$G$9*$G$9 -> 0 | R56: 0 | S56: =R56*J56*$G$9*$G$9*$G$9*$G$9 -> 0 | T56: =K56+M56+O56+Q56+S56 -> 4500 | U56: 0 | V56: =SUM(T56:U56) -> 4500
A57: BANK FEES | B57: 90900 | C57: MEX | D57: MEX | E57: 0 | F57: Banking and cash handling fees | G57: Supplies | H57: Month | I57: 11 | J57: 40 | K57: =I57*J57 -> 440 | L57: 12 | M57: =L57*J57*$G$9 -> 499.2 | N57: 12 | O57: =N57*J57*$G$9*$G$9 -> 519.168 | P57: 12 | Q57: =P57*J57*$G$9*$G$9*$G$9 -> 539.93472 | R57: 5 | S57: =R57*J57*$G$9*$G$9*$G$9*$G$9 -> 233.97171 | T57: =K57+M57+O57+Q57+S57 -> 2232.2744 | U57: 0 | V57: =SUM(T57:U57) -> 2232.2744
A58: COURIER | B58: 82350 | C58: MEX | D58: MEX | E58: 0 | F58: Courier fees/services | G58: Supplies | H58: Year | I58: 1 | J58: 100 | K58: =I58*J58 -> 100 | L58: 1 | M58: =L58*J58*$G$9 -> 104 | N58: 1 | O58: =N58*J58*$G$9*$G$9 -> 108.16 | P58: 1 | Q58: =P58*J58*$G$9*$G$9*$G$9 -> 112.4864 | R58: 1 | S58: =R58*J58*$G$9*$G$9*$G$9*$G$9 -> 116.98586 | T58: =K58+M58+O58+Q58+S58 -> 541.63226 | U58: 0 | V58: =SUM(T58:U58) -> 541.63226
A59: RECRUIT | B59: 90450 | C59: MEX | D59: MEX | E59: 0 | F59: Recruitment/Procurement Advertising | G59: Supplies | H59: Year | I59: 1 | J59: 400 | K59: =I59*J59 -> 400 | L59: 1 | M59: =L59*J59*$G$9 -> 416 | N59: 1 | O59: =N59*J59*$G$9*$G$9 -> 432.64 | P59: 1 | Q59: =P59*J59*$G$9*$G$9*$G$9 -> 449.9456 | R59: 0 | S59: =R59*J59*$G$9*$G$9*$G$9*$G$9 -> 0 | T59: =K59+M59+O59+Q59+S59 -> 1698.5856 | U59: 0 | V59: =SUM(T59:U59) -> 1698.5856
A60: SUPPLIES | B60: 82401 | C60: MEX/0 | D60: MEX/0 | E60: 0 | F60: Office supplies | G60: Supplies | H60: Month | I60: 11 | J60: 125 | K60: =I60*J60 -> 1375 | L60: 12 | M60: =L60*J60*$G$9 -> 1560 | N60: 12 | O60: =N60*J60*$G$9*$G$9 -> 1622.4 | P60: 12 | Q60: =P60*J60*$G$9*$G$9*$G$9 -> 1687.296 | R60: 3 | S60: =R60*J60*$G$9*$G$9*$G$9*$G$9 -> 438.69696 | T60: =K60+M60+O60+Q60+S60 -> 6683.393 | U60: 0 | V60: =SUM(T60:U60) -> 6683.393
A61: RENT & UT | B61: 85180 | C61: MEX | D61: MEX | E61: 0 | F61: Coworking office space | G61: Supplies | H61: Month | I61: 11 | J61: 1900 | K61: =I61*J61 -> 20900 | L61: 12 | M61: =L61*J61*$G$9 -> 23712 | N61: 12 | O61: =N61*J61*$G$9*$G$9 -> 24660.48 | P61: 12 | Q61: =P61*J61*$G$9*$G$9*$G$9 -> 25646.899 | R61: 5 | S61: =R61*J61*$G$9*$G$9*$G$9*$G$9 -> 11113.656 | T61: =K61+M61+O61+Q61+S61 -> 106033.04 | U61: 0 | V61: =SUM(T61:U61) -> 106033.04
A62: PROP&LIAB | B62: 89500 | C62: MEX | D62: MEX | E62: 0 | F62: Property and liability insurance | G62: Supplies | H62: Year | I62: 1 | J62: 400 | K62: =I62*J62 -> 400 | L62: 1 | M62: =L62*J62*$G$9 -> 416 | N62: 1 | O62: =N62*J62*$G$9*$G$9 -> 432.64 | P62: 1 | Q62: =P62*J62*$G$9*$G$9*$G$9 -> 449.9456 | R62: 1 | S62: =R62*J62*$G$9*$G$9*$G$9*$G$9 -> 467.94342 | T62: =K62+M62+O62+Q62+S62 -> 2166.529 | U62: 0 | V62: =SUM(T62:U62) -> 2166.529
A63: LEGAL | B63: 90100 | C63: MEX | D63: MEX | E63: 0 | F63: Legal fees | G63: Supplies | H63: Year | I63: 1 | J63: 1000 | K63: =I63*J63 -> 1000 | L63: 1 | M63: =L63*J63*$G$9 -> 1040 | N63: 1 | O63: =N63*J63*$G$9*$G$9 -> 1081.6 | P63: 1 | Q63: =P63*J63*$G$9*$G$9*$G$9 -> 1124.864 | R63: 1 | S63: =R63*J63*$G$9*$G$9*$G$9*$G$9 -> 1169.8586 | T63: =K63+M63+O63+Q63+S63 -> 5416.3226 | U63: 0 | V63: =SUM(T63:U63) -> 5416.3226
F64: Audits and Attestation Engagements
A65: AUDIT | B65: 82100 | C65: MEX | D65: MEX | E65: 0 | F65: Audit costs (A-133) | G65: Supplies | H65: Year | I65: 1 | J65: 5000 | K65: =I65*J65 -> 5000 | L65: 1 | M65: =L65*J65*$G$8 -> 5150 | N65: 1 | O65: =N65*J65*$G$8*$G$8 -> 5304.5 | P65: 1 | Q65: =P65*J65*$G$8*$G$8*$G$8 -> 5463.635 | R65: 0 | S65: =R65*J65*$G$8*$G$8*$G$8*$G$8 -> 0 | T65: =K65+M65+O65+Q65+S65 -> 20918.135 | U65: 0 | V65: =SUM(T65:U65) -> 20918.135
A66: ATTESTENG | B66: 81010 | C66: MEX | D66: MEX | E66: 0 | F66: Attestation Engagement | G66: Supplies | H66: Year | I66: 0 | J66: 100000 | K66: =I66*J66 -> 0 | L66: 0 | M66: =L66*J66*$G$8 -> 0 | N66: 1 | O66: =N66*J66*$G$8*$G$8 -> 106090 | P66: 0 | Q66: =P66*J66*$G$8*$G$8*$G$8 -> 0 | R66: 0 | S66: =R66*J66*$G$8*$G$8*$G$8*$G$8 -> 0 | T66: =K66+M66+O66+Q66+S66 -> 106090 | U66: 0 | V66: =SUM(T66:U66) -> 106090
F67: Project-wide Web Fees
A68: SUBSCRIPT | B68: 89400 | C68: MEX/0 | D68: MEX/0 | E68: 0 | F68: Timekeeping and expense reporting platform | G68: Supplies | H68: Month | I68: 12 | J68: =5*9 -> 45 | K68: =I68*J68 -> 540 | L68: 12 | M68: =L68*J68*$G$8 -> 556.2 | N68: 12 | O68: =N68*J68*$G$8*$G$8 -> 572.886 | P68: 12 | Q68: =P68*J68*$G$8*$G$8*$G$8 -> 590.07258 | R68: 6 | S68: =R68*J68*$G$8*$G$8*$G$8*$G$8 -> 303.88738 | T68: =K68+M68+O68+Q68+S68 -> 2563.046 | U68: 0 | V68: =SUM(T68:U68) -> 2563.046
A69: SUBSCRIPT | B69: 89400 | C69: MEX/0 | D69: MEX/0 | E69: 0 | F69: Zoom license | G69: Supplies | H69: Year | I69: 1 | J69: 200 | K69: =I69*J69 -> 200 | L69: 1 | M69: =L69*J69*$G$8 -> 206 | N69: 1 | O69: =N69*J69*$G$8*$G$8 -> 212.18 | P69: 1 | Q69: =P69*J69*$G$8*$G$8*$G$8 -> 218.5454 | R69: 1 | S69: =R69*J69*$G$8*$G$8*$G$8*$G$8 -> 225.10176 | T69: =K69+M69+O69+Q69+S69 -> 1061.8272 | U69: 0 | V69: =SUM(T69:U69) -> 1061.8272
F71: Subtotal Supplies and Office Expenses | K71: =SUM(K56:K69) -> 34855 | M71: =SUM(M56:M69) -> 33659.4 | O71: =SUM(O56:O69) -> 141036.65 | Q71: =SUM(Q56:Q69) -> 36283.625 | S71: =SUM(S56:S69) -> 14070.102 | T71: =K71+M71+O71+Q71+S71 -> 259904.78 | U71: =SUM(U58:U69) -> 0 | V71: =SUM(T71:U71) -> 259904.78
F72: Outcome 1: Increase understanding by workers, employers, and union leaders on how to utilize Mexico’s new labor systems to protect labor rights and effectively address labor disputes.
F73: Activities/Costs
F74: 1.1 Sub-awards
A75: MX.1.1.A | B75: 89050 | C75: MEX | D75: MEX | E75: CFO | F75: 1.1.1. Contractual: Sub-award to CFO | G75: Contractual | H75: Unit | K75: =CFO!L67 -> 23679.975 | M75: =CFO!N67 -> 92387.02 | O75: =CFO!P67 -> 101630.3 | Q75: =CFO!R67 -> 91175.072 | S75: =CFO!T63 -> 0 | T75: =K75+M75+O75+Q75+S75 -> 308872.36 | U75: 0 | V75: =T75+U75 -> 308872.36
A76: MX.1.1.B | B76: 89050 | C76: MEX | D76: MEX | E76: CDM | F76: 1.1.2. Contractual: Sub-award to CDM | G76: Contractual | H76: Unit | K76: =CDM!L65 -> 92985.772 | M76: =CDM!N65 -> 216150.6 | O76: =CDM!P65 -> 219518.16 | Q76: =CDM!R65 -> 224750.36 | S76: =CDM!T65 -> 0 | T76: =K76+M76+O76+Q76+S76 -> 753404.89 | U76: 0 | V76: =T76+U76 -> 753404.89
A77: MX.1.1.C | B77: 89050 | C77: 0 | D77: 0 | E77: SAI | F77: 1.1.3. Contractual: Sub-award to SAI | G77: Contractual | H77: Unit | K77: =SAI!F88 -> 193591.42 | M77: =SAI!H88 -> 295910.51 | O77: =SAI!J88 -> 297364.52 | Q77: =SAI!L88 -> 273401.54 | S77: =SAI!N88 -> 52022.877 | T77: =SUM(K77,M77,O77,Q77,S77) -> 1112290.9 | U77: 0 | V77: =T77+U77 -> 1112290.9
F78: 1.2: Baseline Survey of Key Stakeholder Groups (Pre-Program)
A79: MX.1.2.A | B79: 86000 | C79: MEX | D79: MEX | E79: 0 | F79: Local transportation for project staff to support Baseline Survey | G79: Travel | H79: Day | I79: 30 | J79: 30 | K79: =J79*I79 -> 900 | L79: 20 | M79: =L79*J79 -> 600 | N79: 0 | O79: =N79*K79 -> 0 | P79: 0 | Q79: =P79*J79 -> 0 | R79: 0 | S79: =R79*J79 -> 0 | T79: =Q79+O79+M79+K79+S79 -> 1500 | U79: 0 | V79: =SUM(T79:U79) -> 1500
A80: MX.1.2.B | B80: 81021 | C80: MEX | D80: MEX | E80: 0 | F80: Translation of Baseline Survey | G80: Other | H80: Document | I80: 0 | J80: 2000 | K80: =J80*I80 -> 0 | L80: 1 | M80: =L80*J80 -> 2000 | N80: 0 | O80: =N80*K80 -> 0 | P80: 0 | Q80: =P80*J80 -> 0 | R80: 0 | S80: =R80*J80 -> 0 | T80: =Q80+O80+M80+K80+S80 -> 2000 | U80: 0 | V80: =SUM(T80:U80) -> 2000
A81: MX.1.2.C | B81: 87000 | C81: MEX | D81: MEX | E81: 0 | F81: Workshop to socialize results of Baseline Survey with key stakeholders | G81: Other | H81: Workshop | I81: 1 | J81: 500 | K81: =J81*I81 -> 500 | L81: 2 | M81: =L81*J81 -> 1000 | N81: 0 | O81: =N81*K81 -> 0 | P81: 0 | Q81: =P81*J81 -> 0 | R81: 0 | S81: =R81*J81 -> 0 | T81: =Q81+O81+M81+K81+S81 -> 1500 | U81: 0 | V81: =SUM(T81:U81) -> 1500
F82: 1.3 Development of comprehensive STPS website for multiple audiences
A83: MX.1.3.A | B83: 81000 | C83: MEX | D83: MEX | E83: 0 | F83: Technical assistance to develop comprehensive content for STPS website | G83: Contractual | H83: Deliverable | I83: 0.5 | J83: 30000 | K83: =J83*I83 -> 15000 | L83: 0.5 | M83: =L83*J83 -> 15000 | N83: 0 | O83: =N83*J83 -> 0 | P83: 0 | Q83: =P83*J83 -> 0 | R83: 0 | S83: =R83*J83 -> 0 | T83: =Q83+O83+M83+K83+S83 -> 30000 | U83: 0 | V83: =SUM(T83:U83) -> 30000
A84: MX.1.3.B | B84: 87010 | C84: MEX | D84: MEX | E84: 0 | F84: Meetings with STPS to design content for website | G84: Other | H84: Meetings | I84: 6 | J84: 150 | K84: =J84*I84 -> 900 | L84: 12 | M84: =L84*J84 -> 1800 | N84: 12 | O84: =N84*J84 -> 1800 | P84: 12 | Q84: =P84*J84 -> 1800 | R84: 10 | S84: =R84*J84 -> 1500 | T84: =Q84+O84+M84+K84+S84 -> 7800 | U84: 0 | V84: =SUM(T84:U84) -> 7800
A85: MX.1.3.C | B85: 86000 | C85: MEX | D85: MEX | E85: 0 | F85: Local transportation for project staff to support STPS website development | G85: Travel | H85: Day | I85: 6 | J85: 30 | K85: =J85*I85 -> 180 | L85: 12 | M85: =L85*J85 -> 360 | N85: 12 | O85: =N85*J85 -> 360 | P85: 12 | Q85: =P85*J85 -> 360 | R85: 12 | S85: =R85*J85 -> 360 | T85: =Q85+O85+M85+K85+S85 -> 1620 | U85: 0 | V85: =SUM(T85:U85) -> 1620
F86: 1.4 Mass and social media campaigns for workers and the general populace
A87: MX.1.4.A | B87: 81000 | C87: MEX | D87: MEX | E87: 0 | F87: Consultant: Graphic design for mass and social media campaigns | G87: Contractual | H87: Day | I87: 20 | J87: 280 | K87: =J87*I87 -> 5600 | L87: 60 | M87: =L87*J87 -> 16800 | N87: 60 | O87: =N87*J87 -> 16800 | P87: 60 | Q87: =P87*J87 -> 16800 | R87: 10 | S87: =R87*J87 -> 2800 | T87: =SUM(K87,M87,O87,Q87,S87) -> 58800 | U87: 0 | V87: =SUM(T87:U87) -> 58800
A88: MX.1.4.B | B88: 81000 | C88: MEX | D88: MEX | E88: 0 | F88: Consultant: Video production for mass media campaign | G88: Contractual | H88: Day | I88: 15 | J88: 250 | K88: =J88*I88 -> 3750 | L88: 60 | M88: =L88*J88 -> 15000 | N88: 60 | O88: =N88*J88 -> 15000 | P88: 60 | Q88: =P88*J88 -> 15000 | R88: 10 | S88: =R88*J88 -> 2500 | T88: =SUM(K88,M88,O88,Q88,S88) -> 51250 | U88: 0 | V88: =SUM(T88:U88) -> 51250
A89: MX.1.4.C | B89: 86000 | C89: MEX | D89: MEX | E89: 0 | F89: Local transportation for project staff to support STPS Facebook development | G89: Travel | H89: Day | I89: 6 | J89: 30 | K89: =J89*I89 -> 180 | L89: 12 | M89: =L89*J89 -> 360 | N89: 12 | O89: =N89*J89 -> 360 | P89: 12 | Q89: =P89*J89 -> 360 | R89: 6 | S89: =R89*J89 -> 180 | T89: =SUM(K89,M89,O89,Q89,S89) -> 1440 | U89: 0 | V89: =SUM(T89:U89) -> 1440
A90: MX.1.4.D | B90: 87000 | C90: MEX | D90: MEX | E90: 0 | F90: Capacity-building trainings for social media | G90: Other | H90: Trainings | I90: 0 | J90: 500 | K90: =J90*I90 -> 0 | L90: 10 | M90: =L90*J90 -> 5000 | N90: 10 | O90: =N90*J90 -> 5000 | P90: 10 | Q90: =P90*J90 -> 5000 | R90: 0 | S90: =R90*J90 -> 0 | T90: =SUM(K90,M90,O90,Q90,S90) -> 15000 | U90: 0 | V90: =SUM(T90:U90) -> 15000
A91: MX.1.4.E | B91: 86030 (Lodging)/ 86050 (M&IE) | C91: MEX | D91: MEX | E91: 0 | F91: Lodging and M&IE for project staff to support exchanges with CDM | G91: Travel | H91: Day | I91: 0 | J91: 110 | K91: =J91*I91 -> 0 | L91: 15 | M91: =L91*J91 -> 1650 | N91: 15 | O91: =N91*J91 -> 1650 | P91: 15 | Q91: =P91*J91 -> 1650 | R91: 0 | S91: =R91*J91 -> 0 | T91: =SUM(K91,M91,O91,Q91,S91) -> 4950 | U91: 0 | V91: =SUM(T91:U91) -> 4950
A92: MX.1.4.F | B92: 86000 | C92: MEX | D92: MEX | E92: 0 | F92: Local transportation for project staff to support exchanges with CDM | G92: Travel | H92: Day | I92: 0 | J92: 30 | K92: =J92*I92 -> 0 | L92: 15 | M92: =L92*J92 -> 450 | N92: 15 | O92: =N92*J92 -> 450 | P92: 15 | Q92: =P92*J92 -> 450 | R92: 0 | S92: =R92*J92 -> 0 | T92: =SUM(K92,M92,O92,Q92,S92) -> 1350 | U92: 0 | V92: =SUM(T92:U92) -> 1350
A93: MX.1.4.G | B93: 80402 | C93: MEX | D93: MEX | E93: 0 | F93: Dissemination of radio campaigns | G93: Other | H93: Campaign | I93: 8 | J93: 3000 | K93: =J93*I93 -> 24000 | L93: 13 | M93: =L93*J93 -> 39000 | N93: 11 | O93: =N93*J93 -> 33000 | P93: 15 | Q93: =P93*J93 -> 45000 | R93: 5 | S93: =R93*J93 -> 15000 | T93: =SUM(K93,M93,O93,Q93,S93) -> 156000 | U93: 0 | V93: =SUM(T93:U93) -> 156000
A94: MX.1.4.H | B94: 85300 | C94: MEX | D94: MEX | E94: 0 | F94: Development of comic book for workers | G94: Other | H94: Document | I94: 0 | J94: 10000 | K94: =J94*I94 -> 0 | L94: 1 | M94: =L94*J94 -> 10000 | N94: 1 | O94: =N94*J94 -> 10000 | P94: 1 | Q94: =P94*J94 -> 10000 | R94: 0 | S94: =R94*J94 -> 0 | T94: =SUM(K94,M94,O94,Q94,S94) -> 30000 | U94: 0 | V94: =SUM(T94:U94) -> 30000
A95: MX.1.4.I | B95: 90450 | C95: MEX | D95: MEX | E95: 0 | F95: Dissemination of Know Your Rights posters and cards and other materials | G95: Other | H95: Campaign | I95: 8 | J95: 10000 | K95: =J95*I95 -> 80000 | L95: 13 | M95: =L95*J95 -> 130000 | N95: 11 | O95: =N95*J95 -> 110000 | P95: 15 | Q95: =P95*J95 -> 150000 | R95: 5 | S95: =R95*J95 -> 50000 | T95: =SUM(K95,M95,O95,Q95,S95) -> 520000 | U95: 0 | V95: =SUM(T95:U95) -> 520000
F96: 1.5 Public Forums for the public, workers, and union leaders
A97: MX.1.5.A | B97: 86030 (Lodging)/ 86050 (M&IE) | C97: MEX | D97: MEX | E97: 0 | F97: Lodging and M&IE for speakers of public forums | G97: Travel | H97: Day | I97: 0 | J97: 110 | K97: =I97*J97 -> 0 | L97: =(2*6)*2 -> 24 | M97: =L97*J97 -> 2640 | N97: =(2*6)*2 -> 24 | O97: =N97*J97 -> 2640 | P97: =(2*6)*2 -> 24 | Q97: =P97*J97 -> 2640 | R97: =(2*2)*2 -> 8 | S97: =R97*J97 -> 880 | T97: =SUM(K97,M97,O97,Q97,S97) -> 8800 | U97: 0 | V97: =SUM(T97:U97) -> 8800
A98: MX.1.5.B | B98: 86000 | C98: MEX | D98: MEX | E98: 0 | F98: Transportation for speakers of public forums | G98: Travel | H98: Day | I98: 0 | J98: 30 | K98: =I98*J98 -> 0 | L98: =(2*6)*2 -> 24 | M98: =L98*J98 -> 720 | N98: =(2*6)*2 -> 24 | O98: =N98*J98 -> 720 | P98: =(2*6)*2 -> 24 | Q98: =P98*J98 -> 720 | R98: =(2*2)*2 -> 8 | S98: =R98*J98 -> 240 | T98: =SUM(K98,M98,O98,Q98,S98) -> 2400 | U98: 0 | V98: =SUM(T98:U98) -> 2400
A99: MX.1.5.C | B99: 86030 (Lodging)/ 86050 (M&IE) | C99: MEX | D99: MEX | E99: 0 | F99: Lodging and M&IE for project staff to support public forums | G99: Travel | H99: Day | I99: 0 | J99: 110 | K99: =I99*J99 -> 0 | L99: 20 | M99: =L99*J99 -> 2200 | N99: 20 | O99: =N99*J99 -> 2200 | P99: 20 | Q99: =P99*J99 -> 2200 | R99: 10 | S99: =R99*J99 -> 1100 | T99: =SUM(K99,M99,O99,Q99,S99) -> 7700 | U99: 0 | V99: =SUM(T99:U99) -> 7700
A100: MX.1.5.D | B100: 86000 | C100: MEX | D100: MEX | E100: 0 | F100: Transportation for project staff to support public forums | G100: Travel | H100: Day | I100: 0 | J100: 30 | K100: =I100*J100 -> 0 | L100: 20 | M100: =L100*J100 -> 600 | N100: 20 | O100: =N100*J100 -> 600 | P100: 20 | Q100: =P100*J100 -> 600 | R100: 10 | S100: =R100*J100 -> 300 | T100: =SUM(K100,M100,O100,Q100,S100) -> 2100 | U100: 0 | V100: =SUM(T100:U100) -> 2100
A101: MX.1.5.E | B101: 81000 | C101: MEX | D101: MEX | E101: 0 | F101: Consultant: FESIIAAAN: implementation of 9 forums | G101: Contractual | H101: Lump sum | K101: 3239 | M101: 8533 | O101: 9686 | Q101: 5305 | S101: 0 | T101: =SUM(K101,M101,O101,Q101,S101) -> 26763 | U101: 0 | V101: =SUM(T101:U101) -> 26763
A102: MX.1.5.F | B102: 81000 | C102: MEX | D102: MEX | E102: 0 | F102: Consultant: FAT: implementation of 21 public forums | G102: Contractual | H102: Lump sum | K102: 14586 | M102: 39981 | O102: 39981 | Q102: 39981 | S102: 0 | T102: =SUM(K102,M102,O102,Q102,S102) -> 134529 | U102: 0 | V102: =SUM(T102:U102) -> 134529
F103: 1.6 Educational Workshops for Workers and Union Leaders
A104: MX.1.6.A | B104: 90450 | C104: MEX | D104: MEX | E104: 0 | F104: Outreach campaigns for existing workshops | G104: Other | H104: Campaign | I104: 1 | J104: 2000 | K104: =J104*I104 -> 2000 | L104: 6 | M104: =L104*J104 -> 12000 | N104: 6 | O104: =N104*J104 -> 12000 | P104: 6 | Q104: =P104*J104 -> 12000 | R104: 2 | S104: =R104*J104 -> 4000 | T104: =SUM(K104,M104,O104,Q104,S104) -> 42000 | U104: 0 | V104: =SUM(T104:U104) -> 42000
A105: MX.1.6.B | B105: 81000 | C105: MEX | D105: MEX | E105: 0 | F105: Consultant: Development of tailored modules and teaching materials for workshops | G105: Contractual | H105: Day | I105: 0 | J105: 175 | K105: =J105*I105 -> 0 | L105: 30 | M105: =L105*J105 -> 5250 | N105: 30 | O105: =N105*J105 -> 5250 | P105: 20 | Q105: =P105*J105 -> 3500 | R105: 0 | S105: =R105*J105 -> 0 | T105: =SUM(K105,M105,O105,Q105,S105) -> 14000 | U105: 0 | V105: =SUM(T105:U105) -> 14000
A106: MX.1.6.C | B106: 81000 | C106: MEX | D106: MEX | E106: 0 | F106: Consultant: Assessment and development of confederation education programs | G106: Contractual | H106: Day | I106: 0 | J106: 175 | K106: =J106*I106 -> 0 | L106: 30 | M106: =L106*J106 -> 5250 | N106: 30 | O106: =N106*J106 -> 5250 | P106: 20 | Q106: =P106*J106 -> 3500 | R106: 0 | S106: =R106*J106 -> 0 | T106: =SUM(K106,M106,O106,Q106,S106) -> 14000 | U106: 0 | V106: =SUM(T106:U106) -> 14000
A107: MX.1.6.D | B107: 81021 | C107: MEX | D107: MEX | E107: 0 | F107: Translation of outreach materials to native languages | G107: Other | H107: Unit | I107: 0 | J107: 2000 | K107: =J107*I107 -> 0 | L107: 8 | M107: =L107*J107 -> 16000 | N107: 2 | O107: =N107*J107 -> 4000 | P107: 0 | Q107: =P107*J107 -> 0 | R107: 0 | S107: =R107*J107 -> 0 | T107: =SUM(K107,M107,O107,Q107,S107) -> 20000 | U107: 0 | V107: =SUM(T107:U107) -> 20000
F108: 1.7 Trainings for union leadership
...

Sheet CFO
A1: Entity: | B1: P | G1: Name of Project: Mexico Awareness Raising Project
A2: Program-Dept.: | B2: CCL | G2: Name of Subawardee: Comité Fronterizo de Obreros (CFO)
A3: Funder-Grant: | B3: DOL423 | G3: Subaward Budget
G4: Budget Assumptions:
G5: Inflation - Locally Purchased Goods/Services | H5: 1.05
G6: Merit Based Increases for Field Staff | H6: 1.035
A7: Sage Activity | B7: Sage Object Code/ Line Item | C7: Country Code (DC=0 or MX) | D7: Office Code (DC=0 or MX) | E7: Subcontract Code | F7: Open1 Code | G7: BUDGET ITEM | H7: CATEGORY | I7: UNIT | J7: # of Units | K7: RATE/ UNIT | L7: YEAR 1 | M7: # of Units | N7: YEAR 2 | O7: # of Units | P7: YEAR 3 | Q7: # of Units | R7: YEAR 4 | S7: # of Units | T7: YEAR 5 | U7: TOTAL CFO | V7: TOTAL COST SHARING | W7: PROJECT GRAND TOTAL | X7: Percentage 95% to Outcome 1 | Y7: Percentage 5% to Outcome 3
G8: Direct Labor
G9: Personnel
A10: MX.1.1.A (Outcome 1)/ MX.3.7.A (M&E) | B10: 89050 | C10: MX | D10: MX | E10: CFO | F10: CFOPERSLLC | G10: Lead Coordinator for the Project (50%) | H10: Salaries | I10: Month | J10: 3 | K10: 1200 | L10: =J10*K10 -> 3600 | M10: 12 | N10: =M10*K10*$H$6 -> 14904 | O10: 12 | P10: =O10*K10*$H$6*$H$6 -> 15425.64 | Q10: 12 | R10: =Q10*K10*$H$6*$H$6*$H$6 -> 15965.537 | S10: 0 | T10: =S10*K10*$H$6*$H$6*$H$6*$H$6 -> 0 | U10: =SUM(L10+N10+P10+R10+T10) -> 49895.177 | V10: 0 | W10: =SUM(U10:V10) -> 49895.177 | X10: =W10*0.95 -> 47400.419 | Y10: =W10-X10 -> 2494.7589
A11: MX.1.1.A (Outcome 1)/ MX.3.7.A (M&E) | B11: 89050 | C11: MX | D11: MX | E11: CFO | F11: CFOPERSLGC | G11: Gender Coordinator (50%) | H11: Salaries | I11: Month | J11: 3 | K11: 800 | L11: =J11*K11 -> 2400 | M11: 12 | N11: =M11*K11*$H$6 -> 9936 | O11: 12 | P11: =O11*K11*$H$6*$H$6 -> 10283.76 | Q11: 12 | R11: =Q11*K11*$H$6*$H$6*$H$6 -> 10643.692 | S11: 0 | T11: =S11*K11*$H$6*$H$6*$H$6*$H$6 -> 0 | U11: =SUM(L11+N11+P11+R11+T11) -> 33263.452 | V11: 0 | W11: =SUM(U11:V11) -> 33263.452 | X11: =W11*0.95 -> 31600.279 | Y11: =W11-X11 -> 1663.1726
A12: MX.1.1.A (Outcome 1)/ MX.3.7.A (M&E) | B12: 89050 | C12: MX | D12: MX | E12: CFO | F12: CFOPERSLAA | G12: Administrative Assistant (50%) | H12: Salaries | I12: Month | J12: 3 | K12: 400 | L12: =J12*K12 -> 1200 | M12: 12 | N12: =M12*K12*$H$6 -> 4968 | O12: 12 | P12: =O12*K12*$H$6*$H$6 -> 5141.88 | Q12: 12 | R12: =Q12*K12*$H$6*$H$6*$H$6 -> 5321.8458 | S12: 0 | T12: =S12*K12*$H$6*$H$6*$H$6*$H$6 -> 0 | U12: =SUM(L12+N12+P12+R12+T12) -> 16631.726 | V12: 0 | W12: =SUM(U12:V12) -> 16631.726 | X12: =W12*0.95 -> 15800.14 | Y12: =W12-X12 -> 831.58629
A13: MX.1.1.A (Outcome 1)/ MX.3.7.A (M&E) | B13: 89050 | C13: MX | D13: MX | E13: CFO | F13: CFOPERSLP1 | G13: Promoter 1 (100%) | H13: Salaries | I13: Month | J13: 3 | K13: 200 | L13: =J13*K13 -> 600 | M13: 12 | N13: =M13*K13*$H$6 -> 2484 | O13: 12 | P13: =O13*K13*$H$6*$H$6 -> 2570.94 | Q13: 12 | R13: =Q13*K13*$H$6*$H$6*$H$6 -> 2660.9229 | S13: 0 | T13: =S13*K13*$H$6*$H$6*$H$6*$H$6 -> 0 | U13: =SUM(L13+N13+P13+R13+T13) -> 8315.8629 | V13: 0 | W13: =SUM(U13:V13) -> 8315.8629 | X13: =W13*0.95 -> 7900.0698 | Y13: =W13-X13 -> 415.79315
A14: MX.1.1.A (Outcome 1)/ MX.3.7.A (M&E) | B14: 89050 | C14: MX | D14: MX | E14: CFO | F14: CFOPERSLP2 | G14: Promoter 2 (100%) | H14: Salaries | I14: Month | J14: 3 | K14: 200 | L14: =J14*K14 -> 600 | M14: 12 | N14: =M14*K14*$H$6 -> 2484 | O14: 12 | P14: =O14*K14*$H$6*$H$6 -> 2570.94 | Q14: 12 | R14: =Q14*K14*$H$6*$H$6*$H$6 -> 2660.9229 | S14: 0 | T14: =S14*K14*$H$6*$H$6*$H$6*$H$6 -> 0 | U14: =SUM(L14+N14+P14+R14+T14) -> 8315.8629 | V14: 0 | W14: =SUM(U14:V14) -> 8315.8629 | X14: =W14*0.95 -> 7900.0698 | Y14: =W14-X14 -> 415.79315
A15: MX.1.1.A (Outcome 1)/ MX.3.7.A (M&E) | B15: 89050 | C15: MX | D15: MX | E15: CFO | F15: CFOPERSLP3 | G15: Promoter 3 (100%) | H15: Salaries | I15: Month | J15: 3 | K15: 200 | L15: =J15*K15 -> 600 | M15: 12 | N15: =M15*K15*$H$6 -> 2484 | O15: 12 | P15: =O15*K15*$H$6*$H$6 -> 2570.94 | Q15: 12 | R15: =Q15*K15*$H$6*$H$6*$H$6 -> 2660.9229 | S15: 0 | T15: =S15*K15*$H$6*$H$6*$H$6*$H$6 -> 0 | U15: =SUM(L15+N15+P15+R15+T15) -> 8315.8629 | V15: 0 | W15: =SUM(U15:V15) -> 8315.8629 | X15: =W15*0.95 -> 7900.0698 | Y15: =W15-X15 -> 415.79315
G17: Subtotal | L17: =SUM(L10:L15) -> 9000 | N17: =SUM(N10:N15) -> 37260 | P17: =SUM(P10:P15) -> 38564.1 | R17: =SUM(R10:R15) -> 39913.843 | T17: =SUM(T10:T15) -> 0 | U17: =SUM(L17+N17+P17+R17+T17) -> 124737.94 | V17: =SUM(V10:V15) -> 0 | W17: =SUM(U17:V17) -> 124737.94
G19: Fringe Benefits
A20: MX.1.1.A (Outcome 1)/ MX.3.7.A (M&E) | B20: 89050 | C20: MX | D20: MX | E20: CFO | F20: CFOFRINGE | G20: Fringe benefits | H20: Fringe benefits | K20: 0.5 | L20: =K20*L17 -> 4500 | N20: =K20*N17 -> 18630 | P20: =K20*P17 -> 19282.05 | R20: =R17*K20 -> 19956.922 | T20: =K20*T17 -> 0 | U20: =SUM(T20,R20,P20,N20,L20) -> 62368.972 | V20: 0 | W20: =SUM(U20:V20) -> 62368.972 | X20: =W20*0.95 -> 59250.523 | Y20: =W20-X20 -> 3118.4486
G22: Subtotal Direct Labor | L22: =SUM(L17:L20) -> 13500 | N22: =SUM(N17:N20) -> 55890 | P22: =SUM(P17:P20) -> 57846.15 | R22: =SUM(R17:R20) -> 59870.765 | T22: =SUM(T17:T20) -> 0 | U22: =L22+N22+P22+R22+T22 -> 187106.92 | V22: =SUM(V9:V20) -> 0 | W22: =SUM(U22:V22) -> 187106.92
G24: Travel
G25: T1. Meetings with POA in Mexico City
A26: MX.1.1.A (Outcome 1)/ MX.3.7.A (M&E) | B26: 89050 | C26: MX | D26: MX | E26: CFO | F26: CFOT1AIR | G26: Project Staff - Airfare | H26: Travel | I26: Trip | J26: 1 | K26: 375 | L26: =J26*K26 -> 375 | M26: 2 | N26: =M26*K26*$H$5 -> 787.5 | O26: 2 | P26: =O26*K26*$H$5*$H$5 -> 826.875 | Q26: 2 | R26: =Q26*K26*$H$5*$H$5*$H$5 -> 868.21875 | S26: 0 | T26: =S26*K26*$H$5*$H$5*$H$5*$H$5 -> 0 | U26: =L26+N26+P26+R26+T26 -> 2857.5938 | V26: - | W26: =SUM(U26:V26) -> 2857.5938 | X26: =W26*0.95 -> 2714.7141 | Y26: =W26-X26 -> 142.87969
A27: MX.1.1.A (Outcome 1)/ MX.3.7.A (M&E) | B27: 89050 | C27: MX | D27: MX | E27: CFO | F27: CFOT1LODME | G27: Project Staff - Lodging and M&IE | H27: Travel | I27: Day | J27: 7 | K27: 110 | L27: =J27*K27 -> 770 | M27: 14 | N27: =M27*K27*$H$5 -> 1617 | O27: 14 | P27: =O27*K27*$H$5*$H$5 -> 1697.85 | Q27: 14 | R27: =Q27*K27*$H$5*$H$5*$H$5 -> 1782.7425 | S27: 0 | T27: =S27*K27*$H$5*$H$5*$H$5*$H$5 -> 0 | U27: =L27+N27+P27+R27+T27 -> 5867.5925 | V27: - | W27: =SUM(U27:V27) -> 5867.5925 | X27: =W27*0.95 -> 5574.2129 | Y27: =W27-X27 -> 293.37963
A28: MX.1.1.A (Outcome 1)/ MX.3.7.A (M&E) | B28: 89050 | C28: MX | D28: MX | E28: CFO | F28: CFOT1TRANS | G28: Project Staff - Ground Transportation | H28: Travel | I28: Day | J28: 7 | K28: 25 | L28: =J28*K28 -> 175 | M28: 14 | N28: =M28*K28*$H$5 -> 367.5 | O28: 14 | P28: =O28*K28*$H$5*$H$5 -> 385.875 | Q28: 14 | R28: =Q28*K28*$H$5*$H$5*$H$5 -> 405.16875 | S28: 0 | T28: =S28*K28*$H$5*$H$5*$H$5*$H$5 -> 0 | U28: =L28+N28+P28+R28+T28 -> 1333.5438 | V28: - | W28: =SUM(U28:V28) -> 1333.5438 | X28: =W28*0.95 -> 1266.8666 | Y28: =W28-X28 -> 66.677188
G30: Subtotal Travel | L30: =SUM(L26:L28) -> 1320 | N30: =SUM(N26:N28) -> 2772 | P30: =SUM(P26:P28) -> 2910.6 | R30: =SUM(R26:R28) -> 3056.13 | T30: =SUM(T26:T28) -> 0 | U30: =L30+N30+P30+R30+T30 -> 10058.73 | V30: =SUM(V26:V28) -> 0 | W30: =SUM(U30:V30) -> 10058.73
G31: Supplies
A32: MX.1.1.A (Outcome 1)/ MX.3.7.A (M&E) | B32: 89050 | C32: MX | D32: MX | E32: CFO | F32: CFOLAPTOP | G32: Laptops and software | H32: Supplies | I32: Unit | J32: 4 | K32: 650 | L32: =J32*K32 -> 2600 | M32: 0 | N32: =M32*K32*$H$5 -> 0 | O32: 0 | P32: =O32*K32*$H$5*$H$5 -> 0 | Q32: 0 | R32: =Q32*K32*$H$5*$H$5*$H$5 -> 0 | S32: 0 | T32: =S32*K32*$H$5*$H$5*$H$5*$H$5 -> 0 | U32: =L32+N32+P32+R32+T32 -> 2600 | V32: 0 | W32: =SUM(U32:V32) -> 2600 | X32: =W32*0.95 -> 2470 | Y32: =W32-X32 -> 130
A33: MX.1.1.A (Outcome 1)/ MX.3.7.A (M&E) | B33: 89050 | C33: MX | D33: MX | E33: CFO | F33: CFOPHONE | G33: Cellphone | H33: Supplies | I33: Unit | J33: 2 | K33: 600 | L33: =J33*K33 -> 1200 | M33: 0 | N33: =M33*K33*$H$5 -> 0 | O33: 0 | P33: =O33*K33*$H$5*$H$5 -> 0 | Q33: 0 | R33: =Q33*K33*$H$5*$H$5*$H$5 -> 0 | S33: 0 | T33: =S33*K33*$H$5*$H$5*$H$5*$H$5 -> 0 | U33: =L33+N33+P33+R33+T33 -> 1200 | V33: 0 | W33: =SUM(U33:V33) -> 1200 | X33: =W33*0.95 -> 1140 | Y33: =W33-X33 -> 60
A34: MX.1.1.A (Outcome 1)/ MX.3.7.A (M&E) | B34: 89050 | C34: MX | D34: MX | E34: CFO | F34: CFOPRINT | G34: Printer and copier | H34: Supplies | I34: Unit | J34: 1 | K34: 300 | L34: =J34*K34 -> 300 | M34: 0 | N34: =M34*K34*$H$5 -> 0 | O34: 0 | P34: =O34*K34*$H$5*$H$5 -> 0 | Q34: 0 | R34: =Q34*K34*$H$5*$H$5*$H$5 -> 0 | S34: 0 | T34: =S34*K34*$H$5*$H$5*$H$5*$H$5 -> 0 | U34: =L34+N34+P34+R34+T34 -> 300 | V34: 0 | W34: =SUM(U34:V34) -> 300 | X34: =W34*0.95 -> 285 | Y34: =W34-X34 -> 15
G36: Subtotal Supplies | L36: =SUM(L32:L34) -> 4100 | N36: =SUM(N32:N34) -> 0 | P36: =SUM(P32:P34) -> 0 | R36: =SUM(R32:R34) -> 0 | T36: =SUM(T32:T34) -> 0 | U36: =L36+N36+P36+R36+T36 -> 4100 | V36: =SUM(V32:V34) -> 0 | W36: =SUM(U36:V36) -> 4100
G37: Office Expenses
A38: MX.1.1.A (Outcome 1)/ MX.3.7.A (M&E) | B38: 89050 | C38: MX | D38: MX | E38: CFO | F38: CFOBANKFEE | G38: Banking and cash handling fees | H38: Office Expenses | I38: Month | J38: 1 | K38: 30 | L38: =J38*K38 -> 30 | M38: 12 | N38: =M38*K38*$H$5 -> 378 | O38: 12 | P38: =O38*K38*$H$5*$H$5 -> 396.9 | Q38: 12 | R38: =Q38*K38*$H$5*$H$5*$H$5 -> 416.745 | S38: 0 | T38: =S38*K38*$H$5*$H$5*$H$5*$H$5 -> 0 | U38: =L38+N38+P38+R38+T38 -> 1221.645 | V38: 0 | W38: =SUM(U38:V38) -> 1221.645 | X38: =W38*0.95 -> 1160.5628 | Y38: =W38-X38 -> 61.08225
A39: MX.1.1.A (Outcome 1)/ MX.3.7.A (M&E) | B39: 89050 | C39: MX | D39: MX | E39: CFO | F39: CFOPOSTAGE | G39: Courier fees/services/postage | H39: Office Expenses | I39: Year | J39: 0 | K39: 50 | L39: =J39*K39 -> 0 | M39: 1 | N39: =M39*K39*$H$5 -> 52.5 | O39: 1 | P39: =O39*K39*$H$5*$H$5 -> 55.125 | Q39: 1 | R39: =Q39*K39*$H$5*$H$5*$H$5 -> 57.88125 | S39: 0 | T39: =S39*K39*$H$5*$H$5*$H$5*$H$5 -> 0 | U39: =L39+N39+P39+R39+T39 -> 165.50625 | V39: 0 | W39: =SUM(U39:V39) -> 165.50625 | X39: =W39*0.95 -> 157.23094 | Y39: =W39-X39 -> 8.2753125
A40: MX.1.1.A (Outcome 1)/ MX.3.7.A (M&E) | B40: 89050 | C40: MX | D40: MX | E40: CFO | F40: CFOEMAIL | G40: Email/Internet | H40: Office Expenses | I40: Month | J40: 3 | K40: 40 | L40: =J40*K40 -> 120 | M40: 12 | N40: =M40*K40*$H$5 -> 504 | O40: 12 | P40: =O40*K40*$H$5*$H$5 -> 529.2 | Q40: 12 | R40: =Q40*K40*$H$5*$H$5*$H$5 -> 555.66 | S40: 0 | T40: =S40*K40*$H$5*$H$5*$H$5*$H$5 -> 0 | U40: =L40+N40+P40+R40+T40 -> 1708.86 | V40: 0 | W40: =SUM(U40:V40) -> 1708.86 | X40: =W40*0.95 -> 1623.417 | Y40: =W40-X40 -> 85.443
A41: MX.1.1.A (Outcome 1)/ MX.3.7.A (M&E) | B41: 89050 | C41: MX | D41: MX | E41: CFO | F41: CFORENT | G41: Office Rent | H41: Office Expenses | I41: Month | J41: 3 | K41: 435 | L41: =J41*K41 -> 1305 | M41: 12 | N41: =M41*K41*$H$5 -> 5481 | O41: 12 | P41: =O41*K41*$H$5*$H$5 -> 5755.05 | Q41: 12 | R41: =Q41*K41*$H$5*$H$5*$H$5 -> 6042.8025 | S41: 0 | T41: =S41*K41*$H$5*$H$5*$H$5*$H$5 -> 0 | U41: =L41+N41+P41+R41+T41 -> 18583.853 | V41: 0 | W41: =SUM(U41:V41) -> 18583.853 | X41: =W41*0.95 -> 17654.66 | Y41: =W41-X41 -> 929.19262
A42: MX.1.1.A (Outcome 1)/ MX.3.7.A (M&E) | B42: 89050 | C42: MX | D42: MX | E42: CFO | F42: CFOUTILITY | G42: Office Utilities | H42: Office Expenses | I42: Month | J42: 3 | K42: 60 | L42: =J42*K42 -> 180 | M42: 12 | N42: =M42*K42*$H$5 -> 756 | O42: 12 | P42: =O42*K42*$H$5*$H$5 -> 793.8 | Q42: 12 | R42: =Q42*K42*$H$5*$H$5*$H$5 -> 833.49 | S42: 0 | T42: =S42*K42*$H$5*$H$5*$H$5*$H$5 -> 0 | U42: =L42+N42+P42+R42+T42 -> 2563.29 | V42: 0 | W42: =SUM(U42:V42) -> 2563.29 | X42: =W42*0.95 -> 2435.1255 | Y42: =W42-X42 -> 128.1645
A43: MX.1.1.A (Outcome 1)/ MX.3.7.A (M&E) | B43: 89050 | C43: MX | D43: MX | E43: CFO | F43: CFOMAINT | G43: Equipment and office repairs and maintenance | H43: Office Expenses | I43: Year | J43: 0 | K43: 250 | L43: =J43*K43 -> 0 | M43: 1 | N43: =M43*K43*$H$5 -> 262.5 | O43: 1 | P43: =O43*K43*$H$5*$H$5 -> 275.625 | Q43: 1 | R43: =Q43*K43*$H$5*$H$5*$H$5 -> 289.40625 | S43: 0 | T43: =S43*K43*$H$5*$H$5*$H$5*$H$5 -> 0 | U43: =L43+N43+P43+R43+T43 -> 827.53125 | V43: 0 | W43: =SUM(U43:V43) -> 827.53125 | X43: =W43*0.95 -> 786.15469 | Y43: =W43-X43 -> 41.376563
A44: MX.1.1.A (Outcome 1)/ MX.3.7.A (M&E) | B44: 89050 | C44: MX | D44: MX | E44: CFO | F44: CFOTRANS | G44: Translation Costs | H44: Office Expenses | I44: Month | J44: 0 | K44: 100 | L44: =J44*K44 -> 0 | M44: 12 | N44: =M44*K44*$H$5 -> 1260 | O44: 12 | P44: =O44*K44*$H$5*$H$5 -> 1323 | Q44: 12 | R44: =Q44*K44*$H$5*$H$5*$H$5 -> 1389.15 | S44: 0 | T44: =S44*K44*$H$5*$H$5*$H$5*$H$5 -> 0 | U44: =L44+N44+P44+R44+T44 -> 3972.15 | V44: 0 | W44: =SUM(U44:V44) -> 3972.15 | X44: =W44*0.95 -> 3773.5425 | Y44: =W44-X44 -> 198.6075
G46: Subtotal Office Expenses | L46: =SUM(L38:L44) -> 1635 | N46: =SUM(N38:N44) -> 8694 | P46: =SUM(P38:P44) -> 9128.7 | R46: =SUM(R38:R44) -> 9585.135 | T46: =SUM(T38:T44) -> 0 | U46: =L46+N46+P46+R46+T46 -> 29042.835 | V46: =SUM(V38:V44) -> 0 | W46: =SUM(U46:V46) -> 29042.835
G47: The above is only for percentage calculations for the below outcomes
G48: Outcome 1: Increase understanding by workers, employers, and union leaders on how to utilize Mexico’s new labor systems to protect labor rights and effectively address labor disputes.
G49: Activities/Costs
A50: See above | G50: Personnel & Fringe (95% of Direct Labor line item) | H50: Outcome1 | I50: Unit | J50: =$L$22 -> 13500 | K50: 0.95 | L50: =J50*K50 -> 12825 | M50: =$N$22 -> 55890 | N50: =M50*K50 -> 53095.5 | O50: =$P$22 -> 57846.15 | P50: =O50*K50 -> 54953.842 | Q50: =$R$22 -> 59870.765 | R50: =Q50*K50 -> 56877.227 | S50: =$T$22 -> 0 | T50: =S50*K50 -> 0 | U50: =L50+N50+P50+R50+T50 -> 177751.57 | V50: 0 | W50: =SUM(U50:V50) -> 177751.57
A51: See above | G51: Travel 95% | H51: Outcome1 | I51: Unit | J51: =$L$30 -> 1320 | K51: 0.95 | L51: =J51*K51 -> 1254 | M51: =$N$30 -> 2772 | N51: =M51*K51 -> 2633.4 | O51: =$P$30 -> 2910.6 | P51: =O51*K51 -> 2765.07 | Q51: =$R$30 -> 3056.13 | R51: =Q51*K51 -> 2903.3235 | S51: =$T$30 -> 0 | T51: =S51*K51 -> 0 | U51: =L51+N51+P51+R51+T51 -> 9555.7935 | V51: 0 | W51: =SUM(U51:V51) -> 9555.7935
A52: See above | G52: Supplies 95% | H52: Outcome1 | I52: Unit | J52: =$L$36 -> 4100 | K52: 0.95 | L52: =J52*K52 -> 3895 | M52: =$N$36 -> 0 | N52: =M52*K52 -> 0 | O52: =$P$36 -> 0 | P52: =O52*K52 -> 0 | Q52: =$R$36 -> 0 | R52: =Q52*K52 -> 0 | S52: =$T$36 -> 0 | T52: =S52*K52 -> 0 | U52: =L52+N52+P52+R52+T52 -> 3895 | V52: 0 | W52: =SUM(U52:V52) -> 3895
A53: See above | G53: Office Expenses 95% | H53: Outcome1 | I53: Unit | J53: =$L$46 -> 1635 | K53: 0.95 | L53: =J53*K53 -> 1553.25 | M53: =$N$46 -> 8694 | N53: =M53*K53 -> 8259.3 | O53: =$P$46 -> 9128.7 | P53: =O53*K53 -> 8672.265 | Q53: =$R$46 -> 9585.135 | R53: =Q53*K53 -> 9105.8782 | S53: =$T$46 -> 0 | T53: =S53*K53 -> 0 | U53: =L53+N53+P53+R53+T53 -> 27590.693 | V53: 0 | W53: =SUM(U53:V53) -> 27590.693
G54: 1.1.1.1 Educational Workshops for Workers and Union Leaders
A55: MX.1.1.A | B55: 89050 | C55: MX | D55: MX | E55: CFO | F55: CFOGBVPROG | G55: Assessment and inclusion of gender-based violence at work within educational programs | H55: Outcome1 | I55: Unit | J55: 1 | K55: 2000 | L55: =K55*J55 -> 2000 | M55: 1 | N55: =M55*K55 -> 2000 | O55: 1 | P55: =O55*K55 -> 2000 | Q55: 0 | R55: =Q55*K55 -> 0 | S55: 0 | T55: =S55*K55 -> 0 | U55: =SUM(L55,N55,P55,R55,T55) -> 6000 | V55: 0 | W55: =SUM(U55:V55) -> 6000
A56: MX.1.1.A | B56: 89050 | C56: MX | D56: MX | E56: CFO | F56: CFOGEMA | G56: Extension of GEMA to two additional states | H56: Outcome1 | I56: Program | J56: 0 | K56: 10000 | L56: =K56*J56 -> 0 | M56: 1 | N56: =M56*K56 -> 10000 | O56: 1 | P56: =O56*K56 -> 10000 | Q56: 0 | R56: =Q56*K56 -> 0 | S56: 0 | T56: =S56*K56 -> 0 | U56: =SUM(L56,N56,P56,R56,T56) -> 20000 | V56: 0 | W56: =SUM(U56:V56) -> 20000
A57: MX.1.1.A | B57: 89050 | C57: MX | D57: MX | E57: CFO | F57: CFOGEMALOD | G57: Lodging and M&IE for project staff to support GEMA extension | H57: Outcome1 | I57: Day | J57: 0 | K57: 110 | L57: =K57*J57 -> 0 | M57: 50 | N57: =M57*K57 -> 5500 | O57: 50 | P57: =O57*K57 -> 5500 | Q57: 50 | R57: =Q57*K57 -> 5500 | S57: 0 | T57: =S57*K57 -> 0 | U57: =SUM(L57,N57,P57,R57,T57) -> 16500 | V57: 0 | W57: =SUM(U57:V57) -> 16500
A58: MX.1.1.A | B58: 89050 | C58: MX | D58: MX | E58: CFO | F58: CFOGEMATRN | G58: Transportation for project staff to support GEMA extension | H58: Outcome1 | I58: Day | J58: 0 | K58: 50 | L58: =K58*J58 -> 0 | M58: 50 | N58: =M58*K58 -> 2500 | O58: 50 | P58: =O58*K58 -> 2500 | Q58: 50 | R58: =Q58*K58 -> 2500 | S58: 0 | T58: =S58*K58 -> 0 | U58: =SUM(L58,N58,P58,R58,T58) -> 7500 | V58: 0 | W58: =SUM(U58:V58) -> 7500
G59: 1.1.1.2 Exchanges on Best Practices for FOA and Gender
A60: MX.1.1.A | B60: 89050 | C60: MX | D60: MX | E60: CFO | F60: CFOEXTRANS | G60: Local transportation for project staff to support exchanges | H60: Outcome1 | I60: Day | J60: 0 | K60: 50 | L60: =J60*K60 -> 0 | M60: 0 | N60: =M60*K60 -> 0 | O60: 30 | P60: =O60*K60 -> 1500 | Q60: 30 | R60: =Q60*K60 -> 1500 | S60: 0 | T60: =S60*K60 -> 0 | U60: =L60+N60+P60+R60+T60 -> 3000 | V60: 0 | W60: =SUM(U60:V60) -> 3000
A61: MX.1.1.A | B61: 89050 | C61: MX | D61: MX | E61: CFO | F61: CFOEXMATL | G61: Material design and printing for exchanges | H61: Outcome1 | I61: Unit | J61: 0 | K61: 300 | L61: =J61*K61 -> 0 | M61: 0 | N61: =M61*K61 -> 0 | O61: 15 | P61: =O61*K61 -> 4500 | Q61: 15 | R61: =Q61*K61 -> 4500 | S61: 0 | T61: =S61*K61 -> 0 | U61: =L61+N61+P61+R61+T61 -> 9000 | V61: 0 | W61: =SUM(U61:V61) -> 9000
G63: Direct Costs Total for Outcome 1 | L63: =SUM(L50:L61) -> 21527.25 | N63: =SUM(N50:N61) -> 83988.2 | P63: =SUM(P50:P61) -> 92391.177 | R63: =SUM(R50:R61) -> 82886.429 | T63: =SUM(T50:T61) -> 0 | U63: =L63+N63+P63+R63+T63 -> 280793.06 | V63: =SUM(V50:V61) -> 0 | W63: =SUM(U63:V63) -> 280793.06
A65: MX.1.1.A | B65: 89050 | C65: MX | D65: MX | E65: CFO | F65: CFOIDCCOST | G65: Total Indirect Costs (De Minimis 10%) for Outcome 1 | H65: Indirect Charges | K65: 0.1 | L65: =(L63)*K65 -> 2152.725 | N65: =(N63)*K65 -> 8398.82 | P65: =(P63)*K65 -> 9239.1177 | R65: =(R63)*K65 -> 8288.6429 | T65: =(T63)*K65 -> 0 | U65: =SUM(L65+N65+P65+R65+T65) -> 28079.306 | V65: 0 | W65: =SUM(U65:V65) -> 28079.306
G67: Subtotal Outcome 1 | L67: =SUM(L63:L65) -> 23679.975 | N67: =SUM(N63:N65) -> 92387.02 | P67: =SUM(P63:P65) -> 101630.3 | R67: =SUM(R63:R65) -> 91175.072 | T67: =SUM(T63:T65) -> 0 | U67: =L67+N67+P67+R67+T67 -> 308872.36 | V67: =V65 -> 0 | W67: =SUM(U67:V67) -> 308872.36
G68: 3: Monitoring, Evaluation, and Collection of Reliable Data
G69: Activities/Costs
A70: See above | G70: Personnel & Fringe (5% of Direct Labor line item) | H70: M&E | I70: Unit | J70: =$L$22 -> 13500 | K70: 0.05 | L70: =J70*K70 -> 675 | M70: =$N$22 -> 55890 | N70: =M70*K70 -> 2794.5 | O70: =$P$22 -> 57846.15 | P70: =O70*K70 -> 2892.3075 | Q70: =$R$22 -> 59870.765 | R70: =Q70*K70 -> 2993.5383 | S70: =$T$22 -> 0 | T70: =S70*K70 -> 0 | U70: =L70+N70+P70+R70+T70 -> 9355.3458 | V70: 0 | W70: =SUM(U70:V70) -> 9355.3458
A71: See above | G71: Travel 5% | H71: M&E | I71: Unit | J71: =$L$30 -> 1320 | K71: 0.05 | L71: =J71*K71 -> 66 | M71: =$N$30 -> 2772 | N71: =M71*K71 -> 138.6 | O71: =$P$30 -> 2910.6 | P71: =O71*K71 -> 145.53 | Q71: =$R$30 -> 3056.13 | R71: =Q71*K71 -> 152.8065 | S71: =$T$30 -> 0 | T71: =S71*K71 -> 0 | U71: =L71+N71+P71+R71+T71 -> 502.9365 | V71: 0 | W71: =SUM(U71:V71) -> 502.9365
A72: See above | G72: Supplies 5% | H72: M&E | I72: Unit | J72: =$L$36 -> 4100 | K72: 0.05 | L72: =J72*K72 -> 205 | M72: =$N$36 -> 0 | N72: =M72*K72 -> 0 | O72: =$P$36 -> 0 | P72: =O72*K72 -> 0 | Q72: =$R$36 -> 0 | R72: =Q72*K72 -> 0 | S72: =$T$36 -> 0 | T72: =S72*K72 -> 0 | U72: =L72+N72+P72+R72+T72 -> 205 | V72: 0 | W72: =SUM(U72:V72) -> 205
A73: See above | G73: Office Expenses 5% | H73: M&E | I73: Unit | J73: =$L$46 -> 1635 | K73: 0.05 | L73: =J73*K73 -> 81.75 | M73: =$N$46 -> 8694 | N73: =M73*K73 -> 434.7 | O73: =$P$46 -> 9128.7 | P73: =O73*K73 -> 456.435 | Q73: =$R$46 -> 9585.135 | R73: =Q73*K73 -> 479.25675 | S73: =$T$46 -> 0 | T73: =S73*K73 -> 0 | U73: =L73+N73+P73+R73+T73 -> 1452.1418 | V73: 0 | W73: =SUM(U73:V73) -> 1452.1418
G74: 3.7.1.1 Collection of Reliable Data and Processing of Monitoring Data
A75: MX.3.7.A | B75: 89050 | C75: MX | D75: MX | E75: CFO | F75: CFOM&ELOD | G75: Lodging and M&IE - Field verification and data collection visits | H75: M&E | I75: Unit | J75: 6 | K75: 110 | L75: =J75*K75 -> 660 | M75: 15 | N75: =M75*K75 -> 1650 | O75: 10 | P75: =O75*K75 -> 1100 | Q75: 10 | R75: =Q75*K75 -> 1100 | S75: 0 | T75: =S75*K75 -> 0 | U75: =L75+N75+P75+R75+T75 -> 4510 | V75: 0 | W75: =SUM(U75:V75) -> 4510
A76: MX.3.7.A | B76: 89050 | C76: MX | D76: MX | E76: CFO | F76: CFOM&ETRAN | G76: Local transportation - Field verification and data collection visits | H76: M&E | I76: Unit | J76: 6 | K76: 25 | L76: =J76*K76 -> 150 | M76: 15 | N76: =M76*K76 -> 375 | O76: 10 | P76: =O76*K76 -> 250 | Q76: 10 | R76: =Q76*K76 -> 250 | S76: 0 | T76: =S76*K76 -> 0 | U76: =L76+N76+P76+R76+T76 -> 1025 | V76: 0 | W76: =SUM(U76:V76) -> 1025
A77: MX.3.7.A | B77: 89050 | C77: MX | D77: MX | E77: CFO | F77: CFOM&EMATL | G77: Data collection materials and printing | H77: M&E | I77: Unit | J77: 2 | K77: 100 | L77: =J77*K77 -> 200 | M77: 5 | N77: =M77*K77 -> 500 | O77: 5 | P77: =O77*K77 -> 500 | Q77: 5 | R77: =Q77*K77 -> 500 | S77: 0 | T77: =S77*K77 -> 0 | U77: =L77+N77+P77+R77+T77 -> 1700 | V77: 0 | W77: =SUM(U77:V77) -> 1700
G79: Direct Costs Total for Monitoring, Evaluation, and Collection of Reliable Data | L79: =SUM(L70:L77) -> 2037.75 | N79: =SUM(N70:N77) -> 5892.8 | P79: =SUM(P70:P77) -> 5344.2725 | R79: =SUM(R70:R77) -> 5475.6015 | T79: =SUM(T70:T77) -> 0 | U79: =L79+N79+P79+R79+T79 -> 18750.424 | V79: =SUM(V70:V77) -> 0 | W79: =SUM(U79:V79) -> 18750.424
A81: MX.3.7.A | B81: 89050 | C81: MX | D81: MX | E81: CFO | F81: CFOIDCCOST | G81: Total Indirect Costs (NICRA or De Minimis) for M&E and Collection of Reliable Data | H81: Indirect Charges | K81: 0.1 | L81: =(L79)*K81 -> 203.775 | N81: =(N79)*K81 -> 589.28 | P81: =(P79)*K81 -> 534.42725 | R81: =(R79)*K81 -> 547.56015 | T81: =(T79)*K81 -> 0 | U81: =SUM(L81+N81+P81+R81+T81) -> 1875.0424 | V81: 0 | W81: =SUM(U81:V81) -> 1875.0424
G83: Subtotal Monitoring, Evaluation, and Collection of Reliable Data | L83: =SUM(L79:L81) -> 2241.525 | N83: =SUM(N79:N81) -> 6482.08 | P83: =SUM(P79:P81) -> 5878.6997 | R83: =SUM(R79:R81) -> 6023.1617 | T83: =SUM(T79:T81) -> 0 | U83: =L83+N83+P83+R83+T83 -> 20625.466 | V83: =V81 -> 0 | W83: =SUM(U83:V83) -> 20625.466
G85: TOTAL COSTS | L85: =L83+L67 -> 25921.5 | N85: =N83+N67 -> 98869.1 | P85: =P83+P67 -> 107508.99 | R85: =R83+R67 -> 97198.233 | T85: =T83+T67 -> 0 | U85: =T85+R85+P85+N85+L85 -> 329497.83 | V85: =V83+V67 -> 0 | W85: =SUM(U85:V85) -> 329497.83

Sheet CDM
A1: Entity: | B1: P | G1: Name of Project: Mexico Awareness Raising Project
A2: Program-Dept.: | B2: 20200 | G2: Name of Subawardee: Centro de los Derechos del Migrante (CDM)
A3: Funder-Grant: | B3: DOL423 | G3: Subaward Budget
G4: Budget Assumptions:
G5: Inflation - Locally Purchased Goods/Services | H5: 1.05
G6: Merit Based Increases for Staff | H6: 1.035
A7: Sage Activity | B7: Account Code | C7: Country Code | D7: Office Code | E7: Subcontract Code | F7: Sub Activity | G7: BUDGET ITEM | H7: CATEGORY | I7: UNIT | J7: # of Units | K7: RATE/ UNIT | L7: YEAR 1 | M7: # of Units | N7: YEAR 2 | O7: # of Units | P7: YEAR 3 | Q7: # of Units | R7: YEAR 4 | S7: # of Units | T7: YEAR 5 | U7: TOTAL CDM | V7: TOTAL COST SHARING | W7: PROJECT GRAND TOTAL | X7: Percentage 95% to Outcome 1 | Y7: Percentage 5% to Outcome 3
G8: Direct Labor
G9: Personnel
A10: MX.1.1.B (Outcome 1) / MX.3.7.B (M&E) | B10: 89050 | C10: MEX | D10: MEX | E10: CDM | F10: CDMPERSCDC | G10: Communications Director/Coordinator (100%) | H10: Salaries | I10: Month | J10: 6 | K10: =3500 -> 3500 | L10: =J10*K10 -> 21000 | M10: 12 | N10: =M10*K10*$H$6 -> 43470 | O10: 12 | P10: =O10*K10*$H$6*$H$6 -> 44991.45 | Q10: 12 | R10: =Q10*K10*$H$6*$H$6*$H$6 -> 46566.151 | S10: 0 | T10: =S10*K10*$H$6*$H$6*$H$6*$H$6 -> 0 | U10: =SUM(L10+N10+P10+R10+T10) -> 156027.6 | V10: 0 | W10: =SUM(U10:V10) -> 156027.6 | X10: =W10*0.95 -> 148226.22 | Y10: =W10-X10 -> 7801.38
A11: MX.1.1.B (Outcome 1) / MX.3.7.B (M&E) | B11: 89050 | C11: MEX | D11: MEX | E11: CDM | F11: CDMPERSSMS | G11: Social Media Strategist (100%) | H11: Salaries | I11: Month | J11: 6 | K11: =2800 -> 2800 | L11: =J11*K11 -> 16800 | M11: 12 | N11: =M11*K11*$H$6 -> 34776 | O11: 12 | P11: =O11*K11*$H$6*$H$6 -> 35993.16 | Q11: 12 | R11: =Q11*K11*$H$6*$H$6*$H$6 -> 37252.921 | S11: 0 | T11: =S11*K11*$H$6*$H$6*$H$6*$H$6 -> 0 | U11: =SUM(L11+N11+P11+R11+T11) -> 124822.08 | V11: 0 | W11: =SUM(U11:V11) -> 124822.08 | X11: =W11*0.95 -> 118580.98 | Y11: =W11-X11 -> 6241.104
A12: MX.1.1.B (Outcome 1) / MX.3.7.B (M&E) | B12: 89050 | C12: MEX | D12: MEX | E12: CDM | F12: CDMPERSAA | G12: Administration Assistant (100%) | H12: Salaries | I12: Month | J12: 6 | K12: =2200 -> 2200 | L12: =J12*K12 -> 13200 | M12: 12 | N12: =M12*K12*$H$6 -> 27324 | O12: 12 | P12: =O12*K12*$H$6*$H$6 -> 28280.34 | Q12: 12 | R12: =Q12*K12*$H$6*$H$6*$H$6 -> 29270.152 | S12: 0 | T12: =S12*K12*$H$6*$H$6*$H$6*$H$6 -> 0 | U12: =SUM(L12+N12+P12+R12+T12) -> 98074.492 | V12: 0 | W12: =SUM(U12:V12) -> 98074.492 | X12: =W12*0.95 -> 93170.767 | Y12: =W12-X12 -> 4903.7246
A13: MX.1.1.B (Outcome 1) / MX.3.7.B (M&E) | B13: 89050 | C13: MEX | D13: MEX | E13: CDM | F13: CDMPERSPM | G13: Partnerships Manager (50%) | H13: Salaries | I13: Month | J13: 6 | K13: =2300*50% -> 1150 | L13: =J13*K13 -> 6900 | M13: 12 | N13: =M13*K13*$H$6 -> 14283 | O13: 12 | P13: =O13*K13*$H$6*$H$6 -> 14782.905 | Q13: 12 | R13: =Q13*K13*$H$6*$H$6*$H$6 -> 15300.307 | S13: 0 | T13: =S13*K13*$H$6*$H$6*$H$6*$H$6 -> 0 | U13: =SUM(L13+N13+P13+R13+T13) -> 51266.212 | V13: 0 | W13: =SUM(U13:V13) -> 51266.212 | X13: =W13*0.95 -> 48702.901 | Y13: =W13-X13 -> 2563.3106
G15: Subtotal | L15: =SUM(L10:L13) -> 57900 | N15: =SUM(N10:N13) -> 119853 | P15: =SUM(P10:P13) -> 124047.85 | R15: =SUM(R10:R13) -> 128389.53 | T15: =SUM(T10:T13) -> 0 | U15: =SUM(L15+N15+P15+R15+T15) -> 430190.38 | V15: =SUM(V10:V13) -> 0 | W15: =SUM(U15:V15) -> 430190.38
G17: Fringe Benefits
A18: MX.1.1.B (Outcome 1) / MX.3.7.B (M&E) | B18: 89050 | C18: MEX | D18: MEX | E18: CDM | F18: CDMFRINGE | G18: Fringe benefits | H18: Fringe benefits | K18: 0.304 | L18: =K18*L15 -> 17601.6 | N18: =K18*N15 -> 36435.312 | P18: =K18*P15 -> 37710.548 | R18: =R15*K18 -> 39030.417 | T18: =K18*T15 -> 0 | U18: =SUM(T18,R18,P18,N18,L18) -> 130777.88 | V18: 0 | W18: =SUM(U18:V18) -> 130777.88 | X18: =W18*0.95 -> 124238.98 | Y18: =W18-X18 -> 6538.8939
G20: Subtotal Direct Labor | L20: =SUM(L15:L18) -> 75501.6 | N20: =SUM(N15:N18) -> 156288.31 | P20: =SUM(P15:P18) -> 161758.4 | R20: =SUM(R15:R18) -> 167419.95 | T20: =SUM(T15:T18) -> 0 | U20: =L20+N20+P20+R20+T20 -> 560968.26 | V20: =SUM(V9:V18) -> 0 | W20: =SUM(U20:V20) -> 560968.26
G21: T1. Meetings with POA
A22: MX.1.1.B (Outcome 1) / MX.3.7.B (M&E) | B22: 89050 | C22: MEX | D22: MEX | E22: CDM | F22: CDMGROUND | G22: Project Staff - Ground Transportation | H22: Travel | I22: Day | J22: 6 | K22: 30 | L22: =J22*K22 -> 180 | M22: 6 | N22: =M22*K22*$H$5 -> 189 | O22: 6 | P22: =O22*K22*$H$5*$H$5 -> 198.45 | Q22: 6 | R22: =Q22*K22*$H$5*$H$5*$H$5 -> 208.3725 | S22: 0 | T22: =S22*K22*$H$5*$H$5*$H$5*$H$5 -> 0 | U22: =L22+N22+P22+R22+T22 -> 775.8225 | V22: - | W22: =SUM(U22:V22) -> 775.8225 | X22: =W22*0.95 -> 737.03138 | Y22: =W22-X22 -> 38.791125
G24: Subtotal Travel | L24: =SUM(L22:L22) -> 180 | N24: =SUM(N22:N22) -> 189 | P24: =SUM(P22:P22) -> 198.45 | R24: =SUM(R22:R22) -> 208.3725 | T24: =SUM(T22:T22) -> 0 | U24: =L24+N24+P24+R24+T24 -> 775.8225 | V24: =SUM(V22:V22) -> 0 | W24: =SUM(U24:V24) -> 775.8225
G25: Supplies - Under $5,000 USD
A26: MX.1.1.B (Outcome 1) / MX.3.7.B (M&E) | B26: 89050 | C26: MEX | D26: MEX | E26: CDM | F26: CDMLAPTOP | G26: Laptops and software | H26: Supplies | I26: Device | J26: 4 | K26: 800 | L26: =J26*K26 -> 3200 | M26: 0 | N26: =M26*K26*$H$5 -> 0 | O26: 0 | P26: =O26*K26*$H$5*$H$5 -> 0 | Q26: 0 | R26: =Q26*K26*$H$5*$H$5*$H$5 -> 0 | S26: 0 | T26: =S26*K26*$H$5*$H$5*$H$5*$H$5 -> 0 | U26: =L26+N26+P26+R26+T26 -> 3200 | V26: 0 | W26: =SUM(U26:V26) -> 3200 | X26: =W26*0.95 -> 3040 | Y26: =W26-X26 -> 160
A27: MX.1.1.B (Outcome 1) / MX.3.7.B (M&E) | B27: 89050 | C27: MEX | D27: MEX | E27: CDM | F27: CDMPHONE | G27: Cellphone | H27: Supplies | I27: Device | J27: 1 | K27: 550 | L27: =J27*K27 -> 550 | M27: 0 | N27: =M27*K27*$H$5 -> 0 | O27: 0 | P27: =O27*K27*$H$5*$H$5 -> 0 | Q27: 0 | R27: =Q27*K27*$H$5*$H$5*$H$5 -> 0 | S27: 0 | T27: =S27*K27*$H$5*$H$5*$H$5*$H$5 -> 0 | U27: =L27+N27+P27+R27+T27 -> 550 | V27: 0 | W27: =SUM(U27:V27) -> 550 | X27: =W27*0.95 -> 522.5 | Y27: =W27-X27 -> 27.5
A28: MX.1.1.B (Outcome 1) / MX.3.7.B (M&E) | B28: 89050 | C28: MEX | D28: MEX | E28: CDM | F28: CDMSUPPLY | G28: Office Supplies | H28: Supplies | I28: Month | J28: 6 | K28: 125 | L28: =J28*K28 -> 750 | M28: 12 | N28: =M28*K28*$H$5 -> 1575 | O28: 12 | P28: =O28*K28*$H$5*$H$5 -> 1653.75 | Q28: 12 | R28: =Q28*K28*$H$5*$H$5*$H$5 -> 1736.4375 | S28: 0 | T28: =S28*K28*$H$5*$H$5*$H$5*$H$5 -> 0 | U28: =L28+N28+P28+R28+T28 -> 5715.1875 | V28: 0 | W28: =SUM(U28:V28) -> 5715.1875 | X28: =W28*0.95 -> 5429.4281 | Y28: =W28-X28 -> 285.75938
G30: Subtotal Supplies | L30: =SUM(L26:L28) -> 4500 | N30: =SUM(N26:N28) -> 1575 | P30: =SUM(P26:P28) -> 1653.75 | R30: =SUM(R26:R28) -> 1736.4375 | T30: =SUM(T26:T28) -> 0 | U30: =L30+N30+P30+R30+T30 -> 9465.1875 | V30: =SUM(V26:V28) -> 0 | W30: =SUM(U30:V30) -> 9465.1875
G31: Office Expenses
A32: MX.1.1.B (Outcome 1) / MX.3.7.B (M&E) | B32: 89050 | C32: MEX | D32: MEX | E32: CDM | F32: CDMBANKFEE | G32: Banking and cash handling fees | H32: Office Expenses | I32: Month | J32: 5 | K32: 30 | L32: =J32*K32 -> 150 | M32: 12 | N32: =M32*K32*$H$5 -> 378 | O32: 12 | P32: =O32*K32*$H$5*$H$5 -> 396.9 | Q32: 12 | R32: =Q32*K32*$H$5*$H$5*$H$5 -> 416.745 | S32: 0 | T32: =S32*K32*$H$5*$H$5*$H$5*$H$5 -> 0 | U32: =L32+N32+P32+R32+T32 -> 1341.645 | V32: 0 | W32: =SUM(U32:V32) -> 1341.645 | X32: =W32*0.95 -> 1274.5628 | Y32: =W32-X32 -> 67.08225
A33: MX.1.1.B (Outcome 1) / MX.3.7.B (M&E) | B33: 89050 | C33: MEX | D33: MEX | E33: CDM | F33: CDMPOSTAGE | G33: Courier fees/services/postage | H33: Office Expenses | I33: Year | J33: 0 | K33: 50 | L33: =J33*K33 -> 0 | M33: 1 | N33: =M33*K33*$H$5 -> 52.5 | O33: 1 | P33: =O33*K33*$H$5*$H$5 -> 55.125 | Q33: 1 | R33: =Q33*K33*$H$5*$H$5*$H$5 -> 57.88125 | S33: 0 | T33: =S33*K33*$H$5*$H$5*$H$5*$H$5 -> 0 | U33: =L33+N33+P33+R33+T33 -> 165.50625 | V33: 0 | W33: =SUM(U33:V33) -> 165.50625 | X33: =W33*0.95 -> 157.23094 | Y33: =W33-X33 -> 8.2753125
A34: MX.1.1.B (Outcome 1) / MX.3.7.B (M&E) | B34: 89050 | C34: MEX | D34: MEX | E34: CDM | F34: CDMADVERT | G34: Recruitment/Procurement Advertising | H34: Office Expenses | I34: Year | J34: 3 | K34: 300 | L34: =J34*K34 -> 900 | M34: 0 | N34: =M34*K34*$H$5 -> 0 | O34: 0 | P34: =O34*K34*$H$5*$H$5 -> 0 | Q34: 0 | R34: =Q34*K34*$H$5*$H$5*$H$5 -> 0 | S34: 0 | T34: =S34*K34*$H$5*$H$5*$H$5*$H$5 -> 0 | U34: =L34+N34+P34+R34+T34 -> 900 | V34: 0 | W34: =SUM(U34:V34) -> 900 | X34: =W34*0.95 -> 855 | Y34: =W34-X34 -> 45
A35: MX.1.1.B (Outcome 1) / MX.3.7.B (M&E) | B35: 89050 | C35: MEX | D35: MEX | E35: CDM | F35: CDMEMAIL | G35: Email/Internet | H35: Office Expenses | I35: Month | J35: 6 | K35: 200 | L35: =J35*K35 -> 1200 | M35: 12 | N35: =M35*K35*$H$5 -> 2520 | O35: 12 | P35: =O35*K35*$H$5*$H$5 -> 2646 | Q35: 12 | R35: =Q35*K35*$H$5*$H$5*$H$5 -> 2778.3 | S35: 0 | T35: =S35*K35*$H$5*$H$5*$H$5*$H$5 -> 0 | U35: =L35+N35+P35+R35+T35 -> 9144.3 | V35: 0 | W35: =SUM(U35:V35) -> 9144.3 | X35: =W35*0.95 -> 8687.085 | Y35: =W35-X35 -> 457.215
A36: MX.1.1.B (Outcome 1) / MX.3.7.B (M&E) | B36: 89050 | C36: MEX | D36: MEX | E36: CDM | F36: CDMCELL | G36: Cellphone plan | H36: Office Expenses | I36: Month | J36: 6 | K36: 150 | L36: =J36*K36 -> 900 | M36: 12 | N36: =M36*K36*$H$5 -> 1890 | O36: 12 | P36: =O36*K36*$H$5*$H$5 -> 1984.5 | Q36: 12 | R36: =Q36*K36*$H$5*$H$5*$H$5 -> 2083.725 | S36: 0 | T36: =S36*K36*$H$5*$H$5*$H$5*$H$5 -> 0 | U36: =L36+N36+P36+R36+T36 -> 6858.225 | V36: 0 | W36: =SUM(U36:V36) -> 6858.225 | X36: =W36*0.95 -> 6515.3138 | Y36: =W36-X36 -> 342.91125
A37: MX.1.1.B (Outcome 1) / MX.3.7.B (M&E) | B37: 89050 | C37: MEX | D37: MEX | E37: CDM | F37: CDMRENT | G37: Office Rent | H37: Office Expenses | I37: Month | J37: 6 | K37: 900 | L37: =J37*K37 -> 5400 | M37: 12 | N37: =M37*K37*$H$5 -> 11340 | O37: 12 | P37: =O37*K37*$H$5*$H$5 -> 11907 | Q37: 12 | R37: =Q37*K37*$H$5*$H$5*$H$5 -> 12502.35 | S37: 0 | T37: =S37*K37*$H$5*$H$5*$H$5*$H$5 -> 0 | U37: =L37+N37+P37+R37+T37 -> 41149.35 | V37: 0 | W37: =SUM(U37:V37) -> 41149.35 | X37: =W37*0.95 -> 39091.882 | Y37: =W37-X37 -> 2057.4675
A38: MX.1.1.B (Outcome 1) / MX.3.7.B (M&E) | B38: 89050 | C38: MEX | D38: MEX | E38: CDM | F38: CDMMAINT | G38: Equipment and office repairs and maintenance | H38: Office Expenses | I38: Year | J38: 1 | K38: 250 | L38: =J38*K38 -> 250 | M38: 1 | N38: =M38*K38*$H$5 -> 262.5 | O38: 1 | P38: =O38*K38*$H$5*$H$5 -> 275.625 | Q38: 1 | R38: =Q38*K38*$H$5*$H$5*$H$5 -> 289.40625 | S38: 0 | T38: =S38*K38*$H$5*$H$5*$H$5*$H$5 -> 0 | U38: =L38+N38+P38+R38+T38 -> 1077.5312 | V38: 0 | W38: =SUM(U38:V38) -> 1077.5312 | X38: =W38*0.95 -> 1023.6547 | Y38: =W38-X38 -> 53.876563
G40: Subtotal Office Expenses | L40: =SUM(L32:L38) -> 8800 | N40: =SUM(N32:N38) -> 16443 | P40: =SUM(P32:P38) -> 17265.15 | R40: =SUM(R32:R38) -> 18128.408 | T40: =SUM(T32:T38) -> 0 | U40: =L40+N40+P40+R40+T40 -> 60636.558 | V40: =SUM(V32:V38) -> 0 | W40: =SUM(U40:V40) -> 60636.558
G41: The above is only for percentage calculations for the below outcomes
G42: Outcome 1: Increase understanding by workers, employers, and union leaders on how to utilize Mexico’s new labor systems to protect labor rights and effectively address labor disputes.
G43: Activities/Costs
A44: MX.1.1.B | B44: 89050 | C44: MEX | D44: MEX | E44: CDM | F44: See breakdown column X, Y | G44: Personnel & Fringe (95% of Direct Labor line item) | H44: Outcome1 | I44: Unit | J44: =$L$20 -> 75501.6 | K44: 0.95 | L44: =J44*K44 -> 71726.52 | M44: =$N$20 -> 156288.31 | N44: =M44*K44 -> 148473.9 | O44: =$P$20 -> 161758.4 | P44: =O44*K44 -> 153670.48 | Q44: =$R$20 -> 167419.95 | R44: =Q44*K44 -> 159048.95 | S44: =$T$20 -> 0 | T44: =S44*K44 -> 0 | U44: =L44+N44+P44+R44+T44 -> 532919.85 | V44: 0 | W44: =SUM(U44:V44) -> 532919.85
A45: MX.1.1.B | B45: 89050 | C45: MEX | D45: MEX | E45: CDM | F45: See breakdown column X, Y | G45: Travel 95% | H45: Outcome1 | I45: Unit | J45: =L24 -> 180 | K45: 0.95 | L45: =J45*K45 -> 171 | M45: =N24 -> 189 | N45: =M45*K45 -> 179.55 | O45: =P24 -> 198.45 | P45: =O45*K45 -> 188.5275 | Q45: =R24 -> 208.3725 | R45: =Q45*K45 -> 197.95388 | S45: =$T$30 -> 0 | T45: =S45*K45 -> 0 | U45: =L45+N45+P45+R45+T45 -> 737.03138 | V45: 0 | W45: =SUM(U45:V45) -> 737.03138
A46: MX.1.1.B | B46: 89050 | C46: MEX | D46: MEX | E46: CDM | F46: See breakdown column X, Y | G46: Supplies 95% | H46: Outcome1 | I46: Unit | J46: =$L$30 -> 4500 | K46: 0.95 | L46: =J46*K46 -> 4275 | M46: =$N$30 -> 1575 | N46: =M46*K46 -> 1496.25 | O46: =$P$30 -> 1653.75 | P46: =O46*K46 -> 1571.0625 | Q46: =$R$30 -> 1736.4375 | R46: =Q46*K46 -> 1649.6156 | S46: 0 | T46: =S46*K46 -> 0 | U46: =L46+N46+P46+R46+T46 -> 8991.9281 | V46: 0 | W46: =SUM(U46:V46) -> 8991.9281
A47: MX.1.1.B | B47: 89050 | C47: MEX | D47: MEX | E47: CDM | F47: See breakdown column X, Y | G47: Office Expenses 95% | H47: Outcome1 | I47: Unit | J47: =$L$40 -> 8800 | K47: 0.95 | L47: =J47*K47 -> 8360 | M47: =$N$40 -> 16443 | N47: =M47*K47 -> 15620.85 | O47: =$P$40 -> 17265.15 | P47: =O47*K47 -> 16401.893 | Q47: =$R$40 -> 18128.408 | R47: =Q47*K47 -> 17221.987 | S47: =$T$40 -> 0 | T47: =S47*K47 -> 0 | U47: =L47+N47+P47+R47+T47 -> 57604.73 | V47: 0 | W47: =SUM(U47:V47) -> 57604.73
G48: 1.1.1.2 Mass and social media campaigns for workers and the general populace
A49: MX.1.1.B | B49: 89050 | C49: MEX | D49: MEX | E49: CDM | F49: CDMTRANSTP | G49: Local transportation to support STPS Facebook development | H49: Outcome1 | I49: Day | J49: 0 | K49: 30 | L49: =K49*J49 -> 0 | M49: 3 | N49: =M49*K49 -> 90 | O49: 3 | P49: =O49*K49 -> 90 | Q49: 2 | R49: =Q49*K49 -> 60 | S49: 0 | T49: =S49*K49 -> 0 | U49: =SUM(L49,N49,P49,R49,T49) -> 240 | V49: 0 | W49: =SUM(U49:V49) -> 240
A50: MX.1.1.B | B50: 89050 | C50: MEX | D50: MEX | E50: CDM | F50: CDMDESIGN | G50: Graphic design and material development for STPS Facebook | H50: Outcome1 | I50: Unit | J50: 0 | K50: 500 | L50: =K50*J50 -> 0 | M50: 1 | N50: =M50*K50 -> 500 | O50: 1 | P50: =O50*K50 -> 500 | Q50: 0 | R50: =Q50*K50 -> 0 | S50: 0 | T50: =S50*K50 -> 0 | U50: =SUM(L50,N50,P50,R50,T50) -> 1000 | V50: 0 | W50: =SUM(U50:V50) -> 1000
A51: MX.1.1.B | B51: 89050 | C51: MEX | D51: MEX | E51: CDM | F51: CDMCONSULT | G51: Consultant: Mexican Lawyer to inform materials being developed | H51: Outcome1 | I51: Month | J51: 0 | K51: 3200 | L51: =J51*K51 -> 0 | M51: 3 | N51: =M51*K51 -> 9600 | O51: 3 | P51: =O51*K51 -> 9600 | Q51: 3 | R51: =Q51*K51 -> 9600 | S51: 0 | T51: =S51*K51 -> 0 | U51: =SUM(L51+N51+P51+R51+T51) -> 28800 | V51: 0 | W51: =SUM(U51:V51) -> 28800
A52: MX.1.1.B | B52: 89050 | C52: MEX | D52: MEX | E52: CDM | F52: CDMCONTDEV | G52: Content development and diffusion trainings with unions, confederations, and labor rights NGOs | H52: Outcome1 | I52: Trainings | J52: 0 | K52: 500 | L52: =K52*J52 -> 0 | M52: 3 | N52: =M52*K52 -> 1500 | O52: 3 | P52: =O52*K52 -> 1500 | Q52: 3 | R52: =Q52*K52 -> 1500 | S52: 0 | T52: =S52*K52 -> 0 | U52: =SUM(L52,N52,P52,R52,T52) -> 4500 | V52: 0 | W52: =SUM(U52:V52) -> 4500
A53: MX.1.1.B | B53: 89050 | C53: MEX | D53: MEX | E53: CDM | F53: CDMMATLDES | G53: Material design and printing for trainings with unions, confederations, and labor rights NGOs | H53: Outcome1 | I53: Trainings | J53: 0 | K53: 300 | L53: =K53*J53 -> 0 | M53: 3 | N53: =M53*K53 -> 900 | O53: 3 | P53: =O53*K53 -> 900 | Q53: 3 | R53: =Q53*K53 -> 900 | S53: 0 | T53: =S53*K53 -> 0 | U53: =SUM(L53,N53,P53,R53,T53) -> 2700 | V53: 0 | W53: =SUM(U53:V53) -> 2700
A54: MX.1.1.B | B54: 89050 | C54: MEX | D54: MEX | E54: CDM | F54: CDMSUPPTRA | G54: Transportation for project staff to support trainings | H54: Outcome1 | I54: Day | J54: 0 | K54: 150 | L54: =K54*J54 -> 0 | M54: 9 | N54: =M54*K54 -> 1350 | O54: 9 | P54: =O54*K54 -> 1350 | Q54: 9 | R54: =Q54*K54 -> 1350 | S54: 0 | T54: =S54*K54 -> 0 | U54: =SUM(L54,N54,P54,R54,T54) -> 4050 | V54: 0 | W54: =SUM(U54:V54) -> 4050
A55: MX.1.1.B | B55: 89050 | C55: MEX | D55: MEX | E55: CDM | F55: CDMLODGING | G55: Lodging and M&IE for project staff to support trainings | H55: Outcome1 | I55: Day | J55: 0 | K55: 110 | L55: =K55*J55 -> 0 | M55: 9 | N55: =M55*K55 -> 990 | O55: 9 | P55: =O55*K55 -> 990 | Q55: 9 | R55: =Q55*K55 -> 990 | S55: 0 | T55: =S55*K55 -> 0 | U55: =SUM(L55,N55,P55,R55,T55) -> 2970 | V55: 0 | W55: =SUM(U55:V55) -> 2970
A56: MX.1.1.B | B56: 89050 | C56: MEX | D56: MEX | E56: CDM | F56: CDMKNOWRIG | G56: Design of Know Your Rights posters and cards for workers | H56: Outcome1 | I56: Unit | J56: 0 | K56: 8000 | L56: =K56*J56 -> 0 | M56: 1 | N56: =M56*K56 -> 8000 | O56: 1 | P56: =O56*K56 -> 8000 | Q56: 1 | R56: =Q56*K56 -> 8000 | S56: 0 | T56: =S56*K56 -> 0 | U56: =SUM(L56,N56,P56,R56,T56) -> 24000 | V56: 0 | W56: =SUM(U56:V56) -> 24000
A57: MX.1.1.B | B57: 89050 | C57: MEX | D57: MEX | E57: CDM | F57: CDMDISSEM | G57: Dissemination campaign for Know Your Rights posters and cards within their network | H57: Outcome1 | I57: Campaign | J57: 0 | K57: 2000 | L57: =K57*J57 -> 0 | M57: 1 | N57: =M57*K57 -> 2000 | O57: 1 | P57: =O57*K57 -> 2000 | Q57: 1 | R57: =Q57*K57 -> 2000 | S57: 0 | T57: =S57*K57 -> 0 | U57: =SUM(L57,N57,P57,R57,T57) -> 6000 | V57: 0 | W57: =SUM(U57:V57) -> 6000
A58: MX.1.1.B | B58: 89050 | C58: MEX | D58: MEX | E58: CDM | F58: CDMPRINT | G58: Printing of Know Your Rights posters and cards for dissemination within their network | H58: Outcome1 | I58: Unit | J58: 0 | K58: 800 | L58: =K58*J58 -> 0 | M58: 1 | N58: =M58*K58 -> 800 | O58: 1 | P58: =O58*K58 -> 800 | Q58: 1 | R58: =Q58*K58 -> 800 | S58: 0 | T58: =S58*K58 -> 0 | U58: =SUM(L58,N58,P58,R58,T58) -> 2400 | V58: 0 | W58: =SUM(U58:V58) -> 2400
A59: MX.1.1.B | B59: 89050 | C59: MEX | D59: MEX | E59: CDM | F59: CDMTRANSL | G59: Translation costs | H59: Outcome1 | I59: Unit | J59: 0 | K59: 1000 | L59: =K59*J59 -> 0 | M59: 5 | N59: =M59*K59 -> 5000 | O59: 2 | P59: =O59*K59 -> 2000 | Q59: 1 | R59: =Q59*K59 -> 1000 | S59: 0 | T59: =S59*K59 -> 0 | U59: =SUM(L59,N59,P59,R59,T59) -> 8000 | V59: 0 | W59: =SUM(U59:V59) -> 8000
G61: Direct Costs Total for Outcome 1 | L61: =SUM(L44:L59) -> 84532.52 | N61: =SUM(N44:N59) -> 196500.55 | P61: =SUM(P44:P59) -> 199561.97 | R61: =SUM(R44:R59) -> 204318.51 | T61: =SUM(T44:T59) -> 0 | U61: =SUM(U44:U59) -> 684913.54 | V61: =SUM(V44:V59) -> 0 | W61: =SUM(U61:V61) -> 684913.54
A63: MX.1.1.B | B63: 89050 | C63: MEX | D63: MEX | E63: CDM | F63: CDMIDCCOST | G63: Total Indirect Costs (De Minimis 10%) for Outcome 1 | H63: Indirect Charges | K63: 0.1 | L63: =(L61)*K63 -> 8453.252 | N63: =(N61)*K63 -> 19650.055 | P63: =(P61)*K63 -> 19956.197 | R63: =(R61)*K63 -> 20431.851 | T63: =(T61)*K63 -> 0 | U63: =SUM(L63+N63+P63+R63+T63) -> 68491.354 | V63: 0 | W63: =SUM(U63:V63) -> 68491.354
G65: Subtotal Outcome 1 | L65: =SUM(L61:L63) -> 92985.772 | N65: =SUM(N61:N63) -> 216150.6 | P65: =SUM(P61:P63) -> 219518.16 | R65: =SUM(R61:R63) -> 224750.36 | T65: =SUM(T61:T63) -> 0 | U65: =L65+N65+P65+R65+T65 -> 753404.89 | V65: =V63 -> 0 | W65: =SUM(U65:V65) -> 753404.89
G66: 3: Monitoring, Evaluation, and Collection of Reliable Data
G67: Activities/Costs
A68: MX.3.7.B | B68: 89050 | C68: MEX | D68: MEX | E68: CDM | F68: See breakdown column X, Y | G68: Personnel & Fringe (5% of Direct Labor line item) | H68: M&E | I68: Unit | J68: =$L$20 -> 75501.6 | K68: 0.05 | L68: =J68*K68 -> 3775.08 | M68: =$N$20 -> 156288.31 | N68: =M68*K68 -> 7814.4156 | O68: =$P$20 -> 161758.4 | P68: =O68*K68 -> 8087.9201 | Q68: =$R$20 -> 167419.95 | R68: =Q68*K68 -> 8370.9974 | S68: =$T$20 -> 0 | T68: =S68*K68 -> 0 | U68: =L68+N68+P68+R68+T68 -> 28048.413 | V68: 0 | W68: =SUM(U68:V68) -> 28048.413
A69: MX.3.7.B | B69: 89050 | C69: MEX | D69: MEX | E69: CDM | F69: See breakdown column X, Y | G69: Travel 5% | H69: Outcome1 | I69: Unit | J69: =L24 -> 180 | K69: 0.05 | L69: =J69*K69 -> 9 | M69: =N24 -> 189 | N69: =M69*K69 -> 9.45 | O69: =P24 -> 198.45 | P69: =O69*K69 -> 9.9225 | Q69: =R24 -> 208.3725 | R69: =Q69*K69 -> 10.418625 | S69: =$T$30 -> 0 | T69: =S69*K69 -> 0 | U69: =L69+N69+P69+R69+T69 -> 38.791125 | V69: 0 | W69: =SUM(U69:V69) -> 38.791125
A70: MX.3.7.B | B70: 89050 | C70: MEX | D70: MEX | E70: CDM | F70: See breakdown column X, Y | G70: Supplies 5% | H70: M&E | I70: Unit | J70: =$L$30 -> 4500 | K70: 0.05 | L70: =J70*K70 -> 225 | M70: =$N$30 -> 1575 | N70: =M70*K70 -> 78.75 | O70: =$P$30 -> 1653.75 | P70: =O70*K70 -> 82.6875 | Q70: =$R$30 -> 1736.4375 | R70: =Q70*K70 -> 86.821875 | S70: 0 | T70: =S70*K70 -> 0 | U70: =L70+N70+P70+R70+T70 -> 473.25937 | V70: 0 | W70: =SUM(U70:V70) -> 473.25937
A71: MX.3.7.B | B71: 89050 | C71: MEX | D71: MEX | E71: CDM | F71: See breakdown column X, Y | G71: Office Expenses 5% | H71: M&E | I71: Unit | J71: =$L$40 -> 8800 | K71: 0.05 | L71: =J71*K71 -> 440 | M71: =$N$40 -> 16443 | N71: =M71*K71 -> 822.15 | O71: =$P$40 -> 17265.15 | P71: =O71*K71 -> 863.2575 | Q71: =$R$40 -> 18128.408 | R71: =Q71*K71 -> 906.42038 | S71: 0 | T71: =S71*K71 -> 0 | U71: =L71+N71+P71+R71+T71 -> 3031.8279 | V71: 0 | W71: =SUM(U71:V71) -> 3031.8279
G72: 3.7.2.1 Collection of Reliable Data and Processing of Monitoring Data | H72: M&E | I72: Unit | J72: 0 | K72: 0 | L72: =J72*K72 -> 0 | M72: 0 | N72: =M72*K72 -> 0 | O72: 0 | P72: =O72*K72 -> 0 | Q72: 0 | R72: =Q72*K72 -> 0 | T72: =S72*K72 -> 0 | U72: =L72+N72+P72+R72+T72 -> 0 | V72: 0 | W72: =SUM(U72:V72) -> 0
A73: MX.3.7.B | B73: 89050 | C73: MEX | D73: MEX | E73: CDM | F73: CDMM&ELOD | G73: Lodging and M&IE - Field verification and data collection visits | H73: M&E | I73: Unit | J73: 0 | K73: 110 | L73: =K73*J73 -> 0 | M73: 6 | N73: =M73*K73 -> 660 | O73: 10 | P73: =O73*K73 -> 1100 | Q73: 10 | R73: =Q73*K73 -> 1100 | S73: 0 | T73: =S73*K73 -> 0 | U73: =SUM(L73,N73,P73,R73,T73) -> 2860 | V73: - | W73: =SUM(U73:V73) -> 2860
A74: MX.3.7.B | B74: 89050 | C74: MEX | D74: MEX | E74: CDM | F74: CDMM&ETRAN | G74: Local transportation - Field verification and data collection visits | H74: M&E | I74: Unit | J74: 0 | K74: 25 | L74: =K74*J74 -> 0 | M74: 6 | N74: =M74*K74 -> 150 | O74: 10 | P74: =O74*K74 -> 250 | Q74: 10 | R74: =Q74*K74 -> 250 | S74: 0 | T74: =S74*K74 -> 0 | U74: =SUM(L74,N74,P74,R74,T74) -> 650 | V74: - | W74: =SUM(U74:V74) -> 650
A75: MX.3.7.B | B75: 89050 | C75: MEX | D75: MEX | E75: CDM | F75: CDMM&EMATL | G75: Data collection materials and printing | H75: M&E | I75: Unit | J75: 0 | K75: 150 | L75: =K75*J75 -> 0 | M75: 3 | N75: =M75*K75 -> 450 | O75: 5 | P75: =O75*K75 -> 750 | Q75: 5 | R75: =Q75*K75 -> 750 | S75: 0 | T75: =S75*K75 -> 0 | U75: =SUM(L75,N75,P75,R75,T75) -> 1950 | V75: - | W75: =SUM(U75:V75) -> 1950
G77: Direct Costs Total for Monitoring, Evaluation, and Collection of Reliable Data | L77: =SUM(L68:L75) -> 4449.08 | N77: =SUM(N68:N75) -> 9984.7656 | P77: =SUM(P68:P75) -> 11143.788 | R77: =SUM(R68:R75) -> 11474.658 | T77: =SUM(T68:T75) -> 0 | U77: =L77+N77+P77+R77+T77 -> 37052.291 | V77: =SUM(V68:V75) -> 0 | W77: =SUM(U77:V77) -> 37052.291
A79: MX.3.7.B | B79: 89050 | C79: MEX | D79: MEX | E79: CDM | F79: CDMIDCCOST | G79: Total Indirect Costs (NICRA or De Minimis) for M&E and Collection of Reliable Data | H79: Indirect Charges | K79: 0.1 | L79: =(L77)*K79 -> 444.908 | N79: =(N77)*K79 -> 998.47656 | P79: =(P77)*K79 -> 1114.3788 | R79: =(R77)*K79 -> 1147.4658 | T79: =(T77)*K79 -> 0 | U79: =SUM(L79+N79+P79+R79+T79) -> 3705.2291 | V79: 0 | W79: =SUM(U79:V79) -> 3705.2291
G81: Subtotal Monitoring, Evaluation, and Collection of Reliable Data | L81: =SUM(L77:L79) -> 4893.988 | N81: =SUM(N77:N79) -> 10983.242 | P81: =SUM(P77:P79) -> 12258.166 | R81: =SUM(R77:R79) -> 12622.124 | T81: =SUM(T77:T79) -> 0 | U81: =L81+N81+P81+R81+T81 -> 40757.521 | V81: =SUM(V72:V75) -> 0 | W81: =SUM(U81:V81) -> 40757.521
G83: TOTAL COSTS | L83: =L81+L65 -> 97879.76 | N83: =N81+N65 -> 227133.84 | P83: =P81+P65 -> 231776.33 | R83: =R81+R65 -> 237372.48 | T83: =T81+T65 -> 0 | U83: =T83+R83+P83+N83+L83 -> 794162.41 | V83: =V81+V65 -> 0 | W83: =SUM(U83:V83) -> 794162.41

Sheet SAI
A1: Name of Project: Mexico Awareness Raising Project
A2: Name of Subawardee: Social Accountability International (SAI)
A3: Subaward Budget
A4: Budget Assumptions:
A5: Inflation - US Based Goods/Services | B5: 1.03
A6: Inflation - Locally Purchased Goods/Services | B6: 1.05
A7: Merit Based Increases for Staff | B7: 1.035
A9: BUDGET ITEM | B9: CATEGORY | C9: UNIT | D9: # of Units | E9: RATE/ UNIT | F9: YEAR 1 | G9: # of Units | H9: YEAR 2 | I9: # of Units | J9: YEAR 3 | K9: # of Units | L9: YEAR 4 | M9: # of Units | N9: YEAR 5 | O9: TOTALSAI | P9: TOTAL COST SHARING | Q9: PROJECT GRAND TOTAL | R9: Percentage 60% to Outcome 1 | S9: Percentage 35% to Outcome 2 | T9: Percentage 5% to Outcome 3
A11: Direct Labor
A12: Field Personnel
A13: Assessor, Trainer & Facilitator 1 | B13: Salaries | C13: Day | D13: =(6*15)+(3*10) -> 120 | E13: 325 | F13: =D13*E13 -> 39000 | G13: =10*12 -> 120 | H13: =G13*E13*$B$7 -> 40365 | I13: =10*12 -> 120 | J13: =I13*E13*$B$7*$B$7 -> 41777.775 | K13: =10*12 -> 120 | L13: =K13*E13*$B$7*$B$7*$B$7 -> 43239.997 | M13: =3*10 -> 30 | N13: =M13*E13*$B$7*$B$7*$B$7*$B$7 -> 11188.349 | O13: =SUM(F13+H13+J13+L13+N13) -> 175571.12 | P13: 0 | Q13: =SUM(O13:P13) -> 175571.12 | R13: =Q13*0.6 -> 105342.67 | S13: =Q13*0.35 -> 61449.892 | T13: =Q13-R13-S13 -> 8778.5561
A14: Assessor, Trainer & Facilitator 2 | B14: Salaries | C14: Day | D14: =(6*15)+(3*10) -> 120 | E14: 325 | F14: =D14*E14 -> 39000 | G14: =10*12 -> 120 | H14: =G14*E14*$B$7 -> 40365 | I14: =10*12 -> 120 | J14: =I14*E14*$B$7*$B$7 -> 41777.775 | K14: =10*12 -> 120 | L14: =K14*E14*$B$7*$B$7*$B$7 -> 43239.997 | M14: =3*10 -> 30 | N14: =M14*E14*$B$7*$B$7*$B$7*$B$7 -> 11188.349 | O14: =SUM(F14+H14+J14+L14+N14) -> 175571.12 | P14: 0 | Q14: =SUM(O14:P14) -> 175571.12 | R14: =Q14*0.6 -> 105342.67 | S14: =Q14*0.35 -> 61449.892 | T14: =Q14-R14-S14 -> 8778.5561
A15: Assessor, Trainer & Facilitator 3 | B15: Salaries | C15: Day | D15: 10 | E15: 350 | F15: =D15*E15 -> 3500 | G15: 10 | H15: =G15*E15*$B$7 -> 3622.5 | I15: 10 | J15: =I15*E15*$B$7*$B$7 -> 3749.2875 | K15: 0 | L15: =K15*E15*$B$7*$B$7*$B$7 -> 0 | M15: 0 | N15: =M15*E15*$B$7*$B$7*$B$7*$B$7 -> 0 | O15: =SUM(F15+H15+J15+L15+N15) -> 10871.787 | P15: 0 | Q15: =SUM(O15:P15) -> 10871.787 | R15: =Q15*0.6 -> 6523.0725 | S15: =Q15*0.35 -> 3805.1256 | T15: =Q15-R15-S15 -> 543.58938
A16: Assessor, Trainer & Facilitator 4 | B16: Salaries | C16: Day | D16: 10 | E16: 350 | F16: =D16*E16 -> 3500 | G16: 10 | H16: =G16*E16*$B$7 -> 3622.5 | I16: 10 | J16: =I16*E16*$B$7*$B$7 -> 3749.2875 | K16: 0 | L16: =K16*E16*$B$7*$B$7*$B$7 -> 0 | M16: 0 | N16: =M16*E16*$B$7*$B$7*$B$7*$B$7 -> 0 | O16: =SUM(F16+H16+J16+L16+N16) -> 10871.787 | P16: 0 | Q16: =SUM(O16:P16) -> 10871.787
A17: HQ Personnel
A18: Senior Director, Innovations and Capacity Building | B18: Salaries | C18: Day | D18: =4*12 -> 48 | E18: =125000/222 -> 563.06306 | F18: =D18*E18 -> 27027.027 | G18: =4*12 -> 48 | H18: =G18*E18*$B$7 -> 27972.973 | I18: =3*12 -> 36 | J18: =I18*E18*$B$7*$B$7 -> 21714.02 | K18: =2*12 -> 24 | L18: =K18*E18*$B$7*$B$7*$B$7 -> 14982.674 | M18: =2*6 -> 12 | N18: =M18*E18*$B$7*$B$7*$B$7*$B$7 -> 7753.5338 | O18: =SUM(F18+H18+J18+L18+N18) -> 99450.228 | P18: 0 | Q18: =SUM(O18:P18) -> 99450.228 | R18: =Q18*0.6 -> 59670.137 | S18: =Q18*0.35 -> 34807.58 | T18: =Q18-R18-S18 -> 4972.5114
A19: Associate Director, Innovations and Partnerships | B19: Salaries | C19: Day | D19: =2*12 -> 24 | E19: =100000/218 -> 458.7156 | F19: =D19*E19 -> 11009.174 | G19: =3*12 -> 36 | H19: =G19*E19*$B$7 -> 17091.743 | I19: =3*12 -> 36 | J19: =I19*E19*$B$7*$B$7 -> 17689.954 | K19: =2*12 -> 24 | L19: =K19*E19*$B$7*$B$7*$B$7 -> 12206.068 | M19: =2*6 -> 12 | N19: =M19*E19*$B$7*$B$7*$B$7*$B$7 -> 6316.6404 | O19: =SUM(F19+H19+J19+L19+N19) -> 64313.58 | P19: 0 | Q19: =SUM(O19:P19) -> 64313.58 | R19: =Q19*0.6 -> 38588.148 | S19: =Q19*0.35 -> 22509.753 | T19: =Q19-R19-S19 -> 3215.679
A20: Manager, Policy & Stakeholder Engagement | B20: Salaries | C20: Day | D20: =2*12 -> 24 | E20: =75000/218 -> 344.0367 | F20: =D20*E20 -> 8256.8807 | G20: =2*12 -> 24 | H20: =G20*E20*$B$7 -> 8545.8716 | I20: =2*12 -> 24 | J20: =I20*E20*$B$7*$B$7 -> 8844.9771 | K20: =1*12 -> 12 | L20: =K20*E20*$B$7*$B$7*$B$7 -> 4577.2756 | M20: =1*6 -> 6 | N20: =M20*E20*$B$7*$B$7*$B$7*$B$7 -> 2368.7401 | O20: =SUM(F20+H20+J20+L20+N20) -> 32593.745 | P20: 0 | Q20: =SUM(O20:P20) -> 32593.745 | R20: =Q20*0.6 -> 19556.247 | S20: =Q20*0.35 -> 11407.811 | T20: =Q20-R20-S20 -> 1629.6873
A21: Manager, Communications & Marketing | B21: Salaries | C21: Day | D21: =4*12 -> 48 | E21: =75000/222 -> 337.83784 | F21: =D21*E21 -> 16216.216 | G21: =5*12 -> 60 | H21: =G21*E21*$B$7 -> 20979.73 | I21: =5*12 -> 60 | J21: =I21*E21*$B$7*$B$7 -> 21714.02 | K21: =4*12 -> 48 | L21: =K21*E21*$B$7*$B$7*$B$7 -> 17979.209 | M21: 8 | N21: =M21*E21*$B$7*$B$7*$B$7*$B$7 -> 3101.4135 | O21: =SUM(F21+H21+J21+L21+N21) -> 79990.589 | P21: 0 | Q21: =SUM(O21:P21) -> 79990.589 | R21: =Q21*0.6 -> 47994.353 | S21: =Q21*0.35 -> 27996.706 | T21: =Q21-R21-S21 -> 3999.5294
A22: Subtotal | F22: =SUM(F13:F21) -> 147509.3 | H22: =SUM(H13:H21) -> 162565.32 | J22: =SUM(J13:J21) -> 161017.1 | L22: =SUM(L13:L21) -> 136225.22 | N22: =SUM(N13:N21) -> 41917.026 | O22: =SUM(F22+H22+J22+L22+N22) -> 649233.96 | P22: =SUM(P13:P21) -> 0 | Q22: =SUM(O22:P22) -> 649233.96 | R22: =Q22*0.6 -> 389540.38 | S22: =Q22*0.35 -> 227231.89 | T22: =Q22-R22-S22 -> 32461.698
R23: =Q23*0.6 -> 0 | S23: =Q23*0.35 -> 0 | T23: =Q23-R23-S23 -> 0
A24: Fringe Benefits | R24: =Q24*0.6 -> 0 | S24: =Q24*0.35 -> 0 | T24: =Q24-R24-S24 -> 0
A25: Fringe benefits HQ Support | B25: Fringe Benefits | E25: 0.29 | F25: =E25*SUM(F18:F21) -> 18127.697 | H25: =E25*SUM(H18:H21) -> 21631.192 | J25: =E25*SUM(J18:J21) -> 20289.262 | L25: =E25*SUM(L18:L21) -> 14426.116 | N25: =E25*SUM(N18:N21) -> 5666.6951 | O25: =SUM(F25+H25+J25+L25+N25) -> 80140.961 | P25: 0 | Q25: =SUM(O25:P25) -> 80140.961 | R25: =Q25*0.6 -> 48084.577 | S25: =Q25*0.35 -> 28049.336 | T25: =Q25-R25-S25 -> 4007.0481
R26: =Q26*0.6 -> 0 | S26: =Q26*0.35 -> 0 | T26: =Q26-R26-S26 -> 0
A27: Subtotal Direct Labor | F27: =SUM(F22:F25) -> 165636.99 | H27: =SUM(H22:H25) -> 184196.51 | J27: =SUM(J22:J25) -> 181306.36 | L27: =SUM(L22:L25) -> 150651.34 | N27: =SUM(N22:N25) -> 47583.721 | O27: =F27+H27+J27+L27+N27 -> 729374.92 | P27: =SUM(P12:P25) -> 0 | Q27: =SUM(O27:P27) -> 729374.92 | R27: =Q27*0.6 -> 437624.95 | S27: =Q27*0.35 -> 255281.22 | T27: =Q27-R27-S27 -> 36468.746
R28: =Q28*0.6 -> 0 | S28: =Q28*0.35 -> 0 | T28: =Q28-R28-S28 -> 0
A29: Travel
A30: T1. Meetings with Partners and USDOL
A31: HQ Staff - Train NYC<>DC | B31: Travel | C31: Trip | D31: =2*2 -> 4 | E31: 250 | F31: =D31*E31 -> 1000 | G31: 0 | H31: =G31*E31*$B$5 -> 0 | I31: 0 | J31: =I31*E31*$B$5*$B$5 -> 0 | K31: 0 | L31: =K31*E31*$B$5*$B$5*$B$5 -> 0 | M31: 0 | N31: =M31*E31*$B$5*$B$5*$B$5*$B$5 -> 0 | O31: =F31+H31+J31+L31+N31 -> 1000 | P31: - | Q31: =SUM(O31:P31) -> 1000
A32: HQ Staff - Lodging in DC | B32: Travel | C32: Day | D32: =2*2*1 -> 4 | E32: 200 | F32: =D32*E32 -> 800 | G32: 0 | H32: =G32*E32*$B$5 -> 0 | I32: 0 | J32: =I32*E32*$B$5*$B$5 -> 0 | K32: 0 | L32: =K32*E32*$B$5*$B$5*$B$5 -> 0 | M32: 0 | N32: =M32*E32*$B$5*$B$5*$B$5*$B$5 -> 0 | O32: =F32+H32+J32+L32+N32 -> 800 | P32: - | Q32: =SUM(O32:P32) -> 800
A33: HQ Staff - Local Transportation in DC | B33: Travel | C33: Day | D33: =2*2 -> 4 | E33: 50 | F33: =D33*E33 -> 200 | G33: 0 | H33: =G33*E33*$B$5 -> 0 | I33: 0 | J33: =I33*E33*$B$5*$B$5 -> 0 | K33: 0 | L33: =K33*E33*$B$5*$B$5*$B$5 -> 0 | M33: 0 | N33: =M33*E33*$B$5*$B$5*$B$5*$B$5 -> 0 | O33: =F33+H33+J33+L33+N33 -> 200 | P33: - | Q33: =SUM(O33:P33) -> 200 | R33: =Q33*0.6 -> 120 | S33: =Q33*0.35 -> 70 | T33: =Q33-R33-S33 -> 10
A34: HQ Staff - M&IE in DC | B34: Travel | C34: Day | D34: =2*2 -> 4 | E34: 50 | F34: =D34*E34 -> 200 | G34: 0 | H34: =G34*E34*$B$5 -> 0 | I34: 0 | J34: =I34*E34*$B$5*$B$5 -> 0 | K34: 0 | L34: =K34*E34*$B$5*$B$5*$B$5 -> 0 | M34: 0 | N34: =M34*E34*$B$5*$B$5*$B$5*$B$5 -> 0 | O34: =F34+H34+J34+L34+N34 -> 200 | P34: - | Q34: =SUM(O34:P34) -> 200
A35: T2. HQ Trips to Mexico
A36: Airfare for: NYC<>Mexico City | B36: Travel | C36: Trip | D36: 1 | E36: 600 | F36: =D36*E36 -> 600 | G36: 1 | H36: =G36*E36*$B$5 -> 618 | I36: 1 | J36: =I36*E36*$B$5*$B$5 -> 636.54 | K36: 1 | L36: =K36*E36*$B$5*$B$5*$B$5 -> 655.6362 | M36: 1 | N36: =M36*E36*$B$5*$B$5*$B$5*$B$5 -> 675.30529 | O36: =F36+H36+J36+L36+N36 -> 3185.4815 | P36: - | Q36: =SUM(O36:P36) -> 3185.4815
A37: Airfare within Mexico | B37: Travel | C37: Trip | D37: 1 | E37: 125 | F37: =D37*E37 -> 125 | G37: 1 | H37: =G37*E37*$B$6 -> 131.25 | I37: 1 | J37: =I37*E37*$B$6*$B$6 -> 137.8125 | K37: 1 | L37: =K37*E37*$B$6*$B$6*$B$6 -> 144.70312 | M37: 1 | N37: =M37*E37*$B$6*$B$6*$B$6*$B$6 -> 151.93828 | O37: =F37+H37+J37+L37+N37 -> 690.70391 | P37: - | Q37: =SUM(O37:P37) -> 690.70391
A38: Lodging and M&IE | B38: Travel | C38: Day | D38: 20 | E38: 110 | F38: =D38*E38 -> 2200 | G38: 7 | H38: =G38*E38*$B$6 -> 808.5 | I38: 7 | J38: =I38*E38*$B$6*$B$6 -> 848.925 | K38: 7 | L38: =K38*E38*$B$6*$B$6*$B$6 -> 891.37125 | M38: 7 | N38: =M38*E38*$B$6*$B$6*$B$6*$B$6 -> 935.93981 | O38: =F38+H38+J38+L38+N38 -> 5684.7361 | P38: - | Q38: =SUM(O38:P38) -> 5684.7361
A39: Transportation (to and from home airports) | B39: Travel | C39: Day | D39: 20 | E39: 50 | F39: =D39*E39 -> 1000 | G39: 7 | H39: =G39*E39*$B$6 -> 367.5 | I39: 7 | J39: =I39*E39*$B$6*$B$6 -> 385.875 | K39: 7 | L39: =K39*E39*$B$6*$B$6*$B$6 -> 405.16875 | M39: 7 | N39: =M39*E39*$B$6*$B$6*$B$6*$B$6 -> 425.42719 | O39: =F39+H39+J39+L39+N39 -> 2583.9709 | P39: - | Q39: =SUM(O39:P39) -> 2583.9709 | R39: =Q39*0.6 -> 1550.3826 | S39: =Q39*0.35 -> 904.38983 | T39: =Q39-R39-S39 -> 129.19855
A40: Local transportation | B40: Travel | C40: Day | D40: 20 | E40: 30 | F40: =D40*E40 -> 600 | G40: 7 | H40: =G40*E40*$B$6 -> 220.5 | I40: 7 | J40: =I40*E40*$B$6*$B$6 -> 231.525 | K40: 7 | L40: =K40*E40*$B$6*$B$6*$B$6 -> 243.10125 | M40: 7 | N40: =M40*E40*$B$6*$B$6*$B$6*$B$6 -> 255.25631 | O40: =F40+H40+J40+L40+N40 -> 1550.3826 | P40: - | Q40: =SUM(O40:P40) -> 1550.3826 | R40: =Q40*0.6 -> 930.22954 | S40: =Q40*0.35 -> 542.6339 | T40: =Q40-R40-S40 -> 77.519128
A41: T3. Field Personnel Trips in Mexico | R41: =Q41*0.6 -> 0 | S41: =Q41*0.35 -> 0 | T41: =Q41-R41-S41 -> 0
A42: Airfare within Mexico | B42: Travel | C42: Trip | D42: =2*6 -> 12 | E42: 125 | F42: =D42*E42 -> 1500 | G42: =2*6 -> 12 | H42: =G42*E42*$B$6 -> 1575 | I42: =2*6 -> 12 | J42: =I42*E42*$B$6*$B$6 -> 1653.75 | K42: =2*6 -> 12 | L42: =K42*E42*$B$6*$B$6*$B$6 -> 1736.4375 | M42: 2 | N42: =M42*E42*$B$6*$B$6*$B$6*$B$6 -> 303.87656 | O42: =F42+H42+J42+L42+N42 -> 6769.0641 | P42: - | Q42: =SUM(O42:P42) -> 6769.0641 | R42: =Q42*0.6 -> 4061.4384 | S42: =Q42*0.35 -> 2369.1724 | T42: =Q42-R42-S42 -> 338.4532
A43: Lodging and M&IE | B43: Travel | C43: Day | D43: =2*6*5 -> 60 | E43: 110 | F43: =D43*E43 -> 6600 | G43: =2*6*5 -> 60 | H43: =G43*E43*$B$6 -> 6930 | I43: =2*6*5 -> 60 | J43: =I43*E43*$B$6*$B$6 -> 7276.5 | K43: =2*6*5 -> 60 | L43: =K43*E43*$B$6*$B$6*$B$6 -> 7640.325 | M43: =2*5 -> 10 | N43: =M43*E43*$B$6*$B$6*$B$6*$B$6 -> 1337.0569 | O43: =F43+H43+J43+L43+N43 -> 29783.882 | P43: - | Q43: =SUM(O43:P43) -> 29783.882
A44: Transportation (to and from home airports) | B44: Travel | C44: Day | D44: =2*6*5 -> 60 | E44: 30 | F44: =D44*E44 -> 1800 | G44: =2*6*5 -> 60 | H44: =G44*E44*$B$6 -> 1890 | I44: =2*6*5 -> 60 | J44: =I44*E44*$B$6*$B$6 -> 1984.5 | K44: =2*6*5 -> 60 | L44: =K44*E44*$B$6*$B$6*$B$6 -> 2083.725 | M44: =2*5 -> 10 | N44: =M44*E44*$B$6*$B$6*$B$6*$B$6 -> 364.65188 | O44: =F44+H44+J44+L44+N44 -> 8122.8769 | P44: - | Q44: =SUM(O44:P44) -> 8122.8769 | R44: =Q44*0.6 -> 4873.7261 | S44: =Q44*0.35 -> 2843.0069 | T44: =Q44-R44-S44 -> 406.14384
A45: Local transportation | B45: Travel | C45: Day | D45: =2*6*5 -> 60 | E45: 30 | F45: =D45*E45 -> 1800 | G45: =2*6*5 -> 60 | H45: =G45*E45*$B$6 -> 1890 | I45: =2*6*5 -> 60 | J45: =I45*E45*$B$6*$B$6 -> 1984.5 | K45: =2*6*5 -> 60 | L45: =K45*E45*$B$6*$B$6*$B$6 -> 2083.725 | M45: =2*5 -> 10 | N45: =M45*E45*$B$6*$B$6*$B$6*$B$6 -> 364.65188 | O45: =F45+H45+J45+L45+N45 -> 8122.8769 | P45: - | Q45: =SUM(O45:P45) -> 8122.8769 | R45: =Q45*0.6 -> 4873.7261 | S45: =Q45*0.35 -> 2843.0069 | T45: =Q45-R45-S45 -> 406.14384
R46: =Q46*0.6 -> 0 | S46: =Q46*0.35 -> 0 | T46: =Q46-R46-S46 -> 0
A47: Subtotal Travel | F47: =SUM(F31:F46) -> 18425 | H47: =SUM(H31:H46) -> 14430.75 | J47: =SUM(J31:J46) -> 15139.927 | L47: =SUM(L31:L46) -> 15884.193 | N47: =SUM(N31:N46) -> 4814.1041 | O47: =F47+H47+J47+L47+N47 -> 68693.975 | P47: =SUM(P31:P45) -> 0 | Q47: =SUM(O47:P47) -> 68693.975 | R47: =Q47*0.6 -> 41216.385 | S47: =Q47*0.35 -> 24042.891 | T47: =Q47-R47-S47 -> 3434.6987
A48: Supplies - Under $5,000 USD
A49: Desktop computers, laptops and software | B49: Supplies | C49: Unit | D49: 2 | E49: 800 | F49: =E49*D49 -> 1600 | G49: 0 | H49: =G49*E49*$B$6 -> 0 | I49: 0 | J49: =I49*E49*$B$6*$B$6 -> 0 | K49: 0 | L49: =K49*E49*$B$6*$B$6*$B$6 -> 0 | M49: 0 | N49: =M49*E49*$B$6*$B$6*$B$6*$B$6 -> 0 | O49: =F49+H49+J49+L49+N49 -> 1600 | P49: 0 | Q49: =SUM(O49:P49) -> 1600
A50: Stationery/Printing Materials | B50: Supplies | C50: Unit | D50: 10 | E50: 30 | F50: =D50*E50 -> 300 | G50: 12 | H50: =G50*E50*$B$6 -> 378 | I50: 12 | J50: =I50*E50*$B$6*$B$6 -> 396.9 | K50: 12 | L50: =K50*E50*$B$6*$B$6*$B$6 -> 416.745 | M50: 3 | N50: =M50*E50*$B$6*$B$6*$B$6*$B$6 -> 109.39556 | O50: =F50+H50+J50+L50+N50 -> 1601.0406 | P50: 0 | Q50: =SUM(O50:P50) -> 1601.0406
R51: =Q51*0.6 -> 0 | S51: =Q51*0.35 -> 0 | T51: =Q51-R51-S51 -> 0
A52: Subtotal Supplies | F52: =SUM(F49:F50) -> 1900 | H52: =SUM(H49:H50) -> 378 | J52: =SUM(J49:J50) -> 396.9 | L52: =SUM(L49:L50) -> 416.745 | N52: =SUM(N49:N50) -> 109.39556 | O52: =F52+H52+J52+L52+N52 -> 3201.0406 | P52: =SUM(P49:P50) -> 0 | Q52: =SUM(O52:P52) -> 3201.0406 | R52: =Q52*0.6 -> 1920.6243 | S52: =Q52*0.35 -> 1120.3642 | T52: =Q52-R52-S52 -> 160.05203
A53: Office Expenses | R53: =Q53*0.6 -> 0 | S53: =Q53*0.35 -> 0 | T53: =Q53-R53-S53 -> 0
A54: Banking and cash handling fees | B54: Office Expenses | C54: Month | D54: 10 | E54: 30 | F54: =D54*E54 -> 300 | G54: 12 | H54: =G54*E54*$B$6 -> 378 | I54: 12 | J54: =I54*E54*$B$6*$B$6 -> 396.9 | K54: 12 | L54: =K54*E54*$B$6*$B$6*$B$6 -> 416.745 | M54: 3 | N54: =M54*E54*$B$6*$B$6*$B$6*$B$6 -> 109.39556 | O54: =F54+H54+J54+L54+N54 -> 1601.0406 | P54: 0 | Q54: =SUM(O54:P54) -> 1601.0406
A55: Courier fees/services/postage | B55: Office Expenses | C55: Month | D55: 10 | E55: 15 | F55: =D55*E55 -> 150 | G55: 12 | H55: =G55*E55*$B$6 -> 189 | I55: 12 | J55: =I55*E55*$B$6*$B$6 -> 198.45 | K55: 12 | L55: =K55*E55*$B$6*$B$6*$B$6 -> 208.3725 | M55: 3 | N55: =M55*E55*$B$6*$B$6*$B$6*$B$6 -> 54.697781 | O55: =F55+H55+J55+L55+N55 -> 800.52028 | P55: 0 | Q55: =SUM(O55:P55) -> 800.52028
A56: Teleconferencing/Videoconferencing | B56: Office Expenses | C56: Month | D56: 10 | E56: 150 | F56: =D56*E56 -> 1500 | G56: 12 | H56: =G56*E56*$B$6 -> 1890 | I56: 12 | J56: =I56*E56*$B$6*$B$6 -> 1984.5 | K56: 12 | L56: =K56*E56*$B$6*$B$6*$B$6 -> 2083.725 | M56: 3 | N56: =M56*E56*$B$6*$B$6*$B$6*$B$6 -> 546.97781 | O56: =F56+H56+J56+L56+N56 -> 8005.2028 | P56: 0 | Q56: =SUM(O56:P56) -> 8005.2028
A57: Insurance | B57: Office Expenses | C57: Month | D57: 10 | E57: 120 | F57: =D57*E57 -> 1200 | G57: 12 | H57: =G57*E57*$B$6 -> 1512 | I57: 12 | J57: =I57*E57*$B$6*$B$6 -> 1587.6 | K57: 12 | L57: =K57*E57*$B$6*$B$6*$B$6 -> 1666.98 | M57: 3 | N57: =M57*E57*$B$6*$B$6*$B$6*$B$6 -> 437.58225 | O57: =F57+H57+J57+L57+N57 -> 6404.1623 | P57: 0 | Q57: =SUM(O57:P57) -> 6404.1623 | R57: =Q57*0.6 -> 3842.4974 | S57: =Q57*0.35 -> 2241.4568 | T57: =Q57-R57-S57 -> 320.20811
R58: =Q58*0.6 -> 0 | S58: =Q58*0.35 -> 0 | T58: =Q58-R58-S58 -> 0
A59: Subtotal Office Expenses | F59: =SUM(F54:F57) -> 3150 | H59: =SUM(H54:H57) -> 3969 | J59: =SUM(J54:J57) -> 4167.45 | L59: =SUM(L54:L57) -> 4375.8225 | N59: =SUM(N54:N57) -> 1148.6534 | O59: =F59+H59+J59+L59+N59 -> 16810.926 | P59: =SUM(P54:P57) -> 0 | Q59: =SUM(O59:P59) -> 16810.926
A60: The above is only for percentage calculations for the below outcomes
A61: Outcome 1: Increase understanding by workers, employers, and union leaders on how to utilize Mexico’s new labor systems to protect labor rights and effectively address labor disputes.
A62: Activities/Costs
A63: Personnel & Fringe (60% of Direct Labor line item) | B63: Outcome1 | C63: Unit | D63: =$F$27 -> 165636.99 | E63: 0.6 | F63: =D63*E63 -> 99382.197 | G63: =$H$27 -> 184196.51 | H63: =G63*E63 -> 110517.91 | I63: =$J$27 -> 181306.36 | J63: =I63*E63 -> 108783.82 | K63: =$L$27 -> 150651.34 | L63: =K63*E63 -> 90390.802 | M63: =$N$27 -> 47583.721 | N63: =M63*E63 -> 28550.233 | O63: =F63+H63+J63+L63+N63 -> 437624.95 | P63: 0 | Q63: =SUM(O63:P63) -> 437624.95
A64: Travel 60% | B64: Outcome1 | C64: Unit | D64: =$F$47 -> 18425 | E64: 0.6 | F64: =D64*E64 -> 11055 | G64: =$H$47 -> 14430.75 | H64: =G64*E64 -> 8658.45 | I64: =$J$47 -> 15139.927 | J64: =I64*E64 -> 9083.9565 | K64: =$L$47 -> 15884.193 | L64: =K64*E64 -> 9530.5158 | M64: =$N$47 -> 4814.1041 | N64: =M64*E64 -> 2888.4624 | O64: =F64+H64+J64+L64+N64 -> 41216.385 | P64: 0 | Q64: =SUM(O64:P64) -> 41216.385
A65: Supplies 60% | B65: Outcome1 | C65: Unit | D65: =$F$52 -> 1900 | E65: 0.6 | F65: =D65*E65 -> 1140 | G65: =$H$52 -> 378 | H65: =G65*E65 -> 226.8 | I65: =$J$52 -> 396.9 | J65: =I65*E65 -> 238.14 | K65: =$L$52 -> 416.745 | L65: =K65*E65 -> 250.047 | M65: =$N$52 -> 109.39556 | N65: =M65*E65 -> 65.637338 | O65: =F65+H65+J65+L65+N65 -> 1920.6243 | P65: 0 | Q65: =SUM(O65:P65) -> 1920.6243
A66: Office Expenses 60% | B66: Outcome1 | C66: Unit | D66: =$F$59 -> 3150 | E66: 0.6 | F66: =D66*E66 -> 1890 | G66: =$H$59 -> 3969 | H66: =G66*E66 -> 2381.4 | I66: =$J$59 -> 4167.45 | J66: =I66*E66 -> 2500.47 | K66: =$L$59 -> 4375.8225 | L66: =K66*E66 -> 2625.4935 | M66: =$N$59 -> 1148.6534 | N66: =M66*E66 -> 689.19204 | O66: =F66+H66+J66+L66+N66 -> 10086.556 | P66: 0 | Q66: =SUM(O66:P66) -> 10086.556
A67: 1.1.3.1 Baseline Survey of Key Stakeholder Groups (Pre-Program)
A68: Workshops (focus groups) | B68: Outcome1 | C68: Workshop days | D68: 48 | E68: 350 | F68: =D68*E68 -> 16800 | G68: 0 | H68: =G68*E68 -> 0 | I68: 0 | J68: =I68*E68 -> 0 | K68: 0 | L68: =K68*E68 -> 0 | M68: 0 | N68: =M68*E68 -> 0 | O68: =F68+H68+J68+L68+N68 -> 16800 | P68: 0 | Q68: =SUM(O68:P68) -> 16800
A69: Printing and materials | B69: Outcome1 | C69: Workshop | D69: 125 | E69: 125 | F69: =D69*E69 -> 15625 | G69: 0 | H69: =G69*E69 -> 0 | I69: 0 | J69: =I69*E69 -> 0 | K69: 0 | L69: =K69*E69 -> 0 | M69: 0 | N69: =M69*E69 -> 0 | O69: =F69+H69+J69+L69+N69 -> 15625 | P69: 0 | Q69: =SUM(O69:P69) -> 15625
A70: Online surveys and data analysis subscription fees (monthly) | B70: Outcome1 | C70: Monthly | D70: 10 | E70: 1000 | F70: =D70*E70 -> 10000 | G70: 0 | H70: =G70*E70 -> 0 | I70: 0 | J70: =I70*E70 -> 0 | K70: 0 | L70: =K70*E70 -> 0 | M70: 0 | N70: =M70*E70 -> 0 | O70: =F70+H70+J70+L70+N70 -> 10000 | P70: 0 | Q70: =SUM(O70:P70) -> 10000
A71: Mobile and social media surveys | B71: Outcome1 | C71: Survey campaign | D71: 10 | E71: 500 | F71: =D71*E71 -> 5000 | G71: 0 | H71: =G71*E71 -> 0 | I71: 0 | J71: =I71*E71 -> 0 | K71: 0 | L71: =K71*E71 -> 0 | M71: 0 | N71: =M71*E71 -> 0 | O71: =F71+H71+J71+L71+N71 -> 5000 | P71: 0 | Q71: =SUM(O71:P71) -> 5000
A72: Stipends for worker canvassers and participation incentives | B72: Outcome1 | C72: Person | D72: 500 | E72: 25 | F72: =D72*E72 -> 12500 | G72: 0 | H72: =G72*E72 -> 0 | I72: 0 | J72: =I72*E72 -> 0 | K72: 0 | L72: =K72*E72 -> 0 | M72: 0 | N72: =M72*E72 -> 0 | O72: =F72+H72+J72+L72+N72 -> 12500 | P72: 0 | Q72: =SUM(O72:P72) -> 12500
A73: 1.1.3.2 Mass and social media campaigns for workers and the general populace
A74: Stakeholder Focus Group workshops | B74: Outcome1 | C74: Workshop days | D74: 0 | E74: 300 | F74: =D74*E74 -> 0 | G74: 30 | H74: =G74*E74 -> 9000 | I74: 30 | J74: =I74*E74 -> 9000 | K74: 20 | L74: =K74*E74 -> 6000 | M74: 0 | N74: =M74*E74 -> 0 | O74: =F74+H74+J74+L74+N74 -> 24000 | P74: 0 | Q74: =SUM(O74:P74) -> 24000
A75: Printing and materials for Focus Group workshops | B75: Outcome1 | C75: Workshop | D75: 0 | E75: 175 | F75: =D75*E75 -> 0 | G75: 15 | H75: =G75*E75 -> 2625 | I75: 15 | J75: =I75*E75 -> 2625 | K75: 10 | L75: =K75*E75 -> 1750 | M75: 0 | N75: =M75*E75 -> 0 | O75: =F75+H75+J75+L75+N75 -> 7000 | P75: 0 | Q75: =SUM(O75:P75) -> 7000
A76: Prototypes of videos, multi-media campaigns | B76: Outcome1 | C76: Portfolio by state | D76: 0 | E76: 500 | F76: =D76*E76 -> 0 | G76: 6 | H76: =G76*E76 -> 3000 | I76: 6 | J76: =I76*E76 -> 3000 | K76: 6 | L76: =K76*E76 -> 3000 | M76: 0 | N76: =M76*E76 -> 0 | O76: =F76+H76+J76+L76+N76 -> 9000 | P76: 0 | Q76: =SUM(O76:P76) -> 9000
A77: Consultant: Multi-Media Specialist | B77: Outcome1 | C77: Contract | D77: 1 | E77: 2600 | F77: =D77*E77 -> 2600 | G77: 1 | H77: =G77*E77 -> 2600 | I77: 1 | J77: =I77*E77 -> 2600 | K77: 1 | L77: =K77*E77 -> 2600 | M77: 0 | N77: =M77*E77 -> 0 | O77: =F77+H77+J77+L77+N77 -> 10400 | P77: 0 | Q77: =SUM(O77:P77) -> 10400
A78: 1.1.3.3 On-Line Webinars for the Business Sector
A79: Short video and app development and editing fees (for online training) | B79: Outcome1 | C79: Portfolio by state | D79: 0 | E79: 1000 | F79: =D79*E79 -> 0 | G79: 5 | H79: =G79*E79 -> 5000 | I79: 5 | J79: =I79*E79 -> 5000 | K79: 5 | L79: =K79*E79 -> 5000 | M79: 0 | N79: =M79*E79 -> 0 | O79: =F79+H79+J79+L79+N79 -> 15000 | P79: 0 | Q79: =SUM(O79:P79) -> 15000
A80: Online data analysis subscription fees (monthly) | B80: Outcome1 | C80: Unit | D80: 0 | E80: 200 | F80: =D80*E80 -> 0 | G80: 0 | H80: =G80*E80 -> 0 | I80: 0 | J80: =I80*E80 -> 0 | K80: 12 | L80: =K80*E80 -> 2400 | M80: 3 | N80: =M80*E80 -> 600 | O80: =F80+H80+J80+L80+N80 -> 3000 | P80: 0 | Q80: =SUM(O80:P80) -> 3000
A81: Mobile and social media engagement campaigns | B81: Outcome1 | C81: Campaign | D81: 0 | E81: 500 | F81: =D81*E81 -> 0 | G81: 10 | H81: =G81*E81 -> 5000 | I81: 15 | J81: =I81*E81 -> 7500 | K81: 10 | L81: =K81*E81 -> 5000 | M81: 5 | N81: =M81*E81 -> 2500 | O81: =F81+H81+J81+L81+N81 -> 20000 | P81: 0 | Q81: =SUM(O81:P81) -> 20000
A82: Online Training System | B82: Outcome1 | C82: Unit | D82: 0 | E82: 40 | F82: =D82*E82 -> 0 | G82: 3000 | H82: =G82*E82 -> 120000 | I82: 3000 | J82: =I82*E82 -> 120000 | K82: 3000 | L82: =K82*E82 -> 120000 | M82: 300 | N82: =M82*E82 -> 12000 | O82: =F82+H82+J82+L82+N82 -> 372000 | P82: 0 | Q82: =SUM(O82:P82) -> 372000
A84: Direct Costs Total for Outcome 1 | F84: =SUM(F63:F82) -> 175992.2 | H84: =SUM(H63:H82) -> 269009.56 | J84: =SUM(J63:J82) -> 270331.38 | L84: =SUM(L63:L82) -> 248546.86 | N84: =SUM(N63:N82) -> 47293.525 | O84: =F84+H84+J84+L84+N84 -> 1011173.5 | P84: =SUM(P63:P82) -> 0 | Q84: =SUM(O84:P84) -> 1011173.5
A86: Total Indirect Costs (De Minimis 10%) for Outcome 1 | B86: Indirect Charges | E86: 0.1 | F86: =(F84)*E86 -> 17599.22 | H86: =(H84)*E86 -> 26900.956 | J86: =(J84)*E86 -> 27033.138 | L86: =(L84)*E86 -> 24854.686 | N86: =(N84)*E86 -> 4729.3525 | O86: =SUM(F86+H86+J86+L86+N86) -> 101117.35 | P86: 0 | Q86: =SUM(O86:P86) -> 101117.35
A88: Subtotal Outcome 1 | F88: =SUM(F84:F86) -> 193591.42 | H88: =SUM(H84:H86) -> 295910.51 | J88: =SUM(J84:J86) -> 297364.52 | L88: =SUM(L84:L86) -> 273401.54 | N88: =SUM(N84:N86) -> 52022.877 | O88: =F88+H88+J88+L88+N88 -> 1112290.9 | P88: =SUM(P68:P68) -> 0 | Q88: =SUM(O88:P88) -> 1112290.9
A89: Outcome 2: Build the capacity of the federal and state level Secretariat of Labor and Social Welfare (Secretaría de Trabajo y Prevención Social or STPS) staff and constituents from key institutions to conduct outreach regarding labor rights and implementation of the labor reforms among target audiences.
A90: Activities/Costs
A91: Personnel & Fringe (35% of Direct Labor line item) | B91: Outcome2 | C91: Unit | D91: =$F$27 -> 165636.99 | E91: 0.35 | F91: =D91*E91 -> 57972.948 | G91: =$H$27 -> 184196.51 | H91: =G91*E91 -> 64468.778 | I91: =$J$27 -> 181306.36 | J91: =I91*E91 -> 63457.225 | K91: =$L$27 -> 150651.34 | L91: =K91*E91 -> 52727.968 | M91: =$N$27 -> 47583.721 | N91: =M91*E91 -> 16654.302 | O91: =F91+H91+J91+L91+N91 -> 255281.22 | P91: 0 | Q91: =SUM(O91:P91) -> 255281.22
A92: Travel 35% | B92: Outcome2 | C92: Unit | D92: =$F$47 -> 18425 | E92: 0.35 | F92: =D92*E92 -> 6448.75 | G92: =$H$47 -> 14430.75 | H92: =G92*E92 -> 5050.7625 | I92: =$J$47 -> 15139.927 | J92: =I92*E92 -> 5298.9746 | K92: =$L$47 -> 15884.193 | L92: =K92*E92 -> 5559.4676 | M92: =$N$47 -> 4814.1041 | N92: =M92*E92 -> 1684.9364 | O92: =F92+H92+J92+L92+N92 -> 24042.891 | P92: 0 | Q92: =SUM(O92:P92) -> 24042.891
A93: Supplies 35% | B93: Outcome2 | C93: Unit | D93: =$F$52 -> 1900 | E93: 0.35 | F93: =D93*E93 -> 665 | G93: =$H$52 -> 378 | H93: =G93*E93 -> 132.3 | I93: =$J$52 -> 396.9 | J93: =I93*E93 -> 138.915 | K93: =$L$52 -> 416.745 | L93: =K93*E93 -> 145.86075 | M93: =$N$52 -> 109.39556 | N93: =M93*E93 -> 38.288447 | O93: =F93+H93+J93+L93+N93 -> 1120.3642 | P93: 0 | Q93: =SUM(O93:P93) -> 1120.3642
A94: Office Expenses 35% | B94: Outcome2 | C94: Unit | D94: =$F$59 -> 3150 | E94: 0.35 | F94: =D94*E94 -> 1102.5 | G94: =$H$59 -> 3969 | H94: =G94*E94 -> 1389.15 | I94: =$J$59 -> 4167.45 | J94: =I94*E94 -> 1458.6075 | K94: =$L$59 -> 4375.8225 | L94: =K94*E94 -> 1531.5379 | M94: =$N$59 -> 1148.6534 | N94: =M94*E94 -> 402.02869 | O94: =F94+H94+J94+L94+N94 -> 5883.8241 | P94: 0 | Q94: =SUM(O94:P94) -> 5883.8241
A95: 2.1.1 Initial communications capacity assessment of STPS & peer institutions
A96: Training and Stakeholder Consultation workshops | B96: Outcome1 | C96: Unit | D96: 4 | E96: 300 | F96: =D96*E96 -> 1200 | G96: 12 | H96: =G96*E96 -> 3600 | I96: 12 | J96: =I96*E96 -> 3600 | K96: 12 | L96: =K96*E96 -> 3600 | M96: 2 | N96: =M96*E96 -> 600 | O96: =F96+H96+J96+L96+N96 -> 12600 | P96: 0 | Q96: =SUM(O96:P96) -> 12600
A97: Printing and materials for Focus Group workshops | B97: Outcome1 | C97: Unit | D97: 4 | E97: 200 | F97: =D97*E97 -> 800 | G97: 12 | H97: =G97*E97 -> 2400 | I97: 12 | J97: =I97*E97 -> 2400 | K97: 12 | L97: =K97*E97 -> 2400 | M97: 2 | N97: =M97*E97 -> 400 | O97: =F97+H97+J97+L97+N97 -> 8400 | P97: 0 | Q97: =SUM(O97:P97) -> 8400
A98: 2.1.2 Delivery of Capacity-Building Activities
A99: Short video and app development fees (training govt how to deploy) | B99: Outcome1 | C99: Unit | D99: 0 | E99: 900 | F99: =D99*E99 -> 0 | G99: 12 | H99: =G99*E99 -> 10800 | I99: 12 | J99: =I99*E99 -> 10800 | K99: 12 | L99: =K99*E99 -> 10800 | M99: 6 | N99: =M99*E99 -> 5400 | O99: =F99+H99+J99+L99+N99 -> 37800 | P99: 0 | Q99: =SUM(O99:P99) -> 37800
A100: Social media subscription and campaign placement fees (training govt how to deploy) | B100: Outcome1 | C100: Unit | D100: 3 | E100: 1000 | F100: =D100*E100 -> 3000 | G100: 12 | H100: =G100*E100 -> 12000 | I100: 12 | J100: =I100*E100 -> 12000 | K100: 12 | L100: =K100*E100 -> 12000 | M100: 6 | N100: =M100*E100 -> 6000 | O100: =F100+H100+J100+L100+N100 -> 45000 | P100: 0 | Q100: =SUM(O100:P100) -> 45000
A101: Data analysis and management portal (prototyping for govt) | B101: Outcome1 | C101: Unit | D101: 0 | E101: 500 | F101: =D101*E101 -> 0 | G101: 12 | H101: =G101*E101 -> 6000 | I101: 12 | J101: =I101*E101 -> 6000 | K101: 12 | L101: =K101*E101 -> 6000 | M101: 6 | N101: =M101*E101 -> 3000 | O101: =F101+H101+J101+L101+N101 -> 21000 | P101: 0 | Q101: =SUM(O101:P101) -> 21000
A102: Online Training System | B102: Outcome1 | C102: Unit | D102: 10 | E102: 25 | F102: =D102*E102 -> 250 | G102: 130 | H102: =G102*E102 -> 3250 | I102: 130 | J102: =I102*E102 -> 3250 | K102: 130 | L102: =K102*E102 -> 3250 | M102: 100 | N102: =M102*E102 -> 2500 | O102: =F102+H102+J102+L102+N102 -> 12500 | P102: 0 | Q102: =SUM(O102:P102) -> 12500
A104: Direct Costs Total for Outcome 2 | F104: =SUM(F91:F102) -> 71439.198 | H104: =SUM(H91:H102) -> 109090.99 | J104: =SUM(J91:J102) -> 108403.72 | L104: =SUM(L91:L102) -> 98014.834 | N104: =SUM(N91:N102) -> 36679.556 | O104: =F104+H104+J104+L104+N104 -> 423628.3 | P104: =SUM(P91:P102) -> 0 | Q104: =SUM(O104:P104) -> 423628.3
A106: Total Indirect Costs (De Minimis 10%) for Outcome 2 | B106: Indirect Charges | E106: 0.1 | F106: =F104*E106 -> 7143.9198 | H106: =H104*E106 -> 10909.099 | J106: =J104*E106 -> 10840.372 | L106: =L104*E106 -> 9801.4834 | N106: =N104*E106 -> 3667.9556 | O106: =SUM(F106+H106+J106+L106+N106) -> 42362.83 | P106: 0 | Q106: =SUM(O106:P106) -> 42362.83
A108: Subtotal Outcome 2 | F108: =F104+F106 -> 78583.118 | H108: =H104+H106 -> 120000.09 | J108: =J104+J106 -> 119244.09 | L108: =L104+L106 -> 107816.32 | N108: =N104+N106 -> 40347.512 | O108: =F108+H108+J108+L108+N108 -> 465991.13 | P108: =P106 -> 0 | Q108: =SUM(O108:P108) -> 465991.13
...

Sheet SF-424 Cost Categories
B2: Category | C2: TOTAL USDOL
B3: Salaries | C3: =SUMIF(Category,B3,TotalDOL) -> 1640410.6
B4: Fringe Benefits | C4: =SUMIF(Category,"Fringe Benefits",TotalDOL) -> 663469.72
B5: Travel | C5: =SUMIF(Category,"Travel",TotalDOL) -> 265175.3
B6: Equipment | C6: =SUMIF(Category,"Equipment",TotalDOL) -> 4500
B7: Supplies | C7: =SUMIF(Category,"Supplies",TotalDOL) -> 255404.78
B8: Contractual | C8: =SUMIF(Category,"Contractual",TotalDOL) -> 3441032.7
B9: Other Direct Charges | C9: =SUMIF(Category,"Other",TotalDOL) -> 1429218.7
B10: Indirect Charges | C10: =SUMIF(Category,"Indirect Charges",TotalDOL) -> 2229388.6
B12: TOTAL | C12: =SUM(C3:C10) -> 9928600.5
