Workbook
Name \a: '[1]CUADRO No 4'!#REF!
Name \c: #REF!
Name \i: #REF!
Name \P: #REF!
Name \r: #REF!
Name __pd1: [2]Rates!$J$24
Name __pd6: [2]Rates!$J$30
Name __tix1: [2]Rates!$J$40
Name __tix2: [2]Rates!$J$41
Name __tix6: [2]Rates!$J$47
Name _1: #REF!
Name _1998: #REF!
Name _1999: #REF!
Name _2: #REF!
Name _2000: #REF!
Name _2001: #REF!
Name _2002: #REF!
Name _3: #REF!
Name _4: #REF!
Name _5: #REF!
Name _6: #REF!
Name _7: #REF!
Name _8: #REF!
Name _fmi1: [3]PAGOFMI!$A$1:$L$51
Name _fmi2: [3]PAGOFMI!$P$1:$AA$51
Name _fmi3: [3]PAGORES!$AC$1:$AN$43
Name _fmi4: [3]PAGORES!$AP$1:$BA$44
Name _PIB01: [4]SUPUESTOS!#REF!
Name _PIB02: [5]SUPUESTOS!#REF!
Name _PIB95: [4]SUPUESTOS!$J$47
Name _PIB96: [4]SUPUESTOS!$K$47
Name _PIB97: [6]SUPUESTOS!$L$47
Name _PIB98: [6]SUPUESTOS!$M$47
Name _PIB99: [6]SUPUESTOS!$N$47
Name _RES9397: #REF!
Name _rez2: '[3]PAGOS VIGENCIA t'!$A$57:$AH$108
Name _rez3: [3]PAGORES!$A$1:$M$37
Name _rez4: [3]PAGORES!$O$1:$AN$43
Name a: #REF!
Name A_2002: #REF!
Name A_CAPITAL: [9]Hoja4!$B$3:$O$34
Name A_DEPTOS: [9]Hoja4!$B$76:$N$108
Name A_impresión_IM: #REF!
Name A_MUNPIOS: [9]Hoja4!$B$39:$N$71
Name AAA: [10]proyecINGRESOS99!$L$1:$T$97
Name AEFormar: [11]Variables!$C$5
Name Ajustado: #REF!
Name almuerzo: [11]Variables!$C$18
Name alquilertableta: [11]Variables!$C$21
Name ANEXO_No.: #REF!
Name ANEXO_No._5: #REF!
Name ANPDH: '[12]Salary & PR Tax'!#REF!
Name aprnac: [13]GASTOS!#REF!
Name APROPIACIONES_PAC_Y_REZAGO_1999___2000: #REF!
Name aprprp: [13]GASTOS!#REF!
Name asigbas: #REF!
Name asigbasempu: #REF!
Name asigbasisten: #REF!
Name asigmen: #REF!
Name auxalm: #REF!

Sheet 800-FC - Detailed Changes
G1: ESTOY REUBICANDO LA LÍNEA | I1: Letra en rojo, significa cambiar la denominación del ítem
G2: LÍNEA NUEVA | I2: LÍNEA QUE SE VA
A4: Entity: | B4: P
A5: Program-Dept.: | B5: 20300 | G5: Initial Budget Assumptions | L5: Modification 7 - Budget Assumptions
A6: Funder-Grant: | B6: USAID800 | G6: Inflation - Locally Purchased Goods/Services - 3% | H6: 1.03 | L6: Inflation - Locally Purchased Goods/Services | M6: 0.08
G7: Merit Based Increases for HQ & Field Staff - 4% | H7: 1.04 | L7: Merit Based Increases for HQ & Field Staff | M7: 0.1
G9: *Key Personnel | J9: Actuals/Estimates Year 1 and 2 and 3 (January 1, 2023 - December 31, 2023) | P9: Projections for Year 3 (January 1, 2024 - December 31, 2024) - 6 | AO9: New Proposed Budget Total
A10: Sage Activity | B10: Sage Object Code/ Line Item | C10: Country Code (DC=0 or CO) | D10: Office Code (DC=0 or CO) | E10: Subcontract Code | F10: Open 1 Code | G10: Line Items | J10: USAID Year 1 -Actuals August 16, 2021 - December 31, 2021 | K10: Leverage Year 1 - Actuals August 16, 2021 - December 31, 2021 | L10: USAID Year 2 - Actuals January 1, 2022 - December 31, 2022 | M10: Leverage Year 2 - Actuals January 1, 2022 - December 31, 2022 | N10: USAID Year 3 - Actuals January 1, 2023 - December 31, 2023 | O10: Leverage Year 3 - Actuals January 1, 2023 - July 31, 2023 | P10: Year 4 - January 1, 2024 - December 31, 2024 | V10: Year 5 - January 1, 2025 - December 31, 2025 | AB10: Year 6 - January 1, 2026 - Agosto 31, 2026 | AH10: Actuals Year 1- 3 | AI10: Actuals Year 1- 3 | AJ10: Actuals Year 1- 3 | AK10: Year 4- 6 | AL10: Year 4- 6 | AM10: Year 4- 6 | AO10: Total | AP10: Total | AQ10: Grand
P11: Unit LOE | Q11: Cost | R11: Duration | S11: USAID | T11: Leverage | U11: Total | V11: Unit LOE | W11: Cost | X11: Duration | Y11: USAID | Z11: Leverage | AA11: Total | AB11: Unit | AC11: Cost | AD11: Duration | AE11: USAID | AF11: Leverage | AG11: Total | AH11: Total USAID | AI11: Total Leverage | AJ11: Grand Total | AK11: Total USAID | AL11: Total Leverage | AM11: Grand Total | AO11: USAID | AP11: Leverage | AQ11: Total
G12: Personnel | H12: 1. Personnel
G13: Headquarters Personnel (include Level of Effort) | H13: Headquarters Personnel (include Level of Effort)
G14: Fundación Carvajal Office (Cali) | H14: Fundación Carvajal Management Team
A15: SUBFCARVA | B15: 89050 | C15: COL2 | D15: COL2 | E15: CARVAJAL | F15: FCPERSNL/ FCPERSNLEV | G15: Program Director | H15: Program Director | I15: David Gironza | J15: 9207.63 | K15: 1087.7 | L15: 21864.25 | M15: 0 | N15: 16983.86 | O15: 8197.2 | P15: 0 | Q15: 0 | R15: 0 | S15: 0 | T15: 0 | U15: 0 | V15: 0 | W15: =+Q15*10%+Q15 -> 0 | X15: 0 | Y15: 0 | Z15: 0 | AA15: 0 | AB15: 0 | AC15: 0 | AD15: 0 | AE15: 0 | AF15: 0 | AG15: =+AE15+AF15 -> 0 | AH15: =+J15+L15+N15 -> 48055.74 | AI15: =+K15+M15+O15 -> 9284.9 | AJ15: =+AH15+AI15 -> 57340.64 | AK15: =+S15+Y15+AE15 -> 0 | AL15: =+T15+Z15+AF15 -> 0 | AM15: =+AK15+AL15 -> 0 | AO15: =+AH15+AK15 -> 48055.74 | AP15: =+AI15+AL15 -> 9284.9 | AQ15: =+AO15+AP15 -> 57340.64
H16: Management Team | I16: TBD (Marcela Astudillo, Erika Acevedo, Aura Aydé García) | J16: 0 | K16: 0 | L16: 0 | M16: 0 | N16: 0 | O16: 0 | P16: 0.26 | Q16: 1641.45 | R16: 10.5 | S16: =Q16*R16 -> 17235.225 | T16: =704.89*R16 -> 7401.345 | U16: =SUM(S16:T16) -> 24636.57 | V16: 0.5 | W16: =+Q16*10%+Q16 -> 1805.595 | X16: 12 | Y16: =+W16*X16 -> 21667.14 | Z16: =+T16*1.1 -> 8141.4795 | AA16: =SUM(Y16:Z16) -> 29808.62 | AB16: 0.5 | AC16: =+W16*1.1 -> 1986.1545 | AD16: 8 | AE16: =AB16*AC16*AD16 -> 7944.618 | AF16: =+(Z16*1.1)/12*8 -> 5970.4183 | AG16: =SUM(AE16:AF16) -> 13915.036 | AH16: =+J16+L16+N16 -> 0 | AI16: =+K16+M16+O16 -> 0 | AJ16: =+AH16+AI16 -> 0 | AK16: =+S16+Y16+AE16 -> 46846.983 | AL16: =+T16+Z16+AF16 -> 21513.243 | AM16: =+AK16+AL16 -> 68360.226 | AO16: =+AH16+AK16 -> 46846.983 | AP16: =+AI16+AL16 -> 21513.243 | AQ16: =+AO16+AP16 -> 68360.226
A17: SUBFCARVA | B17: 89050 | C17: COL2 | D17: COL2 | E17: CARVAJAL | F17: FCPERSNL | G17: Education Director* | H17: Education Director* | I17: Paola Trujillo | J17: 4793.31 | K17: 0 | L17: 37385.23 | M17: 0 | N17: 0 | O17: 0 | P17: 0 | Q17: 0 | R17: 0 | S17: =Q17*R17 -> 0 | T17: 0 | U17: =SUM(S17:T17) -> 0 | V17: 0 | W17: =+Q17*10%+Q17 -> 0 | X17: 0 | Y17: =+W17*X17 -> 0 | Z17: 0 | AA17: =SUM(Y17:Z17) -> 0 | AB17: 0 | AC17: 0 | AD17: 0 | AE17: =AB17*AC17*AD17 -> 0 | AF17: 0 | AG17: =SUM(AE17:AF17) -> 0 | AH17: =+J17+L17+N17 -> 42178.54 | AI17: =+K17+M17+O17 -> 0 | AJ17: =+AH17+AI17 -> 42178.54 | AK17: =+S17+Y17+AE17 -> 0 | AL17: =+T17+Z17+AF17 -> 0 | AM17: =+AK17+AL17 -> 0 | AO17: =+AH17+AK17 -> 42178.54 | AP17: =+AI17+AL17 -> 0 | AQ17: =+AO17+AP17 -> 42178.54
G18: Education Director* | H18: Education Director* | I18: Catalina Prada | J18: 0 | K18: 0 | L18: 0 | M18: 0 | N18: 41755.1 | O18: 0 | P18: 1 | Q18: 4172.84 | R18: 12 | S18: =Q18*R18 -> 50074.08 | T18: 0 | U18: =SUM(S18:T18) -> 50074.08 | V18: 1 | W18: =+Q18*10%+Q18 -> 4590.124 | X18: 12 | Y18: =+W18*X18 -> 55081.488 | Z18: 0 | AA18: =SUM(Y18:Z18) -> 55081.488 | AB18: 1 | AC18: =+W18*10%+W18 -> 5049.1364 | AD18: 8 | AE18: =AB18*AC18*AD18 -> 40393.091 | AF18: 0 | AG18: =SUM(AE18:AF18) -> 40393.091 | AH18: =+J18+L18+N18 -> 41755.1 | AI18: =+K18+M18+O18 -> 0 | AJ18: =+AH18+AI18 -> 41755.1 | AK18: =+S18+Y18+AE18 -> 145548.66 | AL18: =+T18+Z18+AF18 -> 0 | AM18: =+AK18+AL18 -> 145548.66 | AO18: =+AH18+AK18 -> 187303.76 | AP18: =+AI18+AL18 -> 0 | AQ18: =+AO18+AP18 -> 187303.76
G19: Project Office (Bogotá) | H19: Core Technical Team | AH19: =+J19+L19+N19 -> 0 | AI19: =+K19+M19+O19 -> 0 | AJ19: =+AH19+AI19 -> 0 | AK19: =+S19+Y19+AE19 -> 0 | AL19: =+T19+Z19+AF19 -> 0 | AM19: =+AK19+AL19 -> 0 | AO19: =+AH19+AK19 -> 0 | AP19: =+AI19+AL19 -> 0 | AQ19: =+AO19+AP19 -> 0
A20: SUBFCARVA | B20: 89050 | C20: COL2 | D20: COL2 | E20: CARVAJAL | F20: FCPERSNL | G20: Education Manager | H20: Education Manager | I20: Catalina Prada | J20: 8591.19 | K20: 0 | L20: 21376.46 | M20: 0 | N20: 0 | O20: 0 | P20: 0 | Q20: 0 | R20: 0 | S20: =+Q20*R20 -> 0 | T20: 0 | U20: =SUM(S20:T20) -> 0 | V20: 0 | W20: 0 | X20: 0 | Y20: =+W20*X20 -> 0 | Z20: 0 | AA20: =SUM(Y20:Z20) -> 0 | AB20: 0 | AC20: 0 | AD20: 0 | AE20: =AB20*AC20*AD20 -> 0 | AF20: 0 | AG20: =SUM(AE20:AF20) -> 0 | AH20: =+J20+L20+N20 -> 29967.65 | AI20: =+K20+M20+O20 -> 0 | AJ20: =+AH20+AI20 -> 29967.65 | AK20: =+S20+Y20+AE20 -> 0 | AL20: =+T20+Z20+AF20 -> 0 | AM20: =+AK20+AL20 -> 0 | AO20: =+AH20+AK20 -> 29967.65 | AP20: =+AI20+AL20 -> 0 | AQ20: =+AO20+AP20 -> 29967.65
H21: Education Coordinator | I21: Lisep Castillo | J21: 0 | K21: 0 | L21: 0 | M21: 0 | N21: 14944.37 | O21: 0 | P21: 1 | Q21: 1678.7 | R21: 12 | S21: =+Q21*R21 -> 20144.4 | T21: 0 | U21: =SUM(S21:T21) -> 20144.4 | V21: 1 | W21: =+Q21*10%+Q21 -> 1846.57 | X21: 12 | Y21: =+W21*X21 -> 22158.84 | Z21: 0 | AA21: =SUM(Y21:Z21) -> 22158.84 | AB21: 1 | AC21: =+W21*10%+W21 -> 2031.227 | AD21: 8 | AE21: =AB21*AC21*AD21 -> 16249.816 | AF21: 0 | AG21: =SUM(AE21:AF21) -> 16249.816 | AH21: =+J21+L21+N21 -> 14944.37 | AI21: =+K21+M21+O21 -> 0 | AJ21: =+AH21+AI21 -> 14944.37 | AK21: =+S21+Y21+AE21 -> 58553.056 | AL21: =+T21+Z21+AF21 -> 0 | AM21: =+AK21+AL21 -> 58553.056 | AO21: =+AH21+AK21 -> 73497.426 | AP21: =+AI21+AL21 -> 0 | AQ21: =+AO21+AP21 -> 73497.426
G22: Pre-Primary Education Specialist | H22: Pre-Primary Education Specialist | I22: Lisep Castillo | J22: 1992.97 | K22: 0 | L22: 5558.49 | M22: 0 | N22: 0 | O22: 0 | P22: 0 | Q22: 0 | R22: 0 | S22: =+Q22*R22 -> 0 | T22: 0 | U22: =SUM(S22:T22) -> 0 | V22: 0 | W22: 0 | X22: 0 | Y22: =+W22*X22 -> 0 | Z22: 0 | AA22: =SUM(Y22:Z22) -> 0 | AB22: 0 | AC22: 0 | AD22: 0 | AE22: =AB22*AC22*AD22 -> 0 | AF22: 0 | AG22: =SUM(AE22:AF22) -> 0 | AH22: =+J22+L22+N22 -> 7551.46 | AI22: =+K22+M22+O22 -> 0 | AJ22: =+AH22+AI22 -> 7551.46 | AK22: =+S22+Y22+AE22 -> 0 | AL22: =+T22+Z22+AF22 -> 0 | AM22: =+AK22+AL22 -> 0 | AO22: =+AH22+AK22 -> 7551.46 | AP22: =+AI22+AL22 -> 0 | AQ22: =+AO22+AP22 -> 7551.46
A23: SUBFCARVA | B23: 89050 | C23: COL2 | D23: COL2 | E23: CARVAJAL | F23: FCPERSNL | G23: Pre-Primary Education Specialist | H23: Pre-Primary Education Specialist | I23: Luz Doris Gallego Jiménez | J23: 0 | K23: 0 | L23: 11429.4 | M23: 0 | N23: 16923 | O23: 0 | P23: 1 | Q23: 1645.65 | R23: 12 | S23: =+Q23*R23 -> 19747.8 | T23: 0 | U23: =SUM(S23:T23) -> 19747.8 | V23: 1 | W23: =+Q23*10%+Q23 -> 1810.215 | X23: 12 | Y23: =+W23*X23 -> 21722.58 | Z23: 0 | AA23: =SUM(Y23:Z23) -> 21722.58 | AB23: 1 | AC23: =+W23*10%+W23 -> 1991.2365 | AD23: 6 | AE23: =AB23*AC23*AD23 -> 11947.419 | AF23: 0 | AG23: =SUM(AE23:AF23) -> 11947.419 | AH23: =+J23+L23+N23 -> 28352.4 | AI23: =+K23+M23+O23 -> 0 | AJ23: =+AH23+AI23 -> 28352.4 | AK23: =+S23+Y23+AE23 -> 53417.799 | AL23: =+T23+Z23+AF23 -> 0 | AM23: =+AK23+AL23 -> 53417.799 | AO23: =+AH23+AK23 -> 81770.199 | AP23: =+AI23+AL23 -> 0 | AQ23: =+AO23+AP23 -> 81770.199
A24: SUBFCARVA | B24: 89050 | C24: COL2 | D24: COL2 | E24: CARVAJAL | F24: FCPERSNL | G24: Primary Education Specialist | H24: Primary Education Specialist | I24: Marta Milena Tulcán Tapia | J24: 5796.13 | K24: 0 | L24: 14394.25 | M24: 0 | N24: 15856.88 | O24: 0 | P24: 1 | Q24: 1557.95 | R24: 12 | S24: =+Q24*R24 -> 18695.4 | T24: 0 | U24: =SUM(S24:T24) -> 18695.4 | V24: 1 | W24: =+Q24*10%+Q24 -> 1713.745 | X24: 12 | Y24: =+W24*X24 -> 20564.94 | Z24: 0 | AA24: =SUM(Y24:Z24) -> 20564.94 | AB24: 1 | AC24: =+W24*10%+W24 -> 1885.1195 | AD24: 6 | AE24: =AB24*AC24*AD24 -> 11310.717 | AF24: 0 | AG24: =SUM(AE24:AF24) -> 11310.717 | AH24: =+J24+L24+N24 -> 36047.26 | AI24: =+K24+M24+O24 -> 0 | AJ24: =+AH24+AI24 -> 36047.26 | AK24: =+S24+Y24+AE24 -> 50571.057 | AL24: =+T24+Z24+AF24 -> 0 | AM24: =+AK24+AL24 -> 50571.057 | AO24: =+AH24+AK24 -> 86618.317 | AP24: =+AI24+AL24 -> 0 | AQ24: =+AO24+AP24 -> 86618.317
A25: SUBFCARVA | B25: 89050 | C25: COL2 | D25: COL2 | E25: CARVAJAL | F25: FCPERSNL | G25: Secondary Education Specialist | H25: Secondary Education Specialist | I25: Natalia Suaza | J25: 0 | K25: 0 | L25: 12249.75 | M25: 0 | N25: 17074.28 | O25: 0 | P25: 1 | Q25: 1657.81 | R25: 12 | S25: =+Q25*R25 -> 19893.72 | T25: 0 | U25: =SUM(S25:T25) -> 19893.72 | V25: 1 | W25: =+Q25*10%+Q25 -> 1823.591 | X25: 12 | Y25: =+W25*X25 -> 21883.092 | Z25: 0 | AA25: =SUM(Y25:Z25) -> 21883.092 | AB25: 1 | AC25: =+W25*10%+W25 -> 2005.9501 | AD25: 6 | AE25: =AB25*AC25*AD25 -> 12035.701 | AF25: 0 | AG25: =SUM(AE25:AF25) -> 12035.701 | AH25: =+J25+L25+N25 -> 29324.03 | AI25: =+K25+M25+O25 -> 0 | AJ25: =+AH25+AI25 -> 29324.03 | AK25: =+S25+Y25+AE25 -> 53812.513 | AL25: =+T25+Z25+AF25 -> 0 | AM25: =+AK25+AL25 -> 53812.513 | AO25: =+AH25+AK25 -> 83136.543 | AP25: =+AI25+AL25 -> 0 | AQ25: =+AO25+AP25 -> 83136.543
A26: SUBFCARVA | B26: 89050 | C26: COL2 | D26: COL2 | E26: CARVAJAL | F26: FCPERSNL | G26: Alternative Education Specialist | H26: Alternative Education Specialist | I26: Rufina González | J26: 0 | K26: 0 | L26: 14276.65 | M26: 0 | N26: 11067.62 | O26: 0 | P26: 1 | Q26: 1555.4 | R26: 0 | S26: =+Q26*R26 -> 0 | T26: 0 | U26: =SUM(S26:T26) -> 0 | V26: 1 | W26: =+Q26*10%+Q26 -> 1710.94 | X26: 12 | Y26: =+W26*X26 -> 20531.28 | Z26: 0 | AA26: =SUM(Y26:Z26) -> 20531.28 | AB26: 1 | AC26: =+W26*10%+W26 -> 1882.034 | AD26: 6 | AE26: =AB26*AC26*AD26 -> 11292.204 | AF26: 0 | AG26: =SUM(AE26:AF26) -> 11292.204 | AH26: =+J26+L26+N26 -> 25344.27 | AI26: =+K26+M26+O26 -> 0 | AJ26: =+AH26+AI26 -> 25344.27 | AK26: =+S26+Y26+AE26 -> 31823.484 | AL26: =+T26+Z26+AF26 -> 0 | AM26: =+AK26+AL26 -> 31823.484 | AO26: =+AH26+AK26 -> 57167.754 | AP26: =+AI26+AL26 -> 0 | AQ26: =+AO26+AP26 -> 57167.754
A27: SUBFCARVA | B27: 89050 | C27: COL2 | D27: COL2 | E27: CARVAJAL | F27: FCPERSNL/ FCPERSNLEV | G27: Methodological Coordinator - Flexible Learning Models | H27: Methodological Coordinator/Specialist - MEF | I27: María Eugenia López Maya | J27: 4573.43 | K27: 0 | L27: 12040.88 | M27: 0 | N27: 13903.73 | O27: 0 | P27: 1 | Q27: 1536.1 | R27: 12 | S27: =+Q27*R27 -> 18433.2 | T27: 0 | U27: =SUM(S27:T27) -> 18433.2 | V27: 1 | W27: =+Q27*10%+Q27 -> 1689.71 | X27: 12 | Y27: =+W27*X27 -> 20276.52 | Z27: 0 | AA27: =SUM(Y27:Z27) -> 20276.52 | AB27: 1 | AC27: =+W27*10%+W27 -> 1858.681 | AD27: 6 | AE27: =AB27*AC27*AD27 -> 11152.086 | AF27: 0 | AG27: =SUM(AE27:AF27) -> 11152.086 | AH27: =+J27+L27+N27 -> 30518.04 | AI27: =+K27+M27+O27 -> 0 | AJ27: =+AH27+AI27 -> 30518.04 | AK27: =+S27+Y27+AE27 -> 49861.806 | AL27: =+T27+Z27+AF27 -> 0 | AM27: =+AK27+AL27 -> 49861.806 | AO27: =+AH27+AK27 -> 80379.846 | AP27: =+AI27+AL27 -> 0 | AQ27: =+AO27+AP27 -> 80379.846
H28: Learning Trajectories Manager | I28: Jorge Alberto Riveros | J28: 0 | K28: 0 | L28: 17164.83 | M28: 0 | N28: 23283.11 | O28: 0 | P28: 1 | Q28: 2269.38 | R28: 12 | S28: =+Q28*R28 -> 27232.56 | T28: 0 | U28: =SUM(S28:T28) -> 27232.56 | V28: 1 | W28: =+Q28*10%+Q28 -> 2496.318 | X28: 12 | Y28: =+W28*X28 -> 29955.816 | Z28: 0 | AA28: =SUM(Y28:Z28) -> 29955.816 | AB28: 1 | AC28: =+W28*10%+W28 -> 2745.9498 | AD28: 6 | AE28: =AB28*AC28*AD28 -> 16475.699 | AF28: 0 | AG28: =SUM(AE28:AF28) -> 16475.699 | AH28: =+J28+L28+N28 -> 40447.94 | AI28: =+K28+M28+O28 -> 0 | AJ28: =+AH28+AI28 -> 40447.94 | AK28: =+S28+Y28+AE28 -> 73664.075 | AL28: =+T28+Z28+AF28 -> 0 | AM28: =+AK28+AL28 -> 73664.075 | AO28: =+AH28+AK28 -> 114112.01 | AP28: =+AI28+AL28 -> 0 | AQ28: =+AO28+AP28 -> 114112.01
H29: Migration Officer | I29: Lecsy Bibiana Avendaño | J29: 0 | K29: 0 | L29: 0 | M29: 0 | N29: 0 | O29: 0 | P29: 1 | Q29: 993.99 | R29: 10 | S29: =+Q29*R29 -> 9939.9 | T29: 0 | U29: =SUM(S29:T29) -> 9939.9 | V29: 1 | W29: =+Q29*10%+Q29 -> 1093.389 | X29: 12 | Y29: =+W29*X29 -> 13120.668 | Z29: 0 | AA29: =SUM(Y29:Z29) -> 13120.668 | AB29: 1 | AC29: =+W29*10%+W29 -> 1202.7279 | AD29: 6 | AE29: =AB29*AC29*AD29 -> 7216.3674 | AF29: 0 | AG29: =SUM(AE29:AF29) -> 7216.3674 | AH29: =+J29+L29+N29 -> 0 | AI29: =+K29+M29+O29 -> 0 | AJ29: =+AH29+AI29 -> 0 | AK29: =+S29+Y29+AE29 -> 30276.935 | AL29: =+T29+Z29+AF29 -> 0 | AM29: =+AK29+AL29 -> 30276.935 | AO29: =+AH29+AK29 -> 30276.935 | AP29: =+AI29+AL29 -> 0 | AQ29: =+AO29+AP29 -> 30276.935
G30: Subtotal HQ Personnel | H30: Subtotal HQ + Core Technical Team Personnel | J30: =+SUM(J15:J29) -> 34954.66 | K30: =+SUM(K15:K29) -> 1087.7 | L30: =+SUM(L15:L29) -> 167740.19 | M30: =+SUM(M15:M29) -> 0 | N30: =+SUM(N15:N29) -> 171791.95 | O30: =+SUM(O15:O29) -> 8197.2 | Q30: =+SUM(Q15:Q29) -> 18709.27 | S30: =+SUM(S15:S29) -> 201396.29 | T30: =+SUM(T15:T29) -> 7401.345 | U30: =+SUM(U15:U29) -> 208797.63 | W30: =+SUM(W15:W29) -> 20580.197 | Y30: =+SUM(Y15:Y29) -> 246962.36 | Z30: =+SUM(Z15:Z29) -> 8141.4795 | AA30: =+SUM(AA15:AA29) -> 255103.84 | AC30: =+SUM(AC15:AC29) -> 22638.217 | AE30: =+SUM(AE15:AE29) -> 146017.72 | AF30: =+SUM(AF15:AF29) -> 5970.4183 | AG30: =+SUM(AG15:AG29) -> 151988.14 | AH30: =+SUM(AH15:AH29) -> 374486.8 | AI30: =+SUM(AI15:AI29) -> 9284.9 | AJ30: =+SUM(AJ15:AJ29) -> 383771.7 | AK30: =+SUM(AK15:AK29) -> 594376.37 | AL30: =+SUM(AL15:AL29) -> 21513.243 | AM30: =+SUM(AM15:AM29) -> 615889.61 | AO30: =+SUM(AO15:AO29) -> 968863.17 | AP30: =+SUM(AP15:AP29) -> 30798.143 | AQ30: =+SUM(AQ15:AQ29) -> 999661.31
G31: Field Personnel (include Level of Effort) | H31: Field Personnel
H32: M&E Team | I32: M&E Team
A33: SUBFCARVA | B33: 89050 | C33: COL2 | D33: COL2 | E33: CARVAJAL | F33: FCPERSNL | G33: Monitoring and Evaluation Specialist | H33: Monitoring and Evaluation Specialist | I33: Ángela Patricia Bedoya Valdés | J33: 5221.52 | K33: 0 | L33: 13894.7 | M33: 0 | N33: 15216.99 | O33: 0 | P33: 1 | Q33: 1495.08 | R33: 12 | S33: =+Q33*R33 -> 17940.96 | T33: 0 | U33: =SUM(S33:T33) -> 17940.96 | V33: 1 | W33: =+Q33*10%+Q33 -> 1644.588 | X33: 12 | Y33: =+W33*X33 -> 19735.056 | Z33: 0 | AA33: =SUM(Y33:Z33) -> 19735.056 | AB33: 1 | AC33: =+W33*10%+W33 -> 1809.0468 | AD33: 8 | AE33: =AB33*AC33*AD33 -> 14472.374 | AF33: 0 | AG33: =SUM(AE33:AF33) -> 14472.374 | AH33: =+J33+L33+N33 -> 34333.21 | AI33: =+K33+M33+O33 -> 0 | AJ33: =+AH33+AI33 -> 34333.21 | AK33: =+S33+Y33+AE33 -> 52148.39 | AL33: =+T33+Z33+AF33 -> 0 | AM33: =+AK33+AL33 -> 52148.39 | AO33: =+AH33+AK33 -> 86481.6 | AP33: =+AI33+AL33 -> 0 | AQ33: =+AO33+AP33 -> 86481.6
A34: SUBFCARVA | B34: 89050 | C34: COL2 | D34: COL2 | E34: CARVAJAL | F34: FCPERSNL | G34: Information System Professional | H34: Information System Professional | I34: Isabella Ríos | J34: 3794.35 | K34: 0 | L34: 9100.49 | M34: 0 | N34: 1087.16 | O34: 0 | P34: 0 | Q34: 0 | R34: 0 | S34: =+Q34*R34 -> 0 | T34: 0 | U34: =SUM(S34:T34) -> 0 | V34: 0 | W34: 0 | X34: 0 | Y34: =+W34*X34 -> 0 | Z34: 0 | AA34: =SUM(Y34:Z34) -> 0 | AB34: 0 | AC34: 0 | AD34: 0 | AE34: =AB34*AC34*AD34 -> 0 | AF34: 0 | AG34: =SUM(AE34:AF34) -> 0 | AH34: =+J34+L34+N34 -> 13982 | AI34: =+K34+M34+O34 -> 0 | AJ34: =+AH34+AI34 -> 13982 | AK34: =+S34+Y34+AE34 -> 0 | AL34: =+T34+Z34+AF34 -> 0 | AM34: =+AK34+AL34 -> 0 | AO34: =+AH34+AK34 -> 13982 | AP34: =+AI34+AL34 -> 0 | AQ34: =+AO34+AP34 -> 13982
H35: Information System Professional | I35: Carolina Rojas Sánchez | J35: 0 | K35: 0 | L35: 8194.5 | M35: 0 | N35: 10865.45 | O35: 0 | P35: 1 | Q35: 1054.97 | R35: 12 | S35: =+Q35*R35 -> 12659.64 | T35: 0 | U35: =SUM(S35:T35) -> 12659.64 | V35: 1 | W35: =+Q35*10%+Q35 -> 1160.467 | X35: 12 | Y35: =+W35*X35 -> 13925.604 | Z35: 0 | AA35: =SUM(Y35:Z35) -> 13925.604 | AB35: 1 | AC35: =+W35*10%+W35 -> 1276.5137 | AD35: 6 | AE35: =AB35*AC35*AD35 -> 7659.0822 | AF35: 0 | AG35: =SUM(AE35:AF35) -> 7659.0822 | AH35: =+J35+L35+N35 -> 19059.95 | AI35: =+K35+M35+O35 -> 0 | AJ35: =+AH35+AI35 -> 19059.95 | AK35: =+S35+Y35+AE35 -> 34244.326 | AL35: =+T35+Z35+AF35 -> 0 | AM35: =+AK35+AL35 -> 34244.326 | AO35: =+AH35+AK35 -> 53304.276 | AP35: =+AI35+AL35 -> 0 | AQ35: =+AO35+AP35 -> 53304.276
H36: Information System Professional | I36: Daniela Alejandra Mendieta | J36: 0 | K36: 0 | L36: 0 | M36: 0 | N36: 8985.85 | O36: 0 | P36: 1 | Q36: 878.7 | R36: 12 | S36: =+Q36*R36 -> 10544.4 | T36: 0 | U36: =SUM(S36:T36) -> 10544.4 | V36: 1 | W36: =+Q36*10%+Q36 -> 966.57 | X36: 12 | Y36: =+W36*X36 -> 11598.84 | Z36: 0 | AA36: =SUM(Y36:Z36) -> 11598.84 | AB36: 1 | AC36: =+W36*10%+W36 -> 1063.227 | AD36: 6 | AE36: =AB36*AC36*AD36 -> 6379.362 | AF36: 0 | AG36: =SUM(AE36:AF36) -> 6379.362 | AH36: =+J36+L36+N36 -> 8985.85 | AI36: =+K36+M36+O36 -> 0 | AJ36: =+AH36+AI36 -> 8985.85 | AK36: =+S36+Y36+AE36 -> 28522.602 | AL36: =+T36+Z36+AF36 -> 0 | AM36: =+AK36+AL36 -> 28522.602 | AO36: =+AH36+AK36 -> 37508.452 | AP36: =+AI36+AL36 -> 0 | AQ36: =+AO36+AP36 -> 37508.452
H37: Information System Professional | I37: Juan Guillermo Salguero Astudillo | J37: 0 | K37: 0 | L37: 0 | M37: 0 | N37: 8663.78 | O37: 0 | P37: 1 | Q37: 878.7 | R37: 12 | S37: =+Q37*R37 -> 10544.4 | T37: 0 | U37: =SUM(S37:T37) -> 10544.4 | V37: 1 | W37: =+Q37*10%+Q37 -> 966.57 | X37: 12 | Y37: =+W37*X37 -> 11598.84 | Z37: 0 | AA37: =SUM(Y37:Z37) -> 11598.84 | AB37: 1 | AC37: =+W37*10%+W37 -> 1063.227 | AD37: 6 | AE37: =AB37*AC37*AD37 -> 6379.362 | AF37: 0 | AG37: =SUM(AE37:AF37) -> 6379.362 | AH37: =+J37+L37+N37 -> 8663.78 | AI37: =+K37+M37+O37 -> 0 | AJ37: =+AH37+AI37 -> 8663.78 | AK37: =+S37+Y37+AE37 -> 28522.602 | AL37: =+T37+Z37+AF37 -> 0 | AM37: =+AK37+AL37 -> 28522.602 | AO37: =+AH37+AK37 -> 37186.382 | AP37: =+AI37+AL37 -> 0 | AQ37: =+AO37+AP37 -> 37186.382
H38: Information System Professional | I38: Ma. Alejandra Pinzón | J38: 0 | K38: 0 | L38: 0 | M38: 0 | N38: 8065.44 | O38: 0 | P38: 1 | Q38: 1062.71 | R38: 12 | S38: =+Q38*R38 -> 12752.52 | T38: 0 | U38: =SUM(S38:T38) -> 12752.52 | V38: 1 | W38: =+Q38*10%+Q38 -> 1168.981 | X38: 12 | Y38: =+W38*X38 -> 14027.772 | Z38: 0 | AA38: =SUM(Y38:Z38) -> 14027.772 | AB38: 1 | AC38: =+W38*10%+W38 -> 1285.8791 | AD38: 6 | AE38: =AB38*AC38*AD38 -> 7715.2746 | AF38: 0 | AG38: =SUM(AE38:AF38) -> 7715.2746 | AH38: =+J38+L38+N38 -> 8065.44 | AI38: =+K38+M38+O38 -> 0 | AJ38: =+AH38+AI38 -> 8065.44 | AK38: =+S38+Y38+AE38 -> 34495.567 | AL38: =+T38+Z38+AF38 -> 0 | AM38: =+AK38+AL38 -> 34495.567 | AO38: =+AH38+AK38 -> 42561.007 | AP38: =+AI38+AL38 -> 0 | AQ38: =+AO38+AP38 -> 42561.007
H39: Grants Team
A40: SUBFCARVA | B40: 89050 | C40: COL2 | D40: COL2 | E40: CARVAJAL | F40: FCPERSNL | G40: Grants & Compliance Coordinator | H40: Grants Specialist | I40: Adriana Rodríguez | J40: 4459.29 | K40: 0 | L40: 18701.01 | M40: 0 | N40: 19770.92 | O40: 0 | P40: 1 | Q40: 1748.82 | R40: 12 | S40: =+Q40*R40 -> 20985.84 | T40: 0 | U40: =SUM(S40:T40) -> 20985.84 | V40: 1 | W40: =+Q40*10%+Q40 -> 1923.702 | X40: 12 | Y40: =V40*W40*X40 -> 23084.424 | Z40: 0 | AA40: =SUM(Y40:Z40) -> 23084.424 | AB40: 1 | AC40: =+W40*10%+W40 -> 2116.0722 | AD40: 6 | AE40: =AB40*AC40*AD40 -> 12696.433 | AF40: 0 | AG40: =SUM(AE40:AF40) -> 12696.433 | AH40: =+J40+L40+N40 -> 42931.22 | AI40: =+K40+M40+O40 -> 0 | AJ40: =+AH40+AI40 -> 42931.22 | AK40: =+S40+Y40+AE40 -> 56766.697 | AL40: =+T40+Z40+AF40 -> 0 | AM40: =+AK40+AL40 -> 56766.697 | AO40: =+AH40+AK40 -> 99697.917 | AP40: =+AI40+AL40 -> 0 | AQ40: =+AO40+AP40 -> 99697.917
H41: 2nd Tier Subawardess Technical Supervisor | I41: José García | J41: 0 | K41: 0 | L41: 7199.58 | M41: 0 | N41: 12801.36 | O41: 0 | P41: 1 | Q41: 1284.54 | R41: 6 | S41: =+Q41*R41 -> 7707.24 | T41: 0 | U41: =SUM(S41:T41) -> 7707.24 | V41: 1 | W41: =+Q41*10%+Q41 -> 1412.994 | X41: 12 | Y41: =V41*W41*X41 -> 16955.928 | Z41: 0 | AA41: =SUM(Y41:Z41) -> 16955.928 | AB41: 1 | AC41: =+W41*10%+W41 -> 1554.2934 | AD41: 6 | AE41: =AB41*AC41*AD41 -> 9325.7604 | AF41: 0 | AG41: =SUM(AE41:AF41) -> 9325.7604 | AH41: =+J41+L41+N41 -> 20000.94 | AI41: =+K41+M41+O41 -> 0 | AJ41: =+AH41+AI41 -> 20000.94 | AK41: =+S41+Y41+AE41 -> 33988.928 | AL41: =+T41+Z41+AF41 -> 0 | AM41: =+AK41+AL41 -> 33988.928 | AO41: =+AH41+AK41 -> 53989.868 | AP41: =+AI41+AL41 -> 0 | AQ41: =+AO41+AP41 -> 53989.868
H42: F&A Team
A43: SUBFCARVA | B43: 89050 | C43: COL2 | D43: COL2 | E43: CARVAJAL | F43: FCPERSNL | G43: Finance & Admin Coordinator | H43: Finance & Admin Coordinator | I43: Jenny Milena Castaño | J43: 5716.37 | K43: 0 | L43: 14334.38 | M43: 0 | N43: 15607.17 | O43: 0 | P43: 1 | Q43: 1660.21 | R43: 12 | S43: =+Q43*R43 -> 19922.52 | T43: 0 | U43: =SUM(S43:T43) -> 19922.52 | V43: 1 | W43: 1866.98 | X43: 12 | Y43: =V43*W43*X43 -> 22403.76 | Z43: 0 | AA43: =SUM(Y43:Z43) -> 22403.76 | AB43: 1 | AC43: =+W43*10%+W43 -> 2053.678 | AD43: 8 | AE43: =AB43*AC43*AD43 -> 16429.424 | AF43: 0 | AG43: =SUM(AE43:AF43) -> 16429.424 | AH43: =+J43+L43+N43 -> 35657.92 | AI43: =+K43+M43+O43 -> 0 | AJ43: =+AH43+AI43 -> 35657.92 | AK43: =+S43+Y43+AE43 -> 58755.704 | AL43: =+T43+Z43+AF43 -> 0 | AM43: =+AK43+AL43 -> 58755.704 | AO43: =+AH43+AK43 -> 94413.624 | AP43: =+AI43+AL43 -> 0 | AQ43: =+AO43+AP43 -> 94413.624
A44: SUBFCARVA | B44: 89050 | C44: COL2 | D44: COL2 | E44: CARVAJAL | F44: FCPERSNLEV | G44: Accounting Analyst | H44: Accounting Analyst | I44: Dalis Raquel Tapias Taquez | J44: 2058.13 | K44: 0 | L44: 8631.23 | M44: 0 | N44: 5714.67 | O44: 0 | P44: 1 | Q44: 758.33 | R44: 12 | S44: =+Q44*R44 -> 9099.96 | T44: 0 | U44: =SUM(S44:T44) -> 9099.96 | V44: 1 | W44: =+Q44*10%+Q44 -> 834.163 | X44: 12 | Y44: =V44*W44*X44 -> 10009.956 | Z44: 0 | AA44: =SUM(Y44:Z44) -> 10009.956 | AB44: 1 | AC44: =+W44*10%+W44 -> 917.5793 | AD44: 8 | AE44: =AB44*AC44*AD44 -> 7340.6344 | AF44: 0 | AG44: =SUM(AE44:AF44) -> 7340.6344 | AH44: =+J44+L44+N44 -> 16404.03 | AI44: =+K44+M44+O44 -> 0 | AJ44: =+AH44+AI44 -> 16404.03 | AK44: =+S44+Y44+AE44 -> 26450.55 | AL44: =+T44+Z44+AF44 -> 0 | AM44: =+AK44+AL44 -> 26450.55 | AO44: =+AH44+AK44 -> 42854.58 | AP44: =+AI44+AL44 -> 0 | AQ44: =+AO44+AP44 -> 42854.58
H45: Accounting Analyst (Maternity Leave) | I45: Juan Camilo Zapata | J45: 0 | K45: 0 | L45: 0 | M45: 0 | N45: 3288.75 | O45: 0 | P45: 1 | Q45: 864.2 | R45: 2 | S45: =+Q45*R45 -> 1728.4 | T45: 0 | U45: =SUM(S45:T45) -> 1728.4 | V45: 1 | W45: =+Q45*10%+Q45 -> 950.62 | X45: 0 | Y45: =V45*W45*X45 -> 0 | Z45: 0 | AA45: =SUM(Y45:Z45) -> 0 | AB45: 0 | AC45: 0 | AD45: 0 | AE45: =AB45*AC45*AD45 -> 0 | AF45: 0 | AG45: =SUM(AE45:AF45) -> 0 | AH45: =+J45+L45+N45 -> 3288.75 | AI45: =+K45+M45+O45 -> 0 | AJ45: =+AH45+AI45 -> 3288.75 | AK45: =+S45+Y45+AE45 -> 1728.4 | AL45: =+T45+Z45+AF45 -> 0 | AM45: =+AK45+AL45 -> 1728.4 | AO45: =+AH45+AK45 -> 5017.15 | AP45: =+AI45+AL45 -> 0 | AQ45: =+AO45+AP45 -> 5017.15
A46: SUBFCARVA | B46: 89050 | C46: COL2 | D46: COL2 | E46: CARVAJAL | F46: FCPERSNLEV | G46: Project Assistant | H46: Project Assistant | I46: Geraldine González | J46: 1828.58 | K46: 0 | L46: 5691.93 | M46: 0 | N46: 6142.27 | O46: 0 | P46: 1 | Q46: 608.7 | R46: 12 | S46: =+Q46*R46 -> 7304.4 | T46: 0 | U46: =SUM(S46:T46) -> 7304.4 | V46: 1 | W46: =+Q46*10%+Q46 -> 669.57 | X46: 12 | Y46: =V46*W46*X46 -> 8034.84 | Z46: 0 | AA46: =SUM(Y46:Z46) -> 8034.84 | AB46: 1 | AC46: =+W46*10%+W46 -> 736.527 | AD46: 8 | AE46: =AB46*AC46*AD46 -> 5892.216 | AF46: 0 | AG46: =SUM(AE46:AF46) -> 5892.216 | AH46: =+J46+L46+N46 -> 13662.78 | AI46: =+K46+M46+O46 -> 0 | AJ46: =+AH46+AI46 -> 13662.78 | AK46: =+S46+Y46+AE46 -> 21231.456 | AL46: =+T46+Z46+AF46 -> 0 | AM46: =+AK46+AL46 -> 21231.456 | AO46: =+AH46+AK46 -> 34894.236 | AP46: =+AI46+AL46 -> 0 | AQ46: =+AO46+AP46 -> 34894.236
H47: File Clerk Assistant | I47: Yamile Lorena Cantillo | J47: 0 | K47: 0 | L47: 2930.08 | M47: 0 | N47: 4338.44 | O47: 0 | P47: 1 | Q47: 421.89 | R47: 12 | S47: =+Q47*R47 -> 5062.68 | T47: 0 | U47: =SUM(S47:T47) -> 5062.68 | V47: 1 | W47: =+Q47*10%+Q47 -> 464.079 | X47: 2 | Y47: =V47*W47*X47 -> 928.158 | Z47: 0 | AA47: =SUM(Y47:Z47) -> 928.158 | AB47: 1 | AC47: =+W47*10%+W47 -> 510.4869 | AD47: 8 | AE47: =AB47*AC47*AD47 -> 4083.8952 | AF47: 0 | AG47: =SUM(AE47:AF47) -> 4083.8952 | AH47: =+J47+L47+N47 -> 7268.52 | AI47: =+K47+M47+O47 -> 0 | AJ47: =+AH47+AI47 -> 7268.52 | AK47: =+S47+Y47+AE47 -> 10074.733 | AL47: =+T47+Z47+AF47 -> 0 | AM47: =+AK47+AL47 -> 10074.733 | AO47: =+AH47+AK47 -> 17343.253 | AP47: =+AI47+AL47 -> 0 | AQ47: =+AO47+AP47 -> 17343.253
A48: SUBFCARVA | B48: 89050 | C48: COL2 | D48: COL2 | E48: CARVAJAL | F48: FCPERSNLEV | H48: Promotions Professional (Applies for Cali) | I48: Daniela Ortega Otálora | J48: 114.87 | K48: 125.51 | L48: 741.04 | M48: 814.45 | N48: 821.51 | O48: 889.09 | P48: 0.13 | Q48: 79.52 | R48: 12 | S48: =+Q48*R48 -> 954.24 | T48: =+Q48*R48 -> 954.24 | U48: =SUM(S48:T48) -> 1908.48 | V48: 0.26 | W48: =+Q48*10%+Q48 -> 87.472 | X48: 12 | Y48: =V48*W48*X48 -> 272.91264 | Z48: 252.35 | AA48: =SUM(Y48:Z48) -> 525.26264 | AB48: 0.26 | AC48: =+W48*10%+W48 -> 96.2192 | AD48: 8 | AE48: =AB48*AC48*AD48 -> 200.13594 | AF48: 277.59 | AG48: =SUM(AE48:AF48) -> 477.72594 | AH48: =+J48+L48+N48 -> 1677.42 | AI48: =+K48+M48+O48 -> 1829.05 | AJ48: =+AH48+AI48 -> 3506.47 | AK48: =+S48+Y48+AE48 -> 1427.2886 | AL48: =+T48+Z48+AF48 -> 1484.18 | AM48: =+AK48+AL48 -> 2911.4686 | AO48: =+AH48+AK48 -> 3104.7086 | AP48: =+AI48+AL48 -> 3313.23 | AQ48: =+AO48+AP48 -> 6417.9386
H49: Legal Assistant | I49: Laura Zuleima Mosquera | J49: 952.12 | K49: 0 | L49: 4385.81 | M49: 0 | N49: 5005.85 | O49: 0 | P49: 0.5 | Q49: 290.73 | R49: 12 | S49: =+Q49*R49 -> 3488.76 | T49: 0 | U49: =SUM(S49:T49) -> 3488.76 | V49: 0.5 | W49: =+Q49*10%+Q49 -> 319.803 | X49: 2 | Y49: =V49*W49*X49 -> 319.803 | Z49: 0 | AA49: =SUM(Y49:Z49) -> 319.803 | AB49: 0.5 | AC49: =+W49*10%+W49 -> 351.7833 | AD49: 8 | AE49: =AB49*AC49*AD49 -> 1407.1332 | AF49: 0 | AG49: =SUM(AE49:AF49) -> 1407.1332 | AH49: =+J49+L49+N49 -> 10343.78 | AI49: =+K49+M49+O49 -> 0 | AJ49: =+AH49+AI49 -> 10343.78 | AK49: =+S49+Y49+AE49 -> 5215.6962 | AL49: =+T49+Z49+AF49 -> 0 | AM49: =+AK49+AL49 -> 5215.6962 | AO49: =+AH49+AK49 -> 15559.476 | AP49: =+AI49+AL49 -> 0 | AQ49: =+AO49+AP49 -> 15559.476
H50: Procurement Assistant | I50: TBD | J50: 0 | K50: 0 | L50: 0 | M50: 0 | N50: 0 | O50: 0 | P50: 1 | Q50: 608.7 | R50: 10 | S50: =+Q50*R50 -> 6087 | T50: 0 | U50: =SUM(S50:T50) -> 6087 | V50: 1 | W50: =+Q50*10%+Q50 -> 669.57 | X50: 12 | Y50: =V50*W50*X50 -> 8034.84 | Z50: 0 | AA50: =SUM(Y50:Z50) -> 8034.84 | AB50: 1 | AC50: =+W50*10%+W50 -> 736.527 | AD50: 6 | AE50: =AB50*AC50*AD50 -> 4419.162 | AF50: 0 | AG50: =SUM(AE50:AF50) -> 4419.162 | AH50: =+J50+L50+N50 -> 0 | AI50: =+K50+M50+O50 -> 0 | AJ50: =+AH50+AI50 -> 0 | AK50: =+S50+Y50+AE50 -> 18541.002 | AL50: =+T50+Z50+AF50 -> 0 | AM50: =+AK50+AL50 -> 18541.002 | AO50: =+AH50+AK50 -> 18541.002 | AP50: =+AI50+AL50 -> 0 | AQ50: =+AO50+AP50 -> 18541.002
H51: Comms Team | AH51: =+J51+L51+N51 -> 0 | AI51: =+K51+M51+O51 -> 0 | AJ51: =+AH51+AI51 -> 0 | AK51: =+S51+Y51+AE51 -> 0 | AL51: =+T51+Z51+AF51 -> 0 | AM51: =+AK51+AL51 -> 0 | AO51: =+AH51+AK51 -> 0 | AP51: =+AI51+AL51 -> 0 | AQ51: =+AO51+AP51 -> 0
H52: Communications Senior Analyst | I52: Ana Sofía Bravo | J52: 2308.18 | K52: 0 | L52: 9493.82 | M52: 0 | N52: 11058.81 | O52: 0 | P52: 1 | Q52: 1070.45 | R52: 12 | S52: =+Q52*R52 -> 12845.4 | T52: 0 | U52: =SUM(S52:T52) -> 12845.4 | V52: 1 | W52: =+Q52*10%+Q52 -> 1177.495 | X52: 12 | Y52: =V52*W52*X52 -> 14129.94 | Z52: 0 | AA52: =SUM(Y52:Z52) -> 14129.94 | AB52: 1 | AC52: =+W52*10%+W52 -> 1295.2445 | AD52: 6 | AE52: =AB52*AC52*AD52 -> 7771.467 | AF52: 0 | AG52: =SUM(AE52:AF52) -> 7771.467 | AH52: =+J52+L52+N52 -> 22860.81 | AI52: =+K52+M52+O52 -> 0 | AJ52: =+AH52+AI52 -> 22860.81 | AK52: =+S52+Y52+AE52 -> 34746.807 | AL52: =+T52+Z52+AF52 -> 0 | AM52: =+AK52+AL52 -> 34746.807 | AO52: =+AH52+AK52 -> 57607.617 | AP52: =+AI52+AL52 -> 0 | AQ52: =+AO52+AP52 -> 57607.617
H53: Regionals Team
H54: Technical Advisor - Cali | I54: Marleny Romelia Ordóñez | J54: 0 | K54: 0 | L54: 5375.44 | M54: 0 | N54: 12548.39 | O54: 0 | P54: 1 | Q54: 1238.11 | R54: 12 | S54: =+Q54*R54 -> 14857.32 | T54: 0 | U54: =SUM(S54:T54) -> 14857.32 | V54: 1 | W54: =+Q54*10%+Q54 -> 1361.921 | X54: 12 | Y54: =V54*W54*X54 -> 16343.052 | Z54: 0 | AA54: =SUM(Y54:Z54) -> 16343.052 | AB54: 1 | AC54: =+W54*10%+W54 -> 1498.1131 | AD54: 6 | AE54: =AB54*AC54*AD54 -> 8988.6786 | AF54: 0 | AG54: =SUM(AE54:AF54) -> 8988.6786 | AH54: =+J54+L54+N54 -> 17923.83 | AI54: =+K54+M54+O54 -> 0 | AJ54: =+AH54+AI54 -> 17923.83 | AK54: =+S54+Y54+AE54 -> 40189.051 | AL54: =+T54+Z54+AF54 -> 0 | AM54: =+AK54+AL54 -> 40189.051 | AO54: =+AH54+AK54 -> 58112.881 | AP54: =+AI54+AL54 -> 0 | AQ54: =+AO54+AP54 -> 58112.881
H55: Junior Pedagogical Advisor (Intégrate) - Cali | I55: Yaine Lorena Díaz | J55: 0 | K55: 0 | L55: 1118.2 | M55: 0 | N55: 1888.64 | O55: 0 | P55: 0 | Q55: 0 | R55: 0 | S55: =+Q55*R55 -> 0 | T55: 0 | U55: =SUM(S55:T55) -> 0 | V55: 0 | W55: =+Q55*10%+Q55 -> 0 | X55: 0 | Y55: =V55*W55*X55 -> 0 | Z55: 0 | AA55: =SUM(Y55:Z55) -> 0 | AB55: 0 | AC55: =+W55*10%+W55 -> 0 | AD55: 6 | AE55: =AB55*AC55*AD55 -> 0 | AF55: 0 | AG55: =SUM(AE55:AF55) -> 0 | AH55: =+J55+L55+N55 -> 3006.84 | AI55: =+K55+M55+O55 -> 0 | AJ55: =+AH55+AI55 -> 3006.84 | AK55: =+S55+Y55+AE55 -> 0 | AL55: =+T55+Z55+AF55 -> 0 | AM55: =+AK55+AL55 -> 0 | AO55: =+AH55+AK55 -> 3006.84 | AP55: =+AI55+AL55 -> 0 | AQ55: =+AO55+AP55 -> 3006.84
H56: Technical Advisor - Cúcuta | I56: Manuel Ricardo Daza | J56: 0 | K56: 0 | L56: 0 | M56: 0 | N56: 0 | O56: 0 | P56: 1 | Q56: 1284.54 | R56: 12 | S56: =+Q56*R56 -> 15414.48 | T56: 0 | U56: =SUM(S56:T56) -> 15414.48 | V56: 1 | W56: =+Q56*10%+Q56 -> 1412.994 | X56: 12 | Y56: =V56*W56*X56 -> 16955.928 | Z56: 0 | AA56: =SUM(Y56:Z56) -> 16955.928 | AB56: 1 | AC56: =+W56*10%+W56 -> 1554.2934 | AD56: 6 | AE56: =AB56*AC56*AD56 -> 9325.7604 | AF56: 0 | AG56: =SUM(AE56:AF56) -> 9325.7604 | AH56: =+J56+L56+N56 -> 0 | AI56: =+K56+M56+O56 -> 0 | AJ56: =+AH56+AI56 -> 0 | AK56: =+S56+Y56+AE56 -> 41696.168 | AL56: =+T56+Z56+AF56 -> 0 | AM56: =+AK56+AL56 -> 41696.168 | AO56: =+AH56+AK56 -> 41696.168 | AP56: =+AI56+AL56 -> 0 | AQ56: =+AO56+AP56 -> 41696.168
H57: Technical Advisor - Bucaramanga | I57: Sara Ma. Ariza | J57: 0 | K57: 0 | L57: 0 | M57: 0 | N57: 0 | O57: 0 | P57: 1 | Q57: 1284.54 | R57: 12 | S57: =+Q57*R57 -> 15414.48 | T57: 0 | U57: =SUM(S57:T57) -> 15414.48 | V57: 1 | W57: =+Q57*10%+Q57 -> 1412.994 | X57: 12 | Y57: =V57*W57*X57 -> 16955.928 | Z57: 0 | AA57: =SUM(Y57:Z57) -> 16955.928 | AB57: 1 | AC57: =+W57*10%+W57 -> 1554.2934 | AD57: 6 | AE57: =AB57*AC57*AD57 -> 9325.7604 | AF57: 0 | AG57: =SUM(AE57:AF57) -> 9325.7604 | AH57: =+J57+L57+N57 -> 0 | AI57: =+K57+M57+O57 -> 0 | AJ57: =+AH57+AI57 -> 0 | AK57: =+S57+Y57+AE57 -> 41696.168 | AL57: =+T57+Z57+AF57 -> 0 | AM57: =+AK57+AL57 -> 41696.168 | AO57: =+AH57+AK57 -> 41696.168 | AP57: =+AI57+AL57 -> 0 | AQ57: =+AO57+AP57 -> 41696.168
H58: Technical Advisor - Cartagena | I58: Kaline Paola Romero | J58: 0 | K58: 0 | L58: 0 | M58: 0 | N58: 0 | O58: 0 | P58: 1 | Q58: 1284.54 | R58: 11 | S58: =+Q58*R58 -> 14129.94 | T58: 0 | U58: =SUM(S58:T58) -> 14129.94 | V58: 1 | W58: =+Q58*10%+Q58 -> 1412.994 | X58: 12 | Y58: =V58*W58*X58 -> 16955.928 | Z58: 0 | AA58: =SUM(Y58:Z58) -> 16955.928 | AB58: 1 | AC58: =+W58*10%+W58 -> 1554.2934 | AD58: 6 | AE58: =AB58*AC58*AD58 -> 9325.7604 | AF58: 0 | AG58: =SUM(AE58:AF58) -> 9325.7604 | AH58: =+J58+L58+N58 -> 0 | AI58: =+K58+M58+O58 -> 0 | AJ58: =+AH58+AI58 -> 0 | AK58: =+S58+Y58+AE58 -> 40411.628 | AL58: =+T58+Z58+AF58 -> 0 | AM58: =+AK58+AL58 -> 40411.628 | AO58: =+AH58+AK58 -> 40411.628 | AP58: =+AI58+AL58 -> 0 | AQ58: =+AO58+AP58 -> 40411.628
H59: Technical Advisor - Santa Marta/Riohacha | I59: Joanna Marcela Páez | J59: 0 | K59: 0 | L59: 0 | M59: 0 | N59: 0 | O59: 0 | P59: 1 | Q59: 1530.86 | R59: 12 | S59: =+Q59*R59 -> 18370.32 | T59: 0 | U59: =SUM(S59:T59) -> 18370.32 | V59: 1 | W59: =+Q59*10%+Q59 -> 1683.946 | X59: 12 | Y59: =V59*W59*X59 -> 20207.352 | Z59: 0 | AA59: =SUM(Y59:Z59) -> 20207.352 | AB59: 1 | AC59: =+W59*10%+W59 -> 1852.3406 | AD59: 6 | AE59: =AB59*AC59*AD59 -> 11114.044 | AF59: 0 | AG59: =SUM(AE59:AF59) -> 11114.044 | AH59: =+J59+L59+N59 -> 0 | AI59: =+K59+M59+O59 -> 0 | AJ59: =+AH59+AI59 -> 0 | AK59: =+S59+Y59+AE59 -> 49691.716 | AL59: =+T59+Z59+AF59 -> 0 | AM59: =+AK59+AL59 -> 49691.716 | AO59: =+AH59+AK59 -> 49691.716 | AP59: =+AI59+AL59 -> 0 | AQ59: =+AO59+AP59 -> 49691.716
H60: Technical Team - Subactivity: PI (4PA) | AH60: =+J60+L60+N60 -> 0 | AI60: =+K60+M60+O60 -> 0 | AJ60: =+AH60+AI60 -> 0 | AK60: =+S60+Y60+AE60 -> 0 | AL60: =+T60+Z60+AF60 -> 0 | AM60: =+AK60+AL60 -> 0 | AO60: =+AH60+AK60 -> 0 | AP60: =+AI60+AL60 -> 0 | AQ60: =+AO60+AP60 -> 0
H61: Pedagogical Advisors
H62: PI - Pedagogical Advisor (1) | I62: Prov - Catalina García Ante | J62: 0 | K62: 0 | L62: 5490.09 | M62: 0 | N62: 825.82 | O62: 0 | P62: 0 | Q62: 0 | R62: 0 | S62: =+Q62*R62 -> 0 | T62: 0 | U62: =SUM(S62:T62) -> 0 | V62: 1 | W62: 1093.389 | X62: 12 | Y62: =V62*W62*X62 -> 13120.668 | Z62: 0 | AA62: =SUM(Y62:Z62) -> 13120.668 | AB62: 1 | AC62: =+W62*10%+W62 -> 1202.7279 | AD62: 6 | AE62: =AB62*AC62*AD62 -> 7216.3674 | AF62: 0 | AG62: =SUM(AE62:AF62) -> 7216.3674 | AH62: =+J62+L62+N62 -> 6315.91 | AI62: =+K62+M62+O62 -> 0 | AJ62: =+AH62+AI62 -> 6315.91 | AK62: =+S62+Y62+AE62 -> 20337.035 | AL62: =+T62+Z62+AF62 -> 0 | AM62: =+AK62+AL62 -> 20337.035 | AO62: =+AH62+AK62 -> 26652.945 | AP62: =+AI62+AL62 -> 0 | AQ62: =+AO62+AP62 -> 26652.945
H63: PI - Pedagogical Advisor (2) | I63: Prov - Estefanía Jiménez Taborda | J63: 0 | K63: 0 | L63: 5436.08 | M63: 0 | N63: 8972.71 | O63: 0 | P63: 1 | Q63: 993.99 | R63: 11 | S63: =+Q63*R63 -> 10933.89 | T63: 0 | U63: =SUM(S63:T63) -> 10933.89 | V63: 1 | W63: =+Q63*10%+Q63 -> 1093.389 | X63: 8 | Y63: =V63*W63*X63 -> 8747.112 | Z63: 0 | AA63: =SUM(Y63:Z63) -> 8747.112 | AB63: 1 | AC63: =+W63*10%+W63 -> 1202.7279 | AD63: 6 | AE63: =AB63*AC63*AD63 -> 7216.3674 | AF63: 0 | AG63: =SUM(AE63:AF63) -> 7216.3674 | AH63: =+J63+L63+N63 -> 14408.79 | AI63: =+K63+M63+O63 -> 0 | AJ63: =+AH63+AI63 -> 14408.79 | AK63: =+S63+Y63+AE63 -> 26897.369 | AL63: =+T63+Z63+AF63 -> 0 | AM63: =+AK63+AL63 -> 26897.369 | AO63: =+AH63+AK63 -> 41306.159 | AP63: =+AI63+AL63 -> 0 | AQ63: =+AO63+AP63 -> 41306.159
H64: PI - Pedagogical Advisor (3) | I64: Prov - Herling Ferla | J64: 0 | K64: 0 | L64: 5372.45 | M64: 0 | N64: 0 | O64: 0 | P64: 0 | Q64: 0 | R64: 0 | S64: =+Q64*R64 -> 0 | T64: 0 | U64: =SUM(S64:T64) -> 0 | V64: 1 | W64: 1093.389 | X64: 8 | Y64: =V64*W64*X64 -> 8747.112 | Z64: 0 | AA64: =SUM(Y64:Z64) -> 8747.112 | AB64: 1 | AC64: =+W64*10%+W64 -> 1202.7279 | AD64: 0 | AE64: =AB64*AC64*AD64 -> 0 | AF64: 0 | AG64: =SUM(AE64:AF64) -> 0 | AH64: =+J64+L64+N64 -> 5372.45 | AI64: =+K64+M64+O64 -> 0 | AJ64: =+AH64+AI64 -> 5372.45 | AK64: =+S64+Y64+AE64 -> 8747.112 | AL64: =+T64+Z64+AF64 -> 0 | AM64: =+AK64+AL64 -> 8747.112 | AO64: =+AH64+AK64 -> 14119.562 | AP64: =+AI64+AL64 -> 0 | AQ64: =+AO64+AP64 -> 14119.562
H65: PI - Pedagogical Advisor (4) | I65: Prov - Marlyn Montoya | J65: 0 | K65: 0 | L65: 5085 | M65: 0 | N65: 7966.12 | O65: 0 | P65: 1 | Q65: 993.99 | R65: 11 | S65: =+Q65*R65 -> 10933.89 | T65: 0 | U65: =SUM(S65:T65) -> 10933.89 | V65: 1 | W65: =+Q65*10%+Q65 -> 1093.389 | X65: 0 | Y65: =V65*W65*X65 -> 0 | Z65: 0 | AA65: =SUM(Y65:Z65) -> 0 | AB65: 1 | AC65: =+W65*10%+W65 -> 1202.7279 | AD65: 0 | AE65: =AB65*AC65*AD65 -> 0 | AF65: 0 | AG65: =SUM(AE65:AF65) -> 0 | AH65: =+J65+L65+N65 -> 13051.12 | AI65: =+K65+M65+O65 -> 0 | AJ65: =+AH65+AI65 -> 13051.12 | AK65: =+S65+Y65+AE65 -> 10933.89 | AL65: =+T65+Z65+AF65 -> 0 | AM65: =+AK65+AL65 -> 10933.89 | AO65: =+AH65+AK65 -> 23985.01 | AP65: =+AI65+AL65 -> 0 | AQ65: =+AO65+AP65 -> 23985.01
H66: PI - Pedagogical Advisor (5) | I66: Prov - Jonathan Stiven Pérez | J66: 0 | K66: 0 | L66: 0 | M66: 0 | N66: 7642.65 | O66: 0 | P66: 0 | Q66: 0 | R66: 0 | S66: =+Q66*R66 -> 0 | T66: 0 | U66: =SUM(S66:T66) -> 0 | V66: 0 | W66: =+Q66*10%+Q66 -> 0 | X66: 0 | Y66: =V66*W66*X66 -> 0 | Z66: 0 | AA66: =SUM(Y66:Z66) -> 0 | AB66: 0 | AC66: =+W66*10%+W66 -> 0 | AD66: 0 | AE66: =AB66*AC66*AD66 -> 0 | AF66: 0 | AG66: =SUM(AE66:AF66) -> 0 | AH66: =+J66+L66+N66 -> 7642.65 | AI66: =+K66+M66+O66 -> 0 | AJ66: =+AH66+AI66 -> 7642.65 | AK66: =+S66+Y66+AE66 -> 0 | AL66: =+T66+Z66+AF66 -> 0 | AM66: =+AK66+AL66 -> 0 | AO66: =+AH66+AK66 -> 7642.65 | AP66: =+AI66+AL66 -> 0 | AQ66: =+AO66+AP66 -> 7642.65
H67: PI - Pedagogical Advisor (6) | I67: Prov - Katherine Barba Flórez | J67: 0 | K67: 0 | L67: 0 | M67: 0 | N67: 6875.33 | O67: 0 | P67: 0 | Q67: 0 | R67: 0 | S67: =+Q67*R67 -> 0 | T67: 0 | U67: =SUM(S67:T67) -> 0 | V67: 0 | W67: =+Q67*10%+Q67 -> 0 | X67: 0 | Y67: =V67*W67*X67 -> 0 | Z67: 0 | AA67: =SUM(Y67:Z67) -> 0 | AB67: 0 | AC67: =+W67*10%+W67 -> 0 | AD67: 0 | AE67: =AB67*AC67*AD67 -> 0 | AF67: 0 | AG67: =SUM(AE67:AF67) -> 0 | AH67: =+J67+L67+N67 -> 6875.33 | AI67: =+K67+M67+O67 -> 0 | AJ67: =+AH67+AI67 -> 6875.33 | AK67: =+S67+Y67+AE67 -> 0 | AL67: =+T67+Z67+AF67 -> 0 | AM67: =+AK67+AL67 -> 0 | AO67: =+AH67+AK67 -> 6875.33 | AP67: =+AI67+AL67 -> 0 | AQ67: =+AO67+AP67 -> 6875.33
H68: PI - Pedagogical Advisor (7) | I68: Prov - Ingrid Cosme | J68: 0 | K68: 0 | L68: 0 | M68: 0 | N68: 0 | O68: 0 | P68: 1 | Q68: 993.99 | R68: 11 | S68: =+Q68*R68 -> 10933.89 | T68: 0 | U68: =SUM(S68:T68) -> 10933.89 | V68: 0 | W68: 0 | X68: 0 | Y68: =V68*W68*X68 -> 0 | Z68: 0 | AA68: =SUM(Y68:Z68) -> 0 | AB68: 0 | AC68: =+W68*10%+W68 -> 0 | AD68: 0 | AE68: =AB68*AC68*AD68 -> 0 | AF68: 0 | AG68: =SUM(AE68:AF68) -> 0 | AH68: =+J68+L68+N68 -> 0 | AI68: =+K68+M68+O68 -> 0 | AJ68: =+AH68+AI68 -> 0 | AK68: =+S68+Y68+AE68 -> 10933.89 | AL68: =+T68+Z68+AF68 -> 0 | AM68: =+AK68+AL68 -> 10933.89 | AO68: =+AH68+AK68 -> 10933.89 | AP68: =+AI68+AL68 -> 0 | AQ68: =+AO68+AP68 -> 10933.89
H69: Technical Team - Subactivity: ATL (2AG) | AH69: =+J69+L69+N69 -> 0 | AI69: =+K69+M69+O69 -> 0 | AJ69: =+AH69+AI69 -> 0 | AK69: =+S69+Y69+AE69 -> 0 | AL69: =+T69+Z69+AF69 -> 0 | AM69: =+AK69+AL69 -> 0 | AO69: =+AH69+AK69 -> 0 | AP69: =+AI69+AL69 -> 0 | AQ69: =+AO69+AP69 -> 0
G70: Senior Pedagogical Advisor for Tutors (1 Counselor for 50 Tutors) | H70: Pedagogical Advisors
H71: ATL - Pedagogical Advisor (1) | I71: Cesar Augusto Cano | J71: 4378.1 | K71: 0 | L71: 4936.2 | M71: 0 | N71: 0 | O71: 0 | P71: 0 | Q71: 0 | R71: 0 | S71: =P71*Q71*R71 -> 0 | T71: 0 | U71: =SUM(S71:T71) -> 0 | V71: 1 | W71: 1093.39 | X71: 12 | Y71: =V71*W71*X71 -> 13120.68 | Z71: 0 | AA71: =SUM(Y71:Z71) -> 13120.68 | AB71: 1 | AC71: =+W71*10%+W71 -> 1202.729 | AD71: 6 | AE71: =AB71*AC71*AD71 -> 7216.374 | AF71: 0 | AG71: =SUM(AE71:AF71) -> 7216.374 | AH71: =+J71+L71+N71 -> 9314.3 | AI71: =+K71+M71+O71 -> 0 | AJ71: =+AH71+AI71 -> 9314.3 | AK71: =+S71+Y71+AE71 -> 20337.054 | AL71: =+T71+Z71+AF71 -> 0 | AM71: =+AK71+AL71 -> 20337.054 | AO71: =+AH71+AK71 -> 29651.354 | AP71: =+AI71+AL71 -> 0 | AQ71: =+AO71+AP71 -> 29651.354
H72: ATL - Pedagogical Advisor (2) | I72: Alexandra Hernández Cruz | J72: 0 | K72: 0 | L72: 8408.63 | M72: 0 | N72: 10178.34 | O72: 0 | P72: 0 | Q72: 0 | R72: 0 | S72: =P72*Q72*R72 -> 0 | T72: 0 | U72: =SUM(S72:T72) -> 0 | V72: 1 | W72: 1093.39 | X72: 12 | Y72: =V72*W72*X72 -> 13120.68 | Z72: 0 | AA72: =SUM(Y72:Z72) -> 13120.68 | AB72: 1 | AC72: =+W72*10%+W72 -> 1202.729 | AD72: 6 | AE72: =AB72*AC72*AD72 -> 7216.374 | AF72: 0 | AG72: =SUM(AE72:AF72) -> 7216.374 | AH72: =+J72+L72+N72 -> 18586.97 | AI72: =+K72+M72+O72 -> 0 | AJ72: =+AH72+AI72 -> 18586.97 | AK72: =+S72+Y72+AE72 -> 20337.054 | AL72: =+T72+Z72+AF72 -> 0 | AM72: =+AK72+AL72 -> 20337.054 | AO72: =+AH72+AK72 -> 38924.024 | AP72: =+AI72+AL72 -> 0 | AQ72: =+AO72+AP72 -> 38924.024
H73: ATL - Pedagogical Advisor (3) | I73: Jhon Jairo Sierra Cortés | J73: 0 | K73: 0 | L73: 0 | M73: 0 | N73: 6975.75 | O73: 0 | P73: 1 | Q73: 993.99 | R73: 10 | S73: =+Q73*R73 -> 9939.9 | T73: 0 | U73: =SUM(S73:T73) -> 9939.9 | V73: 0 | W73: 0 | X73: 0 | Y73: =V73*W73*X73 -> 0 | Z73: 0 | AA73: =SUM(Y73:Z73) -> 0 | AB73: 1 | AC73: =+AC72 -> 1202.729 | AD73: 6 | AE73: =AB73*AC73*AD73 -> 7216.374 | AF73: 0 | AG73: =SUM(AE73:AF73) -> 7216.374 | AH73: =+J73+L73+N73 -> 6975.75 | AI73: =+K73+M73+O73 -> 0 | AJ73: =+AH73+AI73 -> 6975.75 | AK73: =+S73+Y73+AE73 -> 17156.274 | AL73: =+T73+Z73+AF73 -> 0 | AM73: =+AK73+AL73 -> 17156.274 | AO73: =+AH73+AK73 -> 24132.024 | AP73: =+AI73+AL73 -> 0 | AQ73: =+AO73+AP73 -> 24132.024
H74: ATL - Pedagogical Advisor (4) | I74: Leidy Yiseth Villaquirán | J74: 0 | K74: 0 | L74: 0 | M74: 0 | N74: 0 | O74: 0 | P74: 1 | Q74: 993.99 | R74: 9 | S74: =+Q74*R74 -> 8945.91 | T74: 0 | U74: =SUM(S74:T74) -> 8945.91 | V74: 0 | W74: 0 | X74: 0 | Y74: =V74*W74*X74 -> 0 | Z74: 0 | AA74: =SUM(Y74:Z74) -> 0 | AB74: 0 | AC74: 0 | AD74: 0 | AE74: =AB74*AC74*AD74 -> 0 | AF74: 0 | AG74: =SUM(AE74:AF74) -> 0 | AH74: =+J74+L74+N74 -> 0 | AI74: =+K74+M74+O74 -> 0 | AJ74: =+AH74+AI74 -> 0 | AK74: =+S74+Y74+AE74 -> 8945.91 | AL74: =+T74+Z74+AF74 -> 0 | AM74: =+AK74+AL74 -> 8945.91 | AO74: =+AH74+AK74 -> 8945.91 | AP74: =+AI74+AL74 -> 0 | AQ74: =+AO74+AP74 -> 8945.91
H75: Technical Team - Subactivity: AG (15AG) | AH75: =+J75+L75+N75 -> 0 | AI75: =+K75+M75+O75 -> 0 | AJ75: =+AH75+AI75 -> 0 | AK75: =+S75+Y75+AE75 -> 0 | AL75: =+T75+Z75+AF75 -> 0 | AM75: =+AK75+AL75 -> 0 | AO75: =+AH75+AK75 -> 0 | AP75: =+AI75+AL75 -> 0 | AQ75: =+AO75+AP75 -> 0
G76: 5 Senior Pedagogical Advisors (1 Advisor for every 50 Teachers) | H76: Pedagogical Advisors
H77: AG - Pedagogical Advisor (1) | I77: Silvia Mariné Pérez | J77: 410.25 | K77: 0 | L77: 9268.49 | M77: 0 | N77: 5396.48 | O77: 327.83 | P77: 1 | Q77: 993.99 | R77: 10 | S77: =+Q77*R77 -> 9939.9 | T77: 0 | U77: =SUM(S77:T77) -> 9939.9 | V77: 1 | W77: =+Q77*10%+Q77 -> 1093.389 | X77: 10 | Y77: =V77*W77*X77 -> 10933.89 | Z77: 0 | AA77: =SUM(Y77:Z77) -> 10933.89 | AB77: 0 | AC77: 0 | AD77: 0 | AE77: =AB77*AC77*AD77 -> 0 | AF77: 0 | AG77: =SUM(AE77:AF77) -> 0 | AH77: =+J77+L77+N77 -> 15075.22 | AI77: =+K77+M77+O77 -> 327.83 | AJ77: =+AH77+AI77 -> 15403.05 | AK77: =+S77+Y77+AE77 -> 20873.79 | AL77: =+T77+Z77+AF77 -> 0 | AM77: =+AK77+AL77 -> 20873.79 | AO77: =+AH77+AK77 -> 35949.01 | AP77: =+AI77+AL77 -> 327.83 | AQ77: =+AO77+AP77 -> 36276.84
H78: AG - Pedagogical Advisor (2) | I78: Alba Milady Zapata | J78: 0 | K78: 0 | L78: 8436.2 | M78: 0 | N78: 8332.8 | O78: 0 | P78: 1 | Q78: 993.99 | R78: 10 | S78: =+Q78*R78 -> 9939.9 | T78: 0 | U78: =SUM(S78:T78) -> 9939.9 | V78: 1 | W78: =+Q78*10%+Q78 -> 1093.389 | X78: 10 | Y78: =V78*W78*X78 -> 10933.89 | Z78: 0 | AA78: =SUM(Y78:Z78) -> 10933.89 | AB78: 0 | AC78: 0 | AD78: 0 | AE78: =AB78*AC78*AD78 -> 0 | AF78: 0 | AG78: =SUM(AE78:AF78) -> 0 | AH78: =+J78+L78+N78 -> 16769 | AI78: =+K78+M78+O78 -> 0 | AJ78: =+AH78+AI78 -> 16769 | AK78: =+S78+Y78+AE78 -> 20873.79 | AL78: =+T78+Z78+AF78 -> 0 | AM78: =+AK78+AL78 -> 20873.79 | AO78: =+AH78+AK78 -> 37642.79 | AP78: =+AI78+AL78 -> 0 | AQ78: =+AO78+AP78 -> 37642.79
H79: AG - Pedagogical Advisor (3) | I79: Dayana Zapata Flórez | J79: 0 | K79: 0 | L79: 6640.45 | M79: 0 | N79: 0 | O79: 0 | P79: 1 | Q79: 993.99 | R79: 10 | S79: 0 | T79: =+Q79*R79 -> 9939.9 | U79: =SUM(S79:T79) -> 9939.9 | V79: 0 | W79: 0 | X79: 0 | Y79: =V79*W79*X79 -> 0 | Z79: 0 | AA79: =SUM(Y79:Z79) -> 0 | AB79: 0 | AC79: 0 | AD79: 0 | AE79: =AB79*AC79*AD79 -> 0 | AF79: 0 | AG79: =SUM(AE79:AF79) -> 0 | AH79: =+J79+L79+N79 -> 6640.45 | AI79: =+K79+M79+O79 -> 0 | AJ79: =+AH79+AI79 -> 6640.45 | AK79: =+S79+Y79+AE79 -> 0 | AL79: =+T79+Z79+AF79 -> 9939.9 | AM79: =+AK79+AL79 -> 9939.9 | AO79: =+AH79+AK79 -> 6640.45 | AP79: =+AI79+AL79 -> 9939.9 | AQ79: =+AO79+AP79 -> 16580.35
H80: AG - Pedagogical Advisor (4) | I80: Gustavo Adolfo Palacios Cadavid | J80: 0 | K80: 0 | L80: 8436.2 | M80: 0 | N80: 5634.65 | O80: 0 | P80: 0 | Q80: 0 | R80: 0 | S80: =+Q80*R80 -> 0 | T80: 0 | U80: =SUM(S80:T80) -> 0 | V80: 0 | W80: 0 | X80: 0 | Y80: =V80*W80*X80 -> 0 | Z80: 0 | AA80: =SUM(Y80:Z80) -> 0 | AB80: 0 | AC80: 0 | AD80: 0 | AE80: =AB80*AC80*AD80 -> 0 | AF80: 0 | AG80: =SUM(AE80:AF80) -> 0 | AH80: =+J80+L80+N80 -> 14070.85 | AI80: =+K80+M80+O80 -> 0 | AJ80: =+AH80+AI80 -> 14070.85 | AK80: =+S80+Y80+AE80 -> 0 | AL80: =+T80+Z80+AF80 -> 0 | AM80: =+AK80+AL80 -> 0 | AO80: =+AH80+AK80 -> 14070.85 | AP80: =+AI80+AL80 -> 0 | AQ80: =+AO80+AP80 -> 14070.85
H81: AG - Pedagogical Advisor (5) | I81: Larissa Valencia Daza | J81: 0 | K81: 0 | L81: 8436.2 | M81: 0 | N81: 10178.34 | O81: 0 | P81: 1 | Q81: 993.99 | R81: 10 | S81: =+Q81*R81 -> 9939.9 | T81: 0 | U81: =SUM(S81:T81) -> 9939.9 | V81: 1 | W81: =+Q81*10%+Q81 -> 1093.389 | X81: 10 | Y81: =V81*W81*X81 -> 10933.89 | Z81: 0 | AA81: =SUM(Y81:Z81) -> 10933.89 | AB81: 0 | AC81: 0 | AD81: 0 | AE81: =AB81*AC81*AD81 -> 0 | AF81: 0 | AG81: =SUM(AE81:AF81) -> 0 | AH81: =+J81+L81+N81 -> 18614.54 | AI81: =+K81+M81+O81 -> 0 | AJ81: =+AH81+AI81 -> 18614.54 | AK81: =+S81+Y81+AE81 -> 20873.79 | AL81: =+T81+Z81+AF81 -> 0 | AM81: =+AK81+AL81 -> 20873.79 | AO81: =+AH81+AK81 -> 39488.33 | AP81: =+AI81+AL81 -> 0 | AQ81: =+AO81+AP81 -> 39488.33
H82: AG - Pedagogical Advisor (6) | I82: Diana Patricia Alemán | J82: 0 | K82: 0 | L82: 0 | M82: 0 | N82: 6875.33 | O82: 0 | P82: 0 | Q82: 0 | R82: 0 | S82: =+Q82*R82 -> 0 | T82: 0 | U82: =SUM(S82:T82) -> 0 | V82: 0 | W82: 0 | X82: 0 | Y82: =V82*W82*X82 -> 0 | Z82: 0 | AA82: =SUM(Y82:Z82) -> 0 | AB82: 0 | AC82: 0 | AD82: 0 | AE82: =AB82*AC82*AD82 -> 0 | AF82: 0 | AG82: =SUM(AE82:AF82) -> 0 | AH82: =+J82+L82+N82 -> 6875.33 | AI82: =+K82+M82+O82 -> 0 | AJ82: =+AH82+AI82 -> 6875.33 | AK82: =+S82+Y82+AE82 -> 0 | AL82: =+T82+Z82+AF82 -> 0 | AM82: =+AK82+AL82 -> 0 | AO82: =+AH82+AK82 -> 6875.33 | AP82: =+AI82+AL82 -> 0 | AQ82: =+AO82+AP82 -> 6875.33
H83: AG - Pedagogical Advisor (7) | I83: Eliana Patricia Patiño Patiño | J83: 0 | K83: 0 | L83: 0 | M83: 0 | N83: 7463.61 | O83: 0 | P83: 0 | Q83: 0 | R83: 0 | S83: =+Q83*R83 -> 0 | T83: 0 | U83: =SUM(S83:T83) -> 0 | V83: 0 | W83: 0 | X83: 0 | Y83: =V83*W83*X83 -> 0 | Z83: 0 | AA83: =SUM(Y83:Z83) -> 0 | AB83: 0 | AC83: 0 | AD83: 0 | AE83: =AB83*AC83*AD83 -> 0 | AF83: 0 | AG83: =SUM(AE83:AF83) -> 0 | AH83: =+J83+L83+N83 -> 7463.61 | AI83: =+K83+M83+O83 -> 0 | AJ83: =+AH83+AI83 -> 7463.61 | AK83: =+S83+Y83+AE83 -> 0 | AL83: =+T83+Z83+AF83 -> 0 | AM83: =+AK83+AL83 -> 0 | AO83: =+AH83+AK83 -> 7463.61 | AP83: =+AI83+AL83 -> 0 | AQ83: =+AO83+AP83 -> 7463.61
H84: AG - Pedagogical Advisor (8) | I84: Gloria Edith Ocampo López | J84: 0 | K84: 0 | L84: 0 | M84: 0 | N84: 7642.65 | O84: 0 | P84: 1 | Q84: 993.99 | R84: 9 | S84: =+Q84*R84 -> 8945.91 | T84: 0 | U84: =SUM(S84:T84) -> 8945.91 | V84: 1 | W84: =+Q84*10%+Q84 -> 1093.389 | X84: 10 | Y84: =V84*W84*X84 -> 10933.89 | Z84: 0 | AA84: =SUM(Y84:Z84) -> 10933.89 | AB84: 0 | AC84: 0 | AD84: 0 | AE84: =AB84*AC84*AD84 -> 0 | AF84: 0 | AG84: =SUM(AE84:AF84) -> 0 | AH84: =+J84+L84+N84 -> 7642.65 | AI84: =+K84+M84+O84 -> 0 | AJ84: =+AH84+AI84 -> 7642.65 | AK84: =+S84+Y84+AE84 -> 19879.8 | AL84: =+T84+Z84+AF84 -> 0 | AM84: =+AK84+AL84 -> 19879.8 | AO84: =+AH84+AK84 -> 27522.45 | AP84: =+AI84+AL84 -> 0 | AQ84: =+AO84+AP84 -> 27522.45
H85: AG - Pedagogical Advisor (9) | I85: Gustavo Humberto Correa Hernández | J85: 0 | K85: 0 | L85: 0 | M85: 0 | N85: 6438.62 | O85: 0 | P85: 0 | Q85: 0 | R85: 0 | S85: =+Q85*R85 -> 0 | T85: 0 | U85: =SUM(S85:T85) -> 0 | V85: 0 | W85: 0 | X85: 0 | Y85: =V85*W85*X85 -> 0 | Z85: 0 | AA85: =SUM(Y85:Z85) -> 0 | AB85: 0 | AC85: 0 | AD85: 0 | AE85: =AB85*AC85*AD85 -> 0 | AF85: 0 | AG85: =SUM(AE85:AF85) -> 0 | AH85: =+J85+L85+N85 -> 6438.62 | AI85: =+K85+M85+O85 -> 0 | AJ85: =+AH85+AI85 -> 6438.62 | AK85: =+S85+Y85+AE85 -> 0 | AL85: =+T85+Z85+AF85 -> 0 | AM85: =+AK85+AL85 -> 0 | AO85: =+AH85+AK85 -> 6438.62 | AP85: =+AI85+AL85 -> 0 | AQ85: =+AO85+AP85 -> 6438.62
H86: AG - Pedagogical Advisor (10) | I86: Isabella Andrea Ruíz Ruíz | J86: 0 | K86: 0 | L86: 0 | M86: 0 | N86: 7463.61 | O86: 0 | P86: 0 | Q86: 0 | R86: 0 | S86: =+Q86*R86 -> 0 | T86: 0 | U86: =SUM(S86:T86) -> 0 | V86: 0 | W86: 0 | X86: 0 | Y86: =V86*W86*X86 -> 0 | Z86: 0 | AA86: =SUM(Y86:Z86) -> 0 | AB86: 0 | AC86: 0 | AD86: 0 | AE86: =AB86*AC86*AD86 -> 0 | AF86: 0 | AG86: =SUM(AE86:AF86) -> 0 | AH86: =+J86+L86+N86 -> 7463.61 | AI86: =+K86+M86+O86 -> 0 | AJ86: =+AH86+AI86 -> 7463.61 | AK86: =+S86+Y86+AE86 -> 0 | AL86: =+T86+Z86+AF86 -> 0 | AM86: =+AK86+AL86 -> 0 | AO86: =+AH86+AK86 -> 7463.61 | AP86: =+AI86+AL86 -> 0 | AQ86: =+AO86+AP86 -> 7463.61
H87: AG - Pedagogical Advisor (11) | I87: Jaime Rafael Franco Bracamonte | J87: 0 | K87: 0 | L87: 0 | M87: 0 | N87: 7642.65 | O87: 0 | P87: 0 | Q87: 0 | R87: 0 | S87: =+Q87*R87 -> 0 | T87: 0 | U87: =SUM(S87:T87) -> 0 | V87: 0 | W87: 0 | X87: 0 | Y87: =V87*W87*X87 -> 0 | Z87: 0 | AA87: =SUM(Y87:Z87) -> 0 | AB87: 0 | AC87: 0 | AD87: 0 | AE87: =AB87*AC87*AD87 -> 0 | AF87: 0 | AG87: =SUM(AE87:AF87) -> 0 | AH87: =+J87+L87+N87 -> 7642.65 | AI87: =+K87+M87+O87 -> 0 | AJ87: =+AH87+AI87 -> 7642.65 | AK87: =+S87+Y87+AE87 -> 0 | AL87: =+T87+Z87+AF87 -> 0 | AM87: =+AK87+AL87 -> 0 | AO87: =+AH87+AK87 -> 7642.65 | AP87: =+AI87+AL87 -> 0 | AQ87: =+AO87+AP87 -> 7642.65
H88: AG - Pedagogical Advisor (12) | I88: Javier Noreña Salas | J88: 0 | K88: 0 | L88: 0 | M88: 0 | N88: 8555.09 | O88: 0 | P88: 1 | Q88: 993.99 | R88: 9 | S88: =+Q88*R88 -> 8945.91 | T88: 0 | U88: =SUM(S88:T88) -> 8945.91 | V88: 1 | W88: =+Q88*10%+Q88 -> 1093.389 | X88: 10 | Y88: =V88*W88*X88 -> 10933.89 | Z88: 0 | AA88: =SUM(Y88:Z88) -> 10933.89 | AB88: 0 | AC88: 0 | AD88: 0 | AE88: =AB88*AC88*AD88 -> 0 | AF88: 0 | AG88: =SUM(AE88:AF88) -> 0 | AH88: =+J88+L88+N88 -> 8555.09 | AI88: =+K88+M88+O88 -> 0 | AJ88: =+AH88+AI88 -> 8555.09 | AK88: =+S88+Y88+AE88 -> 19879.8 | AL88: =+T88+Z88+AF88 -> 0 | AM88: =+AK88+AL88 -> 19879.8 | AO88: =+AH88+AK88 -> 28434.89 | AP88: =+AI88+AL88 -> 0 | AQ88: =+AO88+AP88 -> 28434.89
H89: AG - Pedagogical Advisor (13) | I89: Jéssica Patricia Ayola Bermejo | J89: 0 | K89: 0 | L89: 0 | M89: 0 | N89: 6438.62 | O89: 0 | P89: 1 | Q89: 993.99 | R89: 9 | S89: =+Q89*R89 -> 8945.91 | T89: 0 | U89: =SUM(S89:T89) -> 8945.91 | V89: 1 | W89: =+Q89*10%+Q89 -> 1093.389 | X89: 0 | Y89: =V89*W89*X89 -> 0 | Z89: 0 | AA89: =SUM(Y89:Z89) -> 0 | AB89: 0 | AC89: 0 | AD89: 0 | AE89: =AB89*AC89*AD89 -> 0 | AF89: 0 | AG89: =SUM(AE89:AF89) -> 0 | AH89: =+J89+L89+N89 -> 6438.62 | AI89: =+K89+M89+O89 -> 0 | AJ89: =+AH89+AI89 -> 6438.62 | AK89: =+S89+Y89+AE89 -> 8945.91 | AL89: =+T89+Z89+AF89 -> 0 | AM89: =+AK89+AL89 -> 8945.91 | AO89: =+AH89+AK89 -> 15384.53 | AP89: =+AI89+AL89 -> 0 | AQ89: =+AO89+AP89 -> 15384.53
H90: AG - Pedagogical Advisor (14) | I90: Alexandra Hernández Cruz | J90: 0 | K90: 0 | L90: 0 | M90: 0 | N90: 0 | O90: 0 | P90: 1 | Q90: 993.99 | R90: 12 | S90: =+Q90*R90 -> 11927.88 | T90: 0 | U90: =SUM(S90:T90) -> 11927.88 | V90: 1 | W90: =+Q90*10%+Q90 -> 1093.389 | X90: 0 | Y90: =V90*W90*X90 -> 0 | Z90: 0 | AA90: =SUM(Y90:Z90) -> 0 | AB90: 0 | AC90: 0 | AD90: 0 | AE90: =AB90*AC90*AD90 -> 0 | AF90: 0 | AG90: =SUM(AE90:AF90) -> 0 | AH90: =+J90+L90+N90 -> 0 | AI90: =+K90+M90+O90 -> 0 | AJ90: =+AH90+AI90 -> 0 | AK90: =+S90+Y90+AE90 -> 11927.88 | AL90: =+T90+Z90+AF90 -> 0 | AM90: =+AK90+AL90 -> 11927.88 | AO90: =+AH90+AK90 -> 11927.88 | AP90: =+AI90+AL90 -> 0 | AQ90: =+AO90+AP90 -> 11927.88
H91: AG - Pedagogical Advisor (15) | I91: Sandra Manyoma | J91: 0 | K91: 0 | L91: 0 | M91: 0 | N91: 7642.65 | O91: 0 | P91: 1 | Q91: 993.99 | R91: 9 | S91: =+Q91*R91 -> 8945.91 | T91: 0 | U91: =SUM(S91:T91) -> 8945.91 | V91: 1 | W91: =+Q91*10%+Q91 -> 1093.389 | X91: 0 | Y91: =V91*W91*X91 -> 0 | Z91: 0 | AA91: =SUM(Y91:Z91) -> 0 | AB91: 0 | AC91: 0 | AD91: 0 | AE91: =AB91*AC91*AD91 -> 0 | AF91: 0 | AG91: =SUM(AE91:AF91) -> 0 | AH91: =+J91+L91+N91 -> 7642.65 | AI91: =+K91+M91+O91 -> 0 | AJ91: =+AH91+AI91 -> 7642.65 | AK91: =+S91+Y91+AE91 -> 8945.91 | AL91: =+T91+Z91+AF91 -> 0 | AM91: =+AK91+AL91 -> 8945.91 | AO91: =+AH91+AK91 -> 16588.56 | AP91: =+AI91+AL91 -> 0 | AQ91: =+AO91+AP91 -> 16588.56
H92: AG - Pedagogical Advisor (16) | I92: Sesly Paola Argúmedo Quintero | J92: 0 | K92: 0 | L92: 0 | M92: 0 | N92: 7026.91 | O92: 0 | P92: 0 | Q92: 0 | R92: 0 | S92: =+Q92*R92 -> 0 | T92: 0 | U92: =SUM(S92:T92) -> 0 | V92: 0 | W92: 0 | X92: 0 | Y92: =V92*W92*X92 -> 0 | Z92: 0 | AA92: =SUM(Y92:Z92) -> 0 | AB92: 0 | AC92: 0 | AD92: 0 | AE92: =AB92*AC92*AD92 -> 0 | AF92: 0 | AG92: =SUM(AE92:AF92) -> 0 | AH92: =+J92+L92+N92 -> 7026.91 | AI92: =+K92+M92+O92 -> 0 | AJ92: =+AH92+AI92 -> 7026.91 | AK92: =+S92+Y92+AE92 -> 0 | AL92: =+T92+Z92+AF92 -> 0 | AM92: =+AK92+AL92 -> 0 | AO92: =+AH92+AK92 -> 7026.91 | AP92: =+AI92+AL92 -> 0 | AQ92: =+AO92+AP92 -> 7026.91
H93: AG - Pedagogical Advisor (17) | I93: Angélica Delgado Marulanda | J93: 0 | K93: 0 | L93: 0 | M93: 0 | N93: 2305.85 | O93: 0 | P93: 1 | Q93: 993.99 | R93: 10 | S93: =+Q93*R93 -> 9939.9 | T93: 0 | U93: =SUM(S93:T93) -> 9939.9 | V93: 1 | W93: =+Q93*10%+Q93 -> 1093.389 | X93: 0 | Y93: =V93*W93*X93 -> 0 | Z93: 0 | AA93: =SUM(Y93:Z93) -> 0 | AB93: 0 | AC93: 0 | AD93: 0 | AE93: =AB93*AC93*AD93 -> 0 | AF93: 0 | AG93: =SUM(AE93:AF93) -> 0 | AH93: =+J93+L93+N93 -> 2305.85 | AI93: =+K93+M93+O93 -> 0 | AJ93: =+AH93+AI93 -> 2305.85 | AK93: =+S93+Y93+AE93 -> 9939.9 | AL93: =+T93+Z93+AF93 -> 0 | AM93: =+AK93+AL93 -> 9939.9 | AO93: =+AH93+AK93 -> 12245.75 | AP93: =+AI93+AL93 -> 0 | AQ93: =+AO93+AP93 -> 12245.75
H94: AG - Pedagogical Advisor (18) | I94: Elsy Lorena Balanta Campo | J94: 0 | K94: 0 | L94: 0 | M94: 0 | N94: 2305.85 | O94: 0 | P94: 0 | Q94: 0 | R94: 0 | S94: =+Q94*R94 -> 0 | T94: 0 | U94: =SUM(S94:T94) -> 0 | V94: 0 | W94: 0 | X94: 0 | Y94: =V94*W94*X94 -> 0 | Z94: 0 | AA94: =SUM(Y94:Z94) -> 0 | AB94: 0 | AC94: 0 | AD94: 0 | AE94: =AB94*AC94*AD94 -> 0 | AF94: 0 | AG94: =SUM(AE94:AF94) -> 0 | AH94: =+J94+L94+N94 -> 2305.85 | AI94: =+K94+M94+O94 -> 0 | AJ94: =+AH94+AI94 -> 2305.85 | AK94: =+S94+Y94+AE94 -> 0 | AL94: =+T94+Z94+AF94 -> 0 | AM94: =+AK94+AL94 -> 0 | AO94: =+AH94+AK94 -> 2305.85 | AP94: =+AI94+AL94 -> 0 | AQ94: =+AO94+AP94 -> 2305.85
H95: AG - Pedagogical Advisor (20) | I95: TBD | J95: 0 | K95: 0 | L95: 0 | M95: 0 | N95: 0 | O95: 4101.64 | P95: 1 | Q95: 993.99 | R95: 9 | S95: =+Q95*R95 -> 8945.91 | T95: 0 | U95: =SUM(S95:T95) -> 8945.91 | V95: 1 | W95: =+Q95*10%+Q95 -> 1093.389 | X95: 0 | Y95: =V95*W95*X95 -> 0 | Z95: 0 | AA95: =SUM(Y95:Z95) -> 0 | AB95: 0 | AC95: 0 | AD95: 0 | AE95: =AB95*AC95*AD95 -> 0 | AF95: 0 | AG95: =SUM(AE95:AF95) -> 0 | AH95: =+J95+L95+N95 -> 0 | AI95: =+K95+M95+O95 -> 4101.64 | AJ95: =+AH95+AI95 -> 4101.64 | AK95: =+S95+Y95+AE95 -> 8945.91 | AL95: =+T95+Z95+AF95 -> 0 | AM95: =+AK95+AL95 -> 8945.91 | AO95: =+AH95+AK95 -> 8945.91 | AP95: =+AI95+AL95 -> 4101.64 | AQ95: =+AO95+AP95 -> 13047.55
H96: AG - Pedagogical Advisor (21) | I96: TBD | J96: 0 | K96: 0 | L96: 0 | M96: 0 | N96: 0 | O96: 0 | P96: 1 | Q96: 993.99 | R96: 9 | S96: =+Q96*R96 -> 8945.91 | T96: 0 | U96: =SUM(S96:T96) -> 8945.91 | V96: 1 | W96: =+Q96*10%+Q96 -> 1093.389 | X96: 0 | Y96: =V96*W96*X96 -> 0 | Z96: 0 | AA96: =SUM(Y96:Z96) -> 0 | AB96: 0 | AC96: 0 | AD96: 0 | AE96: =AB96*AC96*AD96 -> 0 | AF96: 0 | AG96: =SUM(AE96:AF96) -> 0 | AH96: =+J96+L96+N96 -> 0 | AI96: =+K96+M96+O96 -> 0 | AJ96: =+AH96+AI96 -> 0 | AK96: =+S96+Y96+AE96 -> 8945.91 | AL96: =+T96+Z96+AF96 -> 0 | AM96: =+AK96+AL96 -> 8945.91 | AO96: =+AH96+AK96 -> 8945.91 | AP96: =+AI96+AL96 -> 0 | AQ96: =+AO96+AP96 -> 8945.91
H97: AG - Pedagogical Advisor (22) | I97: TBD | J97: 0 | K97: 0 | L97: 0 | M97: 0 | N97: 0 | O97: 0 | P97: 1 | Q97: 993.99 | R97: 9 | S97: =+Q97*R97 -> 8945.91 | T97: 0 | U97: =SUM(S97:T97) -> 8945.91 | V97: 1 | W97: =+Q97*10%+Q97 -> 1093.389 | X97: 0 | Y97: =V97*W97*X97 -> 0 | Z97: 0 | AA97: =SUM(Y97:Z97) -> 0 | AB97: 0 | AC97: 0 | AD97: 0 | AE97: =AB97*AC97*AD97 -> 0 | AF97: 0 | AG97: =SUM(AE97:AF97) -> 0 | AH97: =+J97+L97+N97 -> 0 | AI97: =+K97+M97+O97 -> 0 | AJ97: =+AH97+AI97 -> 0 | AK97: =+S97+Y97+AE97 -> 8945.91 | AL97: =+T97+Z97+AF97 -> 0 | AM97: =+AK97+AL97 -> 8945.91 | AO97: =+AH97+AK97 -> 8945.91 | AP97: =+AI97+AL97 -> 0 | AQ97: =+AO97+AP97 -> 8945.91
H98: Technical Team - Subactivity: MEF (2 Sr. - 8PA) | AH98: =+J98+L98+N98 -> 0 | AI98: =+K98+M98+O98 -> 0 | AJ98: =+AH98+AI98 -> 0 | AK98: =+S98+Y98+AE98 -> 0 | AL98: =+T98+Z98+AF98 -> 0 | AM98: =+AK98+AL98 -> 0 | AO98: =+AH98+AK98 -> 0 | AP98: =+AI98+AL98 -> 0 | AQ98: =+AO98+AP98 -> 0
G99: 2 Senior Pedagogical Advisors for Tutors - Flexible Learning Models | H99: Senior Pedagogical Advisors for Tutors - Flexible Learning Models
A100: SUBFCARVA | B100: 89050 | C100: COL2 | D100: COL2 | E100: CARVAJAL | F100: FCPERSNL | H100: MEF - Senior Pedagogical Advisor (1) | I100: Ma. Victoria Villamizar | J100: 4501.67 | K100: 0 | L100: 11300.69 | M100: 0 | N100: 12485.73 | O100: 0 | P100: 1 | Q100: 1289.53 | R100: 10 | S100: =+Q100*R100 -> 12895.3 | T100: 0 | U100: =SUM(S100:T100) -> 12895.3 | V100: 1 | W100: =+Q100*10%+Q100 -> 1418.483 | X100: 10 | Y100: =V100*W100*X100 -> 14184.83 | Z100: 0 | AA100: =SUM(Y100:Z100) -> 14184.83 | AB100: 1 | AC100: =+W100*10%+W100 -> 1560.3313 | AD100: 6 | AE100: =AB100*AC100*AD100 -> 9361.9878 | AF100: 0 | AG100: =SUM(AE100:AF100) -> 9361.9878 | AH100: =+J100+L100+N100 -> 28288.09 | AI100: =+K100+M100+O100 -> 0 | AJ100: =+AH100+AI100 -> 28288.09 | AK100: =+S100+Y100+AE100 -> 36442.118 | AL100: =+T100+Z100+AF100 -> 0 | AM100: =+AK100+AL100 -> 36442.118 | AO100: =+AH100+AK100 -> 64730.208 | AP100: =+AI100+AL100 -> 0 | AQ100: =+AO100+AP100 -> 64730.208
H101: MEF - Senior Pedagogical Advisor (2) | I101: Rubén Darío Betancur | J101: 4501.67 | K101: 0 | L101: 11300.69 | M101: 0 | N101: 12485.73 | O101: 0 | P101: 1 | Q101: 1289.53 | R101: 10 | S101: =+Q101*R101 -> 12895.3 | T101: 0 | U101: =SUM(S101:T101) -> 12895.3 | V101: 1 | W101: =+Q101*10%+Q101 -> 1418.483 | X101: 10 | Y101: =V101*W101*X101 -> 14184.83 | Z101: 0 | AA101: =SUM(Y101:Z101) -> 14184.83 | AB101: 1 | AC101: =+W101*10%+W101 -> 1560.3313 | AD101: 6 | AE101: =AB101*AC101*AD101 -> 9361.9878 | AF101: 0 | AG101: =SUM(AE101:AF101) -> 9361.9878 | AH101: =+J101+L101+N101 -> 28288.09 | AI101: =+K101+M101+O101 -> 0 | AJ101: =+AH101+AI101 -> 28288.09 | AK101: =+S101+Y101+AE101 -> 36442.118 | AL101: =+T101+Z101+AF101 -> 0 | AM101: =+AK101+AL101 -> 36442.118 | AO101: =+AH101+AK101 -> 64730.208 | AP101: =+AI101+AL101 -> 0 | AQ101: =+AO101+AP101 -> 64730.208
G102: 16 Senior Pedagogical Advisors - Flexible Learning Models | H102: Pedagogical Advisors - Flexible Learning Models
...

Sheet 800-FC - Consolidated Details
A4: Entity: | B4: P
A5: Program-Dept.: | B5: 20300 | G5: Modification 7 - Budget Assumptions
A6: Funder-Grant: | B6: USAID800 | G6: Inflation - Locally Purchased Goods/Services - 8%
G7: Merit Based Increases for HQ & Field Staff - 10%
H9: Actuals/Estimates Year 1 and 2 and 3 (January 1, 2023 - December 31, 2023) | N9: Projections for Year 3 (January 1, 2024 - December 31, 2024) - 6 | AM9: New Proposed Budget Total
A10: Sage Activity | B10: Sage Object Code/ Line Item | C10: Country Code (DC=0 or CO) | D10: Office Code (DC=0 or CO) | E10: Subcontract Code | F10: Open 1 Code | H10: USAID Year 1 -Actuals August 16, 2021 - December 31, 2021 | I10: Leverage Year 1 - Actuals August 16, 2021 - December 31, 2021 | J10: USAID Year 2 - Actuals January 1, 2022 - December 31, 2022 | K10: Leverage Year 2 - Actuals January 1, 2022 - December 31, 2022 | L10: USAID Year 3 - Actuals January 1, 2023 - December 31, 2023 | M10: Leverage Year 3 - Actuals January 1, 2023 - July 31, 2023 | N10: Year 4 - January 1, 2024 - December 31, 2024 | T10: Year 5 - January 1, 2025 - December 31, 2025 | Z10: Year 6 - January 1, 2026 - Agosto 31, 2026 | AF10: Actuals Year 1- 3 | AG10: Actuals Year 1- 3 | AH10: Actuals Year 1- 3 | AI10: Year 4- 6 | AJ10: Year 4- 6 | AK10: Year 4- 6 | AM10: Total | AN10: Total | AO10: Grand
N11: Unit LOE | O11: Cost | P11: Duration | Q11: USAID | R11: Leverage | S11: Total | T11: Unit LOE | U11: Cost | V11: Duration | W11: USAID | X11: Leverage | Y11: Total | Z11: Unit | AA11: Cost | AB11: Duration | AC11: USAID | AD11: Leverage | AE11: Total | AF11: Total USAID | AG11: Total Leverage | AH11: Grand Total | AI11: Total USAID | AJ11: Total Leverage | AK11: Grand Total | AM11: USAID | AN11: Leverage | AO11: Total
G12: 1. Personnel
G13: Headquarters Personnel (include Level of Effort)
G14: Fundación Carvajal Management Team
A15: SUBFCARVA | B15: 89050 | C15: COL2 | D15: COL2 | E15: CARVAJAL | F15: FCPERSNL/ FCPERSNLEV | G15: Program Director/Management Team | H15: 9207.63 | I15: 1087.7 | J15: 21864.25 | K15: 0 | L15: 16983.86 | M15: 8197.2 | N15: 0.26 | O15: 1641.45 | P15: 10.5 | Q15: =+O15*P15 -> 17235.225 | R15: =704.89*10.5 -> 7401.345 | S15: =SUM(Q15:R15) -> 24636.57 | T15: 0.5 | U15: =+O15*10%+O15 -> 1805.595 | V15: 12 | W15: =+U15*V15 -> 21667.14 | X15: =+R15*1.1 -> 8141.4795 | Y15: =SUM(W15:X15) -> 29808.62 | Z15: 0.5 | AA15: =+U15*1.1 -> 1986.1545 | AB15: 8 | AC15: =Z15*AA15*AB15 -> 7944.618 | AD15: =+(X15*1.1)/12*AB15 -> 5970.4183 | AE15: =SUM(AC15:AD15) -> 13915.036 | AF15: =+H15+J15+L15 -> 48055.74 | AG15: =+I15+K15+M15 -> 9284.9 | AH15: =+AF15+AG15 -> 57340.64 | AI15: =+Q15+W15+AC15 -> 46846.983 | AJ15: =+R15+X15+AD15 -> 21513.243 | AK15: =+AI15+AJ15 -> 68360.226 | AM15: =+AF15+AI15 -> 94902.723 | AN15: =+AG15+AJ15 -> 30798.143 | AO15: =+AM15+AN15 -> 125700.87
A16: SUBFCARVA | B16: 89050 | C16: COL2 | D16: COL2 | E16: CARVAJAL | F16: FCPERSNL | G16: Education Director* | H16: 4793.31 | I16: 0 | J16: 37385.23 | K16: 0 | L16: 41755.1 | M16: 0 | N16: 1 | O16: 4172.84 | P16: 12 | Q16: =O16*P16 -> 50074.08 | R16: 0 | S16: =SUM(Q16:R16) -> 50074.08 | T16: 1 | U16: =+O16*10%+O16 -> 4590.124 | V16: 12 | W16: =+U16*V16 -> 55081.488 | X16: 0 | Y16: =SUM(W16:X16) -> 55081.488 | Z16: 1 | AA16: =+U16*10%+U16 -> 5049.1364 | AB16: 8 | AC16: =Z16*AA16*AB16 -> 40393.091 | AD16: 0 | AE16: =SUM(AC16:AD16) -> 40393.091 | AF16: =+H16+J16+L16 -> 83933.64 | AG16: =+I16+K16+M16 -> 0 | AH16: =+AF16+AG16 -> 83933.64 | AI16: =+Q16+W16+AC16 -> 145548.66 | AJ16: =+R16+X16+AD16 -> 0 | AK16: =+AI16+AJ16 -> 145548.66 | AM16: =+AF16+AI16 -> 229482.3 | AN16: =+AG16+AJ16 -> 0 | AO16: =+AM16+AN16 -> 229482.3
G17: Core Technical Team | AO17: =+AM17+AN17 -> 0
A18: SUBFCARVA | B18: 89050 | C18: COL2 | D18: COL2 | E18: CARVAJAL | F18: FCPERSNL | G18: Education Manager | H18: 8591.19 | I18: 0 | J18: 21376.46 | K18: 0 | L18: 0 | M18: 0 | N18: 0 | O18: 0 | P18: 0 | Q18: =+O18*P18 -> 0 | R18: 0 | S18: =SUM(Q18:R18) -> 0 | T18: 0 | U18: 0 | V18: 0 | W18: =+U18*V18 -> 0 | X18: 0 | Y18: =SUM(W18:X18) -> 0 | Z18: 0 | AA18: 0 | AB18: 0 | AC18: =Z18*AA18*AB18 -> 0 | AD18: 0 | AE18: =SUM(AC18:AD18) -> 0 | AF18: =+H18+J18+L18 -> 29967.65 | AG18: =+I18+K18+M18 -> 0 | AH18: =+AF18+AG18 -> 29967.65 | AI18: =+Q18+W18+AC18 -> 0 | AJ18: =+R18+X18+AD18 -> 0 | AK18: =+AI18+AJ18 -> 0 | AM18: =+AF18+AI18 -> 29967.65 | AN18: =+AG18+AJ18 -> 0 | AO18: =+AM18+AN18 -> 29967.65
G19: Education Coordinator | H19: 0 | I19: 0 | J19: 0 | K19: 0 | L19: 14944.37 | M19: 0 | N19: 1 | O19: 1678.7 | P19: 12 | Q19: =+O19*P19 -> 20144.4 | R19: 0 | S19: =SUM(Q19:R19) -> 20144.4 | T19: 1 | U19: =+O19*10%+O19 -> 1846.57 | V19: 12 | W19: =+U19*V19 -> 22158.84 | X19: 0 | Y19: =SUM(W19:X19) -> 22158.84 | Z19: 1 | AA19: =+U19*10%+U19 -> 2031.227 | AB19: 8 | AC19: =Z19*AA19*AB19 -> 16249.816 | AD19: 0 | AE19: =SUM(AC19:AD19) -> 16249.816 | AF19: =+H19+J19+L19 -> 14944.37 | AG19: =+I19+K19+M19 -> 0 | AH19: =+AF19+AG19 -> 14944.37 | AI19: =+Q19+W19+AC19 -> 58553.056 | AJ19: =+R19+X19+AD19 -> 0 | AK19: =+AI19+AJ19 -> 58553.056 | AM19: =+AF19+AI19 -> 73497.426 | AN19: =+AG19+AJ19 -> 0 | AO19: =+AM19+AN19 -> 73497.426
A20: SUBFCARVA | B20: 89050 | C20: COL2 | D20: COL2 | E20: CARVAJAL | F20: FCPERSNL | G20: Pre-Primary Education Specialist | H20: 1992.97 | I20: 0 | J20: 16987.89 | K20: 0 | L20: 16923 | M20: 0 | N20: 1 | O20: 1645.65 | P20: 12 | Q20: =+O20*P20 -> 19747.8 | R20: 0 | S20: =SUM(Q20:R20) -> 19747.8 | T20: 1 | U20: =+O20*10%+O20 -> 1810.215 | V20: 12 | W20: =+U20*V20 -> 21722.58 | X20: 0 | Y20: =SUM(W20:X20) -> 21722.58 | Z20: 1 | AA20: =+U20*10%+U20 -> 1991.2365 | AB20: 6 | AC20: =Z20*AA20*AB20 -> 11947.419 | AD20: 0 | AE20: =SUM(AC20:AD20) -> 11947.419 | AF20: =+H20+J20+L20 -> 35903.86 | AG20: =+I20+K20+M20 -> 0 | AH20: =+AF20+AG20 -> 35903.86 | AI20: =+Q20+W20+AC20 -> 53417.799 | AJ20: =+R20+X20+AD20 -> 0 | AK20: =+AI20+AJ20 -> 53417.799 | AM20: =+AF20+AI20 -> 89321.659 | AN20: =+AG20+AJ20 -> 0 | AO20: =+AM20+AN20 -> 89321.659
A21: SUBFCARVA | B21: 89050 | C21: COL2 | D21: COL2 | E21: CARVAJAL | F21: FCPERSNL | G21: Primary Education Specialist | H21: 5796.13 | I21: 0 | J21: 14394.25 | K21: 0 | L21: 15856.88 | M21: 0 | N21: 1 | O21: 1557.95 | P21: 12 | Q21: =+O21*P21 -> 18695.4 | R21: 0 | S21: =SUM(Q21:R21) -> 18695.4 | T21: 1 | U21: =+O21*10%+O21 -> 1713.745 | V21: 12 | W21: =+U21*V21 -> 20564.94 | X21: 0 | Y21: =SUM(W21:X21) -> 20564.94 | Z21: 1 | AA21: =+U21*10%+U21 -> 1885.1195 | AB21: 6 | AC21: =Z21*AA21*AB21 -> 11310.717 | AD21: 0 | AE21: =SUM(AC21:AD21) -> 11310.717 | AF21: =+H21+J21+L21 -> 36047.26 | AG21: =+I21+K21+M21 -> 0 | AH21: =+AF21+AG21 -> 36047.26 | AI21: =+Q21+W21+AC21 -> 50571.057 | AJ21: =+R21+X21+AD21 -> 0 | AK21: =+AI21+AJ21 -> 50571.057 | AM21: =+AF21+AI21 -> 86618.317 | AN21: =+AG21+AJ21 -> 0 | AO21: =+AM21+AN21 -> 86618.317
A22: SUBFCARVA | B22: 89050 | C22: COL2 | D22: COL2 | E22: CARVAJAL | F22: FCPERSNL | G22: Secondary Education Specialist | H22: 0 | I22: 0 | J22: 12249.75 | K22: 0 | L22: 17074.28 | M22: 0 | N22: 1 | O22: 1657.81 | P22: 12 | Q22: =+O22*P22 -> 19893.72 | R22: 0 | S22: =SUM(Q22:R22) -> 19893.72 | T22: 1 | U22: =+O22*10%+O22 -> 1823.591 | V22: 12 | W22: =+U22*V22 -> 21883.092 | X22: 0 | Y22: =SUM(W22:X22) -> 21883.092 | Z22: 1 | AA22: =+U22*10%+U22 -> 2005.9501 | AB22: 6 | AC22: =Z22*AA22*AB22 -> 12035.701 | AD22: 0 | AE22: =SUM(AC22:AD22) -> 12035.701 | AF22: =+H22+J22+L22 -> 29324.03 | AG22: =+I22+K22+M22 -> 0 | AH22: =+AF22+AG22 -> 29324.03 | AI22: =+Q22+W22+AC22 -> 53812.513 | AJ22: =+R22+X22+AD22 -> 0 | AK22: =+AI22+AJ22 -> 53812.513 | AM22: =+AF22+AI22 -> 83136.543 | AN22: =+AG22+AJ22 -> 0 | AO22: =+AM22+AN22 -> 83136.543
A23: SUBFCARVA | B23: 89050 | C23: COL2 | D23: COL2 | E23: CARVAJAL | F23: FCPERSNL | G23: Alternative Education Specialist | H23: 0 | I23: 0 | J23: 14276.65 | K23: 0 | L23: 11067.62 | M23: 0 | N23: 1 | O23: 1555.4 | P23: 0 | Q23: =+O23*P23 -> 0 | R23: 0 | S23: =SUM(Q23:R23) -> 0 | T23: 1 | U23: =+O23*10%+O23 -> 1710.94 | V23: 12 | W23: =+U23*V23 -> 20531.28 | X23: 0 | Y23: =SUM(W23:X23) -> 20531.28 | Z23: 1 | AA23: =+U23*10%+U23 -> 1882.034 | AB23: 6 | AC23: =Z23*AA23*AB23 -> 11292.204 | AD23: 0 | AE23: =SUM(AC23:AD23) -> 11292.204 | AF23: =+H23+J23+L23 -> 25344.27 | AG23: =+I23+K23+M23 -> 0 | AH23: =+AF23+AG23 -> 25344.27 | AI23: =+Q23+W23+AC23 -> 31823.484 | AJ23: =+R23+X23+AD23 -> 0 | AK23: =+AI23+AJ23 -> 31823.484 | AM23: =+AF23+AI23 -> 57167.754 | AN23: =+AG23+AJ23 -> 0 | AO23: =+AM23+AN23 -> 57167.754
A24: SUBFCARVA | B24: 89050 | C24: COL2 | D24: COL2 | E24: CARVAJAL | F24: FCPERSNL | G24: Methodological Coordinator/Specialist - MEF | H24: 4573.43 | I24: 0 | J24: 12040.88 | K24: 0 | L24: 13903.73 | M24: 0 | N24: 1 | O24: 1536.1 | P24: 12 | Q24: =+O24*P24 -> 18433.2 | R24: 0 | S24: =SUM(Q24:R24) -> 18433.2 | T24: 1 | U24: =+O24*10%+O24 -> 1689.71 | V24: 12 | W24: =+U24*V24 -> 20276.52 | X24: 0 | Y24: =SUM(W24:X24) -> 20276.52 | Z24: 1 | AA24: =+U24*10%+U24 -> 1858.681 | AB24: 6 | AC24: =Z24*AA24*AB24 -> 11152.086 | AD24: 0 | AE24: =SUM(AC24:AD24) -> 11152.086 | AF24: =+H24+J24+L24 -> 30518.04 | AG24: =+I24+K24+M24 -> 0 | AH24: =+AF24+AG24 -> 30518.04 | AI24: =+Q24+W24+AC24 -> 49861.806 | AJ24: =+R24+X24+AD24 -> 0 | AK24: =+AI24+AJ24 -> 49861.806 | AM24: =+AF24+AI24 -> 80379.846 | AN24: =+AG24+AJ24 -> 0 | AO24: =+AM24+AN24 -> 80379.846
A25: SUBFCARVA | B25: 89050 | C25: COL2 | D25: COL2 | E25: CARVAJAL | F25: FCPERSNL | G25: Learning Trajectories Manager | H25: 0 | I25: 0 | J25: 17164.83 | K25: 0 | L25: 23283.11 | M25: 0 | N25: 1 | O25: 2269.38 | P25: 12 | Q25: =+O25*P25 -> 27232.56 | R25: 0 | S25: =SUM(Q25:R25) -> 27232.56 | T25: 1 | U25: =+O25*10%+O25 -> 2496.318 | V25: 12 | W25: =+U25*V25 -> 29955.816 | X25: 0 | Y25: =SUM(W25:X25) -> 29955.816 | Z25: 1 | AA25: =+U25*10%+U25 -> 2745.9498 | AB25: 6 | AC25: =Z25*AA25*AB25 -> 16475.699 | AD25: 0 | AE25: =SUM(AC25:AD25) -> 16475.699 | AF25: =+H25+J25+L25 -> 40447.94 | AG25: =+I25+K25+M25 -> 0 | AH25: =+AF25+AG25 -> 40447.94 | AI25: =+Q25+W25+AC25 -> 73664.075 | AJ25: =+R25+X25+AD25 -> 0 | AK25: =+AI25+AJ25 -> 73664.075 | AM25: =+AF25+AI25 -> 114112.01 | AN25: =+AG25+AJ25 -> 0 | AO25: =+AM25+AN25 -> 114112.01
A26: SUBFCARVA | B26: 89050 | C26: COL2 | D26: COL2 | E26: CARVAJAL | F26: FCPERSNL | G26: Migration Officer | H26: 0 | I26: 0 | J26: 0 | K26: 0 | L26: 0 | M26: 0 | N26: 1 | O26: 993.99 | P26: 10 | Q26: =+O26*P26 -> 9939.9 | R26: 0 | S26: =SUM(Q26:R26) -> 9939.9 | T26: 1 | U26: =+O26*10%+O26 -> 1093.389 | V26: 12 | W26: =+U26*V26 -> 13120.668 | X26: 0 | Y26: =SUM(W26:X26) -> 13120.668 | Z26: 1 | AA26: =+U26*10%+U26 -> 1202.7279 | AB26: 6 | AC26: =Z26*AA26*AB26 -> 7216.3674 | AD26: 0 | AE26: =SUM(AC26:AD26) -> 7216.3674 | AF26: =+H26+J26+L26 -> 0 | AG26: =+I26+K26+M26 -> 0 | AH26: =+AF26+AG26 -> 0 | AI26: =+Q26+W26+AC26 -> 30276.935 | AJ26: =+R26+X26+AD26 -> 0 | AK26: =+AI26+AJ26 -> 30276.935 | AM26: =+AF26+AI26 -> 30276.935 | AN26: =+AG26+AJ26 -> 0 | AO26: =+AM26+AN26 -> 30276.935
G27: Subtotal HQ + Core Technical Team Personnel | H27: =+SUM(H15:H26) -> 34954.66 | I27: =+SUM(I15:I26) -> 1087.7 | J27: =+SUM(J15:J26) -> 167740.19 | K27: =+SUM(K15:K26) -> 0 | L27: =+SUM(L15:L26) -> 171791.95 | M27: =+SUM(M15:M26) -> 8197.2 | O27: =+SUM(O15:O26) -> 18709.27 | Q27: =+SUM(Q15:Q26) -> 201396.29 | R27: =+SUM(R15:R26) -> 7401.345 | S27: =+SUM(S15:S26) -> 208797.63 | U27: =+SUM(U15:U26) -> 20580.197 | W27: =+SUM(W15:W26) -> 246962.36 | X27: =+SUM(X15:X26) -> 8141.4795 | Y27: =+SUM(Y15:Y26) -> 255103.84 | AA27: =+SUM(AA15:AA26) -> 22638.217 | AC27: =+SUM(AC15:AC26) -> 146017.72 | AD27: =+SUM(AD15:AD26) -> 5970.4183 | AE27: =+SUM(AE15:AE26) -> 151988.14 | AF27: =+SUM(AF15:AF26) -> 374486.8 | AG27: =+SUM(AG15:AG26) -> 9284.9 | AH27: =+SUM(AH15:AH26) -> 383771.7 | AI27: =+SUM(AI15:AI26) -> 594376.37 | AJ27: =+SUM(AJ15:AJ26) -> 21513.243 | AK27: =+SUM(AK15:AK26) -> 615889.61 | AM27: =+SUM(AM15:AM26) -> 968863.17 | AN27: =+SUM(AN15:AN26) -> 30798.143 | AO27: =+SUM(AO15:AO26) -> 999661.31
G28: Field Personnel
G29: M&E Team
A30: SUBFCARVA | B30: 89050 | C30: COL2 | D30: COL2 | E30: CARVAJAL | F30: FCPERSNL | G30: Monitoring and Evaluation Specialist | H30: 5221.52 | I30: 0 | J30: 13894.7 | K30: 0 | L30: 15216.99 | M30: 0 | N30: 1 | O30: 1495.08 | P30: 12 | Q30: =+O30*P30 -> 17940.96 | R30: 0 | S30: =SUM(Q30:R30) -> 17940.96 | T30: 1 | U30: =+O30*10%+O30 -> 1644.588 | V30: 12 | W30: =+U30*V30 -> 19735.056 | X30: 0 | Y30: =SUM(W30:X30) -> 19735.056 | Z30: 1 | AA30: =+U30*10%+U30 -> 1809.0468 | AB30: 8 | AC30: =Z30*AA30*AB30 -> 14472.374 | AD30: 0 | AE30: =SUM(AC30:AD30) -> 14472.374 | AF30: =+H30+J30+L30 -> 34333.21 | AG30: =+I30+K30+M30 -> 0 | AH30: =+AF30+AG30 -> 34333.21 | AI30: =+Q30+W30+AC30 -> 52148.39 | AJ30: =+R30+X30+AD30 -> 0 | AK30: =+AI30+AJ30 -> 52148.39 | AM30: =+AF30+AI30 -> 86481.6 | AN30: =+AG30+AJ30 -> 0 | AO30: =+AM30+AN30 -> 86481.6
A31: SUBFCARVA | B31: 89050 | C31: COL2 | D31: COL2 | E31: CARVAJAL | F31: FCPERSNL | G31: Information System Professionals | H31: 3794.35 | I31: 0 | J31: 17294.99 | K31: 0 | L31: 20018.05 | M31: 0 | N31: 1 | O31: 2117.68 | P31: 12 | Q31: =+O31*P31 -> 25412.16 | R31: 0 | S31: =SUM(Q31:R31) -> 25412.16 | T31: 1 | U31: =+O31*10%+O31 -> 2329.448 | V31: 12 | W31: =+U31*V31 -> 27953.376 | X31: 0 | Y31: =SUM(W31:X31) -> 27953.376 | Z31: 1 | AA31: =+U31*10%+U31 -> 2562.3928 | AB31: 6 | AC31: =Z31*AA31*AB31 -> 15374.357 | AD31: 0 | AE31: =SUM(AC31:AD31) -> 15374.357 | AF31: =+H31+J31+L31 -> 41107.39 | AG31: =+I31+K31+M31 -> 0 | AH31: =+AF31+AG31 -> 41107.39 | AI31: =+Q31+W31+AC31 -> 68739.893 | AJ31: =+R31+X31+AD31 -> 0 | AK31: =+AI31+AJ31 -> 68739.893 | AM31: =+AF31+AI31 -> 109847.28 | AN31: =+AG31+AJ31 -> 0 | AO31: =+AM31+AN31 -> 109847.28
G32: Information Systems Analysts | H32: 0 | I32: 0 | J32: 0 | K32: 0 | L32: 17649.63 | M32: 0 | N32: 1 | O32: 1757.4 | P32: 12 | Q32: =+O32*P32 -> 21088.8 | R32: 0 | S32: =SUM(Q32:R32) -> 21088.8 | T32: 1 | U32: =+O32*10%+O32 -> 1933.14 | V32: 12 | W32: =+U32*V32 -> 23197.68 | X32: 0 | Y32: =SUM(W32:X32) -> 23197.68 | Z32: 1 | AA32: =+U32*10%+U32 -> 2126.454 | AB32: 6 | AC32: =Z32*AA32*AB32 -> 12758.724 | AD32: 0 | AE32: =SUM(AC32:AD32) -> 12758.724 | AF32: =+H32+J32+L32 -> 17649.63 | AG32: =+I32+K32+M32 -> 0 | AH32: =+AF32+AG32 -> 17649.63 | AI32: =+Q32+W32+AC32 -> 57045.204 | AJ32: =+R32+X32+AD32 -> 0 | AK32: =+AI32+AJ32 -> 57045.204 | AM32: =+AF32+AI32 -> 74694.834 | AN32: =+AG32+AJ32 -> 0 | AO32: =+AM32+AN32 -> 74694.834
G33: Grants Team
A34: SUBFCARVA | B34: 89050 | C34: COL2 | D34: COL2 | E34: CARVAJAL | F34: FCPERSNL | G34: Grants Specialist | H34: 4459.29 | I34: 0 | J34: 18701.01 | K34: 0 | L34: 19770.92 | M34: 0 | N34: 1 | O34: 1748.82 | P34: 12 | Q34: =+O34*P34 -> 20985.84 | R34: 0 | S34: =SUM(Q34:R34) -> 20985.84 | T34: 1 | U34: =+O34*10%+O34 -> 1923.702 | V34: 12 | W34: =T34*U34*V34 -> 23084.424 | X34: 0 | Y34: =SUM(W34:X34) -> 23084.424 | Z34: 1 | AA34: =+U34*10%+U34 -> 2116.0722 | AB34: 6 | AC34: =Z34*AA34*AB34 -> 12696.433 | AD34: 0 | AE34: =SUM(AC34:AD34) -> 12696.433 | AF34: =+H34+J34+L34 -> 42931.22 | AG34: =+I34+K34+M34 -> 0 | AH34: =+AF34+AG34 -> 42931.22 | AI34: =+Q34+W34+AC34 -> 56766.697 | AJ34: =+R34+X34+AD34 -> 0 | AK34: =+AI34+AJ34 -> 56766.697 | AM34: =+AF34+AI34 -> 99697.917 | AN34: =+AG34+AJ34 -> 0 | AO34: =+AM34+AN34 -> 99697.917
A35: SUBFCARVA | B35: 89050 | C35: COL2 | D35: COL2 | E35: CARVAJAL | F35: FCPERSNL | G35: 2nd Tier Subawardess Technical Supervisor | H35: 0 | I35: 0 | J35: 7199.58 | K35: 0 | L35: 12801.36 | M35: 0 | N35: 1 | O35: 1284.54 | P35: 6 | Q35: =+O35*P35 -> 7707.24 | R35: 0 | S35: =SUM(Q35:R35) -> 7707.24 | T35: 1 | U35: =+O35*10%+O35 -> 1412.994 | V35: 12 | W35: =T35*U35*V35 -> 16955.928 | X35: 0 | Y35: =SUM(W35:X35) -> 16955.928 | Z35: 1 | AA35: =+U35*10%+U35 -> 1554.2934 | AB35: 6 | AC35: =Z35*AA35*AB35 -> 9325.7604 | AD35: 0 | AE35: =SUM(AC35:AD35) -> 9325.7604 | AF35: =+H35+J35+L35 -> 20000.94 | AG35: =+I35+K35+M35 -> 0 | AH35: =+AF35+AG35 -> 20000.94 | AI35: =+Q35+W35+AC35 -> 33988.928 | AJ35: =+R35+X35+AD35 -> 0 | AK35: =+AI35+AJ35 -> 33988.928 | AM35: =+AF35+AI35 -> 53989.868 | AN35: =+AG35+AJ35 -> 0 | AO35: =+AM35+AN35 -> 53989.868
G36: F&A Team
A37: SUBFCARVA | B37: 89050 | C37: COL2 | D37: COL2 | E37: CARVAJAL | F37: FCPERSNL | G37: Finance & Admin Coordinator | H37: 5716.37 | I37: 0 | J37: 14334.38 | K37: 0 | L37: 15607.17 | M37: 0 | N37: 1 | O37: 1660.21 | P37: 12 | Q37: =+O37*P37 -> 19922.52 | R37: 0 | S37: =SUM(Q37:R37) -> 19922.52 | T37: 1 | U37: 1866.98 | V37: 12 | W37: =T37*U37*V37 -> 22403.76 | X37: 0 | Y37: =SUM(W37:X37) -> 22403.76 | Z37: 1 | AA37: =+U37*10%+U37 -> 2053.678 | AB37: 8 | AC37: =Z37*AA37*AB37 -> 16429.424 | AD37: 0 | AE37: =SUM(AC37:AD37) -> 16429.424 | AF37: =+H37+J37+L37 -> 35657.92 | AG37: =+I37+K37+M37 -> 0 | AH37: =+AF37+AG37 -> 35657.92 | AI37: =+Q37+W37+AC37 -> 58755.704 | AJ37: =+R37+X37+AD37 -> 0 | AK37: =+AI37+AJ37 -> 58755.704 | AM37: =+AF37+AI37 -> 94413.624 | AN37: =+AG37+AJ37 -> 0 | AO37: =+AM37+AN37 -> 94413.624
A38: SUBFCARVA | B38: 89050 | C38: COL2 | D38: COL2 | E38: CARVAJAL | F38: FCPERSNL | G38: Accounting Analyst | H38: 2058.13 | I38: 0 | J38: 8631.23 | K38: 0 | L38: 5714.67 | M38: 0 | N38: 1 | O38: 758.33 | P38: 12 | Q38: =+O38*P38 -> 9099.96 | R38: 0 | S38: =SUM(Q38:R38) -> 9099.96 | T38: 1 | U38: =+O38*10%+O38 -> 834.163 | V38: 12 | W38: =T38*U38*V38 -> 10009.956 | X38: 0 | Y38: =SUM(W38:X38) -> 10009.956 | Z38: 1 | AA38: =+U38*10%+U38 -> 917.5793 | AB38: 8 | AC38: =Z38*AA38*AB38 -> 7340.6344 | AD38: 0 | AE38: =SUM(AC38:AD38) -> 7340.6344 | AF38: =+H38+J38+L38 -> 16404.03 | AG38: =+I38+K38+M38 -> 0 | AH38: =+AF38+AG38 -> 16404.03 | AI38: =+Q38+W38+AC38 -> 26450.55 | AJ38: =+R38+X38+AD38 -> 0 | AK38: =+AI38+AJ38 -> 26450.55 | AM38: =+AF38+AI38 -> 42854.58 | AN38: =+AG38+AJ38 -> 0 | AO38: =+AM38+AN38 -> 42854.58
A39: SUBFCARVA | B39: 89050 | C39: COL2 | D39: COL2 | E39: CARVAJAL | F39: FCPERSNL | G39: Accounting Analyst (Maternity Leave) | H39: 0 | I39: 0 | J39: 0 | K39: 0 | L39: 3288.75 | M39: 0 | N39: 1 | O39: 864.2 | P39: 2 | Q39: =+O39*P39 -> 1728.4 | R39: 0 | S39: =SUM(Q39:R39) -> 1728.4 | T39: 1 | U39: =+O39*10%+O39 -> 950.62 | V39: 0 | W39: =T39*U39*V39 -> 0 | X39: 0 | Y39: =SUM(W39:X39) -> 0 | Z39: 0 | AA39: 0 | AB39: 0 | AC39: =Z39*AA39*AB39 -> 0 | AD39: 0 | AE39: =SUM(AC39:AD39) -> 0 | AF39: =+H39+J39+L39 -> 3288.75 | AG39: =+I39+K39+M39 -> 0 | AH39: =+AF39+AG39 -> 3288.75 | AI39: =+Q39+W39+AC39 -> 1728.4 | AJ39: =+R39+X39+AD39 -> 0 | AK39: =+AI39+AJ39 -> 1728.4 | AM39: =+AF39+AI39 -> 5017.15 | AN39: =+AG39+AJ39 -> 0 | AO39: =+AM39+AN39 -> 5017.15
A40: SUBFCARVA | B40: 89050 | C40: COL2 | D40: COL2 | E40: CARVAJAL | F40: FCPERSNL | G40: Project Assistant | H40: 1828.58 | I40: 0 | J40: 5691.93 | K40: 0 | L40: 6142.27 | M40: 0 | N40: 1 | O40: 608.7 | P40: 12 | Q40: =+O40*P40 -> 7304.4 | R40: 0 | S40: =SUM(Q40:R40) -> 7304.4 | T40: 1 | U40: =+O40*10%+O40 -> 669.57 | V40: 12 | W40: =T40*U40*V40 -> 8034.84 | X40: 0 | Y40: =SUM(W40:X40) -> 8034.84 | Z40: 1 | AA40: =+U40*10%+U40 -> 736.527 | AB40: 8 | AC40: =Z40*AA40*AB40 -> 5892.216 | AD40: 0 | AE40: =SUM(AC40:AD40) -> 5892.216 | AF40: =+H40+J40+L40 -> 13662.78 | AG40: =+I40+K40+M40 -> 0 | AH40: =+AF40+AG40 -> 13662.78 | AI40: =+Q40+W40+AC40 -> 21231.456 | AJ40: =+R40+X40+AD40 -> 0 | AK40: =+AI40+AJ40 -> 21231.456 | AM40: =+AF40+AI40 -> 34894.236 | AN40: =+AG40+AJ40 -> 0 | AO40: =+AM40+AN40 -> 34894.236
A41: SUBFCARVA | B41: 89050 | C41: COL2 | D41: COL2 | E41: CARVAJAL | F41: FCPERSNL | G41: File Clerk Assistant | H41: 0 | I41: 0 | J41: 2930.08 | K41: 0 | L41: 4338.44 | M41: 0 | N41: 1 | O41: 421.89 | P41: 12 | Q41: =+O41*P41 -> 5062.68 | R41: 0 | S41: =SUM(Q41:R41) -> 5062.68 | T41: 1 | U41: =+O41*10%+O41 -> 464.079 | V41: 2 | W41: =T41*U41*V41 -> 928.158 | X41: 0 | Y41: =SUM(W41:X41) -> 928.158 | Z41: 1 | AA41: =+U41*10%+U41 -> 510.4869 | AB41: 8 | AC41: =Z41*AA41*AB41 -> 4083.8952 | AD41: 0 | AE41: =SUM(AC41:AD41) -> 4083.8952 | AF41: =+H41+J41+L41 -> 7268.52 | AG41: =+I41+K41+M41 -> 0 | AH41: =+AF41+AG41 -> 7268.52 | AI41: =+Q41+W41+AC41 -> 10074.733 | AJ41: =+R41+X41+AD41 -> 0 | AK41: =+AI41+AJ41 -> 10074.733 | AM41: =+AF41+AI41 -> 17343.253 | AN41: =+AG41+AJ41 -> 0 | AO41: =+AM41+AN41 -> 17343.253
A42: SUBFCARVA | B42: 89050 | C42: COL2 | D42: COL2 | E42: CARVAJAL | F42: FCPERSNL/ FCPERSNLEV | G42: Promotions Professional (Applies for Cali) | H42: 114.87 | I42: 125.51 | J42: 741.04 | K42: 814.45 | L42: 821.51 | M42: 889.09 | N42: 0.13 | O42: 79.52 | P42: 12 | Q42: =+O42*P42 -> 954.24 | R42: =+O42*P42 -> 954.24 | S42: =SUM(Q42:R42) -> 1908.48 | T42: 0.26 | U42: =+O42*10%+O42 -> 87.472 | V42: 12 | W42: =T42*U42*V42 -> 272.91264 | X42: 252.35 | Y42: =SUM(W42:X42) -> 525.26264 | Z42: 0.26 | AA42: =+U42*10%+U42 -> 96.2192 | AB42: 8 | AC42: =Z42*AA42*AB42 -> 200.13594 | AD42: 277.59 | AE42: =SUM(AC42:AD42) -> 477.72594 | AF42: =+H42+J42+L42 -> 1677.42 | AG42: =+I42+K42+M42 -> 1829.05 | AH42: =+AF42+AG42 -> 3506.47 | AI42: =+Q42+W42+AC42 -> 1427.2886 | AJ42: =+R42+X42+AD42 -> 1484.18 | AK42: =+AI42+AJ42 -> 2911.4686 | AM42: =+AF42+AI42 -> 3104.7086 | AN42: =+AG42+AJ42 -> 3313.23 | AO42: =+AM42+AN42 -> 6417.9386
A43: SUBFCARVA | B43: 89050 | C43: COL2 | D43: COL2 | E43: CARVAJAL | F43: FCPERSNL | G43: Legal Assistant | H43: 952.12 | I43: 0 | J43: 4385.81 | K43: 0 | L43: 5005.85 | M43: 0 | N43: 0.5 | O43: 290.73 | P43: 12 | Q43: =+O43*P43 -> 3488.76 | R43: 0 | S43: =SUM(Q43:R43) -> 3488.76 | T43: 0.5 | U43: =+O43*10%+O43 -> 319.803 | V43: 2 | W43: =T43*U43*V43 -> 319.803 | X43: 0 | Y43: =SUM(W43:X43) -> 319.803 | Z43: 0.5 | AA43: =+U43*10%+U43 -> 351.7833 | AB43: 8 | AC43: =Z43*AA43*AB43 -> 1407.1332 | AD43: 0 | AE43: =SUM(AC43:AD43) -> 1407.1332 | AF43: =+H43+J43+L43 -> 10343.78 | AG43: =+I43+K43+M43 -> 0 | AH43: =+AF43+AG43 -> 10343.78 | AI43: =+Q43+W43+AC43 -> 5215.6962 | AJ43: =+R43+X43+AD43 -> 0 | AK43: =+AI43+AJ43 -> 5215.6962 | AM43: =+AF43+AI43 -> 15559.476 | AN43: =+AG43+AJ43 -> 0 | AO43: =+AM43+AN43 -> 15559.476
A44: SUBFCARVA | B44: 89050 | C44: COL2 | D44: COL2 | E44: CARVAJAL | F44: FCPERSNL | G44: Procurement Assistant | H44: 0 | I44: 0 | J44: 0 | K44: 0 | L44: 0 | M44: 0 | N44: 1 | O44: 608.7 | P44: 10 | Q44: =+O44*P44 -> 6087 | R44: 0 | S44: =SUM(Q44:R44) -> 6087 | T44: 1 | U44: =+O44*10%+O44 -> 669.57 | V44: 12 | W44: =T44*U44*V44 -> 8034.84 | X44: 0 | Y44: =SUM(W44:X44) -> 8034.84 | Z44: 1 | AA44: =+U44*10%+U44 -> 736.527 | AB44: 6 | AC44: =Z44*AA44*AB44 -> 4419.162 | AD44: 0 | AE44: =SUM(AC44:AD44) -> 4419.162 | AF44: =+H44+J44+L44 -> 0 | AG44: =+I44+K44+M44 -> 0 | AH44: =+AF44+AG44 -> 0 | AI44: =+Q44+W44+AC44 -> 18541.002 | AJ44: =+R44+X44+AD44 -> 0 | AK44: =+AI44+AJ44 -> 18541.002 | AM44: =+AF44+AI44 -> 18541.002 | AN44: =+AG44+AJ44 -> 0 | AO44: =+AM44+AN44 -> 18541.002
G45: Comms Team
G46: Communications Senior Analyst | H46: 2308.18 | I46: 0 | J46: 9493.82 | K46: 0 | L46: 11058.81 | M46: 0 | N46: 1 | O46: 1070.45 | P46: 12 | Q46: =+O46*P46 -> 12845.4 | R46: 0 | S46: =SUM(Q46:R46) -> 12845.4 | T46: 1 | U46: =+O46*10%+O46 -> 1177.495 | V46: 12 | W46: =T46*U46*V46 -> 14129.94 | X46: 0 | Y46: =SUM(W46:X46) -> 14129.94 | Z46: 1 | AA46: =+U46*10%+U46 -> 1295.2445 | AB46: 6 | AC46: =Z46*AA46*AB46 -> 7771.467 | AD46: 0 | AE46: =SUM(AC46:AD46) -> 7771.467 | AF46: =+H46+J46+L46 -> 22860.81 | AG46: =+I46+K46+M46 -> 0 | AH46: =+AF46+AG46 -> 22860.81 | AI46: =+Q46+W46+AC46 -> 34746.807 | AJ46: =+R46+X46+AD46 -> 0 | AK46: =+AI46+AJ46 -> 34746.807 | AM46: =+AF46+AI46 -> 57607.617 | AN46: =+AG46+AJ46 -> 0 | AO46: =+AM46+AN46 -> 57607.617
G47: Regionals Team
A48: SUBFCARVA | B48: 89050 | C48: COL2 | D48: COL2 | E48: CARVAJAL | F48: FCPERSNL | G48: Technical Advisor - Cali | H48: 0 | I48: 0 | J48: 5375.44 | K48: 0 | L48: 12548.39 | M48: 0 | N48: 1 | O48: 1238.11 | P48: 12 | Q48: =+O48*P48 -> 14857.32 | R48: 0 | S48: =SUM(Q48:R48) -> 14857.32 | T48: 1 | U48: =+O48*10%+O48 -> 1361.921 | V48: 12 | W48: =T48*U48*V48 -> 16343.052 | X48: 0 | Y48: =SUM(W48:X48) -> 16343.052 | Z48: 1 | AA48: =+U48*10%+U48 -> 1498.1131 | AB48: 6 | AC48: =Z48*AA48*AB48 -> 8988.6786 | AD48: 0 | AE48: =SUM(AC48:AD48) -> 8988.6786 | AF48: =+H48+J48+L48 -> 17923.83 | AG48: =+I48+K48+M48 -> 0 | AH48: =+AF48+AG48 -> 17923.83 | AI48: =+Q48+W48+AC48 -> 40189.051 | AJ48: =+R48+X48+AD48 -> 0 | AK48: =+AI48+AJ48 -> 40189.051 | AM48: =+AF48+AI48 -> 58112.881 | AN48: =+AG48+AJ48 -> 0 | AO48: =+AM48+AN48 -> 58112.881
A49: SUBFCARVA | B49: 89050 | C49: COL2 | D49: COL2 | E49: CARVAJAL | F49: FCPERSNL | G49: Junior Pedagogical Advisor (Intégrate) - Cali | H49: 0 | I49: 0 | J49: 1118.2 | K49: 0 | L49: 1888.64 | M49: 0 | N49: 0 | O49: 0 | P49: 0 | Q49: =+O49*P49 -> 0 | R49: 0 | S49: =SUM(Q49:R49) -> 0 | T49: 0 | U49: =+O49*10%+O49 -> 0 | V49: 0 | W49: =T49*U49*V49 -> 0 | X49: 0 | Y49: =SUM(W49:X49) -> 0 | Z49: 0 | AA49: =+U49*10%+U49 -> 0 | AB49: 6 | AC49: =Z49*AA49*AB49 -> 0 | AD49: 0 | AE49: =SUM(AC49:AD49) -> 0 | AF49: =+H49+J49+L49 -> 3006.84 | AG49: =+I49+K49+M49 -> 0 | AH49: =+AF49+AG49 -> 3006.84 | AI49: =+Q49+W49+AC49 -> 0 | AJ49: =+R49+X49+AD49 -> 0 | AK49: =+AI49+AJ49 -> 0 | AM49: =+AF49+AI49 -> 3006.84 | AN49: =+AG49+AJ49 -> 0 | AO49: =+AM49+AN49 -> 3006.84
A50: SUBFCARVA | B50: 89050 | C50: COL2 | D50: COL2 | E50: CARVAJAL | F50: FCPERSNL | G50: Technical Advisor - Cúcuta | H50: 0 | I50: 0 | J50: 0 | K50: 0 | L50: 0 | M50: 0 | N50: 1 | O50: 1284.54 | P50: 12 | Q50: =+O50*P50 -> 15414.48 | R50: 0 | S50: =SUM(Q50:R50) -> 15414.48 | T50: 1 | U50: =+O50*10%+O50 -> 1412.994 | V50: 12 | W50: =T50*U50*V50 -> 16955.928 | X50: 0 | Y50: =SUM(W50:X50) -> 16955.928 | Z50: 1 | AA50: =+U50*10%+U50 -> 1554.2934 | AB50: 6 | AC50: =Z50*AA50*AB50 -> 9325.7604 | AD50: 0 | AE50: =SUM(AC50:AD50) -> 9325.7604 | AF50: =+H50+J50+L50 -> 0 | AG50: =+I50+K50+M50 -> 0 | AH50: =+AF50+AG50 -> 0 | AI50: =+Q50+W50+AC50 -> 41696.168 | AJ50: =+R50+X50+AD50 -> 0 | AK50: =+AI50+AJ50 -> 41696.168 | AM50: =+AF50+AI50 -> 41696.168 | AN50: =+AG50+AJ50 -> 0 | AO50: =+AM50+AN50 -> 41696.168
A51: SUBFCARVA | B51: 89050 | C51: COL2 | D51: COL2 | E51: CARVAJAL | F51: FCPERSNL | G51: Technical Advisor - Bucaramanga | H51: 0 | I51: 0 | J51: 0 | K51: 0 | L51: 0 | M51: 0 | N51: 1 | O51: 1284.54 | P51: 12 | Q51: =+O51*P51 -> 15414.48 | R51: 0 | S51: =SUM(Q51:R51) -> 15414.48 | T51: 1 | U51: =+O51*10%+O51 -> 1412.994 | V51: 12 | W51: =T51*U51*V51 -> 16955.928 | X51: 0 | Y51: =SUM(W51:X51) -> 16955.928 | Z51: 1 | AA51: =+U51*10%+U51 -> 1554.2934 | AB51: 6 | AC51: =Z51*AA51*AB51 -> 9325.7604 | AD51: 0 | AE51: =SUM(AC51:AD51) -> 9325.7604 | AF51: =+H51+J51+L51 -> 0 | AG51: =+I51+K51+M51 -> 0 | AH51: =+AF51+AG51 -> 0 | AI51: =+Q51+W51+AC51 -> 41696.168 | AJ51: =+R51+X51+AD51 -> 0 | AK51: =+AI51+AJ51 -> 41696.168 | AM51: =+AF51+AI51 -> 41696.168 | AN51: =+AG51+AJ51 -> 0 | AO51: =+AM51+AN51 -> 41696.168
A52: SUBFCARVA | B52: 89050 | C52: COL2 | D52: COL2 | E52: CARVAJAL | F52: FCPERSNL | G52: Technical Advisor - Cartagena | H52: 0 | I52: 0 | J52: 0 | K52: 0 | L52: 0 | M52: 0 | N52: 1 | O52: 1284.54 | P52: 11 | Q52: =+O52*P52 -> 14129.94 | R52: 0 | S52: =SUM(Q52:R52) -> 14129.94 | T52: 1 | U52: =+O52*10%+O52 -> 1412.994 | V52: 12 | W52: =T52*U52*V52 -> 16955.928 | X52: 0 | Y52: =SUM(W52:X52) -> 16955.928 | Z52: 1 | AA52: =+U52*10%+U52 -> 1554.2934 | AB52: 6 | AC52: =Z52*AA52*AB52 -> 9325.7604 | AD52: 0 | AE52: =SUM(AC52:AD52) -> 9325.7604 | AF52: =+H52+J52+L52 -> 0 | AG52: =+I52+K52+M52 -> 0 | AH52: =+AF52+AG52 -> 0 | AI52: =+Q52+W52+AC52 -> 40411.628 | AJ52: =+R52+X52+AD52 -> 0 | AK52: =+AI52+AJ52 -> 40411.628 | AM52: =+AF52+AI52 -> 40411.628 | AN52: =+AG52+AJ52 -> 0 | AO52: =+AM52+AN52 -> 40411.628
A53: SUBFCARVA | B53: 89050 | C53: COL2 | D53: COL2 | E53: CARVAJAL | F53: FCPERSNL | G53: Technical Advisor - Santa Marta/Riohacha | H53: 0 | I53: 0 | J53: 0 | K53: 0 | L53: 0 | M53: 0 | N53: 1 | O53: 1530.86 | P53: 12 | Q53: =+O53*P53 -> 18370.32 | R53: 0 | S53: =SUM(Q53:R53) -> 18370.32 | T53: 1 | U53: =+O53*10%+O53 -> 1683.946 | V53: 12 | W53: =T53*U53*V53 -> 20207.352 | X53: 0 | Y53: =SUM(W53:X53) -> 20207.352 | Z53: 1 | AA53: =+U53*10%+U53 -> 1852.3406 | AB53: 6 | AC53: =Z53*AA53*AB53 -> 11114.044 | AD53: 0 | AE53: =SUM(AC53:AD53) -> 11114.044 | AF53: =+H53+J53+L53 -> 0 | AG53: =+I53+K53+M53 -> 0 | AH53: =+AF53+AG53 -> 0 | AI53: =+Q53+W53+AC53 -> 49691.716 | AJ53: =+R53+X53+AD53 -> 0 | AK53: =+AI53+AJ53 -> 49691.716 | AM53: =+AF53+AI53 -> 49691.716 | AN53: =+AG53+AJ53 -> 0 | AO53: =+AM53+AN53 -> 49691.716
G54: Technical Team - Subactivity: PI (4PA)
G55: Pedagogical Advisors
A56: SUBFCARVA | B56: 89050 | C56: COL2 | D56: COL2 | E56: CARVAJAL | F56: FCPERSNL | G56: PI - Pedagogical Advisors | H56: 0 | I56: 0 | J56: 21383.62 | K56: 0 | L56: 32282.63 | M56: 0 | N56: 1 | O56: 2981.97 | P56: 11 | Q56: =+O56*P56 -> 32801.67 | R56: 0 | S56: =SUM(Q56:R56) -> 32801.67 | T56: 1 | U56: 4373.56 | V56: 12 | W56: 30614.89 | X56: 0 | Y56: =+W56+X56 -> 30614.89 | Z56: 1 | AA56: 2405.46 | AB56: 6 | AC56: =Z56*AA56*AB56 -> 14432.76 | AD56: 0 | AE56: =SUM(AC56:AD56) -> 14432.76 | AF56: =+H56+J56+L56 -> 53666.25 | AG56: =+I56+K56+M56 -> 0 | AH56: =+AF56+AG56 -> 53666.25 | AI56: =+Q56+W56+AC56 -> 77849.32 | AJ56: =+R56+X56+AD56 -> 0 | AK56: =+AI56+AJ56 -> 77849.32 | AM56: =+AF56+AI56 -> 131515.57 | AN56: =+AG56+AJ56 -> 0 | AO56: =+AM56+AN56 -> 131515.57
G57: Technical Team - Subactivity: ATL (2AG)
G58: Pedagogical Advisors
A59: SUBFCARVA | B59: 89050 | C59: COL2 | D59: COL2 | E59: CARVAJAL | F59: FCPERSNL | G59: ATL - Pedagogical Advisors | H59: 4378.1 | I59: 0 | J59: 13344.83 | K59: 0 | L59: 17154.09 | M59: 0 | N59: 1 | O59: 1987.98 | P59: 10 | Q59: 18885.81 | R59: 0 | S59: =+Q59+R59 -> 18885.81 | T59: 1 | U59: 2186.78 | V59: 12 | W59: =T59*U59*V59 -> 26241.36 | X59: 0 | Y59: =SUM(W59:X59) -> 26241.36 | Z59: 1 | AA59: 3608.19 | AB59: 6 | AC59: =Z59*AA59*AB59 -> 21649.14 | AD59: 0 | AE59: =SUM(AC59:AD59) -> 21649.14 | AF59: =+H59+J59+L59 -> 34877.02 | AG59: =+I59+K59+M59 -> 0 | AH59: =+AF59+AG59 -> 34877.02 | AI59: =+Q59+W59+AC59 -> 66776.31 | AJ59: =+R59+X59+AD59 -> 0 | AK59: =+AI59+AJ59 -> 66776.31 | AM59: =+AF59+AI59 -> 101653.33 | AN59: =+AG59+AJ59 -> 0 | AO59: =+AM59+AN59 -> 101653.33
G60: Technical Team - Subactivity: AG (15AG)
G61: Pedagogical Advisors
A62: SUBFCARVA | B62: 89050 | C62: COL2 | D62: COL2 | E62: CARVAJAL | F62: FCPERSNL/ FCPERSNLEV | G62: AG - Pedagogical Advisors | H62: 410.25 | I62: 0 | J62: 41217.54 | K62: 0 | L62: 107343.71 | M62: 4429.47 | N62: 1 | O62: 993.99 | P62: 12 | Q62: =+O62*P62 -> 11927.88 | R62: 0 | S62: =+Q62+R62 -> 11927.88 | T62: 0 | U62: 0 | V62: 0 | W62: =T62*U62*V62 -> 0 | X62: 0 | Y62: =SUM(W62:X62) -> 0 | Z62: 0 | AA62: =+U62*10%+U62 -> 0 | AB62: 0 | AC62: =Z62*AA62*AB62 -> 0 | AD62: 0 | AE62: =SUM(AC62:AD62) -> 0 | AF62: =+H62+J62+L62 -> 148971.5 | AG62: =+I62+K62+M62 -> 4429.47 | AH62: =+AF62+AG62 -> 153400.97 | AI62: =+Q62+W62+AC62 -> 11927.88 | AJ62: =+R63+X62+AD62 -> 9939.9 | AK62: =+AI62+AJ62 -> 21867.78 | AM62: =+AF62+AI62 -> 160899.38 | AN62: =+AG62+AJ62 -> 14369.37 | AO62: =+AM62+AN62 -> 175268.75
A63: SUBFCARVA | B63: 89050 | C63: COL2 | D63: COL2 | E63: CARVAJAL | F63: FCPERSNL | G63: AG - Pedagogical Advisors | H63: 0 | I63: 0 | J63: 0 | K63: 0 | M63: 0 | N63: 1 | O63: 3975.96 | P63: 10 | Q63: =+O63*P63 -> 39759.6 | R63: 9939.9 | S63: =+Q63+R63 -> 49699.5 | T63: 1 | U63: 5466.95 | V63: 10 | W63: =T63*U63*V63 -> 54669.5 | X63: 0 | Y63: =SUM(W63:X63) -> 54669.5 | Z63: 0 | AA63: 0 | AB63: 0 | AC63: =Z63*AA63*AB63 -> 0 | AD63: 0 | AE63: =SUM(AC63:AD63) -> 0 | AF63: =+H63+J63+L63 -> 0 | AG63: =+I63+K63+M63 -> 0 | AH63: =+AF63+AG63 -> 0 | AI63: =+Q63+W63+AC63 -> 94429.1 | AJ63: =+R64+X63+AD63 -> 0 | AK63: =+AI63+AJ63 -> 94429.1 | AM63: =+AF63+AI63 -> 94429.1 | AN63: =+AG63+AJ63 -> 0 | AO63: =+AM63+AN63 -> 94429.1
A64: SUBFCARVA | B64: 89050 | C64: COL2 | D64: COL2 | E64: CARVAJAL | F64: FCPERSNL | G64: AG - Pedagogical Advisors | H64: 0 | I64: 0 | J64: 0 | K64: 0 | M64: 0 | N64: 1 | O64: 6957.93 | P64: 9 | Q64: =+O64*P64 -> 62621.37 | R64: 0 | S64: =SUM(Q64:R64) -> 62621.37 | T64: 0 | U64: 0 | V64: 0 | W64: =T64*U64*V64 -> 0 | X64: 0 | Y64: =SUM(W64:X64) -> 0 | Z64: 0 | AA64: 0 | AB64: 0 | AC64: =Z64*AA64*AB64 -> 0 | AD64: 0 | AE64: =SUM(AC64:AD64) -> 0 | AF64: =+H64+J64+L64 -> 0 | AG64: =+I64+K64+M64 -> 0 | AH64: =+AF64+AG64 -> 0 | AI64: =+Q64+W64+AC64 -> 62621.37 | AJ64: =+R65+X64+AD64 -> 0 | AK64: =+AI64+AJ64 -> 62621.37 | AM64: =+AF64+AI64 -> 62621.37 | AN64: =+AG64+AJ64 -> 0 | AO64: =+AM64+AN64 -> 62621.37
G65: Technical Team - Subactivity: MEF (2 Sr. - 8PA)
G66: Senior Pedagogical Advisors for Tutors - Flexible Learning Models
A67: SUBFCARVA | B67: 89050 | C67: COL2 | D67: COL2 | E67: CARVAJAL | F67: FCPERSNL | G67: MEF - Senior Pedagogical Advisors | H67: 9003.34 | I67: 0 | J67: =11300.69*2 -> 22601.38 | K67: 0 | L67: =12485.73*2 -> 24971.46 | M67: 0 | N67: 1 | O67: =1289.53*2 -> 2579.06 | P67: 10 | Q67: =+O67*P67 -> 25790.6 | R67: 0 | S67: =SUM(Q67:R67) -> 25790.6 | T67: 1 | U67: =+O67*10%+O67 -> 2836.966 | V67: 10 | W67: =T67*U67*V67 -> 28369.66 | X67: 0 | Y67: =SUM(W67:X67) -> 28369.66 | Z67: 1 | AA67: =+U67*10%+U67 -> 3120.6626 | AB67: 6 | AC67: =Z67*AA67*AB67 -> 18723.976 | AD67: 0 | AE67: =SUM(AC67:AD67) -> 18723.976 | AF67: =+H67+J67+L67 -> 56576.18 | AG67: =+I67+K67+M67 -> 0 | AH67: =+AF67+AG67 -> 56576.18 | AI67: =+Q67+W67+AC67 -> 72884.236 | AJ67: =+R67+X67+AD67 -> 0 | AK67: =+AI67+AJ67 -> 72884.236 | AM67: =+AF67+AI67 -> 129460.42 | AN67: =+AG67+AJ67 -> 0 | AO67: =+AM67+AN67 -> 129460.42
G68: Pedagogical Advisors - Flexible Learning Models
A69: SUBFCARVA | B69: 89050 | C69: COL2 | D69: COL2 | E69: CARVAJAL | F69: FCPERSNL/ FCPERSNLEV | G69: MEF - Pedagogical Advisors | H69: 0 | I69: 0 | J69: 52454.65 | K69: 0 | L69: 55504.2 | M69: 11402.88 | N69: 1 | O69: 993.99 | P69: 12 | Q69: =+O69*P69 -> 11927.88 | R69: 0 | S69: =SUM(Q69:R69) -> 11927.88 | T69: 1 | U69: =+O69*10%+O69 -> 1093.389 | V69: 12 | W69: =T69*U69*V69 -> 13120.668 | X69: 0 | Y69: =SUM(W69:X69) -> 13120.668 | Z69: 1 | AA69: =+(U69*10%+U69)*3 -> 3608.1837 | AB69: 6 | AC69: =Z69*AA69*AB69 -> 21649.102 | AD69: 0 | AE69: =SUM(AC69:AD69) -> 21649.102 | AF69: =+H69+J69+L69 -> 107958.85 | AG69: =+I69+K69+M69 -> 11402.88 | AH69: =+AF69+AG69 -> 119361.73 | AI69: =+Q69+W69+AC69 -> 46697.65 | AJ69: =+R69+X69+AD69 -> 0 | AK69: =+AI69+AJ69 -> 46697.65 | AM69: =+AF69+AI69 -> 154656.5 | AN69: =+AG69+AJ69 -> 11402.88 | AO69: =+AM69+AN69 -> 166059.38
A70: SUBFCARVA | B70: 89050 | C70: COL2 | D70: COL2 | E70: CARVAJAL | F70: FCPERSNL | G70: MEF - Pedagogical Advisors | H70: 0 | I70: 0 | K70: 0 | N70: 1 | O70: 993.99 | P70: 11 | Q70: =+O70*P70 -> 10933.89 | R70: 0 | S70: =SUM(Q70:R70) -> 10933.89 | T70: 0 | U70: 1093.39 | V70: 0 | W70: =T70*U70*V70 -> 0 | X70: 0 | Y70: =SUM(W70:X70) -> 0 | Z70: 0 | AA70: 0 | AB70: 0 | AC70: =Z70*AA70*AB70 -> 0 | AD70: 0 | AE70: =SUM(AC70:AD70) -> 0 | AF70: =+H70+J70+L70 -> 0 | AG70: =+I70+K70+M70 -> 0 | AH70: =+AF70+AG70 -> 0 | AI70: =+Q70+W70+AC70 -> 10933.89 | AJ70: =+R70+X70+AD70 -> 0 | AK70: =+AI70+AJ70 -> 10933.89 | AM70: =+AF70+AI70 -> 10933.89 | AN70: =+AG70+AJ70 -> 0 | AO70: =+AM70+AN70 -> 10933.89
A71: SUBFCARVA | B71: 89050 | C71: COL2 | D71: COL2 | E71: CARVAJAL | F71: FCPERSNL | G71: MEF - Pedagogical Advisors | H71: 0 | I71: 0 | K71: 0 | N71: 1 | O71: 1987.98 | P71: 10 | Q71: =+O71*P71 -> 19879.8 | R71: 0 | S71: =SUM(Q71:R71) -> 19879.8 | T71: 1 | U71: 3280.17 | V71: 10 | W71: =T71*U71*V71 -> 32801.7 | X71: 0 | Y71: =SUM(W71:X71) -> 32801.7 | Z71: 0 | AA71: 0 | AB71: 0 | AC71: =Z71*AA71*AB71 -> 0 | AD71: 0 | AE71: =SUM(AC71:AD71) -> 0 | AF71: =+H71+J71+L71 -> 0 | AG71: =+I71+K71+M71 -> 0 | AH71: =+AF71+AG71 -> 0 | AI71: =+Q71+W71+AC71 -> 52681.5 | AJ71: =+R71+X71+AD71 -> 0 | AK71: =+AI71+AJ71 -> 52681.5 | AM71: =+AF71+AI71 -> 52681.5 | AN71: =+AG71+AJ71 -> 0 | AO71: =+AM71+AN71 -> 52681.5
G72: Teachers - Flexible Learning Models
A73: SUBFCARVA | B73: 89050 | C73: COL2 | D73: COL2 | E73: CARVAJAL | F73: FCPERSNL | G73: MEF - Teachers | H73: 0 | I73: 0 | J73: 42600.11 | K73: 0 | L73: 0 | M73: 0 | N73: 0 | O73: 0 | P73: 0 | Q73: =+O73*P73 -> 0 | R73: 0 | S73: =SUM(Q73:R73) -> 0 | T73: 0 | U73: 0 | V73: 0 | W73: =T73*U73*V73 -> 0 | X73: 0 | Y73: =SUM(W73:X73) -> 0 | Z73: 0 | AA73: 0 | AB73: 0 | AC73: =Z73*AA73*AB73 -> 0 | AD73: 0 | AE73: =SUM(AC73:AD73) -> 0 | AF73: =+H73+J73+L73 -> 42600.11 | AG73: =+I73+K73+M73 -> 0 | AH73: =+AF73+AG73 -> 42600.11 | AI73: =+Q73+W73+AC73 -> 0 | AJ73: =+R73+X73+AD73 -> 0 | AK73: =+AI73+AJ73 -> 0 | AM73: =+AF73+AI73 -> 42600.11 | AN73: =+AG73+AJ73 -> 0 | AO73: =+AM73+AN73 -> 42600.11
A74: SUBFCARVA | B74: 89050 | C74: COL2 | D74: COL2 | E74: CARVAJAL | F74: FCPERSNLEV | G74: Family Specialist | H74: 0 | I74: 0 | J74: 0 | K74: 2410.64 | L74: 0 | M74: 3080.4 | N74: 0 | O74: 0 | P74: 0 | Q74: =+O74*P74 -> 0 | R74: 0 | S74: =SUM(Q74:R74) -> 0 | T74: 0 | U74: 0 | V74: 0 | W74: =T74*U74*V74 -> 0 | X74: 0 | Y74: =SUM(W74:X74) -> 0 | Z74: 0 | AA74: 0 | AB74: 0 | AC74: =Z74*AA74*AB74 -> 0 | AD74: 0 | AE74: =SUM(AC74:AD74) -> 0 | AF74: =+H74+J74+L74 -> 0 | AG74: =+I74+K74+M74 -> 5491.04 | AH74: =+AF74+AG74 -> 5491.04 | AI74: =+Q74+W74+AC74 -> 0 | AJ74: =+R74+X74+AD74 -> 0 | AK74: =+AI74+AJ74 -> 0 | AM74: =+AF74+AI74 -> 0 | AN74: =+AG74+AJ74 -> 5491.04 | AO74: =+AM74+AN74 -> 5491.04
G75: Support Virtual School Fundación Carvajal | H75: 0 | I75: 0 | J75: 0 | K75: 0 | L75: 0 | M75: 0 | N75: 0 | O75: 0 | P75: 0 | Q75: =+O75*P75 -> 0 | R75: 0 | S75: 0 | T75: 0 | U75: 0 | V75: 0 | W75: 0 | X75: 0 | Y75: 0 | Z75: 0 | AA75: 0 | AB75: 0 | AC75: =Z75*AA75*AB75 -> 0 | AD75: 0 | AE75: =SUM(AC75:AD75) -> 0 | AF75: =+H75+J75+L75 -> 0 | AG75: =+I75+K75+M75 -> 0 | AH75: =+AF75+AG75 -> 0 | AI75: =+Q75+W75+AC75 -> 0 | AJ75: =+R75+X75+AD75 -> 0 | AK75: =+AI75+AJ75 -> 0 | AM75: =+AF75+AI75 -> 0 | AN75: =+AG75+AJ75 -> 0 | AO75: =+AM75+AN75 -> 0
G76: Subtotal Field Personnel | H76: =SUM(H30:H75) -> 40245.1 | I76: =SUM(I30:I75) -> 125.51 | J76: =SUM(J30:J75) -> 303394.34 | K76: =SUM(K30:K75) -> 3225.09 | L76: =SUM(L30:L75) -> 389127.54 | M76: =SUM(M30:M75) -> 19801.84 | O76: =SUM(O30:O74) -> 44841.69 | Q76: =SUM(Q30:Q74) -> 472343.4 | R76: =SUM(R30:R74) -> 10894.14 | S76: =SUM(S30:S74) -> 483237.54 | U76: =SUM(U30:U74) -> 43899.678 | W76: =SUM(W30:W74) -> 448296.64 | X76: =SUM(X30:X74) -> 252.35 | Y76: =SUM(Y30:Y74) -> 448548.99 | AA76: =SUM(AA30:AA74) -> 37622.135 | AC76: =SUM(AC30:AC74) -> 236706.7 | AD76: =SUM(AD30:AD74) -> 277.59 | AE76: =SUM(AE30:AE74) -> 236984.29 | AF76: =SUM(AF30:AF74) -> 732766.98 | AG76: =SUM(AG30:AG74) -> 23152.44 | AH76: =SUM(AH30:AH74) -> 755919.42 | AI76: =SUM(AI30:AI74) -> 1157346.7 | AJ76: =SUM(AJ30:AJ74) -> 11424.08 | AK76: =SUM(AK30:AK74) -> 1168770.8 | AM76: =SUM(AM30:AM74) -> 1890113.7 | AN76: =SUM(AN30:AN74) -> 34576.52 | AO76: =SUM(AO30:AO74) -> 1924690.2
G77: 1. Personnel Total | H77: =+H27+H76 -> 75199.76 | I77: =+I27+I76 -> 1213.21 | J77: =+J27+J76 -> 471134.53 | K77: =+K27+K76 -> 3225.09 | L77: =+L27+L76 -> 560919.49 | M77: =+M27+M76 -> 27999.04 | O77: =+O27+O76 -> 63550.96 | Q77: =+Q27+Q76 -> 673739.68 | R77: =+R27+R76 -> 18295.485 | S77: =+S27+S76 -> 692035.17 | U77: =+U27+U76 -> 64479.875 | W77: =+W27+W76 -> 695259 | X77: =+X27+X76 -> 8393.8295 | Y77: =+Y27+Y76 -> 703652.83 | AA77: =+AA27+AA76 -> 60260.351 | AC77: =+AC27+AC76 -> 382724.42 | AD77: =+AD27+AD76 -> 6248.0083 | AE77: =+AE27+AE76 -> 388972.42 | AF77: =+AF27+AF76 -> 1107253.8 | AG77: =+AG27+AG76 -> 32437.34 | AH77: =+AH27+AH76 -> 1139691.1 | AI77: =+AI27+AI76 -> 1751723.1 | AJ77: =+AJ27+AJ76 -> 32937.323 | AK77: =+AK27+AK76 -> 1784660.4 | AM77: =+AM27+AM76 -> 2858976.9 | AN77: =+AN27+AN76 -> 65374.663 | AO77: =+AO27+AO76 -> 2924351.5
AJ78: =+R78+X78+AD78 -> 0
G79: 2. Fringe Benefits
A80: SUBFCARVA | B80: 89050 | C80: COL2 | D80: COL2 | E80: CARVAJAL | F80: FCFRINGE/ FCFRINGEL | G80: Fringe Benefits – HQ + Project Office + Field Staff | H80: 27001.52 | I80: 427.7 | J80: 194200.4 | K80: 954.61 | L80: 271760.78 | M80: 6957.66 | N80: 1 | O80: 340000 | P80: 1 | Q80: =+O80*P80 -> 340000 | R80: 9200 | S80: =SUM(Q80:R80) -> 349200 | T80: 1 | U80: 351000 | V80: 1 | W80: =T80*U80*V80 -> 351000 | X80: 4600 | Y80: =SUM(W80:X80) -> 355600 | Z80: 1 | AA80: 200000 | AB80: 1 | AC80: =Z80*AA80*AB80 -> 200000 | AD80: 2200 | AE80: =SUM(AC80:AD80) -> 202200 | AF80: =+H80+J80+L80 -> 492962.7 | AG80: =+I80+K80+M80 -> 8339.97 | AH80: =+AF80+AG80 -> 501302.67 | AI80: =+Q80+W80+AC80 -> 891000 | AJ80: =+R80+X80+AD80 -> 16000 | AK80: =+AI80+AJ80 -> 907000 | AM80: =+AF80+AI80 -> 1383962.7 | AN80: =+AG80+AJ80 -> 24339.97 | AO80: =+AM80+AN80 -> 1408302.7
G81: 2. Fringe Benefits Total | H81: =+H80 -> 27001.52 | I81: =+I80 -> 427.7 | J81: =+J80 -> 194200.4 | K81: =+K80 -> 954.61 | L81: =+L80 -> 271760.78 | M81: =+M80 -> 6957.66 | O81: =+O80 -> 340000 | Q81: =+Q80 -> 340000 | R81: =+R80 -> 9200 | S81: =+S80 -> 349200 | U81: =+U80 -> 351000 | W81: =+W80 -> 351000 | X81: =+X80 -> 4600 | Y81: =+Y80 -> 355600 | AA81: =+AA80 -> 200000 | AC81: =+AC80 -> 200000 | AD81: =+AD80 -> 2200 | AE81: =+AE80 -> 202200 | AF81: =+AF80 -> 492962.7 | AG81: =+AG80 -> 8339.97 | AH81: =+AH80 -> 501302.67 | AI81: =+AI80 -> 891000 | AJ81: =+AJ80 -> 16000 | AK81: =+AK80 -> 907000 | AM81: =+AM80 -> 1383962.7 | AN81: =+AN80 -> 24339.97 | AO81: =+AO80 -> 1408302.7
G82: 3. Travel
G83: Fundación Carvajal Management Team Travel Expenses
A84: SUBFCARVA | B84: 89050 | C84: COL2 | D84: COL2 | E84: CARVAJAL | F84: FCHQTRVL | G84: Local Transportation (Airfare, Taxis, & Rental Car/Driver) | H84: 1699.88 | I84: 0 | J84: 6638.9 | K84: 0 | L84: 11226.44 | M84: 2672.7 | N84: 1 | O84: 5500 | P84: 1 | Q84: =+O84*P84 -> 5500 | R84: 0 | S84: =SUM(Q84:R84) -> 5500 | T84: 1 | U84: =+O84*8%+O84 -> 5940 | V84: 1 | W84: =T84*U84*V84 -> 5940 | X84: 0 | Y84: =SUM(W84:X84) -> 5940 | Z84: 1 | AA84: =(+U84*8%+U84)/2 -> 3207.6 | AB84: 1 | AC84: =Z84*AA84*AB84 -> 3207.6 | AD84: 0 | AE84: =SUM(AC84:AD84) -> 3207.6 | AF84: =+H84+J84+L84 -> 19565.22 | AG84: =+I84+K84+M84 -> 2672.7 | AH84: =+AF84+AG84 -> 22237.92 | AI84: =+Q84+W84+AC84 -> 14647.6 | AJ84: =+R84+X84+AD84 -> 0 | AK84: =+AI84+AJ84 -> 14647.6 | AM84: =+AF84+AI84 -> 34212.82 | AN84: =+AG84+AJ84 -> 2672.7 | AO84: =+AM84+AN84 -> 36885.52
A85: SUBFCARVA | B85: 89050 | C85: COL2 | D85: COL2 | E85: CARVAJAL | F85: FCHQTRVL | G85: Meals & Incidentals | H85: 339.39 | I85: 0 | J85: 920.27 | K85: 0 | L85: 0 | M85: 0 | N85: 1 | O85: 2000 | P85: 1 | Q85: =+O85*P85 -> 2000 | R85: 0 | S85: =SUM(Q85:R85) -> 2000 | T85: 1 | U85: =+O85*8%+O85 -> 2160 | V85: 1 | W85: =T85*U85*V85 -> 2160 | X85: 0 | Y85: =SUM(W85:X85) -> 2160 | Z85: 1 | AA85: =(+U85*8%+U85)/2 -> 1166.4 | AB85: 1 | AC85: =Z85*AA85*AB85 -> 1166.4 | AD85: 0 | AE85: =SUM(AC85:AD85) -> 1166.4 | AF85: =+H85+J85+L85 -> 1259.66 | AG85: =+I85+K85+M85 -> 0 | AH85: =+AF85+AG85 -> 1259.66 | AI85: =+Q85+W85+AC85 -> 5326.4 | AJ85: =+R85+X85+AD85 -> 0 | AK85: =+AI85+AJ85 -> 5326.4 | AM85: =+AF85+AI85 -> 6586.06 | AN85: =+AG85+AJ85 -> 0 | AO85: =+AM85+AN85 -> 6586.06
A86: SUBFCARVA | B86: 89050 | C86: COL2 | D86: COL2 | E86: CARVAJAL | F86: FCHQTRVL | G86: Lodging | H86: =370.97-49.79 -> 321.18 | I86: 0 | J86: 2383.39 | K86: 0 | L86: 0 | M86: 0 | N86: 1 | O86: 2500 | P86: 1 | Q86: =+O86*P86 -> 2500 | R86: 0 | S86: =SUM(Q86:R86) -> 2500 | T86: 1 | U86: =+O86*8%+O86 -> 2700 | V86: 1 | W86: =T86*U86*V86 -> 2700 | X86: 0 | Y86: =SUM(W86:X86) -> 2700 | Z86: 1 | AA86: =(+U86*8%+U86)/2 -> 1458 | AB86: 1 | AC86: =Z86*AA86*AB86 -> 1458 | AD86: 0 | AE86: =SUM(AC86:AD86) -> 1458 | AF86: =+H86+J86+L86 -> 2704.57 | AG86: =+I86+K86+M86 -> 0 | AH86: =+AF86+AG86 -> 2704.57 | AI86: =+Q86+W86+AC86 -> 6658 | AJ86: =+R86+X86+AD86 -> 0 | AK86: =+AI86+AJ86 -> 6658 | AM86: =+AF86+AI86 -> 9362.57 | AN86: =+AG86+AJ86 -> 0 | AO86: =+AM86+AN86 -> 9362.57
A87: SUBFCARVA | B87: 89050 | C87: COL2 | D87: COL2 | E87: CARVAJAL | F87: FCHQTRVL | G87: Other Travel Related Expenses | H87: 41.2 | I87: 0 | J87: 9.87 | K87: 0 | L87: 0 | M87: 0 | N87: 0 | O87: 500 | P87: 1 | Q87: =+O87*P87 -> 500 | R87: 0 | S87: =SUM(Q87:R87) -> 500 | T87: 1 | U87: =+O87*8%+O87 -> 540 | V87: 1 | W87: =T87*U87*V87 -> 540 | X87: 0 | Y87: =SUM(W87:X87) -> 540 | Z87: 1 | AA87: =(+U87*8%+U87)/2 -> 291.6 | AB87: 1 | AC87: =Z87*AA87*AB87 -> 291.6 | AD87: 0 | AE87: =SUM(AC87:AD87) -> 291.6 | AF87: =+H87+J87+L87 -> 51.07 | AG87: =+I87+K87+M87 -> 0 | AH87: =+AF87+AG87 -> 51.07 | AI87: =+Q87+W87+AC87 -> 1331.6 | AJ87: =+R87+X87+AD87 -> 0 | AK87: =+AI87+AJ87 -> 1331.6 | AM87: =+AF87+AI87 -> 1382.67 | AN87: =+AG87+AJ87 -> 0 | AO87: =+AM87+AN87 -> 1382.67
G88: Subtotal Fundación Carvajal Management Team | H88: =SUM(H84:H87) -> 2401.65 | I88: =SUM(I84:I87) -> 0 | J88: =SUM(J84:J87) -> 9952.43 | K88: =SUM(K84:K87) -> 0 | L88: =SUM(L84:L87) -> 11226.44 | M88: =SUM(M84:M87) -> 2672.7 | O88: =SUM(O84:O87) -> 10500 | Q88: =SUM(Q84:Q87) -> 10500 | R88: =SUM(R84:R87) -> 0 | S88: =SUM(S84:S87) -> 10500 | U88: =SUM(U84:U87) -> 11340 | W88: =SUM(W84:W87) -> 11340 | X88: =SUM(X84:X87) -> 0 | Y88: =SUM(Y84:Y87) -> 11340 | AA88: =SUM(AA84:AA87) -> 6123.6 | AC88: =SUM(AC84:AC87) -> 6123.6 | AD88: =SUM(AD84:AD87) -> 0 | AE88: =SUM(AE84:AE87) -> 6123.6 | AF88: =SUM(AF84:AF87) -> 23580.52 | AG88: =SUM(AG84:AG87) -> 2672.7 | AH88: =SUM(AH84:AH87) -> 26253.22 | AI88: =SUM(AI84:AI87) -> 27963.6 | AJ88: =SUM(AJ84:AJ87) -> 0 | AK88: =SUM(AK84:AK87) -> 27963.6 | AM88: =SUM(AM84:AM87) -> 51544.12 | AN88: =SUM(AN84:AN87) -> 2672.7 | AO88: =SUM(AO84:AO87) -> 54216.82
AJ89: =+R89+X89+AD89 -> 0
G90: Core Technical Team + Field Personnel Travel Expenses | AJ90: =+R90+X90+AD90 -> 0
AJ91: =+R91+X91+AD91 -> 0
A92: SUBFCARVA | B92: 89050 | C92: COL2 | D92: COL2 | E92: CARVAJAL | F92: FCT1TRVL | G92: Local Transportation (Airfare, Taxis, & Rental Car/Driver) | H92: 3744.26 | I92: 0 | J92: 32250.21 | K92: 575.65 | L92: 44522.98 | M92: 300.91 | N92: 1 | O92: 26000 | P92: 1 | Q92: =+O92*P92 -> 26000 | R92: 0 | S92: =SUM(Q92:R92) -> 26000 | T92: 1 | U92: =+O92*8%+O92 -> 28080 | V92: 1 | W92: =T92*U92*V92 -> 28080 | X92: 0 | Y92: =SUM(W92:X92) -> 28080 | Z92: 1 | AA92: =(+U92*8%+U92)/3 -> 10108.8 | AB92: 1 | AC92: =Z92*AA92*AB92 -> 10108.8 | AD92: 0 | AE92: =SUM(AC92:AD92) -> 10108.8 | AF92: =+H92+J92+L92 -> 80517.45 | AG92: =+I92+K92+M92 -> 876.56 | AH92: =+AF92+AG92 -> 81394.01 | AI92: =+Q92+W92+AC92 -> 64188.8 | AJ92: =+R92+X92+AD92 -> 0 | AK92: =+AI92+AJ92 -> 64188.8 | AM92: =+AF92+AI92 -> 144706.25 | AN92: =+AG92+AJ92 -> 876.56 | AO92: =+AM92+AN92 -> 145582.81
A93: SUBFCARVA | B93: 89050 | C93: COL2 | D93: COL2 | E93: CARVAJAL | F93: FCT1TRVL | G93: Meals & Incidentals | H93: 797.48 | I93: 0 | J93: 5030.7 | K93: 0 | L93: 0 | M93: 0 | N93: 1 | O93: 15000 | P93: 1 | Q93: =+O93*P93 -> 15000 | R93: 0 | S93: =SUM(Q93:R93) -> 15000 | T93: 1 | U93: =+O93*8%+O93 -> 16200 | V93: 1 | W93: =T93*U93*V93 -> 16200 | X93: 0 | Y93: =SUM(W93:X93) -> 16200 | Z93: 1 | AA93: =(+U93*8%+U93)/3 -> 5832 | AB93: 1 | AC93: =Z93*AA93*AB93 -> 5832 | AD93: 0 | AE93: =SUM(AC93:AD93) -> 5832 | AF93: =+H93+J93+L93 -> 5828.18 | AG93: =+I93+K93+M93 -> 0 | AH93: =+AF93+AG93 -> 5828.18 | AI93: =+Q93+W93+AC93 -> 37032 | AJ93: =+R93+X93+AD93 -> 0 | AK93: =+AI93+AJ93 -> 37032 | AM93: =+AF93+AI93 -> 42860.18 | AN93: =+AG93+AJ93 -> 0 | AO93: =+AM93+AN93 -> 42860.18
A94: SUBFCARVA | B94: 89050 | C94: COL2 | D94: COL2 | E94: CARVAJAL | F94: FCT1TRVL | G94: Lodging | H94: 1539.32 | I94: 0 | J94: 15496.48 | K94: 0 | L94: 0 | M94: 0 | N94: 1 | O94: 21000 | P94: 1 | Q94: =+O94*P94 -> 21000 | R94: 0 | S94: =SUM(Q94:R94) -> 21000 | T94: 1 | U94: =+O94*8%+O94 -> 22680 | V94: 1 | W94: =T94*U94*V94 -> 22680 | X94: 0 | Y94: =SUM(W94:X94) -> 22680 | Z94: 1 | AA94: =(+U94*8%+U94)/3 -> 8164.8 | AB94: 1 | AC94: =Z94*AA94*AB94 -> 8164.8 | AD94: 0 | AE94: =SUM(AC94:AD94) -> 8164.8 | AF94: =+H94+J94+L94 -> 17035.8 | AG94: =+I94+K94+M94 -> 0 | AH94: =+AF94+AG94 -> 17035.8 | AI94: =+Q94+W94+AC94 -> 51844.8 | AJ94: =+R94+X94+AD94 -> 0 | AK94: =+AI94+AJ94 -> 51844.8 | AM94: =+AF94+AI94 -> 68880.6 | AN94: =+AG94+AJ94 -> 0 | AO94: =+AM94+AN94 -> 68880.6
A95: SUBFCARVA | B95: 89050 | C95: COL2 | D95: COL2 | E95: CARVAJAL | F95: FCT1TRVL | G95: Other Travel Related Expenses | H95: 92.98 | I95: 0 | J95: 74.51 | K95: 0 | L95: 0 | M95: 0 | N95: 1 | O95: 1000 | P95: 1 | Q95: =+O95*P95 -> 1000 | R95: 0 | S95: =SUM(Q95:R95) -> 1000 | T95: 1 | U95: =+O95*8%+O95 -> 1080 | V95: 1 | W95: =T95*U95*V95 -> 1080 | X95: 0 | Y95: =SUM(W95:X95) -> 1080 | Z95: 1 | AA95: =(+U95*8%+U95)/3 -> 388.8 | AB95: 1 | AC95: =Z95*AA95*AB95 -> 388.8 | AD95: 0 | AE95: =SUM(AC95:AD95) -> 388.8 | AF95: =+H95+J95+L95 -> 167.49 | AG95: =+I95+K95+M95 -> 0 | AH95: =+AF95+AG95 -> 167.49 | AI95: =+Q95+W95+AC95 -> 2468.8 | AJ95: =+R95+X95+AD95 -> 0 | AK95: =+AI95+AJ95 -> 2468.8 | AM95: =+AF95+AI95 -> 2636.29 | AN95: =+AG95+AJ95 -> 0 | AO95: =+AM95+AN95 -> 2636.29
A96: SUBFCARVA | B96: 89050 | C96: COL2 | D96: COL2 | E96: CARVAJAL | F96: FCT1TRVL | G96: Field Transport Support for Pedagogical Advisors | H96: 0 | I96: 0 | J96: 0 | K96: 0 | L96: 0 | M96: 0 | N96: 0 | O96: 7000 | P96: 1 | Q96: =+O96*P96-R96 -> 6550 | R96: 450 | S96: =SUM(Q96:R96) -> 7000 | T96: 0 | U96: 0 | V96: 0 | W96: =T96*U96*V96 -> 0 | X96: 0 | Y96: =SUM(W96:X96) -> 0 | Z96: 0 | AA96: 0 | AB96: 0 | AC96: =Z96*AA96*AB96 -> 0 | AD96: 0 | AE96: =SUM(AC96:AD96) -> 0 | AF96: =+H96+J96+L96 -> 0 | AG96: =+I96+K96+M96 -> 0 | AH96: =+AF96+AG96 -> 0 | AI96: =+Q96+W96+AC96 -> 6550 | AJ96: =+R96+X96+AD96 -> 450 | AK96: =+AI96+AJ96 -> 7000 | AM96: =+AF96+AI96 -> 6550 | AN96: =+AG96+AJ96 -> 450 | AO96: =+AM96+AN96 -> 7000
G97: T.2 Local Travel for Field Staff | AF97: =+H97+J97+L97 -> 0 | AG97: =+I97+K97+M97 -> 0 | AH97: =+AF97+AG97 -> 0 | AI97: =+Q97+W97+AC97 -> 0 | AJ97: =+R97+X97+AD97 -> 0 | AK97: =+AI97+AJ97 -> 0 | AO97: =+AM97+AN97 -> 0
A98: SUBFCARVA | B98: 89050 | C98: COL2 | D98: COL2 | E98: CARVAJAL | F98: FCT2FUELEX | G98: Vehicle Fuel Expense | H98: 34.31 | I98: 0 | J98: 0 | K98: 0 | L98: 0 | M98: 0 | N98: 0 | O98: 0 | P98: 0 | Q98: =N98*O98*P98 -> 0 | R98: 0 | S98: =SUM(Q98:R98) -> 0 | T98: 0 | U98: 0 | V98: 0 | W98: =T98*U98*V98 -> 0 | X98: 0 | Y98: =SUM(W98:X98) -> 0 | Z98: 0 | AA98: 0 | AB98: 0 | AC98: =Z98*AA98*AB98 -> 0 | AD98: 0 | AE98: =SUM(AC98:AD98) -> 0 | AF98: =+H98+J98+L98 -> 34.31 | AG98: =+I98+K98+M98 -> 0 | AH98: =+AF98+AG98 -> 34.31 | AI98: =+Q98+W98+AC98 -> 0 | AJ98: =+R98+X98+AD98 -> 0 | AK98: =+AI98+AJ98 -> 0 | AM98: =+AF98+AI98 -> 34.31 | AN98: =+AG98+AJ98 -> 0 | AO98: =+AM98+AN98 -> 34.31
G99: T.5 Travel to SMT In-Person Meetings in Bogota | AF99: =+H99+J99+L99 -> 0 | AG99: =+I99+K99+M99 -> 0 | AH99: =+AF99+AG99 -> 0 | AI99: =+Q99+W99+AC99 -> 0 | AJ99: =+R99+X99+AD99 -> 0 | AK99: =+AI99+AJ99 -> 0 | AO99: =+AM99+AN99 -> 0
A100: SUBFCARVA | B100: 89050 | C100: COL2 | D100: COL2 | E100: CARVAJAL | F100: FCT5TRVL | G100: Local Transportation for SMT Meetings | H100: 1208.06 | I100: 0 | J100: 2940.35 | K100: 0 | N100: 0 | O100: 0 | P100: 0 | Q100: =N100*O100*P100 -> 0 | R100: 0 | S100: =SUM(Q100:R100) -> 0 | T100: 0 | U100: 0 | V100: 0 | W100: =T100*U100*V100 -> 0 | X100: 0 | Y100: =SUM(W100:X100) -> 0 | Z100: 0 | AA100: 0 | AB100: 0 | AC100: =Z100*AA100*AB100 -> 0 | AD100: 0 | AE100: =SUM(AC100:AD100) -> 0 | AF100: =+H100+J100+L100 -> 4148.41 | AG100: =+I100+K100+M100 -> 0 | AH100: =+AF100+AG100 -> 4148.41 | AI100: =+Q100+W100+AC100 -> 0 | AJ100: =+R100+X100+AD100 -> 0 | AK100: =+AI100+AJ100 -> 0 | AM100: =+AF100+AI100 -> 4148.41 | AN100: =+AG100+AJ100 -> 0 | AO100: =+AM100+AN100 -> 4148.41 | AQ100: =SUM(AM100:AM102) -> 5480.25
A101: SUBFCARVA | B101: 89050 | C101: COL2 | D101: COL2 | E101: CARVAJAL | F101: FCT5TRVL | G101: Meals and Incidentals for SMT Meetings | H101: 74.83 | I101: 0 | J101: 558.18 | K101: 0 | N101: 0 | O101: 0 | P101: 0 | Q101: =N101*O101*P101 -> 0 | R101: 0 | S101: =SUM(Q101:R101) -> 0 | T101: 0 | U101: 0 | V101: 0 | W101: =T101*U101*V101 -> 0 | X101: 0 | Y101: =SUM(W101:X101) -> 0 | Z101: 0 | AA101: 0 | AB101: 0 | AC101: =Z101*AA101*AB101 -> 0 | AD101: 0 | AE101: =SUM(AC101:AD101) -> 0 | AF101: =+H101+J101+L101 -> 633.01 | AG101: =+I101+K101+M101 -> 0 | AH101: =+AF101+AG101 -> 633.01 | AI101: =+Q101+W101+AC101 -> 0 | AJ101: =+R101+X101+AD101 -> 0 | AK101: =+AI101+AJ101 -> 0 | AM101: =+AF101+AI101 -> 633.01 | AN101: =+AG101+AJ101 -> 0 | AO101: =+AM101+AN101 -> 633.01
A102: SUBFCARVA | B102: 89050 | C102: COL2 | D102: COL2 | E102: CARVAJAL | F102: FCT5TRVL | G102: Lodging for SMT Meetings | H102: 166.24 | I102: 0 | J102: 330.85 | K102: 0 | L102: 201.74 | N102: 0 | O102: 0 | P102: 0 | Q102: =N102*O102*P102 -> 0 | R102: 0 | S102: =SUM(Q102:R102) -> 0 | T102: 0 | U102: 0 | V102: 0 | W102: =T102*U102*V102 -> 0 | X102: 0 | Y102: =SUM(W102:X102) -> 0 | Z102: 0 | AA102: 0 | AB102: 0 | AC102: =Z102*AA102*AB102 -> 0 | AD102: 0 | AE102: =SUM(AC102:AD102) -> 0 | AF102: =+H102+J102+L102 -> 698.83 | AG102: =+I102+K102+M102 -> 0 | AH102: =+AF102+AG102 -> 698.83 | AI102: =+Q102+W102+AC102 -> 0 | AJ102: =+R102+X102+AD102 -> 0 | AK102: =+AI102+AJ102 -> 0 | AM102: =+AF102+AI102 -> 698.83 | AN102: =+AG102+AJ102 -> 0 | AO102: =+AM102+AN102 -> 698.83
G103: Subtotal Core Technical Team + Field Personnel Travel Expenses | H103: =SUM(H92:H102) -> 7657.48 | I103: =SUM(I92:I102) -> 0 | J103: =SUM(J92:J102) -> 56681.28 | K103: =SUM(K92:K102) -> 575.65 | L103: =SUM(L92:L102) -> 44724.72 | M103: =SUM(M92:M102) -> 300.91 | O103: =SUM(O92:O102) -> 70000 | Q103: =SUM(Q92:Q102) -> 69550 | R103: =SUM(R92:R102) -> 450 | S103: =SUM(S92:S102) -> 70000 | U103: =SUM(U92:U102) -> 68040 | V103: =SUM(V92:V102) -> 4 | W103: =SUM(W92:W102) -> 68040 | X103: =SUM(X92:X102) -> 0 | Y103: =SUM(Y92:Y102) -> 68040 | Z103: =SUM(Z92:Z102) -> 4 | AA103: =SUM(AA92:AA102) -> 24494.4 | AB103: =SUM(AB92:AB102) -> 4 | ... AK103: =SUM(AK92:AK102) -> 162534.4 | AM103: =SUM(AM92:AM102) -> 271147.88 | AN103: =SUM(AN92:AN102) -> 1326.56 | AO103: =SUM(AO92:AO102) -> 272474.44
G104: 3. Travel Total | H104: =+H88+H103 -> 10059.13 | I104: =+I88+I103 -> 0 | J104: =+J88+J103 -> 66633.71 | K104: =+K88+K103 -> 575.65 | L104: =+L88+L103 -> 55951.16 | M104: =+M88+M103 -> 2973.61 | O104: =+O88+O103 -> 80500 | Q104: =+Q88+Q103 -> 80050 | R104: =+R88+R103 -> 450 | S104: =+S88+S103 -> 80500 | U104: =+U103+U88 -> 79380 | W104: =+W103+W88 -> 79380 | X104: =+X103+X88 -> 0 | Y104: =+Y103+Y88 -> 79380 | AA104: =+AA103+AA88 -> 30618 | AC104: =+AC103+AC88 -> 30618 | AD104: =+AD103+AD88 -> 0 | AE104: =+AE103+AE88 -> 30618 | AF104: =+AF103+AF88 -> 132644 | AG104: =+AG103+AG88 -> 3549.26 | AH104: =+AH103+AH88 -> 136193.26 | AI104: =+AI103+AI88 -> 190048 | AJ104: =+AJ103+AJ88 -> 450 | ... AO104: =+AO103+AO88 -> 326691.26
...

Sheet 800-FC - Mod7
A2: 800-FUNDACION CARVAJAL | F2: 800-FUNDACION CARVAJAL - Modification No. 7 - Cost Extension and Budget Realignment
B3: Categories | C3: Amount | D3: Leverage | E3: Total | G3: Categories | H3: Amount | I3: Leverage | J3: Total | L3: % representativo sobre el total del subacuerdo (USAID Funds) | N3: % representativo sobre el total del subacuerdo (Leverage Funds) | P3: % representativo sobre el total del subacuerdo (TOTAL)
B4: Categorías | C4: Monto | D4: Apalancamiento | G4: Categorías | H4: Monto | I4: Apalancamiento | L4: Inicial | M4: Mod.7 | N4: Inicial | O4: Mod.7 | P4: Inicial | Q4: Mod.7
A5: 1. | B5: Personnel | C5: 2847676 | D5: 66152 | E5: =+C5+D5 -> 2913828 | F5: 1. | G5: Personnel | H5: ='800-FC - Consolidated Details'!AM77 -> 2858976.9 | I5: ='800-FC - Consolidated Details'!AN77 -> 65374.663 | J5: ='800-FC - Consolidated Details'!AO77 -> 2924351.5 | K5: =IF(J5>=E5,"SUBE","BAJA") -> SUBE | L5: =+$C5*100/$C$23 -> 32.783661 | M5: =+$H5*100/$H$23 -> 31.395712 | N5: =+$D5*100/$D$23 -> 20.936496 | O5: =+$I5*100/$I$23 -> 13.841655 | P5: =+$E5*100/$E$23 -> 32.367839 | Q5: =+$J5*100/$J$23 -> 30.530146
B6: Personal | G6: Personal
A7: 2. | B7: Fringe Benefits | C7: 1310790 | D7: 29095 | E7: =+C7+D7 -> 1339885 | F7: 2. | G7: Fringe Benefits | H7: ='800-FC - Consolidated Details'!AM81 -> 1383962.7 | I7: ='800-FC - Consolidated Details'!AN81 -> 24339.97 | J7: ='800-FC - Consolidated Details'!AO81 -> 1408302.7 | K7: =IF(J7>=E7,"SUBE","BAJA") -> SUBE | L7: =+$C7*100/$C$23 -> 15.090374 | M7: =+$H7*100/$H$23 -> 15.197917 | N7: =+$D7*100/$D$23 -> 9.2082984 | O7: =+$I7*100/$I$23 -> 5.1534564 | P7: =+$E7*100/$E$23 -> 14.88392 | Q7: =+$J7*100/$J$23 -> 14.702639
B8: Beneficios | G8: Beneficios
A9: 3. | B9: Travel | C9: 188410 | D9: 0 | E9: =+C9+D9 -> 188410 | F9: 3. | G9: Travel | H9: ='800-FC - Consolidated Details'!AM104 -> 322692 | I9: ='800-FC - Consolidated Details'!AN104 -> 3999.26 | J9: ='800-FC - Consolidated Details'!AO104 -> 326691.26 | K9: =IF(J9>=E9,"SUBE","BAJA") -> SUBE | L9: =+$C9*100/$C$23 -> 2.1690563 | M9: =+$H9*100/$H$23 -> 3.5436261 | N9: =+$D9*100/$D$23 -> 0 | O9: =+$I9*100/$I$23 -> 0.84675585 | P9: =+$E9*100/$E$23 -> 2.0929254 | Q9: =+$J9*100/$J$23 -> 3.4106473
B10: Viajes | G10: Viajes
A11: 4. | B11: Equipment | C11: 50000 | D11: 0 | E11: =+C11+D11 -> 50000 | F11: 4. | G11: Equipment | H11: ='800-FC - Consolidated Details'!AM106 -> 0 | I11: ='800-FC - Consolidated Details'!AN106 -> 0 | J11: ='800-FC - Consolidated Details'!AO106 -> 0 | K11: =IF(J11>=E11,"SUBE","BAJA") -> BAJA | L11: =+$C11*100/$C$23 -> 0.57562133 | M11: =+$H11*100/$H$23 -> 0 | N11: =+$D11*100/$D$23 -> 0 | O11: =+$I11*100/$I$23 -> 0 | P11: =+$E11*100/$E$23 -> 0.55541781 | Q11: =+$J11*100/$J$23 -> 0
B12: Equipo | G12: Equipo
A13: 5. | B13: Supplies | C13: 69389 | D13: 0 | E13: =+C13+D13 -> 69389 | F13: 5. | G13: Supplies | H13: ='800-FC - Consolidated Details'!AM111 -> 67039.9 | I13: ='800-FC - Consolidated Details'!AN111 -> 2639.18 | J13: ='800-FC - Consolidated Details'!AO111 -> 69679.08 | K13: =IF(J13>=E13,"SUBE","BAJA") -> SUBE | L13: =+$C13*100/$C$23 -> 0.79883577 | M13: =+$H13*100/$H$23 -> 0.73619531 | N13: =+$D13*100/$D$23 -> 0 | O13: =+$I13*100/$I$23 -> 0.55878865 | P13: =+$E13*100/$E$23 -> 0.77079773 | Q13: =+$J13*100/$J$23 -> 0.72744759
B14: Suministros | G14: Suministros
A15: 6. | B15: Contractual | C15: 3113105 | D15: 0 | E15: =+C15+D15 -> 3113105 | F15: 6. | G15: Contractual | H15: ='800-FC - Consolidated Details'!AM132 -> 2753313.3 | I15: ='800-FC - Consolidated Details'!AN132 -> 230324.4 | J15: ='800-FC - Consolidated Details'!AO132 -> 2983637.7 | K15: =IF(J15>=E15,"SUBE","BAJA") -> BAJA | L15: =+$C15*100/$C$23 -> 35.839393 | M15: =+$H15*100/$H$23 -> 30.235372 | N15: =+$D15*100/$D$23 -> 0 | O15: =+$I15*100/$I$23 -> 48.766155 | P15: =+$E15*100/$E$23 -> 34.581479 | Q15: =+$J15*100/$J$23 -> 31.149092
B16: Contractual | G16: Contractual
A17: 7. | B17: Other Direct Costs | C17: 594509 | D17: 191995 | E17: =+C17+D17 -> 786504 | F17: 7. | G17: Other Direct Costs | H17: ='800-FC - Consolidated Details'!AM170 -> 1064583.8 | I17: ='800-FC - Consolidated Details'!AN170 -> 114460.72 | J17: ='800-FC - Consolidated Details'!AO170 -> 1179044.6 | K17: =IF(J17>=E17,"SUBE","BAJA") -> SUBE | L17: =+$C17*100/$C$23 -> 6.8442412 | M17: =+$H17*100/$H$23 -> 11.690674 | N17: =+$D17*100/$D$23 -> 60.764642 | O17: =+$I17*100/$I$23 -> 24.234554 | P17: =+$E17*100/$E$23 -> 8.7367666 | Q17: =+$J17*100/$J$23 -> 12.309191
B18: Otros Costos Directos | G18: Otros Costos Directos
A19: 8. | B19: Total Direct Costs | C19: =+SUM(C5:C18) -> 8173879 | D19: =+SUM(D5:D18) -> 287242 | E19: =+SUM(E5:E18) -> 8461121 | F19: 8. | G19: Total Direct Costs | H19: =+SUM(H5:H18) -> 8450568.6 | I19: =+SUM(I5:I18) -> 441138.19 | J19: =+SUM(J5:J18) -> 8891706.8 | K19: =IF(J19>=E19,"SUBE","BAJA") -> SUBE | L19: =+$C19*100/$C$23 -> 94.101182 | M19: =+$H19*100/$H$23 -> 92.799497 | N19: =+$D19*100/$D$23 -> 90.909436 | O19: =+$I19*100/$I$23 -> 93.401365 | P19: =+$E19*100/$E$23 -> 93.989146 | Q19: =+$J19*100/$J$23 -> 92.829163
B20: Valor Total Costos Directos | G20: Valor Total Costos Directos
A21: 9. | B21: Indirect Costs | C21: 512388 | D21: 28724 | E21: =+C21+D21 -> 541112 | F21: 9. | G21: Indirect Costs | H21: ='800-FC - Consolidated Details'!AM172 -> 655696.94 | I21: ='800-FC - Consolidated Details'!AN172 -> 31165.602 | J21: ='800-FC - Consolidated Details'!AO172 -> 686863.66 | K21: =IF(J21>=E21,"SUBE","BAJA") -> SUBE | L21: =+$C21*100/$C$23 -> 5.8988293 | M21: =+$H21*100/$H$23 -> 7.2005032 | N21: =+$D21*100/$D$23 -> 9.0908803 | O21: =+$I21*100/$I$23 -> 6.5986347 | P21: =+$E21*100/$E$23 -> 6.0108649 | Q21: =+$J21*100/$J$23 -> 7.1708369
B22: Costos Indirectos | G22: Costos Indirectos
A23: 10. | B23: Total Costs | C23: =+C19+C21-1 -> 8686266 | D23: =+D19+D21-1 -> 315965 | E23: =+E19+E21-1 -> 9002232 | F23: 10. | G23: Total Costs | H23: =+H19+H21 -> 9106265.6 | I23: =+I19+I21 -> 472303.8 | J23: =+J19+J21 -> 9578570.5 | K23: =IF(J23>=E23,"SUBE","BAJA") -> SUBE | L23: =+$C23*100/$C$23 -> 100 | M23: =+$H23*100/$H$23 -> 100 | N23: =+$D23*100/$D$23 -> 100 | O23: =+$I23*100/$I$23 -> 100 | P23: =+$E23*100/$E$23 -> 100 | Q23: =+$J23*100/$J$23 -> 100
B24: Valor Total | G24: Valor Total
A28: 800-FUNDACION CARVAJAL - INITIAL BUDGET
B29: Categories | C29: Amount | D29: Leverage | E29: Total | F29: Expenditures Amount up to Dec/23 | G29: Expenditures Leverage up to Dec/23 | H29: Total Expenditures up to Dec/23 | I29: Remaining USAID | J29: Remaining Leverage | K29: Total Remaining
B30: Categorías | C30: Monto | D30: Apalancamiento | F30: Monto Ejecutado | G30: Apalancamiento Reportado | H30: Apalancamiento Reportado | I30: Saldo USAID | J30: Saldo Apalancamiento | K30: Saldo Total
A31: 1. | B31: Personnel | C31: 2847676 | D31: 66152 | E31: =+C31+D31 -> 2913828 | F31: ='800-FC - Consolidated Details'!AF77 -> 1107253.8 | G31: ='800-FC - Consolidated Details'!AG77 -> 32437.34 | H31: =+F31+G31 -> 1139691.1 | I31: =+C31-F31 -> 1740422.2 | J31: =+D31-G31 -> 33714.66 | K31: =+E31-H31 -> 1774136.9
B32: Personal
A33: 2. | B33: Fringe Benefits | C33: 1310790 | D33: 29095 | E33: =+C33+D33 -> 1339885 | F33: ='800-FC - Consolidated Details'!AF81 -> 492962.7 | G33: ='800-FC - Consolidated Details'!AG81 -> 8339.97 | H33: =+F33+G33 -> 501302.67 | I33: =+C33-F33 -> 817827.3 | J33: =+D33-G33 -> 20755.03 | K33: =+E33-H33 -> 838582.33
B34: Beneficios
A35: 3. | B35: Travel | C35: 188410 | D35: 0 | E35: =+C35+D35 -> 188410 | F35: ='800-FC - Consolidated Details'!AF104 -> 132644 | G35: ='800-FC - Consolidated Details'!AG104 -> 3549.26 | H35: =+F35+G35 -> 136193.26 | I35: =+C35-F35 -> 55766 | J35: =+D35-G35 -> -3549.26 | K35: =+E35-H35 -> 52216.74
B36: Viajes
A37: 4. | B37: Equipment | C37: 50000 | D37: 0 | E37: =+C37+D37 -> 50000 | F37: ='800-FC - Consolidated Details'!AF107 -> 0 | G37: ='800-FC - Consolidated Details'!AG107 -> 0 | H37: =+F37+G37 -> 0 | I37: =+C37-F37 -> 50000 | J37: =+D37-G37 -> 0 | K37: =+E37-H37 -> 50000
B38: Equipo
A39: 5. | B39: Supplies | C39: 69389 | D39: 0 | E39: =+C39+D39 -> 69389 | F39: ='800-FC - Consolidated Details'!AF111 -> 59050.3 | G39: ='800-FC - Consolidated Details'!AG111 -> 2639.18 | H39: =+F39+G39 -> 61689.48 | I39: =+C39-F39 -> 10338.7 | J39: =+D39-G39 -> -2639.18 | K39: =+E39-H39 -> 7699.52
B40: Suministros
A41: 6. | B41: Contractual | C41: 3113105 | D41: 0 | E41: =+C41+D41 -> 3113105 | F41: ='800-FC - Consolidated Details'!AF132 -> 1272971.5 | G41: ='800-FC - Consolidated Details'!AG132 -> 151747.4 | H41: =+F41+G41 -> 1424718.9 | I41: =+C41-F41 -> 1840133.5 | J41: =+D41-G41 -> -151747.4 | K41: =+E41-H41 -> 1688386.1
B42: Contractual
A43: 7. | B43: Other Direct Costs | C43: 594509 | D43: 191995 | E43: =+C43+D43 -> 786504 | F43: ='800-FC - Consolidated Details'!AF170 -> 345033.98 | G43: ='800-FC - Consolidated Details'!AG170 -> 60695.72 | H43: ='800-FC - Consolidated Details'!AG170 -> 60695.72 | I43: =+C43-F43 -> 249475.02 | J43: =+D43-G43 -> 131299.28 | K43: =+E43-H43 -> 725808.28
B44: Otros Costos Directos
A45: 8. | B45: Total Direct Costs | C45: =+C31+C33+C35+C37+C39+C41+C43 -> 8173879 | D45: =+D31+D33+D35+D37+D39+D41+D43 -> 287242 | E45: =+E31+E33+E35+E37+E39+E41+E43 -> 8461121 | F45: =+F31+F33+F35+F37+F39+F41+F43 -> 3409916.3 | G45: =+G31+G33+G35+G37+G39+G41+G43 -> 259408.87 | H45: =+H31+H33+H35+H37+H39+H41+H43 -> 3324291.2 | I45: =+I31+I33+I35+I37+I39+I41+I43 -> 4763962.7 | J45: =+J31+J33+J35+J37+J39+J41+J43 -> 27833.13 | K45: =+K31+K33+K35+K37+K39+K41+K43 -> 5136829.8
B46: Valor Total Costos Directos
A47: 9. | B47: Indirect Costs | C47: 512388 | D47: 28724 | E47: =+C47+D47 -> 541112 | F47: ='800-FC - Consolidated Details'!AF172 -> 257490.82 | G47: ='800-FC - Consolidated Details'!AG172 -> 12992.67 | H47: =+F47+G47 -> 270483.49 | I47: =+C47-F47 -> 254897.18 | J47: =+D47-G47 -> 15731.33 | K47: =+E47-H47 -> 270628.51
B48: Costos Indirectos
A49: 10. | B49: Total Costs | C49: =+C45+C47-1 -> 8686266 | D49: =+D45+D47-1 -> 315965 | E49: =+E45+E47-1 -> 9002232 | F49: =+F45+F47 -> 3667407.1 | G49: =+G45+G47-1 -> 272400.54 | H49: =+H45+H47-1 -> 3594773.7 | I49: =+I45+I47-1 -> 5018858.9 | J49: =+J45+J47-1 -> 43563.46 | K49: =+K45+K47-1 -> 5407457.3
B50: Valor Total
A52: 800-FUNDACION CARVAJAL - Modification No. 7 - Budget Realignment
B53: Categories | C53: Amount | D53: Leverage | E53: Total | F53: Expenditures Amount up to Dec/23 | G53: Expenditures Leverage up to Dec/23 | H53: Total Expenditures up to Dec/23 | I53: Remaining USAID | J53: Remaining Leverage | K53: Total Remaining
B54: Categorías | C54: Monto | D54: Apalancamiento | F54: Monto Ejecutado hasta Dic/23 | G54: Apalancamiento Reportado hasta Dic/23 | H54: Total Ejecución hasta Dic/23 | I54: Saldo USAID | J54: Saldo Apalancamiento | K54: Saldo Total
A55: 1. | B55: Personnel | C55: 2858976.9 | D55: 65374.663 | E55: 2924351.5 | F55: 1107253.8 | G55: 32437.34 | H55: 1139691.1 | I55: =+C55-F55 -> 1751723.1 | J55: =+D55-G55 -> 32937.323 | K55: =+E55-H55 -> 1784660.4
B56: Personal
A57: 2. | B57: Fringe Benefits | C57: 1383962.7 | D57: 24340 | E57: 1406102.7 | F57: 492962.7 | G57: 8339.97 | H57: 501302.67 | I57: =+C57-F57 -> 891000 | J57: =+D57-G57 -> 16000.03 | K57: =+E57-H57 -> 904800
B58: Beneficios
A59: 3. | B59: Travel | C59: 322692 | D59: 3999.26 | E59: 326691.26 | F59: 132644 | G59: 3549.26 | H59: 136193.26 | I59: =+C59-F59 -> 190048 | J59: =+D59-G59 -> 450 | K59: =+E59-H59 -> 190498
B60: Viajes
A61: 4. | B61: Equipment | C61: 0 | D61: 0 | E61: 0 | F61: 0 | G61: 0 | H61: 0 | I61: =+C61-F61 -> 0 | J61: =+D61-G61 -> 0 | K61: =+E61-H61 -> 0
B62: Equipo
A63: 5. | B63: Supplies | C63: 67039.9 | D63: 2639.18 | E63: 69679.08 | F63: 59050.3 | G63: 2639.18 | H63: 61689.48 | I63: =+C63-F63 -> 7989.6 | J63: =+D63-G63 -> 0 | K63: =+E63-H63 -> 7989.6
B64: Suministros
A65: 6. | B65: Contractual | C65: 2753313.8 | D65: 230324 | E65: 2938534.5 | F65: 1272971.5 | G65: 151747.4 | H65: 1424718.9 | I65: =+C65-F65 -> 1480342.3 | J65: =+D65-G65 -> 78576.6 | K65: =+E65-H65 -> 1513815.6
B66: Contractual
A67: 7. | B67: Other Direct Costs | C67: 1064583.8 | D67: 114460.72 | E67: 1179044.6 | F67: 345033.98 | G67: 60695.72 | H67: 60695.72 | I67: =+C67-F67 -> 719549.86 | J67: =+D67-G67 -> 53765 | K67: =+E67-H67 -> 1118348.8
B68: Otros Costos Directos
A69: 8. | B69: Total Direct Costs | C69: 8450569.1 | D69: 441138 | E69: 8844403.6 | F69: 3409916.3 | G69: 259408.87 | H69: 3324291.2 | I69: =+C69-F69 -> 5040652.8 | J69: =+D69-G69 -> 181729.13 | K69: =+E69-H69 -> 5520112.4
B70: Valor Total Costos Directos
A71: 9. | B71: Indirect Costs | C71: 655697 | D71: 31166 | E71: 687219.68 | F71: 257490.82 | G71: 12992.67 | H71: 270483.49 | I71: =+C71-F71 -> 398206.18 | J71: =+D71-G71 -> 18173.33 | K71: =+E71-H71 -> 416736.18
B72: Costos Indirectos
A73: 10. | B73: Total Costs | C73: =+C69+C71 -> 9106266.1 | D73: =+D69+D71 -> 472304 | E73: =+E69+E71 -> 9531623.3 | F73: =+F69+F71 -> 3667407.1 | G73: =+G69+G71 -> 272401.54 | H73: =+H69+H71 -> 3594774.7 | I73: =+I69+I71 -> 5438859 | J73: =+D73-G73 -> 199902.46 | K73: =+E73-H73 -> 5936848.6
B74: Valor Total
B78: TRACKER - OBLIGATED AMOUNTS (According with modifications):
B80: Line Items | C80: Inicial | D80: Modificacion N° 1 | E80: Modification N° 2 | F80: Modification N° 3 | G80: Modification N° 4 | H80: Modification N° 5 | I80: Modification N° 6 | J80: Total Obligated Line Items (After mod 6) | K80: Modification N° 7 | L80: New Obligated Line Items (after mod 7) | M80: REMAINING USD (After Mod. 7)
C81: Original Obligated Amount | D81: Actual Obligated Amount | E81: Increase Obligated Amount | F81: Increase Obligated Amount | G81: Increase Obligated Amount | H81: Increase Obligated Amount | I81: Increase Obligated Amount | K81: Budget Realigment
B82: Personnel | C82: 533897 | D82: 0 | E82: 135000 | F82: 0 | G82: 190966.51 | H82: 266298 | I82: 425365 | J82: =+C82+D82+E82+F82+G82+H82+I82 -> 1551526.5 | K82: 2858977 | L82: =+J82 -> 1551526.5 | M82: =+K82-L82 -> 1307450.5
B83: Fringe Benefits | C83: 241720 | D83: 0 | E83: 46711 | F83: 0 | G83: 104145 | H83: 125000 | I83: 187268 | J83: =+C83+D83+E83+F83+G83+H83+I83 -> 704844 | K83: 1383963 | L83: =+J83 -> 704844 | M83: =+K83-L83 -> 679119
B84: Travel | C84: 31565 | D84: 30000 | E84: 31105.55 | F84: 5100 | G84: 26290.9 | H84: 50000 | I84: 18679 | J84: =+C84+D84+E84+F84+G84+H84+I84 -> 192740.45 | K84: 322692 | L84: =+J84 -> 192740.45 | M84: =+K84-L84 -> 129951.55
B85: Equipment | C85: 50000 | D85: 0 | F85: 0 | G85: 0 | I85: 0 | J85: =+C85+D85+E85+F85+G85+H85+I85 -> 50000 | K85: 0 | L85: =+J85 -> 50000 | M85: =+K85-L85 -> -50000
B86: Supplies | C86: 41854 | D86: 20000 | F86: 0 | G86: 776.2 | I86: 0 | J86: =+C86+D86+E86+F86+G86+H86+I86 -> 62630.2 | K86: 67040 | L86: =+J86 -> 62630.2 | M86: =+K86-L86 -> 4409.8
B87: Contractual
B88: Subwards to Local Implementing Partners | C88: 300000 | D88: 330000 | E88: 0 | F88: =143225.6+974.4 -> 144200 | G88: 36206.15 | H88: 166672 | I88: 0 | J88: =+C88+D88+E88+F88+G88+H88+I88 -> 977078.15 | K88: 1893538 | L88: =+J88 -> 977078.15 | M88: =+K88-L88 -> 916459.85
B89: Consultants | C89: 4200 | D89: 197519 | E89: 48547.34 | F89: 60000 | G89: 87609.47 | H89: 54000 | I89: 96000 | J89: =+C89+D89+E89+F89+G89+H89+I89 -> 547875.81 | K89: 859775 | L89: =+J89 -> 547875.81 | M89: =+K89-L89 -> 311899.19
B90: Other Direct Costs | C90: 131800 | D90: 10000 | E90: 25000 | F90: 12900 | G90: =113150+9098 -> 122248 | H90: 85000 | I90: 90095 | J90: =+C90+D90+E90+F90+G90+H90+I90 -> 477043 | K90: 1064584 | L90: =+J90 -> 477043 | M90: =+K90-L90 -> 587541
B91: Total Direct Costs | C91: =SUM(C82:C90) -> 1335036 | D91: =SUM(D82:D90) -> 587519 | E91: =+SUM(E82:E90) -> 286363.89 | F91: =+SUM(F82:F90) -> 222200 | G91: =+SUM(G82:G90) -> 568242.23 | H91: =+SUM(H82:H90) -> 746970 | I91: =+SUM(I82:I90) -> 817407 | J91: =+SUM(J82:J90) -> 4563738.1 | K91: =+SUM(K82:K90) -> 8450569 | L91: =+J91 -> 4563738.1 | M91: =+K91-L91 -> 3886830.9
B92: Indirect Costs | C92: 98505 | D92: =30752 -> 30752 | E92: =(E91-E88-E85)*10% -> 28636.389 | F92: =(F91-F88-F85)*10% -> 7800 | G92: =ROUND((G91-G88-G85)*10%,2) -> 53203.61 | H92: =ROUND((H91-H88-H85)*10%,0) -> 58030 | I92: =ROUND((I91-I88-I85)*10%,0) -> 81741 | J92: =+C92+D92+E92+F92+G92+H92+I92 -> 358668 | K92: 655697 | L92: =+J92 -> 358668 | M92: =+K92-L92 -> 297029
B93: Total | C93: =SUM(C91:C92) -> 1433541 | D93: =SUM(D91:D92) -> 618271 | E93: =+E91+E92 -> 315000.28 | F93: =+F91+F92 -> 230000 | G93: =+G91+G92 -> 621445.84 | H93: =+H91+H92 -> 805000 | I93: =+I91+I92 -> 899148 | J93: =+J91+J92 -> 4922406.1 | K93: =+K91+K92 -> 9106266 | L93: =+J93 -> 4922406.1 | M93: =+K93-L93 -> 4183859.9
L94: =+L93+M93 -> 9106266

Sheet 800-FC - Summary - Annex B
B1: Name of Subawardee: Fundación Carvajal
B2: 800-FUNDACION CARVAJAL - MODIFICATION No. 7
A4: Line Items | B4: Year 1 | E4: Year 2 | H4: Year 3 | K4: Year 4 | N4: Year 5 | Q4: Year 6 | T4: Total | U4: Total | V4: Grand
B5: USAID | C5: Leverage | D5: Total | E5: USAID | F5: Leverage | G5: Total | H5: USAID | I5: Leverage | J5: Total | K5: USAID | L5: Leverage | M5: Total | N5: USAID | O5: Leverage | P5: Total | Q5: USAID | R5: Leverage | S5: Total | T5: USAID | U5: Leverage | V5: Total
A7: Personnel | B7: 75200 | C7: 1213 | D7: =+B7+C7 -> 76413 | E7: 471135 | F7: 3225 | G7: =+E7+F7 -> 474360 | H7: 560919 | I7: 27999 | J7: =+H7+I7 -> 588918 | K7: 673740 | L7: 18295 | M7: =+K7+L7 -> 692035 | N7: 695259 | O7: 8394 | P7: =+N7+O7 -> 703653 | Q7: 382724 | R7: 6248 | S7: =+Q7+R7 -> 388972 | T7: =+B7+E7+H7+K7+N7+Q7 -> 2858977 | U7: =+C7+F7+I7+L7+O7+R7+1 -> 65375 | V7: =+T7+U7 -> 2924352
A9: Fringe Benefits | B9: 27002 | C9: 428 | D9: =+B9+C9 -> 27430 | E9: 194200 | F9: 955 | G9: =+E9+F9 -> 195155 | H9: 271761 | I9: 6958 | J9: =+H9+I9 -> 278719 | K9: 340000 | L9: 9200 | M9: =+K9+L9 -> 349200 | N9: 351000 | O9: 4600 | P9: =+N9+O9 -> 355600 | Q9: 200000 | R9: 2200 | S9: =+Q9+R9 -> 202200 | T9: =+B9+E9+H9+K9+N9+Q9 -> 1383963 | U9: =+C9+F9+I9+L9+O9+R9-1 -> 24340 | V9: =+T9+U9 -> 1408303
A11: Travel | B11: 10059 | C11: 0 | D11: =+B11+C11 -> 10059 | E11: 66634 | F11: 576 | G11: =+E11+F11 -> 67210 | H11: 55951 | I11: 2974 | J11: =+H11+I11 -> 58925 | K11: 80050 | L11: =450-1 -> 449 | M11: =+K11+L11 -> 80499 | N11: 79380 | O11: 0 | P11: =+N11+O11 -> 79380 | Q11: 30618 | R11: 0 | S11: =+Q11+R11 -> 30618 | T11: =+B11+E11+H11+K11+N11+Q11 -> 322692 | U11: =+C11+F11+I11+L11+O11+R11 -> 3999 | V11: =+T11+U11 -> 326691
A13: Equipment | B13: 0 | C13: 0 | D13: =+B13+C13 -> 0 | E13: 0 | F13: 0 | G13: =+E13+F13 -> 0 | H13: 0 | I13: 0 | J13: =+H13+I13 -> 0 | K13: 0 | L13: 0 | M13: =+K13+L13 -> 0 | N13: 0 | O13: 0 | P13: =+N13+O13 -> 0 | Q13: 0 | R13: 0 | S13: =+Q13+R13 -> 0 | T13: =+B13+E13+H13+K13+N13+Q13 -> 0 | U13: =+C13+F13+I13+L13+O13+R13 -> 0 | V13: =+T13+U13 -> 0
A15: Supplies | B15: 42723 | C15: 0 | D15: =+B15+C15 -> 42723 | E15: 10551 | F15: 0 | G15: =+E15+F15 -> 10551 | H15: 5776 | I15: 2639 | J15: =+H15+I15 -> 8415 | K15: 3000 | L15: 0 | M15: =+K15+L15 -> 3000 | N15: 3240 | O15: 0 | P15: =+N15+O15 -> 3240 | Q15: 1750 | R15: 0 | S15: =+Q15+R15 -> 1750 | T15: =+B15+E15+H15+K15+N15+Q15 -> 67040 | U15: =+C15+F15+I15+L15+O15+R15 -> 2639 | V15: =+T15+U15 -> 69679
A17: Contractual | B17: 46712 | C17: 0 | D17: =+B17+C17 -> 46712 | E17: 565429 | F17: 13314 | G17: =+E17+F17 -> 578743 | H17: 660830 | I17: 138433 | J17: =+H17+I17 -> 799263 | K17: 291619 | L17: 78577 | M17: =+K17+L17 -> 370196 | N17: 932661 | O17: 0 | P17: =+N17+O17 -> 932661 | Q17: 256063 | R17: 0 | S17: =+Q17+R17 -> 256063 | T17: =+B17+E17+H17+K17+N17+Q17 -> 2753314 | U17: =+C17+F17+I17+L17+O17+R17 -> 230324 | V17: =+T17+U17 -> 2983638
A19: Other Direct Costs | B19: 2301 | C19: 7005 | D19: =+B19+C19 -> 9306 | E19: 176624 | F19: 24982 | G19: =+E19+F19 -> 201606 | H19: 166108 | I19: 28709 | J19: =+H19+I19 -> 194817 | K19: 291558 | L19: 53765 | M19: =+K19+L19 -> 345323 | N19: 247029 | O19: 0 | P19: =+N19+O19 -> 247029 | Q19: 180963 | R19: 0 | S19: =+Q19+R19 -> 180963 | T19: =+B19+E19+H19+K19+N19+Q19 -> 1064583 | U19: =+C19+F19+I19+L19+O19+R19 -> 114461 | V19: =+T19+U19 -> 1179044
A21: Total Direct Costs | B21: =SUM(B7:B19) -> 203997 | C21: =SUM(C7:C19) -> 8646 | D21: =SUM(D7:D19) -> 212643 | E21: =SUM(E7:E19) -> 1484573 | F21: =SUM(F7:F19)-1 -> 43051 | G21: =SUM(G7:G19) -> 1527625 | H21: =SUM(H7:H19)+1 -> 1721346 | I21: =SUM(I7:I19) -> 207712 | J21: =SUM(J7:J19) -> 1929057 | K21: =SUM(K7:K19)-1 -> 1679966 | L21: =SUM(L7:L19) -> 160286 | M21: =SUM(M7:M19) -> 1840253 | N21: =SUM(N7:N19) -> 2308569 | O21: =SUM(O7:O19) -> 12994 | P21: =SUM(P7:P19)-1 -> 2321562 | Q21: =SUM(Q7:Q19) -> 1052118 | R21: =SUM(R7:R19) -> 8448 | S21: =SUM(S7:S19) -> 1060566 | T21: =SUM(T7:T19) -> 8450569 | U21: =SUM(U7:U19) -> 441138 | V21: =SUM(V7:V19) -> 8891707
A22: Indirect Costs | B22: 20400 | C22: 0 | D22: =+B22+C22 -> 20400 | E22: 111259 | F22: 0 | G22: =+E22+F22 -> 111259 | H22: 125832 | I22: 12993 | J22: =+H22+I22 -> 138825 | K22: 161497 | L22: 16029 | M22: =+K22+L22-1 -> 177525 | N22: 154196 | O22: 1299 | P22: 155495 | Q22: 82515 | R22: 845 | S22: 83140 | T22: 655698 | U22: 31166 | V22: =+T22+U22 -> 686864
A23: Total | B23: =+B21+B22 -> 224397 | C23: =+C21+C22 -> 8646 | D23: =+D21+D22 -> 233043 | E23: =+E21+E22 -> 1595832 | F23: =+F21+F22 -> 43051 | G23: =+G21+G22 -> 1638884 | H23: =+H21+H22 -> 1847178 | I23: =+I21+I22-1 -> 220704 | J23: =+J21+J22 -> 2067882 | K23: =+K21+K22 -> 1841463 | L23: =+L21+L22 -> 176315 | M23: =+M21+M22 -> 2017778 | N23: =+N21+N22-1 -> 2462764 | O23: =+O21+O22 -> 14293 | P23: =+P21+P22 -> 2477057 | Q23: =+Q21+Q22 -> 1134633 | R23: =+R21+R22 -> 9293 | S23: =+S21+S22 -> 1143706 | T23: =+T21+T22-1 -> 9106266 | U23: =+U21+U22 -> 472304 | V23: =+V21+V22-1 -> 9578570

Sheet 800-FC - Mod7 (2)
A2: 800-FUNDACION CARVAJAL | F2: 800-FUNDACION CARVAJAL - Modification No. 7 - Cost Extension and Budget Realignment
B3: Categories | C3: Amount | D3: Leverage | E3: Total | G3: Categories | H3: Amount | I3: Leverage | J3: Total | L3: % representativo sobre el total del subacuerdo (USAID Funds) | N3: % representativo sobre el total del subacuerdo (Leverage Funds) | P3: % representativo sobre el total del subacuerdo (TOTAL)
B4: Categorías | C4: Monto | D4: Apalancamiento | G4: Categorías | H4: Monto | I4: Apalancamiento | L4: Inicial | M4: Mod.7 | N4: Inicial | O4: Mod.7 | P4: Inicial | Q4: Mod.7
A5: 1. | B5: Personnel | C5: 2847676 | D5: 66152 | E5: =+C5+D5 -> 2913828 | F5: 1. | G5: Personnel | H5: ='800-FC - Consolidated Details'!AM77 -> 2858976.9 | I5: ='800-FC - Consolidated Details'!AN77 -> 65374.663 | J5: ='800-FC - Consolidated Details'!AO77 -> 2924351.5 | K5: =IF(J5>=E5,"SUBE","BAJA") -> SUBE | L5: =+$C5*100/$C$23 -> 32.783661 | M5: =+$H5*100/$H$23 -> 31.395712 | N5: =+$D5*100/$D$23 -> 20.936496 | O5: =+$I5*100/$I$23 -> 13.841655 | P5: =+$E5*100/$E$23 -> 32.367839 | Q5: =+$J5*100/$J$23 -> 30.530146
B6: Personal | G6: Personal
A7: 2. | B7: Fringe Benefits | C7: 1310790 | D7: 29095 | E7: =+C7+D7 -> 1339885 | F7: 2. | G7: Fringe Benefits | H7: ='800-FC - Consolidated Details'!AM81 -> 1383962.7 | I7: ='800-FC - Consolidated Details'!AN81 -> 24339.97 | J7: ='800-FC - Consolidated Details'!AO81 -> 1408302.7 | K7: =IF(J7>=E7,"SUBE","BAJA") -> SUBE | L7: =+$C7*100/$C$23 -> 15.090374 | M7: =+$H7*100/$H$23 -> 15.197917 | N7: =+$D7*100/$D$23 -> 9.2082984 | O7: =+$I7*100/$I$23 -> 5.1534564 | P7: =+$E7*100/$E$23 -> 14.88392 | Q7: =+$J7*100/$J$23 -> 14.702639
B8: Beneficios | G8: Beneficios
A9: 3. | B9: Travel | C9: 188410 | D9: 0 | E9: =+C9+D9 -> 188410 | F9: 3. | G9: Travel | H9: ='800-FC - Consolidated Details'!AM104 -> 322692 | I9: ='800-FC - Consolidated Details'!AN104 -> 3999.26 | J9: ='800-FC - Consolidated Details'!AO104 -> 326691.26 | K9: =IF(J9>=E9,"SUBE","BAJA") -> SUBE | L9: =+$C9*100/$C$23 -> 2.1690563 | M9: =+$H9*100/$H$23 -> 3.5436261 | N9: =+$D9*100/$D$23 -> 0 | O9: =+$I9*100/$I$23 -> 0.84675585 | P9: =+$E9*100/$E$23 -> 2.0929254 | Q9: =+$J9*100/$J$23 -> 3.4106473
B10: Viajes | G10: Viajes
A11: 4. | B11: Equipment | C11: 50000 | D11: 0 | E11: =+C11+D11 -> 50000 | F11: 4. | G11: Equipment | H11: ='800-FC - Consolidated Details'!AM106 -> 0 | I11: ='800-FC - Consolidated Details'!AN106 -> 0 | J11: ='800-FC - Consolidated Details'!AO106 -> 0 | K11: =IF(J11>=E11,"SUBE","BAJA") -> BAJA | L11: =+$C11*100/$C$23 -> 0.57562133 | M11: =+$H11*100/$H$23 -> 0 | N11: =+$D11*100/$D$23 -> 0 | O11: =+$I11*100/$I$23 -> 0 | P11: =+$E11*100/$E$23 -> 0.55541781 | Q11: =+$J11*100/$J$23 -> 0
B12: Equipo | G12: Equipo
A13: 5. | B13: Supplies | C13: 69389 | D13: 0 | E13: =+C13+D13 -> 69389 | F13: 5. | G13: Supplies | H13: ='800-FC - Consolidated Details'!AM111 -> 67039.9 | I13: ='800-FC - Consolidated Details'!AN111 -> 2639.18 | J13: ='800-FC - Consolidated Details'!AO111 -> 69679.08 | K13: =IF(J13>=E13,"SUBE","BAJA") -> SUBE | L13: =+$C13*100/$C$23 -> 0.79883577 | M13: =+$H13*100/$H$23 -> 0.73619531 | N13: =+$D13*100/$D$23 -> 0 | O13: =+$I13*100/$I$23 -> 0.55878865 | P13: =+$E13*100/$E$23 -> 0.77079773 | Q13: =+$J13*100/$J$23 -> 0.72744759
B14: Suministros | G14: Suministros
A15: 6. | B15: Contractual | C15: 3113105 | D15: 0 | E15: =+C15+D15 -> 3113105 | F15: 6. | G15: Contractual | H15: ='800-FC - Consolidated Details'!AM132 -> 2753313.3 | I15: ='800-FC - Consolidated Details'!AN132 -> 230324.4 | J15: ='800-FC - Consolidated Details'!AO132 -> 2983637.7 | K15: =IF(J15>=E15,"SUBE","BAJA") -> BAJA | L15: =+$C15*100/$C$23 -> 35.839393 | M15: =+$H15*100/$H$23 -> 30.235372 | N15: =+$D15*100/$D$23 -> 0 | O15: =+$I15*100/$I$23 -> 48.766155 | P15: =+$E15*100/$E$23 -> 34.581479 | Q15: =+$J15*100/$J$23 -> 31.149092
B16: Contractual | G16: Contractual
A17: 7. | B17: Other Direct Costs | C17: 594509 | D17: 191995 | E17: =+C17+D17 -> 786504 | F17: 7. | G17: Other Direct Costs | H17: ='800-FC - Consolidated Details'!AM170 -> 1064583.8 | I17: ='800-FC - Consolidated Details'!AN170 -> 114460.72 | J17: ='800-FC - Consolidated Details'!AO170 -> 1179044.6 | K17: =IF(J17>=E17,"SUBE","BAJA") -> SUBE | L17: =+$C17*100/$C$23 -> 6.8442412 | M17: =+$H17*100/$H$23 -> 11.690674 | N17: =+$D17*100/$D$23 -> 60.764642 | O17: =+$I17*100/$I$23 -> 24.234554 | P17: =+$E17*100/$E$23 -> 8.7367666 | Q17: =+$J17*100/$J$23 -> 12.309191
B18: Otros Costos Directos | G18: Otros Costos Directos
A19: 8. | B19: Total Direct Costs | C19: =+SUM(C5:C18) -> 8173879 | D19: =+SUM(D5:D18) -> 287242 | E19: =+C19+D19 -> 8461121 | F19: 8. | G19: Total Direct Costs | H19: =+SUM(H5:H18) -> 8450568.6 | I19: =+SUM(I5:I18) -> 441138.19 | J19: =+SUM(J5:J18) -> 8891706.8 | K19: =IF(J19>=E19,"SUBE","BAJA") -> SUBE | L19: =+$C19*100/$C$23 -> 94.101182 | M19: =+$H19*100/$H$23 -> 92.799497 | N19: =+$D19*100/$D$23 -> 90.909436 | O19: =+$I19*100/$I$23 -> 93.401365 | P19: =+$E19*100/$E$23 -> 93.989146 | Q19: =+$J19*100/$J$23 -> 92.829163
B20: Valor Total Costos Directos | G20: Valor Total Costos Directos
A21: 9. | B21: Indirect Costs | C21: 512388 | D21: 28724 | E21: =+C21+D21 -> 541112 | F21: 9. | G21: Indirect Costs | H21: ='800-FC - Consolidated Details'!AM172 -> 655696.94 | I21: ='800-FC - Consolidated Details'!AN172 -> 31165.602 | J21: ='800-FC - Consolidated Details'!AO172 -> 686863.66 | K21: =IF(J21>=E21,"SUBE","BAJA") -> SUBE | L21: =+$C21*100/$C$23 -> 5.8988293 | M21: =+$H21*100/$H$23 -> 7.2005032 | N21: =+$D21*100/$D$23 -> 9.0908803 | O21: =+$I21*100/$I$23 -> 6.5986347 | P21: =+$E21*100/$E$23 -> 6.0108649 | Q21: =+$J21*100/$J$23 -> 7.1708369
B22: Costos Indirectos | G22: Costos Indirectos
A23: 10. | B23: Total Costs | C23: =+C19+C21-1 -> 8686266 | D23: =+D19+D21-1 -> 315965 | E23: =+E19+E21-1 -> 9002232 | F23: 10. | G23: Total Costs | H23: =+H19+H21 -> 9106265.6 | I23: =+I19+I21 -> 472303.8 | J23: =+J19+J21 -> 9578570.5 | K23: =IF(J23>=E23,"SUBE","BAJA") -> SUBE | L23: =+$C23*100/$C$23 -> 100 | M23: =+$H23*100/$H$23 -> 100 | N23: =+$D23*100/$D$23 -> 100 | O23: =+$I23*100/$I$23 -> 100 | P23: =+$E23*100/$E$23 -> 100 | Q23: =+$J23*100/$J$23 -> 100
B24: Valor Total | G24: Valor Total
A28: 800-FUNDACION CARVAJAL - INITIAL BUDGET
B29: Categories | C29: Amount | D29: Leverage | E29: Total | F29: Expenditures Amount up to Dec/23 | G29: Expenditures Leverage up to Dec/23 | H29: Total Expenditures up to Dec/23 | I29: Remaining USAID | J29: Remaining Leverage | K29: Total Remaining
B30: Categorías | C30: Monto | D30: Apalancamiento | F30: Monto Ejecutado | G30: Apalancamiento Reportado | H30: Apalancamiento Reportado | I30: Saldo USAID | J30: Saldo Apalancamiento | K30: Saldo Total
A31: 1. | B31: Personnel | C31: 2847676 | D31: 66152 | E31: =+C31+D31 -> 2913828 | F31: ='800-FC - Consolidated Details'!AF77 -> 1107253.8 | G31: ='800-FC - Consolidated Details'!AG77 -> 32437.34 | H31: =+F31+G31 -> 1139691.1 | I31: =+C31-F31 -> 1740422.2 | J31: =+D31-G31 -> 33714.66 | K31: =+E31-H31 -> 1774136.9
B32: Personal
A33: 2. | B33: Fringe Benefits | C33: 1310790 | D33: 29095 | E33: =+C33+D33 -> 1339885 | F33: ='800-FC - Consolidated Details'!AF81 -> 492962.7 | G33: ='800-FC - Consolidated Details'!AG81 -> 8339.97 | H33: =+F33+G33 -> 501302.67 | I33: =+C33-F33 -> 817827.3 | J33: =+D33-G33 -> 20755.03 | K33: =+E33-H33 -> 838582.33
B34: Beneficios
A35: 3. | B35: Travel | C35: 188410 | D35: 0 | E35: =+C35+D35 -> 188410 | F35: ='800-FC - Consolidated Details'!AF104 -> 132644 | G35: ='800-FC - Consolidated Details'!AG104 -> 3549.26 | H35: =+F35+G35 -> 136193.26 | I35: =+C35-F35 -> 55766 | J35: =+D35-G35 -> -3549.26 | K35: =+E35-H35 -> 52216.74
B36: Viajes
A37: 4. | B37: Equipment | C37: 50000 | D37: 0 | E37: =+C37+D37 -> 50000 | F37: ='800-FC - Consolidated Details'!AF107 -> 0 | G37: ='800-FC - Consolidated Details'!AG107 -> 0 | H37: =+F37+G37 -> 0 | I37: =+C37-F37 -> 50000 | J37: =+D37-G37 -> 0 | K37: =+E37-H37 -> 50000
B38: Equipo
A39: 5. | B39: Supplies | C39: 69389 | D39: 0 | E39: =+C39+D39 -> 69389 | F39: ='800-FC - Consolidated Details'!AF111 -> 59050.3 | G39: ='800-FC - Consolidated Details'!AG111 -> 2639.18 | H39: =+F39+G39 -> 61689.48 | I39: =+C39-F39 -> 10338.7 | J39: =+D39-G39 -> -2639.18 | K39: =+E39-H39 -> 7699.52
B40: Suministros
A41: 6. | B41: Contractual | C41: 3113105 | D41: 0 | E41: =+C41+D41 -> 3113105 | F41: ='800-FC - Consolidated Details'!AF132 -> 1272971.5 | G41: ='800-FC - Consolidated Details'!AG132 -> 151747.4 | H41: =+F41+G41 -> 1424718.9 | I41: =+C41-F41 -> 1840133.5 | J41: =+D41-G41 -> -151747.4 | K41: =+E41-H41 -> 1688386.1
B42: Contractual
A43: 7. | B43: Other Direct Costs | C43: 594509 | D43: 191995 | E43: =+C43+D43 -> 786504 | F43: ='800-FC - Consolidated Details'!AF170 -> 345033.98 | G43: ='800-FC - Consolidated Details'!AG170 -> 60695.72 | H43: =+F43+G43 -> 405729.7 | I43: =+C43-F43 -> 249475.02 | J43: =+D43-G43 -> 131299.28 | K43: =+E43-H43 -> 380774.3
B44: Otros Costos Directos
A45: 8. | B45: Total Direct Costs | C45: =+C31+C33+C35+C37+C39+C41+C43 -> 8173879 | D45: =+D31+D33+D35+D37+D39+D41+D43 -> 287242 | E45: =+C45+D45 -> 8461121 | F45: =+F31+F33+F35+F37+F39+F41+F43 -> 3409916.3 | G45: =+G31+G33+G35+G37+G39+G41+G43 -> 259408.87 | H45: =+F45+G45 -> 3669325.2 | I45: =+C45-F45 -> 4763962.7 | J45: =+J31+J33+J35+J37+J39+J41+J43 -> 27833.13 | K45: =+K31+K33+K35+K37+K39+K41+K43 -> 4791795.8
B46: Valor Total Costos Directos
A47: 9. | B47: Indirect Costs | C47: 512388 | D47: 28724 | E47: =+C47+D47 -> 541112 | F47: ='800-FC - Consolidated Details'!AF172 -> 257490.82 | G47: ='800-FC - Consolidated Details'!AG172 -> 12992.67 | H47: =+F47+G47 -> 270483.49 | I47: =+C47-F47 -> 254897.18 | J47: =+D47-G47 -> 15731.33 | K47: =+E47-H47 -> 270628.51
B48: Costos Indirectos
A49: 10. | B49: Total Costs | C49: =+C45+C47-1 -> 8686266 | D49: =+D45+D47-1 -> 315965 | E49: =+E45+E47-1 -> 9002232 | F49: =+F45+F47-1 -> 3667406.1 | G49: =+G45+G47-1 -> 272400.54 | H49: =+F49+G49 -> 3939806.7 | I49: =+I45+I47-1 -> 5018858.9 | J49: =+J45+J47-1 -> 43563.46 | K49: =+K45+K47-1 -> 5062423.3
B50: Valor Total
A52: 800-FUNDACION CARVAJAL - Modification No. 7 - Budget Realignment
B53: Categories | C53: Amount | D53: Leverage | E53: Total | F53: Expenditures Amount up to Dec/23 | G53: Expenditures Leverage up to Dec/23 | H53: Total Expenditures up to Dec/23 | I53: Remaining USAID | J53: Remaining Leverage | K53: Total Remaining
B54: Categorías | C54: Monto | D54: Apalancamiento | F54: Monto Ejecutado hasta Dic/23 | G54: Apalancamiento Reportado hasta Dic/23 | H54: Total Ejecución hasta Dic/23 | I54: Saldo USAID | J54: Saldo Apalancamiento | K54: Saldo Total
A55: 1. | B55: Personnel | C55: 2858976.9 | D55: 65374.663 | E55: 2924351.5 | F55: 1107253.8 | G55: 32437.34 | H55: 1139691.1 | I55: =+C55-F55 -> 1751723.1 | J55: =+D55-G55 -> 32937.323 | K55: =+E55-H55 -> 1784660.4 | S55: El valor descrito de ejecución de fondes de FC está correcto
B56: Personal | S56: El valor en la tabla de ejecución de fondos USAID está correcto
A57: 2. | B57: Fringe Benefits | C57: 1383962.7 | D57: 24340 | E57: 1406102.7 | F57: 492962.7 | G57: 8339.97 | H57: 501302.67 | I57: =+C57-F57 -> 891000 | J57: =+D57-G57 -> 16000.03 | K57: =+E57-H57 -> 904800 | S57: En la carta no se mencionan temas de leverage
B58: Beneficios
A59: 3. | B59: Travel | C59: 322692 | D59: 3999.26 | E59: 326691.26 | F59: 132644 | G59: 3549.26 | H59: 136193.26 | I59: =+C59-F59 -> 190048 | J59: =+D59-G59 -> 450 | K59: =+E59-H59 -> 190498
B60: Viajes
A61: 4. | B61: Equipment | C61: 0 | D61: 0 | E61: 0 | F61: 0 | G61: 0 | H61: 0 | I61: =+C61-F61 -> 0 | J61: =+D61-G61 -> 0 | K61: =+E61-H61 -> 0
B62: Equipo
A63: 5. | B63: Supplies | C63: 67039.9 | D63: 2639.18 | E63: 69679.08 | F63: 59050.3 | G63: 2639.18 | H63: 61689.48 | I63: =+C63-F63 -> 7989.6 | J63: =+D63-G63 -> 0 | K63: =+E63-H63 -> 7989.6
B64: Suministros
A65: 6. | B65: Contractual | C65: 2753313.8 | D65: 230324 | E65: 2938534.5 | F65: 1272971.5 | G65: 151747.4 | H65: 1424718.9 | I65: =+C65-F65 -> 1480342.3 | J65: =+D65-G65 -> 78576.6 | K65: =+E65-H65 -> 1513815.6
B66: Contractual
A67: 7. | B67: Other Direct Costs | C67: 1064583.8 | D67: 114460.72 | E67: 1179044.6 | F67: 345033.98 | G67: 60695.72 | H67: 405729.7 | I67: =+C67-F67 -> 719549.86 | J67: =+D67-G67 -> 53765 | K67: =+E67-H67 -> 773314.86
B68: Otros Costos Directos
A69: 8. | B69: Total Direct Costs | C69: 8450569.1 | D69: 441138 | E69: 8844403.6 | F69: 3409916.3 | G69: 259408.87 | H69: 3669325.2 | I69: =+C69-F69 -> 5040652.8 | J69: =+D69-G69 -> 181729.13 | K69: =+E69-H69 -> 5175078.5
B70: Valor Total Costos Directos
A71: 9. | B71: Indirect Costs | C71: 655697 | D71: 31166 | E71: 687219.68 | F71: 257490.82 | G71: 12992.67 | H71: 270483.49 | I71: =+C71-F71 -> 398206.18 | J71: =+D71-G71 -> 18173.33 | K71: =+E71-H71 -> 416736.18
B72: Costos Indirectos
A73: 10. | B73: Total Costs | C73: =+C69+C71 -> 9106266.1 | D73: =+D69+D71 -> 472304 | E73: =+E69+E71 -> 9531623.3 | F73: 3667406.1 | G73: 272400.54 | H73: 3939806.7 | I73: =+I69+I71 -> 5438859 | J73: =+D73-G73 -> 199903.46 | K73: =+E73-H73 -> 5591816.6
B74: Valor Total
B78: TRACKER - OBLIGATED AMOUNTS (According with modifications):
B80: Line Items | C80: Inicial | D80: Modificacion N° 1 | E80: Modification N° 2 | F80: Modification N° 3 | G80: Modification N° 4 | H80: Modification N° 5 | I80: Modification N° 6 | J80: Total Obligated Line Items (After mod 6) | K80: Modification N° 7 | L80: New Obligated Line Items (after mod 7) | M80: REMAINING USD (After Mod. 7)
C81: Original Obligated Amount | D81: Actual Obligated Amount | E81: Increase Obligated Amount | F81: Increase Obligated Amount | G81: Increase Obligated Amount | H81: Increase Obligated Amount | I81: Increase Obligated Amount | K81: Budget Realigment
B82: Personnel | C82: 533897 | D82: 0 | E82: 135000 | F82: 0 | G82: 190966.51 | H82: 266298 | I82: 425365 | J82: =+C82+D82+E82+F82+G82+H82+I82 -> 1551526.5 | K82: 2858977 | L82: =+J82 -> 1551526.5 | M82: =+K82-L82 -> 1307450.5
B83: Fringe Benefits | C83: 241720 | D83: 0 | E83: 46711 | F83: 0 | G83: 104145 | H83: 125000 | I83: 187268 | J83: =+C83+D83+E83+F83+G83+H83+I83 -> 704844 | K83: 1383963 | L83: =+J83 -> 704844 | M83: =+K83-L83 -> 679119
B84: Travel | C84: 31565 | D84: 30000 | E84: 31105.55 | F84: 5100 | G84: 26290.9 | H84: 50000 | I84: 18679 | J84: =+C84+D84+E84+F84+G84+H84+I84 -> 192740.45 | K84: 322692 | L84: =+J84 -> 192740.45 | M84: =+K84-L84 -> 129951.55
B85: Equipment | C85: 50000 | D85: 0 | F85: 0 | G85: 0 | I85: 0 | J85: =+C85+D85+E85+F85+G85+H85+I85 -> 50000 | K85: 0 | L85: =+J85 -> 50000 | M85: =+K85-L85 -> -50000
B86: Supplies | C86: 41854 | D86: 20000 | F86: 0 | G86: 776.2 | I86: 0 | J86: =+C86+D86+E86+F86+G86+H86+I86 -> 62630.2 | K86: 67040 | L86: =+J86 -> 62630.2 | M86: =+K86-L86 -> 4409.8
B87: Contractual
B88: Subwards to Local Implementing Partners | C88: 300000 | D88: 330000 | E88: 0 | F88: =143225.6+974.4 -> 144200 | G88: 36206.15 | H88: 166672 | I88: 0 | J88: =+C88+D88+E88+F88+G88+H88+I88 -> 977078.15 | K88: 1893538 | L88: =+J88 -> 977078.15 | M88: =+K88-L88 -> 916459.85
B89: Consultants | C89: 4200 | D89: 197519 | E89: 48547.34 | F89: 60000 | G89: 87609.47 | H89: 54000 | I89: 96000 | J89: =+C89+D89+E89+F89+G89+H89+I89 -> 547875.81 | K89: 859775 | L89: =+J89 -> 547875.81 | M89: =+K89-L89 -> 311899.19
B90: Other Direct Costs | C90: 131800 | D90: 10000 | E90: 25000 | F90: 12900 | G90: =113150+9098 -> 122248 | H90: 85000 | I90: 90095 | J90: =+C90+D90+E90+F90+G90+H90+I90 -> 477043 | K90: 1064584 | L90: =+J90 -> 477043 | M90: =+K90-L90 -> 587541
B91: Total Direct Costs | C91: =SUM(C82:C90) -> 1335036 | D91: =SUM(D82:D90) -> 587519 | E91: =+SUM(E82:E90) -> 286363.89 | F91: =+SUM(F82:F90) -> 222200 | G91: =+SUM(G82:G90) -> 568242.23 | H91: =+SUM(H82:H90) -> 746970 | I91: =+SUM(I82:I90) -> 817407 | J91: =+SUM(J82:J90) -> 4563738.1 | K91: =+SUM(K82:K90) -> 8450569 | L91: =+J91 -> 4563738.1 | M91: =+K91-L91 -> 3886830.9
B92: Indirect Costs | C92: 98505 | D92: =30752 -> 30752 | E92: =(E91-E88-E85)*10% -> 28636.389 | F92: =(F91-F88-F85)*10% -> 7800 | G92: =ROUND((G91-G88-G85)*10%,2) -> 53203.61 | H92: =ROUND((H91-H88-H85)*10%,0) -> 58030 | I92: =ROUND((I91-I88-I85)*10%,0) -> 81741 | J92: =+C92+D92+E92+F92+G92+H92+I92 -> 358668 | K92: 655697 | L92: =+J92 -> 358668 | M92: =+K92-L92 -> 297029
B93: Total | C93: =SUM(C91:C92) -> 1433541 | D93: =SUM(D91:D92) -> 618271 | E93: =+E91+E92 -> 315000.28 | F93: =+F91+F92 -> 230000 | G93: =+G91+G92 -> 621445.84 | H93: =+H91+H92 -> 805000 | I93: =+I91+I92 -> 899148 | J93: =+J91+J92 -> 4922406.1 | K93: =+K91+K92 -> 9106266 | L93: =+J93 -> 4922406.1 | M93: =+K93-L93 -> 4183859.9
L94: =+L93+M93 -> 9106266
