Workbook
Name EmployeeNamesDefaultRange: #REF!
Name EmployeeNamesDefaultRange: #REF!
Name EmployeeValuesDefaultRange: #REF!
Name EmployeeValuesDefaultRange: #REF!
Name SubTotalDefaultRange: #REF!
Name SubTotalDefaultRange: #REF!
Name TotalDefaultRange: #REF!
Name TotalDefaultRange: #REF!

Sheet Comparison Overview
C1: Ancilliary Quote Comparison Prepared for Partners of the Americas Effective Date: 08/01/2023
D4: Current | E4: Renewal | F4: Alternate | H4: Alternate | J4: Alternate
D5: The Standard | E5: The Standard | F5: Principal | H5: Guardian | J5: MetLife
C6: Dental | D6: ='Dental '!D22 -> 2235 | E6: ='Dental '!E22 -> 2435.96 | F6: ='Dental '!G22 -> 2206.47 | H6: ='Dental '!I22 -> 2167.95 | I6: ='Dental '!J22 -> 2235 | J6: ='Dental '!K22 -> 2024.5 | K6: ='Dental '!L22 -> 2320.01
C7: Vision | D7: =Vision!D30 -> 316.6 | E7: =Vision!E30 -> 339.28 | F7: =Vision!G30 -> 278.98 | H7: =Vision!I30 -> 253.28 | J7: =Vision!K30 -> 314.48
C8: Life | D8: ='Life '!C19 -> 467.25 | E8: =D8-0.05*D8 -> 443.8875 | F8: ='Life '!G19 -> 462.8 | H8: ='Life '!I19 -> 445 | J8: ='Life '!K19 -> 436.1
C9: LTD | D9: ='LTD '!C17 -> 463.5495 | E9: =D9 -> 463.5495 | F9: ='LTD '!G17 -> 478.5255 | H9: ='LTD '!I17 -> 478.5255 | J9: ='LTD '!K17 -> 513.61737
C10: STD | E10: ='STD '!C18 -> 1325.5341 | F10: ='STD '!G18 -> 1326.083 | H10: ='STD '!E18 -> 1371.87 | J10: ='STD '!I18 -> 1211.7655
C11: Total Monthly | D11: =SUM(D6:D10) -> 3482.3995 | E11: =SUM(E6:E10) -> 5008.2111 | F11: =SUM(F6:F10) -> 4752.8585 | G11: =SUM(F7:G10) +F6 -> 4752.8585 | H11: =SUM(H6:H10) -> 4716.6255 | I11: =SUM(H7:I10)+I6 -> 4783.6755 | J11: =SUM(J7:K10)+J6 -> 4500.4629 | K11: =SUM(J7:K10)+K6 -> 4795.9729
C12: Total Annual | D12: =SUM(D11*12) -> 41788.794 | E12: =SUM(E11*12) -> 60098.533 | F12: =SUM(F11*12) -> 57034.302 | G12: =SUM(G11*12) -> 57034.302 | H12: =SUM(H11*12) -> 56599.506 | I12: =SUM(I11*12) -> 57404.106 | J12: =SUM(J11*12) -> 54005.554 | K12: =SUM(K11*12) -> 57551.674
C13: % Difference | D13: - | E13: =E14/D12 -> 0.4381495 | F13: =F14/D12 -> 0.36482288 | G13: =G14/E12 -> 0.25367521 | H13: =H14/D12 -> 0.35441827 | I13: =I14/E12 -> 0.2598285 | J13: =J14/F12 -> 0.21420023 | K13: =K14/G12 -> 0.27637544
C14: Annual $ Difference | D14: - | E14: =E12-$D$12 -> 18309.739 | F14: =F12-$D$12 -> 15245.508 | G14: =G12-$D$12 -> 15245.508 | H14: =H12-$D$12 -> 14810.712 | I14: =I12-$D$12 -> 15615.312 | J14: =J12-$D$12 -> 12216.76 | K14: =K12-$D$12 -> 15762.88
C15: Notes | E15: If STD is added there is a 5% discount for LTD.

Sheet Dental 
B1: Ancilliary Quote Comparison Prepared for Partners of the Americas Effective Date: 08/01/2023
B3: 80212
C4: Current | E4: Renewal | G4: Alternative | I4: Alternative | K4: Alternative
B5: Dental | C5: The Standard | E5: The Standard | G5: Principal | I5: Guardian | K5: MetLife
B7: In Network/ Out of Network | C7: In Network | D7: Out of network | E7: In Network | F7: Out of network | G7: In Network | H7: Out of Network | I7: In/ Out | J7: In/ Out | K7: In Network | L7: Out of Network
C8: Fee Schedule | D8: UCR 90% | E8: Fee Schedule | F8: 90th | G8: 90th | H8: 90th | I8: Fee Schedule | J8: 90th | K8: 90th | L8: 90th
B9: Preventative | C9: 1 | D9: 1 | E9: 1 | F9: 1 | G9: 1 | H9: 1 | I9: 1 | J9: 1 | K9: 1 | L9: 1
B10: Basic | C10: 0.8 | D10: 0.8 | E10: 0.8 | F10: 0.8 | G10: 0.8 | H10: 0.8 | I10: 0.8 | J10: 80%/60% | K10: 0.8 | L10: 0.8
B11: Major | C11: 0.5 | D11: 0.5 | E11: 0.5 | F11: 0.5 | G11: 0.5 | H11: 0.5 | I11: 0.5 | J11: 80%/60% | K11: 0.5 | L11: 0.8
B12: Orthodontia | C12: None | D12: None | E12: None | F12: None | G12: None | H12: None | I12: None | J12: None | K12: None | L12: None
B13: Deductible (Ind/Family) | C13: $50 individual/ $150 Family | E13: $50 individual/ $150 Family | G13: $50 individual/ $100 Family | I13: $50 individual/ $150 Family | K13: $50 individual/ $150 Family
B14: Calendar year Maximum | C14: 1500 | D14: 1500 | E14: 1500 | F14: 1500 | G14: 1500 | H14: 1500 | I14: 1500 | J14: 1500 | K14: 2000 | L14: 2000
C16: Current | E16: Renewal | G16: Alternative | I16: Alternative | K16: Alternative
C17: Lives | D17: Premium | E17: Premium | G17: Premium | I17: Premium | K17: Premium
B18: Employee Only | C18: 28 | D18: 37 | E18: 40.32 | G18: 36.52 | I18: 35.89 | J18: 37 | K18: 33.53 | L18: 39.81
B19: Employee + Spouse | C19: 8 | D19: 75 | E19: 81.76 | G19: 74.06 | I19: 72.75 | J19: 75 | K19: 67.92 | L19: 77.97
B20: Employee + Child(ren) | C20: 1 | D20: 87 | E20: 94.84 | G20: 85.91 | I20: 84.39 | J20: 87 | K20: 78.78 | L20: 79.85
B21: Employee + Family | C21: 4 | D21: 128 | E21: 139.52 | G21: 126.38 | I21: 124.16 | J21: 128 | K21: 115.88 | L21: 125.43
B22: Monthly premium | D22: =D18*$C$18+D19*$C$19+D20*$C$20+D21*$C$21 -> 2235 | E22: =E18*$C$18+E19*$C$19+E20*$C$20+E21*$C$21 -> 2435.96 | G22: =G18*$C$18+G19*$C$19+G20*$C$20+G21*$C$21 -> 2206.47 | I22: =I18*$C$18+I19*$C$19+I20*$C$20+I21*$C$21 -> 2167.95 | J22: =J18*$C$18+J19*$C$19+J20*$C$20+J21*$C$21 -> 2235 | K22: =K18*$C$18+K19*$C$19+K20*$C$20+K21*$C$21 -> 2024.5 | L22: =L18*$C$18+L19*$C$19+L20*$C$20+L21*$C$21 -> 2320.01
B23: Total Annual Premium | C23: =D22*12 -> 26820 | E23: =E22*12 -> 29231.52 | G23: =G22*12 -> 26477.64 | I23: =I22*12 -> 26015.4 | J23: =J22*12 -> 26820 | K23: =K22*12 -> 24294 | L23: =L22*12 -> 27840.12
B24: Monthly Change from Current | E24: =E22-$D$22 -> 200.96 | G24: =G22-$D$22 -> -28.53 | I24: =I22-$D$22 -> -67.05 | J24: =J22-$D$22 -> 0 | K24: =K22-$D$22 -> -210.5 | L24: =L22-$D$22 -> 85.01
B25: Annual Change in Premium | E25: =E23-$C$23 -> 2411.52 | G25: =G23-$C$23 -> -342.36 | I25: =I23-$C$23 -> -804.6 | J25: =J23-$C$23 -> 0 | K25: =K23-$C$23 -> -2526 | L25: =L23-$C$23 -> 1020.12
B26: Percentage Change | E26: =E24/$D$22 -> 0.089914989 | G26: =G24/$D$22 -> -0.012765101 | I26: =I24/$D$22 -> -0.03 | J26: =J24/$D$22 -> 0 | K26: =K24/$D$22 -> -0.094183445 | L26: =L24/$D$22 -> 0.038035794

Sheet Vision
B1: Ancilliary Quote Comparison Prepared for Partners of the Americas Effective Date: 08/01/2023
B3: 80212
C4: Current | E4: Renewal | G4: Alternative | I4: Alternative | K4: Alternative
B5: Vision | C5: The Standard | E5: The Standard | G5: Principal | I5: Guardian | K5: MetLife
C7: In Network | D7: Out of Network | E7: In Network | F7: Out of Network | G7: In Network | H7: Out of Network | I7: In Network | J7: Out of Network | K7: In Network | L7: Out of Network
B8: Eye Exam | C8: $10 Copay | D8: $35 Allowance | E8: $10 Copay | F8: $35 Allowance | G8: $10 Copay | H8: $45 Allowance | I8: $10 Copay | J8: $39 Allowance | K8: $10 Copay | L8: $45 Allowance
B9: Frequency | C9: Every 12 months | E9: Every 12 months | G9: Every 12 months | I9: Every 12 months | K9: Every 12 months
B10: Lenses Allowance
B11: Single Vision Lenses | C11: $25 Copay | D11: $25 Allowance | E11: $25 Copay | F11: $25 Allowance | G11: $25 Copay | H11: $30 Allowance | I11: $25 Copay | J11: $23 Allowance | K11: $25 Copay | L11: $30 Allowance
B12: Bifocal Lenses | C12: $25 Copay | D12: $40 Allowance | E12: $25 Copay | F12: $40 Allowance | G12: $25 Copay | H12: $50 Allowance | I12: $25 Copay | J12: $37 Allowance | K12: $25 Copay | L12: $50 Allowance
B13: Trifocal Lenses | C13: $25 Copay | D13: $55 Allowance | E13: $25 Copay | F13: $55 Allowance | G13: $25 Copay | H13: $65 Allowance | I13: $25 Copay | J13: $49 Allowance | K13: $25 Copay | L13: $65 Allowance
B14: Lenticular Lenses | C14: 20% Discount | D14: Not Covered | E14: 20% Discount | F14: Not Covered | G14: $25 Copay | H14: $100 Allowance | I14: $25 Copay | J14: $64 Allowance | K14: $25 Copay | L14: $100 Allowance
B15: Frequency | C15: Every 12 months | E15: Every 12 months | G15: Every 12 months | I15: Every 12 months | K15: Every 12 months
B17: Frame Allowance | C17: $130 Allowance | D17: $65 Allowance | E17: $130 Allowance | F17: $65 Allowance | G17: $130 Allowance | H17: $70 Allowance | I17: $130 Allowance | J17: $46 Allowance | K17: $130 Allowance | L17: $70 Allowance
B18: Frequency | C18: Every 12 months | E18: Every 12 months | G18: Every 24 months | I18: Every 12 months | K18: Every 12 months
B19: Contact Lenses
B20: Elective | C20: $130 Allowance | D20: $104 Allowance | E20: $130 Allowance | F20: $104 Allowance | G20: $130 Allowance | H20: $105 Allowance | I20: $130 Allowance | J20: $100 Allowance | K20: $130 Allowance | L20: $105 Allowance
B21: Necessary | C21: No Copay | D21: $200 Allowance | E21: No Copay | F21: $200 Allowance | G21: $10 Copay | H21: $210 Allowance | I21: $10 Copay | J21: $210 Allowance | K21: $10 Copay | L21: $210 Allowance
B22: Frequency | C22: Every 12 months | E22: Every 12 months | G22: Every 12 months | I22: Every 12 months | K22: Every 12 months
C24: Current | E24: Renewal | G24: Alternative | I24: Alternative | K24: Alternative
C25: Participating lives | D25: Premium | E25: Premium | G25: Premium | I25: Premium | K25: Premium
B26: Employee Only | C26: 21 | D26: 7.5 | E26: 8.04 | G26: 6.61 | I26: 6 | K26: 7.65
B27: Employee + Spouse | C27: 5 | D27: 15.5 | E27: 16.6 | G27: 13.65 | I27: 12.4 | K27: 15.33
B28: Employee + Child(ren) | C28: 1 | D28: 14.4 | E28: 15.44 | G28: 12.7 | I28: 11.52 | K28: 12.98
B29: Employee + Family | C29: 3 | D29: 22.4 | E29: 24 | G29: 19.74 | I29: 17.92 | K29: 21.4
B30: Monthly premium | D30: =$C$26*D26+$C$28*D28+$C$29*D29+$C$27*D27 -> 316.6 | E30: =$C$26*E26+$C$28*E28+$C$29*E29+$C$27*E27 -> 339.28 | G30: =$C$26*G26+$C$28*G28+$C$29*G29+$C$27*G27 -> 278.98 | I30: =$C$26*I26+$C$28*I28+$C$29*I29+$C$27*I27 -> 253.28 | K30: =$C$26*K26+$C$28*K28+$C$29*K29+$C$27*K27 -> 314.48
B31: Annual Premium | D31: =D30*12 -> 3799.2 | E31: =E30*12 -> 4071.36 | G31: =G30*12 -> 3347.76 | I31: =I30*12 -> 3039.36 | K31: =K30*12 -> 3773.76
B32: Monthly Change from Current | E32: =E30-$D$30 -> 22.68 | G32: =G30-$D$30 -> -37.62 | I32: =I30-$D$30 -> -63.32 | K32: =K30-$D$30 -> -2.12
B33: Annual Change from Current | E33: =E32*12 -> 272.16 | G33: =G32*12 -> -451.44 | I33: =I32*12 -> -759.84 | K33: =K32*12 -> -25.44
B34: Percentage Change | E34: =(E30-$D$30)/$D$30 -> 0.071636134 | G34: =(G30-$D$30)/$D$30 -> -0.11882502 | I34: =(I30-$D$30)/$D$30 -> -0.2 | K34: =(K30-$D$30)/$D$30 -> -0.0066961466

Sheet Life 
B1: Ancilliary Quote Comparison Prepared for Partners of the Americas Effective Date: 08/01/2023
B3: 80212
C4: Current | E4: Renewal | G4: Alternative | I4: Alternative | K4: Alternative
B5: Life & AD&D | C5: The Standard | E5: The Standard | G5: Principal | I5: Guardian | K5: Metlife
B7: Life Insurance Rate (Per $1000) | C7: 0.09 | E7: 0.09 | G7: 0.073 | I7: 0.08 | K7: 0.083
B8: AD&D (Per $1000) | C8: 0.015 | E8: 0.015 | G8: 0.031 | I8: 0.02 | K8: 0.015
B9: Employee Volume | C9: =44*100000+50000 -> 4450000 | E9: =44*100000+50000 -> 4450000 | G9: =44*100000+50000 -> 4450000 | I9: 4450000 | K9: 4450000
B10: Coverage amount | C10: 100000 | E10: 100000 | G10: 100000 | I10: 100000 | K10: 100000
B11: Guarantee Issue Amount | C11: 100000 | E11: 100000 | G11: 100000 | I11: 100000 | K11: 100000
B12: Reductions | C12: 35% at age 65 50% at age 70 | E12: 35% at age 65 50% at age 70 | G12: 35% at age 65 50% at age 70 | I12: 35% at age 65 50% at age 70 | K12: 35% at age 65 50% at age 70
B13: Number of lives | C13: 45 | E13: 45 | G13: 45 | I13: 45 | K13: 45
C15: Current | E15: Alternative | G15: Alternative | I15: Alternative | K15: Alternative
C16: Estimated Monthly Cost | E16: Estimated Monthly Cost | G16: Estimated Monthly Cost | I16: Estimated Monthly Cost | K16: Estimated Monthly Cost
B17: Group Life | C17: =C7*C9/1000 -> 400.5 | E17: =E7*E9/1000 -> 400.5 | G17: =G7*G9/1000 -> 324.85 | I17: =I7*I9/1000 -> 356 | K17: =K7*K9/1000 -> 369.35
B18: AD&D | C18: =C8*C9/1000 -> 66.75 | E18: =E8*E9/1000 -> 66.75 | G18: =G8*G9/1000 -> 137.95 | I18: =I8*I9/1000 -> 89 | K18: =K8*K9/1000 -> 66.75
B19: Total Monthly Premium | C19: =C18+C17 -> 467.25 | E19: =E18+E17 -> 467.25 | G19: =G18+G17 -> 462.8 | I19: =I18+I17 -> 445 | K19: =K18+K17 -> 436.1
B20: Estimated Annual Cost | C20: =C19*12 -> 5607 | E20: =E19*12 -> 5607 | G20: =G19*12 -> 5553.6 | I20: =I19*12 -> 5340 | K20: =K19*12 -> 5233.2
B21: Annual Change From Current | E21: =(E19-$C$19) -> 0 | G21: =(G19-$C$19) -> -4.45 | I21: =(I19-$C$19) -> -22.25 | K21: =(K19-$C$19) -> -31.15
B22: Percentage from Current | E22: =(E19-$C$19)/$C$19 -> 0 | G22: =(G19-$C$19)/$C$19 -> -0.0095238095 | I22: =(I19-$C$19)/$C$19 -> -0.047619048 | K22: =(K19-$C$19)/$C$19 -> -0.066666667

Sheet LTD 
B1: Ancilliary Quote Comparison Prepared for Partners of the Americas Effective Date: 08/01/2023
C4: Current | E4: Renewal | G4: Alternative | I4: Alternative | K4: Alternative
B5: Long -Term Disability | C5: The Standard | E5: The Standard | G5: Principal | I5: Guardian | K5: MetLife
B7: LTD Benefit | C7: 60% of Monthly earnings | E7: 60% of Monthly earnings | G7: 60% of Monthly earnings | I7: 60% of Monthly earnings | K7: 60% of Monthly earnings
B8: Maximum Benefit | C8: $6,000/ Month | E8: $6,000/ Month | G8: $6,000/ Month | I8: $6,000/ Month | K8: $6,000/ Month
B9: LTD Rate (Per $100) | C9: 0.15 | E9: =C9 -> 0.15 | G9: 0.15 | I9: 0.15 | K9: 0.161
B10: Monthly covered Payroll | C10: 309033 | E10: 319017 | G10: 319017 | I10: 319017 | K10: 319017
B11: Waiting Period | C11: 90 Days | E11: 90 Days | G11: 90 Days | I11: 90 Days | K11: 90 Days
B12: Rate guarantee | E12: 1 year | G12: 2 years | I12: 2 years | K12: 2 years
B13: Covered Employees | C13: 45 | E13: 45 | G13: 44 | I13: 44 | K13: 44
C15: Current | E15: Renewal | G15: Alternative | I15: Alternative | K15: Alternative
C16: Estimated Cost | E16: Estimated Cost | G16: Estimated Cost | I16: Estimated Cost | K16: Estimated Cost
B17: Total Monthly Premium | C17: =C9*C10/100 -> 463.5495 | E17: =E10*E9/100 -> 478.5255 | G17: =G10*G9/100 -> 478.5255 | I17: =I10*I9/100 -> 478.5255 | K17: =K10*K9/100 -> 513.61737
B18: Estimated Annual Cost | C18: =C17*12 -> 5562.594 | E18: =E17*12 -> 5742.306 | G18: =G17*12 -> 5742.306 | I18: =I17*12 -> 5742.306 | K18: =K17*12 -> 6163.4084
B19: Annual Change from Current | E19: =E18-$C$18 -> 179.712 | G19: =G18-$C$18 -> 179.712 | I19: =I18-$C$18 -> 179.712 | K19: =K18-$C$18 -> 600.81444
B20: Percentage from Current | E20: =(E17-$C$17)/$C$17 -> 0.032307229 | G20: =(G17-$C$17)/$C$17 -> 0.032307229 | I20: =(I17-$C$17)/$C$17 -> 0.032307229 | K20: =(K17-$C$17)/$C$17 -> 0.10800976

Sheet STD 
B1: Ancilliary Quote Comparison Prepared for Partners of the Americas Effective Date: 08/01/2023
C4: Proposal | E4: Alternative | G4: Alternative | I4: Alternative
B5: Short -Term Disability | C5: The Standard | E5: Guardian | G5: Principal | I5: Metlife
B7: STD Benefit | C7: 60% of weekly earnings | E7: 60% of weekly earnings | G7: 60% of weekly earnings | I7: 60% of weekly earnings
B8: Maximum Benefit | C8: $1500 for 12 weeks | E8: $1500 for 13 weeks | G8: $1500 for 13 weeks | I8: $1500 for 13 weeks
B9: STD Rate (per $10) | C9: 0.303 | E9: 0.3 | G9: 0.29 | I9: 0.265
B10: Employee Volume | C10: 43747 | E10: 45729 | G10: 45727 | I10: 45727
B11: Waiting Period (Accident/Sickness) | C11: 14 days | E11: 0 Days/ 7 Days | G11: 0 Days/ 7 Days | I11: 14 days
B12: Contribution | C12: Non- Contributory | E12: Non- Contributory | G12: Non- Contributory | I12: Non- Contributory
B13: Covered Employees | C13: 44 | E13: 44 | G13: 44 | I13: 44
B14: Rate Guarantee | C14: 3 years | E14: 2 Years | G14: 2 years | I14: 2 years
C16: =C4 -> Proposal | E16: =E4 -> Alternative | G16: Alternative | I16: Alternative
C17: Estimated Monthly Cost | E17: Estimated Monthly Cost | G17: Estimated Monthly Cost | I17: Estimated Monthly Cost
B18: Total Monthly Premium | C18: =C10*C9/10 -> 1325.5341 | E18: =E10*E9/10 -> 1371.87 | G18: =G10*G9/10 -> 1326.083 | I18: =I10*I9/10 -> 1211.7655
B19: Estimated Annual Cost | C19: =C18*12 -> 15906.409 | E19: =E18*12 -> 16462.44 | G19: =G18*12 -> 15912.996 | I19: =I18*12 -> 14541.186
B20: Annual Change | E20: =E19-$C$19 -> 556.0308 | G20: =G19-$C$19 -> 6.5868 | I20: =I19-$C$19 -> -1365.2232
B21: Percentage from Current | E21: =(E19-$C$19)/$C$19 -> 0.0349564 | G21: =(G19-$C$19)/$C$19 -> 0.00041409723 | I21: =(I19-$C$19)/$C$19 -> -0.085828497

Sheet Pet Insurance
B1: Ancilliary Quote Comparison Prepared for Partners of the Americas Effective Date: 08/01/2023
C5: ASPCA | E5: SPOT
B6: Funding Type | C6: Voluntary | E6: Voluntary
B7: Enrollment Options | C7: ASPCA Enrollment Landing Page | E7: SPOT Enrollment Landing Page
B8: Waiting Period | C8: Varies Based on Plan Selection | E8: 14 days
B9: Premium Option | C9: Direct Bill | E9: Direct Bill
B10: Price | C10: Individually Rated (Avg $25/$50) Based on Employee Demographics and Plan Selection | E10: Individually Rated Based on Employee Demographics, Pet, and Plan Selection
B11: Pets Covered | C11: Dog or Cat | E11: Dog or Cat
B12: Eligibility | C12: 8 weeks or older Pre-Ex Exclusions | E12: 8 weeks old or older Pre-Ex Exclusions
B13: Annual Limit | C13: Varies Based on Plan Selection | E13: $2,500, $4,000, $5,000, $7,000, $10,000, Unlimited
B14: Deductible | C14: Varies Based on Plan Selection | E14: $100, $250, $500, $750, $1,000
B15: Vet Services | C15: Varies Based on Plan Selection | E15: 70%, 80%, 90%
B16: Prescriptions | C16: Varies Based on Plan Selection | E16: Varies Based on Plan Selection
B17: Telehealth | C17: Unlimited 24/7 Access | E17: Unlimited 24/7 Access
B18: Add'l Discounts | C18: 10%-20% Group Discount | E18: 10%-20% Group Discount
B19: Avg Claim Repayment | E19: 10-14 days
B20: Claim Forms | C20: Yes | E20: Yes
