Workbook
Name \a: #REF!
Name \A1: #REF!
Name \A10: #REF!
Name \A2: #REF!
Name \A4: #REF!
Name \A7: #REF!
Name \A8: #REF!
Name \A9: #REF!
Name \b: #REF!
Name \B1: #REF!
Name \B10: #REF!
Name \B3: #REF!
Name \B4: #REF!
Name \B7: #REF!
Name \B8: #REF!
Name \B9: #REF!
Name \c: #REF!
Name \C1: #REF!
Name \C10: #REF!
Name \C2: #REF!
Name \C3: #REF!
Name \C5: #REF!
Name \C7: #REF!
Name \C8: #REF!
Name \C9: #REF!
Name \d: #REF!
Name \D1: #REF!
Name \D10: #REF!
Name \D2: #REF!
Name \D3: #REF!
Name \D7: #REF!
Name \D8: #REF!
Name \D9: #REF!
Name \g: #N/A
Name \h: #REF!
Name \P: [4]InputData!#REF!
Name \q: '[5]COMPTRFC Page8'!#REF!
Name \R: [4]InputData!#REF!
Name \s: #REF!
Name \T: [4]InputData!#REF!
Name \U: [4]InputData!#REF!
Name \V: [4]InputData!#REF!
Name \W: [4]InputData!#REF!
Name _.: #REF!
Name ___ASO1: #REF!
Name ___MOS6: #REF!
Name ___PUL1: #REF!
Name ___PUL2: #REF!
Name __1_0REV: '[6]Age Sheet'!#REF!
Name __ASO1: #REF!
Name __MOS6: #REF!
Name __PUL1: #REF!
Name __PUL2: #REF!
Name _1_0REV: '[6]Age Sheet'!#REF!
Name _2_0REV: '[6]Age Sheet'!#REF!
Name _219: #REF!
Name _2REV: '[6]Age Sheet'!#REF!
Name _3_0REV: '[6]Age Sheet'!#REF!
Name _4_0REV: '[6]Age Sheet'!#REF!
Name _7: #N/A

Sheet Premium History
A1: Partners of the Americas
E2: 2017 | G2: 2018 | I2: 2019 | K2: 2020 | M2: 2021 | O2: 2022 | Q2: 2023
A3: Partners Estimated Monthly Premium | E3: 9822.01 | G3: 10080.74 | I3: 12149.07 | K3: 15991.23 | M3: 28401.84 | O3: 21338.82 | Q3: ='Partners 23-24 No Change'!M79 -> 33947.246
A4: Renewal Change at 8/1 based on enrollment at that time | G4: =(G3-E3)/E3 -> 0.026341859 | I4: -0.0644 | K4: 0.0264 | M4: 0.0367 | O4: -0.0129 | Q4: ='Partners 23-24 No Change'!M81 -> 0.16077017
A5: Employees Covered | E5: 15 | G5: 15 | I5: 18 | K5: 22 | M5: 27 | O5: 36 | Q5: 30
A6: Percentage Change in Headcount | G6: =(G5-E5)/E5 -> 0 | I6: =(I5-G5)/G5 -> 0.2 | K6: =(K5-I5)/I5 -> 0.22222222 | M6: =(M5-K5)/K5 -> 0.22727273 | O6: =(O5-M5)/M5 -> 0.33333333 | Q6: =(Q5-O5)/O5 -> -0.16666667
A7: ER/EE Breakout | E7: 80/20 | G7: 80/20 | I7: 80/20 | K7: 80/20 | M7: 80/20 | O7: 80/20 | Q7: 80/20
A8: Reference Plan | E8: BlueChoice Plus Platinum | G8: BlueChoice Plus Platinum | I8: BlueChoice Plus Platinum | K8: BlueChoice Plus Platinum | M8: BlueChoice Plus Platinum | O8: BlueChoice Plus Platinum | Q8: BlueChoice Plus Platinum
B10: Paul Notes: there is some variance in the Partners Estimated Monthly Premium due to enrollment types, some years had more families or younger/older employees. Bearing this in mind, I pulled the actual renewal change based on our review from the spreadsheets dating back to 2017. Overall, Partners has had tremendous employee growth and this is the first major increase since 2017. As the next tabs lay out, a severe change in plan may not be needed at this time nor will it do much to relieve the premium increase based on the idea of funding a portion of a deductible for employees. However, it may be the year to change the employer/employee split and encourage employees to look closely at their choices and how they are spending their portion of Partners premium contribution.

Sheet Totals
A1: Partners of the Americas
A4: Rates vary based on option selected
A5: DC Health Link
A6: Total Premium Monthly for DC Health Link*
E7: Employer Costs | G7: Employee Costs
A8: Current June 2023 DC Health Link Premium | E8: ='Partners 23-24 No Change'!M78 -> 29245.45 | G8: =SUM('Partners 23-24 No Change'!F6:F76) -> 5330.16
A9: Current Reference Plan POS BCCS Base 80/20 Split (80% of the cost of the base plan covered by employer, remaining 20% employee) | E9: ='Partners 23-24 No Change'!M79 -> 33947.246 | G9: =SUM('Partners 23-24 No Change'!M6:M75) -> 5237.764 | I9: Option 1
A10: Percentage Change | E10: =(E9-$E$8)/$E$8 -> 0.16077017 | G10: =(G9-$G$8)/$E$8 -> -0.0031593291
A11: Difference Total Dollar Monthly | E11: =E9-$E$8 -> 4701.796 | G11: =G9-$G$8 -> -92.396
A12: Difference Total Dollar Annual | E12: =E11*12 -> 56421.552 | G12: =G11*12 -> -1108.752
A13: Current Reference Plan POS BCCS Base 75/25 Split (75% of the cost of the base plan covered by employer, remaining 25% employee) | E13: ='Partners 23-24 75%'!M79 -> 32236.463 | G13: =SUM('Partners 23-24 75%'!M6:M76) -> 7496.8375 | I13: Option 2 | J13: Recommended
A14: Percentage Change | E14: =(E13-$E$8)/$E$8 -> 0.10227275 | G14: =(G13-$G$8)/$E$8 -> 0.074085969
A15: Difference Total Dollar Monthly | E15: =E13-$E$8 -> 2991.0125 | G15: =G13-$G$8 -> 2166.6775
A16: Difference Total Dollar Annual | E16: =E15*12 -> 35892.15 | G16: =G15*12 -> 26000.13
A17: Change Reference to BlueChoice Advantage Gold HRA 80/20 Split and 100% HRA Funding (80% of the cost of the base plan covered by employer, remaining 20% employee) | E17: ='Prtnrs Change Ref to Gold HRA'!M79+('Prtnrs Change Ref to Gold HRA'!M83/12) -> 38074.68 | G17: =SUM('Prtnrs Change Ref to Gold HRA'!M6:M75) -> 7737.42 | I17: Option 3
A18: Percentage Change | E18: =(E17-$E$8)/$E$8 -> 0.30190098 | G18: =(G17-$G$8)/$E$8 -> 0.082312291
A19: Difference Total Dollar Monthly | E19: =E17-$E$8 -> 8829.23 | G19: =G17-$G$8 -> 2407.26
A20: Difference Total Dollar Annual | E20: =E19*12 -> 105950.76 | G20: =G19*12 -> 28887.12
A21: Change Reference to BlueChoice Advantage Silver HRA 80/20 Split and 100% HRA Funding (80% of the cost of the base plan covered by employer, remaining 20% employee) | E21: ='Prtnrs Change Ref to Silver HRA'!M79+('Prtnrs Change Ref to Silver HRA'!M83/12) -> 34915.888 | G21: =SUM('Prtnrs Change Ref to Silver HRA'!M6:M75) -> 6828.972 | I21: Option 4
A22: Percentage Change | E22: =(E21-$E$8)/$E$8 -> 0.19389129 | G22: =(G21-$G$8)/$E$8 -> 0.051249408
A23: Difference Total Dollar Monthly | E23: =E21-$E$8 -> 5670.438 | G23: =G21-$G$8 -> 1498.812
A24: Difference Total Dollar Annual | E24: =E23*12 -> 68045.256 | G24: =G23*12 -> 17985.744
A25: *Assumptions are based on current enrollment rates
A26: Notes:
A27: PPO - preferred provider organization (usually most expensive)
A28: POS - point-of-service plan (usually mid range costs)
A29: HMO - health maintenance organization (always cheapest option)

Sheet Partners 23-24 No Change
A1: 2023 Benefits Worksheet | M1: Partners Covers | N1: 0.8 | O1: Employee | P1: 0.8 | Q1: Dependents
A2: 1 | N2: No Changes Employees Actual Choices on DCHL
A3: Renewal Date | B3: 45139
A4: Basic Demographic Data | E4: Current Premiums | H4: Renewal Information | K4: Plan Info
A5: Employee | B5: Covered Dependents | C5: DOB | D5: Renewal Age | E5: Partners Current Premium | F5: Employee Current Monthly Premium based on May Invoice | G5: Total Cost Current Premium | H5: Renewal Premium BlueChoice Plus Opt-Out Platinum 0 | I5: Renewal Cost Employee's Actual Plan | J5: Percentage Change on Actual Plan | K5: Employee's Actual Plan Choice | L5: Maximum Renewal Cost for Partners BlueChoice Plus Platinum 0 | M5: Employee Premium On Renewal | N5: Percentage Change for Partners | O5: Percentage Change for Employee | P5: Employee's % Cost of Premium
A6: Alexandra Lishansky | B6: 1 | C6: 34087 | D6: =($B$3-C6)/365 -> 30.279452 | E6: 650.85 | F6: 257.39 | G6: 908.24 | H6: ='[2]MEDICAL-Table Rates'!$S$42 -> 513.4 | I6: 1055.95 | J6: =(I6-G6)/G6 -> 0.16263322 | K6: BlueChoice Advantage Platinum 0 | L6: =IF($N$1*H6+$P$1*H7>=I6,I6,$N$1*H6+$P$1*H7) -> 755.536 | M6: =I6-L6 -> 300.414 | N6: =(L6-E6)/E6 -> 0.16084505 | O6: =(M6-F6)/F6 -> 0.1671549 | P6: =M6/I6 -> 0.28449643
D7: 1 | H7: ='[2]MEDICAL-Table Rates'!$S$16 -> 431.02
A8: Marcio Nascimento | B8: 0 | C8: 26679 | D8: =($B$3-C8)/365 -> 50.575342 | E8: 633.82 | F8: 112.9 | G8: 746.72 | H8: ='[2]MEDICAL-Table Rates'!$S$75 -> 943.1 | I8: 887.51 | J8: =(I8-G8)/G8 -> 0.18854457 | K8: BlueChoice HMO Referral Platinum 0 | L8: =IF($N$1*H8>=I8,I8,$N$1*H8) -> 754.48 | M8: =I8-L8 -> 133.03 | N8: =(L8-E8)/E8 -> 0.19036951 | O8: =(M8-F8)/F8 -> 0.17829938 | P8: =M8/I8 -> 0.14989127
A9: Penelope Kim | B9: 2 | C9: 31381 | D9: =($B$3-C9)/365 -> 37.693151 | E9: 1055.91 | F9: 263.97 | G9: 1319.88 | H9: ='[2]MEDICAL-Table Rates'!$S$54 -> 603.69 | I9: 1535.59 | J9: =(I9-G9)/G9 -> 0.16343152 | K9: BlueChoice Plus Opt-Out Platinum 0 | L9: =IF($N$1*H9+$P$1*SUM(H10:H11)>=I9,I9,$N$1*H9+$P$1*SUM(H10:H11)) -> 1228.472 | M9: =I9-L9 -> 307.118 | N9: =(L9-E9)/E9 -> 0.16342491 | O9: =(M9-F9)/F9 -> 0.16345797 | P9: =M9/I9 -> 0.2
D10: 29 | H10: ='[2]MEDICAL-Table Rates'!$S$41 -> 500.88
D11: 0 | H11: ='[2]MEDICAL-Table Rates'!$S$16 -> 431.02
A12: Michael B Moscarelli | B12: 4 | C12: 30749 | D12: =($B$3-C12)/365 -> 39.424658 | E12: 1733 | F12: 433.25 | G12: 2166.25 | H12: ='[2]MEDICAL-Table Rates'!$S$57 -> 618.19 | I12: 2501.76 | J12: =(I12-G12)/G12 -> 0.15488055 | K12: BlueChoice Plus Opt-Out Platinum 0 | L12: =IF($N$1*H12+$P$1*SUM(H13:H16)>=I12,I12,$N$1*H12+$P$1*SUM(H13:H16)) -> 2001.408 | M12: =I12-L12 -> 500.352 | N12: =(L12-E12)/E12 -> 0.15488055 | O12: =(M12-F12)/F12 -> 0.15488055 | P12: =M12/I12 -> 0.2
D13: 36 | H13: ='[2]MEDICAL-Table Rates'!$S$52 -> 590.51
D14: 6 | H14: ='[2]MEDICAL-Table Rates'!$S$16 -> 431.02
D15: 3 | H15: ='[2]MEDICAL-Table Rates'!$S$16 -> 431.02
D16: 0 | H16: ='[2]MEDICAL-Table Rates'!$S$16 -> 431.02
A17: Ana Aslan | B17: 1 | C17: 24458 | D17: =($B$3-C17)/365 -> 56.660274 | E17: 1758.76 | F17: 439.69 | G17: 2198.45 | H17: 1186.95 | I17: 2518.23 | J17: =(I17-G17)/G17 -> 0.14545703 | K17: BlueChoice Plus Opt-Out Platinum 0 | L17: =IF($N$1*H17+$P$1*H18>=I17,I17,$N$1*H17+$P$1*H18) -> 2014.584 | M17: =I17-L17 -> 503.646 | N17: =(L17-E17)/E17 -> 0.14545703 | O17: =(M17-F17)/F17 -> 0.14545703 | P17: =M17/I17 -> 0.2
D18: 59 | H18: ='[2]MEDICAL-Table Rates'!$S$89 -> 1331.28
A19: Lesly Yohana Rubio | B19: 0 | C19: 31552 | D19: =($B$3-C19)/365 -> 37.224658 | E19: 412.42 | F19: 249.96 | G19: 662.38 | H19: ='[2]MEDICAL-Table Rates'!$S$54 -> 603.69 | I19: 765.65 | J19: =(I19-G19)/G19 -> 0.15590749 | K19: BluePreferred PPO Platinum 0 | L19: =IF($N$1*H19>=I19,I19,$N$1*H19) -> 482.952 | M19: =I19-L19 -> 282.698 | N19: =(L19-E19)/E19 -> 0.17101983 | O19: =(M19-F19)/F19 -> 0.13097296 | P19: =M19/I19 -> 0.36922615
A20: Carmen Pena | B20: 2 | C20: 31899 | D20: =($B$3-C20)/365 -> 36.273973 | E20: 1116.67 | F20: 676.78 | G20: 1793.45 | H20: ='[2]MEDICAL-Table Rates'!$S$52 -> 590.51 | I20: 2061.23 | J20: =(I20-G20)/G20 -> 0.14930999 | K20: BluePreferred PPO Platinum 0 | L20: =IF($N$1*H20+$P$1*SUM(H21:H22)>=I20,I20,$N$1*H20+$P$1*SUM(H21:H22)) -> 1300.176 | M20: =I20-L20 -> 761.054 | N20: =(L20-E20)/E20 -> 0.16433324 | O20: =(M20-F20)/F20 -> 0.124522 | P20: =M20/I20 -> 0.36922323
D21: 37 | H21: ='[2]MEDICAL-Table Rates'!$S$54 -> 603.69
D22: 5 | H22: ='[2]MEDICAL-Table Rates'!$S$16 -> 431.02
A23: Kelly M McNally | B23: 0 | C23: 34588 | D23: =($B$3-C23)/365 -> 28.906849 | E23: 334.63 | F23: 117.07 | G23: 451.7 | H23: ='[2]MEDICAL-Table Rates'!$S$39 -> 490.33 | I23: 534.96 | J23: =(I23-G23)/G23 -> 0.18432588 | K23: HealthyBlue Advantage Platinum 500 | L23: =IF($N$1*H23>=I23,I23,$N$1*H23) -> 392.264 | M23: =I23-L23 -> 142.696 | N23: =(L23-E23)/E23 -> 0.17223202 | O23: =(M23-F23)/F23 -> 0.21889468 | P23: =M23/I23 -> 0.26674144
A24: Susanna J Meyer | B24: 0 | C24: 33900 | D24: =($B$3-C24)/365 -> 30.791781 | E24: 349.82 | F24: 122.38 | G24: 472.2 | H24: ='[2]MEDICAL-Table Rates'!$S$42 -> 513.4 | I24: 560.12 | J24: =(I24-G24)/G24 -> 0.18619229 | K24: HealthyBlue Advantage Platinum 500 | L24: =IF($N$1*H24>=I24,I24,$N$1*H24) -> 410.72 | M24: =I24-L24 -> 149.4 | N24: =(L24-E24)/E24 -> 0.17408953 | O24: =(M24-F24)/F24 -> 0.22078771 | P24: =M24/I24 -> 0.26672856
A25: Madeline Rae Steiner | B25: 0 | C25: 33765 | D25: =($B$3-C25)/365 -> 31.161644 | E25: 358.57 | F25: 125.44 | G25: 484.01 | H25: ='[2]MEDICAL-Table Rates'!$S$44 -> 526.58 | I25: 574.5 | J25: =(I25-G25)/G25 -> 0.18695895 | K25: HealthyBlue Advantage Platinum 500 | L25: =IF($N$1*H25>=I25,I25,$N$1*H25) -> 421.264 | M25: =I25-L25 -> 153.236 | N25: =(L25-E25)/E25 -> 0.17484452 | O25: =(M25-F25)/F25 -> 0.22158801 | P25: =M25/I25 -> 0.26672933
A26: Stephanie Monroy | B26: 0 | C26: 31116 | D26: =($B$3-C26)/365 -> 38.419178 | E26: 426.69 | F26: 149.27 | G26: 575.96 | H26: ='[2]MEDICAL-Table Rates'!$S$55 -> 610.94 | I26: 666.54 | J26: =(I26-G26)/G26 -> 0.15726787 | K26: HealthyBlue Advantage Platinum 500 | L26: =IF($N$1*H26>=I26,I26,$N$1*H26) -> 488.752 | M26: =I26-L26 -> 177.788 | N26: =(L26-E26)/E26 -> 0.14544986 | O26: =(M26-F26)/F26 -> 0.19104978 | P26: =M26/I26 -> 0.26673268
A27: Kirk Amper Del Rosario | B27: 0 | C27: 33886 | D27: =($B$3-C27)/365 -> 30.830137 | E27: 349.82 | F27: 75.87 | G27: 425.69 | H27: ='[2]MEDICAL-Table Rates'!$S$42 -> 513.4 | I27: 504.65 | J27: =(I27-G27)/G27 -> 0.18548709 | K27: HealthyBlue Plus Platinum 500 | L27: =IF($N$1*H27>=I27,I27,$N$1*H27) -> 410.72 | M27: =I27-L27 -> 93.93 | N27: =(L27-E27)/E27 -> 0.17408953 | O27: =(M27-F27)/F27 -> 0.23803875 | P27: =M27/I27 -> 0.186129
A28: Sara Jebena | B28: 0 | C28: 29996 | D28: =($B$3-C28)/365 -> 41.487671 | E28: 448.78 | F28: 97.34 | G28: 546.12 | H28: ='[2]MEDICAL-Table Rates'!$S$60 -> 667.62 | I28: 656.24 | J28: =(I28-G28)/G28 -> 0.20164067 | K28: HealthyBlue Plus Platinum 500 | L28: =IF($N$1*H28>=I28,I28,$N$1*H28) -> 534.096 | M28: =I28-L28 -> 122.144 | N28: =(L28-E28)/E28 -> 0.19010651 | O28: =(M28-F28)/F28 -> 0.25481816 | P28: =M28/I28 -> 0.18612703
A29: Summar T Lyons | B29: 1 | C29: 31217 | D29: =($B$3-C29)/365 -> 38.142466 | E29: 887.89 | F29: 192.58 | G29: 1080.47 | H29: ='[2]MEDICAL-Table Rates'!$S$55 -> 610.94 | I29: 1282.68 | J29: =(I29-G29)/G29 -> 0.18715004 | K29: HealthyBlue Plus Platinum 500 | L29: =IF($N$1*H29+$P$1*H30>=I29,I29,$N$1*H29+$P$1*H30) -> 1043.936 | M29: =I29-L29 -> 238.744 | N29: =(L29-E29)/E29 -> 0.17574925 | O29: =(M29-F29)/F29 -> 0.23971337 | P29: =M29/I29 -> 0.18612904
D30: 42 | H30: ='[2]MEDICAL-Table Rates'!$S$62 -> 693.98
A31: Armin Cordova | B31: 0 | C31: 35369 | D31: =($B$3-C31)/365 -> 26.767123 | E31: 324.42 | F31: 0 | G31: 324.42 | H31: ='[2]MEDICAL-Table Rates'!$S$28 -> 479.13 | I31: 374.63 | J31: =(I31-G31)/G31 -> 0.15476851 | K31: KP DC Platinum 0/10/Vision | L31: =IF($N$1*H31>=I31,I31,$N$1*H31) -> 374.63 | M31: =I31-L31 -> 0 | N31: =(L31-E31)/E31 -> 0.15476851 | O31: =(M31-F31)/F31 -> #DIV/0! | P31: =M31/I31 -> 0
A32: Megan Michelle Ash | B32: 0 | C32: 34295 | D32: =($B$3-C32)/365 -> 29.709589 | E32: 332 | F32: 0 | G32: 332 | H32: 500.88 | I32: 391.63 | J32: =(I32-G32)/G32 -> 0.17960843 | K32: KP DC Platinum 0/10/Vision | L32: =IF($N$1*H32>=I32,I32,$N$1*H32) -> 391.63 | M32: =I32-L32 -> 0 | N32: =(L32-E32)/E32 -> 0.17960843 | O32: =(M32-F32)/F32 -> #DIV/0! | P32: =M32/I32 -> 0
A33: Stephanie Verganza | B33: 0 | C33: 33576 | D33: =($B$3-C33)/365 -> 31.679452 | E33: 347.62 | F33: 0 | G33: 347.62 | H33: 526.58 | I33: 411.73 | J33: =(I33-G33)/G33 -> 0.18442552 | K33: KP DC Platinum 0/10/Vision | L33: =IF($N$1*H33>=I33,I33,$N$1*H33) -> 411.73 | M33: =I33-L33 -> 0 | N33: =(L33-E33)/E33 -> 0.18442552 | O33: =(M33-F33)/F33 -> #DIV/0! | P33: =M33/I33 -> 0
A34: Anh H Nguyen | B34: 1 | C34: 33338 | D34: =($B$3-C34)/365 -> 32.331507 | E34: 680.97 | F34: 0 | G34: 680.97 | H34: ='[2]MEDICAL-Table Rates'!$S$45 -> 538.44 | I34: =421.01+383.39 -> 804.4 | J34: =(I34-G34)/G34 -> 0.18125615 | K34: KP DC Platinum 0/10/Vision | L34: =IF($N$1*H34+$P$1*H35>=I34,I34,$N$1*H34+$P$1*H35) -> 804.4 | M34: =I34-L34 -> 0 | N34: =(L34-E34)/E34 -> 0.18125615 | O34: =(M34-F34)/F34 -> #DIV/0! | P34: =M34/I34 -> 0
D35: 28 | H35: ='[2]MEDICAL-Table Rates'!$S$39 -> 490.33
A36: Janira J Romero Reyes | B36: 1 | C36: 31561 | D36: =($B$3-C36)/365 -> 37.2 | E36: 691.67 | F36: 0 | G36: 691.67 | H36: 603.69 | I36: =472.02+337.01 -> 809.03 | J36: =(I36-G36)/G36 -> 0.16967629 | K36: KP DC Platinum 0/10/Vision | L36: =IF($N$1*H36+$P$1*H37>=I36,I36,$N$1*H36+$P$1*H37) -> 809.03 | M36: =I36-L36 -> 0 | N36: =(L36-E36)/E36 -> 0.16967629 | O36: =(M36-F36)/F36 -> #DIV/0! | P36: =M36/I36 -> 0
D37: 0 | H37: ='[2]MEDICAL-Table Rates'!$S$16 -> 431.02
A38: Danielle R Martin | B38: 1 | C38: 33497 | D38: =($B$3-C38)/365 -> 31.89589 | E38: 695.24 | F38: 0 | G38: 695.24 | H38: ='[2]MEDICAL-Table Rates'!$S$44 -> 526.58 | I38: =395.9*2 -> 791.8 | J38: =(I38-G38)/G38 -> 0.13888729 | K38: KP DC Platinum 0/10/Vision | L38: =IF($N$1*H38+$P$1*H39>=I38,I38,$N$1*H38+$P$1*H39) -> 791.8 | M38: =I38-L38 -> 0 | N38: =(L38-E38)/E38 -> 0.13888729 | O38: =(M38-F38)/F38 -> #DIV/0! | P38: =M38/I38 -> 0
D39: 31 | H39: ='[2]MEDICAL-Table Rates'!$S$44 -> 526.58
A40: William D Webber | B40: 1 | C40: 34122 | D40: =($B$3-C40)/365 -> 30.183562 | E40: 738.97 | F40: 0 | G40: 738.97 | H40: ='[2]MEDICAL-Table Rates'!$S$42 -> 513.4 | I40: =453.87+385.99 -> 839.86 | J40: =(I40-G40)/G40 -> 0.13652787 | K40: KP DC Platinum 0/10/Vision | L40: =IF($N$1*H40+$P$1*H41>=I40,I40,$N$1*H40+$P$1*H41) -> 839.86 | M40: =I40-L40 -> 0 | N40: =(L40-E40)/E40 -> 0.13652787 | O40: =(M40-F40)/F40 -> #DIV/0! | P40: =M40/I40 -> 0
D41: 37 | H41: ='[2]MEDICAL-Table Rates'!$S$54 -> 603.69
A42: Debra L Cooper | B42: 0 | C42: 24504 | D42: =($B$3-C42)/365 -> 56.534247 | E42: 773.34 | F42: 0 | G42: 773.34 | H42: ='[2]MEDICAL-Table Rates'!$S$84 -> 1186.95 | I42: 892.38 | J42: =(I42-G42)/G42 -> 0.15392971 | K42: KP DC Platinum 0/10/Vision | L42: =IF($N$1*H42>=I42,I42,$N$1*H42) -> 892.38 | M42: =I42-L42 -> 0 | N42: =(L42-E42)/E42 -> 0.15392971 | O42: =(M42-F42)/F42 -> #DIV/0! | P42: =M42/I42 -> 0
A43: Pablo Marcelo Gonzalez | B43: 1 | C43: 28690 | D43: =($B$3-C43)/365 -> 45.065753 | E43: 1054.92 | F43: 0 | G43: 1054.92 | H43: 778.34 | I43: =585.17+631.75 -> 1216.92 | J43: =(I43-G43)/G43 -> 0.15356615 | K43: KP DC Platinum 0/10/Vision | L43: =IF($N$1*H43+$P$1*H44>=I43,I43,$N$1*H43+$P$1*H44) -> 1216.92 | M43: =I43-L43 -> 0 | N43: =(L43-E43)/E43 -> 0.15356615 | O43: =(M43-F43)/F43 -> #DIV/0! | P43: =M43/I43 -> 0
D44: 47 | H44: ='[2]MEDICAL-Table Rates'!$S$70 -> 840.29
A45: Sheila Ann Posas | B45: 3 | C45: 27512 | D45: =($B$3-C45)/365 -> 48.293151 | E45: 1700.18 | F45: 0 | G45: 1700.18 | H45: ='[2]MEDICAL-Table Rates'!$S$71 -> 873.24 | I45: =682.78+632.28+(337.01*2) -> 1989.08 | J45: =(I45-G45)/G45 -> 0.16992318 | K45: KP DC Platinum 0/10/Vision | L45: =IF($N$1*H45+$P$1*SUM(H46:H48)>=I45,I45,$N$1*H45+$P$1*SUM(H46:H48)) -> 1989.08 | M45: =I45-L45 -> 0 | N45: =(L45-E45)/E45 -> 0.16992318 | O45: =(M45-F45)/F45 -> #DIV/0! | P45: =M45/I45 -> 0
D46: 46 | H46: ='[2]MEDICAL-Table Rates'!$S$68 -> 808.65
D47: 10 | H47: ='[2]MEDICAL-Table Rates'!$S$16 -> 431.02
D48: 7 | H48: ='[2]MEDICAL-Table Rates'!$S$16 -> 431.02
A49: Mariana Cabrera | B49: 0 | C49: 36111 | D49: =($B$3-C49)/365 -> 24.734247 | E49: 334.63 | F49: 16.28 | G49: 350.91 | H49: ='[2]MEDICAL-Table Rates'!$S$28 -> 479.13 | I49: 391.62 | J49: =(I49-G49)/G49 -> 0.11601265 | K49: KP DC Platinum Added Choice 0/10/POS/Vision | L49: =IF($N$1*H49>=I49,I49,$N$1*H49) -> 383.304 | M49: =I49-L49 -> 8.316 | N49: =(L49-E49)/E49 -> 0.14545618 | O49: =(M49-F49)/F49 -> -0.48918919 | P49: =M49/I49 -> 0.021234871
A50: Natalie M Abegesah | B50: 3 | C50: 31872 | D50: =($B$3-C50)/365 -> 36.347945 | E50: 1417.7 | F50: 68.98 | G50: 1486.68 | H50: ='[2]MEDICAL-Table Rates'!$S$52 -> 590.51 | I50: =482.65+493.43+352.29+352.29 -> 1680.66 | J50: =(I50-G50)/G50 -> 0.13047865 | K50: KP DC Platinum Added Choice 0/10/POS/Vision | L50: =IF($N$1*H50+$P$1*SUM(H51:H53)>=I50,I50,$N$1*H50+$P$1*SUM(H51:H53)) -> 1644.992 | M50: =I50-L50 -> 35.668 | N50: =(L50-E50)/E50 -> 0.16032447 | O50: =(M50-F50)/F50 -> -0.48292259 | P50: =M50/I50 -> 0.021222615
D51: 37 | H51: ='[2]MEDICAL-Table Rates'!$S$54 -> 603.69
D52: 17 | H52: ='[2]MEDICAL-Table Rates'!$S$16 -> 431.02
D53: 15 | H53: ='[2]MEDICAL-Table Rates'!$S$16 -> 431.02
A54: Nilu Rimal | B54: 1 | C54: 24635 | D54: =($B$3-C54)/365 -> 56.175342 | E54: 1727.46 | F54: 84.05 | G54: 1811.51 | H54: ='[2]MEDICAL-Table Rates'!$S$84 -> 1186.95 | I54: =970.15+1088.12 -> 2058.27 | J54: =(I54-G54)/G54 -> 0.13621785 | K54: KP DC Platinum Added Choice 0/10/POS/Vision | L54: =IF($N$1*H54+$P$1*H55>=I54,I54,$N$1*H54+$P$1*H55) -> 2014.584 | M54: =I54-L54 -> 43.686 | N54: =(L54-E54)/E54 -> 0.16621166 | O54: =(M54-F54)/F54 -> -0.48023795 | P54: =M54/I54 -> 0.021224621
D55: 59 | H55: ='[2]MEDICAL-Table Rates'!$S$89 -> 1331.28
A56: Genesis C Torres-Alcantara | B56: 0 | C56: 34977 | D56: =($B$3-C56)/365 -> 27.841096 | E56: 334.63 | F56: 2.76 | G56: 337.39 | H56: ='[2]MEDICAL-Table Rates'!$S$28 -> 479.13 | I56: 374.63 | J56: =(I56-G56)/G56 -> 0.11037672 | K56: KP DC Platinum HMO Plus 0/10/Vision | L56: =IF($N$1*H56>=I56,I56,$N$1*H56) -> 374.63 | M56: =I56-L56 -> 0 | N56: =(L56-E56)/E56 -> 0.11953501 | O56: =(M56-F56)/F56 -> -1 | P56: =M56/I56 -> 0
A57: Arlette G Gutierrez | B57: 0 | C57: 28471 | D57: =($B$3-C57)/365 -> 45.665753 | E57: 523.34 | F57: 4.33 | G57: 527.67 | H57: ='[2]MEDICAL-Table Rates'!$S$66 -> 778.34 | I57: 605.58 | J57: =(I57-G57)/G57 -> 0.1476491 | K57: KP DC Platinum HMO Plus 0/10/Vision | L57: =IF($N$1*H57>=I57,I57,$N$1*H57) -> 605.58 | M57: =I57-L57 -> 0 | N57: =(L57-E57)/E57 -> 0.15714449 | O57: =(M57-F57)/F57 -> -1 | P57: =M57/I57 -> 0
A58: John Robert McPhail | B58: 4 | C58: 25137 | D58: =($B$3-C58)/365 -> 54.8 | E58: 2342.87 | F58: 19.35 | G58: 2362.22 | H58: ='[2]MEDICAL-Table Rates'!$S$81 -> 1099.3 | I58: =859.53+737.4+(374.63*2)+337.01 -> 2683.2 | J58: =(I58-G58)/G58 -> 0.13588065 | K58: KP DC Platinum HMO Plus 0/10/Vision | L58: =IF($N$1*H58+$P$1*SUM(H59:H62)>=I58,I58,$N$1*H58+$P$1*SUM(H59:H62)) -> 2683.2 | M58: =I58-L58 -> 0 | N58: =(L58-E58)/E58 -> 0.14526201 | O58: =(M58-F58)/F58 -> -1 | P58: =M58/I58 -> 0
D59: 50 | H59: ='[2]MEDICAL-Table Rates'!$S$75 -> 943.1
D60: 25 | H60: ='[2]MEDICAL-Table Rates'!$S$28 -> 479.13
D61: 24 | H61: ='[2]MEDICAL-Table Rates'!$S$28 -> 479.13
D62: 19 | H62: ='[2]MEDICAL-Table Rates'!$S$16 -> 431.02
A63: Rachel Shoshana Falek | B63: 0 | C63: 35017 | D63: =($B$3-C63)/365 -> 27.731507 | E63: 334.63 | F63: 159.88 | G63: 494.51 | H63: ='[2]MEDICAL-Table Rates'!$S$28 -> 479.13 | I63: ='[2]MEDICAL-Table Rates'!$Z$37 -> 519.12 | J63: =(I63-G63)/G63 -> 0.049766435 | K63: UHC Choice Platinum 0 | L63: =IF($N$1*H63>=I63,I63,$N$1*H63) -> 383.304 | M63: =I63-L63 -> 135.816 | N63: =(L63-E63)/E63 -> 0.14545618 | O63: =(M63-F63)/F63 -> -0.15051288 | P63: =M63/I63 -> 0.26162737
A64: Angel Kristina Rutter | B64: 0 | C64: 35099 | D64: =($B$3-C64)/365 -> 27.506849 | E64: 334.63 | F64: 76.22 | G64: 410.85 | H64: ='[2]MEDICAL-Table Rates'!$S$28 -> 479.13 | I64: ='[2]MEDICAL-Table Rates'!$V$37 -> 453.59 | J64: =(I64-G64)/G64 -> 0.10402823 | K64: UHC Choice Platinum 500 | L64: =IF($N$1*H64>=I64,I64,$N$1*H64) -> 383.304 | M64: =I64-L64 -> 70.286 | N64: =(L64-E64)/E64 -> 0.14545618 | O64: =(M64-F64)/F64 -> -0.077853582 | P64: =M64/I64 -> 0.15495492
A65: Katherine Julia Matteson de Araujo | B65: 0 | C65: 35229 | D65: =($B$3-C65)/365 -> 27.150685 | E65: 334.63 | F65: 76.22 | G65: 410.85 | H65: ='[2]MEDICAL-Table Rates'!$S$28 -> 479.13 | I65: ='[2]MEDICAL-Table Rates'!$V$37 -> 453.59 | J65: =(I65-G65)/G65 -> 0.10402823 | K65: UHC Choice Platinum 500 | L65: =IF($N$1*H65>=I65,I65,$N$1*H65) -> 383.304 | M65: =I65-L65 -> 70.286 | N65: =(L65-E65)/E65 -> 0.14545618 | O65: =(M65-F65)/F65 -> -0.077853582 | P65: =M65/I65 -> 0.15495492
A66: Maia Moore | B66: 0 | C66: 34375 | D66: =($B$3-C66)/365 -> 29.490411 | E66: 342.46 | F66: 78 | G66: 420.46 | H66: ='[2]MEDICAL-Table Rates'!$S$41 -> 500.88 | I66: ='[2]MEDICAL-Table Rates'!$V$41 -> 474.18 | J66: =(I66-G66)/G66 -> 0.12776483 | K66: UHC Choice Platinum 500 | L66: =IF($N$1*H66>=I66,I66,$N$1*H66) -> 400.704 | M66: =I66-L66 -> 73.476 | N66: =(L66-E66)/E66 -> 0.17007534 | O66: =(M66-F66)/F66 -> -0.058 | P66: =M66/I66 -> 0.15495382
A67: Sarah F Smith | B67: 0 | C67: 31779 | D67: =($B$3-C67)/365 -> 36.60274 | E67: 403.22 | F67: 91.83 | G67: 495.05 | H67: ='[2]MEDICAL-Table Rates'!$S$52 -> 590.51 | I67: ='[2]MEDICAL-Table Rates'!$V$52 -> 559.03 | J67: =(I67-G67)/G67 -> 0.12923947 | K67: UHC Choice Platinum 500 | L67: =IF($N$1*H67>=I67,I67,$N$1*H67) -> 472.408 | M67: =I67-L67 -> 86.622 | N67: =(L67-E67)/E67 -> 0.17158871 | O67: =(M67-F67)/F67 -> -0.056713492 | P67: =M67/I67 -> 0.15495054
A68: Ukiah Busch | B68: 3 | C68: 31376 | D68: =($B$3-C68)/365 -> 37.706849 | E68: 1417.7 | F68: 322.91 | G68: 1740.61 | H68: ='[2]MEDICAL-Table Rates'!$S$54 -> 603.69 | I68: ='[2]MEDICAL-Table Rates'!$V$54+'[2]MEDICAL-Table Rates'!$V$52+(2*'[2]MEDICAL-Table Rates'!$V$16) -> 1946.62 | J68: =(I68-G68)/G68 -> 0.11835506 | K68: UHC Choice Platinum 500 | L68: =IF($N$1*H68+$P$1*SUM(H69:H71)>=I68,I68,$N$1*H68+$P$1*SUM(H69:H71)) -> 1644.992 | M68: =I68-L68 -> 301.628 | N68: =(L68-E68)/E68 -> 0.16032447 | O68: =(M68-F68)/F68 -> -0.065906909 | P68: =M68/I68 -> 0.1549496
D69: 36 | H69: ='[2]MEDICAL-Table Rates'!$S$52 -> 590.51
D70: 9 | H70: ='[2]MEDICAL-Table Rates'!$S$16 -> 431.02
D71: 5 | H71: ='[2]MEDICAL-Table Rates'!$S$16 -> 431.02
A72: Robert Colbry Maher | B72: 0 | C72: 34315 | D72: =($B$3-C72)/365 -> 29.654795 | E72: 342.46 | F72: 101.28 | G72: 443.74 | H72: ='[2]MEDICAL-Table Rates'!$S$41 -> 500.88 | I72: ='[2]MEDICAL-Table Rates'!$U$41 -> 517.74 | J72: =(I72-G72)/G72 -> 0.16676432 | K72: UHC Choice Plus Platinum 0-2 | L72: =IF($N$1*H72>=I72,I72,$N$1*H72) -> 400.704 | M72: =I72-L72 -> 117.036 | N72: =(L72-E72)/E72 -> 0.17007534 | O72: =(M72-F72)/F72 -> 0.15556872 | P72: =M72/I72 -> 0.22605169
A73: Abraham Cisne | B73: 0 | C73: 30417 | D73: =($B$3-C73)/365 -> 40.334247 | E73: 431.75 | F73: 127.69 | G73: 559.44 | H73: ='[2]MEDICAL-Table Rates'!$S$58 -> 642.57 | I73: ='[2]MEDICAL-Table Rates'!$U$58 -> 664.21 | J73: =(I73-G73)/G73 -> 0.18727656 | K73: UHC Choice Plus Platinum 0-2 | L73: =IF($N$1*H73>=I73,I73,$N$1*H73) -> 514.056 | M73: =I73-L73 -> 150.154 | N73: =(L73-E73)/E73 -> 0.19063347 | O73: =(M73-F73)/F73 -> 0.17592607 | P73: =M73/I73 -> 0.22606405
A74: Colleen Suzanne Boyne | B74: 0 | C74: 30382 | D74: =($B$3-C74)/365 -> 40.430137 | E74: 431.75 | F74: 127.69 | G74: 559.44 | H74: ='[2]MEDICAL-Table Rates'!$S$58 -> 642.57 | I74: ='[2]MEDICAL-Table Rates'!$U$58 -> 664.21 | J74: =(I74-G74)/G74 -> 0.18727656 | K74: UHC Choice Plus Platinum 0-2 | L74: =IF($N$1*H74>=I74,I74,$N$1*H74) -> 514.056 | M74: =I74-L74 -> 150.154 | N74: =(L74-E74)/E74 -> 0.19063347 | O74: =(M74-F74)/F74 -> 0.17592607 | P74: =M74/I74 -> 0.22606405
A75: Allison S McGovern | B75: 0 | C75: 35557 | D75: =($B$3-C75)/365 -> 26.252055 | E75: 334.63 | F75: 151.06 | G75: 485.69 | H75: ='[2]MEDICAL-Table Rates'!$S$28 -> 479.13 | I75: ='[2]MEDICAL-Table Rates'!$Y$36 -> 511.69 | J75: =(I75-G75)/G75 -> 0.053532088 | K75: UHC Choice Plus Platinum 250 | L75: =IF($N$1*H75>=I75,I75,$N$1*H75) -> 383.304 | M75: =I75-L75 -> 128.386 | N75: =(L75-E75)/E75 -> 0.14545618 | O75: =(M75-F75)/F75 -> -0.1500993 | P75: =M75/I75 -> 0.25090582
A76: Hannah Elizabeth Guernsey (COBRA) | B76: 0 | C76: 34137 | D76: =($B$3-C76)/365 -> 30.142466 | E76: 0 | F76: 507.74 | G76: 507.74 | H76: ='[2]MEDICAL-Table Rates'!$S$42 -> 513.4 | I76: ='[2]MEDICAL-Table Rates'!$Y$42 -> 548.29 | J76: =(I76-G76)/G76 -> 0.07986371 | K76: UHC Choice Plus Platinum 250 | L76: 0 | M76: =I76-L76 -> 548.29 | N76: =(L76-E76)/E76 -> #DIV/0! | O76: =(M76-F76)/F76 -> 0.07986371 | P76: =(N76-G76)/G76 -> #DIV/0!
L78: Monthly Cost based on 5/1 Invoice (less COBRAs) | M78: =SUM(E6:E75) -> 29245.45
L79: Estimated Monthly Cost Renewal 8.1.23 | M79: =SUM(L6:L76)-L76 -> 33947.246
L80: Difference | M80: =M79-M78 -> 4701.796
L81: Percentage Change | M81: =M80/M78 -> 0.16077017
L82: Annual Difference | M82: =M80*12 -> 56421.552

Sheet Partners 23-24 75%
A1: 2023 Benefits Worksheet | M1: Partners Covers | N1: 0.75 | O1: Employee | P1: 0.75 | Q1: Dependents
A2: 1 | N2: No Changes Employees Actual Choices on DCHL
A3: Renewal Date | B3: 45139
A4: Basic Demographic Data | E4: Current Premiums | H4: Renewal Information | K4: Plan Info
A5: Employee | B5: Covered Dependents | C5: DOB | D5: Renewal Age | E5: Partners Current Premium | F5: Employee Current Monthly Premium based on May Invoice | G5: Total Cost Current Premium | H5: Renewal Premium BlueChoice Plus Opt-Out Platinum 0 | I5: Renewal Cost Employee's Actual Plan | J5: Percentage Change on Actual Plan | K5: Employee's Actual Plan Choice | L5: Maximum Renewal Cost for Partners BlueChoice Plus Platinum 0 | M5: Employee Premium On Renewal | N5: Percentage Change for Partners | O5: Percentage Change for Employee | P5: Employee's % Cost of Premium
A6: Alexandra Lishansky | B6: 1 | C6: 34087 | D6: =($B$3-C6)/365 -> 30.279452 | E6: 650.85 | F6: 257.39 | G6: 908.24 | H6: ='[2]MEDICAL-Table Rates'!$S$42 -> 513.4 | I6: 1055.95 | J6: =(I6-G6)/G6 -> 0.16263322 | K6: BlueChoice Advantage Platinum 0 | L6: =IF($N$1*H6+$P$1*H7>=I6,I6,$N$1*H6+$P$1*H7) -> 708.315 | M6: =I6-L6 -> 347.635 | N6: =(L6-E6)/E6 -> 0.088292233 | O6: =(M6-F6)/F6 -> 0.3506158 | P6: =M6/I6 -> 0.3292154
D7: 1 | H7: ='[2]MEDICAL-Table Rates'!$S$16 -> 431.02
A8: Marcio Nascimento | B8: 0 | C8: 26679 | D8: =($B$3-C8)/365 -> 50.575342 | E8: 633.82 | F8: 112.9 | G8: 746.72 | H8: ='[2]MEDICAL-Table Rates'!$S$75 -> 943.1 | I8: 887.51 | J8: =(I8-G8)/G8 -> 0.18854457 | K8: BlueChoice HMO Referral Platinum 0 | L8: =IF($N$1*H8>=I8,I8,$N$1*H8) -> 707.325 | M8: =I8-L8 -> 180.185 | N8: =(L8-E8)/E8 -> 0.11597141 | O8: =(M8-F8)/F8 -> 0.59596988 | P8: =M8/I8 -> 0.20302306
A9: Penelope Kim | B9: 2 | C9: 31381 | D9: =($B$3-C9)/365 -> 37.693151 | E9: 1055.91 | F9: 263.97 | G9: 1319.88 | H9: ='[2]MEDICAL-Table Rates'!$S$54 -> 603.69 | I9: 1535.59 | J9: =(I9-G9)/G9 -> 0.16343152 | K9: BlueChoice Plus Opt-Out Platinum 0 | L9: =IF($N$1*H9+$P$1*SUM(H10:H11)>=I9,I9,$N$1*H9+$P$1*SUM(H10:H11)) -> 1151.6925 | M9: =I9-L9 -> 383.8975 | N9: =(L9-E9)/E9 -> 0.090710856 | O9: =(M9-F9)/F9 -> 0.45432246 | P9: =M9/I9 -> 0.25
D10: 29 | H10: ='[2]MEDICAL-Table Rates'!$S$41 -> 500.88
D11: 0 | H11: ='[2]MEDICAL-Table Rates'!$S$16 -> 431.02
A12: Michael B Moscarelli | B12: 4 | C12: 30749 | D12: =($B$3-C12)/365 -> 39.424658 | E12: 1733 | F12: 433.25 | G12: 2166.25 | H12: ='[2]MEDICAL-Table Rates'!$S$57 -> 618.19 | I12: 2501.76 | J12: =(I12-G12)/G12 -> 0.15488055 | K12: BlueChoice Plus Opt-Out Platinum 0 | L12: =IF($N$1*H12+$P$1*SUM(H13:H16)>=I12,I12,$N$1*H12+$P$1*SUM(H13:H16)) -> 1876.32 | M12: =I12-L12 -> 625.44 | N12: =(L12-E12)/E12 -> 0.082700519 | O12: =(M12-F12)/F12 -> 0.44360069 | P12: =M12/I12 -> 0.25
D13: 36 | H13: ='[2]MEDICAL-Table Rates'!$S$52 -> 590.51
D14: 6 | H14: ='[2]MEDICAL-Table Rates'!$S$16 -> 431.02
D15: 3 | H15: ='[2]MEDICAL-Table Rates'!$S$16 -> 431.02
D16: 0 | H16: ='[2]MEDICAL-Table Rates'!$S$16 -> 431.02
A17: Ana Aslan | B17: 1 | C17: 24458 | D17: =($B$3-C17)/365 -> 56.660274 | E17: 1758.76 | F17: 439.69 | G17: 2198.45 | H17: 1186.95 | I17: 2518.23 | J17: =(I17-G17)/G17 -> 0.14545703 | K17: BlueChoice Plus Opt-Out Platinum 0 | L17: =IF($N$1*H17+$P$1*H18>=I17,I17,$N$1*H17+$P$1*H18) -> 1888.6725 | M17: =I17-L17 -> 629.5575 | N17: =(L17-E17)/E17 -> 0.073865962 | O17: =(M17-F17)/F17 -> 0.43182128 | P17: =M17/I17 -> 0.25
D18: 59 | H18: ='[2]MEDICAL-Table Rates'!$S$89 -> 1331.28
A19: Lesly Yohana Rubio | B19: 0 | C19: 31552 | D19: =($B$3-C19)/365 -> 37.224658 | E19: 412.42 | F19: 249.96 | G19: 662.38 | H19: ='[2]MEDICAL-Table Rates'!$S$54 -> 603.69 | I19: 765.65 | J19: =(I19-G19)/G19 -> 0.15590749 | K19: BluePreferred PPO Platinum 0 | L19: =IF($N$1*H19>=I19,I19,$N$1*H19) -> 452.7675 | M19: =I19-L19 -> 312.8825 | N19: =(L19-E19)/E19 -> 0.097831095 | O19: =(M19-F19)/F19 -> 0.25173028 | P19: =M19/I19 -> 0.40864951
A20: Carmen Pena | B20: 2 | C20: 31899 | D20: =($B$3-C20)/365 -> 36.273973 | E20: 1116.67 | F20: 676.78 | G20: 1793.45 | H20: ='[2]MEDICAL-Table Rates'!$S$52 -> 590.51 | I20: 2061.23 | J20: =(I20-G20)/G20 -> 0.14930999 | K20: BluePreferred PPO Platinum 0 | L20: =IF($N$1*H20+$P$1*SUM(H21:H22)>=I20,I20,$N$1*H20+$P$1*SUM(H21:H22)) -> 1218.915 | M20: =I20-L20 -> 842.315 | N20: =(L20-E20)/E20 -> 0.091562413 | O20: =(M20-F20)/F20 -> 0.24459204 | P20: =M20/I20 -> 0.40864678
D21: 37 | H21: ='[2]MEDICAL-Table Rates'!$S$54 -> 603.69
D22: 5 | H22: ='[2]MEDICAL-Table Rates'!$S$16 -> 431.02
A23: Kelly M McNally | B23: 0 | C23: 34588 | D23: =($B$3-C23)/365 -> 28.906849 | E23: 334.63 | F23: 117.07 | G23: 451.7 | H23: ='[2]MEDICAL-Table Rates'!$S$39 -> 490.33 | I23: 534.96 | J23: =(I23-G23)/G23 -> 0.18432588 | K23: HealthyBlue Advantage Platinum 500 | L23: =IF($N$1*H23>=I23,I23,$N$1*H23) -> 367.7475 | M23: =I23-L23 -> 167.2125 | N23: =(L23-E23)/E23 -> 0.098967516 | O23: =(M23-F23)/F23 -> 0.42831212 | P23: =M23/I23 -> 0.3125701
A24: Susanna J Meyer | B24: 0 | C24: 33900 | D24: =($B$3-C24)/365 -> 30.791781 | E24: 349.82 | F24: 122.38 | G24: 472.2 | H24: ='[2]MEDICAL-Table Rates'!$S$42 -> 513.4 | I24: 560.12 | J24: =(I24-G24)/G24 -> 0.18619229 | K24: HealthyBlue Advantage Platinum 500 | L24: =IF($N$1*H24>=I24,I24,$N$1*H24) -> 385.05 | M24: =I24-L24 -> 175.07 | N24: =(L24-E24)/E24 -> 0.10070894 | O24: =(M24-F24)/F24 -> 0.43054421 | P24: =M24/I24 -> 0.31255802
A25: Madeline Rae Steiner | B25: 0 | C25: 33765 | D25: =($B$3-C25)/365 -> 31.161644 | E25: 358.57 | F25: 125.44 | G25: 484.01 | H25: ='[2]MEDICAL-Table Rates'!$S$44 -> 526.58 | I25: 574.5 | J25: =(I25-G25)/G25 -> 0.18695895 | K25: HealthyBlue Advantage Platinum 500 | L25: =IF($N$1*H25>=I25,I25,$N$1*H25) -> 394.935 | M25: =I25-L25 -> 179.565 | N25: =(L25-E25)/E25 -> 0.10141674 | O25: =(M25-F25)/F25 -> 0.43148119 | P25: =M25/I25 -> 0.31255875
A26: Stephanie Monroy | B26: 0 | C26: 31116 | D26: =($B$3-C26)/365 -> 38.419178 | E26: 426.69 | F26: 149.27 | G26: 575.96 | H26: ='[2]MEDICAL-Table Rates'!$S$55 -> 610.94 | I26: 666.54 | J26: =(I26-G26)/G26 -> 0.15726787 | K26: HealthyBlue Advantage Platinum 500 | L26: =IF($N$1*H26>=I26,I26,$N$1*H26) -> 458.205 | M26: =I26-L26 -> 208.335 | N26: =(L26-E26)/E26 -> 0.073859242 | O26: =(M26-F26)/F26 -> 0.39569237 | P26: =M26/I26 -> 0.31256189
A27: Kirk Amper Del Rosario | B27: 0 | C27: 33886 | D27: =($B$3-C27)/365 -> 30.830137 | E27: 349.82 | F27: 75.87 | G27: 425.69 | H27: ='[2]MEDICAL-Table Rates'!$S$42 -> 513.4 | I27: 504.65 | J27: =(I27-G27)/G27 -> 0.18548709 | K27: HealthyBlue Plus Platinum 500 | L27: =IF($N$1*H27>=I27,I27,$N$1*H27) -> 385.05 | M27: =I27-L27 -> 119.6 | N27: =(L27-E27)/E27 -> 0.10070894 | O27: =(M27-F27)/F27 -> 0.57638065 | P27: =M27/I27 -> 0.23699594
A28: Sara Jebena | B28: 0 | C28: 29996 | D28: =($B$3-C28)/365 -> 41.487671 | E28: 448.78 | F28: 97.34 | G28: 546.12 | H28: ='[2]MEDICAL-Table Rates'!$S$60 -> 667.62 | I28: 656.24 | J28: =(I28-G28)/G28 -> 0.20164067 | K28: HealthyBlue Plus Platinum 500 | L28: =IF($N$1*H28>=I28,I28,$N$1*H28) -> 500.715 | M28: =I28-L28 -> 155.525 | N28: =(L28-E28)/E28 -> 0.11572485 | O28: =(M28-F28)/F28 -> 0.59775015 | P28: =M28/I28 -> 0.23699409
A29: Summar T Lyons | B29: 1 | C29: 31217 | D29: =($B$3-C29)/365 -> 38.142466 | E29: 887.89 | F29: 192.58 | G29: 1080.47 | H29: ='[2]MEDICAL-Table Rates'!$S$55 -> 610.94 | I29: 1282.68 | J29: =(I29-G29)/G29 -> 0.18715004 | K29: HealthyBlue Plus Platinum 500 | L29: =IF($N$1*H29+$P$1*H30>=I29,I29,$N$1*H29+$P$1*H30) -> 978.69 | M29: =I29-L29 -> 303.99 | N29: =(L29-E29)/E29 -> 0.10226492 | O29: =(M29-F29)/F29 -> 0.57851283 | P29: =M29/I29 -> 0.23699598
D30: 42 | H30: ='[2]MEDICAL-Table Rates'!$S$62 -> 693.98
A31: Armin Cordova | B31: 0 | C31: 35369 | D31: =($B$3-C31)/365 -> 26.767123 | E31: 324.42 | F31: 0 | G31: 324.42 | H31: ='[2]MEDICAL-Table Rates'!$S$28 -> 479.13 | I31: 374.63 | J31: =(I31-G31)/G31 -> 0.15476851 | K31: KP DC Platinum 0/10/Vision | L31: =IF($N$1*H31>=I31,I31,$N$1*H31) -> 359.3475 | M31: =I31-L31 -> 15.2825 | N31: =(L31-E31)/E31 -> 0.10766136 | O31: =(M31-F31)/F31 -> #DIV/0! | P31: =M31/I31 -> 0.040793583
A32: Megan Michelle Ash | B32: 0 | C32: 34295 | D32: =($B$3-C32)/365 -> 29.709589 | E32: 332 | F32: 0 | G32: 332 | H32: 500.88 | I32: 391.63 | J32: =(I32-G32)/G32 -> 0.17960843 | K32: KP DC Platinum 0/10/Vision | L32: =IF($N$1*H32>=I32,I32,$N$1*H32) -> 375.66 | M32: =I32-L32 -> 15.97 | N32: =(L32-E32)/E32 -> 0.13150602 | O32: =(M32-F32)/F32 -> #DIV/0! | P32: =M32/I32 -> 0.040778286
A33: Stephanie Verganza | B33: 0 | C33: 33576 | D33: =($B$3-C33)/365 -> 31.679452 | E33: 347.62 | F33: 0 | G33: 347.62 | H33: 526.58 | I33: 411.73 | J33: =(I33-G33)/G33 -> 0.18442552 | K33: KP DC Platinum 0/10/Vision | L33: =IF($N$1*H33>=I33,I33,$N$1*H33) -> 394.935 | M33: =I33-L33 -> 16.795 | N33: =(L33-E33)/E33 -> 0.13611127 | O33: =(M33-F33)/F33 -> #DIV/0! | P33: =M33/I33 -> 0.040791295
A34: Anh H Nguyen | B34: 1 | C34: 33338 | D34: =($B$3-C34)/365 -> 32.331507 | E34: 680.97 | F34: 0 | G34: 680.97 | H34: ='[2]MEDICAL-Table Rates'!$S$45 -> 538.44 | I34: =421.01+383.39 -> 804.4 | J34: =(I34-G34)/G34 -> 0.18125615 | K34: KP DC Platinum 0/10/Vision | L34: =IF($N$1*H34+$P$1*H35>=I34,I34,$N$1*H34+$P$1*H35) -> 771.5775 | M34: =I34-L34 -> 32.8225 | N34: =(L34-E34)/E34 -> 0.13305652 | O34: =(M34-F34)/F34 -> #DIV/0! | P34: =M34/I34 -> 0.040803705
D35: 28 | H35: ='[2]MEDICAL-Table Rates'!$S$39 -> 490.33
A36: Janira J Romero Reyes | B36: 1 | C36: 31561 | D36: =($B$3-C36)/365 -> 37.2 | E36: 691.67 | F36: 0 | G36: 691.67 | H36: 603.69 | I36: =472.02+337.01 -> 809.03 | J36: =(I36-G36)/G36 -> 0.16967629 | K36: KP DC Platinum 0/10/Vision | L36: =IF($N$1*H36+$P$1*H37>=I36,I36,$N$1*H36+$P$1*H37) -> 776.0325 | M36: =I36-L36 -> 32.9975 | N36: =(L36-E36)/E36 -> 0.12196929 | O36: =(M36-F36)/F36 -> #DIV/0! | P36: =M36/I36 -> 0.040786497
D37: 0 | H37: ='[2]MEDICAL-Table Rates'!$S$16 -> 431.02
A38: Danielle R Martin | B38: 1 | C38: 33497 | D38: =($B$3-C38)/365 -> 31.89589 | E38: 695.24 | F38: 0 | G38: 695.24 | H38: ='[2]MEDICAL-Table Rates'!$S$44 -> 526.58 | I38: =395.9*2 -> 791.8 | J38: =(I38-G38)/G38 -> 0.13888729 | K38: KP DC Platinum 0/10/Vision | L38: =IF($N$1*H38+$P$1*H39>=I38,I38,$N$1*H38+$P$1*H39) -> 789.87 | M38: =I38-L38 -> 1.93 | N38: =(L38-E38)/E38 -> 0.13611127 | O38: =(M38-F38)/F38 -> #DIV/0! | P38: =M38/I38 -> 0.0024374842
D39: 31 | H39: ='[2]MEDICAL-Table Rates'!$S$44 -> 526.58
A40: William D Webber | B40: 1 | C40: 34122 | D40: =($B$3-C40)/365 -> 30.183562 | E40: 738.97 | F40: 0 | G40: 738.97 | H40: ='[2]MEDICAL-Table Rates'!$S$42 -> 513.4 | I40: =453.87+385.99 -> 839.86 | J40: =(I40-G40)/G40 -> 0.13652787 | K40: KP DC Platinum 0/10/Vision | L40: =IF($N$1*H40+$P$1*H41>=I40,I40,$N$1*H40+$P$1*H41) -> 837.8175 | M40: =I40-L40 -> 2.0425 | N40: =(L40-E40)/E40 -> 0.13376389 | O40: =(M40-F40)/F40 -> #DIV/0! | P40: =M40/I40 -> 0.0024319529
D41: 37 | H41: ='[2]MEDICAL-Table Rates'!$S$54 -> 603.69
A42: Debra L Cooper | B42: 0 | C42: 24504 | D42: =($B$3-C42)/365 -> 56.534247 | E42: 773.34 | F42: 0 | G42: 773.34 | H42: ='[2]MEDICAL-Table Rates'!$S$84 -> 1186.95 | I42: 892.38 | J42: =(I42-G42)/G42 -> 0.15392971 | K42: KP DC Platinum 0/10/Vision | L42: =IF($N$1*H42>=I42,I42,$N$1*H42) -> 890.2125 | M42: =I42-L42 -> 2.1675 | N42: =(L42-E42)/E42 -> 0.15112693 | O42: =(M42-F42)/F42 -> #DIV/0! | P42: =M42/I42 -> 0.002428898
A43: Pablo Marcelo Gonzalez | B43: 1 | C43: 28690 | D43: =($B$3-C43)/365 -> 45.065753 | E43: 1054.92 | F43: 0 | G43: 1054.92 | H43: 778.34 | I43: =585.17+631.75 -> 1216.92 | J43: =(I43-G43)/G43 -> 0.15356615 | K43: KP DC Platinum 0/10/Vision | L43: =IF($N$1*H43+$P$1*H44>=I43,I43,$N$1*H43+$P$1*H44) -> 1213.9725 | M43: =I43-L43 -> 2.9475 | N43: =(L43-E43)/E43 -> 0.1507721 | O43: =(M43-F43)/F43 -> #DIV/0! | P43: =M43/I43 -> 0.0024220984
D44: 47 | H44: ='[2]MEDICAL-Table Rates'!$S$70 -> 840.29
A45: Sheila Ann Posas | B45: 3 | C45: 27512 | D45: =($B$3-C45)/365 -> 48.293151 | E45: 1700.18 | F45: 0 | G45: 1700.18 | H45: ='[2]MEDICAL-Table Rates'!$S$71 -> 873.24 | I45: =682.78+632.28+(337.01*2) -> 1989.08 | J45: =(I45-G45)/G45 -> 0.16992318 | K45: KP DC Platinum 0/10/Vision | L45: =IF($N$1*H45+$P$1*SUM(H46:H48)>=I45,I45,$N$1*H45+$P$1*SUM(H46:H48)) -> 1907.9475 | M45: =I45-L45 -> 81.1325 | N45: =(L45-E45)/E45 -> 0.12220324 | O45: =(M45-F45)/F45 -> #DIV/0! | P45: =M45/I45 -> 0.040788958
D46: 46 | H46: ='[2]MEDICAL-Table Rates'!$S$68 -> 808.65
D47: 10 | H47: ='[2]MEDICAL-Table Rates'!$S$16 -> 431.02
D48: 7 | H48: ='[2]MEDICAL-Table Rates'!$S$16 -> 431.02
A49: Mariana Cabrera | B49: 0 | C49: 36111 | D49: =($B$3-C49)/365 -> 24.734247 | E49: 334.63 | F49: 16.28 | G49: 350.91 | H49: ='[2]MEDICAL-Table Rates'!$S$28 -> 479.13 | I49: 391.62 | J49: =(I49-G49)/G49 -> 0.11601265 | K49: KP DC Platinum Added Choice 0/10/POS/Vision | L49: =IF($N$1*H49>=I49,I49,$N$1*H49) -> 359.3475 | M49: =I49-L49 -> 32.2725 | N49: =(L49-E49)/E49 -> 0.073865165 | O49: =(M49-F49)/F49 -> 0.98234029 | P49: =M49/I49 -> 0.082407691
A50: Natalie M Abegesah | B50: 3 | C50: 31872 | D50: =($B$3-C50)/365 -> 36.347945 | E50: 1417.7 | F50: 68.98 | G50: 1486.68 | H50: ='[2]MEDICAL-Table Rates'!$S$52 -> 590.51 | I50: =482.65+493.43+352.29+352.29 -> 1680.66 | J50: =(I50-G50)/G50 -> 0.13047865 | K50: KP DC Platinum Added Choice 0/10/POS/Vision | L50: =IF($N$1*H50+$P$1*SUM(H51:H53)>=I50,I50,$N$1*H50+$P$1*SUM(H51:H53)) -> 1542.18 | M50: =I50-L50 -> 138.48 | N50: =(L50-E50)/E50 -> 0.08780419 | O50: =(M50-F50)/F50 -> 1.0075384 | P50: =M50/I50 -> 0.082396201
D51: 37 | H51: ='[2]MEDICAL-Table Rates'!$S$54 -> 603.69
D52: 17 | H52: ='[2]MEDICAL-Table Rates'!$S$16 -> 431.02
D53: 15 | H53: ='[2]MEDICAL-Table Rates'!$S$16 -> 431.02
A54: Nilu Rimal | B54: 1 | C54: 24635 | D54: =($B$3-C54)/365 -> 56.175342 | E54: 1727.46 | F54: 84.05 | G54: 1811.51 | H54: ='[2]MEDICAL-Table Rates'!$S$84 -> 1186.95 | I54: =970.15+1088.12 -> 2058.27 | J54: =(I54-G54)/G54 -> 0.13621785 | K54: KP DC Platinum Added Choice 0/10/POS/Vision | L54: =IF($N$1*H54+$P$1*H55>=I54,I54,$N$1*H54+$P$1*H55) -> 1888.6725 | M54: =I54-L54 -> 169.5975 | N54: =(L54-E54)/E54 -> 0.093323434 | O54: =(M54-F54)/F54 -> 1.0178168 | P54: =M54/I54 -> 0.082398082
D55: 59 | H55: ='[2]MEDICAL-Table Rates'!$S$89 -> 1331.28
A56: Genesis C Torres-Alcantara | B56: 0 | C56: 34977 | D56: =($B$3-C56)/365 -> 27.841096 | E56: 334.63 | F56: 2.76 | G56: 337.39 | H56: ='[2]MEDICAL-Table Rates'!$S$28 -> 479.13 | I56: 374.63 | J56: =(I56-G56)/G56 -> 0.11037672 | K56: KP DC Platinum HMO Plus 0/10/Vision | L56: =IF($N$1*H56>=I56,I56,$N$1*H56) -> 359.3475 | M56: =I56-L56 -> 15.2825 | N56: =(L56-E56)/E56 -> 0.073865165 | O56: =(M56-F56)/F56 -> 4.5371377 | P56: =M56/I56 -> 0.040793583
A57: Arlette G Gutierrez | B57: 0 | C57: 28471 | D57: =($B$3-C57)/365 -> 45.665753 | E57: 523.34 | F57: 4.33 | G57: 527.67 | H57: ='[2]MEDICAL-Table Rates'!$S$66 -> 778.34 | I57: 605.58 | J57: =(I57-G57)/G57 -> 0.1476491 | K57: KP DC Platinum HMO Plus 0/10/Vision | L57: =IF($N$1*H57>=I57,I57,$N$1*H57) -> 583.755 | M57: =I57-L57 -> 21.825 | N57: =(L57-E57)/E57 -> 0.1154412 | O57: =(M57-F57)/F57 -> 4.0404157 | P57: =M57/I57 -> 0.03603983
A58: John Robert McPhail | B58: 4 | C58: 25137 | D58: =($B$3-C58)/365 -> 54.8 | E58: 2342.87 | F58: 19.35 | G58: 2362.22 | H58: ='[2]MEDICAL-Table Rates'!$S$81 -> 1099.3 | I58: =859.53+737.4+(374.63*2)+337.01 -> 2683.2 | J58: =(I58-G58)/G58 -> 0.13588065 | K58: KP DC Platinum HMO Plus 0/10/Vision | L58: =IF($N$1*H58+$P$1*SUM(H59:H62)>=I58,I58,$N$1*H58+$P$1*SUM(H59:H62)) -> 2573.76 | M58: =I58-L58 -> 109.44 | N58: =(L58-E58)/E58 -> 0.098550069 | O58: =(M58-F58)/F58 -> 4.655814 | P58: =M58/I58 -> 0.04078712
D59: 50 | H59: ='[2]MEDICAL-Table Rates'!$S$75 -> 943.1
D60: 25 | H60: ='[2]MEDICAL-Table Rates'!$S$28 -> 479.13
D61: 24 | H61: ='[2]MEDICAL-Table Rates'!$S$28 -> 479.13
D62: 19 | H62: ='[2]MEDICAL-Table Rates'!$S$16 -> 431.02
A63: Rachel Shoshana Falek | B63: 0 | C63: 35017 | D63: =($B$3-C63)/365 -> 27.731507 | E63: 334.63 | F63: 159.88 | G63: 494.51 | H63: ='[2]MEDICAL-Table Rates'!$S$28 -> 479.13 | I63: ='[2]MEDICAL-Table Rates'!$Z$37 -> 519.12 | J63: =(I63-G63)/G63 -> 0.049766435 | K63: UHC Choice Platinum 0 | L63: =IF($N$1*H63>=I63,I63,$N$1*H63) -> 359.3475 | M63: =I63-L63 -> 159.7725 | N63: =(L63-E63)/E63 -> 0.073865165 | O63: =(M63-F63)/F63 -> -0.00067237928 | P63: =M63/I63 -> 0.30777566
A64: Angel Kristina Rutter | B64: 0 | C64: 35099 | D64: =($B$3-C64)/365 -> 27.506849 | E64: 334.63 | F64: 76.22 | G64: 410.85 | H64: ='[2]MEDICAL-Table Rates'!$S$28 -> 479.13 | I64: ='[2]MEDICAL-Table Rates'!$V$37 -> 453.59 | J64: =(I64-G64)/G64 -> 0.10402823 | K64: UHC Choice Platinum 500 | L64: =IF($N$1*H64>=I64,I64,$N$1*H64) -> 359.3475 | M64: =I64-L64 -> 94.2425 | N64: =(L64-E64)/E64 -> 0.073865165 | O64: =(M64-F64)/F64 -> 0.23645369 | P64: =M64/I64 -> 0.20777023
A65: Katherine Julia Matteson de Araujo | B65: 0 | C65: 35229 | D65: =($B$3-C65)/365 -> 27.150685 | E65: 334.63 | F65: 76.22 | G65: 410.85 | H65: ='[2]MEDICAL-Table Rates'!$S$28 -> 479.13 | I65: ='[2]MEDICAL-Table Rates'!$V$37 -> 453.59 | J65: =(I65-G65)/G65 -> 0.10402823 | K65: UHC Choice Platinum 500 | L65: =IF($N$1*H65>=I65,I65,$N$1*H65) -> 359.3475 | M65: =I65-L65 -> 94.2425 | N65: =(L65-E65)/E65 -> 0.073865165 | O65: =(M65-F65)/F65 -> 0.23645369 | P65: =M65/I65 -> 0.20777023
A66: Maia Moore | B66: 0 | C66: 34375 | D66: =($B$3-C66)/365 -> 29.490411 | E66: 342.46 | F66: 78 | G66: 420.46 | H66: ='[2]MEDICAL-Table Rates'!$S$41 -> 500.88 | I66: ='[2]MEDICAL-Table Rates'!$V$41 -> 474.18 | J66: =(I66-G66)/G66 -> 0.12776483 | K66: UHC Choice Platinum 500 | L66: =IF($N$1*H66>=I66,I66,$N$1*H66) -> 375.66 | M66: =I66-L66 -> 98.52 | N66: =(L66-E66)/E66 -> 0.096945629 | O66: =(M66-F66)/F66 -> 0.26307692 | P66: =M66/I66 -> 0.2077692
A67: Sarah F Smith | B67: 0 | C67: 31779 | D67: =($B$3-C67)/365 -> 36.60274 | E67: 403.22 | F67: 91.83 | G67: 495.05 | H67: ='[2]MEDICAL-Table Rates'!$S$52 -> 590.51 | I67: ='[2]MEDICAL-Table Rates'!$V$52 -> 559.03 | J67: =(I67-G67)/G67 -> 0.12923947 | K67: UHC Choice Platinum 500 | L67: =IF($N$1*H67>=I67,I67,$N$1*H67) -> 442.8825 | M67: =I67-L67 -> 116.1475 | N67: =(L67-E67)/E67 -> 0.098364416 | O67: =(M67-F67)/F67 -> 0.26480997 | P67: =M67/I67 -> 0.20776613
A68: Ukiah Busch | B68: 3 | C68: 31376 | D68: =($B$3-C68)/365 -> 37.706849 | E68: 1417.7 | F68: 322.91 | G68: 1740.61 | H68: ='[2]MEDICAL-Table Rates'!$S$54 -> 603.69 | I68: ='[2]MEDICAL-Table Rates'!$V$54+'[2]MEDICAL-Table Rates'!$V$52+(2*'[2]MEDICAL-Table Rates'!$V$16) -> 1946.62 | J68: =(I68-G68)/G68 -> 0.11835506 | K68: UHC Choice Platinum 500 | L68: =IF($N$1*H68+$P$1*SUM(H69:H71)>=I68,I68,$N$1*H68+$P$1*SUM(H69:H71)) -> 1542.18 | M68: =I68-L68 -> 404.44 | N68: =(L68-E68)/E68 -> 0.08780419 | O68: =(M68-F68)/F68 -> 0.25248521 | P68: =M68/I68 -> 0.20776525
D69: 36 | H69: ='[2]MEDICAL-Table Rates'!$S$52 -> 590.51
D70: 9 | H70: ='[2]MEDICAL-Table Rates'!$S$16 -> 431.02
D71: 5 | H71: ='[2]MEDICAL-Table Rates'!$S$16 -> 431.02
A72: Robert Colbry Maher | B72: 0 | C72: 34315 | D72: =($B$3-C72)/365 -> 29.654795 | E72: 342.46 | F72: 101.28 | G72: 443.74 | H72: ='[2]MEDICAL-Table Rates'!$S$41 -> 500.88 | I72: ='[2]MEDICAL-Table Rates'!$U$41 -> 517.74 | J72: =(I72-G72)/G72 -> 0.16676432 | K72: UHC Choice Plus Platinum 0-2 | L72: =IF($N$1*H72>=I72,I72,$N$1*H72) -> 375.66 | M72: =I72-L72 -> 142.08 | N72: =(L72-E72)/E72 -> 0.096945629 | O72: =(M72-F72)/F72 -> 0.4028436 | P72: =M72/I72 -> 0.27442346
A73: Abraham Cisne | B73: 0 | C73: 30417 | D73: =($B$3-C73)/365 -> 40.334247 | E73: 431.75 | F73: 127.69 | G73: 559.44 | H73: ='[2]MEDICAL-Table Rates'!$S$58 -> 642.57 | I73: ='[2]MEDICAL-Table Rates'!$U$58 -> 664.21 | J73: =(I73-G73)/G73 -> 0.18727656 | K73: UHC Choice Plus Platinum 0-2 | L73: =IF($N$1*H73>=I73,I73,$N$1*H73) -> 481.9275 | M73: =I73-L73 -> 182.2825 | N73: =(L73-E73)/E73 -> 0.11621888 | O73: =(M73-F73)/F73 -> 0.42753935 | P73: =M73/I73 -> 0.27443504
A74: Colleen Suzanne Boyne | B74: 0 | C74: 30382 | D74: =($B$3-C74)/365 -> 40.430137 | E74: 431.75 | F74: 127.69 | G74: 559.44 | H74: ='[2]MEDICAL-Table Rates'!$S$58 -> 642.57 | I74: ='[2]MEDICAL-Table Rates'!$U$58 -> 664.21 | J74: =(I74-G74)/G74 -> 0.18727656 | K74: UHC Choice Plus Platinum 0-2 | L74: =IF($N$1*H74>=I74,I74,$N$1*H74) -> 481.9275 | M74: =I74-L74 -> 182.2825 | N74: =(L74-E74)/E74 -> 0.11621888 | O74: =(M74-F74)/F74 -> 0.42753935 | P74: =M74/I74 -> 0.27443504
A75: Allison S McGovern | B75: 0 | C75: 35557 | D75: =($B$3-C75)/365 -> 26.252055 | E75: 334.63 | F75: 151.06 | G75: 485.69 | H75: ='[2]MEDICAL-Table Rates'!$S$28 -> 479.13 | I75: ='[2]MEDICAL-Table Rates'!$Y$36 -> 511.69 | J75: =(I75-G75)/G75 -> 0.053532088 | K75: UHC Choice Plus Platinum 250 | L75: =IF($N$1*H75>=I75,I75,$N$1*H75) -> 359.3475 | M75: =I75-L75 -> 152.3425 | N75: =(L75-E75)/E75 -> 0.073865165 | O75: =(M75-F75)/F75 -> 0.008490004 | P75: =M75/I75 -> 0.29772421
A76: Hannah Elizabeth Guernsey (COBRA) | B76: 0 | C76: 34137 | D76: =($B$3-C76)/365 -> 30.142466 | E76: 0 | F76: 507.74 | G76: 507.74 | H76: ='[2]MEDICAL-Table Rates'!$S$42 -> 513.4 | I76: ='[2]MEDICAL-Table Rates'!$Y$42 -> 548.29 | J76: =(I76-G76)/G76 -> 0.07986371 | K76: UHC Choice Plus Platinum 250 | L76: 0 | M76: =I76-L76 -> 548.29 | N76: =(L76-E76)/E76 -> #DIV/0! | O76: =(M76-F76)/F76 -> 0.07986371 | P76: =(N76-G76)/G76 -> #DIV/0!
L78: Monthly Cost based on 5/1 Invoice (less COBRAs) | M78: =SUM(E6:E75) -> 29245.45
L79: Estimated Monthly Cost Renewal 8.1.23 | M79: =SUM(L6:L76)-L76 -> 32236.463
L80: Difference | M80: =M79-M78 -> 2991.0125
L81: Percentage Change | M81: =M80/M78 -> 0.10227275
L82: Annual Difference | M82: =M80*12 -> 35892.15

Sheet Prtnrs Change Ref to Gold HRA
A1: 2023 Benefits Worksheet | M1: Partners Covers | N1: 0.8 | O1: Employee | P1: 0.8 | Q1: Dependents
A2: 1 | N2: No Changes Employees Actual Choices on DCHL
A3: Renewal Date | B3: 45139
A4: Basic Demographic Data | E4: Current Premiums | H4: Renewal Information | K4: Plan Info
A5: Employee | B5: Covered Dependents | C5: DOB | D5: Renewal Age | E5: Partners Current Premium | F5: Employee Current Monthly Premium based on May Invoice | G5: Total Cost Current Premium | H5: Renewal Premium BlueChoice Advantage HDHP/HSA/HRA Gold Plan - $1,500 | I5: Renewal Cost Employee's Actual Plan | J5: Percentage Change on Actual Plan | K5: Employee's Actual Plan Choice | L5: Maximum Renewal Cost for Partners BlueChoice Advantage HDHP/HSA/HRA Gold Plan - $1,500 | M5: Employee Premium On Renewal | N5: Percentage Change for Partners | O5: Percentage Change for Employee | P5: Employee's % Cost of Premium
A6: Alexandra Lishansky | B6: 1 | C6: 34087 | D6: =($B$3-C6)/365 -> 30.279452 | E6: 650.85 | F6: 257.39 | G6: 908.24 | H6: 461.62 | I6: =SUM(H6:H7) -> 849.17 | J6: =(I6-G6)/G6 -> -0.065037875 | K6: BlueChoice Advantage HDHP/HSA/HRA Gold Plan - $1,500 | L6: =IF($N$1*H6+$P$1*H7>=I6,I6,$N$1*H6+$P$1*H7) -> 679.336 | M6: =I6-L6 -> 169.834 | N6: =(L6-E6)/E6 -> 0.043767381 | O6: =(M6-F6)/F6 -> -0.34016862 | P6: =M6/I6 -> 0.2
D7: 1 | H7: 387.55
A8: Marcio Nascimento | B8: 0 | C8: 26679 | D8: =($B$3-C8)/365 -> 50.575342 | E8: 633.82 | F8: 112.9 | G8: 746.72 | H8: 847.98 | I8: =H8 -> 847.98 | J8: =(I8-G8)/G8 -> 0.13560639 | K8: BlueChoice Advantage HDHP/HSA/HRA Gold Plan - $1,500 | L8: =IF($N$1*H8>=I8,I8,$N$1*H8) -> 678.384 | M8: =I8-L8 -> 169.596 | N8: =(L8-E8)/E8 -> 0.070310183 | O8: =(M8-F8)/F8 -> 0.50217892 | P8: =M8/I8 -> 0.2
A9: Penelope Kim | B9: 2 | C9: 31381 | D9: =($B$3-C9)/365 -> 37.693151 | E9: 1055.91 | F9: 263.97 | G9: 1319.88 | H9: 542.8 | I9: =SUM(H9:H11) -> 1380.71 | J9: =(I9-G9)/G9 -> 0.046087523 | K9: BlueChoice Advantage HDHP/HSA/HRA Gold Plan - $1,500 | L9: =IF($N$1*H9+$P$1*SUM(H10:H11)>=I9,I9,$N$1*H9+$P$1*SUM(H10:H11)) -> 1104.568 | M9: =I9-L9 -> 276.142 | N9: =(L9-E9)/E9 -> 0.046081579 | O9: =(M9-F9)/F9 -> 0.046111301 | P9: =M9/I9 -> 0.2
D10: 29 | H10: 450.36
D11: 0 | H11: 387.55
A12: Michael B Moscarelli | B12: 4 | C12: 30749 | D12: =($B$3-C12)/365 -> 39.424658 | E12: 1733 | F12: 433.25 | G12: 2166.25 | H12: 555.84 | I12: =SUM(H12:H16) -> 2249.44 | J12: =(I12-G12)/G12 -> 0.03840277 | K12: BlueChoice Advantage HDHP/HSA/HRA Gold Plan - $1,500 | L12: =IF($N$1*H12+$P$1*SUM(H13:H16)>=I12,I12,$N$1*H12+$P$1*SUM(H13:H16)) -> 1799.552 | M12: =I12-L12 -> 449.888 | N12: =(L12-E12)/E12 -> 0.03840277 | O12: =(M12-F12)/F12 -> 0.03840277 | P12: =M12/I12 -> 0.2
D13: 36 | H13: 530.95
D14: 6 | H14: 387.55
D15: 3 | H15: 387.55
D16: 0 | H16: 387.55
A17: Ana Aslan | B17: 1 | C17: 24458 | D17: =($B$3-C17)/365 -> 56.660274 | E17: 1758.76 | F17: 439.69 | G17: 2198.45 | H17: 1067.24 | I17: =SUM(H17:H18) -> 2264.25 | J17: =(I17-G17)/G17 -> 0.029930178 | K17: BlueChoice Advantage HDHP/HSA/HRA Gold Plan - $1,500 | L17: =IF($N$1*H17+$P$1*H18>=I17,I17,$N$1*H17+$P$1*H18) -> 1811.4 | M17: =I17-L17 -> 452.85 | N17: =(L17-E17)/E17 -> 0.029930178 | O17: =(M17-F17)/F17 -> 0.029930178 | P17: =M17/I17 -> 0.2
D18: 59 | H18: 1197.01
A19: Lesly Yohana Rubio | B19: 0 | C19: 31552 | D19: =($B$3-C19)/365 -> 37.224658 | E19: 412.42 | F19: 249.96 | G19: 662.38 | H19: 542.8 | I19: =H19 -> 542.8 | J19: =(I19-G19)/G19 -> -0.18053081 | K19: BlueChoice Advantage HDHP/HSA/HRA Gold Plan - $1,500 | L19: =IF($N$1*H19>=I19,I19,$N$1*H19) -> 434.24 | M19: =I19-L19 -> 108.56 | N19: =(L19-E19)/E19 -> 0.05290723 | O19: =(M19-F19)/F19 -> -0.56569051 | P19: =M19/I19 -> 0.2
A20: Carmen Pena | B20: 2 | C20: 31899 | D20: =($B$3-C20)/365 -> 36.273973 | E20: 1116.67 | F20: 676.78 | G20: 1793.45 | H20: 530.95 | I20: =SUM(H20:H22) -> 1461.3 | J20: =(I20-G20)/G20 -> -0.18520171 | K20: BlueChoice Advantage HDHP/HSA/HRA Gold Plan - $1,500 | L20: =IF($N$1*H20+$P$1*SUM(H21:H22)>=I20,I20,$N$1*H20+$P$1*SUM(H21:H22)) -> 1169.04 | M20: =I20-L20 -> 292.26 | N20: =(L20-E20)/E20 -> 0.046898367 | O20: =(M20-F20)/F20 -> -0.568161 | P20: =M20/I20 -> 0.2
D21: 37 | H21: 542.8
D22: 5 | H22: 387.55
A23: Kelly M McNally | B23: 0 | C23: 34588 | D23: =($B$3-C23)/365 -> 28.906849 | E23: 334.63 | F23: 117.07 | G23: 451.7 | H23: 440.88 | I23: =H23 -> 440.88 | J23: =(I23-G23)/G23 -> -0.023953952 | K23: BlueChoice Advantage HDHP/HSA/HRA Gold Plan - $1,500 | L23: =IF($N$1*H23>=I23,I23,$N$1*H23) -> 352.704 | M23: =I23-L23 -> 88.176 | N23: =(L23-E23)/E23 -> 0.054011894 | O23: =(M23-F23)/F23 -> -0.2468096 | P23: =M23/I23 -> 0.2
A24: Susanna J Meyer | B24: 0 | C24: 33900 | D24: =($B$3-C24)/365 -> 30.791781 | E24: 349.82 | F24: 122.38 | G24: 472.2 | H24: 461.62 | I24: =H24 -> 461.62 | J24: =(I24-G24)/G24 -> -0.02240576 | K24: BlueChoice Advantage HDHP/HSA/HRA Gold Plan - $1,500 | L24: =IF($N$1*H24>=I24,I24,$N$1*H24) -> 369.296 | M24: =I24-L24 -> 92.324 | N24: =(L24-E24)/E24 -> 0.055674347 | O24: =(M24-F24)/F24 -> -0.24559569 | P24: =M24/I24 -> 0.2
A25: Madeline Rae Steiner | B25: 0 | C25: 33765 | D25: =($B$3-C25)/365 -> 31.161644 | E25: 358.57 | F25: 125.44 | G25: 484.01 | H25: 473.47 | I25: =H25 -> 473.47 | J25: =(I25-G25)/G25 -> -0.02177641 | K25: BlueChoice Advantage HDHP/HSA/HRA Gold Plan - $1,500 | L25: =IF($N$1*H25>=I25,I25,$N$1*H25) -> 378.776 | M25: =I25-L25 -> 94.694 | N25: =(L25-E25)/E25 -> 0.056351619 | O25: =(M25-F25)/F25 -> -0.24510523 | P25: =M25/I25 -> 0.2
A26: Stephanie Monroy | B26: 0 | C26: 31116 | D26: =($B$3-C26)/365 -> 38.419178 | E26: 426.69 | F26: 149.27 | G26: 575.96 | H26: 549.32 | I26: =H26 -> 549.32 | J26: =(I26-G26)/G26 -> -0.046253212 | K26: BlueChoice Advantage HDHP/HSA/HRA Gold Plan - $1,500 | L26: =IF($N$1*H26>=I26,I26,$N$1*H26) -> 439.456 | M26: =I26-L26 -> 109.864 | N26: =(L26-E26)/E26 -> 0.029918676 | O26: =(M26-F26)/F26 -> -0.26399142 | P26: =M26/I26 -> 0.2
A27: Kirk Amper Del Rosario | B27: 0 | C27: 33886 | D27: =($B$3-C27)/365 -> 30.830137 | E27: 349.82 | F27: 75.87 | G27: 425.69 | H27: 461.62 | I27: =H27 -> 461.62 | J27: =(I27-G27)/G27 -> 0.084404144 | K27: BlueChoice Advantage HDHP/HSA/HRA Gold Plan - $1,500 | L27: =IF($N$1*H27>=I27,I27,$N$1*H27) -> 369.296 | M27: =I27-L27 -> 92.324 | N27: =(L27-E27)/E27 -> 0.055674347 | O27: =(M27-F27)/F27 -> 0.21687096 | P27: =M27/I27 -> 0.2
A28: Sara Jebena | B28: 0 | C28: 29996 | D28: =($B$3-C28)/365 -> 41.487671 | E28: 448.78 | F28: 97.34 | G28: 546.12 | H28: 600.28 | I28: =H28 -> 600.28 | J28: =(I28-G28)/G28 -> 0.099172343 | K28: BlueChoice Advantage HDHP/HSA/HRA Gold Plan - $1,500 | L28: =IF($N$1*H28>=I28,I28,$N$1*H28) -> 480.224 | M28: =I28-L28 -> 120.056 | N28: =(L28-E28)/E28 -> 0.070065511 | O28: =(M28-F28)/F28 -> 0.23336758 | P28: =M28/I28 -> 0.2
A29: Summar T Lyons | B29: 1 | C29: 31217 | D29: =($B$3-C29)/365 -> 38.142466 | E29: 887.89 | F29: 192.58 | G29: 1080.47 | H29: 549.32 | I29: =SUM(H29:H30) -> 1173.31 | J29: =(I29-G29)/G29 -> 0.085925569 | K29: BlueChoice Advantage HDHP/HSA/HRA Gold Plan - $1,500 | L29: =IF($N$1*H29+$P$1*H30>=I29,I29,$N$1*H29+$P$1*H30) -> 938.648 | M29: =I29-L29 -> 234.662 | N29: =(L29-E29)/E29 -> 0.057166991 | O29: =(M29-F29)/F29 -> 0.21851698 | P29: =M29/I29 -> 0.2
D30: 42 | H30: 623.99
A31: Armin Cordova | B31: 0 | C31: 35369 | D31: =($B$3-C31)/365 -> 26.767123 | E31: 324.42 | F31: 0 | G31: 324.42 | H31: 430.81 | I31: =H31 -> 430.81 | J31: =(I31-G31)/G31 -> 0.32793909 | K31: BlueChoice Advantage HDHP/HSA/HRA Gold Plan - $1,500 | L31: =IF($N$1*H31>=I31,I31,$N$1*H31) -> 344.648 | M31: =I31-L31 -> 86.162 | N31: =(L31-E31)/E31 -> 0.062351273 | O31: =(M31-F31)/F31 -> #DIV/0! | P31: =M31/I31 -> 0.2
A32: Megan Michelle Ash | B32: 0 | C32: 34295 | D32: =($B$3-C32)/365 -> 29.709589 | E32: 332 | F32: 0 | G32: 332 | H32: 450.36 | I32: =H32 -> 450.36 | J32: =(I32-G32)/G32 -> 0.35650602 | K32: BlueChoice Advantage HDHP/HSA/HRA Gold Plan - $1,500 | L32: =IF($N$1*H32>=I32,I32,$N$1*H32) -> 360.288 | M32: =I32-L32 -> 90.072 | N32: =(L32-E32)/E32 -> 0.085204819 | O32: =(M32-F32)/F32 -> #DIV/0! | P32: =M32/I32 -> 0.2
A33: Stephanie Verganza | B33: 0 | C33: 33576 | D33: =($B$3-C33)/365 -> 31.679452 | E33: 347.62 | F33: 0 | G33: 347.62 | H33: 473.47 | I33: =H33 -> 473.47 | J33: =(I33-G33)/G33 -> 0.36203325 | K33: BlueChoice Advantage HDHP/HSA/HRA Gold Plan - $1,500 | L33: =IF($N$1*H33>=I33,I33,$N$1*H33) -> 378.776 | M33: =I33-L33 -> 94.694 | N33: =(L33-E33)/E33 -> 0.089626604 | O33: =(M33-F33)/F33 -> #DIV/0! | P33: =M33/I33 -> 0.2
A34: Anh H Nguyen | B34: 1 | C34: 33338 | D34: =($B$3-C34)/365 -> 32.331507 | E34: 680.97 | F34: 0 | G34: 680.97 | H34: 484.14 | I34: =SUM(H34:H35) -> 925.02 | J34: =(I34-G34)/G34 -> 0.35838583 | K34: BlueChoice Advantage HDHP/HSA/HRA Gold Plan - $1,500 | L34: =IF($N$1*H34+$P$1*H35>=I34,I34,$N$1*H34+$P$1*H35) -> 740.016 | M34: =I34-L34 -> 185.004 | N34: =(L34-E34)/E34 -> 0.086708666 | O34: =(M34-F34)/F34 -> #DIV/0! | P34: =M34/I34 -> 0.2
D35: 28 | H35: 440.88
A36: Janira J Romero Reyes | B36: 1 | C36: 31561 | D36: =($B$3-C36)/365 -> 37.2 | E36: 691.67 | F36: 0 | G36: 691.67 | H36: 542.8 | I36: =SUM(H36:H37) -> 930.35 | J36: =(I36-G36)/G36 -> 0.34507786 | K36: BlueChoice Advantage HDHP/HSA/HRA Gold Plan - $1,500 | L36: =IF($N$1*H36+$P$1*H37>=I36,I36,$N$1*H36+$P$1*H37) -> 744.28 | M36: =I36-L36 -> 186.07 | N36: =(L36-E36)/E36 -> 0.076062284 | O36: =(M36-F36)/F36 -> #DIV/0! | P36: =M36/I36 -> 0.2
D37: 0 | H37: 387.55
A38: Danielle R Martin | B38: 1 | C38: 33497 | D38: =($B$3-C38)/365 -> 31.89589 | E38: 695.24 | F38: 0 | G38: 695.24 | H38: 473.47 | I38: =SUM(H38:H39) -> 946.94 | J38: =(I38-G38)/G38 -> 0.36203325 | K38: BlueChoice Advantage HDHP/HSA/HRA Gold Plan - $1,500 | L38: =IF($N$1*H38+$P$1*H39>=I38,I38,$N$1*H38+$P$1*H39) -> 757.552 | M38: =I38-L38 -> 189.388 | N38: =(L38-E38)/E38 -> 0.089626604 | O38: =(M38-F38)/F38 -> #DIV/0! | P38: =M38/I38 -> 0.2
D39: 31 | H39: 473.47
A40: William D Webber | B40: 1 | C40: 34122 | D40: =($B$3-C40)/365 -> 30.183562 | E40: 738.97 | F40: 0 | G40: 738.97 | H40: 461.62 | I40: =SUM(H40:H41) -> 1004.42 | J40: =(I40-G40)/G40 -> 0.35921621 | K40: BlueChoice Advantage HDHP/HSA/HRA Gold Plan - $1,500 | L40: =IF($N$1*H40+$P$1*H41>=I40,I40,$N$1*H40+$P$1*H41) -> 803.536 | M40: =I40-L40 -> 200.884 | N40: =(L40-E40)/E40 -> 0.087372965 | O40: =(M40-F40)/F40 -> #DIV/0! | P40: =M40/I40 -> 0.2
D41: 37 | H41: 542.8
A42: Debra L Cooper | B42: 0 | C42: 24504 | D42: =($B$3-C42)/365 -> 56.534247 | E42: 773.34 | F42: 0 | G42: 773.34 | H42: 1067.24 | I42: =H42 -> 1067.24 | J42: =(I42-G42)/G42 -> 0.38003983 | K42: BlueChoice Advantage HDHP/HSA/HRA Gold Plan - $1,500 | L42: =IF($N$1*H42>=I42,I42,$N$1*H42) -> 853.792 | M42: =I42-L42 -> 213.448 | N42: =(L42-E42)/E42 -> 0.10403186 | O42: =(M42-F42)/F42 -> #DIV/0! | P42: =M42/I42 -> 0.2
A43: Pablo Marcelo Gonzalez | B43: 1 | C43: 28690 | D43: =($B$3-C43)/365 -> 45.065753 | E43: 1054.92 | F43: 0 | G43: 1054.92 | H43: 699.84 | I43: =SUM(H43:H44) -> 1455.38 | J43: =(I43-G43)/G43 -> 0.37961172 | K43: BlueChoice Advantage HDHP/HSA/HRA Gold Plan - $1,500 | L43: =IF($N$1*H43+$P$1*H44>=I43,I43,$N$1*H43+$P$1*H44) -> 1164.304 | M43: =I43-L43 -> 291.076 | N43: =(L43-E43)/E43 -> 0.10368938 | O43: =(M43-F43)/F43 -> #DIV/0! | P43: =M43/I43 -> 0.2
D44: 47 | H44: 755.54
A45: Sheila Ann Posas | B45: 3 | C45: 27512 | D45: =($B$3-C45)/365 -> 48.293151 | E45: 1700.18 | F45: 0 | G45: 1700.18 | H45: 785.17 | I45: =SUM(H45:H48) -> 2287.37 | J45: =(I45-G45)/G45 -> 0.34536931 | K45: BlueChoice Advantage HDHP/HSA/HRA Gold Plan - $1,500 | L45: =IF($N$1*H45+$P$1*SUM(H46:H48)>=I45,I45,$N$1*H45+$P$1*SUM(H46:H48)) -> 1829.896 | M45: =I45-L45 -> 457.474 | N45: =(L45-E45)/E45 -> 0.076295451 | O45: =(M45-F45)/F45 -> #DIV/0! | P45: =M45/I45 -> 0.2
D46: 46 | H46: 727.1
D47: 10 | H47: 387.55
D48: 7 | H48: 387.55
A49: Mariana Cabrera | B49: 0 | C49: 36111 | D49: =($B$3-C49)/365 -> 24.734247 | E49: 334.63 | F49: 16.28 | G49: 350.91 | H49: 430.81 | I49: =H49 -> 430.81 | J49: =(I49-G49)/G49 -> 0.22769371 | K49: BlueChoice Advantage HDHP/HSA/HRA Gold Plan - $1,500 | L49: =IF($N$1*H49>=I49,I49,$N$1*H49) -> 344.648 | M49: =I49-L49 -> 86.162 | N49: =(L49-E49)/E49 -> 0.029937543 | O49: =(M49-F49)/F49 -> 4.2925061 | P49: =M49/I49 -> 0.2
A50: Natalie M Abegesah | B50: 3 | C50: 31872 | D50: =($B$3-C50)/365 -> 36.347945 | E50: 1417.7 | F50: 68.98 | G50: 1486.68 | H50: 530.95 | I50: =SUM(H50:H53) -> 1848.85 | J50: =(I50-G50)/G50 -> 0.24360992 | K50: BlueChoice Advantage HDHP/HSA/HRA Gold Plan - $1,500 | L50: =IF($N$1*H50+$P$1*SUM(H51:H53)>=I50,I50,$N$1*H50+$P$1*SUM(H51:H53)) -> 1479.08 | M50: =I50-L50 -> 369.77 | N50: =(L50-E50)/E50 -> 0.043295479 | O50: =(M50-F50)/F50 -> 4.3605393 | P50: =M50/I50 -> 0.2
D51: 37 | H51: 542.8
D52: 17 | H52: 387.55
D53: 15 | H53: 387.55
A54: Nilu Rimal | B54: 1 | C54: 24635 | D54: =($B$3-C54)/365 -> 56.175342 | E54: 1727.46 | F54: 84.05 | G54: 1811.51 | H54: 1067.24 | I54: =SUM(H54:H55) -> 2264.25 | J54: =(I54-G54)/G54 -> 0.2499241 | K54: BlueChoice Advantage HDHP/HSA/HRA Gold Plan - $1,500 | L54: =IF($N$1*H54+$P$1*H55>=I54,I54,$N$1*H54+$P$1*H55) -> 1811.4 | M54: =I54-L54 -> 452.85 | N54: =(L54-E54)/E54 -> 0.048591574 | O54: =(M54-F54)/F54 -> 4.3878644 | P54: =M54/I54 -> 0.2
D55: 59 | H55: 1197.01
A56: Genesis C Torres-Alcantara | B56: 0 | C56: 34977 | D56: =($B$3-C56)/365 -> 27.841096 | E56: 334.63 | F56: 2.76 | G56: 337.39 | H56: 430.81 | I56: =H56 -> 430.81 | J56: =(I56-G56)/G56 -> 0.27689025 | K56: BlueChoice Advantage HDHP/HSA/HRA Gold Plan - $1,500 | L56: =IF($N$1*H56>=I56,I56,$N$1*H56) -> 344.648 | M56: =I56-L56 -> 86.162 | N56: =(L56-E56)/E56 -> 0.029937543 | O56: =(M56-F56)/F56 -> 30.218116 | P56: =M56/I56 -> 0.2
A57: Arlette G Gutierrez | B57: 0 | C57: 28471 | D57: =($B$3-C57)/365 -> 45.665753 | E57: 523.34 | F57: 4.33 | G57: 527.67 | H57: 699.84 | I57: =H57 -> 699.84 | J57: =(I57-G57)/G57 -> 0.32628347 | K57: BlueChoice Advantage HDHP/HSA/HRA Gold Plan - $1,500 | L57: =IF($N$1*H57>=I57,I57,$N$1*H57) -> 559.872 | M57: =I57-L57 -> 139.968 | N57: =(L57-E57)/E57 -> 0.06980548 | O57: =(M57-F57)/F57 -> 31.325173 | P57: =M57/I57 -> 0.2
A58: John Robert McPhail | B58: 4 | C58: 25137 | D58: =($B$3-C58)/365 -> 54.8 | E58: 2342.87 | F58: 19.35 | G58: 2362.22 | H58: 988.42 | I58: =SUM(H58:H62) -> 3125.73 | J58: =(I58-G58)/G58 -> 0.32321714 | K58: BlueChoice Advantage HDHP/HSA/HRA Gold Plan - $1,500 | L58: =IF($N$1*H58+$P$1*SUM(H59:H62)>=I58,I58,$N$1*H58+$P$1*SUM(H59:H62)) -> 2500.584 | M58: =I58-L58 -> 625.146 | N58: =(L58-E58)/E58 -> 0.067316582 | O58: =(M58-F58)/F58 -> 31.307287 | P58: =M58/I58 -> 0.2
D59: 50 | H59: 847.98
D60: 25 | H60: 430.81
D61: 24 | H61: 470.97
D62: 19 | H62: 387.55
A63: Rachel Shoshana Falek | B63: 0 | C63: 35017 | D63: =($B$3-C63)/365 -> 27.731507 | E63: 334.63 | F63: 159.88 | G63: 494.51 | H63: 430.81 | I63: =H63 -> 430.81 | J63: =(I63-G63)/G63 -> -0.12881438 | K63: BlueChoice Advantage HDHP/HSA/HRA Gold Plan - $1,500 | L63: =IF($N$1*H63>=I63,I63,$N$1*H63) -> 344.648 | M63: =I63-L63 -> 86.162 | N63: =(L63-E63)/E63 -> 0.029937543 | O63: =(M63-F63)/F63 -> -0.46108331 | P63: =M63/I63 -> 0.2
A64: Angel Kristina Rutter | B64: 0 | C64: 35099 | D64: =($B$3-C64)/365 -> 27.506849 | E64: 334.63 | F64: 76.22 | G64: 410.85 | H64: 430.81 | I64: =H64 -> 430.81 | J64: =(I64-G64)/G64 -> 0.048582208 | K64: BlueChoice Advantage HDHP/HSA/HRA Gold Plan - $1,500 | L64: =IF($N$1*H64>=I64,I64,$N$1*H64) -> 344.648 | M64: =I64-L64 -> 86.162 | N64: =(L64-E64)/E64 -> 0.029937543 | O64: =(M64-F64)/F64 -> 0.13043821 | P64: =M64/I64 -> 0.2
A65: Katherine Julia Matteson de Araujo | B65: 0 | C65: 35229 | D65: =($B$3-C65)/365 -> 27.150685 | E65: 334.63 | F65: 76.22 | G65: 410.85 | H65: 430.81 | I65: =H65 -> 430.81 | J65: =(I65-G65)/G65 -> 0.048582208 | K65: BlueChoice Advantage HDHP/HSA/HRA Gold Plan - $1,500 | L65: =IF($N$1*H65>=I65,I65,$N$1*H65) -> 344.648 | M65: =I65-L65 -> 86.162 | N65: =(L65-E65)/E65 -> 0.029937543 | O65: =(M65-F65)/F65 -> 0.13043821 | P65: =M65/I65 -> 0.2
A66: Maia Moore | B66: 0 | C66: 34375 | D66: =($B$3-C66)/365 -> 29.490411 | E66: 342.46 | F66: 78 | G66: 420.46 | H66: 450.36 | I66: =H66 -> 450.36 | J66: =(I66-G66)/G66 -> 0.071112591 | K66: BlueChoice Advantage HDHP/HSA/HRA Gold Plan - $1,500 | L66: =IF($N$1*H66>=I66,I66,$N$1*H66) -> 360.288 | M66: =I66-L66 -> 90.072 | N66: =(L66-E66)/E66 -> 0.052058635 | O66: =(M66-F66)/F66 -> 0.15476923 | P66: =M66/I66 -> 0.2
A67: Sarah F Smith | B67: 0 | C67: 31779 | D67: =($B$3-C67)/365 -> 36.60274 | E67: 403.22 | F67: 91.83 | G67: 495.05 | H67: 530.95 | I67: =H67 -> 530.95 | J67: =(I67-G67)/G67 -> 0.072517927 | K67: BlueChoice Advantage HDHP/HSA/HRA Gold Plan - $1,500 | L67: =IF($N$1*H67>=I67,I67,$N$1*H67) -> 424.76 | M67: =I67-L67 -> 106.19 | N67: =(L67-E67)/E67 -> 0.053419969 | O67: =(M67-F67)/F67 -> 0.15637591 | P67: =M67/I67 -> 0.2
A68: Ukiah Busch | B68: 3 | C68: 31376 | D68: =($B$3-C68)/365 -> 37.706849 | E68: 1417.7 | F68: 322.91 | G68: 1740.61 | H68: 542.8 | I68: =SUM(H68:H71) -> 1848.85 | J68: =(I68-G68)/G68 -> 0.062185096 | K68: BlueChoice Advantage HDHP/HSA/HRA Gold Plan - $1,500 | L68: =IF($N$1*H68+$P$1*SUM(H69:H71)>=I68,I68,$N$1*H68+$P$1*SUM(H69:H71)) -> 1479.08 | M68: =I68-L68 -> 369.77 | N68: =(L68-E68)/E68 -> 0.043295479 | O68: =(M68-F68)/F68 -> 0.14511783 | P68: =M68/I68 -> 0.2
D69: 36 | H69: 530.95
D70: 9 | H70: 387.55
D71: 5 | H71: 387.55
A72: Robert Colbry Maher | B72: 0 | C72: 34315 | D72: =($B$3-C72)/365 -> 29.654795 | E72: 342.46 | F72: 101.28 | G72: 443.74 | H72: 450.36 | I72: =H72 -> 450.36 | J72: =(I72-G72)/G72 -> 0.014918646 | K72: BlueChoice Advantage HDHP/HSA/HRA Gold Plan - $1,500 | L72: =IF($N$1*H72>=I72,I72,$N$1*H72) -> 360.288 | M72: =I72-L72 -> 90.072 | N72: =(L72-E72)/E72 -> 0.052058635 | O72: =(M72-F72)/F72 -> -0.11066351 | P72: =M72/I72 -> 0.2
A73: Abraham Cisne | B73: 0 | C73: 30417 | D73: =($B$3-C73)/365 -> 40.334247 | E73: 431.75 | F73: 127.69 | G73: 559.44 | H73: 577.77 | I73: =H73 -> 577.77 | J73: =(I73-G73)/G73 -> 0.032764908 | K73: BlueChoice Advantage HDHP/HSA/HRA Gold Plan - $1,500 | L73: =IF($N$1*H73>=I73,I73,$N$1*H73) -> 462.216 | M73: =I73-L73 -> 115.554 | N73: =(L73-E73)/E73 -> 0.070563984 | O73: =(M73-F73)/F73 -> -0.095042681 | P73: =M73/I73 -> 0.2
A74: Colleen Suzanne Boyne | B74: 0 | C74: 30382 | D74: =($B$3-C74)/365 -> 40.430137 | E74: 431.75 | F74: 127.69 | G74: 559.44 | H74: 577.77 | I74: =H74 -> 577.77 | J74: =(I74-G74)/G74 -> 0.032764908 | K74: BlueChoice Advantage HDHP/HSA/HRA Gold Plan - $1,500 | L74: =IF($N$1*H74>=I74,I74,$N$1*H74) -> 462.216 | M74: =I74-L74 -> 115.554 | N74: =(L74-E74)/E74 -> 0.070563984 | O74: =(M74-F74)/F74 -> -0.095042681 | P74: =M74/I74 -> 0.2
A75: Allison S McGovern | B75: 0 | C75: 35557 | D75: =($B$3-C75)/365 -> 26.252055 | E75: 334.63 | F75: 151.06 | G75: 485.69 | H75: 430.81 | I75: =H75 -> 430.81 | J75: =(I75-G75)/G75 -> -0.11299388 | K75: BlueChoice Advantage HDHP/HSA/HRA Gold Plan - $1,500 | L75: =IF($N$1*H75>=I75,I75,$N$1*H75) -> 344.648 | M75: =I75-L75 -> 86.162 | N75: =(L75-E75)/E75 -> 0.029937543 | O75: =(M75-F75)/F75 -> -0.42961737 | P75: =M75/I75 -> 0.2
A76: Hannah Elizabeth Guernsey (COBRA) | B76: 0 | C76: 34137 | D76: =($B$3-C76)/365 -> 30.142466 | E76: 0 | F76: 507.74 | G76: 507.74 | H76: 461.62 | I76: =H76 -> 461.62 | J76: =(I76-G76)/G76 -> -0.090833891 | K76: BlueChoice Advantage HDHP/HSA/HRA Gold Plan - $1,500 | L76: 0 | M76: =I76-L76 -> 461.62 | N76: =(L76-E76)/E76 -> #DIV/0! | O76: =(M76-F76)/F76 -> -0.090833891 | P76: =(N76-G76)/G76 -> #DIV/0!
L78: Monthly Cost based on 5/1 Invoice (less COBRAs) | M78: =SUM(E6:E75) -> 29245.45
L79: Estimated Monthly Cost Renewal 8.1.23 | M79: =SUM(L6:L76)-L76 -> 30949.68
L80: Difference | M80: =M79-M78 -> 1704.23
L81: Percentage Change | M81: =M80/M78 -> 0.058273338
L82: Annual Difference | M82: =M80*12 -> 20450.76
L83: Additional Possible Liability HRA | M83: =25*1500+16*3000 -> 85500
L84: Total Change | M84: =SUM(M82:M83) -> 105950.76
L85: Renewal % | M85: =M84/(M78*12) -> 0.30190098

Sheet Prtnrs Change Ref to Silver HRA
A1: 2023 Benefits Worksheet | M1: Partners Covers | N1: 0.8 | O1: Employee | P1: 0.8 | Q1: Dependents
A2: 1 | N2: No Changes Employees Actual Choices on DCHL
A3: Renewal Date | B3: 45139
A4: Basic Demographic Data | E4: Current Premiums | H4: Renewal Information | K4: Plan Info
A5: Employee | B5: Covered Dependents | C5: DOB | D5: Renewal Age | E5: Partners Current Premium | F5: Employee Current Monthly Premium based on May Invoice | G5: Total Cost Current Premium | H5: Renewal Premium BlueChoice Advantage HSA BlueFund Silver Plan - $1,600 | I5: Renewal Cost Employee's Actual Plan | J5: Percentage Change on Actual Plan | K5: Employee's Actual Plan Choice | L5: Maximum Renewal Cost for Partners BlueChoice Advantage HSA BlueFund Silver Plan - $1,600 | M5: Employee Premium On Renewal | N5: Percentage Change for Partners | O5: Percentage Change for Employee | P5: Employee's % Cost of Premium
A6: Alexandra Lishansky | B6: 1 | C6: 34087 | D6: =($B$3-C6)/365 -> 30.279452 | E6: 650.85 | F6: 257.39 | G6: 908.24 | H6: 407.85 | I6: =SUM(H6:H7) -> 750.25 | J6: =(I6-G6)/G6 -> -0.17395182 | K6: BlueChoice Advantage HSA BlueFund Silver Plan - $1,600 | L6: =IF($N$1*H6+$P$1*H7>=I6,I6,$N$1*H6+$P$1*H7) -> 600.2 | M6: =I6-L6 -> 150.05 | N6: =(L6-E6)/E6 -> -0.077821311 | O6: =(M6-F6)/F6 -> -0.41703252 | P6: =M6/I6 -> 0.2
D7: 1 | H7: 342.4
A8: Marcio Nascimento | B8: 0 | C8: 26679 | D8: =($B$3-C8)/365 -> 50.575342 | E8: 633.82 | F8: 112.9 | G8: 746.72 | H8: 749.2 | I8: =H8 -> 749.2 | J8: =(I8-G8)/G8 -> 0.0033211913 | K8: BlueChoice Advantage HSA BlueFund Silver Plan - $1,600 | L8: =IF($N$1*H8>=I8,I8,$N$1*H8) -> 599.36 | M8: =I8-L8 -> 149.84 | N8: =(L8-E8)/E8 -> -0.054368748 | O8: =(M8-F8)/F8 -> 0.32719221 | P8: =M8/I8 -> 0.2
A9: Penelope Kim | B9: 2 | C9: 31381 | D9: =($B$3-C9)/365 -> 37.693151 | E9: 1055.91 | F9: 263.97 | G9: 1319.88 | H9: 479.57 | I9: =SUM(H9:H11) -> 1219.87 | J9: =(I9-G9)/G9 -> -0.07577204 | K9: BlueChoice Advantage HSA BlueFund Silver Plan - $1,600 | L9: =IF($N$1*H9+$P$1*SUM(H10:H11)>=I9,I9,$N$1*H9+$P$1*SUM(H10:H11)) -> 975.896 | M9: =I9-L9 -> 243.974 | N9: =(L9-E9)/E9 -> -0.075777292 | O9: =(M9-F9)/F9 -> -0.075751032 | P9: =M9/I9 -> 0.2
D10: 29 | H10: 397.9
D11: 0 | H11: 342.4
A12: Michael B Moscarelli | B12: 4 | C12: 30749 | D12: =($B$3-C12)/365 -> 39.424658 | E12: 1733 | F12: 433.25 | G12: 2166.25 | H12: 491.09 | I12: =SUM(H12:H16) -> 1987.39 | J12: =(I12-G12)/G12 -> -0.082566647 | K12: BlueChoice Advantage HSA BlueFund Silver Plan - $1,600 | L12: =IF($N$1*H12+$P$1*SUM(H13:H16)>=I12,I12,$N$1*H12+$P$1*SUM(H13:H16)) -> 1589.912 | M12: =I12-L12 -> 397.478 | N12: =(L12-E12)/E12 -> -0.082566647 | O12: =(M12-F12)/F12 -> -0.082566647 | P12: =M12/I12 -> 0.2
D13: 36 | H13: 469.1
D14: 6 | H14: 342.4
D15: 3 | H15: 342.4
D16: 0 | H16: 342.4
A17: Ana Aslan | B17: 1 | C17: 24458 | D17: =($B$3-C17)/365 -> 56.660274 | E17: 1758.76 | F17: 439.69 | G17: 2198.45 | H17: 942.91 | I17: =SUM(H17:H18) -> 2000.48 | J17: =(I17-G17)/G17 -> -0.090049808 | K17: BlueChoice Advantage HSA BlueFund Silver Plan - $1,600 | L17: =IF($N$1*H17+$P$1*H18>=I17,I17,$N$1*H17+$P$1*H18) -> 1600.384 | M17: =I17-L17 -> 400.096 | N17: =(L17-E17)/E17 -> -0.090049808 | O17: =(M17-F17)/F17 -> -0.090049808 | P17: =M17/I17 -> 0.2
D18: 59 | H18: 1057.57
A19: Lesly Yohana Rubio | B19: 0 | C19: 31552 | D19: =($B$3-C19)/365 -> 37.224658 | E19: 412.42 | F19: 249.96 | G19: 662.38 | H19: 479.57 | I19: =H19 -> 479.57 | J19: =(I19-G19)/G19 -> -0.27598961 | K19: BlueChoice Advantage HSA BlueFund Silver Plan - $1,600 | L19: =IF($N$1*H19>=I19,I19,$N$1*H19) -> 383.656 | M19: =I19-L19 -> 95.914 | N19: =(L19-E19)/E19 -> -0.069744435 | O19: =(M19-F19)/F19 -> -0.61628261 | P19: =M19/I19 -> 0.2
A20: Carmen Pena | B20: 2 | C20: 31899 | D20: =($B$3-C20)/365 -> 36.273973 | E20: 1116.67 | F20: 676.78 | G20: 1793.45 | H20: 469.1 | I20: =SUM(H20:H22) -> 1291.07 | J20: =(I20-G20)/G20 -> -0.28011932 | K20: BlueChoice Advantage HSA BlueFund Silver Plan - $1,600 | L20: =IF($N$1*H20+$P$1*SUM(H21:H22)>=I20,I20,$N$1*H20+$P$1*SUM(H21:H22)) -> 1032.856 | M20: =I20-L20 -> 258.214 | N20: =(L20-E20)/E20 -> -0.075057089 | O20: =(M20-F20)/F20 -> -0.61846686 | P20: =M20/I20 -> 0.2
D21: 37 | H21: 479.57
D22: 5 | H22: 342.4
A23: Kelly M McNally | B23: 0 | C23: 34588 | D23: =($B$3-C23)/365 -> 28.906849 | E23: 334.63 | F23: 117.07 | G23: 451.7 | H23: 389.52 | I23: =H23 -> 389.52 | J23: =(I23-G23)/G23 -> -0.13765774 | K23: BlueChoice Advantage HSA BlueFund Silver Plan - $1,600 | L23: =IF($N$1*H23>=I23,I23,$N$1*H23) -> 311.616 | M23: =I23-L23 -> 77.904 | N23: =(L23-E23)/E23 -> -0.068774467 | O23: =(M23-F23)/F23 -> -0.33455198 | P23: =M23/I23 -> 0.2
A24: Susanna J Meyer | B24: 0 | C24: 33900 | D24: =($B$3-C24)/365 -> 30.791781 | E24: 349.82 | F24: 122.38 | G24: 472.2 | H24: 407.85 | I24: =H24 -> 407.85 | J24: =(I24-G24)/G24 -> -0.136277 | K24: BlueChoice Advantage HSA BlueFund Silver Plan - $1,600 | L24: =IF($N$1*H24>=I24,I24,$N$1*H24) -> 326.28 | M24: =I24-L24 -> 81.57 | N24: =(L24-E24)/E24 -> -0.06729175 | O24: =(M24-F24)/F24 -> -0.33346952 | P24: =M24/I24 -> 0.2
A25: Madeline Rae Steiner | B25: 0 | C25: 33765 | D25: =($B$3-C25)/365 -> 31.161644 | E25: 358.57 | F25: 125.44 | G25: 484.01 | H25: 418.32 | I25: =H25 -> 418.32 | J25: =(I25-G25)/G25 -> -0.13572034 | K25: BlueChoice Advantage HSA BlueFund Silver Plan - $1,600 | L25: =IF($N$1*H25>=I25,I25,$N$1*H25) -> 334.656 | M25: =I25-L25 -> 83.664 | N25: =(L25-E25)/E25 -> -0.066692696 | O25: =(M25-F25)/F25 -> -0.33303571 | P25: =M25/I25 -> 0.2
A26: Stephanie Monroy | B26: 0 | C26: 31116 | D26: =($B$3-C26)/365 -> 38.419178 | E26: 426.69 | F26: 149.27 | G26: 575.96 | H26: 485.33 | I26: =H26 -> 485.33 | J26: =(I26-G26)/G26 -> -0.15735468 | K26: BlueChoice Advantage HSA BlueFund Silver Plan - $1,600 | L26: =IF($N$1*H26>=I26,I26,$N$1*H26) -> 388.264 | M26: =I26-L26 -> 97.066 | N26: =(L26-E26)/E26 -> -0.090056013 | O26: =(M26-F26)/F26 -> -0.34972868 | P26: =M26/I26 -> 0.2
A27: Kirk Amper Del Rosario | B27: 0 | C27: 33886 | D27: =($B$3-C27)/365 -> 30.830137 | E27: 349.82 | F27: 75.87 | G27: 425.69 | H27: 407.85 | I27: =H27 -> 407.85 | J27: =(I27-G27)/G27 -> -0.041908431 | K27: BlueChoice Advantage HSA BlueFund Silver Plan - $1,600 | L27: =IF($N$1*H27>=I27,I27,$N$1*H27) -> 326.28 | M27: =I27-L27 -> 81.57 | N27: =(L27-E27)/E27 -> -0.06729175 | O27: =(M27-F27)/F27 -> 0.075128509 | P27: =M27/I27 -> 0.2
A28: Sara Jebena | B28: 0 | C28: 29996 | D28: =($B$3-C28)/365 -> 41.487671 | E28: 448.78 | F28: 97.34 | G28: 546.12 | H28: 530.36 | I28: =H28 -> 530.36 | J28: =(I28-G28)/G28 -> -0.028858126 | K28: BlueChoice Advantage HSA BlueFund Silver Plan - $1,600 | L28: =IF($N$1*H28>=I28,I28,$N$1*H28) -> 424.288 | M28: =I28-L28 -> 106.072 | N28: =(L28-E28)/E28 -> -0.054574625 | O28: =(M28-F28)/F28 -> 0.089706185 | P28: =M28/I28 -> 0.2
A29: Summar T Lyons | B29: 1 | C29: 31217 | D29: =($B$3-C29)/365 -> 38.142466 | E29: 887.89 | F29: 192.58 | G29: 1080.47 | H29: 485.33 | I29: =SUM(H29:H30) -> 1036.63 | J29: =(I29-G29)/G29 -> -0.040574935 | K29: BlueChoice Advantage HSA BlueFund Silver Plan - $1,600 | L29: =IF($N$1*H29+$P$1*H30>=I29,I29,$N$1*H29+$P$1*H30) -> 829.304 | M29: =I29-L29 -> 207.326 | N29: =(L29-E29)/E29 -> -0.065983399 | O29: =(M29-F29)/F29 -> 0.076570776 | P29: =M29/I29 -> 0.2
D30: 42 | H30: 551.3
A31: Armin Cordova | B31: 0 | C31: 35369 | D31: =($B$3-C31)/365 -> 26.767123 | E31: 324.42 | F31: 0 | G31: 324.42 | H31: 380.62 | I31: =H31 -> 380.62 | J31: =(I31-G31)/G31 -> 0.17323223 | K31: BlueChoice Advantage HSA BlueFund Silver Plan - $1,600 | L31: =IF($N$1*H31>=I31,I31,$N$1*H31) -> 304.496 | M31: =I31-L31 -> 76.124 | N31: =(L31-E31)/E31 -> -0.061414216 | O31: =(M31-F31)/F31 -> #DIV/0! | P31: =M31/I31 -> 0.2
A32: Megan Michelle Ash | B32: 0 | C32: 34295 | D32: =($B$3-C32)/365 -> 29.709589 | E32: 332 | F32: 0 | G32: 332 | H32: 397.9 | I32: =H32 -> 397.9 | J32: =(I32-G32)/G32 -> 0.19849398 | K32: BlueChoice Advantage HSA BlueFund Silver Plan - $1,600 | L32: =IF($N$1*H32>=I32,I32,$N$1*H32) -> 318.32 | M32: =I32-L32 -> 79.58 | N32: =(L32-E32)/E32 -> -0.041204819 | O32: =(M32-F32)/F32 -> #DIV/0! | P32: =M32/I32 -> 0.2
A33: Stephanie Verganza | B33: 0 | C33: 33576 | D33: =($B$3-C33)/365 -> 31.679452 | E33: 347.62 | F33: 0 | G33: 347.62 | H33: 418.32 | I33: =H33 -> 418.32 | J33: =(I33-G33)/G33 -> 0.203383 | K33: BlueChoice Advantage HSA BlueFund Silver Plan - $1,600 | L33: =IF($N$1*H33>=I33,I33,$N$1*H33) -> 334.656 | M33: =I33-L33 -> 83.664 | N33: =(L33-E33)/E33 -> -0.037293596 | O33: =(M33-F33)/F33 -> #DIV/0! | P33: =M33/I33 -> 0.2
A34: Anh H Nguyen | B34: 1 | C34: 33338 | D34: =($B$3-C34)/365 -> 32.331507 | E34: 680.97 | F34: 0 | G34: 680.97 | H34: 427.74 | I34: =SUM(H34:H35) -> 817.26 | J34: =(I34-G34)/G34 -> 0.20014098 | K34: BlueChoice Advantage HSA BlueFund Silver Plan - $1,600 | L34: =IF($N$1*H34+$P$1*H35>=I34,I34,$N$1*H34+$P$1*H35) -> 653.808 | M34: =I34-L34 -> 163.452 | N34: =(L34-E34)/E34 -> -0.03988722 | O34: =(M34-F34)/F34 -> #DIV/0! | P34: =M34/I34 -> 0.2
D35: 28 | H35: 389.52
A36: Janira J Romero Reyes | B36: 1 | C36: 31561 | D36: =($B$3-C36)/365 -> 37.2 | E36: 691.67 | F36: 0 | G36: 691.67 | H36: 479.57 | I36: =SUM(H36:H37) -> 821.97 | J36: =(I36-G36)/G36 -> 0.18838463 | K36: BlueChoice Advantage HSA BlueFund Silver Plan - $1,600 | L36: =IF($N$1*H36+$P$1*H37>=I36,I36,$N$1*H36+$P$1*H37) -> 657.576 | M36: =I36-L36 -> 164.394 | N36: =(L36-E36)/E36 -> -0.049292293 | O36: =(M36-F36)/F36 -> #DIV/0! | P36: =M36/I36 -> 0.2
D37: 0 | H37: 342.4
A38: Danielle R Martin | B38: 1 | C38: 33497 | D38: =($B$3-C38)/365 -> 31.89589 | E38: 695.24 | F38: 0 | G38: 695.24 | H38: 418.32 | I38: =SUM(H38:H39) -> 836.64 | J38: =(I38-G38)/G38 -> 0.203383 | K38: BlueChoice Advantage HSA BlueFund Silver Plan - $1,600 | L38: =IF($N$1*H38+$P$1*H39>=I38,I38,$N$1*H38+$P$1*H39) -> 669.312 | M38: =I38-L38 -> 167.328 | N38: =(L38-E38)/E38 -> -0.037293596 | O38: =(M38-F38)/F38 -> #DIV/0! | P38: =M38/I38 -> 0.2
D39: 31 | H39: 418.32
A40: William D Webber | B40: 1 | C40: 34122 | D40: =($B$3-C40)/365 -> 30.183562 | E40: 738.97 | F40: 0 | G40: 738.97 | H40: 407.85 | I40: =SUM(H40:H41) -> 887.42 | J40: =(I40-G40)/G40 -> 0.20088772 | K40: BlueChoice Advantage HSA BlueFund Silver Plan - $1,600 | L40: =IF($N$1*H40+$P$1*H41>=I40,I40,$N$1*H40+$P$1*H41) -> 709.936 | M40: =I40-L40 -> 177.484 | N40: =(L40-E40)/E40 -> -0.039289822 | O40: =(M40-F40)/F40 -> #DIV/0! | P40: =M40/I40 -> 0.2
D41: 37 | H41: 479.57
A42: Debra L Cooper | B42: 0 | C42: 24504 | D42: =($B$3-C42)/365 -> 56.534247 | E42: 773.34 | F42: 0 | G42: 773.34 | H42: 942.91 | I42: =H42 -> 942.91 | J42: =(I42-G42)/G42 -> 0.21926966 | K42: BlueChoice Advantage HSA BlueFund Silver Plan - $1,600 | L42: =IF($N$1*H42>=I42,I42,$N$1*H42) -> 754.328 | M42: =I42-L42 -> 188.582 | N42: =(L42-E42)/E42 -> -0.024584271 | O42: =(M42-F42)/F42 -> #DIV/0! | P42: =M42/I42 -> 0.2
A43: Pablo Marcelo Gonzalez | B43: 1 | C43: 28690 | D43: =($B$3-C43)/365 -> 45.065753 | E43: 1054.92 | F43: 0 | G43: 1054.92 | H43: 618.31 | I43: =SUM(H43:H44) -> 1285.84 | J43: =(I43-G43)/G43 -> 0.21889812 | K43: BlueChoice Advantage HSA BlueFund Silver Plan - $1,600 | L43: =IF($N$1*H43+$P$1*H44>=I43,I43,$N$1*H43+$P$1*H44) -> 1028.672 | M43: =I43-L43 -> 257.168 | N43: =(L43-E43)/E43 -> -0.024881508 | O43: =(M43-F43)/F43 -> #DIV/0! | P43: =M43/I43 -> 0.2
D44: 47 | H44: 667.53
A45: Sheila Ann Posas | B45: 3 | C45: 27512 | D45: =($B$3-C45)/365 -> 48.293151 | E45: 1700.18 | F45: 0 | G45: 1700.18 | H45: 693.7 | I45: =SUM(H45:H48) -> 2020.9 | J45: =(I45-G45)/G45 -> 0.18863885 | K45: BlueChoice Advantage HSA BlueFund Silver Plan - $1,600 | L45: =IF($N$1*H45+$P$1*SUM(H46:H48)>=I45,I45,$N$1*H45+$P$1*SUM(H46:H48)) -> 1616.72 | M45: =I45-L45 -> 404.18 | N45: =(L45-E45)/E45 -> -0.04908892 | O45: =(M45-F45)/F45 -> #DIV/0! | P45: =M45/I45 -> 0.2
D46: 46 | H46: 642.4
D47: 10 | H47: 342.4
D48: 7 | H48: 342.4
A49: Mariana Cabrera | B49: 0 | C49: 36111 | D49: =($B$3-C49)/365 -> 24.734247 | E49: 334.63 | F49: 16.28 | G49: 350.91 | H49: 380.62 | I49: =H49 -> 380.62 | J49: =(I49-G49)/G49 -> 0.084665584 | K49: BlueChoice Advantage HSA BlueFund Silver Plan - $1,600 | L49: =IF($N$1*H49>=I49,I49,$N$1*H49) -> 304.496 | M49: =I49-L49 -> 76.124 | N49: =(L49-E49)/E49 -> -0.090051699 | O49: =(M49-F49)/F49 -> 3.6759214 | P49: =M49/I49 -> 0.2
A50: Natalie M Abegesah | B50: 3 | C50: 31872 | D50: =($B$3-C50)/365 -> 36.347945 | E50: 1417.7 | F50: 68.98 | G50: 1486.68 | H50: 469.1 | I50: =SUM(H50:H53) -> 1633.47 | J50: =(I50-G50)/G50 -> 0.098736783 | K50: BlueChoice Advantage HSA BlueFund Silver Plan - $1,600 | L50: =IF($N$1*H50+$P$1*SUM(H51:H53)>=I50,I50,$N$1*H50+$P$1*SUM(H51:H53)) -> 1306.776 | M50: =I50-L50 -> 326.694 | N50: =(L50-E50)/E50 -> -0.078242223 | O50: =(M50-F50)/F50 -> 3.7360684 | P50: =M50/I50 -> 0.2
D51: 37 | H51: 479.57
D52: 17 | H52: 342.4
D53: 15 | H53: 342.4
A54: Nilu Rimal | B54: 1 | C54: 24635 | D54: =($B$3-C54)/365 -> 56.175342 | E54: 1727.46 | F54: 84.05 | G54: 1811.51 | H54: 942.91 | I54: =SUM(H54:H55) -> 2000.48 | J54: =(I54-G54)/G54 -> 0.10431629 | K54: BlueChoice Advantage HSA BlueFund Silver Plan - $1,600 | L54: =IF($N$1*H54+$P$1*H55>=I54,I54,$N$1*H54+$P$1*H55) -> 1600.384 | M54: =I54-L54 -> 400.096 | N54: =(L54-E54)/E54 -> -0.07356234 | O54: =(M54-F54)/F54 -> 3.7602142 | P54: =M54/I54 -> 0.2
D55: 59 | H55: 1057.57
A56: Genesis C Torres-Alcantara | B56: 0 | C56: 34977 | D56: =($B$3-C56)/365 -> 27.841096 | E56: 334.63 | F56: 2.76 | G56: 337.39 | H56: 380.62 | I56: =H56 -> 380.62 | J56: =(I56-G56)/G56 -> 0.12813065 | K56: BlueChoice Advantage HSA BlueFund Silver Plan - $1,600 | L56: =IF($N$1*H56>=I56,I56,$N$1*H56) -> 304.496 | M56: =I56-L56 -> 76.124 | N56: =(L56-E56)/E56 -> -0.090051699 | O56: =(M56-F56)/F56 -> 26.581159 | P56: =M56/I56 -> 0.2
A57: Arlette G Gutierrez | B57: 0 | C57: 28471 | D57: =($B$3-C57)/365 -> 45.665753 | E57: 523.34 | F57: 4.33 | G57: 527.67 | H57: 618.31 | I57: =H57 -> 618.31 | J57: =(I57-G57)/G57 -> 0.17177403 | K57: BlueChoice Advantage HSA BlueFund Silver Plan - $1,600 | L57: =IF($N$1*H57>=I57,I57,$N$1*H57) -> 494.648 | M57: =I57-L57 -> 123.662 | N57: =(L57-E57)/E57 -> -0.054824779 | O57: =(M57-F57)/F57 -> 27.559353 | P57: =M57/I57 -> 0.2
A58: John Robert McPhail | B58: 4 | C58: 25137 | D58: =($B$3-C58)/365 -> 54.8 | E58: 2342.87 | F58: 19.35 | G58: 2362.22 | H58: 873.28 | I58: =SUM(H58:H62) -> 2726.12 | J58: =(I58-G58)/G58 -> 0.15405 | K58: BlueChoice Advantage HSA BlueFund Silver Plan - $1,600 | L58: =IF($N$1*H58+$P$1*SUM(H59:H62)>=I58,I58,$N$1*H58+$P$1*SUM(H59:H62)) -> 2180.896 | M58: =I58-L58 -> 545.224 | N58: =(L58-E58)/E58 -> -0.069134865 | O58: =(M58-F58)/F58 -> 27.176951 | P58: =M58/I58 -> 0.2
D59: 50 | H59: 749.2
D60: 25 | H60: 380.62
D61: 24 | H61: 380.62
D62: 19 | H62: 342.4
A63: Rachel Shoshana Falek | B63: 0 | C63: 35017 | D63: =($B$3-C63)/365 -> 27.731507 | E63: 334.63 | F63: 159.88 | G63: 494.51 | H63: 380.62 | I63: =H63 -> 380.62 | J63: =(I63-G63)/G63 -> -0.23030879 | K63: BlueChoice Advantage HSA BlueFund Silver Plan - $1,600 | L63: =IF($N$1*H63>=I63,I63,$N$1*H63) -> 304.496 | M63: =I63-L63 -> 76.124 | N63: =(L63-E63)/E63 -> -0.090051699 | O63: =(M63-F63)/F63 -> -0.5238679 | P63: =M63/I63 -> 0.2
A64: Angel Kristina Rutter | B64: 0 | C64: 35099 | D64: =($B$3-C64)/365 -> 27.506849 | E64: 334.63 | F64: 76.22 | G64: 410.85 | H64: 380.62 | I64: =H64 -> 380.62 | J64: =(I64-G64)/G64 -> -0.073579165 | K64: BlueChoice Advantage HSA BlueFund Silver Plan - $1,600 | L64: =IF($N$1*H64>=I64,I64,$N$1*H64) -> 304.496 | M64: =I64-L64 -> 76.124 | N64: =(L64-E64)/E64 -> -0.090051699 | O64: =(M64-F64)/F64 -> -0.0012595119 | P64: =M64/I64 -> 0.2
A65: Katherine Julia Matteson de Araujo | B65: 0 | C65: 35229 | D65: =($B$3-C65)/365 -> 27.150685 | E65: 334.63 | F65: 76.22 | G65: 410.85 | H65: 380.62 | I65: =H65 -> 380.62 | J65: =(I65-G65)/G65 -> -0.073579165 | K65: BlueChoice Advantage HSA BlueFund Silver Plan - $1,600 | L65: =IF($N$1*H65>=I65,I65,$N$1*H65) -> 304.496 | M65: =I65-L65 -> 76.124 | N65: =(L65-E65)/E65 -> -0.090051699 | O65: =(M65-F65)/F65 -> -0.0012595119 | P65: =M65/I65 -> 0.2
A66: Maia Moore | B66: 0 | C66: 34375 | D66: =($B$3-C66)/365 -> 29.490411 | E66: 342.46 | F66: 78 | G66: 420.46 | H66: 397.9 | I66: =H66 -> 397.9 | J66: =(I66-G66)/G66 -> -0.05365552 | K66: BlueChoice Advantage HSA BlueFund Silver Plan - $1,600 | L66: =IF($N$1*H66>=I66,I66,$N$1*H66) -> 318.32 | M66: =I66-L66 -> 79.58 | N66: =(L66-E66)/E66 -> -0.070489984 | O66: =(M66-F66)/F66 -> 0.02025641 | P66: =M66/I66 -> 0.2
A67: Sarah F Smith | B67: 0 | C67: 31779 | D67: =($B$3-C67)/365 -> 36.60274 | E67: 403.22 | F67: 91.83 | G67: 495.05 | H67: 469.1 | I67: =H67 -> 469.1 | J67: =(I67-G67)/G67 -> -0.052418948 | K67: BlueChoice Advantage HSA BlueFund Silver Plan - $1,600 | L67: =IF($N$1*H67>=I67,I67,$N$1*H67) -> 375.28 | M67: =I67-L67 -> 93.82 | N67: =(L67-E67)/E67 -> -0.069292198 | O67: =(M67-F67)/F67 -> 0.021670478 | P67: =M67/I67 -> 0.2
A68: Ukiah Busch | B68: 3 | C68: 31376 | D68: =($B$3-C68)/365 -> 37.706849 | E68: 1417.7 | F68: 322.91 | G68: 1740.61 | H68: 479.57 | I68: =SUM(H68:H71) -> 1633.47 | J68: =(I68-G68)/G68 -> -0.061553134 | K68: BlueChoice Advantage HSA BlueFund Silver Plan - $1,600 | L68: =IF($N$1*H68+$P$1*SUM(H69:H71)>=I68,I68,$N$1*H68+$P$1*SUM(H69:H71)) -> 1306.776 | M68: =I68-L68 -> 326.694 | N68: =(L68-E68)/E68 -> -0.078242223 | O68: =(M68-F68)/F68 -> 0.011718435 | P68: =M68/I68 -> 0.2
D69: 36 | H69: 469.1
D70: 9 | H70: 342.4
D71: 5 | H71: 342.4
A72: Robert Colbry Maher | B72: 0 | C72: 34315 | D72: =($B$3-C72)/365 -> 29.654795 | E72: 342.46 | F72: 101.28 | G72: 443.74 | H72: 397.9 | I72: =H72 -> 397.9 | J72: =(I72-G72)/G72 -> -0.10330374 | K72: BlueChoice Advantage HSA BlueFund Silver Plan - $1,600 | L72: =IF($N$1*H72>=I72,I72,$N$1*H72) -> 318.32 | M72: =I72-L72 -> 79.58 | N72: =(L72-E72)/E72 -> -0.070489984 | O72: =(M72-F72)/F72 -> -0.2142575 | P72: =M72/I72 -> 0.2
A73: Abraham Cisne | B73: 0 | C73: 30417 | D73: =($B$3-C73)/365 -> 40.334247 | E73: 431.75 | F73: 127.69 | G73: 559.44 | H73: 510.46 | I73: =H73 -> 510.46 | J73: =(I73-G73)/G73 -> -0.087551838 | K73: BlueChoice Advantage HSA BlueFund Silver Plan - $1,600 | L73: =IF($N$1*H73>=I73,I73,$N$1*H73) -> 408.368 | M73: =I73-L73 -> 102.092 | N73: =(L73-E73)/E73 -> -0.05415634 | O73: =(M73-F73)/F73 -> -0.20046989 | P73: =M73/I73 -> 0.2
A74: Colleen Suzanne Boyne | B74: 0 | C74: 30382 | D74: =($B$3-C74)/365 -> 40.430137 | E74: 431.75 | F74: 127.69 | G74: 559.44 | H74: 510.46 | I74: =H74 -> 510.46 | J74: =(I74-G74)/G74 -> -0.087551838 | K74: BlueChoice Advantage HSA BlueFund Silver Plan - $1,600 | L74: =IF($N$1*H74>=I74,I74,$N$1*H74) -> 408.368 | M74: =I74-L74 -> 102.092 | N74: =(L74-E74)/E74 -> -0.05415634 | O74: =(M74-F74)/F74 -> -0.20046989 | P74: =M74/I74 -> 0.2
A75: Allison S McGovern | B75: 0 | C75: 35557 | D75: =($B$3-C75)/365 -> 26.252055 | E75: 334.63 | F75: 151.06 | G75: 485.69 | H75: 380.62 | I75: =H75 -> 380.62 | J75: =(I75-G75)/G75 -> -0.2163314 | K75: BlueChoice Advantage HSA BlueFund Silver Plan - $1,600 | L75: =IF($N$1*H75>=I75,I75,$N$1*H75) -> 304.496 | M75: =I75-L75 -> 76.124 | N75: =(L75-E75)/E75 -> -0.090051699 | O75: =(M75-F75)/F75 -> -0.49606779 | P75: =M75/I75 -> 0.2
A76: Hannah Elizabeth Guernsey (COBRA) | B76: 0 | C76: 34137 | D76: =($B$3-C76)/365 -> 30.142466 | E76: 0 | F76: 507.74 | G76: 507.74 | H76: 407.85 | I76: =H76 -> 407.85 | J76: =(I76-G76)/G76 -> -0.19673455 | K76: BlueChoice Advantage HSA BlueFund Silver Plan - $1,600 | L76: 0 | M76: =I76-L76 -> 407.85 | N76: =(L76-E76)/E76 -> #DIV/0! | O76: =(M76-F76)/F76 -> -0.19673455 | P76: =(N76-G76)/G76 -> #DIV/0!
L78: Monthly Cost based on 5/1 Invoice (less COBRAs) | M78: =SUM(E6:E75) -> 29245.45
L79: Estimated Monthly Cost Renewal 8.1.23 | M79: =SUM(L6:L76)-L76 -> 27315.888
L80: Difference | M80: =M79-M78 -> -1929.562
L81: Percentage Change | M81: =M80/M78 -> -0.065978195
L82: Annual Difference | M82: =M80*12 -> -23154.744
L83: Additional Possible Liability HRA | M83: =25*1600+16*3200 -> 91200
L84: Total Change | M84: =SUM(M82:M83) -> 68045.256
L85: Renewal % | M85: =M84/(M78*12) -> 0.19389129
