Workbook
Name \a: #REF!
Name \c: #REF!
Name \i: #REF!
Name \P: #REF!
Name \r: #REF!
Name __pd1: #REF!
Name __pd6: #REF!
Name __tix1: #REF!
Name __tix2: #REF!
Name __tix6: #REF!
Name _1: #REF!
Name _1998: #REF!
Name _1999: #REF!
Name _2: #REF!
Name _2000: #REF!
Name _2001: #REF!
Name _2002: #REF!
Name _3: #REF!
Name _4: #REF!
Name _5: #REF!
Name _6: #REF!
Name _7: #REF!
Name _8: #REF!
Name _fmi1: #REF!
Name _fmi2: #REF!
Name _fmi3: #REF!
Name _fmi4: #REF!
Name _PIB01: #REF!
Name _PIB02: #REF!
Name _PIB95: #REF!
Name _PIB96: #REF!
Name _PIB97: #REF!
Name _PIB98: #REF!
Name _PIB99: #REF!
Name _RES9397: #REF!
Name _rez2: #REF!
Name _rez3: #REF!
Name _rez4: #REF!
Name a: #REF!
Name A_2002: #REF!
Name A_CAPITAL: #REF!
Name A_DEPTOS: #REF!
Name A_impresión_IM: #REF!
Name A_MUNPIOS: #REF!
Name AAA: #REF!
Name AEFormar: #REF!
Name Ajustado: #REF!
Name almuerzo: #REF!
Name alquilertableta: #REF!
Name ANEXO_No.: #REF!
Name ANEXO_No._5: #REF!
Name ANPDH: #REF!
Name aprnac: #REF!
Name APROPIACIONES_PAC_Y_REZAGO_1999___2000: #REF!
Name aprprp: #REF!
Name asigbas: #REF!
Name asigbasempu: #REF!
Name asigbasisten: #REF!
Name asigmen: #REF!
Name auxalm: #REF!

Sheet OrigBudget Summary ProAntioquia
B1: Name of Subawardee: ProAntioquia
B2: USAID RFA No. 7200AA21RFA00001
A4: Line Items | B4: Year 1 | E4: Year 2 | H4: Year 3 | K4: Year 4 | N4: Year 5 | Q4: Total | R4: Total | S4: Grand
B5: USAID | C5: Leverage | D5: Total | E5: USAID | F5: Leverage | G5: Total | H5: USAID | I5: Leverage | J5: Total | K5: USAID | L5: Leverage | M5: Total | N5: USAID | O5: Leverage | P5: Total | Q5: USAID | R5: Leverage | S5: Total
A7: Personnel | B7: 146525 | C7: 29706.9 | D7: =SUM(B7:C7) -> 176231.9 | E7: 180648 | F7: 33006.272 | G7: =SUM(E7:F7) -> 213654.27 | H7: 187873.92 | I7: 34326.523 | J7: =SUM(H7:I7) -> 222200.44 | K7: 195388.88 | L7: 35699.584 | M7: =SUM(K7:L7) -> 231088.46 | N7: 175186.32 | O7: 35922.73 | P7: =SUM(N7:O7) -> 211109.05 | Q7: 885622.12 | R7: 168662.01 | S7: 1054284.1
A9: Fringe Benefits | B9: 68799.226 | C9: 13520.295 | D9: 82319.521 | E9: 84668.239 | F9: 15057.827 | G9: 99726.066 | H9: 88054.968 | I9: 15660.14 | J9: 103715.11 | K9: 91577.167 | L9: 16286.546 | M9: 107863.71 | N9: 83109.782 | O9: 16289.034 | P9: 99398.816 | Q9: 416209.38 | R9: 76813.842 | S9: 493023.22
A11: Travel | B11: 18570 | C11: 0 | D11: 18570 | E11: 19700.7 | F11: 0 | G11: 19700.7 | H11: 21801.801 | I11: 0 | J11: 21801.801 | K11: 21847.131 | L11: 0 | M11: 21847.131 | N11: 21546.523 | O11: 0 | P11: 21546.523 | Q11: 103466.15 | R11: 0 | S11: 103466.15
A13: Equipment | B13: 50000 | C13: 0 | D13: 50000 | E13: 0 | F13: 0 | G13: 0 | H13: 0 | I13: 0 | J13: 0 | K13: 0 | L13: 0 | M13: 0 | N13: 0 | O13: 0 | P13: 0 | Q13: 50000 | R13: 0 | S13: 50000
A15: Supplies | B15: 15344.91 | C15: 3336 | D15: 18680.91 | E15: 9270 | F15: 4466.904 | G15: 13736.904 | H15: 9548.1 | I15: 4600.9111 | J15: 14149.011 | K15: 4917.2715 | L15: 4738.9385 | M15: 9656.21 | N15: 3798.5922 | O15: 4881.1066 | P15: 8679.6988 | Q15: 42878.874 | R15: 22023.86 | S15: 64902.734
A17: Contractual | B17: 42850 | C17: 0 | D17: 42850 | E17: 47050 | F17: 0 | G17: 47050 | H17: 22050 | I17: 0 | J17: 22050 | K17: 22050 | L17: 0 | M17: 22050 | N17: 19950 | O17: 0 | P17: 19950 | Q17: 153950 | R17: 0 | S17: 153950
A19: Other Direct Costs | B19: 105566 | C19: 33306 | D19: 138872 | E19: 176388.48 | F19: 0 | G19: 176388.48 | H19: 85222.354 | I19: 0 | J19: 85222.354 | K19: 94155.779 | L19: 0 | M19: 94155.779 | N19: 20519.592 | O19: 0 | P19: 20519.592 | Q19: 481852.2 | R19: 33306 | S19: 515158.2
A21: Total Direct Costs | B21: =SUM(B7:B20) -> 447655.14 | C21: =SUM(C7:C20) -> 79869.195 | D21: =SUM(D7:D20) -> 527524.33 | E21: =SUM(E7:E20) -> 517725.42 | F21: =SUM(F7:F20) -> 52531.003 | G21: =SUM(G7:G20) -> 570256.42 | H21: =SUM(H7:H20) -> 414551.14 | I21: =SUM(I7:I20) -> 54587.574 | ... S21: =SUM(S7:S20) -> 2434784.4
A22: Indirect Costs | B22: 0 | C22: 0 | D22: 0 | E22: 0 | F22: 0 | G22: 0 | H22: 0 | I22: 0 | J22: 0 | K22: 0 | L22: 0 | M22: 0 | N22: 0 | O22: 0 | P22: 0 | Q22: 0 | R22: 0 | S22: 0
A23: Total | B23: =B22+B21 -> 447655.14 | C23: =C22+C21 -> 79869.195 | D23: =D22+D21 -> 527524.33 | E23: =E22+E21 -> 517725.42 | F23: =F22+F21 -> 52531.003 | G23: =G22+G21 -> 570256.42 | H23: =H22+H21 -> 414551.14 | I23: =I22+I21 -> 54587.574 | ... S23: =S22+S21 -> 2434784.4

Sheet Budget ProAntioquia
J1: USAID Juntos Aprendemos
J2: ProAntioquia
J3: Subaward Budget
J4: Country: Colombia
F5: Budget Assumptions
F6: Inflation - Locally Purchased Goods/Services - 6% | J6: 1.03
F7: Merit Based Increases for HQ & Field Staff - 4% | J7: 1.04
F8: *Key Personnel | J8: Original Budget | AR8: Actuals/Estimates Year 1 and 2 | BB8: Projections for Year 3 -5 | CE8: New Proposed Budget Total | CH8: DEFICIT/SURPLUS | CK8: SALDO | CL8: BALANCE | CM8: 4 | CN8: 5 | CO8: 7 | CP8: 10 | CQ8: 14 | CR8: 15 | CS8: 16 | CT8: 27 USAID | CU8: 27 LEVERAGE | CV8: 37 | CW8: 38 | CX8: 39 | CY8: 40 | CZ8: 45 | DA8: 46 | DB8: 47 | DC8: 49 | DD8: 51 | DE8: 52 | DF8: 53 | DG8: 54 | DH8: 56 | DI8: 57 | DJ8: 58 | DK8: 59 | DL8: 61 | DM8: 62 | DN8: 63 | DO8: 64 | DP8: 66 | DQ8: 67 | DR8: 68 | DS8: 69 | DT8: 73 | DU8: 85 | DV8: 90 | DW8: 91 | DX8: 92 | DY8: 97 | DZ8: 102 | EA8: 103 | EB8: 104 | EC8: 110 | ED8: 111 | EE8: 112 | EF8: 113 | EG8: 115 | EH8: 116 | EI8: 117 | EJ8: 120 | EK8: 122 | EL8: 123 | EM8: 124 | EN8: 129 | EO8: 131 | EP8: 132 | EQ8: 134 | ER8: 135 | ES8: 137
A9: Sage Activity | B9: Account Code | C9: Country Code | D9: Sub Activity | F9: Line Items | J9: Year 1 | Q9: Year 2 | W9: Year 3 | AC9: Year 4 | AI9: Year 5 | AO9: Total | AP9: Total | AQ9: Grand | AR9: Year 1 | AT9: Year 2 | AV9: Total | BB9: Year 3 | BI9: Year 4 | BO9: Year 5 | BU9: Year 6 | CA9: Year 3- 6 | CB9: Year 3- 6 | CC9: Year 3- 6 | CE9: Total | CF9: Total | CG9: Grand | CM9: BUDGET REALIGNEMENT
E10: LINE NUMBER | F10: Line Items | G10: SECTION | H10: SUB-SCTION | I10: SOURCE | J10: Unit | K10: Cost | L10: Duration | M10: Type | N10: USAID | O10: Leverage | P10: Total | Q10: Unit | R10: Cost | S10: Duration | T10: USAID | U10: Leverage | V10: Total | W10: Unit | X10: Cost | Y10: Duration | Z10: USAID | AA10: Leverage | AB10: Total | AC10: Unit | AD10: Cost | AE10: Duration | AF10: USAID | AG10: Leverage | AH10: Total | AI10: Unit | AJ10: Cost | AK10: Duration | AL10: USAID | AM10: Leverage | AN10: Total | AO10: USAID | AP10: Leverage | AQ10: Total | AR10: USAID Year 1 -Actuals August 16, 2021 - December 31, 2021 | AS10: Leverage Year 1 -Actuals August 16, 2021 - December 31, 2021 | AT10: USAID Year 2 -Actuals/Estimate January 1, 2022 - December 31, 2022 | AU10: Leverage Year 2 -Actuals/Estimate January 1, 2022 - December 31, 2022 | AV10: USAID EXECUTED | AW10: LEVERAGE EXECUTED | AX10: TOTAL EXECUTED | AY10: Balance remaining | AZ10: Balance Remaining | BA10: Control | BB10: Unit | BC10: Cost | BD10: Duration | BE10: USAID | BF10: Leverage | BG10: Total | BH10: NOTAS | BI10: Unit | BJ10: Cost | BK10: Duration | BL10: USAID | BM10: Leverage | BN10: Total | BO10: Unit | BP10: Cost | BQ10: Duration | BR10: USAID | BS10: Leverage | BT10: Total | BU10: Unit | BV10: Cost | BW10: Duration | BX10: USAID | BY10: Leverage | BZ10: Total | CA10: Total USAID | CB10: Total Leverage | CC10: Grand Total | CE10: USAID | CF10: Leverage | CG10: Total | CH10: USAID DEFICIT/SURPLUS | CI10: LEVERAGE DEFICIT/SURPLUS | CJ10: TOTAL DEFICIT/SURPLUS | CM10: Partnerships and Alliances Director* | CN10: Partnerships and Alliances Coordinator | CO10: Education Director (HQ-ProAntioquia) | CP10: Teacher Training Specialist (2) | CQ10: Visual Documentation Communications Professional | CR10: Content Development Professional | CS10: Finance & Admin Coordinator Project Analyst | CT10: Fringe Benefits – Colombia HQ and Field Staff (above $2,600 monthly) | CU10: Fringe Benefits – Colombia HQ and Field Staff (above $2,600 monthly) | CV10: Local Transportation (Airfare, Taxis, & Rental Car/Driver) for Directors | CW10: Meals and Incidentals for Directors | CX10: Lodging for Directors | CY10: Other Travel Related Expenses for Directors | CZ10: Meals and Incidentals for Site Visits and M&E | DA10: Lodging for Site Visits and M&E | DB10: Other Travel Related Expenses for Site Visits and M&E | DC10: Vehicle Fuel Expense | DD10: Local Transportation for Advisory Board Meetings | DE10: Meals and Incidentals for Advisory Board Meetings | DF10: Lodging for Advisory Board Meetings | DG10: Other Travel Related Expenses for Advisory Board Meetings | DH10: Local Transportation for Annual Forums | DI10: Meals and Incidentals for Annual Forums | DJ10: Lodging for Annual Forums | DK10: Other Travel Related Expenses for Annual Forums | DL10: Local Transportation for SMT Meetings | DM10: Meals and Incidentals for SMT Meetings | DN10: Lodging for SMT Meetings | DO10: Other Travel Related Expenses for SMT Meetings | DP10: Local Transportation for Steering Committee Meeting | DQ10: Meals and Incidentals for Steering Committee Meeting | DR10: Lodging for Steering Committee Meeting | DS10: Other Travel Related Expenses for Steering Committee Meeting | DT10: Vehicle for Field Office | DU10: Personal Protective Equipment (Gloves, Masks, Hand Sanitizer, Antibacterial Wipes etc.) | DV10: Consultant for data analysis to build public policy guidelines | DW10: Consultant for technical advice for advocacy on public policy | DX10: Entrena-QL methodology for development of educational materials | DY10: Local Office Security Contractor (Local Hire) | DZ10: Prototypes and pilots of educational materials | EA10: Adaptation of existing content and methodologies for educational materials | EB10: Content for school campaigns | EC10: Translation costs | ED10: Courier fees/services/postage | EE10: Banking and cash handling fees | EF10: Vehicle Insurance & Maintenance | EG10: Development of teacher training books for Replica Workshops | EH10: Graphic and operational design of digital courses | EI10: Graphic design for teachers training materials | EJ10: Transport of books for children | EK10: Process systematization book | EL10: Videos for teacher training | EM10: Books for children (Collection of NEXO literary) | EN10: Printing of informational materials | EO10: Round table with local private sector to build public policy guidelines | EP10: Regional workshops about strategic themes of public policy guidelines | EQ10: M&E Database Platform Access | ER10: Data Collection Tools | ES10: On-going Training Workshops for Data Collection Staff
E11: 1 | F11: PERSONNEL | CL11: =SUM(CM12:ES152) -> 0
E12: 2 | F12: Headquarters Personnel | J12: LOE | CK12: =SUM(CM12:ES12) -> 0 | CL12: =CJ12+CK12 -> 0
E13: 3 | F13: Project Office (Bogota) | CK13: =SUM(CM13:ES13) -> 0 | CL13: =CJ13+CK13 -> 0
A14: SUBPROANT | B14: 89050 | C14: COL2 | D14: PAPERSNL | E14: 4 | F14: Partnerships and Alliances Director* | G14: PERSONNEL | H14: Project Office (Bogota) | I14: USAID | J14: 1 | K14: =52500/12 -> 4375 | L14: 11 | M14: /months | N14: =L14*K14*J14 -> 48125 | O14: 0 | P14: =SUM(N14:O14) -> 48125 | Q14: =J14 -> 1 | R14: =K14*$J$7 -> 4550 | S14: 12 | T14: =Q14*R14*S14 -> 54600 | U14: 0 | V14: =SUM(T14:U14) -> 54600 | W14: =J14 -> 1 | X14: =+K14*$J$7*$J$7 -> 4732 | Y14: 12 | Z14: =W14*X14*Y14 -> 56784 | AA14: 0 | AB14: =SUM(Z14:AA14) -> 56784 | AC14: =W14 -> 1 | AD14: =+K14*$J$7*$J$7*$J$7 -> 4921.28 | AE14: 12 | AF14: =AC14*AD14*AE14 -> 59055.36 | AG14: 0 | AH14: =SUM(AF14:AG14) -> 59055.36 | AI14: =AC14 -> 1 | AJ14: =+K14*$J$7*$J$7*$J$7*$J$7 -> 5118.1312 | AK14: 12 | AL14: =AI14*AJ14*AK14 -> 61417.574 | AM14: 0 | AN14: =SUM(AL14:AM14) -> 61417.574 | AO14: =N14+T14+Z14+AF14+AL14 -> 279981.93 | AP14: =O14+U14+AA14+AG14+AM14 -> 0 | AQ14: =SUM(AO14:AP14) -> 279981.93 | AR14: 0 | AS14: 0 | AT14: =3252.77+3817.03+3948.19+3962.6+3739.26+3813.47+3433.22+3475.34+3384.44+3177.56+3047.83+3137.35 -> 42189.06 | AU14: 0 | AV14: =AR14+AT14 -> 42189.06 | AW14: =AS14+AU14 -> 0 | AX14: =AV14+AW14 -> 42189.06 | AY14: =AQ14-AX14 -> 237792.87 | AZ14: =AQ14-AR14-AS14-AT14-AU14 -> 237792.87 | BA14: =AY14-AZ14 -> 0 | BB14: 1 | BC14: 2923.08 | BD14: 7.9483 | BE14: =BB14*BC14*BD14 -> 23233.517 | BF14: =AA14 -> 0 | BG14: =SUM(BE14:BF14) -> 23233.517 | BH14: Key Personnel responsable de liderar la implementación de procesos y actividades de formalización de Alianzas. Se contrata la nueva persona en este rol el 8 de mayo de 2023 por el tiempo del proyecto. | BI14: 1 | BJ14: =BC14*1.04 -> 3040.0032 | BK14: 12 | BL14: =BI14*BJ14*BK14 -> 36480.038 | BM14: 0 | BN14: =SUM(BL14:BM14) -> 36480.038 | BO14: 1 | BP14: =BJ14*1.04 -> 3161.6033 | BQ14: 12 | BR14: =BO14*BP14*BQ14 -> 37939.24 | BS14: 0 | BT14: =SUM(BR14:BS14) -> 37939.24 | BU14: 1 | BV14: =BP14*1.04 -> 3288.0675 | BW14: 6 | BX14: =BW14*BV14 -> 19728.405 | BY14: 0 | BZ14: =BY14+BX14 -> 19728.405 | CA14: =BR14+BL14+BE14+BX14 -> 117381.2 | CB14: =BY14+BS14+BM14+BF14 -> 0 | CC14: =CA14+CB14 -> 117381.2 | CE14: =AV14+CA14 -> 159570.26 | CF14: =AW14+CB14 -> 0 | CG14: =CE14+CF14 -> 159570.26 | CH14: =AO14-CE14 -> 120411.67 | CI14: =AP14-CF14 -> 0 | CJ14: =AQ14-CG14 -> 120411.67 | CK14: =SUM(CM14:ES14) -> -120412 | CL14: =CJ14+CK14 -> -0.32546672 | CM14: -120412
A15: SUBPROANT | B15: 89050 | C15: COL2 | D15: PAPERSNL | E15: 5 | F15: Partnerships and Alliances Coordinator | G15: PERSONNEL | H15: Project Office (Bogota) | I15: USAID | J15: 1 | K15: =22500/12 -> 1875 | L15: 9 | M15: /months | N15: =L15*K15*J15 -> 16875 | O15: 0 | P15: =SUM(N15:O15) -> 16875 | Q15: =J15 -> 1 | R15: =K15*$J$7 -> 1950 | S15: 12 | T15: =Q15*R15*S15 -> 23400 | U15: 0 | V15: =SUM(T15:U15) -> 23400 | W15: =J15 -> 1 | X15: =+K15*$J$7*$J$7 -> 2028 | Y15: 12 | Z15: =W15*X15*Y15 -> 24336 | AA15: 0 | AB15: =SUM(Z15:AA15) -> 24336 | AC15: =W15 -> 1 | AD15: =+K15*$J$7*$J$7*$J$7 -> 2109.12 | AE15: 12 | AF15: =AC15*AD15*AE15 -> 25309.44 | AG15: 0 | AH15: =SUM(AF15:AG15) -> 25309.44 | AI15: =AC15 -> 1 | AJ15: =+K15*$J$7*$J$7*$J$7*$J$7 -> 2193.4848 | AK15: 10 | AL15: =AI15*AJ15*AK15 -> 21934.848 | AM15: 0 | AN15: =SUM(AL15:AM15) -> 21934.848 | AO15: =N15+T15+Z15+AF15+AL15 -> 111855.29 | AP15: =O15+U15+AA15+AG15+AM15 -> 0 | AQ15: =SUM(AO15:AP15) -> 111855.29 | AR15: 0 | AS15: 0 | AT15: =1144.41+1737.67+1692.22+1588.78+1523.92+1568.68 -> 9255.68 | AU15: 0 | AV15: =AR15+AT15 -> 9255.68 | AW15: =AS15+AU15 -> 0 | AX15: =AV15+AW15 -> 9255.68 | AY15: =AQ15-AX15 -> 102599.61 | AZ15: =AQ15-AR15-AS15-AT15-AU15 -> 102599.61 | BA15: =AY15-AZ15 -> 0 | BB15: 1 | BC15: 1861.4 | BD15: 12 | BE15: =BC15*BD15 -> 22336.8 | BF15: =AA15 -> 0 | BG15: =SUM(BE15:BF15) -> 22336.8 | BH15: Responsable de coordinar la implementación de procesos y actividades de formalización de alianzas en el marco del programa Juntos Aprendemos . | BI15: 1 | BJ15: =BC15*1.04 -> 1935.856 | BK15: 12 | BL15: =BK15*BJ15*BI15 -> 23230.272 | BM15: 0 | BN15: =SUM(BL15:BM15) -> 23230.272 | BO15: 1 | BP15: =BJ15*1.04 -> 2013.2902 | BQ15: 10 | BR15: =BQ15*BP15*BO15 -> 20132.902 | BS15: 0 | BT15: =SUM(BR15:BS15) -> 20132.902 | BU15: 0 | BV15: 0 | BW15: 0 | BX15: =BW15*BV15 -> 0 | BY15: 0 | BZ15: =BY15+BX15 -> 0 | CA15: =BR15+BL15+BE15+BX15 -> 65699.974 | CB15: =BY15+BS15+BM15+BF15 -> 0 | CC15: =CA15+CB15 -> 65699.974 | CE15: =AV15+CA15 -> 74955.654 | CF15: =AW15+CB15 -> 0 | CG15: =CE15+CF15 -> 74955.654 | CH15: =AO15-CE15 -> 36899.634 | CI15: =AP15-CF15 -> 0 | CJ15: =AQ15-CG15 -> 36899.634 | CK15: =SUM(CM15:ES15) -> -36900 | CL15: =CJ15+CK15 -> -0.3664 | CN15: -36900
E16: 6 | F16: ProAntioquia Office | CG16: =CE16+CF16 -> 0 | CJ16: =AQ16-CG16 -> 0 | CK16: =SUM(CM16:ES16) -> 0 | CL16: =CJ16+CK16 -> 0
E17: 7 | F17: Education Director (HQ-ProAntioquia) | G17: PERSONNEL | H17: ProAntioquia Office | I17: LEVERAGE | J17: 0.3 | K17: 3433 | L17: 11 | M17: /months | N17: 0 | O17: =+J17*K17*L17 -> 11328.9 | P17: =SUM(N17:O17) -> 11328.9 | Q17: =J17 -> 0.3 | R17: =K17*$J$7 -> 3570.32 | S17: 12 | T17: 0 | U17: =+Q17*R17*S17 -> 12853.152 | V17: =SUM(T17:U17) -> 12853.152 | W17: =J17 -> 0.3 | X17: =+K17*$J$7*$J$7 -> 3713.1328 | Y17: 12 | Z17: 0 | AA17: =+W17*X17*Y17 -> 13367.278 | AB17: =SUM(Z17:AA17) -> 13367.278 | AC17: =W17 -> 0.3 | AD17: =+K17*$J$7*$J$7*$J$7 -> 3861.6581 | AE17: 12 | AF17: 0 | AG17: =+AC17*AD17*AE17 -> 13901.969 | AH17: =SUM(AF17:AG17) -> 13901.969 | AI17: =AC17 -> 0.3 | AJ17: =+K17*$J$7*$J$7*$J$7*$J$7 -> 4016.1244 | AK17: 11 | AL17: 0 | AM17: =+AI17*AJ17*AK17 -> 13253.211 | AN17: =SUM(AL17:AM17) -> 13253.211 | AO17: =N17+T17+Z17+AF17+AL17 -> 0 | AP17: =O17+U17+AA17+AG17+AM17 -> 64704.51 | AQ17: =SUM(AO17:AP17) -> 64704.51 | AR17: 0 | AS17: 0 | AT17: 0 | AU17: =464.15+480.1+481.85+454.69+463.72 -> 2344.51 | AV17: =AR17+AT17 -> 0 | AW17: =AS17+AU17 -> 2344.51 | AX17: =AV17+AW17 -> 2344.51 | AY17: =AQ17-AX17 -> 62360 | AZ17: =AQ17-AR17-AS17-AT17-AU17 -> 62360 | BA17: =AY17-AZ17 -> 0 | BB17: 0.2 | BC17: 13367 | BE17: =BB17*BC17*BD17 -> 0 | BF17: =BC17 -> 13367 | BG17: =SUM(BE17:BF17) -> 13367 | BH17: Tiempos de dedicación al programa de la dirección del area de Educación de la fundación Proantioquia. (Leverage). | BI17: 0 | BJ17: 0 | BK17: 0 | BL17: =BK17*BJ17*BI17 -> 0 | BM17: =13901.9692032 -> 13901.969 | BN17: =SUM(BL17:BM17) -> 13901.969 | BO17: 0 | BP17: 0 | BQ17: 0 | BR17: =BQ17*BP17*BO17 -> 0 | BS17: =13253.210640384 -> 13253.211 | BT17: =SUM(BR17:BS17) -> 13253.211 | BU17: 0 | BV17: 0 | BW17: 0 | BX17: 0 | BY17: =(BS17/12)*2 -> 2208.8684 | BZ17: =BY17+BX17 -> 2208.8684 | CA17: =BR17+BL17+BE17+BX17 -> 0 | CB17: =BY17+BS17+BM17+BF17 -> 42731.048 | CC17: =CA17+CB17 -> 42731.048 | CE17: =AV17+CA17 -> 0 | CF17: =AW17+CB17 -> 45075.558 | CG17: =CE17+CF17 -> 45075.558 | CH17: =AO17-CE17 -> 0 | CI17: =AP17-CF17 -> 19628.952 | CJ17: =AQ17-CG17 -> 19628.952 | CK17: =SUM(CM17:ES17) -> -19629 | CL17: =CJ17+CK17 -> -0.048360064 | CO17: -19629
E18: 8 | F18: Subtotal HQ Personnel | N18: =SUM(N14:N17) -> 65000 | O18: =SUM(O14:O17) -> 11328.9 | P18: =SUM(P14:P17) -> 76328.9 | T18: =SUM(T14:T17) -> 78000 | U18: =SUM(U14:U17) -> 12853.152 | V18: =SUM(V14:V17) -> 90853.152 | Z18: =SUM(Z14:Z17) -> 81120 | AA18: =SUM(AA14:AA17) -> 13367.278 | AB18: =SUM(AB14:AB17) -> 94487.278 | AD18: =+K18*$J$7*$J$7*$J$7 -> 0 | AF18: =SUM(AF14:AF17) -> 84364.8 | AG18: =SUM(AG14:AG17) -> 13901.969 | AH18: =SUM(AH14:AH17) -> 98266.769 | AL18: =SUM(AL14:AL17) -> 83352.422 | AM18: =SUM(AM14:AM17) -> 13253.211 | AN18: =SUM(AN14:AN17) -> 96605.633 | AO18: =SUM(AO14:AO17) -> 391837.22 | AP18: =SUM(AP14:AP17) -> 64704.51 | AQ18: =SUM(AQ14:AQ17) -> 456541.73 | AR18: =SUM(AR14:AR17) -> 0 | AS18: =SUM(AS14:AS17) -> 0 | AT18: =SUM(AT14:AT17) -> 51444.74 | AU18: =AU17+AU15+AU14 -> 2344.51 | AZ18: =AQ18-AR18-AS18-AT18-AU18 -> 402752.48 | BC18: =BC14+BC15+BC17 -> 18151.48 | BE18: =BE14+BE15 -> 45570.317 | BF18: =BF17 -> 13367 | BG18: =SUM(BE18:BF18) -> 58937.317 | BJ18: =BJ14+BJ15 -> 4975.8592 | BL18: =BL14+BL15 -> 59710.31 | BM18: =BM17 -> 13901.969 | BN18: =SUM(BL18:BM18) -> 73612.28 | BP18: =BP14+BP15 -> 5174.8936 | BR18: =BR14+BR15 -> 58072.142 | BS18: =BS17 -> 13253.211 | BT18: =SUM(BR18:BS18) -> 71325.353 | BV18: =SUM(BV14:BV15) -> 3288.0675 | BX18: =SUM(BX14:BX15) -> 19728.405 | BY18: =BY17 -> 2208.8684 | BZ18: =BY18+BX18 -> 21937.273 | CA18: =SUM(CA14:CA17) -> 183081.17 | CB18: =SUM(CB14:CB17) -> 42731.048 | CC18: =SUM(CC14:CC17) -> 225812.22 | CE18: =SUM(CE14:CE17) -> 234525.91 | CF18: =SUM(CF14:CF17) -> 45075.558 | CG18: =SUM(CG14:CG17) -> 279601.47 | CK18: =SUM(CM18:ES18) -> 0 | CL18: =CJ18+CK18 -> 0
E19: 9 | F19: Field Personnel | J19: LOE | AD19: =+K19*$J$7*$J$7*$J$7 -> 0 | CK19: =SUM(CM19:ES19) -> 0 | CL19: =CJ19+CK19 -> 0
A20: SUBPROANT | B20: 89050 | C20: COL2 | D20: PAPERSNL | E20: 10 | F20: Teacher Training Specialist (2) | G20: PERSONNEL | H20: Field Personnel | I20: USAID | J20: 1 | K20: =31200/12 -> 2600 | L20: 9 | M20: /months | N20: =L20*K20*J20 -> 23400 | O20: 0 | P20: =SUM(N20:O20) -> 23400 | Q20: =J20 -> 1 | R20: =K20*$J$7 -> 2704 | S20: 12 | T20: =Q20*R20*S20 -> 32448 | U20: 0 | V20: =SUM(T20:U20) -> 32448 | W20: =Q20 -> 1 | X20: =+K20*$J$7*$J$7 -> 2812.16 | Y20: 12 | Z20: =W20*X20*Y20 -> 33745.92 | AA20: 0 | AB20: =SUM(Z20:AA20) -> 33745.92 | AC20: =W20 -> 1 | AD20: =+K20*$J$7*$J$7*$J$7 -> 2924.6464 | AE20: 12 | AF20: =AC20*AD20*AE20 -> 35095.757 | AG20: 0 | AH20: =SUM(AF20:AG20) -> 35095.757 | AI20: =AC20 -> 1 | AJ20: =+K20*$J$7*$J$7*$J$7*$J$7 -> 3041.6323 | AK20: 10 | AL20: =AI20*AJ20*AK20 -> 30416.323 | AM20: 0 | AN20: =SUM(AL20:AM20) -> 30416.323 | AO20: =N20+T20+Z20+AF20+AL20 -> 155106 | AP20: =O20+U20+AA20+AG20+AM20 -> 0 | AQ20: =SUM(AO20:AP20) -> 155106 | AR20: 8888 | AS20: 0 | AT20: =(1074.78+1289.74)+970.84+916.12+622.87+(841.14+1121.52)+(567.64+851.46)+(1105.58+829.19)+(1038+778.5)+(995.63+746.72)+(1024.87+281.84)+24822 -> 39878.44 | AU20: 0 | AV20: =AR20+AT20 -> 48766.44 | AW20: =AS20+AU20 -> 0 | AX20: =AV20+AW20 -> 48766.44 | AY20: =AQ20-AX20 -> 106339.56 | AZ20: =AQ20-AR20-AS20-AT20-AU20 -> 106339.56 | BA20: =AY20-AZ20 -> 0 | BB20: 1 | BC20: 2433.44 | BD20: 11.7625 | BE20: =BC20*BD20*BB20 -> 28623.338 | BF20: =AA20 -> 0 | BG20: =SUM(BE20:BF20) -> 28623.338 | BH20: Especialistas responsables de acompañar los procesos de diseño, ejecución y evaluación de programas educativos desde la creación de escenarios que favorezcan la consolidación de prácticas de mediación de maestros/ambientes de aprendizaje incluyentes o con enfoque GESI. Son 2 personas, cargadas al 100%. | BI20: 1 | BJ20: =2347.92*1.04 -> 2441.8368 | BK20: 12 | BL20: =BI20*BJ20*BK20 -> 29302.042 | BM20: 0 | BN20: =SUM(BL20:BM20) -> 29302.042 | BO20: 1 | BP20: =BJ20*1.04 -> 2539.5103 | BQ20: 10 | BR20: =BQ20*BP20*BO20 -> 25395.103 | BS20: 0 | BT20: =SUM(BR20:BS20) -> 25395.103 | BU20: 1 | BV20: =BP20*1.04 -> 2641.0907 | BW20: 6 | BX20: =BW20*BV20 -> 15846.544 | BY20: 0 | BZ20: =BY20+BX20 -> 15846.544 | CA20: =BR20+BL20+BE20+BX20 -> 99167.026 | CB20: =+BY20+BS20+BM20+BF20 -> 0 | CC20: =CA20+CB20 -> 99167.026 | CE20: =AV20+CA20 -> 147933.47 | CF20: =AW20+CB20 -> 0 | CG20: =CE20+CF20 -> 147933.47 | CH20: =AO20-CE20 -> 7172.5329 | CI20: =AP20-CF20 -> 0 | CJ20: =AQ20-CG20 -> 7172.5329 | CK20: =SUM(CM20:ES20) -> -7173 | CL20: =CJ20+CK20 -> -0.46705728 | CP20: -7173
A21: SUBPROANT | B21: 89050 | C21: COL2 | D21: PAPERSNL | E21: 11 | F21: Teacher Training Professionals (4) | G21: PERSONNEL | H21: Field Personnel | I21: USAID | J21: 1 | K21: =(15000/12)*3 -> 3750 | L21: 9 | M21: /months | N21: =L21*K21*J21 -> 33750 | O21: 0 | P21: =SUM(N21:O21) -> 33750 | Q21: 1 | R21: =K21*$J$7 -> 3900 | S21: 12 | T21: =R21*S21*Q21 -> 46800 | U21: 0 | V21: =SUM(T21:U21) -> 46800 | W21: 1 | X21: =+K21*$J$7*$J$7 -> 4056 | Y21: 12 | Z21: =Y21*X21*W21 -> 48672 | AA21: 0 | AB21: =SUM(Z21:AA21) -> 48672 | AC21: 1 | AD21: =+K21*$J$7*$J$7*$J$7 -> 4218.24 | AE21: 12 | AF21: =AE21*AD21*AC21 -> 50618.88 | AG21: 0 | AH21: =SUM(AF21:AG21) -> 50618.88 | AI21: 1 | AJ21: =+K21*$J$7*$J$7*$J$7*$J$7 -> 4386.9696 | AK21: 9 | AL21: =AK21*AJ21*AI21 -> 39482.726 | AM21: 0 | AN21: =SUM(AL21:AM21) -> 39482.726 | AO21: =N21+T21+Z21+AF21+AL21 -> 219323.61 | AP21: =O21+U21+AA21+AG21+AM21 -> 0 | AQ21: =SUM(AO21:AP21) -> 219323.61 | AR21: =(276.67+592.87+592.87)+(1203.86*3)+(2016.17+976.69+976.69+212.51)+(943.07+943.07+1025.97)+(928.26+928.26+1009.85) -> 15034.53 | AS21: 0 | AT21: =(919.98+919.98+1000.85)+(1246.9+1246.9+542.65+67.43+433.66)+(336.78+336.78+1316.06)+((1126.7*2)+1320.87)+(1063.2*2)+(1084.3*3)+((976.18*3)+650.79)+((988.16*4)+922.28)+(962.31*5)+(903.49*5)+(866.6*4)+(892.05*4)+6247+3242 -> 51628.39 | AU21: 0 | AV21: =AR21+AT21 -> 66662.92 | AW21: =AS21+AU21 -> 0 | AX21: =AV21+AW21 -> 66662.92 | AY21: =AQ21-AX21 -> 152660.69 | AZ21: =AQ21-AR21-AS21-AT21-AU21 -> 152660.69 | BA21: =AY21-AZ21 -> 0 | BB21: 1 | BC21: 4233.87 | BD21: 12 | BE21: =BC21*BD21 -> 50806.44 | BF21: =AA21 -> 0 | BG21: =SUM(BE21:BF21) -> 50806.44 | BH21: Profesionales responsables de acompañar los procesos de planeación, diseño, ejecución y evaluación de programas educativos desde la creación de escenarios que favorezcan la consolidación de prácticas de mediación de maestros/ambientes de aprendizaje incluyentes o con enfoque GESI. Son 4 personas, cargadas al 100%. | BI21: 1 | BJ21: =4087.29*1.04 -> 4250.7816 | BK21: 12 | BL21: =BI21*BJ21*BK21 -> 51009.379 | BM21: 0 | BN21: =SUM(BL21:BM21) -> 51009.379 | BO21: 1 | BP21: =BJ21*1.04 -> 4420.8129 | BQ21: 10 | BR21: =BQ21*BP21*BO21 -> 44208.129 | BS21: 0 | BT21: =SUM(BR21:BS21) -> 44208.129 | BU21: 2 | BV21: =(BP21/2)*1.04 -> 2298.8227 | BW21: 6 | BX21: =BW21*BV21 -> 13792.936 | BY21: 0 | BZ21: =BY21+BX21 -> 13792.936 | CA21: =BR21+BL21+BE21+BX21 -> 159816.88 | CB21: =+BY21+BS21+BM21+BF21 -> 0 | CC21: =CA21+CB21 -> 159816.88 | CE21: =AV21+CA21 -> 226479.8 | CF21: =AW21+CB21 -> 0 | CG21: =CE21+CF21 -> 226479.8 | CH21: =AO21-CE21 -> -7156.1976 | CI21: =AP21-CF21 -> 0 | CJ21: =AQ21-CG21 -> -7156.1976 | CK21: =SUM(CM21:ES21) -> 7156 | CL21: =CJ21+CK21 -> -0.19757568 | CP21: 7156
A22: SUBPROANT | B22: 89050 | C22: COL2 | E22: 12 | F22: Administrative Coordinator Administrative and Organizational Cultural Leader | G22: PERSONNEL | H22: Field Personnel | I22: LEVERAGE | J22: 1 | K22: 2000 | L22: 4 | M22: /months | N22: 0 | O22: =+J22*K22*L22 -> 8000 | P22: =SUM(N22:O22) -> 8000 | Q22: 1 | R22: =K22*$J$7 -> 2080 | S22: 4 | T22: 0 | U22: =+Q22*R22*S22 -> 8320 | V22: =SUM(T22:U22) -> 8320 | W22: 1 | X22: =+K22*$J$7*$J$7 -> 2163.2 | Y22: 4 | Z22: 0 | AA22: =+W22*X22*Y22 -> 8652.8 | AB22: =SUM(Z22:AA22) -> 8652.8 | AC22: 1 | AD22: =+K22*$J$7*$J$7*$J$7 -> 2249.728 | AE22: 4 | AF22: 0 | AG22: =+AC22*AD22*AE22 -> 8998.912 | AH22: =SUM(AF22:AG22) -> 8998.912 | AI22: 1 | AJ22: =+K22*$J$7*$J$7*$J$7*$J$7 -> 2339.7171 | AK22: 4 | AL22: 0 | AM22: =+AI22*AJ22*AK22 -> 9358.8685 | AN22: =SUM(AL22:AM22) -> 9358.8685 | AO22: =N22+T22+Z22+AF22+AL22 -> 0 | AP22: =O22+U22+AA22+AG22+AM22 -> 43330.58 | AQ22: =SUM(AO22:AP22) -> 43330.58 | AR22: 0 | AS22: =2000+2000+2000+637.52 -> 6637.52 | AT22: 0 | AU22: =640.29+651.19+673.56+676.02+637.92+650.58+585.71+592.89+577.39+577.39+519.96+535.23 -> 7318.13 | AV22: =AR22+AT22 -> 0 | AW22: =AS22+AU22 -> 13955.65 | AX22: =AV22+AW22 -> 13955.65 | AY22: =AQ22-AX22 -> 29374.93 | AZ22: =AQ22-AR22-AS22-AT22-AU22 -> 29374.93 | BA22: =AY22-AZ22 -> 0 | BB22: 0.3 | BC22: 0 | BD22: 0 | BE22: =BB22*BC22*BD22 -> 0 | BF22: =AA22*0.92 -> 7960.576 | BG22: =SUM(BE22:BF22) -> 7960.576 | BH22: Tiempos de dedicación de la lider administrativa y de cultura organizacional de la fundación Proantioquia al proyecto, en especifico en la coordinación y manejo de temas administrativos propios de movimientos contables y de personal adscritos al programa desde lo que comprende la operación de Proantioquia en el programa Juntos Aprendemos. (Leverage). | BI22: 0.3 | BJ22: 0 | BK22: 12 | BL22: =BI22*BJ22*BK22 -> 0 | BM22: =8998.912 -> 8998.912 | BN22: =SUM(BL22:BM22) -> 8998.912 | BO22: 0.3 | BP22: =BJ22*1.04 -> 0 | BQ22: 8 | BR22: =BQ22*BP22*BO22 -> 0 | BS22: =BM22*1.04 -> 9358.8685 | BT22: =SUM(BR22:BS22) -> 9358.8685 | BU22: 0 | BV22: 0 | BW22: 0 | BX22: =BW22*BV22 -> 0 | BY22: =((BS22/12)*6)-1100+36 -> 3615.4342 | BZ22: =BY22+BX22 -> 3615.4342 | CA22: =BR22+BL22+BE22+BX22 -> 0 | CB22: =+BY22+BS22+BM22+BF22 -> 29933.791 | CC22: =CA22+CB22 -> 29933.791 | CE22: =AV22+CA22 -> 0 | CF22: =AW22+CB22 -> 43889.441 | CG22: =CE22+CF22 -> 43889.441 | CH22: =AO22-CE22 -> 0 | CI22: =AP22-CF22 -> -558.86024 | CJ22: =AQ22-CG22 -> -558.86024 | CK22: =SUM(CM22:ES22) -> 559 | CL22: =CJ22+CK22 -> 0.13976 | CQ22: 559
A23: SUBPROANT | B23: 89050 | C23: COL2 | E23: 13 | F23: Professional Accountant | G23: PERSONNEL | H23: Field Personnel | I23: LEVERAGE | J23: 1 | K23: 1030 | L23: 3 | M23: /months | N23: 0 | O23: =+J23*K23*L23 -> 3090 | P23: =SUM(N23:O23) -> 3090 | Q23: 1 | R23: =K23*$J$7 -> 1071.2 | S23: 3 | T23: 0 | U23: =+Q23*R23*S23 -> 3213.6 | V23: =SUM(T23:U23) -> 3213.6 | W23: 1 | X23: =+K23*$J$7*$J$7 -> 1114.048 | Y23: 3 | Z23: 0 | AA23: =+W23*X23*Y23 -> 3342.144 | AB23: =SUM(Z23:AA23) -> 3342.144 | AC23: 1 | AD23: =+K23*$J$7*$J$7*$J$7 -> 1158.6099 | AE23: 3 | AF23: 0 | AG23: =+AC23*AD23*AE23 -> 3475.8298 | AH23: =SUM(AF23:AG23) -> 3475.8298 | AI23: 1 | AJ23: =+K23*$J$7*$J$7*$J$7*$J$7 -> 1204.9543 | AK23: 3 | AL23: 0 | AM23: =+AI23*AJ23*AK23 -> 3614.863 | AN23: =SUM(AL23:AM23) -> 3614.863 | AO23: =N23+T23+Z23+AF23+AL23 -> 0 | AP23: =O23+U23+AA23+AG23+AM23 -> 16736.437 | AQ23: =SUM(AO23:AP23) -> 16736.437 | AR23: 0 | AS23: =772.5+772.5+772.5+318.76 -> 2636.26 | AT23: 0 | AU23: =319.02+324.45+335.6+336.82+317.84+324.15+291.82+295.4+287.68+287.68+259.07+266.67 -> 3646.2 | AV23: =AR23+AT23 -> 0 | AW23: =AS23+AU23 -> 6282.46 | AX23: =AV23+AW23 -> 6282.46 | AY23: =AQ23-AX23 -> 10453.977 | AZ23: =AQ23-AR23-AS23-AT23-AU23 -> 10453.977 | BA23: =AY23-AZ23 -> 0 | BB23: 0.3 | BC23: 0 | BD23: 0 | BE23: =BB23*BC23*BD23 -> 0 | BF23: =AA23*0.92 -> 3074.7725 | BG23: =SUM(BE23:BF23) -> 3074.7725 | BH23: Tiempos de dedicación de la profesional contable de la fundación Proantioquia al proyecto, en especifico en la coordinación y manejo de temas contables desde lo que comprende la operación de Proantioquia en el programa Juntos Aprendemos. (Leverage). | BI23: 0.3 | BJ23: 0 | BK23: 12 | BL23: =BI23*BJ23*BK23 -> 0 | BM23: =3475.82976 -> 3475.8298 | BN23: =SUM(BL23:BM23) -> 3475.8298 | BO23: 0.3 | BP23: =BJ23*1.04 -> 0 | BQ23: 8 | BR23: =BQ23*BP23*BO23 -> 0 | BS23: =3766.8629504 -> 3766.863 | BT23: =SUM(BR23:BS23) -> 3766.863 | BU23: 0 | BV23: 0 | BW23: 0 | BX23: =BW23*BV23 -> 0 | BY23: =(BS23/12)*6 -> 1883.4315 | BZ23: =BY23+BX23 -> 1883.4315 | CA23: =BR23+BL23+BE23+BX23 -> 0 | CB23: =+BY23+BS23+BM23+BF23 -> 12200.897 | CC23: =CA23+CB23 -> 12200.897 | CE23: =AV23+CA23 -> 0 | CF23: =AW23+CB23 -> 18483.357 | CG23: =CE23+CF23 -> 18483.357 | CH23: =AO23-CE23 -> 0 | CI23: =AP23-CF23 -> -1746.92 | CJ23: =AQ23-CG23 -> -1746.92 | CK23: =SUM(CM23:ES23) -> 1747 | CL23: =CJ23+CK23 -> 0.0800448 | CQ23: 1747
A24: SUBPROANT | B24: 89050 | C24: COL2 | E24: 14 | F24: Visual Documentation Communications Professional | G24: PERSONNEL | H24: Field Personnel | I24: LEVERAGE | J24: 1 | K24: 1144 | L24: 2 | M24: /months | N24: 0 | O24: =+J24*K24*L24 -> 2288 | P24: =SUM(N24:O24) -> 2288 | Q24: 1 | R24: =K24*$J$7 -> 1189.76 | S24: 2 | T24: 0 | U24: =+Q24*R24*S24 -> 2379.52 | V24: =SUM(T24:U24) -> 2379.52 | W24: 1 | X24: =+K24*$J$7*$J$7 -> 1237.3504 | Y24: 2 | Z24: 0 | AA24: =+W24*X24*Y24 -> 2474.7008 | AB24: =SUM(Z24:AA24) -> 2474.7008 | AC24: 1 | AD24: =+K24*$J$7*$J$7*$J$7 -> 1286.8444 | AE24: 2 | AF24: 0 | AG24: =+AC24*AD24*AE24 -> 2573.6888 | AH24: =SUM(AF24:AG24) -> 2573.6888 | AI24: 1 | AJ24: =+K24*$J$7*$J$7*$J$7*$J$7 -> 1338.3182 | AK24: 2 | AL24: 0 | AM24: =+AI24*AJ24*AK24 -> 2676.6364 | AN24: =SUM(AL24:AM24) -> 2676.6364 | AO24: =N24+T24+Z24+AF24+AL24 -> 0 | AP24: =O24+U24+AA24+AG24+AM24 -> 12392.546 | AQ24: =SUM(AO24:AP24) -> 12392.546 | AR24: 0 | AS24: =572+572+572 -> 1716 | AT24: 0 | AU24: 0 | AV24: =AR24+AT24 -> 0 | AW24: =AS24+AU24 -> 1716 | AX24: =AV24+AW24 -> 1716 | AY24: =AQ24-AX24 -> 10676.546 | AZ24: =AQ24-AR24-AS24-AT24-AU24 -> 10676.546 | BA24: =AY24-AZ24 -> 0 | BB24: 0.3 | BC24: 0 | BD24: 0 | BE24: =BB24*BC24*BD24 -> 0 | BF24: =AA24*0.92 -> 2276.7247 | BG24: =SUM(BE24:BF24) -> 2276.7247 | BH24: Tiempos de dedicación del area de comunicaciones de la fundación Proantioquia en el programa Juntos Aprendemos. (Leverage). | BI24: 0.3 | BJ24: 0 | BK24: 12 | BL24: =BI24*BJ24*BK24 -> 0 | BM24: =2573.688832 -> 2573.6888 | BN24: =SUM(BL24:BM24) -> 2573.6888 | BO24: 0.3 | BP24: =BJ24*1.04 -> 0 | BQ24: 0 | BR24: =BQ24*BP24*BO24 -> 0 | BS24: 0 | BT24: =SUM(BR24:BS24) -> 0 | BU24: 0 | BV24: 0 | BW24: 0 | BX24: =BW24*BV24 -> 0 | BY24: 0 | BZ24: =BY24+BX24 -> 0 | CA24: =BR24+BL24+BE24+BX24 -> 0 | CB24: =+BY24+BS24+BM24+BF24 -> 4850.4136 | CC24: =CA24+CB24 -> 4850.4136 | CE24: =AV24+CA24 -> 0 | CF24: =AW24+CB24 -> 6566.4136 | CG24: =CE24+CF24 -> 6566.4136 | CH24: =AO24-CE24 -> 0 | CI24: =AP24-CF24 -> 5826.1324 | CJ24: =AQ24-CG24 -> 5826.1324 | CK24: =SUM(CM24:ES24) -> -5826 | CL24: =CJ24+CK24 -> 0.13244928 | CQ24: -5826
A25: SUBPROANT | B25: 89050 | C25: COL2 | E25: 15 | F25: Content Development Professional | G25: PERSONNEL | H25: Field Personnel | I25: USAID | J25: 1 | K25: =15000/12 -> 1250 | L25: 6 | M25: /months | N25: =L25*K25*J25 -> 7500 | O25: 0 | P25: =SUM(N25:O25) -> 7500 | Q25: 1 | R25: =K25*$J$7 -> 1300 | S25: 0 | T25: =R25*S25*Q25 -> 0 | U25: 0 | V25: =SUM(T25:U25) -> 0 | W25: 1 | X25: =+K25*$J$7*$J$7 -> 1352 | Y25: 0 | Z25: =Y25*X25*W25 -> 0 | AA25: 0 | AB25: =SUM(Z25:AA25) -> 0 | AC25: 1 | AD25: =+K25*$J$7*$J$7*$J$7 -> 1406.08 | AE25: 0 | AF25: =AE25*AD25*AC25 -> 0 | AG25: 0 | AH25: =SUM(AF25:AG25) -> 0 | AI25: 1 | AJ25: =+K25*$J$7*$J$7*$J$7*$J$7 -> 1462.3232 | AK25: 0 | AL25: =AK25*AJ25*AI25 -> 0 | AM25: 0 | AN25: =SUM(AL25:AM25) -> 0 | AO25: =N25+T25+Z25+AF25+AL25 -> 7500 | AP25: =O25+U25+AA25+AG25+AM25 -> 0 | AQ25: =SUM(AO25:AP25) -> 7500 | AR25: 0 | AS25: 0 | AT25: 0 | AU25: 0 | AV25: =AR25+AT25 -> 0 | AW25: =AS25+AU25 -> 0 | AX25: =AV25+AW25 -> 0 | AY25: =AQ25-AX25 -> 7500 | AZ25: =AQ25-AR25-AS25-AT25-AU25 -> 7500 | BA25: =AY25-AZ25 -> 0 | BB25: 0 | BC25: =AI25*$P$7*$P$7 -> 0 | BD25: 0 | BE25: =BB25*BC25*BD25 -> 0 | BF25: =AA25 -> 0 | BG25: =SUM(BE25:BF25) -> 0 | BH25: Tiempos de dedicación del area de educación de la fundación Proantioquia al proyecto, en especifico en temas vinculados a la generación de contenidos y gestión del conocimiento. (Leverage).Esta linea no se requiere. | BI25: 0 | BJ25: =AO25*$P$7*$P$7 -> 0 | BK25: 0 | BL25: =BI25*BJ25*BK25 -> 0 | BM25: 0 | BN25: =SUM(BL25:BM25) -> 0 | BO25: 0 | BP25: =BJ25*1.04 -> 0 | BQ25: 0 | BR25: =BQ25*BP25*BO25 -> 0 | BS25: 0 | BT25: =SUM(BR25:BS25) -> 0 | BU25: 0 | BV25: 0 | BW25: 0 | BX25: =BW25*BV25 -> 0 | BY25: 0 | BZ25: =BY25+BX25 -> 0 | CA25: =BR25+BL25+BE25+BX25 -> 0 | CB25: =+BY25+BS25+BM25+BF25 -> 0 | CC25: =CA25+CB25 -> 0 | CE25: =AV25+CA25 -> 0 | CF25: =AW25+CB25 -> 0 | CG25: =CE25+CF25 -> 0 | CH25: =AO25-CE25 -> 7500 | CI25: =AP25-CF25 -> 0 | CJ25: =AQ25-CG25 -> 7500 | CK25: =SUM(CM25:ES25) -> -7500 | CL25: =CJ25+CK25 -> 0 | CR25: -7500
A26: SUBPROANT | B26: 89050 | C26: COL2 | D26: PAPERSNL | E26: 16 | F26: Finance & Admin Coordinator Project Analyst | G26: PERSONNEL | H26: Field Personnel | I26: USAID | J26: 1 | K26: =22500/12 -> 1875 | L26: 9 | M26: /months | N26: =L26*K26*J26 -> 16875 | O26: 0 | P26: =SUM(N26:O26) -> 16875 | Q26: =J26 -> 1 | R26: =K26*$J$7 -> 1950 | S26: 12 | T26: =Q26*R26*S26 -> 23400 | U26: 0 | V26: =SUM(T26:U26) -> 23400 | W26: =Q26 -> 1 | X26: =+K26*$J$7*$J$7 -> 2028 | Y26: 12 | Z26: =W26*X26*Y26 -> 24336 | AA26: 0 | AB26: =SUM(Z26:AA26) -> 24336 | AC26: =W26 -> 1 | AD26: =+K26*$J$7*$J$7*$J$7 -> 2109.12 | AE26: 12 | AF26: =AC26*AD26*AE26 -> 25309.44 | AG26: 0 | AH26: =SUM(AF26:AG26) -> 25309.44 | AI26: =AC26 -> 1 | AJ26: =+K26*$J$7*$J$7*$J$7*$J$7 -> 2193.4848 | AK26: 10 | AL26: =AI26*AJ26*AK26 -> 21934.848 | AM26: 0 | AN26: =SUM(AL26:AM26) -> 21934.848 | AO26: =N26+T26+Z26+AF26+AL26 -> 111855.29 | AP26: =O26+U26+AA26+AG26+AM26 -> 0 | AQ26: =SUM(AO26:AP26) -> 111855.29 | AR26: =222.73+969.16+982.85+949.02+934.11+3510 -> 7567.87 | AS26: 0 | AT26: =925.79+(1003.88+62.34)+1122.6+1126.7+1063.2+1084.3+976.18+988.16+962.31+903.49+866.6+892.05+8843+2243+10776 -> 33839.6 | AU26: 0 | AV26: =AR26+AT26 -> 41407.47 | AW26: =AS26+AU26 -> 0 | AX26: =AV26+AW26 -> 41407.47 | AY26: =AQ26-AX26 -> 70447.818 | AZ26: =AQ26-AR26-AS26-AT26-AU26 -> 70447.818 | BA26: =AY26-AZ26 -> 0 | BB26: 1 | BC26: 1058.47 | BD26: 12 | BE26: =BB26*BC26*BD26 -> 12701.64 | BF26: =AA26 -> 0 | BG26: =SUM(BE26:BF26) -> 12701.64 | BH26: Responsable de realizar los reportes financieros al cooperante, dar tramite administrativo a las solicitudes de fondos, accruals y demas requerimientos que desde POA sean solicitados para dar cumplimiento a las responsabilidades contractuales adquiridas con el subacuerdo y da cuenta de la operación de la fundación Proantioquia sobre la ejecución de las subactividades y demas información que pueda ser solicitada, se espera que esta persona esté activa hasta el final de proyecto. | BI26: 1 | BJ26: 1062.69 | BK26: 12 | BL26: =BI26*BJ26*BK26 -> 12752.28 | BM26: 0 | BN26: =SUM(BL26:BM26) -> 12752.28 | BO26: 1 | BP26: =BJ26*1.04 -> 1105.1976 | BQ26: 12 | BR26: =BQ26*BP26*BO26 -> 13262.371 | BS26: 0 | BT26: =SUM(BR26:BS26) -> 13262.371 | BU26: 1 | BV26: =BP26*1.04 -> 1149.4055 | BW26: 6 | BX26: =BW26*BV26 -> 6896.433 | BY26: 0 | BZ26: =BY26+BX26 -> 6896.433 | CA26: =BR26+BL26+BE26+BX26 -> 45612.724 | CB26: =+BY26+BS26+BM26+BF26 -> 0 | CC26: =CA26+CB26 -> 45612.724 | CE26: =AV26+CA26 -> 87020.194 | CF26: =AW26+CB26 -> 0 | CG26: =CE26+CF26 -> 87020.194 | CH26: =AO26-CE26 -> 24835.094 | CI26: =AP26-CF26 -> 0 | CJ26: =AQ26-CG26 -> 24835.094 | CK26: =SUM(CM26:ES26) -> -24835 | CL26: =CJ26+CK26 -> 0.093776 | CS26: -24835
A27: SUBPROANT | B27: 89050 | C27: COL2 | D27: PAPERSNL | E27: 17 | F27: Operations and Planning Professional Human Resources Professional | G27: PERSONNEL | H27: Field Personnel | I27: LEVERAGE | J27: 1 | K27: 1000 | L27: 5 | M27: /months | N27: 0 | O27: =+K27*L27 -> 5000 | P27: =SUM(N27:O27) -> 5000 | Q27: 1 | R27: =K27*$J$7 -> 1040 | S27: 6 | T27: 0 | U27: =+R27*S27 -> 6240 | V27: =SUM(T27:U27) -> 6240 | W27: 1 | X27: =+K27*$J$7*$J$7 -> 1081.6 | Y27: 6 | Z27: 0 | AA27: =+X27*Y27 -> 6489.6 | AB27: =SUM(Z27:AA27) -> 6489.6 | AC27: 1 | AD27: =+K27*$J$7*$J$7*$J$7 -> 1124.864 | AE27: 6 | AF27: 0 | AG27: =+AD27*AE27 -> 6749.184 | AH27: =SUM(AF27:AG27) -> 6749.184 | AI27: 1 | AJ27: =+K27*$J$7*$J$7*$J$7*$J$7 -> 1169.8586 | AK27: 6 | AL27: 0 | AM27: =+AJ27*AK27 -> 7019.1514 | AN27: =SUM(AL27:AM27) -> 7019.1514 | AO27: =N27+T27+Z27+AF27+AL27 -> 0 | AP27: =O27+U27+AA27+AG27+AM27 -> 31497.935 | AQ27: =SUM(AO27:AP27) -> 31497.935 | AR27: 0 | AS27: =1250+1250+1250+314.38 -> 4064.38 | AT27: 0 | AU27: =296.13+301.16+311.51+312.65+295.03+300.88+270.88+274.2+267.03+267.03+240.47+247.54 -> 3384.51 | AV27: =AR27+AT27 -> 0 | AW27: =AS27+AU27 -> 7448.89 | AX27: =AV27+AW27 -> 7448.89 | AY27: =AQ27-AX27 -> 24049.045 | AZ27: =AQ27-AR27-AS27-AT27-AU27 -> 24049.045 | BA27: =AY27-AZ27 -> 0 | BB27: 0.3 | BC27: =AI27*$P$7*$P$7 -> 0 | BD27: 0 | BE27: =BB27*BC27*BD27 -> 0 | BF27: 5970.43 | BG27: =SUM(BE27:BF27) -> 5970.43 | BH27: Tiempos de dedicación del area de gestion humana de la fundación Proantioquia al proyecto, en especifico en la coordinación y manejo de manejo de personal adscritos al programa desde lo que comprende la operación de Proantioquia en el programa Juntos Aprendemos. (Leverage). | BI27: 0.3 | BJ27: =AO27*$P$7*$P$7 -> 0 | BK27: 12 | BL27: =BI27*BJ27*BK27 -> 0 | BM27: =6749.184 -> 6749.184 | BN27: =SUM(BL27:BM27) -> 6749.184 | BO27: 0.3 | BP27: =BJ27*1.04 -> 0 | BQ27: 12 | BR27: =BQ27*BP27*BO27 -> 0 | BS27: =BM27*1.04 -> 7019.1514 | BT27: =SUM(BR27:BS27) -> 7019.1514 | BU27: 0 | BV27: 5443.1 | BW27: 0 | BX27: =BW27*BV27 -> 0 | BY27: =BV27 -> 5443.1 | BZ27: =BY27+BX27 -> 5443.1 | CA27: =BR27+BL27+BE27+BX27 -> 0 | CB27: =+BY27+BS27+BM27+BF27 -> 25181.865 | CC27: =CA27+CB27 -> 25181.865 | CE27: =AV27+CA27 -> 0 | CF27: =AW27+CB27 -> 32630.755 | CG27: =CE27+CF27 -> 32630.755 | CH27: =AO27-CE27 -> 0 | CI27: =AP27-CF27 -> -1132.82 | CJ27: =AQ27-CG27 -> -1132.82 | CK27: =SUM(CM27:ES27) -> 1133 | CL27: =CJ27+CK27 -> 0.18 | CQ27: 1133
A28: SUBPROANT | B28: 89050 | C28: COL2 | D28: PAPERSNL | E28: 18 | F28: Juntos Aprendemos Project Leader | G28: PERSONNEL | H28: Field Personnel | I28: USAID | M28: /months | AQ28: 0 | AR28: 0 | AS28: 0 | AT28: 0 | AU28: 0 | AV28: =AR28+AT28 -> 0 | AW28: =AS28+AU28 -> 0 | AX28: =AV28+AW28 -> 0 | AY28: =AQ28-AX28 -> 0 | AZ28: =AQ28-AR28-AS28-AT28-AU28 -> 0 | BA28: =AY28-AZ28 -> 0 | BB28: 1 | BC28: 2209.36 | BD28: 12 | BE28: =BC28*BD28 -> 26512.32 | BF28: =AA28 -> 0 | BG28: =SUM(BE28:BF28) -> 26512.32 | BH28: Responsable de coordinar la implementación de procesos y actividades de formación de maestros en el marco del programa Juntos Aprendemos, se espera que esta persona esté activa hasta el final de proyecto. | BI28: 1 | BJ28: =2132.77*1.04 -> 2218.0808 | BK28: 12 | BL28: =BI28*BJ28*BK28 -> 26616.97 | BM28: 0 | BN28: =SUM(BL28:BM28) -> 26616.97 | BO28: 1 | BP28: =BJ28*1.04 -> 2306.804 | BQ28: 12 | BR28: =BQ28*BP28*BO28 -> 27681.648 | BS28: 0 | BT28: =SUM(BR28:BS28) -> 27681.648 | BU28: 1 | BV28: =BP28*1.04 -> 2399.0762 | BW28: 6 | BX28: =BW28*BV28 -> 14394.457 | BY28: 0 | BZ28: =BY28+BX28 -> 14394.457 | CA28: =BR28+BL28+BE28+BX28 -> 95205.395 | CB28: =+BY28+BS28+BM28+BF28 -> 0 | CC28: =CA28+CB28 -> 95205.395 | CE28: =AV28+CA28 -> 95205.395 | CF28: =AW28+CB28 -> 0 | CG28: =CE28+CF28 -> 95205.395 | CH28: =AO28-CE28 -> -95205.395 | CI28: =AP28-CF28 -> 0 | CJ28: =AQ28-CG28 -> -95205.395 | CK28: =SUM(CM28:ES28) -> 95205 | CL28: =CJ28+CK28 -> -0.39514368 | CM28: 95205
A29: SUBPROANT | B29: 89050 | C29: COL2 | D29: PAPERSNL | E29: 19 | F29: Logistics professional | G29: PERSONNEL | H29: Field Personnel | I29: USAID | M29: /months | AQ29: 0 | AR29: 0 | AS29: 0 | AT29: 0 | AU29: 0 | AV29: =AR29+AT29 -> 0 | AW29: =AS29+AU29 -> 0 | AX29: =AV29+AW29 -> 0 | AY29: =AQ29-AX29 -> 0 | AZ29: =AQ29-AR29-AS29-AT29-AU29 -> 0 | BA29: =AY29-AZ29 -> 0 | BB29: 1 | BC29: 880.49 | BD29: 12 | BE29: =BC29*BD29 -> 10565.88 | BF29: =AA29 -> 0 | BG29: =SUM(BE29:BF29) -> 10565.88 | BH29: Responsable de asistir, acompañar y soportar los procesos logísticos del proyecto Juntos Aprendemos, se espera que esta persona esté activa hasta el final de proyecto. | BI29: 1 | BJ29: =817.46*1.04 -> 850.1584 | BK29: 12 | BL29: =BI29*BJ29*BK29 -> 10201.901 | BM29: 0 | BN29: =SUM(BL29:BM29) -> 10201.901 | BO29: 1 | BP29: =BJ29*1.04 -> 884.16474 | BQ29: 12 | BR29: =BQ29*BP29*BO29 -> 10609.977 | BS29: 0 | BT29: =SUM(BR29:BS29) -> 10609.977 | BU29: 1 | BV29: =BP29*1.04 -> 919.53133 | BW29: 6 | BX29: =BW29*BV29 -> 5517.188 | BY29: 0 | BZ29: =BY29+BX29 -> 5517.188 | CA29: =BR29+BL29+BE29+BX29 -> 36894.946 | CB29: =+BY29+BS29+BM29+BF29 -> 0 | CC29: =CA29+CB29 -> 36894.946 | CE29: =AV29+CA29 -> 36894.946 | CF29: =AW29+CB29 -> 0 | CG29: =CE29+CF29 -> 36894.946 | CH29: =AO29-CE29 -> -36894.946 | CI29: =AP29-CF29 -> 0 | CJ29: =AQ29-CG29 -> -36894.946 | CK29: =SUM(CM29:ES29) -> 36895 | CL29: =CJ29+CK29 -> 0.05441536 | CN29: 36895
A30: SUBPROANT | B30: 89050 | C30: COL2 | D30: PAPERSNL | E30: 20 | F30: Monitoring, evaluation and Learning (MEL) professional | G30: PERSONNEL | H30: Field Personnel | I30: USAID | M30: /months | AQ30: 0 | AR30: 0 | AS30: 0 | AT30: 0 | AU30: 0 | AV30: =AR30+AT30 -> 0 | AW30: =AS30+AU30 -> 0 | AX30: =AV30+AW30 -> 0 | AY30: =AQ30-AX30 -> 0 | AZ30: =AQ30-AR30-AS30-AT30-AU30 -> 0 | BA30: =AY30-AZ30 -> 0 | BB30: 1 | BC30: 979.78 | BD30: 11.7164 | BE30: =BC30*BD30 -> 11479.494 | BF30: =AA30 -> 0 | BG30: =SUM(BE30:BF30) -> 11479.494 | BH30: Responsable de participar y dar el manejo objetivo de los datos según requerimientos de la mesa de monitoreo y evaluación del programa Juntos Aprendemos, se espera que esta persona esté activa hasta el final de proyecto. | BI30: 1 | BJ30: 982.97 | BK30: 12 | BL30: =BI30*BJ30*BK30 -> 11795.64 | BM30: 0 | BN30: =SUM(BL30:BM30) -> 11795.64 | BO30: 1 | BP30: =BJ30*1.04 -> 1022.2888 | BQ30: 12 | BR30: =BQ30*BP30*BO30 -> 12267.466 | BS30: 0 | BT30: =SUM(BR30:BS30) -> 12267.466 | BU30: 0 | BV30: 0 | BW30: 0 | BX30: 0 | BY30: 0 | BZ30: =BY30+BX30 -> 0 | CA30: =BR30+BL30+BE30+BX30 -> 35542.6 | CB30: =+BY30+BS30+BM30+BF30 -> 0 | CC30: =CA30+CB30 -> 35542.6 | CE30: =AV30+CA30 -> 35542.6 | CF30: =AW30+CB30 -> 0 | CG30: =CE30+CF30 -> 35542.6 | CH30: =AO30-CE30 -> -35542.6 | CI30: =AP30-CF30 -> 0 | CJ30: =AQ30-CG30 -> -35542.6 | CK30: =SUM(CM30:ES30) -> 35543 | CL30: =CJ30+CK30 -> 0.400008 | CM30: 25207 | CS30: 10336
A31: SUBPROANT | B31: 89050 | C31: COL2 | D31: PAPERSNL | E31: 21 | F31: Metrics Analyst | G31: PERSONNEL | H31: Field Personnel | I31: USAID | M31: /months | AQ31: 0 | AR31: 0 | AS31: 0 | AT31: 0 | AU31: 0 | AV31: =AR31+AT31 -> 0 | AW31: =AS31+AU31 -> 0 | AX31: =AV31+AW31 -> 0 | AY31: =AQ31-AX31 -> 0 | AZ31: =AQ31-AR31-AS31-AT31-AU31 -> 0 | BA31: =AY31-AZ31 -> 0 | BB31: 1 | BC31: 826.91 | BD31: 1 | BE31: =BB31*BC31*BD31 -> 826.91 | BF31: =AA31 -> 0 | BG31: =SUM(BE31:BF31) -> 826.91 | BH31: Responsable de centralizar y acompañar los procesos de manejo y reporte de datos del programa Juntos Aprendemos desde lo comprendido en la operación de Proantioquia ademas de brindar apoyo al profesional de monitoreo y evaluación según las solicitudes que tenga desde su participación dentro del proyecto. | BI31: 1 | BJ31: 850.16 | BK31: 12 | BL31: =BI31*BJ31*BK31 -> 10201.92 | BM31: 0 | BN31: =SUM(BL31:BM31) -> 10201.92 | BO31: 1 | BP31: =BJ31*1.04 -> 884.1664 | BQ31: 0 | BR31: =BQ31*BP31*BO31 -> 0 | BS31: 0 | BT31: =SUM(BR31:BS31) -> 0 | BU31: 0 | BV31: 0 | BW31: 0 | BX31: 0 | BY31: 0 | BZ31: =BY31+BX31 -> 0 | CA31: =BR31+BL31+BE31+BX31 -> 11028.83 | CB31: =+BY31+BS31+BM31+BF31 -> 0 | CC31: =CA31+CB31 -> 11028.83 | CE31: =AV31+CA31 -> 11028.83 | CF31: =AW31+CB31 -> 0 | CG31: =CE31+CF31 -> 11028.83 | CH31: =AO31-CE31 -> -11028.83 | CI31: =AP31-CF31 -> 0 | CJ31: =AQ31-CG31 -> -11028.83 | CK31: =SUM(CM31:ES31) -> 11029 | CL31: =CJ31+CK31 -> 0.17 | CR31: 7500 | CS31: 3529
A32: SUBPROANT | B32: 89050 | C32: COL2 | D32: PAPERSNL | E32: 22 | F32: Administrative Assistant | G32: PERSONNEL | H32: Field Personnel | I32: USAID | M32: /months | AQ32: 0 | AR32: 0 | AS32: 0 | AT32: 0 | AU32: 0 | AV32: =AR32+AT32 -> 0 | AW32: =AS32+AU32 -> 0 | AX32: =AV32+AW32 -> 0 | AY32: =AQ32-AX32 -> 0 | AZ32: =AQ32-AR32-AS32-AT32-AU32 -> 0 | BA32: =AY32-AZ32 -> 0 | BB32: 1 | BC32: 555.01 | BD32: 12 | BE32: =BB32*BC32*BD32 -> 6660.12 | BF32: =AA32 -> 0 | BG32: =SUM(BE32:BF32) -> 6660.12 | BH32: Responsable de registrar los movimientos contables del proyecto, preparar los pagos de seguridad social, nómina y obligaciones de los colaboradores del proyecto, se espera que esta persona esté activa hasta el final de proyecto. | BI32: 1 | BJ32: 548.16 | BK32: 12 | BL32: =BI32*BJ32*BK32 -> 6577.92 | BM32: 0 | BN32: =SUM(BL32:BM32) -> 6577.92 | BO32: 1 | BP32: =BJ32*1.04 -> 570.0864 | BQ32: 10 | BR32: =BQ32*BP32*BO32 -> 5700.864 | BS32: 0 | BT32: =SUM(BR32:BS32) -> 5700.864 | BU32: 0 | BV32: 0 | BW32: 0 | BX32: 0 | BY32: 0 | BZ32: =BY32+BX32 -> 0 | CA32: =BR32+BL32+BE32+BX32 -> 18938.904 | CB32: =+BY32+BS32+BM32+BF32 -> 0 | CC32: =CA32+CB32 -> 18938.904 | CE32: =AV32+CA32 -> 18938.904 | CF32: =AW32+CB32 -> 0 | CG32: =CE32+CF32 -> 18938.904 | CH32: =AO32-CE32 -> -18938.904 | CI32: =AP32-CF32 -> 0 | CJ32: =AQ32-CG32 -> -18938.904 | CK32: =SUM(CM32:ES32) -> 18939 | CL32: =CJ32+CK32 -> 0.096 | CN32: 5 | CP32: 17 | CS32: 10970 | DU32: 7947
A33: SUBPROANT | B33: 89050 | C33: COL2 | D33: PAPERSNL | E33: 23 | F33: Operations Assistant | G33: PERSONNEL | H33: Field Personnel | I33: USAID | M33: /months | AQ33: 0 | AR33: 0 | AS33: 0 | AT33: 0 | AU33: 0 | AV33: =AR33+AT33 -> 0 | AW33: =AS33+AU33 -> 0 | AX33: =AV33+AW33 -> 0 | AY33: =AQ33-AX33 -> 0 | AZ33: =AQ33-AR33-AS33-AT33-AU33 -> 0 | BA33: =AY33-AZ33 -> 0 | BB33: 1 | BC33: 556.8 | BD33: 10.733 | BE33: =BB33*BC33*BD33 -> 5976.1344 | BF33: =AA33 -> 0 | BG33: =SUM(BE33:BF33) -> 5976.1344 | BH33: Responsable de apoyar las tareas operativas, documentales, logísticas y la sistematización de datos del programa Juntos Aprendemos desde la fundación Proantioquia, se espera que esta persona esté activa hasta el final de proyecto. | BI33: 1 | BJ33: 476.66 | BK33: 12 | BL33: =BI33*BJ33*BK33 -> 5719.92 | BM33: 0 | BN33: =SUM(BL33:BM33) -> 5719.92 | BO33: 1 | BP33: =BJ33*1.04 -> 495.7264 | BQ33: 10 | BR33: =BQ33*BP33*BO33 -> 4957.264 | BS33: 0 | BT33: =SUM(BR33:BS33) -> 4957.264 | BU33: 0 | BV33: 0 | BW33: 0 | BX33: 0 | BY33: 0 | BZ33: =BY33+BX33 -> 0 | CA33: =BR33+BL33+BE33+BX33 -> 16653.318 | CB33: =+BY33+BS33+BM33+BF33 -> 0 | CC33: =CA33+CB33 -> 16653.318 | CE33: =AV33+CA33 -> 16653.318 | CF33: =AW33+CB33 -> 0 | CG33: =CE33+CF33 -> 16653.318 | CH33: =AO33-CE33 -> -16653.318 | CI33: =AP33-CF33 -> 0 | CJ33: =AQ33-CG33 -> -16653.318 | CK33: =SUM(CM33:ES33) -> 16653 | CL33: =CJ33+CK33 -> -0.3184 | DU33: 13922 | DV33: 2731
E34: 24 | F34: Subtotal Field Personnel | N34: =SUM(N20:N27) -> 81525 | O34: =SUM(O20:O27) -> 18378 | P34: =SUM(P20:P27) -> 99903 | T34: =SUM(T20:T27) -> 102648 | U34: =SUM(U20:U27) -> 20153.12 | V34: =SUM(V20:V27) -> 122801.12 | Z34: =SUM(Z20:Z27) -> 106753.92 | AA34: =SUM(AA20:AA27) -> 20959.245 | AB34: =SUM(AB20:AB27) -> 127713.16 | AF34: =SUM(AF20:AF27) -> 111024.08 | AG34: =SUM(AG20:AG27) -> 21797.615 | AH34: =SUM(AH20:AH27) -> 132821.69 | AL34: =SUM(AL20:AL27) -> 91833.897 | AM34: =SUM(AM20:AM27) -> 22669.519 | AN34: =SUM(AN20:AN27) -> 114503.42 | AO34: =SUM(AO20:AO27) -> 493784.89 | AP34: =SUM(AP20:AP27) -> 103957.5 | AQ34: =SUM(AQ20:AQ27) -> 597742.39 | AR34: =SUM(AR20:AR33) -> 31490.4 | AS34: =SUM(AS20:AS33) -> 15054.16 | AT34: =SUM(AT20:AT33) -> 125346.43 | AU34: =SUM(AU20:AU33) -> 14348.84 | AV34: =SUM(AV20:AV33) -> 156836.83 | AW34: =SUM(AW20:AW33) -> 29403 | AX34: =SUM(AX20:AX33) -> 186239.83 | AY34: =SUM(AY20:AY33) -> 411502.56 | AZ34: =AQ34-AR34-AS34-AT34-AU34 -> 411502.56 | BE34: =SUM(BE20:BE33) -> 154152.28 | BF34: =SUM(BF20:BF33) -> 19282.503 | BG34: =SUM(BE34:BF34) -> 173434.78 | BJ34: =SUM(BJ20:BJ33) -> 13681.498 | BL34: =SUM(BL20:BL33) -> 164177.97 | BM34: =SUM(BM20:BM33) -> 21797.615 | BN34: =SUM(BL34:BM34) -> 185975.59 | BP34: =SUM(BP20:BP33) -> 14228.758 | BR34: =SUM(BR20:BR33) -> 144082.82 | BS34: =SUM(BS20:BS33) -> 20144.883 | BT34: =SUM(BR34:BS34) -> 164227.7 | BV34: =SUM(BV20:BV33) -> 14851.026 | BX34: =SUM(BX20:BX33) -> 56447.558 | BY34: =SUM(BY20:BY33) -> 10941.966 | BZ34: =SUM(BZ20:BZ33) -> 67389.524 | CA34: =SUM(CA20:CA33) -> 518860.63 | CB34: =SUM(CB20:CB33) -> 72166.966 | CC34: =SUM(CC20:CC33) -> 591027.59 | CE34: =SUM(CE20:CE33) -> 675697.46 | CF34: =SUM(CF20:CF33) -> 101569.97 | CG34: =SUM(CG20:CG33) -> 777267.42 | CK34: =SUM(CM34:ES34) -> 0 | CL34: =CJ34+CK34 -> 0
E35: 25 | F35: Personnel Total | N35: =N34+N18 -> 146525 | O35: =O34+O18 -> 29706.9 | P35: =P34+P18 -> 176231.9 | T35: =T34+T18 -> 180648 | U35: =U34+U18 -> 33006.272 | V35: =V34+V18 -> 213654.27 | Z35: =Z34+Z18 -> 187873.92 | AA35: =AA34+AA18 -> 34326.523 | AB35: =AB34+AB18 -> 222200.44 | AF35: =AF34+AF18 -> 195388.88 | AG35: =AG34+AG18 -> 35699.584 | AH35: =AH34+AH18 -> 231088.46 | AL35: =AL34+AL18 -> 175186.32 | AM35: =AM34+AM18 -> 35922.73 | AN35: =AN34+AN18 -> 211109.05 | AO35: =AO34+AO18 -> 885622.12 | AP35: =AP34+AP18 -> 168662.01 | AQ35: =AQ34+AQ18 -> 1054284.1 | AR35: =AR34+AR18 -> 31490.4 | AS35: =AS34+AS18 -> 15054.16 | ... AY35: =AY34+AY18 -> 411502.56 | AZ35: =AQ35-AR35-AS35-AT35-AU35 -> 814255.04 | BE35: =BE34+BE18 -> 199722.59 | BF35: =BF34+BF18 -> 32649.503 | BG35: =SUM(BE35:BF35) -> 232372.1 | BJ35: =BJ34+BJ18 -> 18657.357 | BL35: =BL34+BL18 -> 223888.28 | BM35: =BM34+BM18 -> 35699.584 | BN35: =SUM(BL35:BM35) -> 259587.87 | BP35: =BP34+BP18 -> 19403.651 | BR35: =BR34+BR18 -> 202154.96 | BS35: =BS34+BS18 -> 33398.093 | BT35: =SUM(BR35:BS35) -> 235553.06 | BV35: =BV34+BV18 -> 18139.094 | BX35: =BX34+BX18 -> 76175.963 | BY35: =BY34+BY18 -> 13150.834 | BZ35: =BZ34+BZ18 -> 89326.797 | CA35: =CA18+CA34 -> 701941.8 | CB35: =CB18+CB34 -> 114898.01 | CC35: =CC34+CC18 -> 816839.82 | CE35: =CE34+CE18 -> 910223.37 | CF35: =CF34+CF18 -> 146645.52 | CG35: =CG34+CG18 -> 1056868.9 | CK35: =SUM(CM35:ES35) -> 0 | CL35: =CJ35+CK35 -> 0
E36: 26 | F36: FRINGE BENEFITS | CK36: =SUM(CM36:ES36) -> 0 | CL36: =CJ36+CK36 -> 0
A37: SUBPROANT | B37: 89050 | C37: COL2 | D37: PAFRINGE | E37: 27 | F37: Fringe Benefits – Colombia HQ and Field Staff (above $2,600 monthly) | G37: PERSONNEL | H37: Fringe Benefits | I37: MIXED | J37: 0.53864 | N37: =$J$37*(N14+N17+N20) -> 38526.226 | O37: =$J$37*(O14+O17+O20) -> 6102.1987 | P37: =SUM(N37:O37) -> 44628.425 | Q37: =J37 -> 0.53864 | T37: =$J$37*(T14+T17+T20) -> 46887.535 | U37: =$J$37*(U14+U17+U20) -> 6923.2218 | V37: =+T37+U37 -> 53810.757 | W37: =J37 -> 0.53864 | Z37: =$J$37*(Z14+Z17+Z20) -> 48763.036 | AA37: =$J$37*(AA14+AA17+AA20) -> 7200.1507 | AB37: =SUM(Z37:AA37) -> 55963.187 | AC37: =J37 -> 0.53864 | AF37: =$J$37*(AF14+AF17+AF20) -> 50713.558 | AG37: =$J$37*(AG14+AG17+AG20) -> 7488.1567 | AH37: =SUM(AF37:AG37) -> 58201.714 | AI37: =J37 -> 0.53864 | AL37: =$J$37*(AL14+AL17+AL20) -> 49465.41 | AM37: =$J$37*(AM14+AM17+AM20) -> 7138.7094 | AN37: =SUM(AL37:AM37) -> 56604.12 | AO37: =+AL37+AF37+Z37+T37+N37 -> 234355.76 | AP37: =+AM37+AG37+AA37+U37+O37 -> 34852.437 | AQ37: =+SUM(AO37:AP37) -> 269208.2 | AR37: 0 | AS37: 0 | AT37: =(1146.22-152.83)+1165.72+1205.78+1210.18+1141.97+(1164.63+1864.79)+1048.51+1061.37+1033.6+970.42+930.8+(958.14+1602.38)+162.13 -> 16513.81 | AU37: 0 | AV37: =AR37+AT37 -> 16513.81 | AW37: =AS37+AU37 -> 0 | AX37: =AV37+AW37 -> 16513.81 | AY37: =AQ37-AX37 -> 252694.39 | AZ37: =AQ37-AR37-AS37-AT37-AU37 -> 252694.39 | BA37: =AY37-AZ37 -> 0 | BB37: 0 | BC37: 0 | BD37: 0 | BE37: 0 | BF37: 0 | BG37: =SUM(BB37:BF37) -> 0 | BH37: Seguridad social (sobre $2,600), se dejará todo en una sola línea dado que el calculo porcentual a cargar es el mismo para todo el personal | BI37: 0 | BJ37: 0 | BK37: 0 | BL37: 0 | BM37: 0 | BN37: =SUM(BI37:BM37) -> 0 | BO37: 0 | BP37: 0 | BQ37: 0 | BR37: 0 | BS37: 0 | BT37: =SUM(BO37:BS37) -> 0 | CA37: =BR37+BL37+BE37 -> 0 | CB37: =BS37+BM37+BF37 -> 0 | CC37: =CA37+CB37 -> 0 | CE37: =AV37+CA37 -> 16513.81 | CF37: =AW37+CB37 -> 0 | CG37: =CE37+CF37 -> 16513.81 | CH37: =AO37-CE37 -> 217841.95 | CI37: =AP37-CF37 -> 34852.437 | CJ37: =AQ37-CG37 -> 252694.39 | CK37: =SUM(CM37:ES37) -> -252694 | CL37: =CJ37+CK37 -> 0.39186573 | CT37: -217842 | CU37: -34852
A38: SUBPROANT | B38: 89050 | C38: COL2 | D38: PAFRINGE | E38: 28 | F38: Fringe Benefits - Colombia HQ and Field Staff (below $2,600 monthly) | G38: PERSONNEL | H38: Fringe Benefits | I38: MIXED | J38: 0.40364 | N38: =$J$38*(N15+N21+N22+N23+N24+N25+N26+N27) -> 30273 | O38: =$J$38*(O15+O21+O22+O23+O24+O25+O26+O27) -> 7418.0959 | P38: =SUM(N38:O38) -> 37691.096 | Q38: =J38 -> 0.40364 | T38: =$J$38*(T15+T21+T22+T23+T24+T25+T26+T27) -> 37780.704 | U38: =$J$38*(U15+U21+U22+U23+U24+U25+U26+U27) -> 8134.6054 | V38: =+T38+U38 -> 45915.309 | W38: =J38 -> 0.40364 | Z38: =$J$38*(Z15+Z21+Z22+Z23+Z24+Z25+Z26+Z27) -> 39291.932 | AA38: =$J$38*(AA15+AA21+AA22+AA23+AA24+AA25+AA26+AA27) -> 8459.9896 | AB38: =SUM(Z38:AA38) -> 47751.922 | AC38: =J38 -> 0.40364 | AF38: =$J$38*(AF15+AF21+AF22+AF23+AF24+AF25+AF26+AF27) -> 40863.609 | AG38: =$J$38*(AG15+AG21+AG22+AG23+AG24+AG25+AG26+AG27) -> 8798.3892 | AH38: =SUM(AF38:AG38) -> 49661.999 | AI38: =J38 -> 0.40364 | AL38: =$J$38*(AL15+AL21+AL22+AL23+AL24+AL25+AL26+AL27) -> 33644.372 | AM38: =$J$38*(AM15+AM21+AM22+AM23+AM24+AM25+AM26+AM27) -> 9150.3247 | AN38: =SUM(AL38:AM38) -> 42794.696 | AO38: =+AL38+AF38+Z38+T38+N38 -> 181853.62 | AP38: =+AM38+AG38+AA38+U38+O38 -> 41961.405 | AQ38: =+SUM(AO38:AP38) -> 223815.02 | AR38: =1004.62+2384.5+1984.94+2167.27+4452.1 -> 11993.43 | AS38: =610.8+235.92+174.69+381.75+610.8+235.92+174.69+381.75+610.8+235.92+174.69+381.75+194.7+97.35+96.01 -> 4597.54 | AT38: =5666.77+3395+3401.2+3467.08+3271.67+8962.85+5296.53+4925.25+5608.71+8084.1+5733.3+11946.72-AT37 -> 53245.37 | AU38: =195.42+97.37+90.38+141.66+198.74+99.02+91.92+146.53+205.57+102.42+95.07+147.06+206.32+102.8+95.42+138.77+194.69+97+90.04+141.53+198.56+98.93+91.83+178.76+89.06+82.67+180.95+90.16+83.69+176.22+87.8+81.5+176.22+87.8+81.5+158.69+79.07+73.39+163.35+81.39+75.55 -> 5094.82 | AV38: =AR38+AT38 -> 65238.8 | AW38: =AS38+AU38 -> 9692.36 | AX38: =AV38+AW38 -> 74931.16 | AY38: =AQ38-AX38 -> 148883.86 | AZ38: =AQ38-AR38-AS38-AT38-AU38 -> 148883.86 | BA38: =AY38-AZ38 -> 0 | BB38: =52.374% -> 0.52374 | BE38: 96121.16 | BF38: =BF35*BB38 -> 17099.851 | BG38: =SUM(BE38:BF38) -> 113221.01 | BH38: Seguridad social: para lo reportado mes a mes se registra lo efectivamente pagado (30,54%) sobre el salario mensual percibido por los colaboradores (Salud 8,5%, Pensión 12%, Caja de compensación familiar 4%, ARL 1,044%, Sena 2%, ICBF 3%), el restante exigido por ley se reporta en los periodos en que sea efectivamente pagado (provision de vacaciones (4,17%), provision de prima (8,33%), de ello el valor a cargar mes a mes es de 52,4% sobre el salario mensual percibido, para un total cargado a seguridad social de 52,4%. El valor relacionado comprende las provisiones del año 2022 efectivamente pagado en el año 2023. El valor presentado para el año 2023 incluye provision de cesantias (8,33%), provision de int ces (1%) del año 2022 los cuales fueron efectivamente pagados en el mes de enero de 2023. El valor presentado para el 2023 corresponde a lo efectivamente pagado (30,54%) sobre el salario mas los pagos correspondientes a primas legales , se excluyen los pagos de cesantias e intereses a cesantias para ser sumados en el año 2024 dada la limitación del monto obligado actual | BI38: 0.52374 | BL38: =BL35*BI38 -> 117259.25 | BM38: =BM35*BI38 -> 18697.3 | BN38: =SUM(BL38:BM38) -> 135956.55 | BO38: 0.52374 | BR38: =BR35*BO38 -> 105876.64 | BS38: =BS35*BO38 -> 17491.917 | BT38: =BS38+BR38 -> 123368.56 | BU38: 0.52374 | BX38: =BX35*BU38 -> 39896.399 | BY38: =BY35*BU38 -> 6887.6179 | BZ38: =BY38+BX38 -> 46784.017 | CA38: =BR38+BL38+BE38+BX38 -> 359153.45 | CB38: =BF38+BM38+BS38+BY38 -> 60176.686 | CC38: =CA38+CB38 -> 419330.13 | CE38: =AV38+CA38 -> 424392.25 | CF38: =AW38+CB38 -> 69869.046 | CG38: =CE38+CF38 -> 494261.29 | CH38: =AO38-CE38 -> -242538.63 | CI38: =AP38-CF38 -> -27907.641 | CJ38: =AQ38-CG38 -> -270446.27 | CK38: =SUM(CM38:ES38) -> 270446 | CL38: =CJ38+CK38 -> -0.27229192 | CT38: 217842 | CU38: 27908 | EG38: 24696
E39: 29 | F39: Fringe Benefits Total | N39: =SUM(N37:N38) -> 68799.226 | O39: =SUM(O37:O38) -> 13520.295 | P39: =SUM(P37:P38) -> 82319.521 | T39: =SUM(T37:T38) -> 84668.239 | U39: =SUM(U37:U38) -> 15057.827 | V39: =SUM(V37:V38) -> 99726.066 | Z39: =SUM(Z37:Z38) -> 88054.968 | AA39: =SUM(AA37:AA38) -> 15660.14 | AB39: =SUM(AB37:AB38) -> 103715.11 | AF39: =SUM(AF37:AF38) -> 91577.167 | AG39: =SUM(AG37:AG38) -> 16286.546 | AH39: =SUM(AH37:AH38) -> 107863.71 | AL39: =SUM(AL37:AL38) -> 83109.782 | AM39: =SUM(AM37:AM38) -> 16289.034 | AN39: =SUM(AN37:AN38) -> 99398.816 | AO39: =SUM(AO37:AO38) -> 416209.38 | AP39: =SUM(AP37:AP38) -> 76813.842 | AQ39: =SUM(AO39:AP39) -> 493023.22 | AR39: =AR38+AR37 -> 11993.43 | AS39: =AS38+AS37 -> 4597.54 | AT39: =SUM(AT37:AT38) -> 69759.18 | AU39: =SUM(AU37:AU38) -> 5094.82 | AV39: =SUM(AV37:AV38) -> 81752.61 | AW39: =SUM(AW37:AW38) -> 9692.36 | AX39: =SUM(AX37:AX38) -> 91444.97 | AY39: =SUM(AY37:AY38) -> 401578.25 | AZ39: =AQ39-AR39-AS39-AT39-AU39 -> 401578.25 | BC39: =BC38+BC37 -> 0 | BD39: 0 | BE39: =SUM(BE37:BE38) -> 96121.16 | BF39: =SUM(BF37:BF38) -> 17099.851 | BG39: =SUM(BE39:BF39) -> 113221.01 | BJ39: =BJ38+BJ37 -> 0 | BL39: =SUM(BL37:BL38) -> 117259.25 | BM39: =SUM(BM37:BM38) -> 18697.3 | BN39: =SUM(BL39:BM39) -> 135956.55 | BP39: =BP38+BP37 -> 0 | BR39: =SUM(BR37:BR38) -> 105876.64 | BS39: =BS38+BS37 -> 17491.917 | BT39: =SUM(BR39:BS39) -> 123368.56 | BV39: =BV38 -> 0 | BX39: =BX38 -> 39896.399 | BY39: =BY38 -> 6887.6179 | BZ39: =BZ38 -> 46784.017 | CA39: =BR39+BL39+BE39+BX39 -> 359153.45 | CB39: =BY39+BS39+BM39+BF39 -> 60176.686 | CC39: =BZ39+BT39+BN39+BG39 -> 419330.13 | CE39: =CA39+AT39+AR39 -> 440906.06 | CF39: =CF38+CF37 -> 69869.046 | CG39: =CE39+CF39 -> 510775.1 | CK39: =SUM(CM39:ES39) -> 0 | CL39: =CJ39+CK39 -> 0
E40: 30 | F40: TRAVEL | CK40: =SUM(CM40:ES40) -> 0 | CL40: =CJ40+CK40 -> 0
E41: 31 | F41: Staff Travel | CK41: =SUM(CM41:ES41) -> 0 | CL41: =CJ41+CK41 -> 0
A42: SUBPROANT | B42: 89050 | C42: COL2 | D42: PAHQTRVL | E42: 32 | F42: Local Transportation (Airfare, Taxis, & Rental Car/Driver) | G42: TRAVEL | H42: Staff Travel | I42: USAID | M42: /trip | AR42: 0 | AS42: 0 | AT42: 0 | AU42: 0 | AV42: 0 | AW42: =AS42+AU42 -> 0 | AX42: =AV42+AW42 -> 0 | AY42: =AQ42-AX42 -> 0 | AZ42: 0 | BA42: =AY42-AZ42 -> 0 | BB42: 169 | BC42: 212.7 | BE42: =BC42*BB42 -> 35946.3 | BF42: =AA42 -> 0 | BG42: =SUM(BE42:BF42) -> 35946.3 | BH42: Este valor comprende transporte aéreo y terrestre vinculados a la operación del proyecto. Se estiman 137 viajes relacionados con S+M (esto comprende la operación en 3 ciudades que son Santa Marta, Cali y Riohacha para el desarrollo de 5 sesiones vinculadas a actividades de formación a docentes en un total de 47 sedes educativas) este despliegue requiere transporte aéreo ida y vuelta a las ciudades seleccionadas, transporte terrestre hacia los aeropuertos y desplazamiento en campo (adjunto programación) se estima que se realice un viaje por sesión y que en promedio los formadores y personal de apoyo estén 2 días en territorio. De manera adicional, para el desarrollo de las plenarias docentes se requiere que asistan a territorio además del formador, un apoyo para la recolección de datos, 28 viajes relacionados con la subactividad Directivos Docentes, 2 para asuntos generales del proyecto que puede incluir actividades relacionadas con monitoreo y evaluación o actividades GESI y 2 para Alianzas para un total de 169 viajes. según la experiencia en este tipo de actividades. | BJ42: =6510 -> 6510 | BL42: =BJ42 -> 6510 | BM42: 0 | BN42: =SUM(BL42:BM42) -> 6510 | BP42: 17770 | BR42: =BP42 -> 17770 | BS42: 0 | BT42: =BS42+BR42 -> 17770 | BV42: 15940 | BX42: =BV42 -> 15940 | BY42: 0 | BZ42: =BY42+BX42 -> 15940 | CA42: =BR42+BL42+BE42+BX42 -> 76166.3 | CB42: =BS42+BM42+BF42+BY42 -> 0 | CC42: =CA42+CB42 -> 76166.3 | CE42: =AV42+CA42 -> 76166.3 | CF42: =AW42+CB42 -> 0 | CG42: =CE42+CF42 -> 76166.3 | CH42: =AO42-CE42 -> -76166.3 | CI42: =AP42-CF42 -> 0 | CJ42: =AQ42-CG42 -> -76166.3 | CK42: =SUM(CM42:ES42) -> 76166 | CL42: =CJ42+CK42 -> -0.3 | DC42: 9521 | DT42: 50000 | EF42: 16645
A43: SUBPROANT | B43: 89050 | C43: COL2 | D43: PAHQTRVL | E43: 33 | F43: Meals and incidentals | G43: TRAVEL | H43: Staff Travel | I43: USAID | M43: /day | AR43: 0 | AS43: 0 | AT43: 0 | AU43: 0 | AV43: 0 | AW43: =AS43+AU43 -> 0 | AX43: =AV43+AW43 -> 0 | AY43: =AQ43-AX43 -> 0 | AZ43: 0 | BA43: =AY43-AZ43 -> 0 | BB43: 170 | BC43: 98.97 | BE43: =BC43*BB43 -> 16824.9 | BF43: 0 | BG43: =SUM(BE43:BF43) -> 16824.9 | BH43: Este valor comprende viáticos de los colaboradores en campo. Se estiman 137 viajes relacionados con S+M (esto comprende la operación en 3 ciudades que son: Santa Marta, Cali y Riohacha para el desarrollo de 5 sesiones vinculadas a actividades de formación a docentes en un total de 47 sedes educativas) se estima que se realice un viaje por sesión y que en promedio los formadores y personal de apoyo estén 2 días en territorio, el valor unitario corresponde a un estimado de “viaticos perdiem” para que la persona en campo pueda tener acceso a su alimentación e hidratación, esto dado las cantidades de viáticos aprobadas por ciudad, este valor será legalizado por la persona en campo cuando regrese de su viaje dando cuenta de las exclusiones de gasto que le son aplicables desde lo ocurrido. de manera adicional para el desarrollo de las plenarias docentes se requiere que asistan a territorio además del formador, un apoyo para la recolección de datos, 28 relacionados con DD, 2 para asuntos generales del proyecto que puede incluir actividades relacionadas con monitoreo y evaluación o actividades GESI y 2 para Alianzas para un total de 170 perdiem. | BJ43: =5510-341 -> 5169 | BL43: =BJ43 -> 5169 | BM43: 0 | BN43: =SUM(BL43:BM43) -> 5169 | BP43: 20590.38 | BR43: =BP43 -> 20590.38 | BS43: 0 | BT43: =BS43+BR43 -> 20590.38 | BV43: 15540 | BX43: =BV43 -> 15540 | BY43: 0 | BZ43: =BY43+BX43 -> 15540 | CA43: =BR43+BL43+BE43+BX43 -> 58124.28 | CB43: =BS43+BM43+BF43+BY43 -> 0 | CC43: =CA43+CB43 -> 58124.28 | CE43: =AV43+CA43 -> 58124.28 | CF43: =AW43+CB43 -> 0 | CG43: =CE43+CF43 -> 58124.28 | CH43: =AO43-CE43 -> -58124.28 | CI43: =AP43-CF43 -> 0 | CJ43: =AQ43-CG43 -> -58124.28 | CK43: =SUM(CM43:ES43) -> 58124 | CL43: =CJ43+CK43 -> -0.28 | DV43: 23452 | DY43: 34672
A44: SUBPROANT | B44: 89050 | C44: COL2 | D44: PAHQTRVL | E44: 34 | F44: Lodging | G44: TRAVEL | H44: Staff Travel | I44: USAID | M44: /day | AR44: 0 | AS44: 0 | AT44: 0 | AU44: 0 | AV44: 0 | AW44: =AS44+AU44 -> 0 | AX44: =AV44+AW44 -> 0 | AY44: =AQ44-AX44 -> 0 | AZ44: 0 | BA44: =AY44-AZ44 -> 0 | BB44: 170 | BC44: 111.5882 | BE44: =BC44*BB44 -> 18969.994 | BF44: 0 | BG44: =SUM(BE44:BF44) -> 18969.994 | BH44: Este valor comprende hospedajes y otros costos imprevistos que puedan derivarse de la operación. Se estiman 137 viajes relacionados con S+M (esto comprende la operación en 3 ciudades que son: Santa Marta, Cali y Riohacha para el desarrollo de 5 sesiones vinculadas a actividades de formación a docentes en un total de 47 sedes educativas) de manera adicional para el desarrollo de las plenarias docentes se requiere que asistan a territorio además del formador, un apoyo para la recolección de datos, este despliegue requiere transporte aéreo ida y vuelta a las ciudades seleccionadas, transporte terrestre hacia los aeropuertos y desplazamiento en campo (adjunto programación) se estima que se realice un viaje por sesión y que en promedio los formadores y personal de apoyo estén 2 días en territorio lo que requiere un estimado de una noche de alojamiento, 28 relacionados con DD, 2 para asuntos generales del proyecto que puede incluir actividades relacionadas con monitoreo y evaluación o actividades GESI y 3 para Alianzas para un total de 170 hospedajes. | BJ44: 5030.12 | BL44: =BJ44 -> 5030.12 | BM44: 0 | BN44: =SUM(BL44:BM44) -> 5030.12 | BP44: 10600 | BR44: =BP44 -> 10600 | BS44: 0 | BT44: =BS44+BR44 -> 10600 | BV44: 15530.76 | BX44: =BV44 -> 15530.76 | BY44: 0 | BZ44: =BY44+BX44 -> 15530.76 | CA44: =BR44+BL44+BE44+BX44 -> 50130.874 | CB44: =BS44+BM44+BF44+BY44 -> 0 | CC44: =CA44+CB44 -> 50130.874 | CE44: =AV44+CA44 -> 50130.874 | CF44: =AW44+CB44 -> 0 | CG44: =CE44+CF44 -> 50130.874 | CH44: =AO44-CE44 -> -50130.874 | CI44: =AP44-CF44 -> 0 | CJ44: =AQ44-CG44 -> -50130.874 | CK44: =SUM(CM44:ES44) -> 50131 | CL44: =CJ44+CK44 -> 0.126 | DV44: 131 | DX44: 50000
E45: 35 | F45: Subtotal Staff Travel | AR45: =SUM(AR42:AR44) -> 0 | AS45: =SUM(AS42:AS44) -> 0 | AT45: =SUM(AT42:AT44) -> 0 | AU45: =SUM(AU42:AU44) -> 0 | AV45: =SUM(AV42:AV44) -> 0 | AW45: =SUM(AW42:AW44) -> 0 | AX45: =SUM(AX42:AX44) -> 0 | AY45: =SUM(AY42:AY44) -> 0 | AZ45: =SUM(AZ42:AZ44) -> 0 | BC45: =BC42+BC43+BC44 -> 423.2582 | BE45: =+BE44+BE43+BE42 -> 71741.194 | BF45: =AA45 -> 0 | BG45: =+BF45+BE45 -> 71741.194 | BJ45: =BJ42 -> 6510 | BL45: =BL42+BL43+BL44 -> 16709.12 | BM45: =AG45 -> 0 | BN45: =BM45+BL45 -> 16709.12 | BP45: =BP42+BP43+BP44 -> 48960.38 | BR45: =BR42+BR43+BR44 -> 48960.38 | BS45: =AM45 -> 0 | BT45: =BS45+BR45 -> 48960.38 | BV45: =BV42+BV43+BV44 -> 47010.76 | BX45: =BX42+BX43+BX44 -> 47010.76 | BY45: =AS45 -> 0 | BZ45: =BY45+BX45 -> 47010.76 | CA45: =CA42+CA43+CA44 -> 184421.45 | CB45: =AP45 -> 0 | CC45: =BZ45+BT45+BN45+BG45 -> 184421.45 | CE45: =CA45+AR45+AT45 -> 184421.45 | CF45: =CB45+AS45+AU45 -> 0 | CG45: =CE45+CF45 -> 184421.45 | CK45: =SUM(CM45:ES45) -> 0 | CL45: =CJ45+CK45 -> 0
E46: 36 | F46: HQ Staff Travel | CK46: =SUM(CM46:ES46) -> 0 | CL46: =CJ46+CK46 -> 0
A47: SUBPROANT | B47: 89050 | C47: COL2 | D47: PAHQTRVL | E47: 37 | F47: Local Transportation (Airfare, Taxis, & Rental Car/Driver) for Directors | G47: TRAVEL | H47: HQ Staff Travel | I47: USAID | J47: 2 | K47: 250 | L47: 1 | M47: /trip | N47: =L47*K47*J47 -> 500 | O47: 0 | P47: =SUM(N47:O47) -> 500 | Q47: 2 | R47: =K47*$J$6 -> 257.5 | S47: 1 | T47: =Q47*R47*S47 -> 515 | U47: 0 | V47: =SUM(T47:U47) -> 515 | W47: 2 | X47: =K47*$J$6*$J$6 -> 265.225 | Y47: 1 | Z47: =W47*X47*Y47 -> 530.45 | AA47: 0 | AB47: =SUM(Z47:AA47) -> 530.45 | AC47: 2 | AD47: =K47*$J$6*$J$6*$J$6 -> 273.18175 | AE47: 1 | AF47: =AC47*AD47*AE47 -> 546.3635 | AG47: 0 | AH47: =SUM(AF47:AG47) -> 546.3635 | AI47: 2 | AJ47: =K47*$J$6*$J$6*$J$6*$J$6 -> 281.3772 | AK47: 1 | AL47: =AI47*AJ47*AK47 -> 562.75441 | AM47: 0 | AN47: =SUM(AL47:AM47) -> 562.75441 | AO47: =N47+T47+Z47+AF47+AL47 -> 2654.5679 | AP47: =O47+U47+AA47+AG47+AM47 -> 0 | AQ47: =SUM(AO47:AP47) -> 2654.5679 | AR47: 913.59 | AS47: 0 | AT47: 0 | AU47: 0 | AV47: =AR47+AT47 -> 913.59 | AW47: =AS47+AU47 -> 0 | AX47: =AV47+AW47 -> 913.59 | AY47: =AQ47-AX47 -> 1740.9779 | AZ47: =AQ47-AR47-AS47-AT47-AU47 -> 1740.9779 | BA47: =AY47-AZ47 -> 0 | BC47: 0 | BE47: 0 | BF47: =AA47 -> 0 | BG47: =SUM(BE47:BF47) -> 0 | BH47: Transporte local para que los directores viajen a las diferentes áreas de implementación para supervisar las actividades del proyecto, incluidas las actividades de formación de docentes. Esta linea no se requiere. | BJ47: 0 | BL47: 0 | BM47: =AG47 -> 0 | BN47: =SUM(BL47:BM47) -> 0 | BP47: 0 | BR47: 0 | BS47: =AM47 -> 0 | BT47: 0 | BV47: 0 | BX47: 0 | BY47: =AS47 -> 0 | BZ47: 0 | CA47: =BR47+BL47+BE47+BX47 -> 0 | CB47: =BS47+BM47+BF47 -> 0 | CC47: =CA47+CB47 -> 0 | CE47: =AV47+CA47 -> 913.59 | CF47: =AW47+CB47 -> 0 | CG47: =CE47+CF47 -> 913.59 | CH47: =AO47-CE47 -> 1740.9779 | CI47: =AP47-CF47 -> 0 | CJ47: =AQ47-CG47 -> 1740.9779 | CK47: =SUM(CM47:ES47) -> -1741 | CL47: =CJ47+CK47 -> -0.022095 | CV47: -1741
E48: 38 | F48: Meals and Incidentals for Directors | G48: TRAVEL | H48: HQ Staff Travel | I48: USAID | J48: 2 | K48: 40 | L48: 5 | M48: /day | N48: =L48*K48*J48 -> 400 | O48: 0 | P48: =SUM(N48:O48) -> 400 | Q48: 2 | R48: =K48*$J$6 -> 41.2 | S48: 5 | T48: =Q48*R48*S48 -> 412 | U48: 0 | V48: =SUM(T48:U48) -> 412 | W48: 2 | X48: =K48*$J$6*$J$6 -> 42.436 | Y48: 5 | Z48: =W48*X48*Y48 -> 424.36 | AA48: 0 | AB48: =SUM(Z48:AA48) -> 424.36 | AC48: 2 | AD48: =K48*$J$6*$J$6*$J$6 -> 43.70908 | AE48: 5 | AF48: =AC48*AD48*AE48 -> 437.0908 | AG48: 0 | AH48: =SUM(AF48:AG48) -> 437.0908 | AI48: 2 | AJ48: =K48*$J$6*$J$6*$J$6*$J$6 -> 45.020352 | AK48: 5 | AL48: =AI48*AJ48*AK48 -> 450.20352 | AM48: 0 | AN48: =SUM(AL48:AM48) -> 450.20352 | AO48: =N48+T48+Z48+AF48+AL48 -> 2123.6543 | AP48: =O48+U48+AA48+AG48+AM48 -> 0 | AQ48: =SUM(AO48:AP48) -> 2123.6543 | AR48: 0 | AS48: 0 | AT48: 0 | AU48: 0 | AV48: =AR48+AT48 -> 0 | AW48: =AS48+AU48 -> 0 | AX48: =AV48+AW48 -> 0 | AY48: =AQ48-AX48 -> 2123.6543 | AZ48: =AQ48-AR48-AS48-AT48-AU48 -> 2123.6543 | BA48: =AY48-AZ48 -> 0 | BC48: 0 | BE48: 0 | BF48: =AA48 -> 0 | BG48: =SUM(BE48:BF48) -> 0 | BH48: Comidas e imprevistos para que los Directores viajen a las diferentes áreas de implementación para supervisar las actividades del proyecto, incluidas las actividades de Formación de Profesores. Esta linea no se requiere. | BJ48: 0 | BL48: 0 | BM48: =AG48 -> 0 | BN48: =SUM(BL48:BM48) -> 0 | BP48: 0 | BR48: 0 | BS48: =AM48 -> 0 | BT48: 0 | BV48: 0 | BX48: 0 | BY48: =AS48 -> 0 | BZ48: 0 | CA48: =BR48+BL48+BE48+BX48 -> 0 | CB48: =BS48+BM48+BF48 -> 0 | CC48: =CA48+CB48 -> 0 | CE48: =AV48+CA48 -> 0 | CF48: =AW48+CB48 -> 0 | CG48: =CE48+CF48 -> 0 | CH48: =AO48-CE48 -> 2123.6543 | CI48: =AP48-CF48 -> 0 | CJ48: =AQ48-CG48 -> 2123.6543 | CK48: =SUM(CM48:ES48) -> -2124 | CL48: =CJ48+CK48 -> -0.345676 | CW48: -2124
E49: 39 | F49: Lodging for Directors | G49: TRAVEL | H49: HQ Staff Travel | I49: USAID | J49: 2 | K49: 80 | L49: 4 | M49: /day | N49: =L49*K49*J49 -> 640 | O49: 0 | P49: =SUM(N49:O49) -> 640 | Q49: 2 | R49: =K49*$J$6 -> 82.4 | S49: 4 | T49: =Q49*R49*S49 -> 659.2 | U49: 0 | V49: =SUM(T49:U49) -> 659.2 | W49: 2 | X49: =K49*$J$6*$J$6 -> 84.872 | Y49: 4 | Z49: =W49*X49*Y49 -> 678.976 | AA49: 0 | AB49: =SUM(Z49:AA49) -> 678.976 | AC49: 2 | AD49: =K49*$J$6*$J$6*$J$6 -> 87.41816 | AE49: 4 | AF49: =AC49*AD49*AE49 -> 699.34528 | AG49: 0 | AH49: =SUM(AF49:AG49) -> 699.34528 | AI49: 2 | AJ49: =K49*$J$6*$J$6*$J$6*$J$6 -> 90.040705 | AK49: 4 | AL49: =AI49*AJ49*AK49 -> 720.32564 | AM49: 0 | AN49: =SUM(AL49:AM49) -> 720.32564 | AO49: =N49+T49+Z49+AF49+AL49 -> 3397.8469 | AP49: =O49+U49+AA49+AG49+AM49 -> 0 | AQ49: =SUM(AO49:AP49) -> 3397.8469 | AR49: 0 | AS49: 0 | AT49: 0 | AU49: 0 | AV49: =AR49+AT49 -> 0 | AW49: =AS49+AU49 -> 0 | AX49: =AV49+AW49 -> 0 | AY49: =AQ49-AX49 -> 3397.8469 | AZ49: =AQ49-AR49-AS49-AT49-AU49 -> 3397.8469 | BA49: =AY49-AZ49 -> 0 | BC49: 0 | BE49: 0 | BF49: =AA49 -> 0 | BG49: =SUM(BE49:BF49) -> 0 | BH49: Alojamiento para que los Directores viajen a las diferentes áreas de implementación para supervisar las actividades del proyecto, incluidas las actividades de Formación de Docentes. Esta linea no se requiere. | BJ49: 0 | BL49: 0 | BM49: =AG49 -> 0 | BN49: =SUM(BL49:BM49) -> 0 | BP49: 0 | BR49: 0 | BS49: =AM49 -> 0 | BT49: 0 | BV49: 0 | BX49: 0 | BY49: =AS49 -> 0 | BZ49: 0 | CA49: =BR49+BL49+BE49+BX49 -> 0 | CB49: =BS49+BM49+BF49 -> 0 | CC49: =CA49+CB49 -> 0 | CE49: =AV49+CA49 -> 0 | CF49: =AW49+CB49 -> 0 | CG49: =CE49+CF49 -> 0 | CH49: =AO49-CE49 -> 3397.8469 | CI49: =AP49-CF49 -> 0 | CJ49: =AQ49-CG49 -> 3397.8469 | CK49: =SUM(CM49:ES49) -> -3398 | CL49: =CJ49+CK49 -> -0.1530816 | CX49: -3398
E50: 40 | F50: Other Travel Related Expenses for Directors | G50: TRAVEL | H50: HQ Staff Travel | I50: USAID | J50: 2 | K50: 25 | L50: 1 | M50: /trip | N50: =L50*K50*J50 -> 50 | O50: 0 | P50: =SUM(N50:O50) -> 50 | Q50: 2 | R50: =K50*$J$6 -> 25.75 | S50: 1 | T50: =Q50*R50*S50 -> 51.5 | U50: 0 | V50: =SUM(T50:U50) -> 51.5 | W50: 2 | X50: =K50*$J$6*$J$6 -> 26.5225 | Y50: 1 | Z50: =W50*X50*Y50 -> 53.045 | AA50: 0 | AB50: =SUM(Z50:AA50) -> 53.045 | AC50: 2 | AD50: =K50*$J$6*$J$6*$J$6 -> 27.318175 | AE50: 1 | AF50: =AC50*AD50*AE50 -> 54.63635 | AG50: 0 | AH50: =SUM(AF50:AG50) -> 54.63635 | AI50: 2 | AJ50: =K50*$J$6*$J$6*$J$6*$J$6 -> 28.13772 | AK50: 1 | AL50: =AI50*AJ50*AK50 -> 56.275441 | AM50: 0 | AN50: =SUM(AL50:AM50) -> 56.275441 | AO50: =N50+T50+Z50+AF50+AL50 -> 265.45679 | AP50: =O50+U50+AA50+AG50+AM50 -> 0 | AQ50: =SUM(AO50:AP50) -> 265.45679 | AR50: 0 | AS50: 0 | AT50: 0 | AU50: 0 | AV50: =AR50+AT50 -> 0 | AW50: =AS50+AU50 -> 0 | AX50: =AV50+AW50 -> 0 | AY50: =AQ50-AX50 -> 265.45679 | AZ50: =AQ50-AR50-AS50-AT50-AU50 -> 265.45679 | BA50: =AY50-AZ50 -> 0 | BC50: 0 | BE50: =BB50*BC50*BD50 -> 0 | BF50: =AA50 -> 0 | BG50: =SUM(BE50:BF50) -> 0 | BH50: Otros gastos relacionados con los viajes de los Directores para viajar a las diferentes áreas de implementación. Esta linea no se requiere. | BJ50: 0 | BL50: =BI50*BJ50*BK50 -> 0 | BM50: =AG50 -> 0 | BN50: =SUM(BL50:BM50) -> 0 | BP50: 0 | BR50: =BO50*BP50*BQ50 -> 0 | BS50: =AM50 -> 0 | BT50: =SUM(BR50:BS50) -> 0 | BV50: 0 | BX50: =BU50*BV50*BW50 -> 0 | BY50: =AS50 -> 0 | BZ50: =SUM(BX50:BY50) -> 0 | CA50: =BR50+BL50+BE50+BX50 -> 0 | CB50: =BS50+BM50+BF50 -> 0 | CC50: =CA50+CB50 -> 0 | CE50: =AV50+CA50 -> 0 | CF50: =AW50+CB50 -> 0 | CG50: =CE50+CF50 -> 0 | CH50: =AO50-CE50 -> 265.45679 | CI50: =AP50-CF50 -> 0 | CJ50: =AQ50-CG50 -> 265.45679 | CK50: =SUM(CM50:ES50) -> -265 | CL50: =CJ50+CK50 -> 0.4567905 | CY50: -265
E51: 41 | F51: Subtotal HQ Staff Travel | N51: =SUM(N47:N50) -> 1590 | O51: =SUM(O47:O50) -> 0 | P51: =SUM(P47:P50) -> 1590 | T51: =SUM(T47:T50) -> 1637.7 | U51: =SUM(U47:U50) -> 0 | V51: =SUM(V47:V50) -> 1637.7 | Z51: =SUM(Z47:Z50) -> 1686.831 | AA51: =SUM(AA47:AA50) -> 0 | AB51: =SUM(AB47:AB50) -> 1686.831 | AF51: =SUM(AF47:AF50) -> 1737.4359 | AG51: =SUM(AG47:AG50) -> 0 | AH51: =SUM(AH47:AH50) -> 1737.4359 | AL51: =SUM(AL47:AL50) -> 1789.559 | AM51: =SUM(AM47:AM50) -> 0 | AN51: =SUM(AN47:AN50) -> 1789.559 | AO51: =SUM(AO47:AO50) -> 8441.5259 | AP51: =SUM(AP47:AP50) -> 0 | AQ51: =SUM(AQ47:AQ50) -> 8441.5259 | AR51: =SUM(AR47:AR50) -> 913.59 | AS51: 0 | AT51: 0 | AU51: 0 | AV51: 0 | AW51: 0 | AX51: 0 | AY51: 0 | AZ51: =AQ51-AR51-AS51-AT51-AU51 -> 7527.9359 | BC51: 0 | BE51: =BB51*BC51*BD51 -> 0 | BF51: =AA51 -> 0 | BG51: =SUM(BE51:BF51) -> 0 | BJ51: 0 | BL51: =BI51*BJ51*BK51 -> 0 | BM51: =AG51 -> 0 | BN51: =SUM(BL51:BM51) -> 0 | BP51: 0 | BR51: =BO51*BP51*BQ51 -> 0 | BS51: =AM51 -> 0 | BT51: =SUM(BR51:BS51) -> 0 | BV51: 0 | BX51: =BU51*BV51*BW51 -> 0 | BY51: =AS51 -> 0 | BZ51: =SUM(BX51:BY51) -> 0 | CA51: =BR51+BL51+BE51+BX51 -> 0 | CB51: =BS51+BM51+BF51 -> 0 | CC51: =BT51+BN51+BG51 -> 0 | CE51: =CA51+AR51+AT51 -> 913.59 | CF51: =CB51+AS51+AU51 -> 0 | CG51: =CE51+CF51 -> 913.59 | CK51: =SUM(CM51:ES51) -> 0 | CL51: =CJ51+CK51 -> 0
E52: 42 | F52: Field Travel | CK52: =SUM(CM52:ES52) -> 0 | CL52: =CJ52+CK52 -> 0
E53: 43 | F53: T.1 Field Staff Travel for Site Visits and M&E | CK53: =SUM(CM53:ES53) -> 0 | CL53: =CJ53+CK53 -> 0
A54: SUBPROANT | B54: 89050 | C54: COL2 | D54: PAT1TRVL | E54: 44 | F54: Local Transportation (Airfare, Taxis, & Rental Car/Driver) for Site Visits and M&E | G54: TRAVEL | H54: Field Travel | I54: USAID | J54: 12 | K54: 250 | L54: 1 | M54: /trip | N54: =L54*K54*J54 -> 3000 | O54: 0 | P54: =SUM(N54:O54) -> 3000 | Q54: 12 | R54: =K54*$J$6 -> 257.5 | S54: 1 | T54: =Q54*R54*S54 -> 3090 | U54: 0 | V54: =SUM(T54:U54) -> 3090 | W54: 12 | X54: =K54*$J$6*$J$6 -> 265.225 | Y54: 1 | Z54: =W54*X54*Y54 -> 3182.7 | AA54: 0 | AB54: =SUM(Z54:AA54) -> 3182.7 | AC54: 12 | AD54: =K54*$J$6*$J$6*$J$6 -> 273.18175 | AE54: 1 | AF54: =AC54*AD54*AE54 -> 3278.181 | AG54: 0 | AH54: =SUM(AF54:AG54) -> 3278.181 | AI54: 12 | AJ54: =K54*$J$6*$J$6*$J$6*$J$6 -> 281.3772 | AK54: 1 | AL54: =AI54*AJ54*AK54 -> 3376.5264 | AM54: 0 | AN54: =SUM(AL54:AM54) -> 3376.5264 | AO54: =N54+T54+Z54+AF54+AL54 -> 15927.407 | AP54: =O54+U54+AA54+AG54+AM54 -> 0 | AQ54: =SUM(AO54:AP54) -> 15927.407 | AR54: =1816.37+1589.97+1953.64+731.23 -> 6091.21 | AS54: 0 | AT54: =793.72+2634.66+10735.95+15047.83+5040.15+10019.69+6705+10952.62+14283.22+6989.35+2473.44+4128.24 -> 89803.87 | AU54: 0 | AV54: =AR54+AT54 -> 95895.08 | AW54: =AS54+AU54 -> 0 | AX54: =AV54+AW54 -> 95895.08 | AY54: =AQ54-AX54 -> -79967.673 | AZ54: =AQ54-AR54-AS54-AT54-AU54 -> -79967.673 | BA54: =AY54-AZ54 -> 0 | BC54: 0 | BE54: 0 | BF54: =AA54 -> 0 | BG54: =SUM(BE54:BF54) -> 0 | BH54: Transporte local, incluidos pasajes aéreos, taxis y alquiler de automóviles/conductor, presupuestado para que el personal de campo viaje para llevar a cabo actividades de monitoreo y evaluación, incluida la recopilación y verificación de datos. Esta linea no se requiere. | BJ54: 0 | BL54: 0 | BM54: =AG54 -> 0 | BN54: =SUM(BL54:BM54) -> 0 | BP54: 0 | BR54: 0 | BS54: =AM54 -> 0 | BT54: 0 | BV54: 0 | BX54: 0 | BY54: =AS54 -> 0 | BZ54: 0 | CA54: =BR54+BL54+BE54+BX54 -> 0 | CB54: =BS54+BM54+BF54 -> 0 | CC54: =CA54+CB54 -> 0 | CE54: =AV54+CA54 -> 95895.08 | CF54: =AW54+CB54 -> 0 | CG54: =CE54+CF54 -> 95895.08 | CH54: =AO54-CE54 -> -79967.673 | CI54: =AP54-CF54 -> 0 | CJ54: =AQ54-CG54 -> -79967.673 | CK54: =SUM(CM54:ES54) -> 79968 | CL54: =CJ54+CK54 -> 0.32743 | CV54: 1741 | CW54: 2124 | CX54: 3398 | CY54: 265 | CZ54: 12742 | DA54: 20387 | DB54: 1593 | DC54: 7125 | DD54: 1567 | DE54: 1567 | DF54: 3134 | DG54: 490 | DH54: 208 | DI54: 333 | DJ54: 666 | DK54: 104 | DL54: 4604 | DM54: 3683 | DN54: 7366 | DO54: 2302 | DP54: 271 | DQ54: 433 | DR54: 867 | DS54: 135 | DV54: 2863
E55: 45 | F55: Meals and Incidentals for Site Visits and M&E | G55: TRAVEL | H55: Field Travel | I55: USAID | J55: 12 | K55: 40 | L55: 5 | M55: /day | N55: =L55*K55*J55 -> 2400 | O55: 0 | P55: =SUM(N55:O55) -> 2400 | Q55: 12 | R55: =K55*$J$6 -> 41.2 | S55: 5 | T55: =Q55*R55*S55 -> 2472 | U55: 0 | V55: =SUM(T55:U55) -> 2472 | W55: 12 | X55: =K55*$J$6*$J$6 -> 42.436 | Y55: 5 | Z55: =W55*X55*Y55 -> 2546.16 | AA55: 0 | AB55: =SUM(Z55:AA55) -> 2546.16 | AC55: 12 | AD55: =K55*$J$6*$J$6*$J$6 -> 43.70908 | AE55: 5 | AF55: =AC55*AD55*AE55 -> 2622.5448 | AG55: 0 | AH55: =SUM(AF55:AG55) -> 2622.5448 | AI55: 12 | AJ55: =K55*$J$6*$J$6*$J$6*$J$6 -> 45.020352 | AK55: 5 | AL55: =AI55*AJ55*AK55 -> 2701.2211 | AM55: 0 | AN55: =SUM(AL55:AM55) -> 2701.2211 | AO55: =N55+T55+Z55+AF55+AL55 -> 12741.926 | AP55: =O55+U55+AA55+AG55+AM55 -> 0 | AQ55: =SUM(AO55:AP55) -> 12741.926 | AR55: 0 | AS55: 0 | AT55: 0 | AU55: 0 | AV55: =AR55+AT55 -> 0 | AW55: =AS55+AU55 -> 0 | AX55: =AV55+AW55 -> 0 | AY55: =AQ55-AX55 -> 12741.926 | AZ55: =AQ55-AR55-AS55-AT55-AU55 -> 12741.926 | BA55: =AY55-AZ55 -> 0 | BC55: 0 | BE55: 0 | BF55: =AA55 -> 0 | BG55: =SUM(BE55:BF55) -> 0 | BH55: Comidas e imprevistos para que el personal local viaje para llevar a cabo actividades de seguimiento y evaluación, incluida la recopilación y verificación de datos. Esta linea no se requiere. | BJ55: 0 | BL55: 0 | BM55: =AG55 -> 0 | BN55: =SUM(BL55:BM55) -> 0 | BP55: 0 | BR55: 0 | BS55: =AM55 -> 0 | BT55: 0 | BV55: 0 | BX55: 0 | BY55: =AS55 -> 0 | BZ55: 0 | CA55: =BR55+BL55+BE55+BX55 -> 0 | CB55: =BS55+BM55+BF55 -> 0 | CC55: =CA55+CB55 -> 0 | CE55: =AV55+CA55 -> 0 | CF55: =AW55+CB55 -> 0 | CG55: =CE55+CF55 -> 0 | CH55: =AO55-CE55 -> 12741.926 | CI55: =AP55-CF55 -> 0 | CJ55: =AQ55-CG55 -> 12741.926 | CK55: =SUM(CM55:ES55) -> -12742 | CL55: =CJ55+CK55 -> -0.074056 | CZ55: -12742
E56: 46 | F56: Lodging for Site Visits and M&E | G56: TRAVEL | H56: Field Travel | I56: USAID | J56: 12 | K56: 80 | L56: 4 | M56: /day | N56: =L56*K56*J56 -> 3840 | O56: 0 | P56: =SUM(N56:O56) -> 3840 | Q56: 12 | R56: =K56*$J$6 -> 82.4 | S56: 4 | T56: =Q56*R56*S56 -> 3955.2 | U56: 0 | V56: =SUM(T56:U56) -> 3955.2 | W56: 12 | X56: =K56*$J$6*$J$6 -> 84.872 | Y56: 4 | Z56: =W56*X56*Y56 -> 4073.856 | AA56: 0 | AB56: =SUM(Z56:AA56) -> 4073.856 | AC56: 12 | AD56: =K56*$J$6*$J$6*$J$6 -> 87.41816 | AE56: 4 | AF56: =AC56*AD56*AE56 -> 4196.0717 | AG56: 0 | AH56: =SUM(AF56:AG56) -> 4196.0717 | AI56: 12 | AJ56: =K56*$J$6*$J$6*$J$6*$J$6 -> 90.040705 | AK56: 4 | AL56: =AI56*AJ56*AK56 -> 4321.9538 | AM56: 0 | AN56: =SUM(AL56:AM56) -> 4321.9538 | AO56: =N56+T56+Z56+AF56+AL56 -> 20387.082 | AP56: =O56+U56+AA56+AG56+AM56 -> 0 | AQ56: =SUM(AO56:AP56) -> 20387.082 | AR56: 0 | AS56: 0 | AT56: 0 | AU56: 0 | AV56: =AR56+AT56 -> 0 | AW56: =AS56+AU56 -> 0 | AX56: =AV56+AW56 -> 0 | AY56: =AQ56-AX56 -> 20387.082 | AZ56: =AQ56-AR56-AS56-AT56-AU56 -> 20387.082 | BA56: =AY56-AZ56 -> 0 | BC56: 0 | BE56: 0 | BF56: =AA56 -> 0 | BG56: =SUM(BE56:BF56) -> 0 | BH56: Alojamiento para personal local para llevar a cabo actividades de seguimiento y evaluación, incluida la recopilación y verificación de datos. Esta linea no se requiere. | BJ56: 0 | BL56: 0 | BM56: =AG56 -> 0 | BN56: =SUM(BL56:BM56) -> 0 | BP56: 0 | BR56: 0 | BS56: =AM56 -> 0 | BT56: =BS56+BR56 -> 0 | BV56: 0 | BX56: 0 | BY56: =AS56 -> 0 | BZ56: =BY56+BX56 -> 0 | CA56: =BR56+BL56+BE56+BX56 -> 0 | CB56: =BS56+BM56+BF56 -> 0 | CC56: =CA56+CB56 -> 0 | CE56: =AV56+CA56 -> 0 | CF56: =AW56+CB56 -> 0 | CG56: =CE56+CF56 -> 0 | CH56: =AO56-CE56 -> 20387.082 | CI56: =AP56-CF56 -> 0 | CJ56: =AQ56-CG56 -> 20387.082 | CK56: =SUM(CM56:ES56) -> -20387 | CL56: =CJ56+CK56 -> 0.0815104 | DA56: -20387
E57: 47 | F57: Other Travel Related Expenses for Site Visits and M&E | G57: TRAVEL | H57: Field Travel | I57: USAID | J57: 12 | K57: 25 | L57: 1 | M57: /trip | N57: =L57*K57*J57 -> 300 | O57: 0 | P57: =SUM(N57:O57) -> 300 | Q57: 12 | R57: =K57*$J$6 -> 25.75 | S57: 1 | T57: =Q57*R57*S57 -> 309 | U57: 0 | V57: =SUM(T57:U57) -> 309 | W57: 12 | X57: =K57*$J$6*$J$6 -> 26.5225 | Y57: 1 | Z57: =W57*X57*Y57 -> 318.27 | AA57: 0 | AB57: =SUM(Z57:AA57) -> 318.27 | AC57: 12 | AD57: =K57*$J$6*$J$6*$J$6 -> 27.318175 | AE57: 1 | AF57: =AC57*AD57*AE57 -> 327.8181 | AG57: 0 | AH57: =SUM(AF57:AG57) -> 327.8181 | AI57: 12 | AJ57: =K57*$J$6*$J$6*$J$6*$J$6 -> 28.13772 | AK57: 1 | AL57: =AI57*AJ57*AK57 -> 337.65264 | AM57: 0 | AN57: =SUM(AL57:AM57) -> 337.65264 | AO57: =N57+T57+Z57+AF57+AL57 -> 1592.7407 | AP57: =O57+U57+AA57+AG57+AM57 -> 0 | AQ57: =SUM(AO57:AP57) -> 1592.7407 | AR57: 0 | AS57: 0 | AT57: 0 | AU57: 0 | AV57: =AR57+AT57 -> 0 | AW57: =AS57+AU57 -> 0 | AX57: =AV57+AW57 -> 0 | AY57: =AQ57-AX57 -> 1592.7407 | AZ57: =AQ57-AR57-AS57-AT57-AU57 -> 1592.7407 | BA57: =AY57-AZ57 -> 0 | BC57: 0 | BE57: 0 | BF57: =AA57 -> 0 | BG57: =SUM(BE57:BF57) -> 0 | BH57: Otros gastos de viaje relacionados con el personal local para llevar a cabo actividades de seguimiento y evaluación, incluida la recopilación y verificación de datos. Esta linea no se requiere. | BJ57: 0 | BL57: 0 | BM57: =AG57 -> 0 | BN57: =SUM(BL57:BM57) -> 0 | BP57: 0 | BR57: 0 | BS57: =AM57 -> 0 | BT57: =BS57+BR57 -> 0 | BV57: 0 | BX57: 0 | BY57: =AS57 -> 0 | BZ57: =BY57+BX57 -> 0 | CA57: =BR57+BL57+BE57+BX57 -> 0 | CB57: =BS57+BM57+BF57 -> 0 | CC57: =CA57+CB57 -> 0 | CE57: =AV57+CA57 -> 0 | CF57: =AW57+CB57 -> 0 | CG57: =CE57+CF57 -> 0 | CH57: =AO57-CE57 -> 1592.7407 | CI57: =AP57-CF57 -> 0 | CJ57: =AQ57-CG57 -> 1592.7407 | CK57: =SUM(CM57:ES57) -> -1593 | CL57: =CJ57+CK57 -> -0.259257 | DB57: -1593
E58: 48 | F58: T.2 Local Travel in Antioquia for Field Staff | CK58: =SUM(CM58:ES58) -> 0 | CL58: =CJ58+CK58 -> 0
E59: 49 | F59: Vehicle Fuel Expense | G59: TRAVEL | H59: Field Travel | I59: USAID | J59: 6 | K59: =300 -> 300 | L59: 1 | M59: /month | N59: =L59*K59*J59 -> 1800 | O59: 0 | P59: =SUM(N59:O59) -> 1800 | Q59: 12 | R59: =K59*$J$7 -> 312 | S59: 1 | T59: =Q59*R59*S59 -> 3744 | U59: 0 | V59: =SUM(T59:U59) -> 3744 | W59: 12 | X59: =K59*$J$7*$J$7 -> 324.48 | Y59: 1 | Z59: =W59*X59*Y59 -> 3893.76 | AA59: 0 | AB59: =SUM(Z59:AA59) -> 3893.76 | AC59: 12 | AD59: =K59*$J$7*$J$7*$J$7 -> 337.4592 | AE59: 1 | AF59: =AC59*AD59*AE59 -> 4049.5104 | AG59: 0 | AH59: =SUM(AF59:AG59) -> 4049.5104 | AI59: 9 | AJ59: =K59*$J$7*$J$7*$J$7*$J$7 -> 350.95757 | AK59: 1 | AL59: =AI59*AJ59*AK59 -> 3158.6181 | AM59: 0 | AN59: =SUM(AL59:AM59) -> 3158.6181 | AO59: =N59+T59+Z59+AF59+AL59 -> 16645.889 | AP59: =O59+U59+AA59+AG59+AM59 -> 0 | AQ59: =SUM(AO59:AP59) -> 16645.889 | AR59: 0 | AS59: 0 | AT59: 0 | AU59: 0 | AV59: =AR59+AT59 -> 0 | AW59: =AS59+AU59 -> 0 | AX59: =AV59+AW59 -> 0 | AY59: =AQ59-AX59 -> 16645.889 | AZ59: =AQ59-AR59-AS59-AT59-AU59 -> 16645.889 | BA59: =AY59-AZ59 -> 0 | BC59: 0 | BE59: 0 | BF59: =AA59 -> 0 | BG59: =SUM(BE59:BF59) -> 0 | BH59: Gastos de combustible vehicular para el vehículo del proyecto. Esta linea no se requiere. | BJ59: 0 | BL59: 0 | BM59: =AG59 -> 0 | BN59: =SUM(BL59:BM59) -> 0 | BP59: 0 | BR59: 0 | BS59: =AM59 -> 0 | BT59: 0 | BV59: 0 | BX59: 0 | BY59: =AS59 -> 0 | BZ59: 0 | CA59: =BR59+BL59+BE59+BX59 -> 0 | CB59: =BS59+BM59+BF59 -> 0 | CC59: =CA59+CB59 -> 0 | CE59: =AV59+CA59 -> 0 | CF59: =AW59+CB59 -> 0 | CG59: =CE59+CF59 -> 0 | CH59: =AO59-CE59 -> 16645.889 | CI59: =AP59-CF59 -> 0 | CJ59: =AQ59-CG59 -> 16645.889 | CK59: =SUM(CM59:ES59) -> -16646 | CL59: =CJ59+CK59 -> -0.111488 | DC59: -16646
E60: 50 | F60: T.3 Travel for Advisory Board Meetings - 2 Annually | CK60: =SUM(CM60:ES60) -> 0 | CL60: =CJ60+CK60 -> 0
E61: 51 | F61: Local Transportation for Advisory Board Meetings | G61: TRAVEL | H61: Field Travel | I61: USAID | J61: =2*2 -> 4 | K61: 80 | L61: 1 | M61: /trip | N61: =L61*K61*J61 -> 320 | O61: 0 | P61: =SUM(N61:O61) -> 320 | Q61: 2 | R61: =K61*$J$7 -> 83.2 | S61: 1 | T61: =Q61*R61*S61 -> 166.4 | U61: 0 | V61: =SUM(T61:U61) -> 166.4 | W61: =2*2 -> 4 | X61: =K61*$J$7*$J$7 -> 86.528 | Y61: 1 | Z61: =W61*X61*Y61 -> 346.112 | AA61: 0 | AB61: =SUM(Z61:AA61) -> 346.112 | AC61: =2*2 -> 4 | AD61: =K61*$J$7*$J$7*$J$7 -> 89.98912 | AE61: 1 | AF61: =AC61*AD61*AE61 -> 359.95648 | AG61: 0 | AH61: =SUM(AF61:AG61) -> 359.95648 | AI61: =2*2 -> 4 | AJ61: =K61*$J$7*$J$7*$J$7*$J$7 -> 93.588685 | AK61: 1 | AL61: =AI61*AJ61*AK61 -> 374.35474 | AM61: 0 | AN61: =SUM(AL61:AM61) -> 374.35474 | AO61: =N61+T61+Z61+AF61+AL61 -> 1566.8232 | AP61: =O61+U61+AA61+AG61+AM61 -> 0 | AQ61: =SUM(AO61:AP61) -> 1566.8232 | AR61: 0 | AS61: 0 | AT61: 0 | AU61: 0 | AV61: =AR61+AT61 -> 0 | AW61: =AS61+AU61 -> 0 | AX61: =AV61+AW61 -> 0 | AY61: =AQ61-AX61 -> 1566.8232 | AZ61: =AQ61-AR61-AS61-AT61-AU61 -> 1566.8232 | BA61: =AY61-AZ61 -> 0 | BC61: 0 | BE61: 0 | BF61: =AA61 -> 0 | BG61: =SUM(BE61:BF61) -> 0 | BH61: Vuelos domésticos locales dentro del país, transporte desde y hacia los aeropuertos y algunos transportes locales para que el personal de ProAntioquia participe en las reuniones de la Junta Asesora de Juntos Aprendemos. Esta linea no se requiere. | BJ61: 0 | BL61: 0 | BM61: =AG61 -> 0 | BN61: =SUM(BL61:BM61) -> 0 | BP61: 0 | BR61: 0 | BS61: =AM61 -> 0 | BT61: 0 | BV61: 0 | BX61: 0 | BY61: =AS61 -> 0 | BZ61: 0 | CA61: =BR61+BL61+BE61+BX61 -> 0 | CB61: =BS61+BM61+BF61 -> 0 | CC61: =CA61+CB61 -> 0 | CE61: =AV61+CA61 -> 0 | CF61: =AW61+CB61 -> 0 | CG61: =CE61+CF61 -> 0 | CH61: =AO61-CE61 -> 1566.8232 | CI61: =AP61-CF61 -> 0 | CJ61: =AQ61-CG61 -> 1566.8232 | CK61: =SUM(CM61:ES61) -> -1567 | CL61: =CJ61+CK61 -> -0.1767808 | DD61: -1567
E62: 52 | F62: Meals and Incidentals for Advisory Board Meetings | G62: TRAVEL | H62: Field Travel | I62: USAID | J62: =2*2 -> 4 | K62: 40 | L62: 2 | M62: /day | N62: =L62*K62*J62 -> 320 | O62: 0 | P62: =SUM(N62:O62) -> 320 | Q62: 2 | R62: =K62*$J$7 -> 41.6 | S62: 2 | T62: =Q62*R62*S62 -> 166.4 | U62: 0 | V62: =SUM(T62:U62) -> 166.4 | W62: =2*2 -> 4 | X62: =K62*$J$7*$J$7 -> 43.264 | Y62: 2 | Z62: =W62*X62*Y62 -> 346.112 | AA62: 0 | AB62: =SUM(Z62:AA62) -> 346.112 | AC62: =2*2 -> 4 | AD62: =K62*$J$7*$J$7*$J$7 -> 44.99456 | AE62: 2 | AF62: =AC62*AD62*AE62 -> 359.95648 | AG62: 0 | AH62: =SUM(AF62:AG62) -> 359.95648 | AI62: =2*2 -> 4 | AJ62: =K62*$J$7*$J$7*$J$7*$J$7 -> 46.794342 | AK62: 2 | AL62: =AI62*AJ62*AK62 -> 374.35474 | AM62: 0 | AN62: =SUM(AL62:AM62) -> 374.35474 | AO62: =N62+T62+Z62+AF62+AL62 -> 1566.8232 | AP62: =O62+U62+AA62+AG62+AM62 -> 0 | AQ62: =SUM(AO62:AP62) -> 1566.8232 | AR62: 0 | AS62: 0 | AT62: 0 | AU62: 0 | AV62: =AR62+AT62 -> 0 | AW62: =AS62+AU62 -> 0 | AX62: =AV62+AW62 -> 0 | AY62: =AQ62-AX62 -> 1566.8232 | AZ62: =AQ62-AR62-AS62-AT62-AU62 -> 1566.8232 | BA62: =AY62-AZ62 -> 0 | BC62: 0 | BE62: 0 | BF62: =AA62 -> 0 | BG62: =SUM(BE62:BF62) -> 0 | BH62: Alimentos y gastos imprevistos para que el personal de ProAntioquia participe en las reuniones de la Junta Asesora de Juntos Aprendemos. Esta linea no se requiere. | BJ62: 0 | BL62: 0 | BM62: =AG62 -> 0 | BN62: =SUM(BL62:BM62) -> 0 | BP62: 0 | BR62: 0 | BS62: =AM62 -> 0 | BT62: 0 | BV62: 0 | BX62: 0 | BY62: =AS62 -> 0 | BZ62: 0 | CA62: =BR62+BL62+BE62+BX62 -> 0 | CB62: =BS62+BM62+BF62 -> 0 | CC62: =CA62+CB62 -> 0 | CE62: =AV62+CA62 -> 0 | CF62: =AW62+CB62 -> 0 | CG62: =CE62+CF62 -> 0 | CH62: =AO62-CE62 -> 1566.8232 | CI62: =AP62-CF62 -> 0 | CJ62: =AQ62-CG62 -> 1566.8232 | CK62: =SUM(CM62:ES62) -> -1567 | CL62: =CJ62+CK62 -> -0.1767808 | DE62: -1567
E63: 53 | F63: Lodging for Advisory Board Meetings | G63: TRAVEL | H63: Field Travel | I63: USAID | J63: =2*2 -> 4 | K63: 80 | L63: 2 | M63: /day | N63: =L63*K63*J63 -> 640 | O63: 0 | P63: =SUM(N63:O63) -> 640 | Q63: 2 | R63: =K63*$J$7 -> 83.2 | S63: 2 | T63: =Q63*R63*S63 -> 332.8 | U63: 0 | V63: =SUM(T63:U63) -> 332.8 | W63: =2*2 -> 4 | X63: =K63*$J$7*$J$7 -> 86.528 | Y63: 2 | Z63: =W63*X63*Y63 -> 692.224 | AA63: 0 | AB63: =SUM(Z63:AA63) -> 692.224 | AC63: =2*2 -> 4 | AD63: =K63*$J$7*$J$7*$J$7 -> 89.98912 | AE63: 2 | AF63: =AC63*AD63*AE63 -> 719.91296 | AG63: 0 | AH63: =SUM(AF63:AG63) -> 719.91296 | AI63: =2*2 -> 4 | AJ63: =K63*$J$7*$J$7*$J$7*$J$7 -> 93.588685 | AK63: 2 | AL63: =AI63*AJ63*AK63 -> 748.70948 | AM63: 0 | AN63: =SUM(AL63:AM63) -> 748.70948 | AO63: =N63+T63+Z63+AF63+AL63 -> 3133.6464 | AP63: =O63+U63+AA63+AG63+AM63 -> 0 | AQ63: =SUM(AO63:AP63) -> 3133.6464 | AR63: 0 | AS63: 0 | AT63: 0 | AU63: 0 | AV63: =AR63+AT63 -> 0 | AW63: =AS63+AU63 -> 0 | AX63: =AV63+AW63 -> 0 | AY63: =AQ63-AX63 -> 3133.6464 | AZ63: =AQ63-AR63-AS63-AT63-AU63 -> 3133.6464 | BA63: =AY63-AZ63 -> 0 | BC63: 0 | BE63: 0 | BF63: =AA63 -> 0 | BG63: =SUM(BE63:BF63) -> 0 | BH63: Alojamiento para que el personal de ProAntioquia participe en las reuniones de la Junta Asesora de Juntos Aprendemos. Esta linea no se requiere. | BJ63: 0 | BL63: 0 | BM63: =AG63 -> 0 | BN63: =SUM(BL63:BM63) -> 0 | BP63: 0 | BR63: 0 | BS63: =AM63 -> 0 | BT63: 0 | BV63: 0 | BX63: 0 | BY63: =AS63 -> 0 | BZ63: 0 | CA63: =BR63+BL63+BE63+BX63 -> 0 | CB63: =BS63+BM63+BF63 -> 0 | CC63: =CA63+CB63 -> 0 | CE63: =AV63+CA63 -> 0 | CF63: =AW63+CB63 -> 0 | CG63: =CE63+CF63 -> 0 | CH63: =AO63-CE63 -> 3133.6464 | CI63: =AP63-CF63 -> 0 | CJ63: =AQ63-CG63 -> 3133.6464 | CK63: =SUM(CM63:ES63) -> -3134 | CL63: =CJ63+CK63 -> -0.3535616 | DF63: -3134
E64: 54 | F64: Other Travel Related Expenses for Advisory Board Meetings | G64: TRAVEL | H64: Field Travel | I64: USAID | J64: =2*2 -> 4 | K64: 25 | L64: 1 | M64: /trip | N64: =L64*K64*J64 -> 100 | O64: 0 | P64: =SUM(N64:O64) -> 100 | Q64: 2 | R64: =K64*$J$7 -> 26 | S64: 1 | T64: =Q64*R64*S64 -> 52 | U64: 0 | V64: =SUM(T64:U64) -> 52 | W64: =2*2 -> 4 | X64: =K64*$J$7*$J$7 -> 27.04 | Y64: 1 | Z64: =W64*X64*Y64 -> 108.16 | AA64: 0 | AB64: =SUM(Z64:AA64) -> 108.16 | AC64: =2*2 -> 4 | AD64: =K64*$J$7*$J$7*$J$7 -> 28.1216 | AE64: 1 | AF64: =AC64*AD64*AE64 -> 112.4864 | AG64: 0 | AH64: =SUM(AF64:AG64) -> 112.4864 | AI64: =2*2 -> 4 | AJ64: =K64*$J$7*$J$7*$J$7*$J$7 -> 29.246464 | AK64: 1 | AL64: =AI64*AJ64*AK64 -> 116.98586 | AM64: 0 | AN64: =SUM(AL64:AM64) -> 116.98586 | AO64: =N64+T64+Z64+AF64+AL64 -> 489.63226 | AP64: =O64+U64+AA64+AG64+AM64 -> 0 | AQ64: =SUM(AO64:AP64) -> 489.63226 | AR64: 0 | AS64: 0 | AT64: 0 | AU64: 0 | AV64: =AR64+AT64 -> 0 | AW64: =AS64+AU64 -> 0 | AX64: =AV64+AW64 -> 0 | AY64: =AQ64-AX64 -> 489.63226 | AZ64: =AQ64-AR64-AS64-AT64-AU64 -> 489.63226 | BA64: =AY64-AZ64 -> 0 | BC64: 0 | BE64: 0 | BF64: =AA64 -> 0 | BG64: =SUM(BE64:BF64) -> 0 | BH64: Otros gastos de viaje relacionados con que el personal de ProAntioquia participe en las reuniones de la Junta Asesora de Juntos Aprendemos. Esta linea no se requiere. | BJ64: 0 | BL64: 0 | BM64: =AG64 -> 0 | BN64: =SUM(BL64:BM64) -> 0 | BP64: 0 | BR64: 0 | BS64: =AM64 -> 0 | BT64: 0 | BV64: 0 | BX64: 0 | BY64: =AS64 -> 0 | BZ64: 0 | CA64: =BR64+BL64+BE64+BX64 -> 0 | CB64: =BS64+BM64+BF64 -> 0 | CC64: =CA64+CB64 -> 0 | CE64: =AV64+CA64 -> 0 | CF64: =AW64+CB64 -> 0 | CG64: =CE64+CF64 -> 0 | CH64: =AO64-CE64 -> 489.63226 | CI64: =AP64-CF64 -> 0 | CJ64: =AQ64-CG64 -> 489.63226 | CK64: =SUM(CM64:ES64) -> -490 | CL64: =CJ64+CK64 -> -0.367744 | DG64: -490
E65: 55 | F65: T.4 Travel for Annual Forums for Education Observatories | CK65: =SUM(CM65:ES65) -> 0 | CL65: =CJ65+CK65 -> 0
E66: 56 | F66: Local Transportation for Annual Forums | G66: TRAVEL | H66: Field Travel | I66: USAID | J66: 2 | K66: 50 | L66: 1 | M66: /trip | N66: =L66*K66*J66 -> 100 | O66: 0 | P66: =SUM(N66:O66) -> 100 | Q66: 0 | R66: =K66*$J$7 -> 52 | S66: 1 | T66: =Q66*R66*S66 -> 0 | U66: 0 | V66: =SUM(T66:U66) -> 0 | W66: 2 | X66: =K66*$J$7*$J$7 -> 54.08 | Y66: 1 | Z66: =W66*X66*Y66 -> 108.16 | AA66: 0 | AB66: =SUM(Z66:AA66) -> 108.16 | AC66: 0 | AD66: =K66*$J$7*$J$7*$J$7 -> 56.2432 | AE66: 1 | AF66: =AC66*AD66*AE66 -> 0 | AG66: 0 | AH66: =SUM(AF66:AG66) -> 0 | AI66: 0 | AJ66: =K66*$J$7*$J$7*$J$7*$J$7 -> 58.492928 | AK66: 1 | AL66: =AI66*AJ66*AK66 -> 0 | AM66: 0 | AN66: =SUM(AL66:AM66) -> 0 | AO66: =N66+T66+Z66+AF66+AL66 -> 208.16 | AP66: =O66+U66+AA66+AG66+AM66 -> 0 | AQ66: =SUM(AO66:AP66) -> 208.16 | AR66: 0 | AS66: 0 | AT66: 0 | AU66: 0 | AV66: =AR66+AT66 -> 0 | AW66: =AS66+AU66 -> 0 | AX66: =AV66+AW66 -> 0 | AY66: =AQ66-AX66 -> 208.16 | AZ66: =AQ66-AR66-AS66-AT66-AU66 -> 208.16 | BA66: =AY66-AZ66 -> 0 | BC66: 0 | BE66: 0 | BF66: =AA66 -> 0 | BG66: =SUM(BE66:BF66) -> 0 | BH66: Vuelos domésticos locales dentro del país, transporte desde y hacia los aeropuertos y algunos transportes locales para que el personal de ProAntioquia participe en los Foros Anuales Juntos Aprendemos para observatorios educativos. Esta linea no se requiere. | BJ66: 0 | BL66: 0 | BM66: =AG66 -> 0 | BN66: =SUM(BL66:BM66) -> 0 | BP66: 0 | BR66: 0 | BS66: =AM66 -> 0 | BT66: 0 | BV66: 0 | BX66: 0 | BY66: =AS66 -> 0 | BZ66: 0 | CA66: =BR66+BL66+BE66+BX66 -> 0 | CB66: =BS66+BM66+BF66 -> 0 | CC66: =CA66+CB66 -> 0 | CE66: =AV66+CA66 -> 0 | CF66: =AW66+CB66 -> 0 | CG66: =CE66+CF66 -> 0 | CH66: =AO66-CE66 -> 208.16 | CI66: =AP66-CF66 -> 0 | CJ66: =AQ66-CG66 -> 208.16 | CK66: =SUM(CM66:ES66) -> -208 | CL66: =CJ66+CK66 -> 0.16 | DH66: -208
E67: 57 | F67: Meals and Incidentals for Annual Forums | G67: TRAVEL | H67: Field Travel | I67: USAID | J67: 2 | K67: 40 | L67: 2 | M67: /day | N67: =L67*K67*J67 -> 160 | O67: 0 | P67: =SUM(N67:O67) -> 160 | Q67: 0 | R67: =K67*$J$7 -> 41.6 | S67: 2 | T67: =Q67*R67*S67 -> 0 | U67: 0 | V67: =SUM(T67:U67) -> 0 | W67: 2 | X67: =K67*$J$7*$J$7 -> 43.264 | Y67: 2 | Z67: =W67*X67*Y67 -> 173.056 | AA67: 0 | AB67: =SUM(Z67:AA67) -> 173.056 | AC67: 0 | AD67: =K67*$J$7*$J$7*$J$7 -> 44.99456 | AE67: 2 | AF67: =AC67*AD67*AE67 -> 0 | AG67: 0 | AH67: =SUM(AF67:AG67) -> 0 | AI67: 0 | AJ67: =K67*$J$7*$J$7*$J$7*$J$7 -> 46.794342 | AK67: 2 | AL67: =AI67*AJ67*AK67 -> 0 | AM67: 0 | AN67: =SUM(AL67:AM67) -> 0 | AO67: =N67+T67+Z67+AF67+AL67 -> 333.056 | AP67: =O67+U67+AA67+AG67+AM67 -> 0 | AQ67: =SUM(AO67:AP67) -> 333.056 | AR67: 0 | AS67: 0 | AT67: 0 | AU67: 0 | AV67: =AR67+AT67 -> 0 | AW67: =AS67+AU67 -> 0 | AX67: =AV67+AW67 -> 0 | AY67: =AQ67-AX67 -> 333.056 | AZ67: =AQ67-AR67-AS67-AT67-AU67 -> 333.056 | BA67: =AY67-AZ67 -> 0 | BC67: 0 | BE67: 0 | BF67: =AA67 -> 0 | BG67: =SUM(BE67:BF67) -> 0 | BH67: Alimentos y gastos imprevistos para que el personal de ProAntioquia participe en los Foros Anuales Juntos Aprendemos para observatorios educativos. Esta linea no se requiere. | BJ67: 0 | BL67: 0 | BM67: =AG67 -> 0 | BN67: =SUM(BL67:BM67) -> 0 | BP67: 0 | BR67: 0 | BS67: =AM67 -> 0 | BT67: 0 | BV67: 0 | BX67: 0 | BY67: =AS67 -> 0 | BZ67: 0 | CA67: =BR67+BL67+BE67+BX67 -> 0 | CB67: =BS67+BM67+BF67 -> 0 | CC67: =BT67+BN67+BG67 -> 0 | CE67: =AV67+CA67 -> 0 | CF67: =AW67+CB67 -> 0 | CG67: =CE67+CF67 -> 0 | CH67: =AO67-CE67 -> 333.056 | CI67: =AP67-CF67 -> 0 | CJ67: =AQ67-CG67 -> 333.056 | CK67: =SUM(CM67:ES67) -> -333 | CL67: =CJ67+CK67 -> 0.056 | DI67: -333
E68: 58 | F68: Lodging for Annual Forums | G68: TRAVEL | H68: Field Travel | I68: USAID | J68: 2 | K68: 80 | L68: 2 | M68: /day | N68: =L68*K68*J68 -> 320 | O68: 0 | P68: =SUM(N68:O68) -> 320 | Q68: 0 | R68: =K68*$J$7 -> 83.2 | S68: 2 | T68: =Q68*R68*S68 -> 0 | U68: 0 | V68: =SUM(T68:U68) -> 0 | W68: 2 | X68: =K68*$J$7*$J$7 -> 86.528 | Y68: 2 | Z68: =W68*X68*Y68 -> 346.112 | AA68: 0 | AB68: =SUM(Z68:AA68) -> 346.112 | AC68: 0 | AD68: =K68*$J$7*$J$7*$J$7 -> 89.98912 | AE68: 2 | AF68: =AC68*AD68*AE68 -> 0 | AG68: 0 | AH68: =SUM(AF68:AG68) -> 0 | AI68: 0 | AJ68: =K68*$J$7*$J$7*$J$7*$J$7 -> 93.588685 | AK68: 2 | AL68: =AI68*AJ68*AK68 -> 0 | AM68: 0 | AN68: =SUM(AL68:AM68) -> 0 | AO68: =N68+T68+Z68+AF68+AL68 -> 666.112 | AP68: =O68+U68+AA68+AG68+AM68 -> 0 | AQ68: =SUM(AO68:AP68) -> 666.112 | AR68: 0 | AS68: 0 | AT68: 0 | AU68: 0 | AV68: =AR68+AT68 -> 0 | AW68: =AS68+AU68 -> 0 | AX68: =AV68+AW68 -> 0 | AY68: =AQ68-AX68 -> 666.112 | AZ68: =AQ68-AR68-AS68-AT68-AU68 -> 666.112 | BA68: =AY68-AZ68 -> 0 | BC68: 0 | BE68: 0 | BF68: =AA68 -> 0 | BG68: =SUM(BE68:BF68) -> 0 | BH68: Alojamiento para que el personal de ProAntioquia participe en los Foros Anuales Juntos Aprendemos para observatorios educativos. Esta linea no se requiere. | BJ68: 0 | BL68: 0 | BM68: =AG68 -> 0 | BN68: =SUM(BL68:BM68) -> 0 | BP68: 0 | BR68: 0 | BS68: =AM68 -> 0 | BT68: 0 | BV68: 0 | BX68: 0 | BY68: =AS68 -> 0 | BZ68: 0 | CA68: =BR68+BL68+BE68+BX68 -> 0 | CB68: =BS68+BM68+BF68 -> 0 | CC68: =BT68+BN68+BG68 -> 0 | CE68: =AV68+CA68 -> 0 | CF68: =AW68+CB68 -> 0 | CG68: =CE68+CF68 -> 0 | CH68: =AO68-CE68 -> 666.112 | CI68: =AP68-CF68 -> 0 | CJ68: =AQ68-CG68 -> 666.112 | CK68: =SUM(CM68:ES68) -> -666 | CL68: =CJ68+CK68 -> 0.112 | DJ68: -666
E69: 59 | F69: Other Travel Related Expenses for Annual Forums | G69: TRAVEL | H69: Field Travel | I69: USAID | J69: 2 | K69: 25 | L69: 1 | M69: /trip | N69: =L69*K69*J69 -> 50 | O69: 0 | P69: =SUM(N69:O69) -> 50 | Q69: 0 | R69: =K69*$J$7 -> 26 | S69: 1 | T69: =Q69*R69*S69 -> 0 | U69: 0 | V69: =SUM(T69:U69) -> 0 | W69: 2 | X69: =K69*$J$7*$J$7 -> 27.04 | Y69: 1 | Z69: =W69*X69*Y69 -> 54.08 | AA69: 0 | AB69: =SUM(Z69:AA69) -> 54.08 | AC69: 0 | AD69: =K69*$J$7*$J$7*$J$7 -> 28.1216 | AE69: 1 | AF69: =AC69*AD69*AE69 -> 0 | AG69: 0 | AH69: =SUM(AF69:AG69) -> 0 | AI69: 0 | AJ69: =K69*$J$7*$J$7*$J$7*$J$7 -> 29.246464 | AK69: 1 | AL69: =AI69*AJ69*AK69 -> 0 | AM69: 0 | AN69: =SUM(AL69:AM69) -> 0 | AO69: =N69+T69+Z69+AF69+AL69 -> 104.08 | AP69: =O69+U69+AA69+AG69+AM69 -> 0 | AQ69: =SUM(AO69:AP69) -> 104.08 | AR69: 0 | AS69: 0 | AT69: 0 | AU69: 0 | AV69: =AR69+AT69 -> 0 | AW69: =AS69+AU69 -> 0 | AX69: =AV69+AW69 -> 0 | AY69: =AQ69-AX69 -> 104.08 | AZ69: =AQ69-AR69-AS69-AT69-AU69 -> 104.08 | BA69: =AY69-AZ69 -> 0 | BC69: 0 | BE69: 0 | BF69: =AA69 -> 0 | BG69: =SUM(BE69:BF69) -> 0 | BH69: Otros gastos de viaje relacionados a que el personal de ProAntioquia participe en los Foros Anuales Juntos Aprendemos para observatorios educativos. Esta linea no se requiere. | BJ69: 0 | BL69: 0 | BM69: =AG69 -> 0 | BN69: =SUM(BL69:BM69) -> 0 | BP69: 0 | BR69: 0 | BS69: =AM69 -> 0 | BT69: 0 | BV69: 0 | BX69: 0 | BY69: =AS69 -> 0 | BZ69: 0 | CA69: =BR69+BL69+BE69+BX69 -> 0 | CB69: =BS69+BM69+BF69 -> 0 | CC69: =BT69+BN69+BG69 -> 0 | CE69: =AV69+CA69 -> 0 | CF69: =AW69+CB69 -> 0 | CG69: =CE69+CF69 -> 0 | CH69: =AO69-CE69 -> 104.08 | CI69: =AP69-CF69 -> 0 | CJ69: =AQ69-CG69 -> 104.08 | CK69: =SUM(CM69:ES69) -> -104 | CL69: =CJ69+CK69 -> 0.08 | DK69: -104
E70: 60 | F70: T.5 Travel to SMT In-Person Meetings in Bogota | CK70: =SUM(CM70:ES70) -> 0 | CL70: =CJ70+CK70 -> 0
E71: 61 | F71: Local Transportation for SMT Meetings | G71: TRAVEL | H71: Field Travel | I71: USAID | J71: 17 | K71: 50 | L71: 1 | M71: /trip | N71: =L71*K71*J71 -> 850 | O71: 0 | P71: =SUM(N71:O71) -> 850 | Q71: 17 | R71: =K71*$J$7 -> 52 | S71: 1 | T71: =Q71*R71*S71 -> 884 | U71: 0 | V71: =SUM(T71:U71) -> 884 | W71: 17 | X71: =K71*$J$7*$J$7 -> 54.08 | Y71: 1 | Z71: =W71*X71*Y71 -> 919.36 | AA71: 0 | AB71: =SUM(Z71:AA71) -> 919.36 | AC71: 17 | AD71: =K71*$J$7*$J$7*$J$7 -> 56.2432 | AE71: 1 | AF71: =AC71*AD71*AE71 -> 956.1344 | AG71: 0 | AH71: =SUM(AF71:AG71) -> 956.1344 | AI71: 17 | AJ71: =K71*$J$7*$J$7*$J$7*$J$7 -> 58.492928 | AK71: 1 | AL71: =AI71*AJ71*AK71 -> 994.37978 | AM71: 0 | AN71: =SUM(AL71:AM71) -> 994.37978 | AO71: =N71+T71+Z71+AF71+AL71 -> 4603.8742 | AP71: =O71+U71+AA71+AG71+AM71 -> 0 | AQ71: =SUM(AO71:AP71) -> 4603.8742 | AR71: 0 | AS71: 0 | AT71: 0 | AU71: 0 | AV71: =AR71+AT71 -> 0 | AW71: =AS71+AU71 -> 0 | AX71: =AV71+AW71 -> 0 | AY71: =AQ71-AX71 -> 4603.8742 | AZ71: =AQ71-AR71-AS71-AT71-AU71 -> 4603.8742 | BA71: =AY71-AZ71 -> 0 | BC71: 0 | BE71: 0 | BF71: =AA71 -> 0 | BG71: =SUM(BE71:BF71) -> 0 | BH71: Vuelos domésticos locales en el país, transporte desde y hacia los aeropuertos y algunos transportes locales para que el personal de ProAntioquia participe en las reuniones presenciales del SMT en Bogotá.Esta linea no se requiere. | BJ71: 0 | BL71: 0 | BM71: =AG71 -> 0 | BN71: =SUM(BL71:BM71) -> 0 | BP71: 0 | BR71: 0 | BS71: =AM71 -> 0 | BT71: 0 | BV71: 0 | BX71: 0 | BY71: =AS71 -> 0 | BZ71: 0 | CA71: =BR71+BL71+BE71+BX71 -> 0 | CB71: =BS71+BM71+BF71 -> 0 | CC71: =BT71+BN71+BG71 -> 0 | CE71: =AV71+CA71 -> 0 | CF71: =AW71+CB71 -> 0 | CG71: =CE71+CF71 -> 0 | CH71: =AO71-CE71 -> 4603.8742 | CI71: =AP71-CF71 -> 0 | CJ71: =AQ71-CG71 -> 4603.8742 | CK71: =SUM(CM71:ES71) -> -4604 | CL71: =CJ71+CK71 -> -0.125824 | DL71: -4604
E72: 62 | F72: Meals and Incidentals for SMT Meetings | G72: TRAVEL | H72: Field Travel | I72: USAID | J72: 17 | K72: 40 | L72: 1 | M72: /day | N72: =L72*K72*J72 -> 680 | O72: 0 | P72: =SUM(N72:O72) -> 680 | Q72: 17 | R72: =K72*$J$7 -> 41.6 | S72: 1 | T72: =Q72*R72*S72 -> 707.2 | U72: 0 | V72: =SUM(T72:U72) -> 707.2 | W72: 17 | X72: =K72*$J$7*$J$7 -> 43.264 | Y72: 1 | Z72: =W72*X72*Y72 -> 735.488 | AA72: 0 | AB72: =SUM(Z72:AA72) -> 735.488 | AC72: 17 | AD72: =K72*$J$7*$J$7*$J$7 -> 44.99456 | AE72: 1 | AF72: =AC72*AD72*AE72 -> 764.90752 | AG72: 0 | AH72: =SUM(AF72:AG72) -> 764.90752 | AI72: 17 | AJ72: =K72*$J$7*$J$7*$J$7*$J$7 -> 46.794342 | AK72: 1 | AL72: =AI72*AJ72*AK72 -> 795.50382 | AM72: 0 | AN72: =SUM(AL72:AM72) -> 795.50382 | AO72: =N72+T72+Z72+AF72+AL72 -> 3683.0993 | AP72: =O72+U72+AA72+AG72+AM72 -> 0 | AQ72: =SUM(AO72:AP72) -> 3683.0993 | AR72: 0 | AS72: 0 | AT72: 0 | AU72: 0 | AV72: =AR72+AT72 -> 0 | AW72: =AS72+AU72 -> 0 | AX72: =AV72+AW72 -> 0 | AY72: =AQ72-AX72 -> 3683.0993 | AZ72: =AQ72-AR72-AS72-AT72-AU72 -> 3683.0993 | BA72: =AY72-AZ72 -> 0 | BC72: 0 | BE72: 0 | BF72: =AA72 -> 0 | BG72: =SUM(BE72:BF72) -> 0 | BH72: Alimentos y gastos imprevistos para que el personal de ProAntioquia participe en las reuniones presenciales del SMT en Bogotá.Esta linea no se requiere. | BJ72: 0 | BL72: 0 | BM72: =AG72 -> 0 | BN72: =SUM(BL72:BM72) -> 0 | BP72: 0 | BR72: 0 | BS72: =AM72 -> 0 | BT72: 0 | BV72: 0 | BX72: 0 | BY72: =AS72 -> 0 | BZ72: 0 | CA72: =BR72+BL72+BE72+BX72 -> 0 | CB72: =BS72+BM72+BF72 -> 0 | CC72: =BT72+BN72+BG72 -> 0 | CE72: =AV72+CA72 -> 0 | CF72: =AW72+CB72 -> 0 | CG72: =CE72+CF72 -> 0 | CH72: =AO72-CE72 -> 3683.0993 | CI72: =AP72-CF72 -> 0 | CJ72: =AQ72-CG72 -> 3683.0993 | CK72: =SUM(CM72:ES72) -> -3683 | CL72: =CJ72+CK72 -> 0.0993408 | DM72: -3683
E73: 63 | F73: Lodging for SMT Meetings | G73: TRAVEL | H73: Field Travel | I73: USAID | J73: 17 | K73: 80 | L73: 1 | M73: /day | N73: =L73*K73*J73 -> 1360 | O73: 0 | P73: =SUM(N73:O73) -> 1360 | Q73: 17 | R73: =K73*$J$7 -> 83.2 | S73: 1 | T73: =Q73*R73*S73 -> 1414.4 | U73: 0 | V73: =SUM(T73:U73) -> 1414.4 | W73: 17 | X73: =K73*$J$7*$J$7 -> 86.528 | Y73: 1 | Z73: =W73*X73*Y73 -> 1470.976 | AA73: 0 | AB73: =SUM(Z73:AA73) -> 1470.976 | AC73: 17 | AD73: =K73*$J$7*$J$7*$J$7 -> 89.98912 | AE73: 1 | AF73: =AC73*AD73*AE73 -> 1529.815 | AG73: 0 | AH73: =SUM(AF73:AG73) -> 1529.815 | AI73: 17 | AJ73: =K73*$J$7*$J$7*$J$7*$J$7 -> 93.588685 | AK73: 1 | AL73: =AI73*AJ73*AK73 -> 1591.0076 | AM73: 0 | AN73: =SUM(AL73:AM73) -> 1591.0076 | AO73: =N73+T73+Z73+AF73+AL73 -> 7366.1987 | AP73: =O73+U73+AA73+AG73+AM73 -> 0 | AQ73: =SUM(AO73:AP73) -> 7366.1987 | AR73: 0 | AS73: 0 | AT73: 0 | AU73: 0 | AV73: =AR73+AT73 -> 0 | AW73: =AS73+AU73 -> 0 | AX73: =AV73+AW73 -> 0 | AY73: =AQ73-AX73 -> 7366.1987 | AZ73: =AQ73-AR73-AS73-AT73-AU73 -> 7366.1987 | BA73: =AY73-AZ73 -> 0 | BC73: 0 | BE73: 0 | BF73: =AA73 -> 0 | BG73: =SUM(BE73:BF73) -> 0 | BH73: Alojamiento para que el personal de ProAntioquia participe en las reuniones presenciales del SMT en Bogotá.Esta linea no se requiere. | BJ73: 0 | BL73: 0 | BM73: =AG73 -> 0 | BN73: =SUM(BL73:BM73) -> 0 | BP73: 0 | BR73: 0 | BS73: =AM73 -> 0 | BT73: 0 | BV73: 0 | BX73: 0 | BY73: =AS73 -> 0 | BZ73: 0 | CA73: =BR73+BL73+BE73+BX73 -> 0 | CB73: =BS73+BM73+BF73 -> 0 | CC73: =BT73+BN73+BG73 -> 0 | CE73: =AV73+CA73 -> 0 | CF73: =AW73+CB73 -> 0 | CG73: =CE73+CF73 -> 0 | CH73: =AO73-CE73 -> 7366.1987 | CI73: =AP73-CF73 -> 0 | CJ73: =AQ73-CG73 -> 7366.1987 | CK73: =SUM(CM73:ES73) -> -7366 | CL73: =CJ73+CK73 -> 0.1986816 | DN73: -7366
E74: 64 | F74: Other Travel Related Expenses for SMT Meetings | G74: TRAVEL | H74: Field Travel | I74: USAID | J74: 17 | K74: 25 | L74: 1 | M74: /trip | N74: =L74*K74*J74 -> 425 | O74: 0 | P74: =SUM(N74:O74) -> 425 | Q74: 17 | R74: =K74*$J$7 -> 26 | S74: 1 | T74: =Q74*R74*S74 -> 442 | U74: 0 | V74: =SUM(T74:U74) -> 442 | W74: 17 | X74: =K74*$J$7*$J$7 -> 27.04 | Y74: 1 | Z74: =W74*X74*Y74 -> 459.68 | AA74: 0 | AB74: =SUM(Z74:AA74) -> 459.68 | AC74: 17 | AD74: =K74*$J$7*$J$7*$J$7 -> 28.1216 | AE74: 1 | AF74: =AC74*AD74*AE74 -> 478.0672 | AG74: 0 | AH74: =SUM(AF74:AG74) -> 478.0672 | AI74: 17 | AJ74: =K74*$J$7*$J$7*$J$7*$J$7 -> 29.246464 | AK74: 1 | AL74: =AI74*AJ74*AK74 -> 497.18989 | AM74: 0 | AN74: =SUM(AL74:AM74) -> 497.18989 | AO74: =N74+T74+Z74+AF74+AL74 -> 2301.9371 | AP74: =O74+U74+AA74+AG74+AM74 -> 0 | AQ74: =SUM(AO74:AP74) -> 2301.9371 | AR74: 0 | AS74: 0 | AT74: 0 | AU74: 0 | AV74: =AR74+AT74 -> 0 | AW74: =AS74+AU74 -> 0 | AX74: =AV74+AW74 -> 0 | AY74: =AQ74-AX74 -> 2301.9371 | AZ74: =AQ74-AR74-AS74-AT74-AU74 -> 2301.9371 | BA74: =AY74-AZ74 -> 0 | BC74: 0 | BE74: 0 | BF74: =AA74 -> 0 | BG74: =SUM(BE74:BF74) -> 0 | BH74: Otros gastos de viaje relacionados con que el personal de ProAntioquia participe en las reuniones presenciales del SMT en Bogotá. Esta linea no se requiere. | BJ74: 0 | BL74: 0 | BM74: =AG74 -> 0 | BN74: =SUM(BL74:BM74) -> 0 | BP74: 0 | BR74: 0 | BS74: =AM74 -> 0 | BT74: 0 | BV74: 0 | BX74: 0 | BY74: =AS74 -> 0 | BZ74: 0 | CA74: =BR74+BL74+BE74+BX74 -> 0 | CB74: =BS74+BM74+BF74 -> 0 | CC74: =BT74+BN74+BG74 -> 0 | CE74: =AV74+CA74 -> 0 | CF74: =AW74+CB74 -> 0 | CG74: =CE74+CF74 -> 0 | CH74: =AO74-CE74 -> 2301.9371 | CI74: =AP74-CF74 -> 0 | CJ74: =AQ74-CG74 -> 2301.9371 | CK74: =SUM(CM74:ES74) -> -2302 | CL74: =CJ74+CK74 -> -0.062912 | DO74: -2302
E75: 65 | F75: T.6 Travel to Annual In-Person Steering Committee Meeting in Bogota | CK75: =SUM(CM75:ES75) -> 0 | CL75: =CJ75+CK75 -> 0
E76: 66 | F76: Local Transportation for Steering Committee Meeting | G76: TRAVEL | H76: Field Travel | I76: USAID | J76: 1 | K76: 50 | L76: 1 | M76: /trip | N76: =L76*K76*J76 -> 50 | O76: 0 | P76: =SUM(N76:O76) -> 50 | Q76: 1 | R76: =K76*$J$7 -> 52 | S76: 1 | T76: =Q76*R76*S76 -> 52 | U76: 0 | V76: =SUM(T76:U76) -> 52 | W76: 1 | X76: =K76*$J$7*$J$7 -> 54.08 | Y76: 1 | Z76: =W76*X76*Y76 -> 54.08 | AA76: 0 | AB76: =SUM(Z76:AA76) -> 54.08 | AC76: 1 | AD76: =K76*$J$7*$J$7*$J$7 -> 56.2432 | AE76: 1 | AF76: =AC76*AD76*AE76 -> 56.2432 | AG76: 0 | AH76: =SUM(AF76:AG76) -> 56.2432 | AI76: 1 | AJ76: =K76*$J$7*$J$7*$J$7*$J$7 -> 58.492928 | AK76: 1 | AL76: =AI76*AJ76*AK76 -> 58.492928 | AM76: 0 | AN76: =SUM(AL76:AM76) -> 58.492928 | AO76: =N76+T76+Z76+AF76+AL76 -> 270.81613 | AP76: =O76+U76+AA76+AG76+AM76 -> 0 | AQ76: =SUM(AO76:AP76) -> 270.81613 | AR76: 0 | AS76: 0 | AT76: 0 | AU76: 0 | AV76: =AR76+AT76 -> 0 | AW76: =AS76+AU76 -> 0 | AX76: =AV76+AW76 -> 0 | AY76: =AQ76-AX76 -> 270.81613 | AZ76: =AQ76-AR76-AS76-AT76-AU76 -> 270.81613 | BA76: =AY76-AZ76 -> 0 | BC76: 0 | BE76: 0 | BF76: =AA76 -> 0 | BG76: =SUM(BE76:BF76) -> 0 | BH76: Vuelos domésticos locales en el país, transporte desde y hacia los aeropuertos y algunos transportes locales para que el personal de ProAntioquia participe en las reuniones anuales presenciales del Comité Directivo de Juntos Aprendemos en Bogotá. Esta linea no se requiere. | BJ76: 0 | BL76: 0 | BM76: =AG76 -> 0 | BN76: =SUM(BL76:BM76) -> 0 | BP76: 0 | BR76: 0 | BS76: =AM76 -> 0 | BT76: 0 | BV76: 0 | BX76: 0 | BY76: =AS76 -> 0 | BZ76: 0 | CA76: =BR76+BL76+BE76+BX76 -> 0 | CB76: =BS76+BM76+BF76 -> 0 | CC76: =BT76+BN76+BG76 -> 0 | CE76: =AV76+CA76 -> 0 | CF76: =AW76+CB76 -> 0 | CG76: =CE76+CF76 -> 0 | CH76: =AO76-CE76 -> 270.81613 | CI76: =AP76-CF76 -> 0 | CJ76: =AQ76-CG76 -> 270.81613 | CK76: =SUM(CM76:ES76) -> -271 | CL76: =CJ76+CK76 -> -0.183872 | DP76: -271
E77: 67 | F77: Meals and Incidentals for Steering Committee Meeting | G77: TRAVEL | H77: Field Travel | I77: USAID | J77: 1 | K77: 40 | L77: 2 | M77: /day | N77: =L77*K77*J77 -> 80 | O77: 0 | P77: =SUM(N77:O77) -> 80 | Q77: 1 | R77: =K77*$J$7 -> 41.6 | S77: 2 | T77: =Q77*R77*S77 -> 83.2 | U77: 0 | V77: =SUM(T77:U77) -> 83.2 | W77: 1 | X77: =K77*$J$7*$J$7 -> 43.264 | Y77: 2 | Z77: =W77*X77*Y77 -> 86.528 | AA77: 0 | AB77: =SUM(Z77:AA77) -> 86.528 | AC77: 1 | AD77: =K77*$J$7*$J$7*$J$7 -> 44.99456 | AE77: 2 | AF77: =AC77*AD77*AE77 -> 89.98912 | AG77: 0 | AH77: =SUM(AF77:AG77) -> 89.98912 | AI77: 1 | AJ77: =K77*$J$7*$J$7*$J$7*$J$7 -> 46.794342 | AK77: 2 | AL77: =AI77*AJ77*AK77 -> 93.588685 | AM77: 0 | AN77: =SUM(AL77:AM77) -> 93.588685 | AO77: =N77+T77+Z77+AF77+AL77 -> 433.3058 | AP77: =O77+U77+AA77+AG77+AM77 -> 0 | AQ77: =SUM(AO77:AP77) -> 433.3058 | AS77: 0 | AU77: 0 | AV77: =AR77+AT77 -> 0 | AW77: =AS77+AU77 -> 0 | AX77: =AV77+AW77 -> 0 | AY77: =AQ77-AX77 -> 433.3058 | AZ77: =AQ77-AR77-AS77-AT77-AU77 -> 433.3058 | BA77: =AY77-AZ77 -> 0 | BC77: 0 | BE77: 0 | BF77: =AA77 -> 0 | BG77: =SUM(BE77:BF77) -> 0 | BH77: Alimentos y gastos imprevistos para que el personal de ProAntioquia participe en las reuniones anuales presenciales del Comité Directivo de Juntos Aprendemos en Bogotá. Esta linea no se requiere. | BJ77: 0 | BL77: 0 | BM77: =AG77 -> 0 | BN77: =SUM(BL77:BM77) -> 0 | BP77: 0 | BR77: 0 | BS77: =AM77 -> 0 | BT77: 0 | BV77: 0 | BX77: 0 | BY77: =AS77 -> 0 | BZ77: 0 | CA77: =BR77+BL77+BE77+BX77 -> 0 | CB77: =BS77+BM77+BF77 -> 0 | CC77: =BT77+BN77+BG77 -> 0 | CE77: =AV77+CA77 -> 0 | CF77: =AW77+CB77 -> 0 | CG77: =CE77+CF77 -> 0 | CH77: =AO77-CE77 -> 433.3058 | CI77: =AP77-CF77 -> 0 | CJ77: =AQ77-CG77 -> 433.3058 | CK77: =SUM(CM77:ES77) -> -433 | CL77: =CJ77+CK77 -> 0.3058048 | DQ77: -433
E78: 68 | F78: Lodging for Steering Committee Meeting | G78: TRAVEL | H78: Field Travel | I78: USAID | J78: 1 | K78: 80 | L78: 2 | M78: /day | N78: =L78*K78*J78 -> 160 | O78: 0 | P78: =SUM(N78:O78) -> 160 | Q78: 1 | R78: =K78*$J$7 -> 83.2 | S78: 2 | T78: =Q78*R78*S78 -> 166.4 | U78: 0 | V78: =SUM(T78:U78) -> 166.4 | W78: 1 | X78: =K78*$J$7*$J$7 -> 86.528 | Y78: 2 | Z78: =W78*X78*Y78 -> 173.056 | AA78: 0 | AB78: =SUM(Z78:AA78) -> 173.056 | AC78: 1 | AD78: =K78*$J$7*$J$7*$J$7 -> 89.98912 | AE78: 2 | AF78: =AC78*AD78*AE78 -> 179.97824 | AG78: 0 | AH78: =SUM(AF78:AG78) -> 179.97824 | AI78: 1 | AJ78: =K78*$J$7*$J$7*$J$7*$J$7 -> 93.588685 | AK78: 2 | AL78: =AI78*AJ78*AK78 -> 187.17737 | AM78: 0 | AN78: =SUM(AL78:AM78) -> 187.17737 | AO78: =N78+T78+Z78+AF78+AL78 -> 866.61161 | AP78: =O78+U78+AA78+AG78+AM78 -> 0 | AQ78: =SUM(AO78:AP78) -> 866.61161 | AS78: 0 | AU78: 0 | AV78: =AR78+AT78 -> 0 | AW78: =AS78+AU78 -> 0 | AX78: =AV78+AW78 -> 0 | AY78: =AQ78-AX78 -> 866.61161 | AZ78: =AQ78-AR78-AS78-AT78-AU78 -> 866.61161 | BA78: =AY78-AZ78 -> 0 | BC78: 0 | BE78: 0 | BF78: =AA78 -> 0 | BG78: =SUM(BE78:BF78) -> 0 | BH78: Alojamiento para que el personal de ProAntioquia participe en las reuniones anuales presenciales del Comité Directivo de Juntos Aprendemos en Bogotá. Esta linea no se requiere. | BJ78: 0 | BL78: 0 | BM78: =AG78 -> 0 | BN78: =SUM(BL78:BM78) -> 0 | BP78: 0 | BR78: 0 | BS78: =AM78 -> 0 | BT78: 0 | BV78: 0 | BX78: 0 | BY78: =AS78 -> 0 | BZ78: 0 | CA78: =BR78+BL78+BE78+BX78 -> 0 | CB78: =BS78+BM78+BF78 -> 0 | CC78: =BT78+BN78+BG78 -> 0 | CE78: =AV78+CA78 -> 0 | CF78: =AW78+CB78 -> 0 | CG78: =CE78+CF78 -> 0 | CH78: =AO78-CE78 -> 866.61161 | CI78: =AP78-CF78 -> 0 | CJ78: =AQ78-CG78 -> 866.61161 | CK78: =SUM(CM78:ES78) -> -867 | CL78: =CJ78+CK78 -> -0.3883904 | DR78: -867
E79: 69 | F79: Other Travel Related Expenses for Steering Committee Meeting | G79: TRAVEL | H79: Field Travel | I79: USAID | J79: 1 | K79: 25 | L79: 1 | M79: /trip | N79: =L79*K79*J79 -> 25 | O79: 0 | P79: =SUM(N79:O79) -> 25 | Q79: 1 | R79: =K79*$J$7 -> 26 | S79: 1 | T79: =Q79*R79*S79 -> 26 | U79: 0 | V79: =SUM(T79:U79) -> 26 | W79: 1 | X79: =K79*$J$7*$J$7 -> 27.04 | Y79: 1 | Z79: =W79*X79*Y79 -> 27.04 | AA79: 0 | AB79: =SUM(Z79:AA79) -> 27.04 | AC79: 1 | AD79: =K79*$J$7*$J$7*$J$7 -> 28.1216 | AE79: 1 | AF79: =AC79*AD79*AE79 -> 28.1216 | AG79: 0 | AH79: =SUM(AF79:AG79) -> 28.1216 | AI79: 1 | AJ79: =K79*$J$7*$J$7*$J$7*$J$7 -> 29.246464 | AK79: 1 | AL79: =AI79*AJ79*AK79 -> 29.246464 | AM79: 0 | AN79: =SUM(AL79:AM79) -> 29.246464 | AO79: =N79+T79+Z79+AF79+AL79 -> 135.40806 | AP79: =O79+U79+AA79+AG79+AM79 -> 0 | AQ79: =SUM(AO79:AP79) -> 135.40806 | AR79: 0 | AS79: 0 | AT79: 0 | AU79: 0 | AV79: =AR79+AT79 -> 0 | AW79: =AS79+AU79 -> 0 | AX79: =AV79+AW79 -> 0 | AY79: =AQ79-AX79 -> 135.40806 | AZ79: =AQ79-AR79-AS79-AT79-AU79 -> 135.40806 | BA79: =AY79-AZ79 -> 0 | BC79: 0 | BE79: 0 | BF79: =AA79 -> 0 | BG79: =SUM(BE79:BF79) -> 0 | BH79: Otros gastos de viaje relacionados con que el personal de ProAntioquia participe en las reuniones anuales presenciales del Comité Directivo de Juntos Aprendemos en Bogotá. Esta linea no se requiere. | BJ79: 0 | BL79: 0 | BM79: =AG79 -> 0 | BN79: =SUM(BL79:BM79) -> 0 | BP79: 0 | BR79: 0 | BS79: =AM79 -> 0 | BT79: 0 | BV79: 0 | BX79: 0 | BY79: =AS79 -> 0 | BZ79: 0 | CA79: =BR79+BL79+BE79+BX79 -> 0 | CB79: =BS79+BM79+BF79 -> 0 | CC79: =BT79+BN79+BG79 -> 0 | CE79: =AV79+CA79 -> 0 | CF79: =AW79+CB79 -> 0 | CG79: =CE79+CF79 -> 0 | CH79: =AO79-CE79 -> 135.40806 | CI79: =AP79-CF79 -> 0 | CJ79: =AQ79-CG79 -> 135.40806 | CK79: =SUM(CM79:ES79) -> -135 | CL79: =CJ79+CK79 -> 0.408064 | DS79: -135
E80: 70 | F80: Subtotal Field Travel | N80: =SUM(N54:N79) -> 16980 | O80: =SUM(O54:O79) -> 0 | P80: =SUM(P54:P79) -> 16980 | T80: =SUM(T54:T79) -> 18063 | U80: =SUM(U54:U79) -> 0 | V80: =SUM(V54:V79) -> 18063 | Z80: =SUM(Z54:Z79) -> 20114.97 | AA80: =SUM(AA54:AA79) -> 0 | AB80: =SUM(AB54:AB79) -> 20114.97 | AF80: =SUM(AF54:AF79) -> 20109.695 | AG80: =SUM(AG54:AG79) -> 0 | AH80: =SUM(AH54:AH79) -> 20109.695 | AL80: =SUM(AL54:AL79) -> 19756.964 | AM80: =SUM(AM54:AM79) -> 0 | AN80: =SUM(AN54:AN79) -> 19756.964 | AO80: =N80+T80+Z80+AF80+AL80 -> 95024.628 | AP80: =O80+U80+AA80+AG80+AM80 -> 0 | AQ80: =SUM(AO80:AP80) -> 95024.628 | AR80: =SUM(AR54:AR79) -> 6091.21 | AS80: 0 | AT80: =SUM(AT54:AT79) -> 89803.87 | AU80: 0 | AV80: 0 | AW80: 0 | AX80: 0 | AY80: 0 | AZ80: =AQ80-AR80-AS80-AT80-AU80 -> -870.45184 | BC80: 0 | BE80: 0 | BF80: =AA80 -> 0 | BG80: 0 | BJ80: 0 | BL80: 0 | BM80: =AG80 -> 0 | BN80: 0 | BP80: 0 | BR80: 0 | BS80: =AM80 -> 0 | BT80: 0 | BV80: 0 | BX80: 0 | BY80: =AS80 -> 0 | BZ80: 0 | CA80: =BR80+BL80+BE80 -> 0 | CB80: =BS80+BM80+BF80 -> 0 | CC80: =BT80+BN80+BG80 -> 0 | CE80: =CA80+AR80+AT80 -> 95895.08 | CF80: =CB80+AS80+AU80 -> 0 | CG80: =CE80+CF80 -> 95895.08 | CK80: =SUM(CM80:ES80) -> 0 | CL80: =CJ80+CK80 -> 0
E81: 71 | F81: Travel Total | N81: =N80+N51 -> 18570 | O81: =O80+O51 -> 0 | P81: =P80+P51 -> 18570 | T81: =T80+T51 -> 19700.7 | U81: =U80+U51 -> 0 | V81: =V80+V51 -> 19700.7 | Z81: =Z80+Z51 -> 21801.801 | AA81: =AA80+AA51 -> 0 | AB81: =AB80+AB51 -> 21801.801 | AF81: =AF80+AF51 -> 21847.131 | AG81: =AG80+AG51 -> 0 | AH81: =AH80+AH51 -> 21847.131 | AL81: =AL80+AL51 -> 21546.523 | AM81: =AM80+AM51 -> 0 | AN81: =AN80+AN51 -> 21546.523 | AO81: =AO80+AO51 -> 103466.15 | AP81: =AP80+AP51 -> 0 | AQ81: =AQ80+AQ51 -> 103466.15 | AR81: =AR80+AR51 -> 7004.8 | AS81: 0 | AT81: =AT80+AT51 -> 89803.87 | AU81: 0 | AV81: 0 | AW81: 0 | AX81: 0 | AY81: 0 | AZ81: =AQ81-AR81-AS81-AT81-AU81 -> 6657.4841 | BC81: =+BC80+BC51+BC45 -> 423.2582 | BE81: =BE45+BE51+BE80 -> 71741.194 | BF81: 0 | BG81: =SUM(BE81:BF81) -> 71741.194 | BJ81: 0 | BL81: =BL45+BL51+BL80 -> 16709.12 | BM81: 0 | BN81: =SUM(BL81:BM81) -> 16709.12 | BP81: 0 | BR81: =BR45+BR51+BR80 -> 48960.38 | BS81: 0 | BT81: =SUM(BR81:BS81) -> 48960.38 | BV81: 0 | BX81: =BX45+BX51+BX80 -> 47010.76 | BY81: 0 | BZ81: =SUM(BX81:BY81) -> 47010.76 | CA81: =BX81+BR81+BL81+BE81 -> 184421.45 | CB81: =BY81+BS81+BM81+BF81 -> 0 | CC81: =BZ81+BT81+BN81+BG81 -> 184421.45 | CE81: =CE80+CE51+CE45 -> 281230.12 | CF81: =CB81+AS81+AU81 -> 0 | CG81: =CE81+CF81 -> 281230.12 | CK81: =SUM(CM81:ES81) -> 0 | CL81: =CJ81+CK81 -> 0
E82: 72 | F82: Equipment - Over $5,000 USD | CK82: =SUM(CM82:ES82) -> 0 | CL82: =CJ82+CK82 -> 0
E83: 73 | F83: Vehicle for Field Office | G83: EQUIPMENT | H83: VEHICLE | I83: USAID | J83: 1 | K83: 50000 | L83: 0 | M83: /unit | N83: =K83*J83 -> 50000 | O83: 0 | P83: =SUM(N83:O83) -> 50000 | Q83: 0 | R83: =K83 -> 50000 | T83: =Q83*R83 -> 0 | U83: 0 | V83: =SUM(T83:U83) -> 0 | W83: 0 | X83: =K83 -> 50000 | Z83: =X83*W83 -> 0 | AA83: 0 | AB83: =SUM(Z83:AA83) -> 0 | AC83: 0 | AD83: =K83 -> 50000 | AF83: =AC83*AD83 -> 0 | AG83: 0 | AH83: =SUM(AF83:AG83) -> 0 | AI83: 0 | AJ83: =K83 -> 50000 | AL83: =AJ83*AI83 -> 0 | AM83: 0 | AN83: =SUM(AL83:AM83) -> 0 | AO83: =N83+T83+Z83+AF83+AL83 -> 50000 | AP83: =O83+U83+AA83+AG83+AM83 -> 0 | AQ83: =SUM(AO83:AP83) -> 50000 | AR83: 0 | AS83: 0 | AT83: 0 | AU83: 0 | AV83: =AR83+AT83 -> 0 | AW83: =AS83+AU83 -> 0 | AX83: =AV83+AW83 -> 0 | AY83: =AQ83-AX83 -> 50000 | AZ83: =AQ83-AR83-AS83-AT83-AU83 -> 50000 | BA83: =AY83-AZ83 -> 0 | BC83: 0 | BE83: 0 | BF83: 0 | BG83: =SUM(BE83:BF83) -> 0 | BH83: El presupuesto original incluía la compra de un (1) vehículo (siguiendo las pautas de adquisición y los requisitos de abastecimiento de USAID) para las operaciones del proyecto en Antioquia. Esta linea no se requiere. | BJ83: 0 | BL83: 0 | BM83: 0 | BN83: =SUM(BL83:BM83) -> 0 | BP83: 0 | BR83: 0 | BS83: 0 | BT83: 0 | BV83: 0 | BX83: 0 | BY83: 0 | BZ83: 0 | CA83: =BR83+BL83+BE83 -> 0 | CB83: =BS83+BM83+BF83 -> 0 | CC83: =BT83+BN83+BG83 -> 0 | CE83: =AV83+CA83 -> 0 | CF83: =AW83+CB83 -> 0 | CG83: =CE83+CF83 -> 0 | CH83: =AO83-CE83 -> 50000 | CI83: =AP83-CF83 -> 0 | CJ83: =AQ83-CG83 -> 50000 | CK83: =SUM(CM83:ES83) -> -50000 | CL83: =CJ83+CK83 -> 0 | DT83: -50000
E84: 74 | F84: Equipment Total | N84: =SUM(N83:N83) -> 50000 | O84: =SUM(O83:O83) -> 0 | P84: =SUM(P83:P83) -> 50000 | T84: =SUM(T83:T83) -> 0 | U84: =SUM(U83:U83) -> 0 | V84: =SUM(V83:V83) -> 0 | Z84: =SUM(Z83:Z83) -> 0 | AA84: =SUM(AA83:AA83) -> 0 | AB84: =SUM(AB83:AB83) -> 0 | AF84: =SUM(AF83:AF83) -> 0 | AG84: =SUM(AG83:AG83) -> 0 | AH84: =SUM(AH83:AH83) -> 0 | AL84: =SUM(AL83:AL83) -> 0 | AM84: =SUM(AM83:AM83) -> 0 | AN84: =SUM(AN83:AN83) -> 0 | AO84: =SUM(AO83:AO83) -> 50000 | AP84: =SUM(AP83:AP83) -> 0 | AQ84: =SUM(AQ83:AQ83) -> 50000 | AR84: 0 | AS84: 0 | AT84: 0 | AU84: 0 | AV84: 0 | AW84: 0 | AX84: 0 | AY84: 0 | AZ84: =AQ84-AR84-AS84-AT84-AU84 -> 50000 | BC84: 0 | BE84: =BB84*BC84*BD84 -> 0 | BF84: 0 | BG84: =SUM(BE84:BF84) -> 0 | BJ84: 0 | BL84: =BI84*BJ84*BK84 -> 0 | BM84: 0 | BN84: =SUM(BL84:BM84) -> 0 | BP84: 0 | BR84: =BO84*BP84*BQ84 -> 0 | BS84: 0 | BT84: =SUM(BR84:BS84) -> 0 | BV84: 0 | BX84: =BU84*BV84*BW84 -> 0 | BY84: 0 | BZ84: =SUM(BX84:BY84) -> 0 | CA84: =BR84+BL84+BE84 -> 0 | CB84: =BS84+BM84+BF84 -> 0 | CC84: =BT84+BN84+BG84 -> 0 | CE84: =CA84+AR84+AT84 -> 0 | CF84: =CB84+AS84+AU84 -> 0 | CG84: =CE84+CF84 -> 0 | CK84: =SUM(CM84:ES84) -> 0 | CL84: =CJ84+CK84 -> 0
E85: 75 | F85: Supplies - Under $5,000 USD | CK85: =SUM(CM85:ES85) -> 0 | CL85: =CJ85+CK85 -> 0
E86: 76 | F86: Supplies | CK86: =SUM(CM86:ES86) -> 0 | CL86: =CJ86+CK86 -> 0
A87: SUBPROANT | B87: 89050 | C87: COL2 | D87: PASUPPLIES | E87: 77 | F87: Office supplies & stationery | G87: SUPPLIES | H87: Supplies | I87: USAID | M87: /unit | AR87: 0 | AS87: 0 | AT87: 0 | AU87: 0 | AV87: 0 | AW87: 0 | AX87: 0 | AY87: 0 | AZ87: 0 | BA87: =AY87-AZ87 -> 0 | BB87: 12 | BC87: 188.558 | BE87: =BB87*BC87 -> 2262.696 | BF87: 0 | BG87: =SUM(BE87:BF87) -> 2262.696 | BH87: Recursos requeridos para la compra de materiales de apoyo a los talleres e insumos menores para el desarrollo de las funciones del equipo, tales como papelería, elementos de oficina como impresora, tintas para impresión, tablero, elementos de apoyo audiovisual. | BJ87: =BC87*1.04 -> 196.10032 | BL87: =BJ87 -> 196.10032 | BM87: 0 | BN87: =SUM(BL87:BM87) -> 196.10032 | BP87: =BJ87*1.04 -> 203.94433 | BR87: =BP87 -> 203.94433 | BS87: 0 | BT87: =BS87+BR87 -> 203.94433 | BV87: 35 | BW87: 8 | BX87: =BW87*BV87 -> 280 | BY87: 0 | BZ87: =BY87+BX87 -> 280 | CA87: =BR87+BL87+BE87+BX87 -> 2942.7407 | CB87: =BS87+BM87+BF87+BY87 -> 0 | CC87: =BT87+BN87+BG87+BZ87 -> 2942.7407 | CE87: =AV87+CA87 -> 2942.7407 | CF87: =AW87+CB87 -> 0 | CG87: =CE87+CF87 -> 2942.7407 | CH87: =AO87-CE87 -> -2942.7407 | CI87: =AP87-CF87 -> 0 | CJ87: =AQ87-CG87 -> -2942.7407 | CK87: =SUM(CM87:ES87) -> 2943 | CL87: =CJ87+CK87 -> 0.2593472 | DU87: 2943
E88: 78 | F88: Subtotal Supplies | AR88: 0 | AS88: 0 | AT88: 0 | AU88: 0 | AV88: 0 | AW88: 0 | AX88: 0 | AY88: 0 | AZ88: 0 | BC88: =BC87 -> 188.558 | BE88: =BE87 -> 2262.696 | BF88: =BF87 -> 0 | BG88: =BG87 -> 2262.696 | BJ88: =BJ87 -> 196.10032 | BL88: =BL87 -> 196.10032 | BM88: =BM87 -> 0 | BN88: =BN87 -> 196.10032 | BP88: =BP87 -> 203.94433 | BR88: =BR87 -> 203.94433 | BS88: =BS87 -> 0 | BT88: =BT87 -> 203.94433 | BV88: =BV87 -> 35 | BX88: =BX87 -> 280 | BY88: =BY87 -> 0 | BZ88: =BZ87 -> 280 | CA88: =BR88+BL88+BE88+BX88 -> 2942.7407 | CB88: =BS88+BM88+BF88+BY88 -> 0 | CC88: =BT88+BN88+BG88+BZ88 -> 2942.7407 | CE88: =CA88+AR88+AT88 -> 2942.7407 | CF88: =CB88+AS88+AU88 -> 0 | CG88: =CE88+CF88 -> 2942.7407 | CK88: =SUM(CM88:ES88) -> 0 | CL88: =CJ88+CK88 -> 0
E89: 79 | F89: HQ Office Supplies | CK89: =SUM(CM89:ES89) -> 0 | CL89: =CJ89+CK89 -> 0
A90: SUBPROANT | B90: 89050 | C90: COL2 | D90: PAHQLAPTOP | E90: 80 | F90: Laptops and software | G90: SUPPLIES | H90: HQ Office Supplies | I90: USAID | J90: 1 | K90: 1204.99 | L90: 1 | M90: /unit | N90: =K90*J90 -> 1204.99 | O90: 0 | P90: =SUM(N90:O90) -> 1204.99 | Q90: 0 | R90: =K90*$J$6 -> 1241.1397 | S90: 1 | T90: =Q90*R90 -> 0 | U90: 0 | V90: =SUM(T90:U90) -> 0 | W90: =T90*U90*V90 -> 0 | X90: =K90*$J$6*$J$6 -> 1278.3739 | Y90: 1 | Z90: =X90*W90 -> 0 | AA90: 0 | AB90: =SUM(Z90:AA90) -> 0 | AC90: =Z90*AA90*AB90 -> 0 | AD90: =K90*$J$6*$J$6*$J$6 -> 1316.7251 | AE90: 1 | AF90: =AD90*AC90 -> 0 | AG90: 0 | AH90: =SUM(AF90:AG90) -> 0 | AI90: =AF90*AG90*AH90 -> 0 | AJ90: =K90*$J$6*$J$6*$J$6*$J$6 -> 1356.2269 | AK90: 1 | AL90: =AJ90*AI90 -> 0 | AM90: 0 | AN90: =SUM(AL90:AM90) -> 0 | AO90: =N90+T90+Z90+AF90+AL90 -> 1204.99 | AP90: =O90+U90+AA90+AG90+AM90 -> 0 | AQ90: =SUM(AO90:AP90) -> 1204.99 | AR90: 0 | AS90: 0 | AT90: =7255.99 -> 7255.99 | AU90: 0 | AV90: =AR90+AT90 -> 7255.99 | AW90: =AS90+AU90 -> 0 | AX90: =AV90+AW90 -> 7255.99 | AY90: =AQ90-AX90 -> -6051 | AZ90: =AQ90-AR90-AS90-AT90-AU90 -> -6051 | BA90: =AY90-AZ90 -> 0 | BC90: 0 | BE90: 0 | BF90: 0 | BG90: =SUM(BE90:BF90) -> 0 | BH90: El presupuesto original incluía la compra de (1) computadora portátil según las cotizaciones locales. | BJ90: 0 | BL90: 0 | BM90: 0 | BN90: =SUM(BL90:BM90) -> 0 | BP90: 0 | BR90: 0 | BS90: 0 | BT90: 0 | BV90: 0 | BX90: 0 | BY90: 0 | BZ90: =BX90+BY90 -> 0 | CA90: =BR90+BL90+BE90+BX90 -> 0 | CB90: =BS90+BM90+BF90 -> 0 | CC90: =BT90+BN90+BG90 -> 0 | CE90: =AV90+CA90 -> 7255.99 | CF90: =AW90+CB90 -> 0 | CG90: =CE90+CF90 -> 7255.99 | CH90: =AO90-CE90 -> -6051 | CI90: =AP90-CF90 -> 0 | CJ90: =AQ90-CG90 -> -6051 | CK90: =SUM(CM90:ES90) -> 6051 | CL90: =CJ90+CK90 -> 0 | DU90: 6051
A91: SUBPROANT | B91: 89050 | C91: COL2 | D91: PAHQWORK | E91: 81 | F91: Workspaces (Space, furniture, internet access, telephone and meeting room) | G91: SUPPLIES | H91: HQ Office Supplies | I91: MIXED | J91: 1 | K91: 278 | L91: 12 | M91: /month | N91: 0 | O91: =+J91*K91*L91 -> 3336 | P91: =SUM(N91:O91) -> 3336 | Q91: 1.3 | R91: =K91*$J$6 -> 286.34 | S91: 12 | T91: 0 | U91: =+Q91*R91*S91 -> 4466.904 | V91: =SUM(T91:U91) -> 4466.904 | W91: 1.3 | X91: =K91*$J$6*$J$6 -> 294.9302 | Y91: 12 | Z91: 0 | AA91: =+W91*X91*Y91 -> 4600.9111 | AB91: =SUM(Z91:AA91) -> 4600.9111 | AC91: 1.3 | AD91: =K91*$J$6*$J$6*$J$6 -> 303.77811 | AE91: 12 | AF91: 0 | AG91: =+AC91*AD91*AE91 -> 4738.9385 | AH91: =SUM(AF91:AG91) -> 4738.9385 | AI91: 1.3 | AJ91: =K91*$J$6*$J$6*$J$6*$J$6 -> 312.89145 | AK91: 12 | AL91: 0 | AM91: =+AI91*AJ91*AK91 -> 4881.1066 | AN91: =SUM(AL91:AM91) -> 4881.1066 | AO91: =N91+T91+Z91+AF91+AL91 -> 0 | AP91: =O91+U91+AA91+AG91+AM91 -> 22023.86 | AQ91: =SUM(AO91:AP91) -> 22023.86 | AR91: 0 | AS91: =293.32+73.87+337.4+91.55+176.01+278.28+192.72+28.27 -> 1471.42 | AT91: 0 | AU91: =170.36+288.97+80.91+30.58+156.82+361.78+170.93+34.75+214.14+331.78+227.69+35.16+179.42+262.04+139.34+30.88+170.7+267.4+140.36+29.14+243.9+378.48+230.88+41.15+319.06+425.62+517.84+46.27+336.01+428.62+272.56+46.6+374.89+428.62+318.66+46.6+289.37+385.99+321.4+41.96+300.81+397.33+535.73+43.19 -> 10094.69 | AV91: =AR91+AT91 -> 0 | AW91: =AS91+AU91 -> 11566.11 | AX91: =AV91+AW91 -> 11566.11 | AY91: =AQ91-AX91 -> 10457.75 | AZ91: =AQ91-AR91-AS91-AT91-AU91 -> 10457.75 | BA91: =AY91-AZ91 -> 0 | BB91: 12 | BC91: 780.276 | BE91: =BC91*BB91 -> 9363.312 | BF91: 4232.96 | BG91: =SUM(BE91:BF91) -> 13596.272 | BH91: Espacios de oficina del programa cargado al 100% y alquiler de la bodega donde se almacenan los materiales, libros y otros elementos asociados a la ejecución de la subactividad Ser+Maestro. | BJ91: 3830 | BL91: =BJ91 -> 3830 | BM91: 17109.74 | BN91: =SUM(BL91:BM91) -> 20939.74 | BP91: 29953 | BR91: =BO91*BP91*BQ91 -> 0 | BS91: =BP91 -> 29953 | BT91: =SUM(BR91:BS91) -> 29953 | BV91: 0 | BX91: 0 | BY91: 1119.8 | BZ91: =BX91+BY91 -> 1119.8 | CA91: =BR91+BL91+BE91+BX91 -> 13193.312 | CB91: =BS91+BM91+BF91+BY91 -> 52415.5 | CC91: =BT91+BN91+BG91+BZ91 -> 65608.812 | CE91: =AV91+CA91 -> 13193.312 | CF91: =AW91+CB91 -> 63981.61 | CG91: =CE91+CF91 -> 77174.922 | CH91: =AO91-CE91 -> -13193.312 | CI91: =AP91-CF91 -> -41957.75 | CJ91: =AQ91-CG91 -> -55151.062 | CK91: =SUM(CM91:ES91) -> 55151 | CL91: =CJ91+CK91 -> -0.061819192 | CO91: 1566 | CQ91: 2387 | CU91: 6944 | EA91: 27750 | EB91: 3311 | EG91: 130 | EI91: 13063
E92: 82 | F92: Subtotal HQ Office Supplies | N92: =SUM(N90:N123) -> 1204.99 | O92: =SUM(O90:O123) -> 3336 | P92: =SUM(P90:P123) -> 4540.99 | T92: =SUM(T90:T123) -> 0 | U92: =SUM(U90:U123) -> 4466.904 | V92: =SUM(V90:V123) -> 4466.904 | Z92: =SUM(Z90:Z123) -> 0 | AA92: =SUM(AA90:AA123) -> 4600.9111 | AB92: =SUM(AB90:AB123) -> 4600.9111 | AF92: =SUM(AF90:AF123) -> 0 | AG92: =SUM(AG90:AG123) -> 4738.9385 | AH92: =SUM(AH90:AH123) -> 4738.9385 | AL92: =SUM(AL90:AL123) -> 0 | AM92: =SUM(AM90:AM123) -> 4881.1066 | AN92: =SUM(AN90:AN123) -> 4881.1066 | AO92: =SUM(AO90:AO123) -> 1204.99 | AP92: =SUM(AP90:AP123) -> 22023.86 | AQ92: =SUM(AQ90:AQ123) -> 23228.85 | AR92: =AR91+AR90 -> 0 | AS92: =AS91+AS90 -> 1471.42 | AT92: =AT91+AT90 -> 7255.99 | AU92: =SUM(AU87:AU91) -> 10094.69 | AV92: =SUM(AV87:AV91) -> 7255.99 | AW92: =SUM(AW87:AW91) -> 11566.11 | AX92: =SUM(AX87:AX91) -> 18822.1 | AY92: =SUM(AY87:AY91) -> 4406.7502 | AZ92: =SUM(AZ90:AZ91) -> 4406.7502 | BC92: =BC90 -> 0 | BE92: =BE91+BE90 -> 9363.312 | BF92: =BF91+BF90+BF88 -> 4232.96 | BG92: =SUM(BE92:BF92) -> 13596.272 | BJ92: 0 | BL92: =BL91+BL90 -> 3830 | BM92: =BM91+BM90 -> 17109.74 | BN92: =SUM(BL92:BM92) -> 20939.74 | BP92: 0 | BR92: =BR91+BR90 -> 0 | BS92: =BS91+BS90 -> 29953 | BT92: =BT91+BT90 -> 29953 | BV92: 0 | BX92: =BX91+BX90 -> 0 | BY92: =BY91+BY90 -> 1119.8 | BZ92: =BZ91+BZ90 -> 1119.8 | CA92: =BR92+BL92+BE92+BX92 -> 13193.312 | CB92: =BY92+BS92+BM92+BF92 -> 52415.5 | CC92: =SUM(CC90:CC91) -> 65608.812 | CE92: =CA92+AR92+AT92 -> 20449.302 | CF92: =CB92+AS92+AU92 -> 63981.61 | CG92: =CE92+CF92 -> 84430.912 | CK92: =SUM(CM92:ES92) -> 0 | CL92: =CJ92+CK92 -> 0
E93: 83 | F93: Field Office Supplies | CK93: =SUM(CM93:ES93) -> 0 | CL93: =CJ93+CK93 -> 0
A94: SUBPROANT | B94: 89050 | C94: COL2 | D94: PAFODESKTP | E94: 84 | F94: Desktop computers, laptops and software | G94: SUPPLIES | H94: Field Office Supplies | I94: USAID | J94: 8 | K94: 1204.99 | L94: 1 | M94: /unit | N94: =K94*J94 -> 9639.92 | O94: 0 | P94: =SUM(N94:O94) -> 9639.92 | Q94: 0 | R94: =K94*$J$6 -> 1241.1397 | S94: 1 | T94: =Q94*R94 -> 0 | U94: 0 | V94: =SUM(T94:U94) -> 0 | W94: =T94*U94*V94 -> 0 | X94: =K94*$J$6*$J$6 -> 1278.3739 | Y94: 1 | Z94: =X94*W94 -> 0 | AA94: 0 | AB94: =SUM(Z94:AA94) -> 0 | AC94: =Z94*AA94*AB94 -> 0 | AD94: =K94*$J$6*$J$6*$J$6 -> 1316.7251 | AE94: 1 | AF94: =AD94*AC94 -> 0 | AG94: 0 | AH94: =SUM(AF94:AG94) -> 0 | AI94: =AF94*AG94*AH94 -> 0 | AJ94: =K94*$J$6*$J$6*$J$6*$J$6 -> 1356.2269 | AK94: 1 | AL94: =AJ94*AI94 -> 0 | AM94: 0 | AN94: =SUM(AL94:AM94) -> 0 | AO94: =N94+T94+Z94+AF94+AL94 -> 9639.92 | AP94: =O94+U94+AA94+AG94+AM94 -> 0 | AQ94: =SUM(AO94:AP94) -> 9639.92 | AR94: =7038.54 -> 7038.54 | AS94: 0 | AT94: =1551.32+246.45+170.87+74.91+229.99+184.84 -> 2458.38 | AU94: 0 | AV94: =AR94+AT94 -> 9496.92 | AW94: =AS94+AU94 -> 0 | AX94: =AV94+AW94 -> 9496.92 | AY94: =AQ94-AX94 -> 143 | AZ94: =AQ94-AR94-AS94-AT94-AU94 -> 143 | BA94: =AY94-AZ94 -> 0 | BB94: 1 | BC94: 1208.79 | BE94: =BC94 -> 1208.79 | BF94: 0 | BG94: =SUM(BE94:BF94) -> 1208.79 | BH94: Rubro para la compra de equipos de cómputo (estimado en USD 750) y software (se estima 1 desarrollo para mejorar el proceso de recolección de datos estimado en USD 563,33) y/o licencias (se estiman 2 licencias de power bi anual por valor de USD 220) para el trabajo de los profesionales del proyecto además de costos de mantenimiento de los ya adquiridos según necesidades de la operación (según experiencia de Proantioquia se estima en USD 300). | BJ94: 0 | BL94: 0 | BM94: 0 | BN94: =SUM(BL94:BM94) -> 0 | BP94: 0 | BR94: 0 | BS94: 0 | BT94: 0 | BV94: 0 | BX94: 0 | BY94: 0 | BZ94: 0 | CA94: =BR94+BL94+BE94+BX94 -> 1208.79 | CB94: =BS94+BM94+BF94 -> 0 | CC94: =BT94+BN94+BG94 -> 1208.79 | CE94: =AV94+CA94 -> 10705.71 | CF94: =AW94+CB94 -> 0 | CG94: =CE94+CF94 -> 10705.71 | CH94: =AO94-CE94 -> -1065.79 | CI94: =AP94-CF94 -> 0 | CJ94: =AQ94-CG94 -> -1065.79 | CK94: =SUM(CM94:ES94) -> 1066 | CL94: =CJ94+CK94 -> 0.21 | DU94: 1066
A95: SUBPROANT | B95: 89050 | C95: COL2 | D95: PAPPE | E95: 85 | F95: Personal Protective Equipment (Gloves, Masks, Hand Sanitizer, Antibacterial Wipes etc.) | G95: SUPPLIES | H95: Field Office Supplies | I95: USAID | J95: 1 | K95: 750 | L95: 6 | M95: /month | N95: =L95*K95*J95 -> 4500 | O95: 0 | P95: =SUM(N95:O95) -> 4500 | Q95: 1 | R95: =K95*$J$6 -> 772.5 | S95: 12 | T95: =S95*Q95*R95 -> 9270 | U95: 0 | V95: =SUM(T95:U95) -> 9270 | W95: 1 | X95: =K95*$J$6*$J$6 -> 795.675 | Y95: 12 | Z95: =X95*Y95*W95 -> 9548.1 | AA95: 0 | AB95: =SUM(Z95:AA95) -> 9548.1 | AC95: 1 | AD95: =K95*$J$6*$J$6*$J$6*0.5 -> 409.77263 | AE95: 12 | AF95: =AD95*AC95*AE95 -> 4917.2715 | AG95: 0 | AH95: =SUM(AF95:AG95) -> 4917.2715 | AI95: 1 | AJ95: =K95*$J$6*$J$6*$J$6*$J$6*0.5 -> 422.0658 | AK95: 9 | AL95: =AJ95*AI95*AK95 -> 3798.5922 | AM95: 0 | AN95: =SUM(AL95:AM95) -> 3798.5922 | AO95: =N95+T95+Z95+AF95+AL95 -> 32033.964 | AP95: =O95+U95+AA95+AG95+AM95 -> 0 | AQ95: =SUM(AO95:AP95) -> 32033.964 | AR95: 0 | AS95: 0 | AT95: =24.99+36.51 -> 61.5 | AU95: 0 | AV95: =AR95+AT95 -> 61.5 | AW95: =AS95+AU95 -> 0 | AX95: =AV95+AW95 -> 61.5 | AY95: =AQ95-AX95 -> 31972.464 | AZ95: =AQ95-AR95-AS95-AT95-AU95 -> 31972.464 | BA95: =AY95-AZ95 -> 0 | BB95: 1 | BC95: 43.96 | BE95: =BC95*BB95 -> 43.96 | BF95: 0 | BG95: =SUM(BE95:BF95) -> 43.96 | BH95: Rubro para la compra y disposición de elementos de cuidado de la bioseguridad en campo en procesos de formación y eventos que se realicen desde la operación de Proantioquia en JA. SE suspende este requisito en mayo 2023. | BJ95: 0 | BL95: 0 | BM95: 0 | BN95: =SUM(BL95:BM95) -> 0 | BP95: 0 | BR95: 0 | BS95: 0 | BT95: 0 | BV95: 0 | BX95: 0 | BY95: 0 | BZ95: 0 | CA95: =BR95+BL95+BE95+BX95 -> 43.96 | CB95: =BS95+BM95+BF95 -> 0 | CC95: =BT95+BN95+BG95 -> 43.96 | CE95: =AV95+CA95 -> 105.46 | CF95: =AW95+CB95 -> 0 | CG95: =CE95+CF95 -> 105.46 | CH95: =AO95-CE95 -> 31928.504 | CI95: =AP95-CF95 -> 0 | CJ95: =AQ95-CG95 -> 31928.504 | CK95: =SUM(CM95:ES95) -> -31929 | CL95: =CJ95+CK95 -> -0.49626625 | DU95: -31929
E96: 86 | F96: Subtotal Field Office Supplies | N96: =SUM(N94:N95) -> 14139.92 | O96: =SUM(O94:O95) -> 0 | P96: =SUM(P94:P95) -> 14139.92 | T96: =SUM(T94:T95) -> 9270 | U96: =SUM(U94:U95) -> 0 | V96: =SUM(V94:V95) -> 9270 | Z96: =SUM(Z94:Z95) -> 9548.1 | AA96: =SUM(AA94:AA95) -> 0 | AB96: =SUM(AB94:AB95) -> 9548.1 | AF96: =SUM(AF94:AF95) -> 4917.2715 | AG96: =SUM(AG94:AG95) -> 0 | AH96: =SUM(AH94:AH95) -> 4917.2715 | AL96: =SUM(AL94:AL95) -> 3798.5922 | AM96: =SUM(AM94:AM95) -> 0 | AN96: =SUM(AN94:AN95) -> 3798.5922 | AO96: =SUM(AO94:AO95) -> 41673.884 | AP96: =SUM(AP94:AP95) -> 0 | AQ96: =SUM(AQ94:AQ95) -> 41673.884 | AR96: =AR94+AR95 -> 7038.54 | AS96: =AS94+AS95 -> 0 | AT96: =AT94+AT95 -> 2519.88 | AU96: =AU94+AU95 -> 0 | AV96: =AV94+AV95 -> 9558.42 | AW96: =AW94+AW95 -> 0 | AX96: =AX94+AX95 -> 9558.42 | AY96: =AY94+AY95 -> 32115.464 | AZ96: =AQ96-AR96-AS96-AT96-AU96 -> 32115.464 | BC96: =SUM(BC94:BC95) -> 1252.75 | BE96: =SUM(BE94:BE95) -> 1252.75 | BF96: 0 | BG96: =SUM(BE96:BF96) -> 1252.75 | BJ96: 0 | BL96: =SUM(BL94:BL95) -> 0 | BM96: 0 | BN96: =SUM(BL96:BM96) -> 0 | BP96: 0 | BR96: =SUM(BR94:BR95) -> 0 | BS96: 0 | BT96: =SUM(BR96:BS96) -> 0 | BV96: 0 | BX96: =SUM(BX94:BX95) -> 0 | BY96: 0 | BZ96: =SUM(BX96:BY96) -> 0 | CA96: =BR96+BL96+BE96+BX96 -> 1252.75 | CB96: =BS96+BM96+BF96 -> 0 | CC96: =SUM(CC94:CC95) -> 1252.75 | CE96: =CA96+AR96+AT96 -> 10811.17 | CF96: =CB96+AS96+AU96 -> 0 | CG96: =CE96+CF96 -> 10811.17 | CK96: =SUM(CM96:ES96) -> 0 | CL96: =CJ96+CK96 -> 0
E97: 87 | F97: Supplies Total | N97: =N96+N92 -> 0 | O97: =O96+O92 -> 3336 | P97: =P96+P92 -> 0 | T97: =T96+T92 -> 9270 | U97: =U96+U92 -> 4466.904 | V97: =V96+V92 -> 13736.904 | Z97: =Z96+Z92 -> 9548.1 | AA97: =AA96+AA92 -> 4600.9111 | AB97: =AB96+AB92 -> 14149.011 | AF97: =AF96+AF92 -> 4917.2715 | AG97: =AG96+AG92 -> 4738.9385 | AH97: =AH96+AH92 -> 9656.21 | AL97: =AL96+AL92 -> 3798.5922 | AM97: =AM96+AM92 -> 4881.1066 | AN97: =AN96+AN92 -> 8679.6988 | AO97: =AO96+AO92 -> 42878.874 | AP97: =AP96+AP92 -> 22023.86 | AQ97: =AQ96+AQ92 -> 64902.734 | AR97: =AR96+AR92 -> 7038.54 | AS97: =AS96+AS92 -> 1471.42 | ... AY97: =AY96+AY92 -> 36522.214 | AZ97: =AQ97-AR97-AS97-AT97-AU97 -> 0 | BC97: =+BC96+BC92+BC88 -> 1441.308 | BE97: =BE96+BE92+BE88 -> 12878.758 | BF97: =+BF96+BF92+BF88 -> 4232.96 | BG97: =BE97+BF97 -> 17111.718 | BL97: =BL96+BL92+BL88 -> 4026.1003 | BM97: =BM96+BM92+BM88 -> 17109.74 | BN97: =BL97+BM97 -> 21135.84 | BP97: 0 | BR97: =BR96+BR92+BR88 -> 203.94433 | BS97: =BS96+BS92+BS88 -> 29953 | BT97: =BR97+BS97 -> 30156.944 | BV97: 0 | BX97: =BX96+BX92+BX88 -> 280 | BY97: =BY96+BY92 -> 1119.8 | BZ97: =BX97+BY97 -> 1399.8 | CA97: =BR97+BL97+BE97+BX97 -> 17388.803 | CB97: =BS97+BM97+BF97 -> 51295.7 | CC97: =BZ97+BT97+BN97+BG97 -> 69804.303 | CE97: =CE88+CE92+CE96 -> 34203.213 | CF97: =CF88+CF92+CF96 -> 63981.61 | CG97: =CE97+CF97 -> 98184.823 | CK97: =SUM(CM97:ES97) -> 0 | CL97: =CJ97+CK97 -> 0
E98: 88 | F98: Contractual | CK98: =SUM(CM98:ES98) -> 0 | CL98: =CJ98+CK98 -> 0
E99: 89 | F99: Consultants | CF99: =CB99+AS99+AU99 -> 0 | CK99: =SUM(CM99:ES99) -> 0 | CL99: =CJ99+CK99 -> 0
E100: 90 | F100: Consultant for data analysis to build public policy guidelines | G100: CONTRACTUAL | H100: CONSULTANTS | I100: USAID | J100: 1 | K100: 1950 | L100: 3 | M100: /month | N100: =K100*J100*L100 -> 5850 | O100: 0 | P100: =SUM(N100:O100) -> 5850 | Q100: 1 | R100: =K100 -> 1950 | S100: 3 | T100: =R100*Q100*S100 -> 5850 | U100: 0 | V100: =SUM(T100:U100) -> 5850 | W100: 1 | X100: =K100 -> 1950 | Y100: 3 | Z100: =W100*X100*Y100 -> 5850 | AA100: 0 | AB100: =SUM(Z100:AA100) -> 5850 | AC100: 1 | AD100: =K100 -> 1950 | AE100: 3 | AF100: =AD100*AC100*AE100 -> 5850 | AG100: 0 | AH100: =SUM(AF100:AG100) -> 5850 | AI100: 1 | AJ100: =K100 -> 1950 | AK100: 3 | AL100: =AJ100*AI100*AK100 -> 5850 | AM100: 0 | AN100: =SUM(AL100:AM100) -> 5850 | AO100: =N100+T100+Z100+AF100+AL100 -> 29250 | AP100: =O100+U100+AA100+AG100+AM100 -> 0 | AQ100: =SUM(AO100:AP100) -> 29250 | AR100: 0 | AS100: 0 | AT100: 0 | AU100: 0 | AV100: =AR100+AT100 -> 0 | AW100: =AS100+AU100 -> 0 | AX100: =AV100+AW100 -> 0 | AY100: =AQ100-AX100 -> 29250 | AZ100: =AQ100-AR100-AS100-AT100-AU100 -> 29250 | BA100: =AY100-AZ100 -> 0 | BC100: 0 | BE100: =BB100*BC100*BD100 -> 0 | BF100: 0 | BG100: =SUM(BE100:BF100) -> 0 | BH100: El presupuesto original incluía un consultor local de análisis de datos al 50% LOE durante 15 meses para construir lineamientos de política pública. Esta linea no se requiere. | BJ100: 0 | BL100: =BI100*BJ100*BK100 -> 0 | BM100: 0 | BN100: =SUM(BL100:BM100) -> 0 | BP100: 0 | BR100: =BO100*BP100*BQ100 -> 0 | BS100: 0 | BT100: =SUM(BR100:BS100) -> 0 | BV100: 0 | BX100: =BU100*BV100*BW100 -> 0 | BY100: 0 | BZ100: =SUM(BX100:BY100) -> 0 | CA100: =BR100+BL100+BE100+BX100 -> 0 | CB100: =BS100+BM100+BF100 -> 0 | CC100: =BT100+BN100+BG100 -> 0 | CE100: =AV100+CA100 -> 0 | CF100: =AW100+CB100 -> 0 | CG100: =CE100+CF100 -> 0 | CH100: =AO100-CE100 -> 29250 | CI100: =AP100-CF100 -> 0 | CJ100: =AQ100-CG100 -> 29250 | CK100: =SUM(CM100:ES100) -> -29250 | CL100: =CJ100+CK100 -> 0 | DV100: -29250
...

Sheet Hoja1
F1: 1 | G1: 2 | H1: 3 | I1: 4 | J1: 5 | K1: 6 | L1: 7 | M1: 8 | N1: 9 | O1: 10 | P1: 11 | Q1: 12 | R1: 13 | S1: 14 | T1: 15 | U1: 16 | V1: 17 | W1: 18 | X1: 19 | Y1: 20 | Z1: 21 | AA1: 22 | AB1: 23 | AC1: 24 | AD1: 25 | AE1: 26 | AF1: 27 | AG1: 28 | AH1: 29 | AI1: 30 | AJ1: 31 | AK1: 32 | AL1: 33 | AM1: 34 | AN1: NA | AO1: 35 | AP1: 36 | AQ1: 37 | AR1: 38 | AS1: 39 | AT1: 40 | AU1: 41 | AV1: 42 | AW1: 43 | AX1: 44 | AY1: 45 | AZ1: 46 | BA1: 47 | BB1: 48 | BC1: 49 | BD1: 50 | BE1: 51 | BF1: 52 | BG1: 53 | BH1: 54 | BI1: 55 | BJ1: 56 | BK1: 57 | BL1: 58 | BM1: 59 | BN1: 60 | BO1: 61 | BP1: 62 | BQ1: 63 | BR1: 64 | BS1: 65 | BT1: 66 | BU1: 67 | BV1: 68 | BW1: 69 | BX1: 70 | BY1: 71 | BZ1: 72 | CA1: 73 | CB1: 74 | CC1: 75 | CD1: 76 | CE1: 77 | CF1: 78 | CG1: 79 | CH1: 80 | CI1: 81 | CJ1: 82 | CK1: 83 | CL1: 84 | CM1: 85 | CN1: 86 | CO1: 87 | CP1: 88 | CQ1: 89 | CR1: 90 | CS1: 91 | CT1: 92 | CU1: 93 | CV1: 139 | CW1: 94 | CX1: 95 | CY1: 96 | CZ1: 97 | DA1: 98 | DB1: 99 | DC1: 100 | DD1: 101 | DE1: 102 | DF1: 103 | DG1: 139 | DH1: 104 | DI1: 105 | DJ1: 106 | DK1: 107 | DL1: 108 | DM1: 109 | DN1: 110 | DO1: 111 | DP1: 112 | DQ1: 113 | DR1: 114 | DS1: 115 | DT1: 116 | DU1: 117 | DV1: 118 | DW1: 119 | DX1: 120 | DY1: 121 | DZ1: 122 | EA1: 123 | EB1: 124 | EC1: 125 | ED1: 126 | EE1: 127 | EF1: 128 | EG1: 129 | EH1: 130 | EI1: 131 | EJ1: 132 | EK1: 133 | EL1: 134 | EM1: 135 | EN1: 136 | EO1: 137 | EP1: 138 | EQ1: 140
F2: 1 | G2: 2 | H2: 3 | I2: 4 | J2: 5 | K2: 6 | L2: 7 | M2: 8 | N2: 9 | O2: 10 | P2: 11 | Q2: 12 | R2: 13 | S2: 14 | T2: 15 | U2: 16 | V2: 17 | W2: 18 | X2: 19 | Y2: 20 | Z2: 21 | AA2: 22 | AB2: 23 | AC2: 24 | AD2: 25 | AE2: 26 | AF2: 27 | AG2: 28 | AH2: 29 | AI2: 30 | AJ2: 31 | AK2: 32 | AL2: 33 | AM2: 34 | AN2: 35 | AO2: 36 | AP2: 37 | AQ2: 38 | AR2: 39 | AS2: 40 | AT2: 41 | AU2: 42 | AV2: 43 | AW2: 44 | AX2: 45 | AY2: 46 | AZ2: 47 | BA2: 48 | BB2: 49 | BC2: 50 | BD2: 51 | BE2: 52 | BF2: 53 | BG2: 54 | BH2: 55 | BI2: 56 | BJ2: 57 | BK2: 58 | BL2: 59 | BM2: 60 | BN2: 61 | BO2: 62 | BP2: 63 | BQ2: 64 | BR2: 65 | BS2: 66 | BT2: 67 | BU2: 68 | BV2: 69 | BW2: 70 | BX2: 71 | BY2: 72 | BZ2: 73 | CA2: 74 | CB2: 75 | CC2: 76 | CD2: 77 | CE2: 78 | CF2: 79 | CG2: 80 | CH2: 81 | CI2: 82 | CJ2: 83 | CK2: 84 | CL2: 85 | CM2: 86 | CN2: 87 | CO2: 88 | CP2: 89 | CQ2: 90 | CR2: 91 | CS2: 92 | CT2: 93 | CU2: 94 | CV2: 95 | CW2: 96 | CX2: 97 | CY2: 98 | CZ2: 99 | DA2: 100 | DB2: 101 | DC2: 102 | DD2: 103 | DE2: 104 | DF2: 105 | DG2: 106 | DH2: 107 | DI2: 108 | DJ2: 109 | DK2: 110 | DL2: 111 | DM2: 112 | DN2: 113 | DO2: 114 | DP2: 115 | DQ2: 116 | DR2: 117 | DS2: 118 | DT2: 119 | DU2: 120 | DV2: 121 | DW2: 122 | DX2: 123 | DY2: 124 | DZ2: 125 | EA2: 126 | EB2: 127 | EC2: 128 | ED2: 129 | EE2: 130 | EF2: 131 | EG2: 132 | EH2: 133 | EI2: 134 | EJ2: 135 | EK2: 136 | EL2: 137 | EM2: 138 | EN2: 139 | EO2: 140 | EP2: 141 | EQ2: 142
A3: 1 | B3: 1 | C3: PERSONNEL | F3: PERSONNEL | G3: Headquarters Personnel | H3: Project Office (Bogota) | I3: Partnerships and Alliances Director* | J3: Partnerships and Alliances Coordinator | K3: ProAntioquia Office | L3: Education Director (HQ-ProAntioquia) | M3: Subtotal HQ Personnel | N3: Field Personnel | O3: Teacher Training Specialist (2) | P3: Teacher Training Professionals (4) | Q3: Administrative Coordinator Administrative and Organizational Cultural Leader | R3: Professional Accountant | S3: Visual Documentation Communications Professional | T3: Content Development Professional | U3: Finance & Admin Coordinator Project Analyst | V3: Operations and Planning Professional Human Resources Professional | W3: Juntos Aprendemos Project Leader | X3: Logistics professional | Y3: Monitoring, evaluation and Learning (MEL) professional | Z3: Metrics Analyst | AA3: Administrative Assistant | AB3: Operations Assistant | AC3: Subtotal Field Personnel | AD3: Personnel Total | AE3: FRINGE BENEFITS | AF3: Fringe Benefits – Colombia HQ and Field Staff (above $2,600 monthly) | AG3: Fringe Benefits - Colombia HQ and Field Staff (below $2,600 monthly) | AH3: Fringe Benefits Total | AI3: TRAVEL | AJ3: Staff Travel | AK3: Local Transportation (Airfare, Taxis, & Rental Car/Driver) | AL3: Meals and incidentals | AM3: Lodging | AN3: Other travel related expenses | AO3: Subtotal Staff Travel | AP3: HQ Staff Travel | AQ3: Local Transportation (Airfare, Taxis, & Rental Car/Driver) for Directors | AR3: Meals and Incidentals for Directors | AS3: Lodging for Directors | AT3: Other Travel Related Expenses for Directors | AU3: Subtotal HQ Staff Travel | AV3: Field Travel | AW3: T.1 Field Staff Travel for Site Visits and M&E | AX3: Local Transportation (Airfare, Taxis, & Rental Car/Driver) for Site Visits and M&E | AY3: Meals and Incidentals for Site Visits and M&E | AZ3: Lodging for Site Visits and M&E | BA3: Other Travel Related Expenses for Site Visits and M&E | BB3: T.2 Local Travel in Antioquia for Field Staff | BC3: Vehicle Fuel Expense | BD3: T.3 Travel for Advisory Board Meetings - 2 Annually | BE3: Local Transportation for Advisory Board Meetings | BF3: Meals and Incidentals for Advisory Board Meetings | BG3: Lodging for Advisory Board Meetings | BH3: Other Travel Related Expenses for Advisory Board Meetings | BI3: T.4 Travel for Annual Forums for Education Observatories | BJ3: Local Transportation for Annual Forums | BK3: Meals and Incidentals for Annual Forums | BL3: Lodging for Annual Forums | BM3: Other Travel Related Expenses for Annual Forums | BN3: T.5 Travel to SMT In-Person Meetings in Bogota | BO3: Local Transportation for SMT Meetings | BP3: Meals and Incidentals for SMT Meetings | BQ3: Lodging for SMT Meetings | BR3: Other Travel Related Expenses for SMT Meetings | BS3: T.6 Travel to Annual In-Person Steering Committee Meeting in Bogota | BT3: Local Transportation for Steering Committee Meeting | BU3: Meals and Incidentals for Steering Committee Meeting | BV3: Lodging for Steering Committee Meeting | BW3: Other Travel Related Expenses for Steering Committee Meeting | BX3: Subtotal Field Travel | BY3: Travel Total | BZ3: Equipment - Over $5,000 USD | CA3: Vehicle for Field Office | CB3: Equipment Total | CC3: Supplies - Under $5,000 USD | CD3: Supplies | CE3: Office supplies & stationery | CF3: Subtotal Supplies | CG3: HQ Office Supplies | CH3: Laptops and software | CI3: Workspaces (Space, furniture, internet access, telephone and meeting room) | CJ3: Subtotal HQ Office Supplies | CK3: Field Office Supplies | CL3: Desktop computers, laptops and software | CM3: Personal Protective Equipment (Gloves, Masks, Hand Sanitizer, Antibacterial Wipes etc.) | CN3: Subtotal Field Office Supplies | CO3: Supplies Total | CP3: Contractual | CQ3: Consultants | CR3: Consultant for data analysis to build public policy guidelines | CS3: Consultant for technical advice for advocacy on public policy | CT3: Entrena-QL methodology for development of educational materials | CU3: General consultants | CV3: Rapid Response Fund Consultant Pool | CW3: Subtotal Consultants | CX3: Security | CY3: Local Office Security Contractor (Local Hire) | CZ3: Subtotal Security | DA3: Contractual Total | DB3: Other Direct Costs | DC3: HQ - Other Direct Costs | DD3: Prototypes and pilots of educational materials | DE3: Adaptation of existing content and methodologies for educational materials | DF3: Content for school campaigns | DG3: Rapid response fund (3%) | DH3: Food (snacks) for activities | DI3: Food (coffee station) for activities | DJ3: Subtotal HQ Other Direct Costs | DK3: Field Office (FO) - Other Direct Costs | DL3: Translation costs | DM3: Courier fees/services/postage | DN3: Banking and cash handling fees | DO3: Vehicle Insurance & Maintenance | DP3: Objective 1: Improved quality of education for children and youth in receptor communities | DQ3: Development of teacher training books for Replica Workshops | DR3: Graphic and operational design of digital courses | DS3: Graphic design for teachers training materials | DT3: Development of digital network strategy for Parche Maestro | DU3: Transport of books for teacher training Replica Workshops | DV3: Transport of books for children | DW3: Graphic design of classroom guides | DX3: Process systematization book | DY3: Videos for teacher training | DZ3: Books for children (Collection of NEXO literary) | EA3: Editorial production | EB3: Objective 2: Increased access to quality education for children and youth in receptor communities | EC3: Local government and community-based organizations support the enrollment of children and youth in schools | ED3: Round tables with interest stakeholders | EE3: Printing of informational materials | EF3: Objective 3: Strengthened community engagement in educational opportunities | EG3: Round table with local private sector to build public policy guidelines | EH3: Regional workshops about strategic themes of public policy guidelines | EI3: Monitoring, Evaluation, and Collection of Reliable Data | EJ3: M&E Database Platform Access | EK3: Data Collection Tools | EL3: On-going M&E Training Workshops | EM3: On-going Training Workshops for Data Collection Staff | EN3: Subtotal Field Office Other Direct Costs | EO3: Other Direct Costs Total | EP3: Total Direct Costs | EQ3: Total Indirect Costs (NICRA or De Minimis)
A4: 2 | B4: 2 | C4: Headquarters Personnel
A5: 3 | B5: 3 | C5: Project Office (Bogota)
A6: 4 | B6: 4 | C6: Partnerships and Alliances Director*
A7: 5 | B7: 5 | C7: Partnerships and Alliances Coordinator
A8: 6 | B8: 6 | C8: ProAntioquia Office
A9: 7 | B9: 7 | C9: Education Director (HQ-ProAntioquia)
A10: 8 | B10: 8 | C10: Subtotal HQ Personnel
A11: 9 | B11: 9 | C11: Field Personnel
A12: 10 | B12: 10 | C12: Teacher Training Specialist (2)
A13: 11 | B13: 11 | C13: Teacher Training Professionals (4)
A14: 12 | B14: 12 | C14: Administrative Coordinator Administrative and Organizational Cultural Leader
A15: 13 | B15: 13 | C15: Professional Accountant
... A36: 34 | B36: 34 | C36: Lodging
A37: NA | B37: 35 | C37: Other travel related expenses
A38: 35 | B38: 36 | C38: Subtotal Staff Travel
A39: 36 | B39: 37 | C39: HQ Staff Travel
A40: 37 | B40: 38 | C40: Local Transportation (Airfare, Taxis, & Rental Car/Driver) for Directors
A41: 38 | B41: 39 | C41: Meals and Incidentals for Directors
A42: 39 | B42: 40 | C42: Lodging for Directors
A43: 40 | B43: 41 | C43: Other Travel Related Expenses for Directors
A44: 41 | B44: 42 | C44: Subtotal HQ Staff Travel
A45: 42 | B45: 43 | C45: Field Travel
A46: 43 | B46: 44 | C46: T.1 Field Staff Travel for Site Visits and M&E
A47: 44 | B47: 45 | C47: Local Transportation (Airfare, Taxis, & Rental Car/Driver) for Site Visits and M&E
A48: 45 | B48: 46 | C48: Meals and Incidentals for Site Visits and M&E
A49: 46 | B49: 47 | C49: Lodging for Site Visits and M&E
... A144: 140 | B144: 142 | C144: Total Indirect Costs (NICRA or De Minimis)

Sheet Proyecciones 2023
F1: ENERO | G1: FEBRERO | H1: MARZO | I1: ABRIL | J1: MAYO | K1: JUNIO | L1: JULIO | M1: AGOSTO | N1: SEPTIEMBRE | O1: OCTUBRE | P1: NOVIEMBRE | Q1: DICIEMBRE | R1: TOTAL
A3: PERSONAL | B3: 10-10-89 | F3: =SUM(F4:F17)/F93 -> 12102.62 | G3: =SUM(G4:G17)/G93 -> 12124.764 | H3: =SUM(H4:H17)/H93 -> 12437.365 | I3: =SUM(I4:I17)/I93 -> 13034.591 | J3: =SUM(J4:J17)/$U$4 -> 13006.154 | K3: =SUM(K4:K17)/$U$4 -> 13006.154 | L3: =SUM(L4:L17)/$U$4 -> 13073.407 | M3: =SUM(M4:M17)/$U$4 -> 13073.407 | N3: =SUM(N4:N17)/$U$4 -> 13073.407 | O3: =SUM(O4:O17)/$U$4 -> 13073.407 | P3: =SUM(P4:P17)/$U$4 -> 13073.407 | Q3: =SUM(Q4:Q17)/$U$4 -> 13073.407 | R3: =SUM(F3:Q3) -> 154152.09
A4: NOMBRE | B4: CARGO | C4: DEDICACIÓN | D4: SALARIO | T4: TRM | U4: 4550 | W4: Enero | X4: Febrero | Y4: Marzo | Z4: Abril | AA4: Mayo | AB4: Enero | AC4: Febrero | AD4: Marzo | AE4: Abril | AF4: Mayo | AG4: Total | AI4: II Semestre | AK4: 4550
A5: Luz Mery Rojas | B5: Coordinadora de formación de maestros | C5: 1 | D5: 8902000 | E5: =D5*1.1412 -> 10158962 | F5: 10159000 | G5: 10159000 | H5: 10159000 | I5: 10159000 | J5: 10159000 | K5: 10159000 | L5: 10159000 | M5: 10159000 | N5: 10159000 | O5: 10159000 | P5: 10159000 | Q5: 10159000 | R5: =SUM(F5:Q5) -> 121908000 | S5: =R5/U$4 -> 26792.967 | T5: =Q5/U4 -> 2232.7473 | W5: =F5 -> 10159000 | X5: =G5 -> 10159000 | Y5: =H5 -> 10159000 | Z5: =I5 -> 10159000 | AA5: =J5 -> 10159000 | AB5: =+W5/$F$93 -> 2157.3015 | AC5: =+X5/$G$93 -> 2120.3469 | AD5: =+Y5/$H$93 -> 2135.1042 | AE5: =+Z5/$I$93 -> 2237.6291 | AF5: =+AA5/$U$4 -> 2232.7473 | AG5: =SUM(AB5:AF5) -> 10883.129 | AI5: =SUM(K5:Q5)/$U$4 -> 15629.231 | AJ5: =AG5+AI5 -> 26512.36
A6: Carolina Taborda | B6: Profesional de educación | C6: 1 | D6: 4900000 | E6: =(D6*1.1412) -> 5591880 | F6: 2935800 | G6: 5592000 | H6: 5592000 | I6: 5592000 | J6: 5592000 | K6: 5592000 | L6: 5592000 | M6: 5592000 | N6: 5592000 | O6: 5592000 | P6: 5592000 | Q6: 5592000 | R6: =SUM(F6:Q6) -> 64447800 | S6: =R6/U$4 -> 14164.352 | T6: =Q6/U4 -> 1229.011 | W6: =F6 -> 2935800 | X6: =G6 -> 5592000 | Y6: =H6 -> 5592000 | Z6: =I6 -> 5592000 | AA6: =J6 -> 5592000 | AB6: =+W6/$F$93 -> 623.42807 | AC6: =+X6/$G$93 -> 1167.1404 | AD6: =+Y6/$H$93 -> 1175.2636 | AE6: =+Z6/$I$93 -> 1231.6982 | AF6: =+AA6/$U$4 -> 1229.011 | AG6: =SUM(AB6:AF6) -> 5426.5413 | AI6: =SUM(K6:Q6)/$U$4 -> 8603.0769 | AJ6: =AG6+AI6 -> 14029.618
A7: Andres Restrepo | B7: Profesional de educación | C7: 1 | D7: 4265000 | E7: =D7*1.1412 -> 4867218 | F7: 4867000 | G7: 4867000 | H7: 4867000 | I7: 4867000 | J7: 4867000 | K7: 4867000 | L7: 4867000 | M7: 4867000 | N7: 4867000 | O7: 4867000 | P7: 4867000 | Q7: 4867000 | R7: =SUM(F7:Q7) -> 58404000 | S7: =R7/U$4 -> 12836.044 | T7: =Q7/U$4 -> 1069.6703 | W7: =F7 -> 4867000 | X7: =G7 -> 4867000 | Y7: =H7 -> 4867000 | Z7: =I7 -> 4867000 | AA7: =J7 -> 4867000 | AB7: =+W7/$F$93 -> 1033.5256 | AC7: =+X7/$G$93 -> 1015.8213 | AD7: =+Y7/$H$93 -> 1022.8912 | AE7: =+Z7/$I$93 -> 1072.0091 | AF7: =+AA7/$U$4 -> 1069.6703 | AG7: =SUM(AB7:AF7) -> 5213.9176 | AI7: =SUM(K7:Q7)/$U$4 -> 7487.6923 | AJ7: =AG7+AI7 -> 12701.61
A8: Juan Carlos Ramirez | B8: Profesional de educación | C8: 1 | D8: 4265000 | E8: =D8*1.1412 -> 4867218 | F8: 4867000 | G8: 4867000 | H8: 4867000 | I8: 4867000 | J8: 4867000 | K8: 4867000 | L8: 4867000 | M8: 4867000 | N8: 4867000 | O8: 4867000 | P8: 4867000 | Q8: 4867000 | R8: =SUM(F8:Q8) -> 58404000 | S8: =R8/U$4 -> 12836.044 | T8: =Q8/U$4 -> 1069.6703 | W8: =F8 -> 4867000 | X8: =G8 -> 4867000 | Y8: =H8 -> 4867000 | Z8: =I8 -> 4867000 | AA8: =J8 -> 4867000 | AB8: =+W8/$F$93 -> 1033.5256 | AC8: =+X8/$G$93 -> 1015.8213 | AD8: =+Y8/$H$93 -> 1022.8912 | AE8: =+Z8/$I$93 -> 1072.0091 | AF8: =+AA8/$U$4 -> 1069.6703 | AG8: =SUM(AB8:AF8) -> 5213.9176 | AI8: =SUM(K8:Q8)/$U$4 -> 7487.6923 | AJ8: =AG8+AI8 -> 12701.61
A9: Sara Castañeda | B9: Profesional de educación | C9: 1 | D9: 4265000 | E9: =D9*1.1412 -> 4867218 | F9: 4867000 | G9: 4867000 | H9: 4867000 | I9: 4867000 | J9: 4867000 | K9: 4867000 | L9: 4867000 | M9: 4867000 | N9: 4867000 | O9: 4867000 | P9: 4867000 | Q9: 4867000 | R9: =SUM(F9:Q9) -> 58404000 | S9: =R9/U$4 -> 12836.044 | T9: =Q9/U$4 -> 1069.6703 | W9: =F9 -> 4867000 | X9: =G9 -> 4867000 | Y9: =H9 -> 4867000 | Z9: =I9 -> 4867000 | AA9: =J9 -> 4867000 | AB9: =+W9/$F$93 -> 1033.5256 | AC9: =+X9/$G$93 -> 1015.8213 | AD9: =+Y9/$H$93 -> 1022.8912 | AE9: =+Z9/$I$93 -> 1072.0091 | AF9: =+AA9/$U$4 -> 1069.6703 | AG9: =SUM(AB9:AF9) -> 5213.9176 | AI9: =SUM(K9:Q9)/$U$4 -> 7487.6923 | AJ9: =AG9+AI9 -> 12701.61
A10: Juan David Colorado | B10: Profesional de monitoreo y evaluación | C10: 1 | D10: 3945000 | E10: 4200000 | F10: 3630938 | G10: 4096667 | H10: 4502000 | I10: 4502000 | J10: 4502000 | K10: 4502000 | L10: 4502000 | M10: 4502000 | N10: 4502000 | O10: 4502000 | P10: 4502000 | Q10: 4502000 | R10: =SUM(F10:Q10) -> 52747605 | S10: =R10/U$4 -> 11592.88 | T10: =Q10/U4 -> 989.45055 | W10: =F10 -> 3630938 | X10: =G10 -> 4096667 | Y10: =H10 -> 4502000 | Z10: =I10 -> 4502000 | AA10: =J10 -> 4502000 | AB10: =+W10/$F$93 -> 771.04322 | AC10: =+X10/$G$93 -> 855.04037 | AD10: =+Y10/$H$93 -> 946.17964 | AE10: =+Z10/$I$93 -> 991.61396 | AF10: =+AA10/$U$4 -> 989.45055 | AG10: =SUM(AB10:AF10) -> 4553.3277 | AI10: =SUM(K10:Q10)/$U$4 -> 6926.1538 | AJ10: =AG10+AI10 -> 11479.482
A11: Carolina Zuluaga | B11: Profesional logistica | C11: 1 | D11: 3412000 | E11: =D11*1.1412 -> 3893774.4 | F11: 3894000 | G11: 3894000 | H11: 3894000 | I11: 3894000 | J11: 3894000 | K11: 3894000 | L11: 4200000 | M11: 4200000 | N11: 4200000 | O11: 4200000 | P11: 4200000 | Q11: 4200000 | R11: =SUM(F11:Q11) -> 48564000 | S11: =R11/U$4 -> 10673.407 | T11: =Q11/U4 -> 923.07692 | W11: =F11 -> 3894000 | X11: =G11 -> 3894000 | Y11: =H11 -> 3894000 | Z11: =I11 -> 3894000 | AA11: =J11 -> 3894000 | AB11: =+W11/$F$93 -> 826.90542 | AC11: =+X11/$G$93 -> 812.7405 | AD11: =+Y11/$H$93 -> 818.39705 | AE11: =+Z11/$I$93 -> 857.69541 | AF11: =+AA11/$U$4 -> 855.82418 | AG11: =SUM(AB11:AF11) -> 4171.5626 | AI11: =SUM(K11:Q11)/$U$4 -> 6394.2857 | AJ11: =AG11+AI11 -> 10565.848
A12: Johnatan Diaz | B12: Profesional de proyectos | C12: 1 | D12: 4265000 | E12: =D12*1.1412 -> 4867218 | F12: 4867000 | G12: 4867000 | H12: 4867000 | I12: 4867000 | J12: 4867000 | K12: 4867000 | L12: 4867000 | M12: 4867000 | N12: 4867000 | O12: 4867000 | P12: 4867000 | Q12: 4867000 | R12: =SUM(F12:Q12) -> 58404000 | S12: =R12/U$4 -> 12836.044 | T12: =Q12/U4 -> 1069.6703 | W12: =F12 -> 4867000 | X12: =G12 -> 4867000 | Y12: =H12 -> 4867000 | Z12: =I12 -> 4867000 | AA12: =J12 -> 4867000 | AB12: =+W12/$F$93 -> 1033.5256 | AC12: =+X12/$G$93 -> 1015.8213 | AD12: =+Y12/$H$93 -> 1022.8912 | AE12: =+Z12/$I$93 -> 1072.0091 | AF12: =+AA12/$U$4 -> 1069.6703 | AG12: =SUM(AB12:AF12) -> 5213.9176 | AI12: =SUM(K12:Q12)/$U$4 -> 7487.6923 | AJ12: =AG12+AI12 -> 12701.61
A13: alba osorio | B13: Profesional de educación | C13: 1 | D13: =2450000*2 -> 4900000 | E13: =D13*1.1412 -> 5591880 | F13: 5592000 | G13: 5592000 | H13: 5592000 | I13: 5592000 | J13: 5592000 | K13: 5592000 | L13: 5592000 | M13: 5592000 | N13: 5592000 | O13: 5592000 | P13: 5592000 | Q13: 5592000 | R13: =SUM(F13:Q13) -> 67104000 | S13: =R13/U$4 -> 14748.132 | T13: =Q13/U4 -> 1229.011 | W13: =F13 -> 5592000 | X13: =G13 -> 5592000 | Y13: =H13 -> 5592000 | Z13: =I13 -> 5592000 | AA13: =J13 -> 5592000 | AB13: =+W13/$F$93 -> 1187.482 | AC13: =+X13/$G$93 -> 1167.1404 | AD13: =+Y13/$H$93 -> 1175.2636 | AE13: =+Z13/$I$93 -> 1231.6982 | AF13: =+AA13/$U$4 -> 1229.011 | AG13: =SUM(AB13:AF13) -> 5990.5952 | AI13: =SUM(K13:Q13)/$U$4 -> 8603.0769 | AJ13: =AG13+AI13 -> 14593.672
A14: Julieth Taborda | B14: profesional de educación | C14: 1 | D14: 4265000 | E14: =D14*1.1412 -> 4867218 | F14: 4867000 | G14: 4867000 | H14: 4867000 | I14: 4867000 | J14: 4867000 | K14: 4867000 | L14: 4867000 | M14: 4867000 | N14: 4867000 | O14: 4867000 | P14: 4867000 | Q14: 4867000 | R14: =SUM(F14:Q14) -> 58404000 | S14: =R14/U$4 -> 12836.044 | T14: =Q14/U4 -> 1069.6703 | W14: =F14 -> 4867000 | X14: =G14 -> 4867000 | Y14: =H14 -> 4867000 | Z14: =I14 -> 4867000 | AA14: =J14 -> 4867000 | AB14: =+W14/$F$93 -> 1033.5256 | AC14: =+X14/$G$93 -> 1015.8213 | AD14: =+Y14/$H$93 -> 1022.8912 | AE14: =+Z14/$I$93 -> 1072.0091 | AF14: =+AA14/$U$4 -> 1069.6703 | AG14: =SUM(AB14:AF14) -> 5213.9176 | AI14: =SUM(K14:Q14)/$U$4 -> 7487.6923 | AJ14: =AG14+AI14 -> 12701.61
A15: Analista de Metricas | B15: Analista de metricas | C15: 1 | D15: 3412000 | E15: =D15*1.1412 -> 3893774.4 | F15: 3894000 | G15: 0 | H15: 0 | I15: 0 | J15: 0 | K15: 0 | L15: 0 | M15: 0 | N15: 0 | O15: 0 | P15: 0 | Q15: 0 | R15: =SUM(F15:Q15) -> 3894000 | S15: =R15/U$4 -> 855.82418 | T15: =Q15/U4 -> 0 | W15: =F15 -> 3894000 | X15: =G15 -> 0 | Y15: =H15 -> 0 | Z15: =I15 -> 0 | AA15: =J15 -> 0 | AB15: =+W15/$F$93 -> 826.90542 | AC15: =+X15/$G$93 -> 0 | AD15: =+Y15/$H$93 -> 0 | AE15: =+Z15/$I$93 -> 0 | AF15: =+AA15/$U$4 -> 0 | AG15: =SUM(AB15:AF15) -> 826.90542 | AI15: =SUM(K15:Q15)/$U$4 -> 0 | AJ15: =AG15+AI15 -> 826.90542
A16: Karina anaya | B16: auxiliar administrativo | C16: 1 | D16: 2200000 | E16: =D16*1.16 -> 2552000 | F16: 2552000 | G16: 2552000 | H16: 2552000 | I16: 2552000 | J16: 2552000 | K16: 2552000 | L16: 2552000 | M16: 2552000 | N16: 2552000 | O16: 2552000 | P16: 2552000 | Q16: 2552000 | R16: =SUM(F16:Q16) -> 30624000 | S16: =R16/U$4 -> 6730.5495 | T16: =Q16/U4 -> 560.87912 | W16: =F16 -> 2552000 | X16: =G16 -> 2552000 | Y16: =H16 -> 2552000 | Z16: =I16 -> 2552000 | AA16: =J16 -> 2552000 | AB16: =+W16/$F$93 -> 541.92671 | AC16: =+X16/$G$93 -> 532.64349 | AD16: =+Y16/$H$93 -> 536.35061 | AE16: =+Z16/$I$93 -> 562.10547 | AF16: =+AA16/$U$4 -> 560.87912 | AG16: =SUM(AB16:AF16) -> 2733.9054 | AI16: =SUM(K16:Q16)/$U$4 -> 3926.1538 | AJ16: =AG16+AI16 -> 6660.0592
A17: Auxiliar operativo | B17: Auxiliar operativo | C17: 1 | D17: 2200000 | E17: =D17*1.1412 -> 2510640 | F17: 0 | G17: 1871466.7 | H17: 2552000 | I17: 2552000 | J17: 2552000 | K17: 2552000 | L17: 2552000 | M17: 2552000 | N17: 2552000 | O17: 2552000 | P17: 2552000 | Q17: 2552000 | R17: =SUM(F17:Q17) -> 27391467 | S17: =R17/U$4 -> 6020.1026 | T17: =Q17/U4 -> 560.87912 | W17: =F17 -> 0 | X17: =G17 -> 1871466.7 | Y17: =H17 -> 2552000 | Z17: =I17 -> 2552000 | AA17: =J17 -> 2552000 | AB17: =+W17/$F$93 -> 0 | AC17: =+X17/$G$93 -> 390.60523 | AD17: =+Y17/$H$93 -> 536.35061 | AE17: =+Z17/$I$93 -> 562.10547 | AF17: =+AA17/$U$4 -> 560.87912 | AG17: =SUM(AB17:AF17) -> 2049.9404 | AI17: =SUM(K17:Q17)/$U$4 -> 3926.1538 | AJ17: =AG17+AI17 -> 5976.0943
W18: =F18 -> 0 | X18: =G18 -> 0 | Y18: =H18 -> 0 | Z18: =I18 -> 0 | AA18: =J18 -> 0 | AB18: =+W18/$F$93 -> 0 | AC18: =+X18/$G$93 -> 0 | AD18: =+Y18/$H$93 -> 0 | AE18: =+Z18/$I$93 -> 0 | AF18: =+AA18/$U$4 -> 0 | AG18: =SUM(AB18:AF18) -> 0 | AI18: =SUM(K18:Q18)/$U$4 -> 0
A19: SEGURIDAD SOCIAL | B19: 10-10-89 | F19: =(F20+F21+F22)/F93 -> 15395.223 | G19: =(G20+G21)/G93 -> 4248.4697 | H19: =(H20/H93)+(H21/H94) -> 4244.0681 | I19: {=SUM(I20:I22/I93)} -> 3980.7642 | J19: {=SUM(J20:J22/$U$4)} -> 3972.0794 | K19: {=SUM(K20:K22/$U$4)} -> 10416.215 | L19: {=SUM(L20:L22/$U$4)} -> 3992.6184 | M19: {=SUM(M20:M22/$U$4)} -> 3992.6184 | N19: {=SUM(N20:N22/$U$4)} -> 3992.6184 | O19: {=SUM(O20:O22/$U$4)} -> 3992.6184 | P19: {=SUM(P20:P22/$U$4)} -> 3992.6184 | Q19: {=SUM(Q20:Q22/$U$4)} -> 16391.497 | R19: =SUM(F19:Q19) -> 78611.409 | W19: =F19 -> 15395.223 | X19: =G19 -> 4248.4697 | Y19: =H19 -> 4244.0681 | Z19: =I19 -> 3980.7642 | AA19: =J19 -> 3972.0794 | AB19: =+W19/$F$93 -> 3.269233 | AC19: =+X19/$G$93 -> 0.88672404 | AD19: =+Y19/$H$93 -> 0.89197043 | AE19: =+Z19/$I$93 -> 0.87680617 | AF19: =+AA19/$U$4 -> 0.87298448 | AG19: =SUM(AB19:AF19) -> 6.7977181 | AI19: =SUM(K19:Q19)/$U$4 -> 10.279298
A20: Seguridad social | F20: 19674112 | G20: 20355256 | H20: =SUM(H5:H17)*0.3054 -> 18072961 | I20: =SUM(I5:I17)*0.3054 -> 18072961 | J20: =SUM(J5:J17)*0.3054 -> 18072961 | K20: =SUM(K5:K17)*0.3054 -> 18072961 | L20: =SUM(L5:L17)*0.3054 -> 18166414 | M20: =SUM(M5:M17)*0.3054 -> 18166414 | N20: =SUM(N5:N17)*0.3054 -> 18166414 | O20: =SUM(O5:O17)*0.3054 -> 18166414 | ... Q20: =SUM(Q5:Q17)*0.3054 -> 18166414 | R20: =SUM(F20:Q20) -> 2.2131969e+08 | S20: =R20/U4 -> 48641.691 | W20: =F20 -> 19674112 | X20: =G20 -> 20355256 | Y20: =H20 -> 18072961 | Z20: =I20 -> 18072961 | AA20: =J20 -> 18072961 | AB20: =+W20/$F$93 -> 4177.8711 | AC20: =+X20/$G$93 -> 4248.4697 | AD20: =+Y20/$H$93 -> 3798.3714 | AE20: =+Z20/$I$93 -> 3980.7642 | AF20: =+AA20/$U$4 -> 3972.0794 | AG20: =SUM(AB20:AF20) -> 20177.556 | AI20: =SUM(K20:Q20)/$U$4 -> 27927.79 | AJ20: =AG20+AI20 -> 48105.345
A21: Primas por servicio y/o liquidaciones | F21: 21280775 | G21: 0 | H21: 2193510 | I21: 0 | J21: 0 | K21: 29320816 | L21: 0 | M21: 0 | N21: 0 | O21: 0 | P21: 0 | Q21: =SUM(Q5:Q17)*0.5 -> 29742000 | R21: =SUM(F21:Q21) -> 82537101 | S21: =R21/U4 -> 18140.022 | W21: =F21 -> 21280775 | X21: =G21 -> 0 | Y21: =H21 -> 2193510 | Z21: =I21 -> 0 | AA21: =J21 -> 0 | AB21: =+W21/$F$93 -> 4519.0519 | AC21: =+X21/$G$93 -> 0 | AD21: =+Y21/$H$93 -> 461.00722 | AE21: =+Z21/$I$93 -> 0 | AF21: =+AA21/$U$4 -> 0 | AG21: =SUM(AB21:AF21) -> 4980.0591 | AI21: =SUM(K21:Q21)/$U$4 -> 12980.839 | AJ21: =AG21+AI21 -> 17960.898
A22: Cesantías e intereses | F22: 31543125 | G22: 0 | H22: 0 | I22: 0 | J22: 0 | K22: 0 | L22: 0 | M22: 0 | N22: 0 | O22: 0 | P22: 0 | Q22: 26672900 | R22: =SUM(F22:Q22) -> 58216025 | S22: =R22/U4 -> 12794.731 | W22: =F22 -> 31543125 | X22: =G22 -> 0 | Y22: =H22 -> 0 | Z22: =I22 -> 0 | AA22: =J22 -> 0 | AB22: =+W22/$F$93 -> 6698.3002 | AC22: =+X22/$G$93 -> 0 | AD22: =+Y22/$H$93 -> 0 | AE22: =+Z22/$I$93 -> 0 | AF22: =+AA22/$U$4 -> 0 | AG22: =SUM(AB22:AF22) -> 6698.3002 | AI22: =SUM(K22:Q22)/$U$4 -> 5862.1758 | AJ22: =AG22+AI22 -> 12560.476
W23: =F23 -> 0 | X23: =G23 -> 0 | Y23: =H23 -> 0 | Z23: =I23 -> 0 | AA23: =J23 -> 0 | AB23: =+W23/$F$93 -> 0 | AC23: =+X23/$G$93 -> 0 | AD23: =+Y23/$H$93 -> 0 | AE23: =+Z23/$I$93 -> 0 | AF23: =+AA23/$U$4 -> 0 | AG23: =SUM(AB23:AF23) -> 0 | AI23: =SUM(K23:Q23)/$U$4 -> 0 | AJ23: =AG23+AI23 -> 0
A24: GENERAL O TRANSVERSAL | B24: 10-10-89 | F24: =SUM(F25:F30)/F93 -> 231.61578 | G24: =(SUM(G25:G30)/G93)+(429000/G93)-(429000/4369.073223) -> 738.02282 | H24: =SUM(H25:H30)/H93 -> 976.70256 | I24: =SUM(I25:I30)/I93 -> 1645.2908 | J24: =SUM(J25:J30)/$U$4 -> 2878.2418 | K24: =SUM(K25:K30)/$U$4 -> 889.23077 | L24: =SUM(L25:L30)/$U$4 -> 1152.967 | M24: =SUM(M25:M30)/$U$4 -> 746.37363 | N24: =SUM(N25:N30)/$U$4 -> 713.40659 | O24: =SUM(O25:O30)/$U$4 -> 669.45055 | P24: =SUM(P25:P30)/$U$4 -> 779.34066 | Q24: =SUM(Q25:Q30)/$U$4 -> 713.40659 | R24: =SUM(F24:Q24) -> 12134.05 | W24: =F24 -> 231.61578 | X24: =G24 -> 738.02282 | Y24: =H24 -> 976.70256 | Z24: =I24 -> 1645.2908 | AA24: =J24 -> 2878.2418 | AB24: =+W24/$F$93 -> 0.049184475 | AC24: =+X24/$G$93 -> 0.15403725 | AD24: =+Y24/$H$93 -> 0.20527234 | AE24: =+Z24/$I$93 -> 0.36239302 | AF24: =+AA24/$U$4 -> 0.63258061 | AG24: =SUM(AB24:AF24) -> 1.4034677 | AI24: =SUM(K24:Q24)/$U$4 -> 1.2448738
A25: Viajes | D25: =F13*1.54 -> 8611680 | F25: 0 | G25: =2884642-429000 -> 2455642 | H25: 1399725 | I25: 1330000 | J25: =3400000 -> 3400000 | K25: 0 | L25: 2000000 | M25: 0 | N25: 0 | O25: 0 | P25: 0 | Q25: 0 | R25: =SUM(F25:Q25) -> 10585367 | S25: =R25/U$4 -> 2326.4543 | W25: =F25 -> 0 | X25: =G25 -> 2455642 | Y25: =H25 -> 1399725 | Z25: =I25 -> 1330000 | AA25: =J25 -> 3400000 | AB25: =+W25/$F$93 -> 0 | AC25: =+X25/$G$93 -> 512.53203 | AD25: =+Y25/$H$93 -> 294.17843 | AE25: =+Z25/$I$93 -> 292.94681 | AF25: =+AA25/$U$4 -> 747.25275 | AG25: =SUM(AB25:AF25) -> 1846.91 | AI25: =SUM(K25:Q25)/$U$4 -> 439.56044 | AJ25: =AG25+AI25 -> 2286.4705
A26: Laptops and software (licencias) | F26: 0 | G26: 0 | H26: 0 | I26: 0 | J26: 5500000 | K26: 0 | L26: 0 | M26: 0 | N26: 0 | O26: 0 | P26: 0 | Q26: 0 | R26: =SUM(F26:Q26) -> 5500000 | S26: =R26/U$4 -> 1208.7912 | W26: =F26 -> 0 | X26: =G26 -> 0 | Y26: =H26 -> 0 | Z26: =I26 -> 0 | AA26: =J26 -> 5500000 | AB26: =+W26/$F$93 -> 0 | AC26: =+X26/$G$93 -> 0 | AD26: =+Y26/$H$93 -> 0 | AE26: =+Z26/$I$93 -> 0 | AF26: =+AA26/$U$4 -> 1208.7912 | AG26: =SUM(AB26:AF26) -> 1208.7912 | AI26: =SUM(K26:Q26)/$U$4 -> 0 | AJ26: =AG26+AI26 -> 1208.7912
A27: Banking and handling cash | F27: 541907.41 | G27: 406819.3 | H27: 520005.53 | I27: 747740.97 | J27: 350000 | K27: 350000 | L27: 350000 | M27: 350000 | N27: 350000 | O27: 350000 | P27: 350000 | Q27: 350000 | R27: =SUM(F27:Q27) -> 5016473.2 | S27: =R27/U$4 -> 1102.5216 | W27: =F27 -> 541907.41 | X27: =G27 -> 406819.3 | Y27: =H27 -> 520005.53 | Z27: =I27 -> 747740.97 | AA27: =J27 -> 350000 | AB27: =+W27/$F$93 -> 115.07606 | AC27: =+X27/$G$93 -> 84.909738 | AD27: =+Y27/$H$93 -> 109.2889 | AE27: =+Z27/$I$93 -> 164.698 | AF27: =+AA27/$U$4 -> 76.923077 | AG27: =SUM(AB27:AF27) -> 550.89577 | AI27: =SUM(K27:Q27)/$U$4 -> 538.46154 | AJ27: =AG27+AI27 -> 1089.3573
A28: suministros | F28: =284800+264000 -> 548800 | G28: 715000 | H28: 31500 | I28: 0 | J28: 1000000 | K28: 1000000 | L28: 200000 | M28: 200000 | N28: 200000 | O28: 0 | P28: 200000 | Q28: 200000 | R28: =SUM(F28:Q28) -> 4295300 | S28: =R28/U$4 -> 944.02198 | W28: =F28 -> 548800 | X28: =G28 -> 715000 | Y28: =H28 -> 31500 | Z28: =I28 -> 0 | AA28: =J28 -> 1000000 | AB28: =+W28/$F$93 -> 116.53973 | AC28: =+X28/$G$93 -> 149.23201 | AD28: =+Y28/$H$93 -> 6.6203151 | AE28: =+Z28/$I$93 -> 0 | AF28: =+AA28/$U$4 -> 219.78022 | AG28: =SUM(AB28:AF28) -> 492.17227 | AI28: =SUM(K28:Q28)/$U$4 -> 439.56044 | AJ28: =AG28+AI28 -> 931.73271
A29: locaciones Workspaces (Space, furniture, internet access, telephone and meeting room) | F29: 0 | G29: 0 | H29: 2696000 | I29: 5392000 | J29: 2696000 | K29: 2696000 | L29: 2696000 | M29: 2696000 | N29: 2696000 | O29: 2696000 | P29: 2696000 | Q29: 2696000 | R29: =SUM(F29:Q29) -> 29656000 | S29: =R29/U$4 -> 6517.8022 | W29: =F29 -> 0 | X29: =G29 -> 0 | Y29: =H29 -> 2696000 | Z29: =I29 -> 5392000 | AA29: =J29 -> 2696000 | AB29: =+W29/$F$93 -> 0 | AC29: =+X29/$G$93 -> 0 | AD29: =+Y29/$H$93 -> 566.61491 | AE29: =+Z29/$I$93 -> 1187.646 | AF29: =+AA29/$U$4 -> 592.52747 | AG29: =SUM(AB29:AF29) -> 2346.7884 | AI29: =SUM(K29:Q29)/$U$4 -> 4147.6923 | AJ29: =AG29+AI29 -> 6494.4807
A30: Alimentación en reuniones | F30: 0 | G30: 0 | H30: 0 | I30: 0 | J30: 150000 | K30: 0 | L30: 0 | M30: 150000 | N30: 0 | O30: 0 | P30: 300000 | Q30: 0 | R30: =SUM(F30:Q30) -> 600000 | S30: =R30/U$4 -> 131.86813 | W30: =F30 -> 0 | X30: =G30 -> 0 | Y30: =H30 -> 0 | Z30: =I30 -> 0 | AA30: =J30 -> 150000 | AB30: =+W30/$F$93 -> 0 | AC30: =+X30/$G$93 -> 0 | AD30: =+Y30/$H$93 -> 0 | AE30: =+Z30/$I$93 -> 0 | AF30: =+AA30/$U$4 -> 32.967033 | AG30: =SUM(AB30:AF30) -> 32.967033 | AI30: =SUM(K30:Q30)/$U$4 -> 98.901099 | AJ30: =AG30+AI30 -> 131.86813
W31: =F31 -> 0 | X31: =G31 -> 0 | Y31: =H31 -> 0 | Z31: =I31 -> 0 | AA31: =J31 -> 0 | AB31: =+W31/$F$93 -> 0 | AC31: =+X31/$G$93 -> 0 | AD31: =+Y31/$H$93 -> 0 | AE31: =+Z31/$I$93 -> 0 | AF31: =+AA31/$U$4 -> 0 | AG31: =SUM(AB31:AF31) -> 0 | AI31: =SUM(K31:Q31)/$U$4 -> 0 | AJ31: =AG31+AI31 -> 0
A32: SUBACTIVIDADES | F32: =F34+F44+F52+F60+F66+F77+F80 -> 5775.9427 | G32: =G34+G44+G52+G60+G66+G77+G80 -> 2503.069 | H32: =H34+H44+H52+H60+H66+H77+H80 -> 9150.2849 | I32: =I34+I44+I52+I60+I66+I77+I80 -> 10906.912 | J32: =J34+J44+J52+J60+J66+J77+J80 -> 32346.633 | K32: =K34+K44+K52+K60+K66+K77+K80 -> 14674.338 | L32: =L34+L44+L52+L60+L66+L77+L80 -> 28176.146 | M32: =M34+M44+M52+M60+M66+M77+M80 -> 25470.698 | ... Q32: =Q34+Q44+Q52+Q60+Q66+Q77+Q80 -> 8673.459 | R32: =SUM(F32:Q32) -> 197293.5 | W32: =F32 -> 5775.9427 | X32: =G32 -> 2503.069 | Y32: =H32 -> 9150.2849 | Z32: =I32 -> 10906.912 | AA32: =J32 -> 32346.633 | AB32: =+W32/$F$93 -> 1.226543 | AC32: =+X32/$G$93 -> 0.5224308 | AD32: =+Y32/$H$93 -> 1.9231038 | AE32: =+Z32/$I$93 -> 2.4023647 | AF32: =+AA32/$U$4 -> 7.10915 | AG32: =SUM(AB32:AF32) -> 13.183592 | AI32: =SUM(K32:Q32)/$U$4 -> 30.02432
W33: =F33 -> 0 | X33: =G33 -> 0 | Y33: =H33 -> 0 | Z33: =I33 -> 0 | AA33: =J33 -> 0 | AB33: =+W33/$F$93 -> 0 | AC33: =+X33/$G$93 -> 0 | AD33: =+Y33/$H$93 -> 0 | AE33: =+Z33/$I$93 -> 0 | AF33: =+AA33/$U$4 -> 0 | AG33: =SUM(AB33:AF33) -> 0 | AI33: =SUM(K33:Q33)/$U$4 -> 0 | AJ33: =AG33+AI33 -> 0
A34: SER+MAESTRO | B34: 10-10-84 | F34: =(SUM(F35:F42))/F93 -> 2376.6015 | G34: =((SUM(G35:G42))/G93)-533.75 -> -283.29068 | H34: =(SUM(H35:H42))/H93 -> 5073.411 | I34: =(SUM(I35:I42))/I93 -> 8127.8898 | J34: =(SUM(J35:J42))/$U$4 -> 20325.405 | K34: =(SUM(K35:K42))/$U$4 -> 6548.5593 | L34: =(SUM(L35:L42))/$U$4 -> 19835.998 | M34: =(SUM(M35:M42))/$U$4 -> 17130.549 | N34: =(SUM(N35:N42))/$U$4 -> 18833.195 | O34: =(SUM(O35:O42))/$U$4 -> 11380.515 | P34: =(SUM(P35:P42))/$U$4 -> 5857.2308 | Q34: =(SUM(Q35:Q42))/$U$4 -> 0 | R34: =SUM(F34:Q34) -> 115206.06 | S34: costo por sesion | T34: costo por grupo | W34: =F34 -> 2376.6015 | X34: =G34 -> -283.29068 | Y34: =H34 -> 5073.411 | Z34: =I34 -> 8127.8898 | AA34: =J34 -> 20325.405 | AB34: =+W34/$F$93 -> 0.5046802 | AC34: =+X34/$G$93 -> -0.059127326 | AD34: =+Y34/$H$93 -> 1.0662724 | AE34: =+Z34/$I$93 -> 1.7902552 | AF34: =+AA34/$U$4 -> 4.467122 | AG34: =SUM(AB34:AF34) -> 7.7692024 | AI34: =SUM(K34:Q34)/$U$4 -> 17.491439
A35: Travel | F35: 9991711 | G35: 0 | H35: 8839704 | I35: 18670703 | J35: 39134593 | K35: =16650000+366444.94-1551666.667 -> 15464778 | L35: 39897289 | M35: 50798889 | N35: 47054539 | O35: 36200343 | P35: =9069400+4000000 -> 13069400 | Q35: 0 | R35: =SUM(F35:Q35) -> 2.7912195e+08 | S35: 3.0182359e+08 | T35: =SUM(R35:R42) -> 5.2802974e+08 | U35: =R35/U$4 -> 61345.483 | W35: =F35 -> 9991711 | X35: =G35 -> 0 | Y35: =H35 -> 8839704 | Z35: =I35 -> 18670703 | AA35: =J35 -> 39134593 | AB35: =+W35/$F$93 -> 2121.7771 | AC35: =+X35/$G$93 -> 0 | AD35: =+Y35/$H$93 -> 1857.8294 | AE35: =+Z35/$I$93 -> 4112.4233 | AF35: =+AA35/$U$4 -> 8601.0094 | AG35: =SUM(AB35:AF35) -> 16693.039 | AI35: =SUM(K35:Q35)/$U$4 -> 44502.25 | AJ35: =AG35+AI35 -> 61195.289
A36: Auxilio de vivienda operación en Riohacha | F36: 0 | G36: 0 | H36: 0 | I36: 0 | J36: 0 | K36: 0 | L36: 1000000 | M36: 1000000 | N36: 1000000 | O36: 1000000 | P36: 0 | Q36: 0 | R36: =SUM(L36:Q36) -> 4000000
A37: Alimentación de maestros | F37: 0 | G37: 0 | I37: 1055120 | J37: 11361000 | K37: =4600000-1333333.333 -> 3266666.7 | L37: 10386500 | M37: 17041500 | N37: 17041500 | O37: 12361000 | P37: 11361000 | Q37: 0 | R37: =SUM(F37:Q37) -> 83874287 | S37: 93728250 | T37: =SUM(S35:S42) -> 5.2114852e+08 | U37: =R37/U$4 -> 18433.909 | W37: =F37 -> 0 | X37: =G37 -> 0 | Y37: =H37 -> 0 | Z37: =I37 -> 1055120 | AA37: =J37 -> 11361000 | AB37: =+W37/$F$93 -> 0 | AC37: =+X37/$G$93 -> 0 | AD37: =+Y37/$H$93 -> 0 | AE37: =+Z37/$I$93 -> 232.40154 | AF37: =+AA37/$U$4 -> 2496.9231 | AG37: =SUM(AB37:AF37) -> 2729.3246 | AI37: =SUM(K37:Q37)/$U$4 -> 15705.092 | AJ37: =AG37+AI37 -> 18434.416
A38: Development of teacher training books for Replica Workshops | F38: 0 | G38: 0 | H38: 4300000 | I38: 15850000 | J38: 12000000 | K38: 9864500 | L38: =18375000*2 -> 36750000 | M38: 6883610 | N38: 18375000 | O38: 0 | P38: 0 | Q38: 0 | R38: =SUM(F38:Q38) -> 104023110 | S38: 100601680 | T38: =T37-T35 -> -6881221.1 | U38: =R38/U$4 -> 22862.222 | W38: =F38 -> 0 | X38: =G38 -> 0 | Y38: =H38 -> 4300000 | Z38: =I38 -> 15850000 | AA38: =J38 -> 12000000 | AB38: =+W38/$F$93 -> 0 | AC38: =+X38/$G$93 -> 0 | AD38: =+Y38/$H$93 -> 903.72556 | AE38: =+Z38/$I$93 -> 3491.1331 | AF38: =+AA38/$U$4 -> 2637.3626 | AG38: =SUM(AB38:AF38) -> 7032.2213 | AI38: =SUM(K38:Q38)/$U$4 -> 15796.288 | AJ38: =AG38+AI38 -> 22828.509
A39: Transport of books for teacher training Replica Workshops | F39: 0 | G39: 0 | H39: 0 | I39: 0 | J39: =140000*0.75 -> 105000 | K39: 0 | L39: 0 | M39: 0 | N39: 0 | O39: 0 | P39: 0 | Q39: 0 | R39: =SUM(F39:Q39) -> 105000 | S39: 210000 | U39: =R39/U$4 -> 23.076923 | W39: =F39 -> 0 | X39: =G39 -> 0 | Y39: =H39 -> 0 | Z39: =I39 -> 0 | AA39: =J39 -> 105000 | AB39: =+W39/$F$93 -> 0 | AC39: =+X39/$G$93 -> 0 | AD39: =+Y39/$H$93 -> 0 | AE39: =+Z39/$I$93 -> 0 | AF39: =+AA39/$U$4 -> 23.076923 | AG39: =SUM(AB39:AF39) -> 23.076923 | AI39: =SUM(K39:Q39)/$U$4 -> 0 | AJ39: =AG39+AI39 -> 23.076923
A40: Suministros | F40: 0 | G40: 0 | H40: 0 | I40: =10500+114892 -> 125392 | J40: 680000 | K40: 0 | L40: 1020000 | M40: 1020000 | N40: 1020000 | O40: 1020000 | P40: 1020000 | Q40: 0 | R40: =SUM(F40:Q40) -> 5905392 | S40: 6290000 | U40: =R40/U$4 -> 1297.8884 | W40: =F40 -> 0 | X40: =G40 -> 0 | Y40: =H40 -> 0 | Z40: =I40 -> 125392 | AA40: =J40 -> 680000 | AB40: =+W40/$F$93 -> 0 | AC40: =+X40/$G$93 -> 0 | AD40: =+Y40/$H$93 -> 0 | AE40: =+Z40/$I$93 -> 27.618938 | AF40: =+AA40/$U$4 -> 149.45055 | AG40: =SUM(AB40:AF40) -> 177.06949 | AI40: =SUM(K40:Q40)/$U$4 -> 1120.8791 | AJ40: =AG40+AI40 -> 1297.9486
A41: Graphic design of classroom guides | F41: 0 | G41: 0 | H41: 9800000 | I41: 0 | J41: =16000000+12000000 -> 28000000 | K41: 0 | L41: 0 | M41: 0 | N41: 0 | O41: 0 | P41: 0 | Q41: 0 | R41: =SUM(F41:Q41) -> 37800000 | S41: 4095000 | U41: =R41/U$4 -> 8307.6923 | W41: =F41 -> 0 | X41: =G41 -> 0 | Y41: =H41 -> 9800000 | Z41: =I41 -> 0 | AA41: =J41 -> 28000000 | AB41: =+W41/$F$93 -> 0 | AC41: =+X41/$G$93 -> 0 | AD41: =+Y41/$H$93 -> 2059.6536 | AE41: =+Z41/$I$93 -> 0 | AF41: =+AA41/$U$4 -> 6153.8462 | AG41: =SUM(AB41:AF41) -> 8213.4998 | AI41: =SUM(K41:Q41)/$U$4 -> 0 | AJ41: =AG41+AI41 -> 8213.4998
A42: Bodega - locaciones Workspaces (Space, furniture, internet access, telephone and meeting room) | F42: 1200000 | G42: 1200000 | H42: 1200000 | I42: 1200000 | J42: 1200000 | K42: 1200000 | L42: 1200000 | M42: 1200000 | N42: 1200000 | O42: 1200000 | P42: 1200000 | Q42: 0 | R42: =SUM(F42:Q42) -> 13200000 | S42: 14400000 | U42: =R42/U$4 -> 2901.0989 | W42: =F42 -> 1200000 | X42: =G42 -> 1200000 | Y42: =H42 -> 1200000 | Z42: =I42 -> 1200000 | AA42: =J42 -> 1200000 | AB42: =+W42/$F$93 -> 254.82447 | AC42: =+X42/$G$93 -> 250.45932 | AD42: =+Y42/$H$93 -> 252.20248 | AE42: =+Z42/$I$93 -> 264.31292 | AF42: =+AA42/$U$4 -> 263.73626 | AG42: =SUM(AB42:AF42) -> 1285.5355 | AI42: =SUM(K42:Q42)/$U$4 -> 1582.4176 | AJ42: =AG42+AI42 -> 2867.953
W43: =F43 -> 0 | X43: =G43 -> 0 | Y43: =H43 -> 0 | Z43: =I43 -> 0 | AA43: =J43 -> 0 | AB43: =+W43/$F$93 -> 0 | AC43: =+X43/$G$93 -> 0 | AD43: =+Y43/$H$93 -> 0 | AE43: =+Z43/$I$93 -> 0 | AF43: =+AA43/$U$4 -> 0 | AG43: =SUM(AB43:AF43) -> 0 | AI43: =SUM(K43:Q43)/$U$4 -> 0 | AJ43: =AG43+AI43 -> 0
A44: PARCHE | B44: 10-10-85 | F44: =(SUM(F45:F50))/4910 -> 0 | G44: 0 | H44: =(SUM(H45:H50))/4900 -> 0 | I44: =(SUM(I45:I50))/4900 -> 0 | J44: =(SUM(J45:J50))/4900 -> 0 | K44: =(SUM(K45:K50))/4900 -> 0 | L44: =(SUM(L45:L50))/4900 -> 0 | M44: =(SUM(M45:M50))/4900 -> 0 | N44: =(SUM(N45:N50))/4900 -> 0 | O44: =(SUM(O45:O50))/4910 -> 0 | P44: =(SUM(P45:P50))/4900 -> 0 | Q44: =(SUM(Q45:Q50))/4900 -> 0 | R44: =SUM(F44:Q44) -> 0 | W44: =F44 -> 0 | X44: =G44 -> 0 | Y44: =H44 -> 0 | Z44: =I44 -> 0 | AA44: =J44 -> 0 | AB44: =+W44/$F$93 -> 0 | AC44: =+X44/$G$93 -> 0 | AD44: =+Y44/$H$93 -> 0 | AE44: =+Z44/$I$93 -> 0 | AF44: =+AA44/$U$4 -> 0 | AG44: =SUM(AB44:AF44) -> 0 | AI44: =SUM(K44:Q44)/$U$4 -> 0 | AJ44: =AG44+AI44 -> 0
A45: Travel | F45: 0 | G45: 0 | H45: 0 | I45: 0 | J45: 0 | K45: 0 | L45: 0 | M45: 0 | N45: 0 | O45: 0 | P45: 0 | Q45: 0 | R45: =SUM(F45:Q45) -> 0 | W45: =F45 -> 0 | X45: =G45 -> 0 | Y45: =H45 -> 0 | Z45: =I45 -> 0 | AA45: =J45 -> 0 | AB45: =+W45/$F$93 -> 0 | AC45: =+X45/$G$93 -> 0 | AD45: =+Y45/$H$93 -> 0 | AE45: =+Z45/$I$93 -> 0 | AF45: =+AA45/$U$4 -> 0 | AG45: =SUM(AB45:AF45) -> 0 | AI45: =SUM(K45:Q45)/$U$4 -> 0 | AJ45: =AG45+AI45 -> 0
A46: Alimentación de maestros | F46: 0 | G46: 0 | H46: 0 | I46: 0 | J46: 0 | K46: 0 | L46: 0 | M46: 0 | N46: 0 | O46: 0 | P46: 0 | Q46: 0 | R46: =SUM(F46:Q46) -> 0 | W46: =F46 -> 0 | X46: =G46 -> 0 | Y46: =H46 -> 0 | Z46: =I46 -> 0 | AA46: =J46 -> 0 | AB46: =+W46/$F$93 -> 0 | AC46: =+X46/$G$93 -> 0 | AD46: =+Y46/$H$93 -> 0 | AE46: =+Z46/$I$93 -> 0 | AF46: =+AA46/$U$4 -> 0 | AG46: =SUM(AB46:AF46) -> 0 | AI46: =SUM(K46:Q46)/$U$4 -> 0 | AJ46: =AG46+AI46 -> 0
A47: Consultores-contratistas | B47: hotel, viaticos y tiquetes para tener una experiencia exitosa por subactividad (y 2 mas de las subactividades d elos tors socios) y por cad auna de las ciudadades + espacios y todo el equipo nuestro apoyando (viatixcos y tiquetes) y un solo speaker + seria un evento de 2 dias (tiquetes y viativpoxs ´para 3 dias) + espacios | F47: 0 | G47: 0 | H47: 0 | I47: 0 | J47: 0 | K47: 0 | L47: 0 | M47: 0 | N47: 0 | O47: 0 | P47: 0 | Q47: 0 | R47: =SUM(F47:Q47) -> 0 | W47: =F47 -> 0 | X47: =G47 -> 0 | Y47: =H47 -> 0 | Z47: =I47 -> 0 | AA47: =J47 -> 0 | AB47: =+W47/$F$93 -> 0 | AC47: =+X47/$G$93 -> 0 | AD47: =+Y47/$H$93 -> 0 | AE47: =+Z47/$I$93 -> 0 | AF47: =+AA47/$U$4 -> 0 | AG47: =SUM(AB47:AF47) -> 0 | AI47: =SUM(K47:Q47)/$U$4 -> 0 | AJ47: =AG47+AI47 -> 0
A48: Graphic and operational design of digital courses | F48: 0 | G48: 0 | H48: 0 | I48: 0 | J48: 0 | K48: 0 | L48: 0 | M48: 0 | N48: 0 | O48: 0 | P48: 0 | Q48: 0 | R48: =SUM(F48:Q48) -> 0 | W48: =F48 -> 0 | X48: =G48 -> 0 | Y48: =H48 -> 0 | Z48: =I48 -> 0 | AA48: =J48 -> 0 | AB48: =+W48/$F$93 -> 0 | AC48: =+X48/$G$93 -> 0 | AD48: =+Y48/$H$93 -> 0 | AE48: =+Z48/$I$93 -> 0 | AF48: =+AA48/$U$4 -> 0 | AG48: =SUM(AB48:AF48) -> 0 | AI48: =SUM(K48:Q48)/$U$4 -> 0 | AJ48: =AG48+AI48 -> 0
A49: Development of digital network strategy for Parche Maestro | F49: 0 | G49: 0 | H49: 0 | I49: 0 | J49: 0 | K49: 0 | L49: 0 | M49: 0 | N49: 0 | O49: 0 | P49: 0 | Q49: 0 | R49: =SUM(F49:Q49) -> 0 | W49: =F49 -> 0 | X49: =G49 -> 0 | Y49: =H49 -> 0 | Z49: =I49 -> 0 | AA49: =J49 -> 0 | AB49: =+W49/$F$93 -> 0 | AC49: =+X49/$G$93 -> 0 | AD49: =+Y49/$H$93 -> 0 | AE49: =+Z49/$I$93 -> 0 | AF49: =+AA49/$U$4 -> 0 | AG49: =SUM(AB49:AF49) -> 0 | AI49: =SUM(K49:Q49)/$U$4 -> 0 | AJ49: =AG49+AI49 -> 0
A50: Personal Protective Equipment (Gloves, Masks, Hand Sanitizer, Antibacterial Wipes etc.) | F50: 0 | G50: 0 | H50: 0 | I50: 0 | J50: 0 | K50: 0 | L50: 0 | M50: 0 | N50: 0 | O50: 0 | P50: 0 | Q50: 0 | R50: =SUM(F50:Q50) -> 0 | W50: =F50 -> 0 | X50: =G50 -> 0 | Y50: =H50 -> 0 | Z50: =I50 -> 0 | AA50: =J50 -> 0 | AB50: =+W50/$F$93 -> 0 | AC50: =+X50/$G$93 -> 0 | AD50: =+Y50/$H$93 -> 0 | AE50: =+Z50/$I$93 -> 0 | AF50: =+AA50/$U$4 -> 0 | AG50: =SUM(AB50:AF50) -> 0 | AI50: =SUM(K50:Q50)/$U$4 -> 0 | AJ50: =AG50+AI50 -> 0
W51: =F51 -> 0 | X51: =G51 -> 0 | Y51: =H51 -> 0 | Z51: =I51 -> 0 | AA51: =J51 -> 0 | AB51: =+W51/$F$93 -> 0 | AC51: =+X51/$G$93 -> 0 | AD51: =+Y51/$H$93 -> 0 | AE51: =+Z51/$I$93 -> 0 | AF51: =+AA51/$U$4 -> 0 | AG51: =SUM(AB51:AF51) -> 0 | AI51: =SUM(K51:Q51)/$U$4 -> 0 | AJ51: =AG51+AI51 -> 0
A52: POLITICAS PUBLICAS | B52: 10-10-87 | F52: =(SUM(F53:F58))/F93 -> 0 | G52: =G54/G93 -> -171.75665 | H52: =(SUM(H53:H58))/U4 -> 0 | I52: =(SUM(I53:I58))/U4 -> 0 | J52: =(SUM(J53:J58))/U4 -> 0 | K52: =(SUM(K53:K58))/U4 -> 0 | L52: =(SUM(L53:L58))/U4 -> 0 | M52: =(SUM(M53:M58))/U4 -> 0 | N52: =(SUM(N53:N58))/U4 -> 0 | O52: =(SUM(O53:O58))/U4 -> 0 | P52: =(SUM(P53:P58))/U4 -> 0 | Q52: =(SUM(Q53:Q58))/U4 -> 0 | R52: =SUM(F52:Q52) -> -171.75665 | W52: =F52 -> 0 | X52: =G52 -> -171.75665 | Y52: =H52 -> 0 | Z52: =I52 -> 0 | AA52: =J52 -> 0 | AB52: =+W52/$F$93 -> 0 | AC52: =+X52/$G$93 -> -0.035848379 | AD52: =+Y52/$H$93 -> 0 | AE52: =+Z52/$I$93 -> 0 | AF52: =+AA52/$U$4 -> 0 | AG52: =SUM(AB52:AF52) -> -0.035848379 | AI52: =SUM(K52:Q52)/$U$4 -> 0
A53: Travel | F53: 0 | G53: 0 | H53: 0 | I53: 0 | J53: 0 | K53: 0 | L53: 0 | M53: 0 | N53: 0 | O53: 0 | P53: 0 | Q53: 0 | R53: =SUM(F53:Q53) -> 0 | W53: =F53 -> 0 | X53: =G53 -> 0 | Y53: =H53 -> 0 | Z53: =I53 -> 0 | AA53: =J53 -> 0 | AB53: =+W53/$F$93 -> 0 | AC53: =+X53/$G$93 -> 0 | AD53: =+Y53/$H$93 -> 0 | AE53: =+Z53/$I$93 -> 0 | AF53: =+AA53/$U$4 -> 0 | AG53: =SUM(AB53:AF53) -> 0 | AI53: =SUM(K53:Q53)/$U$4 -> 0 | AJ53: =AG53+AI53 -> 0
A54: Consultant for technical advice for advocacy on public policy | G54: -822920 | H54: 0 | I54: 0 | J54: 0 | K54: 0 | L54: 0 | M54: 0 | N54: 0 | O54: 0 | P54: 0 | Q54: 0 | R54: =SUM(G54:Q54) -> -822920 | W54: =F54 -> 0 | X54: =G54 -> -822920 | Y54: =H54 -> 0 | Z54: =I54 -> 0 | AA54: =J54 -> 0 | AB54: =+W54/$F$93 -> 0 | AC54: =+X54/$G$93 -> -171.75665 | AD54: =+Y54/$H$93 -> 0 | AE54: =+Z54/$I$93 -> 0 | AF54: =+AA54/$U$4 -> 0 | AG54: =SUM(AB54:AF54) -> -171.75665 | AI54: =SUM(K54:Q54)/$U$4 -> 0 | AJ54: =AG54+AI54 -> -171.75665
A55: Round table with local private sector to build public policy guidelines | F55: 0 | G55: 0 | H55: 0 | I55: 0 | J55: 0 | K55: 0 | L55: 0 | M55: 0 | N55: 0 | O55: 0 | P55: 0 | Q55: 0 | R55: =SUM(F55:Q55) -> 0 | W55: =F55 -> 0 | X55: =G55 -> 0 | Y55: =H55 -> 0 | Z55: =I55 -> 0 | AA55: =J55 -> 0 | AB55: =+W55/$F$93 -> 0 | AC55: =+X55/$G$93 -> 0 | AD55: =+Y55/$H$93 -> 0 | AE55: =+Z55/$I$93 -> 0 | AF55: =+AA55/$U$4 -> 0 | AG55: =SUM(AB55:AF55) -> 0 | AI55: =SUM(K55:Q55)/$U$4 -> 0 | AJ55: =AG55+AI55 -> 0
A56: Regional workshops about strategic themes of public policy guidelines | F56: 0 | G56: 0 | H56: 0 | I56: 0 | J56: 0 | K56: 0 | L56: 0 | M56: 0 | N56: 0 | O56: 0 | P56: 0 | Q56: 0 | R56: =SUM(F56:Q56) -> 0 | W56: =F56 -> 0 | X56: =G56 -> 0 | Y56: =H56 -> 0 | Z56: =I56 -> 0 | AA56: =J56 -> 0 | AB56: =+W56/$F$93 -> 0 | AC56: =+X56/$G$93 -> 0 | AD56: =+Y56/$H$93 -> 0 | AE56: =+Z56/$I$93 -> 0 | AF56: =+AA56/$U$4 -> 0 | AG56: =SUM(AB56:AF56) -> 0 | AI56: =SUM(K56:Q56)/$U$4 -> 0 | AJ56: =AG56+AI56 -> 0
A57: Suministros | F57: 0 | G57: 0 | H57: 0 | I57: 0 | J57: 0 | K57: 0 | L57: 0 | M57: 0 | N57: 0 | O57: 0 | P57: 0 | Q57: 0 | R57: =SUM(F57:Q57) -> 0 | W57: =F57 -> 0 | X57: =G57 -> 0 | Y57: =H57 -> 0 | Z57: =I57 -> 0 | AA57: =J57 -> 0 | AB57: =+W57/$F$93 -> 0 | AC57: =+X57/$G$93 -> 0 | AD57: =+Y57/$H$93 -> 0 | AE57: =+Z57/$I$93 -> 0 | AF57: =+AA57/$U$4 -> 0 | AG57: =SUM(AB57:AF57) -> 0 | AI57: =SUM(K57:Q57)/$U$4 -> 0 | AJ57: =AG57+AI57 -> 0
A58: Data Collection Tools | F58: 0 | G58: 0 | H58: 0 | I58: 0 | J58: 0 | K58: 0 | L58: 0 | M58: 0 | N58: 0 | O58: 0 | P58: 0 | Q58: 0 | R58: =SUM(F58:Q58) -> 0 | W58: =F58 -> 0 | X58: =G58 -> 0 | Y58: =H58 -> 0 | Z58: =I58 -> 0 | AA58: =J58 -> 0 | AB58: =+W58/$F$93 -> 0 | AC58: =+X58/$G$93 -> 0 | AD58: =+Y58/$H$93 -> 0 | AE58: =+Z58/$I$93 -> 0 | AF58: =+AA58/$U$4 -> 0 | AG58: =SUM(AB58:AF58) -> 0 | AI58: =SUM(K58:Q58)/$U$4 -> 0 | AJ58: =AG58+AI58 -> 0
W59: =F59 -> 0 | X59: =G59 -> 0 | Y59: =H59 -> 0 | Z59: =I59 -> 0 | AA59: =J59 -> 0 | AB59: =+W59/$F$93 -> 0 | AC59: =+X59/$G$93 -> 0 | AD59: =+Y59/$H$93 -> 0 | AE59: =+Z59/$I$93 -> 0 | AF59: =+AA59/$U$4 -> 0 | AG59: =SUM(AB59:AF59) -> 0 | AI59: =SUM(K59:Q59)/$U$4 -> 0 | AJ59: =AG59+AI59 -> 0
A60: DIRECTIVOS DOCENTES | B60: 10-10-83 | F60: =(SUM(F61:F64))/U4 -> 0 | G60: =(SUM(G61:G64))/U4 -> 0 | H60: =(SUM(H61:H64))/U4 -> 0 | I60: =(SUM(I61:I64))/U4 -> 0 | J60: =(SUM(J61:J64))/$U$4 -> 1629.2171 | K60: =(SUM(K61:K64))/$U$4 -> 0 | L60: =(SUM(L61:L64))/$U$4 -> 1585.2611 | M60: =(SUM(M61:M64))/$U$4 -> 1585.2611 | N60: =(SUM(N61:N64))/$U$4 -> 1585.2611 | O60: =(SUM(O61:O64))/$U$4 -> 1585.2611 | P60: =(SUM(P61:P64))/$U$4 -> 0 | Q60: =(SUM(Q61:Q64))/$U$4 -> 0 | R60: =SUM(F60:Q60) -> 7970.2614 | W60: =F60 -> 0 | X60: =G60 -> 0 | Y60: =H60 -> 0 | Z60: =I60 -> 0 | AA60: =J60 -> 1629.2171 | AB60: =+W60/$F$93 -> 0 | AC60: =+X60/$G$93 -> 0 | AD60: =+Y60/$H$93 -> 0 | AE60: =+Z60/$I$93 -> 0 | AF60: =+AA60/$U$4 -> 0.35806969 | AG60: =SUM(AB60:AF60) -> 0.35806969 | AI60: =SUM(K60:Q60)/$U$4 -> 1.3936361
A61: Travel | F61: 0 | G61: 0 | H61: 0 | I61: 0 | J61: 6121137.8 | K61: 0 | L61: =J61 -> 6121137.8 | M61: =L61 -> 6121137.8 | N61: =M61 -> 6121137.8 | O61: =N61 -> 6121137.8 | P61: 0 | Q61: 0 | R61: =SUM(F61:Q61) -> 30605689 | T61: =R61/U$4 -> 6726.5251 | W61: =F61 -> 0 | X61: =G61 -> 0 | Y61: =H61 -> 0 | Z61: =I61 -> 0 | AA61: =J61 -> 6121137.8 | AB61: =+W61/$F$93 -> 0 | AC61: =+X61/$G$93 -> 0 | AD61: =+Y61/$H$93 -> 0 | AE61: =+Z61/$I$93 -> 0 | AF61: =+AA61/$U$4 -> 1345.305 | AG61: =SUM(AB61:AF61) -> 1345.305 | AI61: =SUM(K61:Q61)/$U$4 -> 5381.2201 | AJ61: =AG61+AI61 -> 6726.5251
A62: Personal Protective Equipment (Gloves, Masks, Hand Sanitizer, Antibacterial Wipes etc.) | F62: 0 | G62: 0 | H62: 0 | I62: 0 | J62: 200000 | K62: 0 | L62: 0 | M62: 0 | N62: 0 | O62: 0 | P62: 0 | Q62: 0 | R62: =SUM(F62:Q62) -> 200000 | T62: =R62/U$4 -> 43.956044 | W62: =F62 -> 0 | X62: =G62 -> 0 | Y62: =H62 -> 0 | Z62: =I62 -> 0 | AA62: =J62 -> 200000 | AB62: =+W62/$F$93 -> 0 | AC62: =+X62/$G$93 -> 0 | AD62: =+Y62/$H$93 -> 0 | AE62: =+Z62/$I$93 -> 0 | AF62: =+AA62/$U$4 -> 43.956044 | AG62: =SUM(AB62:AF62) -> 43.956044 | AI62: =SUM(K62:Q62)/$U$4 -> 0 | AJ62: =AG62+AI62 -> 43.956044
A63: Alimentación de maestros/asistentes | F63: 0 | G63: 0 | H63: 0 | I63: 0 | J63: =I63+1000000 -> 1000000 | K63: 0 | L63: =J63 -> 1000000 | M63: =L63 -> 1000000 | N63: =M63 -> 1000000 | O63: =N63 -> 1000000 | P63: 0 | Q63: 0 | R63: =SUM(F63:Q63) -> 5000000 | T63: =R63/U$4 -> 1098.9011 | W63: =F63 -> 0 | X63: =G63 -> 0 | Y63: =H63 -> 0 | Z63: =I63 -> 0 | AA63: =J63 -> 1000000 | AB63: =+W63/$F$93 -> 0 | AC63: =+X63/$G$93 -> 0 | AD63: =+Y63/$H$93 -> 0 | AE63: =+Z63/$I$93 -> 0 | AF63: =+AA63/$U$4 -> 219.78022 | AG63: =SUM(AB63:AF63) -> 219.78022 | AI63: =SUM(K63:Q63)/$U$4 -> 879.12088 | AJ63: =AG63+AI63 -> 1098.9011
A64: Suministros | F64: 0 | G64: 0 | H64: 0 | I64: 0 | J64: 91800 | K64: 0 | L64: 91800 | M64: 91800 | N64: 91800 | O64: 91800 | P64: 0 | Q64: 0 | R64: =SUM(F64:Q64) -> 459000 | T64: =R64/U$4 -> 100.87912 | W64: =F64 -> 0 | X64: =G64 -> 0 | Y64: =H64 -> 0 | Z64: =I64 -> 0 | AA64: =J64 -> 91800 | AB64: =+W64/$F$93 -> 0 | AC64: =+X64/$G$93 -> 0 | AD64: =+Y64/$H$93 -> 0 | AE64: =+Z64/$I$93 -> 0 | AF64: =+AA64/$U$4 -> 20.175824 | AG64: =SUM(AB64:AF64) -> 20.175824 | AI64: =SUM(K64:Q64)/$U$4 -> 80.703297 | AJ64: =AG64+AI64 -> 100.87912
W65: =F65 -> 0 | X65: =G65 -> 0 | Y65: =H65 -> 0 | Z65: =I65 -> 0 | AA65: =J65 -> 0 | AB65: =+W65/$F$93 -> 0 | AC65: =+X65/$G$93 -> 0 | AD65: =+Y65/$H$93 -> 0 | AE65: =+Z65/$I$93 -> 0 | AF65: =+AA65/$U$4 -> 0 | AG65: =SUM(AB65:AF65) -> 0 | AI65: =SUM(K65:Q65)/$U$4 -> 0 | AJ65: =AG65+AI65 -> 0
A66: ALIANZAS | B66: 10-10-88 | F66: =(SUM(F67:F75))/F93 -> 2903.4952 | G66: =(SUM(G67:G75))/G93 -> 2331.968 | H66: =(SUM(H67:H75))/H93 -> 4076.8738 | I66: =(SUM(I67:I75))/I93 -> 2779.0218 | J66: =(SUM(J67:J75))/$U$4 -> 10282.12 | K66: =(SUM(K67:K75))/$U$4 -> 8125.7789 | L66: =(SUM(L67:L75))/$U$4 -> 6754.8876 | M66: =(SUM(M67:M75))/$U$4 -> 6754.8876 | N66: =(SUM(N67:N75))/$U$4 -> 6754.8876 | O66: =(SUM(O67:O75))/$U$4 -> 6754.8876 | P66: =(SUM(P67:P75))/$U$4 -> 6754.8876 | Q66: =(SUM(Q67:Q75))/$U$4 -> 8673.459 | R66: =SUM(F66:Q66) -> 72947.155 | W66: =F66 -> 2903.4952 | X66: =G66 -> 2331.968 | Y66: =H66 -> 4076.8738 | Z66: =I66 -> 2779.0218 | AA66: =J66 -> 10282.12 | AB66: =+W66/$F$93 -> 0.61656804 | AC66: =+X66/$G$93 -> 0.48671927 | AD66: =+Y66/$H$93 -> 0.85683141 | AE66: =+Z66/$I$93 -> 0.61210946 | AF66: =+AA66/$U$4 -> 2.2598067 | AG66: =SUM(AB66:AF66) -> 4.8320349 | AI66: =SUM(K66:Q66)/$U$4 -> 11.115094
A67: Salario Dir Alianzas | B67: Directora de alianzas | C67: 1 | F67: 2500000 | G67: 0 | H67: 0 | I67: 0 | J67: 10196667 | K67: 13300000 | L67: 13300000 | M67: 13300000 | N67: 13300000 | O67: 13300000 | P67: 13300000 | Q67: =P67 -> 13300000 | R67: =SUM(F67:Q67) -> 105796667 | S67: =R67/U$4 -> 23252.015 | T67: =P67/U$4 -> 2923.0769 | W67: =F67 -> 2500000 | X67: =G67 -> 0 | Y67: =H67 -> 0 | Z67: =I67 -> 0 | AA67: =J67 -> 10196667 | AB67: =+W67/$F$93 -> 530.88432 | AC67: =+X67/$G$93 -> 0 | AD67: =+Y67/$H$93 -> 0 | AE67: =+Z67/$I$93 -> 0 | AF67: =+AA67/$U$4 -> 2241.0257 | AG67: =SUM(AB67:AF67) -> 2771.91 | AI67: =SUM(K67:Q67)/$U$4 -> 20461.538 | AJ67: =AG67+AI67 -> 23233.448
A68: Seg social Dir Alianzas | B68: Directora de alianzas | C68: 0.524 | F68: 0 | G68: =G67*0.524 -> 0 | H68: =H67*0.524 -> 0 | I68: =I67*0.524 -> 0 | J68: =J67*0.3054 -> 3114062.1 | K68: =K67*0.3054 -> 4061820 | L68: =L67*0.3054 -> 4061820 | M68: =M67*0.3054 -> 4061820 | N68: =N67*0.3054 -> 4061820 | O68: =O67*0.3054 -> 4061820 | P68: =P67*0.3054 -> 4061820 | Q68: =Q67*0.3054 -> 4061820 | R68: =SUM(F68:Q68) -> 31546802 | S68: =R68/U$4 -> 6933.3631 | T68: =Q68/U$4 -> 892.70769 | W68: =F68 -> 0 | X68: =G68 -> 0 | Y68: =H68 -> 0 | Z68: =I68 -> 0 | AA68: =J68 -> 3114062.1 | AB68: =+W68/$F$93 -> 0 | AC68: =+X68/$G$93 -> 0 | AD68: =+Y68/$H$93 -> 0 | AE68: =+Z68/$I$93 -> 0 | AF68: =+AA68/$U$4 -> 684.40925 | AG68: =SUM(AB68:AF68) -> 684.40925 | AI68: =SUM(K68:Q68)/$U$4 -> 6248.9538 | AJ68: =AG68+AI68 -> 6933.3631
A69: Salario coord alianzas | B69: Coordinadora de alianzas | C69: 1 | D69: 7500000 | E69: =D69*1.1412 -> 8559000 | F69: 8559000 | G69: 8559000 | H69: 8559000 | I69: 8559000 | J69: 8559000 | K69: =J69 -> 8559000 | L69: 8559000 | M69: 8559000 | N69: 8559000 | O69: 8559000 | P69: 8559000 | Q69: =P69 -> 8559000 | R69: =SUM(F69:Q69) -> 102708000 | S69: =R69/U$4 -> 22573.187 | T69: =Q69/U$4 -> 1881.0989 | W69: =F69 -> 8559000 | X69: =G69 -> 8559000 | Y69: =H69 -> 8559000 | Z69: =I69 -> 8559000 | AA69: =J69 -> 8559000 | AB69: =+W69/$F$93 -> 1817.5356 | AC69: =+X69/$G$93 -> 1786.4011 | AD69: =+Y69/$H$93 -> 1798.8342 | AE69: =+Z69/$I$93 -> 1885.2119 | AF69: =+AA69/$U$4 -> 1881.0989 | AG69: =SUM(AB69:AF69) -> 9169.0816 | AI69: =SUM(K69:Q69)/$U$4 -> 13167.692 | AJ69: =AG69+AI69 -> 22336.774
A70: Seg social Coord alianzas | B70: Coordinadora de alianzas | C70: 0.524 | F70: =F69*0.3054 -> 2613918.6 | G70: =G69*0.3054 -> 2613918.6 | H70: =H69*0.3054 -> 2613918.6 | I70: =I69*0.3054 -> 2613918.6 | J70: =J69*0.3054 -> 2613918.6 | K70: =K69*0.3054 -> 2613918.6 | L70: =L69*0.3054 -> 2613918.6 | M70: =M69*0.3054 -> 2613918.6 | ... Q70: =Q69*0.3054 -> 2613918.6 | R70: =SUM(F70:Q70) -> 31367023 | S70: =R70/U$4 -> 6893.8513 | T70: =Q70/U$4 -> 574.4876 | W70: =F70 -> 2613918.6 | X70: =G70 -> 2613918.6 | Y70: =H70 -> 2613918.6 | Z70: =I70 -> 2613918.6 | AA70: =J70 -> 2613918.6 | AB70: =+W70/$F$93 -> 555.07536 | AC70: =+X70/$G$93 -> 545.5669 | AD70: =+Y70/$H$93 -> 549.36396 | AE70: =+Z70/$I$93 -> 575.74371 | AF70: =+AA70/$U$4 -> 574.4876 | AG70: =SUM(AB70:AF70) -> 2800.2375 | AI70: =SUM(K70:Q70)/$U$4 -> 4021.4132 | AJ70: =AG70+AI70 -> 6821.6508
A71: Headhunter para dirección de alianzas | F71: 0 | G71: 0 | H71: 6947980 | I71: 0 | J71: 19950000 | K71: 0 | L71: 0 | M71: 0 | N71: 0 | O71: 0 | P71: 0 | Q71: 0 | R71: =SUM(F71:Q71) -> 26897980 | S71: =R71/U$4 -> 5911.644 | V71: 3504544 | W71: =F71 -> 0 | X71: =G71 -> 0 | Y71: =H71 -> 6947980 | Z71: =I71 -> 0 | AA71: =J71 -> 19950000 | AB71: =+W71/$F$93 -> 0 | AC71: =+X71/$G$93 -> 0 | AD71: =+Y71/$H$93 -> 1460.2482 | AE71: =+Z71/$I$93 -> 0 | AF71: =+AA71/$U$4 -> 4384.6154 | AG71: =SUM(AB71:AF71) -> 5844.8635 | AI71: =SUM(K71:Q71)/$U$4 -> 0 | AJ71: =AG71+AI71 -> 5844.8635
A72: Travel | F72: 0 | G72: 0 | H72: 1277200 | I72: 1444044 | J72: 2200000 | K72: 2200000 | L72: 2200000 | M72: 2200000 | N72: 2200000 | O72: 2200000 | P72: 2200000 | Q72: 0 | R72: =SUM(F72:Q72) -> 18121244 | S72: =R72/U$4 -> 3982.691 | W72: =F72 -> 0 | X72: =G72 -> 0 | Y72: =H72 -> 1277200 | Z72: =I72 -> 1444044 | AA72: =J72 -> 2200000 | AB72: =+W72/$F$93 -> 0 | AC72: =+X72/$G$93 -> 0 | AD72: =+Y72/$H$93 -> 268.42751 | AE72: =+Z72/$I$93 -> 318.06623 | AF72: =+AA72/$U$4 -> 483.51648 | AG72: =SUM(AB72:AF72) -> 1070.0102 | AI72: =SUM(K72:Q72)/$U$4 -> 2901.0989 | AJ72: =AG72+AI72 -> 3971.1091
A73: Suministros | F73: 0 | G73: 0 | H73: 0 | I73: 0 | J73: 150000 | R73: =SUM(F73:Q73) -> 150000 | S73: =R73/U$4 -> 32.967033 | W73: =F73 -> 0 | X73: =G73 -> 0 | Y73: =H73 -> 0 | Z73: =I73 -> 0 | AA73: =J73 -> 150000 | AB73: =+W73/$F$93 -> 0 | AC73: =+X73/$G$93 -> 0 | AD73: =+Y73/$H$93 -> 0 | AE73: =+Z73/$I$93 -> 0 | AF73: =+AA73/$U$4 -> 32.967033 | AG73: =SUM(AB73:AF73) -> 32.967033 | AI73: =SUM(K73:Q73)/$U$4 -> 0 | AJ73: =AG73+AI73 -> 32.967033
A74: Organización de encuentros, meetings y eventos | F74: 0 | G74: 0 | H74: 0 | I74: 0 | J74: 0 | L74: 0 | M74: 0 | O74: 0 | P74: 0 | Q74: 0 | R74: =SUM(F74:Q74) -> 0 | S74: =R74/U$4 -> 0 | W74: =F74 -> 0 | X74: =G74 -> 0 | Y74: =H74 -> 0 | Z74: =I74 -> 0 | AA74: =J74 -> 0 | AB74: =+W74/$F$93 -> 0 | AC74: =+X74/$G$93 -> 0 | AD74: =+Y74/$H$93 -> 0 | AE74: =+Z74/$I$93 -> 0 | AF74: =+AA74/$U$4 -> 0 | AG74: =SUM(AB74:AF74) -> 0 | AI74: =SUM(K74:Q74)/$U$4 -> 0 | AJ74: =AG74+AI74 -> 0
A75: Prima por servicios personal alianzas | F75: 0 | G75: 0 | H75: 0 | I75: 0 | J75: 0 | K75: =(K69*0.5)+(I67/12)+(J67/12)+(K67/12) -> 6237555.6 | L75: 0 | M75: 0 | N75: 0 | O75: 0 | P75: 0 | Q75: =(Q67+Q69)*0.5 -> 10929500 | R75: =SUM(F75:Q75) -> 17167056 | S75: =R75/U$4 -> 3772.9792 | W75: =F75 -> 0 | X75: =G75 -> 0 | Y75: =H75 -> 0 | Z75: =I75 -> 0 | AA75: =J75 -> 0 | AB75: =+W75/$F$93 -> 0 | AC75: =+X75/$G$93 -> 0 | AD75: =+Y75/$H$93 -> 0 | AE75: =+Z75/$I$93 -> 0 | AF75: =+AA75/$U$4 -> 0 | AG75: =SUM(AB75:AF75) -> 0 | AI75: =SUM(K75:Q75)/$U$4 -> 3772.9792 | AJ75: =AG75+AI75 -> 3772.9792
W76: =F76 -> 0 | X76: =G76 -> 0 | Y76: =H76 -> 0 | Z76: =I76 -> 0 | AA76: =J76 -> 0 | AB76: =+W76/$F$93 -> 0 | AC76: =+X76/$G$93 -> 0 | AD76: =+Y76/$H$93 -> 0 | AE76: =+Z76/$I$93 -> 0 | AF76: =+AA76/$U$4 -> 0 | AG76: =SUM(AB76:AF76) -> 0 | AI76: =SUM(K76:Q76)/$U$4 -> 0
A77: GESI | F77: =(SUM(F78))/U4 -> 0 | G77: =(SUM(G78))/U4 -> 0 | H77: =(SUM(H78))/U4 -> 0 | I77: =(SUM(I78))/U4 -> 0 | J77: =(SUM(J78))/U4 -> 0 | K77: =(SUM(K78))/U4 -> 0 | L77: =(SUM(L78))/U4 -> 0 | M77: =(SUM(M78))/U4 -> 0 | N77: =(SUM(N78))/U4 -> 0 | O77: =(SUM(O78))/U4 -> 0 | P77: =(SUM(P78))/U4 -> 0 | Q77: =(SUM(Q78))/U4 -> 0 | R77: =SUM(F77:Q77) -> 0 | W77: =F77 -> 0 | X77: =G77 -> 0 | Y77: =H77 -> 0 | Z77: =I77 -> 0 | AA77: =J77 -> 0 | AB77: =+W77/$F$93 -> 0 | AC77: =+X77/$G$93 -> 0 | AD77: =+Y77/$H$93 -> 0 | AE77: =+Z77/$I$93 -> 0 | AF77: =+AA77/$U$4 -> 0 | AG77: =SUM(AB77:AF77) -> 0 | AI77: =SUM(K77:Q77)/$U$4 -> 0
A78: Travel | F78: 0 | G78: 0 | H78: 0 | I78: 0 | J78: 0 | K78: 0 | L78: 0 | M78: 0 | N78: 0 | O78: 0 | P78: 0 | Q78: 0 | R78: =SUM(F78:Q78) -> 0 | S78: =R78/U4 -> 0 | W78: =F78 -> 0 | X78: =G78 -> 0 | Y78: =H78 -> 0 | Z78: =I78 -> 0 | AA78: =J78 -> 0 | AB78: =+W78/$F$93 -> 0 | AC78: =+X78/$G$93 -> 0 | AD78: =+Y78/$H$93 -> 0 | AE78: =+Z78/$I$93 -> 0 | AF78: =+AA78/$U$4 -> 0 | AG78: =SUM(AB78:AF78) -> 0 | AI78: =SUM(K78:Q78)/$U$4 -> 0
R79: =SUM(F79:Q79) -> 0 | W79: =F79 -> 0 | X79: =G79 -> 0 | Y79: =H79 -> 0 | Z79: =I79 -> 0 | AA79: =J79 -> 0 | AB79: =+W79/$F$93 -> 0 | AC79: =+X79/$G$93 -> 0 | AD79: =+Y79/$H$93 -> 0 | AE79: =+Z79/$I$93 -> 0 | AF79: =+AA79/$U$4 -> 0 | AG79: =SUM(AB79:AF79) -> 0 | AI79: =SUM(K79:Q79)/$U$4 -> 0
A80: MONITOREO Y EVALUACIÓN | B80: 10-10-86 | F80: =(SUM(F81:F83))/F93 -> 495.84595 | G80: =(SUM(G81:G83))/G93 -> 626.14831 | H80: =(SUM(H81:H83))/U4 -> 0 | I80: =(SUM(I81:I83))/U4 -> 0 | J80: =(SUM(J81:J83))/$U$4 -> 109.89011 | K80: =(SUM(K81:K83))/$U$4 -> 0 | L80: =(SUM(L81:L83))/$U$4 -> 0 | M80: =(SUM(M81:M83))/$U$4 -> 0 | N80: =(SUM(N81:N83))/$U$4 -> 109.89011 | O80: =(SUM(O81:O83))/$U$4 -> 0 | P80: =(SUM(P81:P83))/$U$4 -> 0 | Q80: =(SUM(Q81:Q83))/$U$4 -> 0 | R80: =SUM(F80:Q80) -> 1341.7745 | W80: =F80 -> 495.84595 | X80: =G80 -> 626.14831 | Y80: =H80 -> 0 | Z80: =I80 -> 0 | AA80: =J80 -> 109.89011 | AB80: =+W80/$F$93 -> 0.10529474 | AC80: =+X80/$G$93 -> 0.13068723 | AD80: =+Y80/$H$93 -> 0 | AE80: =+Z80/$I$93 -> 0 | AF80: =+AA80/$U$4 -> 0.024151673 | AG80: =SUM(AB80:AF80) -> 0.26013364 | AI80: =SUM(K80:Q80)/$U$4 -> 0.024151673
A81: Laptops y software | F81: 0 | G81: 0 | H81: 0 | I81: 0 | J81: 0 | K81: 0 | M81: 0 | N81: 0 | O81: 0 | P81: 0 | Q81: 0 | R81: =SUM(F81:Q81) -> 0 | S81: =R81/U$4 -> 0 | W81: =F81 -> 0 | X81: =G81 -> 0 | Y81: =H81 -> 0 | Z81: =I81 -> 0 | AA81: =J81 -> 0 | AB81: =+W81/$F$93 -> 0 | AC81: =+X81/$G$93 -> 0 | AD81: =+Y81/$H$93 -> 0 | AE81: =+Z81/$I$93 -> 0 | AF81: =+AA81/$U$4 -> 0 | AG81: =SUM(AB81:AF81) -> 0 | AI81: =SUM(K81:Q81)/$U$4 -> 0 | AJ81: =AG81+AI81 -> 0
A82: Consultores | F82: 2335000 | G82: 3000000 | H82: 0 | I82: 0 | J82: 0 | K82: 0 | L82: 0 | M82: 0 | N82: 0 | O82: 0 | P82: 0 | Q82: 0 | R82: =SUM(F82:Q82) -> 5335000 | S82: =R82/U$4 -> 1172.5275 | W82: =F82 -> 2335000 | X82: =G82 -> 3000000 | Y82: =H82 -> 0 | Z82: =I82 -> 0 | AA82: =J82 -> 0 | AB82: =+W82/$F$93 -> 495.84595 | AC82: =+X82/$G$93 -> 626.14831 | AD82: =+Y82/$H$93 -> 0 | AE82: =+Z82/$I$93 -> 0 | AF82: =+AA82/$U$4 -> 0 | AG82: =SUM(AB82:AF82) -> 1121.9943 | AI82: =SUM(K82:Q82)/$U$4 -> 0 | AJ82: =AG82+AI82 -> 1121.9943
A83: Data Collection Tools | F83: 0 | G83: 0 | H83: 0 | I83: 0 | J83: 500000 | K83: 0 | L83: 0 | M83: 0 | N83: 500000 | O83: 0 | P83: 0 | Q83: 0 | R83: =SUM(F83:Q83) -> 1000000 | S83: =R83/U$4 -> 219.78022 | W83: =F83 -> 0 | X83: =G83 -> 0 | Y83: =H83 -> 0 | Z83: =I83 -> 0 | AA83: =J83 -> 500000 | AB83: =+W83/$F$93 -> 0 | AC83: =+X83/$G$93 -> 0 | AD83: =+Y83/$H$93 -> 0 | AE83: =+Z83/$I$93 -> 0 | AF83: =+AA83/$U$4 -> 109.89011 | AG83: =SUM(AB83:AF83) -> 109.89011 | AI83: =SUM(K83:Q83)/$U$4 -> 109.89011 | AJ83: =AG83+AI83 -> 219.78022
W84: =F84 -> 0 | X84: =G84 -> 0 | Y84: =H84 -> 0 | Z84: =I84 -> 0 | AA84: =J84 -> 0 | AB84: =+W84/$F$93 -> 0 | AC84: =+X84/$G$93 -> 0 | AD84: =+Y84/$H$93 -> 0 | AE84: =+Z84/$I$93 -> 0 | AF84: =+AA84/$U$4 -> 0 | AG84: =SUM(AB84:AF84) -> 0 | AI84: =SUM(K84:Q84)/$U$4 -> 0 | AJ84: =AG84+AI84 -> 0
A85: FONDO DE EMERGENCIA | L85: 1002.5 | M85: 1002.5 | N85: 1002.5 | O85: 1002.5 | P85: 1002.5 | Q85: 1002.5 | R85: =SUM(L85:Q85) -> 6015
A87: EJECUCIÓN | F87: =F3+F19+F24+F32 -> 33505.402 | G87: =G3+G19+G24+G32 -> 19614.325 | H87: =H3+H19+H24+H32 -> 26808.421 | I87: =I3+I19+I24+I32 -> 29567.558 | J87: =J3+J19+J24+J32 -> 52203.108 | K87: =K3+K19+K24+K32 -> 38985.938 | L87: =L3+L19+L24+L32+L85 -> 47397.638 | M87: =M3+M19+M24+M32+M85 -> 44285.596 | N87: =N3+N19+N24+N32+N85 -> 46065.166 | O87: =O3+O19+O24+O32+O85 -> 38458.639 | P87: =P3+P19+P24+P32+P85 -> 31459.984 | Q87: =Q3+Q19+Q24+Q32+Q85 -> 39854.27 | R87: =SUM(F87:Q87) -> 448206.04 | S87: =R87*U4 -> 2.0393375e+09 | W87: =F87 -> 33505.402 | X87: =G87 -> 19614.325 | Y87: =H87 -> 26808.421 | Z87: =I87 -> 29567.558 | AA87: =J87 -> 52203.108 | AB87: =+W87/$F$93 -> 7.114997 | AC87: =+X87/$G$93 -> 4.0938255 | AD87: =+Y87/$H$93 -> 5.6342919 | AE87: =+Z87/$I$93 -> 6.5125729 | AF87: =+AA87/$U$4 -> 11.47321 | AG87: =SUM(AB87:AF87) -> 34.828898 | AI87: =SUM(K87:Q87)/$U$4 -> 62.968622 | AJ87: =AG87+AI87 -> 97.79752
K88: =K87*(1-9%) -> 35477.203
