Workbook
Name \A: #REF!
Name \A: #REF!
Name \P: #REF!
Name \P: #REF!
Name \S: #REF!
Name \S: #REF!
Name _______sho1: '[3]Detailed Budget-SAVE'!#REF!
Name _______sho1: #REF!
Name __2DAI_1: #N/A
Name __3FEE: #N/A
Name __AFP1: #N/A
Name __AFP2: #N/A
Name __AFP3: #N/A
Name __AFP4: #N/A
Name __AMP1: #N/A
Name __AMP2: #N/A
Name __AMP3: #N/A
Name __AMP4: #N/A
Name __DAI4: #N/A
Name __EES1: #N/A
Name __EES2: #N/A
Name __EES3: #N/A
Name __EES4: #N/A
Name __EXT1: #N/A
Name __EXT2: #N/A
Name __EXT3: #N/A
Name __EXT4: #N/A
Name __FCP1: #N/A
Name __FCP2: #N/A
Name __FCP3: #N/A
Name __FCP4: #N/A
Name __FRI1: #N/A
Name __FRI4: #N/A
Name __HRA1: #N/A
Name __HRA2: #N/A
Name __HRA3: #N/A
Name __HRA4: #N/A
Name __inf1: #REF!
Name __inf1: #REF!
Name __LT4: [4]Parameters!$B$40
Name __LT4: #REF!
Name __ODC1: #N/A
Name __ODC2: #N/A
Name __POL1: #N/A
Name __POL2: #N/A
Name __POL3: #N/A
Name __POL4: #N/A
Name __TOT1: #N/A
Name __TOT2: #N/A
Name __TRV1: #N/A
Name __TRV2: #N/A
Name _060: #REF!
Name _060: #REF!
Name _1_1: #REF!
Name _1_1: #REF!
Name _13th_and_14th_month: [5]Parameters!$D$62
Name _13th_and_14th_month: #REF!
Name _2_1034: #REF!
Name _2_1034: #REF!
Name _2DAI_1: #N/A

Sheet USDA Budget Summary
A1: Attachment C-1
A2: Budget Summary
A4: Program (FFPr or MGD): | B4: MGD
A5: Country of Operation: | B5: Honduras
A6: Implementing Organization: | B6: Partners of the Americas Inc.
A7: Fiscal Year: | B7: 2025
A8: Agreement Number: | B8: USDA-FAS-10.608-0700-25-(522)
A10: Total Amount of Federal Funds Requested
A11: Funding Source (FAS for MGD) (CCC for FFPr) | B11: Funding Year | C11: Commodity Cost | D11: Freight Cost | E11: Project Operating Cost | F11: Total Federal Funding Obligated | G11: Original Agreement Total | H11: Difference
B12: 2025 | C12: 9958720 | D12: 2511080 | E12: =E68 -> 27530200 | F12: =E12+D12+C12 -> 40000000
A14: Project Operating Budget
A15: Expense Type | B15: Monetization Proceeds (FFPr Only) | C15: FAS or CCC Funds (CCC is Admin Only) | D15: Cost Share | E15: Total w/out Cost Share | F15: Total w/Cost Share
A16: Administration
A17: Salaries/Personnel | B17: 0 | C17: ='Program Budget'!Y53 -> 5286497.8 | D17: ='Program Budget'!Z53 -> 0 | E17: =B17+C17 -> 5286497.8 | F17: =B17+C17+D17 -> 5286497.8 | G17: 2402720.4 | H17: =F17-G17 -> 2883777.4
A18: Benefits | B18: 0 | C18: ='Program Budget'!Y59 -> 2027171 | D18: ='Program Budget'!Z59 -> 0 | E18: =B18+C18 -> 2027171 | F18: =B18+C18+D18 -> 2027171 | G18: 659056.67 | H18: =F18-G18 -> 1368114.3
A19: Travel | B19: 0 | C19: ='Program Budget'!Y80 -> 368758.3 | D19: ='Program Budget'!Z80 -> 0 | E19: =B19+C19 -> 368758.3 | F19: =B19+C19+D19 -> 368758.3 | G19: 368758.3 | H19: =F19-G19 -> 0.0027323751
A20: Professional Services/Contractual | B20: 0 | C20: ='Program Budget'!Y101 -> 1116800 | D20: ='Program Budget'!Z101 -> 0 | E20: =B20+C20 -> 1116800 | F20: =B20+C20+D20 -> 1116800 | G20: 1082000 | H20: =F20-G20 -> 34800
A21: Equipment | B21: 0 | C21: ='Program Budget'!Y106 -> 53000 | D21: ='Program Budget'!Z106 -> 0 | E21: =B21+C21 -> 53000 | F21: =B21+C21+D21 -> 53000 | G21: 159000 | H21: =F21-G21 -> -106000
A22: Supplies | B22: 0 | C22: ='Program Budget'!Y121 -> 82190.637 | D22: ='Program Budget'!Z121 -> 0 | E22: =B22+C22 -> 82190.637 | F22: =B22+C22+D22 -> 82190.637 | G22: 91027.43 | H22: =F22-G22 -> -8836.7925
A23: Other | B23: 0 | C23: ='Program Budget'!Y148 -> 646819.51 | D23: ='Program Budget'!Z148 -> 0 | E23: =B23+C23 -> 646819.51 | F23: =B23+C23+D23 -> 646819.51 | G23: 640169.34 | H23: =F23-G23 -> 6650.1702
A24: Total Administration | B24: =SUM(B17:B23) -> 0 | C24: =SUM(C17:C23) -> 9581237.2 | D24: =SUM(D17:D23) -> 0 | E24: =SUM(E17:E23) -> 9581237.2 | F24: =SUM(F17:F23) -> 9581237.2 | G24: 5402732.1 | H24: =F24-G24 -> 4178505.1 | J24: 9715046.9 | K24: =J24-F24 -> 133809.69
A26: Activities
A27: Activity 1: Provide School Meals | B27: 0 | C27: ='Program Budget'!Y210 -> 658976.11 | D27: ='Program Budget'!Z210 -> 187000 | E27: =B27+C27 -> 658976.11 | F27: =B27+C27+D27 -> 845976.11 | G27: 1161155.5 | H27: =F27-G27 -> -315179.41
A28: Activity 2: Distribution: School Supplies and Materials | B28: 0 | C28: ='Program Budget'!Y269 -> 407143.18 | D28: ='Program Budget'!Z269 -> 0 | E28: =B28+C28 -> 407143.18 | F28: =B28+C28+D28 -> 407143.18 | G28: 750076.07 | H28: =F28-G28 -> -342932.89
A29: Activity 3: Training: Teacher and Administrators | B29: 0 | C29: ='Program Budget'!Y338 -> 2400715.2 | D29: ='Program Budget'!Z338 -> 0 | E29: =B29+C29 -> 2400715.2 | F29: =B29+C29+D29 -> 2400715.2 | G29: 2723500.9 | H29: =F29-G29 -> -322785.68
A30: Activity 4: Enrollment Campaigns | B30: 0 | C30: ='Program Budget'!Y405 -> 629594.49 | D30: ='Program Budget'!Z405 -> 0 | E30: =B30+C30 -> 629594.49 | F30: =B30+C30+D30 -> 629594.49 | G30: 935164.19 | H30: =F30-G30 -> -305569.7
A31: Activity 5: Building/Rehabilitation: Wells and Water Stations/Systems | B31: 0 | C31: ='Program Budget'!Y477 -> 520716.18 | D31: ='Program Budget'!Z477 -> 182500 | E31: =B31+C31 -> 520716.18 | F31: =B31+C31+D31 -> 703216.18 | G31: 1011819.9 | H31: =F31-G31 -> -308603.68
A32: Activity 6: Training: Good Health and Nutrition Practices | B32: 0 | C32: ='Program Budget'!Y552 -> 1056867.1 | D32: ='Program Budget'!Z552 -> 0 | E32: =B32+C32 -> 1056867.1 | F32: =B32+C32+D32 -> 1056867.1 | G32: 1251376.6 | H32: =F32-G32 -> -194509.49
A33: Activity 7: Training: Commodity Management | B33: 0 | C33: ='Program Budget'!Y607 -> 357568.95 | D33: ='Program Budget'!Z607 -> 0 | E33: =B33+C33 -> 357568.95 | F33: =B33+C33+D33 -> 357568.95 | G33: 951532.38 | H33: =F33-G33 -> -593963.43
A34: Activity 8: Capacity Building: Local and Regional Level | B34: 0 | C34: ='Program Budget'!Y681 -> 365869.91 | D34: ='Program Budget'!Z681 -> 11500 | E34: =B34+C34 -> 365869.91 | F34: =B34+C34+D34 -> 377369.91 | G34: 689004.77 | H34: =F34-G34 -> -311634.86
A35: Activity 9: Capacity Building: National Level | B35: 0 | C35: ='Program Budget'!Y755 -> 425854.9 | D35: ='Program Budget'!Z755 -> 0 | E35: =B35+C35 -> 425854.9 | F35: =B35+C35+D35 -> 425854.9 | G35: 632635.61 | H35: =F35-G35 -> -206780.71
A36: Activity 10: Develop Public-Private Partnerships to Support School Feeding Sustainability | B36: 0 | C36: ='Program Budget'!Y827 -> 462935.92 | D36: ='Program Budget'!Z827 -> 21000 | E36: =B36+C36 -> 462935.92 | F36: =B36+C36+D36 -> 483935.92 | G36: 807880.29 | H36: =F36-G36 -> -323944.37
A37: Activity 11: Expand Use of US Commodities in Honduras School Feeding Program | B37: 0 | C37: ='Program Budget'!Y886 -> 89328.663 | D37: ='Program Budget'!Z886 -> 4980 | E37: =B37+C37 -> 89328.663 | F37: =B37+C37+D37 -> 94308.663 | G37: 424932.75 | H37: =F37-G37 -> -330624.09
A38: Total Activities | B38: =SUM(B27:B37) -> 0 | C38: =SUM(C27:C37) -> 7375570.6 | D38: =SUM(D27:D37) -> 406980 | E38: =SUM(E27:E37) -> 7375570.6 | F38: =SUM(F27:F37) -> 7782550.6 | G38: 11339079 | H38: =F38-G38 -> -3556528.3
A40: Commodity and Food Purchases (N/A to FFPr)
A41: Commodity Procurement | B41: 0 | C41: ='Program Budget'!Y978 -> 3282393.1 | D41: ='Program Budget'!Z978 -> 0 | E41: =B41+C41 -> 3282393.1 | F41: =B41+C41+D41 -> 3282393.1
A42: Food Vouchers (N/A to MGD)
A43: Cash Transfers (N/A to MGD)
A44: Total Commodity Procurement | B44: =SUM(B41:B43) -> 0 | C44: =SUM(C41:C43) -> 3282393.1 | D44: =SUM(D41:D43) -> 0 | E44: =SUM(E41:E43) -> 3282393.1 | F44: =SUM(F41:F43) -> 3282393.1 | G44: 3136470 | H44: =F44-G44 -> 145923.11 | I44: =F44/C68 -> 0.11922881 | J44: =C44+C55 -> 5985025.6
J45: =J44*20% -> 1197005.1
A46: ITSH (N/A to FFPr) | J46: =J45+J44 -> 7182030.7 | K46: =J46/E12 -> 0.26087826
A47: Salaries | B47: 0 | C47: ='Program Budget'!Y925 -> 953187.37 | D47: ='Program Budget'!Z925 -> 0 | E47: =B47+C47 -> 953187.37 | F47: =B47+C47+D47 -> 953187.37 | G47: 685849.95 | H47: =F47-G47 -> 267337.42
A48: Benefits | B48: 0 | C48: ='Program Budget'!Y929 -> 460008.22 | D48: ='Program Budget'!Z929 -> 0 | E48: =B48+C48 -> 460008.22 | F48: =B48+C48+D48 -> 460008.22 | G48: 330991.18 | H48: =F48-G48 -> 129017.04
A49: Travel | B49: 0 | C49: ='Program Budget'!Y958 -> 37600.878 | D49: ='Program Budget'!Z958 -> 0 | E49: =B49+C49 -> 37600.878 | F49: =B49+C49+D49 -> 37600.878 | G49: 37600.88 | H49: =F49-G49 -> -0.002196875
A50: Internal Transportation | B50: 0 | C50: ='Program Budget'!Y963 -> 381450 | D50: ='Program Budget'!Z963 -> 0 | E50: =B50+C50 -> 381450 | F50: =B50+C50+D50 -> 381450 | G50: 384650 | H50: =F50-G50 -> -3200
A51: Professional Services | B51: 0 | C51: ='Program Budget'!Y937 -> 279600 | D51: ='Program Budget'!Z937 -> 0 | E51: =B51+C51 -> 279600 | F51: =B51+C51+D51 -> 279600 | G51: 99702 | H51: =F51-G51 -> 179898
A52: Warehouse | B52: 0 | C52: ='Program Budget'!Y948 -> 588336 | D52: ='Program Budget'!Z948 -> 0 | E52: =B52+C52 -> 588336 | F52: =B52+C52+D52 -> 588336 | G52: 1011615 | H52: =F52-G52 -> -423279
A53: Supplies | B53: 0 | C53: ='Program Budget'!Y952 -> 2450 | D53: ='Program Budget'!Z952 -> 0 | E53: =B53+C53 -> 2450 | F53: =B53+C53+D53 -> 2450 | G53: 2450 | H53: =F53-G53 -> 0
A54: Other | B54: 0 | C54: ='Program Budget'!Y967 -> 0 | D54: ='Program Budget'!Z967 -> 0 | E54: =B54+C54 -> 0 | F54: =B54+C54+D54 -> 0 | G54: 0 | H54: =F54-G54 -> 0
A55: Total ITSH | B55: =SUM(B47:B54) -> 0 | C55: =SUM(C47:C54) -> 2702632.5 | D55: =SUM(D47:D54) -> 0 | E55: =SUM(E47:E54) -> 2702632.5 | F55: =SUM(F47:F54) -> 2702632.5 | G55: 2552859 | H55: =F55-G55 -> 149773.46 | I55: =F55/C68 -> 0.098169736
A57: Total Direct Costs | B57: =B24+B38+B55+B44 -> 0 | C57: =C24+C38+C55+C44 -> 22941833 | D57: =D24+D38+D55+D44 -> 406980 | E57: =E24+E38+E55+E44 -> 22941833 | F57: =F24+F38+F55+F44 -> 23348813 | G57: 22431140 | H57: =F57-G57 -> 917673.33
A59: Indirect Costs
A60: ICR on Administration | B60: =B24*0.2 -> 0 | C60: =C24*0.2 -> 1916247.4 | E60: =B60+C60 -> 1916247.4 | G60: 1350683 | H60: =E60-G60 -> 565564.4
A61: ICR on Activities | B61: =((B38)*0.2) -> 0 | C61: =C38*0.2 -> 1475114.1 | E61: =B61+C61 -> 1475114.1 | G61: 2733024.7 | H61: =E61-G61 -> -1257910.6
A62: ICR on Commodity and Food Purchases (N/A to FFPr) | B62: =B44*0.2 -> 0 | C62: =C44*0.2 -> 656478.62 | E62: =B62+C62 -> 656478.62 | G62: 784117.5 | H62: =E62-G62 -> -127638.88
A63: ICR on ITSH (N/A to FFPr) | B63: =B55*0.2 -> 0 | C63: =C55*0.2 -> 540526.49 | E63: =B63+C63 -> 540526.49 | G63: 638214.75 | H63: =E63-G63 -> -97688.257
A64: Total Indirect Costs | B64: =ROUND(SUM(B60:B63),0) -> 0 | C64: =SUM(C60:C63) -> 4588366.7 | E64: =SUM(E60:E63) -> 4588366.7 | G64: 5506040 | H64: =E64-G64 -> -917673.33
A66: Anticipated Program Income
A68: Total Project Operating Costs | B68: =(B64+B57) -> 0 | C68: =(C64+C57) -> 27530200 | D68: =(D64+D57) -> 406980 | E68: =(E64+E57) -> 27530200 | F68: =(F57+E64) -> 27937180 | G68: 27937180 | H68: =F68-G68 -> -0.00051064417
A70: Total Amount of Federal Award (Total Federal Funds Requested Plus Cost Share): | F70: =F12+D68 -> 40406980 | G70: 40406980 | H70: =F70-G70 -> -0.00051064789

Sheet Program Budget
D1: Partners of the Americas – FY 2025 McGovern-Dole Honduras
D2: NOFO: USDA-FAS-10.608-0700-25-(522)
D3: Duration: 6 Years
D4: Country: Honduras
D5: Budget Assumptions:
A6: Program/Dept.: | B6: 20300 | D6: Inflation Increases- 5% | E6: 1.05
A7: Funder Grant: | B7: USDA801 | D7: Merit Based Increases for HQ & Field Staff | E7: 1.05
A9: Activity Code | B9: Account Code | C9: Country Code | D9: BUDGET ITEM | E9: Level of Effort (LOE) Year 1 | F9: UNIT | G9: # of Units | H9: RATE/ UNIT | I9: YEAR 1 | J9: Level of Effort (LOE) Year 2 | K9: # of Units | L9: YEAR 2 | M9: Level of Effort (LOE) Year 3 | N9: # of Units | O9: YEAR 3 | P9: Level of Effort (LOE) Year 4 | Q9: # of Units | R9: YEAR 4 | S9: Level of Effort (LOE) Year 5 | T9: # of Units | U9: YEAR 5 | V9: Level of Effort (LOE) Year 6 | W9: # of Units | X9: YEAR 6 | Y9: TOTAL USDA | Z9: TOTAL COST SHARE | AA9: PROJECT GRAND TOTAL
D10: Salaries/Personnel (Administration)
D11: CCN Honduran Field Staff (LOE)
A12: PERADMNCOP | B12: 70000 | C12: HND | D12: Key Personnel: Chief of Party - Roger Sanchez O’Neill | E12: ='LOE Breakdown by Year'!D11 -> 1 | F12: Month | G12: 11 | H12: =115000/12 -> 9583.3333 | I12: =G12*H12*E12 -> 105416.67 | J12: ='LOE Breakdown by Year'!D57 -> 1 | K12: 12 | L12: =K12*H12*$E$7*$J12 -> 120750 | M12: ='LOE Breakdown by Year'!D103 -> 1 | N12: 12 | O12: =N12*H12*$M12*$E$7*$E$7 -> 126787.5 | P12: ='LOE Breakdown by Year'!D149 -> 1 | Q12: 12 | R12: =Q12*H12*$P12*$E$7*$E$7*$E$7 -> 133126.88 | S12: ='LOE Breakdown by Year'!D195 -> 1 | T12: 12 | U12: =T12*H12*$S12*$E$7*$E$7*$E$7*$E$7 -> 139783.22 | V12: ='LOE Breakdown by Year'!D241 -> 1 | W12: 12 | X12: =W12*H12*$V12*$E$7*$E$7*$E$7*$E$7*$E$7 -> 146772.38 | Y12: =SUM(R12,O12,L12,I12,U12,X12) -> 772636.64 | Z12: 0 | AA12: =SUM(Y12:Z12) -> 772636.64
A13: PERADMNDOP | B13: 70000 | C13: HND | D13: Key Personnel: Deputy Chief of Party - David Medina Mayo | E13: ='LOE Breakdown by Year'!D12 -> 1 | F13: Month | G13: 11 | H13: =78000/12 -> 6500 | I13: =G13*H13*E13 -> 71500 | J13: ='LOE Breakdown by Year'!D58 -> 1 | K13: 12 | L13: =K13*H13*$E$7*$J13 -> 81900 | M13: ='LOE Breakdown by Year'!D104 -> 1 | N13: 12 | O13: =N13*H13*$M13*$E$7*$E$7 -> 85995 | P13: ='LOE Breakdown by Year'!D150 -> 1 | Q13: 12 | R13: =Q13*H13*$P13*$E$7*$E$7*$E$7 -> 90294.75 | S13: ='LOE Breakdown by Year'!D196 -> 1 | T13: 12 | U13: =T13*H13*$S13*$E$7*$E$7*$E$7*$E$7 -> 94809.488 | V13: ='LOE Breakdown by Year'!D242 -> 1 | W13: 12 | X13: =W13*H13*$V13*$E$7*$E$7*$E$7*$E$7*$E$7 -> 99549.962 | Y13: =SUM(R13,O13,L13,I13,U13,X13) -> 524049.2 | Z13: 0 | AA13: =SUM(Y13:Z13) -> 524049.2
A14: PERADMNPOL | B14: 70000 | C14: HND | D14: Policy & Sustainability Specialist | E14: ='LOE Breakdown by Year'!D13 -> 0 | F14: Month | G14: 0 | H14: =18000/12 -> 1500 | I14: =G14*H14*E14 -> 0 | J14: ='LOE Breakdown by Year'!D59 -> 0 | K14: 0 | L14: =K14*H14*$E$7*$J14 -> 0 | M14: ='LOE Breakdown by Year'!D105 -> 0 | N14: 7 | O14: =N14*H14*$M14*$E$7*$E$7 -> 0 | P14: ='LOE Breakdown by Year'!D151 -> 0 | Q14: 12 | R14: =Q14*H14*$P14*$E$7*$E$7*$E$7 -> 0 | S14: ='LOE Breakdown by Year'!D197 -> 0 | T14: 12 | U14: =T14*H14*$S14*$E$7*$E$7*$E$7*$E$7 -> 0 | V14: ='LOE Breakdown by Year'!D243 -> 0 | W14: 6 | X14: =W14*H14*$V14*$E$7*$E$7*$E$7*$E$7*$E$7 -> 0 | Y14: =SUM(R14,O14,L14,I14,U14,X14) -> 0 | Z14: 0 | AA14: =SUM(Y14:Z14) -> 0
A15: PERADMNEDD | B15: 70000 | C15: HND | D15: Education Director | E15: ='LOE Breakdown by Year'!D14 -> 0 | F15: Month | G15: 9 | H15: =55000/12 -> 4583.3333 | I15: =G15*H15*E15 -> 0 | J15: ='LOE Breakdown by Year'!D60 -> 0 | K15: 12 | L15: =K15*H15*$E$7*$J15 -> 0 | M15: ='LOE Breakdown by Year'!D106 -> 0 | N15: 12 | O15: =N15*H15*$M15*$E$7*$E$7 -> 0 | P15: ='LOE Breakdown by Year'!D152 -> 0 | Q15: 12 | R15: =Q15*H15*$P15*$E$7*$E$7*$E$7 -> 0 | S15: ='LOE Breakdown by Year'!D198 -> 0 | T15: 12 | U15: =T15*H15*$S15*$E$7*$E$7*$E$7*$E$7 -> 0 | V15: ='LOE Breakdown by Year'!D244 -> 0 | W15: 8 | X15: =W15*H15*$V15*$E$7*$E$7*$E$7*$E$7*$E$7 -> 0 | Y15: =SUM(R15,O15,L15,I15,U15,X15) -> 0 | Z15: 0 | AA15: =SUM(Y15:Z15) -> 0
A16: PERADMNEDS | B16: 70000 | C16: HND | D16: Education Specialist | E16: ='LOE Breakdown by Year'!D15 -> 0 | F16: Month | G16: 8 | H16: =30000/12 -> 2500 | I16: =G16*H16*E16 -> 0 | J16: ='LOE Breakdown by Year'!D61 -> 0 | K16: 12 | L16: =K16*H16*$E$7*$J16 -> 0 | M16: ='LOE Breakdown by Year'!D107 -> 0 | N16: 12 | O16: =N16*H16*$M16*$E$7*$E$7 -> 0 | P16: ='LOE Breakdown by Year'!D153 -> 0 | Q16: 12 | R16: =Q16*H16*$P16*$E$7*$E$7*$E$7 -> 0 | S16: ='LOE Breakdown by Year'!D199 -> 0 | T16: 12 | U16: =T16*H16*$S16*$E$7*$E$7*$E$7*$E$7 -> 0 | V16: ='LOE Breakdown by Year'!D245 -> 0 | W16: 3 | X16: =W16*H16*$V16*$E$7*$E$7*$E$7*$E$7*$E$7 -> 0 | Y16: =SUM(R16,O16,L16,I16,U16,X16) -> 0 | Z16: 0 | AA16: =SUM(Y16:Z16) -> 0
A17: PERADMNEDO | B17: 70000 | C17: HND | D17: Education Officer | E17: ='LOE Breakdown by Year'!D16 -> 0 | F17: Month | G17: =6 -> 6 | H17: =(12000/12) -> 1000 | I17: =G17*H17*E17 -> 0 | J17: ='LOE Breakdown by Year'!D62 -> 0 | K17: =12 -> 12 | L17: =K17*H17*$E$7*$J17 -> 0 | M17: ='LOE Breakdown by Year'!D108 -> 0 | N17: =12 -> 12 | O17: =N17*H17*$M17*$E$7*$E$7 -> 0 | P17: ='LOE Breakdown by Year'!D154 -> 0 | Q17: =12 -> 12 | R17: =Q17*H17*$P17*$E$7*$E$7*$E$7 -> 0 | S17: ='LOE Breakdown by Year'!D200 -> 0 | T17: =12 -> 12 | U17: =T17*H17*$S17*$E$7*$E$7*$E$7*$E$7 -> 0 | V17: ='LOE Breakdown by Year'!D246 -> 0 | W17: 3 | X17: =W17*H17*$V17*$E$7*$E$7*$E$7*$E$7*$E$7 -> 0 | Y17: =SUM(R17,O17,L17,I17,U17,X17) -> 0 | Z17: 0 | AA17: =SUM(Y17:Z17) -> 0
A18: PERADMNNHS | B18: 70000 | C18: HND | D18: Nutrition and Health Specialist | E18: ='LOE Breakdown by Year'!D17 -> 0 | F18: Month | G18: 9 | H18: =18000/12 -> 1500 | I18: =G18*H18*E18 -> 0 | J18: ='LOE Breakdown by Year'!D63 -> 0 | K18: 12 | L18: =K18*H18*$E$7*$J18 -> 0 | M18: ='LOE Breakdown by Year'!D109 -> 0 | N18: 12 | O18: =N18*H18*$M18*$E$7*$E$7 -> 0 | P18: ='LOE Breakdown by Year'!D155 -> 0 | Q18: 12 | R18: =Q18*H18*$P18*$E$7*$E$7*$E$7 -> 0 | S18: ='LOE Breakdown by Year'!D201 -> 0 | T18: 12 | U18: =T18*H18*$S18*$E$7*$E$7*$E$7*$E$7 -> 0 | V18: ='LOE Breakdown by Year'!D247 -> 0 | W18: 6 | X18: =W18*H18*$V18*$E$7*$E$7*$E$7*$E$7*$E$7 -> 0 | Y18: =SUM(R18,O18,L18,I18,U18,X18) -> 0 | Z18: 0 | AA18: =SUM(Y18:Z18) -> 0
A19: PERADMNNOF | B19: 70000 | C19: HND | D19: Nutrition Officer - (2 Individuals) | E19: ='LOE Breakdown by Year'!D18 -> 0 | F19: Month | G19: =2*3 -> 6 | H19: =(12000/12) -> 1000 | I19: =G19*H19*E19 -> 0 | J19: ='LOE Breakdown by Year'!D64 -> 0 | K19: =2*12 -> 24 | L19: =K19*H19*$E$7*$J19 -> 0 | M19: ='LOE Breakdown by Year'!D110 -> 0 | N19: =2*12 -> 24 | O19: =N19*H19*$M19*$E$7*$E$7 -> 0 | P19: ='LOE Breakdown by Year'!D156 -> 0 | Q19: =2*12 -> 24 | R19: =Q19*H19*$P19*$E$7*$E$7*$E$7 -> 0 | S19: ='LOE Breakdown by Year'!D202 -> 0 | T19: =2*12 -> 24 | U19: =T19*H19*$S19*$E$7*$E$7*$E$7*$E$7 -> 0 | V19: ='LOE Breakdown by Year'!D248 -> 0 | W19: =2*3 -> 6 | X19: =W19*H19*$V19*$E$7*$E$7*$E$7*$E$7*$E$7 -> 0 | Y19: =SUM(R19,O19,L19,I19,U19,X19) -> 0 | Z19: 0 | AA19: =SUM(Y19:Z19) -> 0
A20: PERADMNSFS | B20: 70000 | C20: HND | D20: School Feeding Specialist | E20: ='LOE Breakdown by Year'!D19 -> 0 | F20: Month | G20: 9 | H20: =18000/12 -> 1500 | I20: =G20*H20*E20 -> 0 | J20: ='LOE Breakdown by Year'!D65 -> 0 | K20: 12 | L20: =K20*H20*$E$7*$J20 -> 0 | M20: ='LOE Breakdown by Year'!D111 -> 0 | N20: 12 | O20: =N20*H20*$M20*$E$7*$E$7 -> 0 | P20: ='LOE Breakdown by Year'!D157 -> 0 | Q20: 12 | R20: =Q20*H20*$P20*$E$7*$E$7*$E$7 -> 0 | S20: ='LOE Breakdown by Year'!D203 -> 0 | T20: 6 | U20: =T20*H20*$S20*$E$7*$E$7*$E$7*$E$7 -> 0 | V20: ='LOE Breakdown by Year'!D249 -> 0 | W20: 6 | X20: =W20*H20*$V20*$E$7*$E$7*$E$7*$E$7*$E$7 -> 0 | Y20: =SUM(R20,O20,L20,I20,U20,X20) -> 0 | Z20: 0 | AA20: =SUM(Y20:Z20) -> 0
A21: PERADMNFAM | B21: 70000 | C21: HND | D21: Food Aid Monitors - (2 Individuals) | E21: ='LOE Breakdown by Year'!D20 -> 0 | F21: Month | G21: =2*3 -> 6 | H21: =(12000/12) -> 1000 | I21: =G21*H21*E21 -> 0 | J21: ='LOE Breakdown by Year'!D66 -> 0 | K21: =2*12 -> 24 | L21: =K21*H21*$E$7*$J21 -> 0 | M21: ='LOE Breakdown by Year'!D112 -> 0 | N21: =2*12 -> 24 | O21: =N21*H21*$M21*$E$7*$E$7 -> 0 | P21: ='LOE Breakdown by Year'!D158 -> 0 | Q21: =2*12 -> 24 | R21: =Q21*H21*$P21*$E$7*$E$7*$E$7 -> 0 | S21: ='LOE Breakdown by Year'!D204 -> 0 | T21: =2*12 -> 24 | U21: =T21*H21*$S21*$E$7*$E$7*$E$7*$E$7 -> 0 | V21: ='LOE Breakdown by Year'!D250 -> 0 | W21: =2*6 -> 12 | X21: =W21*H21*$V21*$E$7*$E$7*$E$7*$E$7*$E$7 -> 0 | Y21: =SUM(R21,O21,L21,I21,U21,X21) -> 0 | Z21: 0 | AA21: =SUM(Y21:Z21) -> 0
A22: PERADMNWAS | B22: 70000 | C22: HND | D22: WASH Officer | E22: ='LOE Breakdown by Year'!D21 -> 0 | F22: Month | G22: 6 | H22: =(12000/12) -> 1000 | I22: =G22*H22*E22 -> 0 | J22: ='LOE Breakdown by Year'!D67 -> 0 | K22: 12 | L22: =K22*H22*$E$7*$J22 -> 0 | M22: ='LOE Breakdown by Year'!D113 -> 0 | N22: 12 | O22: =N22*H22*$M22*$E$7*$E$7 -> 0 | P22: ='LOE Breakdown by Year'!D159 -> 0 | Q22: 12 | R22: =Q22*H22*$P22*$E$7*$E$7*$E$7 -> 0 | S22: ='LOE Breakdown by Year'!D205 -> 0 | T22: 12 | U22: =T22*H22*$S22*$E$7*$E$7*$E$7*$E$7 -> 0 | V22: ='LOE Breakdown by Year'!D251 -> 0 | W22: 3 | X22: =W22*H22*$V22*$E$7*$E$7*$E$7*$E$7*$E$7 -> 0 | Y22: =SUM(R22,O22,L22,I22,U22,X22) -> 0 | Z22: 0 | AA22: =SUM(Y22:Z22) -> 0
A23: PERADMNCMS | B23: 70000 | C23: HND | D23: Communications Specialist | E23: ='LOE Breakdown by Year'!D22 -> 0.5 | F23: Month | G23: 8 | H23: 1500 | I23: =G23*H23*E23 -> 6000 | J23: ='LOE Breakdown by Year'!D68 -> 0.5 | K23: 12 | L23: =K23*H23*$E$7*$J23 -> 9450 | M23: ='LOE Breakdown by Year'!D114 -> 0.5 | N23: 12 | O23: =N23*H23*$M23*$E$7*$E$7 -> 9922.5 | P23: ='LOE Breakdown by Year'!D160 -> 0.5 | Q23: 12 | R23: =Q23*H23*$P23*$E$7*$E$7*$E$7 -> 10418.625 | S23: ='LOE Breakdown by Year'!D206 -> 0.5 | T23: 12 | U23: =T23*H23*$S23*$E$7*$E$7*$E$7*$E$7 -> 10939.556 | V23: ='LOE Breakdown by Year'!D252 -> 0.5 | W23: 8 | X23: =W23*H23*$V23*$E$7*$E$7*$E$7*$E$7*$E$7 -> 7657.6894 | Y23: =SUM(R23,O23,L23,I23,U23,X23) -> 54388.371 | Z23: 0 | AA23: =SUM(Y23:Z23) -> 54388.371
A24: PERADMNCMO | B24: 70000 | C24: HND | D24: Communications Officer | E24: ='LOE Breakdown by Year'!D23 -> 0 | F24: Month | G24: 0 | H24: =12000/12 -> 1000 | I24: =G24*H24*E24 -> 0 | J24: ='LOE Breakdown by Year'!D69 -> 0 | K24: 12 | L24: =K24*H24*$E$7*$J24 -> 0 | M24: ='LOE Breakdown by Year'!D115 -> 0 | N24: 12 | O24: =N24*H24*$M24*$E$7*$E$7 -> 0 | P24: ='LOE Breakdown by Year'!D161 -> 0 | Q24: 12 | R24: =Q24*H24*$P24*$E$7*$E$7*$E$7 -> 0 | S24: ='LOE Breakdown by Year'!D207 -> 0 | T24: 12 | U24: =T24*H24*$S24*$E$7*$E$7*$E$7*$E$7 -> 0 | V24: ='LOE Breakdown by Year'!D253 -> 0 | W24: 0 | X24: =W24*H24*$V24*$E$7*$E$7*$E$7*$E$7*$E$7 -> 0 | Y24: =SUM(R24,O24,L24,I24,U24,X24) -> 0 | Z24: 0 | AA24: =SUM(Y24:Z24) -> 0
A25: PERADMNECS | B25: 70000 | C25: HND | D25: Education & Community Engagement Specialist | E25: ='LOE Breakdown by Year'!D24 -> 0 | F25: Month | G25: 6 | H25: =18000/12 -> 1500 | I25: =G25*H25*E25 -> 0 | J25: ='LOE Breakdown by Year'!D70 -> 0 | K25: 12 | L25: =K25*H25*$E$7*$J25 -> 0 | M25: ='LOE Breakdown by Year'!D116 -> 0 | N25: 12 | O25: =N25*H25*$M25*$E$7*$E$7 -> 0 | P25: ='LOE Breakdown by Year'!D162 -> 0 | Q25: 12 | R25: =Q25*H25*$P25*$E$7*$E$7*$E$7 -> 0 | S25: ='LOE Breakdown by Year'!D208 -> 0 | T25: 12 | U25: =T25*H25*$S25*$E$7*$E$7*$E$7*$E$7 -> 0 | V25: ='LOE Breakdown by Year'!D254 -> 0 | W25: 8 | X25: =W25*H25*$V25*$E$7*$E$7*$E$7*$E$7*$E$7 -> 0 | Y25: =SUM(R25,O25,L25,I25,U25,X25) -> 0 | Z25: 0 | AA25: =SUM(Y25:Z25) -> 0
A26: PERADMNECO | B26: 70000 | C26: HND | D26: Education & Community Engagement Officer | E26: ='LOE Breakdown by Year'!D25 -> 0 | F26: Month | G26: 3 | H26: =12000/12 -> 1000 | I26: =G26*H26*E26 -> 0 | J26: ='LOE Breakdown by Year'!D71 -> 0 | K26: 12 | L26: =K26*H26*$E$7*$J26 -> 0 | M26: ='LOE Breakdown by Year'!D117 -> 0 | N26: 12 | O26: =N26*H26*$M26*$E$7*$E$7 -> 0 | P26: ='LOE Breakdown by Year'!D163 -> 0 | Q26: 12 | R26: =Q26*H26*$P26*$E$7*$E$7*$E$7 -> 0 | S26: ='LOE Breakdown by Year'!D209 -> 0 | T26: 12 | U26: =T26*H26*$S26*$E$7*$E$7*$E$7*$E$7 -> 0 | V26: ='LOE Breakdown by Year'!D255 -> 0 | W26: 0 | X26: =W26*H26*$V26*$E$7*$E$7*$E$7*$E$7*$E$7 -> 0 | Y26: =SUM(R26,O26,L26,I26,U26,X26) -> 0 | Z26: 0 | AA26: =SUM(Y26:Z26) -> 0
A27: PERADMNPSS | B27: 70000 | C27: HND | D27: Private Sector Specialist | E27: ='LOE Breakdown by Year'!D26 -> 0 | F27: Month | G27: 9 | H27: =24000/12 -> 2000 | I27: =G27*H27*E27 -> 0 | J27: ='LOE Breakdown by Year'!D72 -> 0 | K27: 12 | L27: =K27*H27*$E$7*$J27 -> 0 | M27: ='LOE Breakdown by Year'!D118 -> 0 | N27: 12 | O27: =N27*H27*$M27*$E$7*$E$7 -> 0 | P27: ='LOE Breakdown by Year'!D164 -> 0 | Q27: 12 | R27: =Q27*H27*$P27*$E$7*$E$7*$E$7 -> 0 | S27: ='LOE Breakdown by Year'!D210 -> 0 | T27: 12 | U27: =T27*H27*$S27*$E$7*$E$7*$E$7*$E$7 -> 0 | V27: ='LOE Breakdown by Year'!D256 -> 0 | W27: 6 | X27: =W27*H27*$V27*$E$7*$E$7*$E$7*$E$7*$E$7 -> 0 | Y27: =SUM(R27,O27,L27,I27,U27,X27) -> 0 | Z27: 0 | AA27: =SUM(Y27:Z27) -> 0
A28: PERADMNMED | B28: 70000 | C28: HND | D28: Key Personnel: M&E Director | E28: ='LOE Breakdown by Year'!D27 -> 1 | F28: Month | G28: 11 | H28: =55000/12 -> 4583.3333 | I28: =G28*H28*E28 -> 50416.667 | J28: ='LOE Breakdown by Year'!D73 -> 1 | K28: 12 | L28: =K28*H28*$E$7*$J28 -> 57750 | M28: ='LOE Breakdown by Year'!D119 -> 1 | N28: 12 | O28: =N28*H28*$M28*$E$7*$E$7 -> 60637.5 | P28: ='LOE Breakdown by Year'!D165 -> 1 | Q28: 12 | R28: =Q28*H28*$P28*$E$7*$E$7*$E$7 -> 63669.375 | S28: ='LOE Breakdown by Year'!D211 -> 1 | T28: 12 | U28: =T28*H28*$S28*$E$7*$E$7*$E$7*$E$7 -> 66852.844 | V28: ='LOE Breakdown by Year'!D257 -> 1 | W28: 12 | X28: =W28*H28*$V28*$E$7*$E$7*$E$7*$E$7*$E$7 -> 70195.486 | Y28: =SUM(R28,O28,L28,I28,U28,X28) -> 369521.87 | Z28: 0 | AA28: =SUM(Y28:Z28) -> 369521.87
A29: PERADMNMES | B29: 70000 | C29: HND | D29: M&E Specialist | E29: ='LOE Breakdown by Year'!D28 -> 1 | F29: Month | G29: 6 | H29: =(24000/12) -> 2000 | I29: =G29*H29*E29 -> 12000 | J29: ='LOE Breakdown by Year'!D74 -> 1 | K29: 12 | L29: =K29*H29*$E$7*$J29 -> 25200 | M29: ='LOE Breakdown by Year'!D120 -> 1 | N29: 12 | O29: =N29*H29*$M29*$E$7*$E$7 -> 26460 | P29: ='LOE Breakdown by Year'!D166 -> 1 | Q29: 12 | R29: =Q29*H29*$P29*$E$7*$E$7*$E$7 -> 27783 | S29: ='LOE Breakdown by Year'!D212 -> 1 | T29: 12 | U29: =T29*H29*$S29*$E$7*$E$7*$E$7*$E$7 -> 29172.15 | V29: ='LOE Breakdown by Year'!D258 -> 1 | W29: 11 | X29: =W29*H29*$V29*$E$7*$E$7*$E$7*$E$7*$E$7 -> 28078.194 | Y29: =SUM(R29,O29,L29,I29,U29,X29) -> 148693.34 | Z29: 0 | AA29: =SUM(Y29:Z29) -> 148693.34
A30: PERADMNMEO | B30: 70000 | C30: HND | D30: M&E Officer | E30: ='LOE Breakdown by Year'!D29 -> 1 | F30: Month | G30: 2 | H30: =15000/12 -> 1250 | I30: =G30*H30*E30 -> 2500 | J30: ='LOE Breakdown by Year'!D75 -> 1 | K30: =12 -> 12 | L30: =K30*H30*$E$7*$J30 -> 15750 | M30: ='LOE Breakdown by Year'!D121 -> 1 | N30: =12 -> 12 | O30: =N30*H30*$M30*$E$7*$E$7 -> 16537.5 | P30: ='LOE Breakdown by Year'!D167 -> 1 | Q30: =12 -> 12 | R30: =Q30*H30*$P30*$E$7*$E$7*$E$7 -> 17364.375 | S30: ='LOE Breakdown by Year'!D213 -> 1 | T30: =12 -> 12 | U30: =T30*H30*$S30*$E$7*$E$7*$E$7*$E$7 -> 18232.594 | V30: ='LOE Breakdown by Year'!D259 -> 1 | W30: 3 | X30: =W30*H30*$V30*$E$7*$E$7*$E$7*$E$7*$E$7 -> 4786.0559 | Y30: =SUM(R30,O30,L30,I30,U30,X30) -> 75170.525 | Z30: 0 | AA30: =SUM(Y30:Z30) -> 75170.525
A31: PERADMNSCM | B31: 70000 | C31: HND | D31: Supply Chain Manager | E31: ='LOE Breakdown by Year'!D30 -> 0 | F31: Month | G31: 11 | H31: =60000/12 -> 5000 | I31: =G31*H31*E31 -> 0 | J31: ='LOE Breakdown by Year'!D76 -> 0 | K31: 12 | L31: =K31*H31*$E$7*$J31 -> 0 | M31: ='LOE Breakdown by Year'!D122 -> 0 | N31: 12 | O31: =N31*H31*$M31*$E$7*$E$7 -> 0 | P31: ='LOE Breakdown by Year'!D168 -> 0 | Q31: 12 | R31: =Q31*H31*$P31*$E$7*$E$7*$E$7 -> 0 | S31: ='LOE Breakdown by Year'!D214 -> 0 | T31: 12 | U31: =T31*H31*$S31*$E$7*$E$7*$E$7*$E$7 -> 0 | V31: ='LOE Breakdown by Year'!D260 -> 0 | W31: 8 | X31: =W31*H31*$V31*$E$7*$E$7*$E$7*$E$7*$E$7 -> 0 | Y31: =SUM(R31,O31,L31,I31,U31,X31) -> 0 | Z31: 0 | AA31: =SUM(Y31:Z31) -> 0
A32: PERADMNCLO | B32: 70000 | C32: HND | D32: In-Country Logistics Specialist | E32: ='LOE Breakdown by Year'!D31 -> 0 | F32: Month | G32: 9 | H32: =24000/12 -> 2000 | I32: =G32*H32*E32 -> 0 | J32: ='LOE Breakdown by Year'!D77 -> 0 | K32: 12 | L32: =K32*H32*$E$7*$J32 -> 0 | M32: ='LOE Breakdown by Year'!D123 -> 0 | N32: 12 | O32: =N32*H32*$M32*$E$7*$E$7 -> 0 | P32: ='LOE Breakdown by Year'!D169 -> 0 | Q32: 12 | R32: =Q32*H32*$P32*$E$7*$E$7*$E$7 -> 0 | S32: ='LOE Breakdown by Year'!D215 -> 0 | T32: 12 | U32: =T32*H32*$S32*$E$7*$E$7*$E$7*$E$7 -> 0 | V32: ='LOE Breakdown by Year'!D261 -> 0 | W32: 8 | X32: =W32*H32*$V32*$E$7*$E$7*$E$7*$E$7*$E$7 -> 0 | Y32: =SUM(R32,O32,L32,I32,U32,X32) -> 0 | Z32: 0 | AA32: =SUM(Y32:Z32) -> 0
A33: PERADMNULO | B33: 70000 | C33: HND | D33: US Commodity Logistics Specialist | E33: ='LOE Breakdown by Year'!D32 -> 0 | F33: Month | G33: 9 | H33: =24000/12 -> 2000 | I33: =G33*H33*E33 -> 0 | J33: ='LOE Breakdown by Year'!D78 -> 0 | K33: 12 | L33: =K33*H33*$E$7*$J33 -> 0 | M33: ='LOE Breakdown by Year'!D124 -> 0 | N33: 12 | O33: =N33*H33*$M33*$E$7*$E$7 -> 0 | P33: ='LOE Breakdown by Year'!D170 -> 0 | Q33: 12 | R33: =Q33*H33*$P33*$E$7*$E$7*$E$7 -> 0 | S33: ='LOE Breakdown by Year'!D216 -> 0 | T33: 12 | U33: =T33*H33*$S33*$E$7*$E$7*$E$7*$E$7 -> 0 | V33: ='LOE Breakdown by Year'!D262 -> 0 | W33: 8 | X33: =W33*H33*$V33*$E$7*$E$7*$E$7*$E$7*$E$7 -> 0 | Y33: =SUM(R33,O33,L33,I33,U33,X33) -> 0 | Z33: 0 | AA33: =SUM(Y33:Z33) -> 0
A34: PERADMNWHM | B34: 70000 | C34: HND | D34: Warehouse Manager | E34: ='LOE Breakdown by Year'!D33 -> 0 | F34: Month | G34: 8 | H34: 1250 | I34: =G34*H34*E34 -> 0 | J34: ='LOE Breakdown by Year'!D79 -> 0 | K34: 12 | L34: =K34*H34*$E$7*$J34 -> 0 | M34: ='LOE Breakdown by Year'!D125 -> 0 | N34: 12 | O34: =N34*H34*$M34*$E$7*$E$7 -> 0 | P34: ='LOE Breakdown by Year'!D171 -> 0 | Q34: 12 | R34: =Q34*H34*$P34*$E$7*$E$7*$E$7 -> 0 | S34: ='LOE Breakdown by Year'!D217 -> 0 | T34: 12 | U34: =T34*H34*$S34*$E$7*$E$7*$E$7*$E$7 -> 0 | V34: ='LOE Breakdown by Year'!D263 -> 0 | W34: 8 | X34: =W34*H34*$V34*$E$7*$E$7*$E$7*$E$7*$E$7 -> 0 | Y34: =SUM(R34,O34,L34,I34,U34,X34) -> 0 | Z34: 0 | AA34: =SUM(Y34:Z34) -> 0
A35: PERADMNWHO | B35: 70000 | C35: HND | D35: Warehouse Officer - (2 Individuals) | E35: ='LOE Breakdown by Year'!D34 -> 0 | F35: Month | G35: =2*4 -> 8 | H35: =(12000/12) -> 1000 | I35: =G35*H35*E35 -> 0 | J35: ='LOE Breakdown by Year'!D80 -> 0 | K35: =2*12 -> 24 | L35: =K35*H35*$E$7*$J35 -> 0 | M35: ='LOE Breakdown by Year'!D126 -> 0 | N35: =2*12 -> 24 | O35: =N35*H35*$M35*$E$7*$E$7 -> 0 | P35: ='LOE Breakdown by Year'!D172 -> 0 | Q35: =2*12 -> 24 | R35: =Q35*H35*$P35*$E$7*$E$7*$E$7 -> 0 | S35: ='LOE Breakdown by Year'!D218 -> 0 | T35: =2*12 -> 24 | U35: =T35*H35*$S35*$E$7*$E$7*$E$7*$E$7 -> 0 | V35: ='LOE Breakdown by Year'!D264 -> 0 | W35: =2*4 -> 8 | X35: =W35*H35*$V35*$E$7*$E$7*$E$7*$E$7*$E$7 -> 0 | Y35: =SUM(R35,O35,L35,I35,U35,X35) -> 0 | Z35: 0 | AA35: =SUM(Y35:Z35) -> 0
A36: PERADMNLRP | B36: 70000 | C36: HND | D36: LRP Technical Specialist | E36: ='LOE Breakdown by Year'!D35 -> 0 | F36: Month | G36: 8 | H36: =18000/12 -> 1500 | I36: =G36*H36*E36 -> 0 | J36: ='LOE Breakdown by Year'!D81 -> 0 | K36: 12 | L36: =K36*H36*$E$7*$J36 -> 0 | M36: ='LOE Breakdown by Year'!D127 -> 0 | N36: 12 | O36: =N36*H36*$M36*$E$7*$E$7 -> 0 | P36: ='LOE Breakdown by Year'!D173 -> 0 | Q36: 12 | R36: =Q36*H36*$P36*$E$7*$E$7*$E$7 -> 0 | S36: ='LOE Breakdown by Year'!D219 -> 0 | T36: 12 | U36: =T36*H36*$S36*$E$7*$E$7*$E$7*$E$7 -> 0 | V36: ='LOE Breakdown by Year'!D265 -> 0 | W36: 0 | X36: =W36*H36*$V36*$E$7*$E$7*$E$7*$E$7*$E$7 -> 0 | Y36: =SUM(R36,O36,L36,I36,U36,X36) -> 0 | Z36: 0 | AA36: =SUM(Y36:Z36) -> 0
A37: PERADMNFAD | B37: 70000 | C37: HND | D37: Finance & Administration Director | E37: ='LOE Breakdown by Year'!D36 -> 1 | F37: Month | G37: 9 | H37: =60000/12 -> 5000 | I37: =G37*H37*E37 -> 45000 | J37: ='LOE Breakdown by Year'!D82 -> 1 | K37: 12 | L37: =K37*H37*$E$7*$J37 -> 63000 | M37: ='LOE Breakdown by Year'!D128 -> 1 | N37: 12 | O37: =N37*H37*$M37*$E$7*$E$7 -> 66150 | P37: ='LOE Breakdown by Year'!D174 -> 1 | Q37: 12 | R37: =Q37*H37*$P37*$E$7*$E$7*$E$7 -> 69457.5 | S37: ='LOE Breakdown by Year'!D220 -> 1 | T37: 12 | U37: =T37*H37*$S37*$E$7*$E$7*$E$7*$E$7 -> 72930.375 | V37: ='LOE Breakdown by Year'!D266 -> 1 | W37: 12 | X37: =W37*H37*$V37*$E$7*$E$7*$E$7*$E$7*$E$7 -> 76576.894 | Y37: =SUM(R37,O37,L37,I37,U37,X37) -> 393114.77 | Z37: 0 | AA37: =SUM(Y37:Z37) -> 393114.77
A38: PERADMNCCM | B38: 70000 | C38: HND | D38: Contracts & Compliance Manager | E38: ='LOE Breakdown by Year'!D37 -> 1 | F38: Month | G38: 9 | H38: =31600/12 -> 2633.3333 | I38: =G38*H38*E38 -> 23700 | J38: ='LOE Breakdown by Year'!D83 -> 1 | K38: 12 | L38: =K38*H38*$E$7*$J38 -> 33180 | M38: ='LOE Breakdown by Year'!D129 -> 1 | N38: 12 | O38: =N38*H38*$M38*$E$7*$E$7 -> 34839 | P38: ='LOE Breakdown by Year'!D175 -> 1 | Q38: 12 | R38: =Q38*H38*$P38*$E$7*$E$7*$E$7 -> 36580.95 | S38: ='LOE Breakdown by Year'!D221 -> 1 | T38: 12 | U38: =T38*H38*$S38*$E$7*$E$7*$E$7*$E$7 -> 38409.998 | V38: ='LOE Breakdown by Year'!D267 -> 1 | W38: 11 | X38: =W38*H38*$V38*$E$7*$E$7*$E$7*$E$7*$E$7 -> 36969.623 | Y38: =SUM(R38,O38,L38,I38,U38,X38) -> 203679.57 | Z38: 0 | AA38: =SUM(Y38:Z38) -> 203679.57
A39: PERADMNGPS | B39: 70000 | C39: HND | D39: Grants & Procurement Specialist | E39: ='LOE Breakdown by Year'!D38 -> 1 | F39: Month | G39: 6 | H39: 1500 | I39: =G39*H39*E39 -> 9000 | J39: ='LOE Breakdown by Year'!D84 -> 1 | K39: 12 | L39: =K39*H39*$E$7*$J39 -> 18900 | M39: ='LOE Breakdown by Year'!D130 -> 1 | N39: 12 | O39: =N39*H39*$M39*$E$7*$E$7 -> 19845 | P39: ='LOE Breakdown by Year'!D176 -> 1 | Q39: 12 | R39: =Q39*H39*$P39*$E$7*$E$7*$E$7 -> 20837.25 | S39: ='LOE Breakdown by Year'!D222 -> 1 | T39: 12 | U39: =T39*H39*$S39*$E$7*$E$7*$E$7*$E$7 -> 21879.112 | V39: ='LOE Breakdown by Year'!D268 -> 1 | W39: 6 | X39: =W39*H39*$V39*$E$7*$E$7*$E$7*$E$7*$E$7 -> 11486.534 | Y39: =SUM(R39,O39,L39,I39,U39,X39) -> 101947.9 | Z39: 0 | AA39: =SUM(Y39:Z39) -> 101947.9
A40: PERADMNGPO | B40: 70000 | C40: HND | D40: Grants & Procurement Officer | E40: ='LOE Breakdown by Year'!D39 -> 1 | F40: Month | G40: 2 | H40: =12000/12 -> 1000 | I40: =G40*H40*E40 -> 2000 | J40: ='LOE Breakdown by Year'!D85 -> 1 | K40: 12 | L40: =K40*H40*$E$7*$J40 -> 12600 | M40: ='LOE Breakdown by Year'!D131 -> 1 | N40: 12 | O40: =N40*H40*$M40*$E$7*$E$7 -> 13230 | P40: ='LOE Breakdown by Year'!D177 -> 1 | Q40: 12 | R40: =Q40*H40*$P40*$E$7*$E$7*$E$7 -> 13891.5 | S40: ='LOE Breakdown by Year'!D223 -> 1 | T40: 12 | U40: =T40*H40*$S40*$E$7*$E$7*$E$7*$E$7 -> 14586.075 | V40: ='LOE Breakdown by Year'!D269 -> 1 | W40: 3 | X40: =W40*H40*$V40*$E$7*$E$7*$E$7*$E$7*$E$7 -> 3828.8447 | Y40: =SUM(R40,O40,L40,I40,U40,X40) -> 60136.42 | Z40: 0 | AA40: =SUM(Y40:Z40) -> 60136.42
A41: PERADMNFNO | B41: 70000 | C41: HND | D41: Finance Officer | E41: ='LOE Breakdown by Year'!D40 -> 1 | F41: Month | G41: 9 | H41: =15000/12 -> 1250 | I41: =G41*H41*E41 -> 11250 | J41: ='LOE Breakdown by Year'!D86 -> 1 | K41: 12 | L41: =K41*H41*$E$7*$J41 -> 15750 | M41: ='LOE Breakdown by Year'!D132 -> 1 | N41: 12 | O41: =N41*H41*$M41*$E$7*$E$7 -> 16537.5 | P41: ='LOE Breakdown by Year'!D178 -> 1 | Q41: 12 | R41: =Q41*H41*$P41*$E$7*$E$7*$E$7 -> 17364.375 | S41: ='LOE Breakdown by Year'!D224 -> 1 | T41: 12 | U41: =T41*H41*$S41*$E$7*$E$7*$E$7*$E$7 -> 18232.594 | V41: ='LOE Breakdown by Year'!D270 -> 1 | W41: 11 | X41: =W41*H41*$V41*$E$7*$E$7*$E$7*$E$7*$E$7 -> 17548.871 | Y41: =SUM(R41,O41,L41,I41,U41,X41) -> 96683.34 | Z41: 0 | AA41: =SUM(Y41:Z41) -> 96683.34
A42: PERADMNACT | B42: 70000 | C42: HND | D42: Accountant | E42: ='LOE Breakdown by Year'!D41 -> 1 | F42: Month | G42: 3 | H42: =(12000/12) -> 1000 | I42: =G42*H42*E42 -> 3000 | J42: ='LOE Breakdown by Year'!D87 -> 1 | K42: 12 | L42: =K42*H42*$E$7*$J42 -> 12600 | M42: ='LOE Breakdown by Year'!D133 -> 1 | N42: 12 | O42: =N42*H42*$M42*$E$7*$E$7 -> 13230 | P42: ='LOE Breakdown by Year'!D179 -> 1 | Q42: 12 | R42: =Q42*H42*$P42*$E$7*$E$7*$E$7 -> 13891.5 | S42: ='LOE Breakdown by Year'!D225 -> 1 | T42: 12 | U42: =T42*H42*$S42*$E$7*$E$7*$E$7*$E$7 -> 14586.075 | V42: ='LOE Breakdown by Year'!D271 -> 1 | W42: 9 | X42: =W42*H42*$V42*$E$7*$E$7*$E$7*$E$7*$E$7 -> 11486.534 | Y42: =SUM(R42,O42,L42,I42,U42,X42) -> 68794.109 | Z42: 0 | AA42: =SUM(Y42:Z42) -> 68794.109
A43: PERADMNHRM | B43: 70000 | C43: HND | D43: Operation & HR Manager | E43: ='LOE Breakdown by Year'!D42 -> 1 | F43: Month | G43: 9 | H43: =21600/12 -> 1800 | I43: =G43*H43*E43 -> 16200 | J43: ='LOE Breakdown by Year'!D88 -> 1 | K43: 12 | L43: =K43*H43*$E$7*$J43 -> 22680 | M43: ='LOE Breakdown by Year'!D134 -> 1 | N43: 12 | O43: =N43*H43*$M43*$E$7*$E$7 -> 23814 | P43: ='LOE Breakdown by Year'!D180 -> 1 | Q43: 12 | R43: =Q43*H43*$P43*$E$7*$E$7*$E$7 -> 25004.7 | S43: ='LOE Breakdown by Year'!D226 -> 1 | T43: 12 | U43: =T43*H43*$S43*$E$7*$E$7*$E$7*$E$7 -> 26254.935 | V43: ='LOE Breakdown by Year'!D272 -> 1 | W43: 11 | X43: =W43*H43*$V43*$E$7*$E$7*$E$7*$E$7*$E$7 -> 25270.375 | Y43: =SUM(R43,O43,L43,I43,U43,X43) -> 139224.01 | Z43: 0 | AA43: =SUM(Y43:Z43) -> 139224.01
A44: PERADMNADA | B44: 70000 | C44: HND | D44: Administrative Assistant - (2 Individuals) | E44: ='LOE Breakdown by Year'!D43 -> 1 | F44: Month | G44: =3*2 -> 6 | H44: =(9000/12) -> 750 | I44: =G44*H44*E44 -> 4500 | J44: ='LOE Breakdown by Year'!D89 -> 1 | K44: =12*2 -> 24 | L44: =K44*H44*$E$7*$J44 -> 18900 | M44: ='LOE Breakdown by Year'!D135 -> 1 | N44: =12*2 -> 24 | O44: =N44*H44*$M44*$E$7*$E$7 -> 19845 | P44: ='LOE Breakdown by Year'!D181 -> 1 | Q44: =12*2 -> 24 | R44: =Q44*H44*$P44*$E$7*$E$7*$E$7 -> 20837.25 | S44: ='LOE Breakdown by Year'!D227 -> 1 | T44: =12*2 -> 24 | U44: =T44*H44*$S44*$E$7*$E$7*$E$7*$E$7 -> 21879.112 | V44: ='LOE Breakdown by Year'!D273 -> 1 | W44: =5*2 -> 10 | X44: =W44*H44*$V44*$E$7*$E$7*$E$7*$E$7*$E$7 -> 9572.1117 | Y44: =SUM(R44,O44,L44,I44,U44,X44) -> 95533.474 | Z44: 0 | AA44: =SUM(Y44:Z44) -> 95533.474
A45: PERADMNDRV | B45: 70000 | C45: HND | D45: Driver - (2 Individuals) | E45: ='LOE Breakdown by Year'!D44 -> 1 | F45: Month | G45: =2*3 -> 6 | H45: =(6000/12) -> 500 | I45: =G45*H45*E45 -> 3000 | J45: ='LOE Breakdown by Year'!D90 -> 1 | K45: =2*12 -> 24 | L45: =K45*H45*$E$7*$J45 -> 12600 | M45: ='LOE Breakdown by Year'!D136 -> 1 | N45: =2*12 -> 24 | O45: =N45*H45*$M45*$E$7*$E$7 -> 13230 | P45: ='LOE Breakdown by Year'!D182 -> 1 | Q45: =2*12 -> 24 | R45: =Q45*H45*$P45*$E$7*$E$7*$E$7 -> 13891.5 | S45: ='LOE Breakdown by Year'!D228 -> 1 | T45: =2*12 -> 24 | U45: =T45*H45*$S45*$E$7*$E$7*$E$7*$E$7 -> 14586.075 | V45: ='LOE Breakdown by Year'!D274 -> 1 | W45: =2*9 -> 18 | X45: =W45*H45*$V45*$E$7*$E$7*$E$7*$E$7*$E$7 -> 11486.534 | Y45: =SUM(R45,O45,L45,I45,U45,X45) -> 68794.109 | Z45: 0 | AA45: =SUM(Y45:Z45) -> 68794.109
D46: Headquarters (HQ) Support (LOE)
A47: PERADMNVPP | B47: 50000 | C47: USA | D47: Senior Vice President of Programs | E47: ='LOE Breakdown by Year'!D46 -> 0.35 | F47: Month | G47: 12 | H47: =162000/12 -> 13500 | I47: =G47*H47*E47 -> 56700 | J47: ='LOE Breakdown by Year'!D92 -> 0.35 | K47: 12 | L47: =K47*H47*$E$7*$J47 -> 59535 | M47: ='LOE Breakdown by Year'!D138 -> 0.35 | N47: 12 | O47: =N47*H47*$M47*$E$7*$E$7 -> 62511.75 | P47: ='LOE Breakdown by Year'!D184 -> 0.35 | Q47: 12 | R47: =Q47*H47*$P47*$E$7*$E$7*$E$7 -> 65637.338 | S47: ='LOE Breakdown by Year'!D230 -> 0.35 | T47: 12 | U47: =T47*H47*$S47*$E$7*$E$7*$E$7*$E$7 -> 68919.204 | V47: ='LOE Breakdown by Year'!D276 -> 0.35 | W47: 12 | X47: =W47*H47*$V47*$E$7*$E$7*$E$7*$E$7*$E$7 -> 72365.165 | Y47: =SUM(R47,O47,L47,I47,U47,X47) -> 385668.46 | Z47: 0 | AA47: =SUM(Y47:Z47) -> 385668.46
A48: PERADMNPGD | B48: 50000 | C48: USA | D48: Program Director | E48: ='LOE Breakdown by Year'!D47 -> 0.9 | F48: Month | G48: 12 | H48: =150000/12 -> 12500 | I48: =G48*H48*E48 -> 135000 | J48: ='LOE Breakdown by Year'!D93 -> 0.9 | K48: 12 | L48: =K48*H48*$E$7*$J48 -> 141750 | M48: ='LOE Breakdown by Year'!D139 -> 0.9 | N48: 12 | O48: =N48*H48*$M48*$E$7*$E$7 -> 148837.5 | P48: ='LOE Breakdown by Year'!D185 -> 0.9 | Q48: 12 | R48: =Q48*H48*$P48*$E$7*$E$7*$E$7 -> 156279.38 | S48: ='LOE Breakdown by Year'!D231 -> 0.9 | T48: 12 | U48: =T48*H48*$S48*$E$7*$E$7*$E$7*$E$7 -> 164093.34 | V48: ='LOE Breakdown by Year'!D277 -> 0.9 | W48: 12 | X48: =W48*H48*$V48*$E$7*$E$7*$E$7*$E$7*$E$7 -> 172298.01 | Y48: =SUM(R48,O48,L48,I48,U48,X48) -> 918258.23 | Z48: 0 | AA48: =SUM(Y48:Z48) -> 918258.23
A49: PERADMNCCD | B49: 50000 | C49: USA | D49: Compliance & Contracts Director | E49: ='LOE Breakdown by Year'!D48 -> 0.2 | F49: Month | G49: 12 | H49: =110000/12 -> 9166.6667 | I49: =G49*H49*E49 -> 22000 | J49: ='LOE Breakdown by Year'!D94 -> 0.2 | K49: 12 | L49: =K49*H49*$E$7*$J49 -> 23100 | M49: ='LOE Breakdown by Year'!D140 -> 0.2 | N49: 12 | O49: =N49*H49*$M49*$E$7*$E$7 -> 24255 | P49: ='LOE Breakdown by Year'!D186 -> 0.2 | Q49: 12 | R49: =Q49*H49*$P49*$E$7*$E$7*$E$7 -> 25467.75 | S49: ='LOE Breakdown by Year'!D232 -> 0.2 | T49: 12 | U49: =T49*H49*$S49*$E$7*$E$7*$E$7*$E$7 -> 26741.138 | V49: ='LOE Breakdown by Year'!D278 -> 0.2 | W49: 12 | X49: =W49*H49*$V49*$E$7*$E$7*$E$7*$E$7*$E$7 -> 28078.194 | Y49: =SUM(R49,O49,L49,I49,U49,X49) -> 149642.08 | Z49: 0 | AA49: =SUM(Y49:Z49) -> 149642.08
A50: PERADMNASD | B50: 50000 | C50: USA | D50: Associate Director | E50: ='LOE Breakdown by Year'!D49 -> 1 | F50: Month | G50: 12 | H50: =90000/12 -> 7500 | I50: =G50*H50*E50 -> 90000 | J50: ='LOE Breakdown by Year'!D95 -> 1 | K50: 12 | L50: =K50*H50*$E$7*$J50 -> 94500 | M50: ='LOE Breakdown by Year'!D141 -> 1 | N50: 12 | O50: =N50*H50*$M50*$E$7*$E$7 -> 99225 | P50: ='LOE Breakdown by Year'!D187 -> 1 | Q50: 12 | R50: =Q50*H50*$P50*$E$7*$E$7*$E$7 -> 104186.25 | S50: ='LOE Breakdown by Year'!D233 -> 1 | T50: 12 | U50: =T50*H50*$S50*$E$7*$E$7*$E$7*$E$7 -> 109395.56 | V50: ='LOE Breakdown by Year'!D279 -> 1 | W50: 12 | X50: =W50*H50*$V50*$E$7*$E$7*$E$7*$E$7*$E$7 -> 114865.34 | Y50: =SUM(R50,O50,L50,I50,U50,X50) -> 612172.15 | Z50: 0 | AA50: =SUM(Y50:Z50) -> 612172.15
A51: PERADMNSPO | B51: 50000 | C51: USA | D51: Senior Program Officer | E51: ='LOE Breakdown by Year'!D50 -> 0.2 | F51: Month | G51: 12 | H51: =71000/12 -> 5916.6667 | I51: =G51*H51*E51 -> 14200 | J51: ='LOE Breakdown by Year'!D96 -> 0.05 | K51: 12 | L51: =K51*H51*$E$7*$J51 -> 3727.5 | M51: ='LOE Breakdown by Year'!D142 -> 0.05 | N51: 12 | O51: =N51*H51*$M51*$E$7*$E$7 -> 3913.875 | P51: ='LOE Breakdown by Year'!D188 -> 0.05 | Q51: 12 | R51: =Q51*H51*$P51*$E$7*$E$7*$E$7 -> 4109.5688 | S51: ='LOE Breakdown by Year'!D234 -> 0.05 | T51: 12 | U51: =T51*H51*$S51*$E$7*$E$7*$E$7*$E$7 -> 4315.0472 | V51: ='LOE Breakdown by Year'!D280 -> 0.2 | W51: 12 | X51: =W51*H51*$V51*$E$7*$E$7*$E$7*$E$7*$E$7 -> 18123.198 | Y51: =SUM(R51,O51,L51,I51,U51,X51) -> 48389.189 | Z51: 0 | AA51: =SUM(Y51:Z51) -> 48389.189
D53: Total Personnel | I53: =SUM(I12:I51) -> 683383.33 | L53: =SUM(L12:L51) -> 843622.5 | O53: =SUM(O12:O51) -> 885803.62 | R53: =SUM(R12:R51) -> 930093.81 | U53: =SUM(U12:U51) -> 976598.5 | X53: =SUM(X12:X51) -> 966996 | Y53: =SUM(Y12:Y51) -> 5286497.8 | Z53: =SUM(Z12:Z51) -> 0 | AA53: =SUM(AA12:AA51) -> 5286497.8
D55: Fringe Benefits
A56: FRINGEADM | B56: 70015 | C56: HND | D56: Fringe Benefits CCN - Honduras | F56: % | H56: 0.4826 | I56: =(SUM(I12:I45))*$H$56 -> 176382.26 | L56: =(SUM(L12:L45))*$H$56 -> 251439.43 | O56: =(SUM(O12:O45))*$H$56 -> 264011.4 | R56: =(SUM(R12:R45))*$H$56 -> 277211.97 | U56: =(SUM(U12:U45))*$H$56 -> 291072.57 | X56: =(SUM(X12:X45))*$H$56 -> 270867.01 | Y56: =SUM(R56,O56,L56,I56,U56,X56) -> 1530984.6 | Z56: 0 | AA56: =SUM(Y56:Z56) -> 1530984.6
A57: FRINGE | B57: 50900 | C57: USA | D57: Fringe Benefits - HQ | F57: % | H57: 0.2347 | I57: =(SUM(I46:I51))*$H$57 -> 74611.13 | L57: =(SUM(L46:L51))*$H$57 -> 75717.154 | O57: =(SUM(O46:O51))*$H$57 -> 79503.011 | R57: =(SUM(R46:R51))*$H$57 -> 83478.162 | U57: =(SUM(U46:U51))*$H$57 -> 87652.07 | X57: =(SUM(X46:X51))*$H$57 -> 95224.81 | Y57: =SUM(R57,O57,L57,I57,U57,X57) -> 496186.34 | Z57: 0 | AA57: =SUM(Y57:Z57) -> 496186.34
D59: Total Fringe Benefits | I59: =SUM(I56:I58) -> 250993.39 | L59: =SUM(L56:L58) -> 327156.58 | O59: =SUM(O56:O58) -> 343514.41 | R59: =SUM(R56:R58) -> 360690.13 | U59: =SUM(U56:U58) -> 378724.64 | X59: =SUM(X56:X58) -> 366091.82 | Y59: =SUM(Y56:Y58) -> 2027171 | Z59: =SUM(Z56:Z58) -> 0 | AA59: =SUM(AA56:AA58) -> 2027171
D61: Travel
D62: HQ Staff Travel - International
A63: STFTRAVEL | B63: 86040 | C63: USA | D63: Airfare - DC-Honduras - HQ Project Management Trip | F63: Trip | G63: 4 | H63: 800 | I63: =G63*H63 -> 3200 | K63: 4 | L63: =H63*K63*$E$6 -> 3360 | N63: 4 | O63: =H63*N63*$E$6*$E$6 -> 3528 | Q63: 4 | R63: =H63*Q63*$E$6*$E$6*$E$6 -> 3704.4 | T63: 4 | U63: =T63*H63*$E$6*$E$6*$E$6*$E$6 -> 3889.62 | W63: 4 | X63: =W63*H63*$E$6*$E$6*$E$6*$E$6*$E$6 -> 4084.101 | Y63: =SUM(R63,O63,L63,I63,U63,X63) -> 21766.121 | Z63: - | AA63: =SUM(Y63:Z63) -> 21766.121
A64: STFTRVCTS | B64: 86030 (Lodging)/ 86050 (M&IE) | C64: USA | D64: Lodging and M&IE - HQ Project Management Trip | F64: Day | G64: =G63*7 -> 28 | H64: =150 + (0.9*87) -> 228.3 | I64: =G64*H64 -> 6392.4 | K64: =K63*7 -> 28 | L64: =H64*K64*$E$6 -> 6712.02 | N64: =N63*7 -> 28 | O64: =H64*N64*$E$6*$E$6 -> 7047.621 | Q64: =Q63*7 -> 28 | R64: =H64*Q64*$E$6*$E$6*$E$6 -> 7400.0021 | T64: =T63*7 -> 28 | U64: =T64*H64*$E$6*$E$6*$E$6*$E$6 -> 7770.0022 | W64: =W63*7 -> 28 | X64: =W64*H64*$E$6*$E$6*$E$6*$E$6*$E$6 -> 8158.5023 | Y64: =SUM(R64,O64,L64,I64,U64,X64) -> 43480.547 | Z64: - | AA64: =SUM(Y64:Z64) -> 43480.547
A65: STFTRVCTS | B65: 86000 | C65: USA | D65: Local Transportation – HQ Project Management Trip | F65: Trip | G65: =G63 -> 4 | H65: =120 -> 120 | I65: =G65*H65 -> 480 | K65: =K63 -> 4 | L65: =H65*K65*$E$6 -> 504 | N65: =N63 -> 4 | O65: =H65*N65*$E$6*$E$6 -> 529.2 | Q65: =Q63 -> 4 | R65: =H65*Q65*$E$6*$E$6*$E$6 -> 555.66 | T65: =T63 -> 4 | U65: =T65*H65*$E$6*$E$6*$E$6*$E$6 -> 583.443 | W65: =W63 -> 4 | X65: =W65*H65*$E$6*$E$6*$E$6*$E$6*$E$6 -> 612.61515 | Y65: =SUM(R65,O65,L65,I65,U65,X65) -> 3264.9182 | Z65: - | AA65: =SUM(Y65:Z65) -> 3264.9182
A66: STFTRVCTS | B66: 86050 | C66: USA | D66: Other Travel Related Expenses – HQ Project Management Trip | F66: Trip | G66: =G63 -> 4 | H66: 100 | I66: =G66*H66 -> 400 | K66: =K63 -> 4 | L66: =H66*K66*$E$6 -> 420 | N66: =N63 -> 4 | O66: =H66*N66*$E$6*$E$6 -> 441 | Q66: =Q63 -> 4 | R66: =H66*Q66*$E$6*$E$6*$E$6 -> 463.05 | T66: =T63 -> 4 | U66: =T66*H66*$E$6*$E$6*$E$6*$E$6 -> 486.2025 | W66: =W63 -> 4 | X66: =W66*H66*$E$6*$E$6*$E$6*$E$6*$E$6 -> 510.51263 | Y66: =SUM(R66,O66,L66,I66,U66,X66) -> 2720.7651 | Z66: - | AA66: =SUM(Y66:Z66) -> 2720.7651
D67: Honduras Staff Travel - International
A68: INTLTRVLHN | B68: 86040 | C68: HND | D68: Airfare - Roundtrip - Honduras to USA | F68: Trip | G68: 2 | H68: 800 | I68: =G68*H68 -> 1600 | K68: 2 | L68: =H68*K68*$E$6 -> 1680 | N68: 2 | O68: =H68*N68*$E$6*$E$6 -> 1764 | Q68: 2 | R68: =H68*Q68*$E$6*$E$6*$E$6 -> 1852.2 | T68: 2 | U68: =T68*H68*$E$6*$E$6*$E$6*$E$6 -> 1944.81 | W68: 2 | X68: =W68*H68*$E$6*$E$6*$E$6*$E$6*$E$6 -> 2042.0505 | Y68: =SUM(R68,O68,L68,I68,U68,X68) -> 10883.06 | Z68: - | AA68: =SUM(Y68:Z68) -> 10883.06
A69: INTLTRVLHN | B69: 86030 (Lodging)/ 86050 (M&IE) | C69: HND | D69: Lodging and M&IE for Honduras Staff Travel | F69: Day | G69: =7*G68 -> 14 | H69: =180 + (0.9*92) -> 262.8 | I69: =G69*H69 -> 3679.2 | K69: =7*K68 -> 14 | L69: =H69*K69*$E$6 -> 3863.16 | N69: =7*N68 -> 14 | O69: =H69*N69*$E$6*$E$6 -> 4056.318 | Q69: =7*Q68 -> 14 | R69: =H69*Q69*$E$6*$E$6*$E$6 -> 4259.1339 | T69: =7*T68 -> 14 | U69: =T69*H69*$E$6*$E$6*$E$6*$E$6 -> 4472.0906 | W69: =7*W68 -> 14 | X69: =W69*H69*$E$6*$E$6*$E$6*$E$6*$E$6 -> 4695.6951 | Y69: =SUM(R69,O69,L69,I69,U69,X69) -> 25025.598 | Z69: - | AA69: =SUM(Y69:Z69) -> 25025.598
A70: INTLTRVLHN | B70: 86000 | C70: HND | D70: Local Transportation for Honduras Staff Travel | F70: Trip | G70: =G68 -> 2 | H70: =120 -> 120 | I70: =G70*H70 -> 240 | K70: =K68 -> 2 | L70: =H70*K70*$E$6 -> 252 | N70: =N68 -> 2 | O70: =H70*N70*$E$6*$E$6 -> 264.6 | Q70: =Q68 -> 2 | R70: =H70*Q70*$E$6*$E$6*$E$6 -> 277.83 | T70: =T68 -> 2 | U70: =T70*H70*$E$6*$E$6*$E$6*$E$6 -> 291.7215 | W70: =W68 -> 2 | X70: =W70*H70*$E$6*$E$6*$E$6*$E$6*$E$6 -> 306.30758 | Y70: =SUM(R70,O70,L70,I70,U70,X70) -> 1632.4591 | Z70: - | AA70: =SUM(Y70:Z70) -> 1632.4591
A71: INTLTRVLHN | B71: 86050 | C71: HND | D71: Other Travel Related Expenses for Honduras Staff Travel | F71: Trip | G71: =G68 -> 2 | H71: 100 | I71: =G71*H71 -> 200 | K71: =K68 -> 2 | L71: =H71*K71*$E$6 -> 210 | N71: =N68 -> 2 | O71: =H71*N71*$E$6*$E$6 -> 220.5 | Q71: =Q68 -> 2 | R71: =H71*Q71*$E$6*$E$6*$E$6 -> 231.525 | T71: =T68 -> 2 | U71: =T71*H71*$E$6*$E$6*$E$6*$E$6 -> 243.10125 | W71: =W68 -> 2 | X71: =W71*H71*$E$6*$E$6*$E$6*$E$6*$E$6 -> 255.25631 | Y71: =SUM(R71,O71,L71,I71,U71,X71) -> 1360.3826 | Z71: - | AA71: =SUM(Y71:Z71) -> 1360.3826
D72: Honduras Staff Travel - Domestic (Tegucigalpa-Intibucá)
A73: LOTRVLINT | B73: 86000 | C73: HND | D73: Vehicle Fuel Expense | F73: Month | G73: 3 | H73: 120 | I73: =G73*H73 -> 360 | K73: 12 | L73: =H73*K73*$E$6 -> 1512 | N73: 12 | O73: =H73*N73*$E$6*$E$6 -> 1587.6 | Q73: 12 | R73: =H73*Q73*$E$6*$E$6*$E$6 -> 1666.98 | T73: 12 | U73: =T73*H73*$E$6*$E$6*$E$6*$E$6 -> 1750.329 | W73: 7 | X73: =W73*H73*$E$6*$E$6*$E$6*$E$6*$E$6 -> 1072.0765 | Y73: =SUM(R73,O73,L73,I73,U73,X73) -> 7948.9855 | Z73: - | AA73: =SUM(Y73:Z73) -> 7948.9855
A74: LOTRVLINT | B74: 86000 | C74: HND | D74: Local Transportation – Training, M&E, & Data Collection | F74: Trip | G74: =12*3 -> 36 | H74: 55 | I74: =G74*H74 -> 1980 | K74: =12*3 -> 36 | L74: =H74*K74*$E$6 -> 2079 | N74: =12*3 -> 36 | O74: =H74*N74*$E$6*$E$6 -> 2182.95 | Q74: =12*3 -> 36 | R74: =H74*Q74*$E$6*$E$6*$E$6 -> 2292.0975 | T74: =12*3 -> 36 | U74: =T74*H74*$E$6*$E$6*$E$6*$E$6 -> 2406.7024 | W74: =12*3 -> 36 | X74: =W74*H74*$E$6*$E$6*$E$6*$E$6*$E$6 -> 2527.0375 | Y74: =SUM(R74,O74,L74,I74,U74,X74) -> 13467.787 | Z74: - | AA74: =SUM(Y74:Z74) -> 13467.787
A75: LOTRVLINT | B75: 86030 (Lodging)/ 86050 (M&IE) | C75: HND | D75: Lodging and M&IE - Training, M&E, & Data Collection | F75: Day | G75: =4*G74 -> 144 | H75: =70 + (0.5*80) -> 110 | I75: =G75*H75 -> 15840 | K75: =4*K74 -> 144 | L75: =H75*K75*$E$6 -> 16632 | N75: =4*N74 -> 144 | O75: =H75*N75*$E$6*$E$6 -> 17463.6 | Q75: =4*Q74 -> 144 | R75: =H75*Q75*$E$6*$E$6*$E$6 -> 18336.78 | T75: =4*T74 -> 144 | U75: =T75*H75*$E$6*$E$6*$E$6*$E$6 -> 19253.619 | W75: =4*W74 -> 144 | X75: =W75*H75*$E$6*$E$6*$E$6*$E$6*$E$6 -> 20216.3 | Y75: =SUM(R75,O75,L75,I75,U75,X75) -> 107742.3 | Z75: - | AA75: =SUM(Y75:Z75) -> 107742.3
D76: Honduras Staff Travel - Domestic (Tegucigalpa-La Paz)
A77: LOTRVLPAZ | B77: 86000 | C77: HND | D77: Vehicle Fuel Expense | F77: Month | G77: 3 | H77: 120 | I77: =G77*H77 -> 360 | K77: 12 | L77: =H77*K77*$E$6 -> 1512 | N77: 12 | O77: =H77*N77*$E$6*$E$6 -> 1587.6 | Q77: 12 | R77: =H77*Q77*$E$6*$E$6*$E$6 -> 1666.98 | T77: 12 | U77: =T77*H77*$E$6*$E$6*$E$6*$E$6 -> 1750.329 | W77: 9 | X77: =W77*H77*$E$6*$E$6*$E$6*$E$6*$E$6 -> 1378.3841 | Y77: =SUM(R77,O77,L77,I77,U77,X77) -> 8255.2931 | Z77: - | AA77: =SUM(Y77:Z77) -> 8255.2931
A78: LOTRVLPAZ | B78: 86000 | C78: HND | D78: Local Transportation – Training, M&E, & Data Collection | F78: Trip | G78: =12*3 -> 36 | H78: 35 | I78: =G78*H78 -> 1260 | K78: =12*3 -> 36 | L78: =H78*K78*$E$6 -> 1323 | N78: =12*3 -> 36 | O78: =H78*N78*$E$6*$E$6 -> 1389.15 | Q78: =12*3 -> 36 | R78: =H78*Q78*$E$6*$E$6*$E$6 -> 1458.6075 | T78: =12*3 -> 36 | U78: =T78*H78*$E$6*$E$6*$E$6*$E$6 -> 1531.5379 | W78: =12*3 -> 36 | X78: =W78*H78*$E$6*$E$6*$E$6*$E$6*$E$6 -> 1608.1148 | Y78: =SUM(R78,O78,L78,I78,U78,X78) -> 8570.4101 | Z78: - | AA78: =SUM(Y78:Z78) -> 8570.4101
A79: LOTRVLPAZ | B79: 86030 (Lodging)/ 86050 (M&IE) | C79: HND | D79: Lodging and M&IE - Training, M&E, & Data Collection | F79: Day | G79: =4*G78 -> 144 | H79: =75 + + (0.5*80) -> 115 | I79: =G79*H79 -> 16560 | K79: =4*K78 -> 144 | L79: =H79*K79*$E$6 -> 17388 | N79: =4*N78 -> 144 | O79: =H79*N79*$E$6*$E$6 -> 18257.4 | Q79: =4*Q78 -> 144 | R79: =H79*Q79*$E$6*$E$6*$E$6 -> 19170.27 | T79: =4*T78 -> 144 | U79: =T79*H79*$E$6*$E$6*$E$6*$E$6 -> 20128.784 | W79: =4*W78 -> 144 | X79: =W79*H79*$E$6*$E$6*$E$6*$E$6*$E$6 -> 21135.223 | Y79: =SUM(R79,O79,L79,I79,U79,X79) -> 112639.68 | Z79: - | AA79: =SUM(Y79:Z79) -> 112639.68
D80: Total Travel | I80: =SUM(I62:I79) -> 52551.6 | L80: =SUM(L62:L79) -> 57447.18 | O80: =SUM(O62:O79) -> 60319.539 | R80: =SUM(R62:R79) -> 63335.516 | U80: =SUM(U62:U79) -> 66502.292 | X80: =SUM(X62:X79) -> 68602.176 | Y80: =SUM(Y62:Y79) -> 368758.3 | Z80: =SUM(Z62:Z79) -> 0 | AA80: =SUM(AA62:AA79) -> 368758.3
D82: Professional Services/Contractual
A83: AUDIT | B83: 82100 | C83: HND | D83: Audit Costs - (Program Specific Audits) | F83: Year | G83: 1 | H83: 5000 | I83: =G83*H83 -> 5000 | K83: 1 | L83: =K83*H83 -> 5000 | N83: 1 | O83: =N83*H83 -> 5000 | Q83: 1 | R83: =Q83*H83 -> 5000 | T83: 1 | U83: =T83*H83 -> 5000 | W83: 1 | X83: =W83*H83 -> 5000 | Y83: =SUM(R83,O83,L83,I83,U83,X83) -> 30000 | Z83: 0 | AA83: =Y83+Z83 -> 30000
A84: LEGAL | B84: 81010 | C84: HND | D84: Legal & Representation Fees | F84: Year | G84: 1 | H84: 7000 | I84: =G84*H84 -> 7000 | K84: 1 | L84: =K84*H84 -> 7000 | N84: 1 | O84: =N84*H84 -> 7000 | Q84: 1 | R84: =Q84*H84 -> 7000 | T84: 1 | U84: =T84*H84 -> 7000 | W84: 1 | X84: =W84*H84 -> 7000 | Y84: =SUM(R84,O84,L84,I84,U84,X84) -> 42000 | Z84: 0 | AA84: =Y84+Z84 -> 42000
A85: SECURITY | B85: 86110 | C85: HND | D85: Security Services, Risk Assessments, & Security Assessment | F85: Year | G85: 1 | H85: 20000 | I85: =G85*H85 -> 20000 | K85: 1 | L85: =K85*H85 -> 20000 | N85: 1 | O85: =N85*H85 -> 20000 | Q85: 1 | R85: =Q85*H85 -> 20000 | T85: 1 | U85: =T85*H85 -> 20000 | W85: 1 | X85: =W85*H85 -> 20000 | Y85: =SUM(R85,O85,L85,I85,U85,X85) -> 120000 | Z85: 0 | AA85: =Y85+Z85 -> 120000
A86: CONSULT | B86: 81000 | C86: HND | D86: Start-up Consultant | F86: Day | G86: 108 | H86: 600 | I86: =G86*H86 -> 64800 | K86: 0 | L86: =K86*H86 -> 0 | N86: 0 | O86: =N86*H86 -> 0 | Q86: 0 | R86: =Q86*H86 -> 0 | T86: 0 | U86: =T86*H86 -> 0 | W86: 0 | X86: =W86*H86 -> 0 | Y86: =SUM(R86,O86,L86,I86,U86,X86) -> 64800 | Z86: 0 | AA86: =Y86+Z86 -> 64800
A87: STUDY | B87: 81010 | C87: HND | D87: Market Study | F87: Day | G87: 75 | H87: 400 | I87: =H87*G87 -> 30000 | K87: 0 | L87: =K87*H87 -> 0 | N87: 0 | O87: =N87*H87 -> 0 | Q87: 0 | R87: =Q87*H87 -> 0 | T87: 0 | U87: =T87*H87 -> 0 | W87: 0 | X87: =W87*H87 -> 0 | Y87: =SUM(R87,O87,L87,I87,U87,X87) -> 30000 | Z87: 0 | AA87: =Y87+Z87 -> 30000
D88: Evaluations
A89: BASELINE | B89: 81010 | C89: HND | D89: Baseline Evaluation | F89: Unit | G89: 1 | H89: 150000 | I89: =G89*H89 -> 150000 | K89: 0 | L89: =K89*H89 -> 0 | N89: 0 | O89: =N89*H89 -> 0 | Q89: 0 | R89: =Q89*H89 -> 0 | T89: 0 | U89: =T89*H89 -> 0 | W89: 0 | X89: =W89*H89 -> 0 | Y89: =SUM(R89,O89,L89,I89,U89,X89) -> 150000 | Z89: 0 | AA89: =Y89+Z89 -> 150000
A90: MIDTERM | B90: 81010 | C90: HND | D90: Midterm Evaluation | F90: Unit | G90: 0 | H90: 160000 | I90: =G90*H90 -> 0 | K90: 0 | L90: =K90*H90 -> 0 | N90: 1 | O90: =N90*H90 -> 160000 | Q90: 0 | R90: =Q90*H90 -> 0 | T90: 0 | U90: =T90*H90 -> 0 | W90: 0 | X90: =W90*H90 -> 0 | Y90: =SUM(R90,O90,L90,I90,U90,X90) -> 160000 | Z90: 0 | AA90: =Y90+Z90 -> 160000
A91: ENDLINE | B91: 81010 | C91: HND | D91: Final Evaluation | F91: Unit | G91: 0 | H91: 175000 | I91: =G91*H91 -> 0 | K91: 0 | L91: =K91*H91 -> 0 | N91: 0 | O91: =N91*H91 -> 0 | Q91: 0 | R91: =Q91*H91 -> 0 | T91: 0 | U91: =T91*H91 -> 0 | W91: 1 | X91: =W91*H91 -> 175000 | Y91: =SUM(R91,O91,L91,I91,U91,X91) -> 175000 | Z91: 0 | AA91: =Y91+Z91 -> 175000
A92: SPECSTUDY | B92: 81010 | C92: HND | D92: 2 Special Studies: (1) Feasibility of Integrating CSB+ into the National Feeding Program Study & (2) Sustainability & Institutional Readiness Study | F92: Unit | G92: 0.5 | H92: 125000 | I92: =G92*H92 -> 62500 | K92: 0 | L92: =K92*H92 -> 0 | N92: 1 | O92: =N92*H92 -> 125000 | Q92: 0.5 | R92: =Q92*H92 -> 62500 | T92: 0 | U92: =T92*H92 -> 0 | W92: 0 | X92: =W92*H92 -> 0 | Y92: =SUM(R92,O92,L92,I92,U92,X92) -> 250000 | Z92: 0 | AA92: =Y92+Z92 -> 250000
D93: Monitoring Guidelines Development
A94: M&EGUIDE | B94: 81021 (Translation)/ 85300 (Printing) | C94: HND | D94: Monitoring Guidelines Creation, Translation & Printing | F94: Document | G94: 1 | H94: 10000 | I94: =G94*H94 -> 10000 | K94: 0 | L94: =K94*H94 -> 0 | N94: 0 | O94: =N94*H94 -> 0 | Q94: 0 | R94: =Q94*H94 -> 0 | T94: 0 | U94: =T94*H94 -> 0 | W94: 0 | X94: =W94*H94 -> 0 | Y94: =SUM(R94,O94,L94,I94,U94,X94) -> 10000 | Z94: - | AA94: =SUM(Y94:Z94) -> 10000
A95: M&EGUIDE | B95: 81021 (Translation)/ 85300 (Printing) | C95: HND | D95: Monitoring Guidelines Revision, Translation & Printing | F95: Year | G95: 0 | H95: 2000 | I95: =G95*H95 -> 0 | K95: 1 | L95: =K95*H95 -> 2000 | N95: 1 | O95: =N95*H95 -> 2000 | Q95: 1 | R95: =Q95*H95 -> 2000 | T95: 1 | U95: =T95*H95 -> 2000 | W95: 1 | X95: =W95*H95 -> 2000 | Y95: =SUM(R95,O95,L95,I95,U95,X95) -> 10000 | Z95: - | AA95: =SUM(Y95:Z95) -> 10000
A96: M&ETRAIN | B96: 87000 | C96: HND | D96: Monitoring Guidelines Staff Training on Indicators and Data Collection/Analysis | F96: Workshop | G96: 1 | H96: 6000 | I96: =G96*H96 -> 6000 | K96: 1 | L96: =K96*H96 -> 6000 | N96: 1 | O96: =N96*H96 -> 6000 | Q96: 1 | R96: =Q96*H96 -> 6000 | T96: 1 | U96: =T96*H96 -> 6000 | W96: 1 | X96: =W96*H96 -> 6000 | Y96: =SUM(R96,O96,L96,I96,U96,X96) -> 36000 | Z96: - | AA96: =SUM(Y96:Z96) -> 36000
D97: M&E Database
A98: M&EDATA | B98: 89400 | C98: USA | D98: M&E Database Platform Subscription (includes training) | F98: Year | G98: 1 | H98: 6500 | I98: =G98*H98 -> 6500 | K98: 1 | L98: =K98*H98 -> 6500 | N98: 1 | O98: =N98*H98 -> 6500 | Q98: 1 | R98: =Q98*H98 -> 6500 | T98: 1 | U98: =T98*H98 -> 6500 | W98: 1 | X98: =W98*H98 -> 6500 | Y98: =SUM(R98,O98,L98,I98,U98,X98) -> 39000 | AA98: =SUM(Y98:Z98) -> 39000 | AB98: M&E Budget
D99: Monitoring, Evaluation, and Collection of Reliable Data Subtotal | I99: =SUM(I88:I98) -> 235000 | L99: =SUM(L88:L98) -> 14500 | O99: =SUM(O88:O98) -> 299500 | R99: =SUM(R88:R98) -> 77000 | U99: =SUM(U88:U98) -> 14500 | X99: =SUM(X88:X98) -> 189500 | Y99: =SUM(Y88:Y98) -> 830000 | Z99: =SUM(Z88:Z98) -> 0 | AA99: =SUM(AA88:AA98) -> 830000 | AB99: =AA99/'USDA Budget Summary'!E12 -> 0.030148709
D101: Total Professional Services/Contractual | I101: =SUM(I83:I98) -> 361800 | L101: =SUM(L83:L98) -> 46500 | O101: =SUM(O83:O98) -> 331500 | R101: =SUM(R83:R98) -> 109000 | U101: =SUM(U83:U98) -> 46500 | X101: =SUM(X83:X98) -> 221500 | Y101: =SUM(Y83:Y98) -> 1116800 | Z101: =SUM(Z83:Z98) -> 0 | AA101: =SUM(Y101:Z101) -> 1116800
D103: Equipment
A104: VEHICLE | B104: 85200 | C104: HND | D104: Vehicles for Field Office | F104: Unit | G104: 1 | H104: 53000 | I104: =G104*H104 -> 53000 | K104: 0 | L104: =K104*H104 -> 0 | N104: 0 | O104: =N104*H104 -> 0 | Q104: 0 | R104: =Q104*H104 -> 0 | T104: 0 | U104: =T104*K104 -> 0 | W104: 0 | X104: =W104*H104 -> 0 | Y104: =SUM(R104,O104,L104,I104,U104,X104) -> 53000 | Z104: 0 | AA104: =Y104+Z104 -> 53000
D106: Total Equipment | I106: =SUM(I104:I104) -> 53000 | L106: =SUM(L104:L104) -> 0 | O106: =SUM(O104:O104) -> 0 | R106: =SUM(R104:R104) -> 0 | U106: =SUM(U104:U104) -> 0 | X106: =SUM(X104:X104) -> 0 | Y106: =SUM(Y104:Y105) -> 53000 | Z106: =SUM(Z104:Z104) -> 0 | AA106: =SUM(Y106:Z106) -> 53000
D108: Office Supplies
A109: LAPTOP | B109: 82401 | C109: HND/USA | D109: Desktop/Laptop Computers | F109: Unit | G109: 37 | H109: 1280 | I109: =G109*H109 -> 47360 | K109: 0 | L109: =K109*H109 -> 0 | N109: 0 | O109: =N109*H109 -> 0 | Q109: 0 | R109: =Q109*H109 -> 0 | T109: 0 | U109: =T109*K109 -> 0 | W109: 0 | X109: =W109*H109 -> 0 | Y109: =SUM(R109,O109,L109,I109,U109,X109) -> 47360 | Z109: 0 | AA109: =Y109+Z109 -> 47360
A110: SUPPLIES | B110: 82401 | C110: HND/USA | D110: All in One: Printer, Photocopier & Scanner | F110: Unit | G110: 2 | H110: 350 | I110: =G110*H110 -> 700 | K110: 0 | L110: =K110*H110 -> 0 | N110: 0 | O110: =N110*H110 -> 0 | Q110: 0 | R110: =Q110*H110 -> 0 | T110: 0 | U110: =T110*K110 -> 0 | W110: 0 | X110: =W110*H110 -> 0 | Y110: =SUM(R110,O110,L110,I110,U110,X110) -> 700 | Z110: 0 | AA110: =Y110+Z110 -> 700
...

Sheet FEREMA Sub Budget
C2: Subrecipient Budget MGD
C3: Country of Operation: HONDURAS
C4: Implementing Organization: FEREMA
A5: Budget Assumptions
A6: Merit Based Increases for Staff - 5% | B6: 1.05
A7: Inflation rate - 5% | B7: 1.05
A9: Item | B9: Type of Unit | C9: Year 1 | G9: Year 2 | K9: Year 3 | O9: Year 4 | S9: Year 5 | W9: Total | AA9: Activity 3 | AB9: Activity 4 | AC9: Activity 6
C10: Cost | D10: Quantity | E10: Percent Allocated | F10: Total | G10: Cost | H10: Quantity | I10: Percent Allocated | J10: Total | K10: Cost | L10: Quantity | M10: Percent Allocated | N10: Total | O10: Cost | P10: Quantity | Q10: Percent Allocated | R10: Total | S10: Cost | T10: Quantity | U10: Percent Allocated | V10: Total | AA10: 0.73024993 | AB10: 0.080106447 | AC10: 0.18964362
A11: Direct Costs | X11: A3 | Y11: A4 | Z11: A6
A12: Salaries | X12: 0.8 | Y12: 0.1 | Z12: 0.1
A13: CCN Staff
A14: Project Coordinator | B14: Month | C14: 2900 | D14: 3 | E14: 1 | F14: =C14*D14*E14 -> 8700 | G14: =C14*$B$6 -> 3045 | H14: 12 | I14: 1 | J14: =G14*H14*I14 -> 36540 | K14: =G14*$B$6 -> 3197.25 | L14: 12 | M14: 1 | N14: =K14*L14*M14 -> 38367 | O14: =K14*$B$6 -> 3357.1125 | P14: 12 | Q14: 1 | R14: =O14*P14*Q14 -> 40285.35 | S14: =O14*$B$6 -> 3524.9681 | T14: 3 | U14: 1 | V14: =S14*T14*U14 -> 10574.904 | W14: =F14+J14+N14+V14+R14 -> 134467.25 | X14: =+W14*$X$12 -> 107573.8 | Y14: =+W14*$Y$12 -> 13446.725 | Z14: =+W14*$Z$12 -> 13446.725
A15: Education Officer (3 officers) | B15: Month | C15: 950 | D15: =3*1 -> 3 | E15: 1 | F15: =C15*D15*E15 -> 2850 | G15: =C15*$B$6 -> 997.5 | H15: =12*3 -> 36 | I15: 1 | J15: =G15*H15*I15 -> 35910 | K15: =G15*$B$6 -> 1047.375 | L15: =12*3 -> 36 | M15: 1 | N15: =K15*L15*M15 -> 37705.5 | O15: =K15*$B$6 -> 1099.7438 | P15: =12*3 -> 36 | Q15: 1 | R15: =O15*P15*Q15 -> 39590.775 | S15: =O15*$B$6 -> 1154.7309 | T15: =3*2 -> 6 | U15: 1 | V15: =S15*T15*U15 -> 6928.3856 | W15: =F15+J15+N15+V15+R15 -> 122984.66 | X15: =+W15 -> 122984.66
A16: Preschool Specialist | B16: Month | C16: 1900 | D16: 0 | E16: 1 | F16: =C16*D16*E16 -> 0 | G16: =C16*$B$6 -> 1995 | H16: 12 | I16: 1 | J16: =G16*H16*I16 -> 23940 | K16: =G16*$B$6 -> 2094.75 | L16: 12 | M16: 1 | N16: =K16*L16*M16 -> 25137 | O16: =K16*$B$6 -> 2199.4875 | P16: 12 | Q16: 1 | R16: =O16*P16*Q16 -> 26393.85 | S16: =O16*$B$6 -> 2309.4619 | T16: 0 | U16: 1 | V16: =S16*T16*U16 -> 0 | W16: =F16+J16+N16+V16+R16 -> 75470.85 | Y16: =+W16 -> 75470.85
A17: Logistics Officer | B17: Month | C17: 950 | D17: 0 | E17: 1 | F17: =C17*D17*E17 -> 0 | G17: =C17*$B$6 -> 997.5 | H17: 12 | I17: 1 | J17: =G17*H17*I17 -> 11970 | K17: =G17*$B$6 -> 1047.375 | L17: 12 | M17: 1 | N17: =K17*L17*M17 -> 12568.5 | O17: =K17*$B$6 -> 1099.7438 | P17: 12 | Q17: 1 | R17: =O17*P17*Q17 -> 13196.925 | S17: =O17*$B$6 -> 1154.7309 | T17: 0 | U17: 1 | V17: =S17*T17*U17 -> 0 | W17: =F17+J17+N17+V17+R17 -> 37735.425 | Y17: =+W17 -> 37735.425
A18: Financial Specialist | B18: Month | C18: 1900 | D18: 3 | E18: 1 | F18: =C18*D18*E18 -> 5700 | G18: =C18*$B$6 -> 1995 | H18: 12 | I18: 1 | J18: =G18*H18*I18 -> 23940 | K18: =G18*$B$6 -> 2094.75 | L18: 12 | M18: 1 | N18: =K18*L18*M18 -> 25137 | O18: =K18*$B$6 -> 2199.4875 | P18: 12 | Q18: 1 | R18: =O18*P18*Q18 -> 26393.85 | S18: =O18*$B$6 -> 2309.4619 | T18: 3 | U18: 1 | V18: =S18*T18*U18 -> 6928.3856 | W18: =F18+J18+N18+V18+R18 -> 88099.236 | X18: =+W18*$X$12 -> 70479.389 | Y18: =+W18*$Y$12 -> 8809.9236 | Z18: =+W18*$Z$12 -> 8809.9236
A19: Financial, Accounting, and Logistics Assistant | B19: Month | C19: 950 | D19: 3 | E19: 0.5 | F19: =C19*D19*E19 -> 1425 | G19: =C19*$B$6 -> 997.5 | H19: 12 | I19: 1 | J19: =G19*H19*I19 -> 11970 | K19: =G19*$B$6 -> 1047.375 | L19: 12 | M19: 1 | N19: =K19*L19*M19 -> 12568.5 | O19: =K19*$B$6 -> 1099.7438 | P19: 12 | Q19: 1 | R19: =O19*P19*Q19 -> 13196.925 | S19: =O19*$B$6 -> 1154.7309 | T19: 3 | U19: 1 | V19: =S19*T19*U19 -> 3464.1928 | W19: =F19+J19+N19+V19+R19 -> 42624.618 | X19: =+W19*$X$12 -> 34099.694 | Y19: =+W19*$Y$12 -> 4262.4618 | Z19: =+W19*$Z$12 -> 4262.4618
A21: Subtotal: Salaries & Wages | F21: =SUM(F14:F19) -> 18675 | J21: =SUM(J14:J19) -> 144270 | N21: =SUM(N14:N19) -> 151483.5 | R21: =SUM(R14:R19) -> 159057.67 | V21: =SUM(V14:V19) -> 27895.868 | W21: =SUM(W14:W19) -> 501382.04 | AA21: =W21*$AA$10 -> 366134.2 | AB21: =W21*$AB$10 -> 40163.934 | AC21: =W21*$AC$10 -> 95083.906
A22: Fringe
A23: CCN Staff | B23: 0.37 | C23: =(SUM(F14:F19))*$B$23 -> 6909.75 | E23: 1 | F23: =C23*E23 -> 6909.75 | G23: =(SUM(J14:J19))*$B$23 -> 53379.9 | I23: 1 | J23: =G23*I23 -> 53379.9 | K23: =(SUM(N14:N19))*$B$23 -> 56048.895 | M23: 1 | N23: =K23*M23 -> 56048.895 | O23: =(SUM(R14:R19))*$B$23 -> 58851.34 | Q23: 1 | R23: =O23*Q23 -> 58851.34 | S23: =(SUM(V14:V19))*$B$23 -> 10321.471 | U23: 1 | V23: =S23*U23 -> 10321.471 | W23: =F23+J23+N23+V23+R23 -> 185511.36
A25: Subtotal: Benefits | F25: =F23 -> 6909.75 | J25: =J23 -> 53379.9 | N25: =N23 -> 56048.895 | R25: =R23 -> 58851.34 | V25: =V23 -> 10321.471 | W25: =W23 -> 185511.36 | X25: =+W25*$X$12 -> 148409.08 | Y25: =+W25*$Y$12 -> 18551.136 | Z25: =+W25*$Z$12 -> 18551.136 | AA25: =W25*$AA$10 -> 135469.66 | AB25: =W25*$AB$10 -> 14860.656 | AC25: =W25*$AC$10 -> 35181.045
A26: Local Travel
A27: Local Transportation for Trainings and Field Activities - Staff | B27: Daily | C27: 10 | D27: =((1*10)*2)+((2*10)*2)+((0*10)*2)+((1*5)*2)+((1*5)*2) -> 80 | E27: 1 | F27: =C27*D27*E27 -> 800 | G27: =C27*$B$6 -> 10.5 | H27: =((1*10)*12)+((2*10)*12)+((1*10)*12)+((1*5)*12)+((1*5)*12) -> 600 | I27: 1 | J27: =G27*H27*I27 -> 6300 | K27: =G27*$B$6 -> 11.025 | L27: =((1*10)*12)+((2*10)*12)+((1*10)*12)+((1*5)*12)+((1*5)*12) -> 600 | M27: 1 | N27: =K27*L27*M27 -> 6615 | O27: =K27*$B$6 -> 11.57625 | P27: =((1*10)*12)+((2*10)*12)+((1*10)*12)+((1*5)*12)+((1*5)*12) -> 600 | Q27: 1 | R27: =O27*P27*Q27 -> 6945.75 | S27: =O27*$B$6 -> 12.155063 | T27: =((1*10)*2)+((2*10)*2)+((0*10)*2)+((1*5)*2)+((1*5)*2) -> 80 | U27: 1 | V27: =S27*T27*U27 -> 972.405 | W27: =F27+J27+N27+V27+R27 -> 21633.155 | X27: =+W27*$X$12 -> 17306.524 | Y27: =+W27*$Y$12 -> 2163.3155 | Z27: =+W27*$Z$12 -> 2163.3155
A28: Local Transportation for Trainings and Field Activities - Consultants Activity 3.1 (Strengthen Teaching Using Targeted Instruction and GANE Guides) | B28: Daily | C28: 10 | D28: =+(10*5)+(0*10) -> 50 | E28: 1 | F28: =C28*D28*E28 -> 500 | G28: =C28*$B$6 -> 10.5 | H28: =+(10*5)+(35*10) -> 400 | I28: 1 | J28: =G28*H28*I28 -> 4200 | K28: =G28*$B$6 -> 11.025 | L28: =+(10*5)+(35*10) -> 400 | M28: 1 | N28: =K28*L28*M28 -> 4410 | O28: =K28*$B$6 -> 11.57625 | P28: =+(10*5)+(35*10) -> 400 | Q28: 1 | R28: =O28*P28*Q28 -> 4630.5 | S28: =O28*$B$6 -> 12.155063 | T28: 0 | U28: 1 | V28: =S28*T28*U28 -> 0 | W28: =F28+J28+N28+V28+R28 -> 13740.5 | X28: =+W28 -> 13740.5
A29: Local Transportation for Trainings and Field Activities - Consultants Activity 6.2 Deliver Nutrition for Early Learners and Caregivers | B29: Daily | C29: 10 | D29: =8*10 -> 80 | E29: 1 | F29: =C29*D29*E29 -> 800 | G29: =C29*$B$6 -> 10.5 | H29: =8*10*12 -> 960 | I29: 1 | J29: =G29*H29*I29 -> 10080 | K29: =G29*$B$6 -> 11.025 | L29: =8*10*12 -> 960 | M29: 1 | N29: =K29*L29*M29 -> 10584 | O29: =K29*$B$6 -> 11.57625 | P29: =8*10*12 -> 960 | Q29: 1 | R29: =O29*P29*Q29 -> 11113.2 | S29: =O29*$B$6 -> 12.155063 | T29: 0 | U29: 1 | V29: =S29*T29*U29 -> 0 | W29: =F29+J29+N29+V29+R29 -> 32577.2 | Z29: =+W29 -> 32577.2
A30: Per Diem | W30: =F30+J30+N30+V30+R30 -> 0
A31: Per Diem - Staff | B31: Daily | C31: 20 | D31: =+D27 -> 80 | E31: 1 | F31: =C31*D31*E31 -> 1600 | G31: =C31*$B$6 -> 21 | H31: =+H27 -> 600 | I31: 1 | J31: =G31*H31*I31 -> 12600 | K31: =G31*$B$6 -> 22.05 | L31: =+L27 -> 600 | M31: 1 | N31: =K31*L31*M31 -> 13230 | O31: =K31*$B$6 -> 23.1525 | P31: =+P27 -> 600 | Q31: 1 | R31: =O31*P31*Q31 -> 13891.5 | S31: =O31*$B$6 -> 24.310125 | T31: =+T27 -> 80 | U31: 1 | V31: =S31*T31*U31 -> 1944.81 | W31: =F31+J31+N31+V31+R31 -> 43266.31 | X31: =+W31*$X$12 -> 34613.048 | Y31: =+W31*$Y$12 -> 4326.631 | Z31: =+W31*$Z$12 -> 4326.631
A32: Per Diem - - Consultants Activity 3.1 (Strengthen Teaching Using Targeted Instruction and GANE Guides) | B32: Daily | C32: 20 | D32: =+D28 -> 50 | E32: 1 | F32: =C32*D32*E32 -> 1000 | G32: =C32*$B$6 -> 21 | H32: =+H28 -> 400 | I32: 1 | J32: =G32*H32*I32 -> 8400 | K32: =G32*$B$6 -> 22.05 | L32: =+L28 -> 400 | M32: 1 | N32: =K32*L32*M32 -> 8820 | O32: =K32*$B$6 -> 23.1525 | P32: =+P28 -> 400 | Q32: 1 | R32: =O32*P32*Q32 -> 9261 | S32: =O32*$B$6 -> 24.310125 | T32: 0 | U32: 1 | V32: =S32*T32*U32 -> 0 | W32: =F32+J32+N32+V32+R32 -> 27481 | X32: =+W32 -> 27481
A33: Per Diem -Consultants Activity 6.2 Deliver Nutrition for Early Learners and Caregivers | B33: Daily | C33: 20 | D33: =+D29 -> 80 | E33: 1 | F33: =C33*D33*E33 -> 1600 | G33: =C33*$B$6 -> 21 | H33: =+H29 -> 960 | I33: 1 | J33: =G33*H33*I33 -> 20160 | K33: =G33*$B$6 -> 22.05 | L33: =+L29 -> 960 | M33: 1 | N33: =K33*L33*M33 -> 21168 | O33: =K33*$B$6 -> 23.1525 | P33: =+P29 -> 960 | Q33: 1 | R33: =O33*P33*Q33 -> 22226.4 | S33: =O33*$B$6 -> 24.310125 | T33: 0 | U33: 1 | V33: =S33*T33*U33 -> 0 | W33: =F33+J33+N33+V33+R33 -> 65154.4 | Z33: =+W33 -> 65154.4
A34: Lodging and M&IE for Trainings | W34: =F34+J34+N34+V34+R34 -> 0
A35: Lodging and M&IE for Trainings - Staff | B35: Daily | C35: 45 | D35: 80 | E35: 1 | F35: =C35*D35*E35 -> 3600 | G35: =C35*$B$6 -> 47.25 | H35: 450 | I35: 1 | J35: =G35*H35*I35 -> 21262.5 | K35: =G35*$B$6 -> 49.6125 | L35: 450 | M35: 1 | N35: =K35*L35*M35 -> 22325.625 | O35: =K35*$B$6 -> 52.093125 | P35: 450 | Q35: 1 | R35: =O35*P35*Q35 -> 23441.906 | S35: =O35*$B$6 -> 54.697781 | T35: 80 | U35: 1 | V35: =S35*T35*U35 -> 4375.8225 | W35: =F35+J35+N35+V35+R35 -> 75005.854 | X35: =+W35*$X$12 -> 60004.683 | Y35: =+W35*$Y$12 -> 7500.5854 | Z35: =+W35*$Z$12 -> 7500.5854
A36: Lodging and M&IE for Trainings - Consultants Activity 3.1 (Strengthen Teaching Using Targeted Instruction and GANE Guides) | B36: Daily | C36: 45 | D36: 50 | E36: 1 | F36: =C36*D36*E36 -> 2250 | G36: =C36*$B$6 -> 47.25 | H36: 300 | I36: 1 | J36: =G36*H36*I36 -> 14175 | K36: =G36*$B$6 -> 49.6125 | L36: 300 | M36: 1 | N36: =K36*L36*M36 -> 14883.75 | O36: =K36*$B$6 -> 52.093125 | P36: 300 | Q36: 1 | R36: =O36*P36*Q36 -> 15627.938 | S36: =O36*$B$6 -> 54.697781 | T36: 0 | U36: 1 | V36: =S36*T36*U36 -> 0 | W36: =F36+J36+N36+V36+R36 -> 46936.688 | X36: =+W36 -> 46936.688
A37: Lodging and M&IE for Trainings - Consultants Activity 6.2 Deliver Nutrition for Early Learners and Caregivers | B37: Daily | C37: 45 | D37: 80 | E37: 1 | F37: =C37*D37*E37 -> 3600 | G37: =C37*$B$6 -> 47.25 | H37: 800 | I37: 1 | J37: =G37*H37*I37 -> 37800 | K37: =G37*$B$6 -> 49.6125 | L37: 800 | M37: 1 | N37: =K37*L37*M37 -> 39690 | O37: =K37*$B$6 -> 52.093125 | P37: 800 | Q37: 1 | R37: =O37*P37*Q37 -> 41674.5 | S37: =O37*$B$6 -> 54.697781 | T37: 0 | U37: 1 | V37: =S37*T37*U37 -> 0 | W37: =F37+J37+N37+V37+R37 -> 122764.5 | Z37: =+W37 -> 122764.5
A38: Rent and Full transportation | B38: Daily | C38: 120 | D38: =3*5*4 -> 60 | E38: 1 | F38: =C38*D38*E38 -> 7200 | G38: =C38*$B$6 -> 126 | H38: =9*5*4 -> 180 | I38: 1 | J38: =G38*H38*I38 -> 22680 | K38: =G38*$B$6 -> 132.3 | L38: =9*5*4 -> 180 | M38: 1 | N38: =K38*L38*M38 -> 23814 | O38: =K38*$B$6 -> 138.915 | P38: =9*5*4 -> 180 | Q38: 1 | R38: =O38*P38*Q38 -> 25004.7 | S38: =O38*$B$6 -> 145.86075 | T38: =3*5*4 -> 60 | U38: 1 | V38: =S38*T38*U38 -> 8751.645 | W38: =F38+J38+N38+V38+R38 -> 87450.345 | X38: =+W38*$X$12 -> 69960.276 | Y38: =+W38*$Y$12 -> 8745.0345 | Z38: =+W38*$Z$12 -> 8745.0345
A39: Subtotal: Travel | F39: =SUM(F26:F38) -> 22950 | J39: =SUM(J26:J38) -> 157657.5 | N39: =SUM(N26:N38) -> 165540.38 | R39: =SUM(R26:R38) -> 173817.39 | V39: =SUM(V26:V38) -> 16044.683 | W39: =SUM(W26:W38) -> 536009.95 | AA39: =W39*$AA$10 -> 391421.23 | AB39: =W39*$AB$10 -> 42937.853 | AC39: =W39*$AC$10 -> 101650.87
A40: Professional Services
A41: Master Trainers | B41: Daily | C41: 40 | D41: =10*10*1 -> 100 | E41: 1 | F41: =C41*D41*E41 -> 4000 | G41: =C41*$B$6 -> 42 | H41: =10*10*11 -> 1100 | I41: 1 | J41: =G41*H41*I41 -> 46200 | K41: =G41*$B$6 -> 44.1 | L41: =10*10*11 -> 1100 | M41: 1 | N41: =K41*L41*M41 -> 48510 | O41: =K41*$B$6 -> 46.305 | P41: =10*10*11 -> 1100 | Q41: 1 | R41: =O41*P41*Q41 -> 50935.5 | S41: =O41*$B$6 -> 48.62025 | T41: 0 | U41: 1 | V41: =S41*T41*U41 -> 0 | W41: =F41+J41+N41+V41+R41 -> 149645.5 | X41: =+W41 -> 149645.5
A42: Teacher Coaches | B42: Daily | C42: 35 | D42: 0 | E42: 1 | F42: =C42*D42*E42 -> 0 | G42: =C42*$B$6 -> 36.75 | H42: =35*10*11 -> 3850 | I42: 1 | J42: =G42*H42*I42 -> 141487.5 | K42: =G42*$B$6 -> 38.5875 | L42: =35*10*11 -> 3850 | M42: 1 | N42: =K42*L42*M42 -> 148561.88 | O42: =K42*$B$6 -> 40.516875 | P42: =35*10*11 -> 3850 | Q42: 1 | R42: =O42*P42*Q42 -> 155989.97 | S42: =O42*$B$6 -> 42.542719 | T42: 0 | U42: 1 | V42: =S42*T42*U42 -> 0 | W42: =F42+J42+N42+V42+R42 -> 446039.34 | X42: =+W42 -> 446039.34
A43: Literacy Specialist | B43: Daily | C43: 55 | D43: =5*1 -> 5 | E43: 1 | F43: =C43*D43*E43 -> 275 | G43: =C43*$B$6 -> 57.75 | H43: =5*11 -> 55 | I43: 1 | J43: =G43*H43*I43 -> 3176.25 | K43: =G43*$B$6 -> 60.6375 | L43: =5*11 -> 55 | M43: 1 | N43: =K43*L43*M43 -> 3335.0625 | O43: =K43*$B$6 -> 63.669375 | P43: =5*11 -> 55 | Q43: 1 | R43: =O43*P43*Q43 -> 3501.8156 | S43: =O43*$B$6 -> 66.852844 | T43: 0 | U43: 1 | V43: =S43*T43*U43 -> 0 | W43: =F43+J43+N43+V43+R43 -> 10288.128 | X43: =+W43 -> 10288.128
A44: Math Specialist | B44: Daily | C44: 55 | D44: =5*1 -> 5 | E44: 1 | F44: =C44*D44*E44 -> 275 | G44: =C44*$B$6 -> 57.75 | H44: =5*11 -> 55 | I44: 1 | J44: =G44*H44*I44 -> 3176.25 | K44: =G44*$B$6 -> 60.6375 | L44: =5*11 -> 55 | M44: 1 | N44: =K44*L44*M44 -> 3335.0625 | O44: =K44*$B$6 -> 63.669375 | P44: =5*11 -> 55 | Q44: 1 | R44: =O44*P44*Q44 -> 3501.8156 | S44: =O44*$B$6 -> 66.852844 | T44: 0 | U44: 1 | V44: =S44*T44*U44 -> 0 | W44: =F44+J44+N44+V44+R44 -> 10288.128 | X44: =+W44 -> 10288.128
A45: Nutrition technicians / mobilizers | B45: Unit | C45: 30 | D45: =16*10*1 -> 160 | E45: 1 | F45: =C45*D45*E45 -> 4800 | G45: =C45*$B$6 -> 31.5 | H45: =16*10*11 -> 1760 | I45: 1 | J45: =G45*H45*I45 -> 55440 | K45: =G45*$B$6 -> 33.075 | L45: =16*10*11 -> 1760 | M45: 1 | N45: =K45*L45*M45 -> 58212 | O45: =K45*$B$6 -> 34.72875 | P45: =16*10*11 -> 1760 | Q45: 1 | R45: =O45*P45*Q45 -> 61122.6 | S45: =O45*$B$6 -> 36.465188 | T45: 0 | U45: 1 | V45: =S45*T45*U45 -> 0 | W45: =F45+J45+N45+V45+R45 -> 179574.6 | Z45: =+W45 -> 179574.6
A46: Print materials designer and layout specialist | B46: Month | C46: 150 | D46: 3 | E46: 1 | F46: =C46*D46*E46 -> 450 | G46: =C46*$B$6 -> 157.5 | H46: 12 | I46: 1 | J46: =G46*H46*I46 -> 1890 | K46: =G46*$B$6 -> 165.375 | L46: 12 | M46: 1 | N46: =K46*L46*M46 -> 1984.5 | O46: =K46*$B$6 -> 173.64375 | P46: 12 | Q46: 1 | R46: =O46*P46*Q46 -> 2083.725 | S46: =O46*$B$6 -> 182.32594 | T46: 3 | U46: 1 | V46: =S46*T46*U46 -> 546.97781 | W46: =F46+J46+N46+V46+R46 -> 6955.2028 | X46: =+W46*$X$12 -> 5564.1623 | Y46: =+W46*$Y$12 -> 695.52028 | Z46: =+W46*$Z$12 -> 695.52028
A47: Subtotal: Professional Services/Contractual | F47: =SUM(F41:F46) -> 9800 | J47: =SUM(J41:J46) -> 251370 | N47: =SUM(N41:N46) -> 263938.5 | R47: =SUM(R41:R46) -> 277135.42 | V47: =SUM(V41:V46) -> 546.97781 | W47: =SUM(W41:W46) -> 802790.9 | AA47: =W47*$AA$10 -> 586238 | AB47: =W47*$AB$10 -> 64308.727 | AC47: =W47*$AC$10 -> 152244.17
A48: Equipment | B48: unit | D48: 1 | E48: 1 | F48: =C48*D48*E48 -> 0 | J48: =G48*H48*I48 -> 0 | N48: =K48*L48*M48 -> 0 | R48: =O48*P48*Q48 -> 0 | V48: =S48*T48*U48 -> 0 | W48: =F48+J48+N48+V48+R48 -> 0
A49: Subtotal: Equipment | F49: =+F48 -> 0 | J49: =+J48 -> 0 | N49: =+N48 -> 0 | R49: =+R48 -> 0 | V49: =+V48 -> 0 | W49: =+W48 -> 0 | X49: =+W49*$X$12 -> 0 | Y49: =+W49*$Y$12 -> 0 | Z49: =+W49*$Z$12 -> 0 | AA49: =W49*$AA$10 -> 0 | AB49: =W49*$AB$10 -> 0 | AC49: =W49*$AC$10 -> 0
A50: Office | B50: unit | D50: 1 | E50: 1 | F50: =C50*D50*E50 -> 0 | J50: =G50*H50*I50 -> 0 | N50: =K50*L50*M50 -> 0 | R50: =O50*P50*Q50 -> 0 | V50: =S50*T50*U50 -> 0 | W50: =F50+J50+N50+V50+R50 -> 0
A51: Subtotal: Office | F51: =+F50 -> 0 | J51: =+J50 -> 0 | N51: =+N50 -> 0 | R51: =+R50 -> 0 | V51: =+V50 -> 0 | W51: =+W50 -> 0 | X51: =+W51*$X$12 -> 0 | Y51: =+W51*$Y$12 -> 0 | Z51: =+W51*$Z$12 -> 0 | AA51: =W51*$AA$10 -> 0 | AB51: =W51*$AB$10 -> 0 | AC51: =W51*$AC$10 -> 0
A52: Supplies
A53: Laptop | B53: Unit | C53: 800 | D53: 4 | E53: 1 | F53: =C53*D53*E53 -> 3200 | G53: =C53*$B$7 -> 840 | H53: 0 | I53: 1 | J53: =G53*H53*I53 -> 0 | K53: =G53*$B$7 -> 882 | L53: 0 | M53: 1 | N53: =K53*L53*M53 -> 0 | O53: =K53*$B$7 -> 926.1 | P53: 0 | Q53: 1 | R53: =O53*P53*Q53 -> 0 | S53: =O53*$B$7 -> 972.405 | T53: 0 | U53: 1 | V53: =S53*T53*U53 -> 0 | W53: =F53+J53+N53+V53+R53 -> 3200
A54: Projector | B54: Unit | C54: 350 | D54: 2 | E54: 1 | F54: =C54*D54*E54 -> 700 | G54: =C54*$B$7 -> 367.5 | H54: 0 | I54: 1 | J54: =G54*H54*I54 -> 0 | K54: =G54*$B$7 -> 385.875 | L54: 0 | M54: 1 | N54: =K54*L54*M54 -> 0 | O54: =K54*$B$7 -> 405.16875 | P54: 0 | Q54: 1 | R54: =O54*P54*Q54 -> 0 | S54: =O54*$B$7 -> 425.42719 | T54: 0 | U54: 1 | V54: =S54*T54*U54 -> 0 | W54: =F54+J54+N54+V54+R54 -> 700
A55: Multifunction printer | B55: Unit | C55: 300 | D55: 1 | E55: 1 | F55: =C55*D55*E55 -> 300 | G55: =C55*$B$7 -> 315 | H55: 0 | I55: 1 | J55: =G55*H55*I55 -> 0 | K55: =G55*$B$7 -> 330.75 | L55: 0 | M55: 1 | N55: =K55*L55*M55 -> 0 | O55: =K55*$B$7 -> 347.2875 | P55: 0 | Q55: 1 | R55: =O55*P55*Q55 -> 0 | S55: =O55*$B$7 -> 364.65188 | T55: 0 | U55: 1 | V55: =S55*T55*U55 -> 0 | W55: =F55+J55+N55+V55+R55 -> 300
A56: Tablets | B56: Unit | C56: 250 | D56: 60 | E56: 1 | F56: =C56*D56*E56 -> 15000 | G56: =C56*$B$7 -> 262.5 | H56: 2 | I56: 1 | J56: =G56*H56*I56 -> 525 | K56: =G56*$B$7 -> 275.625 | L56: 2 | M56: 1 | N56: =K56*L56*M56 -> 551.25 | O56: =K56*$B$7 -> 289.40625 | P56: 2 | Q56: 1 | R56: =O56*P56*Q56 -> 578.8125 | S56: =O56*$B$7 -> 303.87656 | T56: 2 | U56: 1 | V56: =S56*T56*U56 -> 607.75313 | W56: =F56+J56+N56+V56+R56 -> 17262.816
A57: Office Supplies | B57: Monthly | C57: 250 | D57: 3 | E57: 1 | F57: =C57*D57*E57 -> 750 | G57: =C57*$B$7 -> 262.5 | H57: 12 | I57: 1 | J57: =G57*H57*I57 -> 3150 | K57: =G57*$B$7 -> 275.625 | L57: 12 | M57: 1 | N57: =K57*L57*M57 -> 3307.5 | O57: =K57*$B$7 -> 289.40625 | P57: 12 | Q57: 1 | R57: =O57*P57*Q57 -> 3472.875 | S57: =O57*$B$7 -> 303.87656 | T57: 3 | U57: 1 | V57: =S57*T57*U57 -> 911.62969 | W57: =F57+J57+N57+V57+R57 -> 11592.005
A58: Subtotal: Supplies | F58: =SUM(F53:F57) -> 19950 | J58: =SUM(J53:J57) -> 3675 | N58: =SUM(N53:N57) -> 3858.75 | R58: =SUM(R53:R57) -> 4051.6875 | V58: =SUM(V53:V57) -> 1519.3828 | W58: =SUM(W53:W57) -> 33054.82 | X58: =+W58*$X$12 -> 26443.856 | Y58: =+W58*$Y$12 -> 3305.482 | Z58: =+W58*$Z$12 -> 3305.482 | AA58: =W58*$AA$10 -> 24138.28 | AB58: =W58*$AB$10 -> 2647.9042 | AC58: =W58*$AC$10 -> 6268.6358
A59: Other Direct Cost
A60: Workshops and training
A61: 3.1.1 Strengthen Teacher Using Targeted Instruction and GANE Guides - Master Trainers Training | B61: Unit
A62: Materials and supplies | B62: Participant | C62: 5 | D62: 10 | E62: 1 | F62: =C62*D62*E62 -> 50 | G62: =C62*$B$7 -> 5.25 | H62: 10 | I62: 1 | J62: =G62*H62*I62 -> 52.5 | K62: =G62*$B$7 -> 5.5125 | L62: 10 | M62: 1 | N62: =K62*L62*M62 -> 55.125 | O62: =K62*$B$7 -> 5.788125 | P62: 10 | Q62: 1 | R62: =O62*P62*Q62 -> 57.88125 | S62: =O62*$B$7 -> 6.0775313 | T62: 0 | U62: 1 | V62: =S62*T62*U62 -> 0 | W62: =F62+J62+N62+V62+R62 -> 215.50625 | X62: =+W62 -> 215.50625
A63: Meals | B63: Participant/day | C63: 10 | D63: 10 | E63: 1 | F63: =C63*D63*E63 -> 100 | G63: =C63*$B$7 -> 10.5 | H63: 10 | I63: 1 | J63: =G63*H63*I63 -> 105 | K63: =G63*$B$7 -> 11.025 | L63: 10 | M63: 1 | N63: =K63*L63*M63 -> 110.25 | O63: =K63*$B$7 -> 11.57625 | P63: 10 | Q63: 1 | R63: =O63*P63*Q63 -> 115.7625 | S63: =O63*$B$7 -> 12.155063 | T63: 0 | U63: 1 | V63: =S63*T63*U63 -> 0 | W63: =F63+J63+N63+V63+R63 -> 431.0125 | X63: =+W63 -> 431.0125
A64: Lodging | B64: Participant/day | C64: 45 | D64: 10 | E64: 1 | F64: =C64*D64*E64 -> 450 | G64: =C64*$B$7 -> 47.25 | H64: 10 | I64: 1 | J64: =G64*H64*I64 -> 472.5 | K64: =G64*$B$7 -> 49.6125 | L64: 10 | M64: 1 | N64: =K64*L64*M64 -> 496.125 | O64: =K64*$B$7 -> 52.093125 | P64: 10 | Q64: 1 | R64: =O64*P64*Q64 -> 520.93125 | S64: =O64*$B$7 -> 54.697781 | T64: 0 | U64: 1 | V64: =S64*T64*U64 -> 0 | W64: =F64+J64+N64+V64+R64 -> 1939.5563 | X64: =+W64 -> 1939.5563
A65: Participant transportation | B65: Trips/participant | C65: 5 | D65: 10 | E65: 1 | F65: =C65*D65*E65 -> 50 | G65: =C65*$B$7 -> 5.25 | H65: 10 | I65: 1 | J65: =G65*H65*I65 -> 52.5 | K65: =G65*$B$7 -> 5.5125 | L65: 10 | M65: 1 | N65: =K65*L65*M65 -> 55.125 | O65: =K65*$B$7 -> 5.788125 | P65: 10 | Q65: 1 | R65: =O65*P65*Q65 -> 57.88125 | S65: =O65*$B$7 -> 6.0775313 | T65: 0 | U65: 1 | V65: =S65*T65*U65 -> 0 | W65: =F65+J65+N65+V65+R65 -> 215.50625 | X65: =+W65 -> 215.50625
A67: 3.1.2 Strengthen Teacher Using Targeted Instruction and GANE Guides - Teacher Coaches Training
A68: Materials and supplies | B68: Participant | C68: 5 | D68: 0 | E68: 1 | F68: =C68*D68*E68 -> 0 | G68: =C68*$B$7 -> 5.25 | H68: 35 | I68: 1 | J68: =G68*H68*I68 -> 183.75 | K68: =G68*$B$7 -> 5.5125 | L68: 35 | M68: 1 | N68: =K68*L68*M68 -> 192.9375 | O68: =K68*$B$7 -> 5.788125 | P68: 35 | Q68: 1 | R68: =O68*P68*Q68 -> 202.58438 | S68: =O68*$B$7 -> 6.0775313 | T68: 0 | U68: 1 | V68: =S68*T68*U68 -> 0 | W68: =F68+J68+N68+V68+R68 -> 579.27188 | X68: =+W68 -> 579.27188
A69: Meals | B69: Participant | C69: 10 | D69: 0 | E69: 1 | F69: =C69*D69*E69 -> 0 | G69: =C69*$B$7 -> 10.5 | H69: 35 | I69: 1 | J69: =G69*H69*I69 -> 367.5 | K69: =G69*$B$7 -> 11.025 | L69: 35 | M69: 1 | N69: =K69*L69*M69 -> 385.875 | O69: =K69*$B$7 -> 11.57625 | P69: 35 | Q69: 1 | R69: =O69*P69*Q69 -> 405.16875 | S69: =O69*$B$7 -> 12.155063 | T69: 0 | U69: 1 | V69: =S69*T69*U69 -> 0 | W69: =F69+J69+N69+V69+R69 -> 1158.5438 | X69: =+W69 -> 1158.5438
A70: Lodging | B70: Participant | C70: 45 | D70: 0 | E70: 1 | F70: =C70*D70*E70 -> 0 | G70: =C70*$B$7 -> 47.25 | H70: 35 | I70: 1 | J70: =G70*H70*I70 -> 1653.75 | K70: =G70*$B$7 -> 49.6125 | L70: 35 | M70: 1 | N70: =K70*L70*M70 -> 1736.4375 | O70: =K70*$B$7 -> 52.093125 | P70: 35 | Q70: 1 | R70: =O70*P70*Q70 -> 1823.2594 | S70: =O70*$B$7 -> 54.697781 | T70: 0 | U70: 1 | V70: =S70*T70*U70 -> 0 | W70: =F70+J70+N70+V70+R70 -> 5213.4469 | X70: =+W70 -> 5213.4469
A71: Participant transportation | B71: Participant | C71: 5 | D71: 0 | E71: 1 | F71: =C71*D71*E71 -> 0 | G71: =C71*$B$7 -> 5.25 | H71: 35 | I71: 1 | J71: =G71*H71*I71 -> 183.75 | K71: =G71*$B$7 -> 5.5125 | L71: 35 | M71: 1 | N71: =K71*L71*M71 -> 192.9375 | O71: =K71*$B$7 -> 5.788125 | P71: 35 | Q71: 1 | R71: =O71*P71*Q71 -> 202.58438 | S71: =O71*$B$7 -> 6.0775313 | T71: 0 | U71: 1 | V71: =S71*T71*U71 -> 0 | W71: =F71+J71+N71+V71+R71 -> 579.27188 | X71: =+W71 -> 579.27188
A73: 3.1.3 Strengthen Teacher Using Targeted Instruction and GANE Guides - Teachers Training
A74: Materials and supplies | B74: Participant | C74: 5 | D74: 1762 | E74: 1 | F74: =C74*D74*E74 -> 8810 | G74: =C74*$B$7 -> 5.25 | H74: 1762 | I74: 1 | J74: =G74*H74*I74 -> 9250.5 | K74: =G74*$B$7 -> 5.5125 | L74: 1762 | M74: 1 | N74: =K74*L74*M74 -> 9713.025 | O74: =K74*$B$7 -> 5.788125 | P74: 1762 | Q74: 1 | R74: =O74*P74*Q74 -> 10198.676 | S74: =O74*$B$7 -> 6.0775313 | T74: 0 | U74: 1 | V74: =S74*T74*U74 -> 0 | W74: =F74+J74+N74+V74+R74 -> 37972.201 | X74: =+W74 -> 37972.201
A75: Meals | B75: Participant | C75: 10 | D75: 1762 | E75: 1 | F75: =C75*D75*E75 -> 17620 | G75: =C75*$B$7 -> 10.5 | H75: 1762 | I75: 1 | J75: =G75*H75*I75 -> 18501 | K75: =G75*$B$7 -> 11.025 | L75: 1762 | M75: 1 | N75: =K75*L75*M75 -> 19426.05 | O75: =K75*$B$7 -> 11.57625 | P75: 1762 | Q75: 1 | R75: =O75*P75*Q75 -> 20397.353 | S75: =O75*$B$7 -> 12.155063 | T75: 0 | U75: 1 | V75: =S75*T75*U75 -> 0 | W75: =F75+J75+N75+V75+R75 -> 75944.403 | X75: =+W75 -> 75944.403
A77: 3.1.4 School Administrators Training
A78: Materials and supplies | B78: Participant | C78: 5 | D78: 337 | E78: 1 | F78: =C78*D78*E78 -> 1685 | G78: =C78*$B$7 -> 5.25 | H78: 337 | I78: 1 | J78: =G78*H78*I78 -> 1769.25 | K78: =G78*$B$7 -> 5.5125 | L78: 337 | M78: 1 | N78: =K78*L78*M78 -> 1857.7125 | O78: =K78*$B$7 -> 5.788125 | P78: 337 | Q78: 1 | R78: =O78*P78*Q78 -> 1950.5981 | S78: =O78*$B$7 -> 6.0775313 | T78: 0 | U78: 1 | V78: =S78*T78*U78 -> 0 | W78: =F78+J78+N78+V78+R78 -> 7262.5606 | X78: =+W78 -> 7262.5606
A79: Meals | B79: Participant | C79: 10 | D79: 337 | E79: 1 | F79: =C79*D79*E79 -> 3370 | G79: =C79*$B$7 -> 10.5 | H79: 337 | I79: 1 | J79: =G79*H79*I79 -> 3538.5 | K79: =G79*$B$7 -> 11.025 | L79: 337 | M79: 1 | N79: =K79*L79*M79 -> 3715.425 | O79: =K79*$B$7 -> 11.57625 | P79: 337 | Q79: 1 | R79: =O79*P79*Q79 -> 3901.1963 | S79: =O79*$B$7 -> 12.155063 | T79: 0 | U79: 1 | V79: =S79*T79*U79 -> 0 | W79: =F79+J79+N79+V79+R79 -> 14525.121 | X79: =+W79 -> 14525.121
A81: 4.4. Expand Pre-Primary Access through Educator Training - Preschool teachers Training
A82: Materials and supplies | B82: Participant | C82: 5 | D82: 0 | E82: 1 | F82: =C82*D82*E82 -> 0 | G82: =C82*$B$7 -> 5.25 | H82: 102 | I82: 1 | J82: =G82*H82*I82 -> 535.5 | K82: =G82*$B$7 -> 5.5125 | L82: =+H82 -> 102 | M82: 1 | N82: =K82*L82*M82 -> 562.275 | O82: =K82*$B$7 -> 5.788125 | P82: =+H82 -> 102 | Q82: 1 | R82: =O82*P82*Q82 -> 590.38875 | S82: =O82*$B$7 -> 6.0775313 | T82: 0 | U82: 1 | V82: =S82*T82*U82 -> 0 | W82: =F82+J82+N82+V82+R82 -> 1688.1638 | Y82: =+W82 -> 1688.1638
A83: Meals | B83: Participant | C83: 10 | D83: 0 | E83: 1 | F83: =C83*D83*E83 -> 0 | G83: =C83*$B$7 -> 10.5 | H83: 102 | I83: 1 | J83: =G83*H83*I83 -> 1071 | K83: =G83*$B$7 -> 11.025 | L83: =+H83 -> 102 | M83: 1 | N83: =K83*L83*M83 -> 1124.55 | O83: =K83*$B$7 -> 11.57625 | P83: =+H83 -> 102 | Q83: 1 | R83: =O83*P83*Q83 -> 1180.7775 | S83: =O83*$B$7 -> 12.155063 | T83: 0 | U83: 1 | V83: =S83*T83*U83 -> 0 | W83: =F83+J83+N83+V83+R83 -> 3376.3275 | Y83: =+W83 -> 3376.3275
A84: Play-based kits | B84: Unit | C84: 40 | D84: 0 | E84: 1 | F84: =C84*D84*E84 -> 0 | G84: =C84*$B$7 -> 42 | H84: 102 | I84: 1 | J84: =G84*H84*I84 -> 4284 | K84: =G84*$B$7 -> 44.1 | L84: =+H84 -> 102 | M84: 1 | N84: =K84*L84*M84 -> 4498.2 | O84: =K84*$B$7 -> 46.305 | P84: =+H84 -> 102 | Q84: 1 | R84: =O84*P84*Q84 -> 4723.11 | S84: =O84*$B$7 -> 48.62025 | T84: 0 | U84: 1 | V84: =S84*T84*U84 -> 0 | W84: =F84+J84+N84+V84+R84 -> 13505.31 | Y84: =+W84 -> 13505.31
A86: 6.2.1 Deliver Nutrition Education for Early Learners and Caregivers - Mobilizers
A87: Materials and supplies | B87: Participant | C87: 5 | D87: 8 | E87: 1 | F87: =C87*D87*E87 -> 40 | G87: =C87*$B$7 -> 5.25 | H87: 8 | I87: 1 | J87: =G87*H87*I87 -> 42 | K87: =G87*$B$7 -> 5.5125 | L87: 8 | M87: 1 | N87: =K87*L87*M87 -> 44.1 | O87: =K87*$B$7 -> 5.788125 | P87: 8 | Q87: 1 | R87: =O87*P87*Q87 -> 46.305 | S87: =O87*$B$7 -> 6.0775313 | T87: 0 | U87: 1 | V87: =S87*T87*U87 -> 0 | W87: =F87+J87+N87+V87+R87 -> 172.405 | Z87: =+W87 -> 172.405
A88: Meals | B88: Participant | C88: 10 | D88: 8 | E88: 1 | F88: =C88*D88*E88 -> 80 | G88: =C88*$B$7 -> 10.5 | H88: 8 | I88: 1 | J88: =G88*H88*I88 -> 84 | K88: =G88*$B$7 -> 11.025 | L88: 8 | M88: 1 | N88: =K88*L88*M88 -> 88.2 | O88: =K88*$B$7 -> 11.57625 | P88: 8 | Q88: 1 | R88: =O88*P88*Q88 -> 92.61 | S88: =O88*$B$7 -> 12.155063 | T88: 0 | U88: 1 | V88: =S88*T88*U88 -> 0 | W88: =F88+J88+N88+V88+R88 -> 344.81 | Z88: =+W88 -> 344.81
A89: Lodging | B89: Participant | C89: 45 | D89: 8 | E89: 1 | F89: =C89*D89*E89 -> 360 | G89: =C89*$B$7 -> 47.25 | H89: 8 | I89: 1 | J89: =G89*H89*I89 -> 378 | K89: =G89*$B$7 -> 49.6125 | L89: 8 | M89: 1 | N89: =K89*L89*M89 -> 396.9 | O89: =K89*$B$7 -> 52.093125 | P89: 8 | Q89: 1 | R89: =O89*P89*Q89 -> 416.745 | S89: =O89*$B$7 -> 54.697781 | T89: 0 | U89: 1 | V89: =S89*T89*U89 -> 0 | W89: =F89+J89+N89+V89+R89 -> 1551.645 | Z89: =+W89 -> 1551.645
A90: Participant transportation | B90: Participant | C90: 5 | D90: 8 | E90: 1 | F90: =C90*D90*E90 -> 40 | G90: =C90*$B$7 -> 5.25 | H90: 8 | I90: 1 | J90: =G90*H90*I90 -> 42 | K90: =G90*$B$7 -> 5.5125 | L90: 8 | M90: 1 | N90: =K90*L90*M90 -> 44.1 | O90: =K90*$B$7 -> 5.788125 | P90: 8 | Q90: 1 | R90: =O90*P90*Q90 -> 46.305 | S90: =O90*$B$7 -> 6.0775313 | T90: 0 | U90: 1 | V90: =S90*T90*U90 -> 0 | W90: =F90+J90+N90+V90+R90 -> 172.405 | Z90: =+W90 -> 172.405
A92: 6.2.2 Deliver Nutrition Education for Early Learners and Caregivers - Teachers, Parents and Caregivers
A93: Materials and supplies | B93: Participant | C93: 5 | D93: 150 | E93: 1 | F93: =C93*D93*E93 -> 750 | G93: =C93*$B$7 -> 5.25 | H93: 150 | I93: 1 | J93: =G93*H93*I93 -> 787.5 | K93: =G93*$B$7 -> 5.5125 | L93: =+H93 -> 150 | M93: 1 | N93: =K93*L93*M93 -> 826.875 | O93: =K93*$B$7 -> 5.788125 | P93: =+H93 -> 150 | Q93: 1 | R93: =O93*P93*Q93 -> 868.21875 | S93: =O93*$B$7 -> 6.0775313 | T93: 0 | U93: 1 | V93: =S93*T93*U93 -> 0 | W93: =F93+J93+N93+V93+R93 -> 3232.5938 | Z93: =+W93 -> 3232.5938
A94: Meals | B94: Participant | C94: 10 | D94: 150 | E94: 1 | F94: =C94*D94*E94 -> 1500 | G94: =C94*$B$7 -> 10.5 | H94: 150 | I94: 1 | J94: =G94*H94*I94 -> 1575 | K94: =G94*$B$7 -> 11.025 | L94: =+H94 -> 150 | M94: 1 | N94: =K94*L94*M94 -> 1653.75 | O94: =K94*$B$7 -> 11.57625 | P94: =+H94 -> 150 | Q94: 1 | R94: =O94*P94*Q94 -> 1736.4375 | S94: =O94*$B$7 -> 12.155063 | T94: 0 | U94: 1 | V94: =S94*T94*U94 -> 0 | W94: =F94+J94+N94+V94+R94 -> 6465.1875 | Z94: =+W94 -> 6465.1875
A96: Microsoft 365 license | B96: Monthly | C96: 25 | D96: 3 | E96: 1 | F96: =C96*D96*E96 -> 75 | G96: =C96*$B$6 -> 26.25 | H96: 6 | I96: 1 | J96: =G96*H96*I96 -> 157.5 | K96: =G96*$B$6 -> 27.5625 | L96: 6 | M96: 1 | N96: =K96*L96*M96 -> 165.375 | O96: =K96*$B$6 -> 28.940625 | P96: 6 | Q96: 1 | R96: =O96*P96*Q96 -> 173.64375 | S96: =O96*$B$6 -> 30.387656 | T96: 3 | U96: 1 | V96: =S96*T96*U96 -> 91.162969 | W96: =F96+J96+N96+V96+R96 -> 662.68172 | X96: =+W96*$X$12 -> 530.14538 | Y96: =+W96*$Y$12 -> 66.268172 | Z96: =+W96*$Z$12 -> 66.268172
A97: Kobotoolbox-Power Bi license | B97: Monthly | C97: 50 | D97: 3 | E97: 1 | F97: =C97*D97*E97 -> 150 | G97: =C97*$B$6 -> 52.5 | H97: 1 | I97: 1 | J97: =G97*H97*I97 -> 52.5 | K97: =G97*$B$6 -> 55.125 | L97: 1 | M97: 1 | N97: =K97*L97*M97 -> 55.125 | O97: =K97*$B$6 -> 57.88125 | P97: 1 | Q97: 1 | R97: =O97*P97*Q97 -> 57.88125 | S97: =O97*$B$6 -> 60.775313 | T97: 3 | U97: 1 | V97: =S97*T97*U97 -> 182.32594 | W97: =F97+J97+N97+V97+R97 -> 497.83219 | X97: =+W97*$X$12 -> 398.26575 | Y97: =+W97*$Y$12 -> 49.783219 | Z97: =+W97*$Z$12 -> 49.783219
A98: Antivirus-firewall license | B98: Monthly | C98: 15 | D98: 3 | E98: 1 | F98: =C98*D98*E98 -> 45 | G98: =C98*$B$6 -> 15.75 | H98: 6 | I98: 1 | J98: =G98*H98*I98 -> 94.5 | K98: =G98*$B$6 -> 16.5375 | L98: 6 | M98: 1 | N98: =K98*L98*M98 -> 99.225 | O98: =K98*$B$6 -> 17.364375 | P98: 6 | Q98: 1 | R98: =O98*P98*Q98 -> 104.18625 | S98: =O98*$B$6 -> 18.232594 | T98: 3 | U98: 1 | V98: =S98*T98*U98 -> 54.697781 | W98: =F98+J98+N98+V98+R98 -> 397.60903 | X98: =+W98*$X$12 -> 318.08723 | Y98: =+W98*$Y$12 -> 39.760903 | Z98: =+W98*$Z$12 -> 39.760903
A99: Office communications | B99: Monthly | C99: 50 | D99: 3 | E99: 1 | F99: =C99*D99*E99 -> 150 | G99: =C99*$B$7 -> 52.5 | H99: 12 | I99: 1 | J99: =G99*H99*I99 -> 630 | K99: =G99*$B$7 -> 55.125 | L99: 12 | M99: 1 | N99: =K99*L99*M99 -> 661.5 | O99: =K99*$B$7 -> 57.88125 | P99: 12 | Q99: 1 | R99: =O99*P99*Q99 -> 694.575 | S99: =O99*$B$7 -> 60.775313 | T99: 3 | U99: 1 | V99: =S99*T99*U99 -> 182.32594 | W99: =F99+J99+N99+V99+R99 -> 2318.4009 | X99: =+W99*$X$12 -> 1854.7208 | Y99: =+W99*$Y$12 -> 231.84009 | Z99: =+W99*$Z$12 -> 231.84009
A100: Cellular communications services for staff | B100: Monthly | C100: 6 | D100: =5*3 -> 15 | E100: 1 | F100: =C100*D100*E100 -> 90 | G100: =C100*$B$7 -> 6.3 | H100: =6*12 -> 72 | I100: 1 | J100: =G100*H100*I100 -> 453.6 | K100: =G100*$B$7 -> 6.615 | L100: =6*12 -> 72 | M100: 1 | N100: =K100*L100*M100 -> 476.28 | O100: =K100*$B$7 -> 6.94575 | P100: =6*12 -> 72 | Q100: 1 | R100: =O100*P100*Q100 -> 500.094 | S100: =O100*$B$7 -> 7.2930375 | T100: =5*3 -> 15 | U100: 1 | V100: =S100*T100*U100 -> 109.39556 | W100: =F100+J100+N100+V100+R100 -> 1629.3696 | X100: =+W100*$X$12 -> 1303.4957 | Y100: =+W100*$Y$12 -> 162.93696 | Z100: =+W100*$Z$12 -> 162.93696
A101: Cellular communications services for field team | B101: Monthly | C101: 6 | D101: =+((10+1+1+8)*2) -> 40 | E101: 1 | F101: =C101*D101*E101 -> 240 | G101: =C101*$B$7 -> 6.3 | H101: =+((10+35+1+1+8)*12) -> 660 | I101: 1 | J101: =G101*H101*I101 -> 4158 | K101: =G101*$B$7 -> 6.615 | L101: =+((10+35+1+1+8)*12) -> 660 | M101: 1 | N101: =K101*L101*M101 -> 4365.9 | O101: =K101*$B$7 -> 6.94575 | P101: =+((10+35+1+1+8)*12) -> 660 | Q101: 1 | R101: =O101*P101*Q101 -> 4584.195 | S101: =O101*$B$7 -> 7.2930375 | T101: 3 | U101: 1 | V101: =S101*T101*U101 -> 21.879113 | W101: =F101+J101+N101+V101+R101 -> 13369.974 | X101: =+W101*$X$12 -> 10695.979 | Y101: =+W101*$Y$12 -> 1336.9974 | Z101: =+W101*$Z$12 -> 1336.9974
A102: Local currier | B102: Monthly | C102: 20 | D102: 3 | E102: 1 | F102: =C102*D102*E102 -> 60 | G102: =C102*$B$7 -> 21 | H102: 12 | I102: 1 | J102: =G102*H102*I102 -> 252 | K102: =G102*$B$7 -> 22.05 | L102: 12 | M102: 1 | N102: =K102*L102*M102 -> 264.6 | O102: =K102*$B$7 -> 23.1525 | P102: 12 | Q102: 1 | R102: =O102*P102*Q102 -> 277.83 | S102: =O102*$B$7 -> 24.310125 | T102: 3 | U102: 1 | V102: =S102*T102*U102 -> 72.930375 | W102: =F102+J102+N102+V102+R102 -> 927.36038 | X102: =+W102*$X$12 -> 741.8883 | Y102: =+W102*$Y$12 -> 92.736038 | Z102: =+W102*$Z$12 -> 92.736038
A103: Legal fees | B103: Monthly | C103: 50 | D103: 3 | E103: 1 | F103: =C103*D103*E103 -> 150 | G103: =C103*$B$7 -> 52.5 | H103: 12 | I103: 1 | J103: =G103*H103*I103 -> 630 | K103: =G103*$B$7 -> 55.125 | L103: 12 | M103: 1 | N103: =K103*L103*M103 -> 661.5 | O103: =K103*$B$7 -> 57.88125 | P103: 12 | Q103: 1 | R103: =O103*P103*Q103 -> 694.575 | S103: =O103*$B$7 -> 60.775313 | T103: 3 | U103: 1 | V103: =S103*T103*U103 -> 182.32594 | W103: =F103+J103+N103+V103+R103 -> 2318.4009 | X103: =+W103*$X$12 -> 1854.7208 | Y103: =+W103*$Y$12 -> 231.84009 | Z103: =+W103*$Z$12 -> 231.84009
A104: Banking fees | B104: Monthly | C104: 25 | D104: 3 | E104: 1 | F104: =C104*D104*E104 -> 75 | G104: =C104*$B$7 -> 26.25 | H104: 12 | I104: 1 | J104: =G104*H104*I104 -> 315 | K104: =G104*$B$7 -> 27.5625 | L104: 12 | M104: 1 | N104: =K104*L104*M104 -> 330.75 | O104: =K104*$B$7 -> 28.940625 | P104: 12 | Q104: 1 | R104: =O104*P104*Q104 -> 347.2875 | S104: =O104*$B$7 -> 30.387656 | T104: 3 | U104: 1 | V104: =S104*T104*U104 -> 91.162969 | W104: =F104+J104+N104+V104+R104 -> 1159.2005 | X104: =+W104*$X$12 -> 927.36038 | Y104: =+W104*$Y$12 -> 115.92005 | Z104: =+W104*$Z$12 -> 115.92005
A105: Subtotal: Other Direct Cost | F105: =SUM(F60:F104) -> 35940 | J105: =SUM(J60:J104) -> 51672.6 | N105: =SUM(N60:N104) -> 54256.23 | R105: =SUM(R60:R104) -> 56969.041 | V105: =SUM(V60:V104) -> 988.20658 | W105: =SUM(W60:W104) -> 199826.08 | AA105: =W105*$AA$10 -> 145922.98 | AB105: =W105*$AB$10 -> 16007.357 | AC105: =W105*$AC$10 -> 37895.741
A107: Total Direct Cost | F107: =F21+F25+F39+F49+F51+F58+F47+F105 -> 114224.75 | J107: =J21+J25+J39+J49+J51+J58+J47+J105 -> 662025 | N107: =N21+N25+N39+N49+N51+N58+N47+N105 -> 695126.25 | R107: =R21+R25+R39+R49+R51+R58+R47+R105 -> 729882.56 | V107: =V21+V25+V39+V49+V51+V58+V47+V105 -> 57316.589 | W107: =W21+W25+W39+W49+W51+W58+W47+W105 -> 2258575.2 | X107: =SUM(X14:X106) -> 1566519.5 | Y107: =SUM(Y14:Y106) -> 205910.97 | Z107: =SUM(Z14:Z106) -> 486144.64
A109: Indirect Costs
A110: ICR on Activities | B110: % | C110: =+F107-F49-F51 -> 114224.75 | D110: 1 | E110: 0.15 | F110: =C110*D110*E110 -> 17133.712 | G110: =+J107-J49-J51 -> 662025 | H110: 1 | I110: =+E110 -> 0.15 | J110: =G110*H110*I110 -> 99303.75 | K110: =+N107-N49-N51 -> 695126.25 | L110: 1 | M110: =+E110 -> 0.15 | N110: =K110*L110*M110 -> 104268.94 | O110: =+R107-R49-R51 -> 729882.56 | P110: 1 | Q110: =+E110 -> 0.15 | R110: =O110*P110*Q110 -> 109482.38 | S110: =+V107-V49-V51 -> 57316.589 | T110: 1 | U110: =+E110 -> 0.15 | V110: =S110*T110*U110 -> 8597.4884 | W110: =F110+J110+N110+V110+R110 -> 338786.27 | X110: =+X107*10% -> 156651.95 | Y110: =+Y107*10% -> 20591.097 | Z110: =+Z107*10% -> 48614.464 | AA110: =W110*$AA$10 -> 247398.65 | AB110: =W110*$AB$10 -> 27138.965 | AC110: =W110*$AC$10 -> 64248.656
A112: Subtotal Indirect Cost | F112: =SUM(F110:F111) -> 17133.712 | J112: =SUM(J110:J111) -> 99303.75 | N112: =SUM(N110:N111) -> 104268.94 | R112: =SUM(R110:R111) -> 109482.38 | V112: =SUM(V110:V111) -> 8597.4884 | W112: =SUM(W110:W111) -> 338786.27
A114: Total Estimated Cost (Direct Cost + Indirect Cost) | F114: =F107+F112 -> 131358.46 | J114: =J107+J112 -> 761328.75 | N114: =N107+N112 -> 799395.19 | R114: =R107+R112 -> 839364.95 | V114: =V107+V112 -> 65914.078 | W114: =W107+W112 -> 2597361.4 | X114: =+X107+X110 -> 1723171.5 | Y114: =+Y107+Y110 -> 226502.07 | Z114: =+Z107+Z110 -> 534759.11
A115: Total Cost Share (for reference) | F115: =C115*D115*E115 -> 0 | J115: =G115*H115*I115 -> 0 | N115: =K115*L115*M115 -> 0 | R115: =O115*P115*Q115 -> 0 | V115: =S115*T115*U115 -> 0 | W115: =F115+J115+N115+V115+R115 -> 0
...

Sheet Personnel & LOE Summary
B1: Partners of the Americas – FY 2025 McGovern-Dole Honduras
B2: NOFO: USDA-FAS-10.608-0700-25-(522)
B3: Duration: 6 Years
B4: Country: Honduras
B5: Level of Effort (LOE) Breakdown by Activity
C7: Months in Year 1 | D7: Year 1 LOE | E7: Total Salary Amount Year 1 | F7: Months in Year 2 | G7: Year 2 LOE | H7: Total Salary Amount Year 2 | I7: Months in Year 3 | J7: Year 3 LOE | K7: Total Salary Amount Year 3 | L7: Months in Year 4 | M7: Year 4 LOE | N7: Total Salary Amount Year 4 | O7: Months in Year 5 | P7: Year 5 LOE | Q7: Total Salary Amount Year 5 | R7: Months in Year 6 | S7: Year 6 LOE | T7: Total Salary Amount Year 6 | U7: Total Amount LOP | V7: Total Months Worked | W7: Average Salary
C8: LOE | D8: LOE | E8: LOE | F8: LOE | G8: LOE | H8: LOE | I8: LOE | J8: LOE | K8: LOE | L8: LOE | M8: LOE | N8: LOE | O8: LOE | P8: LOE | Q8: LOE | R8: LOE | S8: LOE | T8: LOE | U8: LOE | W8: LOE
B9: Personnel (Administration)
B10: Honduran National Staff
B11: ='Program Budget'!D12 -> Key Personnel: Chief of Party - Roger Sanchez O’Neill | C11: ='Program Budget'!G12 -> 11 | D11: ='Program Budget'!E12+'Program Budget'!E153+'Program Budget'!E215+'Program Budget'!E274+'Program Budget'!E343+'Program Budget'!E410+'Program Budget'!E482+'Program Budget'!E557+'Program Budget'!E612+'Program Budget'!E686+'Program Budget'!E760+'Program Budget'!E832+'Program Budget'!E891 -> 1 | E11: ='Program Budget'!I12+'Program Budget'!I153+'Program Budget'!I215+'Program Budget'!I274+'Program Budget'!I343+'Program Budget'!I410+'Program Budget'!I482+'Program Budget'!I557+'Program Budget'!I612+'Program Budget'!I686+'Program Budget'!I760+'Program Budget'!I832+'Program Budget'!I891 -> 105416.67 | F11: ='Program Budget'!K12 -> 12 | G11: ='Program Budget'!J12+'Program Budget'!J153+'Program Budget'!J215+'Program Budget'!J274+'Program Budget'!J343+'Program Budget'!J410+'Program Budget'!J482+'Program Budget'!J557+'Program Budget'!J612+'Program Budget'!J686+'Program Budget'!J760+'Program Budget'!J832+'Program Budget'!J891 -> 1 | H11: ='Program Budget'!L12+'Program Budget'!L153+'Program Budget'!L215+'Program Budget'!L274+'Program Budget'!L343+'Program Budget'!L410+'Program Budget'!L482+'Program Budget'!L557+'Program Budget'!L612+'Program Budget'!L686+'Program Budget'!L760+'Program Budget'!L832+'Program Budget'!L891 -> 120750 | I11: ='Program Budget'!N12 -> 12 | J11: ='Program Budget'!M12+'Program Budget'!M153+'Program Budget'!M215+'Program Budget'!M274+'Program Budget'!M343+'Program Budget'!M410+'Program Budget'!M482+'Program Budget'!M557+'Program Budget'!M612+'Program Budget'!M686+'Program Budget'!M760+'Program Budget'!M832+'Program Budget'!M891 -> 1 | K11: ='Program Budget'!O12+'Program Budget'!O153+'Program Budget'!O215+'Program Budget'!O274+'Program Budget'!O343+'Program Budget'!O410+'Program Budget'!O482+'Program Budget'!O557+'Program Budget'!O612+'Program Budget'!O686+'Program Budget'!O760+'Program Budget'!O832+'Program Budget'!O891 -> 126787.5 | L11: ='Program Budget'!Q12 -> 12 | M11: ='Program Budget'!P12+'Program Budget'!P153+'Program Budget'!P215+'Program Budget'!P274+'Program Budget'!P343+'Program Budget'!P410+'Program Budget'!P482+'Program Budget'!P557+'Program Budget'!P612+'Program Budget'!P686+'Program Budget'!P760+'Program Budget'!P832+'Program Budget'!P891 -> 1 | N11: ='Program Budget'!R12+'Program Budget'!R153+'Program Budget'!R215+'Program Budget'!R274+'Program Budget'!R343+'Program Budget'!R410+'Program Budget'!R482+'Program Budget'!R557+'Program Budget'!R612+'Program Budget'!R686+'Program Budget'!R760+'Program Budget'!R832+'Program Budget'!R891 -> 133126.88 | O11: ='Program Budget'!T12 -> 12 | P11: ='Program Budget'!S12+'Program Budget'!S153+'Program Budget'!S215+'Program Budget'!S274+'Program Budget'!S343+'Program Budget'!S410+'Program Budget'!S482+'Program Budget'!S557+'Program Budget'!S612+'Program Budget'!S686+'Program Budget'!S760+'Program Budget'!S832+'Program Budget'!S891 -> 1 | Q11: ='Program Budget'!U12+'Program Budget'!U153+'Program Budget'!U215+'Program Budget'!U274+'Program Budget'!U343+'Program Budget'!U410+'Program Budget'!U482+'Program Budget'!U557+'Program Budget'!U612+'Program Budget'!U686+'Program Budget'!U760+'Program Budget'!U832+'Program Budget'!U891 -> 139783.22 | R11: ='Program Budget'!W12 -> 12 | S11: ='Program Budget'!V12+'Program Budget'!V153+'Program Budget'!V215+'Program Budget'!V274+'Program Budget'!V343+'Program Budget'!V410+'Program Budget'!V482+'Program Budget'!V557+'Program Budget'!V612+'Program Budget'!V686+'Program Budget'!V760+'Program Budget'!V832+'Program Budget'!V891 -> 1 | T11: ='Program Budget'!X12+'Program Budget'!X153+'Program Budget'!X215+'Program Budget'!X274+'Program Budget'!X343+'Program Budget'!X410+'Program Budget'!X482+'Program Budget'!X557+'Program Budget'!X612+'Program Budget'!X686+'Program Budget'!X760+'Program Budget'!X832+'Program Budget'!X891 -> 146772.38 | U11: =E11+H11+K11+N11+Q11+T11 -> 772636.64 | V11: =C11+F11+I11+L11+O11+R11 -> 71 | W11: =U11/V11 -> 10882.206
B12: ='Program Budget'!D13 -> Key Personnel: Deputy Chief of Party - David Medina Mayo | C12: ='Program Budget'!G13 -> 11 | D12: ='Program Budget'!E13+'Program Budget'!E154+'Program Budget'!E216+'Program Budget'!E275+'Program Budget'!E344+'Program Budget'!E411+'Program Budget'!E483+'Program Budget'!E558+'Program Budget'!E613+'Program Budget'!E687+'Program Budget'!E761+'Program Budget'!E833+'Program Budget'!E892 -> 1 | E12: ='Program Budget'!I13+'Program Budget'!I154+'Program Budget'!I216+'Program Budget'!I275+'Program Budget'!I344+'Program Budget'!I411+'Program Budget'!I483+'Program Budget'!I558+'Program Budget'!I613+'Program Budget'!I687+'Program Budget'!I761+'Program Budget'!I833+'Program Budget'!I892 -> 71500 | F12: ='Program Budget'!K13 -> 12 | G12: ='Program Budget'!J13+'Program Budget'!J154+'Program Budget'!J216+'Program Budget'!J275+'Program Budget'!J344+'Program Budget'!J411+'Program Budget'!J483+'Program Budget'!J558+'Program Budget'!J613+'Program Budget'!J687+'Program Budget'!J761+'Program Budget'!J833+'Program Budget'!J892 -> 1 | H12: ='Program Budget'!L13+'Program Budget'!L154+'Program Budget'!L216+'Program Budget'!L275+'Program Budget'!L344+'Program Budget'!L411+'Program Budget'!L483+'Program Budget'!L558+'Program Budget'!L613+'Program Budget'!L687+'Program Budget'!L761+'Program Budget'!L833+'Program Budget'!L892 -> 81900 | I12: ='Program Budget'!N13 -> 12 | J12: ='Program Budget'!M13+'Program Budget'!M154+'Program Budget'!M216+'Program Budget'!M275+'Program Budget'!M344+'Program Budget'!M411+'Program Budget'!M483+'Program Budget'!M558+'Program Budget'!M613+'Program Budget'!M687+'Program Budget'!M761+'Program Budget'!M833+'Program Budget'!M892 -> 1 | K12: ='Program Budget'!O13+'Program Budget'!O154+'Program Budget'!O216+'Program Budget'!O275+'Program Budget'!O344+'Program Budget'!O411+'Program Budget'!O483+'Program Budget'!O558+'Program Budget'!O613+'Program Budget'!O687+'Program Budget'!O761+'Program Budget'!O833+'Program Budget'!O892 -> 85995 | L12: ='Program Budget'!Q13 -> 12 | M12: ='Program Budget'!P13+'Program Budget'!P154+'Program Budget'!P216+'Program Budget'!P275+'Program Budget'!P344+'Program Budget'!P411+'Program Budget'!P483+'Program Budget'!P558+'Program Budget'!P613+'Program Budget'!P687+'Program Budget'!P761+'Program Budget'!P833+'Program Budget'!P892 -> 1 | N12: ='Program Budget'!R13+'Program Budget'!R154+'Program Budget'!R216+'Program Budget'!R275+'Program Budget'!R344+'Program Budget'!R411+'Program Budget'!R483+'Program Budget'!R558+'Program Budget'!R613+'Program Budget'!R687+'Program Budget'!R761+'Program Budget'!R833+'Program Budget'!R892 -> 90294.75 | O12: ='Program Budget'!T13 -> 12 | P12: ='Program Budget'!S13+'Program Budget'!S154+'Program Budget'!S216+'Program Budget'!S275+'Program Budget'!S344+'Program Budget'!S411+'Program Budget'!S483+'Program Budget'!S558+'Program Budget'!S613+'Program Budget'!S687+'Program Budget'!S761+'Program Budget'!S833+'Program Budget'!S892 -> 1 | Q12: ='Program Budget'!U13+'Program Budget'!U154+'Program Budget'!U216+'Program Budget'!U275+'Program Budget'!U344+'Program Budget'!U411+'Program Budget'!U483+'Program Budget'!U558+'Program Budget'!U613+'Program Budget'!U687+'Program Budget'!U761+'Program Budget'!U833+'Program Budget'!U892 -> 94809.488 | R12: ='Program Budget'!W13 -> 12 | S12: ='Program Budget'!V13+'Program Budget'!V154+'Program Budget'!V216+'Program Budget'!V275+'Program Budget'!V344+'Program Budget'!V411+'Program Budget'!V483+'Program Budget'!V558+'Program Budget'!V613+'Program Budget'!V687+'Program Budget'!V761+'Program Budget'!V833+'Program Budget'!V892 -> 1 | T12: ='Program Budget'!X13+'Program Budget'!X154+'Program Budget'!X216+'Program Budget'!X275+'Program Budget'!X344+'Program Budget'!X411+'Program Budget'!X483+'Program Budget'!X558+'Program Budget'!X613+'Program Budget'!X687+'Program Budget'!X761+'Program Budget'!X833+'Program Budget'!X892 -> 99549.962 | U12: =E12+H12+K12+N12+Q12+T12 -> 524049.2 | V12: =C12+F12+I12+L12+O12+R12 -> 71 | W12: =U12/V12 -> 7380.9746
B13: ='Program Budget'!D14 -> Policy & Sustainability Specialist | C13: ='Program Budget'!G14 -> 0 | D13: ='Program Budget'!E14+'Program Budget'!E155+'Program Budget'!E217+'Program Budget'!E276+'Program Budget'!E345+'Program Budget'!E412+'Program Budget'!E484+'Program Budget'!E559+'Program Budget'!E614+'Program Budget'!E688+'Program Budget'!E762+'Program Budget'!E834+'Program Budget'!E893 -> 1 | E13: ='Program Budget'!I14+'Program Budget'!I155+'Program Budget'!I217+'Program Budget'!I276+'Program Budget'!I345+'Program Budget'!I412+'Program Budget'!I484+'Program Budget'!I559+'Program Budget'!I614+'Program Budget'!I688+'Program Budget'!I762+'Program Budget'!I834+'Program Budget'!I893 -> 0 | F13: ='Program Budget'!K14 -> 0 | G13: ='Program Budget'!J14+'Program Budget'!J155+'Program Budget'!J217+'Program Budget'!J276+'Program Budget'!J345+'Program Budget'!J412+'Program Budget'!J484+'Program Budget'!J559+'Program Budget'!J614+'Program Budget'!J688+'Program Budget'!J762+'Program Budget'!J834+'Program Budget'!J893 -> 1 | H13: ='Program Budget'!L14+'Program Budget'!L155+'Program Budget'!L217+'Program Budget'!L276+'Program Budget'!L345+'Program Budget'!L412+'Program Budget'!L484+'Program Budget'!L559+'Program Budget'!L614+'Program Budget'!L688+'Program Budget'!L762+'Program Budget'!L834+'Program Budget'!L893 -> 0 | I13: ='Program Budget'!N14 -> 7 | J13: ='Program Budget'!M14+'Program Budget'!M155+'Program Budget'!M217+'Program Budget'!M276+'Program Budget'!M345+'Program Budget'!M412+'Program Budget'!M484+'Program Budget'!M559+'Program Budget'!M614+'Program Budget'!M688+'Program Budget'!M762+'Program Budget'!M834+'Program Budget'!M893 -> 1 | K13: ='Program Budget'!O14+'Program Budget'!O155+'Program Budget'!O217+'Program Budget'!O276+'Program Budget'!O345+'Program Budget'!O412+'Program Budget'!O484+'Program Budget'!O559+'Program Budget'!O614+'Program Budget'!O688+'Program Budget'!O762+'Program Budget'!O834+'Program Budget'!O893 -> 11576.25 | L13: ='Program Budget'!Q14 -> 12 | M13: ='Program Budget'!P14+'Program Budget'!P155+'Program Budget'!P217+'Program Budget'!P276+'Program Budget'!P345+'Program Budget'!P412+'Program Budget'!P484+'Program Budget'!P559+'Program Budget'!P614+'Program Budget'!P688+'Program Budget'!P762+'Program Budget'!P834+'Program Budget'!P893 -> 1 | N13: ='Program Budget'!R14+'Program Budget'!R155+'Program Budget'!R217+'Program Budget'!R276+'Program Budget'!R345+'Program Budget'!R412+'Program Budget'!R484+'Program Budget'!R559+'Program Budget'!R614+'Program Budget'!R688+'Program Budget'!R762+'Program Budget'!R834+'Program Budget'!R893 -> 20837.25 | O13: ='Program Budget'!T14 -> 12 | P13: ='Program Budget'!S14+'Program Budget'!S155+'Program Budget'!S217+'Program Budget'!S276+'Program Budget'!S345+'Program Budget'!S412+'Program Budget'!S484+'Program Budget'!S559+'Program Budget'!S614+'Program Budget'!S688+'Program Budget'!S762+'Program Budget'!S834+'Program Budget'!S893 -> 1 | Q13: ='Program Budget'!U14+'Program Budget'!U155+'Program Budget'!U217+'Program Budget'!U276+'Program Budget'!U345+'Program Budget'!U412+'Program Budget'!U484+'Program Budget'!U559+'Program Budget'!U614+'Program Budget'!U688+'Program Budget'!U762+'Program Budget'!U834+'Program Budget'!U893 -> 21879.113 | R13: ='Program Budget'!W14 -> 6 | S13: ='Program Budget'!V14+'Program Budget'!V155+'Program Budget'!V217+'Program Budget'!V276+'Program Budget'!V345+'Program Budget'!V412+'Program Budget'!V484+'Program Budget'!V559+'Program Budget'!V614+'Program Budget'!V688+'Program Budget'!V762+'Program Budget'!V834+'Program Budget'!V893 -> 1 | T13: ='Program Budget'!X14+'Program Budget'!X155+'Program Budget'!X217+'Program Budget'!X276+'Program Budget'!X345+'Program Budget'!X412+'Program Budget'!X484+'Program Budget'!X559+'Program Budget'!X614+'Program Budget'!X688+'Program Budget'!X762+'Program Budget'!X834+'Program Budget'!X893 -> 11486.534 | U13: =E13+H13+K13+N13+Q13+T13 -> 65779.147 | V13: =C13+F13+I13+L13+O13+R13 -> 37 | W13: =U13/V13 -> 1777.8148
B14: ='Program Budget'!D15 -> Education Director | C14: ='Program Budget'!G15 -> 9 | D14: ='Program Budget'!E15+'Program Budget'!E156+'Program Budget'!E218+'Program Budget'!E277+'Program Budget'!E346+'Program Budget'!E413+'Program Budget'!E485+'Program Budget'!E560+'Program Budget'!E615+'Program Budget'!E689+'Program Budget'!E763+'Program Budget'!E835+'Program Budget'!E894 -> 1 | E14: ='Program Budget'!I15+'Program Budget'!I156+'Program Budget'!I218+'Program Budget'!I277+'Program Budget'!I346+'Program Budget'!I413+'Program Budget'!I485+'Program Budget'!I560+'Program Budget'!I615+'Program Budget'!I689+'Program Budget'!I763+'Program Budget'!I835+'Program Budget'!I894 -> 41250 | F14: ='Program Budget'!K15 -> 12 | G14: ='Program Budget'!J15+'Program Budget'!J156+'Program Budget'!J218+'Program Budget'!J277+'Program Budget'!J346+'Program Budget'!J413+'Program Budget'!J485+'Program Budget'!J560+'Program Budget'!J615+'Program Budget'!J689+'Program Budget'!J763+'Program Budget'!J835+'Program Budget'!J894 -> 1 | H14: ='Program Budget'!L15+'Program Budget'!L156+'Program Budget'!L218+'Program Budget'!L277+'Program Budget'!L346+'Program Budget'!L413+'Program Budget'!L485+'Program Budget'!L560+'Program Budget'!L615+'Program Budget'!L689+'Program Budget'!L763+'Program Budget'!L835+'Program Budget'!L894 -> 57750 | I14: ='Program Budget'!N15 -> 12 | J14: ='Program Budget'!M15+'Program Budget'!M156+'Program Budget'!M218+'Program Budget'!M277+'Program Budget'!M346+'Program Budget'!M413+'Program Budget'!M485+'Program Budget'!M560+'Program Budget'!M615+'Program Budget'!M689+'Program Budget'!M763+'Program Budget'!M835+'Program Budget'!M894 -> 1 | K14: ='Program Budget'!O15+'Program Budget'!O156+'Program Budget'!O218+'Program Budget'!O277+'Program Budget'!O346+'Program Budget'!O413+'Program Budget'!O485+'Program Budget'!O560+'Program Budget'!O615+'Program Budget'!O689+'Program Budget'!O763+'Program Budget'!O835+'Program Budget'!O894 -> 60637.5 | L14: ='Program Budget'!Q15 -> 12 | M14: ='Program Budget'!P15+'Program Budget'!P156+'Program Budget'!P218+'Program Budget'!P277+'Program Budget'!P346+'Program Budget'!P413+'Program Budget'!P485+'Program Budget'!P560+'Program Budget'!P615+'Program Budget'!P689+'Program Budget'!P763+'Program Budget'!P835+'Program Budget'!P894 -> 1 | N14: ='Program Budget'!R15+'Program Budget'!R156+'Program Budget'!R218+'Program Budget'!R277+'Program Budget'!R346+'Program Budget'!R413+'Program Budget'!R485+'Program Budget'!R560+'Program Budget'!R615+'Program Budget'!R689+'Program Budget'!R763+'Program Budget'!R835+'Program Budget'!R894 -> 63669.375 | O14: ='Program Budget'!T15 -> 12 | P14: ='Program Budget'!S15+'Program Budget'!S156+'Program Budget'!S218+'Program Budget'!S277+'Program Budget'!S346+'Program Budget'!S413+'Program Budget'!S485+'Program Budget'!S560+'Program Budget'!S615+'Program Budget'!S689+'Program Budget'!S763+'Program Budget'!S835+'Program Budget'!S894 -> 1 | Q14: ='Program Budget'!U15+'Program Budget'!U156+'Program Budget'!U218+'Program Budget'!U277+'Program Budget'!U346+'Program Budget'!U413+'Program Budget'!U485+'Program Budget'!U560+'Program Budget'!U615+'Program Budget'!U689+'Program Budget'!U763+'Program Budget'!U835+'Program Budget'!U894 -> 66852.844 | R14: ='Program Budget'!W15 -> 8 | S14: ='Program Budget'!V15+'Program Budget'!V156+'Program Budget'!V218+'Program Budget'!V277+'Program Budget'!V346+'Program Budget'!V413+'Program Budget'!V485+'Program Budget'!V560+'Program Budget'!V615+'Program Budget'!V689+'Program Budget'!V763+'Program Budget'!V835+'Program Budget'!V894 -> 1 | T14: ='Program Budget'!X15+'Program Budget'!X156+'Program Budget'!X218+'Program Budget'!X277+'Program Budget'!X346+'Program Budget'!X413+'Program Budget'!X485+'Program Budget'!X560+'Program Budget'!X615+'Program Budget'!X689+'Program Budget'!X763+'Program Budget'!X835+'Program Budget'!X894 -> 46796.991 | U14: =E14+H14+K14+N14+Q14+T14 -> 336956.71 | V14: =C14+F14+I14+L14+O14+R14 -> 65 | W14: =U14/V14 -> 5183.9494
B15: ='Program Budget'!D16 -> Education Specialist | C15: ='Program Budget'!G16 -> 8 | D15: ='Program Budget'!E16+'Program Budget'!E157+'Program Budget'!E219+'Program Budget'!E278+'Program Budget'!E347+'Program Budget'!E414+'Program Budget'!E486+'Program Budget'!E561+'Program Budget'!E616+'Program Budget'!E690+'Program Budget'!E764+'Program Budget'!E836+'Program Budget'!E895 -> 1 | E15: ='Program Budget'!I16+'Program Budget'!I157+'Program Budget'!I219+'Program Budget'!I278+'Program Budget'!I347+'Program Budget'!I414+'Program Budget'!I486+'Program Budget'!I561+'Program Budget'!I616+'Program Budget'!I690+'Program Budget'!I764+'Program Budget'!I836+'Program Budget'!I895 -> 20000 | F15: ='Program Budget'!K16 -> 12 | G15: ='Program Budget'!J16+'Program Budget'!J157+'Program Budget'!J219+'Program Budget'!J278+'Program Budget'!J347+'Program Budget'!J414+'Program Budget'!J486+'Program Budget'!J561+'Program Budget'!J616+'Program Budget'!J690+'Program Budget'!J764+'Program Budget'!J836+'Program Budget'!J895 -> 1 | H15: ='Program Budget'!L16+'Program Budget'!L157+'Program Budget'!L219+'Program Budget'!L278+'Program Budget'!L347+'Program Budget'!L414+'Program Budget'!L486+'Program Budget'!L561+'Program Budget'!L616+'Program Budget'!L690+'Program Budget'!L764+'Program Budget'!L836+'Program Budget'!L895 -> 31500 | I15: ='Program Budget'!N16 -> 12 | J15: ='Program Budget'!M16+'Program Budget'!M157+'Program Budget'!M219+'Program Budget'!M278+'Program Budget'!M347+'Program Budget'!M414+'Program Budget'!M486+'Program Budget'!M561+'Program Budget'!M616+'Program Budget'!M690+'Program Budget'!M764+'Program Budget'!M836+'Program Budget'!M895 -> 1 | K15: ='Program Budget'!O16+'Program Budget'!O157+'Program Budget'!O219+'Program Budget'!O278+'Program Budget'!O347+'Program Budget'!O414+'Program Budget'!O486+'Program Budget'!O561+'Program Budget'!O616+'Program Budget'!O690+'Program Budget'!O764+'Program Budget'!O836+'Program Budget'!O895 -> 33075 | L15: ='Program Budget'!Q16 -> 12 | M15: ='Program Budget'!P16+'Program Budget'!P157+'Program Budget'!P219+'Program Budget'!P278+'Program Budget'!P347+'Program Budget'!P414+'Program Budget'!P486+'Program Budget'!P561+'Program Budget'!P616+'Program Budget'!P690+'Program Budget'!P764+'Program Budget'!P836+'Program Budget'!P895 -> 1 | N15: ='Program Budget'!R16+'Program Budget'!R157+'Program Budget'!R219+'Program Budget'!R278+'Program Budget'!R347+'Program Budget'!R414+'Program Budget'!R486+'Program Budget'!R561+'Program Budget'!R616+'Program Budget'!R690+'Program Budget'!R764+'Program Budget'!R836+'Program Budget'!R895 -> 34728.75 | O15: ='Program Budget'!T16 -> 12 | P15: ='Program Budget'!S16+'Program Budget'!S157+'Program Budget'!S219+'Program Budget'!S278+'Program Budget'!S347+'Program Budget'!S414+'Program Budget'!S486+'Program Budget'!S561+'Program Budget'!S616+'Program Budget'!S690+'Program Budget'!S764+'Program Budget'!S836+'Program Budget'!S895 -> 1 | Q15: ='Program Budget'!U16+'Program Budget'!U157+'Program Budget'!U219+'Program Budget'!U278+'Program Budget'!U347+'Program Budget'!U414+'Program Budget'!U486+'Program Budget'!U561+'Program Budget'!U616+'Program Budget'!U690+'Program Budget'!U764+'Program Budget'!U836+'Program Budget'!U895 -> 36465.188 | R15: ='Program Budget'!W16 -> 3 | S15: ='Program Budget'!V16+'Program Budget'!V157+'Program Budget'!V219+'Program Budget'!V278+'Program Budget'!V347+'Program Budget'!V414+'Program Budget'!V486+'Program Budget'!V561+'Program Budget'!V616+'Program Budget'!V690+'Program Budget'!V764+'Program Budget'!V836+'Program Budget'!V895 -> 1 | T15: ='Program Budget'!X16+'Program Budget'!X157+'Program Budget'!X219+'Program Budget'!X278+'Program Budget'!X347+'Program Budget'!X414+'Program Budget'!X486+'Program Budget'!X561+'Program Budget'!X616+'Program Budget'!X690+'Program Budget'!X764+'Program Budget'!X836+'Program Budget'!X895 -> 9572.1117 | U15: =E15+H15+K15+N15+Q15+T15 -> 165341.05 | V15: =C15+F15+I15+L15+O15+R15 -> 59 | W15: =U15/V15 -> 2802.3907
B16: ='Program Budget'!D17 -> Education Officer | C16: ='Program Budget'!G17 -> 6 | D16: ='Program Budget'!E17+'Program Budget'!E158+'Program Budget'!E220+'Program Budget'!E279+'Program Budget'!E348+'Program Budget'!E415+'Program Budget'!E487+'Program Budget'!E562+'Program Budget'!E617+'Program Budget'!E691+'Program Budget'!E765+'Program Budget'!E837+'Program Budget'!E896 -> 1 | E16: ='Program Budget'!I17+'Program Budget'!I158+'Program Budget'!I220+'Program Budget'!I279+'Program Budget'!I348+'Program Budget'!I415+'Program Budget'!I487+'Program Budget'!I562+'Program Budget'!I617+'Program Budget'!I691+'Program Budget'!I765+'Program Budget'!I837+'Program Budget'!I896 -> 6000 | F16: ='Program Budget'!K17 -> 12 | G16: ='Program Budget'!J17+'Program Budget'!J158+'Program Budget'!J220+'Program Budget'!J279+'Program Budget'!J348+'Program Budget'!J415+'Program Budget'!J487+'Program Budget'!J562+'Program Budget'!J617+'Program Budget'!J691+'Program Budget'!J765+'Program Budget'!J837+'Program Budget'!J896 -> 1 | H16: ='Program Budget'!L17+'Program Budget'!L158+'Program Budget'!L220+'Program Budget'!L279+'Program Budget'!L348+'Program Budget'!L415+'Program Budget'!L487+'Program Budget'!L562+'Program Budget'!L617+'Program Budget'!L691+'Program Budget'!L765+'Program Budget'!L837+'Program Budget'!L896 -> 12600 | I16: ='Program Budget'!N17 -> 12 | J16: ='Program Budget'!M17+'Program Budget'!M158+'Program Budget'!M220+'Program Budget'!M279+'Program Budget'!M348+'Program Budget'!M415+'Program Budget'!M487+'Program Budget'!M562+'Program Budget'!M617+'Program Budget'!M691+'Program Budget'!M765+'Program Budget'!M837+'Program Budget'!M896 -> 1 | K16: ='Program Budget'!O17+'Program Budget'!O158+'Program Budget'!O220+'Program Budget'!O279+'Program Budget'!O348+'Program Budget'!O415+'Program Budget'!O487+'Program Budget'!O562+'Program Budget'!O617+'Program Budget'!O691+'Program Budget'!O765+'Program Budget'!O837+'Program Budget'!O896 -> 13230 | L16: ='Program Budget'!Q17 -> 12 | M16: ='Program Budget'!P17+'Program Budget'!P158+'Program Budget'!P220+'Program Budget'!P279+'Program Budget'!P348+'Program Budget'!P415+'Program Budget'!P487+'Program Budget'!P562+'Program Budget'!P617+'Program Budget'!P691+'Program Budget'!P765+'Program Budget'!P837+'Program Budget'!P896 -> 1 | N16: ='Program Budget'!R17+'Program Budget'!R158+'Program Budget'!R220+'Program Budget'!R279+'Program Budget'!R348+'Program Budget'!R415+'Program Budget'!R487+'Program Budget'!R562+'Program Budget'!R617+'Program Budget'!R691+'Program Budget'!R765+'Program Budget'!R837+'Program Budget'!R896 -> 13891.5 | O16: ='Program Budget'!T17 -> 12 | P16: ='Program Budget'!S17+'Program Budget'!S158+'Program Budget'!S220+'Program Budget'!S279+'Program Budget'!S348+'Program Budget'!S415+'Program Budget'!S487+'Program Budget'!S562+'Program Budget'!S617+'Program Budget'!S691+'Program Budget'!S765+'Program Budget'!S837+'Program Budget'!S896 -> 1 | Q16: ='Program Budget'!U17+'Program Budget'!U158+'Program Budget'!U220+'Program Budget'!U279+'Program Budget'!U348+'Program Budget'!U415+'Program Budget'!U487+'Program Budget'!U562+'Program Budget'!U617+'Program Budget'!U691+'Program Budget'!U765+'Program Budget'!U837+'Program Budget'!U896 -> 14586.075 | R16: ='Program Budget'!W17 -> 3 | S16: ='Program Budget'!V17+'Program Budget'!V158+'Program Budget'!V220+'Program Budget'!V279+'Program Budget'!V348+'Program Budget'!V415+'Program Budget'!V487+'Program Budget'!V562+'Program Budget'!V617+'Program Budget'!V691+'Program Budget'!V765+'Program Budget'!V837+'Program Budget'!V896 -> 1 | T16: ='Program Budget'!X17+'Program Budget'!X158+'Program Budget'!X220+'Program Budget'!X279+'Program Budget'!X348+'Program Budget'!X415+'Program Budget'!X487+'Program Budget'!X562+'Program Budget'!X617+'Program Budget'!X691+'Program Budget'!X765+'Program Budget'!X837+'Program Budget'!X896 -> 3828.8447 | U16: =E16+H16+K16+N16+Q16+T16 -> 64136.42 | V16: =C16+F16+I16+L16+O16+R16 -> 57 | W16: =U16/V16 -> 1125.2003
B17: ='Program Budget'!D18 -> Nutrition and Health Specialist | C17: ='Program Budget'!G18 -> 9 | D17: ='Program Budget'!E18+'Program Budget'!E159+'Program Budget'!E221+'Program Budget'!E280+'Program Budget'!E349+'Program Budget'!E416+'Program Budget'!E488+'Program Budget'!E563+'Program Budget'!E618+'Program Budget'!E692+'Program Budget'!E766+'Program Budget'!E838+'Program Budget'!E897 -> 1 | E17: ='Program Budget'!I18+'Program Budget'!I159+'Program Budget'!I221+'Program Budget'!I280+'Program Budget'!I349+'Program Budget'!I416+'Program Budget'!I488+'Program Budget'!I563+'Program Budget'!I618+'Program Budget'!I692+'Program Budget'!I766+'Program Budget'!I838+'Program Budget'!I897 -> 13500 | F17: ='Program Budget'!K18 -> 12 | G17: ='Program Budget'!J18+'Program Budget'!J159+'Program Budget'!J221+'Program Budget'!J280+'Program Budget'!J349+'Program Budget'!J416+'Program Budget'!J488+'Program Budget'!J563+'Program Budget'!J618+'Program Budget'!J692+'Program Budget'!J766+'Program Budget'!J838+'Program Budget'!J897 -> 1 | H17: ='Program Budget'!L18+'Program Budget'!L159+'Program Budget'!L221+'Program Budget'!L280+'Program Budget'!L349+'Program Budget'!L416+'Program Budget'!L488+'Program Budget'!L563+'Program Budget'!L618+'Program Budget'!L692+'Program Budget'!L766+'Program Budget'!L838+'Program Budget'!L897 -> 18900 | I17: ='Program Budget'!N18 -> 12 | J17: ='Program Budget'!M18+'Program Budget'!M159+'Program Budget'!M221+'Program Budget'!M280+'Program Budget'!M349+'Program Budget'!M416+'Program Budget'!M488+'Program Budget'!M563+'Program Budget'!M618+'Program Budget'!M692+'Program Budget'!M766+'Program Budget'!M838+'Program Budget'!M897 -> 1 | K17: ='Program Budget'!O18+'Program Budget'!O159+'Program Budget'!O221+'Program Budget'!O280+'Program Budget'!O349+'Program Budget'!O416+'Program Budget'!O488+'Program Budget'!O563+'Program Budget'!O618+'Program Budget'!O692+'Program Budget'!O766+'Program Budget'!O838+'Program Budget'!O897 -> 19845 | L17: ='Program Budget'!Q18 -> 12 | M17: ='Program Budget'!P18+'Program Budget'!P159+'Program Budget'!P221+'Program Budget'!P280+'Program Budget'!P349+'Program Budget'!P416+'Program Budget'!P488+'Program Budget'!P563+'Program Budget'!P618+'Program Budget'!P692+'Program Budget'!P766+'Program Budget'!P838+'Program Budget'!P897 -> 1 | N17: ='Program Budget'!R18+'Program Budget'!R159+'Program Budget'!R221+'Program Budget'!R280+'Program Budget'!R349+'Program Budget'!R416+'Program Budget'!R488+'Program Budget'!R563+'Program Budget'!R618+'Program Budget'!R692+'Program Budget'!R766+'Program Budget'!R838+'Program Budget'!R897 -> 20837.25 | O17: ='Program Budget'!T18 -> 12 | P17: ='Program Budget'!S18+'Program Budget'!S159+'Program Budget'!S221+'Program Budget'!S280+'Program Budget'!S349+'Program Budget'!S416+'Program Budget'!S488+'Program Budget'!S563+'Program Budget'!S618+'Program Budget'!S692+'Program Budget'!S766+'Program Budget'!S838+'Program Budget'!S897 -> 1 | Q17: ='Program Budget'!U18+'Program Budget'!U159+'Program Budget'!U221+'Program Budget'!U280+'Program Budget'!U349+'Program Budget'!U416+'Program Budget'!U488+'Program Budget'!U563+'Program Budget'!U618+'Program Budget'!U692+'Program Budget'!U766+'Program Budget'!U838+'Program Budget'!U897 -> 21879.112 | R17: ='Program Budget'!W18 -> 6 | S17: ='Program Budget'!V18+'Program Budget'!V159+'Program Budget'!V221+'Program Budget'!V280+'Program Budget'!V349+'Program Budget'!V416+'Program Budget'!V488+'Program Budget'!V563+'Program Budget'!V618+'Program Budget'!V692+'Program Budget'!V766+'Program Budget'!V838+'Program Budget'!V897 -> 1 | T17: ='Program Budget'!X18+'Program Budget'!X159+'Program Budget'!X221+'Program Budget'!X280+'Program Budget'!X349+'Program Budget'!X416+'Program Budget'!X488+'Program Budget'!X563+'Program Budget'!X618+'Program Budget'!X692+'Program Budget'!X766+'Program Budget'!X838+'Program Budget'!X897 -> 11486.534 | U17: =E17+H17+K17+N17+Q17+T17 -> 106447.9 | V17: =C17+F17+I17+L17+O17+R17 -> 63 | W17: =U17/V17 -> 1689.6492
B18: ='Program Budget'!D19 -> Nutrition Officer - (2 Individuals) | C18: ='Program Budget'!G19 -> 6 | D18: ='Program Budget'!E19+'Program Budget'!E160+'Program Budget'!E222+'Program Budget'!E281+'Program Budget'!E350+'Program Budget'!E417+'Program Budget'!E489+'Program Budget'!E564+'Program Budget'!E619+'Program Budget'!E693+'Program Budget'!E767+'Program Budget'!E839+'Program Budget'!E898 -> 1 | E18: ='Program Budget'!I19+'Program Budget'!I160+'Program Budget'!I222+'Program Budget'!I281+'Program Budget'!I350+'Program Budget'!I417+'Program Budget'!I489+'Program Budget'!I564+'Program Budget'!I619+'Program Budget'!I693+'Program Budget'!I767+'Program Budget'!I839+'Program Budget'!I898 -> 6000 | F18: ='Program Budget'!K19 -> 24 | G18: ='Program Budget'!J19+'Program Budget'!J160+'Program Budget'!J222+'Program Budget'!J281+'Program Budget'!J350+'Program Budget'!J417+'Program Budget'!J489+'Program Budget'!J564+'Program Budget'!J619+'Program Budget'!J693+'Program Budget'!J767+'Program Budget'!J839+'Program Budget'!J898 -> 1 | H18: ='Program Budget'!L19+'Program Budget'!L160+'Program Budget'!L222+'Program Budget'!L281+'Program Budget'!L350+'Program Budget'!L417+'Program Budget'!L489+'Program Budget'!L564+'Program Budget'!L619+'Program Budget'!L693+'Program Budget'!L767+'Program Budget'!L839+'Program Budget'!L898 -> 25200 | I18: ='Program Budget'!N19 -> 24 | J18: ='Program Budget'!M19+'Program Budget'!M160+'Program Budget'!M222+'Program Budget'!M281+'Program Budget'!M350+'Program Budget'!M417+'Program Budget'!M489+'Program Budget'!M564+'Program Budget'!M619+'Program Budget'!M693+'Program Budget'!M767+'Program Budget'!M839+'Program Budget'!M898 -> 1 | K18: ='Program Budget'!O19+'Program Budget'!O160+'Program Budget'!O222+'Program Budget'!O281+'Program Budget'!O350+'Program Budget'!O417+'Program Budget'!O489+'Program Budget'!O564+'Program Budget'!O619+'Program Budget'!O693+'Program Budget'!O767+'Program Budget'!O839+'Program Budget'!O898 -> 26460 | L18: ='Program Budget'!Q19 -> 24 | M18: ='Program Budget'!P19+'Program Budget'!P160+'Program Budget'!P222+'Program Budget'!P281+'Program Budget'!P350+'Program Budget'!P417+'Program Budget'!P489+'Program Budget'!P564+'Program Budget'!P619+'Program Budget'!P693+'Program Budget'!P767+'Program Budget'!P839+'Program Budget'!P898 -> 1 | N18: ='Program Budget'!R19+'Program Budget'!R160+'Program Budget'!R222+'Program Budget'!R281+'Program Budget'!R350+'Program Budget'!R417+'Program Budget'!R489+'Program Budget'!R564+'Program Budget'!R619+'Program Budget'!R693+'Program Budget'!R767+'Program Budget'!R839+'Program Budget'!R898 -> 27783 | O18: ='Program Budget'!T19 -> 24 | P18: ='Program Budget'!S19+'Program Budget'!S160+'Program Budget'!S222+'Program Budget'!S281+'Program Budget'!S350+'Program Budget'!S417+'Program Budget'!S489+'Program Budget'!S564+'Program Budget'!S619+'Program Budget'!S693+'Program Budget'!S767+'Program Budget'!S839+'Program Budget'!S898 -> 1 | Q18: ='Program Budget'!U19+'Program Budget'!U160+'Program Budget'!U222+'Program Budget'!U281+'Program Budget'!U350+'Program Budget'!U417+'Program Budget'!U489+'Program Budget'!U564+'Program Budget'!U619+'Program Budget'!U693+'Program Budget'!U767+'Program Budget'!U839+'Program Budget'!U898 -> 29172.15 | R18: ='Program Budget'!W19 -> 6 | S18: ='Program Budget'!V19+'Program Budget'!V160+'Program Budget'!V222+'Program Budget'!V281+'Program Budget'!V350+'Program Budget'!V417+'Program Budget'!V489+'Program Budget'!V564+'Program Budget'!V619+'Program Budget'!V693+'Program Budget'!V767+'Program Budget'!V839+'Program Budget'!V898 -> 1 | T18: ='Program Budget'!X19+'Program Budget'!X160+'Program Budget'!X222+'Program Budget'!X281+'Program Budget'!X350+'Program Budget'!X417+'Program Budget'!X489+'Program Budget'!X564+'Program Budget'!X619+'Program Budget'!X693+'Program Budget'!X767+'Program Budget'!X839+'Program Budget'!X898 -> 7657.6894 | U18: =E18+H18+K18+N18+Q18+T18 -> 122272.84 | V18: =C18+F18+I18+L18+O18+R18 -> 108 | W18: =U18/V18 -> 1132.1559
B19: ='Program Budget'!D20 -> School Feeding Specialist | C19: ='Program Budget'!G20 -> 9 | D19: ='Program Budget'!E20+'Program Budget'!E161+'Program Budget'!E223+'Program Budget'!E282+'Program Budget'!E351+'Program Budget'!E418+'Program Budget'!E490+'Program Budget'!E565+'Program Budget'!E620+'Program Budget'!E694+'Program Budget'!E768+'Program Budget'!E840+'Program Budget'!E899 -> 1 | E19: ='Program Budget'!I20+'Program Budget'!I161+'Program Budget'!I223+'Program Budget'!I282+'Program Budget'!I351+'Program Budget'!I418+'Program Budget'!I490+'Program Budget'!I565+'Program Budget'!I620+'Program Budget'!I694+'Program Budget'!I768+'Program Budget'!I840+'Program Budget'!I899 -> 13500 | F19: ='Program Budget'!K20 -> 12 | G19: ='Program Budget'!J20+'Program Budget'!J161+'Program Budget'!J223+'Program Budget'!J282+'Program Budget'!J351+'Program Budget'!J418+'Program Budget'!J490+'Program Budget'!J565+'Program Budget'!J620+'Program Budget'!J694+'Program Budget'!J768+'Program Budget'!J840+'Program Budget'!J899 -> 1 | H19: ='Program Budget'!L20+'Program Budget'!L161+'Program Budget'!L223+'Program Budget'!L282+'Program Budget'!L351+'Program Budget'!L418+'Program Budget'!L490+'Program Budget'!L565+'Program Budget'!L620+'Program Budget'!L694+'Program Budget'!L768+'Program Budget'!L840+'Program Budget'!L899 -> 18900 | I19: ='Program Budget'!N20 -> 12 | J19: ='Program Budget'!M20+'Program Budget'!M161+'Program Budget'!M223+'Program Budget'!M282+'Program Budget'!M351+'Program Budget'!M418+'Program Budget'!M490+'Program Budget'!M565+'Program Budget'!M620+'Program Budget'!M694+'Program Budget'!M768+'Program Budget'!M840+'Program Budget'!M899 -> 1 | K19: ='Program Budget'!O20+'Program Budget'!O161+'Program Budget'!O223+'Program Budget'!O282+'Program Budget'!O351+'Program Budget'!O418+'Program Budget'!O490+'Program Budget'!O565+'Program Budget'!O620+'Program Budget'!O694+'Program Budget'!O768+'Program Budget'!O840+'Program Budget'!O899 -> 19845 | L19: ='Program Budget'!Q20 -> 12 | M19: ='Program Budget'!P20+'Program Budget'!P161+'Program Budget'!P223+'Program Budget'!P282+'Program Budget'!P351+'Program Budget'!P418+'Program Budget'!P490+'Program Budget'!P565+'Program Budget'!P620+'Program Budget'!P694+'Program Budget'!P768+'Program Budget'!P840+'Program Budget'!P899 -> 1 | N19: ='Program Budget'!R20+'Program Budget'!R161+'Program Budget'!R223+'Program Budget'!R282+'Program Budget'!R351+'Program Budget'!R418+'Program Budget'!R490+'Program Budget'!R565+'Program Budget'!R620+'Program Budget'!R694+'Program Budget'!R768+'Program Budget'!R840+'Program Budget'!R899 -> 20837.25 | O19: ='Program Budget'!T20 -> 6 | P19: ='Program Budget'!S20+'Program Budget'!S161+'Program Budget'!S223+'Program Budget'!S282+'Program Budget'!S351+'Program Budget'!S418+'Program Budget'!S490+'Program Budget'!S565+'Program Budget'!S620+'Program Budget'!S694+'Program Budget'!S768+'Program Budget'!S840+'Program Budget'!S899 -> 1 | Q19: ='Program Budget'!U20+'Program Budget'!U161+'Program Budget'!U223+'Program Budget'!U282+'Program Budget'!U351+'Program Budget'!U418+'Program Budget'!U490+'Program Budget'!U565+'Program Budget'!U620+'Program Budget'!U694+'Program Budget'!U768+'Program Budget'!U840+'Program Budget'!U899 -> 10939.556 | R19: ='Program Budget'!W20 -> 6 | S19: ='Program Budget'!V20+'Program Budget'!V161+'Program Budget'!V223+'Program Budget'!V282+'Program Budget'!V351+'Program Budget'!V418+'Program Budget'!V490+'Program Budget'!V565+'Program Budget'!V620+'Program Budget'!V694+'Program Budget'!V768+'Program Budget'!V840+'Program Budget'!V899 -> 1 | T19: ='Program Budget'!X20+'Program Budget'!X161+'Program Budget'!X223+'Program Budget'!X282+'Program Budget'!X351+'Program Budget'!X418+'Program Budget'!X490+'Program Budget'!X565+'Program Budget'!X620+'Program Budget'!X694+'Program Budget'!X768+'Program Budget'!X840+'Program Budget'!X899 -> 11486.534 | U19: =E19+H19+K19+N19+Q19+T19 -> 95508.34 | V19: =C19+F19+I19+L19+O19+R19 -> 57 | W19: =U19/V19 -> 1675.5849
B20: ='Program Budget'!D21 -> Food Aid Monitors - (2 Individuals) | C20: ='Program Budget'!G21 -> 6 | D20: ='Program Budget'!E21+'Program Budget'!E162+'Program Budget'!E224+'Program Budget'!E283+'Program Budget'!E352+'Program Budget'!E419+'Program Budget'!E491+'Program Budget'!E566+'Program Budget'!E621+'Program Budget'!E695+'Program Budget'!E769+'Program Budget'!E841+'Program Budget'!E900 -> 1 | E20: ='Program Budget'!I21+'Program Budget'!I162+'Program Budget'!I224+'Program Budget'!I283+'Program Budget'!I352+'Program Budget'!I419+'Program Budget'!I491+'Program Budget'!I566+'Program Budget'!I621+'Program Budget'!I695+'Program Budget'!I769+'Program Budget'!I841+'Program Budget'!I900 -> 6000 | F20: ='Program Budget'!K21 -> 24 | G20: ='Program Budget'!J21+'Program Budget'!J162+'Program Budget'!J224+'Program Budget'!J283+'Program Budget'!J352+'Program Budget'!J419+'Program Budget'!J491+'Program Budget'!J566+'Program Budget'!J621+'Program Budget'!J695+'Program Budget'!J769+'Program Budget'!J841+'Program Budget'!J900 -> 1 | H20: ='Program Budget'!L21+'Program Budget'!L162+'Program Budget'!L224+'Program Budget'!L283+'Program Budget'!L352+'Program Budget'!L419+'Program Budget'!L491+'Program Budget'!L566+'Program Budget'!L621+'Program Budget'!L695+'Program Budget'!L769+'Program Budget'!L841+'Program Budget'!L900 -> 25200 | I20: ='Program Budget'!N21 -> 24 | J20: ='Program Budget'!M21+'Program Budget'!M162+'Program Budget'!M224+'Program Budget'!M283+'Program Budget'!M352+'Program Budget'!M419+'Program Budget'!M491+'Program Budget'!M566+'Program Budget'!M621+'Program Budget'!M695+'Program Budget'!M769+'Program Budget'!M841+'Program Budget'!M900 -> 1 | K20: ='Program Budget'!O21+'Program Budget'!O162+'Program Budget'!O224+'Program Budget'!O283+'Program Budget'!O352+'Program Budget'!O419+'Program Budget'!O491+'Program Budget'!O566+'Program Budget'!O621+'Program Budget'!O695+'Program Budget'!O769+'Program Budget'!O841+'Program Budget'!O900 -> 26460 | L20: ='Program Budget'!Q21 -> 24 | M20: ='Program Budget'!P21+'Program Budget'!P162+'Program Budget'!P224+'Program Budget'!P283+'Program Budget'!P352+'Program Budget'!P419+'Program Budget'!P491+'Program Budget'!P566+'Program Budget'!P621+'Program Budget'!P695+'Program Budget'!P769+'Program Budget'!P841+'Program Budget'!P900 -> 1 | N20: ='Program Budget'!R21+'Program Budget'!R162+'Program Budget'!R224+'Program Budget'!R283+'Program Budget'!R352+'Program Budget'!R419+'Program Budget'!R491+'Program Budget'!R566+'Program Budget'!R621+'Program Budget'!R695+'Program Budget'!R769+'Program Budget'!R841+'Program Budget'!R900 -> 27783 | O20: ='Program Budget'!T21 -> 24 | P20: ='Program Budget'!S21+'Program Budget'!S162+'Program Budget'!S224+'Program Budget'!S283+'Program Budget'!S352+'Program Budget'!S419+'Program Budget'!S491+'Program Budget'!S566+'Program Budget'!S621+'Program Budget'!S695+'Program Budget'!S769+'Program Budget'!S841+'Program Budget'!S900 -> 1 | Q20: ='Program Budget'!U21+'Program Budget'!U162+'Program Budget'!U224+'Program Budget'!U283+'Program Budget'!U352+'Program Budget'!U419+'Program Budget'!U491+'Program Budget'!U566+'Program Budget'!U621+'Program Budget'!U695+'Program Budget'!U769+'Program Budget'!U841+'Program Budget'!U900 -> 29172.15 | R20: ='Program Budget'!W21 -> 12 | S20: ='Program Budget'!V21+'Program Budget'!V162+'Program Budget'!V224+'Program Budget'!V283+'Program Budget'!V352+'Program Budget'!V419+'Program Budget'!V491+'Program Budget'!V566+'Program Budget'!V621+'Program Budget'!V695+'Program Budget'!V769+'Program Budget'!V841+'Program Budget'!V900 -> 1 | T20: ='Program Budget'!X21+'Program Budget'!X162+'Program Budget'!X224+'Program Budget'!X283+'Program Budget'!X352+'Program Budget'!X419+'Program Budget'!X491+'Program Budget'!X566+'Program Budget'!X621+'Program Budget'!X695+'Program Budget'!X769+'Program Budget'!X841+'Program Budget'!X900 -> 15315.379 | U20: =E20+H20+K20+N20+Q20+T20 -> 129930.53 | V20: =C20+F20+I20+L20+O20+R20 -> 114 | W20: =U20/V20 -> 1139.7415
B21: ='Program Budget'!D22 -> WASH Officer | C21: ='Program Budget'!G22 -> 6 | D21: ='Program Budget'!E22+'Program Budget'!E163+'Program Budget'!E225+'Program Budget'!E284+'Program Budget'!E353+'Program Budget'!E420+'Program Budget'!E492+'Program Budget'!E567+'Program Budget'!E622+'Program Budget'!E696+'Program Budget'!E770+'Program Budget'!E842+'Program Budget'!E901 -> 1 | E21: ='Program Budget'!I22+'Program Budget'!I163+'Program Budget'!I225+'Program Budget'!I284+'Program Budget'!I353+'Program Budget'!I420+'Program Budget'!I492+'Program Budget'!I567+'Program Budget'!I622+'Program Budget'!I696+'Program Budget'!I770+'Program Budget'!I842+'Program Budget'!I901 -> 6000 | F21: ='Program Budget'!K22 -> 12 | G21: ='Program Budget'!J22+'Program Budget'!J163+'Program Budget'!J225+'Program Budget'!J284+'Program Budget'!J353+'Program Budget'!J420+'Program Budget'!J492+'Program Budget'!J567+'Program Budget'!J622+'Program Budget'!J696+'Program Budget'!J770+'Program Budget'!J842+'Program Budget'!J901 -> 1 | H21: ='Program Budget'!L22+'Program Budget'!L163+'Program Budget'!L225+'Program Budget'!L284+'Program Budget'!L353+'Program Budget'!L420+'Program Budget'!L492+'Program Budget'!L567+'Program Budget'!L622+'Program Budget'!L696+'Program Budget'!L770+'Program Budget'!L842+'Program Budget'!L901 -> 12600 | I21: ='Program Budget'!N22 -> 12 | J21: ='Program Budget'!M22+'Program Budget'!M163+'Program Budget'!M225+'Program Budget'!M284+'Program Budget'!M353+'Program Budget'!M420+'Program Budget'!M492+'Program Budget'!M567+'Program Budget'!M622+'Program Budget'!M696+'Program Budget'!M770+'Program Budget'!M842+'Program Budget'!M901 -> 1 | K21: ='Program Budget'!O22+'Program Budget'!O163+'Program Budget'!O225+'Program Budget'!O284+'Program Budget'!O353+'Program Budget'!O420+'Program Budget'!O492+'Program Budget'!O567+'Program Budget'!O622+'Program Budget'!O696+'Program Budget'!O770+'Program Budget'!O842+'Program Budget'!O901 -> 13230 | L21: ='Program Budget'!Q22 -> 12 | M21: ='Program Budget'!P22+'Program Budget'!P163+'Program Budget'!P225+'Program Budget'!P284+'Program Budget'!P353+'Program Budget'!P420+'Program Budget'!P492+'Program Budget'!P567+'Program Budget'!P622+'Program Budget'!P696+'Program Budget'!P770+'Program Budget'!P842+'Program Budget'!P901 -> 1 | N21: ='Program Budget'!R22+'Program Budget'!R163+'Program Budget'!R225+'Program Budget'!R284+'Program Budget'!R353+'Program Budget'!R420+'Program Budget'!R492+'Program Budget'!R567+'Program Budget'!R622+'Program Budget'!R696+'Program Budget'!R770+'Program Budget'!R842+'Program Budget'!R901 -> 13891.5 | O21: ='Program Budget'!T22 -> 12 | P21: ='Program Budget'!S22+'Program Budget'!S163+'Program Budget'!S225+'Program Budget'!S284+'Program Budget'!S353+'Program Budget'!S420+'Program Budget'!S492+'Program Budget'!S567+'Program Budget'!S622+'Program Budget'!S696+'Program Budget'!S770+'Program Budget'!S842+'Program Budget'!S901 -> 1 | Q21: ='Program Budget'!U22+'Program Budget'!U163+'Program Budget'!U225+'Program Budget'!U284+'Program Budget'!U353+'Program Budget'!U420+'Program Budget'!U492+'Program Budget'!U567+'Program Budget'!U622+'Program Budget'!U696+'Program Budget'!U770+'Program Budget'!U842+'Program Budget'!U901 -> 14586.075 | R21: ='Program Budget'!W22 -> 3 | S21: ='Program Budget'!V22+'Program Budget'!V163+'Program Budget'!V225+'Program Budget'!V284+'Program Budget'!V353+'Program Budget'!V420+'Program Budget'!V492+'Program Budget'!V567+'Program Budget'!V622+'Program Budget'!V696+'Program Budget'!V770+'Program Budget'!V842+'Program Budget'!V901 -> 1 | T21: ='Program Budget'!X22+'Program Budget'!X163+'Program Budget'!X225+'Program Budget'!X284+'Program Budget'!X353+'Program Budget'!X420+'Program Budget'!X492+'Program Budget'!X567+'Program Budget'!X622+'Program Budget'!X696+'Program Budget'!X770+'Program Budget'!X842+'Program Budget'!X901 -> 3828.8447 | U21: =E21+H21+K21+N21+Q21+T21 -> 64136.42 | V21: =C21+F21+I21+L21+O21+R21 -> 57 | W21: =U21/V21 -> 1125.2003
B22: ='Program Budget'!D23 -> Communications Specialist | C22: ='Program Budget'!G23 -> 8 | D22: ='Program Budget'!E23+'Program Budget'!E164+'Program Budget'!E226+'Program Budget'!E285+'Program Budget'!E354+'Program Budget'!E421+'Program Budget'!E493+'Program Budget'!E568+'Program Budget'!E623+'Program Budget'!E697+'Program Budget'!E771+'Program Budget'!E843+'Program Budget'!E902 -> 1 | E22: ='Program Budget'!I23+'Program Budget'!I164+'Program Budget'!I226+'Program Budget'!I285+'Program Budget'!I354+'Program Budget'!I421+'Program Budget'!I493+'Program Budget'!I568+'Program Budget'!I623+'Program Budget'!I697+'Program Budget'!I771+'Program Budget'!I843+'Program Budget'!I902 -> 12000 | F22: ='Program Budget'!K23 -> 12 | G22: ='Program Budget'!J23+'Program Budget'!J164+'Program Budget'!J226+'Program Budget'!J285+'Program Budget'!J354+'Program Budget'!J421+'Program Budget'!J493+'Program Budget'!J568+'Program Budget'!J623+'Program Budget'!J697+'Program Budget'!J771+'Program Budget'!J843+'Program Budget'!J902 -> 1 | H22: ='Program Budget'!L23+'Program Budget'!L164+'Program Budget'!L226+'Program Budget'!L285+'Program Budget'!L354+'Program Budget'!L421+'Program Budget'!L493+'Program Budget'!L568+'Program Budget'!L623+'Program Budget'!L697+'Program Budget'!L771+'Program Budget'!L843+'Program Budget'!L902 -> 18900 | I22: ='Program Budget'!N23 -> 12 | J22: ='Program Budget'!M23+'Program Budget'!M164+'Program Budget'!M226+'Program Budget'!M285+'Program Budget'!M354+'Program Budget'!M421+'Program Budget'!M493+'Program Budget'!M568+'Program Budget'!M623+'Program Budget'!M697+'Program Budget'!M771+'Program Budget'!M843+'Program Budget'!M902 -> 1 | K22: ='Program Budget'!O23+'Program Budget'!O164+'Program Budget'!O226+'Program Budget'!O285+'Program Budget'!O354+'Program Budget'!O421+'Program Budget'!O493+'Program Budget'!O568+'Program Budget'!O623+'Program Budget'!O697+'Program Budget'!O771+'Program Budget'!O843+'Program Budget'!O902 -> 19845 | L22: ='Program Budget'!Q23 -> 12 | M22: ='Program Budget'!P23+'Program Budget'!P164+'Program Budget'!P226+'Program Budget'!P285+'Program Budget'!P354+'Program Budget'!P421+'Program Budget'!P493+'Program Budget'!P568+'Program Budget'!P623+'Program Budget'!P697+'Program Budget'!P771+'Program Budget'!P843+'Program Budget'!P902 -> 1 | N22: ='Program Budget'!R23+'Program Budget'!R164+'Program Budget'!R226+'Program Budget'!R285+'Program Budget'!R354+'Program Budget'!R421+'Program Budget'!R493+'Program Budget'!R568+'Program Budget'!R623+'Program Budget'!R697+'Program Budget'!R771+'Program Budget'!R843+'Program Budget'!R902 -> 20837.25 | O22: ='Program Budget'!T23 -> 12 | P22: ='Program Budget'!S23+'Program Budget'!S164+'Program Budget'!S226+'Program Budget'!S285+'Program Budget'!S354+'Program Budget'!S421+'Program Budget'!S493+'Program Budget'!S568+'Program Budget'!S623+'Program Budget'!S697+'Program Budget'!S771+'Program Budget'!S843+'Program Budget'!S902 -> 1 | Q22: ='Program Budget'!U23+'Program Budget'!U164+'Program Budget'!U226+'Program Budget'!U285+'Program Budget'!U354+'Program Budget'!U421+'Program Budget'!U493+'Program Budget'!U568+'Program Budget'!U623+'Program Budget'!U697+'Program Budget'!U771+'Program Budget'!U843+'Program Budget'!U902 -> 21879.112 | R22: ='Program Budget'!W23 -> 8 | S22: ='Program Budget'!V23+'Program Budget'!V164+'Program Budget'!V226+'Program Budget'!V285+'Program Budget'!V354+'Program Budget'!V421+'Program Budget'!V493+'Program Budget'!V568+'Program Budget'!V623+'Program Budget'!V697+'Program Budget'!V771+'Program Budget'!V843+'Program Budget'!V902 -> 1 | T22: ='Program Budget'!X23+'Program Budget'!X164+'Program Budget'!X226+'Program Budget'!X285+'Program Budget'!X354+'Program Budget'!X421+'Program Budget'!X493+'Program Budget'!X568+'Program Budget'!X623+'Program Budget'!X697+'Program Budget'!X771+'Program Budget'!X843+'Program Budget'!X902 -> 15315.379 | U22: =E22+H22+K22+N22+Q22+T22 -> 108776.74 | V22: =C22+F22+I22+L22+O22+R22 -> 64 | W22: =U22/V22 -> 1699.6366
... B44: ='Program Budget'!D45 -> Driver - (2 Individuals) | C44: ='Program Budget'!G45 -> 6 | D44: ='Program Budget'!E45+'Program Budget'!E186+'Program Budget'!E248+'Program Budget'!E307+'Program Budget'!E376+'Program Budget'!E443+'Program Budget'!E515+'Program Budget'!E590+'Program Budget'!E645+'Program Budget'!E719+'Program Budget'!E793+'Program Budget'!E865+'Program Budget'!E924 -> 1 | E44: ='Program Budget'!I45+'Program Budget'!I186+'Program Budget'!I248+'Program Budget'!I307+'Program Budget'!I376+'Program Budget'!I443+'Program Budget'!I515+'Program Budget'!I590+'Program Budget'!I645+'Program Budget'!I719+'Program Budget'!I793+'Program Budget'!I865+'Program Budget'!I924 -> 3000 | F44: ='Program Budget'!K45 -> 24 | G44: ='Program Budget'!J45+'Program Budget'!J186+'Program Budget'!J248+'Program Budget'!J307+'Program Budget'!J376+'Program Budget'!J443+'Program Budget'!J515+'Program Budget'!J590+'Program Budget'!J645+'Program Budget'!J719+'Program Budget'!J793+'Program Budget'!J865+'Program Budget'!J924 -> 1 | H44: ='Program Budget'!L45+'Program Budget'!L186+'Program Budget'!L248+'Program Budget'!L307+'Program Budget'!L376+'Program Budget'!L443+'Program Budget'!L515+'Program Budget'!L590+'Program Budget'!L645+'Program Budget'!L719+'Program Budget'!L793+'Program Budget'!L865+'Program Budget'!L924 -> 12600 | I44: ='Program Budget'!N45 -> 24 | J44: ='Program Budget'!M45+'Program Budget'!M186+'Program Budget'!M248+'Program Budget'!M307+'Program Budget'!M376+'Program Budget'!M443+'Program Budget'!M515+'Program Budget'!M590+'Program Budget'!M645+'Program Budget'!M719+'Program Budget'!M793+'Program Budget'!M865+'Program Budget'!M924 -> 1 | K44: ='Program Budget'!O45+'Program Budget'!O186+'Program Budget'!O248+'Program Budget'!O307+'Program Budget'!O376+'Program Budget'!O443+'Program Budget'!O515+'Program Budget'!O590+'Program Budget'!O645+'Program Budget'!O719+'Program Budget'!O793+'Program Budget'!O865+'Program Budget'!O924 -> 13230 | L44: ='Program Budget'!Q45 -> 24 | M44: ='Program Budget'!P45+'Program Budget'!P186+'Program Budget'!P248+'Program Budget'!P307+'Program Budget'!P376+'Program Budget'!P443+'Program Budget'!P515+'Program Budget'!P590+'Program Budget'!P645+'Program Budget'!P719+'Program Budget'!P793+'Program Budget'!P865+'Program Budget'!P924 -> 1 | N44: ='Program Budget'!R45+'Program Budget'!R186+'Program Budget'!R248+'Program Budget'!R307+'Program Budget'!R376+'Program Budget'!R443+'Program Budget'!R515+'Program Budget'!R590+'Program Budget'!R645+'Program Budget'!R719+'Program Budget'!R793+'Program Budget'!R865+'Program Budget'!R924 -> 13891.5 | O44: ='Program Budget'!T45 -> 24 | P44: ='Program Budget'!S45+'Program Budget'!S186+'Program Budget'!S248+'Program Budget'!S307+'Program Budget'!S376+'Program Budget'!S443+'Program Budget'!S515+'Program Budget'!S590+'Program Budget'!S645+'Program Budget'!S719+'Program Budget'!S793+'Program Budget'!S865+'Program Budget'!S924 -> 1 | Q44: ='Program Budget'!U45+'Program Budget'!U186+'Program Budget'!U248+'Program Budget'!U307+'Program Budget'!U376+'Program Budget'!U443+'Program Budget'!U515+'Program Budget'!U590+'Program Budget'!U645+'Program Budget'!U719+'Program Budget'!U793+'Program Budget'!U865+'Program Budget'!U924 -> 14586.075 | R44: ='Program Budget'!W45 -> 18 | S44: ='Program Budget'!V45+'Program Budget'!V186+'Program Budget'!V248+'Program Budget'!V307+'Program Budget'!V376+'Program Budget'!V443+'Program Budget'!V515+'Program Budget'!V590+'Program Budget'!V645+'Program Budget'!V719+'Program Budget'!V793+'Program Budget'!V865+'Program Budget'!V924 -> 1 | T44: ='Program Budget'!X45+'Program Budget'!X186+'Program Budget'!X248+'Program Budget'!X307+'Program Budget'!X376+'Program Budget'!X443+'Program Budget'!X515+'Program Budget'!X590+'Program Budget'!X645+'Program Budget'!X719+'Program Budget'!X793+'Program Budget'!X865+'Program Budget'!X924 -> 11486.534 | U44: =E44+H44+K44+N44+Q44+T44 -> 68794.109 | V44: =C44+F44+I44+L44+O44+R44 -> 120 | W44: =U44/V44 -> 573.28424
B45: Home Office Support | X45: Average Monthly
B46: ='Program Budget'!D47 -> Senior Vice President of Programs | C46: ='Program Budget'!G47 -> 12 | D46: ='Program Budget'!E47+'Program Budget'!E187+'Program Budget'!E249+'Program Budget'!E308+'Program Budget'!E377+'Program Budget'!E444+'Program Budget'!E516+'Program Budget'!E591+'Program Budget'!E646+'Program Budget'!E720+'Program Budget'!E794+'Program Budget'!E866+'Program Budget'!E925 -> 0.35 | E46: ='Program Budget'!I47 -> 56700 | F46: ='Program Budget'!K47 -> 12 | G46: ='Program Budget'!J47+'Program Budget'!J187+'Program Budget'!J249+'Program Budget'!J308+'Program Budget'!J377+'Program Budget'!J444+'Program Budget'!J516+'Program Budget'!J591+'Program Budget'!J646+'Program Budget'!J720+'Program Budget'!J794+'Program Budget'!J866+'Program Budget'!J925 -> 0.35 | H46: ='Program Budget'!L47 -> 59535 | I46: ='Program Budget'!N47 -> 12 | J46: ='Program Budget'!M47+'Program Budget'!M187+'Program Budget'!M249+'Program Budget'!M308+'Program Budget'!M377+'Program Budget'!M444+'Program Budget'!M516+'Program Budget'!M591+'Program Budget'!M646+'Program Budget'!M720+'Program Budget'!M794+'Program Budget'!M866+'Program Budget'!M925 -> 0.35 | K46: ='Program Budget'!O47 -> 62511.75 | L46: ='Program Budget'!Q47 -> 12 | M46: ='Program Budget'!P47+'Program Budget'!P187+'Program Budget'!P249+'Program Budget'!P308+'Program Budget'!P377+'Program Budget'!P444+'Program Budget'!P516+'Program Budget'!P591+'Program Budget'!P646+'Program Budget'!P720+'Program Budget'!P794+'Program Budget'!P866+'Program Budget'!P925 -> 0.35 | N46: ='Program Budget'!R47 -> 65637.338 | O46: ='Program Budget'!T47 -> 12 | P46: ='Program Budget'!S47+'Program Budget'!S187+'Program Budget'!S249+'Program Budget'!S308+'Program Budget'!S377+'Program Budget'!S444+'Program Budget'!S516+'Program Budget'!S591+'Program Budget'!S646+'Program Budget'!S720+'Program Budget'!S794+'Program Budget'!S866+'Program Budget'!S925 -> 0.35 | Q46: ='Program Budget'!U47 -> 68919.204 | R46: ='Program Budget'!W47 -> 12 | S46: ='Program Budget'!V47+'Program Budget'!V187+'Program Budget'!V249+'Program Budget'!V308+'Program Budget'!V377+'Program Budget'!V444+'Program Budget'!V516+'Program Budget'!V591+'Program Budget'!V646+'Program Budget'!V720+'Program Budget'!V794+'Program Budget'!V866+'Program Budget'!V925 -> 0.35 | T46: ='Program Budget'!X47 -> 72365.165 | U46: =E46+H46+K46+N46+Q46+T46 -> 385668.46 | V46: =C46+F46+I46+L46+O46+R46 -> 72 | W46: =U46/V46 -> 5356.5063 | X46: =(13500+(13500*1.05)+(13500*1.05*1.05)+(13500*1.05*1.05*1.05)+(13500*1.05*1.05*1.05*1.05)+(13500*1.05*1.05*1.05*1.05*1.05))/6 -> 15304.304
B47: ='Program Budget'!D48 -> Program Director | C47: ='Program Budget'!G48 -> 12 | D47: ='Program Budget'!E48+'Program Budget'!E188+'Program Budget'!E250+'Program Budget'!E309+'Program Budget'!E378+'Program Budget'!E445+'Program Budget'!E517+'Program Budget'!E592+'Program Budget'!E647+'Program Budget'!E721+'Program Budget'!E795+'Program Budget'!E867+'Program Budget'!E926 -> 0.9 | E47: ='Program Budget'!I48 -> 135000 | F47: ='Program Budget'!K48 -> 12 | G47: ='Program Budget'!J48+'Program Budget'!J188+'Program Budget'!J250+'Program Budget'!J309+'Program Budget'!J378+'Program Budget'!J445+'Program Budget'!J517+'Program Budget'!J592+'Program Budget'!J647+'Program Budget'!J721+'Program Budget'!J795+'Program Budget'!J867+'Program Budget'!J926 -> 0.9 | H47: ='Program Budget'!L48 -> 141750 | I47: ='Program Budget'!N48 -> 12 | J47: ='Program Budget'!M48+'Program Budget'!M188+'Program Budget'!M250+'Program Budget'!M309+'Program Budget'!M378+'Program Budget'!M445+'Program Budget'!M517+'Program Budget'!M592+'Program Budget'!M647+'Program Budget'!M721+'Program Budget'!M795+'Program Budget'!M867+'Program Budget'!M926 -> 0.9 | K47: ='Program Budget'!O48 -> 148837.5 | L47: ='Program Budget'!Q48 -> 12 | M47: ='Program Budget'!P48+'Program Budget'!P188+'Program Budget'!P250+'Program Budget'!P309+'Program Budget'!P378+'Program Budget'!P445+'Program Budget'!P517+'Program Budget'!P592+'Program Budget'!P647+'Program Budget'!P721+'Program Budget'!P795+'Program Budget'!P867+'Program Budget'!P926 -> 0.9 | N47: ='Program Budget'!R48 -> 156279.38 | O47: ='Program Budget'!T48 -> 12 | P47: ='Program Budget'!S48+'Program Budget'!S188+'Program Budget'!S250+'Program Budget'!S309+'Program Budget'!S378+'Program Budget'!S445+'Program Budget'!S517+'Program Budget'!S592+'Program Budget'!S647+'Program Budget'!S721+'Program Budget'!S795+'Program Budget'!S867+'Program Budget'!S926 -> 0.9 | Q47: ='Program Budget'!U48 -> 164093.34 | R47: ='Program Budget'!W48 -> 12 | S47: ='Program Budget'!V48+'Program Budget'!V188+'Program Budget'!V250+'Program Budget'!V309+'Program Budget'!V378+'Program Budget'!V445+'Program Budget'!V517+'Program Budget'!V592+'Program Budget'!V647+'Program Budget'!V721+'Program Budget'!V795+'Program Budget'!V867+'Program Budget'!V926 -> 0.9 | T47: ='Program Budget'!X48 -> 172298.01 | U47: =E47+H47+K47+N47+Q47+T47 -> 918258.23 | V47: =C47+F47+I47+L47+O47+R47 -> 72 | W47: =U47/V47 -> 12753.587 | X47: =(12500+(12500*1.05)+(12500*1.05*1.05)+(12500*1.05*1.05*1.05)+(12500*1.05*1.05*1.05*1.05)+(12500*1.05*1.05*1.05*1.05*1.05))/6 -> 14170.652
B48: ='Program Budget'!D49 -> Compliance & Contracts Director | C48: ='Program Budget'!G49 -> 12 | D48: ='Program Budget'!E49+'Program Budget'!E189+'Program Budget'!E251+'Program Budget'!E310+'Program Budget'!E379+'Program Budget'!E446+'Program Budget'!E518+'Program Budget'!E593+'Program Budget'!E648+'Program Budget'!E722+'Program Budget'!E796+'Program Budget'!E868+'Program Budget'!E927 -> 0.2 | E48: ='Program Budget'!I49 -> 22000 | F48: ='Program Budget'!K49 -> 12 | G48: ='Program Budget'!J49+'Program Budget'!J189+'Program Budget'!J251+'Program Budget'!J310+'Program Budget'!J379+'Program Budget'!J446+'Program Budget'!J518+'Program Budget'!J593+'Program Budget'!J648+'Program Budget'!J722+'Program Budget'!J796+'Program Budget'!J868+'Program Budget'!J927 -> 0.2 | H48: ='Program Budget'!L49 -> 23100 | I48: ='Program Budget'!N49 -> 12 | J48: ='Program Budget'!M49+'Program Budget'!M189+'Program Budget'!M251+'Program Budget'!M310+'Program Budget'!M379+'Program Budget'!M446+'Program Budget'!M518+'Program Budget'!M593+'Program Budget'!M648+'Program Budget'!M722+'Program Budget'!M796+'Program Budget'!M868+'Program Budget'!M927 -> 0.2 | K48: ='Program Budget'!O49 -> 24255 | L48: ='Program Budget'!Q49 -> 12 | M48: ='Program Budget'!P49+'Program Budget'!P189+'Program Budget'!P251+'Program Budget'!P310+'Program Budget'!P379+'Program Budget'!P446+'Program Budget'!P518+'Program Budget'!P593+'Program Budget'!P648+'Program Budget'!P722+'Program Budget'!P796+'Program Budget'!P868+'Program Budget'!P927 -> 0.2 | N48: ='Program Budget'!R49 -> 25467.75 | O48: ='Program Budget'!T49 -> 12 | P48: ='Program Budget'!S49+'Program Budget'!S189+'Program Budget'!S251+'Program Budget'!S310+'Program Budget'!S379+'Program Budget'!S446+'Program Budget'!S518+'Program Budget'!S593+'Program Budget'!S648+'Program Budget'!S722+'Program Budget'!S796+'Program Budget'!S868+'Program Budget'!S927 -> 0.2 | Q48: ='Program Budget'!U49 -> 26741.138 | R48: ='Program Budget'!W49 -> 12 | S48: ='Program Budget'!V49+'Program Budget'!V189+'Program Budget'!V251+'Program Budget'!V310+'Program Budget'!V379+'Program Budget'!V446+'Program Budget'!V518+'Program Budget'!V593+'Program Budget'!V648+'Program Budget'!V722+'Program Budget'!V796+'Program Budget'!V868+'Program Budget'!V927 -> 0.2 | T48: ='Program Budget'!X49 -> 28078.194 | U48: =E48+H48+K48+N48+Q48+T48 -> 149642.08 | V48: =C48+F48+I48+L48+O48+R48 -> 72 | W48: =U48/V48 -> 2078.3622 | X48: =(9167+(9167*1.05)+(9167*1.05*1.05)+(9167*1.05*1.05*1.05)+(9167*1.05*1.05*1.05*1.05)+(9167*1.05*1.05*1.05*1.05*1.05))/6 -> 10392.189
B49: ='Program Budget'!D50 -> Associate Director | C49: ='Program Budget'!G50 -> 12 | D49: ='Program Budget'!E50+'Program Budget'!E190+'Program Budget'!E252+'Program Budget'!E311+'Program Budget'!E380+'Program Budget'!E447+'Program Budget'!E519+'Program Budget'!E594+'Program Budget'!E649+'Program Budget'!E723+'Program Budget'!E797+'Program Budget'!E869+'Program Budget'!E928 -> 1 | E49: ='Program Budget'!I50 -> 90000 | F49: ='Program Budget'!K50 -> 12 | G49: ='Program Budget'!J50+'Program Budget'!J190+'Program Budget'!J252+'Program Budget'!J311+'Program Budget'!J380+'Program Budget'!J447+'Program Budget'!J519+'Program Budget'!J594+'Program Budget'!J649+'Program Budget'!J723+'Program Budget'!J797+'Program Budget'!J869+'Program Budget'!J928 -> 1 | H49: ='Program Budget'!L50 -> 94500 | I49: ='Program Budget'!N50 -> 12 | J49: ='Program Budget'!M50+'Program Budget'!M190+'Program Budget'!M252+'Program Budget'!M311+'Program Budget'!M380+'Program Budget'!M447+'Program Budget'!M519+'Program Budget'!M594+'Program Budget'!M649+'Program Budget'!M723+'Program Budget'!M797+'Program Budget'!M869+'Program Budget'!M928 -> 1 | K49: ='Program Budget'!O50 -> 99225 | L49: ='Program Budget'!Q50 -> 12 | M49: ='Program Budget'!P50+'Program Budget'!P190+'Program Budget'!P252+'Program Budget'!P311+'Program Budget'!P380+'Program Budget'!P447+'Program Budget'!P519+'Program Budget'!P594+'Program Budget'!P649+'Program Budget'!P723+'Program Budget'!P797+'Program Budget'!P869+'Program Budget'!P928 -> 1 | N49: ='Program Budget'!R50 -> 104186.25 | O49: ='Program Budget'!T50 -> 12 | P49: ='Program Budget'!S50+'Program Budget'!S190+'Program Budget'!S252+'Program Budget'!S311+'Program Budget'!S380+'Program Budget'!S447+'Program Budget'!S519+'Program Budget'!S594+'Program Budget'!S649+'Program Budget'!S723+'Program Budget'!S797+'Program Budget'!S869+'Program Budget'!S928 -> 1 | Q49: ='Program Budget'!U50 -> 109395.56 | R49: ='Program Budget'!W50 -> 12 | S49: ='Program Budget'!V50+'Program Budget'!V190+'Program Budget'!V252+'Program Budget'!V311+'Program Budget'!V380+'Program Budget'!V447+'Program Budget'!V519+'Program Budget'!V594+'Program Budget'!V649+'Program Budget'!V723+'Program Budget'!V797+'Program Budget'!V869+'Program Budget'!V928 -> 1 | T49: ='Program Budget'!X50 -> 114865.34 | U49: =E49+H49+K49+N49+Q49+T49 -> 612172.15 | V49: =C49+F49+I49+L49+O49+R49 -> 72 | W49: =U49/V49 -> 8502.391 | X49: =(7500+(7500*1.05)+(7500*1.05*1.05)+(7500*1.05*1.05*1.05)+(7500*1.05*1.05*1.05*1.05)+(7500*1.05*1.05*1.05*1.05*1.05))/6 -> 8502.391
B50: ='Program Budget'!D51 -> Senior Program Officer | C50: ='Program Budget'!G51 -> 12 | D50: ='Program Budget'!E51+'Program Budget'!E191+'Program Budget'!E253+'Program Budget'!E312+'Program Budget'!E381+'Program Budget'!E448+'Program Budget'!E520+'Program Budget'!E595+'Program Budget'!E650+'Program Budget'!E724+'Program Budget'!E798+'Program Budget'!E870+'Program Budget'!E929 -> 0.2 | E50: ='Program Budget'!I51 -> 14200 | F50: ='Program Budget'!K51 -> 12 | G50: ='Program Budget'!J51+'Program Budget'!J191+'Program Budget'!J253+'Program Budget'!J312+'Program Budget'!J381+'Program Budget'!J448+'Program Budget'!J520+'Program Budget'!J595+'Program Budget'!J650+'Program Budget'!J724+'Program Budget'!J798+'Program Budget'!J870+'Program Budget'!J929 -> 0.05 | H50: ='Program Budget'!L51 -> 3727.5 | I50: ='Program Budget'!N51 -> 12 | J50: ='Program Budget'!M51+'Program Budget'!M191+'Program Budget'!M253+'Program Budget'!M312+'Program Budget'!M381+'Program Budget'!M448+'Program Budget'!M520+'Program Budget'!M595+'Program Budget'!M650+'Program Budget'!M724+'Program Budget'!M798+'Program Budget'!M870+'Program Budget'!M929 -> 0.05 | K50: ='Program Budget'!O51 -> 3913.875 | L50: ='Program Budget'!Q51 -> 12 | M50: ='Program Budget'!P51+'Program Budget'!P191+'Program Budget'!P253+'Program Budget'!P312+'Program Budget'!P381+'Program Budget'!P448+'Program Budget'!P520+'Program Budget'!P595+'Program Budget'!P650+'Program Budget'!P724+'Program Budget'!P798+'Program Budget'!P870+'Program Budget'!P929 -> 0.05 | N50: ='Program Budget'!R51 -> 4109.5688 | O50: ='Program Budget'!T51 -> 12 | P50: ='Program Budget'!S51+'Program Budget'!S191+'Program Budget'!S253+'Program Budget'!S312+'Program Budget'!S381+'Program Budget'!S448+'Program Budget'!S520+'Program Budget'!S595+'Program Budget'!S650+'Program Budget'!S724+'Program Budget'!S798+'Program Budget'!S870+'Program Budget'!S929 -> 0.05 | Q50: ='Program Budget'!U51 -> 4315.0472 | R50: ='Program Budget'!W51 -> 12 | S50: ='Program Budget'!V51+'Program Budget'!V191+'Program Budget'!V253+'Program Budget'!V312+'Program Budget'!V381+'Program Budget'!V448+'Program Budget'!V520+'Program Budget'!V595+'Program Budget'!V650+'Program Budget'!V724+'Program Budget'!V798+'Program Budget'!V870+'Program Budget'!V929 -> 0.2 | T50: ='Program Budget'!X51 -> 18123.198 | U50: =E50+H50+K50+N50+Q50+T50 -> 48389.189 | V50: =C50+F50+I50+L50+O50+R50 -> 72 | W50: =U50/V50 -> 672.07207 | X50: =(5917+(5917*1.05)+(5917*1.05*1.05)+(5917*1.05*1.05*1.05)+(5917*1.05*1.05*1.05*1.05)+(5917*1.05*1.05*1.05*1.05*1.05))/6 -> 6707.8197
B51: Total Personnel | E51: =SUM(E11:E50) -> 952633.33 | H51: =SUM(H11:H50) -> 1298272.5 | K51: =SUM(K11:K50) -> 1374762.4 | N51: =SUM(N11:N50) -> 1452182.7 | Q51: =SUM(Q11:Q50) -> 1513852.3 | T51: =SUM(T11:T50) -> 1241609.2 | U51: =SUM(U11:U50) -> 7833312.4

Sheet LRP Budget Summary
A1: Summary of Local and Regional Procurement Budget
A2: Salaries/Personnel (from Administration) | B2: 0
A3: Benefits (from Administration) | B3: 0
A4: Salaries/Personnel (from ITSH) | B4: ='Personnel & LOE Summary'!U35*0.367625-0.02 -> 34358.713
A5: Benefits (from ITSH) | B5: =B4*'Program Budget'!H56 -> 16581.515
A6: Internal Transportation | B6: 0
A7: Warehouse | B7: 0
A8: Commodity Procurement | B8: ='Program Budget'!Y974+'Program Budget'!Y975+'Program Budget'!Y976 -> 3282393.1
A9: ICR on Administration | B9: =SUM(B2:B3)*20% -> 0
A10: ICR on ITSH | B10: =SUM(B4:B7)*20% -> 10188.046
A11: ICR on Commodity and Food Purchases | B11: =B8*20% -> 656478.62
A12: Total | B12: =SUM(B2:B11) -> 4000000
A13: Percentage of Budget | B13: =B12/40000000 -> 0.1

Sheet LOE Breakdown by Year
B1: Partners of the Americas – FY 2025 McGovern-Dole Honduras
B2: NOFO: USDA-FAS-10.608-0700-25-(522)
B3: Duration: 6 Years
B4: Country: Honduras
B5: Level of Effort (LOE) Breakdown by Activity
D7: Administration | E7: ='USDA Budget Summary'!A27 -> Activity 1: Provide School Meals | F7: ='USDA Budget Summary'!A28 -> Activity 2: Distribution: School Supplies and Materials | G7: ='USDA Budget Summary'!A29 -> Activity 3: Training: Teacher and Administrators | H7: ='USDA Budget Summary'!A30 -> Activity 4: Enrollment Campaigns | I7: ='USDA Budget Summary'!A31 -> Activity 5: Building/Rehabilitation: Wells and Water Stations/Systems | J7: ='USDA Budget Summary'!A32 -> Activity 6: Training: Good Health and Nutrition Practices | K7: ='USDA Budget Summary'!A33 -> Activity 7: Training: Commodity Management | L7: ='USDA Budget Summary'!A34 -> Activity 8: Capacity Building: Local and Regional Level | M7: ='USDA Budget Summary'!A35 -> Activity 9: Capacity Building: National Level | N7: ='USDA Budget Summary'!A36 -> Activity 10: Develop Public-Private Partnerships to Support School Feeding Sustainability | O7: ='USDA Budget Summary'!A37 -> Activity 11: Expand Use of US Commodities in Honduras School Feeding Program | P7: ='Program Budget'!D888 -> Internal Transportation Storage and Handling (ITSH) | Q7: Total LOE
B8: Year 1 | D8: LOE | E8: LOE | F8: LOE | G8: LOE | Q8: LOE
B9: Personnel (Administration)
B10: Honduran National Staff
B11: ='Program Budget'!D12 -> Key Personnel: Chief of Party - Roger Sanchez O’Neill | D11: 1 | E11: 0 | F11: 0 | G11: 0 | H11: 0 | I11: 0 | J11: 0 | K11: 0 | L11: 0 | M11: 0 | N11: 0 | O11: 0 | P11: 0 | Q11: =SUM(D11:P11) -> 1
B12: ='Program Budget'!D13 -> Key Personnel: Deputy Chief of Party - David Medina Mayo | D12: 1 | E12: 0 | F12: 0 | G12: 0 | H12: 0 | I12: 0 | J12: 0 | K12: 0 | L12: 0 | M12: 0 | N12: 0 | O12: 0 | P12: 0 | Q12: =SUM(D12:P12) -> 1
B13: ='Program Budget'!D14 -> Policy & Sustainability Specialist | D13: 0 | E13: 0 | F13: 0 | G13: 0 | H13: 0 | I13: 0 | J13: 0 | K13: 0.1 | L13: 0.2 | M13: 0.3 | N13: 0.3 | O13: 0.1 | P13: 0 | Q13: =SUM(D13:P13) -> 1
B14: ='Program Budget'!D15 -> Education Director | D14: 0 | E14: 0 | F14: 0.1 | G14: 0.2 | H14: 0.2 | I14: 0 | J14: 0.2 | K14: 0 | L14: 0.1 | M14: 0.1 | N14: 0.1 | O14: 0 | P14: 0 | Q14: =SUM(D14:P14) -> 1
B15: ='Program Budget'!D16 -> Education Specialist | D15: 0 | E15: 0 | F15: 0.1 | G15: 0.2 | H15: 0.2 | I15: 0 | J15: 0.2 | K15: 0 | L15: 0.1 | M15: 0.1 | N15: 0.1 | O15: 0 | P15: 0 | Q15: =SUM(D15:P15) -> 1
B16: ='Program Budget'!D17 -> Education Officer | D16: 0 | E16: 0 | F16: 0.1 | G16: 0.2 | H16: 0.2 | I16: 0 | J16: 0.2 | K16: 0 | L16: 0.1 | M16: 0.1 | N16: 0.1 | O16: 0 | P16: 0 | Q16: =SUM(D16:P16) -> 1
B17: ='Program Budget'!D18 -> Nutrition and Health Specialist | D17: 0 | E17: 0.25 | F17: 0 | G17: 0 | H17: 0 | I17: 0.25 | J17: 0.15 | K17: 0.1 | L17: 0.05 | M17: 0.05 | N17: 0.1 | O17: 0.05 | P17: 0 | Q17: =SUM(D17:P17) -> 1
B18: ='Program Budget'!D19 -> Nutrition Officer - (2 Individuals) | D18: 0 | E18: 0.85 | F18: 0 | G18: 0 | H18: 0 | I18: 0 | J18: 0.15 | K18: 0 | L18: 0 | M18: 0 | N18: 0 | O18: 0 | P18: 0 | Q18: =SUM(D18:P18) -> 1
B19: ='Program Budget'!D20 -> School Feeding Specialist | D19: 0 | E19: 0.4 | F19: 0 | G19: 0 | H19: 0 | I19: 0 | J19: 0.15 | K19: 0.25 | L19: 0.05 | M19: 0.05 | N19: 0.05 | O19: 0.05 | P19: 0 | Q19: =SUM(D19:P19) -> 1
B20: ='Program Budget'!D21 -> Food Aid Monitors - (2 Individuals) | D20: 0 | E20: 0.85 | F20: 0 | G20: 0 | H20: 0 | I20: 0 | J20: 0.07 | K20: 0.08 | L20: 0 | M20: 0 | N20: 0 | O20: 0 | P20: 0 | Q20: =SUM(D20:P20) -> 1
B21: ='Program Budget'!D22 -> WASH Officer | D21: 0 | E21: 0 | F21: 0 | G21: 0 | H21: 0 | I21: 1 | J21: 0 | K21: 0 | L21: 0 | M21: 0 | N21: 0 | O21: 0 | P21: 0 | Q21: =SUM(D21:P21) -> 1
B22: ='Program Budget'!D23 -> Communications Specialist | D22: 0.5 | E22: 0 | F22: 0 | G22: 0 | H22: 0.1 | I22: 0 | J22: 0.15 | K22: 0 | L22: 0.1 | M22: 0 | N22: 0.15 | O22: 0 | P22: 0 | Q22: =SUM(D22:P22) -> 1
... B44: ='Program Budget'!D45 -> Driver - (2 Individuals) | D44: 1 | E44: 0 | F44: 0 | G44: 0 | H44: 0 | I44: 0 | J44: 0 | K44: 0 | L44: 0 | M44: 0 | N44: 0 | O44: 0 | P44: 0 | Q44: =SUM(D44:P44) -> 1
B45: Home Office Support
B46: ='Program Budget'!D47 -> Senior Vice President of Programs | D46: 0.35 | Q46: =SUM(D46:O46) -> 0.35
B47: ='Program Budget'!D48 -> Program Director | D47: 0.9 | Q47: =SUM(D47:O47) -> 0.9
B48: ='Program Budget'!D49 -> Compliance & Contracts Director | D48: 0.2 | Q48: =SUM(D48:O48) -> 0.2
B49: ='Program Budget'!D50 -> Associate Director | D49: 1 | Q49: =SUM(D49:O49) -> 1
B50: ='Program Budget'!D51 -> Senior Program Officer | D50: 0.2 | Q50: =SUM(D50:O50) -> 0.2
B51: Total Personnel
D53: =D7 -> Administration | E53: =E7 -> Activity 1: Provide School Meals | F53: =F7 -> Activity 2: Distribution: School Supplies and Materials | G53: =G7 -> Activity 3: Training: Teacher and Administrators | H53: =H7 -> Activity 4: Enrollment Campaigns | I53: =I7 -> Activity 5: Building/Rehabilitation: Wells and Water Stations/Systems | J53: =J7 -> Activity 6: Training: Good Health and Nutrition Practices | K53: =K7 -> Activity 7: Training: Commodity Management | ... P53: =P7 -> Internal Transportation Storage and Handling (ITSH) | Q53: Total LOE
B54: Year 2 | D54: LOE | E54: LOE | F54: LOE | G54: LOE | Q54: LOE
B55: Personnel (Administration)
B56: Honduran National Staff
B57: ='Program Budget'!D12 -> Key Personnel: Chief of Party - Roger Sanchez O’Neill | D57: 1 | E57: 0 | F57: 0 | G57: 0 | H57: 0 | I57: 0 | J57: 0 | K57: 0 | L57: 0 | M57: 0 | N57: 0 | O57: 0 | P57: 0 | Q57: =SUM(D57:P57) -> 1
B58: ='Program Budget'!D13 -> Key Personnel: Deputy Chief of Party - David Medina Mayo | D58: 1 | E58: 0 | F58: 0 | G58: 0 | H58: 0 | I58: 0 | J58: 0 | K58: 0 | L58: 0 | M58: 0 | N58: 0 | O58: 0 | P58: 0 | Q58: =SUM(D58:P58) -> 1
B59: ='Program Budget'!D14 -> Policy & Sustainability Specialist | D59: 0 | E59: 0 | F59: 0 | G59: 0 | H59: 0 | I59: 0 | J59: 0 | K59: 0.1 | L59: 0.2 | M59: 0.3 | N59: 0.3 | O59: 0.1 | P59: 0 | Q59: =SUM(D59:P59) -> 1
B60: ='Program Budget'!D15 -> Education Director | D60: 0 | E60: 0 | F60: 0.1 | G60: 0.2 | H60: 0.2 | I60: 0 | J60: 0.2 | K60: 0 | L60: 0.1 | M60: 0.1 | N60: 0.1 | O60: 0 | P60: 0 | Q60: =SUM(D60:P60) -> 1
B61: ='Program Budget'!D16 -> Education Specialist | D61: 0 | E61: 0 | F61: 0.1 | G61: 0.2 | H61: 0.2 | I61: 0 | J61: 0.2 | K61: 0 | L61: 0.1 | M61: 0.1 | N61: 0.1 | O61: 0 | P61: 0 | Q61: =SUM(D61:P61) -> 1
B62: ='Program Budget'!D17 -> Education Officer | D62: 0 | E62: 0 | F62: 0.1 | G62: 0.2 | H62: 0.2 | I62: 0 | J62: 0.2 | K62: 0 | L62: 0.1 | M62: 0.1 | N62: 0.1 | O62: 0 | P62: 0 | Q62: =SUM(D62:P62) -> 1
B63: ='Program Budget'!D18 -> Nutrition and Health Specialist | D63: 0 | E63: 0.25 | F63: 0 | G63: 0 | H63: 0 | I63: 0.25 | J63: 0.15 | K63: 0.1 | L63: 0.05 | M63: 0.05 | N63: 0.1 | O63: 0.05 | P63: 0 | Q63: =SUM(D63:P63) -> 1
B64: ='Program Budget'!D19 -> Nutrition Officer - (2 Individuals) | D64: 0 | E64: 0.85 | F64: 0 | G64: 0 | H64: 0 | I64: 0 | J64: 0.15 | K64: 0 | L64: 0 | M64: 0 | N64: 0 | O64: 0 | P64: 0 | Q64: =SUM(D64:P64) -> 1
B65: ='Program Budget'!D20 -> School Feeding Specialist | D65: 0 | E65: 0.4 | F65: 0 | G65: 0 | H65: 0 | I65: 0 | J65: 0.15 | K65: 0.25 | L65: 0.05 | M65: 0.05 | N65: 0.05 | O65: 0.05 | P65: 0 | Q65: =SUM(D65:P65) -> 1
B66: ='Program Budget'!D21 -> Food Aid Monitors - (2 Individuals) | D66: 0 | E66: 0.85 | F66: 0 | G66: 0 | H66: 0 | I66: 0 | J66: 0.07 | K66: 0.08 | L66: 0 | M66: 0 | N66: 0 | O66: 0 | P66: 0 | Q66: =SUM(D66:P66) -> 1
B67: ='Program Budget'!D22 -> WASH Officer | D67: 0 | E67: 0 | F67: 0 | G67: 0 | H67: 0 | I67: 1 | J67: 0 | K67: 0 | L67: 0 | M67: 0 | N67: 0 | O67: 0 | P67: 0 | Q67: =SUM(D67:P67) -> 1
B68: ='Program Budget'!D23 -> Communications Specialist | D68: 0.5 | E68: 0 | F68: 0 | G68: 0 | H68: 0.1 | I68: 0 | J68: 0.15 | K68: 0 | L68: 0.1 | M68: 0 | N68: 0.15 | O68: 0 | P68: 0 | Q68: =SUM(D68:P68) -> 1
... B90: ='Program Budget'!D45 -> Driver - (2 Individuals) | D90: 1 | E90: 0 | F90: 0 | G90: 0 | H90: 0 | I90: 0 | J90: 0 | K90: 0 | L90: 0 | M90: 0 | N90: 0 | O90: 0 | P90: 0 | Q90: =SUM(D90:P90) -> 1
B91: Home Office Support
B92: ='Program Budget'!D47 -> Senior Vice President of Programs | D92: 0.35 | Q92: =SUM(D92:O92) -> 0.35
B93: ='Program Budget'!D48 -> Program Director | D93: 0.9 | Q93: =SUM(D93:O93) -> 0.9
B94: ='Program Budget'!D49 -> Compliance & Contracts Director | D94: 0.2 | Q94: =SUM(D94:O94) -> 0.2
B95: ='Program Budget'!D50 -> Associate Director | D95: 1 | Q95: =SUM(D95:O95) -> 1
B96: ='Program Budget'!D51 -> Senior Program Officer | D96: 0.05 | Q96: =SUM(D96:O96) -> 0.05
B97: Total Personnel
D99: =D7 -> Administration | E99: =E7 -> Activity 1: Provide School Meals | F99: =F7 -> Activity 2: Distribution: School Supplies and Materials | G99: =G7 -> Activity 3: Training: Teacher and Administrators | H99: =H7 -> Activity 4: Enrollment Campaigns | I99: =I7 -> Activity 5: Building/Rehabilitation: Wells and Water Stations/Systems | J99: =J7 -> Activity 6: Training: Good Health and Nutrition Practices | K99: =K7 -> Activity 7: Training: Commodity Management | ... P99: =P7 -> Internal Transportation Storage and Handling (ITSH) | Q99: Total LOE
B100: Year 3 | D100: LOE | E100: LOE | F100: LOE | G100: LOE | Q100: LOE
B101: Personnel (Administration)
B102: Honduran National Staff
B103: ='Program Budget'!D12 -> Key Personnel: Chief of Party - Roger Sanchez O’Neill | D103: 1 | E103: 0 | F103: 0 | G103: 0 | H103: 0 | I103: 0 | J103: 0 | K103: 0 | L103: 0 | M103: 0 | N103: 0 | O103: 0 | P103: 0 | Q103: =SUM(D103:P103) -> 1
B104: ='Program Budget'!D13 -> Key Personnel: Deputy Chief of Party - David Medina Mayo | D104: 1 | E104: 0 | F104: 0 | G104: 0 | H104: 0 | I104: 0 | J104: 0 | K104: 0 | L104: 0 | M104: 0 | N104: 0 | O104: 0 | P104: 0 | Q104: =SUM(D104:P104) -> 1
B105: ='Program Budget'!D14 -> Policy & Sustainability Specialist | D105: 0 | E105: 0 | F105: 0 | G105: 0 | H105: 0 | I105: 0 | J105: 0 | K105: 0.1 | L105: 0.2 | M105: 0.3 | N105: 0.3 | O105: 0.1 | P105: 0 | Q105: =SUM(D105:P105) -> 1
B106: ='Program Budget'!D15 -> Education Director | D106: 0 | E106: 0 | F106: 0.1 | G106: 0.2 | H106: 0.2 | I106: 0 | J106: 0.2 | K106: 0 | L106: 0.1 | M106: 0.1 | N106: 0.1 | O106: 0 | P106: 0 | Q106: =SUM(D106:P106) -> 1
B107: ='Program Budget'!D16 -> Education Specialist | D107: 0 | E107: 0 | F107: 0.1 | G107: 0.2 | H107: 0.2 | I107: 0 | J107: 0.2 | K107: 0 | L107: 0.1 | M107: 0.1 | N107: 0.1 | O107: 0 | P107: 0 | Q107: =SUM(D107:P107) -> 1
B108: ='Program Budget'!D17 -> Education Officer | D108: 0 | E108: 0 | F108: 0.1 | G108: 0.2 | H108: 0.2 | I108: 0 | J108: 0.2 | K108: 0 | L108: 0.1 | M108: 0.1 | N108: 0.1 | O108: 0 | P108: 0 | Q108: =SUM(D108:P108) -> 1
B109: ='Program Budget'!D18 -> Nutrition and Health Specialist | D109: 0 | E109: 0.25 | F109: 0 | G109: 0 | H109: 0 | I109: 0.25 | J109: 0.15 | K109: 0.1 | L109: 0.05 | M109: 0.05 | N109: 0.1 | O109: 0.05 | P109: 0 | Q109: =SUM(D109:P109) -> 1
B110: ='Program Budget'!D19 -> Nutrition Officer - (2 Individuals) | D110: 0 | E110: 0.85 | F110: 0 | G110: 0 | H110: 0 | I110: 0 | J110: 0.15 | K110: 0 | L110: 0 | M110: 0 | N110: 0 | O110: 0 | P110: 0 | Q110: =SUM(D110:P110) -> 1
B111: ='Program Budget'!D20 -> School Feeding Specialist | D111: 0 | E111: 0.4 | F111: 0 | G111: 0 | H111: 0 | I111: 0 | J111: 0.15 | K111: 0.25 | L111: 0.05 | M111: 0.05 | N111: 0.05 | O111: 0.05 | P111: 0 | Q111: =SUM(D111:P111) -> 1
B112: ='Program Budget'!D21 -> Food Aid Monitors - (2 Individuals) | D112: 0 | E112: 0.85 | F112: 0 | G112: 0 | H112: 0 | I112: 0 | J112: 0.07 | K112: 0.08 | L112: 0 | M112: 0 | N112: 0 | O112: 0 | P112: 0 | Q112: =SUM(D112:P112) -> 1
B113: ='Program Budget'!D22 -> WASH Officer | D113: 0 | E113: 0 | F113: 0 | G113: 0 | H113: 0 | I113: 1 | J113: 0 | K113: 0 | L113: 0 | M113: 0 | N113: 0 | O113: 0 | P113: 0 | Q113: =SUM(D113:P113) -> 1
B114: ='Program Budget'!D23 -> Communications Specialist | D114: 0.5 | E114: 0 | F114: 0 | G114: 0 | H114: 0.1 | I114: 0 | J114: 0.15 | K114: 0 | L114: 0.1 | M114: 0 | N114: 0.15 | O114: 0 | P114: 0 | Q114: =SUM(D114:P114) -> 1
... B136: ='Program Budget'!D45 -> Driver - (2 Individuals) | D136: 1 | E136: 0 | F136: 0 | G136: 0 | H136: 0 | I136: 0 | J136: 0 | K136: 0 | L136: 0 | M136: 0 | N136: 0 | O136: 0 | P136: 0 | Q136: =SUM(D136:P136) -> 1
B137: Home Office Support
B138: ='Program Budget'!D47 -> Senior Vice President of Programs | D138: 0.35 | Q138: =SUM(D138:O138) -> 0.35
B139: ='Program Budget'!D48 -> Program Director | D139: 0.9 | Q139: =SUM(D139:O139) -> 0.9
B140: ='Program Budget'!D49 -> Compliance & Contracts Director | D140: 0.2 | Q140: =SUM(D140:O140) -> 0.2
B141: ='Program Budget'!D50 -> Associate Director | D141: 1 | Q141: =SUM(D141:O141) -> 1
B142: ='Program Budget'!D51 -> Senior Program Officer | D142: 0.05 | Q142: =SUM(D142:O142) -> 0.05
B143: Total Personnel
D145: =D7 -> Administration | E145: =E7 -> Activity 1: Provide School Meals | F145: =F7 -> Activity 2: Distribution: School Supplies and Materials | G145: =G7 -> Activity 3: Training: Teacher and Administrators | H145: =H7 -> Activity 4: Enrollment Campaigns | I145: =I7 -> Activity 5: Building/Rehabilitation: Wells and Water Stations/Systems | J145: =J7 -> Activity 6: Training: Good Health and Nutrition Practices | K145: =K7 -> Activity 7: Training: Commodity Management | ... P145: =P7 -> Internal Transportation Storage and Handling (ITSH) | Q145: Total LOE
B146: Year 4 | D146: LOE | E146: LOE | F146: LOE | G146: LOE | Q146: LOE
B147: Personnel (Administration)
B148: Honduran National Staff
B149: ='Program Budget'!D12 -> Key Personnel: Chief of Party - Roger Sanchez O’Neill | D149: 1 | E149: 0 | F149: 0 | G149: 0 | H149: 0 | I149: 0 | J149: 0 | K149: 0 | L149: 0 | M149: 0 | N149: 0 | O149: 0 | P149: 0 | Q149: =SUM(D149:P149) -> 1
B150: ='Program Budget'!D13 -> Key Personnel: Deputy Chief of Party - David Medina Mayo | D150: 1 | E150: 0 | F150: 0 | G150: 0 | H150: 0 | I150: 0 | J150: 0 | K150: 0 | L150: 0 | M150: 0 | N150: 0 | O150: 0 | P150: 0 | Q150: =SUM(D150:P150) -> 1
B151: ='Program Budget'!D14 -> Policy & Sustainability Specialist | D151: 0 | E151: 0 | F151: 0 | G151: 0 | H151: 0 | I151: 0 | J151: 0 | K151: 0.1 | L151: 0.2 | M151: 0.3 | N151: 0.3 | O151: 0.1 | P151: 0 | Q151: =SUM(D151:P151) -> 1
B152: ='Program Budget'!D15 -> Education Director | D152: 0 | E152: 0 | F152: 0.1 | G152: 0.2 | H152: 0.2 | I152: 0 | J152: 0.2 | K152: 0 | L152: 0.1 | M152: 0.1 | N152: 0.1 | O152: 0 | P152: 0 | Q152: =SUM(D152:P152) -> 1
B153: ='Program Budget'!D16 -> Education Specialist | D153: 0 | E153: 0 | F153: 0.1 | G153: 0.2 | H153: 0.2 | I153: 0 | J153: 0.2 | K153: 0 | L153: 0.1 | M153: 0.1 | N153: 0.1 | O153: 0 | P153: 0 | Q153: =SUM(D153:P153) -> 1
B154: ='Program Budget'!D17 -> Education Officer | D154: 0 | E154: 0 | F154: 0.1 | G154: 0.2 | H154: 0.2 | I154: 0 | J154: 0.2 | K154: 0 | L154: 0.1 | M154: 0.1 | N154: 0.1 | O154: 0 | P154: 0 | Q154: =SUM(D154:P154) -> 1
B155: ='Program Budget'!D18 -> Nutrition and Health Specialist | D155: 0 | E155: 0.25 | F155: 0 | G155: 0 | H155: 0 | I155: 0.25 | J155: 0.15 | K155: 0.1 | L155: 0.05 | M155: 0.05 | N155: 0.1 | O155: 0.05 | P155: 0 | Q155: =SUM(D155:P155) -> 1
B156: ='Program Budget'!D19 -> Nutrition Officer - (2 Individuals) | D156: 0 | E156: 0.85 | F156: 0 | G156: 0 | H156: 0 | I156: 0 | J156: 0.15 | K156: 0 | L156: 0 | M156: 0 | N156: 0 | O156: 0 | P156: 0 | Q156: =SUM(D156:P156) -> 1
B157: ='Program Budget'!D20 -> School Feeding Specialist | D157: 0 | E157: 0.4 | F157: 0 | G157: 0 | H157: 0 | I157: 0 | J157: 0.15 | K157: 0.25 | L157: 0.05 | M157: 0.05 | N157: 0.05 | O157: 0.05 | P157: 0 | Q157: =SUM(D157:P157) -> 1
B158: ='Program Budget'!D21 -> Food Aid Monitors - (2 Individuals) | D158: 0 | E158: 0.85 | F158: 0 | G158: 0 | H158: 0 | I158: 0 | J158: 0.07 | K158: 0.08 | L158: 0 | M158: 0 | N158: 0 | O158: 0 | P158: 0 | Q158: =SUM(D158:P158) -> 1
B159: ='Program Budget'!D22 -> WASH Officer | D159: 0 | E159: 0 | F159: 0 | G159: 0 | H159: 0 | I159: 1 | J159: 0 | K159: 0 | L159: 0 | M159: 0 | N159: 0 | O159: 0 | P159: 0 | Q159: =SUM(D159:P159) -> 1
B160: ='Program Budget'!D23 -> Communications Specialist | D160: 0.5 | E160: 0 | F160: 0 | G160: 0 | H160: 0.1 | I160: 0 | J160: 0.15 | K160: 0 | L160: 0.1 | M160: 0 | N160: 0.15 | O160: 0 | P160: 0 | Q160: =SUM(D160:P160) -> 1
... B182: ='Program Budget'!D45 -> Driver - (2 Individuals) | D182: 1 | E182: 0 | F182: 0 | G182: 0 | H182: 0 | I182: 0 | J182: 0 | K182: 0 | L182: 0 | M182: 0 | N182: 0 | O182: 0 | P182: 0 | Q182: =SUM(D182:P182) -> 1
B183: Home Office Support
B184: ='Program Budget'!D47 -> Senior Vice President of Programs | D184: 0.35 | Q184: =SUM(D184:O184) -> 0.35
B185: ='Program Budget'!D48 -> Program Director | D185: 0.9 | Q185: =SUM(D185:O185) -> 0.9
B186: ='Program Budget'!D49 -> Compliance & Contracts Director | D186: 0.2 | Q186: =SUM(D186:O186) -> 0.2
B187: ='Program Budget'!D50 -> Associate Director | D187: 1 | Q187: =SUM(D187:O187) -> 1
B188: ='Program Budget'!D51 -> Senior Program Officer | D188: 0.05 | Q188: =SUM(D188:O188) -> 0.05
...

Sheet Indirect Calculations
B1: Partners of the Americas – FY 2025 McGovern-Dole Honduras
B2: NOFO: USDA-FAS-10.608-0700-25-(522)
B3: Duration: 6 Years
B4: Country: Honduras
B5: Summary of Indirect Cost Rates Applied
B7: BUDGET ITEM | C7: RATE/ UNIT | D7: YEAR 1 | E7: YEAR 2 | F7: YEAR 3 | G7: YEAR 4 | H7: YEAR 5 | I7: YEAR 6 | J7: TOTAL USDA
B8: Administration Salaries/Personnel
B9: Total Personnel | D9: ='Program Budget'!I53 -> 683383.33 | E9: ='Program Budget'!L53 -> 843622.5 | F9: ='Program Budget'!O53 -> 885803.62 | G9: ='Program Budget'!R53 -> 930093.81 | H9: ='Program Budget'!U53 -> 976598.5 | I9: ='Program Budget'!X53 -> 966996 | J9: =SUM(D9:I9) -> 5286497.8
B10: Administration Fringe Benefits
B11: Total Fringe Benefits | D11: ='Program Budget'!I59 -> 250993.39 | E11: ='Program Budget'!L59 -> 327156.58 | F11: ='Program Budget'!O59 -> 343514.41 | G11: ='Program Budget'!R59 -> 360690.13 | H11: ='Program Budget'!U59 -> 378724.64 | I11: ='Program Budget'!X59 -> 366091.82 | J11: =SUM(D11:I11) -> 2027171
B12: Administration Travel
B13: Total Travel | D13: ='Program Budget'!I80 -> 52551.6 | E13: ='Program Budget'!L80 -> 57447.18 | F13: ='Program Budget'!O80 -> 60319.539 | G13: ='Program Budget'!R80 -> 63335.516 | H13: ='Program Budget'!U80 -> 66502.292 | I13: ='Program Budget'!X80 -> 68602.176 | J13: =SUM(D13:I13) -> 368758.3
B14: Administration Professional Services/Contractual
B15: Total Professional Services/Contractual | D15: ='Program Budget'!I101 -> 361800 | E15: ='Program Budget'!L101 -> 46500 | F15: ='Program Budget'!O101 -> 331500 | G15: ='Program Budget'!R101 -> 109000 | H15: ='Program Budget'!U101 -> 46500 | I15: ='Program Budget'!X101 -> 221500 | J15: =SUM(D15:I15) -> 1116800
B16: Administration Equipment
B17: Total Equipment | D17: ='Program Budget'!I106 -> 53000 | E17: ='Program Budget'!L106 -> 0 | F17: ='Program Budget'!O106 -> 0 | G17: ='Program Budget'!R106 -> 0 | H17: ='Program Budget'!U106 -> 0 | I17: ='Program Budget'!X106 -> 0 | J17: =SUM(D17:I17) -> 53000
B18: Administration Office Supplies
B19: Total Office Supplies | D19: ='Program Budget'!I121 -> 63198.365 | E19: ='Program Budget'!L121 -> 3780 | F19: ='Program Budget'!O121 -> 3969 | G19: ='Program Budget'!R121 -> 4167.45 | H19: ='Program Budget'!U121 -> 4375.8225 | I19: ='Program Budget'!X121 -> 2700 | J19: =SUM(D19:I19) -> 82190.637
B20: Administration Other
B21: Total Other | D21: ='Program Budget'!I148 -> 81154 | E21: ='Program Budget'!L148 -> 107642.1 | F21: ='Program Budget'!O148 -> 112724.21 | G21: ='Program Budget'!R148 -> 118060.42 | H21: ='Program Budget'!U148 -> 123663.44 | I21: ='Program Budget'!X148 -> 103575.35 | J21: =SUM(D21:I21) -> 646819.51
B22: Total Administration Direct Costs | D22: =SUM(D9:D21) -> 1546080.7 | E22: =SUM(E9:E21) -> 1386148.4 | F22: =SUM(F9:F21) -> 1737830.8 | G22: =SUM(G9:G21) -> 1585347.3 | H22: =SUM(H9:H21) -> 1596364.7 | I22: =SUM(I9:I21) -> 1729465.4 | J22: =SUM(J9:J21) -> 9581237.2
B24: Total Indirect Costs (NICRA) on Administration | C24: 0.2 | D24: =D22*$C$24 -> 309216.14 | E24: =E22*$C$24 -> 277229.67 | F24: =F22*$C$24 -> 347566.16 | G24: =G22*$C$24 -> 317069.46 | H24: =H22*$C$24 -> 319272.94 | I24: =I22*$C$24 -> 345893.07 | J24: =SUM(D24:I24) -> 1916247.4
B26: TOTAL ADMINISTRATION INDIRECT COSTS | D26: =D24 -> 309216.14 | E26: =E24 -> 277229.67 | F26: =F24 -> 347566.16 | G26: =G24 -> 317069.46 | H26: =H24 -> 319272.94 | I26: =I24 -> 345893.07 | J26: =J24 -> 1916247.4
B28: ='USDA Budget Summary'!A27 -> Activity 1: Provide School Meals
B29: Total Activity 1 | D29: ='Program Budget'!I210 -> 52126.455 | E29: ='Program Budget'!L210 -> 129858.26 | F29: ='Program Budget'!O210 -> 134351.18 | G29: ='Program Budget'!R210 -> 139068.74 | H29: ='Program Budget'!U210 -> 137534.58 | I29: ='Program Budget'!X210 -> 66036.893 | J29: =SUM(D29:I29) -> 658976.11 | K29: =J29*20% -> 131795.22
B30: ='USDA Budget Summary'!A28 -> Activity 2: Distribution: School Supplies and Materials | K30: =J30*20% -> 0
B31: Total Activity 2 | D31: ='Program Budget'!I269 -> 62399.945 | E31: ='Program Budget'!L269 -> 141822.05 | F31: ='Program Budget'!O269 -> 80257.649 | G31: ='Program Budget'!R269 -> 81485.732 | H31: ='Program Budget'!U269 -> 27079.218 | I31: ='Program Budget'!X269 -> 14098.585 | J31: =SUM(D31:I31) -> 407143.18 | K31: =J31*20% -> 81428.635
B32: ='USDA Budget Summary'!A29 -> Activity 3: Training: Teacher and Administrators | K32: =J32*20% -> 0
B33: Total Activity 3 | D33: ='Program Budget'!I338 -> 157489.6 | E33: ='Program Budget'!L338 -> 648382.77 | F33: ='Program Budget'!O338 -> 679006.61 | G33: ='Program Budget'!R338 -> 711161.64 | H33: ='Program Budget'!U338 -> 149464.67 | I33: ='Program Budget'!X338 -> 55209.903 | J33: =SUM(D33:I33) -> 2400715.2 | K33: =J33*20% -> 480143.04
B34: ='USDA Budget Summary'!A30 -> Activity 4: Enrollment Campaigns | K34: =J34*20% -> 0
B35: Total Activity 4 | D35: ='Program Budget'!I405 -> 44451.43 | E35: ='Program Budget'!L405 -> 148743.76 | F35: ='Program Budget'!O405 -> 150920.95 | G35: ='Program Budget'!R405 -> 147806.99 | H35: ='Program Budget'!U405 -> 89297.015 | I35: ='Program Budget'!X405 -> 48374.343 | J35: =SUM(D35:I35) -> 629594.49 | K35: =J35*20% -> 125918.9
B36: ='USDA Budget Summary'!A31 -> Activity 5: Building/Rehabilitation: Wells and Water Stations/Systems | K36: =J36*20% -> 0
B37: Total Activity 5 | D37: ='Program Budget'!I477 -> 41348.835 | E37: ='Program Budget'!L477 -> 138033.31 | F37: ='Program Budget'!O477 -> 139826.18 | G37: ='Program Budget'!R477 -> 91608.685 | H37: ='Program Budget'!U477 -> 93585.32 | I37: ='Program Budget'!X477 -> 16313.852 | J37: =SUM(D37:I37) -> 520716.18 | K37: =J37*20% -> 104143.24
B38: ='USDA Budget Summary'!A32 -> Activity 6: Training: Good Health and Nutrition Practices | K38: =J38*20% -> 0
B39: Total Activity 6 | D39: ='Program Budget'!I552 -> 109129.63 | E39: ='Program Budget'!L552 -> 270235.55 | F39: ='Program Budget'!O552 -> 269108.93 | G39: ='Program Budget'!R552 -> 254598 | H39: ='Program Budget'!U552 -> 107967.62 | I39: ='Program Budget'!X552 -> 45827.385 | J39: =SUM(D39:I39) -> 1056867.1 | K39: =J39*20% -> 211373.42
B40: ='USDA Budget Summary'!A33 -> Activity 7: Training: Commodity Management | K40: =J40*20% -> 0
B41: Total Activity 7 | D41: ='Program Budget'!I607 -> 72676.053 | E41: ='Program Budget'!L607 -> 81153.011 | F41: ='Program Budget'!O607 -> 83801.956 | G41: ='Program Budget'!R607 -> 86154.275 | H41: ='Program Budget'!U607 -> 20782.242 | I41: ='Program Budget'!X607 -> 13001.411 | J41: =SUM(D41:I41) -> 357568.95 | K41: =J41*20% -> 71513.79
B42: ='USDA Budget Summary'!A34 -> Activity 8: Capacity Building: Local and Regional Level | K42: =J42*20% -> 0
B43: Total Activity 8 | D43: ='Program Budget'!I681 -> 39028.915 | E43: ='Program Budget'!L681 -> 129877.18 | F43: ='Program Budget'!O681 -> 63833.413 | G43: ='Program Budget'!R681 -> 53315.026 | H43: ='Program Budget'!U681 -> 54635.328 | I43: ='Program Budget'!X681 -> 25180.055 | J43: =SUM(D43:I43) -> 365869.91 | K43: =J43*20% -> 73173.983
B44: ='USDA Budget Summary'!A35 -> Activity 9: Capacity Building: National Level | K44: =J44*20% -> 0
B45: Total Activity 9 | D45: ='Program Budget'!I755 -> 61457.735 | E45: ='Program Budget'!L755 -> 72186.142 | F45: ='Program Budget'!O755 -> 96599.334 | G45: ='Program Budget'!R755 -> 71745.964 | H45: ='Program Budget'!U755 -> 68592.312 | I45: ='Program Budget'!X755 -> 55273.413 | J45: =SUM(D45:I45) -> 425854.9 | K45: =J45*20% -> 85170.98
B46: ='USDA Budget Summary'!A36 -> Activity 10: Develop Public-Private Partnerships to Support School Feeding Sustainability | K46: =J46*20% -> 0
B47: Total Activity 10 | D47: ='Program Budget'!I827 -> 58721.75 | E47: ='Program Budget'!L827 -> 72737.396 | F47: ='Program Budget'!O827 -> 93384.125 | G47: ='Program Budget'!R827 -> 98028.601 | H47: ='Program Budget'!U827 -> 100774.08 | I47: ='Program Budget'!X827 -> 39289.962 | J47: =SUM(D47:I47) -> 462935.92 | K47: =J47*20% -> 92587.183
B48: ='USDA Budget Summary'!A37 -> Activity 11: Expand Use of US Commodities in Honduras School Feeding Program | K48: =J48*20% -> 0
B49: Total Activity 11 | D49: ='Program Budget'!I886 -> 8878.43 | E49: ='Program Budget'!L886 -> 13670.013 | F49: ='Program Budget'!O886 -> 17349.808 | G49: ='Program Budget'!R886 -> 18160.52 | H49: ='Program Budget'!U886 -> 18257.597 | I49: ='Program Budget'!X886 -> 13012.295 | J49: =SUM(D49:I49) -> 89328.663 | K49: =J49*20% -> 17865.733
B50: Total Activities Direct Costs | D50: =SUM(D29:D49) -> 707708.77 | E50: =SUM(E29:E49) -> 1846699.4 | F50: =SUM(F29:F49) -> 1808440.1 | G50: =SUM(G29:G49) -> 1753134.2 | H50: =SUM(H29:H49) -> 867969.98 | I50: =SUM(I29:I49) -> 391618.1 | J50: =SUM(J29:J49) -> 7375570.6
B52: Total Indirect Costs (NICRA) on Activities | C52: 0.2 | D52: =D50*$C$52 -> 141541.75 | E52: =(E50)*$C$52 -> 369339.89 | F52: =F50*$C$52 -> 361688.03 | G52: =G50*$C$52 -> 350626.83 | H52: =H50*$C$52 -> 173594 | I52: =I50*$C$52 -> 78323.619 | J52: =SUM(D52:I52) -> 1475114.1
B54: TOTAL ACTIVITIES INDIRECT COSTS | D54: =D52 -> 141541.75 | E54: =E52 -> 369339.89 | F54: =F52 -> 361688.03 | G54: =G52 -> 350626.83 | H54: =H52 -> 173594 | I54: =I52 -> 78323.619 | J54: =J52 -> 1475114.1
B56: Total Internal Transportation Storage and Handling (ITSH) | D56: ='Program Budget'!I969 -> 442612.24 | E56: ='Program Budget'!L969 -> 466641.15 | F56: ='Program Budget'!O969 -> 473444.45 | G56: ='Program Budget'!R969 -> 486887.93 | H56: ='Program Budget'!U969 -> 501003.57 | I56: ='Program Budget'!X969 -> 332043.13 | J56: =SUM(D56:H56) -> 2370589.3
B58: Total Indirect Costs (NICRA) on ITSH | C58: 0.2 | D58: =D56*$C$58 -> 88522.448 | E58: =E56*$C$58 -> 93328.229 | F58: =F56*$C$58 -> 94688.891 | G58: =G56*$C$58 -> 97377.585 | H58: =H56*$C$58 -> 100200.71 | I58: =I56*$C$58 -> 66408.626 | J58: =SUM(D58:I58) -> 540526.49
B60: TOTAL ITSH | D60: =D58 -> 88522.448 | E60: =E58 -> 93328.229 | F60: =F58 -> 94688.891 | G60: =G58 -> 97377.585 | H60: =H58 -> 100200.71 | I60: =I58 -> 66408.626 | J60: =J58 -> 540526.49
B62: Total Commodity Procurement | D62: ='Program Budget'!I978 -> 484933.33 | E62: ='Program Budget'!L978 -> 509180 | F62: ='Program Budget'!O978 -> 534639 | G62: ='Program Budget'!R978 -> 561370.95 | H62: ='Program Budget'!U978 -> 589439.5 | I62: ='Program Budget'!X978 -> 602830.32 | J62: =SUM(D62:H62) -> 2679562.8
B64: Total Indirect Costs (NICRA) on Commodity Procurement | C64: 0.2 | D64: =D62*$C$58 -> 96986.667 | E64: =E62*$C$58 -> 101836 | F64: =F62*$C$58 -> 106927.8 | G64: =G62*$C$58 -> 112274.19 | H64: =H62*$C$58 -> 117887.9 | I64: =I62*$C$58 -> 120566.06 | J64: =SUM(D64:I64) -> 656478.62
B66: TOTAL Commodity Procurement | D66: =D64 -> 96986.667 | E66: =E64 -> 101836 | F66: =F64 -> 106927.8 | G66: =G64 -> 112274.19 | H66: =H64 -> 117887.9 | I66: =I64 -> 120566.06 | J66: =J64 -> 656478.62
B68: TOTAL INDIRECT COSTS | D68: =D54+D26+D60+D66 -> 636267.01 | E68: =E54+E26+E60+E66 -> 841733.79 | F68: =F54+F26+F60+F66 -> 910870.87 | G68: =G54+G26+G60+G66 -> 877348.07 | H68: =H54+H26+H60+H66 -> 710955.55 | I68: =I54+I26+I60+I66 -> 611191.38 | J68: =J54+J26+J60+J66 -> 4588366.7

Sheet Commodity Calculator
A1: FY2025 COMMODITY CALCULATION WORKSHEET
C2: Country | E2: Submission Date | G2: PVO | O2: Program Year | Q2: Inland Rate
C3: Honduras | O3: 2025 | Q3: 150
C5: METRIC TONNAGE (MT) | G5: COMMODITY & FREIGHT (C&F) COSTS | O5: PROGRAM SUMMARY
C6: =SUM(D13:D20) -> 8780 | D6: DD MT Total | G6: =SUM(S13:S22) -> 11198784 | H6: DD C&F Total | O6: =G10 -> 11198784 | P6: Total C&F (000s)
C7: =C6/C10 -> 1 | D7: % DD | P7: Section 202(e) (000s)
C8: =SUM(D23:D28) -> 0 | D8: Monet MT Total | G8: =SUM(S23:S29) -> 0 | H8: Monet C&F Total (000s) | O8: =O7/O10 -> 0 | P8: % Section 202(e)
C9: =C8/C10 -> 0 | D9: % Monet | P9: ITSH (000s)
C10: =C6+C8 -> 8780 | D10: TOTAL MT | G10: =SUM(S13:S29) -> 11198784 | H10: TOTAL C&F (000s) | O10: =O6+O7+O9 -> 11198784 | P10: TOTAL PROGRAM COST (000s)
B12: Line | C12: Commodity | D12: MT | E12: Commodity Type | F12: FY Funding Source | G12: Inland Rate ($/MT) | H12: Inland Value | I12: Ocean Rate ($/MT) | J12: Ocean Value | K12: Fumigation Rate ($/MT) | L12: Fumigation Value | M12: Inspection Surveyor Rate ($/MT) | N12: Inspection Surveyor Value | O12: Total Trans (000s) | P12: Commodity Price ($/MT) | Q12: Commodity Value | R12: Warehousing | S12: Estimated Total Com and Frt (000s)
A13: Direct Distribution (DD) | B13: 1 | C13: Fortified Rice | D13: 1500 | E13: Packaged | F13: =IF(C13<>0,$O$3,0) -> 2025 | G13: 65 | H13: =(D13*G13) -> 97500 | I13: 190 | J13: =(I13*D13) -> 285000 | K13: 25 | L13: =K13*D13 -> 37500 | M13: 6 | N13: =M13*D13 -> 9000 | O13: =H13+J13+L13+N13 -> 429000 | P13: 675 | Q13: =(D13*P13) -> 1012500 | R13: =SUM((((D13*950)/50)*0.2)*11) -> 62700 | S13: =H13+J13+Q13+R13+L13+N13 -> 1504200
B14: 2 | C14: Oil | D14: 390 | E14: Bulk | F14: =IF(C14<>0,$O$3,0) -> 2025 | G14: 65 | H14: =(D14*G14) -> 25350 | I14: 190 | J14: =(I14*D14) -> 74100 | K14: 25 | L14: =K14*D14 -> 9750 | M14: 6 | N14: =M14*D14 -> 2340 | O14: =H14+J14+L14+N14 -> 111540 | P14: 2100 | Q14: =(D14*P14) -> 819000 | R14: =SUM((((D14*950)/50)*0.2)*11) -> 16302 | S14: =H14+J14+Q14+R14+L14+N14 -> 946842
B15: 3 | C15: Red Beans | D15: 1710 | E15: Packaged | F15: =IF(C15<>0,$O$3,0) -> 2025 | G15: 65 | H15: =(D15*G15) -> 111150 | I15: 190 | J15: =(I15*D15) -> 324900 | K15: 25 | L15: =K15*D15 -> 42750 | M15: 6 | N15: =M15*D15 -> 10260 | O15: =H15+J15+L15+N15 -> 489060 | P15: 1320 | Q15: =(D15*P15) -> 2257200 | R15: =SUM((((D15*950)/50)*0.2)*11) -> 71478 | S15: =H15+J15+Q15+R15+L15+N15 -> 2817738
B16: 4 | C16: Corn | D16: 1080 | E16: Packaged | F16: =IF(C16<>0,$O$3,0) -> 2025 | G16: 65 | H16: =(D16*G16) -> 70200 | I16: 190 | J16: =(I16*D16) -> 205200 | K16: 25 | L16: =K16*D16 -> 27000 | M16: 6 | N16: =M16*D16 -> 6480 | O16: =H16+J16+L16+N16 -> 308880 | P16: 350 | Q16: =(D16*P16) -> 378000 | R16: =SUM((((D16*950)/50)*0.2)*11) -> 45144 | S16: =H16+J16+Q16+R16+L16+N16 -> 732024
B17: 5 | C17: CSB+ | D17: 4100 | E17: Bulk | F17: =IF(C17<>0,$O$3,0) -> 2025 | G17: 65 | H17: =(D17*G17) -> 266500 | I17: 190 | J17: =(I17*D17) -> 779000 | K17: 25 | L17: =K17*D17 -> 102500 | M17: 6 | N17: =M17*D17 -> 24600 | O17: =H17+J17+L17+N17 -> 1172600 | P17: 940 | Q17: =(D17*P17) -> 3854000 | R17: =SUM((((D17*950)/50)*0.2)*11) -> 171380 | S17: =H17+J17+Q17+R17+L17+N17 -> 5197980
B18: 6 | C18: Egg | D18: ='Program Budget'!G978+'Program Budget'!K978+'Program Budget'!N978+'Program Budget'!Q978+'Program Budget'!T978+'Program Budget'!W978 -> 0 | E18: Bulk | F18: =IF(C18<>0,$O$3,0) -> 2025 | G18: 0 | H18: =(D18*G18)/1000 -> 0 | I18: 0 | J18: =(I18*D18) -> 0 | K18: 0 | L18: =K18*D18 -> 0 | M18: 0 | N18: =M18*D18 -> 0 | O18: =H18+J18+L18+N18 -> 0 | P18: 1760 | Q18: =(D18*P18) -> 0 | R18: 0 | S18: =H18+J18+Q18+R18+L18+N18 -> 0
B19: 7 | C19: Fruits | D19: ='Program Budget'!G979+'Program Budget'!K979+'Program Budget'!N979+'Program Budget'!Q979+'Program Budget'!T979+'Program Budget'!W979 -> 0 | E19: Bulk | F19: =IF(C19<>0,$O$3,0) -> 2025 | G19: 0 | H19: =(D19*G19)/1000 -> 0 | I19: 0 | J19: =(I19*D19) -> 0 | K19: 0 | L19: =K19*D19 -> 0 | M19: 0 | N19: =M19*D19 -> 0 | O19: =H19+J19+L19+N19 -> 0 | P19: 630 | Q19: =(D19*P19) -> 0 | R19: 0 | S19: =H19+J19+Q19+R19+L19+N19 -> 0
B20: 8 | C20: Veggies | D20: ='Program Budget'!G980+'Program Budget'!K980+'Program Budget'!N980+'Program Budget'!Q980+'Program Budget'!T980+'Program Budget'!W980 -> 0 | E20: Bulk | F20: =IF(C20<>0,$O$3,0) -> 2025 | G20: 0 | H20: =(D20*G20)/1000 -> 0 | I20: 0 | J20: =(I20*D20) -> 0 | K20: 0 | L20: =K20*D20 -> 0 | M20: 0 | N20: =M20*D20 -> 0 | O20: =H20+J20+L20+N20 -> 0 | P20: 630 | Q20: =(D20*P20) -> 0 | R20: 0 | S20: =H20+J20+Q20+R20+L20+N20 -> 0
B21: 9 | E21: 0 | F21: =IF(C21<>0,$O$3,0) -> 0
B22: 10 | C22: BAGS, WOVEN POLYPROPYLENE- 50 KG 100752 | E22: 0 | F22: =IF(C22<>0,$O$3,0) -> 2025
B23: 11 | E23: 0 | F23: =IF(C23<>0,$O$3,0) -> 0 | G23: =IF(D23<>0,$Q$3,0) -> 0 | H23: =(D23*G23)/1000 -> 0 | I23: 0 | J23: =(I23*D23)/1000 -> 0 | K23: {=IF(F23<>0,INDEX('[49]Ocean Freight Rates'!$C$3:$E$188,MATCH($C$3,'[49]Ocean Freight Rates'!$B$3:$B$188),MATCH(X23,'[49]Ocean Freight Rates'!$C$2:$E$2,)),0)} -> 0 | L23: =K23*D23 -> 0 | M23: {=IF(H23<>0,INDEX('[49]Ocean Freight Rates'!$C$3:$E$188,MATCH($C$3,'[49]Ocean Freight Rates'!$B$3:$B$188),MATCH(Z23,'[49]Ocean Freight Rates'!$C$2:$E$2,)),0)} -> 0 | N23: =M23*D23 -> 0 | O23: =H23+J23+L23+N23 -> 0 | P23: 0 | Q23: =(D23*P23)/1000 -> 0 | S23: =H23+J23+Q23 -> 0
B24: 12 | E24: 0 | F24: =IF(C24<>0,$O$3,0) -> 0 | G24: =IF(D24<>0,$Q$3,0) -> 0 | H24: =(D24*G24)/1000 -> 0 | I24: 0 | J24: =(I24*D24)/1000 -> 0 | K24: {=IF(F24<>0,INDEX('[49]Ocean Freight Rates'!$C$3:$E$188,MATCH($C$3,'[49]Ocean Freight Rates'!$B$3:$B$188),MATCH(X24,'[49]Ocean Freight Rates'!$C$2:$E$2,)),0)} -> 0 | L24: =K24*D24 -> 0 | M24: {=IF(H24<>0,INDEX('[49]Ocean Freight Rates'!$C$3:$E$188,MATCH($C$3,'[49]Ocean Freight Rates'!$B$3:$B$188),MATCH(Z24,'[49]Ocean Freight Rates'!$C$2:$E$2,)),0)} -> 0 | N24: =M24*D24 -> 0 | O24: =H24+J24+L24+N24 -> 0 | P24: 0 | Q24: =(D24*P24)/1000 -> 0 | S24: =H24+J24+Q24 -> 0
B25: 13 | E25: 0 | F25: =IF(C25<>0,$O$3,0) -> 0 | G25: =IF(D25<>0,$Q$3,0) -> 0 | H25: =(D25*G25)/1000 -> 0 | I25: 0 | J25: =(I25*D25)/1000 -> 0 | K25: {=IF(F25<>0,INDEX('[49]Ocean Freight Rates'!$C$3:$E$188,MATCH($C$3,'[49]Ocean Freight Rates'!$B$3:$B$188),MATCH(X25,'[49]Ocean Freight Rates'!$C$2:$E$2,)),0)} -> 0 | L25: =K25*D25 -> 0 | M25: {=IF(H25<>0,INDEX('[49]Ocean Freight Rates'!$C$3:$E$188,MATCH($C$3,'[49]Ocean Freight Rates'!$B$3:$B$188),MATCH(Z25,'[49]Ocean Freight Rates'!$C$2:$E$2,)),0)} -> 0 | N25: =M25*D25 -> 0 | O25: =H25+J25+L25+N25 -> 0 | P25: 0 | Q25: =(D25*P25)/1000 -> 0 | S25: =H25+J25+Q25 -> 0
B26: 14 | E26: 0 | F26: =IF(C26<>0,$O$3,0) -> 0 | G26: =IF(D26<>0,$Q$3,0) -> 0 | H26: =(D26*G26)/1000 -> 0 | I26: 0 | J26: =(I26*D26)/1000 -> 0 | K26: {=IF(F26<>0,INDEX('[49]Ocean Freight Rates'!$C$3:$E$188,MATCH($C$3,'[49]Ocean Freight Rates'!$B$3:$B$188),MATCH(X26,'[49]Ocean Freight Rates'!$C$2:$E$2,)),0)} -> 0 | L26: =K26*D26 -> 0 | M26: {=IF(H26<>0,INDEX('[49]Ocean Freight Rates'!$C$3:$E$188,MATCH($C$3,'[49]Ocean Freight Rates'!$B$3:$B$188),MATCH(Z26,'[49]Ocean Freight Rates'!$C$2:$E$2,)),0)} -> 0 | N26: =M26*D26 -> 0 | O26: =H26+J26+L26+N26 -> 0 | P26: 0 | Q26: =(D26*P26)/1000 -> 0 | S26: =H26+J26+Q26 -> 0
B27: 15 | E27: 0 | F27: =IF(C27<>0,$O$3,0) -> 0 | G27: =IF(D27<>0,$Q$3,0) -> 0 | H27: =(D27*G27)/1000 -> 0 | I27: 0 | J27: =(I27*D27)/1000 -> 0 | K27: {=IF(F27<>0,INDEX('[49]Ocean Freight Rates'!$C$3:$E$188,MATCH($C$3,'[49]Ocean Freight Rates'!$B$3:$B$188),MATCH(X27,'[49]Ocean Freight Rates'!$C$2:$E$2,)),0)} -> 0 | L27: =K27*D27 -> 0 | M27: {=IF(H27<>0,INDEX('[49]Ocean Freight Rates'!$C$3:$E$188,MATCH($C$3,'[49]Ocean Freight Rates'!$B$3:$B$188),MATCH(Z27,'[49]Ocean Freight Rates'!$C$2:$E$2,)),0)} -> 0 | N27: =M27*D27 -> 0 | O27: =H27+J27+L27+N27 -> 0 | P27: 0 | Q27: =(D27*P27)/1000 -> 0 | S27: =H27+J27+Q27 -> 0
B28: 16 | E28: 0 | F28: =IF(C28<>0,$O$3,0) -> 0 | G28: =IF(D28<>0,$Q$3,0) -> 0 | H28: =(D28*G28)/1000 -> 0 | I28: 0 | J28: =(I28*D28)/1000 -> 0 | K28: {=IF(F28<>0,INDEX('[49]Ocean Freight Rates'!$C$3:$E$188,MATCH($C$3,'[49]Ocean Freight Rates'!$B$3:$B$188),MATCH(X28,'[49]Ocean Freight Rates'!$C$2:$E$2,)),0)} -> 0 | L28: =K28*D28 -> 0 | M28: {=IF(H28<>0,INDEX('[49]Ocean Freight Rates'!$C$3:$E$188,MATCH($C$3,'[49]Ocean Freight Rates'!$B$3:$B$188),MATCH(Z28,'[49]Ocean Freight Rates'!$C$2:$E$2,)),0)} -> 0 | N28: =M28*D28 -> 0 | O28: =H28+J28+L28+N28 -> 0 | P28: 0 | Q28: =(D28*P28)/1000 -> 0 | S28: =H28+J28+Q28 -> 0
B29: 17 | C29: BAGS, WOVEN POLYPROPYLENE- 50 KG 100752 | F29: =IF(C29<>0,$O$3,0) -> 2025 | G29: N/A | H29: N/A | I29: N/A | J29: N/A | O29: N/A | P29: 0 | Q29: =(D29*P29)/1000 -> 0 | S29: =Q29 -> 0
