Workbook

Sheet 1. Summary Budget
A1: SUMMARY BUDGET
A2: Partners of the Americas
A3: 100,000 Strong in the Americas
A4: 24 Months
D6: Original Budget
A8: A | C8: Personnel | D8: ='2. Detailed Budget'!J14 -> 38959.956
A9: B | C9: Fringe Benefits | D9: ='2. Detailed Budget'!J17 -> 9143.9017
A10: C | C10: Travel | D10: ='2. Detailed Budget'!J18 -> 0
A11: D | C11: Equipment | D11: 0
A12: E | C12: Supplies | D12: 0
A13: F | C13: Contractual | D13: 0
A14: G | C14: Construction | D14: 0
A15: H | C15: Other Direct Costs | D15: 0
A16: I | C16: Total Direct charges | D16: 0
A17: J | C17: Total Indirect costs | D17: ='2. Detailed Budget'!J34 -> 17636
A18: K | C18: Total Project Cost | D18: ='2. Detailed Budget'!J35 -> 79999.858
A19: L | C19: Cost Share (if applicable)
A21: * line item amounts auto-fill from "Detailed Grant Budget Template" tab

Sheet 2. Detailed Budget
C1: LINE-ITEM BUDGET
C3: Partners of the Americas | H3: Project Title
A4: Program/Dept. | B4: 40100 | E4: Expanding Colombia-U.S. Higher Education Climate Cooperation and Inclusive Education Exchanges through 100K Strong Americas
A5: Funder/Grant: | B5: DOS267 | C5: Project Duration: 24 months | H5: Project duration
F7: Unit Cost | J7: Original Budget Federal Share
F8: Unit | G8: Number | H8: Amount | I8: Rate
A9: Activity (Budget) Code | B9: Account Code | C9: A | E9: Personnel | F9: months or years | H9: salary (monthly) | I9: % effort for Personnel only
C10: A.1 | E10: US-Based personnel
A11: PERSNL | B11: 50000 | C11: A.1.1 | E11: Program Officer | F11: months | G11: 24 | H11: 5005.35 | I11: 0.15 | J11: =G11*H11*I11 -> 18019.26
A12: PERSNL | B12: 50000 | C12: A.1.2 | E12: Communications Officer | F12: months | G12: 24 | H12: 3802.49 | I12: 0.1 | J12: =G12*H12*I12 -> 9125.976
A13: PERSNL | B13: 50000 | C13: A.1.3 | E13: MEL Officer | F13: months | G13: 24 | H13: 4922.8 | I13: 0.1 | J13: =G13*H13*I13 -> 11814.72
C14: Subtotal Personnel | J14: =SUM(J11:J13) -> 38959.956
C15: B | E15: Fringe
A16: FRINGE | B16: 50900 | C16: B.1 | E16: US-Based Personnel Fringe Benefits | I16: 0.2347 | J16: =J14*I16 -> 9143.9017
C17: Subtotal Fringe Benefits | J17: =J16 -> 9143.9017
C18: C | E18: Travel | F18: # people | G18: # days | H18: Cost
C19: C.1 | E19: Staff Travel
A20: STFTRAVEL | B20: 86040 | C20: C.1.1 | E20: International Round Trip Airfare | F20: trips | G20: 2 | H20: 800 | J20: =G20*H20 -> 1600
A21: STFCN DIEM | B21: 86050 | C21: C.1.2 | E21: International M&IE | F21: days | G21: =G20*5 -> 10 | H21: 156 | J21: =G21*H21 -> 1560
A22: LODGING | B22: 86030 | C22: C.1.3 | E22: International Lodging | F22: nights | G22: =G20*4 -> 8 | H22: 200 | J22: =G22*H22 -> 1600
A23: LOCAL TRVL | B23: 86000 | C23: C.1.4 | E23: International Local Transportation | F23: days | G23: =G21 -> 10 | H23: 50 | J23: =G23*H23 -> 500
C24: Subtotal Travel | J24: =SUM(J20:J23) -> 5260
C25: D | E25: Equipment (> $5,000 per unit ) | G25: # units | H25: unit cost
C26: E | E26: Supplies (< $5,000 per unit) | G26: # units | H26: unit cost
C27: F | E27: Contractual (Subrecipients, Subcontracts, and Consultant fees)
C28: F.1 | E28: Sub-grants | H28: daily rate
A29: GRANTS | B29: 89000 | C29: F.1.1 | E29: HEI Sub-grants | F29: grants | G29: 1 | H29: 9000 | J29: =G29*H29 -> 9000
C30: Subtotal Contractual | J30: =SUM(J29) -> 9000
C31: G | E31: Construction
C32: H | E32: Other Direct Costs
C33: I | E33: Total Direct Costs | J33: =J14+J16+J24+J30 -> 62363.858
A34: IDC | B34: 94050 | C34: J | E34: Indirect Costs | F34: 0.2828 | J34: =ROUND(J33*F34,0) -> 17636
C35: K | E35: Total Project Cost | J35: =SUM(J33:J34) -> 79999.858

Sheet 2. REV Detailed Budget
C1: LINE-ITEM BUDGET
C3: Partners of the Americas | H3: Project Title
A4: Program/Dept. | B4: 40100 | E4: Expanding Colombia-U.S. Higher Education Climate Cooperation and Inclusive Education Exchanges through 100K Strong Americas
A5: Funder/Grant: | B5: DOS267 | C5: Project Duration: 24 months | H5: Project duration
F7: Unit Cost | J7: Original Budget Federal Share
F8: Unit | G8: Number | H8: Amount | I8: Rate
A9: Activity (Budget) Code | B9: Account Code | C9: A | E9: Personnel | F9: months or years | H9: salary (monthly) | I9: % effort for Personnel only
C10: A.1 | E10: US-Based personnel
A11: PERSNL | B11: 50000 | C11: A.1.1 | E11: Program Officer | F11: months | G11: 24 | H11: 5005.35 | I11: 0.15 | J11: =G11*H11*I11 -> 18019.26
A12: PERSNL | B12: 50000 | C12: A.1.2 | E12: Communications Officer | F12: months | G12: 24 | H12: 3802.49 | I12: 0.1 | J12: =G12*H12*I12 -> 9125.976
A13: PERSNL | B13: 50000 | C13: A.1.3 | E13: MEL Officer | F13: months | G13: 24 | H13: 4922.8 | I13: 0.1 | J13: =G13*H13*I13 -> 11814.72
C14: Subtotal Personnel | J14: =SUM(J11:J13) -> 38959.956 | L14: =J14/$J$35 -> 0.10252613
C15: B | E15: Fringe
A16: FRINGE | B16: 50900 | C16: B.1 | E16: US-Based Personnel Fringe Benefits | I16: 0.2347 | J16: =J14*I16 -> 9143.9017 | L16: =J16/$J$35 -> 0.024062882
C17: Subtotal Fringe Benefits | J17: =J16 -> 9143.9017
C18: C | E18: Travel | F18: # people | G18: # days | H18: Cost
C19: C.1 | E19: Staff Travel
A20: STFTRAVEL | B20: 86040 | C20: C.1.1 | E20: International Round Trip Airfare | F20: trips | G20: 2 | H20: 800 | J20: =G20*H20 -> 1600
A21: STFCN DIEM | B21: 86050 | C21: C.1.2 | E21: International M&IE | F21: days | G21: =G20*5 -> 10 | H21: 156 | J21: =G21*H21 -> 1560
A22: LODGING | B22: 86030 | C22: C.1.3 | E22: International Lodging | F22: nights | G22: =G20*4 -> 8 | H22: 200 | J22: =G22*H22 -> 1600
A23: LOCAL TRVL | B23: 86000 | C23: C.1.4 | E23: International Local Transportation | F23: days | G23: =G21 -> 10 | H23: 50 | J23: =G23*H23 -> 500
C24: Subtotal Travel | J24: =SUM(J20:J23) -> 5260 | L24: =J24/$J$35 -> 0.013842095
C25: D | E25: Equipment (> $5,000 per unit ) | G25: # units | H25: unit cost
C26: E | E26: Supplies (< $5,000 per unit) | G26: # units | H26: unit cost
C27: F | E27: Contractual (Subrecipients, Subcontracts, and Consultant fees)
C28: F.1 | E28: Sub-grants | H28: daily rate
A29: GRANTS | B29: 89000 | C29: F.1.1 | E29: HEI Sub-grants | F29: grants | G29: =J29/H29 -> 4.8572684 | H29: 50000 | J29: =233863.42+9000 -> 242863.42
C30: Subtotal Contractual | J30: =SUM(J29) -> 242863.42 | L30: =J30/$J$35 -> 0.6391138
C31: G | E31: Construction
C32: H | E32: Other Direct Costs
C33: I | E33: Total Direct Costs | J33: =J14+J16+J24+J30 -> 296227.28
A34: IDC | B34: 94050 | C34: J | E34: Indirect Costs | F34: 0.2828 | J34: =ROUND(J33*F34,0) -> 83773 | L34: =J34/$J$35 -> 0.2204551
C35: K | E35: Total Project Cost | J35: =SUM(J33:J34) -> 380000.28
