Workbook

Sheet Budget Summary
A1: PARTNERS OF THE AMERICAS
A2: SUMMARY BUDGET
A3: Funding Opportunity: , CFDA: 19.019
A4: Program Name
A5: 48 Months
A6: BUDGET SUMMARY CATEGORIES | B6: Year 1 | E6: Year 2 | H6: Year 3 | K6: Year 4 | N6: Total
B7: JTIP | C7: Cost Share | D7: Total | E7: JTIP | F7: Cost Share | G7: Total | H7: JTIP | I7: Cost Share | J7: Total | K7: JTIP | L7: Cost Share | M7: Total | N7: JTIP | O7: Cost Share | P7: Total
A8: 1. Personnel | B8: ='Line Item Budget'!H16 -> 0 | C8: ='Line Item Budget'!I16 -> 0 | D8: =B8+C8 -> 0 | E8: ='Line Item Budget'!N16 -> 0 | F8: ='Line Item Budget'!O16 -> 0 | G8: =E8+F8 -> 0 | H8: ='Line Item Budget'!T16 -> 0 | I8: ='Line Item Budget'!U16 -> 0 | J8: =H8+I8 -> 0 | K8: ='Line Item Budget'!Z16 -> 0 | L8: ='Line Item Budget'!AA16 -> 0 | M8: =K8+L8 -> 0 | N8: ='Line Item Budget'!AB16 -> 0 | O8: ='Line Item Budget'!AC16 -> 0 | P8: =N8+O8 -> 0
A9: 2. Fringe Benefits | B9: ='Line Item Budget'!H25 -> 0 | C9: ='Line Item Budget'!I25 -> 0 | D9: =B9+C9 -> 0 | E9: ='Line Item Budget'!N25 -> 0 | F9: ='Line Item Budget'!O25 -> 0 | G9: =E9+F9 -> 0 | H9: ='Line Item Budget'!T25 -> 0 | I9: ='Line Item Budget'!U25 -> 0 | J9: =H9+I9 -> 0 | K9: ='Line Item Budget'!Z25 -> 0 | L9: ='Line Item Budget'!AA25 -> 0 | M9: =K9+L9 -> 0 | N9: ='Line Item Budget'!AB25 -> 0 | O9: ='Line Item Budget'!AC25 -> 0 | P9: =N9+O9 -> 0
A10: 3. Travel | B10: ='Line Item Budget'!H41 -> 0 | C10: ='Line Item Budget'!I41 -> 0 | D10: =B10+C10 -> 0 | E10: ='Line Item Budget'!N41 -> 0 | F10: ='Line Item Budget'!O41 -> 0 | G10: =E10+F10 -> 0 | H10: ='Line Item Budget'!T41 -> 0 | I10: ='Line Item Budget'!U41 -> 0 | J10: =H10+I10 -> 0 | K10: ='Line Item Budget'!Z41 -> 0 | L10: ='Line Item Budget'!AA41 -> 0 | M10: =K10+L10 -> 0 | N10: ='Line Item Budget'!AB41 -> 0 | O10: ='Line Item Budget'!AC41 -> 0 | P10: =N10+O10 -> 0
A11: 4. Equipment
A12: 5. Supplies | B12: ='Line Item Budget'!H48 -> 0 | C12: ='Line Item Budget'!I48 -> 0 | D12: =B12+C12 -> 0 | E12: ='Line Item Budget'!N48 -> 0 | F12: ='Line Item Budget'!O48 -> 0 | G12: =E12+F12 -> 0 | H12: ='Line Item Budget'!T48 -> 0 | I12: ='Line Item Budget'!U48 -> 0 | J12: =H12+I12 -> 0 | K12: ='Line Item Budget'!Z48 -> 0 | L12: ='Line Item Budget'!AA48 -> 0 | M12: =K12+L12 -> 0 | N12: ='Line Item Budget'!AB48 -> 0 | O12: ='Line Item Budget'!AC48 -> 0 | P12: =N12+O12 -> 0
A13: 6. Contractual | B13: ='Line Item Budget'!H54 -> 0 | C13: ='Line Item Budget'!I54 -> 0 | D13: =B13+C13 -> 0 | E13: ='Line Item Budget'!N54 -> 0 | F13: ='Line Item Budget'!O54 -> 0 | G13: =E13+F13 -> 0 | H13: ='Line Item Budget'!T54 -> 0 | I13: ='Line Item Budget'!U54 -> 0 | J13: =H13+I13 -> 0 | K13: ='Line Item Budget'!Z54 -> 0 | L13: ='Line Item Budget'!AA54 -> 0 | M13: =K13+L13 -> 0 | N13: ='Line Item Budget'!AB54 -> 0 | O13: ='Line Item Budget'!AC54 -> 0 | P13: =N13+O13 -> 0
A14: 7. Construction
A15: 8. Other Direct Costs | B15: ='Line Item Budget'!H85 -> 0 | C15: ='Line Item Budget'!I85 -> 0 | D15: =B15+C15 -> 0 | E15: ='Line Item Budget'!N85 -> 0 | F15: ='Line Item Budget'!O85 -> 0 | G15: =E15+F15 -> 0 | H15: ='Line Item Budget'!T85 -> 0 | I15: ='Line Item Budget'!U85 -> 0 | J15: =H15+I15 -> 0 | K15: ='Line Item Budget'!Z85 -> 0 | L15: ='Line Item Budget'!AA85 -> 0 | M15: =K15+L15 -> 0 | N15: ='Line Item Budget'!AB85 -> 0 | O15: ='Line Item Budget'!AC85 -> 0 | P15: =N15+O15 -> 0
A16: 9. Total Direct Costs | B16: =SUM(B8:B15) -> 0 | C16: =SUM(C8:C15) -> 0 | D16: =SUM(D8:D15) -> 0 | E16: =SUM(E8:E15) -> 0 | F16: =SUM(F8:F15) -> 0 | G16: =SUM(G8:G15) -> 0 | H16: =SUM(H8:H15) -> 0 | I16: =SUM(I8:I15) -> 0 | ... P16: =SUM(P8:P15) -> 0
A17: 10. Indirect Costs | B17: ='Line Item Budget'!H87 -> 0 | C17: ='Line Item Budget'!I87 -> 0 | D17: =B17+C17 -> 0 | E17: ='Line Item Budget'!N87 -> 0 | F17: ='Line Item Budget'!O87 -> 0 | G17: =E17+F17 -> 0 | H17: ='Line Item Budget'!T87 -> 0 | I17: ='Line Item Budget'!U87 -> 0 | J17: =H17+I17 -> 0 | K17: ='Line Item Budget'!Z87 -> 0 | L17: ='Line Item Budget'!AA87 -> 0 | M17: =K17+L17 -> 0 | N17: ='Line Item Budget'!AB87 -> 0 | O17: ='Line Item Budget'!AC87 -> 0 | P17: =N17+O17 -> 0
A18: 11. Total Costs | B18: =B16+B17 -> 0 | C18: =C16+C17 -> 0 | D18: =D16+D17 -> 0 | E18: =E16+E17 -> 0 | F18: =F16+F17 -> 0 | G18: =G16+G17 -> 0 | H18: =H16+H17 -> 0 | I18: =I16+I17 -> 0 | ... P18: =P16+P17 -> 0

Sheet Line Item Budget
A1: PARTNERS OF THE AMERICAS
A2: Detailed Budget
A3: Funding Opportunity: , CFDA: 19.019
A4: Name of Project
A5: PARTNERS OF THE AMERICAS
A6: All costs in US$ | B6: Year 1 | J6: Year 2 | P6: Year 3 | V6: Year 4 | AB6: Total
A7: Budget Line Items | B7: No. | C7: Unit Type | D7: Freq. | E7: % | F7: Rate | G7: Total | H7: JTIP | I7: Cost Share | J7: No. | K7: Freq. | L7: Rate | M7: Total | N7: JTIP | O7: Cost Share | P7: No. | Q7: Freq. | R7: Rate | S7: Total | T7: JTIP | U7: Cost Share | V7: No. | W7: Freq. | X7: Rate | Y7: Total | Z7: JTIP | AA7: Cost Share | AB7: JTIP | AC7: Cost Share | AD7: Grand Total
A8: Personnel
A9: Project Coordinator (XX%) | B9: 0 | C9: FTE/month | D9: 0 | E9: 0 | F9: 0 | G9: =B9*F9*D9*E9 -> 0 | H9: =G9 -> 0 | I9: =G9-H9 -> 0 | J9: 0 | K9: 0 | L9: =F9*1.04 -> 0 | M9: =J9*L9*K9*E9 -> 0 | N9: =M9 -> 0 | O9: =M9-N9 -> 0 | P9: 0 | Q9: 0 | R9: =L9*1.04 -> 0 | S9: =P9*R9*Q9*E9 -> 0 | T9: =S9 -> 0 | U9: =S9-T9 -> 0 | V9: 0 | W9: 0 | X9: =R9*1.04 -> 0 | Y9: =V9*X9*W9*K9 -> 0 | Z9: =Y9 -> 0 | AA9: =Y9-Z9 -> 0 | AB9: =H9+N9+T9+Z9 -> 0 | AC9: =I9+O9+U9+AA9 -> 0 | AD9: =AB9+AC9 -> 0
A10: M&E Specialist (XX%) | B10: 0 | C10: FTE/month | D10: 0 | E10: 0 | F10: 0 | G10: =B10*F10*D10*E10 -> 0 | H10: =G10 -> 0 | I10: =G10-H10 -> 0 | J10: 0 | K10: 0 | L10: =F10*1.04 -> 0 | M10: =J10*L10*K10*E10 -> 0 | N10: =M10 -> 0 | O10: =M10-N10 -> 0 | P10: 0 | Q10: 0 | R10: =L10*1.04 -> 0 | S10: =P10*R10*Q10*E10 -> 0 | T10: =S10 -> 0 | U10: =S10-T10 -> 0 | V10: 0 | W10: 0 | X10: =R10*1.04 -> 0 | Y10: =V10*X10*W10*K10 -> 0 | Z10: =Y10 -> 0 | AA10: =Y10-Z10 -> 0 | AB10: =H10+N10+T10+Z10 -> 0 | AC10: =I10+O10+U10+AA10 -> 0 | AD10: =AB10+AC10 -> 0
A11: Position (XX%) | B11: 0 | C11: FTE/month | D11: 0 | E11: 0 | F11: 0 | G11: =B11*F11*D11*E11 -> 0 | H11: =G11 -> 0 | I11: 0 | J11: 0 | K11: 0 | L11: =F11*1.04 -> 0 | M11: =J11*L11*K11*E11 -> 0 | N11: =M11 -> 0 | O11: 0 | P11: 0 | Q11: 0 | R11: =L11*1.04 -> 0 | S11: =P11*R11*Q11*E11 -> 0 | T11: =S11 -> 0 | U11: 0 | V11: 0 | W11: 0 | X11: =R11*1.04 -> 0 | Y11: =V11*X11*W11*K11 -> 0 | Z11: =Y11 -> 0 | AA11: 0 | AB11: =H11+N11+T11+Z11 -> 0 | AC11: =I11+O11+U11+AA11 -> 0 | AD11: =AB11+AC11 -> 0
A12: Position (XX%) | B12: 0 | C12: FTE/month | D12: 0 | E12: 0 | F12: 0 | G12: =B12*F12*D12*E12 -> 0 | H12: =G12 -> 0 | I12: 0 | J12: 0 | K12: 0 | L12: =F12*1.04 -> 0 | M12: =J12*L12*K12*E12 -> 0 | N12: =M12 -> 0 | O12: 0 | P12: 0 | Q12: 0 | R12: =L12*1.04 -> 0 | S12: =P12*R12*Q12*E12 -> 0 | T12: =S12 -> 0 | U12: 0 | V12: 0 | W12: 0 | X12: =R12*1.04 -> 0 | Y12: =V12*X12*W12*K12 -> 0 | Z12: =Y12 -> 0 | AA12: 0 | AB12: =H12+N12+T12+Z12 -> 0 | AC12: =I12+O12+U12+AA12 -> 0 | AD12: =AB12+AC12 -> 0
A13: Position (XX%) | B13: 0 | C13: FTE/month | D13: 0 | E13: 0 | F13: 0 | G13: =B13*F13*D13*E13 -> 0 | H13: =G13 -> 0 | I13: =G13-H13 -> 0 | J13: 0 | K13: 0 | L13: =F13*1.04 -> 0 | M13: =J13*L13*K13*E13 -> 0 | N13: =M13 -> 0 | O13: =M13-N13 -> 0 | P13: 0 | Q13: 0 | R13: =L13*1.04 -> 0 | S13: =P13*R13*Q13*E13 -> 0 | T13: =S13 -> 0 | U13: =S13-T13 -> 0 | V13: 0 | W13: 0 | X13: =R13*1.04 -> 0 | Y13: =V13*X13*W13*K13 -> 0 | Z13: =Y13 -> 0 | AA13: =Y13-Z13 -> 0 | AB13: =H13+N13+T13+Z13 -> 0 | AC13: =I13+O13+U13+AA13 -> 0 | AD13: =AB13+AC13 -> 0
A14: Position (XX%) | B14: 0 | C14: FTE/month | D14: 0 | E14: 0 | F14: 0 | G14: =B14*F14*D14*E14 -> 0 | H14: =G14 -> 0 | I14: =G14-H14 -> 0 | J14: 0 | K14: 0 | L14: =F14*1.04 -> 0 | M14: =J14*L14*K14*E14 -> 0 | N14: =M14 -> 0 | O14: =M14-N14 -> 0 | P14: 0 | Q14: 0 | R14: =L14*1.04 -> 0 | S14: =P14*R14*Q14*E14 -> 0 | T14: =S14 -> 0 | U14: =S14-T14 -> 0 | V14: 0 | W14: 0 | X14: =R14*1.04 -> 0 | Y14: =V14*X14*W14*K14 -> 0 | Z14: =Y14 -> 0 | AA14: =Y14-Z14 -> 0 | AB14: =H14+N14+T14+Z14 -> 0 | AC14: =I14+O14+U14+AA14 -> 0 | AD14: =AB14+AC14 -> 0
A15: Position (XX%) | B15: 0 | C15: FTE/month | D15: 0 | E15: 0 | F15: 0 | G15: =B15*F15*D15*E15 -> 0 | H15: =G15 -> 0 | I15: =G15-H15 -> 0 | J15: 0 | K15: 0 | L15: =F15*1.04 -> 0 | M15: =J15*L15*K15*E15 -> 0 | N15: =M15 -> 0 | O15: =M15-N15 -> 0 | P15: 0 | Q15: 0 | R15: =L15*1.04 -> 0 | S15: =P15*R15*Q15*E15 -> 0 | T15: =S15 -> 0 | U15: =S15-T15 -> 0 | V15: 0 | W15: 0 | X15: =R15*1.04 -> 0 | Y15: =V15*X15*W15*K15 -> 0 | Z15: =Y15 -> 0 | AA15: =Y15-Z15 -> 0 | AB15: =H15+N15+T15+Z15 -> 0 | AC15: =I15+O15+U15+AA15 -> 0 | AD15: =AB15+AC15 -> 0
A16: Subtotal Personnel | G16: =SUM(G9:G15) -> 0 | H16: =SUM(H9:H15) -> 0 | I16: =SUM(I9:I15) -> 0 | M16: =SUM(M9:M15) -> 0 | N16: =SUM(N9:N15) -> 0 | O16: =SUM(O9:O15) -> 0 | S16: =SUM(S9:S15) -> 0 | T16: =SUM(T9:T15) -> 0 | U16: =SUM(U9:U15) -> 0 | Y16: =SUM(Y9:Y15) -> 0 | Z16: =SUM(Z9:Z15) -> 0 | AA16: =SUM(AA9:AA15) -> 0 | AB16: =SUM(AB9:AB15) -> 0 | AC16: =SUM(AC9:AC15) -> 0 | AD16: =SUM(AD9:AD15) -> 0
A17: Fringe Benefits
A18: =A9 -> Project Coordinator (XX%) | B18: =B9 -> 0 | C18: Month | D18: =D9 -> 0 | E18: 0 | F18: =F9 -> 0 | G18: =B18*F18*D18*E18 -> 0 | H18: =G18 -> 0 | I18: 0 | J18: =J9 -> 0 | K18: =K9 -> 0 | L18: =L9 -> 0 | M18: =E18*L18*J18*K18 -> 0 | N18: =M18 -> 0 | O18: =M18-N18 -> 0 | P18: =P9 -> 0 | Q18: =Q9 -> 0 | R18: =R9 -> 0 | S18: =E18*R18*P18*Q18 -> 0 | T18: =S18 -> 0 | U18: =S18-T18 -> 0 | V18: =V9 -> 0 | W18: =W9 -> 0 | X18: =X9 -> 0 | Y18: =K18*X18*V18*W18 -> 0 | Z18: =Y18 -> 0 | AA18: =Y18-Z18 -> 0 | AB18: =H18+N18+T18+Z18 -> 0 | AC18: =I18+O18+U18+AA18 -> 0 | AD18: =AB18+AC18 -> 0
A19: =A10 -> M&E Specialist (XX%) | B19: =B10 -> 0 | C19: Month | D19: =D10 -> 0 | E19: 0 | F19: =F10 -> 0 | G19: =B19*F19*D19*E19 -> 0 | H19: =G19 -> 0 | I19: 0 | J19: =J10 -> 0 | K19: =K10 -> 0 | L19: =L10 -> 0 | M19: =E19*L19*J19*K19 -> 0 | N19: =M19 -> 0 | O19: =M19-N19 -> 0 | P19: =P10 -> 0 | Q19: =Q10 -> 0 | R19: =R10 -> 0 | S19: =E19*R19*P19*Q19 -> 0 | T19: =S19 -> 0 | U19: =S19-T19 -> 0 | V19: =V10 -> 0 | W19: =W10 -> 0 | X19: =X10 -> 0 | Y19: =K19*X19*V19*W19 -> 0 | Z19: =Y19 -> 0 | AA19: =Y19-Z19 -> 0 | AB19: =H19+N19+T19+Z19 -> 0 | AC19: =I19+O19+U19+AA19 -> 0 | AD19: =AB19+AC19 -> 0
A20: =A11 -> Position (XX%) | B20: =B11 -> 0 | C20: Month | D20: =D11 -> 0 | E20: 0 | F20: =F11 -> 0 | G20: =B20*F20*D20*E20 -> 0 | H20: =G20 -> 0 | I20: 0 | J20: =J11 -> 0 | K20: =K11 -> 0 | L20: =L11 -> 0 | M20: =E20*L20*J20*K20 -> 0 | N20: =M20 -> 0 | O20: =M20-N20 -> 0 | P20: =P11 -> 0 | Q20: =Q11 -> 0 | R20: =R11 -> 0 | S20: =E20*R20*P20*Q20 -> 0 | T20: =S20 -> 0 | U20: =S20-T20 -> 0 | V20: =V11 -> 0 | W20: =W11 -> 0 | X20: =X11 -> 0 | Y20: =K20*X20*V20*W20 -> 0 | Z20: =Y20 -> 0 | AA20: =Y20-Z20 -> 0 | AB20: =H20+N20+T20+Z20 -> 0 | AC20: =I20+O20+U20+AA20 -> 0 | AD20: =AB20+AC20 -> 0
A21: =A12 -> Position (XX%) | B21: =B12 -> 0 | C21: Month | D21: =D12 -> 0 | E21: 0 | F21: =F12 -> 0 | G21: =B21*F21*D21*E21 -> 0 | H21: =G21 -> 0 | I21: 0 | J21: =J12 -> 0 | K21: =K12 -> 0 | L21: =L12 -> 0 | M21: =E21*L21*J21*K21 -> 0 | N21: =M21 -> 0 | O21: =M21-N21 -> 0 | P21: =P12 -> 0 | Q21: =Q12 -> 0 | R21: =R12 -> 0 | S21: =E21*R21*P21*Q21 -> 0 | T21: =S21 -> 0 | U21: =S21-T21 -> 0 | V21: =V12 -> 0 | W21: =W12 -> 0 | X21: =X12 -> 0 | Y21: =K21*X21*V21*W21 -> 0 | Z21: =Y21 -> 0 | AA21: =Y21-Z21 -> 0 | AB21: =H21+N21+T21+Z21 -> 0 | AC21: =I21+O21+U21+AA21 -> 0 | AD21: =AB21+AC21 -> 0
A22: =A13 -> Position (XX%) | B22: =B13 -> 0 | C22: Month | D22: =D13 -> 0 | E22: 0 | F22: =F13 -> 0 | G22: =B22*F22*D22*E22 -> 0 | H22: =G22 -> 0 | I22: 0 | J22: =J13 -> 0 | K22: =K13 -> 0 | L22: =L13 -> 0 | M22: =E22*L22*J22*K22 -> 0 | N22: =M22 -> 0 | O22: =M22-N22 -> 0 | P22: =P13 -> 0 | Q22: =Q13 -> 0 | R22: =R13 -> 0 | S22: =E22*R22*P22*Q22 -> 0 | T22: =S22 -> 0 | U22: =S22-T22 -> 0 | V22: =V13 -> 0 | W22: =W13 -> 0 | X22: =X13 -> 0 | Y22: =K22*X22*V22*W22 -> 0 | Z22: =Y22 -> 0 | AA22: =Y22-Z22 -> 0 | AB22: =H22+N22+T22+Z22 -> 0 | AC22: =I22+O22+U22+AA22 -> 0 | AD22: =AB22+AC22 -> 0
A23: =A14 -> Position (XX%) | B23: =B14 -> 0 | C23: Month | D23: =D14 -> 0 | E23: 0 | F23: =F14 -> 0 | G23: =B23*F23*D23*E23 -> 0 | H23: =G23 -> 0 | I23: 0 | J23: =J14 -> 0 | K23: =K14 -> 0 | L23: =L14 -> 0 | M23: =E23*L23*J23*K23 -> 0 | N23: =M23 -> 0 | O23: =M23-N23 -> 0 | P23: =P14 -> 0 | Q23: =Q14 -> 0 | R23: =R14 -> 0 | S23: =E23*R23*P23*Q23 -> 0 | T23: =S23 -> 0 | U23: =S23-T23 -> 0 | V23: =V14 -> 0 | W23: =W14 -> 0 | X23: =X14 -> 0 | Y23: =K23*X23*V23*W23 -> 0 | Z23: =Y23 -> 0 | AA23: =Y23-Z23 -> 0 | AB23: =H23+N23+T23+Z23 -> 0 | AC23: =I23+O23+U23+AA23 -> 0 | AD23: =AB23+AC23 -> 0
A24: =A15 -> Position (XX%) | B24: =B15 -> 0 | C24: Month | D24: =D15 -> 0 | E24: 0 | F24: =F15 -> 0 | G24: =B24*F24*D24*E24 -> 0 | H24: =G24 -> 0 | I24: 0 | J24: =J15 -> 0 | K24: =K15 -> 0 | L24: =L15 -> 0 | M24: =E24*L24*J24*K24 -> 0 | N24: =M24 -> 0 | O24: =M24-N24 -> 0 | P24: =P15 -> 0 | Q24: =Q15 -> 0 | R24: =R15 -> 0 | S24: =E24*R24*P24*Q24 -> 0 | T24: =S24 -> 0 | U24: =S24-T24 -> 0 | V24: =V15 -> 0 | W24: =W15 -> 0 | X24: =X15 -> 0 | Y24: =K24*X24*V24*W24 -> 0 | Z24: =Y24 -> 0 | AA24: =Y24-Z24 -> 0 | AB24: =H24+N24+T24+Z24 -> 0 | AC24: =I24+O24+U24+AA24 -> 0 | AD24: =AB24+AC24 -> 0
A25: Subtotal Fringe Benefits | G25: =SUM(G18:G24) -> 0 | H25: =SUM(H18:H24) -> 0 | I25: =SUM(I18:I24) -> 0 | M25: =SUM(M18:M24) -> 0 | N25: =SUM(N18:N24) -> 0 | O25: =SUM(O18:O24) -> 0 | S25: =SUM(S18:S24) -> 0 | T25: =SUM(T18:T24) -> 0 | U25: =SUM(U18:U24) -> 0 | Y25: =SUM(Y18:Y24) -> 0 | Z25: =SUM(Z18:Z24) -> 0 | AA25: =SUM(AA18:AA24) -> 0 | AB25: =SUM(AB18:AB24) -> 0 | AC25: =SUM(AC18:AC24) -> 0 | AD25: =SUM(AD18:AD24) -> 0
A26: Travel
A27: 1. HQ Staff International Travel
A28: International Airfare (Washington, XXX) | B28: 0 | C28: Trip | D28: 0 | E28: 1 | F28: 0 | G28: =B28*F28*D28 -> 0 | H28: =G28 -> 0 | I28: =G28-H28 -> 0 | J28: 0 | K28: 0 | L28: =F28*1.03 -> 0 | M28: =J28*L28*K28*E28 -> 0 | N28: =M28 -> 0 | O28: =M28-N28 -> 0 | P28: 0 | Q28: 0 | R28: =L28*1.03 -> 0 | S28: =P28*R28*Q28*E28 -> 0 | T28: =S28 -> 0 | U28: =S28-T28 -> 0 | V28: 0 | W28: 0 | X28: =R28*1.03 -> 0 | Y28: =V28*X28*W28*K28 -> 0 | Z28: =Y28 -> 0 | AA28: =Y28-Z28 -> 0 | AB28: =H28+N28+T28+Z28 -> 0 | AC28: =I28+O28+U28+AA28 -> 0 | AD28: =AB28+AC28 -> 0
A29: Domestic Airfare (Mexico City - XXXX) | B29: 0 | C29: Trip | D29: 0 | E29: 1 | F29: 0 | G29: =B29*F29*D29 -> 0 | H29: =G29 -> 0 | I29: =G29-H29 -> 0 | J29: 0 | K29: 0 | L29: =F29*1.03 -> 0 | M29: =J29*L29*K29*E29 -> 0 | N29: =M29 -> 0 | O29: =M29-N29 -> 0 | P29: 0 | Q29: 0 | R29: =L29*1.03 -> 0 | S29: =P29*R29*Q29*E29 -> 0 | T29: =S29 -> 0 | U29: =S29-T29 -> 0 | V29: 0 | W29: 0 | X29: =R29*1.03 -> 0 | Y29: =V29*X29*W29*K29 -> 0 | Z29: =Y29 -> 0 | AA29: =Y29-Z29 -> 0 | AB29: =H29+N29+T29+Z29 -> 0 | AC29: =I29+O29+U29+AA29 -> 0 | AD29: =AB29+AC29 -> 0
A30: Ground Transportation | B30: 0 | C30: Trip | D30: 0 | E30: 1 | F30: 0 | G30: =B30*F30*D30 -> 0 | H30: =G30 -> 0 | I30: =G30-H30 -> 0 | J30: 0 | K30: 0 | L30: =F30*1.03 -> 0 | M30: =J30*L30*K30*E30 -> 0 | N30: =M30 -> 0 | O30: =M30-N30 -> 0 | P30: 0 | Q30: 0 | R30: =L30*1.03 -> 0 | S30: =P30*R30*Q30*E30 -> 0 | T30: =S30 -> 0 | U30: =S30-T30 -> 0 | V30: 0 | W30: 0 | X30: =R30*1.03 -> 0 | Y30: =V30*X30*W30*K30 -> 0 | Z30: =Y30 -> 0 | AA30: =Y30-Z30 -> 0 | AB30: =H30+N30+T30+Z30 -> 0 | AC30: =I30+O30+U30+AA30 -> 0 | AD30: =AB30+AC30 -> 0
A31: Lodging in XXX | B31: 0 | C31: Night | D31: 0 | E31: 1 | F31: 0 | G31: =B31*F31*D31 -> 0 | H31: =G31 -> 0 | I31: =G31-H31 -> 0 | J31: 0 | K31: 0 | L31: =F31*1.03 -> 0 | M31: =J31*L31*K31*E31 -> 0 | N31: =M31 -> 0 | O31: =M31-N31 -> 0 | P31: 0 | Q31: 0 | R31: =L31*1.03 -> 0 | S31: =P31*R31*Q31*E31 -> 0 | T31: =S31 -> 0 | U31: =S31-T31 -> 0 | V31: 0 | W31: 0 | X31: =R31*1.03 -> 0 | Y31: =V31*X31*W31*K31 -> 0 | Z31: =Y31 -> 0 | AA31: =Y31-Z31 -> 0 | AB31: =H31+N31+T31+Z31 -> 0 | AC31: =I31+O31+U31+AA31 -> 0 | AD31: =AB31+AC31 -> 0
A32: M&IE in XXX | B32: 0 | C32: Day | D32: 0 | E32: 1 | F32: 0 | G32: =B32*F32*D32 -> 0 | H32: =G32 -> 0 | I32: =G32-H32 -> 0 | J32: 0 | K32: 0 | L32: =F32*1.03 -> 0 | M32: =J32*L32*K32*E32 -> 0 | N32: =M32 -> 0 | O32: =M32-N32 -> 0 | P32: 0 | Q32: 0 | R32: =L32*1.03 -> 0 | S32: =P32*R32*Q32*E32 -> 0 | T32: =S32 -> 0 | U32: =S32-T32 -> 0 | V32: 0 | W32: 0 | X32: =R32*1.03 -> 0 | Y32: =V32*X32*W32*K32 -> 0 | Z32: =Y32 -> 0 | AA32: =Y32-Z32 -> 0 | AB32: =H32+N32+T32+Z32 -> 0 | AC32: =I32+O32+U32+AA32 -> 0 | AD32: =AB32+AC32 -> 0
A33: 2. Local Staff In-Country Travel
A34: Domestic Airfare (location - location) | B34: 0 | C34: Trip | D34: 0 | E34: 1 | F34: 0 | G34: =B34*F34*D34 -> 0 | H34: =G34 -> 0 | I34: =G34-H34 -> 0 | J34: 0 | K34: 0 | L34: =F34*1.03 -> 0 | M34: =J34*L34*K34*E34 -> 0 | N34: =M34 -> 0 | O34: =M34-N34 -> 0 | P34: 0 | Q34: 0 | R34: =L34*1.03 -> 0 | S34: =P34*R34*Q34*E34 -> 0 | T34: =S34 -> 0 | U34: =S34-T34 -> 0 | V34: 0 | W34: 0 | X34: =R34*1.03 -> 0 | Y34: =V34*X34*W34*K34 -> 0 | Z34: =Y34 -> 0 | AA34: =Y34-Z34 -> 0 | AB34: =H34+N34+T34+Z34 -> 0 | AC34: =I34+O34+U34+AA34 -> 0 | AD34: =AB34+AC34 -> 0
A35: Lodging - XXX | B35: 0 | C35: Night | D35: 0 | E35: 1 | F35: 0 | G35: =B35*F35*D35 -> 0 | H35: =G35 -> 0 | I35: =G35-H35 -> 0 | J35: 0 | K35: 0 | L35: =F35*1.03 -> 0 | M35: =J35*L35*K35*E35 -> 0 | N35: =M35 -> 0 | O35: =M35-N35 -> 0 | P35: 0 | Q35: 0 | R35: =L35*1.03 -> 0 | S35: =P35*R35*Q35*E35 -> 0 | T35: =S35 -> 0 | U35: =S35-T35 -> 0 | V35: 0 | W35: 0 | X35: =R35*1.03 -> 0 | Y35: =V35*X35*W35*K35 -> 0 | Z35: =Y35 -> 0 | AA35: =Y35-Z35 -> 0 | AB35: =H35+N35+T35+Z35 -> 0 | AC35: =I35+O35+U35+AA35 -> 0 | AD35: =AB35+AC35 -> 0
A36: M&IE - XXX | B36: 0 | C36: Day | D36: 0 | E36: 1 | F36: 0 | G36: =B36*F36*D36 -> 0 | H36: =G36 -> 0 | I36: =G36-H36 -> 0 | J36: 0 | K36: 0 | L36: =F36*1.03 -> 0 | M36: =J36*L36*K36*E36 -> 0 | N36: =M36 -> 0 | O36: =M36-N36 -> 0 | P36: 0 | Q36: 0 | R36: =L36*1.03 -> 0 | S36: =P36*R36*Q36*E36 -> 0 | T36: =S36 -> 0 | U36: =S36-T36 -> 0 | V36: 0 | W36: 0 | X36: =R36*1.03 -> 0 | Y36: =V36*X36*W36*K36 -> 0 | Z36: =Y36 -> 0 | AA36: =Y36-Z36 -> 0 | AB36: =H36+N36+T36+Z36 -> 0 | AC36: =I36+O36+U36+AA36 -> 0 | AD36: =AB36+AC36 -> 0
A37: Lodging - XXX | B37: 0 | C37: Night | D37: 0 | E37: 1 | F37: 0 | G37: =B37*F37*D37 -> 0 | H37: =G37 -> 0 | I37: =G37-H37 -> 0 | J37: 0 | K37: 0 | L37: =F37*1.03 -> 0 | M37: =J37*L37*K37*E37 -> 0 | N37: =M37 -> 0 | O37: =M37-N37 -> 0 | P37: 0 | Q37: 0 | R37: =L37*1.03 -> 0 | S37: =P37*R37*Q37*E37 -> 0 | T37: =S37 -> 0 | U37: =S37-T37 -> 0 | V37: 0 | W37: 0 | X37: =R37*1.03 -> 0 | Y37: =V37*X37*W37*K37 -> 0 | Z37: =Y37 -> 0 | AA37: =Y37-Z37 -> 0 | AB37: =H37+N37+T37+Z37 -> 0 | AC37: =I37+O37+U37+AA37 -> 0 | AD37: =AB37+AC37 -> 0
A38: M&IE - XXX | B38: 0 | C38: Day | D38: 0 | E38: 1 | F38: 0 | G38: =B38*F38*D38 -> 0 | H38: =G38 -> 0 | I38: =G38-H38 -> 0 | J38: 0 | K38: 0 | L38: =F38*1.03 -> 0 | M38: =J38*L38*K38*E38 -> 0 | N38: =M38 -> 0 | O38: =M38-N38 -> 0 | P38: 0 | Q38: 0 | R38: =L38*1.03 -> 0 | S38: =P38*R38*Q38*E38 -> 0 | T38: =S38 -> 0 | U38: =S38-T38 -> 0 | V38: 0 | W38: 0 | X38: =R38*1.03 -> 0 | Y38: =V38*X38*W38*K38 -> 0 | Z38: =Y38 -> 0 | AA38: =Y38-Z38 -> 0 | AB38: =H38+N38+T38+Z38 -> 0 | AC38: =I38+O38+U38+AA38 -> 0 | AD38: =AB38+AC38 -> 0
A39: Transportation Stipend | B39: 0 | C39: Person | D39: 0 | E39: 1 | F39: 0 | G39: =B39*F39*D39 -> 0 | H39: =G39 -> 0 | I39: =G39-H39 -> 0 | J39: 0 | K39: 0 | L39: =F39*1.03 -> 0 | M39: =J39*L39*K39*E39 -> 0 | N39: =M39 -> 0 | O39: =M39-N39 -> 0 | P39: 0 | Q39: 0 | R39: =L39*1.03 -> 0 | S39: =P39*R39*Q39*E39 -> 0 | T39: =S39 -> 0 | U39: =S39-T39 -> 0 | V39: 0 | W39: 0 | X39: =R39*1.03 -> 0 | Y39: =V39*X39*W39*K39 -> 0 | Z39: =Y39 -> 0 | AA39: =Y39-Z39 -> 0 | AB39: =H39+N39+T39+Z39 -> 0 | AC39: =I39+O39+U39+AA39 -> 0 | AD39: =AB39+AC39 -> 0
A40: Ground Transportation | B40: 0 | C40: Month | D40: 0 | E40: 1 | F40: 0 | G40: =B40*F40*D40 -> 0 | H40: =G40 -> 0 | I40: =G40-H40 -> 0 | J40: 0 | K40: 0 | L40: =F40*1.03 -> 0 | M40: =J40*L40*K40*E40 -> 0 | N40: =M40 -> 0 | O40: =M40-N40 -> 0 | P40: 0 | Q40: 0 | R40: =L40*1.03 -> 0 | S40: =P40*R40*Q40*E40 -> 0 | T40: =S40 -> 0 | U40: =S40-T40 -> 0 | V40: 0 | W40: 0 | X40: =R40*1.03 -> 0 | Y40: =V40*X40*W40*K40 -> 0 | Z40: =Y40 -> 0 | AA40: =Y40-Z40 -> 0 | AB40: =H40+N40+T40+Z40 -> 0 | AC40: =I40+O40+U40+AA40 -> 0 | AD40: =AB40+AC40 -> 0
A41: Subtotal Travel | G41: =SUM(G28:G40) -> 0 | H41: =SUM(H28:H40) -> 0 | I41: =SUM(I28:I40) -> 0 | M41: =SUM(M28:M40) -> 0 | N41: =SUM(N28:N40) -> 0 | O41: =SUM(O28:O40) -> 0 | S41: =SUM(S28:S40) -> 0 | T41: =SUM(T28:T40) -> 0 | U41: =SUM(U28:U40) -> 0 | Y41: =SUM(Y28:Y40) -> 0 | Z41: =SUM(Z28:Z40) -> 0 | AA41: =SUM(AA28:AA40) -> 0 | AB41: =SUM(AB28:AB40) -> 0 | AC41: =SUM(AC28:AC40) -> 0 | AD41: =SUM(AD28:AD40) -> 0
A42: Supplies
A43: Office Supplies | B43: 0 | C43: Month | D43: 0 | E43: 1 | F43: 0 | G43: =B43*F43*D43*E43 -> 0 | H43: =G43 -> 0 | I43: =G43-H43 -> 0 | J43: 0 | K43: 0 | L43: =F43 -> 0 | M43: =J43*L43*K43*E43 -> 0 | N43: =M43 -> 0 | O43: =M43-N43 -> 0 | P43: 0 | Q43: 0 | R43: =L43 -> 0 | S43: =P43*R43*Q43*E43 -> 0 | T43: =S43 -> 0 | U43: =S43-T43 -> 0 | V43: 0 | W43: 0 | X43: =R43 -> 0 | Y43: =V43*X43*W43*K43 -> 0 | Z43: =Y43 -> 0 | AA43: =Y43-Z43 -> 0 | AB43: =H43+N43+T43+Z43 -> 0 | AC43: =I43+O43+U43+AA43 -> 0 | AD43: =AB43+AC43 -> 0
A44: Laptop Computers & Software | B44: 0 | C44: Unit | D44: 0 | E44: 1 | F44: 0 | G44: =B44*F44*D44*E44 -> 0 | H44: =G44 -> 0 | I44: =G44-H44 -> 0 | J44: 0 | K44: 0 | L44: =F44 -> 0 | M44: =J44*L44*K44*E44 -> 0 | N44: =M44 -> 0 | O44: =M44-N44 -> 0 | P44: 0 | Q44: 0 | R44: =L44 -> 0 | S44: =P44*R44*Q44*E44 -> 0 | T44: =S44 -> 0 | U44: =S44-T44 -> 0 | V44: 0 | W44: 0 | X44: =R44 -> 0 | Y44: =V44*X44*W44*K44 -> 0 | Z44: =Y44 -> 0 | AA44: =Y44-Z44 -> 0 | AB44: =H44+N44+T44+Z44 -> 0 | AC44: =I44+O44+U44+AA44 -> 0 | AD44: =AB44+AC44 -> 0
A45: Printer, Photocopier & Scanner | B45: 0 | C45: Unit | D45: 0 | E45: 1 | F45: 0 | G45: =B45*F45*D45*E45 -> 0 | H45: =G45 -> 0 | I45: =G45-H45 -> 0 | J45: 0 | K45: 0 | L45: =F45 -> 0 | M45: =J45*L45*K45*E45 -> 0 | N45: =M45 -> 0 | O45: =M45-N45 -> 0 | P45: 0 | Q45: 0 | R45: =L45 -> 0 | S45: =P45*R45*Q45*E45 -> 0 | T45: =S45 -> 0 | U45: =S45-T45 -> 0 | V45: 0 | W45: 0 | X45: =R45 -> 0 | Y45: =V45*X45*W45*K45 -> 0 | Z45: =Y45 -> 0 | AA45: =Y45-Z45 -> 0 | AB45: =H45+N45+T45+Z45 -> 0 | AC45: =I45+O45+U45+AA45 -> 0 | AD45: =AB45+AC45 -> 0
A46: XXX Supplies | B46: 0 | C46: Unit | D46: 0 | E46: 1 | F46: 0 | G46: =B46*F46*D46*E46 -> 0 | H46: =G46 -> 0 | I46: =G46-H46 -> 0 | J46: 0 | K46: 0 | L46: =F46 -> 0 | M46: =J46*L46*K46*E46 -> 0 | N46: =M46 -> 0 | O46: =M46-N46 -> 0 | P46: 0 | Q46: 0 | R46: =L46 -> 0 | S46: =P46*R46*Q46*E46 -> 0 | T46: =S46 -> 0 | U46: =S46-T46 -> 0 | V46: 0 | W46: 0 | X46: =R46 -> 0 | Y46: =V46*X46*W46*K46 -> 0 | Z46: =Y46 -> 0 | AA46: =Y46-Z46 -> 0 | AB46: =H46+N46+T46+Z46 -> 0 | AC46: =I46+O46+U46+AA46 -> 0 | AD46: =AB46+AC46 -> 0
A47: XXX Supplies | B47: 0 | C47: Unit | D47: 0 | E47: 1 | F47: 0 | G47: =B47*F47*D47*E47 -> 0 | H47: =G47 -> 0 | I47: =G47-H47 -> 0 | J47: 0 | K47: 0 | L47: =F47 -> 0 | M47: =J47*L47*K47*E47 -> 0 | N47: =M47 -> 0 | O47: =M47-N47 -> 0 | P47: 0 | Q47: 0 | R47: =L47 -> 0 | S47: =P47*R47*Q47*E47 -> 0 | T47: =S47 -> 0 | U47: =S47-T47 -> 0 | V47: 0 | W47: 0 | X47: =R47 -> 0 | Y47: =V47*X47*W47*K47 -> 0 | Z47: =Y47 -> 0 | AA47: =Y47-Z47 -> 0 | AB47: =H47+N47+T47+Z47 -> 0 | AC47: =I47+O47+U47+AA47 -> 0 | AD47: =AB47+AC47 -> 0
A48: Subtotal Supplies | G48: =SUM(G43:G47) -> 0 | H48: =SUM(H43:H47) -> 0 | I48: =SUM(I43:I47) -> 0 | M48: =SUM(M43:M47) -> 0 | N48: =SUM(N43:N47) -> 0 | O48: =SUM(O43:O47) -> 0 | S48: =SUM(S43:S47) -> 0 | T48: =SUM(T43:T47) -> 0 | U48: =SUM(U43:U47) -> 0 | Y48: =SUM(Y43:Y47) -> 0 | Z48: =SUM(Z43:Z47) -> 0 | AA48: =SUM(AA43:AA47) -> 0 | AB48: =SUM(AB43:AB47) -> 0 | AC48: =SUM(AC43:AC47) -> 0 | AD48: =SUM(AD43:AD47) -> 0
A49: Contractual
A50: Consultants to XXXX | B50: 0 | C50: Month | D50: 0 | E50: 1 | F50: 0 | G50: =B50*D50*E50*F50 -> 0 | H50: =G50 -> 0 | I50: =G50-H50 -> 0 | J50: =B50 -> 0 | K50: 0 | L50: =F50 -> 0 | M50: =J50*K50*L50*E50 -> 0 | N50: =M50 -> 0 | O50: 0 | P50: 0 | Q50: 0 | R50: =L50 -> 0 | S50: =P50*R50*Q50*E50 -> 0 | T50: =S50 -> 0 | U50: =S50-T50 -> 0 | V50: 0 | W50: 0 | X50: =R50 -> 0 | Y50: =V50*X50*W50*K50 -> 0 | Z50: =Y50 -> 0 | AA50: =Y50-Z50 -> 0 | AB50: =H50+N50+T50+Z50 -> 0 | AC50: =I50+O50+U50+AA50 -> 0 | AD50: =AB50+AC50 -> 0
A51: Consultants to XXXX | B51: 0 | C51: Month | D51: 0 | E51: 1 | F51: 0 | G51: =B51*D51*E51*F51 -> 0 | H51: =G51 -> 0 | I51: =G51-H51 -> 0 | J51: 0 | K51: 0 | L51: =F51 -> 0 | M51: =J51*K51*L51*E51 -> 0 | N51: =M51 -> 0 | O51: 0 | P51: 0 | Q51: 0 | R51: =L51 -> 0 | S51: =P51*R51*Q51*E51 -> 0 | T51: =S51 -> 0 | U51: =S51-T51 -> 0 | V51: 0 | W51: 0 | X51: =R51 -> 0 | Y51: =V51*X51*W51*K51 -> 0 | Z51: =Y51 -> 0 | AA51: =Y51-Z51 -> 0 | AB51: =H51+N51+T51+Z51 -> 0 | AC51: =I51+O51+U51+AA51 -> 0 | AD51: =AB51+AC51 -> 0
A52: Consultants to XXXX | B52: 0 | C52: Month | D52: 0 | E52: 1 | F52: 0 | G52: =B52*D52*E52*F52 -> 0 | H52: =G52 -> 0 | I52: =G52-H52 -> 0 | J52: 0 | K52: 0 | L52: =F52 -> 0 | M52: =E52*J52*K52*L52 -> 0 | N52: =M52 -> 0 | O52: =M52-N52 -> 0 | P52: 0 | Q52: 0 | R52: =L52 -> 0 | S52: =E52*P52*Q52*R52 -> 0 | T52: =S52 -> 0 | U52: =S52-T52 -> 0 | V52: 0 | W52: 0 | X52: =R52 -> 0 | Y52: =K52*V52*W52*X52 -> 0 | Z52: =Y52 -> 0 | AA52: =Y52-Z52 -> 0 | AB52: =H52+N52+T52+Z52 -> 0 | AC52: =I52+O52+U52+AA52 -> 0 | AD52: =AB52 -> 0
A53: Subaward (need to provide detailed breakdown) | B53: 0 | C53: Lumpsum | D53: 0 | E53: 1 | F53: 0 | G53: =B53*D53*E53*F53 -> 0 | H53: =G53 -> 0 | I53: =G53-H53 -> 0 | J53: =B53 -> 0 | K53: 0 | L53: =F53 -> 0 | M53: =J53*K53*L53*E53 -> 0 | N53: =M53 -> 0 | O53: 0 | P53: 0 | Q53: 0 | R53: =L53 -> 0 | S53: =P53*R53*Q53*E53 -> 0 | T53: =S53 -> 0 | U53: =S53-T53 -> 0 | V53: 0 | W53: 0 | X53: =R53 -> 0 | Y53: =V53*X53*W53*K53 -> 0 | Z53: =Y53 -> 0 | AA53: =Y53-Z53 -> 0 | AB53: =H53+N53+T53+Z53 -> 0 | AC53: =I53+O53+U53+AA53 -> 0 | AD53: =AB53+AC53 -> 0
A54: Subtotal Contractual | G54: =SUM(G50:G53) -> 0 | H54: =SUM(H50:H53) -> 0 | I54: =SUM(I50:I53) -> 0 | M54: =SUM(M50:M53) -> 0 | N54: =SUM(N50:N53) -> 0 | O54: =SUM(O50:O53) -> 0 | S54: =SUM(S50:S53) -> 0 | T54: =SUM(T50:T53) -> 0 | U54: =SUM(U50:U53) -> 0 | Y54: =SUM(Y50:Y53) -> 0 | Z54: =SUM(Z50:Z53) -> 0 | AA54: =SUM(AA50:AA53) -> 0 | AB54: =SUM(AB50:AB53) -> 0 | AC54: =SUM(AC50:AC53) -> 0 | AD54: =SUM(AD50:AD53) -> 0
A55: Other Direct Costs
A56: Objectives and Activities
A57: Banking and Cash Handling Fees | B57: 0 | C57: Month | D57: 0 | E57: 1 | F57: 0 | G57: =B57*F57*D57*E57 -> 0 | H57: =G57 -> 0 | I57: =G57-H57 -> 0 | J57: 0 | K57: 0 | L57: =F57 -> 0 | M57: =J57*L57*K57*E57 -> 0 | N57: =M57 -> 0 | O57: =M57-N57 -> 0 | P57: 0 | Q57: 0 | R57: =L57 -> 0 | S57: =P57*R57*Q57*E57 -> 0 | T57: =S57 -> 0 | U57: =S57-T57 -> 0 | V57: 0 | W57: 0 | X57: =R57 -> 0 | Y57: =V57*X57*W57*K57 -> 0 | Z57: =Y57 -> 0 | AA57: =Y57-Z57 -> 0 | AB57: =H57+N57+T57+Z57 -> 0 | AC57: =I57+O57+U57+AA57 -> 0 | AD57: =AB57+AC57 -> 0
A58: Communication Costs (internet, data, phones) | B58: 0 | C58: Month | D58: 0 | E58: 1 | F58: 0 | G58: =B58*F58*D58*E58 -> 0 | H58: =G58 -> 0 | I58: =G58-H58 -> 0 | J58: 0 | K58: 0 | L58: =F58 -> 0 | M58: =J58*L58*K58*E58 -> 0 | N58: =M58 -> 0 | O58: =M58-N58 -> 0 | P58: 0 | Q58: 0 | R58: =L58 -> 0 | S58: =P58*R58*Q58*E58 -> 0 | T58: =S58 -> 0 | U58: =S58-T58 -> 0 | V58: 0 | W58: 0 | X58: =R58 -> 0 | Y58: =V58*X58*W58*K58 -> 0 | Z58: =Y58 -> 0 | AA58: =Y58-Z58 -> 0 | AB58: =H58+N58+T58+Z58 -> 0 | AC58: =I58+O58+U58+AA58 -> 0 | AD58: =AB58+AC58 -> 0
A59: Timekeeping and expense reporting platform and other subscriptions | B59: 0 | C59: Month | D59: 0 | E59: 1 | F59: 0 | G59: =B59*F59*D59*E59 -> 0 | H59: =G59 -> 0 | I59: =G59-H59 -> 0 | J59: 0 | K59: 0 | L59: =F59 -> 0 | M59: =J59*L59*K59*E59 -> 0 | N59: =M59 -> 0 | O59: =M59-N59 -> 0 | P59: 0 | Q59: 0 | R59: =L59 -> 0 | S59: =P59*R59*Q59*E59 -> 0 | T59: =S59 -> 0 | U59: =S59-T59 -> 0 | V59: 0 | W59: 0 | X59: =R59 -> 0 | Y59: =V59*X59*W59*K59 -> 0 | Z59: =Y59 -> 0 | AA59: =Y59-Z59 -> 0 | AB59: =H59+N59+T59+Z59 -> 0 | AC59: =I59+O59+U59+AA59 -> 0 | AD59: =AB59+AC59 -> 0
A60: Payroll Processing | B60: 0 | C60: Month | D60: 0 | E60: 1 | F60: 0 | G60: =B60*F60*D60*E60 -> 0 | H60: =G60 -> 0 | I60: =G60-H60 -> 0 | J60: 0 | K60: 0 | L60: =F60 -> 0 | M60: =J60*L60*K60*E60 -> 0 | N60: =M60 -> 0 | O60: =M60-N60 -> 0 | P60: 0 | Q60: 0 | R60: =L60 -> 0 | S60: =P60*R60*Q60*E60 -> 0 | T60: =S60 -> 0 | U60: =S60-T60 -> 0 | V60: 0 | W60: 0 | X60: =R60 -> 0 | Y60: =V60*X60*W60*K60 -> 0 | Z60: =Y60 -> 0 | AA60: =Y60-Z60 -> 0 | AB60: =H60+N60+T60+Z60 -> 0 | AC60: =I60+O60+U60+AA60 -> 0 | AD60: =AB60+AC60 -> 0
A61: Recruitment, Procurement & Advertising Fees | B61: 0 | C61: Year | D61: 0 | E61: 1 | F61: 0 | G61: =B61*F61*D61*E61 -> 0 | H61: =G61 -> 0 | I61: =G61-H61 -> 0 | J61: 0 | K61: 0 | L61: =F61 -> 0 | M61: =J61*L61*K61*E61 -> 0 | N61: =M61 -> 0 | O61: =M61-N61 -> 0 | P61: 0 | Q61: 0 | R61: =L61 -> 0 | S61: =P61*R61*Q61*E61 -> 0 | T61: =S61 -> 0 | U61: =S61-T61 -> 0 | V61: 0 | W61: 0 | X61: =R61 -> 0 | Y61: =V61*X61*W61*K61 -> 0 | Z61: =Y61 -> 0 | AA61: =Y61-Z61 -> 0 | AB61: =H61+N61+T61+Z61 -> 0 | AC61: =I61+O61+U61+AA61 -> 0 | AD61: =AB61+AC61 -> 0
A62: Legal Fees | B62: 0 | C62: Year | D62: 0 | E62: 1 | F62: 0 | G62: =B62*F62*D62*E62 -> 0 | H62: =G62 -> 0 | I62: =G62-H62 -> 0 | J62: 0 | K62: 0 | L62: =F62 -> 0 | M62: =J62*L62*K62*E62 -> 0 | N62: =M62 -> 0 | O62: =M62-N62 -> 0 | P62: 0 | Q62: 0 | R62: =L62 -> 0 | S62: =P62*R62*Q62*E62 -> 0 | T62: =S62 -> 0 | U62: =S62-T62 -> 0 | V62: 0 | W62: 0 | X62: =R62 -> 0 | Y62: =V62*X62*W62*K62 -> 0 | Z62: =Y62 -> 0 | AA62: =Y62-Z62 -> 0 | AB62: =H62+N62+T62+Z62 -> 0 | AC62: =I62+O62+U62+AA62 -> 0 | AD62: =AB62+AC62 -> 0
A63: O1: XXX
B64: 0 | C64: Training | D64: 0 | E64: 1 | F64: 0 | G64: =B64*D64*F64*E64 -> 0 | H64: =G64 -> 0 | I64: =G64-H64 -> 0 | J64: 0 | K64: 0 | L64: =F64 -> 0 | M64: =J64*K64*L64*E64 -> 0 | N64: =M64 -> 0 | O64: =M64-N64 -> 0 | P64: 0 | Q64: 0 | R64: =L64 -> 0 | S64: =P64*Q64*R64*E64 -> 0 | T64: =S64 -> 0 | U64: =S64-T64 -> 0 | V64: 0 | W64: 0 | X64: =R64 -> 0 | Y64: =V64*W64*X64*K64 -> 0 | Z64: =Y64 -> 0 | AA64: =Y64-Z64 -> 0 | AB64: =H64+N64+T64+Z64 -> 0 | AC64: =I64+O64+U64+AA64 -> 0 | AD64: =AB64+AC64 -> 0
B65: 0 | C65: Unit | D65: 0 | E65: 1 | F65: 0 | G65: =B65*D65*E65*F65 -> 0 | H65: =G65 -> 0 | I65: =G65-H65 -> 0 | J65: 0 | K65: 0 | L65: =F65 -> 0 | M65: =E65*J65*K65*L65 -> 0 | N65: =M65 -> 0 | O65: =M65-N65 -> 0 | P65: 0 | Q65: 0 | R65: =L65 -> 0 | S65: =E65*P65*Q65*R65 -> 0 | T65: =S65 -> 0 | U65: =S65-T65 -> 0 | V65: 0 | W65: 0 | X65: =R65 -> 0 | Y65: =K65*V65*W65*X65 -> 0 | Z65: =Y65 -> 0 | AA65: =Y65-Z65 -> 0 | AB65: =H65+N65+T65+Z65 -> 0 | AC65: =I65+O65+U65+AA65 -> 0 | AD65: =AB65 -> 0
B66: 0 | C66: Unit | D66: 0 | E66: 1 | F66: 0 | G66: =B66*D66*E66*F66 -> 0 | H66: =G66 -> 0 | I66: =G66-H66 -> 0 | J66: 0 | K66: 0 | L66: =F66 -> 0 | M66: =E66*J66*K66*L66 -> 0 | N66: =M66 -> 0 | O66: =M66-N66 -> 0 | P66: 0 | Q66: 0 | R66: =L66 -> 0 | S66: =E66*P66*Q66*R66 -> 0 | T66: =S66 -> 0 | U66: =S66-T66 -> 0 | V66: 0 | W66: 0 | X66: =R66 -> 0 | Y66: =K66*V66*W66*X66 -> 0 | Z66: =Y66 -> 0 | AA66: =Y66-Z66 -> 0 | AB66: =H66+N66+T66+Z66 -> 0 | AC66: =I66+O66+U66+AA66 -> 0 | AD66: =AB66 -> 0
B67: 0 | C67: Training | D67: 0 | E67: 1 | F67: 0 | G67: =B67*D67*F67*E67 -> 0 | H67: =G67 -> 0 | I67: =G67-H67 -> 0 | J67: 0 | K67: 0 | L67: =F67 -> 0 | M67: =J67*K67*L67*E67 -> 0 | N67: =M67 -> 0 | O67: =M67-N67 -> 0 | P67: 0 | Q67: 0 | R67: =L67 -> 0 | S67: =P67*Q67*R67*E67 -> 0 | T67: =S67 -> 0 | U67: =S67-T67 -> 0 | V67: 0 | W67: 0 | X67: =R67 -> 0 | Y67: =V67*W67*X67*K67 -> 0 | Z67: =Y67 -> 0 | AA67: =Y67-Z67 -> 0 | AB67: =H67+N67+T67+Z67 -> 0 | AC67: =I67+O67+U67+AA67 -> 0 | AD67: =AB67+AC67 -> 0
A68: O2: XXXX
B69: 0 | C69: Meeting | D69: 0 | E69: 1 | F69: 0 | G69: =B69*D69*E69*F69 -> 0 | H69: =G69 -> 0 | I69: =G69-H69 -> 0 | J69: 0 | K69: 0 | L69: =F69 -> 0 | M69: =E69*J69*K69*L69 -> 0 | N69: =M69 -> 0 | O69: =M69-N69 -> 0 | P69: 0 | Q69: 0 | R69: =L69 -> 0 | S69: =E69*P69*Q69*R69 -> 0 | T69: =S69 -> 0 | U69: =S69-T69 -> 0 | V69: 0 | W69: 0 | X69: =R69 -> 0 | Y69: =K69*V69*W69*X69 -> 0 | Z69: =Y69 -> 0 | AA69: =Y69-Z69 -> 0 | AB69: =H69+N69+T69+Z69 -> 0 | AC69: =I69+O69+U69+AA69 -> 0 | AD69: =AB69 -> 0
B70: 0 | C70: Workshop | D70: 0 | E70: 1 | F70: 0 | G70: =B70*D70*E70*F70 -> 0 | H70: =G70 -> 0 | I70: =G70-H70 -> 0 | J70: 0 | K70: 0 | L70: =F70 -> 0 | M70: =E70*J70*K70*L70 -> 0 | N70: =M70 -> 0 | O70: =M70-N70 -> 0 | P70: 0 | Q70: 0 | R70: =L70 -> 0 | S70: =E70*P70*Q70*R70 -> 0 | T70: =S70 -> 0 | U70: =S70-T70 -> 0 | V70: 0 | W70: 0 | X70: =R70 -> 0 | Y70: =K70*V70*W70*X70 -> 0 | Z70: =Y70 -> 0 | AA70: =Y70-Z70 -> 0 | AB70: =H70+N70+T70+Z70 -> 0 | AC70: =I70+O70+U70+AA70 -> 0 | AD70: =AB70 -> 0
B71: 0 | C71: Day | D71: 0 | E71: 1 | F71: 0 | G71: =B71*D71*E71*F71 -> 0 | H71: =G71 -> 0 | I71: =G71-H71 -> 0 | J71: 0 | K71: 0 | L71: =F71 -> 0 | M71: =E71*J71*K71*L71 -> 0 | N71: =M71 -> 0 | O71: =M71-N71 -> 0 | P71: 0 | Q71: 0 | R71: =L71 -> 0 | S71: =E71*P71*Q71*R71 -> 0 | T71: =S71 -> 0 | U71: =S71-T71 -> 0 | V71: 0 | W71: 0 | X71: =R71 -> 0 | Y71: =K71*V71*W71*X71 -> 0 | Z71: =Y71 -> 0 | AA71: =Y71-Z71 -> 0 | AB71: =H71+N71+T71+Z71 -> 0 | AC71: =I71+O71+U71+AA71 -> 0 | AD71: =AB71 -> 0
B72: 0 | C72: Unit | D72: 0 | E72: 1 | F72: 0 | G72: =B72*D72*E72*F72 -> 0 | H72: =G72 -> 0 | I72: =G72-H72 -> 0 | J72: 0 | K72: 0 | L72: =F72 -> 0 | M72: =E72*J72*K72*L72 -> 0 | N72: =M72 -> 0 | O72: =M72-N72 -> 0 | P72: 0 | Q72: 0 | R72: =L72 -> 0 | S72: =E72*P72*Q72*R72 -> 0 | T72: =S72 -> 0 | U72: =S72-T72 -> 0 | V72: 0 | W72: 0 | X72: =R72 -> 0 | Y72: =K72*V72*W72*X72 -> 0 | Z72: =Y72 -> 0 | AA72: =Y72-Z72 -> 0 | AB72: =H72+N72+T72+Z72 -> 0 | AC72: =I72+O72+U72+AA72 -> 0 | AD72: =AB72 -> 0
B73: 0 | C73: Workshop | D73: 0 | E73: 1 | F73: 0 | G73: =B73*D73*E73*F73 -> 0 | H73: =G73 -> 0 | I73: =G73-H73 -> 0 | J73: 0 | K73: 0 | L73: =F73 -> 0 | M73: =E73*J73*K73*L73 -> 0 | N73: =M73 -> 0 | O73: =M73-N73 -> 0 | P73: 0 | Q73: 0 | R73: =L73 -> 0 | S73: =E73*P73*Q73*R73 -> 0 | T73: =S73 -> 0 | U73: =S73-T73 -> 0 | V73: 0 | W73: 0 | X73: =R73 -> 0 | Y73: =K73*V73*W73*X73 -> 0 | Z73: =Y73 -> 0 | AA73: =Y73-Z73 -> 0 | AB73: =H73+N73+T73+Z73 -> 0 | AC73: =I73+O73+U73+AA73 -> 0 | AD73: =AB73 -> 0
A74: O3: XXX
B75: 0 | C75: Training | D75: 0 | E75: 1 | F75: 0 | G75: =B75*D75*F75*E75 -> 0 | H75: =G75 -> 0 | I75: =G75-H75 -> 0 | J75: 0 | K75: 0 | L75: =F75 -> 0 | M75: =J75*K75*L75*E75 -> 0 | N75: =M75 -> 0 | O75: =M75-N75 -> 0 | P75: 0 | Q75: 0 | R75: =L75 -> 0 | S75: =P75*Q75*R75*E75 -> 0 | T75: =S75 -> 0 | U75: =S75-T75 -> 0 | V75: 0 | W75: 0 | X75: =R75 -> 0 | Y75: =V75*W75*X75*K75 -> 0 | Z75: =Y75 -> 0 | AA75: =Y75-Z75 -> 0 | AB75: =H75+N75+T75+Z75 -> 0 | AC75: =I75+O75+U75+AA75 -> 0 | AD75: =AB75+AC75 -> 0
B76: 0 | C76: Training | D76: 0 | E76: 1 | F76: 0 | G76: =B76*D76*E76*F76 -> 0 | H76: =G76 -> 0 | I76: =G76-H76 -> 0 | J76: 0 | K76: 0 | L76: =F76 -> 0 | M76: =E76*J76*K76*L76 -> 0 | N76: =M76 -> 0 | O76: =M76-N76 -> 0 | P76: 0 | Q76: 0 | R76: =L76 -> 0 | S76: =E76*P76*Q76*R76 -> 0 | T76: =S76 -> 0 | U76: =S76-T76 -> 0 | V76: 0 | W76: 0 | X76: =R76 -> 0 | Y76: =K76*V76*W76*X76 -> 0 | Z76: =Y76 -> 0 | AA76: =Y76-Z76 -> 0 | AB76: =H76+N76+T76+Z76 -> 0 | AC76: =I76+O76+U76+AA76 -> 0 | AD76: =AB76 -> 0
B77: 0 | C77: Year | D77: 0 | E77: 1 | F77: 0 | G77: =B77*D77*F77*E77 -> 0 | H77: =G77 -> 0 | I77: =G77-H77 -> 0 | J77: 0 | K77: 0 | L77: =F77 -> 0 | M77: =J77*K77*L77*E77 -> 0 | N77: =M77 -> 0 | O77: =M77-N77 -> 0 | P77: 0 | Q77: 0 | R77: =L77 -> 0 | S77: =P77*Q77*R77*E77 -> 0 | T77: =S77 -> 0 | U77: =S77-T77 -> 0 | V77: 0 | W77: 0 | X77: =R77 -> 0 | Y77: =V77*W77*X77*K77 -> 0 | Z77: =Y77 -> 0 | AA77: =Y77-Z77 -> 0 | AB77: =H77+N77+T77+Z77 -> 0 | AC77: =I77+O77+U77+AA77 -> 0 | AD77: =AB77+AC77 -> 0
B78: 0 | C78: Unit | D78: 0 | E78: 1 | F78: 0 | G78: =B78*D78*F78*E78 -> 0 | H78: =G78 -> 0 | I78: =G78-H78 -> 0 | J78: 0 | K78: 0 | L78: =F78 -> 0 | M78: =J78*K78*L78*E78 -> 0 | N78: =M78 -> 0 | O78: =M78-N78 -> 0 | P78: 0 | Q78: 0 | R78: =L78 -> 0 | S78: =P78*Q78*R78*E78 -> 0 | T78: =S78 -> 0 | U78: =S78-T78 -> 0 | V78: 0 | W78: 0 | X78: =R78 -> 0 | Y78: =V78*W78*X78*K78 -> 0 | Z78: =Y78 -> 0 | AA78: =Y78-Z78 -> 0 | AB78: =H78+N78+T78+Z78 -> 0 | AC78: =I78+O78+U78+AA78 -> 0 | AD78: =AB78+AC78 -> 0
B79: 0 | C79: Training | D79: 0 | E79: 1 | F79: 0 | G79: =B79*D79*E79*F79 -> 0 | H79: =G79 -> 0 | I79: =G79-H79 -> 0 | J79: 0 | K79: 0 | L79: =F79 -> 0 | M79: =E79*J79*K79*L79 -> 0 | N79: =M79 -> 0 | O79: =M79-N79 -> 0 | P79: 0 | Q79: 0 | R79: =L79 -> 0 | S79: =E79*P79*Q79*R79 -> 0 | T79: =S79 -> 0 | U79: =S79-T79 -> 0 | V79: 0 | W79: 0 | X79: =R79 -> 0 | Y79: =K79*V79*W79*X79 -> 0 | Z79: =Y79 -> 0 | AA79: =Y79-Z79 -> 0 | AB79: =H79+N79+T79+Z79 -> 0 | AC79: =I79+O79+U79+AA79 -> 0 | AD79: =AB79 -> 0
A80: Monitoring, Evaluation, Research, and Learning
A81: M&E Materials & Database Development | B81: 0 | C81: Year | D81: 0 | E81: 1 | F81: 0 | G81: =B81*D81*F81 -> 0 | H81: =G81 -> 0 | I81: =G81-H81 -> 0 | J81: 0 | K81: 0 | L81: =F81 -> 0 | M81: =J81*K81*L81 -> 0 | N81: =M81 -> 0 | O81: =M81-N81 -> 0 | P81: 0 | Q81: 0 | R81: =L81 -> 0 | S81: =P81*Q81*R81 -> 0 | T81: =S81 -> 0 | U81: =S81-T81 -> 0 | V81: 0 | W81: 0 | X81: =R81 -> 0 | Y81: =V81*W81*X81 -> 0 | Z81: =Y81 -> 0 | AA81: =Y81-Z81 -> 0 | AB81: =H81+N81+T81+Z81 -> 0 | AC81: =I81+O81+U81+AA81 -> 0 | AD81: =AB81+AC81 -> 0
A82: M&E Training and Coordination Meetings | B82: 0 | C82: Meetings | D82: 0 | E82: 1 | F82: 0 | G82: =B82*D82*F82 -> 0 | H82: =G82 -> 0 | I82: =G82-H82 -> 0 | J82: 0 | K82: 0 | L82: =F82 -> 0 | M82: =J82*K82*L82 -> 0 | N82: =M82 -> 0 | O82: =M82-N82 -> 0 | P82: 0 | Q82: 0 | R82: =L82 -> 0 | S82: =P82*Q82*R82 -> 0 | T82: =S82 -> 0 | U82: =S82-T82 -> 0 | V82: 0 | W82: 0 | X82: =R82 -> 0 | Y82: =V82*W82*X82 -> 0 | Z82: =Y82 -> 0 | AA82: =Y82-Z82 -> 0 | AB82: =H82+N82+T82+Z82 -> 0 | AC82: =I82+O82+U82+AA82 -> 0 | AD82: =AB82+AC82 -> 0
A83: External Midline Evaluation | B83: 0 | C83: Lumpsum | D83: 0 | E83: 1 | F83: 0 | G83: =B83*D83*F83 -> 0 | H83: =G83 -> 0 | I83: =G83-H83 -> 0 | J83: 0 | K83: 0 | L83: =F83 -> 0 | M83: =J83*K83*L83 -> 0 | N83: =M83 -> 0 | O83: =M83-N83 -> 0 | P83: 0 | Q83: 0 | R83: =L83 -> 0 | S83: =P83*Q83*R83 -> 0 | T83: =S83 -> 0 | U83: =S83-T83 -> 0 | V83: 0 | W83: 0 | X83: =R83 -> 0 | Y83: =V83*W83*X83 -> 0 | Z83: =Y83 -> 0 | AA83: =Y83-Z83 -> 0 | AB83: =H83+N83+T83+Z83 -> 0 | AC83: =I83+O83+U83+AA83 -> 0 | AD83: =AB83+AC83 -> 0
A84: External Final Evaluation | B84: 0 | C84: Lumpsum | D84: 0 | E84: 1 | F84: 0 | G84: =B84*D84*F84 -> 0 | H84: =G84 -> 0 | I84: =G84-H84 -> 0 | J84: 0 | K84: 0 | L84: =F84 -> 0 | M84: =J84*K84*L84 -> 0 | N84: =M84 -> 0 | O84: =M84-N84 -> 0 | P84: 0 | Q84: 0 | R84: =L84 -> 0 | S84: =P84*Q84*R84 -> 0 | T84: =S84 -> 0 | U84: =S84-T84 -> 0 | V84: 0 | W84: 0 | X84: =R84 -> 0 | Y84: =V84*W84*X84 -> 0 | Z84: =Y84 -> 0 | AA84: =Y84-Z84 -> 0 | AB84: =H84+N84+T84+Z84 -> 0 | AC84: =I84+O84+U84+AA84 -> 0 | AD84: =AB84+AC84 -> 0
A85: Sub Total Other Direct Costs | G85: =SUM(G57:G84) -> 0 | H85: =SUM(H57:H84) -> 0 | I85: =SUM(I57:I84) -> 0 | M85: =SUM(M57:M84) -> 0 | N85: =SUM(N57:N84) -> 0 | O85: =SUM(O57:O84) -> 0 | S85: =SUM(S57:S84) -> 0 | T85: =SUM(T57:T84) -> 0 | U85: =SUM(U57:U84) -> 0 | Y85: =SUM(Y57:Y84) -> 0 | Z85: =SUM(Z57:Z84) -> 0 | AA85: =SUM(AA57:AA84) -> 0 | AB85: =SUM(AB57:AB84) -> 0 | AC85: =SUM(AC57:AC84) -> 0 | AD85: =SUM(AD57:AD84) -> 0
A86: Total Direct Costs | G86: =G16+G25+G41+G48+G54+G85 -> 0 | H86: =H16+H25+H41+H48+H54+H85 -> 0 | I86: =I16+I25+I41+I48+I54+I85 -> 0 | M86: =M16+M25+M41+M48+M54+M85 -> 0 | N86: =N16+N25+N41+N48+N54+N85 -> 0 | O86: =O16+O25+O41+O48+O54+O85 -> 0 | S86: =S16+S25+S41+S48+S54+S85 -> 0 | T86: =T16+T25+T41+T48+T54+T85 -> 0 | U86: =U16+U25+U41+U48+U54+U85 -> 0 | Y86: =Y16+Y25+Y41+Y48+Y54+Y85 -> 0 | Z86: =Z16+Z25+Z41+Z48+Z54+Z85 -> 0 | AA86: =AA16+AA25+AA41+AA48+AA54+AA85 -> 0 | AB86: =AB16+AB25+AB41+AB48+AB54+AB85 -> 0 | AC86: =AC16+AC25+AC41+AC48+AC54+AC85 -> 0 | AD86: =AD16+AD25+AD41+AD48+AD54+AD85 -> 0
A87: Indirect Cost (28.69% NICRA rate) | C87: 0.2828 | G87: =G86*$C$87 -> 0 | H87: =G87 -> 0 | I87: =G87-H87 -> 0 | M87: =M86*$C$87 -> 0 | N87: =M87 -> 0 | O87: =M87-N87 -> 0 | S87: =S86*$C$87 -> 0 | T87: =S87 -> 0 | U87: =S87-T87 -> 0 | Y87: =Y86*$C$87 -> 0 | Z87: =Y87 -> 0 | AA87: =Y87-Z87 -> 0 | AB87: =H87+N87+T87+Z87 -> 0 | AC87: =I87+O87+U87+AA87 -> 0 | AD87: =AB87+AC87 -> 0
A88: Total Indirect Cost | G88: =G87 -> 0 | H88: =H87 -> 0 | I88: =I87 -> 0 | M88: =M87 -> 0 | N88: =N87 -> 0 | O88: =O87 -> 0 | S88: =S87 -> 0 | T88: =T87 -> 0 | U88: =U87 -> 0 | Y88: =Y87 -> 0 | Z88: =Z87 -> 0 | AA88: =AA87 -> 0 | AB88: =AB87 -> 0 | AC88: =AC87 -> 0 | AD88: =AD87 -> 0
A89: GRAND TOTAL | G89: =G86+G88 -> 0 | H89: =H86+H88 -> 0 | I89: =I86+I88 -> 0 | M89: =M86+M88 -> 0 | N89: =N86+N88 -> 0 | O89: =O86+O88 -> 0 | S89: =S86+S88 -> 0 | T89: =T86+T88 -> 0 | U89: =U86+U88 -> 0 | Y89: =Y86+Y88 -> 0 | Z89: =Z86+Z88 -> 0 | AA89: =AA86+AA88 -> 0 | AB89: =AB86+AB88 -> 0 | AC89: =AC86+AC88 -> 0 | AD89: =AD86+AD88 -> 0
