Workbook

Sheet 2. Summary Budget
A1: Summary Budget
A2: Partners of the Americas
A3: PROJECT NAME
A4: 12 Months
D6: Requested Federal Funds
A8: A | C8: Personnel | D8: ='3. Detailed Budget'!H16 -> 0
A9: B | C9: Fringe Benefits | D9: ='3. Detailed Budget'!H20 -> 0
A10: C | C10: Travel | D10: ='3. Detailed Budget'!H31 -> 0
A11: D | C11: Equipment | D11: ='3. Detailed Budget'!H32 -> 0
A12: E | C12: Supplies | D12: ='3. Detailed Budget'!H35 -> 0
A13: F | C13: Contractual | D13: ='3. Detailed Budget'!H40 -> 0
A14: G | C14: Construction | D14: ='3. Detailed Budget'!H41 -> 0
A15: H | C15: Other Direct Costs | D15: ='3. Detailed Budget'!H62 -> 0
A16: I | C16: Total Direct charges | D16: =SUM(D8:D15) -> 0
A17: J | C17: Total Indirect costs | D17: ='3. Detailed Budget'!H64 -> 0
A18: K | C18: Total Project Cost | D18: =SUM(D16:D17) -> 0
A19: L | C19: Cost Share (if applicable) | D19: ='3. Detailed Budget'!J65 -> 0
A21: * line item amounts auto-fill from "Detailed Grant Budget Template" tab

Sheet 3. Detailed Budget
A1: LINE-ITEM BUDGET
A2: Partners of the Americas - PROJECT NAME | F2: Project Title
A3: Project Duration: 12 months | F3: Project duration
A4: *Key personnel
D5: Unit Cost | H5: Requested Federal Funds | J5: Cost-Share by Applicant | L5: Program Total
D6: Unit | E6: Number | F6: Amount | G6: Rate
A7: A | C7: Personnel | D7: months or years | F7: salary (monthly) | G7: % effort for Personnel ONLY
A8: A.1 | C8: US-Based personnel
A9: A.1.1 | C9: VP of Programs | D9: months | E9: 1 | F9: 0 | G9: 1 | H9: =ROUND((E9*F9)*G9,0) -> 0 | J9: 0 | L9: =H9+J9 -> 0
A10: A.1.2 | C10: Program Director* | D10: months | E10: 1 | F10: 0 | G10: 1 | H10: =ROUND((E10*F10)*G10,0) -> 0 | J10: 0 | L10: =H10+J10 -> 0
A11: A.1.3 | C11: Associate Director | D11: months | E11: 1 | F11: 0 | G11: 1 | H11: =ROUND((E11*F11)*G11,0) -> 0 | J11: 0 | L11: =H11+J11 -> 0
A12: A.1.4 | C12: Program Officer | D12: months | E12: 1 | F12: 0 | G12: 1 | H12: =ROUND((E12*F12)*G12,0) -> 0 | J12: 0 | L12: =H12+J12 -> 0
A13: A.2 | C13: XXX-Based personnel
A14: A.2.1 | C14: Program Coordinator | D14: months | E14: 1 | F14: 0 | G14: 1 | H14: =ROUND((E14*F14)*G14,0) -> 0 | J14: 0 | L14: =H14+J14 -> 0
A15: A.2.2 | C15: MEL Officer | D15: months | E15: 1 | F15: 0 | G15: 1 | H15: =ROUND((E15*F15)*G15,0) -> 0 | J15: 0 | L15: =H15+J15 -> 0
A16: Subtotal Personnel | H16: =SUM(H9:H15) -> 0 | J16: =SUM(J9:J15) -> 0 | L16: =H16+J16 -> 0
A17: B | C17: Fringe Benefits
A18: B.1 | C18: US-Based Personnel Fringe Benefits | G18: 0.2347 | H18: =ROUND((SUM(H9:H12))*G18,0) -> 0 | J18: 0 | L18: =H18+J18 -> 0
A19: B.2 | C19: XX-Based Personnel Fringe Benefits | G19: 0 | H19: =ROUND((SUM(H14:H15))*G19,0) -> 0 | J19: =ROUND(J16*G19,0) -> 0 | L19: =H19+J19 -> 0
A20: Subtotal Fringe Benefits | H20: =SUM(H18:H19) -> 0 | J20: =SUM(J18:J19) -> 0 | L20: =SUM(L18:L19) -> 0
A21: C | C21: Travel | D21: # people | E21: # trips/or days | F21: unit Cost
A22: C.1 | C22: Staff Travel
A23: C.1.1 | C23: International Round Trip Airfare | D23: 1 | E23: 1 | F23: 0 | H23: =D23*16*F23 -> 0 | J23: =F23*17*D23 -> 0 | L23: =H23+J23 -> 0
A24: C.1.2 | C24: International M&IE | D24: 1 | E24: 2 | F24: 0 | H24: =D24*67*F24 -> 0 | J24: =F24*67*D24 -> 0 | L24: =H24+J24 -> 0
A25: C.1.3 | C25: International Lodging | D25: 1 | E25: =E24 -> 2 | F25: 0 | H25: =D25*67*F25 -> 0 | J25: =F25*67*D25 -> 0 | L25: =H25+J25 -> 0
A26: C.1.4 | C26: International Local Transportation | D26: 1 | E26: =E24 -> 2 | F26: 0 | H26: =D26*67*F26 -> 0 | J26: =F26*67*D26 -> 0 | L26: =H26+J26 -> 0
A27: C.1.5 | C27: Domestic Round Trip Airfare | D27: 1 | E27: 1 | F27: 0 | H27: =D27*18*F27 -> 0 | J27: =F27*14*D27 -> 0 | L27: =H27+J27 -> 0
A28: C.1.6 | C28: Domestic M&IE | D28: 1 | E28: 2 | F28: 0 | H28: =D28*80*F28 -> 0 | J28: =F28*53*D28 -> 0 | L28: =H28+J28 -> 0
A29: C.1.7 | C29: Domestic Lodging | D29: 1 | E29: =E28 -> 2 | F29: 0 | H29: =D29*80*F29 -> 0 | J29: =F29*53*D29 -> 0 | L29: =H29+J29 -> 0
A30: C.1.8 | C30: Domestic Local Transportation | D30: 1 | E30: =E28 -> 2 | F30: 0 | H30: =D30*80*F30 -> 0 | J30: =F30*53*D30 -> 0 | L30: =H30+J30 -> 0
A31: Subtotal Travel | H31: =SUM(H23:H30) -> 0 | J31: =SUM(J23:J30) -> 0 | L31: =H31+J31 -> 0
A32: D | C32: Equipment (> $5,000 per unit ) | D32: unit | E32: # units | F32: unit cost
A33: E | C33: Supplies (< $5,000 per unit) | D33: unit | E33: # units | F33: unit cost
A34: E.1 | C34: XXX | D34: unit | E34: 1 | F34: 0 | H34: =E34*F34 -> 0 | L34: =H34+J34 -> 0
A35: Subtotal Supplies | H35: =H34 -> 0 | J35: =J34 -> 0 | L35: =H35+J35 -> 0
A36: F | C36: Contractual (Subrecipients, Subcontracts, and Consultant fees)
A37: F.1 | C37: Consultants and Contracts
A38: F.1.1 | C38: XXX Contract | D38: months | E38: 1 | F38: 0 | H38: =F38*E38 -> 0 | J38: 0 | L38: =H38+J38 -> 0
A39: F.1.2 | C39: XXXX Consultant | D39: months | E39: 1 | F39: 0 | H39: 0 | J39: 0 | L39: =H39+J39 -> 0
A40: Subtotal Contractual | H40: =SUM(H37:H39) -> 0 | J40: =SUM(J37:J39) -> 0 | L40: =H40+J40 -> 0
A41: G | C41: Construction
A42: H | C42: Other Direct Costs
A43: H.1 | C43: Outreach/Branded Materials | D43: bulk | E43: 1 | F43: 0 | H43: =E43*F43 -> 0 | J43: 0 | L43: =H43+J43 -> 0
A44: H.2 | C44: Printing & Postage | D44: bulk | E44: 1 | F44: 0 | H44: =E44*F44 -> 0 | J44: 0 | L44: =H44+J44 -> 0
A45: H.3 | C45: Translation Costs | D45: documents | E45: 1 | F45: 0 | H45: =E45*F45 -> 0 | J45: 0 | L45: =H45+J45 -> 0
A46: H.4 | C46: Grants Management System | D46: months | E46: 1 | F46: 0 | H46: =E46*F46 -> 0 | J46: 0 | L46: =H46+J46 -> 0
A47: H.5 | C47: Network Management System | D47: months | E47: 1 | F47: 0 | H47: =E47*F47 -> 0 | J47: 0 | L47: =H47+J47 -> 0
A48: H.6 | C48: Data Tracking & Collection (M&E) | D48: hours | E48: 1 | F48: 0 | H48: =E48*F48 -> 0 | J48: 0 | L48: =H48+J48 -> 0
A49: H.7 | C49: Platform Subscriptions | D49: years | E49: 1 | F49: 0 | H49: =E49*F49 -> 0 | J49: 0 | L49: =H49+J49 -> 0
A50: H.8 | C50: Workshops
A51: H.8.1 | C51: Space Rental | D51: venue | E51: 1 | F51: 0 | H51: =E51*F51 -> 0 | J51: 0 | L51: =H51+J51 -> 0
A52: H.8.2 | C52: Printed Materials | D52: events | E52: 1 | F52: 0 | H52: =E52*F52 -> 0 | J52: 0 | L52: =H52+J52 -> 0
A53: H.8.3 | C53: Working Meals | D53: persons | E53: 1 | F53: 0 | H53: =E53*F53 -> 0 | J53: 0 | L53: =H53+J53 -> 0
A54: H.8.4 | C54: Audio-Visual Equipment Rental | D54: bulk | E54: 1 | F54: 0 | H54: =E54*F54 -> 0 | J54: 0 | L54: =H54+J54 -> 0
A55: H.9 | C55: Conference Registrations
A56: H.9.1 | C56: International Conference Registration Fees | D56: events | E56: 1 | F56: 0 | H56: =E56*F56 -> 0 | J56: 0 | L56: =H56+J56 -> 0
A57: H.9.2 | C57: U.S. Conference Registration Fees | D57: events | E57: 1 | F57: 0 | H57: =E57*F57 -> 0 | J57: 0 | L57: =H57+J57 -> 0
A58: H.10 | C58: Media/Digital Engagement
A59: H.10.1 | C59: Digital Education Platform | D59: module | E59: 1 | F59: 0 | H59: =E59*F59 -> 0 | J59: 0 | L59: =H59+J59 -> 0
A60: H.10.2 | C60: Virtual Orientation/Country Exploration Modules | D60: module | E60: 1 | F60: 0 | H60: =E60*F60 -> 0 | J60: 0 | L60: =H60+J60 -> 0
A61: H.10.3 | C61: Paid Digital Media Placement | D61: ads | E61: 1 | F61: 0 | H61: =E61*F61 -> 0 | J61: 0 | L61: =H61+J61 -> 0
A62: Subtotal Other Direct Costs | H62: =SUM(H43:H61) -> 0 | J62: =SUM(J43:J61) -> 0 | L62: =H62+J62 -> 0
A63: I | C63: Total Direct Costs | H63: =H16+H20+H31+H40+H62+H35 -> 0 | J63: =J16+J20+J31+J40+J62+J35 -> 0 | L63: =H63+J63 -> 0
A64: J | C64: Indirect Costs | D64: 0.2828 | H64: =ROUNDDOWN(H63*D64,0) -> 0 | J64: 0 | L64: =H64+J64 -> 0
A65: K | C65: Total Project Cost | H65: =SUM(H63:H64) -> 0 | J65: =SUM(J63:J64) -> 0 | L65: =H65+J65 -> 0
