Workbook
Name __pd1: [1]Rates!$J$24
Name __pd6: [1]Rates!$J$30
Name __tix1: [1]Rates!$J$40
Name __tix2: [1]Rates!$J$41
Name __tix6: [1]Rates!$J$47
Name ANPDH: '[2]Salary & PR Tax'!#REF!
Name Board: '[3]Schedule E - Other'!$F$102
Name CEE_Consult: #REF!
Name CENIDH: #REF!
Name Consultants: #REF!
Name Equipment: '[4]Schedule D - Equipment'!$E$26
Name fg: #REF!
Name Housing: '[2]Salary & PR Tax'!#REF!
Name inf: [5]Assumptions!$C$75
Name Inflation: '[6]Detail-1'!$J$2
Name Interns: #REF!
Name jenn: #REF!
Name Local_Hire: #REF!
Name Local_Hires: #REF!
Name Merit: '[6]Detail-1'!$J$1
Name padf01: '[7]Level of Effort'!$C$14
Name padf02: '[7]Level of Effort'!$C$15
Name padf03: '[7]Level of Effort'!$C$16
Name padf04: '[7]Level of Effort'!$C$17
Name padf05: [7]Rates!$J$23
Name postdif01: [7]Rates!$J$34
Name postdif02: [7]Rates!$J$65
Name Print_Titles_MI: #REF!
Name sdf: #REF!
Name Travel_Regional: #REF!
Name Travel_WDC: #REF!

Sheet Budget Summary
B1: Name of Subawardee:
B2: USAID RFA No. XXXXX
A4: Line Items | B4: Year 1 | E4: Year 2 | H4: Year 3 | K4: Year 4 | N4: Year 5 | Q4: Total | R4: Total | S4: Grand
B5: USAID | C5: Leverage | D5: Total | E5: USAID | F5: Leverage | G5: Total | H5: USAID | I5: Leverage | J5: Total | K5: USAID | L5: Leverage | M5: Total | N5: USAID | O5: Leverage | P5: Total | Q5: USAID | R5: Leverage | S5: Total
A7: Personnel | B7: =Budget!F28 -> 0 | C7: =Budget!G28 -> 0 | D7: =SUM(B7:C7) -> 0 | E7: =Budget!L28 -> 0 | F7: =Budget!M28 -> 0 | G7: =SUM(E7:F7) -> 0 | H7: =Budget!R28 -> 0 | I7: =Budget!S28 -> 0 | J7: =SUM(H7:I7) -> 0 | K7: =Budget!X28 -> 0 | L7: =Budget!Y28 -> 0 | M7: =SUM(K7:L7) -> 0 | N7: =Budget!AD28 -> 0 | O7: =Budget!AE28 -> 0 | P7: =SUM(N7:O7) -> 0 | Q7: =Budget!AG28 -> 0 | R7: =Budget!AH28 -> 0 | S7: =Budget!AI28 -> 0
A9: Fringe Benefits | B9: =Budget!F34 -> 0 | C9: =Budget!G34 -> 0 | D9: =Budget!H34 -> 0 | E9: =Budget!L34 -> 0 | F9: =Budget!M34 -> 0 | G9: =Budget!N34 -> 0 | H9: =Budget!R34 -> 0 | I9: =Budget!S34 -> 0 | J9: =Budget!T34 -> 0 | K9: =Budget!X34 -> 0 | L9: =Budget!Y34 -> 0 | M9: =Budget!Z34 -> 0 | N9: =Budget!AD34 -> 0 | O9: =Budget!AE34 -> 0 | P9: =Budget!AF34 -> 0 | Q9: =Budget!AG34 -> 0 | R9: =Budget!AH34 -> 0 | S9: =Budget!AI34 -> 0
A11: Travel | B11: =Budget!F59 -> 0 | C11: =Budget!G59 -> 0 | D11: =Budget!H59 -> 0 | E11: =Budget!L59 -> 0 | F11: =Budget!M59 -> 0 | G11: =Budget!N59 -> 0 | H11: =Budget!R59 -> 0 | I11: =Budget!S59 -> 0 | J11: =Budget!T59 -> 0 | K11: =Budget!X59 -> 0 | L11: =Budget!Y59 -> 0 | M11: =Budget!Z59 -> 0 | N11: =Budget!AD59 -> 0 | O11: =Budget!AE59 -> 0 | P11: =Budget!AF59 -> 0 | Q11: =Budget!AG59 -> 0 | R11: =Budget!AH59 -> 0 | S11: =Budget!AI59 -> 0
A13: Equipment | B13: =Budget!F66 -> 0 | C13: =Budget!G66 -> 0 | D13: =Budget!H66 -> 0 | E13: =Budget!L66 -> 0 | F13: =Budget!M66 -> 0 | G13: =Budget!N66 -> 0 | H13: =Budget!R66 -> 0 | I13: =Budget!S66 -> 0 | J13: =Budget!T66 -> 0 | K13: =Budget!X66 -> 0 | L13: =Budget!Y66 -> 0 | M13: =Budget!Z66 -> 0 | N13: =Budget!AD66 -> 0 | O13: =Budget!AE66 -> 0 | P13: =Budget!AF66 -> 0 | Q13: =Budget!AG66 -> 0 | R13: =Budget!AH66 -> 0 | S13: =Budget!AI66 -> 0
A15: Supplies | B15: =Budget!F88 -> 0 | C15: =Budget!G88 -> 0 | D15: =Budget!H88 -> 0 | E15: =Budget!L88 -> 0 | F15: =Budget!M88 -> 0 | G15: =Budget!N88 -> 0 | H15: =Budget!R88 -> 0 | I15: =Budget!S88 -> 0 | J15: =Budget!T88 -> 0 | K15: =Budget!X88 -> 0 | L15: =Budget!Y88 -> 0 | M15: =Budget!Z88 -> 0 | N15: =Budget!AD88 -> 0 | O15: =Budget!AE88 -> 0 | P15: =Budget!AF88 -> 0 | Q15: =Budget!AG88 -> 0 | R15: =Budget!AH88 -> 0 | S15: =Budget!AI88 -> 0
A17: Contractual | B17: =Budget!F106 -> 0 | C17: =Budget!G106 -> 0 | D17: =Budget!H106 -> 0 | E17: =Budget!L106 -> 0 | F17: =Budget!M106 -> 0 | G17: =Budget!N106 -> 0 | H17: =Budget!R106 -> 0 | I17: =Budget!S106 -> 0 | J17: =Budget!T106 -> 0 | K17: =Budget!X106 -> 0 | L17: =Budget!Y106 -> 0 | M17: =Budget!Z106 -> 0 | N17: =Budget!AD106 -> 0 | O17: =Budget!AE106 -> 0 | P17: =Budget!AF106 -> 0 | Q17: =Budget!AG106 -> 0 | R17: =Budget!AH106 -> 0 | S17: =Budget!AI106 -> 0
A19: Other Direct Costs | B19: =Budget!F140 -> 0 | C19: =Budget!G140 -> 0 | D19: =Budget!H140 -> 0 | E19: =Budget!L140 -> 0 | F19: =Budget!M140 -> 0 | G19: =Budget!N140 -> 0 | H19: =Budget!R140 -> 0 | I19: =Budget!S140 -> 0 | J19: =Budget!T140 -> 0 | K19: =Budget!X140 -> 0 | L19: =Budget!Y140 -> 0 | M19: =Budget!Z140 -> 0 | N19: =Budget!AD140 -> 0 | O19: =Budget!AE140 -> 0 | P19: =Budget!AF140 -> 0 | Q19: =Budget!AG140 -> 0 | R19: =Budget!AH140 -> 0 | S19: =Budget!AI140 -> 0
A21: Total Direct Costs | B21: =Budget!F142 -> 0 | C21: =Budget!G142 -> 0 | D21: =Budget!H142 -> 0 | E21: =Budget!L142 -> 0 | F21: =Budget!M142 -> 0 | G21: =Budget!N142 -> 0 | H21: =Budget!R142 -> 0 | I21: =Budget!S142 -> 0 | J21: =Budget!T142 -> 0 | K21: =Budget!X142 -> 0 | L21: =Budget!Y142 -> 0 | M21: =Budget!Z142 -> 0 | N21: =Budget!AD142 -> 0 | O21: =Budget!AE142 -> 0 | P21: =Budget!AF142 -> 0 | Q21: =Budget!AG142 -> 0 | R21: =Budget!AH142 -> 0 | S21: =Budget!AI142 -> 0
A22: Indirect Costs | B22: =Budget!F143 -> 0 | C22: =Budget!G143 -> 0 | D22: =Budget!H143 -> 0 | E22: =Budget!L143 -> 0 | F22: =Budget!M143 -> 0 | G22: =Budget!N143 -> 0 | H22: =Budget!R143 -> 0 | I22: =Budget!S143 -> 0 | J22: =Budget!T143 -> 0 | K22: =Budget!X143 -> 0 | L22: =Budget!Y143 -> 0 | M22: =Budget!Z143 -> 0 | N22: =Budget!AD143 -> 0 | O22: =Budget!AE143 -> 0 | P22: =Budget!AF143 -> 0 | Q22: =Budget!AG143 -> 0 | R22: =Budget!AH143 -> 0 | S22: =Budget!AI143 -> 0
A23: Total | B23: =Budget!F144 -> 0 | C23: =Budget!G144 -> 0 | D23: =Budget!H144 -> 0 | E23: =Budget!L144 -> 0 | F23: =Budget!M144 -> 0 | G23: =Budget!N144 -> 0 | H23: =Budget!R144 -> 0 | I23: =Budget!S144 -> 0 | J23: =Budget!T144 -> 0 | K23: =Budget!X144 -> 0 | L23: =Budget!Y144 -> 0 | M23: =Budget!Z144 -> 0 | N23: =Budget!AD144 -> 0 | O23: =Budget!AE144 -> 0 | P23: =Budget!AF144 -> 0 | Q23: =Budget!AG144 -> 0 | R23: =Budget!AH144 -> 0 | S23: =Budget!AI144 -> 0

Sheet Budget
B1: Name of Project:
B2: Name of Subawardee:
B3: Subaward Budget
B4: Country: XXX
A5: Budget Assumptions
A6: Inflation - Locally Purchased Goods/Services - XXXX% | B6: 1
A7: Merit Based Increases for Staff - XXXX% | B7: 1
A11: Line Items | F11: Year 1 | L11: Year 2 | O11: Year 3 | X11: Year 4 | AD11: Year 5 | AG11: Total | AH11: Total | AI11: Grand
B12: Unit | C12: Cost | D12: Duration | E12: Type | F12: USAID | G12: Leverage | H12: Total | I12: Unit | J12: Cost | K12: Duration | L12: USAID | M12: Leverage | N12: Total | O12: Unit | P12: Cost | Q12: Duration | R12: USAID | S12: Leverage | T12: Total | U12: Unit | V12: Cost | W12: Duration | X12: USAID | Y12: Leverage | Z12: Total | AA12: Unit | AB12: Cost | AC12: Duration | AD12: USAID | AE12: Leverage | AF12: Total | AG12: USAID | AH12: Leverage | AI12: Total
A14: Personnel
A15: Headquarters Personnel (include Level of Effort) | B15: LOE
A16: Position 1 | B16: 0 | C16: 0 | D16: 0 | E16: /months | F16: =D16*C16*B16 -> 0 | G16: 0 | H16: =SUM(F16:G16) -> 0 | I16: =B16 -> 0 | J16: =C16*$B$7 -> 0 | K16: 0 | L16: =I16*J16*K16 -> 0 | M16: 0 | N16: =SUM(L16:M16) -> 0 | O16: =B16 -> 0 | P16: =C16*$B$7*$B$7 -> 0 | Q16: 0 | R16: =O16*P16*Q16 -> 0 | S16: 0 | T16: =SUM(R16:S16) -> 0 | U16: =O16 -> 0 | V16: =C16*$B$7*$B$7*$B$7 -> 0 | W16: 0 | X16: =U16*V16*W16 -> 0 | Y16: 0 | Z16: =SUM(X16:Y16) -> 0 | AA16: =U16 -> 0 | AB16: =C16*$B$7*$B$7*$B$7*$B$7 -> 0 | AC16: 0 | AD16: =AA16*AB16*AC16 -> 0 | AE16: 0 | AF16: =SUM(AD16:AE16) -> 0 | AG16: =F16+L16+R16+X16+AD16 -> 0 | AH16: =G16+M16+S16+Y16+AE16 -> 0 | AI16: =SUM(AG16:AH16) -> 0
A17: Position 2 | B17: 0 | C17: 0 | D17: 0 | E17: /months | F17: =D17*C17*B17 -> 0 | G17: 0 | H17: =SUM(F17:G17) -> 0 | I17: =B17 -> 0 | J17: =C17*$B$7 -> 0 | K17: 0 | L17: =I17*J17*K17 -> 0 | M17: 0 | N17: =SUM(L17:M17) -> 0 | O17: =I17 -> 0 | P17: =C17*$B$7*$B$7 -> 0 | Q17: 0 | R17: =O17*P17*Q17 -> 0 | S17: 0 | T17: =SUM(R17:S17) -> 0 | U17: =O17 -> 0 | V17: =C17*$B$7*$B$7*$B$7 -> 0 | W17: 0 | X17: =U17*V17*W17 -> 0 | Y17: 0 | Z17: =SUM(X17:Y17) -> 0 | AA17: =U17 -> 0 | AB17: =C17*$B$7*$B$7*$B$7*$B$7 -> 0 | AC17: 0 | AD17: =AA17*AB17*AC17 -> 0 | AE17: 0 | AF17: =SUM(AD17:AE17) -> 0 | AG17: =F17+L17+R17+X17+AD17 -> 0 | AH17: =G17+M17+S17+Y17+AE17 -> 0 | AI17: =SUM(AG17:AH17) -> 0
A18: Subtotal HQ Personnel | F18: =SUM(F16:F17) -> 0 | G18: =SUM(G16:G17) -> 0 | H18: =SUM(H16:H17) -> 0 | L18: =SUM(L16:L17) -> 0 | M18: =SUM(M16:M17) -> 0 | N18: =SUM(N16:N17) -> 0 | R18: =SUM(R16:R17) -> 0 | S18: =SUM(S16:S17) -> 0 | T18: =SUM(T16:T17) -> 0 | X18: =SUM(X16:X17) -> 0 | Y18: =SUM(Y16:Y17) -> 0 | Z18: =SUM(Z16:Z17) -> 0 | AD18: =SUM(AD16:AD17) -> 0 | AE18: =SUM(AE16:AE17) -> 0 | AF18: =SUM(AF16:AF17) -> 0 | AG18: =SUM(AG16:AG17) -> 0 | AH18: =SUM(AH16:AH17) -> 0 | AI18: =SUM(AI16:AI17) -> 0
A19: *Key Personnel
A20: Field Personnel (include Level of Effort) | B20: LOE
A21: Field Position 1 | B21: 0 | C21: 0 | D21: 0 | E21: /months | F21: =D21*C21*B21 -> 0 | G21: 0 | H21: =SUM(F21:G21) -> 0 | I21: 0 | J21: =C21*$B$7 -> 0 | K21: 0 | L21: =J21*K21*I21 -> 0 | M21: 0 | N21: =SUM(L21:M21) -> 0 | O21: 0 | P21: =C21*$B$7*$B$7 -> 0 | Q21: 0 | R21: =Q21*P21*O21 -> 0 | S21: 0 | T21: =SUM(R21:S21) -> 0 | U21: 0 | V21: =C21*$B$7*$B$7*$B$7 -> 0 | W21: 0 | X21: =W21*V21*U21 -> 0 | Y21: 0 | Z21: =SUM(X21:Y21) -> 0 | AA21: 0 | AB21: =C21*$B$7*$B$7*$B$7*$B$7 -> 0 | AC21: 0 | AD21: =AC21*AB21*AA21 -> 0 | AE21: 0 | AF21: =SUM(AD21:AE21) -> 0 | AG21: =F21+L21+R21+X21+AD21 -> 0 | AH21: =G21+M21+S21+Y21+AE21 -> 0 | AI21: =SUM(AG21:AH21) -> 0
A22: Field Position 2 | B22: 0 | C22: 0 | D22: 0 | E22: /months | F22: =D22*C22*B22 -> 0 | G22: 0 | H22: =SUM(F22:G22) -> 0 | I22: 0 | J22: =C22*$B$7 -> 0 | K22: 0 | L22: =J22*K22*I22 -> 0 | M22: 0 | N22: =SUM(L22:M22) -> 0 | O22: 0 | P22: =C22*$B$7*$B$7 -> 0 | Q22: 0 | R22: =Q22*P22*O22 -> 0 | S22: 0 | T22: =SUM(R22:S22) -> 0 | U22: 0 | V22: =C22*$B$7*$B$7*$B$7 -> 0 | W22: 0 | X22: =W22*V22*U22 -> 0 | Y22: 0 | Z22: =SUM(X22:Y22) -> 0 | AA22: 0 | AB22: =C22*$B$7*$B$7*$B$7*$B$7 -> 0 | AC22: 0 | AD22: =AC22*AB22*AA22 -> 0 | AE22: 0 | AF22: =SUM(AD22:AE22) -> 0 | AG22: =F22+L22+R22+X22+AD22 -> 0 | AH22: =G22+M22+S22+Y22+AE22 -> 0 | AI22: =SUM(AG22:AH22) -> 0
A23: Field Position 3 | B23: 0 | C23: 0 | D23: 0 | E23: /months | F23: =D23*C23*B23 -> 0 | G23: 0 | H23: =SUM(F23:G23) -> 0 | I23: 0 | J23: =C23*$B$7 -> 0 | K23: 0 | L23: =J23*K23*I23 -> 0 | M23: 0 | N23: =SUM(L23:M23) -> 0 | O23: 0 | P23: =C23*$B$7*$B$7 -> 0 | Q23: 0 | R23: =Q23*P23*O23 -> 0 | S23: 0 | T23: =SUM(R23:S23) -> 0 | U23: 0 | V23: =C23*$B$7*$B$7*$B$7 -> 0 | W23: 0 | X23: =W23*V23*U23 -> 0 | Y23: 0 | Z23: =SUM(X23:Y23) -> 0 | AA23: 0 | AB23: =C23*$B$7*$B$7*$B$7*$B$7 -> 0 | AC23: 0 | AD23: =AC23*AB23*AA23 -> 0 | AE23: 0 | AF23: =SUM(AD23:AE23) -> 0 | AG23: =F23+L23+R23+X23+AD23 -> 0 | AH23: =G23+M23+S23+Y23+AE23 -> 0 | AI23: =SUM(AG23:AH23) -> 0
A24: Field Position 4 | B24: 0 | C24: 0 | D24: 0 | E24: /months | F24: =D24*C24*B24 -> 0 | G24: 0 | H24: =SUM(F24:G24) -> 0 | I24: 0 | J24: =C24*$B$7 -> 0 | K24: 0 | L24: =J24*K24*I24 -> 0 | M24: 0 | N24: =SUM(L24:M24) -> 0 | O24: 0 | P24: =C24*$B$7*$B$7 -> 0 | Q24: 0 | R24: =Q24*P24*O24 -> 0 | S24: 0 | T24: =SUM(R24:S24) -> 0 | U24: 0 | V24: =C24*$B$7*$B$7*$B$7 -> 0 | W24: 0 | X24: =W24*V24*U24 -> 0 | Y24: 0 | Z24: =SUM(X24:Y24) -> 0 | AA24: 0 | AB24: =C24*$B$7*$B$7*$B$7*$B$7 -> 0 | AC24: 0 | AD24: =AC24*AB24*AA24 -> 0 | AE24: 0 | AF24: =SUM(AD24:AE24) -> 0 | AG24: =F24+L24+R24+X24+AD24 -> 0 | AH24: =G24+M24+S24+Y24+AE24 -> 0 | AI24: =SUM(AG24:AH24) -> 0
A25: Field Position 5 | B25: 0 | C25: 0 | D25: 0 | E25: /months | F25: =D25*C25*B25 -> 0 | G25: 0 | H25: =SUM(F25:G25) -> 0 | I25: 0 | J25: =C25*$B$7 -> 0 | K25: 0 | L25: =J25*K25*I25 -> 0 | M25: 0 | N25: =SUM(L25:M25) -> 0 | O25: 0 | P25: =C25*$B$7*$B$7 -> 0 | Q25: 0 | R25: =Q25*P25*O25 -> 0 | S25: 0 | T25: =SUM(R25:S25) -> 0 | U25: 0 | V25: =C25*$B$7*$B$7*$B$7 -> 0 | W25: 0 | X25: =W25*V25*U25 -> 0 | Y25: 0 | Z25: =SUM(X25:Y25) -> 0 | AA25: 0 | AB25: =C25*$B$7*$B$7*$B$7*$B$7 -> 0 | AC25: 0 | AD25: =AC25*AB25*AA25 -> 0 | AE25: 0 | AF25: =SUM(AD25:AE25) -> 0 | AG25: =F25+L25+R25+X25+AD25 -> 0 | AH25: =G25+M25+S25+Y25+AE25 -> 0 | AI25: =SUM(AG25:AH25) -> 0
A26: Subtotal Field Personnel | F26: =SUM(F21:F25) -> 0 | G26: =SUM(G21:G25) -> 0 | H26: =SUM(H21:H25) -> 0 | L26: =SUM(L21:L25) -> 0 | M26: =SUM(M21:M25) -> 0 | N26: =SUM(N21:N25) -> 0 | R26: =SUM(R21:R25) -> 0 | S26: =SUM(S21:S25) -> 0 | T26: =SUM(T21:T25) -> 0 | X26: =SUM(X21:X25) -> 0 | Y26: =SUM(Y21:Y25) -> 0 | Z26: =SUM(Z21:Z25) -> 0 | AD26: =SUM(AD21:AD25) -> 0 | AE26: =SUM(AE21:AE25) -> 0 | AF26: =SUM(AF21:AF25) -> 0 | AG26: =F26+L26+R26+X26+AD26 -> 0 | AH26: =G26+M26+S26+Y26+AE26 -> 0 | AI26: =SUM(AG26:AH26) -> 0
A28: Personnel Total | F28: =F26+F18 -> 0 | G28: =G26+G18 -> 0 | H28: =H26+H18 -> 0 | L28: =L26+L18 -> 0 | M28: =M26+M18 -> 0 | N28: =N26+N18 -> 0 | R28: =R26+R18 -> 0 | S28: =S26+S18 -> 0 | T28: =T26+T18 -> 0 | X28: =X26+X18 -> 0 | Y28: =Y26+Y18 -> 0 | Z28: =Z26+Z18 -> 0 | AD28: =AD26+AD18 -> 0 | AE28: =AE26+AE18 -> 0 | AF28: =AF26+AF18 -> 0 | AG28: =AG26+AG18 -> 0 | AH28: =AH26+AH18 -> 0 | AI28: =AI26+AI18 -> 0
A30: Fringe Benefits
A31: Fringe Benefits - Headquarters | B31: 0 | F31: =F18*B31 -> 0 | G31: 0 | H31: =SUM(F31:G31) -> 0 | L31: =L18*$B$31 -> 0 | M31: 0 | N31: =SUM(L31:M31) -> 0 | R31: =R18*$B$31 -> 0 | S31: 0 | T31: =SUM(R31:S31) -> 0 | X31: =X18*$B$31 -> 0 | Y31: 0 | Z31: =SUM(X31:Y31) -> 0 | AD31: =AD18*$B$31 -> 0 | AE31: 0 | AF31: =SUM(AD31:AE31) -> 0 | AG31: =F31+L31+R31+X31+AD31 -> 0 | AH31: =G31+M31+S31+Y31+AE31 -> 0 | AI31: =SUM(AG31:AH31) -> 0
A32: Fringe Benefits CCN | B32: 0 | F32: =F26*$B$32 -> 0 | G32: 0 | H32: =SUM(F32:G32) -> 0 | L32: =L26*$B$32 -> 0 | M32: 0 | N32: =SUM(L32:M32) -> 0 | R32: =R26*$B$32 -> 0 | S32: 0 | T32: =SUM(R32:S32) -> 0 | X32: =X26*$B$32 -> 0 | Y32: 0 | Z32: =SUM(X32:Y32) -> 0 | AD32: =AD26*$B$32 -> 0 | AE32: 0 | AF32: =SUM(AD32:AE32) -> 0 | AG32: =F32+L32+R32+X32+AD32 -> 0 | AH32: =G32+M32+S32+Y32+AE32 -> 0 | AI32: =SUM(AG32:AH32) -> 0
A34: Fringe Benefits Total | F34: =SUM(F31:F33) -> 0 | G34: =SUM(G31:G33) -> 0 | H34: =SUM(H31:H33) -> 0 | L34: =SUM(L31:L33) -> 0 | M34: =SUM(M31:M33) -> 0 | N34: =SUM(N31:N33) -> 0 | R34: =SUM(R31:R33) -> 0 | S34: =SUM(S31:S33) -> 0 | T34: =SUM(T31:T33) -> 0 | X34: =SUM(X31:X33) -> 0 | Y34: =SUM(Y31:Y33) -> 0 | Z34: =SUM(Z31:Z33) -> 0 | AD34: =SUM(AD31:AD33) -> 0 | AE34: =SUM(AE31:AE33) -> 0 | AF34: =SUM(AF31:AF33) -> 0 | AG34: =SUM(AG31:AG33) -> 0 | AH34: =SUM(AH31:AH33) -> 0 | AI34: =SUM(AI31:AI33) -> 0
A36: Travel
A38: HQ Staff Travel
A39: HQ Staff - Airfare | B39: 0 | C39: 0 | D39: 0 | E39: /RT | F39: =D39*C39*B39 -> 0 | G39: 0 | H39: =SUM(F39:G39) -> 0 | I39: 0 | J39: =C39*$B$6 -> 0 | K39: 0 | L39: =I39*J39*K39 -> 0 | M39: 0 | N39: =SUM(L39:M39) -> 0 | O39: 0 | P39: =C39*$B$6*$B$6 -> 0 | Q39: 0 | R39: =O39*P39*Q39 -> 0 | S39: 0 | T39: =SUM(R39:S39) -> 0 | U39: 0 | V39: =C39*$B$6*$B$6*$B$6 -> 0 | W39: 0 | X39: =U39*V39*W39 -> 0 | Y39: 0 | Z39: =SUM(X39:Y39) -> 0 | AA39: 0 | AB39: =C39*$B$6*$B$6*$B$6*$B$6 -> 0 | AC39: 0 | AD39: =AA39*AB39*AC39 -> 0 | AE39: 0 | AF39: =SUM(AD39:AE39) -> 0 | AG39: =F39+L39+R39+X39+AD39 -> 0 | AH39: =G39+M39+S39+Y39+AE39 -> 0 | AI39: =SUM(AG39:AH39) -> 0
A40: HQ Staff - Lodging | B40: 0 | C40: 0 | D40: 0 | E40: /day | F40: =D40*C40*B40 -> 0 | G40: 0 | H40: =SUM(F40:G40) -> 0 | I40: 0 | J40: =C40*$B$6 -> 0 | K40: 0 | L40: =I40*J40*K40 -> 0 | M40: 0 | N40: =SUM(L40:M40) -> 0 | O40: 0 | P40: =C40*$B$6*$B$6 -> 0 | Q40: 0 | R40: =O40*P40*Q40 -> 0 | S40: 0 | T40: =SUM(R40:S40) -> 0 | U40: 0 | V40: =C40*$B$6*$B$6*$B$6 -> 0 | W40: 0 | X40: =U40*V40*W40 -> 0 | Y40: 0 | Z40: =SUM(X40:Y40) -> 0 | AA40: 0 | AB40: =C40*$B$6*$B$6*$B$6*$B$6 -> 0 | AC40: 0 | AD40: =AA40*AB40*AC40 -> 0 | AE40: 0 | AF40: =SUM(AD40:AE40) -> 0 | AG40: =F40+L40+R40+X40+AD40 -> 0 | AH40: =G40+M40+S40+Y40+AE40 -> 0 | AI40: =SUM(AG40:AH40) -> 0
A41: HQ Staff - Ground Transportation | B41: 0 | C41: 0 | D41: 0 | E41: /day | F41: =D41*C41*B41 -> 0 | G41: 0 | H41: =SUM(F41:G41) -> 0 | I41: 0 | J41: =C41*$B$6 -> 0 | K41: 0 | L41: =I41*J41*K41 -> 0 | M41: 0 | N41: =SUM(L41:M41) -> 0 | O41: 0 | P41: =C41*$B$6*$B$6 -> 0 | Q41: 0 | R41: =O41*P41*Q41 -> 0 | S41: 0 | T41: =SUM(R41:S41) -> 0 | U41: =U39 -> 0 | V41: =C41*$B$6*$B$6*$B$6 -> 0 | W41: 0 | X41: =U41*V41*W41 -> 0 | Y41: 0 | Z41: =SUM(X41:Y41) -> 0 | AA41: 0 | AB41: =C41*$B$6*$B$6*$B$6*$B$6 -> 0 | AC41: 0 | AD41: =AA41*AB41*AC41 -> 0 | AE41: 0 | AF41: =SUM(AD41:AE41) -> 0 | AG41: =F41+L41+R41+X41+AD41 -> 0 | AH41: =G41+M41+S41+Y41+AE41 -> 0 | AI41: =SUM(AG41:AH41) -> 0
A42: HQ Staff - Misc. Staff Travel Related Expenses | B42: 0 | C42: 0 | D42: 0 | E42: /trip | F42: =D42*C42*B42 -> 0 | G42: 0 | H42: =SUM(F42:G42) -> 0 | I42: 0 | J42: =C42*$B$6 -> 0 | K42: 0 | L42: =I42*J42*K42 -> 0 | M42: 0 | N42: =SUM(L42:M42) -> 0 | O42: 0 | P42: =C42*$B$6*$B$6 -> 0 | Q42: 0 | R42: =O42*P42*Q42 -> 0 | S42: 0 | T42: =SUM(R42:S42) -> 0 | U42: 0 | V42: =C42*$B$6*$B$6*$B$6 -> 0 | W42: 0 | X42: =U42*V42*W42 -> 0 | Y42: 0 | Z42: =SUM(X42:Y42) -> 0 | AA42: 0 | AB42: =C42*$B$6*$B$6*$B$6*$B$6 -> 0 | AC42: 0 | AD42: =AA42*AB42*AC42 -> 0 | AE42: 0 | AF42: =SUM(AD42:AE42) -> 0 | AG42: =F42+L42+R42+X42+AD42 -> 0 | AH42: =G42+M42+S42+Y42+AE42 -> 0 | AI42: =SUM(AG42:AH42) -> 0
A43: HQ Staff - M&IE | B43: 0 | C43: 0 | D43: 0 | E43: /trip | F43: =D43*C43*B43 -> 0 | G43: 0 | H43: =SUM(F43:G43) -> 0 | I43: 0 | J43: =C43*$B$6 -> 0 | K43: 0 | L43: =I43*J43*K43 -> 0 | M43: 0 | N43: =SUM(L43:M43) -> 0 | O43: 0 | P43: =C43*$B$6*$B$6 -> 0 | Q43: 0 | R43: =O43*P43*Q43 -> 0 | S43: 0 | T43: =SUM(R43:S43) -> 0 | U43: 0 | V43: =C43*$B$6*$B$6*$B$6 -> 0 | W43: 0 | X43: =U43*V43*W43 -> 0 | Y43: 0 | Z43: =SUM(X43:Y43) -> 0 | AA43: 0 | AB43: =C43*$B$6*$B$6*$B$6*$B$6 -> 0 | AC43: 0 | AD43: =AA43*AB43*AC43 -> 0 | AE43: 0 | AF43: =SUM(AD43:AE43) -> 0 | AG43: =F43+L43+R43+X43+AD43 -> 0 | AH43: =G43+M43+S43+Y43+AE43 -> 0 | AI43: =SUM(AG43:AH43) -> 0
A44: Total HQ Staff Travel | F44: =SUM(F39:F43) -> 0 | G44: =SUM(G39:G43) -> 0 | H44: =SUM(H39:H43) -> 0 | L44: =SUM(L39:L43) -> 0 | M44: =SUM(M39:M43) -> 0 | N44: =SUM(N39:N43) -> 0 | P44: =C44*$B$6*$B$6 -> 0 | R44: =SUM(R39:R43) -> 0 | S44: =SUM(S39:S43) -> 0 | T44: =SUM(T39:T43) -> 0 | V44: =C44*$B$6*$B$6*$B$6 -> 0 | X44: =SUM(X39:X43) -> 0 | Y44: =SUM(Y39:Y43) -> 0 | Z44: =SUM(Z39:Z43) -> 0 | AB44: =C44*$B$6*$B$6*$B$6*$B$6 -> 0 | AD44: =SUM(AD39:AD43) -> 0 | AE44: =SUM(AE39:AE43) -> 0 | AF44: =SUM(AF39:AF43) -> 0 | AG44: =SUM(AG39:AG43) -> 0 | AH44: =SUM(AH39:AH43) -> 0 | AI44: =SUM(AI39:AI43) -> 0
A46: Local Staff Travel
A47: Airfare for: XXX | B47: =B28 -> 0 | C47: 0 | D47: 0 | E47: /day | F47: =D47*C47*B47 -> 0 | G47: 0 | H47: =SUM(F47:G47) -> 0 | I47: 0 | J47: =C47*$B$6 -> 0 | K47: 0 | L47: =I47*J47*K47 -> 0 | M47: 0 | N47: =SUM(L47:M47) -> 0 | O47: =O28 -> 0 | P47: =C47*$B$6*$B$6 -> 0 | Q47: 0 | R47: =O47*P47*Q47 -> 0 | S47: 0 | T47: =SUM(R47:S47) -> 0 | U47: =U28 -> 0 | V47: =C47*$B$6*$B$6*$B$6 -> 0 | W47: 0 | X47: =U47*V47*W47 -> 0 | Y47: 0 | Z47: =SUM(X47:Y47) -> 0 | AA47: =AA28 -> 0 | AB47: =C47*$B$6*$B$6*$B$6*$B$6 -> 0 | AC47: 0 | AD47: =AA47*AB47*AC47 -> 0 | AE47: 0 | AF47: =SUM(AD47:AE47) -> 0 | AG47: =F47+L47+R47+X47+AD47 -> 0 | AH47: =G47+M47+S47+Y47+AE47 -> 0 | AI47: =SUM(AG47:AH47) -> 0
A48: Lodging for: XXX | B48: =B29 -> 0 | C48: 0 | D48: 0 | E48: /day | F48: =D48*C48*B48 -> 0 | G48: 0 | H48: =SUM(F48:G48) -> 0 | I48: 0 | J48: =C48*$B$6 -> 0 | K48: 0 | L48: =I48*J48*K48 -> 0 | M48: 0 | N48: =SUM(L48:M48) -> 0 | O48: =O29 -> 0 | P48: =C48*$B$6*$B$6 -> 0 | Q48: 0 | R48: =O48*P48*Q48 -> 0 | S48: 0 | T48: =SUM(R48:S48) -> 0 | U48: =U29 -> 0 | V48: =C48*$B$6*$B$6*$B$6 -> 0 | W48: 0 | X48: =U48*V48*W48 -> 0 | Y48: 0 | Z48: =SUM(X48:Y48) -> 0 | AA48: =AA29 -> 0 | AB48: =C48*$B$6*$B$6*$B$6*$B$6 -> 0 | AC48: 0 | AD48: =AA48*AB48*AC48 -> 0 | AE48: 0 | AF48: =SUM(AD48:AE48) -> 0 | AG48: =F48+L48+R48+X48+AD48 -> 0 | AH48: =G48+M48+S48+Y48+AE48 -> 0 | AI48: =SUM(AG48:AH48) -> 0
A49: Ground Transportation for: XXX | B49: =B30 -> 0 | C49: 0 | D49: 0 | E49: /trip | F49: =D49*C49*B49 -> 0 | G49: 0 | H49: =SUM(F49:G49) -> 0 | I49: 0 | J49: =C49*$B$6 -> 0 | K49: 0 | L49: =I49*J49*K49 -> 0 | M49: 0 | N49: =SUM(L49:M49) -> 0 | O49: 0 | P49: =C49*$B$6*$B$6 -> 0 | Q49: 0 | R49: =O49*P49*Q49 -> 0 | S49: 0 | T49: =SUM(R49:S49) -> 0 | U49: =U30 -> 0 | V49: =C49*$B$6*$B$6*$B$6 -> 0 | W49: 0 | X49: =U49*V49*W49 -> 0 | Y49: 0 | Z49: =SUM(X49:Y49) -> 0 | AA49: =AA30 -> 0 | AB49: =C49*$B$6*$B$6*$B$6*$B$6 -> 0 | AC49: 0 | AD49: =AA49*AB49*AC49 -> 0 | AE49: 0 | AF49: =SUM(AD49:AE49) -> 0 | AG49: =F49+L49+R49+X49+AD49 -> 0 | AH49: =G49+M49+S49+Y49+AE49 -> 0 | AI49: =SUM(AG49:AH49) -> 0
A50: Misc. Staff Travel Related Expenses for: XXX | B50: =B30 -> 0 | C50: 0 | D50: 0 | E50: /trip | F50: =D50*C50*B50 -> 0 | G50: 0 | H50: =SUM(F50:G50) -> 0 | I50: 0 | J50: =C50*$B$6 -> 0 | K50: 0 | L50: =I50*J50*K50 -> 0 | M50: 0 | N50: =SUM(L50:M50) -> 0 | O50: 0 | P50: =C50*$B$6*$B$6 -> 0 | Q50: 0 | R50: =O50*P50*Q50 -> 0 | S50: 0 | T50: =SUM(R50:S50) -> 0 | U50: =U30 -> 0 | V50: =C50*$B$6*$B$6*$B$6 -> 0 | W50: 0 | X50: =U50*V50*W50 -> 0 | Y50: 0 | Z50: =SUM(X50:Y50) -> 0 | AA50: =AA30 -> 0 | AB50: =C50*$B$6*$B$6*$B$6*$B$6 -> 0 | AC50: 0 | AD50: =AA50*AB50*AC50 -> 0 | AE50: 0 | AF50: =SUM(AD50:AE50) -> 0 | AG50: =F50+L50+R50+X50+AD50 -> 0 | AH50: =G50+M50+S50+Y50+AE50 -> 0 | AI50: =SUM(AG50:AH50) -> 0
A51: M&IE for: XXX | B51: 0 | C51: 0 | D51: 0 | E51: /day | F51: =D51*C51*B51 -> 0 | G51: 0 | H51: =SUM(F51:G51) -> 0 | I51: 0 | J51: =C51*$B$6 -> 0 | K51: 0 | L51: =I51*J51*K51 -> 0 | M51: 0 | N51: =SUM(L51:M51) -> 0 | O51: 0 | P51: =C51*$B$6*$B$6 -> 0 | Q51: 0 | R51: =O51*P51*Q51 -> 0 | S51: 0 | T51: =SUM(R51:S51) -> 0 | U51: 0 | V51: =C51*$B$6*$B$6*$B$6 -> 0 | W51: 0 | X51: =U51*V51*W51 -> 0 | Y51: 0 | Z51: =SUM(X51:Y51) -> 0 | AA51: 0 | AB51: =C51*$B$6*$B$6*$B$6*$B$6 -> 0 | AC51: 0 | AD51: =AA51*AB51*AC51 -> 0 | AE51: 0 | AF51: =SUM(AD51:AE51) -> 0 | AG51: =F51+L51+R51+X51+AD51 -> 0 | AH51: =G51+M51+S51+Y51+AE51 -> 0 | AI51: =SUM(AG51:AH51) -> 0
A52: Airfare for: XXX | B52: =B33 -> 0 | C52: 0 | D52: 0 | E52: /day | F52: =D52*C52*B52 -> 0 | G52: 0 | H52: =SUM(F52:G52) -> 0 | I52: 0 | J52: =C52*$B$6 -> 0 | K52: 0 | L52: =I52*J52*K52 -> 0 | M52: 0 | N52: =SUM(L52:M52) -> 0 | O52: 0 | P52: =C52*$B$6*$B$6 -> 0 | Q52: 0 | R52: =O52*P52*Q52 -> 0 | S52: 0 | T52: =SUM(R52:S52) -> 0 | U52: =U33 -> 0 | V52: =C52*$B$6*$B$6*$B$6 -> 0 | W52: 0 | X52: =U52*V52*W52 -> 0 | Y52: 0 | Z52: =SUM(X52:Y52) -> 0 | AA52: =AA33 -> 0 | AB52: =C52*$B$6*$B$6*$B$6*$B$6 -> 0 | AC52: 0 | AD52: =AA52*AB52*AC52 -> 0 | AE52: 0 | AF52: =SUM(AD52:AE52) -> 0 | AG52: =F52+L52+R52+X52+AD52 -> 0 | AH52: =G52+M52+S52+Y52+AE52 -> 0 | AI52: =SUM(AG52:AH52) -> 0
A53: Lodging for: XXX | B53: =B34 -> 0 | C53: 0 | D53: 0 | E53: /day | F53: =D53*C53*B53 -> 0 | G53: 0 | H53: =SUM(F53:G53) -> 0 | I53: 0 | J53: =C53*$B$6 -> 0 | K53: 0 | L53: =I53*J53*K53 -> 0 | M53: 0 | N53: =SUM(L53:M53) -> 0 | O53: 0 | P53: =C53*$B$6*$B$6 -> 0 | Q53: 0 | R53: =O53*P53*Q53 -> 0 | S53: 0 | T53: =SUM(R53:S53) -> 0 | U53: =U34 -> 0 | V53: =C53*$B$6*$B$6*$B$6 -> 0 | W53: 0 | X53: =U53*V53*W53 -> 0 | Y53: 0 | Z53: =SUM(X53:Y53) -> 0 | AA53: =AA34 -> 0 | AB53: =C53*$B$6*$B$6*$B$6*$B$6 -> 0 | AC53: 0 | AD53: =AA53*AB53*AC53 -> 0 | AE53: 0 | AF53: =SUM(AD53:AE53) -> 0 | AG53: =F53+L53+R53+X53+AD53 -> 0 | AH53: =G53+M53+S53+Y53+AE53 -> 0 | AI53: =SUM(AG53:AH53) -> 0
A54: Ground Transportation for: XXX | B54: =B35 -> 0 | C54: 0 | D54: 0 | E54: /trip | F54: =D54*C54*B54 -> 0 | G54: 0 | H54: =SUM(F54:G54) -> 0 | I54: =I35 -> 0 | J54: =C54*$B$6 -> 0 | K54: 0 | L54: =I54*J54*K54 -> 0 | M54: 0 | N54: =SUM(L54:M54) -> 0 | O54: 0 | P54: =C54*$B$6*$B$6 -> 0 | Q54: 0 | R54: =O54*P54*Q54 -> 0 | S54: 0 | T54: =SUM(R54:S54) -> 0 | U54: =U35 -> 0 | V54: =C54*$B$6*$B$6*$B$6 -> 0 | W54: 0 | X54: =U54*V54*W54 -> 0 | Y54: 0 | Z54: =SUM(X54:Y54) -> 0 | AA54: =AA35 -> 0 | AB54: =C54*$B$6*$B$6*$B$6*$B$6 -> 0 | AC54: 0 | AD54: =AA54*AB54*AC54 -> 0 | AE54: 0 | AF54: =SUM(AD54:AE54) -> 0 | AG54: =F54+L54+R54+X54+AD54 -> 0 | AH54: =G54+M54+S54+Y54+AE54 -> 0 | AI54: =SUM(AG54:AH54) -> 0
A55: Misc. Staff Travel Related Expenses for: XXX | B55: =B35 -> 0 | C55: 0 | D55: 0 | E55: /trip | F55: =D55*C55*B55 -> 0 | G55: 0 | H55: =SUM(F55:G55) -> 0 | I55: 0 | J55: =C55*$B$6 -> 0 | K55: 0 | L55: =I55*J55*K55 -> 0 | M55: 0 | N55: =SUM(L55:M55) -> 0 | O55: 0 | P55: =C55*$B$6*$B$6 -> 0 | Q55: 0 | R55: =O55*P55*Q55 -> 0 | S55: 0 | T55: =SUM(R55:S55) -> 0 | U55: =U35 -> 0 | V55: =C55*$B$6*$B$6*$B$6 -> 0 | W55: 0 | X55: =U55*V55*W55 -> 0 | Y55: 0 | Z55: =SUM(X55:Y55) -> 0 | AA55: =AA35 -> 0 | AB55: =C55*$B$6*$B$6*$B$6*$B$6 -> 0 | AC55: 0 | AD55: =AA55*AB55*AC55 -> 0 | AE55: 0 | AF55: =SUM(AD55:AE55) -> 0 | AG55: =F55+L55+R55+X55+AD55 -> 0 | AH55: =G55+M55+S55+Y55+AE55 -> 0 | AI55: =SUM(AG55:AH55) -> 0
A56: M&IE for: XXX | B56: 0 | C56: 0 | D56: 0 | E56: /day | F56: =D56*C56*B56 -> 0 | G56: 0 | H56: =SUM(F56:G56) -> 0 | I56: 0 | J56: =C56*$B$6 -> 0 | K56: 0 | L56: =I56*J56*K56 -> 0 | M56: 0 | N56: =SUM(L56:M56) -> 0 | O56: 0 | P56: =C56*$B$6*$B$6 -> 0 | Q56: 0 | R56: =O56*P56*Q56 -> 0 | S56: 0 | T56: =SUM(R56:S56) -> 0 | U56: 0 | V56: =C56*$B$6*$B$6*$B$6 -> 0 | W56: 0 | X56: =U56*V56*W56 -> 0 | Y56: 0 | Z56: =SUM(X56:Y56) -> 0 | AA56: 0 | AB56: =C56*$B$6*$B$6*$B$6*$B$6 -> 0 | AC56: 0 | AD56: =AA56*AB56*AC56 -> 0 | AE56: 0 | AF56: =SUM(AD56:AE56) -> 0 | AG56: =F56+L56+R56+X56+AD56 -> 0 | AH56: =G56+M56+S56+Y56+AE56 -> 0 | AI56: =SUM(AG56:AH56) -> 0
A57: Total Local Staff Travel | F57: =SUM(F47:F56) -> 0 | G57: =SUM(G47:G56) -> 0 | H57: =SUM(H47:H56) -> 0 | L57: =SUM(L47:L56) -> 0 | M57: =SUM(M47:M56) -> 0 | N57: =SUM(N47:N56) -> 0 | R57: =SUM(R47:R56) -> 0 | S57: =SUM(S47:S56) -> 0 | T57: =SUM(T47:T56) -> 0 | X57: =SUM(X47:X56) -> 0 | Y57: =SUM(Y47:Y56) -> 0 | Z57: =SUM(Z47:Z56) -> 0 | AD57: =SUM(AD47:AD56) -> 0 | AE57: =SUM(AE47:AE56) -> 0 | AF57: =SUM(AF47:AF56) -> 0 | AG57: =SUM(AG47:AG56) -> 0 | AH57: =SUM(AH47:AH56) -> 0 | AI57: =SUM(AI47:AI56) -> 0
A59: Travel Total | F59: =F57+F44 -> 0 | G59: =G57+G44 -> 0 | H59: =H57+H44 -> 0 | L59: =L57+L44 -> 0 | M59: =M57+M44 -> 0 | N59: =N57+N44 -> 0 | R59: =R57+R44 -> 0 | S59: =S57+S44 -> 0 | T59: =T57+T44 -> 0 | X59: =X57+X44 -> 0 | Y59: =Y57+Y44 -> 0 | Z59: =Z57+Z44 -> 0 | AD59: =AD57+AD44 -> 0 | AE59: =AE57+AE44 -> 0 | AF59: =AF57+AF44 -> 0 | AG59: =AG57+AG44 -> 0 | AH59: =AH57+AH44 -> 0 | AI59: =AI57+AI44 -> 0
A61: Equipment - Over $5,000 USD
A63: Equipment 1 | B63: 0 | C63: 0 | D63: 0 | E63: /unit | F63: =C63*B63 -> 0 | G63: 0 | H63: =SUM(F63:G63) -> 0 | I63: 0 | J63: =C63 -> 0 | L63: =I63*J63 -> 0 | M63: 0 | N63: =SUM(L63:M63) -> 0 | O63: 0 | P63: =C63 -> 0 | R63: =P63*O63 -> 0 | S63: 0 | T63: =SUM(R63:S63) -> 0 | U63: 0 | V63: =C63 -> 0 | X63: =U63*V63 -> 0 | Y63: 0 | Z63: =SUM(X63:Y63) -> 0 | AA63: 0 | AB63: =C63 -> 0 | AD63: =AB63*AA63 -> 0 | AE63: 0 | AF63: =SUM(AD63:AE63) -> 0 | AG63: =F63+L63+R63+X63+AD63 -> 0 | AH63: =G63+M63+S63+Y63+AE63 -> 0 | AI63: =SUM(AG63:AH63) -> 0
A64: Equipment 2 | B64: 0 | C64: 0 | E64: /unit | F64: =C64*B64 -> 0 | G64: 0 | H64: =SUM(F64:G64) -> 0 | I64: 0 | J64: =C64 -> 0 | L64: =I64*J64 -> 0 | M64: 0 | N64: =SUM(L64:M64) -> 0 | O64: 0 | P64: =C64 -> 0 | R64: =P64*O64 -> 0 | S64: 0 | T64: =SUM(R64:S64) -> 0 | U64: 0 | V64: =C64 -> 0 | X64: =U64*V64 -> 0 | Y64: 0 | Z64: =SUM(X64:Y64) -> 0 | AA64: 0 | AB64: =C64 -> 0 | AD64: =AB64*AA64 -> 0 | AE64: 0 | AF64: =SUM(AD64:AE64) -> 0 | AG64: =F64+L64+R64+X64+AD64 -> 0 | AH64: =G64+M64+S64+Y64+AE64 -> 0 | AI64: =SUM(AG64:AH64) -> 0
A66: Equipment Total | F66: =SUM(F63:F65) -> 0 | G66: =SUM(G63:G65) -> 0 | H66: =SUM(H63:H65) -> 0 | L66: =SUM(L63:L65) -> 0 | M66: =SUM(M63:M65) -> 0 | N66: =SUM(N63:N65) -> 0 | R66: =SUM(R63:R65) -> 0 | S66: =SUM(S63:S65) -> 0 | T66: =SUM(T63:T65) -> 0 | X66: =SUM(X63:X65) -> 0 | Y66: =SUM(Y63:Y65) -> 0 | Z66: =SUM(Z63:Z65) -> 0 | AD66: =SUM(AD63:AD65) -> 0 | AE66: =SUM(AE63:AE65) -> 0 | AF66: =SUM(AF63:AF65) -> 0 | AG66: =SUM(AG63:AG65) -> 0 | AH66: =SUM(AH63:AH65) -> 0 | AI66: =SUM(AI63:AI65) -> 0
A68: Supplies - Under $5,000 USD
A70: HQ Office Supplies
A71: Other Supplies 1 | B71: 0 | C71: 0 | D71: 0 | E71: /XXX | F71: =C71*B71 -> 0 | G71: 0 | H71: =SUM(F71:G71) -> 0 | I71: 0 | J71: =C71 -> 0 | K71: 0 | L71: =I71*J71 -> 0 | M71: 0 | N71: =SUM(L71:M71) -> 0 | O71: =L71*M71*N71 -> 0 | P71: =C71 -> 0 | Q71: 0 | R71: =P71*O71 -> 0 | S71: 0 | T71: =SUM(R71:S71) -> 0 | U71: =R71*S71*T71 -> 0 | V71: =C71 -> 0 | W71: 0 | X71: =V71*U71 -> 0 | Y71: 0 | Z71: =SUM(X71:Y71) -> 0 | AA71: =X71*Y71*Z71 -> 0 | AB71: =C71 -> 0 | AC71: 0 | AD71: =AB71*AA71 -> 0 | AE71: 0 | AF71: =SUM(AD71:AE71) -> 0 | AG71: =F71+L71+R71+X71+AD71 -> 0 | AH71: =G71+M71+S71+Y71+AE71 -> 0 | AI71: =SUM(AG71:AH71) -> 0
A72: Other Supplies 2 | B72: 0 | C72: 0 | D72: 0 | E72: /XXX | F72: =C72*B72 -> 0 | G72: 0 | H72: =SUM(F72:G72) -> 0 | I72: 0 | J72: =C72 -> 0 | K72: 0 | L72: =I72*J72 -> 0 | M72: 0 | N72: =SUM(L72:M72) -> 0 | O72: =L72*M72*N72 -> 0 | P72: =C72 -> 0 | Q72: 0 | R72: =P72*O72 -> 0 | S72: 0 | T72: =SUM(R72:S72) -> 0 | U72: =R72*S72*T72 -> 0 | V72: =C72 -> 0 | W72: 0 | X72: =V72*U72 -> 0 | Y72: 0 | Z72: =SUM(X72:Y72) -> 0 | AA72: =X72*Y72*Z72 -> 0 | AB72: =C72 -> 0 | AC72: 0 | AD72: =AB72*AA72 -> 0 | AE72: 0 | AF72: =SUM(AD72:AE72) -> 0 | AG72: =F72+L72+R72+X72+AD72 -> 0 | AH72: =G72+M72+S72+Y72+AE72 -> 0 | AI72: =SUM(AG72:AH72) -> 0
A73: Other Supplies 3 | B73: 0 | C73: 0 | D73: 0 | E73: /XXX | F73: =C73*B73 -> 0 | G73: 0 | H73: =SUM(F73:G73) -> 0 | I73: 0 | J73: =C73 -> 0 | K73: 0 | L73: =I73*J73 -> 0 | M73: 0 | N73: =SUM(L73:M73) -> 0 | O73: =L73*M73*N73 -> 0 | P73: =C73 -> 0 | Q73: 0 | R73: =P73*O73 -> 0 | S73: 0 | T73: =SUM(R73:S73) -> 0 | U73: =R73*S73*T73 -> 0 | V73: =C73 -> 0 | W73: 0 | X73: =V73*U73 -> 0 | Y73: 0 | Z73: =SUM(X73:Y73) -> 0 | AA73: =X73*Y73*Z73 -> 0 | AB73: =C73 -> 0 | AC73: 0 | AD73: =AB73*AA73 -> 0 | AE73: 0 | AF73: =SUM(AD73:AE73) -> 0 | AG73: =F73+L73+R73+X73+AD73 -> 0 | AH73: =G73+M73+S73+Y73+AE73 -> 0 | AI73: =SUM(AG73:AH73) -> 0
A74: Total HQ Office Supplies | F74: =SUM(F71:F73) -> 0 | G74: =SUM(G71:G73) -> 0 | H74: =SUM(H71:H73) -> 0 | L74: =SUM(L71:L73) -> 0 | M74: =SUM(M71:M73) -> 0 | N74: =SUM(N71:N73) -> 0 | R74: =SUM(R71:R73) -> 0 | S74: =SUM(S71:S73) -> 0 | T74: =SUM(T71:T73) -> 0 | X74: =SUM(X71:X73) -> 0 | Y74: =SUM(Y71:Y73) -> 0 | Z74: =SUM(Z71:Z73) -> 0 | AD74: =SUM(AD71:AD73) -> 0 | AE74: =SUM(AE71:AE73) -> 0 | AF74: =SUM(AF71:AF73) -> 0 | AG74: =F74+L74+R74+X74+AD74 -> 0 | AH74: =G74+M74+S74+Y74+AE74 -> 0 | AI74: =SUM(AG74:AH74) -> 0
A76: Field Office Supplies
A77: Desktop computers, laptops and software | B77: 0 | C77: 0 | D77: 0 | E77: /XXX | F77: =C77*B77 -> 0 | G77: 0 | H77: =SUM(F77:G77) -> 0 | I77: 0 | J77: =C77 -> 0 | K77: 0 | L77: =I77*J77 -> 0 | M77: 0 | N77: =SUM(L77:M77) -> 0 | O77: =L77*M77*N77 -> 0 | P77: =C77 -> 0 | Q77: 0 | R77: =P77*O77 -> 0 | S77: 0 | T77: =SUM(R77:S77) -> 0 | U77: =R77*S77*T77 -> 0 | V77: =C77 -> 0 | W77: 0 | X77: =V77*U77 -> 0 | Y77: 0 | Z77: =SUM(X77:Y77) -> 0 | AA77: =X77*Y77*Z77 -> 0 | AB77: =C77 -> 0 | AC77: 0 | AD77: =AB77*AA77 -> 0 | AE77: 0 | AF77: =SUM(AD77:AE77) -> 0 | AG77: =F77+L77+R77+X77+AD77 -> 0 | AH77: =G77+M77+S77+Y77+AE77 -> 0 | AI77: =SUM(AG77:AH77) -> 0
A78: Phones | B78: 0 | C78: 0 | D78: 0 | E78: /XXX | F78: =C78*B78 -> 0 | G78: 0 | H78: =SUM(F78:G78) -> 0 | I78: 0 | J78: =C78 -> 0 | K78: 0 | L78: =I78*J78 -> 0 | M78: 0 | N78: =SUM(L78:M78) -> 0 | O78: =L78*M78*N78 -> 0 | P78: =C78 -> 0 | Q78: 0 | R78: =P78*O78 -> 0 | S78: 0 | T78: =SUM(R78:S78) -> 0 | U78: =R78*S78*T78 -> 0 | V78: =C78 -> 0 | W78: 0 | X78: =V78*U78 -> 0 | Y78: 0 | Z78: =SUM(X78:Y78) -> 0 | AA78: =X78*Y78*Z78 -> 0 | AB78: =C78 -> 0 | AC78: 0 | AD78: =AB78*AA78 -> 0 | AE78: 0 | AF78: =SUM(AD78:AE78) -> 0 | AG78: =F78+L78+R78+X78+AD78 -> 0 | AH78: =G78+M78+S78+Y78+AE78 -> 0 | AI78: =SUM(AG78:AH78) -> 0
A79: Stationary/Printing Materials | B79: 0 | C79: 0 | D79: 0 | E79: /XXX | F79: =C79*B79 -> 0 | G79: 0 | H79: =SUM(F79:G79) -> 0 | I79: 0 | J79: =C79 -> 0 | K79: 0 | L79: =I79*J79 -> 0 | M79: 0 | N79: =SUM(L79:M79) -> 0 | O79: =L79*M79*N79 -> 0 | P79: =C79 -> 0 | Q79: 0 | R79: =P79*O79 -> 0 | S79: 0 | T79: =SUM(R79:S79) -> 0 | U79: =R79*S79*T79 -> 0 | V79: =C79 -> 0 | W79: 0 | X79: =V79*U79 -> 0 | Y79: 0 | Z79: =SUM(X79:Y79) -> 0 | AA79: =X79*Y79*Z79 -> 0 | AB79: =C79 -> 0 | AC79: 0 | AD79: =AB79*AA79 -> 0 | AE79: 0 | AF79: =SUM(AD79:AE79) -> 0 | AG79: =F79+L79+R79+X79+AD79 -> 0 | AH79: =G79+M79+S79+Y79+AE79 -> 0 | AI79: =SUM(AG79:AH79) -> 0
A80: Misc. Office Supplies | B80: 0 | C80: 0 | D80: 0 | E80: /XXX | F80: =C80*B80 -> 0 | G80: 0 | H80: =SUM(F80:G80) -> 0 | I80: 0 | J80: =C80 -> 0 | K80: 0 | L80: =I80*J80 -> 0 | M80: 0 | N80: =SUM(L80:M80) -> 0 | O80: =L80*M80*N80 -> 0 | P80: =C80 -> 0 | Q80: 0 | R80: =P80*O80 -> 0 | S80: 0 | T80: =SUM(R80:S80) -> 0 | U80: =R80*S80*T80 -> 0 | V80: =C80 -> 0 | W80: 0 | X80: =V80*U80 -> 0 | Y80: 0 | Z80: =SUM(X80:Y80) -> 0 | AA80: =X80*Y80*Z80 -> 0 | AB80: =C80 -> 0 | AC80: 0 | AD80: =AB80*AA80 -> 0 | AE80: 0 | AF80: =SUM(AD80:AE80) -> 0 | AG80: =F80+L80+R80+X80+AD80 -> 0 | AH80: =G80+M80+S80+Y80+AE80 -> 0 | AI80: =SUM(AG80:AH80) -> 0
A81: Other Supplies 1 | B81: 0 | C81: 0 | D81: 0 | E81: /XXX | F81: =C81*B81 -> 0 | G81: 0 | H81: =SUM(F81:G81) -> 0 | I81: 0 | J81: =C81 -> 0 | K81: 0 | L81: =I81*J81 -> 0 | M81: 0 | N81: =SUM(L81:M81) -> 0 | O81: 0 | P81: =C81 -> 0 | Q81: 0 | R81: =P81*O81 -> 0 | S81: 0 | T81: =SUM(R81:S81) -> 0 | U81: 0 | V81: =C81 -> 0 | W81: 0 | X81: =V81*U81 -> 0 | Y81: 0 | Z81: =SUM(X81:Y81) -> 0 | AA81: 0 | AB81: =C81 -> 0 | AC81: 0 | AD81: =AB81*AA81 -> 0 | AE81: 0 | AF81: =SUM(AD81:AE81) -> 0 | AG81: =F81+L81+R81+X81+AD81 -> 0 | AH81: =G81+M81+S81+Y81+AE81 -> 0 | AI81: =SUM(AG81:AH81) -> 0
A82: Other Supplies 2 | B82: 0 | C82: 0 | D82: 0 | E82: /XXX | F82: =C82*B82 -> 0 | G82: 0 | H82: =SUM(F82:G82) -> 0 | I82: 0 | J82: =C82 -> 0 | K82: 0 | L82: =J82*I82 -> 0 | M82: 0 | N82: =SUM(L82:M82) -> 0 | O82: =L82*M82*N82 -> 0 | P82: =C82 -> 0 | Q82: 0 | R82: =P82*O82 -> 0 | S82: 0 | T82: =SUM(R82:S82) -> 0 | U82: =R82*S82*T82 -> 0 | V82: =C82 -> 0 | W82: 0 | X82: =V82*U82 -> 0 | Y82: 0 | Z82: =SUM(X82:Y82) -> 0 | AA82: =X82*Y82*Z82 -> 0 | AB82: =C82 -> 0 | AC82: 0 | AD82: =AB82*AA82 -> 0 | AE82: 0 | AF82: =SUM(AD82:AE82) -> 0 | AG82: =F82+L82+R82+X82+AD82 -> 0 | AH82: =G82+M82+S82+Y82+AE82 -> 0 | AI82: =SUM(AG82:AH82) -> 0
A83: Other Supplies 3 | B83: 0 | C83: 0 | D83: 0 | E83: /XXX | F83: =C83*B83 -> 0 | G83: 0 | H83: =SUM(F83:G83) -> 0 | I83: 0 | J83: =C83 -> 0 | K83: 0 | L83: =I83*J83 -> 0 | M83: 0 | N83: =SUM(L83:M83) -> 0 | O83: 0 | P83: =C83 -> 0 | Q83: 0 | R83: =P83*O83 -> 0 | S83: 0 | T83: =SUM(R83:S83) -> 0 | U83: 0 | V83: =C83 -> 0 | W83: 0 | X83: =V83*U83 -> 0 | Y83: 0 | Z83: =SUM(X83:Y83) -> 0 | AA83: 0 | AB83: =C83 -> 0 | AC83: 0 | AD83: =AB83*AA83 -> 0 | AE83: 0 | AF83: =SUM(AD83:AE83) -> 0 | AG83: =F83+L83+R83+X83+AD83 -> 0 | AH83: =G83+M83+S83+Y83+AE83 -> 0 | AI83: =SUM(AG83:AH83) -> 0
A84: Other Supplies 4 | B84: 0 | C84: 0 | D84: 0 | E84: /XXX | F84: =D84*C84*B84 -> 0 | G84: 0 | H84: =SUM(F84:G84) -> 0 | I84: 0 | J84: =C84 -> 0 | K84: 0 | L84: =K84*I84*J84 -> 0 | M84: 0 | N84: =SUM(L84:M84) -> 0 | O84: 0 | P84: =C84 -> 0 | Q84: 0 | R84: =P84*Q84*O84 -> 0 | S84: 0 | T84: =SUM(R84:S84) -> 0 | U84: 0 | V84: =C84 -> 0 | W84: 0 | X84: =V84*U84*W84 -> 0 | Y84: 0 | Z84: =SUM(X84:Y84) -> 0 | AA84: 0 | AB84: =C84 -> 0 | AC84: 0 | AD84: =AB84*AA84*AC84 -> 0 | AE84: 0 | AF84: =SUM(AD84:AE84) -> 0 | AG84: =F84+L84+R84+X84+AD84 -> 0 | AH84: =G84+M84+S84+Y84+AE84 -> 0 | AI84: =SUM(AG84:AH84) -> 0
A85: Other Supplies 5 | B85: 0 | C85: 0 | D85: 0 | E85: /XXX | F85: =C85*B85*D85 -> 0 | G85: 0 | H85: =SUM(F85:G85) -> 0 | I85: =I95 -> 0 | J85: =C85 -> 0 | K85: 0 | L85: =I85*J85*K85 -> 0 | M85: 0 | N85: =SUM(L85:M85) -> 0 | O85: =O95 -> 0 | P85: =C85 -> 0 | Q85: 0 | R85: =P85*O85*Q85 -> 0 | S85: 0 | T85: =SUM(R85:S85) -> 0 | U85: 0 | V85: =C85 -> 0 | W85: 0 | X85: =V85*U85*W85 -> 0 | Y85: 0 | Z85: =SUM(X85:Y85) -> 0 | AA85: 0 | AB85: =C85 -> 0 | AC85: 0 | AD85: =AB85*AA85*AC85 -> 0 | AE85: 0 | AF85: =SUM(AD85:AE85) -> 0 | AG85: =F85+L85+R85+X85+AD85 -> 0 | AH85: =G85+M85+S85+Y85+AE85 -> 0 | AI85: =SUM(AG85:AH85) -> 0
A86: Total Field Office Supplies | F86: =SUM(F77:F85) -> 0 | G86: =SUM(G77:G85) -> 0 | H86: =SUM(H77:H85) -> 0 | L86: =SUM(L77:L85) -> 0 | M86: =SUM(M77:M85) -> 0 | N86: =SUM(N77:N85) -> 0 | R86: =SUM(R77:R85) -> 0 | S86: =SUM(S77:S85) -> 0 | T86: =SUM(T77:T85) -> 0 | X86: =SUM(X77:X85) -> 0 | Y86: =SUM(Y77:Y85) -> 0 | Z86: =SUM(Z77:Z85) -> 0 | AD86: =SUM(AD77:AD85) -> 0 | AE86: =SUM(AE77:AE85) -> 0 | AF86: =SUM(AF77:AF85) -> 0 | AG86: =SUM(AG77:AG85) -> 0 | AH86: =SUM(AH77:AH85) -> 0 | AI86: =SUM(AI77:AI85) -> 0
A88: Supplies Total | F88: =F86+F74 -> 0 | G88: =G86+G74 -> 0 | H88: =H86+H74 -> 0 | L88: =L86+L74 -> 0 | M88: =M86+M74 -> 0 | N88: =N86+N74 -> 0 | R88: =R86+R74 -> 0 | S88: =S86+S74 -> 0 | T88: =T86+T74 -> 0 | X88: =X86+X74 -> 0 | Y88: =Y86+Y74 -> 0 | Z88: =Z86+Z74 -> 0 | AD88: =AD86+AD74 -> 0 | AE88: =AE86+AE74 -> 0 | AF88: =AF86+AF74 -> 0 | AG88: =AD88+X88+R88+L88+F88 -> 0 | AH88: =AE88+Y88+S88+M88+G88 -> 0 | AI88: =AF88+Z88+T88+N88+H88 -> 0
A90: Contractual
A92: Subawards
A93: Subaward to XXXX for XXXX | B93: 0 | C93: 0 | D93: 0 | E93: /unit | F93: =C93*B93*D93 -> 0 | G93: 0 | H93: =SUM(F93:G93) -> 0 | I93: 0 | J93: =C93 -> 0 | K93: 0 | L93: =J93*I93*K93 -> 0 | M93: 0 | N93: =SUM(L93:M93) -> 0 | O93: 0 | P93: =C93 -> 0 | Q93: 0 | R93: =O93*P93*Q93 -> 0 | S93: 0 | T93: =SUM(R93:S93) -> 0 | U93: 0 | V93: =C93 -> 0 | W93: 0 | X93: =V93*U93*W93 -> 0 | Y93: 0 | Z93: =SUM(X93:Y93) -> 0 | AA93: 0 | AB93: =C93 -> 0 | AC93: 0 | AD93: =AB93*AA93*AC93 -> 0 | AE93: 0 | AF93: =SUM(AD93:AE93) -> 0 | AG93: =F93+L93+R93+X93+AD93 -> 0 | AH93: =G93+M93+S93+Y93+AE93 -> 0 | AI93: =SUM(AG93:AH93) -> 0
A94: Subaward to XXXX for XXXX | B94: 0 | C94: 0 | D94: 0 | E94: /unit | F94: =C94*B94*D94 -> 0 | G94: 0 | H94: =SUM(F94:G94) -> 0 | I94: 0 | J94: =C94 -> 0 | K94: 0 | L94: =J94*I94*K94 -> 0 | M94: 0 | N94: =SUM(L94:M94) -> 0 | O94: 0 | P94: =C94 -> 0 | Q94: 0 | R94: =O94*P94*Q94 -> 0 | S94: 0 | T94: =SUM(R94:S94) -> 0 | U94: 0 | V94: =C94 -> 0 | W94: 0 | X94: =V94*U94*W94 -> 0 | Y94: 0 | Z94: =SUM(X94:Y94) -> 0 | AA94: 0 | AB94: =C94 -> 0 | AC94: 0 | AD94: =AB94*AA94*AC94 -> 0 | AE94: 0 | AF94: =SUM(AD94:AE94) -> 0 | AG94: =F94+L94+R94+X94+AD94 -> 0 | AH94: =G94+M94+S94+Y94+AE94 -> 0 | AI94: =SUM(AG94:AH94) -> 0
A95: Contractual to XXXX for XXXX | B95: 0 | C95: 0 | D95: 0 | E95: /unit | F95: =C95*B95*D95 -> 0 | G95: 0 | H95: =SUM(F95:G95) -> 0 | I95: 0 | J95: =C95 -> 0 | K95: 0 | L95: =J95*I95*K95 -> 0 | M95: 0 | N95: =SUM(L95:M95) -> 0 | O95: 0 | P95: =C95 -> 0 | Q95: 0 | R95: =O95*P95*Q95 -> 0 | S95: 0 | T95: =SUM(R95:S95) -> 0 | U95: 0 | V95: =C95 -> 0 | W95: 0 | X95: =V95*U95*W95 -> 0 | Y95: 0 | Z95: =SUM(X95:Y95) -> 0 | AA95: 0 | AB95: =C95 -> 0 | AC95: 0 | AD95: =AB95*AA95*AC95 -> 0 | AE95: 0 | AF95: =SUM(AD95:AE95) -> 0 | AG95: =F95+L95+R95+X95+AD95 -> 0 | AH95: =G95+M95+S95+Y95+AE95 -> 0 | AI95: =SUM(AG95:AH95) -> 0
A96: Contractual to XXXX for XXXX | B96: 0 | C96: 0 | D96: 0 | E96: /unit | F96: =C96*B96 -> 0 | G96: 0 | H96: =SUM(F96:G96) -> 0 | I96: 0 | J96: =C96 -> 0 | K96: 0 | L96: =J96*I96 -> 0 | M96: 0 | N96: =SUM(L96:M96) -> 0 | O96: 0 | P96: =C96 -> 0 | Q96: 0 | R96: =O96*P96 -> 0 | S96: 0 | T96: =SUM(R96:S96) -> 0 | U96: 0 | V96: =C96 -> 0 | W96: 0 | X96: =V96*U96 -> 0 | Y96: 0 | Z96: =SUM(X96:Y96) -> 0 | AA96: 0 | AB96: =C96 -> 0 | AC96: 0 | AD96: =AB96*AA96 -> 0 | AE96: 0 | AF96: =SUM(AD96:AE96) -> 0 | AG96: =F96+L96+R96+X96+AD96 -> 0 | AH96: =G96+M96+S96+Y96+AE96 -> 0 | AI96: =SUM(AG96:AH96) -> 0
A97: Total Subawards | F97: =SUM(F92:F96) -> 0 | G97: =SUM(G92:G96) -> 0 | H97: =SUM(H92:H96) -> 0 | L97: =SUM(L92:L96) -> 0 | M97: =SUM(M92:M96) -> 0 | N97: =SUM(N92:N96) -> 0 | R97: =SUM(R92:R96) -> 0 | S97: =SUM(S92:S96) -> 0 | T97: =SUM(T92:T96) -> 0 | X97: =SUM(X92:X96) -> 0 | Y97: =SUM(Y92:Y96) -> 0 | Z97: =SUM(Z92:Z96) -> 0 | AD97: =SUM(AD92:AD96) -> 0 | AE97: =SUM(AE92:AE96) -> 0 | AF97: =SUM(AF92:AF96) -> 0 | AG97: =SUM(AG92:AG96) -> 0 | AH97: =SUM(AH92:AH96) -> 0 | AI97: =SUM(AI92:AI96) -> 0
A99: Consultants
A100: Consultant 1 | B100: 0 | C100: 0 | D100: 0 | E100: /month | F100: =D100*C100*B100 -> 0 | G100: 0 | H100: =SUM(F100:G100) -> 0 | I100: 0 | J100: =C100 -> 0 | K100: 0 | L100: =K100*J100*I100 -> 0 | M100: 0 | N100: =SUM(L100:M100) -> 0 | O100: 0 | P100: =C100 -> 0 | Q100: 0 | R100: =Q100*P100*O100 -> 0 | S100: 0 | T100: =SUM(R100:R100) -> 0 | U100: 0 | V100: =C100 -> 0 | W100: 0 | X100: =W100*V100*U100 -> 0 | Y100: 0 | Z100: =SUM(X100:Y100) -> 0 | AA100: 0 | AB100: =C100 -> 0 | AC100: 0 | AD100: =AC100*AB100*AA100 -> 0 | AE100: 0 | AF100: =SUM(AD100:AE100) -> 0 | AG100: =F100+L100+R100+X100+AD100 -> 0 | AH100: =G100+M100+S100+Y100+AE100 -> 0 | AI100: =SUM(AG100:AH100) -> 0
A101: Consultant 2 | B101: 0 | C101: 0 | D101: 0 | E101: /month | F101: =D101*C101*B101 -> 0 | G101: 0 | H101: =SUM(F101:G101) -> 0 | I101: 0 | J101: =C101 -> 0 | K101: 0 | L101: =K101*J101*I101 -> 0 | M101: 0 | N101: =SUM(L101:M101) -> 0 | O101: 0 | P101: =C101 -> 0 | Q101: 0 | R101: =Q101*P101*O101 -> 0 | S101: 0 | T101: =SUM(R101:S101) -> 0 | U101: 0 | V101: =C101 -> 0 | W101: 0 | X101: =W101*V101*U101 -> 0 | Y101: 0 | Z101: =SUM(X101:Y101) -> 0 | AA101: 0 | AB101: =C101 -> 0 | AC101: 0 | AD101: =AC101*AA101*AB101 -> 0 | AE101: 0 | AF101: =SUM(AD101:AE101) -> 0 | AG101: =F101+L101+R101+X101+AD101 -> 0 | AH101: =G101+M101+S101+Y101+AE101 -> 0 | AI101: =SUM(AG101:AH101) -> 0
A102: Consultant 3 | B102: 0 | C102: 0 | D102: 0 | E102: /day | F102: =D102*C102*B102 -> 0 | G102: 0 | H102: =SUM(F102:G102) -> 0 | I102: 0 | J102: =C102 -> 0 | K102: 0 | L102: =K102*J102*I102 -> 0 | M102: 0 | N102: =SUM(L102:M102) -> 0 | O102: 0 | P102: =C102 -> 0 | Q102: 0 | R102: =Q102*P102*O102 -> 0 | S102: 0 | T102: =SUM(R102:S102) -> 0 | U102: 0 | V102: =C102 -> 0 | W102: 0 | X102: =W102*V102*U102 -> 0 | Y102: 0 | Z102: =SUM(X102:Y102) -> 0 | AA102: 0 | AB102: =C102 -> 0 | AC102: 0 | AD102: =AC102*AA102*AB102 -> 0 | AE102: 0 | AF102: =SUM(AD102:AE102) -> 0 | AG102: =F102+L102+R102+X102+AD102 -> 0 | AH102: =G102+M102+S102+Y102+AE102 -> 0 | AI102: =SUM(AG102:AH102) -> 0
A103: Consultant 4 | B103: 0 | C103: 0 | D103: 0 | E103: /day | F103: =D103*C103*B103 -> 0 | G103: 0 | H103: =SUM(F103:G103) -> 0 | I103: 0 | J103: =C103 -> 0 | K103: 0 | L103: =K103*J103*I103 -> 0 | M103: 0 | N103: =SUM(L103:M103) -> 0 | O103: 0 | P103: =C103 -> 0 | Q103: 0 | R103: =Q103*P103*O103 -> 0 | S103: 0 | T103: =SUM(R103:R103) -> 0 | U103: 0 | V103: =C103 -> 0 | W103: 0 | X103: =W103*V103*U103 -> 0 | Y103: 0 | Z103: =SUM(X103:Y103) -> 0 | AA103: 0 | AB103: =C103 -> 0 | AC103: 0 | AD103: =AC103*AB103*AA103 -> 0 | AE103: 0 | AF103: =SUM(AD103:AE103) -> 0 | AG103: =F103+L103+R103+X103+AD103 -> 0 | AH103: =G103+M103+S103+Y103+AE103 -> 0 | AI103: =SUM(AG103:AH103) -> 0
A104: Total Consultants | F104: =SUM(F100:F103) -> 0 | G104: =SUM(G100:G103) -> 0 | H104: =SUM(H100:H103) -> 0 | L104: =SUM(L100:L103) -> 0 | M104: =SUM(M100:M103) -> 0 | N104: =SUM(N100:N103) -> 0 | R104: =SUM(R100:R103) -> 0 | S104: =SUM(S100:S103) -> 0 | T104: =SUM(T100:T103) -> 0 | X104: =SUM(X100:X103) -> 0 | Y104: =SUM(Y100:Y103) -> 0 | Z104: =SUM(Z100:Z103) -> 0 | AD104: =SUM(AD100:AD103) -> 0 | AE104: =SUM(AE100:AE103) -> 0 | AF104: =SUM(AF100:AF103) -> 0 | AG104: =SUM(AG99:AG103) -> 0 | AH104: =SUM(AH99:AH103) -> 0 | AI104: =SUM(AI99:AI103) -> 0
A106: Contractual Total | F106: =F104+F97 -> 0 | G106: =G104+G97 -> 0 | H106: =H104+H97 -> 0 | L106: =L104+L97 -> 0 | M106: =M104+M97 -> 0 | N106: =N104+N97 -> 0 | R106: =R104+R97 -> 0 | S106: =S104+S97 -> 0 | T106: =T104+T97 -> 0 | X106: =X104+X97 -> 0 | Y106: =Y104+Y97 -> 0 | Z106: =Z104+Z97 -> 0 | AD106: =AD104+AD97 -> 0 | AE106: =AE104+AE97 -> 0 | AF106: =AF104+AF97 -> 0 | AG106: =AG104+AG97 -> 0 | AH106: =AH104+AH97 -> 0 | AI106: =AI104+AI97 -> 0
A108: Other Direct Costs
A110: HQ - Other Direct Costs
A111: Other Direct Expenses 1: | B111: 0 | C111: 0 | D111: 0 | E111: /XXX | F111: =D111*C111*B111 -> 0 | G111: 0 | H111: =SUM(F111:G111) -> 0 | I111: 0 | J111: =C111*$B$6 -> 0 | K111: 0 | L111: =I111*J111*K111 -> 0 | M111: 0 | N111: =SUM(L111:M111) -> 0 | O111: 0 | P111: =C111*$B$6*$B$6 -> 0 | Q111: 0 | R111: =O111*P111*Q111 -> 0 | S111: 0 | T111: =SUM(R111:S111) -> 0 | U111: 0 | V111: =C111*$B$6*$B$6*$B$6 -> 0 | W111: 0 | X111: =U111*V111*W111 -> 0 | Y111: 0 | Z111: =SUM(X111:Y111) -> 0 | AA111: 0 | AB111: =C111*$B$6*$B$6*$B$6*$B$6 -> 0 | AC111: 0 | AD111: =AA111*AB111*AC111 -> 0 | AE111: 0 | AF111: =SUM(AD111:AE111) -> 0 | AG111: =F111+L111+R111+X111+AD111 -> 0 | AH111: =G111+M111+S111+Y111+AE111 -> 0 | AI111: =SUM(AG111:AH111) -> 0
A112: Other Direct Expenses 2: | B112: 0 | C112: 0 | D112: 0 | E112: /XXX | F112: =D112*C112*B112 -> 0 | G112: 0 | H112: =SUM(F112:G112) -> 0 | I112: 0 | J112: =C112*$B$6 -> 0 | K112: 0 | L112: =I112*J112*K112 -> 0 | M112: 0 | N112: =SUM(L112:M112) -> 0 | O112: 0 | P112: =C112*$B$6*$B$6 -> 0 | Q112: 0 | R112: =O112*P112*Q112 -> 0 | S112: 0 | T112: =SUM(R112:S112) -> 0 | U112: 0 | V112: =C112*$B$6*$B$6*$B$6 -> 0 | W112: 0 | X112: =U112*V112*W112 -> 0 | Y112: 0 | Z112: =SUM(X112:Y112) -> 0 | AA112: 0 | AB112: =C112*$B$6*$B$6*$B$6*$B$6 -> 0 | AC112: 0 | AD112: =AA112*AB112*AC112 -> 0 | AE112: 0 | AF112: =SUM(AD112:AE112) -> 0 | AG112: =F112+L112+R112+X112+AD112 -> 0 | AH112: =G112+M112+S112+Y112+AE112 -> 0 | AI112: =SUM(AG112:AH112) -> 0
A113: Other Direct Expenses 3: | B113: 0 | C113: 0 | D113: 0 | E113: /XXX | F113: =D113*C113*B113 -> 0 | G113: 0 | H113: =SUM(F113:G113) -> 0 | I113: 0 | J113: =C113*$B$6 -> 0 | K113: 0 | L113: =I113*J113*K113 -> 0 | M113: 0 | N113: =SUM(L113:M113) -> 0 | O113: 0 | P113: =C113*$B$6*$B$6 -> 0 | Q113: 0 | R113: =O113*P113*Q113 -> 0 | S113: 0 | T113: =SUM(R113:S113) -> 0 | U113: 0 | V113: =C113*$B$6*$B$6*$B$6 -> 0 | W113: 0 | X113: =U113*V113*W113 -> 0 | Y113: 0 | Z113: =SUM(X113:Y113) -> 0 | AA113: 0 | AB113: =C113*$B$6*$B$6*$B$6*$B$6 -> 0 | AC113: 0 | AD113: =AA113*AB113*AC113 -> 0 | AE113: 0 | AF113: =SUM(AD113:AE113) -> 0 | AG113: =F113+L113+R113+X113+AD113 -> 0 | AH113: =G113+M113+S113+Y113+AE113 -> 0 | AI113: =SUM(AG113:AH113) -> 0
A114: Other Direct Expenses 4: | B114: 0 | C114: 0 | D114: 0 | E114: /XXX | F114: =D114*C114*B114 -> 0 | G114: 0 | H114: =SUM(F114:G114) -> 0 | I114: 0 | J114: =C114*$B$6 -> 0 | K114: 0 | L114: =I114*J114*K114 -> 0 | M114: 0 | N114: =SUM(L114:M114) -> 0 | O114: 0 | P114: =C114*$B$6*$B$6 -> 0 | Q114: 0 | R114: =O114*P114*Q114 -> 0 | S114: 0 | T114: =SUM(R114:S114) -> 0 | U114: 0 | V114: =C114*$B$6*$B$6*$B$6 -> 0 | W114: 0 | X114: =U114*V114*W114 -> 0 | Y114: 0 | Z114: =SUM(X114:Y114) -> 0 | AA114: 0 | AB114: =C114*$B$6*$B$6*$B$6*$B$6 -> 0 | AC114: 0 | AD114: =AA114*AB114*AC114 -> 0 | AE114: 0 | AF114: =SUM(AD114:AE114) -> 0 | AG114: =F114+L114+R114+X114+AD114 -> 0 | AH114: =G114+M114+S114+Y114+AE114 -> 0 | AI114: =SUM(AG114:AH114) -> 0
A115: Other Direct Expenses 5: | B115: 0 | C115: 0 | D115: 0 | E115: /XXX | F115: =D115*C115*B115 -> 0 | G115: 0 | H115: =SUM(F115:G115) -> 0 | I115: 0 | J115: =C115*$B$6 -> 0 | K115: 0 | L115: =I115*J115*K115 -> 0 | M115: 0 | N115: =SUM(L115:M115) -> 0 | O115: 0 | P115: =C115*$B$6*$B$6 -> 0 | Q115: 0 | R115: =O115*P115*Q115 -> 0 | S115: 0 | T115: =SUM(R115:S115) -> 0 | U115: 0 | V115: =C115*$B$6*$B$6*$B$6 -> 0 | W115: 0 | X115: =U115*V115*W115 -> 0 | Y115: 0 | Z115: =SUM(X115:Y115) -> 0 | AA115: 0 | AB115: =C115*$B$6*$B$6*$B$6*$B$6 -> 0 | AC115: 0 | AD115: =AA115*AB115*AC115 -> 0 | AE115: 0 | AF115: =SUM(AD115:AE115) -> 0 | AG115: =F115+L115+R115+X115+AD115 -> 0 | AH115: =G115+M115+S115+Y115+AE115 -> 0 | AI115: =SUM(AG115:AH115) -> 0
A116: Subtotal HQ Other Direct Costs | F116: =SUM(F111:F115) -> 0 | G116: =SUM(G111:G115) -> 0 | H116: =SUM(H111:H115) -> 0 | L116: =SUM(L111:L115) -> 0 | M116: =SUM(M111:M115) -> 0 | N116: =SUM(N111:N115) -> 0 | R116: =SUM(R111:R115) -> 0 | S116: =SUM(S111:S115) -> 0 | T116: =SUM(T111:T115) -> 0 | X116: =SUM(X111:X115) -> 0 | Y116: =SUM(Y111:Y115) -> 0 | Z116: =SUM(Z111:Z115) -> 0 | AD116: =SUM(AD111:AD115) -> 0 | AE116: =SUM(AE111:AE115) -> 0 | AF116: =SUM(AF111:AF115) -> 0 | AG116: =SUM(AG111:AG115) -> 0 | AH116: =SUM(AH111:AH115) -> 0 | AI116: =SUM(AI111:AI115) -> 0
A118: Field Office (FO) - Other Direct Costs
A119: Audit Costs | B119: 0 | C119: 0 | D119: 0 | E119: /year | F119: =D119*C119*B119 -> 0 | G119: 0 | H119: =SUM(F119:G119) -> 0 | I119: 0 | J119: =C119*$B$6 -> 0 | K119: 0 | L119: =I119*J119*K119 -> 0 | M119: 0 | N119: =SUM(L119:M119) -> 0 | O119: 0 | P119: =C119*$B$6*$B$6 -> 0 | Q119: 0 | R119: =Q119*P119*O119 -> 0 | S119: 0 | T119: =SUM(R119:S119) -> 0 | U119: 0 | V119: =C119*$B$6*$B$6*$B$6 -> 0 | W119: 0 | X119: =W119*V119*U119 -> 0 | Y119: 0 | Z119: =SUM(X119:Y119) -> 0 | AA119: 0 | AB119: =C119*$B$6*$B$6*$B$6*$B$6 -> 0 | AC119: 0 | AD119: =AC119*AB119*AA119 -> 0 | AE119: 0 | AF119: =SUM(AD119:AE119) -> 0 | AG119: =F119+L119+R119+X119+AD119 -> 0 | AH119: =G119+M119+S119+Y119+AE119 -> 0 | AI119: =SUM(AG119:AH119) -> 0
A120: Banking and cash handling fees | B120: 0 | C120: 0 | D120: 0 | E120: /XXX | F120: =D120*C120*B120 -> 0 | G120: 0 | H120: =SUM(F120:G120) -> 0 | I120: 0 | J120: =C120*$B$6 -> 0 | K120: 0 | L120: =I120*J120*K120 -> 0 | M120: 0 | N120: =SUM(L120:M120) -> 0 | O120: 0 | P120: =C120*$B$6*$B$6 -> 0 | Q120: 0 | R120: =Q120*P120*O120 -> 0 | S120: 0 | T120: =SUM(R120:S120) -> 0 | U120: 0 | V120: =C120*$B$6*$B$6*$B$6 -> 0 | W120: 0 | X120: =W120*V120*U120 -> 0 | Y120: 0 | Z120: =SUM(X120:Y120) -> 0 | AA120: 0 | AB120: =C120*$B$6*$B$6*$B$6*$B$6 -> 0 | AC120: 0 | AD120: =AC120*AB120*AA120 -> 0 | AE120: 0 | AF120: =SUM(AD120:AE120) -> 0 | AG120: =F120+L120+R120+X120+AD120 -> 0 | AH120: =G120+M120+S120+Y120+AE120 -> 0 | AI120: =SUM(AG120:AH120) -> 0
A121: Courier fees/services/postage | B121: 0 | C121: 0 | D121: 0 | E121: /XXX | F121: =D121*C121*B121 -> 0 | G121: 0 | H121: =SUM(F121:G121) -> 0 | I121: 0 | J121: =C121*$B$6 -> 0 | K121: 0 | L121: =I121*J121*K121 -> 0 | M121: 0 | N121: =SUM(L121:M121) -> 0 | O121: 0 | P121: =C121*$B$6*$B$6 -> 0 | Q121: 0 | R121: =Q121*P121*O121 -> 0 | S121: 0 | T121: =SUM(R121:S121) -> 0 | U121: 0 | V121: =C121*$B$6*$B$6*$B$6 -> 0 | W121: 0 | X121: =W121*V121*U121 -> 0 | Y121: 0 | Z121: =SUM(X121:Y121) -> 0 | AA121: 0 | AB121: =C121*$B$6*$B$6*$B$6*$B$6 -> 0 | AC121: 0 | AD121: =AC121*AB121*AA121 -> 0 | AE121: 0 | AF121: =SUM(AD121:AE121) -> 0 | AG121: =F121+L121+R121+X121+AD121 -> 0 | AH121: =G121+M121+S121+Y121+AE121 -> 0 | AI121: =SUM(AG121:AH121) -> 0
A122: Recruitment/Procurement Advertising | B122: 0 | C122: 0 | D122: 0 | E122: /XXX | F122: =D122*C122*B122 -> 0 | G122: 0 | H122: =SUM(F122:G122) -> 0 | I122: 0 | J122: =C122*$B$6 -> 0 | K122: 0 | L122: =I122*J122*K122 -> 0 | M122: 0 | N122: =SUM(L122:M122) -> 0 | O122: 0 | P122: =C122*$B$6*$B$6 -> 0 | Q122: 0 | R122: =Q122*P122*O122 -> 0 | S122: 0 | T122: =SUM(R122:S122) -> 0 | U122: 0 | V122: =C122*$B$6*$B$6*$B$6 -> 0 | W122: 0 | X122: =W122*V122*U122 -> 0 | Y122: 0 | Z122: =SUM(X122:Y122) -> 0 | AA122: 0 | AB122: =C122*$B$6*$B$6*$B$6*$B$6 -> 0 | AC122: 0 | AD122: =AC122*AB122*AA122 -> 0 | AE122: 0 | AF122: =SUM(AD122:AE122) -> 0 | AG122: =F122+L122+R122+X122+AD122 -> 0 | AH122: =G122+M122+S122+Y122+AE122 -> 0 | AI122: =SUM(AG122:AH122) -> 0
A123: Email/Internet | B123: 0 | C123: 0 | D123: 0 | E123: /XXX | F123: =D123*C123*B123 -> 0 | G123: 0 | H123: =SUM(F123:G123) -> 0 | I123: 0 | J123: =C123*$B$6 -> 0 | K123: 0 | L123: =I123*J123*K123 -> 0 | M123: 0 | N123: =SUM(L123:M123) -> 0 | O123: 0 | P123: =C123*$B$6*$B$6 -> 0 | Q123: 0 | R123: =Q123*P123*O123 -> 0 | S123: 0 | T123: =SUM(R123:S123) -> 0 | U123: 0 | V123: =C123*$B$6*$B$6*$B$6 -> 0 | W123: 0 | X123: =W123*V123*U123 -> 0 | Y123: 0 | Z123: =SUM(X123:Y123) -> 0 | AA123: 0 | AB123: =C123*$B$6*$B$6*$B$6*$B$6 -> 0 | AC123: 0 | AD123: =AC123*AB123*AA123 -> 0 | AE123: 0 | AF123: =SUM(AD123:AE123) -> 0 | AG123: =F123+L123+R123+X123+AD123 -> 0 | AH123: =G123+M123+S123+Y123+AE123 -> 0 | AI123: =SUM(AG123:AH123) -> 0
A124: Phones | B124: 0 | C124: 0 | D124: 0 | E124: /XXX | F124: =D124*C124*B124 -> 0 | G124: 0 | H124: =SUM(F124:G124) -> 0 | I124: 0 | J124: =C124*$B$6 -> 0 | K124: 0 | L124: =I124*J124*K124 -> 0 | M124: 0 | N124: =SUM(L124:M124) -> 0 | O124: 0 | P124: =C124*$B$6*$B$6 -> 0 | Q124: 0 | R124: =Q124*P124*O124 -> 0 | S124: 0 | T124: =SUM(R124:S124) -> 0 | U124: 0 | V124: =C124*$B$6*$B$6*$B$6 -> 0 | W124: 0 | X124: =W124*V124*U124 -> 0 | Y124: 0 | Z124: =SUM(X124:Y124) -> 0 | AA124: 0 | AB124: =C124*$B$6*$B$6*$B$6*$B$6 -> 0 | AC124: 0 | AD124: =AC124*AB124*AA124 -> 0 | AE124: 0 | AF124: =SUM(AD124:AE124) -> 0 | AG124: =F124+L124+R124+X124+AD124 -> 0 | AH124: =G124+M124+S124+Y124+AE124 -> 0 | AI124: =SUM(AG124:AH124) -> 0
A125: Office Rent | B125: 0 | C125: 0 | D125: 0 | E125: /XXX | F125: =D125*C125*B125 -> 0 | G125: 0 | H125: =SUM(F125:G125) -> 0 | I125: 0 | J125: =C125*$B$6 -> 0 | K125: 0 | L125: =I125*J125*K125 -> 0 | M125: 0 | N125: =SUM(L125:M125) -> 0 | O125: 0 | P125: =C125*$B$6*$B$6 -> 0 | Q125: 0 | R125: =Q125*P125*O125 -> 0 | S125: 0 | T125: =SUM(R125:S125) -> 0 | U125: 0 | V125: =C125*$B$6*$B$6*$B$6 -> 0 | W125: 0 | X125: =W125*V125*U125 -> 0 | Y125: 0 | Z125: =SUM(X125:Y125) -> 0 | AA125: 0 | AB125: =C125*$B$6*$B$6*$B$6*$B$6 -> 0 | AC125: 0 | AD125: =AC125*AB125*AA125 -> 0 | AE125: 0 | AF125: =SUM(AD125:AE125) -> 0 | AG125: =F125+L125+R125+X125+AD125 -> 0 | AH125: =G125+M125+S125+Y125+AE125 -> 0 | AI125: =SUM(AG125:AH125) -> 0
...
